Workbook

Sheet はじめに
B1: 来庁者数・窓口時間の集計
B2: 番号発券機データ（令和7年4月〜令和8年3月、762,002件）を集計。市民部・厚生部の削減効果は、発券機のCSVを取り込んで計算。
B4: シート
B5: 計算の説明 | C5: どのデータを、どんな条件で、どう計算しているか（初めに読むシート）
B6: ダッシュボード | C6: 区・月・開庁時間・指標を選択して、来庁者数と待ち時間等を表示
B7: 時間外削減効果 | C7: 市民部・厚生部の時間外削減効果（総括）
B8: 市民部 | C8: 市民部の削減効果の計算（発券機CSVの取込＋発券数×平均処理時間）
B9: 厚生部 | C9: 厚生部の削減効果の計算（発券機CSVの取込＋発券数×平均処理時間）
B10: 待ち・対応時間 | C10: 区別の待ち時間・対応時間・滞在時間、待ち時間の分布
B11: ヒートマップ | C11: 曜日×時間、月×時間、区別の時間帯分布
B12: カレンダー | C12: 日別の来庁者数・平均待ち・平均対応
B13: シミュレーター | C13: 開庁時間案ごとの時間外の発券数
B14: 業務ランキング | C14: 窓口業務別の件数と平均時間
B15: データ | C15: 集計データ
B16: 取込_市民部 | C16: 市民部・厚生部のCSV取込結果（取込_市民部／取込_厚生部／取込_業務別）
B17: 用語
B18: 発券 | C18: 番号札を取ること。来庁1件として数える。
B19: 待ち時間 | C19: 発券から呼出まで。
B20: 対応時間（処理時間） | C20: 呼出から処理済みまで。
B21: 滞在時間 | C21: 発券から処理済みまで（待ち＋対応）。
B22: 開庁時間外 | C22: 指定した開庁時間の前後に発券された件数。
B24: 注意
B25: (1) | C25: 3時間を超える待ち・対応時間は平均から除く。処理済みの時刻がない件（約5%）は対応・滞在の平均に含まれない。
B26: (2) | C26: 記録のない区・月がある：中区 12月（14日分のみ）、東区 1月（10日分のみ）、南区 11月（記録なし）、安佐北区 1月（7日分のみ）。該当月の人数は少なく表示される。
B27: (3) | C27: 黄色のセルは選択・入力項目。
B28: (4) | C28: 市民部・厚生部の数字は、発券機CSVを集計した取込_○○のシートの値から計算している（このファイルはマクロなし。CSVの取り込み直しはマクロ版で行う）。

Sheet ダッシュボード
B1: 来庁者数集計（令和7年度）
B2: 番号発券機データ（令和7年4月〜令和8年3月、762,002件）。黄色のセルは選択項目。
B4: ① 区 | D4: 全区 | H4: ② 月 | J4: 全期間 | N4: ③ 開始 | P4: 0.375 | T4: ④ 終了 | V4: 0.6875
B5: ⑤ 指標 | D5: 来庁者数 | J5: ③④は開庁時間（案）。⑤は時間帯別・区別・月別グラフの指標。
C7: 来庁者の合計（人） | I7: 1日あたり（人） | O7: 来庁者数最大の15分 | U7: 開庁時間外の割合
C8: ='計算'!B13 -> 762002 | I8: ='計算'!B24 -> 2953.4961 | O8: ='計算'!B18 -> 10:30〜10:45 | U8: ='計算'!B16 -> 0.10972806
C10: ='ダッシュボード'!$D$4&" ／ "&'ダッシュボード'!$J$4 -> 全区 ／ 全期間 | I10: ="営業日 "&'計算'!B23&" 日" -> 営業日 258 日 | O10: ="最大 "&TEXT('計算'!B19,"#,##0")&" 人" -> 最大 26,217 人 | U10: =TEXT('計算'!B15,"#,##0")&" 人が時間外" -> 83,613 人が時間外
C12: 平均待ち時間（分） | I12: 15分以内に呼ばれた割合 | O12: 平均対応時間（分） | U12: 平均滞在時間（分）
C13: ='計算'!B25 -> 7.8387378 | I13: ='計算'!B26 -> 0.84952364 | O13: ='計算'!B27 -> 7.6375636 | U13: ='計算'!B28 -> 15.309631
C15: ="発券→呼出" -> 発券→呼出 | I15: ="待ち時間15分未満" -> 待ち時間15分未満 | O15: ="呼出→処理済み" -> 呼出→処理済み | U15: ="発券→処理済み" -> 発券→処理済み
B53: 来庁者数の多い日（上位5日、選択した区） | N53: 平均待ち時間の長い日（上位5日、選択した区）
B54: 1位 | D54: =INDEX('データ'!$A$880:$A$1244,MATCH(I54,INDEX('データ'!$B$880:$J$1244,0,'計算'!$B$22),0)) -> 46104 | I54: =LARGE(INDEX('データ'!$B$880:$J$1244,0,'計算'!$B$22),1) -> 5392 | N54: 1位 | P54: =INDEX('データ'!$A$880:$A$1244,MATCH(V54,INDEX('データ'!$L$880:$T$1244,0,'計算'!$B$22),0)) -> 46032 | V54: =LARGE(INDEX('データ'!$L$880:$T$1244,0,'計算'!$B$22),1) -> 168.2
B55: 2位 | D55: =INDEX('データ'!$A$880:$A$1244,MATCH(I55,INDEX('データ'!$B$880:$J$1244,0,'計算'!$B$22),0)) -> 46111 | I55: =LARGE(INDEX('データ'!$B$880:$J$1244,0,'計算'!$B$22),2) -> 5319 | N55: 2位 | P55: =INDEX('データ'!$A$880:$A$1244,MATCH(V55,INDEX('データ'!$L$880:$T$1244,0,'計算'!$B$22),0)) -> 46005 | V55: =LARGE(INDEX('データ'!$L$880:$T$1244,0,'計算'!$B$22),2) -> 98.9
B56: 3位 | D56: =INDEX('データ'!$A$880:$A$1244,MATCH(I56,INDEX('データ'!$B$880:$J$1244,0,'計算'!$B$22),0)) -> 46090 | I56: =LARGE(INDEX('データ'!$B$880:$J$1244,0,'計算'!$B$22),3) -> 4814 | N56: 3位 | P56: =INDEX('データ'!$A$880:$A$1244,MATCH(V56,INDEX('データ'!$L$880:$T$1244,0,'計算'!$B$22),0)) -> 45998 | V56: =LARGE(INDEX('データ'!$L$880:$T$1244,0,'計算'!$B$22),3) -> 58.4
B57: 4位 | D57: =INDEX('データ'!$A$880:$A$1244,MATCH(I57,INDEX('データ'!$B$880:$J$1244,0,'計算'!$B$22),0)) -> 46097 | I57: =LARGE(INDEX('データ'!$B$880:$J$1244,0,'計算'!$B$22),4) -> 4720 | N57: 4位 | P57: =INDEX('データ'!$A$880:$A$1244,MATCH(V57,INDEX('データ'!$L$880:$T$1244,0,'計算'!$B$22),0)) -> 46039 | V57: =LARGE(INDEX('データ'!$L$880:$T$1244,0,'計算'!$B$22),4) -> 48.3
B58: 5位 | D58: =INDEX('データ'!$A$880:$A$1244,MATCH(I58,INDEX('データ'!$B$880:$J$1244,0,'計算'!$B$22),0)) -> 45881 | I58: =LARGE(INDEX('データ'!$B$880:$J$1244,0,'計算'!$B$22),5) -> 4680 | N58: 5位 | P58: =INDEX('データ'!$A$880:$A$1244,MATCH(V58,INDEX('データ'!$L$880:$T$1244,0,'計算'!$B$22),0)) -> 46034 | V58: =LARGE(INDEX('データ'!$L$880:$T$1244,0,'計算'!$B$22),5) -> 34.6
B60: 注：開庁時間外＝③〜④の時間帯の前後に発券された件数。待ち＝発券→呼出、対応＝呼出→処理済み、滞在＝発券→処理済み。3時間超の値は平均から除く。
B61: 注：記録のない区・月がある（中区 12月（14日分のみ）、東区 1月（10日分のみ）、南区 11月（記録なし）、安佐北区 1月（7日分のみ） など）。該当月の人数は少なく表示される。

Sheet 時間外削減効果
B1: 時間外削減効果（市民部・厚生部）
B2: 窓口の受付時間を短縮した場合に減らせる、時間外の窓口対応時間の見込み（時間／年）。
B4: 削減効果
B5: 区分 | C5: 削減対象の発券数（年間・件） | D5: 平均処理時間（分） | E5: 削減効果（時間／年） | F5: 別添の値（時間／年） | G5: 差
B6: 市民部（8区役所） | C6: ='市民部'!C22 -> 38403 | D6: ='市民部'!D22 -> 9.1814608 | E6: ='市民部'!F22 -> 5876.594 | F6: ='市民部'!F26 -> 6131.4933 | G6: =E6/F6-1 -> -0.04157215
B7: 厚生部（8区役所に換算） | C7: ='厚生部'!F20 -> 37209.143 | D7: ='厚生部'!C7 -> 18.28506 | E7: ='厚生部'!G20 -> 11339.523 | F7: ='厚生部'!H24 -> 10372.526 | G7: =E7/F7-1 -> 0.093226838
B8: 合計 | E8: =E6+E7 -> 17216.117 | F8: =F6+F7 -> 16504.019 | G8: =E8/F8-1 -> 0.04314697
B10: 時間外勤務の実績との比較（令和7年度、給与課提供）
B11: 区分 | C11: 時間外勤務の実績（時間） | D11: 削減効果（時間） | E11: 実績に対する割合
B12: 市民部（市民課・保険年金課） | C12: 38566 | D12: =E6 -> 5876.594 | E12: =D12/C12 -> 0.15237759
B13: 厚生部（地域支えあい課・福祉課） | C13: 92894 | D13: =E7 -> 11339.523 | E13: =D13/C13 -> 0.12206949
B14: 合計 | C14: =C12+C13 -> 131460 | D14: =D12+D13 -> 17216.117 | E14: =D14/C14 -> 0.13096088
B15: 職員ベースの試算（別添「区役所別集計」） | C15: =C52 -> 18660 | D15: 年間削減時間（時間）。正規職員数×1日の削減時間×営業日数
B17: 区別：職員ベースの試算とデータ算出（時間／年）
B18: 区 | C18: 市民課（職員ベース） | D18: 市民部（データ） | E18: 福祉課（職員ベース） | F18: 厚生部（データ）
B19: 中区 | C19: =C40*$C$50*$C$51 -> 960 | D19: ='市民部'!F14 -> 1644.5527 | E19: =D40*$C$50*$C$51 -> 1560 | F19: ='厚生部'!G12 -> 986.78374
B20: 東区 | C20: =C41*$C$50*$C$51 -> 660 | D20: ='市民部'!F15 -> 539.41082 | E20: =D41*$C$50*$C$51 -> 1500 | F20: ='厚生部'!G13 -> 711.28883
B21: 南区 | C21: =C42*$C$50*$C$51 -> 780 | D21: ='市民部'!F16 -> 828.47381 | E21: =D42*$C$50*$C$51 -> 1680 | F21: ='厚生部'!G14 -> 2152.1516
B22: 西区 | C22: =C43*$C$50*$C$51 -> 1020 | D22: ='市民部'!F17 -> 1165.2804 | E22: =D43*$C$50*$C$51 -> 1860 | F22: ='厚生部'!G15 -> 2773.2341
B23: 安佐南区 | C23: =C44*$C$50*$C$51 -> 660 | D23: ='市民部'!F18 -> 218.67179 | E23: =D44*$C$50*$C$51 -> 2040 | F23: ='厚生部'!G16 -> 1273.8592
B24: 安佐北区 | C24: =C45*$C$50*$C$51 -> 540 | D24: ='市民部'!F19 -> 457.5428 | E24: =D45*$C$50*$C$51 -> 1680 | F24: ='厚生部'!G17 -> 728.35489
B25: 安芸区 | C25: =C46*$C$50*$C$51 -> 360 | D25: ='市民部'!F20 -> 271.46519 | E25: =D46*$C$50*$C$51 -> 1140 | F25: ='厚生部'!G19/7 -> 1417.4404
B26: 佐伯区 | C26: =C47*$C$50*$C$51 -> 660 | D26: ='市民部'!F21 -> 751.19652 | E26: =D47*$C$50*$C$51 -> 1560 | F26: ='厚生部'!G18 -> 1296.4108
B27: 計 | C27: =SUM(C19:C26) -> 5640 | D27: =SUM(D19:D26) -> 5876.594 | E27: =SUM(E19:E26) -> 13020 | F27: =SUM(F19:F26) -> 11339.523
B28: 注：厚生部の安芸区は7区計÷7で補完。
B30: 算出方法
B31: (1) 市民部：2025年1〜12月の16:30〜17:15の発券数 × 同期間の平均処理時間（呼出→処理済み）。いずれも発券機のCSVから集計。
B32: (2) 厚生部：令和8年4〜9月の16:30以降の発券数を区ごとに月平均×12で年間換算し、期間の平均処理時間を掛ける。安芸区は7区計×8÷7で換算。
B33: (3) 平均処理時間・基準時刻・集計期間は、市民部・厚生部シートの黄色のセルで変更できる。
B38: 職員ベースの設定（別添「区役所別集計」の値）
B39: 区 | C39: 市民課の正規職員（人） | D39: 福祉課の正規職員（人）
B40: 中区 | C40: 16 | D40: 26
B41: 東区 | C41: 11 | D41: 25
B42: 南区 | C42: 13 | D42: 28
B43: 西区 | C43: 17 | D43: 31
B44: 安佐南区 | C44: 11 | D44: 34
B45: 安佐北区 | C45: 9 | D45: 28
B46: 安芸区 | C46: 6 | D46: 19
B47: 佐伯区 | C47: 11 | D47: 26
B48: 計 | C48: =SUM(C40:C47) -> 94 | D48: =SUM(D40:D47) -> 217
B50: 1人あたり1日の削減時間（時間） | C50: 0.25
B51: 年間の営業日数（日） | C51: 240
B52: 職員ベース 年間削減時間（時間） | C52: =(C48+D48)*C50*C51 -> 18660

Sheet 計算の説明
B1: 計算の説明（どのデータを、どんな条件で、どう計算しているか）
B2: 数字は、各シートの値をそのまま表示しています。条件を変えると、ここも変わります。
B4: 1. 何を計算しているか
B5: 窓口の受付を16:30で終わりにした場合、16:30以降に来た人の対応にかかっていた時間（＝減らせる時間外の窓口対応時間）が、1年でどれくらいになるかを求めています。
B7: 2. 使っているデータ
B8: 項目 | C8: 市民部（市民課） | D8: 厚生部（福祉課など）
B9: 元のデータ | C9: 市民課の番号発券機のCSV（1日1ファイル、区ごとのフォルダ） | D9: 厚生部の番号発券機のCSV（令和8年のR8.○月フォルダ、区ごと）
B10: CSVから読む項目 | C10: 発券した時刻、呼び出した時刻、処理が済んだ時刻 | D10: 同左（さらに窓口の業務の種類）
B11: データの範囲 | C11: 2024年1月〜2025年12月（計算に使うのは「市民部」シートの集計期間） | D11: 令和8年4月〜9月
B12: ないデータ | C12: 南区の2025年11月など、記録のない月がある | D12: 東区の8・9月、安芸区は全期間ない
B13: 使わないファイル | C13: 「全区」フォルダ（各区のコピー）。同じ区・同じ日のファイルが重複しているときは1つだけ使う。 | D13: 同左
B14: 取り込んだ件数（発券） | C14: =SUM('取込_市民部'!$C$8:$C$1007) -> 1339669 | D14: =SUM('取込_厚生部'!$C$8:$C$1007) -> 203959
B16: 3. 計算の条件
B17: 項目 | C17: 市民部 | D17: 厚生部
B18: 減らす時間帯 | C18: ="発券が "&TEXT('市民部'!C4,"h:mm")&" 〜 "&TEXT('市民部'!C5,"h:mm")&" の人" -> 発券が 16:30 〜 17:15 の人 | D18: ="発券が "&TEXT('厚生部'!C4,"h:mm")&" 以降の人" -> 発券が 16:30 以降の人
B19: 集計する期間 | C19: =LEFT('市民部'!C6,4)&"年"&RIGHT('市民部'!C6,2)&"月 〜 "&LEFT('市民部'!C7,4)&"年"&RIGHT('市民部'!C7,2)&"月" -> 2025年01月 〜 2025年12月 | D19: =LEFT('厚生部'!C8,4)&"年"&RIGHT('厚生部'!C8,2)&"月 〜 "&LEFT('厚生部'!D8,4)&"年"&RIGHT('厚生部'!D8,2)&"月" -> 2026年04月 〜 2026年09月
B20: 1年分への直し方 | C20: 集計期間が1年分なので、そのまま使う | D20: 区ごとに「1か月あたりの件数」を出して12倍する。データのない区（安芸区）は、他の7区の合計を8÷7倍して補う
B21: 1件あたりの処理時間 | C21: 集計期間の平均（呼出から処理済みまで） | D21: 集計期間の平均（呼出から処理済みまで）
B22: 平均処理時間（分） | C22: ='市民部'!C10 -> 9.1814608 | D22: ='厚生部'!C7 -> 18.28506
B23: 時刻の細かさ | C23: 15分ごとにまとめて数える | D23: 15分ごとにまとめて数える
B25: 4. 計算の手順
B26: 市民部 | C26: 内容 | E26: 数値
B27: ① 対象の人数 | C27: 減らす時間帯に発券した件数（8区の合計） | E27: ='市民部'!C22 -> 38403
B28: ② 平均処理時間（分） | C28: 1人の対応にかかった時間の平均 | E28: ='市民部'!D22 -> 9.1814608
B29: ③ 合計の時間（分） | C29: ① × ② | E29: ='市民部'!E22 -> 352595.64
B30: ④ 減らせる時間（時間） | C30: ③ ÷ 60（分を時間に直す） | E30: ='市民部'!F22 -> 5876.594
B32: 厚生部 | C32: 内容 | E32: 数値
B33: ① 対象の人数（期間計） | C33: 基準時刻以降に発券した件数（7区の合計） | E33: ='厚生部'!D19 -> 15890
B34: ② 1年分に直す | C34: 区ごとに 件数 ÷ データのある月数 × 12 をして合計 | E34: ='厚生部'!F19 -> 32558
B35: ③ 8区に換算 | C35: ② × 8 ÷ 7（安芸区の分を補う） | E35: ='厚生部'!F20 -> 37209.143
B36: ④ 平均処理時間（分） | C36: 1人の対応にかかった時間の平均 | E36: ='厚生部'!C7 -> 18.28506
B37: ⑤ 減らせる時間（時間） | C37: ③ × ④ ÷ 60 | E37: ='厚生部'!G20 -> 11339.523
B39: 合計（時間／年） | C39: 市民部 ＋ 厚生部。「時間外削減効果」シートの合計と同じ | E39: ='時間外削減効果'!E8 -> 17216.117
B41: 5. 見るときの注意
B42: ・記録のない月がある区は、その月の人数が少なく出る（市民部の「データのある月数」で確認できる）。
B43: ・厚生部は半年分のデータを12倍しているので、月による来庁数の違い（繁忙期など）は反映されていない。
B44: ・処理時間は、呼出から処理済みまでの時間。長く放置された件も除かずに平均している。
B45: ・別添の値（市民部6,131時間、厚生部10,373時間）とは、期間やデータの範囲が違うため、少し差が出る。
B47: → 時間外削減効果の総括へ

Sheet 市民部
B1: 市民部の時間外削減効果
B2: 削減対象の発券数 × 平均処理時間 ÷ 60 ＝ 削減できる窓口対応時間（時間／年）。発券機のCSVを取り込んで集計する。
B4: 削減対象の発券時間 開始 | C4: 0.6875
B5: 削減対象の発券時間 終了（これより前） | C5: 0.71875 | D5: 現行の受付終了時刻（15分刻みで集計）
B6: 集計期間 開始（年月） | C6: 202501 | D6: 発券数・平均処理時間とも、この期間で集計
B7: 集計期間 終了（年月） | C7: 202512
B8: 平均処理時間（分）の指定 | D8: 空欄の場合は実績平均を使用
B9: 平均処理時間の実績（集計期間） | C9: =IFERROR(SUMIFS('取込_市民部'!$D$8:$D$1007,'取込_市民部'!$B$8:$B$1007,">="&C6,'取込_市民部'!$B$8:$B$1007,"<="&C7)/SUMIFS('取込_市民部'!$E$8:$E$1007,'取込_市民部'!$B$8:$B$1007,">="&C6,'取込_市民部'!$B$8:$B$1007,"<="&C7),0) -> 9.1814608
B10: 採用する平均処理時間（分） | C10: =IF(ISNUMBER(C8),C8,C9) -> 9.1814608
B12: 区別
B13: 区 | C13: 削減対象の発券数（件） | D13: 平均処理時間（分） | E13: 分 | F13: 削減時間（時間） | G13: データのある月数
B14: 中区 | C14: =SUMPRODUCT(('取込_市民部'!$A$8:$A$1007=$B14)*('取込_市民部'!$B$8:$B$1007>=$C$6)*('取込_市民部'!$B$8:$B$1007<=$C$7)*('取込_市民部'!$F$6:$CW$6>=ROUND($C$4*1440,0))*('取込_市民部'!$F$6:$CW$6<ROUND($C$5*1440,0))*'取込_市民部'!$F$8:$CW$1007) -> 10747 | D14: =$C$10 -> 9.1814608 | E14: =C14*D14 -> 98673.159 | F14: =E14/60 -> 1644.5527 | G14: =SUMPRODUCT(('取込_市民部'!$A$8:$A$1007=$B14)*('取込_市民部'!$B$8:$B$1007>=$C$6)*('取込_市民部'!$B$8:$B$1007<=$C$7)*('取込_市民部'!$C$8:$C$1007>0)) -> 11
B15: 東区 | C15: =SUMPRODUCT(('取込_市民部'!$A$8:$A$1007=$B15)*('取込_市民部'!$B$8:$B$1007>=$C$6)*('取込_市民部'!$B$8:$B$1007<=$C$7)*('取込_市民部'!$F$6:$CW$6>=ROUND($C$4*1440,0))*('取込_市民部'!$F$6:$CW$6<ROUND($C$5*1440,0))*'取込_市民部'!$F$8:$CW$1007) -> 3525 | D15: =$C$10 -> 9.1814608 | E15: =C15*D15 -> 32364.649 | F15: =E15/60 -> 539.41082 | G15: =SUMPRODUCT(('取込_市民部'!$A$8:$A$1007=$B15)*('取込_市民部'!$B$8:$B$1007>=$C$6)*('取込_市民部'!$B$8:$B$1007<=$C$7)*('取込_市民部'!$C$8:$C$1007>0)) -> 12
B16: 南区 | C16: =SUMPRODUCT(('取込_市民部'!$A$8:$A$1007=$B16)*('取込_市民部'!$B$8:$B$1007>=$C$6)*('取込_市民部'!$B$8:$B$1007<=$C$7)*('取込_市民部'!$F$6:$CW$6>=ROUND($C$4*1440,0))*('取込_市民部'!$F$6:$CW$6<ROUND($C$5*1440,0))*'取込_市民部'!$F$8:$CW$1007) -> 5414 | D16: =$C$10 -> 9.1814608 | E16: =C16*D16 -> 49708.429 | F16: =E16/60 -> 828.47381 | G16: =SUMPRODUCT(('取込_市民部'!$A$8:$A$1007=$B16)*('取込_市民部'!$B$8:$B$1007>=$C$6)*('取込_市民部'!$B$8:$B$1007<=$C$7)*('取込_市民部'!$C$8:$C$1007>0)) -> 10
B17: 西区 | C17: =SUMPRODUCT(('取込_市民部'!$A$8:$A$1007=$B17)*('取込_市民部'!$B$8:$B$1007>=$C$6)*('取込_市民部'!$B$8:$B$1007<=$C$7)*('取込_市民部'!$F$6:$CW$6>=ROUND($C$4*1440,0))*('取込_市民部'!$F$6:$CW$6<ROUND($C$5*1440,0))*'取込_市民部'!$F$8:$CW$1007) -> 7615 | D17: =$C$10 -> 9.1814608 | E17: =C17*D17 -> 69916.824 | F17: =E17/60 -> 1165.2804 | G17: =SUMPRODUCT(('取込_市民部'!$A$8:$A$1007=$B17)*('取込_市民部'!$B$8:$B$1007>=$C$6)*('取込_市民部'!$B$8:$B$1007<=$C$7)*('取込_市民部'!$C$8:$C$1007>0)) -> 12
B18: 安佐南区 | C18: =SUMPRODUCT(('取込_市民部'!$A$8:$A$1007=$B18)*('取込_市民部'!$B$8:$B$1007>=$C$6)*('取込_市民部'!$B$8:$B$1007<=$C$7)*('取込_市民部'!$F$6:$CW$6>=ROUND($C$4*1440,0))*('取込_市民部'!$F$6:$CW$6<ROUND($C$5*1440,0))*'取込_市民部'!$F$8:$CW$1007) -> 1429 | D18: =$C$10 -> 9.1814608 | E18: =C18*D18 -> 13120.307 | F18: =E18/60 -> 218.67179 | G18: =SUMPRODUCT(('取込_市民部'!$A$8:$A$1007=$B18)*('取込_市民部'!$B$8:$B$1007>=$C$6)*('取込_市民部'!$B$8:$B$1007<=$C$7)*('取込_市民部'!$C$8:$C$1007>0)) -> 11
B19: 安佐北区 | C19: =SUMPRODUCT(('取込_市民部'!$A$8:$A$1007=$B19)*('取込_市民部'!$B$8:$B$1007>=$C$6)*('取込_市民部'!$B$8:$B$1007<=$C$7)*('取込_市民部'!$F$6:$CW$6>=ROUND($C$4*1440,0))*('取込_市民部'!$F$6:$CW$6<ROUND($C$5*1440,0))*'取込_市民部'!$F$8:$CW$1007) -> 2990 | D19: =$C$10 -> 9.1814608 | E19: =C19*D19 -> 27452.568 | F19: =E19/60 -> 457.5428 | G19: =SUMPRODUCT(('取込_市民部'!$A$8:$A$1007=$B19)*('取込_市民部'!$B$8:$B$1007>=$C$6)*('取込_市民部'!$B$8:$B$1007<=$C$7)*('取込_市民部'!$C$8:$C$1007>0)) -> 12
B20: 安芸区 | C20: =SUMPRODUCT(('取込_市民部'!$A$8:$A$1007=$B20)*('取込_市民部'!$B$8:$B$1007>=$C$6)*('取込_市民部'!$B$8:$B$1007<=$C$7)*('取込_市民部'!$F$6:$CW$6>=ROUND($C$4*1440,0))*('取込_市民部'!$F$6:$CW$6<ROUND($C$5*1440,0))*'取込_市民部'!$F$8:$CW$1007) -> 1774 | D20: =$C$10 -> 9.1814608 | E20: =C20*D20 -> 16287.911 | F20: =E20/60 -> 271.46519 | G20: =SUMPRODUCT(('取込_市民部'!$A$8:$A$1007=$B20)*('取込_市民部'!$B$8:$B$1007>=$C$6)*('取込_市民部'!$B$8:$B$1007<=$C$7)*('取込_市民部'!$C$8:$C$1007>0)) -> 12
B21: 佐伯区 | C21: =SUMPRODUCT(('取込_市民部'!$A$8:$A$1007=$B21)*('取込_市民部'!$B$8:$B$1007>=$C$6)*('取込_市民部'!$B$8:$B$1007<=$C$7)*('取込_市民部'!$F$6:$CW$6>=ROUND($C$4*1440,0))*('取込_市民部'!$F$6:$CW$6<ROUND($C$5*1440,0))*'取込_市民部'!$F$8:$CW$1007) -> 4909 | D21: =$C$10 -> 9.1814608 | E21: =C21*D21 -> 45071.791 | F21: =E21/60 -> 751.19652 | G21: =SUMPRODUCT(('取込_市民部'!$A$8:$A$1007=$B21)*('取込_市民部'!$B$8:$B$1007>=$C$6)*('取込_市民部'!$B$8:$B$1007<=$C$7)*('取込_市民部'!$C$8:$C$1007>0)) -> 12
B22: 計 | C22: =SUM(C14:C21) -> 38403 | D22: =C10 -> 9.1814608 | E22: =SUM(E14:E21) -> 352595.64 | F22: =SUM(F14:F21) -> 5876.594
B24: 別添の値
B25: 区分 | C25: 発券数（件） | D25: 平均処理時間（分） | E25: 分 | F25: 時間
B26: 市民部8区役所12ヶ月 | C26: 39988 | D26: 9.2 | E26: =C26*D26 -> 367889.6 | F26: =E26/60 -> 6131.4933
B27: 差（データ−別添） | C27: =C22-C26 -> -1585 | F27: =F22/F26-1 -> -0.04157215
B29: 注：別添の発券数（39,988件）は令和7年度の集計。取り込んだCSVの範囲（2024年1月〜2025年12月）では、2025年1〜12月を既定の集計期間としている。
B30: 注：南区の2025年11月、令和7年度後半など、発券機データのない月がある。「データのある月数」で確認できる。
B31: 注：取り込んだCSVは、同じ区・同じ日のファイルが複数あるときは最初の1つだけ使う（区をまたいだコピーの混入を防ぐため）。

Sheet 厚生部
B1: 厚生部の時間外削減効果
B2: 発券機のCSVから、基準時刻以降の発券数を年間に換算し、平均処理時間を掛ける。安芸区のデータがないため、7区の値を×8÷7で8区に換算。
B4: 基準時刻（これ以降の発券） | C4: 0.6875 | D4: 15分刻みで集計
B5: 平均処理時間（分）の指定 | D5: 空欄の場合は集計期間の実績平均を使用
B6: 平均処理時間の実績（集計期間） | C6: =IFERROR(SUMIFS('取込_厚生部'!$D$8:$D$1007,'取込_厚生部'!$B$8:$B$1007,">="&C8,'取込_厚生部'!$B$8:$B$1007,"<="&D8)/SUMIFS('取込_厚生部'!$E$8:$E$1007,'取込_厚生部'!$B$8:$B$1007,">="&C8,'取込_厚生部'!$B$8:$B$1007,"<="&D8),0) -> 18.28506
B7: 採用する平均処理時間（分） | C7: =IF(ISNUMBER(C5),C5,C6) -> 18.28506
B8: 集計期間（年月〜年月） | C8: 202604 | D8: 202609
B10: 区別
B11: 区 | C11: データのある月数 | D11: 基準以降の発券数（期間計） | E11: 月平均（件） | F11: 年間換算（件） | G11: 削減時間（時間／年）
B12: 中区 | C12: =SUMPRODUCT(('取込_厚生部'!$A$8:$A$1007=$B12)*('取込_厚生部'!$B$8:$B$1007>=$C$8)*('取込_厚生部'!$B$8:$B$1007<=$D$8)*('取込_厚生部'!$C$8:$C$1007>0)) -> 6 | D12: =SUMPRODUCT(('取込_厚生部'!$A$8:$A$1007=$B12)*('取込_厚生部'!$B$8:$B$1007>=$C$8)*('取込_厚生部'!$B$8:$B$1007<=$D$8)*('取込_厚生部'!$F$6:$CW$6>=ROUND($C$4*1440,0))*'取込_厚生部'!$F$8:$CW$1007) -> 1619 | E12: =IF(C12=0,0,D12/C12) -> 269.83333 | F12: =E12*12 -> 3238 | G12: =F12*$C$7/60 -> 986.78374
B13: 東区 | C13: =SUMPRODUCT(('取込_厚生部'!$A$8:$A$1007=$B13)*('取込_厚生部'!$B$8:$B$1007>=$C$8)*('取込_厚生部'!$B$8:$B$1007<=$D$8)*('取込_厚生部'!$C$8:$C$1007>0)) -> 4 | D13: =SUMPRODUCT(('取込_厚生部'!$A$8:$A$1007=$B13)*('取込_厚生部'!$B$8:$B$1007>=$C$8)*('取込_厚生部'!$B$8:$B$1007<=$D$8)*('取込_厚生部'!$F$6:$CW$6>=ROUND($C$4*1440,0))*'取込_厚生部'!$F$8:$CW$1007) -> 778 | E13: =IF(C13=0,0,D13/C13) -> 194.5 | F13: =E13*12 -> 2334 | G13: =F13*$C$7/60 -> 711.28883
B14: 南区 | C14: =SUMPRODUCT(('取込_厚生部'!$A$8:$A$1007=$B14)*('取込_厚生部'!$B$8:$B$1007>=$C$8)*('取込_厚生部'!$B$8:$B$1007<=$D$8)*('取込_厚生部'!$C$8:$C$1007>0)) -> 6 | D14: =SUMPRODUCT(('取込_厚生部'!$A$8:$A$1007=$B14)*('取込_厚生部'!$B$8:$B$1007>=$C$8)*('取込_厚生部'!$B$8:$B$1007<=$D$8)*('取込_厚生部'!$F$6:$CW$6>=ROUND($C$4*1440,0))*'取込_厚生部'!$F$8:$CW$1007) -> 3531 | E14: =IF(C14=0,0,D14/C14) -> 588.5 | F14: =E14*12 -> 7062 | G14: =F14*$C$7/60 -> 2152.1516
B15: 西区 | C15: =SUMPRODUCT(('取込_厚生部'!$A$8:$A$1007=$B15)*('取込_厚生部'!$B$8:$B$1007>=$C$8)*('取込_厚生部'!$B$8:$B$1007<=$D$8)*('取込_厚生部'!$C$8:$C$1007>0)) -> 6 | D15: =SUMPRODUCT(('取込_厚生部'!$A$8:$A$1007=$B15)*('取込_厚生部'!$B$8:$B$1007>=$C$8)*('取込_厚生部'!$B$8:$B$1007<=$D$8)*('取込_厚生部'!$F$6:$CW$6>=ROUND($C$4*1440,0))*'取込_厚生部'!$F$8:$CW$1007) -> 4550 | E15: =IF(C15=0,0,D15/C15) -> 758.33333 | F15: =E15*12 -> 9100 | G15: =F15*$C$7/60 -> 2773.2341
B16: 安佐南区 | C16: =SUMPRODUCT(('取込_厚生部'!$A$8:$A$1007=$B16)*('取込_厚生部'!$B$8:$B$1007>=$C$8)*('取込_厚生部'!$B$8:$B$1007<=$D$8)*('取込_厚生部'!$C$8:$C$1007>0)) -> 6 | D16: =SUMPRODUCT(('取込_厚生部'!$A$8:$A$1007=$B16)*('取込_厚生部'!$B$8:$B$1007>=$C$8)*('取込_厚生部'!$B$8:$B$1007<=$D$8)*('取込_厚生部'!$F$6:$CW$6>=ROUND($C$4*1440,0))*'取込_厚生部'!$F$8:$CW$1007) -> 2090 | E16: =IF(C16=0,0,D16/C16) -> 348.33333 | F16: =E16*12 -> 4180 | G16: =F16*$C$7/60 -> 1273.8592
B17: 安佐北区 | C17: =SUMPRODUCT(('取込_厚生部'!$A$8:$A$1007=$B17)*('取込_厚生部'!$B$8:$B$1007>=$C$8)*('取込_厚生部'!$B$8:$B$1007<=$D$8)*('取込_厚生部'!$C$8:$C$1007>0)) -> 6 | D17: =SUMPRODUCT(('取込_厚生部'!$A$8:$A$1007=$B17)*('取込_厚生部'!$B$8:$B$1007>=$C$8)*('取込_厚生部'!$B$8:$B$1007<=$D$8)*('取込_厚生部'!$F$6:$CW$6>=ROUND($C$4*1440,0))*'取込_厚生部'!$F$8:$CW$1007) -> 1195 | E17: =IF(C17=0,0,D17/C17) -> 199.16667 | F17: =E17*12 -> 2390 | G17: =F17*$C$7/60 -> 728.35489
B18: 佐伯区 | C18: =SUMPRODUCT(('取込_厚生部'!$A$8:$A$1007=$B18)*('取込_厚生部'!$B$8:$B$1007>=$C$8)*('取込_厚生部'!$B$8:$B$1007<=$D$8)*('取込_厚生部'!$C$8:$C$1007>0)) -> 6 | D18: =SUMPRODUCT(('取込_厚生部'!$A$8:$A$1007=$B18)*('取込_厚生部'!$B$8:$B$1007>=$C$8)*('取込_厚生部'!$B$8:$B$1007<=$D$8)*('取込_厚生部'!$F$6:$CW$6>=ROUND($C$4*1440,0))*'取込_厚生部'!$F$8:$CW$1007) -> 2127 | E18: =IF(C18=0,0,D18/C18) -> 354.5 | F18: =E18*12 -> 4254 | G18: =F18*$C$7/60 -> 1296.4108
B19: 7区計 | D19: =SUM(D12:D18) -> 15890 | F19: =SUM(F12:F18) -> 32558 | G19: =SUM(G12:G18) -> 9922.083
B20: 8区換算（×8÷7） | F20: =F19*8/7 -> 37209.143 | G20: =G19*8/7 -> 11339.523
B22: 別添の値
B23: 区分 | C23: 発券数（2ヶ月） | D23: 平均処理時間（分） | E23: 分 | F23: 時間 | G23: 12ヶ月換算 | H23: 8区換算
B24: 厚生部7区役所（安芸区除く）2ヶ月 | C24: 4449 | D24: 20.4 | E24: 90759.6 | F24: 1512.66 | G24: 9075.96 | H24: 10372.526
B25: 差（データ−別添） | H25: =G20/H24-1 -> 0.093226838
B27: 月別の発券数（全時間帯）
B28: 区 | C28: =$C$8 -> 202604 | D28: =IF(C28="","",IF(IF(MOD(C28,100)=12,C28+89,C28+1)>$D$8,"",IF(MOD(C28,100)=12,C28+89,C28+1))) -> 202605 | E28: =IF(D28="","",IF(IF(MOD(D28,100)=12,D28+89,D28+1)>$D$8,"",IF(MOD(D28,100)=12,D28+89,D28+1))) -> 202606 | F28: =IF(E28="","",IF(IF(MOD(E28,100)=12,E28+89,E28+1)>$D$8,"",IF(MOD(E28,100)=12,E28+89,E28+1))) -> 202607 | G28: =IF(F28="","",IF(IF(MOD(F28,100)=12,F28+89,F28+1)>$D$8,"",IF(MOD(F28,100)=12,F28+89,F28+1))) -> 202608 | H28: =IF(G28="","",IF(IF(MOD(G28,100)=12,G28+89,G28+1)>$D$8,"",IF(MOD(G28,100)=12,G28+89,G28+1))) -> 202609
B29: 中区 | C29: =IF(C$28="","",SUMIFS('取込_厚生部'!$C$8:$C$1007,'取込_厚生部'!$A$8:$A$1007,$B29,'取込_厚生部'!$B$8:$B$1007,C$28)) -> 3767 | D29: =IF(D$28="","",SUMIFS('取込_厚生部'!$C$8:$C$1007,'取込_厚生部'!$A$8:$A$1007,$B29,'取込_厚生部'!$B$8:$B$1007,D$28)) -> 3465 | E29: =IF(E$28="","",SUMIFS('取込_厚生部'!$C$8:$C$1007,'取込_厚生部'!$A$8:$A$1007,$B29,'取込_厚生部'!$B$8:$B$1007,E$28)) -> 4777 | F29: =IF(F$28="","",SUMIFS('取込_厚生部'!$C$8:$C$1007,'取込_厚生部'!$A$8:$A$1007,$B29,'取込_厚生部'!$B$8:$B$1007,F$28)) -> 4638 | G29: =IF(G$28="","",SUMIFS('取込_厚生部'!$C$8:$C$1007,'取込_厚生部'!$A$8:$A$1007,$B29,'取込_厚生部'!$B$8:$B$1007,G$28)) -> 5250 | H29: =IF(H$28="","",SUMIFS('取込_厚生部'!$C$8:$C$1007,'取込_厚生部'!$A$8:$A$1007,$B29,'取込_厚生部'!$B$8:$B$1007,H$28)) -> 3938
B30: 東区 | C30: =IF(C$28="","",SUMIFS('取込_厚生部'!$C$8:$C$1007,'取込_厚生部'!$A$8:$A$1007,$B30,'取込_厚生部'!$B$8:$B$1007,C$28)) -> 3595 | D30: =IF(D$28="","",SUMIFS('取込_厚生部'!$C$8:$C$1007,'取込_厚生部'!$A$8:$A$1007,$B30,'取込_厚生部'!$B$8:$B$1007,D$28)) -> 3507 | E30: =IF(E$28="","",SUMIFS('取込_厚生部'!$C$8:$C$1007,'取込_厚生部'!$A$8:$A$1007,$B30,'取込_厚生部'!$B$8:$B$1007,E$28)) -> 4559 | F30: =IF(F$28="","",SUMIFS('取込_厚生部'!$C$8:$C$1007,'取込_厚生部'!$A$8:$A$1007,$B30,'取込_厚生部'!$B$8:$B$1007,F$28)) -> 4412 | G30: =IF(G$28="","",SUMIFS('取込_厚生部'!$C$8:$C$1007,'取込_厚生部'!$A$8:$A$1007,$B30,'取込_厚生部'!$B$8:$B$1007,G$28)) -> 0 | H30: =IF(H$28="","",SUMIFS('取込_厚生部'!$C$8:$C$1007,'取込_厚生部'!$A$8:$A$1007,$B30,'取込_厚生部'!$B$8:$B$1007,H$28)) -> 0
B31: 南区 | C31: =IF(C$28="","",SUMIFS('取込_厚生部'!$C$8:$C$1007,'取込_厚生部'!$A$8:$A$1007,$B31,'取込_厚生部'!$B$8:$B$1007,C$28)) -> 3624 | D31: =IF(D$28="","",SUMIFS('取込_厚生部'!$C$8:$C$1007,'取込_厚生部'!$A$8:$A$1007,$B31,'取込_厚生部'!$B$8:$B$1007,D$28)) -> 3868 | E31: =IF(E$28="","",SUMIFS('取込_厚生部'!$C$8:$C$1007,'取込_厚生部'!$A$8:$A$1007,$B31,'取込_厚生部'!$B$8:$B$1007,E$28)) -> 5278 | F31: =IF(F$28="","",SUMIFS('取込_厚生部'!$C$8:$C$1007,'取込_厚生部'!$A$8:$A$1007,$B31,'取込_厚生部'!$B$8:$B$1007,F$28)) -> 5466 | G31: =IF(G$28="","",SUMIFS('取込_厚生部'!$C$8:$C$1007,'取込_厚生部'!$A$8:$A$1007,$B31,'取込_厚生部'!$B$8:$B$1007,G$28)) -> 5944 | H31: =IF(H$28="","",SUMIFS('取込_厚生部'!$C$8:$C$1007,'取込_厚生部'!$A$8:$A$1007,$B31,'取込_厚生部'!$B$8:$B$1007,H$28)) -> 4485
B32: 西区 | C32: =IF(C$28="","",SUMIFS('取込_厚生部'!$C$8:$C$1007,'取込_厚生部'!$A$8:$A$1007,$B32,'取込_厚生部'!$B$8:$B$1007,C$28)) -> 5370 | D32: =IF(D$28="","",SUMIFS('取込_厚生部'!$C$8:$C$1007,'取込_厚生部'!$A$8:$A$1007,$B32,'取込_厚生部'!$B$8:$B$1007,D$28)) -> 5020 | E32: =IF(E$28="","",SUMIFS('取込_厚生部'!$C$8:$C$1007,'取込_厚生部'!$A$8:$A$1007,$B32,'取込_厚生部'!$B$8:$B$1007,E$28)) -> 6607 | F32: =IF(F$28="","",SUMIFS('取込_厚生部'!$C$8:$C$1007,'取込_厚生部'!$A$8:$A$1007,$B32,'取込_厚生部'!$B$8:$B$1007,F$28)) -> 6636 | G32: =IF(G$28="","",SUMIFS('取込_厚生部'!$C$8:$C$1007,'取込_厚生部'!$A$8:$A$1007,$B32,'取込_厚生部'!$B$8:$B$1007,G$28)) -> 7296 | H32: =IF(H$28="","",SUMIFS('取込_厚生部'!$C$8:$C$1007,'取込_厚生部'!$A$8:$A$1007,$B32,'取込_厚生部'!$B$8:$B$1007,H$28)) -> 5534
B33: 安佐南区 | C33: =IF(C$28="","",SUMIFS('取込_厚生部'!$C$8:$C$1007,'取込_厚生部'!$A$8:$A$1007,$B33,'取込_厚生部'!$B$8:$B$1007,C$28)) -> 6558 | D33: =IF(D$28="","",SUMIFS('取込_厚生部'!$C$8:$C$1007,'取込_厚生部'!$A$8:$A$1007,$B33,'取込_厚生部'!$B$8:$B$1007,D$28)) -> 6316 | E33: =IF(E$28="","",SUMIFS('取込_厚生部'!$C$8:$C$1007,'取込_厚生部'!$A$8:$A$1007,$B33,'取込_厚生部'!$B$8:$B$1007,E$28)) -> 8023 | F33: =IF(F$28="","",SUMIFS('取込_厚生部'!$C$8:$C$1007,'取込_厚生部'!$A$8:$A$1007,$B33,'取込_厚生部'!$B$8:$B$1007,F$28)) -> 8089 | G33: =IF(G$28="","",SUMIFS('取込_厚生部'!$C$8:$C$1007,'取込_厚生部'!$A$8:$A$1007,$B33,'取込_厚生部'!$B$8:$B$1007,G$28)) -> 8307 | H33: =IF(H$28="","",SUMIFS('取込_厚生部'!$C$8:$C$1007,'取込_厚生部'!$A$8:$A$1007,$B33,'取込_厚生部'!$B$8:$B$1007,H$28)) -> 6681
B34: 安佐北区 | C34: =IF(C$28="","",SUMIFS('取込_厚生部'!$C$8:$C$1007,'取込_厚生部'!$A$8:$A$1007,$B34,'取込_厚生部'!$B$8:$B$1007,C$28)) -> 3284 | D34: =IF(D$28="","",SUMIFS('取込_厚生部'!$C$8:$C$1007,'取込_厚生部'!$A$8:$A$1007,$B34,'取込_厚生部'!$B$8:$B$1007,D$28)) -> 3112 | E34: =IF(E$28="","",SUMIFS('取込_厚生部'!$C$8:$C$1007,'取込_厚生部'!$A$8:$A$1007,$B34,'取込_厚生部'!$B$8:$B$1007,E$28)) -> 4312 | F34: =IF(F$28="","",SUMIFS('取込_厚生部'!$C$8:$C$1007,'取込_厚生部'!$A$8:$A$1007,$B34,'取込_厚生部'!$B$8:$B$1007,F$28)) -> 4192 | G34: =IF(G$28="","",SUMIFS('取込_厚生部'!$C$8:$C$1007,'取込_厚生部'!$A$8:$A$1007,$B34,'取込_厚生部'!$B$8:$B$1007,G$28)) -> 4785 | H34: =IF(H$28="","",SUMIFS('取込_厚生部'!$C$8:$C$1007,'取込_厚生部'!$A$8:$A$1007,$B34,'取込_厚生部'!$B$8:$B$1007,H$28)) -> 3328
B35: 佐伯区 | C35: =IF(C$28="","",SUMIFS('取込_厚生部'!$C$8:$C$1007,'取込_厚生部'!$A$8:$A$1007,$B35,'取込_厚生部'!$B$8:$B$1007,C$28)) -> 4240 | D35: =IF(D$28="","",SUMIFS('取込_厚生部'!$C$8:$C$1007,'取込_厚生部'!$A$8:$A$1007,$B35,'取込_厚生部'!$B$8:$B$1007,D$28)) -> 4020 | E35: =IF(E$28="","",SUMIFS('取込_厚生部'!$C$8:$C$1007,'取込_厚生部'!$A$8:$A$1007,$B35,'取込_厚生部'!$B$8:$B$1007,E$28)) -> 5511 | F35: =IF(F$28="","",SUMIFS('取込_厚生部'!$C$8:$C$1007,'取込_厚生部'!$A$8:$A$1007,$B35,'取込_厚生部'!$B$8:$B$1007,F$28)) -> 5217 | G35: =IF(G$28="","",SUMIFS('取込_厚生部'!$C$8:$C$1007,'取込_厚生部'!$A$8:$A$1007,$B35,'取込_厚生部'!$B$8:$B$1007,G$28)) -> 6528 | H35: =IF(H$28="","",SUMIFS('取込_厚生部'!$C$8:$C$1007,'取込_厚生部'!$A$8:$A$1007,$B35,'取込_厚生部'!$B$8:$B$1007,H$28)) -> 4420
B36: 計 | C36: =SUM(C29:C35) -> 30438 | D36: =SUM(D29:D35) -> 29308 | E36: =SUM(E29:E35) -> 39067 | F36: =SUM(F29:F35) -> 38650 | G36: =SUM(G29:G35) -> 38110 | H36: =SUM(H29:H35) -> 28386
B38: 基準以降
B39: 区 | C39: =C28 -> 202604 | D39: =D28 -> 202605 | E39: =E28 -> 202606 | F39: =F28 -> 202607 | G39: =G28 -> 202608 | H39: =H28 -> 202609
B40: 中区 | C40: =IF(C$39="","",SUMPRODUCT(('取込_厚生部'!$A$8:$A$1007=$B40)*('取込_厚生部'!$B$8:$B$1007=C$39)*('取込_厚生部'!$F$6:$CW$6>=ROUND($C$4*1440,0))*'取込_厚生部'!$F$8:$CW$1007)) -> 251 | D40: =IF(D$39="","",SUMPRODUCT(('取込_厚生部'!$A$8:$A$1007=$B40)*('取込_厚生部'!$B$8:$B$1007=D$39)*('取込_厚生部'!$F$6:$CW$6>=ROUND($C$4*1440,0))*'取込_厚生部'!$F$8:$CW$1007)) -> 232 | E40: =IF(E$39="","",SUMPRODUCT(('取込_厚生部'!$A$8:$A$1007=$B40)*('取込_厚生部'!$B$8:$B$1007=E$39)*('取込_厚生部'!$F$6:$CW$6>=ROUND($C$4*1440,0))*'取込_厚生部'!$F$8:$CW$1007)) -> 276 | F40: =IF(F$39="","",SUMPRODUCT(('取込_厚生部'!$A$8:$A$1007=$B40)*('取込_厚生部'!$B$8:$B$1007=F$39)*('取込_厚生部'!$F$6:$CW$6>=ROUND($C$4*1440,0))*'取込_厚生部'!$F$8:$CW$1007)) -> 279 | G40: =IF(G$39="","",SUMPRODUCT(('取込_厚生部'!$A$8:$A$1007=$B40)*('取込_厚生部'!$B$8:$B$1007=G$39)*('取込_厚生部'!$F$6:$CW$6>=ROUND($C$4*1440,0))*'取込_厚生部'!$F$8:$CW$1007)) -> 348 | H40: =IF(H$39="","",SUMPRODUCT(('取込_厚生部'!$A$8:$A$1007=$B40)*('取込_厚生部'!$B$8:$B$1007=H$39)*('取込_厚生部'!$F$6:$CW$6>=ROUND($C$4*1440,0))*'取込_厚生部'!$F$8:$CW$1007)) -> 233
B41: 東区 | C41: =IF(C$39="","",SUMPRODUCT(('取込_厚生部'!$A$8:$A$1007=$B41)*('取込_厚生部'!$B$8:$B$1007=C$39)*('取込_厚生部'!$F$6:$CW$6>=ROUND($C$4*1440,0))*'取込_厚生部'!$F$8:$CW$1007)) -> 159 | D41: =IF(D$39="","",SUMPRODUCT(('取込_厚生部'!$A$8:$A$1007=$B41)*('取込_厚生部'!$B$8:$B$1007=D$39)*('取込_厚生部'!$F$6:$CW$6>=ROUND($C$4*1440,0))*'取込_厚生部'!$F$8:$CW$1007)) -> 191 | E41: =IF(E$39="","",SUMPRODUCT(('取込_厚生部'!$A$8:$A$1007=$B41)*('取込_厚生部'!$B$8:$B$1007=E$39)*('取込_厚生部'!$F$6:$CW$6>=ROUND($C$4*1440,0))*'取込_厚生部'!$F$8:$CW$1007)) -> 213 | F41: =IF(F$39="","",SUMPRODUCT(('取込_厚生部'!$A$8:$A$1007=$B41)*('取込_厚生部'!$B$8:$B$1007=F$39)*('取込_厚生部'!$F$6:$CW$6>=ROUND($C$4*1440,0))*'取込_厚生部'!$F$8:$CW$1007)) -> 215 | G41: =IF(G$39="","",SUMPRODUCT(('取込_厚生部'!$A$8:$A$1007=$B41)*('取込_厚生部'!$B$8:$B$1007=G$39)*('取込_厚生部'!$F$6:$CW$6>=ROUND($C$4*1440,0))*'取込_厚生部'!$F$8:$CW$1007)) -> 0 | H41: =IF(H$39="","",SUMPRODUCT(('取込_厚生部'!$A$8:$A$1007=$B41)*('取込_厚生部'!$B$8:$B$1007=H$39)*('取込_厚生部'!$F$6:$CW$6>=ROUND($C$4*1440,0))*'取込_厚生部'!$F$8:$CW$1007)) -> 0
B42: 南区 | C42: =IF(C$39="","",SUMPRODUCT(('取込_厚生部'!$A$8:$A$1007=$B42)*('取込_厚生部'!$B$8:$B$1007=C$39)*('取込_厚生部'!$F$6:$CW$6>=ROUND($C$4*1440,0))*'取込_厚生部'!$F$8:$CW$1007)) -> 428 | D42: =IF(D$39="","",SUMPRODUCT(('取込_厚生部'!$A$8:$A$1007=$B42)*('取込_厚生部'!$B$8:$B$1007=D$39)*('取込_厚生部'!$F$6:$CW$6>=ROUND($C$4*1440,0))*'取込_厚生部'!$F$8:$CW$1007)) -> 472 | E42: =IF(E$39="","",SUMPRODUCT(('取込_厚生部'!$A$8:$A$1007=$B42)*('取込_厚生部'!$B$8:$B$1007=E$39)*('取込_厚生部'!$F$6:$CW$6>=ROUND($C$4*1440,0))*'取込_厚生部'!$F$8:$CW$1007)) -> 603 | F42: =IF(F$39="","",SUMPRODUCT(('取込_厚生部'!$A$8:$A$1007=$B42)*('取込_厚生部'!$B$8:$B$1007=F$39)*('取込_厚生部'!$F$6:$CW$6>=ROUND($C$4*1440,0))*'取込_厚生部'!$F$8:$CW$1007)) -> 697 | G42: =IF(G$39="","",SUMPRODUCT(('取込_厚生部'!$A$8:$A$1007=$B42)*('取込_厚生部'!$B$8:$B$1007=G$39)*('取込_厚生部'!$F$6:$CW$6>=ROUND($C$4*1440,0))*'取込_厚生部'!$F$8:$CW$1007)) -> 797 | H42: =IF(H$39="","",SUMPRODUCT(('取込_厚生部'!$A$8:$A$1007=$B42)*('取込_厚生部'!$B$8:$B$1007=H$39)*('取込_厚生部'!$F$6:$CW$6>=ROUND($C$4*1440,0))*'取込_厚生部'!$F$8:$CW$1007)) -> 534
B43: 西区 | C43: =IF(C$39="","",SUMPRODUCT(('取込_厚生部'!$A$8:$A$1007=$B43)*('取込_厚生部'!$B$8:$B$1007=C$39)*('取込_厚生部'!$F$6:$CW$6>=ROUND($C$4*1440,0))*'取込_厚生部'!$F$8:$CW$1007)) -> 737 | D43: =IF(D$39="","",SUMPRODUCT(('取込_厚生部'!$A$8:$A$1007=$B43)*('取込_厚生部'!$B$8:$B$1007=D$39)*('取込_厚生部'!$F$6:$CW$6>=ROUND($C$4*1440,0))*'取込_厚生部'!$F$8:$CW$1007)) -> 595 | E43: =IF(E$39="","",SUMPRODUCT(('取込_厚生部'!$A$8:$A$1007=$B43)*('取込_厚生部'!$B$8:$B$1007=E$39)*('取込_厚生部'!$F$6:$CW$6>=ROUND($C$4*1440,0))*'取込_厚生部'!$F$8:$CW$1007)) -> 784 | F43: =IF(F$39="","",SUMPRODUCT(('取込_厚生部'!$A$8:$A$1007=$B43)*('取込_厚生部'!$B$8:$B$1007=F$39)*('取込_厚生部'!$F$6:$CW$6>=ROUND($C$4*1440,0))*'取込_厚生部'!$F$8:$CW$1007)) -> 828 | G43: =IF(G$39="","",SUMPRODUCT(('取込_厚生部'!$A$8:$A$1007=$B43)*('取込_厚生部'!$B$8:$B$1007=G$39)*('取込_厚生部'!$F$6:$CW$6>=ROUND($C$4*1440,0))*'取込_厚生部'!$F$8:$CW$1007)) -> 933 | H43: =IF(H$39="","",SUMPRODUCT(('取込_厚生部'!$A$8:$A$1007=$B43)*('取込_厚生部'!$B$8:$B$1007=H$39)*('取込_厚生部'!$F$6:$CW$6>=ROUND($C$4*1440,0))*'取込_厚生部'!$F$8:$CW$1007)) -> 673
B44: 安佐南区 | C44: =IF(C$39="","",SUMPRODUCT(('取込_厚生部'!$A$8:$A$1007=$B44)*('取込_厚生部'!$B$8:$B$1007=C$39)*('取込_厚生部'!$F$6:$CW$6>=ROUND($C$4*1440,0))*'取込_厚生部'!$F$8:$CW$1007)) -> 267 | D44: =IF(D$39="","",SUMPRODUCT(('取込_厚生部'!$A$8:$A$1007=$B44)*('取込_厚生部'!$B$8:$B$1007=D$39)*('取込_厚生部'!$F$6:$CW$6>=ROUND($C$4*1440,0))*'取込_厚生部'!$F$8:$CW$1007)) -> 239 | E44: =IF(E$39="","",SUMPRODUCT(('取込_厚生部'!$A$8:$A$1007=$B44)*('取込_厚生部'!$B$8:$B$1007=E$39)*('取込_厚生部'!$F$6:$CW$6>=ROUND($C$4*1440,0))*'取込_厚生部'!$F$8:$CW$1007)) -> 332 | F44: =IF(F$39="","",SUMPRODUCT(('取込_厚生部'!$A$8:$A$1007=$B44)*('取込_厚生部'!$B$8:$B$1007=F$39)*('取込_厚生部'!$F$6:$CW$6>=ROUND($C$4*1440,0))*'取込_厚生部'!$F$8:$CW$1007)) -> 445 | G44: =IF(G$39="","",SUMPRODUCT(('取込_厚生部'!$A$8:$A$1007=$B44)*('取込_厚生部'!$B$8:$B$1007=G$39)*('取込_厚生部'!$F$6:$CW$6>=ROUND($C$4*1440,0))*'取込_厚生部'!$F$8:$CW$1007)) -> 459 | H44: =IF(H$39="","",SUMPRODUCT(('取込_厚生部'!$A$8:$A$1007=$B44)*('取込_厚生部'!$B$8:$B$1007=H$39)*('取込_厚生部'!$F$6:$CW$6>=ROUND($C$4*1440,0))*'取込_厚生部'!$F$8:$CW$1007)) -> 348
B45: 安佐北区 | C45: =IF(C$39="","",SUMPRODUCT(('取込_厚生部'!$A$8:$A$1007=$B45)*('取込_厚生部'!$B$8:$B$1007=C$39)*('取込_厚生部'!$F$6:$CW$6>=ROUND($C$4*1440,0))*'取込_厚生部'!$F$8:$CW$1007)) -> 150 | D45: =IF(D$39="","",SUMPRODUCT(('取込_厚生部'!$A$8:$A$1007=$B45)*('取込_厚生部'!$B$8:$B$1007=D$39)*('取込_厚生部'!$F$6:$CW$6>=ROUND($C$4*1440,0))*'取込_厚生部'!$F$8:$CW$1007)) -> 149 | E45: =IF(E$39="","",SUMPRODUCT(('取込_厚生部'!$A$8:$A$1007=$B45)*('取込_厚生部'!$B$8:$B$1007=E$39)*('取込_厚生部'!$F$6:$CW$6>=ROUND($C$4*1440,0))*'取込_厚生部'!$F$8:$CW$1007)) -> 186 | F45: =IF(F$39="","",SUMPRODUCT(('取込_厚生部'!$A$8:$A$1007=$B45)*('取込_厚生部'!$B$8:$B$1007=F$39)*('取込_厚生部'!$F$6:$CW$6>=ROUND($C$4*1440,0))*'取込_厚生部'!$F$8:$CW$1007)) -> 216 | G45: =IF(G$39="","",SUMPRODUCT(('取込_厚生部'!$A$8:$A$1007=$B45)*('取込_厚生部'!$B$8:$B$1007=G$39)*('取込_厚生部'!$F$6:$CW$6>=ROUND($C$4*1440,0))*'取込_厚生部'!$F$8:$CW$1007)) -> 323 | H45: =IF(H$39="","",SUMPRODUCT(('取込_厚生部'!$A$8:$A$1007=$B45)*('取込_厚生部'!$B$8:$B$1007=H$39)*('取込_厚生部'!$F$6:$CW$6>=ROUND($C$4*1440,0))*'取込_厚生部'!$F$8:$CW$1007)) -> 171
B46: 佐伯区 | C46: =IF(C$39="","",SUMPRODUCT(('取込_厚生部'!$A$8:$A$1007=$B46)*('取込_厚生部'!$B$8:$B$1007=C$39)*('取込_厚生部'!$F$6:$CW$6>=ROUND($C$4*1440,0))*'取込_厚生部'!$F$8:$CW$1007)) -> 312 | D46: =IF(D$39="","",SUMPRODUCT(('取込_厚生部'!$A$8:$A$1007=$B46)*('取込_厚生部'!$B$8:$B$1007=D$39)*('取込_厚生部'!$F$6:$CW$6>=ROUND($C$4*1440,0))*'取込_厚生部'!$F$8:$CW$1007)) -> 271 | E46: =IF(E$39="","",SUMPRODUCT(('取込_厚生部'!$A$8:$A$1007=$B46)*('取込_厚生部'!$B$8:$B$1007=E$39)*('取込_厚生部'!$F$6:$CW$6>=ROUND($C$4*1440,0))*'取込_厚生部'!$F$8:$CW$1007)) -> 354 | F46: =IF(F$39="","",SUMPRODUCT(('取込_厚生部'!$A$8:$A$1007=$B46)*('取込_厚生部'!$B$8:$B$1007=F$39)*('取込_厚生部'!$F$6:$CW$6>=ROUND($C$4*1440,0))*'取込_厚生部'!$F$8:$CW$1007)) -> 379 | G46: =IF(G$39="","",SUMPRODUCT(('取込_厚生部'!$A$8:$A$1007=$B46)*('取込_厚生部'!$B$8:$B$1007=G$39)*('取込_厚生部'!$F$6:$CW$6>=ROUND($C$4*1440,0))*'取込_厚生部'!$F$8:$CW$1007)) -> 488 | H46: =IF(H$39="","",SUMPRODUCT(('取込_厚生部'!$A$8:$A$1007=$B46)*('取込_厚生部'!$B$8:$B$1007=H$39)*('取込_厚生部'!$F$6:$CW$6>=ROUND($C$4*1440,0))*'取込_厚生部'!$F$8:$CW$1007)) -> 323
B47: 計 | C47: =SUM(C40:C46) -> 2304 | D47: =SUM(D40:D46) -> 2149 | E47: =SUM(E40:E46) -> 2748 | F47: =SUM(F40:F46) -> 3059 | G47: =SUM(G40:G46) -> 3348 | H47: =SUM(H40:H46) -> 2282
B49: 業務別（件数の多い15件、取り込んだ全期間・全区）
B50: 区分名 | C50: 発券数 | D50: 基準以降の発券数 | E50: 平均処理時間（分）
B51: =INDEX('取込_業務別'!$A$8:$A$507,1)&"" -> 介護保険 | C51: =INDEX('取込_業務別'!$B$8:$B$507,1) -> 34917 | D51: =SUMPRODUCT(('取込_業務別'!$E$6:$CV$6>=ROUND($C$4*1440,0))*INDEX('取込_業務別'!$E$8:$CV$507,1,0)) -> 3289 | E51: =IFERROR(INDEX('取込_業務別'!$C$8:$C$507,1)/INDEX('取込_業務別'!$D$8:$D$507,1),0) -> 14.908869
B52: =INDEX('取込_業務別'!$A$8:$A$507,2)&"" -> 障害福祉 | C52: =INDEX('取込_業務別'!$B$8:$B$507,2) -> 10692 | D52: =SUMPRODUCT(('取込_業務別'!$E$6:$CV$6>=ROUND($C$4*1440,0))*INDEX('取込_業務別'!$E$8:$CV$507,2,0)) -> 512 | E52: =IFERROR(INDEX('取込_業務別'!$C$8:$C$507,2)/INDEX('取込_業務別'!$D$8:$D$507,2),0) -> 14.517115
B53: =INDEX('取込_業務別'!$A$8:$A$507,3)&"" -> その他 | C53: =INDEX('取込_業務別'!$B$8:$B$507,3) -> 10675 | D53: =SUMPRODUCT(('取込_業務別'!$E$6:$CV$6>=ROUND($C$4*1440,0))*INDEX('取込_業務別'!$E$8:$CV$507,3,0)) -> 516 | E53: =IFERROR(INDEX('取込_業務別'!$C$8:$C$507,3)/INDEX('取込_業務別'!$D$8:$D$507,3),0) -> 13.359766
B54: =INDEX('取込_業務別'!$A$8:$A$507,4)&"" -> 後期高齢者医療・高齢福祉 | C54: =INDEX('取込_業務別'!$B$8:$B$507,4) -> 10188 | D54: =SUMPRODUCT(('取込_業務別'!$E$6:$CV$6>=ROUND($C$4*1440,0))*INDEX('取込_業務別'!$E$8:$CV$507,4,0)) -> 591 | E54: =IFERROR(INDEX('取込_業務別'!$C$8:$C$507,4)/INDEX('取込_業務別'!$D$8:$D$507,4),0) -> 17.35094
B55: =INDEX('取込_業務別'!$A$8:$A$507,5)&"" -> 身体・療育手帳 | C55: =INDEX('取込_業務別'!$B$8:$B$507,5) -> 9895 | D55: =SUMPRODUCT(('取込_業務別'!$E$6:$CV$6>=ROUND($C$4*1440,0))*INDEX('取込_業務別'!$E$8:$CV$507,5,0)) -> 1178 | E55: =IFERROR(INDEX('取込_業務別'!$C$8:$C$507,5)/INDEX('取込_業務別'!$D$8:$D$507,5),0) -> 17.180772
B56: =INDEX('取込_業務別'!$A$8:$A$507,6)&"" -> 児童手当・こども医療 | C56: =INDEX('取込_業務別'!$B$8:$B$507,6) -> 8788 | D56: =SUMPRODUCT(('取込_業務別'!$E$6:$CV$6>=ROUND($C$4*1440,0))*INDEX('取込_業務別'!$E$8:$CV$507,6,0)) -> 831 | E56: =IFERROR(INDEX('取込_業務別'!$C$8:$C$507,6)/INDEX('取込_業務別'!$D$8:$D$507,6),0) -> 14.729418
B57: =INDEX('取込_業務別'!$A$8:$A$507,7)&"" -> 精神保健（手帳・医療費） | C57: =INDEX('取込_業務別'!$B$8:$B$507,7) -> 8406 | D57: =SUMPRODUCT(('取込_業務別'!$E$6:$CV$6>=ROUND($C$4*1440,0))*INDEX('取込_業務別'!$E$8:$CV$507,7,0)) -> 954 | E57: =IFERROR(INDEX('取込_業務別'!$C$8:$C$507,7)/INDEX('取込_業務別'!$D$8:$D$507,7),0) -> 17.470182
B58: =INDEX('取込_業務別'!$A$8:$A$507,8)&"" -> 障害福祉サービス | C58: =INDEX('取込_業務別'!$B$8:$B$507,8) -> 7421 | D58: =SUMPRODUCT(('取込_業務別'!$E$6:$CV$6>=ROUND($C$4*1440,0))*INDEX('取込_業務別'!$E$8:$CV$507,8,0)) -> 486 | E58: =IFERROR(INDEX('取込_業務別'!$C$8:$C$507,8)/INDEX('取込_業務別'!$D$8:$D$507,8),0) -> 13.344722
B59: =INDEX('取込_業務別'!$A$8:$A$507,9)&"" -> 保育園等 | C59: =INDEX('取込_業務別'!$B$8:$B$507,9) -> 7331 | D59: =SUMPRODUCT(('取込_業務別'!$E$6:$CV$6>=ROUND($C$4*1440,0))*INDEX('取込_業務別'!$E$8:$CV$507,9,0)) -> 537 | E59: =IFERROR(INDEX('取込_業務別'!$C$8:$C$507,9)/INDEX('取込_業務別'!$D$8:$D$507,9),0) -> 20.819665
B60: =INDEX('取込_業務別'!$A$8:$A$507,10)&"" -> 手帳（身体・療育） | C60: =INDEX('取込_業務別'!$B$8:$B$507,10) -> 7075 | D60: =SUMPRODUCT(('取込_業務別'!$E$6:$CV$6>=ROUND($C$4*1440,0))*INDEX('取込_業務別'!$E$8:$CV$507,10,0)) -> 817 | E60: =IFERROR(INDEX('取込_業務別'!$C$8:$C$507,10)/INDEX('取込_業務別'!$D$8:$D$507,10),0) -> 13.619545
B61: =INDEX('取込_業務別'!$A$8:$A$507,11)&"" -> 精神手帳／自立支援医療 | C61: =INDEX('取込_業務別'!$B$8:$B$507,11) -> 6578 | D61: =SUMPRODUCT(('取込_業務別'!$E$6:$CV$6>=ROUND($C$4*1440,0))*INDEX('取込_業務別'!$E$8:$CV$507,11,0)) -> 312 | E61: =IFERROR(INDEX('取込_業務別'!$C$8:$C$507,11)/INDEX('取込_業務別'!$D$8:$D$507,11),0) -> 16.925263
B62: =INDEX('取込_業務別'!$A$8:$A$507,12)&"" -> 保育園 | C62: =INDEX('取込_業務別'!$B$8:$B$507,12) -> 4761 | D62: =SUMPRODUCT(('取込_業務別'!$E$6:$CV$6>=ROUND($C$4*1440,0))*INDEX('取込_業務別'!$E$8:$CV$507,12,0)) -> 385 | E62: =IFERROR(INDEX('取込_業務別'!$C$8:$C$507,12)/INDEX('取込_業務別'!$D$8:$D$507,12),0) -> 24.959317
B63: =INDEX('取込_業務別'!$A$8:$A$507,13)&"" -> 身体障害者手帳・療育手帳 | C63: =INDEX('取込_業務別'!$B$8:$B$507,13) -> 4737 | D63: =SUMPRODUCT(('取込_業務別'!$E$6:$CV$6>=ROUND($C$4*1440,0))*INDEX('取込_業務別'!$E$8:$CV$507,13,0)) -> 215 | E63: =IFERROR(INDEX('取込_業務別'!$C$8:$C$507,13)/INDEX('取込_業務別'!$D$8:$D$507,13),0) -> 18.013205
B64: =INDEX('取込_業務別'!$A$8:$A$507,14)&"" -> 介護保険事業者の方 | C64: =INDEX('取込_業務別'!$B$8:$B$507,14) -> 4723 | D64: =SUMPRODUCT(('取込_業務別'!$E$6:$CV$6>=ROUND($C$4*1440,0))*INDEX('取込_業務別'!$E$8:$CV$507,14,0)) -> 286 | E64: =IFERROR(INDEX('取込_業務別'!$C$8:$C$507,14)/INDEX('取込_業務別'!$D$8:$D$507,14),0) -> 23.261711
B65: =INDEX('取込_業務別'!$A$8:$A$507,15)&"" -> 後期高齢者医療保険 | C65: =INDEX('取込_業務別'!$B$8:$B$507,15) -> 4699 | D65: =SUMPRODUCT(('取込_業務別'!$E$6:$CV$6>=ROUND($C$4*1440,0))*INDEX('取込_業務別'!$E$8:$CV$507,15,0)) -> 180 | E65: =IFERROR(INDEX('取込_業務別'!$C$8:$C$507,15)/INDEX('取込_業務別'!$D$8:$D$507,15),0) -> 19.562851
B67: 注：「全区」フォルダは各区ファイルのコピーのため取り込まない。同じ区・同じ日のファイルが複数あるときは最初の1つだけ使う。東区は8・9月のデータがない。安芸区のデータはない。
B68: 注：平均処理時間は呼出→処理済み（外れ値は除いていない）。月別の表は集計期間の先頭から最大6か月分を表示する（計算は集計期間の全体）。

Sheet 待ち・対応時間
B1: 待ち時間・対応時間・滞在時間
B3: 月 | C3: 全期間 | E3: 待ち＝発券→呼出、対応＝呼出→処理済み、滞在＝発券→処理済み（平均・分）
B5: 区ごとの比較
B6: 区 | C6: 来庁者数 | D6: 平均待ち(分) | E6: 15分以内率 | F6: 30分以内率 | G6: 平均対応(分) | H6: 平均滞在(分) | I6: 60分以上待った人
B7: 全区 | C7: =INDEX('データ'!D$759:D$875,MATCH($B7&"|"&$C$3,'データ'!$A$7:$A$123,0)) -> 762002 | D7: =IFERROR(INDEX('データ'!E$759:E$875,MATCH($B7&"|"&$C$3,'データ'!$A$7:$A$123,0))/INDEX('データ'!F$759:F$875,MATCH($B7&"|"&$C$3,'データ'!$A$7:$A$123,0))/60,0) -> 7.8387378 | E7: =IFERROR(SUM(INDEX('データ'!K$759:K$875,MATCH($B7&"|"&$C$3,'データ'!$A$7:$A$123,0)),INDEX('データ'!L$759:L$875,MATCH($B7&"|"&$C$3,'データ'!$A$7:$A$123,0)),INDEX('データ'!M$759:M$875,MATCH($B7&"|"&$C$3,'データ'!$A$7:$A$123,0)))/SUM(INDEX('データ'!K$759:K$875,MATCH($B7&"|"&$C$3,'データ'!$A$7:$A$123,0)),INDEX('データ'!L$759:L$875,MATCH($B7&"|"&$C$3,'データ'!$A$7:$A$123,0)),INDEX('データ'!M$759:M$875,MATCH($B7&"|"&$C$3,'データ'!$A$7:$A$123,0)),INDEX('データ'!N$759:N$875,MATCH($B7&"|"&$C$3,'データ'!$A$7:$A$123,0)),INDEX('データ'!O$759:O$875,MATCH($B7&"|"&$C$3,'データ'!$A$7:$A$123,0)),INDEX('データ'!P$759:P$875,MATCH($B7&"|"&$C$3,'データ'!$A$7:$A$123,0))),0) -> 0.84952364 | F7: =IFERROR(SUM(INDEX('データ'!K$759:K$875,MATCH($B7&"|"&$C$3,'データ'!$A$7:$A$123,0)),INDEX('データ'!L$759:L$875,MATCH($B7&"|"&$C$3,'データ'!$A$7:$A$123,0)),INDEX('データ'!M$759:M$875,MATCH($B7&"|"&$C$3,'データ'!$A$7:$A$123,0)),INDEX('データ'!N$759:N$875,MATCH($B7&"|"&$C$3,'データ'!$A$7:$A$123,0)))/SUM(INDEX('データ'!K$759:K$875,MATCH($B7&"|"&$C$3,'データ'!$A$7:$A$123,0)),INDEX('データ'!L$759:L$875,MATCH($B7&"|"&$C$3,'データ'!$A$7:$A$123,0)),INDEX('データ'!M$759:M$875,MATCH($B7&"|"&$C$3,'データ'!$A$7:$A$123,0)),INDEX('データ'!N$759:N$875,MATCH($B7&"|"&$C$3,'データ'!$A$7:$A$123,0)),INDEX('データ'!O$759:O$875,MATCH($B7&"|"&$C$3,'データ'!$A$7:$A$123,0)),INDEX('データ'!P$759:P$875,MATCH($B7&"|"&$C$3,'データ'!$A$7:$A$123,0))),0) -> 0.94102391 | G7: =IFERROR(INDEX('データ'!G$759:G$875,MATCH($B7&"|"&$C$3,'データ'!$A$7:$A$123,0))/INDEX('データ'!H$759:H$875,MATCH($B7&"|"&$C$3,'データ'!$A$7:$A$123,0))/60,0) -> 7.6375636 | H7: =IFERROR(INDEX('データ'!I$759:I$875,MATCH($B7&"|"&$C$3,'データ'!$A$7:$A$123,0))/INDEX('データ'!J$759:J$875,MATCH($B7&"|"&$C$3,'データ'!$A$7:$A$123,0))/60,0) -> 15.309631 | I7: =INDEX('データ'!P$759:P$875,MATCH($B7&"|"&$C$3,'データ'!$A$7:$A$123,0)) -> 12040
B8: 中区 | C8: =INDEX('データ'!D$759:D$875,MATCH($B8&"|"&$C$3,'データ'!$A$7:$A$123,0)) -> 143974 | D8: =IFERROR(INDEX('データ'!E$759:E$875,MATCH($B8&"|"&$C$3,'データ'!$A$7:$A$123,0))/INDEX('データ'!F$759:F$875,MATCH($B8&"|"&$C$3,'データ'!$A$7:$A$123,0))/60,0) -> 4.5271817 | E8: =IFERROR(SUM(INDEX('データ'!K$759:K$875,MATCH($B8&"|"&$C$3,'データ'!$A$7:$A$123,0)),INDEX('データ'!L$759:L$875,MATCH($B8&"|"&$C$3,'データ'!$A$7:$A$123,0)),INDEX('データ'!M$759:M$875,MATCH($B8&"|"&$C$3,'データ'!$A$7:$A$123,0)))/SUM(INDEX('データ'!K$759:K$875,MATCH($B8&"|"&$C$3,'データ'!$A$7:$A$123,0)),INDEX('データ'!L$759:L$875,MATCH($B8&"|"&$C$3,'データ'!$A$7:$A$123,0)),INDEX('データ'!M$759:M$875,MATCH($B8&"|"&$C$3,'データ'!$A$7:$A$123,0)),INDEX('データ'!N$759:N$875,MATCH($B8&"|"&$C$3,'データ'!$A$7:$A$123,0)),INDEX('データ'!O$759:O$875,MATCH($B8&"|"&$C$3,'データ'!$A$7:$A$123,0)),INDEX('データ'!P$759:P$875,MATCH($B8&"|"&$C$3,'データ'!$A$7:$A$123,0))),0) -> 0.92569726 | F8: =IFERROR(SUM(INDEX('データ'!K$759:K$875,MATCH($B8&"|"&$C$3,'データ'!$A$7:$A$123,0)),INDEX('データ'!L$759:L$875,MATCH($B8&"|"&$C$3,'データ'!$A$7:$A$123,0)),INDEX('データ'!M$759:M$875,MATCH($B8&"|"&$C$3,'データ'!$A$7:$A$123,0)),INDEX('データ'!N$759:N$875,MATCH($B8&"|"&$C$3,'データ'!$A$7:$A$123,0)))/SUM(INDEX('データ'!K$759:K$875,MATCH($B8&"|"&$C$3,'データ'!$A$7:$A$123,0)),INDEX('データ'!L$759:L$875,MATCH($B8&"|"&$C$3,'データ'!$A$7:$A$123,0)),INDEX('データ'!M$759:M$875,MATCH($B8&"|"&$C$3,'データ'!$A$7:$A$123,0)),INDEX('データ'!N$759:N$875,MATCH($B8&"|"&$C$3,'データ'!$A$7:$A$123,0)),INDEX('データ'!O$759:O$875,MATCH($B8&"|"&$C$3,'データ'!$A$7:$A$123,0)),INDEX('データ'!P$759:P$875,MATCH($B8&"|"&$C$3,'データ'!$A$7:$A$123,0))),0) -> 0.98299564 | G8: =IFERROR(INDEX('データ'!G$759:G$875,MATCH($B8&"|"&$C$3,'データ'!$A$7:$A$123,0))/INDEX('データ'!H$759:H$875,MATCH($B8&"|"&$C$3,'データ'!$A$7:$A$123,0))/60,0) -> 7.869897 | H8: =IFERROR(INDEX('データ'!I$759:I$875,MATCH($B8&"|"&$C$3,'データ'!$A$7:$A$123,0))/INDEX('データ'!J$759:J$875,MATCH($B8&"|"&$C$3,'データ'!$A$7:$A$123,0))/60,0) -> 12.372074 | I8: =INDEX('データ'!P$759:P$875,MATCH($B8&"|"&$C$3,'データ'!$A$7:$A$123,0)) -> 455
B9: 東区 | C9: =INDEX('データ'!D$759:D$875,MATCH($B9&"|"&$C$3,'データ'!$A$7:$A$123,0)) -> 81818 | D9: =IFERROR(INDEX('データ'!E$759:E$875,MATCH($B9&"|"&$C$3,'データ'!$A$7:$A$123,0))/INDEX('データ'!F$759:F$875,MATCH($B9&"|"&$C$3,'データ'!$A$7:$A$123,0))/60,0) -> 4.3975001 | E9: =IFERROR(SUM(INDEX('データ'!K$759:K$875,MATCH($B9&"|"&$C$3,'データ'!$A$7:$A$123,0)),INDEX('データ'!L$759:L$875,MATCH($B9&"|"&$C$3,'データ'!$A$7:$A$123,0)),INDEX('データ'!M$759:M$875,MATCH($B9&"|"&$C$3,'データ'!$A$7:$A$123,0)))/SUM(INDEX('データ'!K$759:K$875,MATCH($B9&"|"&$C$3,'データ'!$A$7:$A$123,0)),INDEX('データ'!L$759:L$875,MATCH($B9&"|"&$C$3,'データ'!$A$7:$A$123,0)),INDEX('データ'!M$759:M$875,MATCH($B9&"|"&$C$3,'データ'!$A$7:$A$123,0)),INDEX('データ'!N$759:N$875,MATCH($B9&"|"&$C$3,'データ'!$A$7:$A$123,0)),INDEX('データ'!O$759:O$875,MATCH($B9&"|"&$C$3,'データ'!$A$7:$A$123,0)),INDEX('データ'!P$759:P$875,MATCH($B9&"|"&$C$3,'データ'!$A$7:$A$123,0))),0) -> 0.94102797 | F9: =IFERROR(SUM(INDEX('データ'!K$759:K$875,MATCH($B9&"|"&$C$3,'データ'!$A$7:$A$123,0)),INDEX('データ'!L$759:L$875,MATCH($B9&"|"&$C$3,'データ'!$A$7:$A$123,0)),INDEX('データ'!M$759:M$875,MATCH($B9&"|"&$C$3,'データ'!$A$7:$A$123,0)),INDEX('データ'!N$759:N$875,MATCH($B9&"|"&$C$3,'データ'!$A$7:$A$123,0)))/SUM(INDEX('データ'!K$759:K$875,MATCH($B9&"|"&$C$3,'データ'!$A$7:$A$123,0)),INDEX('データ'!L$759:L$875,MATCH($B9&"|"&$C$3,'データ'!$A$7:$A$123,0)),INDEX('データ'!M$759:M$875,MATCH($B9&"|"&$C$3,'データ'!$A$7:$A$123,0)),INDEX('データ'!N$759:N$875,MATCH($B9&"|"&$C$3,'データ'!$A$7:$A$123,0)),INDEX('データ'!O$759:O$875,MATCH($B9&"|"&$C$3,'データ'!$A$7:$A$123,0)),INDEX('データ'!P$759:P$875,MATCH($B9&"|"&$C$3,'データ'!$A$7:$A$123,0))),0) -> 0.98189907 | G9: =IFERROR(INDEX('データ'!G$759:G$875,MATCH($B9&"|"&$C$3,'データ'!$A$7:$A$123,0))/INDEX('データ'!H$759:H$875,MATCH($B9&"|"&$C$3,'データ'!$A$7:$A$123,0))/60,0) -> 8.644546 | H9: =IFERROR(INDEX('データ'!I$759:I$875,MATCH($B9&"|"&$C$3,'データ'!$A$7:$A$123,0))/INDEX('データ'!J$759:J$875,MATCH($B9&"|"&$C$3,'データ'!$A$7:$A$123,0))/60,0) -> 13.029044 | I9: =INDEX('データ'!P$759:P$875,MATCH($B9&"|"&$C$3,'データ'!$A$7:$A$123,0)) -> 465
B10: 南区 | C10: =INDEX('データ'!D$759:D$875,MATCH($B10&"|"&$C$3,'データ'!$A$7:$A$123,0)) -> 115887 | D10: =IFERROR(INDEX('データ'!E$759:E$875,MATCH($B10&"|"&$C$3,'データ'!$A$7:$A$123,0))/INDEX('データ'!F$759:F$875,MATCH($B10&"|"&$C$3,'データ'!$A$7:$A$123,0))/60,0) -> 14.264511 | E10: =IFERROR(SUM(INDEX('データ'!K$759:K$875,MATCH($B10&"|"&$C$3,'データ'!$A$7:$A$123,0)),INDEX('データ'!L$759:L$875,MATCH($B10&"|"&$C$3,'データ'!$A$7:$A$123,0)),INDEX('データ'!M$759:M$875,MATCH($B10&"|"&$C$3,'データ'!$A$7:$A$123,0)))/SUM(INDEX('データ'!K$759:K$875,MATCH($B10&"|"&$C$3,'データ'!$A$7:$A$123,0)),INDEX('データ'!L$759:L$875,MATCH($B10&"|"&$C$3,'データ'!$A$7:$A$123,0)),INDEX('データ'!M$759:M$875,MATCH($B10&"|"&$C$3,'データ'!$A$7:$A$123,0)),INDEX('データ'!N$759:N$875,MATCH($B10&"|"&$C$3,'データ'!$A$7:$A$123,0)),INDEX('データ'!O$759:O$875,MATCH($B10&"|"&$C$3,'データ'!$A$7:$A$123,0)),INDEX('データ'!P$759:P$875,MATCH($B10&"|"&$C$3,'データ'!$A$7:$A$123,0))),0) -> 0.71184381 | F10: =IFERROR(SUM(INDEX('データ'!K$759:K$875,MATCH($B10&"|"&$C$3,'データ'!$A$7:$A$123,0)),INDEX('データ'!L$759:L$875,MATCH($B10&"|"&$C$3,'データ'!$A$7:$A$123,0)),INDEX('データ'!M$759:M$875,MATCH($B10&"|"&$C$3,'データ'!$A$7:$A$123,0)),INDEX('データ'!N$759:N$875,MATCH($B10&"|"&$C$3,'データ'!$A$7:$A$123,0)))/SUM(INDEX('データ'!K$759:K$875,MATCH($B10&"|"&$C$3,'データ'!$A$7:$A$123,0)),INDEX('データ'!L$759:L$875,MATCH($B10&"|"&$C$3,'データ'!$A$7:$A$123,0)),INDEX('データ'!M$759:M$875,MATCH($B10&"|"&$C$3,'データ'!$A$7:$A$123,0)),INDEX('データ'!N$759:N$875,MATCH($B10&"|"&$C$3,'データ'!$A$7:$A$123,0)),INDEX('データ'!O$759:O$875,MATCH($B10&"|"&$C$3,'データ'!$A$7:$A$123,0)),INDEX('データ'!P$759:P$875,MATCH($B10&"|"&$C$3,'データ'!$A$7:$A$123,0))),0) -> 0.84992751 | G10: =IFERROR(INDEX('データ'!G$759:G$875,MATCH($B10&"|"&$C$3,'データ'!$A$7:$A$123,0))/INDEX('データ'!H$759:H$875,MATCH($B10&"|"&$C$3,'データ'!$A$7:$A$123,0))/60,0) -> 6.3850113 | H10: =IFERROR(INDEX('データ'!I$759:I$875,MATCH($B10&"|"&$C$3,'データ'!$A$7:$A$123,0))/INDEX('データ'!J$759:J$875,MATCH($B10&"|"&$C$3,'データ'!$A$7:$A$123,0))/60,0) -> 20.469119 | I10: =INDEX('データ'!P$759:P$875,MATCH($B10&"|"&$C$3,'データ'!$A$7:$A$123,0)) -> 5875
B11: 西区 | C11: =INDEX('データ'!D$759:D$875,MATCH($B11&"|"&$C$3,'データ'!$A$7:$A$123,0)) -> 141243 | D11: =IFERROR(INDEX('データ'!E$759:E$875,MATCH($B11&"|"&$C$3,'データ'!$A$7:$A$123,0))/INDEX('データ'!F$759:F$875,MATCH($B11&"|"&$C$3,'データ'!$A$7:$A$123,0))/60,0) -> 8.7043545 | E11: =IFERROR(SUM(INDEX('データ'!K$759:K$875,MATCH($B11&"|"&$C$3,'データ'!$A$7:$A$123,0)),INDEX('データ'!L$759:L$875,MATCH($B11&"|"&$C$3,'データ'!$A$7:$A$123,0)),INDEX('データ'!M$759:M$875,MATCH($B11&"|"&$C$3,'データ'!$A$7:$A$123,0)))/SUM(INDEX('データ'!K$759:K$875,MATCH($B11&"|"&$C$3,'データ'!$A$7:$A$123,0)),INDEX('データ'!L$759:L$875,MATCH($B11&"|"&$C$3,'データ'!$A$7:$A$123,0)),INDEX('データ'!M$759:M$875,MATCH($B11&"|"&$C$3,'データ'!$A$7:$A$123,0)),INDEX('データ'!N$759:N$875,MATCH($B11&"|"&$C$3,'データ'!$A$7:$A$123,0)),INDEX('データ'!O$759:O$875,MATCH($B11&"|"&$C$3,'データ'!$A$7:$A$123,0)),INDEX('データ'!P$759:P$875,MATCH($B11&"|"&$C$3,'データ'!$A$7:$A$123,0))),0) -> 0.81311601 | F11: =IFERROR(SUM(INDEX('データ'!K$759:K$875,MATCH($B11&"|"&$C$3,'データ'!$A$7:$A$123,0)),INDEX('データ'!L$759:L$875,MATCH($B11&"|"&$C$3,'データ'!$A$7:$A$123,0)),INDEX('データ'!M$759:M$875,MATCH($B11&"|"&$C$3,'データ'!$A$7:$A$123,0)),INDEX('データ'!N$759:N$875,MATCH($B11&"|"&$C$3,'データ'!$A$7:$A$123,0)))/SUM(INDEX('データ'!K$759:K$875,MATCH($B11&"|"&$C$3,'データ'!$A$7:$A$123,0)),INDEX('データ'!L$759:L$875,MATCH($B11&"|"&$C$3,'データ'!$A$7:$A$123,0)),INDEX('データ'!M$759:M$875,MATCH($B11&"|"&$C$3,'データ'!$A$7:$A$123,0)),INDEX('データ'!N$759:N$875,MATCH($B11&"|"&$C$3,'データ'!$A$7:$A$123,0)),INDEX('データ'!O$759:O$875,MATCH($B11&"|"&$C$3,'データ'!$A$7:$A$123,0)),INDEX('データ'!P$759:P$875,MATCH($B11&"|"&$C$3,'データ'!$A$7:$A$123,0))),0) -> 0.93121971 | G11: =IFERROR(INDEX('データ'!G$759:G$875,MATCH($B11&"|"&$C$3,'データ'!$A$7:$A$123,0))/INDEX('データ'!H$759:H$875,MATCH($B11&"|"&$C$3,'データ'!$A$7:$A$123,0))/60,0) -> 6.1987521 | H11: =IFERROR(INDEX('データ'!I$759:I$875,MATCH($B11&"|"&$C$3,'データ'!$A$7:$A$123,0))/INDEX('データ'!J$759:J$875,MATCH($B11&"|"&$C$3,'データ'!$A$7:$A$123,0))/60,0) -> 14.873418 | I11: =INDEX('データ'!P$759:P$875,MATCH($B11&"|"&$C$3,'データ'!$A$7:$A$123,0)) -> 1566
B12: 安佐南区 | C12: =INDEX('データ'!D$759:D$875,MATCH($B12&"|"&$C$3,'データ'!$A$7:$A$123,0)) -> 88181 | D12: =IFERROR(INDEX('データ'!E$759:E$875,MATCH($B12&"|"&$C$3,'データ'!$A$7:$A$123,0))/INDEX('データ'!F$759:F$875,MATCH($B12&"|"&$C$3,'データ'!$A$7:$A$123,0))/60,0) -> 13.970985 | E12: =IFERROR(SUM(INDEX('データ'!K$759:K$875,MATCH($B12&"|"&$C$3,'データ'!$A$7:$A$123,0)),INDEX('データ'!L$759:L$875,MATCH($B12&"|"&$C$3,'データ'!$A$7:$A$123,0)),INDEX('データ'!M$759:M$875,MATCH($B12&"|"&$C$3,'データ'!$A$7:$A$123,0)))/SUM(INDEX('データ'!K$759:K$875,MATCH($B12&"|"&$C$3,'データ'!$A$7:$A$123,0)),INDEX('データ'!L$759:L$875,MATCH($B12&"|"&$C$3,'データ'!$A$7:$A$123,0)),INDEX('データ'!M$759:M$875,MATCH($B12&"|"&$C$3,'データ'!$A$7:$A$123,0)),INDEX('データ'!N$759:N$875,MATCH($B12&"|"&$C$3,'データ'!$A$7:$A$123,0)),INDEX('データ'!O$759:O$875,MATCH($B12&"|"&$C$3,'データ'!$A$7:$A$123,0)),INDEX('データ'!P$759:P$875,MATCH($B12&"|"&$C$3,'データ'!$A$7:$A$123,0))),0) -> 0.69754357 | F12: =IFERROR(SUM(INDEX('データ'!K$759:K$875,MATCH($B12&"|"&$C$3,'データ'!$A$7:$A$123,0)),INDEX('データ'!L$759:L$875,MATCH($B12&"|"&$C$3,'データ'!$A$7:$A$123,0)),INDEX('データ'!M$759:M$875,MATCH($B12&"|"&$C$3,'データ'!$A$7:$A$123,0)),INDEX('データ'!N$759:N$875,MATCH($B12&"|"&$C$3,'データ'!$A$7:$A$123,0)))/SUM(INDEX('データ'!K$759:K$875,MATCH($B12&"|"&$C$3,'データ'!$A$7:$A$123,0)),INDEX('データ'!L$759:L$875,MATCH($B12&"|"&$C$3,'データ'!$A$7:$A$123,0)),INDEX('データ'!M$759:M$875,MATCH($B12&"|"&$C$3,'データ'!$A$7:$A$123,0)),INDEX('データ'!N$759:N$875,MATCH($B12&"|"&$C$3,'データ'!$A$7:$A$123,0)),INDEX('データ'!O$759:O$875,MATCH($B12&"|"&$C$3,'データ'!$A$7:$A$123,0)),INDEX('データ'!P$759:P$875,MATCH($B12&"|"&$C$3,'データ'!$A$7:$A$123,0))),0) -> 0.86187732 | G12: =IFERROR(INDEX('データ'!G$759:G$875,MATCH($B12&"|"&$C$3,'データ'!$A$7:$A$123,0))/INDEX('データ'!H$759:H$875,MATCH($B12&"|"&$C$3,'データ'!$A$7:$A$123,0))/60,0) -> 7.2427846 | H12: =IFERROR(INDEX('データ'!I$759:I$875,MATCH($B12&"|"&$C$3,'データ'!$A$7:$A$123,0))/INDEX('データ'!J$759:J$875,MATCH($B12&"|"&$C$3,'データ'!$A$7:$A$123,0))/60,0) -> 21.02121 | I12: =INDEX('データ'!P$759:P$875,MATCH($B12&"|"&$C$3,'データ'!$A$7:$A$123,0)) -> 3352
B13: 安佐北区 | C13: =INDEX('データ'!D$759:D$875,MATCH($B13&"|"&$C$3,'データ'!$A$7:$A$123,0)) -> 48568 | D13: =IFERROR(INDEX('データ'!E$759:E$875,MATCH($B13&"|"&$C$3,'データ'!$A$7:$A$123,0))/INDEX('データ'!F$759:F$875,MATCH($B13&"|"&$C$3,'データ'!$A$7:$A$123,0))/60,0) -> 3.4987133 | E13: =IFERROR(SUM(INDEX('データ'!K$759:K$875,MATCH($B13&"|"&$C$3,'データ'!$A$7:$A$123,0)),INDEX('データ'!L$759:L$875,MATCH($B13&"|"&$C$3,'データ'!$A$7:$A$123,0)),INDEX('データ'!M$759:M$875,MATCH($B13&"|"&$C$3,'データ'!$A$7:$A$123,0)))/SUM(INDEX('データ'!K$759:K$875,MATCH($B13&"|"&$C$3,'データ'!$A$7:$A$123,0)),INDEX('データ'!L$759:L$875,MATCH($B13&"|"&$C$3,'データ'!$A$7:$A$123,0)),INDEX('データ'!M$759:M$875,MATCH($B13&"|"&$C$3,'データ'!$A$7:$A$123,0)),INDEX('データ'!N$759:N$875,MATCH($B13&"|"&$C$3,'データ'!$A$7:$A$123,0)),INDEX('データ'!O$759:O$875,MATCH($B13&"|"&$C$3,'データ'!$A$7:$A$123,0)),INDEX('データ'!P$759:P$875,MATCH($B13&"|"&$C$3,'データ'!$A$7:$A$123,0))),0) -> 0.9677506 | F13: =IFERROR(SUM(INDEX('データ'!K$759:K$875,MATCH($B13&"|"&$C$3,'データ'!$A$7:$A$123,0)),INDEX('データ'!L$759:L$875,MATCH($B13&"|"&$C$3,'データ'!$A$7:$A$123,0)),INDEX('データ'!M$759:M$875,MATCH($B13&"|"&$C$3,'データ'!$A$7:$A$123,0)),INDEX('データ'!N$759:N$875,MATCH($B13&"|"&$C$3,'データ'!$A$7:$A$123,0)))/SUM(INDEX('データ'!K$759:K$875,MATCH($B13&"|"&$C$3,'データ'!$A$7:$A$123,0)),INDEX('データ'!L$759:L$875,MATCH($B13&"|"&$C$3,'データ'!$A$7:$A$123,0)),INDEX('データ'!M$759:M$875,MATCH($B13&"|"&$C$3,'データ'!$A$7:$A$123,0)),INDEX('データ'!N$759:N$875,MATCH($B13&"|"&$C$3,'データ'!$A$7:$A$123,0)),INDEX('データ'!O$759:O$875,MATCH($B13&"|"&$C$3,'データ'!$A$7:$A$123,0)),INDEX('データ'!P$759:P$875,MATCH($B13&"|"&$C$3,'データ'!$A$7:$A$123,0))),0) -> 0.99750021 | G13: =IFERROR(INDEX('データ'!G$759:G$875,MATCH($B13&"|"&$C$3,'データ'!$A$7:$A$123,0))/INDEX('データ'!H$759:H$875,MATCH($B13&"|"&$C$3,'データ'!$A$7:$A$123,0))/60,0) -> 8.3550143 | H13: =IFERROR(INDEX('データ'!I$759:I$875,MATCH($B13&"|"&$C$3,'データ'!$A$7:$A$123,0))/INDEX('データ'!J$759:J$875,MATCH($B13&"|"&$C$3,'データ'!$A$7:$A$123,0))/60,0) -> 11.859127 | I13: =INDEX('データ'!P$759:P$875,MATCH($B13&"|"&$C$3,'データ'!$A$7:$A$123,0)) -> 19
B14: 安芸区 | C14: =INDEX('データ'!D$759:D$875,MATCH($B14&"|"&$C$3,'データ'!$A$7:$A$123,0)) -> 37567 | D14: =IFERROR(INDEX('データ'!E$759:E$875,MATCH($B14&"|"&$C$3,'データ'!$A$7:$A$123,0))/INDEX('データ'!F$759:F$875,MATCH($B14&"|"&$C$3,'データ'!$A$7:$A$123,0))/60,0) -> 2.3776665 | E14: =IFERROR(SUM(INDEX('データ'!K$759:K$875,MATCH($B14&"|"&$C$3,'データ'!$A$7:$A$123,0)),INDEX('データ'!L$759:L$875,MATCH($B14&"|"&$C$3,'データ'!$A$7:$A$123,0)),INDEX('データ'!M$759:M$875,MATCH($B14&"|"&$C$3,'データ'!$A$7:$A$123,0)))/SUM(INDEX('データ'!K$759:K$875,MATCH($B14&"|"&$C$3,'データ'!$A$7:$A$123,0)),INDEX('データ'!L$759:L$875,MATCH($B14&"|"&$C$3,'データ'!$A$7:$A$123,0)),INDEX('データ'!M$759:M$875,MATCH($B14&"|"&$C$3,'データ'!$A$7:$A$123,0)),INDEX('データ'!N$759:N$875,MATCH($B14&"|"&$C$3,'データ'!$A$7:$A$123,0)),INDEX('データ'!O$759:O$875,MATCH($B14&"|"&$C$3,'データ'!$A$7:$A$123,0)),INDEX('データ'!P$759:P$875,MATCH($B14&"|"&$C$3,'データ'!$A$7:$A$123,0))),0) -> 0.97299393 | F14: =IFERROR(SUM(INDEX('データ'!K$759:K$875,MATCH($B14&"|"&$C$3,'データ'!$A$7:$A$123,0)),INDEX('データ'!L$759:L$875,MATCH($B14&"|"&$C$3,'データ'!$A$7:$A$123,0)),INDEX('データ'!M$759:M$875,MATCH($B14&"|"&$C$3,'データ'!$A$7:$A$123,0)),INDEX('データ'!N$759:N$875,MATCH($B14&"|"&$C$3,'データ'!$A$7:$A$123,0)))/SUM(INDEX('データ'!K$759:K$875,MATCH($B14&"|"&$C$3,'データ'!$A$7:$A$123,0)),INDEX('データ'!L$759:L$875,MATCH($B14&"|"&$C$3,'データ'!$A$7:$A$123,0)),INDEX('データ'!M$759:M$875,MATCH($B14&"|"&$C$3,'データ'!$A$7:$A$123,0)),INDEX('データ'!N$759:N$875,MATCH($B14&"|"&$C$3,'データ'!$A$7:$A$123,0)),INDEX('データ'!O$759:O$875,MATCH($B14&"|"&$C$3,'データ'!$A$7:$A$123,0)),INDEX('データ'!P$759:P$875,MATCH($B14&"|"&$C$3,'データ'!$A$7:$A$123,0))),0) -> 0.99441162 | G14: =IFERROR(INDEX('データ'!G$759:G$875,MATCH($B14&"|"&$C$3,'データ'!$A$7:$A$123,0))/INDEX('データ'!H$759:H$875,MATCH($B14&"|"&$C$3,'データ'!$A$7:$A$123,0))/60,0) -> 14.894857 | H14: =IFERROR(INDEX('データ'!I$759:I$875,MATCH($B14&"|"&$C$3,'データ'!$A$7:$A$123,0))/INDEX('データ'!J$759:J$875,MATCH($B14&"|"&$C$3,'データ'!$A$7:$A$123,0))/60,0) -> 17.242039 | I14: =INDEX('データ'!P$759:P$875,MATCH($B14&"|"&$C$3,'データ'!$A$7:$A$123,0)) -> 60
B15: 佐伯区 | C15: =INDEX('データ'!D$759:D$875,MATCH($B15&"|"&$C$3,'データ'!$A$7:$A$123,0)) -> 104764 | D15: =IFERROR(INDEX('データ'!E$759:E$875,MATCH($B15&"|"&$C$3,'データ'!$A$7:$A$123,0))/INDEX('データ'!F$759:F$875,MATCH($B15&"|"&$C$3,'データ'!$A$7:$A$123,0))/60,0) -> 5.6626135 | E15: =IFERROR(SUM(INDEX('データ'!K$759:K$875,MATCH($B15&"|"&$C$3,'データ'!$A$7:$A$123,0)),INDEX('データ'!L$759:L$875,MATCH($B15&"|"&$C$3,'データ'!$A$7:$A$123,0)),INDEX('データ'!M$759:M$875,MATCH($B15&"|"&$C$3,'データ'!$A$7:$A$123,0)))/SUM(INDEX('データ'!K$759:K$875,MATCH($B15&"|"&$C$3,'データ'!$A$7:$A$123,0)),INDEX('データ'!L$759:L$875,MATCH($B15&"|"&$C$3,'データ'!$A$7:$A$123,0)),INDEX('データ'!M$759:M$875,MATCH($B15&"|"&$C$3,'データ'!$A$7:$A$123,0)),INDEX('データ'!N$759:N$875,MATCH($B15&"|"&$C$3,'データ'!$A$7:$A$123,0)),INDEX('データ'!O$759:O$875,MATCH($B15&"|"&$C$3,'データ'!$A$7:$A$123,0)),INDEX('データ'!P$759:P$875,MATCH($B15&"|"&$C$3,'データ'!$A$7:$A$123,0))),0) -> 0.9024073 | F15: =IFERROR(SUM(INDEX('データ'!K$759:K$875,MATCH($B15&"|"&$C$3,'データ'!$A$7:$A$123,0)),INDEX('データ'!L$759:L$875,MATCH($B15&"|"&$C$3,'データ'!$A$7:$A$123,0)),INDEX('データ'!M$759:M$875,MATCH($B15&"|"&$C$3,'データ'!$A$7:$A$123,0)),INDEX('データ'!N$759:N$875,MATCH($B15&"|"&$C$3,'データ'!$A$7:$A$123,0)))/SUM(INDEX('データ'!K$759:K$875,MATCH($B15&"|"&$C$3,'データ'!$A$7:$A$123,0)),INDEX('データ'!L$759:L$875,MATCH($B15&"|"&$C$3,'データ'!$A$7:$A$123,0)),INDEX('データ'!M$759:M$875,MATCH($B15&"|"&$C$3,'データ'!$A$7:$A$123,0)),INDEX('データ'!N$759:N$875,MATCH($B15&"|"&$C$3,'データ'!$A$7:$A$123,0)),INDEX('データ'!O$759:O$875,MATCH($B15&"|"&$C$3,'データ'!$A$7:$A$123,0)),INDEX('データ'!P$759:P$875,MATCH($B15&"|"&$C$3,'データ'!$A$7:$A$123,0))),0) -> 0.98597894 | G15: =IFERROR(INDEX('データ'!G$759:G$875,MATCH($B15&"|"&$C$3,'データ'!$A$7:$A$123,0))/INDEX('データ'!H$759:H$875,MATCH($B15&"|"&$C$3,'データ'!$A$7:$A$123,0))/60,0) -> 7.1985816 | H15: =IFERROR(INDEX('データ'!I$759:I$875,MATCH($B15&"|"&$C$3,'データ'!$A$7:$A$123,0))/INDEX('データ'!J$759:J$875,MATCH($B15&"|"&$C$3,'データ'!$A$7:$A$123,0))/60,0) -> 12.878106 | I15: =INDEX('データ'!P$759:P$875,MATCH($B15&"|"&$C$3,'データ'!$A$7:$A$123,0)) -> 248
B18: 待ち＋対応（区別・平均分） | L18: 待ち時間の分布（区別）
L20: 区 | M20: 5分未満 | N20: 5〜10分 | O20: 10〜15分 | P20: 15〜30分 | Q20: 30〜60分 | R20: 60分以上
L21: 全区 | M21: =IFERROR(INDEX('データ'!K$759:K$875,MATCH($L21&"|"&$C$3,'データ'!$A$7:$A$123,0))/SUM(INDEX('データ'!K$759:K$875,MATCH($L21&"|"&$C$3,'データ'!$A$7:$A$123,0)),INDEX('データ'!L$759:L$875,MATCH($L21&"|"&$C$3,'データ'!$A$7:$A$123,0)),INDEX('データ'!M$759:M$875,MATCH($L21&"|"&$C$3,'データ'!$A$7:$A$123,0)),INDEX('データ'!N$759:N$875,MATCH($L21&"|"&$C$3,'データ'!$A$7:$A$123,0)),INDEX('データ'!O$759:O$875,MATCH($L21&"|"&$C$3,'データ'!$A$7:$A$123,0)),INDEX('データ'!P$759:P$875,MATCH($L21&"|"&$C$3,'データ'!$A$7:$A$123,0))),0) -> 0.64020554 | N21: =IFERROR(INDEX('データ'!L$759:L$875,MATCH($L21&"|"&$C$3,'データ'!$A$7:$A$123,0))/SUM(INDEX('データ'!K$759:K$875,MATCH($L21&"|"&$C$3,'データ'!$A$7:$A$123,0)),INDEX('データ'!L$759:L$875,MATCH($L21&"|"&$C$3,'データ'!$A$7:$A$123,0)),INDEX('データ'!M$759:M$875,MATCH($L21&"|"&$C$3,'データ'!$A$7:$A$123,0)),INDEX('データ'!N$759:N$875,MATCH($L21&"|"&$C$3,'データ'!$A$7:$A$123,0)),INDEX('データ'!O$759:O$875,MATCH($L21&"|"&$C$3,'データ'!$A$7:$A$123,0)),INDEX('データ'!P$759:P$875,MATCH($L21&"|"&$C$3,'データ'!$A$7:$A$123,0))),0) -> 0.13594375 | O21: =IFERROR(INDEX('データ'!M$759:M$875,MATCH($L21&"|"&$C$3,'データ'!$A$7:$A$123,0))/SUM(INDEX('データ'!K$759:K$875,MATCH($L21&"|"&$C$3,'データ'!$A$7:$A$123,0)),INDEX('データ'!L$759:L$875,MATCH($L21&"|"&$C$3,'データ'!$A$7:$A$123,0)),INDEX('データ'!M$759:M$875,MATCH($L21&"|"&$C$3,'データ'!$A$7:$A$123,0)),INDEX('データ'!N$759:N$875,MATCH($L21&"|"&$C$3,'データ'!$A$7:$A$123,0)),INDEX('データ'!O$759:O$875,MATCH($L21&"|"&$C$3,'データ'!$A$7:$A$123,0)),INDEX('データ'!P$759:P$875,MATCH($L21&"|"&$C$3,'データ'!$A$7:$A$123,0))),0) -> 0.073374351 | P21: =IFERROR(INDEX('データ'!N$759:N$875,MATCH($L21&"|"&$C$3,'データ'!$A$7:$A$123,0))/SUM(INDEX('データ'!K$759:K$875,MATCH($L21&"|"&$C$3,'データ'!$A$7:$A$123,0)),INDEX('データ'!L$759:L$875,MATCH($L21&"|"&$C$3,'データ'!$A$7:$A$123,0)),INDEX('データ'!M$759:M$875,MATCH($L21&"|"&$C$3,'データ'!$A$7:$A$123,0)),INDEX('データ'!N$759:N$875,MATCH($L21&"|"&$C$3,'データ'!$A$7:$A$123,0)),INDEX('データ'!O$759:O$875,MATCH($L21&"|"&$C$3,'データ'!$A$7:$A$123,0)),INDEX('データ'!P$759:P$875,MATCH($L21&"|"&$C$3,'データ'!$A$7:$A$123,0))),0) -> 0.091500272 | Q21: =IFERROR(INDEX('データ'!O$759:O$875,MATCH($L21&"|"&$C$3,'データ'!$A$7:$A$123,0))/SUM(INDEX('データ'!K$759:K$875,MATCH($L21&"|"&$C$3,'データ'!$A$7:$A$123,0)),INDEX('データ'!L$759:L$875,MATCH($L21&"|"&$C$3,'データ'!$A$7:$A$123,0)),INDEX('データ'!M$759:M$875,MATCH($L21&"|"&$C$3,'データ'!$A$7:$A$123,0)),INDEX('データ'!N$759:N$875,MATCH($L21&"|"&$C$3,'データ'!$A$7:$A$123,0)),INDEX('データ'!O$759:O$875,MATCH($L21&"|"&$C$3,'データ'!$A$7:$A$123,0)),INDEX('データ'!P$759:P$875,MATCH($L21&"|"&$C$3,'データ'!$A$7:$A$123,0))),0) -> 0.043117063 | R21: =IFERROR(INDEX('データ'!P$759:P$875,MATCH($L21&"|"&$C$3,'データ'!$A$7:$A$123,0))/SUM(INDEX('データ'!K$759:K$875,MATCH($L21&"|"&$C$3,'データ'!$A$7:$A$123,0)),INDEX('データ'!L$759:L$875,MATCH($L21&"|"&$C$3,'データ'!$A$7:$A$123,0)),INDEX('データ'!M$759:M$875,MATCH($L21&"|"&$C$3,'データ'!$A$7:$A$123,0)),INDEX('データ'!N$759:N$875,MATCH($L21&"|"&$C$3,'データ'!$A$7:$A$123,0)),INDEX('データ'!O$759:O$875,MATCH($L21&"|"&$C$3,'データ'!$A$7:$A$123,0)),INDEX('データ'!P$759:P$875,MATCH($L21&"|"&$C$3,'データ'!$A$7:$A$123,0))),0) -> 0.015859029
L22: 中区 | M22: =IFERROR(INDEX('データ'!K$759:K$875,MATCH($L22&"|"&$C$3,'データ'!$A$7:$A$123,0))/SUM(INDEX('データ'!K$759:K$875,MATCH($L22&"|"&$C$3,'データ'!$A$7:$A$123,0)),INDEX('データ'!L$759:L$875,MATCH($L22&"|"&$C$3,'データ'!$A$7:$A$123,0)),INDEX('データ'!M$759:M$875,MATCH($L22&"|"&$C$3,'データ'!$A$7:$A$123,0)),INDEX('データ'!N$759:N$875,MATCH($L22&"|"&$C$3,'データ'!$A$7:$A$123,0)),INDEX('データ'!O$759:O$875,MATCH($L22&"|"&$C$3,'データ'!$A$7:$A$123,0)),INDEX('データ'!P$759:P$875,MATCH($L22&"|"&$C$3,'データ'!$A$7:$A$123,0))),0) -> 0.7455401 | N22: =IFERROR(INDEX('データ'!L$759:L$875,MATCH($L22&"|"&$C$3,'データ'!$A$7:$A$123,0))/SUM(INDEX('データ'!K$759:K$875,MATCH($L22&"|"&$C$3,'データ'!$A$7:$A$123,0)),INDEX('データ'!L$759:L$875,MATCH($L22&"|"&$C$3,'データ'!$A$7:$A$123,0)),INDEX('データ'!M$759:M$875,MATCH($L22&"|"&$C$3,'データ'!$A$7:$A$123,0)),INDEX('データ'!N$759:N$875,MATCH($L22&"|"&$C$3,'データ'!$A$7:$A$123,0)),INDEX('データ'!O$759:O$875,MATCH($L22&"|"&$C$3,'データ'!$A$7:$A$123,0)),INDEX('データ'!P$759:P$875,MATCH($L22&"|"&$C$3,'データ'!$A$7:$A$123,0))),0) -> 0.12257342 | O22: =IFERROR(INDEX('データ'!M$759:M$875,MATCH($L22&"|"&$C$3,'データ'!$A$7:$A$123,0))/SUM(INDEX('データ'!K$759:K$875,MATCH($L22&"|"&$C$3,'データ'!$A$7:$A$123,0)),INDEX('データ'!L$759:L$875,MATCH($L22&"|"&$C$3,'データ'!$A$7:$A$123,0)),INDEX('データ'!M$759:M$875,MATCH($L22&"|"&$C$3,'データ'!$A$7:$A$123,0)),INDEX('データ'!N$759:N$875,MATCH($L22&"|"&$C$3,'データ'!$A$7:$A$123,0)),INDEX('データ'!O$759:O$875,MATCH($L22&"|"&$C$3,'データ'!$A$7:$A$123,0)),INDEX('データ'!P$759:P$875,MATCH($L22&"|"&$C$3,'データ'!$A$7:$A$123,0))),0) -> 0.057583752 | P22: =IFERROR(INDEX('データ'!N$759:N$875,MATCH($L22&"|"&$C$3,'データ'!$A$7:$A$123,0))/SUM(INDEX('データ'!K$759:K$875,MATCH($L22&"|"&$C$3,'データ'!$A$7:$A$123,0)),INDEX('データ'!L$759:L$875,MATCH($L22&"|"&$C$3,'データ'!$A$7:$A$123,0)),INDEX('データ'!M$759:M$875,MATCH($L22&"|"&$C$3,'データ'!$A$7:$A$123,0)),INDEX('データ'!N$759:N$875,MATCH($L22&"|"&$C$3,'データ'!$A$7:$A$123,0)),INDEX('データ'!O$759:O$875,MATCH($L22&"|"&$C$3,'データ'!$A$7:$A$123,0)),INDEX('データ'!P$759:P$875,MATCH($L22&"|"&$C$3,'データ'!$A$7:$A$123,0))),0) -> 0.057298373 | Q22: =IFERROR(INDEX('データ'!O$759:O$875,MATCH($L22&"|"&$C$3,'データ'!$A$7:$A$123,0))/SUM(INDEX('データ'!K$759:K$875,MATCH($L22&"|"&$C$3,'データ'!$A$7:$A$123,0)),INDEX('データ'!L$759:L$875,MATCH($L22&"|"&$C$3,'データ'!$A$7:$A$123,0)),INDEX('データ'!M$759:M$875,MATCH($L22&"|"&$C$3,'データ'!$A$7:$A$123,0)),INDEX('データ'!N$759:N$875,MATCH($L22&"|"&$C$3,'データ'!$A$7:$A$123,0)),INDEX('データ'!O$759:O$875,MATCH($L22&"|"&$C$3,'データ'!$A$7:$A$123,0)),INDEX('データ'!P$759:P$875,MATCH($L22&"|"&$C$3,'データ'!$A$7:$A$123,0))),0) -> 0.013837362 | R22: =IFERROR(INDEX('データ'!P$759:P$875,MATCH($L22&"|"&$C$3,'データ'!$A$7:$A$123,0))/SUM(INDEX('データ'!K$759:K$875,MATCH($L22&"|"&$C$3,'データ'!$A$7:$A$123,0)),INDEX('データ'!L$759:L$875,MATCH($L22&"|"&$C$3,'データ'!$A$7:$A$123,0)),INDEX('データ'!M$759:M$875,MATCH($L22&"|"&$C$3,'データ'!$A$7:$A$123,0)),INDEX('データ'!N$759:N$875,MATCH($L22&"|"&$C$3,'データ'!$A$7:$A$123,0)),INDEX('データ'!O$759:O$875,MATCH($L22&"|"&$C$3,'データ'!$A$7:$A$123,0)),INDEX('データ'!P$759:P$875,MATCH($L22&"|"&$C$3,'データ'!$A$7:$A$123,0))),0) -> 0.0031670019
L23: 東区 | M23: =IFERROR(INDEX('データ'!K$759:K$875,MATCH($L23&"|"&$C$3,'データ'!$A$7:$A$123,0))/SUM(INDEX('データ'!K$759:K$875,MATCH($L23&"|"&$C$3,'データ'!$A$7:$A$123,0)),INDEX('データ'!L$759:L$875,MATCH($L23&"|"&$C$3,'データ'!$A$7:$A$123,0)),INDEX('データ'!M$759:M$875,MATCH($L23&"|"&$C$3,'データ'!$A$7:$A$123,0)),INDEX('データ'!N$759:N$875,MATCH($L23&"|"&$C$3,'データ'!$A$7:$A$123,0)),INDEX('データ'!O$759:O$875,MATCH($L23&"|"&$C$3,'データ'!$A$7:$A$123,0)),INDEX('データ'!P$759:P$875,MATCH($L23&"|"&$C$3,'データ'!$A$7:$A$123,0))),0) -> 0.75626854 | N23: =IFERROR(INDEX('データ'!L$759:L$875,MATCH($L23&"|"&$C$3,'データ'!$A$7:$A$123,0))/SUM(INDEX('データ'!K$759:K$875,MATCH($L23&"|"&$C$3,'データ'!$A$7:$A$123,0)),INDEX('データ'!L$759:L$875,MATCH($L23&"|"&$C$3,'データ'!$A$7:$A$123,0)),INDEX('データ'!M$759:M$875,MATCH($L23&"|"&$C$3,'データ'!$A$7:$A$123,0)),INDEX('データ'!N$759:N$875,MATCH($L23&"|"&$C$3,'データ'!$A$7:$A$123,0)),INDEX('データ'!O$759:O$875,MATCH($L23&"|"&$C$3,'データ'!$A$7:$A$123,0)),INDEX('データ'!P$759:P$875,MATCH($L23&"|"&$C$3,'データ'!$A$7:$A$123,0))),0) -> 0.12522366 | O23: =IFERROR(INDEX('データ'!M$759:M$875,MATCH($L23&"|"&$C$3,'データ'!$A$7:$A$123,0))/SUM(INDEX('データ'!K$759:K$875,MATCH($L23&"|"&$C$3,'データ'!$A$7:$A$123,0)),INDEX('データ'!L$759:L$875,MATCH($L23&"|"&$C$3,'データ'!$A$7:$A$123,0)),INDEX('データ'!M$759:M$875,MATCH($L23&"|"&$C$3,'データ'!$A$7:$A$123,0)),INDEX('データ'!N$759:N$875,MATCH($L23&"|"&$C$3,'データ'!$A$7:$A$123,0)),INDEX('データ'!O$759:O$875,MATCH($L23&"|"&$C$3,'データ'!$A$7:$A$123,0)),INDEX('データ'!P$759:P$875,MATCH($L23&"|"&$C$3,'データ'!$A$7:$A$123,0))),0) -> 0.059535773 | P23: =IFERROR(INDEX('データ'!N$759:N$875,MATCH($L23&"|"&$C$3,'データ'!$A$7:$A$123,0))/SUM(INDEX('データ'!K$759:K$875,MATCH($L23&"|"&$C$3,'データ'!$A$7:$A$123,0)),INDEX('データ'!L$759:L$875,MATCH($L23&"|"&$C$3,'データ'!$A$7:$A$123,0)),INDEX('データ'!M$759:M$875,MATCH($L23&"|"&$C$3,'データ'!$A$7:$A$123,0)),INDEX('データ'!N$759:N$875,MATCH($L23&"|"&$C$3,'データ'!$A$7:$A$123,0)),INDEX('データ'!O$759:O$875,MATCH($L23&"|"&$C$3,'データ'!$A$7:$A$123,0)),INDEX('データ'!P$759:P$875,MATCH($L23&"|"&$C$3,'データ'!$A$7:$A$123,0))),0) -> 0.0408711 | Q23: =IFERROR(INDEX('データ'!O$759:O$875,MATCH($L23&"|"&$C$3,'データ'!$A$7:$A$123,0))/SUM(INDEX('データ'!K$759:K$875,MATCH($L23&"|"&$C$3,'データ'!$A$7:$A$123,0)),INDEX('データ'!L$759:L$875,MATCH($L23&"|"&$C$3,'データ'!$A$7:$A$123,0)),INDEX('データ'!M$759:M$875,MATCH($L23&"|"&$C$3,'データ'!$A$7:$A$123,0)),INDEX('データ'!N$759:N$875,MATCH($L23&"|"&$C$3,'データ'!$A$7:$A$123,0)),INDEX('データ'!O$759:O$875,MATCH($L23&"|"&$C$3,'データ'!$A$7:$A$123,0)),INDEX('データ'!P$759:P$875,MATCH($L23&"|"&$C$3,'データ'!$A$7:$A$123,0))),0) -> 0.012402265 | R23: =IFERROR(INDEX('データ'!P$759:P$875,MATCH($L23&"|"&$C$3,'データ'!$A$7:$A$123,0))/SUM(INDEX('データ'!K$759:K$875,MATCH($L23&"|"&$C$3,'データ'!$A$7:$A$123,0)),INDEX('データ'!L$759:L$875,MATCH($L23&"|"&$C$3,'データ'!$A$7:$A$123,0)),INDEX('データ'!M$759:M$875,MATCH($L23&"|"&$C$3,'データ'!$A$7:$A$123,0)),INDEX('データ'!N$759:N$875,MATCH($L23&"|"&$C$3,'データ'!$A$7:$A$123,0)),INDEX('データ'!O$759:O$875,MATCH($L23&"|"&$C$3,'データ'!$A$7:$A$123,0)),INDEX('データ'!P$759:P$875,MATCH($L23&"|"&$C$3,'データ'!$A$7:$A$123,0))),0) -> 0.0056986691
L24: 南区 | M24: =IFERROR(INDEX('データ'!K$759:K$875,MATCH($L24&"|"&$C$3,'データ'!$A$7:$A$123,0))/SUM(INDEX('データ'!K$759:K$875,MATCH($L24&"|"&$C$3,'データ'!$A$7:$A$123,0)),INDEX('データ'!L$759:L$875,MATCH($L24&"|"&$C$3,'データ'!$A$7:$A$123,0)),INDEX('データ'!M$759:M$875,MATCH($L24&"|"&$C$3,'データ'!$A$7:$A$123,0)),INDEX('データ'!N$759:N$875,MATCH($L24&"|"&$C$3,'データ'!$A$7:$A$123,0)),INDEX('データ'!O$759:O$875,MATCH($L24&"|"&$C$3,'データ'!$A$7:$A$123,0)),INDEX('データ'!P$759:P$875,MATCH($L24&"|"&$C$3,'データ'!$A$7:$A$123,0))),0) -> 0.51545694 | N24: =IFERROR(INDEX('データ'!L$759:L$875,MATCH($L24&"|"&$C$3,'データ'!$A$7:$A$123,0))/SUM(INDEX('データ'!K$759:K$875,MATCH($L24&"|"&$C$3,'データ'!$A$7:$A$123,0)),INDEX('データ'!L$759:L$875,MATCH($L24&"|"&$C$3,'データ'!$A$7:$A$123,0)),INDEX('データ'!M$759:M$875,MATCH($L24&"|"&$C$3,'データ'!$A$7:$A$123,0)),INDEX('データ'!N$759:N$875,MATCH($L24&"|"&$C$3,'データ'!$A$7:$A$123,0)),INDEX('データ'!O$759:O$875,MATCH($L24&"|"&$C$3,'データ'!$A$7:$A$123,0)),INDEX('データ'!P$759:P$875,MATCH($L24&"|"&$C$3,'データ'!$A$7:$A$123,0))),0) -> 0.11925411 | O24: =IFERROR(INDEX('データ'!M$759:M$875,MATCH($L24&"|"&$C$3,'データ'!$A$7:$A$123,0))/SUM(INDEX('データ'!K$759:K$875,MATCH($L24&"|"&$C$3,'データ'!$A$7:$A$123,0)),INDEX('データ'!L$759:L$875,MATCH($L24&"|"&$C$3,'データ'!$A$7:$A$123,0)),INDEX('データ'!M$759:M$875,MATCH($L24&"|"&$C$3,'データ'!$A$7:$A$123,0)),INDEX('データ'!N$759:N$875,MATCH($L24&"|"&$C$3,'データ'!$A$7:$A$123,0)),INDEX('データ'!O$759:O$875,MATCH($L24&"|"&$C$3,'データ'!$A$7:$A$123,0)),INDEX('データ'!P$759:P$875,MATCH($L24&"|"&$C$3,'データ'!$A$7:$A$123,0))),0) -> 0.077132762 | P24: =IFERROR(INDEX('データ'!N$759:N$875,MATCH($L24&"|"&$C$3,'データ'!$A$7:$A$123,0))/SUM(INDEX('データ'!K$759:K$875,MATCH($L24&"|"&$C$3,'データ'!$A$7:$A$123,0)),INDEX('データ'!L$759:L$875,MATCH($L24&"|"&$C$3,'データ'!$A$7:$A$123,0)),INDEX('データ'!M$759:M$875,MATCH($L24&"|"&$C$3,'データ'!$A$7:$A$123,0)),INDEX('データ'!N$759:N$875,MATCH($L24&"|"&$C$3,'データ'!$A$7:$A$123,0)),INDEX('データ'!O$759:O$875,MATCH($L24&"|"&$C$3,'データ'!$A$7:$A$123,0)),INDEX('データ'!P$759:P$875,MATCH($L24&"|"&$C$3,'データ'!$A$7:$A$123,0))),0) -> 0.1380837 | Q24: =IFERROR(INDEX('データ'!O$759:O$875,MATCH($L24&"|"&$C$3,'データ'!$A$7:$A$123,0))/SUM(INDEX('データ'!K$759:K$875,MATCH($L24&"|"&$C$3,'データ'!$A$7:$A$123,0)),INDEX('データ'!L$759:L$875,MATCH($L24&"|"&$C$3,'データ'!$A$7:$A$123,0)),INDEX('データ'!M$759:M$875,MATCH($L24&"|"&$C$3,'データ'!$A$7:$A$123,0)),INDEX('データ'!N$759:N$875,MATCH($L24&"|"&$C$3,'データ'!$A$7:$A$123,0)),INDEX('データ'!O$759:O$875,MATCH($L24&"|"&$C$3,'データ'!$A$7:$A$123,0)),INDEX('データ'!P$759:P$875,MATCH($L24&"|"&$C$3,'データ'!$A$7:$A$123,0))),0) -> 0.09907024 | R24: =IFERROR(INDEX('データ'!P$759:P$875,MATCH($L24&"|"&$C$3,'データ'!$A$7:$A$123,0))/SUM(INDEX('データ'!K$759:K$875,MATCH($L24&"|"&$C$3,'データ'!$A$7:$A$123,0)),INDEX('データ'!L$759:L$875,MATCH($L24&"|"&$C$3,'データ'!$A$7:$A$123,0)),INDEX('データ'!M$759:M$875,MATCH($L24&"|"&$C$3,'データ'!$A$7:$A$123,0)),INDEX('データ'!N$759:N$875,MATCH($L24&"|"&$C$3,'データ'!$A$7:$A$123,0)),INDEX('データ'!O$759:O$875,MATCH($L24&"|"&$C$3,'データ'!$A$7:$A$123,0)),INDEX('データ'!P$759:P$875,MATCH($L24&"|"&$C$3,'データ'!$A$7:$A$123,0))),0) -> 0.051002248
L25: 西区 | M25: =IFERROR(INDEX('データ'!K$759:K$875,MATCH($L25&"|"&$C$3,'データ'!$A$7:$A$123,0))/SUM(INDEX('データ'!K$759:K$875,MATCH($L25&"|"&$C$3,'データ'!$A$7:$A$123,0)),INDEX('データ'!L$759:L$875,MATCH($L25&"|"&$C$3,'データ'!$A$7:$A$123,0)),INDEX('データ'!M$759:M$875,MATCH($L25&"|"&$C$3,'データ'!$A$7:$A$123,0)),INDEX('データ'!N$759:N$875,MATCH($L25&"|"&$C$3,'データ'!$A$7:$A$123,0)),INDEX('データ'!O$759:O$875,MATCH($L25&"|"&$C$3,'データ'!$A$7:$A$123,0)),INDEX('データ'!P$759:P$875,MATCH($L25&"|"&$C$3,'データ'!$A$7:$A$123,0))),0) -> 0.57371547 | N25: =IFERROR(INDEX('データ'!L$759:L$875,MATCH($L25&"|"&$C$3,'データ'!$A$7:$A$123,0))/SUM(INDEX('データ'!K$759:K$875,MATCH($L25&"|"&$C$3,'データ'!$A$7:$A$123,0)),INDEX('データ'!L$759:L$875,MATCH($L25&"|"&$C$3,'データ'!$A$7:$A$123,0)),INDEX('データ'!M$759:M$875,MATCH($L25&"|"&$C$3,'データ'!$A$7:$A$123,0)),INDEX('データ'!N$759:N$875,MATCH($L25&"|"&$C$3,'データ'!$A$7:$A$123,0)),INDEX('データ'!O$759:O$875,MATCH($L25&"|"&$C$3,'データ'!$A$7:$A$123,0)),INDEX('データ'!P$759:P$875,MATCH($L25&"|"&$C$3,'データ'!$A$7:$A$123,0))),0) -> 0.15253997 | O25: =IFERROR(INDEX('データ'!M$759:M$875,MATCH($L25&"|"&$C$3,'データ'!$A$7:$A$123,0))/SUM(INDEX('データ'!K$759:K$875,MATCH($L25&"|"&$C$3,'データ'!$A$7:$A$123,0)),INDEX('データ'!L$759:L$875,MATCH($L25&"|"&$C$3,'データ'!$A$7:$A$123,0)),INDEX('データ'!M$759:M$875,MATCH($L25&"|"&$C$3,'データ'!$A$7:$A$123,0)),INDEX('データ'!N$759:N$875,MATCH($L25&"|"&$C$3,'データ'!$A$7:$A$123,0)),INDEX('データ'!O$759:O$875,MATCH($L25&"|"&$C$3,'データ'!$A$7:$A$123,0)),INDEX('データ'!P$759:P$875,MATCH($L25&"|"&$C$3,'データ'!$A$7:$A$123,0))),0) -> 0.086860573 | P25: =IFERROR(INDEX('データ'!N$759:N$875,MATCH($L25&"|"&$C$3,'データ'!$A$7:$A$123,0))/SUM(INDEX('データ'!K$759:K$875,MATCH($L25&"|"&$C$3,'データ'!$A$7:$A$123,0)),INDEX('データ'!L$759:L$875,MATCH($L25&"|"&$C$3,'データ'!$A$7:$A$123,0)),INDEX('データ'!M$759:M$875,MATCH($L25&"|"&$C$3,'データ'!$A$7:$A$123,0)),INDEX('データ'!N$759:N$875,MATCH($L25&"|"&$C$3,'データ'!$A$7:$A$123,0)),INDEX('データ'!O$759:O$875,MATCH($L25&"|"&$C$3,'データ'!$A$7:$A$123,0)),INDEX('データ'!P$759:P$875,MATCH($L25&"|"&$C$3,'データ'!$A$7:$A$123,0))),0) -> 0.1181037 | Q25: =IFERROR(INDEX('データ'!O$759:O$875,MATCH($L25&"|"&$C$3,'データ'!$A$7:$A$123,0))/SUM(INDEX('データ'!K$759:K$875,MATCH($L25&"|"&$C$3,'データ'!$A$7:$A$123,0)),INDEX('データ'!L$759:L$875,MATCH($L25&"|"&$C$3,'データ'!$A$7:$A$123,0)),INDEX('データ'!M$759:M$875,MATCH($L25&"|"&$C$3,'データ'!$A$7:$A$123,0)),INDEX('データ'!N$759:N$875,MATCH($L25&"|"&$C$3,'データ'!$A$7:$A$123,0)),INDEX('データ'!O$759:O$875,MATCH($L25&"|"&$C$3,'データ'!$A$7:$A$123,0)),INDEX('データ'!P$759:P$875,MATCH($L25&"|"&$C$3,'データ'!$A$7:$A$123,0))),0) -> 0.057668154 | R25: =IFERROR(INDEX('データ'!P$759:P$875,MATCH($L25&"|"&$C$3,'データ'!$A$7:$A$123,0))/SUM(INDEX('データ'!K$759:K$875,MATCH($L25&"|"&$C$3,'データ'!$A$7:$A$123,0)),INDEX('データ'!L$759:L$875,MATCH($L25&"|"&$C$3,'データ'!$A$7:$A$123,0)),INDEX('データ'!M$759:M$875,MATCH($L25&"|"&$C$3,'データ'!$A$7:$A$123,0)),INDEX('データ'!N$759:N$875,MATCH($L25&"|"&$C$3,'データ'!$A$7:$A$123,0)),INDEX('データ'!O$759:O$875,MATCH($L25&"|"&$C$3,'データ'!$A$7:$A$123,0)),INDEX('データ'!P$759:P$875,MATCH($L25&"|"&$C$3,'データ'!$A$7:$A$123,0))),0) -> 0.011112136
L26: 安佐南区 | M26: =IFERROR(INDEX('データ'!K$759:K$875,MATCH($L26&"|"&$C$3,'データ'!$A$7:$A$123,0))/SUM(INDEX('データ'!K$759:K$875,MATCH($L26&"|"&$C$3,'データ'!$A$7:$A$123,0)),INDEX('データ'!L$759:L$875,MATCH($L26&"|"&$C$3,'データ'!$A$7:$A$123,0)),INDEX('データ'!M$759:M$875,MATCH($L26&"|"&$C$3,'データ'!$A$7:$A$123,0)),INDEX('データ'!N$759:N$875,MATCH($L26&"|"&$C$3,'データ'!$A$7:$A$123,0)),INDEX('データ'!O$759:O$875,MATCH($L26&"|"&$C$3,'データ'!$A$7:$A$123,0)),INDEX('データ'!P$759:P$875,MATCH($L26&"|"&$C$3,'データ'!$A$7:$A$123,0))),0) -> 0.46531494 | N26: =IFERROR(INDEX('データ'!L$759:L$875,MATCH($L26&"|"&$C$3,'データ'!$A$7:$A$123,0))/SUM(INDEX('データ'!K$759:K$875,MATCH($L26&"|"&$C$3,'データ'!$A$7:$A$123,0)),INDEX('データ'!L$759:L$875,MATCH($L26&"|"&$C$3,'データ'!$A$7:$A$123,0)),INDEX('データ'!M$759:M$875,MATCH($L26&"|"&$C$3,'データ'!$A$7:$A$123,0)),INDEX('データ'!N$759:N$875,MATCH($L26&"|"&$C$3,'データ'!$A$7:$A$123,0)),INDEX('データ'!O$759:O$875,MATCH($L26&"|"&$C$3,'データ'!$A$7:$A$123,0)),INDEX('データ'!P$759:P$875,MATCH($L26&"|"&$C$3,'データ'!$A$7:$A$123,0))),0) -> 0.13677325 | O26: =IFERROR(INDEX('データ'!M$759:M$875,MATCH($L26&"|"&$C$3,'データ'!$A$7:$A$123,0))/SUM(INDEX('データ'!K$759:K$875,MATCH($L26&"|"&$C$3,'データ'!$A$7:$A$123,0)),INDEX('データ'!L$759:L$875,MATCH($L26&"|"&$C$3,'データ'!$A$7:$A$123,0)),INDEX('データ'!M$759:M$875,MATCH($L26&"|"&$C$3,'データ'!$A$7:$A$123,0)),INDEX('データ'!N$759:N$875,MATCH($L26&"|"&$C$3,'データ'!$A$7:$A$123,0)),INDEX('データ'!O$759:O$875,MATCH($L26&"|"&$C$3,'データ'!$A$7:$A$123,0)),INDEX('データ'!P$759:P$875,MATCH($L26&"|"&$C$3,'データ'!$A$7:$A$123,0))),0) -> 0.095455377 | P26: =IFERROR(INDEX('データ'!N$759:N$875,MATCH($L26&"|"&$C$3,'データ'!$A$7:$A$123,0))/SUM(INDEX('データ'!K$759:K$875,MATCH($L26&"|"&$C$3,'データ'!$A$7:$A$123,0)),INDEX('データ'!L$759:L$875,MATCH($L26&"|"&$C$3,'データ'!$A$7:$A$123,0)),INDEX('データ'!M$759:M$875,MATCH($L26&"|"&$C$3,'データ'!$A$7:$A$123,0)),INDEX('データ'!N$759:N$875,MATCH($L26&"|"&$C$3,'データ'!$A$7:$A$123,0)),INDEX('データ'!O$759:O$875,MATCH($L26&"|"&$C$3,'データ'!$A$7:$A$123,0)),INDEX('データ'!P$759:P$875,MATCH($L26&"|"&$C$3,'データ'!$A$7:$A$123,0))),0) -> 0.16433375 | Q26: =IFERROR(INDEX('データ'!O$759:O$875,MATCH($L26&"|"&$C$3,'データ'!$A$7:$A$123,0))/SUM(INDEX('データ'!K$759:K$875,MATCH($L26&"|"&$C$3,'データ'!$A$7:$A$123,0)),INDEX('データ'!L$759:L$875,MATCH($L26&"|"&$C$3,'データ'!$A$7:$A$123,0)),INDEX('データ'!M$759:M$875,MATCH($L26&"|"&$C$3,'データ'!$A$7:$A$123,0)),INDEX('データ'!N$759:N$875,MATCH($L26&"|"&$C$3,'データ'!$A$7:$A$123,0)),INDEX('データ'!O$759:O$875,MATCH($L26&"|"&$C$3,'データ'!$A$7:$A$123,0)),INDEX('データ'!P$759:P$875,MATCH($L26&"|"&$C$3,'データ'!$A$7:$A$123,0))),0) -> 0.09978958 | R26: =IFERROR(INDEX('データ'!P$759:P$875,MATCH($L26&"|"&$C$3,'データ'!$A$7:$A$123,0))/SUM(INDEX('データ'!K$759:K$875,MATCH($L26&"|"&$C$3,'データ'!$A$7:$A$123,0)),INDEX('データ'!L$759:L$875,MATCH($L26&"|"&$C$3,'データ'!$A$7:$A$123,0)),INDEX('データ'!M$759:M$875,MATCH($L26&"|"&$C$3,'データ'!$A$7:$A$123,0)),INDEX('データ'!N$759:N$875,MATCH($L26&"|"&$C$3,'データ'!$A$7:$A$123,0)),INDEX('データ'!O$759:O$875,MATCH($L26&"|"&$C$3,'データ'!$A$7:$A$123,0)),INDEX('データ'!P$759:P$875,MATCH($L26&"|"&$C$3,'データ'!$A$7:$A$123,0))),0) -> 0.038333105
L27: 安佐北区 | M27: =IFERROR(INDEX('データ'!K$759:K$875,MATCH($L27&"|"&$C$3,'データ'!$A$7:$A$123,0))/SUM(INDEX('データ'!K$759:K$875,MATCH($L27&"|"&$C$3,'データ'!$A$7:$A$123,0)),INDEX('データ'!L$759:L$875,MATCH($L27&"|"&$C$3,'データ'!$A$7:$A$123,0)),INDEX('データ'!M$759:M$875,MATCH($L27&"|"&$C$3,'データ'!$A$7:$A$123,0)),INDEX('データ'!N$759:N$875,MATCH($L27&"|"&$C$3,'データ'!$A$7:$A$123,0)),INDEX('データ'!O$759:O$875,MATCH($L27&"|"&$C$3,'データ'!$A$7:$A$123,0)),INDEX('データ'!P$759:P$875,MATCH($L27&"|"&$C$3,'データ'!$A$7:$A$123,0))),0) -> 0.76466821 | N27: =IFERROR(INDEX('データ'!L$759:L$875,MATCH($L27&"|"&$C$3,'データ'!$A$7:$A$123,0))/SUM(INDEX('データ'!K$759:K$875,MATCH($L27&"|"&$C$3,'データ'!$A$7:$A$123,0)),INDEX('データ'!L$759:L$875,MATCH($L27&"|"&$C$3,'データ'!$A$7:$A$123,0)),INDEX('データ'!M$759:M$875,MATCH($L27&"|"&$C$3,'データ'!$A$7:$A$123,0)),INDEX('データ'!N$759:N$875,MATCH($L27&"|"&$C$3,'データ'!$A$7:$A$123,0)),INDEX('データ'!O$759:O$875,MATCH($L27&"|"&$C$3,'データ'!$A$7:$A$123,0)),INDEX('データ'!P$759:P$875,MATCH($L27&"|"&$C$3,'データ'!$A$7:$A$123,0))),0) -> 0.14911991 | O27: =IFERROR(INDEX('データ'!M$759:M$875,MATCH($L27&"|"&$C$3,'データ'!$A$7:$A$123,0))/SUM(INDEX('データ'!K$759:K$875,MATCH($L27&"|"&$C$3,'データ'!$A$7:$A$123,0)),INDEX('データ'!L$759:L$875,MATCH($L27&"|"&$C$3,'データ'!$A$7:$A$123,0)),INDEX('データ'!M$759:M$875,MATCH($L27&"|"&$C$3,'データ'!$A$7:$A$123,0)),INDEX('データ'!N$759:N$875,MATCH($L27&"|"&$C$3,'データ'!$A$7:$A$123,0)),INDEX('データ'!O$759:O$875,MATCH($L27&"|"&$C$3,'データ'!$A$7:$A$123,0)),INDEX('データ'!P$759:P$875,MATCH($L27&"|"&$C$3,'データ'!$A$7:$A$123,0))),0) -> 0.053962482 | P27: =IFERROR(INDEX('データ'!N$759:N$875,MATCH($L27&"|"&$C$3,'データ'!$A$7:$A$123,0))/SUM(INDEX('データ'!K$759:K$875,MATCH($L27&"|"&$C$3,'データ'!$A$7:$A$123,0)),INDEX('データ'!L$759:L$875,MATCH($L27&"|"&$C$3,'データ'!$A$7:$A$123,0)),INDEX('データ'!M$759:M$875,MATCH($L27&"|"&$C$3,'データ'!$A$7:$A$123,0)),INDEX('データ'!N$759:N$875,MATCH($L27&"|"&$C$3,'データ'!$A$7:$A$123,0)),INDEX('データ'!O$759:O$875,MATCH($L27&"|"&$C$3,'データ'!$A$7:$A$123,0)),INDEX('データ'!P$759:P$875,MATCH($L27&"|"&$C$3,'データ'!$A$7:$A$123,0))),0) -> 0.029749607 | Q27: =IFERROR(INDEX('データ'!O$759:O$875,MATCH($L27&"|"&$C$3,'データ'!$A$7:$A$123,0))/SUM(INDEX('データ'!K$759:K$875,MATCH($L27&"|"&$C$3,'データ'!$A$7:$A$123,0)),INDEX('データ'!L$759:L$875,MATCH($L27&"|"&$C$3,'データ'!$A$7:$A$123,0)),INDEX('データ'!M$759:M$875,MATCH($L27&"|"&$C$3,'データ'!$A$7:$A$123,0)),INDEX('データ'!N$759:N$875,MATCH($L27&"|"&$C$3,'データ'!$A$7:$A$123,0)),INDEX('データ'!O$759:O$875,MATCH($L27&"|"&$C$3,'データ'!$A$7:$A$123,0)),INDEX('データ'!P$759:P$875,MATCH($L27&"|"&$C$3,'データ'!$A$7:$A$123,0))),0) -> 0.0021072639 | R27: =IFERROR(INDEX('データ'!P$759:P$875,MATCH($L27&"|"&$C$3,'データ'!$A$7:$A$123,0))/SUM(INDEX('データ'!K$759:K$875,MATCH($L27&"|"&$C$3,'データ'!$A$7:$A$123,0)),INDEX('データ'!L$759:L$875,MATCH($L27&"|"&$C$3,'データ'!$A$7:$A$123,0)),INDEX('データ'!M$759:M$875,MATCH($L27&"|"&$C$3,'データ'!$A$7:$A$123,0)),INDEX('データ'!N$759:N$875,MATCH($L27&"|"&$C$3,'データ'!$A$7:$A$123,0)),INDEX('データ'!O$759:O$875,MATCH($L27&"|"&$C$3,'データ'!$A$7:$A$123,0)),INDEX('データ'!P$759:P$875,MATCH($L27&"|"&$C$3,'データ'!$A$7:$A$123,0))),0) -> 0.00039252954
L28: 安芸区 | M28: =IFERROR(INDEX('データ'!K$759:K$875,MATCH($L28&"|"&$C$3,'データ'!$A$7:$A$123,0))/SUM(INDEX('データ'!K$759:K$875,MATCH($L28&"|"&$C$3,'データ'!$A$7:$A$123,0)),INDEX('データ'!L$759:L$875,MATCH($L28&"|"&$C$3,'データ'!$A$7:$A$123,0)),INDEX('データ'!M$759:M$875,MATCH($L28&"|"&$C$3,'データ'!$A$7:$A$123,0)),INDEX('データ'!N$759:N$875,MATCH($L28&"|"&$C$3,'データ'!$A$7:$A$123,0)),INDEX('データ'!O$759:O$875,MATCH($L28&"|"&$C$3,'データ'!$A$7:$A$123,0)),INDEX('データ'!P$759:P$875,MATCH($L28&"|"&$C$3,'データ'!$A$7:$A$123,0))),0) -> 0.85542394 | N28: =IFERROR(INDEX('データ'!L$759:L$875,MATCH($L28&"|"&$C$3,'データ'!$A$7:$A$123,0))/SUM(INDEX('データ'!K$759:K$875,MATCH($L28&"|"&$C$3,'データ'!$A$7:$A$123,0)),INDEX('データ'!L$759:L$875,MATCH($L28&"|"&$C$3,'データ'!$A$7:$A$123,0)),INDEX('データ'!M$759:M$875,MATCH($L28&"|"&$C$3,'データ'!$A$7:$A$123,0)),INDEX('データ'!N$759:N$875,MATCH($L28&"|"&$C$3,'データ'!$A$7:$A$123,0)),INDEX('データ'!O$759:O$875,MATCH($L28&"|"&$C$3,'データ'!$A$7:$A$123,0)),INDEX('データ'!P$759:P$875,MATCH($L28&"|"&$C$3,'データ'!$A$7:$A$123,0))),0) -> 0.085590524 | O28: =IFERROR(INDEX('データ'!M$759:M$875,MATCH($L28&"|"&$C$3,'データ'!$A$7:$A$123,0))/SUM(INDEX('データ'!K$759:K$875,MATCH($L28&"|"&$C$3,'データ'!$A$7:$A$123,0)),INDEX('データ'!L$759:L$875,MATCH($L28&"|"&$C$3,'データ'!$A$7:$A$123,0)),INDEX('データ'!M$759:M$875,MATCH($L28&"|"&$C$3,'データ'!$A$7:$A$123,0)),INDEX('データ'!N$759:N$875,MATCH($L28&"|"&$C$3,'データ'!$A$7:$A$123,0)),INDEX('データ'!O$759:O$875,MATCH($L28&"|"&$C$3,'データ'!$A$7:$A$123,0)),INDEX('データ'!P$759:P$875,MATCH($L28&"|"&$C$3,'データ'!$A$7:$A$123,0))),0) -> 0.031979465 | P28: =IFERROR(INDEX('データ'!N$759:N$875,MATCH($L28&"|"&$C$3,'データ'!$A$7:$A$123,0))/SUM(INDEX('データ'!K$759:K$875,MATCH($L28&"|"&$C$3,'データ'!$A$7:$A$123,0)),INDEX('データ'!L$759:L$875,MATCH($L28&"|"&$C$3,'データ'!$A$7:$A$123,0)),INDEX('データ'!M$759:M$875,MATCH($L28&"|"&$C$3,'データ'!$A$7:$A$123,0)),INDEX('データ'!N$759:N$875,MATCH($L28&"|"&$C$3,'データ'!$A$7:$A$123,0)),INDEX('データ'!O$759:O$875,MATCH($L28&"|"&$C$3,'データ'!$A$7:$A$123,0)),INDEX('データ'!P$759:P$875,MATCH($L28&"|"&$C$3,'データ'!$A$7:$A$123,0))),0) -> 0.021417685 | Q28: =IFERROR(INDEX('データ'!O$759:O$875,MATCH($L28&"|"&$C$3,'データ'!$A$7:$A$123,0))/SUM(INDEX('データ'!K$759:K$875,MATCH($L28&"|"&$C$3,'データ'!$A$7:$A$123,0)),INDEX('データ'!L$759:L$875,MATCH($L28&"|"&$C$3,'データ'!$A$7:$A$123,0)),INDEX('データ'!M$759:M$875,MATCH($L28&"|"&$C$3,'データ'!$A$7:$A$123,0)),INDEX('データ'!N$759:N$875,MATCH($L28&"|"&$C$3,'データ'!$A$7:$A$123,0)),INDEX('データ'!O$759:O$875,MATCH($L28&"|"&$C$3,'データ'!$A$7:$A$123,0)),INDEX('データ'!P$759:P$875,MATCH($L28&"|"&$C$3,'データ'!$A$7:$A$123,0))),0) -> 0.0039840637 | R28: =IFERROR(INDEX('データ'!P$759:P$875,MATCH($L28&"|"&$C$3,'データ'!$A$7:$A$123,0))/SUM(INDEX('データ'!K$759:K$875,MATCH($L28&"|"&$C$3,'データ'!$A$7:$A$123,0)),INDEX('データ'!L$759:L$875,MATCH($L28&"|"&$C$3,'データ'!$A$7:$A$123,0)),INDEX('データ'!M$759:M$875,MATCH($L28&"|"&$C$3,'データ'!$A$7:$A$123,0)),INDEX('データ'!N$759:N$875,MATCH($L28&"|"&$C$3,'データ'!$A$7:$A$123,0)),INDEX('データ'!O$759:O$875,MATCH($L28&"|"&$C$3,'データ'!$A$7:$A$123,0)),INDEX('データ'!P$759:P$875,MATCH($L28&"|"&$C$3,'データ'!$A$7:$A$123,0))),0) -> 0.001604321
L29: 佐伯区 | M29: =IFERROR(INDEX('データ'!K$759:K$875,MATCH($L29&"|"&$C$3,'データ'!$A$7:$A$123,0))/SUM(INDEX('データ'!K$759:K$875,MATCH($L29&"|"&$C$3,'データ'!$A$7:$A$123,0)),INDEX('データ'!L$759:L$875,MATCH($L29&"|"&$C$3,'データ'!$A$7:$A$123,0)),INDEX('データ'!M$759:M$875,MATCH($L29&"|"&$C$3,'データ'!$A$7:$A$123,0)),INDEX('データ'!N$759:N$875,MATCH($L29&"|"&$C$3,'データ'!$A$7:$A$123,0)),INDEX('データ'!O$759:O$875,MATCH($L29&"|"&$C$3,'データ'!$A$7:$A$123,0)),INDEX('データ'!P$759:P$875,MATCH($L29&"|"&$C$3,'データ'!$A$7:$A$123,0))),0) -> 0.64361066 | N29: =IFERROR(INDEX('データ'!L$759:L$875,MATCH($L29&"|"&$C$3,'データ'!$A$7:$A$123,0))/SUM(INDEX('データ'!K$759:K$875,MATCH($L29&"|"&$C$3,'データ'!$A$7:$A$123,0)),INDEX('データ'!L$759:L$875,MATCH($L29&"|"&$C$3,'データ'!$A$7:$A$123,0)),INDEX('データ'!M$759:M$875,MATCH($L29&"|"&$C$3,'データ'!$A$7:$A$123,0)),INDEX('データ'!N$759:N$875,MATCH($L29&"|"&$C$3,'データ'!$A$7:$A$123,0)),INDEX('データ'!O$759:O$875,MATCH($L29&"|"&$C$3,'データ'!$A$7:$A$123,0)),INDEX('データ'!P$759:P$875,MATCH($L29&"|"&$C$3,'データ'!$A$7:$A$123,0))),0) -> 0.16991689 | O29: =IFERROR(INDEX('データ'!M$759:M$875,MATCH($L29&"|"&$C$3,'データ'!$A$7:$A$123,0))/SUM(INDEX('データ'!K$759:K$875,MATCH($L29&"|"&$C$3,'データ'!$A$7:$A$123,0)),INDEX('データ'!L$759:L$875,MATCH($L29&"|"&$C$3,'データ'!$A$7:$A$123,0)),INDEX('データ'!M$759:M$875,MATCH($L29&"|"&$C$3,'データ'!$A$7:$A$123,0)),INDEX('データ'!N$759:N$875,MATCH($L29&"|"&$C$3,'データ'!$A$7:$A$123,0)),INDEX('データ'!O$759:O$875,MATCH($L29&"|"&$C$3,'データ'!$A$7:$A$123,0)),INDEX('データ'!P$759:P$875,MATCH($L29&"|"&$C$3,'データ'!$A$7:$A$123,0))),0) -> 0.08887975 | P29: =IFERROR(INDEX('データ'!N$759:N$875,MATCH($L29&"|"&$C$3,'データ'!$A$7:$A$123,0))/SUM(INDEX('データ'!K$759:K$875,MATCH($L29&"|"&$C$3,'データ'!$A$7:$A$123,0)),INDEX('データ'!L$759:L$875,MATCH($L29&"|"&$C$3,'データ'!$A$7:$A$123,0)),INDEX('データ'!M$759:M$875,MATCH($L29&"|"&$C$3,'データ'!$A$7:$A$123,0)),INDEX('データ'!N$759:N$875,MATCH($L29&"|"&$C$3,'データ'!$A$7:$A$123,0)),INDEX('データ'!O$759:O$875,MATCH($L29&"|"&$C$3,'データ'!$A$7:$A$123,0)),INDEX('データ'!P$759:P$875,MATCH($L29&"|"&$C$3,'データ'!$A$7:$A$123,0))),0) -> 0.08357164 | Q29: =IFERROR(INDEX('データ'!O$759:O$875,MATCH($L29&"|"&$C$3,'データ'!$A$7:$A$123,0))/SUM(INDEX('データ'!K$759:K$875,MATCH($L29&"|"&$C$3,'データ'!$A$7:$A$123,0)),INDEX('データ'!L$759:L$875,MATCH($L29&"|"&$C$3,'データ'!$A$7:$A$123,0)),INDEX('データ'!M$759:M$875,MATCH($L29&"|"&$C$3,'データ'!$A$7:$A$123,0)),INDEX('データ'!N$759:N$875,MATCH($L29&"|"&$C$3,'データ'!$A$7:$A$123,0)),INDEX('データ'!O$759:O$875,MATCH($L29&"|"&$C$3,'データ'!$A$7:$A$123,0)),INDEX('データ'!P$759:P$875,MATCH($L29&"|"&$C$3,'データ'!$A$7:$A$123,0))),0) -> 0.011649148 | R29: =IFERROR(INDEX('データ'!P$759:P$875,MATCH($L29&"|"&$C$3,'データ'!$A$7:$A$123,0))/SUM(INDEX('データ'!K$759:K$875,MATCH($L29&"|"&$C$3,'データ'!$A$7:$A$123,0)),INDEX('データ'!L$759:L$875,MATCH($L29&"|"&$C$3,'データ'!$A$7:$A$123,0)),INDEX('データ'!M$759:M$875,MATCH($L29&"|"&$C$3,'データ'!$A$7:$A$123,0)),INDEX('データ'!N$759:N$875,MATCH($L29&"|"&$C$3,'データ'!$A$7:$A$123,0)),INDEX('データ'!O$759:O$875,MATCH($L29&"|"&$C$3,'データ'!$A$7:$A$123,0)),INDEX('データ'!P$759:P$875,MATCH($L29&"|"&$C$3,'データ'!$A$7:$A$123,0))),0) -> 0.002371912
B52: 注：3時間（180分）を超える値は平均から除く。15分以内率＝待ち時間が15分未満の割合。

Sheet ヒートマップ
B1: 時間帯別ヒートマップ
A3: =MATCH($H$3,'計算'!$A$310:$A$313,0) -> 1 | B3: 区 | C3: 全区 | E3: 指標 | H3: 来庁者数 | P3: 数値は非表示（セルを選択すると数式バーに表示）
B5: 曜日×時間帯（選択した区）
B6: 曜日 | D6: 7時 | H6: 8時 | L6: 9時 | P6: 10時 | T6: 11時 | X6: 12時 | AB6: 13時 | AF6: 14時 | AJ6: 15時 | AN6: 16時 | AR6: 17時 | AV6: 18時 | AZ6: 19時 | BD6: 20時
B7: 月 | C7: =MATCH($C$3&"|"&$B7,'データ'!$A$491:$A$553,0) -> 1 | D7: =IFERROR(CHOOSE($A$3,INDEX('データ'!D$491:D$553,$C7),INDEX('データ'!D$558:D$620,$C7),INDEX('データ'!D$625:D$687,$C7),INDEX('データ'!D$692:D$754,$C7)),0) -> 0 | E7: =IFERROR(CHOOSE($A$3,INDEX('データ'!E$491:E$553,$C7),INDEX('データ'!E$558:E$620,$C7),INDEX('データ'!E$625:E$687,$C7),INDEX('データ'!E$692:E$754,$C7)),0) -> 0 | F7: =IFERROR(CHOOSE($A$3,INDEX('データ'!F$491:F$553,$C7),INDEX('データ'!F$558:F$620,$C7),INDEX('データ'!F$625:F$687,$C7),INDEX('データ'!F$692:F$754,$C7)),0) -> 0 | G7: =IFERROR(CHOOSE($A$3,INDEX('データ'!G$491:G$553,$C7),INDEX('データ'!G$558:G$620,$C7),INDEX('データ'!G$625:G$687,$C7),INDEX('データ'!G$692:G$754,$C7)),0) -> 43 | H7: =IFERROR(CHOOSE($A$3,INDEX('データ'!H$491:H$553,$C7),INDEX('データ'!H$558:H$620,$C7),INDEX('データ'!H$625:H$687,$C7),INDEX('データ'!H$692:H$754,$C7)),0) -> 314 | I7: =IFERROR(CHOOSE($A$3,INDEX('データ'!I$491:I$553,$C7),INDEX('データ'!I$558:I$620,$C7),INDEX('データ'!I$625:I$687,$C7),INDEX('データ'!I$692:I$754,$C7)),0) -> 1645 | J7: =IFERROR(CHOOSE($A$3,INDEX('データ'!J$491:J$553,$C7),INDEX('データ'!J$558:J$620,$C7),INDEX('データ'!J$625:J$687,$C7),INDEX('データ'!J$692:J$754,$C7)),0) -> 3375 | K7: =IFERROR(CHOOSE($A$3,INDEX('データ'!K$491:K$553,$C7),INDEX('データ'!K$558:K$620,$C7),INDEX('データ'!K$625:K$687,$C7),INDEX('データ'!K$692:K$754,$C7)),0) -> 3651 | ... BG7: =IFERROR(CHOOSE($A$3,INDEX('データ'!BG$491:BG$553,$C7),INDEX('データ'!BG$558:BG$620,$C7),INDEX('データ'!BG$625:BG$687,$C7),INDEX('データ'!BG$692:BG$754,$C7)),0) -> 0
B8: 火 | C8: =MATCH($C$3&"|"&$B8,'データ'!$A$491:$A$553,0) -> 2 | D8: =IFERROR(CHOOSE($A$3,INDEX('データ'!D$491:D$553,$C8),INDEX('データ'!D$558:D$620,$C8),INDEX('データ'!D$625:D$687,$C8),INDEX('データ'!D$692:D$754,$C8)),0) -> 0 | E8: =IFERROR(CHOOSE($A$3,INDEX('データ'!E$491:E$553,$C8),INDEX('データ'!E$558:E$620,$C8),INDEX('データ'!E$625:E$687,$C8),INDEX('データ'!E$692:E$754,$C8)),0) -> 0 | F8: =IFERROR(CHOOSE($A$3,INDEX('データ'!F$491:F$553,$C8),INDEX('データ'!F$558:F$620,$C8),INDEX('データ'!F$625:F$687,$C8),INDEX('データ'!F$692:F$754,$C8)),0) -> 2 | G8: =IFERROR(CHOOSE($A$3,INDEX('データ'!G$491:G$553,$C8),INDEX('データ'!G$558:G$620,$C8),INDEX('データ'!G$625:G$687,$C8),INDEX('データ'!G$692:G$754,$C8)),0) -> 33 | H8: =IFERROR(CHOOSE($A$3,INDEX('データ'!H$491:H$553,$C8),INDEX('データ'!H$558:H$620,$C8),INDEX('データ'!H$625:H$687,$C8),INDEX('データ'!H$692:H$754,$C8)),0) -> 344 | I8: =IFERROR(CHOOSE($A$3,INDEX('データ'!I$491:I$553,$C8),INDEX('データ'!I$558:I$620,$C8),INDEX('データ'!I$625:I$687,$C8),INDEX('データ'!I$692:I$754,$C8)),0) -> 1404 | J8: =IFERROR(CHOOSE($A$3,INDEX('データ'!J$491:J$553,$C8),INDEX('データ'!J$558:J$620,$C8),INDEX('データ'!J$625:J$687,$C8),INDEX('データ'!J$692:J$754,$C8)),0) -> 3116 | K8: =IFERROR(CHOOSE($A$3,INDEX('データ'!K$491:K$553,$C8),INDEX('データ'!K$558:K$620,$C8),INDEX('データ'!K$625:K$687,$C8),INDEX('データ'!K$692:K$754,$C8)),0) -> 3250 | ... BG8: =IFERROR(CHOOSE($A$3,INDEX('データ'!BG$491:BG$553,$C8),INDEX('データ'!BG$558:BG$620,$C8),INDEX('データ'!BG$625:BG$687,$C8),INDEX('データ'!BG$692:BG$754,$C8)),0) -> 0
B9: 水 | C9: =MATCH($C$3&"|"&$B9,'データ'!$A$491:$A$553,0) -> 3 | D9: =IFERROR(CHOOSE($A$3,INDEX('データ'!D$491:D$553,$C9),INDEX('データ'!D$558:D$620,$C9),INDEX('データ'!D$625:D$687,$C9),INDEX('データ'!D$692:D$754,$C9)),0) -> 0 | E9: =IFERROR(CHOOSE($A$3,INDEX('データ'!E$491:E$553,$C9),INDEX('データ'!E$558:E$620,$C9),INDEX('データ'!E$625:E$687,$C9),INDEX('データ'!E$692:E$754,$C9)),0) -> 0 | F9: =IFERROR(CHOOSE($A$3,INDEX('データ'!F$491:F$553,$C9),INDEX('データ'!F$558:F$620,$C9),INDEX('データ'!F$625:F$687,$C9),INDEX('データ'!F$692:F$754,$C9)),0) -> 0 | G9: =IFERROR(CHOOSE($A$3,INDEX('データ'!G$491:G$553,$C9),INDEX('データ'!G$558:G$620,$C9),INDEX('データ'!G$625:G$687,$C9),INDEX('データ'!G$692:G$754,$C9)),0) -> 24 | H9: =IFERROR(CHOOSE($A$3,INDEX('データ'!H$491:H$553,$C9),INDEX('データ'!H$558:H$620,$C9),INDEX('データ'!H$625:H$687,$C9),INDEX('データ'!H$692:H$754,$C9)),0) -> 287 | I9: =IFERROR(CHOOSE($A$3,INDEX('データ'!I$491:I$553,$C9),INDEX('データ'!I$558:I$620,$C9),INDEX('データ'!I$625:I$687,$C9),INDEX('データ'!I$692:I$754,$C9)),0) -> 1258 | J9: =IFERROR(CHOOSE($A$3,INDEX('データ'!J$491:J$553,$C9),INDEX('データ'!J$558:J$620,$C9),INDEX('データ'!J$625:J$687,$C9),INDEX('データ'!J$692:J$754,$C9)),0) -> 2958 | K9: =IFERROR(CHOOSE($A$3,INDEX('データ'!K$491:K$553,$C9),INDEX('データ'!K$558:K$620,$C9),INDEX('データ'!K$625:K$687,$C9),INDEX('データ'!K$692:K$754,$C9)),0) -> 2987 | ... BG9: =IFERROR(CHOOSE($A$3,INDEX('データ'!BG$491:BG$553,$C9),INDEX('データ'!BG$558:BG$620,$C9),INDEX('データ'!BG$625:BG$687,$C9),INDEX('データ'!BG$692:BG$754,$C9)),0) -> 0
B10: 木 | C10: =MATCH($C$3&"|"&$B10,'データ'!$A$491:$A$553,0) -> 4 | D10: =IFERROR(CHOOSE($A$3,INDEX('データ'!D$491:D$553,$C10),INDEX('データ'!D$558:D$620,$C10),INDEX('データ'!D$625:D$687,$C10),INDEX('データ'!D$692:D$754,$C10)),0) -> 0 | E10: =IFERROR(CHOOSE($A$3,INDEX('データ'!E$491:E$553,$C10),INDEX('データ'!E$558:E$620,$C10),INDEX('データ'!E$625:E$687,$C10),INDEX('データ'!E$692:E$754,$C10)),0) -> 0 | F10: =IFERROR(CHOOSE($A$3,INDEX('データ'!F$491:F$553,$C10),INDEX('データ'!F$558:F$620,$C10),INDEX('データ'!F$625:F$687,$C10),INDEX('データ'!F$692:F$754,$C10)),0) -> 0 | G10: =IFERROR(CHOOSE($A$3,INDEX('データ'!G$491:G$553,$C10),INDEX('データ'!G$558:G$620,$C10),INDEX('データ'!G$625:G$687,$C10),INDEX('データ'!G$692:G$754,$C10)),0) -> 36 | H10: =IFERROR(CHOOSE($A$3,INDEX('データ'!H$491:H$553,$C10),INDEX('データ'!H$558:H$620,$C10),INDEX('データ'!H$625:H$687,$C10),INDEX('データ'!H$692:H$754,$C10)),0) -> 266 | I10: =IFERROR(CHOOSE($A$3,INDEX('データ'!I$491:I$553,$C10),INDEX('データ'!I$558:I$620,$C10),INDEX('データ'!I$625:I$687,$C10),INDEX('データ'!I$692:I$754,$C10)),0) -> 1215 | J10: =IFERROR(CHOOSE($A$3,INDEX('データ'!J$491:J$553,$C10),INDEX('データ'!J$558:J$620,$C10),INDEX('データ'!J$625:J$687,$C10),INDEX('データ'!J$692:J$754,$C10)),0) -> 2748 | K10: =IFERROR(CHOOSE($A$3,INDEX('データ'!K$491:K$553,$C10),INDEX('データ'!K$558:K$620,$C10),INDEX('データ'!K$625:K$687,$C10),INDEX('データ'!K$692:K$754,$C10)),0) -> 3056 | ... BG10: =IFERROR(CHOOSE($A$3,INDEX('データ'!BG$491:BG$553,$C10),INDEX('データ'!BG$558:BG$620,$C10),INDEX('データ'!BG$625:BG$687,$C10),INDEX('データ'!BG$692:BG$754,$C10)),0) -> 0
B11: 金 | C11: =MATCH($C$3&"|"&$B11,'データ'!$A$491:$A$553,0) -> 5 | D11: =IFERROR(CHOOSE($A$3,INDEX('データ'!D$491:D$553,$C11),INDEX('データ'!D$558:D$620,$C11),INDEX('データ'!D$625:D$687,$C11),INDEX('データ'!D$692:D$754,$C11)),0) -> 0 | E11: =IFERROR(CHOOSE($A$3,INDEX('データ'!E$491:E$553,$C11),INDEX('データ'!E$558:E$620,$C11),INDEX('データ'!E$625:E$687,$C11),INDEX('データ'!E$692:E$754,$C11)),0) -> 0 | F11: =IFERROR(CHOOSE($A$3,INDEX('データ'!F$491:F$553,$C11),INDEX('データ'!F$558:F$620,$C11),INDEX('データ'!F$625:F$687,$C11),INDEX('データ'!F$692:F$754,$C11)),0) -> 1 | G11: =IFERROR(CHOOSE($A$3,INDEX('データ'!G$491:G$553,$C11),INDEX('データ'!G$558:G$620,$C11),INDEX('データ'!G$625:G$687,$C11),INDEX('データ'!G$692:G$754,$C11)),0) -> 37 | H11: =IFERROR(CHOOSE($A$3,INDEX('データ'!H$491:H$553,$C11),INDEX('データ'!H$558:H$620,$C11),INDEX('データ'!H$625:H$687,$C11),INDEX('データ'!H$692:H$754,$C11)),0) -> 315 | I11: =IFERROR(CHOOSE($A$3,INDEX('データ'!I$491:I$553,$C11),INDEX('データ'!I$558:I$620,$C11),INDEX('データ'!I$625:I$687,$C11),INDEX('データ'!I$692:I$754,$C11)),0) -> 1264 | J11: =IFERROR(CHOOSE($A$3,INDEX('データ'!J$491:J$553,$C11),INDEX('データ'!J$558:J$620,$C11),INDEX('データ'!J$625:J$687,$C11),INDEX('データ'!J$692:J$754,$C11)),0) -> 2932 | K11: =IFERROR(CHOOSE($A$3,INDEX('データ'!K$491:K$553,$C11),INDEX('データ'!K$558:K$620,$C11),INDEX('データ'!K$625:K$687,$C11),INDEX('データ'!K$692:K$754,$C11)),0) -> 3282 | ... BG11: =IFERROR(CHOOSE($A$3,INDEX('データ'!BG$491:BG$553,$C11),INDEX('データ'!BG$558:BG$620,$C11),INDEX('データ'!BG$625:BG$687,$C11),INDEX('データ'!BG$692:BG$754,$C11)),0) -> 0
B12: 土 | C12: =MATCH($C$3&"|"&$B12,'データ'!$A$491:$A$553,0) -> 6 | D12: =IFERROR(CHOOSE($A$3,INDEX('データ'!D$491:D$553,$C12),INDEX('データ'!D$558:D$620,$C12),INDEX('データ'!D$625:D$687,$C12),INDEX('データ'!D$692:D$754,$C12)),0) -> 0 | E12: =IFERROR(CHOOSE($A$3,INDEX('データ'!E$491:E$553,$C12),INDEX('データ'!E$558:E$620,$C12),INDEX('データ'!E$625:E$687,$C12),INDEX('データ'!E$692:E$754,$C12)),0) -> 0 | F12: =IFERROR(CHOOSE($A$3,INDEX('データ'!F$491:F$553,$C12),INDEX('データ'!F$558:F$620,$C12),INDEX('データ'!F$625:F$687,$C12),INDEX('データ'!F$692:F$754,$C12)),0) -> 0 | G12: =IFERROR(CHOOSE($A$3,INDEX('データ'!G$491:G$553,$C12),INDEX('データ'!G$558:G$620,$C12),INDEX('データ'!G$625:G$687,$C12),INDEX('データ'!G$692:G$754,$C12)),0) -> 0 | H12: =IFERROR(CHOOSE($A$3,INDEX('データ'!H$491:H$553,$C12),INDEX('データ'!H$558:H$620,$C12),INDEX('データ'!H$625:H$687,$C12),INDEX('データ'!H$692:H$754,$C12)),0) -> 1 | I12: =IFERROR(CHOOSE($A$3,INDEX('データ'!I$491:I$553,$C12),INDEX('データ'!I$558:I$620,$C12),INDEX('データ'!I$625:I$687,$C12),INDEX('データ'!I$692:I$754,$C12)),0) -> 10 | J12: =IFERROR(CHOOSE($A$3,INDEX('データ'!J$491:J$553,$C12),INDEX('データ'!J$558:J$620,$C12),INDEX('データ'!J$625:J$687,$C12),INDEX('データ'!J$692:J$754,$C12)),0) -> 19 | K12: =IFERROR(CHOOSE($A$3,INDEX('データ'!K$491:K$553,$C12),INDEX('データ'!K$558:K$620,$C12),INDEX('データ'!K$625:K$687,$C12),INDEX('データ'!K$692:K$754,$C12)),0) -> 11 | ... BG12: =IFERROR(CHOOSE($A$3,INDEX('データ'!BG$491:BG$553,$C12),INDEX('データ'!BG$558:BG$620,$C12),INDEX('データ'!BG$625:BG$687,$C12),INDEX('データ'!BG$692:BG$754,$C12)),0) -> 0
B13: 日 | C13: =MATCH($C$3&"|"&$B13,'データ'!$A$491:$A$553,0) -> 7 | D13: =IFERROR(CHOOSE($A$3,INDEX('データ'!D$491:D$553,$C13),INDEX('データ'!D$558:D$620,$C13),INDEX('データ'!D$625:D$687,$C13),INDEX('データ'!D$692:D$754,$C13)),0) -> 0 | E13: =IFERROR(CHOOSE($A$3,INDEX('データ'!E$491:E$553,$C13),INDEX('データ'!E$558:E$620,$C13),INDEX('データ'!E$625:E$687,$C13),INDEX('データ'!E$692:E$754,$C13)),0) -> 0 | F13: =IFERROR(CHOOSE($A$3,INDEX('データ'!F$491:F$553,$C13),INDEX('データ'!F$558:F$620,$C13),INDEX('データ'!F$625:F$687,$C13),INDEX('データ'!F$692:F$754,$C13)),0) -> 0 | G13: =IFERROR(CHOOSE($A$3,INDEX('データ'!G$491:G$553,$C13),INDEX('データ'!G$558:G$620,$C13),INDEX('データ'!G$625:G$687,$C13),INDEX('データ'!G$692:G$754,$C13)),0) -> 10 | H13: =IFERROR(CHOOSE($A$3,INDEX('データ'!H$491:H$553,$C13),INDEX('データ'!H$558:H$620,$C13),INDEX('データ'!H$625:H$687,$C13),INDEX('データ'!H$692:H$754,$C13)),0) -> 83 | I13: =IFERROR(CHOOSE($A$3,INDEX('データ'!I$491:I$553,$C13),INDEX('データ'!I$558:I$620,$C13),INDEX('データ'!I$625:I$687,$C13),INDEX('データ'!I$692:I$754,$C13)),0) -> 189 | J13: =IFERROR(CHOOSE($A$3,INDEX('データ'!J$491:J$553,$C13),INDEX('データ'!J$558:J$620,$C13),INDEX('データ'!J$625:J$687,$C13),INDEX('データ'!J$692:J$754,$C13)),0) -> 218 | K13: =IFERROR(CHOOSE($A$3,INDEX('データ'!K$491:K$553,$C13),INDEX('データ'!K$558:K$620,$C13),INDEX('データ'!K$625:K$687,$C13),INDEX('データ'!K$692:K$754,$C13)),0) -> 190 | ... BG13: =IFERROR(CHOOSE($A$3,INDEX('データ'!BG$491:BG$553,$C13),INDEX('データ'!BG$558:BG$620,$C13),INDEX('データ'!BG$625:BG$687,$C13),INDEX('データ'!BG$692:BG$754,$C13)),0) -> 0
B15: 月×時間帯（選択した区）
D16: 7時 | H16: 8時 | L16: 9時 | P16: 10時 | T16: 11時 | X16: 12時 | AB16: 13時 | AF16: 14時 | AJ16: 15時 | AN16: 16時 | AR16: 17時 | AV16: 18時 | AZ16: 19時 | BD16: 20時
B17: 4月 | C17: =MATCH($C$3&"|"&$B17,'データ'!$A$7:$A$123,0) -> 2 | D17: =IFERROR(CHOOSE($A$3,INDEX('データ'!D$7:D$123,$C17),INDEX('データ'!D$128:D$244,$C17),INDEX('データ'!D$249:D$365,$C17),INDEX('データ'!D$370:D$486,$C17)),0) -> 0 | E17: =IFERROR(CHOOSE($A$3,INDEX('データ'!E$7:E$123,$C17),INDEX('データ'!E$128:E$244,$C17),INDEX('データ'!E$249:E$365,$C17),INDEX('データ'!E$370:E$486,$C17)),0) -> 0 | F17: =IFERROR(CHOOSE($A$3,INDEX('データ'!F$7:F$123,$C17),INDEX('データ'!F$128:F$244,$C17),INDEX('データ'!F$249:F$365,$C17),INDEX('データ'!F$370:F$486,$C17)),0) -> 0 | G17: =IFERROR(CHOOSE($A$3,INDEX('データ'!G$7:G$123,$C17),INDEX('データ'!G$128:G$244,$C17),INDEX('データ'!G$249:G$365,$C17),INDEX('データ'!G$370:G$486,$C17)),0) -> 23 | H17: =IFERROR(CHOOSE($A$3,INDEX('データ'!H$7:H$123,$C17),INDEX('データ'!H$128:H$244,$C17),INDEX('データ'!H$249:H$365,$C17),INDEX('データ'!H$370:H$486,$C17)),0) -> 186 | I17: =IFERROR(CHOOSE($A$3,INDEX('データ'!I$7:I$123,$C17),INDEX('データ'!I$128:I$244,$C17),INDEX('データ'!I$249:I$365,$C17),INDEX('データ'!I$370:I$486,$C17)),0) -> 801 | J17: =IFERROR(CHOOSE($A$3,INDEX('データ'!J$7:J$123,$C17),INDEX('データ'!J$128:J$244,$C17),INDEX('データ'!J$249:J$365,$C17),INDEX('データ'!J$370:J$486,$C17)),0) -> 1479 | K17: =IFERROR(CHOOSE($A$3,INDEX('データ'!K$7:K$123,$C17),INDEX('データ'!K$128:K$244,$C17),INDEX('データ'!K$249:K$365,$C17),INDEX('データ'!K$370:K$486,$C17)),0) -> 1695 | ... BG17: =IFERROR(CHOOSE($A$3,INDEX('データ'!BG$7:BG$123,$C17),INDEX('データ'!BG$128:BG$244,$C17),INDEX('データ'!BG$249:BG$365,$C17),INDEX('データ'!BG$370:BG$486,$C17)),0) -> 0
B18: 5月 | C18: =MATCH($C$3&"|"&$B18,'データ'!$A$7:$A$123,0) -> 3 | D18: =IFERROR(CHOOSE($A$3,INDEX('データ'!D$7:D$123,$C18),INDEX('データ'!D$128:D$244,$C18),INDEX('データ'!D$249:D$365,$C18),INDEX('データ'!D$370:D$486,$C18)),0) -> 0 | E18: =IFERROR(CHOOSE($A$3,INDEX('データ'!E$7:E$123,$C18),INDEX('データ'!E$128:E$244,$C18),INDEX('データ'!E$249:E$365,$C18),INDEX('データ'!E$370:E$486,$C18)),0) -> 0 | F18: =IFERROR(CHOOSE($A$3,INDEX('データ'!F$7:F$123,$C18),INDEX('データ'!F$128:F$244,$C18),INDEX('データ'!F$249:F$365,$C18),INDEX('データ'!F$370:F$486,$C18)),0) -> 2 | G18: =IFERROR(CHOOSE($A$3,INDEX('データ'!G$7:G$123,$C18),INDEX('データ'!G$128:G$244,$C18),INDEX('データ'!G$249:G$365,$C18),INDEX('データ'!G$370:G$486,$C18)),0) -> 18 | H18: =IFERROR(CHOOSE($A$3,INDEX('データ'!H$7:H$123,$C18),INDEX('データ'!H$128:H$244,$C18),INDEX('データ'!H$249:H$365,$C18),INDEX('データ'!H$370:H$486,$C18)),0) -> 169 | I18: =IFERROR(CHOOSE($A$3,INDEX('データ'!I$7:I$123,$C18),INDEX('データ'!I$128:I$244,$C18),INDEX('データ'!I$249:I$365,$C18),INDEX('データ'!I$370:I$486,$C18)),0) -> 645 | J18: =IFERROR(CHOOSE($A$3,INDEX('データ'!J$7:J$123,$C18),INDEX('データ'!J$128:J$244,$C18),INDEX('データ'!J$249:J$365,$C18),INDEX('データ'!J$370:J$486,$C18)),0) -> 1373 | K18: =IFERROR(CHOOSE($A$3,INDEX('データ'!K$7:K$123,$C18),INDEX('データ'!K$128:K$244,$C18),INDEX('データ'!K$249:K$365,$C18),INDEX('データ'!K$370:K$486,$C18)),0) -> 1502 | ... BG18: =IFERROR(CHOOSE($A$3,INDEX('データ'!BG$7:BG$123,$C18),INDEX('データ'!BG$128:BG$244,$C18),INDEX('データ'!BG$249:BG$365,$C18),INDEX('データ'!BG$370:BG$486,$C18)),0) -> 0
B19: 6月 | C19: =MATCH($C$3&"|"&$B19,'データ'!$A$7:$A$123,0) -> 4 | D19: =IFERROR(CHOOSE($A$3,INDEX('データ'!D$7:D$123,$C19),INDEX('データ'!D$128:D$244,$C19),INDEX('データ'!D$249:D$365,$C19),INDEX('データ'!D$370:D$486,$C19)),0) -> 0 | E19: =IFERROR(CHOOSE($A$3,INDEX('データ'!E$7:E$123,$C19),INDEX('データ'!E$128:E$244,$C19),INDEX('データ'!E$249:E$365,$C19),INDEX('データ'!E$370:E$486,$C19)),0) -> 0 | F19: =IFERROR(CHOOSE($A$3,INDEX('データ'!F$7:F$123,$C19),INDEX('データ'!F$128:F$244,$C19),INDEX('データ'!F$249:F$365,$C19),INDEX('データ'!F$370:F$486,$C19)),0) -> 1 | G19: =IFERROR(CHOOSE($A$3,INDEX('データ'!G$7:G$123,$C19),INDEX('データ'!G$128:G$244,$C19),INDEX('データ'!G$249:G$365,$C19),INDEX('データ'!G$370:G$486,$C19)),0) -> 14 | H19: =IFERROR(CHOOSE($A$3,INDEX('データ'!H$7:H$123,$C19),INDEX('データ'!H$128:H$244,$C19),INDEX('データ'!H$249:H$365,$C19),INDEX('データ'!H$370:H$486,$C19)),0) -> 150 | I19: =IFERROR(CHOOSE($A$3,INDEX('データ'!I$7:I$123,$C19),INDEX('データ'!I$128:I$244,$C19),INDEX('データ'!I$249:I$365,$C19),INDEX('データ'!I$370:I$486,$C19)),0) -> 591 | J19: =IFERROR(CHOOSE($A$3,INDEX('データ'!J$7:J$123,$C19),INDEX('データ'!J$128:J$244,$C19),INDEX('データ'!J$249:J$365,$C19),INDEX('データ'!J$370:J$486,$C19)),0) -> 1256 | K19: =IFERROR(CHOOSE($A$3,INDEX('データ'!K$7:K$123,$C19),INDEX('データ'!K$128:K$244,$C19),INDEX('データ'!K$249:K$365,$C19),INDEX('データ'!K$370:K$486,$C19)),0) -> 1482 | ... BG19: =IFERROR(CHOOSE($A$3,INDEX('データ'!BG$7:BG$123,$C19),INDEX('データ'!BG$128:BG$244,$C19),INDEX('データ'!BG$249:BG$365,$C19),INDEX('データ'!BG$370:BG$486,$C19)),0) -> 0
B20: 7月 | C20: =MATCH($C$3&"|"&$B20,'データ'!$A$7:$A$123,0) -> 5 | D20: =IFERROR(CHOOSE($A$3,INDEX('データ'!D$7:D$123,$C20),INDEX('データ'!D$128:D$244,$C20),INDEX('データ'!D$249:D$365,$C20),INDEX('データ'!D$370:D$486,$C20)),0) -> 0 | E20: =IFERROR(CHOOSE($A$3,INDEX('データ'!E$7:E$123,$C20),INDEX('データ'!E$128:E$244,$C20),INDEX('データ'!E$249:E$365,$C20),INDEX('データ'!E$370:E$486,$C20)),0) -> 0 | F20: =IFERROR(CHOOSE($A$3,INDEX('データ'!F$7:F$123,$C20),INDEX('データ'!F$128:F$244,$C20),INDEX('データ'!F$249:F$365,$C20),INDEX('データ'!F$370:F$486,$C20)),0) -> 0 | G20: =IFERROR(CHOOSE($A$3,INDEX('データ'!G$7:G$123,$C20),INDEX('データ'!G$128:G$244,$C20),INDEX('データ'!G$249:G$365,$C20),INDEX('データ'!G$370:G$486,$C20)),0) -> 38 | H20: =IFERROR(CHOOSE($A$3,INDEX('データ'!H$7:H$123,$C20),INDEX('データ'!H$128:H$244,$C20),INDEX('データ'!H$249:H$365,$C20),INDEX('データ'!H$370:H$486,$C20)),0) -> 217 | I20: =IFERROR(CHOOSE($A$3,INDEX('データ'!I$7:I$123,$C20),INDEX('データ'!I$128:I$244,$C20),INDEX('データ'!I$249:I$365,$C20),INDEX('データ'!I$370:I$486,$C20)),0) -> 766 | J20: =IFERROR(CHOOSE($A$3,INDEX('データ'!J$7:J$123,$C20),INDEX('データ'!J$128:J$244,$C20),INDEX('データ'!J$249:J$365,$C20),INDEX('データ'!J$370:J$486,$C20)),0) -> 1541 | K20: =IFERROR(CHOOSE($A$3,INDEX('データ'!K$7:K$123,$C20),INDEX('データ'!K$128:K$244,$C20),INDEX('データ'!K$249:K$365,$C20),INDEX('データ'!K$370:K$486,$C20)),0) -> 1666 | ... BG20: =IFERROR(CHOOSE($A$3,INDEX('データ'!BG$7:BG$123,$C20),INDEX('データ'!BG$128:BG$244,$C20),INDEX('データ'!BG$249:BG$365,$C20),INDEX('データ'!BG$370:BG$486,$C20)),0) -> 0
B21: 8月 | C21: =MATCH($C$3&"|"&$B21,'データ'!$A$7:$A$123,0) -> 6 | D21: =IFERROR(CHOOSE($A$3,INDEX('データ'!D$7:D$123,$C21),INDEX('データ'!D$128:D$244,$C21),INDEX('データ'!D$249:D$365,$C21),INDEX('データ'!D$370:D$486,$C21)),0) -> 0 | E21: =IFERROR(CHOOSE($A$3,INDEX('データ'!E$7:E$123,$C21),INDEX('データ'!E$128:E$244,$C21),INDEX('データ'!E$249:E$365,$C21),INDEX('データ'!E$370:E$486,$C21)),0) -> 0 | F21: =IFERROR(CHOOSE($A$3,INDEX('データ'!F$7:F$123,$C21),INDEX('データ'!F$128:F$244,$C21),INDEX('データ'!F$249:F$365,$C21),INDEX('データ'!F$370:F$486,$C21)),0) -> 0 | G21: =IFERROR(CHOOSE($A$3,INDEX('データ'!G$7:G$123,$C21),INDEX('データ'!G$128:G$244,$C21),INDEX('データ'!G$249:G$365,$C21),INDEX('データ'!G$370:G$486,$C21)),0) -> 25 | H21: =IFERROR(CHOOSE($A$3,INDEX('データ'!H$7:H$123,$C21),INDEX('データ'!H$128:H$244,$C21),INDEX('データ'!H$249:H$365,$C21),INDEX('データ'!H$370:H$486,$C21)),0) -> 187 | I21: =IFERROR(CHOOSE($A$3,INDEX('データ'!I$7:I$123,$C21),INDEX('データ'!I$128:I$244,$C21),INDEX('データ'!I$249:I$365,$C21),INDEX('データ'!I$370:I$486,$C21)),0) -> 610 | J21: =IFERROR(CHOOSE($A$3,INDEX('データ'!J$7:J$123,$C21),INDEX('データ'!J$128:J$244,$C21),INDEX('データ'!J$249:J$365,$C21),INDEX('データ'!J$370:J$486,$C21)),0) -> 1303 | K21: =IFERROR(CHOOSE($A$3,INDEX('データ'!K$7:K$123,$C21),INDEX('データ'!K$128:K$244,$C21),INDEX('データ'!K$249:K$365,$C21),INDEX('データ'!K$370:K$486,$C21)),0) -> 1462 | ... BG21: =IFERROR(CHOOSE($A$3,INDEX('データ'!BG$7:BG$123,$C21),INDEX('データ'!BG$128:BG$244,$C21),INDEX('データ'!BG$249:BG$365,$C21),INDEX('データ'!BG$370:BG$486,$C21)),0) -> 0
B22: 9月 | C22: =MATCH($C$3&"|"&$B22,'データ'!$A$7:$A$123,0) -> 7 | D22: =IFERROR(CHOOSE($A$3,INDEX('データ'!D$7:D$123,$C22),INDEX('データ'!D$128:D$244,$C22),INDEX('データ'!D$249:D$365,$C22),INDEX('データ'!D$370:D$486,$C22)),0) -> 0 | E22: =IFERROR(CHOOSE($A$3,INDEX('データ'!E$7:E$123,$C22),INDEX('データ'!E$128:E$244,$C22),INDEX('データ'!E$249:E$365,$C22),INDEX('データ'!E$370:E$486,$C22)),0) -> 0 | F22: =IFERROR(CHOOSE($A$3,INDEX('データ'!F$7:F$123,$C22),INDEX('データ'!F$128:F$244,$C22),INDEX('データ'!F$249:F$365,$C22),INDEX('データ'!F$370:F$486,$C22)),0) -> 0 | G22: =IFERROR(CHOOSE($A$3,INDEX('データ'!G$7:G$123,$C22),INDEX('データ'!G$128:G$244,$C22),INDEX('データ'!G$249:G$365,$C22),INDEX('データ'!G$370:G$486,$C22)),0) -> 16 | H22: =IFERROR(CHOOSE($A$3,INDEX('データ'!H$7:H$123,$C22),INDEX('データ'!H$128:H$244,$C22),INDEX('データ'!H$249:H$365,$C22),INDEX('データ'!H$370:H$486,$C22)),0) -> 152 | I22: =IFERROR(CHOOSE($A$3,INDEX('データ'!I$7:I$123,$C22),INDEX('データ'!I$128:I$244,$C22),INDEX('データ'!I$249:I$365,$C22),INDEX('データ'!I$370:I$486,$C22)),0) -> 492 | J22: =IFERROR(CHOOSE($A$3,INDEX('データ'!J$7:J$123,$C22),INDEX('データ'!J$128:J$244,$C22),INDEX('データ'!J$249:J$365,$C22),INDEX('データ'!J$370:J$486,$C22)),0) -> 1121 | K22: =IFERROR(CHOOSE($A$3,INDEX('データ'!K$7:K$123,$C22),INDEX('データ'!K$128:K$244,$C22),INDEX('データ'!K$249:K$365,$C22),INDEX('データ'!K$370:K$486,$C22)),0) -> 1291 | ... BG22: =IFERROR(CHOOSE($A$3,INDEX('データ'!BG$7:BG$123,$C22),INDEX('データ'!BG$128:BG$244,$C22),INDEX('データ'!BG$249:BG$365,$C22),INDEX('データ'!BG$370:BG$486,$C22)),0) -> 0
B23: 10月 | C23: =MATCH($C$3&"|"&$B23,'データ'!$A$7:$A$123,0) -> 8 | D23: =IFERROR(CHOOSE($A$3,INDEX('データ'!D$7:D$123,$C23),INDEX('データ'!D$128:D$244,$C23),INDEX('データ'!D$249:D$365,$C23),INDEX('データ'!D$370:D$486,$C23)),0) -> 0 | E23: =IFERROR(CHOOSE($A$3,INDEX('データ'!E$7:E$123,$C23),INDEX('データ'!E$128:E$244,$C23),INDEX('データ'!E$249:E$365,$C23),INDEX('データ'!E$370:E$486,$C23)),0) -> 0 | F23: =IFERROR(CHOOSE($A$3,INDEX('データ'!F$7:F$123,$C23),INDEX('データ'!F$128:F$244,$C23),INDEX('データ'!F$249:F$365,$C23),INDEX('データ'!F$370:F$486,$C23)),0) -> 0 | G23: =IFERROR(CHOOSE($A$3,INDEX('データ'!G$7:G$123,$C23),INDEX('データ'!G$128:G$244,$C23),INDEX('データ'!G$249:G$365,$C23),INDEX('データ'!G$370:G$486,$C23)),0) -> 18 | H23: =IFERROR(CHOOSE($A$3,INDEX('データ'!H$7:H$123,$C23),INDEX('データ'!H$128:H$244,$C23),INDEX('データ'!H$249:H$365,$C23),INDEX('データ'!H$370:H$486,$C23)),0) -> 161 | I23: =IFERROR(CHOOSE($A$3,INDEX('データ'!I$7:I$123,$C23),INDEX('データ'!I$128:I$244,$C23),INDEX('データ'!I$249:I$365,$C23),INDEX('データ'!I$370:I$486,$C23)),0) -> 476 | J23: =IFERROR(CHOOSE($A$3,INDEX('データ'!J$7:J$123,$C23),INDEX('データ'!J$128:J$244,$C23),INDEX('データ'!J$249:J$365,$C23),INDEX('データ'!J$370:J$486,$C23)),0) -> 1189 | K23: =IFERROR(CHOOSE($A$3,INDEX('データ'!K$7:K$123,$C23),INDEX('データ'!K$128:K$244,$C23),INDEX('データ'!K$249:K$365,$C23),INDEX('データ'!K$370:K$486,$C23)),0) -> 1400 | ... BG23: =IFERROR(CHOOSE($A$3,INDEX('データ'!BG$7:BG$123,$C23),INDEX('データ'!BG$128:BG$244,$C23),INDEX('データ'!BG$249:BG$365,$C23),INDEX('データ'!BG$370:BG$486,$C23)),0) -> 0
B24: 11月 | C24: =MATCH($C$3&"|"&$B24,'データ'!$A$7:$A$123,0) -> 9 | D24: =IFERROR(CHOOSE($A$3,INDEX('データ'!D$7:D$123,$C24),INDEX('データ'!D$128:D$244,$C24),INDEX('データ'!D$249:D$365,$C24),INDEX('データ'!D$370:D$486,$C24)),0) -> 0 | E24: =IFERROR(CHOOSE($A$3,INDEX('データ'!E$7:E$123,$C24),INDEX('データ'!E$128:E$244,$C24),INDEX('データ'!E$249:E$365,$C24),INDEX('データ'!E$370:E$486,$C24)),0) -> 0 | F24: =IFERROR(CHOOSE($A$3,INDEX('データ'!F$7:F$123,$C24),INDEX('データ'!F$128:F$244,$C24),INDEX('データ'!F$249:F$365,$C24),INDEX('データ'!F$370:F$486,$C24)),0) -> 0 | G24: =IFERROR(CHOOSE($A$3,INDEX('データ'!G$7:G$123,$C24),INDEX('データ'!G$128:G$244,$C24),INDEX('データ'!G$249:G$365,$C24),INDEX('データ'!G$370:G$486,$C24)),0) -> 22 | H24: =IFERROR(CHOOSE($A$3,INDEX('データ'!H$7:H$123,$C24),INDEX('データ'!H$128:H$244,$C24),INDEX('データ'!H$249:H$365,$C24),INDEX('データ'!H$370:H$486,$C24)),0) -> 115 | I24: =IFERROR(CHOOSE($A$3,INDEX('データ'!I$7:I$123,$C24),INDEX('データ'!I$128:I$244,$C24),INDEX('データ'!I$249:I$365,$C24),INDEX('データ'!I$370:I$486,$C24)),0) -> 341 | J24: =IFERROR(CHOOSE($A$3,INDEX('データ'!J$7:J$123,$C24),INDEX('データ'!J$128:J$244,$C24),INDEX('データ'!J$249:J$365,$C24),INDEX('データ'!J$370:J$486,$C24)),0) -> 793 | K24: =IFERROR(CHOOSE($A$3,INDEX('データ'!K$7:K$123,$C24),INDEX('データ'!K$128:K$244,$C24),INDEX('データ'!K$249:K$365,$C24),INDEX('データ'!K$370:K$486,$C24)),0) -> 934 | ... BG24: =IFERROR(CHOOSE($A$3,INDEX('データ'!BG$7:BG$123,$C24),INDEX('データ'!BG$128:BG$244,$C24),INDEX('データ'!BG$249:BG$365,$C24),INDEX('データ'!BG$370:BG$486,$C24)),0) -> 0
B25: 12月 | C25: =MATCH($C$3&"|"&$B25,'データ'!$A$7:$A$123,0) -> 10 | D25: =IFERROR(CHOOSE($A$3,INDEX('データ'!D$7:D$123,$C25),INDEX('データ'!D$128:D$244,$C25),INDEX('データ'!D$249:D$365,$C25),INDEX('データ'!D$370:D$486,$C25)),0) -> 0 | E25: =IFERROR(CHOOSE($A$3,INDEX('データ'!E$7:E$123,$C25),INDEX('データ'!E$128:E$244,$C25),INDEX('データ'!E$249:E$365,$C25),INDEX('データ'!E$370:E$486,$C25)),0) -> 0 | F25: =IFERROR(CHOOSE($A$3,INDEX('データ'!F$7:F$123,$C25),INDEX('データ'!F$128:F$244,$C25),INDEX('データ'!F$249:F$365,$C25),INDEX('データ'!F$370:F$486,$C25)),0) -> 0 | G25: =IFERROR(CHOOSE($A$3,INDEX('データ'!G$7:G$123,$C25),INDEX('データ'!G$128:G$244,$C25),INDEX('データ'!G$249:G$365,$C25),INDEX('データ'!G$370:G$486,$C25)),0) -> 2 | H25: =IFERROR(CHOOSE($A$3,INDEX('データ'!H$7:H$123,$C25),INDEX('データ'!H$128:H$244,$C25),INDEX('データ'!H$249:H$365,$C25),INDEX('データ'!H$370:H$486,$C25)),0) -> 43 | I25: =IFERROR(CHOOSE($A$3,INDEX('データ'!I$7:I$123,$C25),INDEX('データ'!I$128:I$244,$C25),INDEX('データ'!I$249:I$365,$C25),INDEX('データ'!I$370:I$486,$C25)),0) -> 366 | J25: =IFERROR(CHOOSE($A$3,INDEX('データ'!J$7:J$123,$C25),INDEX('データ'!J$128:J$244,$C25),INDEX('データ'!J$249:J$365,$C25),INDEX('データ'!J$370:J$486,$C25)),0) -> 1021 | K25: =IFERROR(CHOOSE($A$3,INDEX('データ'!K$7:K$123,$C25),INDEX('データ'!K$128:K$244,$C25),INDEX('データ'!K$249:K$365,$C25),INDEX('データ'!K$370:K$486,$C25)),0) -> 1014 | ... BG25: =IFERROR(CHOOSE($A$3,INDEX('データ'!BG$7:BG$123,$C25),INDEX('データ'!BG$128:BG$244,$C25),INDEX('データ'!BG$249:BG$365,$C25),INDEX('データ'!BG$370:BG$486,$C25)),0) -> 0
B26: 1月 | C26: =MATCH($C$3&"|"&$B26,'データ'!$A$7:$A$123,0) -> 11 | D26: =IFERROR(CHOOSE($A$3,INDEX('データ'!D$7:D$123,$C26),INDEX('データ'!D$128:D$244,$C26),INDEX('データ'!D$249:D$365,$C26),INDEX('データ'!D$370:D$486,$C26)),0) -> 0 | E26: =IFERROR(CHOOSE($A$3,INDEX('データ'!E$7:E$123,$C26),INDEX('データ'!E$128:E$244,$C26),INDEX('データ'!E$249:E$365,$C26),INDEX('データ'!E$370:E$486,$C26)),0) -> 0 | F26: =IFERROR(CHOOSE($A$3,INDEX('データ'!F$7:F$123,$C26),INDEX('データ'!F$128:F$244,$C26),INDEX('データ'!F$249:F$365,$C26),INDEX('データ'!F$370:F$486,$C26)),0) -> 0 | G26: =IFERROR(CHOOSE($A$3,INDEX('データ'!G$7:G$123,$C26),INDEX('データ'!G$128:G$244,$C26),INDEX('データ'!G$249:G$365,$C26),INDEX('データ'!G$370:G$486,$C26)),0) -> 3 | H26: =IFERROR(CHOOSE($A$3,INDEX('データ'!H$7:H$123,$C26),INDEX('データ'!H$128:H$244,$C26),INDEX('データ'!H$249:H$365,$C26),INDEX('データ'!H$370:H$486,$C26)),0) -> 46 | I26: =IFERROR(CHOOSE($A$3,INDEX('データ'!I$7:I$123,$C26),INDEX('データ'!I$128:I$244,$C26),INDEX('データ'!I$249:I$365,$C26),INDEX('データ'!I$370:I$486,$C26)),0) -> 406 | J26: =IFERROR(CHOOSE($A$3,INDEX('データ'!J$7:J$123,$C26),INDEX('データ'!J$128:J$244,$C26),INDEX('データ'!J$249:J$365,$C26),INDEX('データ'!J$370:J$486,$C26)),0) -> 930 | K26: =IFERROR(CHOOSE($A$3,INDEX('データ'!K$7:K$123,$C26),INDEX('データ'!K$128:K$244,$C26),INDEX('データ'!K$249:K$365,$C26),INDEX('データ'!K$370:K$486,$C26)),0) -> 878 | ... BG26: =IFERROR(CHOOSE($A$3,INDEX('データ'!BG$7:BG$123,$C26),INDEX('データ'!BG$128:BG$244,$C26),INDEX('データ'!BG$249:BG$365,$C26),INDEX('データ'!BG$370:BG$486,$C26)),0) -> 0
B27: 2月 | C27: =MATCH($C$3&"|"&$B27,'データ'!$A$7:$A$123,0) -> 12 | D27: =IFERROR(CHOOSE($A$3,INDEX('データ'!D$7:D$123,$C27),INDEX('データ'!D$128:D$244,$C27),INDEX('データ'!D$249:D$365,$C27),INDEX('データ'!D$370:D$486,$C27)),0) -> 0 | E27: =IFERROR(CHOOSE($A$3,INDEX('データ'!E$7:E$123,$C27),INDEX('データ'!E$128:E$244,$C27),INDEX('データ'!E$249:E$365,$C27),INDEX('データ'!E$370:E$486,$C27)),0) -> 0 | F27: =IFERROR(CHOOSE($A$3,INDEX('データ'!F$7:F$123,$C27),INDEX('データ'!F$128:F$244,$C27),INDEX('データ'!F$249:F$365,$C27),INDEX('データ'!F$370:F$486,$C27)),0) -> 0 | G27: =IFERROR(CHOOSE($A$3,INDEX('データ'!G$7:G$123,$C27),INDEX('データ'!G$128:G$244,$C27),INDEX('データ'!G$249:G$365,$C27),INDEX('データ'!G$370:G$486,$C27)),0) -> 1 | H27: =IFERROR(CHOOSE($A$3,INDEX('データ'!H$7:H$123,$C27),INDEX('データ'!H$128:H$244,$C27),INDEX('データ'!H$249:H$365,$C27),INDEX('データ'!H$370:H$486,$C27)),0) -> 52 | I27: =IFERROR(CHOOSE($A$3,INDEX('データ'!I$7:I$123,$C27),INDEX('データ'!I$128:I$244,$C27),INDEX('データ'!I$249:I$365,$C27),INDEX('データ'!I$370:I$486,$C27)),0) -> 510 | J27: =IFERROR(CHOOSE($A$3,INDEX('データ'!J$7:J$123,$C27),INDEX('データ'!J$128:J$244,$C27),INDEX('データ'!J$249:J$365,$C27),INDEX('データ'!J$370:J$486,$C27)),0) -> 1301 | K27: =IFERROR(CHOOSE($A$3,INDEX('データ'!K$7:K$123,$C27),INDEX('データ'!K$128:K$244,$C27),INDEX('データ'!K$249:K$365,$C27),INDEX('データ'!K$370:K$486,$C27)),0) -> 1250 | ... BG27: =IFERROR(CHOOSE($A$3,INDEX('データ'!BG$7:BG$123,$C27),INDEX('データ'!BG$128:BG$244,$C27),INDEX('データ'!BG$249:BG$365,$C27),INDEX('データ'!BG$370:BG$486,$C27)),0) -> 0
B28: 3月 | C28: =MATCH($C$3&"|"&$B28,'データ'!$A$7:$A$123,0) -> 13 | D28: =IFERROR(CHOOSE($A$3,INDEX('データ'!D$7:D$123,$C28),INDEX('データ'!D$128:D$244,$C28),INDEX('データ'!D$249:D$365,$C28),INDEX('データ'!D$370:D$486,$C28)),0) -> 0 | E28: =IFERROR(CHOOSE($A$3,INDEX('データ'!E$7:E$123,$C28),INDEX('データ'!E$128:E$244,$C28),INDEX('データ'!E$249:E$365,$C28),INDEX('データ'!E$370:E$486,$C28)),0) -> 0 | F28: =IFERROR(CHOOSE($A$3,INDEX('データ'!F$7:F$123,$C28),INDEX('データ'!F$128:F$244,$C28),INDEX('データ'!F$249:F$365,$C28),INDEX('データ'!F$370:F$486,$C28)),0) -> 0 | G28: =IFERROR(CHOOSE($A$3,INDEX('データ'!G$7:G$123,$C28),INDEX('データ'!G$128:G$244,$C28),INDEX('データ'!G$249:G$365,$C28),INDEX('データ'!G$370:G$486,$C28)),0) -> 3 | H28: =IFERROR(CHOOSE($A$3,INDEX('データ'!H$7:H$123,$C28),INDEX('データ'!H$128:H$244,$C28),INDEX('データ'!H$249:H$365,$C28),INDEX('データ'!H$370:H$486,$C28)),0) -> 132 | I28: =IFERROR(CHOOSE($A$3,INDEX('データ'!I$7:I$123,$C28),INDEX('データ'!I$128:I$244,$C28),INDEX('データ'!I$249:I$365,$C28),INDEX('データ'!I$370:I$486,$C28)),0) -> 981 | J28: =IFERROR(CHOOSE($A$3,INDEX('データ'!J$7:J$123,$C28),INDEX('データ'!J$128:J$244,$C28),INDEX('データ'!J$249:J$365,$C28),INDEX('データ'!J$370:J$486,$C28)),0) -> 2059 | K28: =IFERROR(CHOOSE($A$3,INDEX('データ'!K$7:K$123,$C28),INDEX('データ'!K$128:K$244,$C28),INDEX('データ'!K$249:K$365,$C28),INDEX('データ'!K$370:K$486,$C28)),0) -> 1853 | ... BG28: =IFERROR(CHOOSE($A$3,INDEX('データ'!BG$7:BG$123,$C28),INDEX('データ'!BG$128:BG$244,$C28),INDEX('データ'!BG$249:BG$365,$C28),INDEX('データ'!BG$370:BG$486,$C28)),0) -> 0
B30: 区別の時間帯分布（各区内で最大の時間帯を最も濃く表示）
B31: 区 | C31: 1年の形 | D31: 7時 | H31: 8時 | L31: 9時 | P31: 10時 | T31: 11時 | X31: 12時 | AB31: 13時 | AF31: 14時 | AJ31: 15時 | AN31: 16時 | AR31: 17時 | AV31: 18時 | AZ31: 19時 | BD31: 20時
B32: 中区 | D32: =IFERROR(CHOOSE($A$3,INDEX('データ'!D$7:D$123,$BI32),INDEX('データ'!D$128:D$244,$BI32),INDEX('データ'!D$249:D$365,$BI32),INDEX('データ'!D$370:D$486,$BI32)),0) -> 0 | E32: =IFERROR(CHOOSE($A$3,INDEX('データ'!E$7:E$123,$BI32),INDEX('データ'!E$128:E$244,$BI32),INDEX('データ'!E$249:E$365,$BI32),INDEX('データ'!E$370:E$486,$BI32)),0) -> 0 | F32: =IFERROR(CHOOSE($A$3,INDEX('データ'!F$7:F$123,$BI32),INDEX('データ'!F$128:F$244,$BI32),INDEX('データ'!F$249:F$365,$BI32),INDEX('データ'!F$370:F$486,$BI32)),0) -> 1 | G32: =IFERROR(CHOOSE($A$3,INDEX('データ'!G$7:G$123,$BI32),INDEX('データ'!G$128:G$244,$BI32),INDEX('データ'!G$249:G$365,$BI32),INDEX('データ'!G$370:G$486,$BI32)),0) -> 0 | H32: =IFERROR(CHOOSE($A$3,INDEX('データ'!H$7:H$123,$BI32),INDEX('データ'!H$128:H$244,$BI32),INDEX('データ'!H$249:H$365,$BI32),INDEX('データ'!H$370:H$486,$BI32)),0) -> 46 | I32: =IFERROR(CHOOSE($A$3,INDEX('データ'!I$7:I$123,$BI32),INDEX('データ'!I$128:I$244,$BI32),INDEX('データ'!I$249:I$365,$BI32),INDEX('データ'!I$370:I$486,$BI32)),0) -> 345 | J32: =IFERROR(CHOOSE($A$3,INDEX('データ'!J$7:J$123,$BI32),INDEX('データ'!J$128:J$244,$BI32),INDEX('データ'!J$249:J$365,$BI32),INDEX('データ'!J$370:J$486,$BI32)),0) -> 1064 | K32: =IFERROR(CHOOSE($A$3,INDEX('データ'!K$7:K$123,$BI32),INDEX('データ'!K$128:K$244,$BI32),INDEX('データ'!K$249:K$365,$BI32),INDEX('データ'!K$370:K$486,$BI32)),0) -> 2310 | ... BG32: =IFERROR(CHOOSE($A$3,INDEX('データ'!BG$7:BG$123,$BI32),INDEX('データ'!BG$128:BG$244,$BI32),INDEX('データ'!BG$249:BG$365,$BI32),INDEX('データ'!BG$370:BG$486,$BI32)),0) -> 0 | BI32: =MATCH($B32&"|全期間",'データ'!$A$7:$A$123,0) -> 14
B33: 東区 | D33: =IFERROR(CHOOSE($A$3,INDEX('データ'!D$7:D$123,$BI33),INDEX('データ'!D$128:D$244,$BI33),INDEX('データ'!D$249:D$365,$BI33),INDEX('データ'!D$370:D$486,$BI33)),0) -> 0 | E33: =IFERROR(CHOOSE($A$3,INDEX('データ'!E$7:E$123,$BI33),INDEX('データ'!E$128:E$244,$BI33),INDEX('データ'!E$249:E$365,$BI33),INDEX('データ'!E$370:E$486,$BI33)),0) -> 0 | F33: =IFERROR(CHOOSE($A$3,INDEX('データ'!F$7:F$123,$BI33),INDEX('データ'!F$128:F$244,$BI33),INDEX('データ'!F$249:F$365,$BI33),INDEX('データ'!F$370:F$486,$BI33)),0) -> 0 | G33: =IFERROR(CHOOSE($A$3,INDEX('データ'!G$7:G$123,$BI33),INDEX('データ'!G$128:G$244,$BI33),INDEX('データ'!G$249:G$365,$BI33),INDEX('データ'!G$370:G$486,$BI33)),0) -> 9 | H33: =IFERROR(CHOOSE($A$3,INDEX('データ'!H$7:H$123,$BI33),INDEX('データ'!H$128:H$244,$BI33),INDEX('データ'!H$249:H$365,$BI33),INDEX('データ'!H$370:H$486,$BI33)),0) -> 137 | I33: =IFERROR(CHOOSE($A$3,INDEX('データ'!I$7:I$123,$BI33),INDEX('データ'!I$128:I$244,$BI33),INDEX('データ'!I$249:I$365,$BI33),INDEX('データ'!I$370:I$486,$BI33)),0) -> 1027 | J33: =IFERROR(CHOOSE($A$3,INDEX('データ'!J$7:J$123,$BI33),INDEX('データ'!J$128:J$244,$BI33),INDEX('データ'!J$249:J$365,$BI33),INDEX('データ'!J$370:J$486,$BI33)),0) -> 1681 | K33: =IFERROR(CHOOSE($A$3,INDEX('データ'!K$7:K$123,$BI33),INDEX('データ'!K$128:K$244,$BI33),INDEX('データ'!K$249:K$365,$BI33),INDEX('データ'!K$370:K$486,$BI33)),0) -> 1814 | ... BG33: =IFERROR(CHOOSE($A$3,INDEX('データ'!BG$7:BG$123,$BI33),INDEX('データ'!BG$128:BG$244,$BI33),INDEX('データ'!BG$249:BG$365,$BI33),INDEX('データ'!BG$370:BG$486,$BI33)),0) -> 0 | BI33: =MATCH($B33&"|全期間",'データ'!$A$7:$A$123,0) -> 27
B34: 南区 | D34: =IFERROR(CHOOSE($A$3,INDEX('データ'!D$7:D$123,$BI34),INDEX('データ'!D$128:D$244,$BI34),INDEX('データ'!D$249:D$365,$BI34),INDEX('データ'!D$370:D$486,$BI34)),0) -> 0 | E34: =IFERROR(CHOOSE($A$3,INDEX('データ'!E$7:E$123,$BI34),INDEX('データ'!E$128:E$244,$BI34),INDEX('データ'!E$249:E$365,$BI34),INDEX('データ'!E$370:E$486,$BI34)),0) -> 0 | F34: =IFERROR(CHOOSE($A$3,INDEX('データ'!F$7:F$123,$BI34),INDEX('データ'!F$128:F$244,$BI34),INDEX('データ'!F$249:F$365,$BI34),INDEX('データ'!F$370:F$486,$BI34)),0) -> 1 | G34: =IFERROR(CHOOSE($A$3,INDEX('データ'!G$7:G$123,$BI34),INDEX('データ'!G$128:G$244,$BI34),INDEX('データ'!G$249:G$365,$BI34),INDEX('データ'!G$370:G$486,$BI34)),0) -> 24 | H34: =IFERROR(CHOOSE($A$3,INDEX('データ'!H$7:H$123,$BI34),INDEX('データ'!H$128:H$244,$BI34),INDEX('データ'!H$249:H$365,$BI34),INDEX('データ'!H$370:H$486,$BI34)),0) -> 152 | I34: =IFERROR(CHOOSE($A$3,INDEX('データ'!I$7:I$123,$BI34),INDEX('データ'!I$128:I$244,$BI34),INDEX('データ'!I$249:I$365,$BI34),INDEX('データ'!I$370:I$486,$BI34)),0) -> 1466 | J34: =IFERROR(CHOOSE($A$3,INDEX('データ'!J$7:J$123,$BI34),INDEX('データ'!J$128:J$244,$BI34),INDEX('データ'!J$249:J$365,$BI34),INDEX('データ'!J$370:J$486,$BI34)),0) -> 3002 | K34: =IFERROR(CHOOSE($A$3,INDEX('データ'!K$7:K$123,$BI34),INDEX('データ'!K$128:K$244,$BI34),INDEX('データ'!K$249:K$365,$BI34),INDEX('データ'!K$370:K$486,$BI34)),0) -> 2851 | ... BG34: =IFERROR(CHOOSE($A$3,INDEX('データ'!BG$7:BG$123,$BI34),INDEX('データ'!BG$128:BG$244,$BI34),INDEX('データ'!BG$249:BG$365,$BI34),INDEX('データ'!BG$370:BG$486,$BI34)),0) -> 0 | BI34: =MATCH($B34&"|全期間",'データ'!$A$7:$A$123,0) -> 40
B35: 西区 | D35: =IFERROR(CHOOSE($A$3,INDEX('データ'!D$7:D$123,$BI35),INDEX('データ'!D$128:D$244,$BI35),INDEX('データ'!D$249:D$365,$BI35),INDEX('データ'!D$370:D$486,$BI35)),0) -> 0 | E35: =IFERROR(CHOOSE($A$3,INDEX('データ'!E$7:E$123,$BI35),INDEX('データ'!E$128:E$244,$BI35),INDEX('データ'!E$249:E$365,$BI35),INDEX('データ'!E$370:E$486,$BI35)),0) -> 0 | F35: =IFERROR(CHOOSE($A$3,INDEX('データ'!F$7:F$123,$BI35),INDEX('データ'!F$128:F$244,$BI35),INDEX('データ'!F$249:F$365,$BI35),INDEX('データ'!F$370:F$486,$BI35)),0) -> 0 | G35: =IFERROR(CHOOSE($A$3,INDEX('データ'!G$7:G$123,$BI35),INDEX('データ'!G$128:G$244,$BI35),INDEX('データ'!G$249:G$365,$BI35),INDEX('データ'!G$370:G$486,$BI35)),0) -> 3 | H35: =IFERROR(CHOOSE($A$3,INDEX('データ'!H$7:H$123,$BI35),INDEX('データ'!H$128:H$244,$BI35),INDEX('データ'!H$249:H$365,$BI35),INDEX('データ'!H$370:H$486,$BI35)),0) -> 48 | I35: =IFERROR(CHOOSE($A$3,INDEX('データ'!I$7:I$123,$BI35),INDEX('データ'!I$128:I$244,$BI35),INDEX('データ'!I$249:I$365,$BI35),INDEX('データ'!I$370:I$486,$BI35)),0) -> 1360 | J35: =IFERROR(CHOOSE($A$3,INDEX('データ'!J$7:J$123,$BI35),INDEX('データ'!J$128:J$244,$BI35),INDEX('データ'!J$249:J$365,$BI35),INDEX('データ'!J$370:J$486,$BI35)),0) -> 3832 | K35: =IFERROR(CHOOSE($A$3,INDEX('データ'!K$7:K$123,$BI35),INDEX('データ'!K$128:K$244,$BI35),INDEX('データ'!K$249:K$365,$BI35),INDEX('データ'!K$370:K$486,$BI35)),0) -> 3275 | ... BG35: =IFERROR(CHOOSE($A$3,INDEX('データ'!BG$7:BG$123,$BI35),INDEX('データ'!BG$128:BG$244,$BI35),INDEX('データ'!BG$249:BG$365,$BI35),INDEX('データ'!BG$370:BG$486,$BI35)),0) -> 0 | BI35: =MATCH($B35&"|全期間",'データ'!$A$7:$A$123,0) -> 53
B36: 安佐南区 | D36: =IFERROR(CHOOSE($A$3,INDEX('データ'!D$7:D$123,$BI36),INDEX('データ'!D$128:D$244,$BI36),INDEX('データ'!D$249:D$365,$BI36),INDEX('データ'!D$370:D$486,$BI36)),0) -> 0 | E36: =IFERROR(CHOOSE($A$3,INDEX('データ'!E$7:E$123,$BI36),INDEX('データ'!E$128:E$244,$BI36),INDEX('データ'!E$249:E$365,$BI36),INDEX('データ'!E$370:E$486,$BI36)),0) -> 0 | F36: =IFERROR(CHOOSE($A$3,INDEX('データ'!F$7:F$123,$BI36),INDEX('データ'!F$128:F$244,$BI36),INDEX('データ'!F$249:F$365,$BI36),INDEX('データ'!F$370:F$486,$BI36)),0) -> 1 | G36: =IFERROR(CHOOSE($A$3,INDEX('データ'!G$7:G$123,$BI36),INDEX('データ'!G$128:G$244,$BI36),INDEX('データ'!G$249:G$365,$BI36),INDEX('データ'!G$370:G$486,$BI36)),0) -> 144 | H36: =IFERROR(CHOOSE($A$3,INDEX('データ'!H$7:H$123,$BI36),INDEX('データ'!H$128:H$244,$BI36),INDEX('データ'!H$249:H$365,$BI36),INDEX('データ'!H$370:H$486,$BI36)),0) -> 1081 | I36: =IFERROR(CHOOSE($A$3,INDEX('データ'!I$7:I$123,$BI36),INDEX('データ'!I$128:I$244,$BI36),INDEX('データ'!I$249:I$365,$BI36),INDEX('データ'!I$370:I$486,$BI36)),0) -> 1719 | J36: =IFERROR(CHOOSE($A$3,INDEX('データ'!J$7:J$123,$BI36),INDEX('データ'!J$128:J$244,$BI36),INDEX('データ'!J$249:J$365,$BI36),INDEX('データ'!J$370:J$486,$BI36)),0) -> 2053 | K36: =IFERROR(CHOOSE($A$3,INDEX('データ'!K$7:K$123,$BI36),INDEX('データ'!K$128:K$244,$BI36),INDEX('データ'!K$249:K$365,$BI36),INDEX('データ'!K$370:K$486,$BI36)),0) -> 2257 | ... BG36: =IFERROR(CHOOSE($A$3,INDEX('データ'!BG$7:BG$123,$BI36),INDEX('データ'!BG$128:BG$244,$BI36),INDEX('データ'!BG$249:BG$365,$BI36),INDEX('データ'!BG$370:BG$486,$BI36)),0) -> 0 | BI36: =MATCH($B36&"|全期間",'データ'!$A$7:$A$123,0) -> 66
B37: 安佐北区 | D37: =IFERROR(CHOOSE($A$3,INDEX('データ'!D$7:D$123,$BI37),INDEX('データ'!D$128:D$244,$BI37),INDEX('データ'!D$249:D$365,$BI37),INDEX('データ'!D$370:D$486,$BI37)),0) -> 0 | E37: =IFERROR(CHOOSE($A$3,INDEX('データ'!E$7:E$123,$BI37),INDEX('データ'!E$128:E$244,$BI37),INDEX('データ'!E$249:E$365,$BI37),INDEX('データ'!E$370:E$486,$BI37)),0) -> 0 | F37: =IFERROR(CHOOSE($A$3,INDEX('データ'!F$7:F$123,$BI37),INDEX('データ'!F$128:F$244,$BI37),INDEX('データ'!F$249:F$365,$BI37),INDEX('データ'!F$370:F$486,$BI37)),0) -> 0 | G37: =IFERROR(CHOOSE($A$3,INDEX('データ'!G$7:G$123,$BI37),INDEX('データ'!G$128:G$244,$BI37),INDEX('データ'!G$249:G$365,$BI37),INDEX('データ'!G$370:G$486,$BI37)),0) -> 1 | H37: =IFERROR(CHOOSE($A$3,INDEX('データ'!H$7:H$123,$BI37),INDEX('データ'!H$128:H$244,$BI37),INDEX('データ'!H$249:H$365,$BI37),INDEX('データ'!H$370:H$486,$BI37)),0) -> 12 | I37: =IFERROR(CHOOSE($A$3,INDEX('データ'!I$7:I$123,$BI37),INDEX('データ'!I$128:I$244,$BI37),INDEX('データ'!I$249:I$365,$BI37),INDEX('データ'!I$370:I$486,$BI37)),0) -> 133 | J37: =IFERROR(CHOOSE($A$3,INDEX('データ'!J$7:J$123,$BI37),INDEX('データ'!J$128:J$244,$BI37),INDEX('データ'!J$249:J$365,$BI37),INDEX('データ'!J$370:J$486,$BI37)),0) -> 810 | K37: =IFERROR(CHOOSE($A$3,INDEX('データ'!K$7:K$123,$BI37),INDEX('データ'!K$128:K$244,$BI37),INDEX('データ'!K$249:K$365,$BI37),INDEX('データ'!K$370:K$486,$BI37)),0) -> 1025 | ... BG37: =IFERROR(CHOOSE($A$3,INDEX('データ'!BG$7:BG$123,$BI37),INDEX('データ'!BG$128:BG$244,$BI37),INDEX('データ'!BG$249:BG$365,$BI37),INDEX('データ'!BG$370:BG$486,$BI37)),0) -> 0 | BI37: =MATCH($B37&"|全期間",'データ'!$A$7:$A$123,0) -> 79
B38: 安芸区 | D38: =IFERROR(CHOOSE($A$3,INDEX('データ'!D$7:D$123,$BI38),INDEX('データ'!D$128:D$244,$BI38),INDEX('データ'!D$249:D$365,$BI38),INDEX('データ'!D$370:D$486,$BI38)),0) -> 0 | E38: =IFERROR(CHOOSE($A$3,INDEX('データ'!E$7:E$123,$BI38),INDEX('データ'!E$128:E$244,$BI38),INDEX('データ'!E$249:E$365,$BI38),INDEX('データ'!E$370:E$486,$BI38)),0) -> 0 | F38: =IFERROR(CHOOSE($A$3,INDEX('データ'!F$7:F$123,$BI38),INDEX('データ'!F$128:F$244,$BI38),INDEX('データ'!F$249:F$365,$BI38),INDEX('データ'!F$370:F$486,$BI38)),0) -> 0 | G38: =IFERROR(CHOOSE($A$3,INDEX('データ'!G$7:G$123,$BI38),INDEX('データ'!G$128:G$244,$BI38),INDEX('データ'!G$249:G$365,$BI38),INDEX('データ'!G$370:G$486,$BI38)),0) -> 0 | H38: =IFERROR(CHOOSE($A$3,INDEX('データ'!H$7:H$123,$BI38),INDEX('データ'!H$128:H$244,$BI38),INDEX('データ'!H$249:H$365,$BI38),INDEX('データ'!H$370:H$486,$BI38)),0) -> 3 | I38: =IFERROR(CHOOSE($A$3,INDEX('データ'!I$7:I$123,$BI38),INDEX('データ'!I$128:I$244,$BI38),INDEX('データ'!I$249:I$365,$BI38),INDEX('データ'!I$370:I$486,$BI38)),0) -> 190 | J38: =IFERROR(CHOOSE($A$3,INDEX('データ'!J$7:J$123,$BI38),INDEX('データ'!J$128:J$244,$BI38),INDEX('データ'!J$249:J$365,$BI38),INDEX('データ'!J$370:J$486,$BI38)),0) -> 676 | K38: =IFERROR(CHOOSE($A$3,INDEX('データ'!K$7:K$123,$BI38),INDEX('データ'!K$128:K$244,$BI38),INDEX('データ'!K$249:K$365,$BI38),INDEX('データ'!K$370:K$486,$BI38)),0) -> 746 | ... BG38: =IFERROR(CHOOSE($A$3,INDEX('データ'!BG$7:BG$123,$BI38),INDEX('データ'!BG$128:BG$244,$BI38),INDEX('データ'!BG$249:BG$365,$BI38),INDEX('データ'!BG$370:BG$486,$BI38)),0) -> 0 | BI38: =MATCH($B38&"|全期間",'データ'!$A$7:$A$123,0) -> 92
B39: 佐伯区 | D39: =IFERROR(CHOOSE($A$3,INDEX('データ'!D$7:D$123,$BI39),INDEX('データ'!D$128:D$244,$BI39),INDEX('データ'!D$249:D$365,$BI39),INDEX('データ'!D$370:D$486,$BI39)),0) -> 0 | E39: =IFERROR(CHOOSE($A$3,INDEX('データ'!E$7:E$123,$BI39),INDEX('データ'!E$128:E$244,$BI39),INDEX('データ'!E$249:E$365,$BI39),INDEX('データ'!E$370:E$486,$BI39)),0) -> 0 | F39: =IFERROR(CHOOSE($A$3,INDEX('データ'!F$7:F$123,$BI39),INDEX('データ'!F$128:F$244,$BI39),INDEX('データ'!F$249:F$365,$BI39),INDEX('データ'!F$370:F$486,$BI39)),0) -> 0 | G39: =IFERROR(CHOOSE($A$3,INDEX('データ'!G$7:G$123,$BI39),INDEX('データ'!G$128:G$244,$BI39),INDEX('データ'!G$249:G$365,$BI39),INDEX('データ'!G$370:G$486,$BI39)),0) -> 2 | H39: =IFERROR(CHOOSE($A$3,INDEX('データ'!H$7:H$123,$BI39),INDEX('データ'!H$128:H$244,$BI39),INDEX('データ'!H$249:H$365,$BI39),INDEX('データ'!H$370:H$486,$BI39)),0) -> 131 | I39: =IFERROR(CHOOSE($A$3,INDEX('データ'!I$7:I$123,$BI39),INDEX('データ'!I$128:I$244,$BI39),INDEX('データ'!I$249:I$365,$BI39),INDEX('データ'!I$370:I$486,$BI39)),0) -> 745 | J39: =IFERROR(CHOOSE($A$3,INDEX('データ'!J$7:J$123,$BI39),INDEX('データ'!J$128:J$244,$BI39),INDEX('データ'!J$249:J$365,$BI39),INDEX('データ'!J$370:J$486,$BI39)),0) -> 2248 | K39: =IFERROR(CHOOSE($A$3,INDEX('データ'!K$7:K$123,$BI39),INDEX('データ'!K$128:K$244,$BI39),INDEX('データ'!K$249:K$365,$BI39),INDEX('データ'!K$370:K$486,$BI39)),0) -> 2149 | ... BG39: =IFERROR(CHOOSE($A$3,INDEX('データ'!BG$7:BG$123,$BI39),INDEX('データ'!BG$128:BG$244,$BI39),INDEX('データ'!BG$249:BG$365,$BI39),INDEX('データ'!BG$370:BG$486,$BI39)),0) -> 0 | BI39: =MATCH($B39&"|全期間",'データ'!$A$7:$A$123,0) -> 105
B41: 凡例 | O41: 小 ← → 大
B43: 注：平均待ち・対応・滞在は、15件未満の時間帯を0として表示。

Sheet カレンダー
B1: 日別来庁カレンダー
A2: =MATCH($C$3,'データ'!$B$879:$J$879,0) -> 1
A3: =MATCH($G$3,'計算'!$A$310:$A$312,0) -> 1 | B3: 区 | C3: 全区 | E3: 指標 | G3: 来庁者数 | K3: 注：全区は8区の合計。空白は休庁日または発券なし。
B5: 2025年4月 | J5: 2025年5月 | R5: 2025年6月 | Z5: 2025年7月
B6: 月 | C6: 火 | D6: 水 | E6: 木 | F6: 金 | G6: 土 | H6: 日 | J6: 月 | K6: 火 | L6: 水 | M6: 木 | N6: 金 | O6: 土 | P6: 日 | R6: 月 | S6: 火 | T6: 水 | U6: 木 | V6: 金 | W6: 土 | X6: 日 | Z6: 月 | AA6: 火 | AB6: 水 | AC6: 木 | AD6: 金 | AE6: 土 | AF6: 日
B7: =DATE(2025,4,1)-WEEKDAY(DATE(2025,4,1),2)+1 -> 45747 | C7: =DATE(2025,4,1)-WEEKDAY(DATE(2025,4,1),2)+2 -> 45748 | D7: =DATE(2025,4,1)-WEEKDAY(DATE(2025,4,1),2)+3 -> 45749 | E7: =DATE(2025,4,1)-WEEKDAY(DATE(2025,4,1),2)+4 -> 45750 | F7: =DATE(2025,4,1)-WEEKDAY(DATE(2025,4,1),2)+5 -> 45751 | G7: =DATE(2025,4,1)-WEEKDAY(DATE(2025,4,1),2)+6 -> 45752 | H7: =DATE(2025,4,1)-WEEKDAY(DATE(2025,4,1),2)+7 -> 45753 | J7: =DATE(2025,5,1)-WEEKDAY(DATE(2025,5,1),2)+1 -> 45775 | K7: =DATE(2025,5,1)-WEEKDAY(DATE(2025,5,1),2)+2 -> 45776 | L7: =DATE(2025,5,1)-WEEKDAY(DATE(2025,5,1),2)+3 -> 45777 | M7: =DATE(2025,5,1)-WEEKDAY(DATE(2025,5,1),2)+4 -> 45778 | N7: =DATE(2025,5,1)-WEEKDAY(DATE(2025,5,1),2)+5 -> 45779 | O7: =DATE(2025,5,1)-WEEKDAY(DATE(2025,5,1),2)+6 -> 45780 | P7: =DATE(2025,5,1)-WEEKDAY(DATE(2025,5,1),2)+7 -> 45781 | R7: =DATE(2025,6,1)-WEEKDAY(DATE(2025,6,1),2)+1 -> 45803 | S7: =DATE(2025,6,1)-WEEKDAY(DATE(2025,6,1),2)+2 -> 45804 | T7: =DATE(2025,6,1)-WEEKDAY(DATE(2025,6,1),2)+3 -> 45805 | U7: =DATE(2025,6,1)-WEEKDAY(DATE(2025,6,1),2)+4 -> 45806 | V7: =DATE(2025,6,1)-WEEKDAY(DATE(2025,6,1),2)+5 -> 45807 | W7: =DATE(2025,6,1)-WEEKDAY(DATE(2025,6,1),2)+6 -> 45808 | X7: =DATE(2025,6,1)-WEEKDAY(DATE(2025,6,1),2)+7 -> 45809 | Z7: =DATE(2025,7,1)-WEEKDAY(DATE(2025,7,1),2)+1 -> 45838 | AA7: =DATE(2025,7,1)-WEEKDAY(DATE(2025,7,1),2)+2 -> 45839 | AB7: =DATE(2025,7,1)-WEEKDAY(DATE(2025,7,1),2)+3 -> 45840 | AC7: =DATE(2025,7,1)-WEEKDAY(DATE(2025,7,1),2)+4 -> 45841 | AD7: =DATE(2025,7,1)-WEEKDAY(DATE(2025,7,1),2)+5 -> 45842 | AE7: =DATE(2025,7,1)-WEEKDAY(DATE(2025,7,1),2)+6 -> 45843 | AF7: =DATE(2025,7,1)-WEEKDAY(DATE(2025,7,1),2)+7 -> 45844
B8: =IF(MONTH(B7)=4,IF(IFERROR(CHOOSE($A$3,INDEX('データ'!$B$880:$J$1244,MATCH(B7,'データ'!$A$880:$A$1244,0),$A$2),INDEX('データ'!$L$880:$T$1244,MATCH(B7,'データ'!$A$880:$A$1244,0),$A$2),INDEX('データ'!$V$880:$AD$1244,MATCH(B7,'データ'!$A$880:$A$1244,0),$A$2)),0)=0,"",CHOOSE($A$3,INDEX('データ'!$B$880:$J$1244,MATCH(B7,'データ'!$A$880:$A$1244,0),$A$2),INDEX('データ'!$L$880:$T$1244,MATCH(B7,'データ'!$A$880:$A$1244,0),$A$2),INDEX('データ'!$V$880:$AD$1244,MATCH(B7,'データ'!$A$880:$A$1244,0),$A$2))),"") | C8: =IF(MONTH(C7)=4,IF(IFERROR(CHOOSE($A$3,INDEX('データ'!$B$880:$J$1244,MATCH(C7,'データ'!$A$880:$A$1244,0),$A$2),INDEX('データ'!$L$880:$T$1244,MATCH(C7,'データ'!$A$880:$A$1244,0),$A$2),INDEX('データ'!$V$880:$AD$1244,MATCH(C7,'データ'!$A$880:$A$1244,0),$A$2)),0)=0,"",CHOOSE($A$3,INDEX('データ'!$B$880:$J$1244,MATCH(C7,'データ'!$A$880:$A$1244,0),$A$2),INDEX('データ'!$L$880:$T$1244,MATCH(C7,'データ'!$A$880:$A$1244,0),$A$2),INDEX('データ'!$V$880:$AD$1244,MATCH(C7,'データ'!$A$880:$A$1244,0),$A$2))),"") -> 4032 | D8: =IF(MONTH(D7)=4,IF(IFERROR(CHOOSE($A$3,INDEX('データ'!$B$880:$J$1244,MATCH(D7,'データ'!$A$880:$A$1244,0),$A$2),INDEX('データ'!$L$880:$T$1244,MATCH(D7,'データ'!$A$880:$A$1244,0),$A$2),INDEX('データ'!$V$880:$AD$1244,MATCH(D7,'データ'!$A$880:$A$1244,0),$A$2)),0)=0,"",CHOOSE($A$3,INDEX('データ'!$B$880:$J$1244,MATCH(D7,'データ'!$A$880:$A$1244,0),$A$2),INDEX('データ'!$L$880:$T$1244,MATCH(D7,'データ'!$A$880:$A$1244,0),$A$2),INDEX('データ'!$V$880:$AD$1244,MATCH(D7,'データ'!$A$880:$A$1244,0),$A$2))),"") -> 3588 | E8: =IF(MONTH(E7)=4,IF(IFERROR(CHOOSE($A$3,INDEX('データ'!$B$880:$J$1244,MATCH(E7,'データ'!$A$880:$A$1244,0),$A$2),INDEX('データ'!$L$880:$T$1244,MATCH(E7,'データ'!$A$880:$A$1244,0),$A$2),INDEX('データ'!$V$880:$AD$1244,MATCH(E7,'データ'!$A$880:$A$1244,0),$A$2)),0)=0,"",CHOOSE($A$3,INDEX('データ'!$B$880:$J$1244,MATCH(E7,'データ'!$A$880:$A$1244,0),$A$2),INDEX('データ'!$L$880:$T$1244,MATCH(E7,'データ'!$A$880:$A$1244,0),$A$2),INDEX('データ'!$V$880:$AD$1244,MATCH(E7,'データ'!$A$880:$A$1244,0),$A$2))),"") -> 3560 | F8: =IF(MONTH(F7)=4,IF(IFERROR(CHOOSE($A$3,INDEX('データ'!$B$880:$J$1244,MATCH(F7,'データ'!$A$880:$A$1244,0),$A$2),INDEX('データ'!$L$880:$T$1244,MATCH(F7,'データ'!$A$880:$A$1244,0),$A$2),INDEX('データ'!$V$880:$AD$1244,MATCH(F7,'データ'!$A$880:$A$1244,0),$A$2)),0)=0,"",CHOOSE($A$3,INDEX('データ'!$B$880:$J$1244,MATCH(F7,'データ'!$A$880:$A$1244,0),$A$2),INDEX('データ'!$L$880:$T$1244,MATCH(F7,'データ'!$A$880:$A$1244,0),$A$2),INDEX('データ'!$V$880:$AD$1244,MATCH(F7,'データ'!$A$880:$A$1244,0),$A$2))),"") -> 3487 | G8: =IF(MONTH(G7)=4,IF(IFERROR(CHOOSE($A$3,INDEX('データ'!$B$880:$J$1244,MATCH(G7,'データ'!$A$880:$A$1244,0),$A$2),INDEX('データ'!$L$880:$T$1244,MATCH(G7,'データ'!$A$880:$A$1244,0),$A$2),INDEX('データ'!$V$880:$AD$1244,MATCH(G7,'データ'!$A$880:$A$1244,0),$A$2)),0)=0,"",CHOOSE($A$3,INDEX('データ'!$B$880:$J$1244,MATCH(G7,'データ'!$A$880:$A$1244,0),$A$2),INDEX('データ'!$L$880:$T$1244,MATCH(G7,'データ'!$A$880:$A$1244,0),$A$2),INDEX('データ'!$V$880:$AD$1244,MATCH(G7,'データ'!$A$880:$A$1244,0),$A$2))),"") | H8: =IF(MONTH(H7)=4,IF(IFERROR(CHOOSE($A$3,INDEX('データ'!$B$880:$J$1244,MATCH(H7,'データ'!$A$880:$A$1244,0),$A$2),INDEX('データ'!$L$880:$T$1244,MATCH(H7,'データ'!$A$880:$A$1244,0),$A$2),INDEX('データ'!$V$880:$AD$1244,MATCH(H7,'データ'!$A$880:$A$1244,0),$A$2)),0)=0,"",CHOOSE($A$3,INDEX('データ'!$B$880:$J$1244,MATCH(H7,'データ'!$A$880:$A$1244,0),$A$2),INDEX('データ'!$L$880:$T$1244,MATCH(H7,'データ'!$A$880:$A$1244,0),$A$2),INDEX('データ'!$V$880:$AD$1244,MATCH(H7,'データ'!$A$880:$A$1244,0),$A$2))),"") | J8: =IF(MONTH(J7)=5,IF(IFERROR(CHOOSE($A$3,INDEX('データ'!$B$880:$J$1244,MATCH(J7,'データ'!$A$880:$A$1244,0),$A$2),INDEX('データ'!$L$880:$T$1244,MATCH(J7,'データ'!$A$880:$A$1244,0),$A$2),INDEX('データ'!$V$880:$AD$1244,MATCH(J7,'データ'!$A$880:$A$1244,0),$A$2)),0)=0,"",CHOOSE($A$3,INDEX('データ'!$B$880:$J$1244,MATCH(J7,'データ'!$A$880:$A$1244,0),$A$2),INDEX('データ'!$L$880:$T$1244,MATCH(J7,'データ'!$A$880:$A$1244,0),$A$2),INDEX('データ'!$V$880:$AD$1244,MATCH(J7,'データ'!$A$880:$A$1244,0),$A$2))),"") | K8: =IF(MONTH(K7)=5,IF(IFERROR(CHOOSE($A$3,INDEX('データ'!$B$880:$J$1244,MATCH(K7,'データ'!$A$880:$A$1244,0),$A$2),INDEX('データ'!$L$880:$T$1244,MATCH(K7,'データ'!$A$880:$A$1244,0),$A$2),INDEX('データ'!$V$880:$AD$1244,MATCH(K7,'データ'!$A$880:$A$1244,0),$A$2)),0)=0,"",CHOOSE($A$3,INDEX('データ'!$B$880:$J$1244,MATCH(K7,'データ'!$A$880:$A$1244,0),$A$2),INDEX('データ'!$L$880:$T$1244,MATCH(K7,'データ'!$A$880:$A$1244,0),$A$2),INDEX('データ'!$V$880:$AD$1244,MATCH(K7,'データ'!$A$880:$A$1244,0),$A$2))),"") | L8: =IF(MONTH(L7)=5,IF(IFERROR(CHOOSE($A$3,INDEX('データ'!$B$880:$J$1244,MATCH(L7,'データ'!$A$880:$A$1244,0),$A$2),INDEX('データ'!$L$880:$T$1244,MATCH(L7,'データ'!$A$880:$A$1244,0),$A$2),INDEX('データ'!$V$880:$AD$1244,MATCH(L7,'データ'!$A$880:$A$1244,0),$A$2)),0)=0,"",CHOOSE($A$3,INDEX('データ'!$B$880:$J$1244,MATCH(L7,'データ'!$A$880:$A$1244,0),$A$2),INDEX('データ'!$L$880:$T$1244,MATCH(L7,'データ'!$A$880:$A$1244,0),$A$2),INDEX('データ'!$V$880:$AD$1244,MATCH(L7,'データ'!$A$880:$A$1244,0),$A$2))),"") | M8: =IF(MONTH(M7)=5,IF(IFERROR(CHOOSE($A$3,INDEX('データ'!$B$880:$J$1244,MATCH(M7,'データ'!$A$880:$A$1244,0),$A$2),INDEX('データ'!$L$880:$T$1244,MATCH(M7,'データ'!$A$880:$A$1244,0),$A$2),INDEX('データ'!$V$880:$AD$1244,MATCH(M7,'データ'!$A$880:$A$1244,0),$A$2)),0)=0,"",CHOOSE($A$3,INDEX('データ'!$B$880:$J$1244,MATCH(M7,'データ'!$A$880:$A$1244,0),$A$2),INDEX('データ'!$L$880:$T$1244,MATCH(M7,'データ'!$A$880:$A$1244,0),$A$2),INDEX('データ'!$V$880:$AD$1244,MATCH(M7,'データ'!$A$880:$A$1244,0),$A$2))),"") -> 3842 | N8: =IF(MONTH(N7)=5,IF(IFERROR(CHOOSE($A$3,INDEX('データ'!$B$880:$J$1244,MATCH(N7,'データ'!$A$880:$A$1244,0),$A$2),INDEX('データ'!$L$880:$T$1244,MATCH(N7,'データ'!$A$880:$A$1244,0),$A$2),INDEX('データ'!$V$880:$AD$1244,MATCH(N7,'データ'!$A$880:$A$1244,0),$A$2)),0)=0,"",CHOOSE($A$3,INDEX('データ'!$B$880:$J$1244,MATCH(N7,'データ'!$A$880:$A$1244,0),$A$2),INDEX('データ'!$L$880:$T$1244,MATCH(N7,'データ'!$A$880:$A$1244,0),$A$2),INDEX('データ'!$V$880:$AD$1244,MATCH(N7,'データ'!$A$880:$A$1244,0),$A$2))),"") -> 3546 | O8: =IF(MONTH(O7)=5,IF(IFERROR(CHOOSE($A$3,INDEX('データ'!$B$880:$J$1244,MATCH(O7,'データ'!$A$880:$A$1244,0),$A$2),INDEX('データ'!$L$880:$T$1244,MATCH(O7,'データ'!$A$880:$A$1244,0),$A$2),INDEX('データ'!$V$880:$AD$1244,MATCH(O7,'データ'!$A$880:$A$1244,0),$A$2)),0)=0,"",CHOOSE($A$3,INDEX('データ'!$B$880:$J$1244,MATCH(O7,'データ'!$A$880:$A$1244,0),$A$2),INDEX('データ'!$L$880:$T$1244,MATCH(O7,'データ'!$A$880:$A$1244,0),$A$2),INDEX('データ'!$V$880:$AD$1244,MATCH(O7,'データ'!$A$880:$A$1244,0),$A$2))),"") | P8: =IF(MONTH(P7)=5,IF(IFERROR(CHOOSE($A$3,INDEX('データ'!$B$880:$J$1244,MATCH(P7,'データ'!$A$880:$A$1244,0),$A$2),INDEX('データ'!$L$880:$T$1244,MATCH(P7,'データ'!$A$880:$A$1244,0),$A$2),INDEX('データ'!$V$880:$AD$1244,MATCH(P7,'データ'!$A$880:$A$1244,0),$A$2)),0)=0,"",CHOOSE($A$3,INDEX('データ'!$B$880:$J$1244,MATCH(P7,'データ'!$A$880:$A$1244,0),$A$2),INDEX('データ'!$L$880:$T$1244,MATCH(P7,'データ'!$A$880:$A$1244,0),$A$2),INDEX('データ'!$V$880:$AD$1244,MATCH(P7,'データ'!$A$880:$A$1244,0),$A$2))),"") | R8: =IF(MONTH(R7)=6,IF(IFERROR(CHOOSE($A$3,INDEX('データ'!$B$880:$J$1244,MATCH(R7,'データ'!$A$880:$A$1244,0),$A$2),INDEX('データ'!$L$880:$T$1244,MATCH(R7,'データ'!$A$880:$A$1244,0),$A$2),INDEX('データ'!$V$880:$AD$1244,MATCH(R7,'データ'!$A$880:$A$1244,0),$A$2)),0)=0,"",CHOOSE($A$3,INDEX('データ'!$B$880:$J$1244,MATCH(R7,'データ'!$A$880:$A$1244,0),$A$2),INDEX('データ'!$L$880:$T$1244,MATCH(R7,'データ'!$A$880:$A$1244,0),$A$2),INDEX('データ'!$V$880:$AD$1244,MATCH(R7,'データ'!$A$880:$A$1244,0),$A$2))),"") | S8: =IF(MONTH(S7)=6,IF(IFERROR(CHOOSE($A$3,INDEX('データ'!$B$880:$J$1244,MATCH(S7,'データ'!$A$880:$A$1244,0),$A$2),INDEX('データ'!$L$880:$T$1244,MATCH(S7,'データ'!$A$880:$A$1244,0),$A$2),INDEX('データ'!$V$880:$AD$1244,MATCH(S7,'データ'!$A$880:$A$1244,0),$A$2)),0)=0,"",CHOOSE($A$3,INDEX('データ'!$B$880:$J$1244,MATCH(S7,'データ'!$A$880:$A$1244,0),$A$2),INDEX('データ'!$L$880:$T$1244,MATCH(S7,'データ'!$A$880:$A$1244,0),$A$2),INDEX('データ'!$V$880:$AD$1244,MATCH(S7,'データ'!$A$880:$A$1244,0),$A$2))),"") | T8: =IF(MONTH(T7)=6,IF(IFERROR(CHOOSE($A$3,INDEX('データ'!$B$880:$J$1244,MATCH(T7,'データ'!$A$880:$A$1244,0),$A$2),INDEX('データ'!$L$880:$T$1244,MATCH(T7,'データ'!$A$880:$A$1244,0),$A$2),INDEX('データ'!$V$880:$AD$1244,MATCH(T7,'データ'!$A$880:$A$1244,0),$A$2)),0)=0,"",CHOOSE($A$3,INDEX('データ'!$B$880:$J$1244,MATCH(T7,'データ'!$A$880:$A$1244,0),$A$2),INDEX('データ'!$L$880:$T$1244,MATCH(T7,'データ'!$A$880:$A$1244,0),$A$2),INDEX('データ'!$V$880:$AD$1244,MATCH(T7,'データ'!$A$880:$A$1244,0),$A$2))),"") | U8: =IF(MONTH(U7)=6,IF(IFERROR(CHOOSE($A$3,INDEX('データ'!$B$880:$J$1244,MATCH(U7,'データ'!$A$880:$A$1244,0),$A$2),INDEX('データ'!$L$880:$T$1244,MATCH(U7,'データ'!$A$880:$A$1244,0),$A$2),INDEX('データ'!$V$880:$AD$1244,MATCH(U7,'データ'!$A$880:$A$1244,0),$A$2)),0)=0,"",CHOOSE($A$3,INDEX('データ'!$B$880:$J$1244,MATCH(U7,'データ'!$A$880:$A$1244,0),$A$2),INDEX('データ'!$L$880:$T$1244,MATCH(U7,'データ'!$A$880:$A$1244,0),$A$2),INDEX('データ'!$V$880:$AD$1244,MATCH(U7,'データ'!$A$880:$A$1244,0),$A$2))),"") | V8: =IF(MONTH(V7)=6,IF(IFERROR(CHOOSE($A$3,INDEX('データ'!$B$880:$J$1244,MATCH(V7,'データ'!$A$880:$A$1244,0),$A$2),INDEX('データ'!$L$880:$T$1244,MATCH(V7,'データ'!$A$880:$A$1244,0),$A$2),INDEX('データ'!$V$880:$AD$1244,MATCH(V7,'データ'!$A$880:$A$1244,0),$A$2)),0)=0,"",CHOOSE($A$3,INDEX('データ'!$B$880:$J$1244,MATCH(V7,'データ'!$A$880:$A$1244,0),$A$2),INDEX('データ'!$L$880:$T$1244,MATCH(V7,'データ'!$A$880:$A$1244,0),$A$2),INDEX('データ'!$V$880:$AD$1244,MATCH(V7,'データ'!$A$880:$A$1244,0),$A$2))),"") | W8: =IF(MONTH(W7)=6,IF(IFERROR(CHOOSE($A$3,INDEX('データ'!$B$880:$J$1244,MATCH(W7,'データ'!$A$880:$A$1244,0),$A$2),INDEX('データ'!$L$880:$T$1244,MATCH(W7,'データ'!$A$880:$A$1244,0),$A$2),INDEX('データ'!$V$880:$AD$1244,MATCH(W7,'データ'!$A$880:$A$1244,0),$A$2)),0)=0,"",CHOOSE($A$3,INDEX('データ'!$B$880:$J$1244,MATCH(W7,'データ'!$A$880:$A$1244,0),$A$2),INDEX('データ'!$L$880:$T$1244,MATCH(W7,'データ'!$A$880:$A$1244,0),$A$2),INDEX('データ'!$V$880:$AD$1244,MATCH(W7,'データ'!$A$880:$A$1244,0),$A$2))),"") | X8: =IF(MONTH(X7)=6,IF(IFERROR(CHOOSE($A$3,INDEX('データ'!$B$880:$J$1244,MATCH(X7,'データ'!$A$880:$A$1244,0),$A$2),INDEX('データ'!$L$880:$T$1244,MATCH(X7,'データ'!$A$880:$A$1244,0),$A$2),INDEX('データ'!$V$880:$AD$1244,MATCH(X7,'データ'!$A$880:$A$1244,0),$A$2)),0)=0,"",CHOOSE($A$3,INDEX('データ'!$B$880:$J$1244,MATCH(X7,'データ'!$A$880:$A$1244,0),$A$2),INDEX('データ'!$L$880:$T$1244,MATCH(X7,'データ'!$A$880:$A$1244,0),$A$2),INDEX('データ'!$V$880:$AD$1244,MATCH(X7,'データ'!$A$880:$A$1244,0),$A$2))),"") | Z8: =IF(MONTH(Z7)=7,IF(IFERROR(CHOOSE($A$3,INDEX('データ'!$B$880:$J$1244,MATCH(Z7,'データ'!$A$880:$A$1244,0),$A$2),INDEX('データ'!$L$880:$T$1244,MATCH(Z7,'データ'!$A$880:$A$1244,0),$A$2),INDEX('データ'!$V$880:$AD$1244,MATCH(Z7,'データ'!$A$880:$A$1244,0),$A$2)),0)=0,"",CHOOSE($A$3,INDEX('データ'!$B$880:$J$1244,MATCH(Z7,'データ'!$A$880:$A$1244,0),$A$2),INDEX('データ'!$L$880:$T$1244,MATCH(Z7,'データ'!$A$880:$A$1244,0),$A$2),INDEX('データ'!$V$880:$AD$1244,MATCH(Z7,'データ'!$A$880:$A$1244,0),$A$2))),"") | AA8: =IF(MONTH(AA7)=7,IF(IFERROR(CHOOSE($A$3,INDEX('データ'!$B$880:$J$1244,MATCH(AA7,'データ'!$A$880:$A$1244,0),$A$2),INDEX('データ'!$L$880:$T$1244,MATCH(AA7,'データ'!$A$880:$A$1244,0),$A$2),INDEX('データ'!$V$880:$AD$1244,MATCH(AA7,'データ'!$A$880:$A$1244,0),$A$2)),0)=0,"",CHOOSE($A$3,INDEX('データ'!$B$880:$J$1244,MATCH(AA7,'データ'!$A$880:$A$1244,0),$A$2),INDEX('データ'!$L$880:$T$1244,MATCH(AA7,'データ'!$A$880:$A$1244,0),$A$2),INDEX('データ'!$V$880:$AD$1244,MATCH(AA7,'データ'!$A$880:$A$1244,0),$A$2))),"") -> 3024 | AB8: =IF(MONTH(AB7)=7,IF(IFERROR(CHOOSE($A$3,INDEX('データ'!$B$880:$J$1244,MATCH(AB7,'データ'!$A$880:$A$1244,0),$A$2),INDEX('データ'!$L$880:$T$1244,MATCH(AB7,'データ'!$A$880:$A$1244,0),$A$2),INDEX('データ'!$V$880:$AD$1244,MATCH(AB7,'データ'!$A$880:$A$1244,0),$A$2)),0)=0,"",CHOOSE($A$3,INDEX('データ'!$B$880:$J$1244,MATCH(AB7,'データ'!$A$880:$A$1244,0),$A$2),INDEX('データ'!$L$880:$T$1244,MATCH(AB7,'データ'!$A$880:$A$1244,0),$A$2),INDEX('データ'!$V$880:$AD$1244,MATCH(AB7,'データ'!$A$880:$A$1244,0),$A$2))),"") -> 2912 | AC8: =IF(MONTH(AC7)=7,IF(IFERROR(CHOOSE($A$3,INDEX('データ'!$B$880:$J$1244,MATCH(AC7,'データ'!$A$880:$A$1244,0),$A$2),INDEX('データ'!$L$880:$T$1244,MATCH(AC7,'データ'!$A$880:$A$1244,0),$A$2),INDEX('データ'!$V$880:$AD$1244,MATCH(AC7,'データ'!$A$880:$A$1244,0),$A$2)),0)=0,"",CHOOSE($A$3,INDEX('データ'!$B$880:$J$1244,MATCH(AC7,'データ'!$A$880:$A$1244,0),$A$2),INDEX('データ'!$L$880:$T$1244,MATCH(AC7,'データ'!$A$880:$A$1244,0),$A$2),INDEX('データ'!$V$880:$AD$1244,MATCH(AC7,'データ'!$A$880:$A$1244,0),$A$2))),"") -> 2856 | AD8: =IF(MONTH(AD7)=7,IF(IFERROR(CHOOSE($A$3,INDEX('データ'!$B$880:$J$1244,MATCH(AD7,'データ'!$A$880:$A$1244,0),$A$2),INDEX('データ'!$L$880:$T$1244,MATCH(AD7,'データ'!$A$880:$A$1244,0),$A$2),INDEX('データ'!$V$880:$AD$1244,MATCH(AD7,'データ'!$A$880:$A$1244,0),$A$2)),0)=0,"",CHOOSE($A$3,INDEX('データ'!$B$880:$J$1244,MATCH(AD7,'データ'!$A$880:$A$1244,0),$A$2),INDEX('データ'!$L$880:$T$1244,MATCH(AD7,'データ'!$A$880:$A$1244,0),$A$2),INDEX('データ'!$V$880:$AD$1244,MATCH(AD7,'データ'!$A$880:$A$1244,0),$A$2))),"") -> 3048 | AE8: =IF(MONTH(AE7)=7,IF(IFERROR(CHOOSE($A$3,INDEX('データ'!$B$880:$J$1244,MATCH(AE7,'データ'!$A$880:$A$1244,0),$A$2),INDEX('データ'!$L$880:$T$1244,MATCH(AE7,'データ'!$A$880:$A$1244,0),$A$2),INDEX('データ'!$V$880:$AD$1244,MATCH(AE7,'データ'!$A$880:$A$1244,0),$A$2)),0)=0,"",CHOOSE($A$3,INDEX('データ'!$B$880:$J$1244,MATCH(AE7,'データ'!$A$880:$A$1244,0),$A$2),INDEX('データ'!$L$880:$T$1244,MATCH(AE7,'データ'!$A$880:$A$1244,0),$A$2),INDEX('データ'!$V$880:$AD$1244,MATCH(AE7,'データ'!$A$880:$A$1244,0),$A$2))),"") | AF8: =IF(MONTH(AF7)=7,IF(IFERROR(CHOOSE($A$3,INDEX('データ'!$B$880:$J$1244,MATCH(AF7,'データ'!$A$880:$A$1244,0),$A$2),INDEX('データ'!$L$880:$T$1244,MATCH(AF7,'データ'!$A$880:$A$1244,0),$A$2),INDEX('データ'!$V$880:$AD$1244,MATCH(AF7,'データ'!$A$880:$A$1244,0),$A$2)),0)=0,"",CHOOSE($A$3,INDEX('データ'!$B$880:$J$1244,MATCH(AF7,'データ'!$A$880:$A$1244,0),$A$2),INDEX('データ'!$L$880:$T$1244,MATCH(AF7,'データ'!$A$880:$A$1244,0),$A$2),INDEX('データ'!$V$880:$AD$1244,MATCH(AF7,'データ'!$A$880:$A$1244,0),$A$2))),"")
B9: =DATE(2025,4,1)-WEEKDAY(DATE(2025,4,1),2)+8 -> 45754 | C9: =DATE(2025,4,1)-WEEKDAY(DATE(2025,4,1),2)+9 -> 45755 | D9: =DATE(2025,4,1)-WEEKDAY(DATE(2025,4,1),2)+10 -> 45756 | E9: =DATE(2025,4,1)-WEEKDAY(DATE(2025,4,1),2)+11 -> 45757 | F9: =DATE(2025,4,1)-WEEKDAY(DATE(2025,4,1),2)+12 -> 45758 | G9: =DATE(2025,4,1)-WEEKDAY(DATE(2025,4,1),2)+13 -> 45759 | H9: =DATE(2025,4,1)-WEEKDAY(DATE(2025,4,1),2)+14 -> 45760 | J9: =DATE(2025,5,1)-WEEKDAY(DATE(2025,5,1),2)+8 -> 45782 | K9: =DATE(2025,5,1)-WEEKDAY(DATE(2025,5,1),2)+9 -> 45783 | L9: =DATE(2025,5,1)-WEEKDAY(DATE(2025,5,1),2)+10 -> 45784 | M9: =DATE(2025,5,1)-WEEKDAY(DATE(2025,5,1),2)+11 -> 45785 | N9: =DATE(2025,5,1)-WEEKDAY(DATE(2025,5,1),2)+12 -> 45786 | O9: =DATE(2025,5,1)-WEEKDAY(DATE(2025,5,1),2)+13 -> 45787 | P9: =DATE(2025,5,1)-WEEKDAY(DATE(2025,5,1),2)+14 -> 45788 | R9: =DATE(2025,6,1)-WEEKDAY(DATE(2025,6,1),2)+8 -> 45810 | S9: =DATE(2025,6,1)-WEEKDAY(DATE(2025,6,1),2)+9 -> 45811 | T9: =DATE(2025,6,1)-WEEKDAY(DATE(2025,6,1),2)+10 -> 45812 | U9: =DATE(2025,6,1)-WEEKDAY(DATE(2025,6,1),2)+11 -> 45813 | V9: =DATE(2025,6,1)-WEEKDAY(DATE(2025,6,1),2)+12 -> 45814 | W9: =DATE(2025,6,1)-WEEKDAY(DATE(2025,6,1),2)+13 -> 45815 | X9: =DATE(2025,6,1)-WEEKDAY(DATE(2025,6,1),2)+14 -> 45816 | Z9: =DATE(2025,7,1)-WEEKDAY(DATE(2025,7,1),2)+8 -> 45845 | AA9: =DATE(2025,7,1)-WEEKDAY(DATE(2025,7,1),2)+9 -> 45846 | AB9: =DATE(2025,7,1)-WEEKDAY(DATE(2025,7,1),2)+10 -> 45847 | AC9: =DATE(2025,7,1)-WEEKDAY(DATE(2025,7,1),2)+11 -> 45848 | AD9: =DATE(2025,7,1)-WEEKDAY(DATE(2025,7,1),2)+12 -> 45849 | AE9: =DATE(2025,7,1)-WEEKDAY(DATE(2025,7,1),2)+13 -> 45850 | AF9: =DATE(2025,7,1)-WEEKDAY(DATE(2025,7,1),2)+14 -> 45851
B10: =IF(MONTH(B9)=4,IF(IFERROR(CHOOSE($A$3,INDEX('データ'!$B$880:$J$1244,MATCH(B9,'データ'!$A$880:$A$1244,0),$A$2),INDEX('データ'!$L$880:$T$1244,MATCH(B9,'データ'!$A$880:$A$1244,0),$A$2),INDEX('データ'!$V$880:$AD$1244,MATCH(B9,'データ'!$A$880:$A$1244,0),$A$2)),0)=0,"",CHOOSE($A$3,INDEX('データ'!$B$880:$J$1244,MATCH(B9,'データ'!$A$880:$A$1244,0),$A$2),INDEX('データ'!$L$880:$T$1244,MATCH(B9,'データ'!$A$880:$A$1244,0),$A$2),INDEX('データ'!$V$880:$AD$1244,MATCH(B9,'データ'!$A$880:$A$1244,0),$A$2))),"") -> 3875 | C10: =IF(MONTH(C9)=4,IF(IFERROR(CHOOSE($A$3,INDEX('データ'!$B$880:$J$1244,MATCH(C9,'データ'!$A$880:$A$1244,0),$A$2),INDEX('データ'!$L$880:$T$1244,MATCH(C9,'データ'!$A$880:$A$1244,0),$A$2),INDEX('データ'!$V$880:$AD$1244,MATCH(C9,'データ'!$A$880:$A$1244,0),$A$2)),0)=0,"",CHOOSE($A$3,INDEX('データ'!$B$880:$J$1244,MATCH(C9,'データ'!$A$880:$A$1244,0),$A$2),INDEX('データ'!$L$880:$T$1244,MATCH(C9,'データ'!$A$880:$A$1244,0),$A$2),INDEX('データ'!$V$880:$AD$1244,MATCH(C9,'データ'!$A$880:$A$1244,0),$A$2))),"") -> 3288 | D10: =IF(MONTH(D9)=4,IF(IFERROR(CHOOSE($A$3,INDEX('データ'!$B$880:$J$1244,MATCH(D9,'データ'!$A$880:$A$1244,0),$A$2),INDEX('データ'!$L$880:$T$1244,MATCH(D9,'データ'!$A$880:$A$1244,0),$A$2),INDEX('データ'!$V$880:$AD$1244,MATCH(D9,'データ'!$A$880:$A$1244,0),$A$2)),0)=0,"",CHOOSE($A$3,INDEX('データ'!$B$880:$J$1244,MATCH(D9,'データ'!$A$880:$A$1244,0),$A$2),INDEX('データ'!$L$880:$T$1244,MATCH(D9,'データ'!$A$880:$A$1244,0),$A$2),INDEX('データ'!$V$880:$AD$1244,MATCH(D9,'データ'!$A$880:$A$1244,0),$A$2))),"") -> 3225 | E10: =IF(MONTH(E9)=4,IF(IFERROR(CHOOSE($A$3,INDEX('データ'!$B$880:$J$1244,MATCH(E9,'データ'!$A$880:$A$1244,0),$A$2),INDEX('データ'!$L$880:$T$1244,MATCH(E9,'データ'!$A$880:$A$1244,0),$A$2),INDEX('データ'!$V$880:$AD$1244,MATCH(E9,'データ'!$A$880:$A$1244,0),$A$2)),0)=0,"",CHOOSE($A$3,INDEX('データ'!$B$880:$J$1244,MATCH(E9,'データ'!$A$880:$A$1244,0),$A$2),INDEX('データ'!$L$880:$T$1244,MATCH(E9,'データ'!$A$880:$A$1244,0),$A$2),INDEX('データ'!$V$880:$AD$1244,MATCH(E9,'データ'!$A$880:$A$1244,0),$A$2))),"") -> 2651 | F10: =IF(MONTH(F9)=4,IF(IFERROR(CHOOSE($A$3,INDEX('データ'!$B$880:$J$1244,MATCH(F9,'データ'!$A$880:$A$1244,0),$A$2),INDEX('データ'!$L$880:$T$1244,MATCH(F9,'データ'!$A$880:$A$1244,0),$A$2),INDEX('データ'!$V$880:$AD$1244,MATCH(F9,'データ'!$A$880:$A$1244,0),$A$2)),0)=0,"",CHOOSE($A$3,INDEX('データ'!$B$880:$J$1244,MATCH(F9,'データ'!$A$880:$A$1244,0),$A$2),INDEX('データ'!$L$880:$T$1244,MATCH(F9,'データ'!$A$880:$A$1244,0),$A$2),INDEX('データ'!$V$880:$AD$1244,MATCH(F9,'データ'!$A$880:$A$1244,0),$A$2))),"") -> 3091 | G10: =IF(MONTH(G9)=4,IF(IFERROR(CHOOSE($A$3,INDEX('データ'!$B$880:$J$1244,MATCH(G9,'データ'!$A$880:$A$1244,0),$A$2),INDEX('データ'!$L$880:$T$1244,MATCH(G9,'データ'!$A$880:$A$1244,0),$A$2),INDEX('データ'!$V$880:$AD$1244,MATCH(G9,'データ'!$A$880:$A$1244,0),$A$2)),0)=0,"",CHOOSE($A$3,INDEX('データ'!$B$880:$J$1244,MATCH(G9,'データ'!$A$880:$A$1244,0),$A$2),INDEX('データ'!$L$880:$T$1244,MATCH(G9,'データ'!$A$880:$A$1244,0),$A$2),INDEX('データ'!$V$880:$AD$1244,MATCH(G9,'データ'!$A$880:$A$1244,0),$A$2))),"") | H10: =IF(MONTH(H9)=4,IF(IFERROR(CHOOSE($A$3,INDEX('データ'!$B$880:$J$1244,MATCH(H9,'データ'!$A$880:$A$1244,0),$A$2),INDEX('データ'!$L$880:$T$1244,MATCH(H9,'データ'!$A$880:$A$1244,0),$A$2),INDEX('データ'!$V$880:$AD$1244,MATCH(H9,'データ'!$A$880:$A$1244,0),$A$2)),0)=0,"",CHOOSE($A$3,INDEX('データ'!$B$880:$J$1244,MATCH(H9,'データ'!$A$880:$A$1244,0),$A$2),INDEX('データ'!$L$880:$T$1244,MATCH(H9,'データ'!$A$880:$A$1244,0),$A$2),INDEX('データ'!$V$880:$AD$1244,MATCH(H9,'データ'!$A$880:$A$1244,0),$A$2))),"") -> 85 | J10: =IF(MONTH(J9)=5,IF(IFERROR(CHOOSE($A$3,INDEX('データ'!$B$880:$J$1244,MATCH(J9,'データ'!$A$880:$A$1244,0),$A$2),INDEX('データ'!$L$880:$T$1244,MATCH(J9,'データ'!$A$880:$A$1244,0),$A$2),INDEX('データ'!$V$880:$AD$1244,MATCH(J9,'データ'!$A$880:$A$1244,0),$A$2)),0)=0,"",CHOOSE($A$3,INDEX('データ'!$B$880:$J$1244,MATCH(J9,'データ'!$A$880:$A$1244,0),$A$2),INDEX('データ'!$L$880:$T$1244,MATCH(J9,'データ'!$A$880:$A$1244,0),$A$2),INDEX('データ'!$V$880:$AD$1244,MATCH(J9,'データ'!$A$880:$A$1244,0),$A$2))),"") | K10: =IF(MONTH(K9)=5,IF(IFERROR(CHOOSE($A$3,INDEX('データ'!$B$880:$J$1244,MATCH(K9,'データ'!$A$880:$A$1244,0),$A$2),INDEX('データ'!$L$880:$T$1244,MATCH(K9,'データ'!$A$880:$A$1244,0),$A$2),INDEX('データ'!$V$880:$AD$1244,MATCH(K9,'データ'!$A$880:$A$1244,0),$A$2)),0)=0,"",CHOOSE($A$3,INDEX('データ'!$B$880:$J$1244,MATCH(K9,'データ'!$A$880:$A$1244,0),$A$2),INDEX('データ'!$L$880:$T$1244,MATCH(K9,'データ'!$A$880:$A$1244,0),$A$2),INDEX('データ'!$V$880:$AD$1244,MATCH(K9,'データ'!$A$880:$A$1244,0),$A$2))),"") | L10: =IF(MONTH(L9)=5,IF(IFERROR(CHOOSE($A$3,INDEX('データ'!$B$880:$J$1244,MATCH(L9,'データ'!$A$880:$A$1244,0),$A$2),INDEX('データ'!$L$880:$T$1244,MATCH(L9,'データ'!$A$880:$A$1244,0),$A$2),INDEX('データ'!$V$880:$AD$1244,MATCH(L9,'データ'!$A$880:$A$1244,0),$A$2)),0)=0,"",CHOOSE($A$3,INDEX('データ'!$B$880:$J$1244,MATCH(L9,'データ'!$A$880:$A$1244,0),$A$2),INDEX('データ'!$L$880:$T$1244,MATCH(L9,'データ'!$A$880:$A$1244,0),$A$2),INDEX('データ'!$V$880:$AD$1244,MATCH(L9,'データ'!$A$880:$A$1244,0),$A$2))),"") -> 3462 | M10: =IF(MONTH(M9)=5,IF(IFERROR(CHOOSE($A$3,INDEX('データ'!$B$880:$J$1244,MATCH(M9,'データ'!$A$880:$A$1244,0),$A$2),INDEX('データ'!$L$880:$T$1244,MATCH(M9,'データ'!$A$880:$A$1244,0),$A$2),INDEX('データ'!$V$880:$AD$1244,MATCH(M9,'データ'!$A$880:$A$1244,0),$A$2)),0)=0,"",CHOOSE($A$3,INDEX('データ'!$B$880:$J$1244,MATCH(M9,'データ'!$A$880:$A$1244,0),$A$2),INDEX('データ'!$L$880:$T$1244,MATCH(M9,'データ'!$A$880:$A$1244,0),$A$2),INDEX('データ'!$V$880:$AD$1244,MATCH(M9,'データ'!$A$880:$A$1244,0),$A$2))),"") -> 3133 | N10: =IF(MONTH(N9)=5,IF(IFERROR(CHOOSE($A$3,INDEX('データ'!$B$880:$J$1244,MATCH(N9,'データ'!$A$880:$A$1244,0),$A$2),INDEX('データ'!$L$880:$T$1244,MATCH(N9,'データ'!$A$880:$A$1244,0),$A$2),INDEX('データ'!$V$880:$AD$1244,MATCH(N9,'データ'!$A$880:$A$1244,0),$A$2)),0)=0,"",CHOOSE($A$3,INDEX('データ'!$B$880:$J$1244,MATCH(N9,'データ'!$A$880:$A$1244,0),$A$2),INDEX('データ'!$L$880:$T$1244,MATCH(N9,'データ'!$A$880:$A$1244,0),$A$2),INDEX('データ'!$V$880:$AD$1244,MATCH(N9,'データ'!$A$880:$A$1244,0),$A$2))),"") -> 2556 | O10: =IF(MONTH(O9)=5,IF(IFERROR(CHOOSE($A$3,INDEX('データ'!$B$880:$J$1244,MATCH(O9,'データ'!$A$880:$A$1244,0),$A$2),INDEX('データ'!$L$880:$T$1244,MATCH(O9,'データ'!$A$880:$A$1244,0),$A$2),INDEX('データ'!$V$880:$AD$1244,MATCH(O9,'データ'!$A$880:$A$1244,0),$A$2)),0)=0,"",CHOOSE($A$3,INDEX('データ'!$B$880:$J$1244,MATCH(O9,'データ'!$A$880:$A$1244,0),$A$2),INDEX('データ'!$L$880:$T$1244,MATCH(O9,'データ'!$A$880:$A$1244,0),$A$2),INDEX('データ'!$V$880:$AD$1244,MATCH(O9,'データ'!$A$880:$A$1244,0),$A$2))),"") | P10: =IF(MONTH(P9)=5,IF(IFERROR(CHOOSE($A$3,INDEX('データ'!$B$880:$J$1244,MATCH(P9,'データ'!$A$880:$A$1244,0),$A$2),INDEX('データ'!$L$880:$T$1244,MATCH(P9,'データ'!$A$880:$A$1244,0),$A$2),INDEX('データ'!$V$880:$AD$1244,MATCH(P9,'データ'!$A$880:$A$1244,0),$A$2)),0)=0,"",CHOOSE($A$3,INDEX('データ'!$B$880:$J$1244,MATCH(P9,'データ'!$A$880:$A$1244,0),$A$2),INDEX('データ'!$L$880:$T$1244,MATCH(P9,'データ'!$A$880:$A$1244,0),$A$2),INDEX('データ'!$V$880:$AD$1244,MATCH(P9,'データ'!$A$880:$A$1244,0),$A$2))),"") -> 383 | R10: =IF(MONTH(R9)=6,IF(IFERROR(CHOOSE($A$3,INDEX('データ'!$B$880:$J$1244,MATCH(R9,'データ'!$A$880:$A$1244,0),$A$2),INDEX('データ'!$L$880:$T$1244,MATCH(R9,'データ'!$A$880:$A$1244,0),$A$2),INDEX('データ'!$V$880:$AD$1244,MATCH(R9,'データ'!$A$880:$A$1244,0),$A$2)),0)=0,"",CHOOSE($A$3,INDEX('データ'!$B$880:$J$1244,MATCH(R9,'データ'!$A$880:$A$1244,0),$A$2),INDEX('データ'!$L$880:$T$1244,MATCH(R9,'データ'!$A$880:$A$1244,0),$A$2),INDEX('データ'!$V$880:$AD$1244,MATCH(R9,'データ'!$A$880:$A$1244,0),$A$2))),"") -> 3649 | S10: =IF(MONTH(S9)=6,IF(IFERROR(CHOOSE($A$3,INDEX('データ'!$B$880:$J$1244,MATCH(S9,'データ'!$A$880:$A$1244,0),$A$2),INDEX('データ'!$L$880:$T$1244,MATCH(S9,'データ'!$A$880:$A$1244,0),$A$2),INDEX('データ'!$V$880:$AD$1244,MATCH(S9,'データ'!$A$880:$A$1244,0),$A$2)),0)=0,"",CHOOSE($A$3,INDEX('データ'!$B$880:$J$1244,MATCH(S9,'データ'!$A$880:$A$1244,0),$A$2),INDEX('データ'!$L$880:$T$1244,MATCH(S9,'データ'!$A$880:$A$1244,0),$A$2),INDEX('データ'!$V$880:$AD$1244,MATCH(S9,'データ'!$A$880:$A$1244,0),$A$2))),"") -> 2848 | T10: =IF(MONTH(T9)=6,IF(IFERROR(CHOOSE($A$3,INDEX('データ'!$B$880:$J$1244,MATCH(T9,'データ'!$A$880:$A$1244,0),$A$2),INDEX('データ'!$L$880:$T$1244,MATCH(T9,'データ'!$A$880:$A$1244,0),$A$2),INDEX('データ'!$V$880:$AD$1244,MATCH(T9,'データ'!$A$880:$A$1244,0),$A$2)),0)=0,"",CHOOSE($A$3,INDEX('データ'!$B$880:$J$1244,MATCH(T9,'データ'!$A$880:$A$1244,0),$A$2),INDEX('データ'!$L$880:$T$1244,MATCH(T9,'データ'!$A$880:$A$1244,0),$A$2),INDEX('データ'!$V$880:$AD$1244,MATCH(T9,'データ'!$A$880:$A$1244,0),$A$2))),"") -> 3364 | U10: =IF(MONTH(U9)=6,IF(IFERROR(CHOOSE($A$3,INDEX('データ'!$B$880:$J$1244,MATCH(U9,'データ'!$A$880:$A$1244,0),$A$2),INDEX('データ'!$L$880:$T$1244,MATCH(U9,'データ'!$A$880:$A$1244,0),$A$2),INDEX('データ'!$V$880:$AD$1244,MATCH(U9,'データ'!$A$880:$A$1244,0),$A$2)),0)=0,"",CHOOSE($A$3,INDEX('データ'!$B$880:$J$1244,MATCH(U9,'データ'!$A$880:$A$1244,0),$A$2),INDEX('データ'!$L$880:$T$1244,MATCH(U9,'データ'!$A$880:$A$1244,0),$A$2),INDEX('データ'!$V$880:$AD$1244,MATCH(U9,'データ'!$A$880:$A$1244,0),$A$2))),"") -> 3025 | V10: =IF(MONTH(V9)=6,IF(IFERROR(CHOOSE($A$3,INDEX('データ'!$B$880:$J$1244,MATCH(V9,'データ'!$A$880:$A$1244,0),$A$2),INDEX('データ'!$L$880:$T$1244,MATCH(V9,'データ'!$A$880:$A$1244,0),$A$2),INDEX('データ'!$V$880:$AD$1244,MATCH(V9,'データ'!$A$880:$A$1244,0),$A$2)),0)=0,"",CHOOSE($A$3,INDEX('データ'!$B$880:$J$1244,MATCH(V9,'データ'!$A$880:$A$1244,0),$A$2),INDEX('データ'!$L$880:$T$1244,MATCH(V9,'データ'!$A$880:$A$1244,0),$A$2),INDEX('データ'!$V$880:$AD$1244,MATCH(V9,'データ'!$A$880:$A$1244,0),$A$2))),"") -> 3254 | W10: =IF(MONTH(W9)=6,IF(IFERROR(CHOOSE($A$3,INDEX('データ'!$B$880:$J$1244,MATCH(W9,'データ'!$A$880:$A$1244,0),$A$2),INDEX('データ'!$L$880:$T$1244,MATCH(W9,'データ'!$A$880:$A$1244,0),$A$2),INDEX('データ'!$V$880:$AD$1244,MATCH(W9,'データ'!$A$880:$A$1244,0),$A$2)),0)=0,"",CHOOSE($A$3,INDEX('データ'!$B$880:$J$1244,MATCH(W9,'データ'!$A$880:$A$1244,0),$A$2),INDEX('データ'!$L$880:$T$1244,MATCH(W9,'データ'!$A$880:$A$1244,0),$A$2),INDEX('データ'!$V$880:$AD$1244,MATCH(W9,'データ'!$A$880:$A$1244,0),$A$2))),"") | X10: =IF(MONTH(X9)=6,IF(IFERROR(CHOOSE($A$3,INDEX('データ'!$B$880:$J$1244,MATCH(X9,'データ'!$A$880:$A$1244,0),$A$2),INDEX('データ'!$L$880:$T$1244,MATCH(X9,'データ'!$A$880:$A$1244,0),$A$2),INDEX('データ'!$V$880:$AD$1244,MATCH(X9,'データ'!$A$880:$A$1244,0),$A$2)),0)=0,"",CHOOSE($A$3,INDEX('データ'!$B$880:$J$1244,MATCH(X9,'データ'!$A$880:$A$1244,0),$A$2),INDEX('データ'!$L$880:$T$1244,MATCH(X9,'データ'!$A$880:$A$1244,0),$A$2),INDEX('データ'!$V$880:$AD$1244,MATCH(X9,'データ'!$A$880:$A$1244,0),$A$2))),"") | Z10: =IF(MONTH(Z9)=7,IF(IFERROR(CHOOSE($A$3,INDEX('データ'!$B$880:$J$1244,MATCH(Z9,'データ'!$A$880:$A$1244,0),$A$2),INDEX('データ'!$L$880:$T$1244,MATCH(Z9,'データ'!$A$880:$A$1244,0),$A$2),INDEX('データ'!$V$880:$AD$1244,MATCH(Z9,'データ'!$A$880:$A$1244,0),$A$2)),0)=0,"",CHOOSE($A$3,INDEX('データ'!$B$880:$J$1244,MATCH(Z9,'データ'!$A$880:$A$1244,0),$A$2),INDEX('データ'!$L$880:$T$1244,MATCH(Z9,'データ'!$A$880:$A$1244,0),$A$2),INDEX('データ'!$V$880:$AD$1244,MATCH(Z9,'データ'!$A$880:$A$1244,0),$A$2))),"") -> 3688 | AA10: =IF(MONTH(AA9)=7,IF(IFERROR(CHOOSE($A$3,INDEX('データ'!$B$880:$J$1244,MATCH(AA9,'データ'!$A$880:$A$1244,0),$A$2),INDEX('データ'!$L$880:$T$1244,MATCH(AA9,'データ'!$A$880:$A$1244,0),$A$2),INDEX('データ'!$V$880:$AD$1244,MATCH(AA9,'データ'!$A$880:$A$1244,0),$A$2)),0)=0,"",CHOOSE($A$3,INDEX('データ'!$B$880:$J$1244,MATCH(AA9,'データ'!$A$880:$A$1244,0),$A$2),INDEX('データ'!$L$880:$T$1244,MATCH(AA9,'データ'!$A$880:$A$1244,0),$A$2),INDEX('データ'!$V$880:$AD$1244,MATCH(AA9,'データ'!$A$880:$A$1244,0),$A$2))),"") -> 3069 | AB10: =IF(MONTH(AB9)=7,IF(IFERROR(CHOOSE($A$3,INDEX('データ'!$B$880:$J$1244,MATCH(AB9,'データ'!$A$880:$A$1244,0),$A$2),INDEX('データ'!$L$880:$T$1244,MATCH(AB9,'データ'!$A$880:$A$1244,0),$A$2),INDEX('データ'!$V$880:$AD$1244,MATCH(AB9,'データ'!$A$880:$A$1244,0),$A$2)),0)=0,"",CHOOSE($A$3,INDEX('データ'!$B$880:$J$1244,MATCH(AB9,'データ'!$A$880:$A$1244,0),$A$2),INDEX('データ'!$L$880:$T$1244,MATCH(AB9,'データ'!$A$880:$A$1244,0),$A$2),INDEX('データ'!$V$880:$AD$1244,MATCH(AB9,'データ'!$A$880:$A$1244,0),$A$2))),"") -> 2924 | AC10: =IF(MONTH(AC9)=7,IF(IFERROR(CHOOSE($A$3,INDEX('データ'!$B$880:$J$1244,MATCH(AC9,'データ'!$A$880:$A$1244,0),$A$2),INDEX('データ'!$L$880:$T$1244,MATCH(AC9,'データ'!$A$880:$A$1244,0),$A$2),INDEX('データ'!$V$880:$AD$1244,MATCH(AC9,'データ'!$A$880:$A$1244,0),$A$2)),0)=0,"",CHOOSE($A$3,INDEX('データ'!$B$880:$J$1244,MATCH(AC9,'データ'!$A$880:$A$1244,0),$A$2),INDEX('データ'!$L$880:$T$1244,MATCH(AC9,'データ'!$A$880:$A$1244,0),$A$2),INDEX('データ'!$V$880:$AD$1244,MATCH(AC9,'データ'!$A$880:$A$1244,0),$A$2))),"") -> 2859 | AD10: =IF(MONTH(AD9)=7,IF(IFERROR(CHOOSE($A$3,INDEX('データ'!$B$880:$J$1244,MATCH(AD9,'データ'!$A$880:$A$1244,0),$A$2),INDEX('データ'!$L$880:$T$1244,MATCH(AD9,'データ'!$A$880:$A$1244,0),$A$2),INDEX('データ'!$V$880:$AD$1244,MATCH(AD9,'データ'!$A$880:$A$1244,0),$A$2)),0)=0,"",CHOOSE($A$3,INDEX('データ'!$B$880:$J$1244,MATCH(AD9,'データ'!$A$880:$A$1244,0),$A$2),INDEX('データ'!$L$880:$T$1244,MATCH(AD9,'データ'!$A$880:$A$1244,0),$A$2),INDEX('データ'!$V$880:$AD$1244,MATCH(AD9,'データ'!$A$880:$A$1244,0),$A$2))),"") -> 2973 | AE10: =IF(MONTH(AE9)=7,IF(IFERROR(CHOOSE($A$3,INDEX('データ'!$B$880:$J$1244,MATCH(AE9,'データ'!$A$880:$A$1244,0),$A$2),INDEX('データ'!$L$880:$T$1244,MATCH(AE9,'データ'!$A$880:$A$1244,0),$A$2),INDEX('データ'!$V$880:$AD$1244,MATCH(AE9,'データ'!$A$880:$A$1244,0),$A$2)),0)=0,"",CHOOSE($A$3,INDEX('データ'!$B$880:$J$1244,MATCH(AE9,'データ'!$A$880:$A$1244,0),$A$2),INDEX('データ'!$L$880:$T$1244,MATCH(AE9,'データ'!$A$880:$A$1244,0),$A$2),INDEX('データ'!$V$880:$AD$1244,MATCH(AE9,'データ'!$A$880:$A$1244,0),$A$2))),"") | AF10: =IF(MONTH(AF9)=7,IF(IFERROR(CHOOSE($A$3,INDEX('データ'!$B$880:$J$1244,MATCH(AF9,'データ'!$A$880:$A$1244,0),$A$2),INDEX('データ'!$L$880:$T$1244,MATCH(AF9,'データ'!$A$880:$A$1244,0),$A$2),INDEX('データ'!$V$880:$AD$1244,MATCH(AF9,'データ'!$A$880:$A$1244,0),$A$2)),0)=0,"",CHOOSE($A$3,INDEX('データ'!$B$880:$J$1244,MATCH(AF9,'データ'!$A$880:$A$1244,0),$A$2),INDEX('データ'!$L$880:$T$1244,MATCH(AF9,'データ'!$A$880:$A$1244,0),$A$2),INDEX('データ'!$V$880:$AD$1244,MATCH(AF9,'データ'!$A$880:$A$1244,0),$A$2))),"") -> 675
B11: =DATE(2025,4,1)-WEEKDAY(DATE(2025,4,1),2)+15 -> 45761 | C11: =DATE(2025,4,1)-WEEKDAY(DATE(2025,4,1),2)+16 -> 45762 | D11: =DATE(2025,4,1)-WEEKDAY(DATE(2025,4,1),2)+17 -> 45763 | E11: =DATE(2025,4,1)-WEEKDAY(DATE(2025,4,1),2)+18 -> 45764 | F11: =DATE(2025,4,1)-WEEKDAY(DATE(2025,4,1),2)+19 -> 45765 | G11: =DATE(2025,4,1)-WEEKDAY(DATE(2025,4,1),2)+20 -> 45766 | H11: =DATE(2025,4,1)-WEEKDAY(DATE(2025,4,1),2)+21 -> 45767 | J11: =DATE(2025,5,1)-WEEKDAY(DATE(2025,5,1),2)+15 -> 45789 | K11: =DATE(2025,5,1)-WEEKDAY(DATE(2025,5,1),2)+16 -> 45790 | L11: =DATE(2025,5,1)-WEEKDAY(DATE(2025,5,1),2)+17 -> 45791 | M11: =DATE(2025,5,1)-WEEKDAY(DATE(2025,5,1),2)+18 -> 45792 | N11: =DATE(2025,5,1)-WEEKDAY(DATE(2025,5,1),2)+19 -> 45793 | O11: =DATE(2025,5,1)-WEEKDAY(DATE(2025,5,1),2)+20 -> 45794 | P11: =DATE(2025,5,1)-WEEKDAY(DATE(2025,5,1),2)+21 -> 45795 | R11: =DATE(2025,6,1)-WEEKDAY(DATE(2025,6,1),2)+15 -> 45817 | S11: =DATE(2025,6,1)-WEEKDAY(DATE(2025,6,1),2)+16 -> 45818 | T11: =DATE(2025,6,1)-WEEKDAY(DATE(2025,6,1),2)+17 -> 45819 | U11: =DATE(2025,6,1)-WEEKDAY(DATE(2025,6,1),2)+18 -> 45820 | V11: =DATE(2025,6,1)-WEEKDAY(DATE(2025,6,1),2)+19 -> 45821 | W11: =DATE(2025,6,1)-WEEKDAY(DATE(2025,6,1),2)+20 -> 45822 | X11: =DATE(2025,6,1)-WEEKDAY(DATE(2025,6,1),2)+21 -> 45823 | Z11: =DATE(2025,7,1)-WEEKDAY(DATE(2025,7,1),2)+15 -> 45852 | AA11: =DATE(2025,7,1)-WEEKDAY(DATE(2025,7,1),2)+16 -> 45853 | AB11: =DATE(2025,7,1)-WEEKDAY(DATE(2025,7,1),2)+17 -> 45854 | AC11: =DATE(2025,7,1)-WEEKDAY(DATE(2025,7,1),2)+18 -> 45855 | AD11: =DATE(2025,7,1)-WEEKDAY(DATE(2025,7,1),2)+19 -> 45856 | AE11: =DATE(2025,7,1)-WEEKDAY(DATE(2025,7,1),2)+20 -> 45857 | AF11: =DATE(2025,7,1)-WEEKDAY(DATE(2025,7,1),2)+21 -> 45858
B12: =IF(MONTH(B11)=4,IF(IFERROR(CHOOSE($A$3,INDEX('データ'!$B$880:$J$1244,MATCH(B11,'データ'!$A$880:$A$1244,0),$A$2),INDEX('データ'!$L$880:$T$1244,MATCH(B11,'データ'!$A$880:$A$1244,0),$A$2),INDEX('データ'!$V$880:$AD$1244,MATCH(B11,'データ'!$A$880:$A$1244,0),$A$2)),0)=0,"",CHOOSE($A$3,INDEX('データ'!$B$880:$J$1244,MATCH(B11,'データ'!$A$880:$A$1244,0),$A$2),INDEX('データ'!$L$880:$T$1244,MATCH(B11,'データ'!$A$880:$A$1244,0),$A$2),INDEX('データ'!$V$880:$AD$1244,MATCH(B11,'データ'!$A$880:$A$1244,0),$A$2))),"") -> 3075 | C12: =IF(MONTH(C11)=4,IF(IFERROR(CHOOSE($A$3,INDEX('データ'!$B$880:$J$1244,MATCH(C11,'データ'!$A$880:$A$1244,0),$A$2),INDEX('データ'!$L$880:$T$1244,MATCH(C11,'データ'!$A$880:$A$1244,0),$A$2),INDEX('データ'!$V$880:$AD$1244,MATCH(C11,'データ'!$A$880:$A$1244,0),$A$2)),0)=0,"",CHOOSE($A$3,INDEX('データ'!$B$880:$J$1244,MATCH(C11,'データ'!$A$880:$A$1244,0),$A$2),INDEX('データ'!$L$880:$T$1244,MATCH(C11,'データ'!$A$880:$A$1244,0),$A$2),INDEX('データ'!$V$880:$AD$1244,MATCH(C11,'データ'!$A$880:$A$1244,0),$A$2))),"") -> 2890 | D12: =IF(MONTH(D11)=4,IF(IFERROR(CHOOSE($A$3,INDEX('データ'!$B$880:$J$1244,MATCH(D11,'データ'!$A$880:$A$1244,0),$A$2),INDEX('データ'!$L$880:$T$1244,MATCH(D11,'データ'!$A$880:$A$1244,0),$A$2),INDEX('データ'!$V$880:$AD$1244,MATCH(D11,'データ'!$A$880:$A$1244,0),$A$2)),0)=0,"",CHOOSE($A$3,INDEX('データ'!$B$880:$J$1244,MATCH(D11,'データ'!$A$880:$A$1244,0),$A$2),INDEX('データ'!$L$880:$T$1244,MATCH(D11,'データ'!$A$880:$A$1244,0),$A$2),INDEX('データ'!$V$880:$AD$1244,MATCH(D11,'データ'!$A$880:$A$1244,0),$A$2))),"") -> 3025 | E12: =IF(MONTH(E11)=4,IF(IFERROR(CHOOSE($A$3,INDEX('データ'!$B$880:$J$1244,MATCH(E11,'データ'!$A$880:$A$1244,0),$A$2),INDEX('データ'!$L$880:$T$1244,MATCH(E11,'データ'!$A$880:$A$1244,0),$A$2),INDEX('データ'!$V$880:$AD$1244,MATCH(E11,'データ'!$A$880:$A$1244,0),$A$2)),0)=0,"",CHOOSE($A$3,INDEX('データ'!$B$880:$J$1244,MATCH(E11,'データ'!$A$880:$A$1244,0),$A$2),INDEX('データ'!$L$880:$T$1244,MATCH(E11,'データ'!$A$880:$A$1244,0),$A$2),INDEX('データ'!$V$880:$AD$1244,MATCH(E11,'データ'!$A$880:$A$1244,0),$A$2))),"") -> 2844 | F12: =IF(MONTH(F11)=4,IF(IFERROR(CHOOSE($A$3,INDEX('データ'!$B$880:$J$1244,MATCH(F11,'データ'!$A$880:$A$1244,0),$A$2),INDEX('データ'!$L$880:$T$1244,MATCH(F11,'データ'!$A$880:$A$1244,0),$A$2),INDEX('データ'!$V$880:$AD$1244,MATCH(F11,'データ'!$A$880:$A$1244,0),$A$2)),0)=0,"",CHOOSE($A$3,INDEX('データ'!$B$880:$J$1244,MATCH(F11,'データ'!$A$880:$A$1244,0),$A$2),INDEX('データ'!$L$880:$T$1244,MATCH(F11,'データ'!$A$880:$A$1244,0),$A$2),INDEX('データ'!$V$880:$AD$1244,MATCH(F11,'データ'!$A$880:$A$1244,0),$A$2))),"") -> 3361 | G12: =IF(MONTH(G11)=4,IF(IFERROR(CHOOSE($A$3,INDEX('データ'!$B$880:$J$1244,MATCH(G11,'データ'!$A$880:$A$1244,0),$A$2),INDEX('データ'!$L$880:$T$1244,MATCH(G11,'データ'!$A$880:$A$1244,0),$A$2),INDEX('データ'!$V$880:$AD$1244,MATCH(G11,'データ'!$A$880:$A$1244,0),$A$2)),0)=0,"",CHOOSE($A$3,INDEX('データ'!$B$880:$J$1244,MATCH(G11,'データ'!$A$880:$A$1244,0),$A$2),INDEX('データ'!$L$880:$T$1244,MATCH(G11,'データ'!$A$880:$A$1244,0),$A$2),INDEX('データ'!$V$880:$AD$1244,MATCH(G11,'データ'!$A$880:$A$1244,0),$A$2))),"") | H12: =IF(MONTH(H11)=4,IF(IFERROR(CHOOSE($A$3,INDEX('データ'!$B$880:$J$1244,MATCH(H11,'データ'!$A$880:$A$1244,0),$A$2),INDEX('データ'!$L$880:$T$1244,MATCH(H11,'データ'!$A$880:$A$1244,0),$A$2),INDEX('データ'!$V$880:$AD$1244,MATCH(H11,'データ'!$A$880:$A$1244,0),$A$2)),0)=0,"",CHOOSE($A$3,INDEX('データ'!$B$880:$J$1244,MATCH(H11,'データ'!$A$880:$A$1244,0),$A$2),INDEX('データ'!$L$880:$T$1244,MATCH(H11,'データ'!$A$880:$A$1244,0),$A$2),INDEX('データ'!$V$880:$AD$1244,MATCH(H11,'データ'!$A$880:$A$1244,0),$A$2))),"") | J12: =IF(MONTH(J11)=5,IF(IFERROR(CHOOSE($A$3,INDEX('データ'!$B$880:$J$1244,MATCH(J11,'データ'!$A$880:$A$1244,0),$A$2),INDEX('データ'!$L$880:$T$1244,MATCH(J11,'データ'!$A$880:$A$1244,0),$A$2),INDEX('データ'!$V$880:$AD$1244,MATCH(J11,'データ'!$A$880:$A$1244,0),$A$2)),0)=0,"",CHOOSE($A$3,INDEX('データ'!$B$880:$J$1244,MATCH(J11,'データ'!$A$880:$A$1244,0),$A$2),INDEX('データ'!$L$880:$T$1244,MATCH(J11,'データ'!$A$880:$A$1244,0),$A$2),INDEX('データ'!$V$880:$AD$1244,MATCH(J11,'データ'!$A$880:$A$1244,0),$A$2))),"") -> 3720 | K12: =IF(MONTH(K11)=5,IF(IFERROR(CHOOSE($A$3,INDEX('データ'!$B$880:$J$1244,MATCH(K11,'データ'!$A$880:$A$1244,0),$A$2),INDEX('データ'!$L$880:$T$1244,MATCH(K11,'データ'!$A$880:$A$1244,0),$A$2),INDEX('データ'!$V$880:$AD$1244,MATCH(K11,'データ'!$A$880:$A$1244,0),$A$2)),0)=0,"",CHOOSE($A$3,INDEX('データ'!$B$880:$J$1244,MATCH(K11,'データ'!$A$880:$A$1244,0),$A$2),INDEX('データ'!$L$880:$T$1244,MATCH(K11,'データ'!$A$880:$A$1244,0),$A$2),INDEX('データ'!$V$880:$AD$1244,MATCH(K11,'データ'!$A$880:$A$1244,0),$A$2))),"") -> 3190 | L12: =IF(MONTH(L11)=5,IF(IFERROR(CHOOSE($A$3,INDEX('データ'!$B$880:$J$1244,MATCH(L11,'データ'!$A$880:$A$1244,0),$A$2),INDEX('データ'!$L$880:$T$1244,MATCH(L11,'データ'!$A$880:$A$1244,0),$A$2),INDEX('データ'!$V$880:$AD$1244,MATCH(L11,'データ'!$A$880:$A$1244,0),$A$2)),0)=0,"",CHOOSE($A$3,INDEX('データ'!$B$880:$J$1244,MATCH(L11,'データ'!$A$880:$A$1244,0),$A$2),INDEX('データ'!$L$880:$T$1244,MATCH(L11,'データ'!$A$880:$A$1244,0),$A$2),INDEX('データ'!$V$880:$AD$1244,MATCH(L11,'データ'!$A$880:$A$1244,0),$A$2))),"") -> 3160 | M12: =IF(MONTH(M11)=5,IF(IFERROR(CHOOSE($A$3,INDEX('データ'!$B$880:$J$1244,MATCH(M11,'データ'!$A$880:$A$1244,0),$A$2),INDEX('データ'!$L$880:$T$1244,MATCH(M11,'データ'!$A$880:$A$1244,0),$A$2),INDEX('データ'!$V$880:$AD$1244,MATCH(M11,'データ'!$A$880:$A$1244,0),$A$2)),0)=0,"",CHOOSE($A$3,INDEX('データ'!$B$880:$J$1244,MATCH(M11,'データ'!$A$880:$A$1244,0),$A$2),INDEX('データ'!$L$880:$T$1244,MATCH(M11,'データ'!$A$880:$A$1244,0),$A$2),INDEX('データ'!$V$880:$AD$1244,MATCH(M11,'データ'!$A$880:$A$1244,0),$A$2))),"") -> 3085 | N12: =IF(MONTH(N11)=5,IF(IFERROR(CHOOSE($A$3,INDEX('データ'!$B$880:$J$1244,MATCH(N11,'データ'!$A$880:$A$1244,0),$A$2),INDEX('データ'!$L$880:$T$1244,MATCH(N11,'データ'!$A$880:$A$1244,0),$A$2),INDEX('データ'!$V$880:$AD$1244,MATCH(N11,'データ'!$A$880:$A$1244,0),$A$2)),0)=0,"",CHOOSE($A$3,INDEX('データ'!$B$880:$J$1244,MATCH(N11,'データ'!$A$880:$A$1244,0),$A$2),INDEX('データ'!$L$880:$T$1244,MATCH(N11,'データ'!$A$880:$A$1244,0),$A$2),INDEX('データ'!$V$880:$AD$1244,MATCH(N11,'データ'!$A$880:$A$1244,0),$A$2))),"") -> 3009 | O12: =IF(MONTH(O11)=5,IF(IFERROR(CHOOSE($A$3,INDEX('データ'!$B$880:$J$1244,MATCH(O11,'データ'!$A$880:$A$1244,0),$A$2),INDEX('データ'!$L$880:$T$1244,MATCH(O11,'データ'!$A$880:$A$1244,0),$A$2),INDEX('データ'!$V$880:$AD$1244,MATCH(O11,'データ'!$A$880:$A$1244,0),$A$2)),0)=0,"",CHOOSE($A$3,INDEX('データ'!$B$880:$J$1244,MATCH(O11,'データ'!$A$880:$A$1244,0),$A$2),INDEX('データ'!$L$880:$T$1244,MATCH(O11,'データ'!$A$880:$A$1244,0),$A$2),INDEX('データ'!$V$880:$AD$1244,MATCH(O11,'データ'!$A$880:$A$1244,0),$A$2))),"") | P12: =IF(MONTH(P11)=5,IF(IFERROR(CHOOSE($A$3,INDEX('データ'!$B$880:$J$1244,MATCH(P11,'データ'!$A$880:$A$1244,0),$A$2),INDEX('データ'!$L$880:$T$1244,MATCH(P11,'データ'!$A$880:$A$1244,0),$A$2),INDEX('データ'!$V$880:$AD$1244,MATCH(P11,'データ'!$A$880:$A$1244,0),$A$2)),0)=0,"",CHOOSE($A$3,INDEX('データ'!$B$880:$J$1244,MATCH(P11,'データ'!$A$880:$A$1244,0),$A$2),INDEX('データ'!$L$880:$T$1244,MATCH(P11,'データ'!$A$880:$A$1244,0),$A$2),INDEX('データ'!$V$880:$AD$1244,MATCH(P11,'データ'!$A$880:$A$1244,0),$A$2))),"") | R12: =IF(MONTH(R11)=6,IF(IFERROR(CHOOSE($A$3,INDEX('データ'!$B$880:$J$1244,MATCH(R11,'データ'!$A$880:$A$1244,0),$A$2),INDEX('データ'!$L$880:$T$1244,MATCH(R11,'データ'!$A$880:$A$1244,0),$A$2),INDEX('データ'!$V$880:$AD$1244,MATCH(R11,'データ'!$A$880:$A$1244,0),$A$2)),0)=0,"",CHOOSE($A$3,INDEX('データ'!$B$880:$J$1244,MATCH(R11,'データ'!$A$880:$A$1244,0),$A$2),INDEX('データ'!$L$880:$T$1244,MATCH(R11,'データ'!$A$880:$A$1244,0),$A$2),INDEX('データ'!$V$880:$AD$1244,MATCH(R11,'データ'!$A$880:$A$1244,0),$A$2))),"") -> 3245 | S12: =IF(MONTH(S11)=6,IF(IFERROR(CHOOSE($A$3,INDEX('データ'!$B$880:$J$1244,MATCH(S11,'データ'!$A$880:$A$1244,0),$A$2),INDEX('データ'!$L$880:$T$1244,MATCH(S11,'データ'!$A$880:$A$1244,0),$A$2),INDEX('データ'!$V$880:$AD$1244,MATCH(S11,'データ'!$A$880:$A$1244,0),$A$2)),0)=0,"",CHOOSE($A$3,INDEX('データ'!$B$880:$J$1244,MATCH(S11,'データ'!$A$880:$A$1244,0),$A$2),INDEX('データ'!$L$880:$T$1244,MATCH(S11,'データ'!$A$880:$A$1244,0),$A$2),INDEX('データ'!$V$880:$AD$1244,MATCH(S11,'データ'!$A$880:$A$1244,0),$A$2))),"") -> 2521 | T12: =IF(MONTH(T11)=6,IF(IFERROR(CHOOSE($A$3,INDEX('データ'!$B$880:$J$1244,MATCH(T11,'データ'!$A$880:$A$1244,0),$A$2),INDEX('データ'!$L$880:$T$1244,MATCH(T11,'データ'!$A$880:$A$1244,0),$A$2),INDEX('データ'!$V$880:$AD$1244,MATCH(T11,'データ'!$A$880:$A$1244,0),$A$2)),0)=0,"",CHOOSE($A$3,INDEX('データ'!$B$880:$J$1244,MATCH(T11,'データ'!$A$880:$A$1244,0),$A$2),INDEX('データ'!$L$880:$T$1244,MATCH(T11,'データ'!$A$880:$A$1244,0),$A$2),INDEX('データ'!$V$880:$AD$1244,MATCH(T11,'データ'!$A$880:$A$1244,0),$A$2))),"") -> 3151 | U12: =IF(MONTH(U11)=6,IF(IFERROR(CHOOSE($A$3,INDEX('データ'!$B$880:$J$1244,MATCH(U11,'データ'!$A$880:$A$1244,0),$A$2),INDEX('データ'!$L$880:$T$1244,MATCH(U11,'データ'!$A$880:$A$1244,0),$A$2),INDEX('データ'!$V$880:$AD$1244,MATCH(U11,'データ'!$A$880:$A$1244,0),$A$2)),0)=0,"",CHOOSE($A$3,INDEX('データ'!$B$880:$J$1244,MATCH(U11,'データ'!$A$880:$A$1244,0),$A$2),INDEX('データ'!$L$880:$T$1244,MATCH(U11,'データ'!$A$880:$A$1244,0),$A$2),INDEX('データ'!$V$880:$AD$1244,MATCH(U11,'データ'!$A$880:$A$1244,0),$A$2))),"") -> 2934 | V12: =IF(MONTH(V11)=6,IF(IFERROR(CHOOSE($A$3,INDEX('データ'!$B$880:$J$1244,MATCH(V11,'データ'!$A$880:$A$1244,0),$A$2),INDEX('データ'!$L$880:$T$1244,MATCH(V11,'データ'!$A$880:$A$1244,0),$A$2),INDEX('データ'!$V$880:$AD$1244,MATCH(V11,'データ'!$A$880:$A$1244,0),$A$2)),0)=0,"",CHOOSE($A$3,INDEX('データ'!$B$880:$J$1244,MATCH(V11,'データ'!$A$880:$A$1244,0),$A$2),INDEX('データ'!$L$880:$T$1244,MATCH(V11,'データ'!$A$880:$A$1244,0),$A$2),INDEX('データ'!$V$880:$AD$1244,MATCH(V11,'データ'!$A$880:$A$1244,0),$A$2))),"") -> 3398 | W12: =IF(MONTH(W11)=6,IF(IFERROR(CHOOSE($A$3,INDEX('データ'!$B$880:$J$1244,MATCH(W11,'データ'!$A$880:$A$1244,0),$A$2),INDEX('データ'!$L$880:$T$1244,MATCH(W11,'データ'!$A$880:$A$1244,0),$A$2),INDEX('データ'!$V$880:$AD$1244,MATCH(W11,'データ'!$A$880:$A$1244,0),$A$2)),0)=0,"",CHOOSE($A$3,INDEX('データ'!$B$880:$J$1244,MATCH(W11,'データ'!$A$880:$A$1244,0),$A$2),INDEX('データ'!$L$880:$T$1244,MATCH(W11,'データ'!$A$880:$A$1244,0),$A$2),INDEX('データ'!$V$880:$AD$1244,MATCH(W11,'データ'!$A$880:$A$1244,0),$A$2))),"") | X12: =IF(MONTH(X11)=6,IF(IFERROR(CHOOSE($A$3,INDEX('データ'!$B$880:$J$1244,MATCH(X11,'データ'!$A$880:$A$1244,0),$A$2),INDEX('データ'!$L$880:$T$1244,MATCH(X11,'データ'!$A$880:$A$1244,0),$A$2),INDEX('データ'!$V$880:$AD$1244,MATCH(X11,'データ'!$A$880:$A$1244,0),$A$2)),0)=0,"",CHOOSE($A$3,INDEX('データ'!$B$880:$J$1244,MATCH(X11,'データ'!$A$880:$A$1244,0),$A$2),INDEX('データ'!$L$880:$T$1244,MATCH(X11,'データ'!$A$880:$A$1244,0),$A$2),INDEX('データ'!$V$880:$AD$1244,MATCH(X11,'データ'!$A$880:$A$1244,0),$A$2))),"") | Z12: =IF(MONTH(Z11)=7,IF(IFERROR(CHOOSE($A$3,INDEX('データ'!$B$880:$J$1244,MATCH(Z11,'データ'!$A$880:$A$1244,0),$A$2),INDEX('データ'!$L$880:$T$1244,MATCH(Z11,'データ'!$A$880:$A$1244,0),$A$2),INDEX('データ'!$V$880:$AD$1244,MATCH(Z11,'データ'!$A$880:$A$1244,0),$A$2)),0)=0,"",CHOOSE($A$3,INDEX('データ'!$B$880:$J$1244,MATCH(Z11,'データ'!$A$880:$A$1244,0),$A$2),INDEX('データ'!$L$880:$T$1244,MATCH(Z11,'データ'!$A$880:$A$1244,0),$A$2),INDEX('データ'!$V$880:$AD$1244,MATCH(Z11,'データ'!$A$880:$A$1244,0),$A$2))),"") -> 2973 | AA12: =IF(MONTH(AA11)=7,IF(IFERROR(CHOOSE($A$3,INDEX('データ'!$B$880:$J$1244,MATCH(AA11,'データ'!$A$880:$A$1244,0),$A$2),INDEX('データ'!$L$880:$T$1244,MATCH(AA11,'データ'!$A$880:$A$1244,0),$A$2),INDEX('データ'!$V$880:$AD$1244,MATCH(AA11,'データ'!$A$880:$A$1244,0),$A$2)),0)=0,"",CHOOSE($A$3,INDEX('データ'!$B$880:$J$1244,MATCH(AA11,'データ'!$A$880:$A$1244,0),$A$2),INDEX('データ'!$L$880:$T$1244,MATCH(AA11,'データ'!$A$880:$A$1244,0),$A$2),INDEX('データ'!$V$880:$AD$1244,MATCH(AA11,'データ'!$A$880:$A$1244,0),$A$2))),"") -> 3229 | AB12: =IF(MONTH(AB11)=7,IF(IFERROR(CHOOSE($A$3,INDEX('データ'!$B$880:$J$1244,MATCH(AB11,'データ'!$A$880:$A$1244,0),$A$2),INDEX('データ'!$L$880:$T$1244,MATCH(AB11,'データ'!$A$880:$A$1244,0),$A$2),INDEX('データ'!$V$880:$AD$1244,MATCH(AB11,'データ'!$A$880:$A$1244,0),$A$2)),0)=0,"",CHOOSE($A$3,INDEX('データ'!$B$880:$J$1244,MATCH(AB11,'データ'!$A$880:$A$1244,0),$A$2),INDEX('データ'!$L$880:$T$1244,MATCH(AB11,'データ'!$A$880:$A$1244,0),$A$2),INDEX('データ'!$V$880:$AD$1244,MATCH(AB11,'データ'!$A$880:$A$1244,0),$A$2))),"") -> 2989 | AC12: =IF(MONTH(AC11)=7,IF(IFERROR(CHOOSE($A$3,INDEX('データ'!$B$880:$J$1244,MATCH(AC11,'データ'!$A$880:$A$1244,0),$A$2),INDEX('データ'!$L$880:$T$1244,MATCH(AC11,'データ'!$A$880:$A$1244,0),$A$2),INDEX('データ'!$V$880:$AD$1244,MATCH(AC11,'データ'!$A$880:$A$1244,0),$A$2)),0)=0,"",CHOOSE($A$3,INDEX('データ'!$B$880:$J$1244,MATCH(AC11,'データ'!$A$880:$A$1244,0),$A$2),INDEX('データ'!$L$880:$T$1244,MATCH(AC11,'データ'!$A$880:$A$1244,0),$A$2),INDEX('データ'!$V$880:$AD$1244,MATCH(AC11,'データ'!$A$880:$A$1244,0),$A$2))),"") -> 2622 | AD12: =IF(MONTH(AD11)=7,IF(IFERROR(CHOOSE($A$3,INDEX('データ'!$B$880:$J$1244,MATCH(AD11,'データ'!$A$880:$A$1244,0),$A$2),INDEX('データ'!$L$880:$T$1244,MATCH(AD11,'データ'!$A$880:$A$1244,0),$A$2),INDEX('データ'!$V$880:$AD$1244,MATCH(AD11,'データ'!$A$880:$A$1244,0),$A$2)),0)=0,"",CHOOSE($A$3,INDEX('データ'!$B$880:$J$1244,MATCH(AD11,'データ'!$A$880:$A$1244,0),$A$2),INDEX('データ'!$L$880:$T$1244,MATCH(AD11,'データ'!$A$880:$A$1244,0),$A$2),INDEX('データ'!$V$880:$AD$1244,MATCH(AD11,'データ'!$A$880:$A$1244,0),$A$2))),"") -> 2841 | AE12: =IF(MONTH(AE11)=7,IF(IFERROR(CHOOSE($A$3,INDEX('データ'!$B$880:$J$1244,MATCH(AE11,'データ'!$A$880:$A$1244,0),$A$2),INDEX('データ'!$L$880:$T$1244,MATCH(AE11,'データ'!$A$880:$A$1244,0),$A$2),INDEX('データ'!$V$880:$AD$1244,MATCH(AE11,'データ'!$A$880:$A$1244,0),$A$2)),0)=0,"",CHOOSE($A$3,INDEX('データ'!$B$880:$J$1244,MATCH(AE11,'データ'!$A$880:$A$1244,0),$A$2),INDEX('データ'!$L$880:$T$1244,MATCH(AE11,'データ'!$A$880:$A$1244,0),$A$2),INDEX('データ'!$V$880:$AD$1244,MATCH(AE11,'データ'!$A$880:$A$1244,0),$A$2))),"") | AF12: =IF(MONTH(AF11)=7,IF(IFERROR(CHOOSE($A$3,INDEX('データ'!$B$880:$J$1244,MATCH(AF11,'データ'!$A$880:$A$1244,0),$A$2),INDEX('データ'!$L$880:$T$1244,MATCH(AF11,'データ'!$A$880:$A$1244,0),$A$2),INDEX('データ'!$V$880:$AD$1244,MATCH(AF11,'データ'!$A$880:$A$1244,0),$A$2)),0)=0,"",CHOOSE($A$3,INDEX('データ'!$B$880:$J$1244,MATCH(AF11,'データ'!$A$880:$A$1244,0),$A$2),INDEX('データ'!$L$880:$T$1244,MATCH(AF11,'データ'!$A$880:$A$1244,0),$A$2),INDEX('データ'!$V$880:$AD$1244,MATCH(AF11,'データ'!$A$880:$A$1244,0),$A$2))),"")
B13: =DATE(2025,4,1)-WEEKDAY(DATE(2025,4,1),2)+22 -> 45768 | C13: =DATE(2025,4,1)-WEEKDAY(DATE(2025,4,1),2)+23 -> 45769 | D13: =DATE(2025,4,1)-WEEKDAY(DATE(2025,4,1),2)+24 -> 45770 | E13: =DATE(2025,4,1)-WEEKDAY(DATE(2025,4,1),2)+25 -> 45771 | F13: =DATE(2025,4,1)-WEEKDAY(DATE(2025,4,1),2)+26 -> 45772 | G13: =DATE(2025,4,1)-WEEKDAY(DATE(2025,4,1),2)+27 -> 45773 | H13: =DATE(2025,4,1)-WEEKDAY(DATE(2025,4,1),2)+28 -> 45774 | J13: =DATE(2025,5,1)-WEEKDAY(DATE(2025,5,1),2)+22 -> 45796 | K13: =DATE(2025,5,1)-WEEKDAY(DATE(2025,5,1),2)+23 -> 45797 | L13: =DATE(2025,5,1)-WEEKDAY(DATE(2025,5,1),2)+24 -> 45798 | M13: =DATE(2025,5,1)-WEEKDAY(DATE(2025,5,1),2)+25 -> 45799 | N13: =DATE(2025,5,1)-WEEKDAY(DATE(2025,5,1),2)+26 -> 45800 | O13: =DATE(2025,5,1)-WEEKDAY(DATE(2025,5,1),2)+27 -> 45801 | P13: =DATE(2025,5,1)-WEEKDAY(DATE(2025,5,1),2)+28 -> 45802 | R13: =DATE(2025,6,1)-WEEKDAY(DATE(2025,6,1),2)+22 -> 45824 | S13: =DATE(2025,6,1)-WEEKDAY(DATE(2025,6,1),2)+23 -> 45825 | T13: =DATE(2025,6,1)-WEEKDAY(DATE(2025,6,1),2)+24 -> 45826 | U13: =DATE(2025,6,1)-WEEKDAY(DATE(2025,6,1),2)+25 -> 45827 | V13: =DATE(2025,6,1)-WEEKDAY(DATE(2025,6,1),2)+26 -> 45828 | W13: =DATE(2025,6,1)-WEEKDAY(DATE(2025,6,1),2)+27 -> 45829 | X13: =DATE(2025,6,1)-WEEKDAY(DATE(2025,6,1),2)+28 -> 45830 | Z13: =DATE(2025,7,1)-WEEKDAY(DATE(2025,7,1),2)+22 -> 45859 | AA13: =DATE(2025,7,1)-WEEKDAY(DATE(2025,7,1),2)+23 -> 45860 | AB13: =DATE(2025,7,1)-WEEKDAY(DATE(2025,7,1),2)+24 -> 45861 | AC13: =DATE(2025,7,1)-WEEKDAY(DATE(2025,7,1),2)+25 -> 45862 | AD13: =DATE(2025,7,1)-WEEKDAY(DATE(2025,7,1),2)+26 -> 45863 | AE13: =DATE(2025,7,1)-WEEKDAY(DATE(2025,7,1),2)+27 -> 45864 | AF13: =DATE(2025,7,1)-WEEKDAY(DATE(2025,7,1),2)+28 -> 45865
B14: =IF(MONTH(B13)=4,IF(IFERROR(CHOOSE($A$3,INDEX('データ'!$B$880:$J$1244,MATCH(B13,'データ'!$A$880:$A$1244,0),$A$2),INDEX('データ'!$L$880:$T$1244,MATCH(B13,'データ'!$A$880:$A$1244,0),$A$2),INDEX('データ'!$V$880:$AD$1244,MATCH(B13,'データ'!$A$880:$A$1244,0),$A$2)),0)=0,"",CHOOSE($A$3,INDEX('データ'!$B$880:$J$1244,MATCH(B13,'データ'!$A$880:$A$1244,0),$A$2),INDEX('データ'!$L$880:$T$1244,MATCH(B13,'データ'!$A$880:$A$1244,0),$A$2),INDEX('データ'!$V$880:$AD$1244,MATCH(B13,'データ'!$A$880:$A$1244,0),$A$2))),"") -> 3588 | C14: =IF(MONTH(C13)=4,IF(IFERROR(CHOOSE($A$3,INDEX('データ'!$B$880:$J$1244,MATCH(C13,'データ'!$A$880:$A$1244,0),$A$2),INDEX('データ'!$L$880:$T$1244,MATCH(C13,'データ'!$A$880:$A$1244,0),$A$2),INDEX('データ'!$V$880:$AD$1244,MATCH(C13,'データ'!$A$880:$A$1244,0),$A$2)),0)=0,"",CHOOSE($A$3,INDEX('データ'!$B$880:$J$1244,MATCH(C13,'データ'!$A$880:$A$1244,0),$A$2),INDEX('データ'!$L$880:$T$1244,MATCH(C13,'データ'!$A$880:$A$1244,0),$A$2),INDEX('データ'!$V$880:$AD$1244,MATCH(C13,'データ'!$A$880:$A$1244,0),$A$2))),"") -> 2834 | D14: =IF(MONTH(D13)=4,IF(IFERROR(CHOOSE($A$3,INDEX('データ'!$B$880:$J$1244,MATCH(D13,'データ'!$A$880:$A$1244,0),$A$2),INDEX('データ'!$L$880:$T$1244,MATCH(D13,'データ'!$A$880:$A$1244,0),$A$2),INDEX('データ'!$V$880:$AD$1244,MATCH(D13,'データ'!$A$880:$A$1244,0),$A$2)),0)=0,"",CHOOSE($A$3,INDEX('データ'!$B$880:$J$1244,MATCH(D13,'データ'!$A$880:$A$1244,0),$A$2),INDEX('データ'!$L$880:$T$1244,MATCH(D13,'データ'!$A$880:$A$1244,0),$A$2),INDEX('データ'!$V$880:$AD$1244,MATCH(D13,'データ'!$A$880:$A$1244,0),$A$2))),"") -> 2840 | E14: =IF(MONTH(E13)=4,IF(IFERROR(CHOOSE($A$3,INDEX('データ'!$B$880:$J$1244,MATCH(E13,'データ'!$A$880:$A$1244,0),$A$2),INDEX('データ'!$L$880:$T$1244,MATCH(E13,'データ'!$A$880:$A$1244,0),$A$2),INDEX('データ'!$V$880:$AD$1244,MATCH(E13,'データ'!$A$880:$A$1244,0),$A$2)),0)=0,"",CHOOSE($A$3,INDEX('データ'!$B$880:$J$1244,MATCH(E13,'データ'!$A$880:$A$1244,0),$A$2),INDEX('データ'!$L$880:$T$1244,MATCH(E13,'データ'!$A$880:$A$1244,0),$A$2),INDEX('データ'!$V$880:$AD$1244,MATCH(E13,'データ'!$A$880:$A$1244,0),$A$2))),"") -> 2701 | F14: =IF(MONTH(F13)=4,IF(IFERROR(CHOOSE($A$3,INDEX('データ'!$B$880:$J$1244,MATCH(F13,'データ'!$A$880:$A$1244,0),$A$2),INDEX('データ'!$L$880:$T$1244,MATCH(F13,'データ'!$A$880:$A$1244,0),$A$2),INDEX('データ'!$V$880:$AD$1244,MATCH(F13,'データ'!$A$880:$A$1244,0),$A$2)),0)=0,"",CHOOSE($A$3,INDEX('データ'!$B$880:$J$1244,MATCH(F13,'データ'!$A$880:$A$1244,0),$A$2),INDEX('データ'!$L$880:$T$1244,MATCH(F13,'データ'!$A$880:$A$1244,0),$A$2),INDEX('データ'!$V$880:$AD$1244,MATCH(F13,'データ'!$A$880:$A$1244,0),$A$2))),"") -> 2974 | G14: =IF(MONTH(G13)=4,IF(IFERROR(CHOOSE($A$3,INDEX('データ'!$B$880:$J$1244,MATCH(G13,'データ'!$A$880:$A$1244,0),$A$2),INDEX('データ'!$L$880:$T$1244,MATCH(G13,'データ'!$A$880:$A$1244,0),$A$2),INDEX('データ'!$V$880:$AD$1244,MATCH(G13,'データ'!$A$880:$A$1244,0),$A$2)),0)=0,"",CHOOSE($A$3,INDEX('データ'!$B$880:$J$1244,MATCH(G13,'データ'!$A$880:$A$1244,0),$A$2),INDEX('データ'!$L$880:$T$1244,MATCH(G13,'データ'!$A$880:$A$1244,0),$A$2),INDEX('データ'!$V$880:$AD$1244,MATCH(G13,'データ'!$A$880:$A$1244,0),$A$2))),"") | H14: =IF(MONTH(H13)=4,IF(IFERROR(CHOOSE($A$3,INDEX('データ'!$B$880:$J$1244,MATCH(H13,'データ'!$A$880:$A$1244,0),$A$2),INDEX('データ'!$L$880:$T$1244,MATCH(H13,'データ'!$A$880:$A$1244,0),$A$2),INDEX('データ'!$V$880:$AD$1244,MATCH(H13,'データ'!$A$880:$A$1244,0),$A$2)),0)=0,"",CHOOSE($A$3,INDEX('データ'!$B$880:$J$1244,MATCH(H13,'データ'!$A$880:$A$1244,0),$A$2),INDEX('データ'!$L$880:$T$1244,MATCH(H13,'データ'!$A$880:$A$1244,0),$A$2),INDEX('データ'!$V$880:$AD$1244,MATCH(H13,'データ'!$A$880:$A$1244,0),$A$2))),"") | J14: =IF(MONTH(J13)=5,IF(IFERROR(CHOOSE($A$3,INDEX('データ'!$B$880:$J$1244,MATCH(J13,'データ'!$A$880:$A$1244,0),$A$2),INDEX('データ'!$L$880:$T$1244,MATCH(J13,'データ'!$A$880:$A$1244,0),$A$2),INDEX('データ'!$V$880:$AD$1244,MATCH(J13,'データ'!$A$880:$A$1244,0),$A$2)),0)=0,"",CHOOSE($A$3,INDEX('データ'!$B$880:$J$1244,MATCH(J13,'データ'!$A$880:$A$1244,0),$A$2),INDEX('データ'!$L$880:$T$1244,MATCH(J13,'データ'!$A$880:$A$1244,0),$A$2),INDEX('データ'!$V$880:$AD$1244,MATCH(J13,'データ'!$A$880:$A$1244,0),$A$2))),"") -> 3432 | K14: =IF(MONTH(K13)=5,IF(IFERROR(CHOOSE($A$3,INDEX('データ'!$B$880:$J$1244,MATCH(K13,'データ'!$A$880:$A$1244,0),$A$2),INDEX('データ'!$L$880:$T$1244,MATCH(K13,'データ'!$A$880:$A$1244,0),$A$2),INDEX('データ'!$V$880:$AD$1244,MATCH(K13,'データ'!$A$880:$A$1244,0),$A$2)),0)=0,"",CHOOSE($A$3,INDEX('データ'!$B$880:$J$1244,MATCH(K13,'データ'!$A$880:$A$1244,0),$A$2),INDEX('データ'!$L$880:$T$1244,MATCH(K13,'データ'!$A$880:$A$1244,0),$A$2),INDEX('データ'!$V$880:$AD$1244,MATCH(K13,'データ'!$A$880:$A$1244,0),$A$2))),"") -> 3096 | L14: =IF(MONTH(L13)=5,IF(IFERROR(CHOOSE($A$3,INDEX('データ'!$B$880:$J$1244,MATCH(L13,'データ'!$A$880:$A$1244,0),$A$2),INDEX('データ'!$L$880:$T$1244,MATCH(L13,'データ'!$A$880:$A$1244,0),$A$2),INDEX('データ'!$V$880:$AD$1244,MATCH(L13,'データ'!$A$880:$A$1244,0),$A$2)),0)=0,"",CHOOSE($A$3,INDEX('データ'!$B$880:$J$1244,MATCH(L13,'データ'!$A$880:$A$1244,0),$A$2),INDEX('データ'!$L$880:$T$1244,MATCH(L13,'データ'!$A$880:$A$1244,0),$A$2),INDEX('データ'!$V$880:$AD$1244,MATCH(L13,'データ'!$A$880:$A$1244,0),$A$2))),"") -> 2730 | M14: =IF(MONTH(M13)=5,IF(IFERROR(CHOOSE($A$3,INDEX('データ'!$B$880:$J$1244,MATCH(M13,'データ'!$A$880:$A$1244,0),$A$2),INDEX('データ'!$L$880:$T$1244,MATCH(M13,'データ'!$A$880:$A$1244,0),$A$2),INDEX('データ'!$V$880:$AD$1244,MATCH(M13,'データ'!$A$880:$A$1244,0),$A$2)),0)=0,"",CHOOSE($A$3,INDEX('データ'!$B$880:$J$1244,MATCH(M13,'データ'!$A$880:$A$1244,0),$A$2),INDEX('データ'!$L$880:$T$1244,MATCH(M13,'データ'!$A$880:$A$1244,0),$A$2),INDEX('データ'!$V$880:$AD$1244,MATCH(M13,'データ'!$A$880:$A$1244,0),$A$2))),"") -> 2747 | N14: =IF(MONTH(N13)=5,IF(IFERROR(CHOOSE($A$3,INDEX('データ'!$B$880:$J$1244,MATCH(N13,'データ'!$A$880:$A$1244,0),$A$2),INDEX('データ'!$L$880:$T$1244,MATCH(N13,'データ'!$A$880:$A$1244,0),$A$2),INDEX('データ'!$V$880:$AD$1244,MATCH(N13,'データ'!$A$880:$A$1244,0),$A$2)),0)=0,"",CHOOSE($A$3,INDEX('データ'!$B$880:$J$1244,MATCH(N13,'データ'!$A$880:$A$1244,0),$A$2),INDEX('データ'!$L$880:$T$1244,MATCH(N13,'データ'!$A$880:$A$1244,0),$A$2),INDEX('データ'!$V$880:$AD$1244,MATCH(N13,'データ'!$A$880:$A$1244,0),$A$2))),"") -> 3130 | O14: =IF(MONTH(O13)=5,IF(IFERROR(CHOOSE($A$3,INDEX('データ'!$B$880:$J$1244,MATCH(O13,'データ'!$A$880:$A$1244,0),$A$2),INDEX('データ'!$L$880:$T$1244,MATCH(O13,'データ'!$A$880:$A$1244,0),$A$2),INDEX('データ'!$V$880:$AD$1244,MATCH(O13,'データ'!$A$880:$A$1244,0),$A$2)),0)=0,"",CHOOSE($A$3,INDEX('データ'!$B$880:$J$1244,MATCH(O13,'データ'!$A$880:$A$1244,0),$A$2),INDEX('データ'!$L$880:$T$1244,MATCH(O13,'データ'!$A$880:$A$1244,0),$A$2),INDEX('データ'!$V$880:$AD$1244,MATCH(O13,'データ'!$A$880:$A$1244,0),$A$2))),"") | P14: =IF(MONTH(P13)=5,IF(IFERROR(CHOOSE($A$3,INDEX('データ'!$B$880:$J$1244,MATCH(P13,'データ'!$A$880:$A$1244,0),$A$2),INDEX('データ'!$L$880:$T$1244,MATCH(P13,'データ'!$A$880:$A$1244,0),$A$2),INDEX('データ'!$V$880:$AD$1244,MATCH(P13,'データ'!$A$880:$A$1244,0),$A$2)),0)=0,"",CHOOSE($A$3,INDEX('データ'!$B$880:$J$1244,MATCH(P13,'データ'!$A$880:$A$1244,0),$A$2),INDEX('データ'!$L$880:$T$1244,MATCH(P13,'データ'!$A$880:$A$1244,0),$A$2),INDEX('データ'!$V$880:$AD$1244,MATCH(P13,'データ'!$A$880:$A$1244,0),$A$2))),"") | R14: =IF(MONTH(R13)=6,IF(IFERROR(CHOOSE($A$3,INDEX('データ'!$B$880:$J$1244,MATCH(R13,'データ'!$A$880:$A$1244,0),$A$2),INDEX('データ'!$L$880:$T$1244,MATCH(R13,'データ'!$A$880:$A$1244,0),$A$2),INDEX('データ'!$V$880:$AD$1244,MATCH(R13,'データ'!$A$880:$A$1244,0),$A$2)),0)=0,"",CHOOSE($A$3,INDEX('データ'!$B$880:$J$1244,MATCH(R13,'データ'!$A$880:$A$1244,0),$A$2),INDEX('データ'!$L$880:$T$1244,MATCH(R13,'データ'!$A$880:$A$1244,0),$A$2),INDEX('データ'!$V$880:$AD$1244,MATCH(R13,'データ'!$A$880:$A$1244,0),$A$2))),"") -> 3641 | S14: =IF(MONTH(S13)=6,IF(IFERROR(CHOOSE($A$3,INDEX('データ'!$B$880:$J$1244,MATCH(S13,'データ'!$A$880:$A$1244,0),$A$2),INDEX('データ'!$L$880:$T$1244,MATCH(S13,'データ'!$A$880:$A$1244,0),$A$2),INDEX('データ'!$V$880:$AD$1244,MATCH(S13,'データ'!$A$880:$A$1244,0),$A$2)),0)=0,"",CHOOSE($A$3,INDEX('データ'!$B$880:$J$1244,MATCH(S13,'データ'!$A$880:$A$1244,0),$A$2),INDEX('データ'!$L$880:$T$1244,MATCH(S13,'データ'!$A$880:$A$1244,0),$A$2),INDEX('データ'!$V$880:$AD$1244,MATCH(S13,'データ'!$A$880:$A$1244,0),$A$2))),"") -> 3126 | T14: =IF(MONTH(T13)=6,IF(IFERROR(CHOOSE($A$3,INDEX('データ'!$B$880:$J$1244,MATCH(T13,'データ'!$A$880:$A$1244,0),$A$2),INDEX('データ'!$L$880:$T$1244,MATCH(T13,'データ'!$A$880:$A$1244,0),$A$2),INDEX('データ'!$V$880:$AD$1244,MATCH(T13,'データ'!$A$880:$A$1244,0),$A$2)),0)=0,"",CHOOSE($A$3,INDEX('データ'!$B$880:$J$1244,MATCH(T13,'データ'!$A$880:$A$1244,0),$A$2),INDEX('データ'!$L$880:$T$1244,MATCH(T13,'データ'!$A$880:$A$1244,0),$A$2),INDEX('データ'!$V$880:$AD$1244,MATCH(T13,'データ'!$A$880:$A$1244,0),$A$2))),"") -> 3011 | U14: =IF(MONTH(U13)=6,IF(IFERROR(CHOOSE($A$3,INDEX('データ'!$B$880:$J$1244,MATCH(U13,'データ'!$A$880:$A$1244,0),$A$2),INDEX('データ'!$L$880:$T$1244,MATCH(U13,'データ'!$A$880:$A$1244,0),$A$2),INDEX('データ'!$V$880:$AD$1244,MATCH(U13,'データ'!$A$880:$A$1244,0),$A$2)),0)=0,"",CHOOSE($A$3,INDEX('データ'!$B$880:$J$1244,MATCH(U13,'データ'!$A$880:$A$1244,0),$A$2),INDEX('データ'!$L$880:$T$1244,MATCH(U13,'データ'!$A$880:$A$1244,0),$A$2),INDEX('データ'!$V$880:$AD$1244,MATCH(U13,'データ'!$A$880:$A$1244,0),$A$2))),"") -> 2705 | V14: =IF(MONTH(V13)=6,IF(IFERROR(CHOOSE($A$3,INDEX('データ'!$B$880:$J$1244,MATCH(V13,'データ'!$A$880:$A$1244,0),$A$2),INDEX('データ'!$L$880:$T$1244,MATCH(V13,'データ'!$A$880:$A$1244,0),$A$2),INDEX('データ'!$V$880:$AD$1244,MATCH(V13,'データ'!$A$880:$A$1244,0),$A$2)),0)=0,"",CHOOSE($A$3,INDEX('データ'!$B$880:$J$1244,MATCH(V13,'データ'!$A$880:$A$1244,0),$A$2),INDEX('データ'!$L$880:$T$1244,MATCH(V13,'データ'!$A$880:$A$1244,0),$A$2),INDEX('データ'!$V$880:$AD$1244,MATCH(V13,'データ'!$A$880:$A$1244,0),$A$2))),"") -> 3011 | W14: =IF(MONTH(W13)=6,IF(IFERROR(CHOOSE($A$3,INDEX('データ'!$B$880:$J$1244,MATCH(W13,'データ'!$A$880:$A$1244,0),$A$2),INDEX('データ'!$L$880:$T$1244,MATCH(W13,'データ'!$A$880:$A$1244,0),$A$2),INDEX('データ'!$V$880:$AD$1244,MATCH(W13,'データ'!$A$880:$A$1244,0),$A$2)),0)=0,"",CHOOSE($A$3,INDEX('データ'!$B$880:$J$1244,MATCH(W13,'データ'!$A$880:$A$1244,0),$A$2),INDEX('データ'!$L$880:$T$1244,MATCH(W13,'データ'!$A$880:$A$1244,0),$A$2),INDEX('データ'!$V$880:$AD$1244,MATCH(W13,'データ'!$A$880:$A$1244,0),$A$2))),"") | X14: =IF(MONTH(X13)=6,IF(IFERROR(CHOOSE($A$3,INDEX('データ'!$B$880:$J$1244,MATCH(X13,'データ'!$A$880:$A$1244,0),$A$2),INDEX('データ'!$L$880:$T$1244,MATCH(X13,'データ'!$A$880:$A$1244,0),$A$2),INDEX('データ'!$V$880:$AD$1244,MATCH(X13,'データ'!$A$880:$A$1244,0),$A$2)),0)=0,"",CHOOSE($A$3,INDEX('データ'!$B$880:$J$1244,MATCH(X13,'データ'!$A$880:$A$1244,0),$A$2),INDEX('データ'!$L$880:$T$1244,MATCH(X13,'データ'!$A$880:$A$1244,0),$A$2),INDEX('データ'!$V$880:$AD$1244,MATCH(X13,'データ'!$A$880:$A$1244,0),$A$2))),"") | Z14: =IF(MONTH(Z13)=7,IF(IFERROR(CHOOSE($A$3,INDEX('データ'!$B$880:$J$1244,MATCH(Z13,'データ'!$A$880:$A$1244,0),$A$2),INDEX('データ'!$L$880:$T$1244,MATCH(Z13,'データ'!$A$880:$A$1244,0),$A$2),INDEX('データ'!$V$880:$AD$1244,MATCH(Z13,'データ'!$A$880:$A$1244,0),$A$2)),0)=0,"",CHOOSE($A$3,INDEX('データ'!$B$880:$J$1244,MATCH(Z13,'データ'!$A$880:$A$1244,0),$A$2),INDEX('データ'!$L$880:$T$1244,MATCH(Z13,'データ'!$A$880:$A$1244,0),$A$2),INDEX('データ'!$V$880:$AD$1244,MATCH(Z13,'データ'!$A$880:$A$1244,0),$A$2))),"") | AA14: =IF(MONTH(AA13)=7,IF(IFERROR(CHOOSE($A$3,INDEX('データ'!$B$880:$J$1244,MATCH(AA13,'データ'!$A$880:$A$1244,0),$A$2),INDEX('データ'!$L$880:$T$1244,MATCH(AA13,'データ'!$A$880:$A$1244,0),$A$2),INDEX('データ'!$V$880:$AD$1244,MATCH(AA13,'データ'!$A$880:$A$1244,0),$A$2)),0)=0,"",CHOOSE($A$3,INDEX('データ'!$B$880:$J$1244,MATCH(AA13,'データ'!$A$880:$A$1244,0),$A$2),INDEX('データ'!$L$880:$T$1244,MATCH(AA13,'データ'!$A$880:$A$1244,0),$A$2),INDEX('データ'!$V$880:$AD$1244,MATCH(AA13,'データ'!$A$880:$A$1244,0),$A$2))),"") -> 3363 | AB14: =IF(MONTH(AB13)=7,IF(IFERROR(CHOOSE($A$3,INDEX('データ'!$B$880:$J$1244,MATCH(AB13,'データ'!$A$880:$A$1244,0),$A$2),INDEX('データ'!$L$880:$T$1244,MATCH(AB13,'データ'!$A$880:$A$1244,0),$A$2),INDEX('データ'!$V$880:$AD$1244,MATCH(AB13,'データ'!$A$880:$A$1244,0),$A$2)),0)=0,"",CHOOSE($A$3,INDEX('データ'!$B$880:$J$1244,MATCH(AB13,'データ'!$A$880:$A$1244,0),$A$2),INDEX('データ'!$L$880:$T$1244,MATCH(AB13,'データ'!$A$880:$A$1244,0),$A$2),INDEX('データ'!$V$880:$AD$1244,MATCH(AB13,'データ'!$A$880:$A$1244,0),$A$2))),"") -> 3228 | AC14: =IF(MONTH(AC13)=7,IF(IFERROR(CHOOSE($A$3,INDEX('データ'!$B$880:$J$1244,MATCH(AC13,'データ'!$A$880:$A$1244,0),$A$2),INDEX('データ'!$L$880:$T$1244,MATCH(AC13,'データ'!$A$880:$A$1244,0),$A$2),INDEX('データ'!$V$880:$AD$1244,MATCH(AC13,'データ'!$A$880:$A$1244,0),$A$2)),0)=0,"",CHOOSE($A$3,INDEX('データ'!$B$880:$J$1244,MATCH(AC13,'データ'!$A$880:$A$1244,0),$A$2),INDEX('データ'!$L$880:$T$1244,MATCH(AC13,'データ'!$A$880:$A$1244,0),$A$2),INDEX('データ'!$V$880:$AD$1244,MATCH(AC13,'データ'!$A$880:$A$1244,0),$A$2))),"") -> 3353 | AD14: =IF(MONTH(AD13)=7,IF(IFERROR(CHOOSE($A$3,INDEX('データ'!$B$880:$J$1244,MATCH(AD13,'データ'!$A$880:$A$1244,0),$A$2),INDEX('データ'!$L$880:$T$1244,MATCH(AD13,'データ'!$A$880:$A$1244,0),$A$2),INDEX('データ'!$V$880:$AD$1244,MATCH(AD13,'データ'!$A$880:$A$1244,0),$A$2)),0)=0,"",CHOOSE($A$3,INDEX('データ'!$B$880:$J$1244,MATCH(AD13,'データ'!$A$880:$A$1244,0),$A$2),INDEX('データ'!$L$880:$T$1244,MATCH(AD13,'データ'!$A$880:$A$1244,0),$A$2),INDEX('データ'!$V$880:$AD$1244,MATCH(AD13,'データ'!$A$880:$A$1244,0),$A$2))),"") -> 3222 | AE14: =IF(MONTH(AE13)=7,IF(IFERROR(CHOOSE($A$3,INDEX('データ'!$B$880:$J$1244,MATCH(AE13,'データ'!$A$880:$A$1244,0),$A$2),INDEX('データ'!$L$880:$T$1244,MATCH(AE13,'データ'!$A$880:$A$1244,0),$A$2),INDEX('データ'!$V$880:$AD$1244,MATCH(AE13,'データ'!$A$880:$A$1244,0),$A$2)),0)=0,"",CHOOSE($A$3,INDEX('データ'!$B$880:$J$1244,MATCH(AE13,'データ'!$A$880:$A$1244,0),$A$2),INDEX('データ'!$L$880:$T$1244,MATCH(AE13,'データ'!$A$880:$A$1244,0),$A$2),INDEX('データ'!$V$880:$AD$1244,MATCH(AE13,'データ'!$A$880:$A$1244,0),$A$2))),"") | AF14: =IF(MONTH(AF13)=7,IF(IFERROR(CHOOSE($A$3,INDEX('データ'!$B$880:$J$1244,MATCH(AF13,'データ'!$A$880:$A$1244,0),$A$2),INDEX('データ'!$L$880:$T$1244,MATCH(AF13,'データ'!$A$880:$A$1244,0),$A$2),INDEX('データ'!$V$880:$AD$1244,MATCH(AF13,'データ'!$A$880:$A$1244,0),$A$2)),0)=0,"",CHOOSE($A$3,INDEX('データ'!$B$880:$J$1244,MATCH(AF13,'データ'!$A$880:$A$1244,0),$A$2),INDEX('データ'!$L$880:$T$1244,MATCH(AF13,'データ'!$A$880:$A$1244,0),$A$2),INDEX('データ'!$V$880:$AD$1244,MATCH(AF13,'データ'!$A$880:$A$1244,0),$A$2))),"")
B15: =DATE(2025,4,1)-WEEKDAY(DATE(2025,4,1),2)+29 -> 45775 | C15: =DATE(2025,4,1)-WEEKDAY(DATE(2025,4,1),2)+30 -> 45776 | D15: =DATE(2025,4,1)-WEEKDAY(DATE(2025,4,1),2)+31 -> 45777 | E15: =DATE(2025,4,1)-WEEKDAY(DATE(2025,4,1),2)+32 -> 45778 | F15: =DATE(2025,4,1)-WEEKDAY(DATE(2025,4,1),2)+33 -> 45779 | G15: =DATE(2025,4,1)-WEEKDAY(DATE(2025,4,1),2)+34 -> 45780 | H15: =DATE(2025,4,1)-WEEKDAY(DATE(2025,4,1),2)+35 -> 45781 | J15: =DATE(2025,5,1)-WEEKDAY(DATE(2025,5,1),2)+29 -> 45803 | K15: =DATE(2025,5,1)-WEEKDAY(DATE(2025,5,1),2)+30 -> 45804 | L15: =DATE(2025,5,1)-WEEKDAY(DATE(2025,5,1),2)+31 -> 45805 | M15: =DATE(2025,5,1)-WEEKDAY(DATE(2025,5,1),2)+32 -> 45806 | N15: =DATE(2025,5,1)-WEEKDAY(DATE(2025,5,1),2)+33 -> 45807 | O15: =DATE(2025,5,1)-WEEKDAY(DATE(2025,5,1),2)+34 -> 45808 | P15: =DATE(2025,5,1)-WEEKDAY(DATE(2025,5,1),2)+35 -> 45809 | R15: =DATE(2025,6,1)-WEEKDAY(DATE(2025,6,1),2)+29 -> 45831 | S15: =DATE(2025,6,1)-WEEKDAY(DATE(2025,6,1),2)+30 -> 45832 | T15: =DATE(2025,6,1)-WEEKDAY(DATE(2025,6,1),2)+31 -> 45833 | U15: =DATE(2025,6,1)-WEEKDAY(DATE(2025,6,1),2)+32 -> 45834 | V15: =DATE(2025,6,1)-WEEKDAY(DATE(2025,6,1),2)+33 -> 45835 | W15: =DATE(2025,6,1)-WEEKDAY(DATE(2025,6,1),2)+34 -> 45836 | X15: =DATE(2025,6,1)-WEEKDAY(DATE(2025,6,1),2)+35 -> 45837 | Z15: =DATE(2025,7,1)-WEEKDAY(DATE(2025,7,1),2)+29 -> 45866 | AA15: =DATE(2025,7,1)-WEEKDAY(DATE(2025,7,1),2)+30 -> 45867 | AB15: =DATE(2025,7,1)-WEEKDAY(DATE(2025,7,1),2)+31 -> 45868 | AC15: =DATE(2025,7,1)-WEEKDAY(DATE(2025,7,1),2)+32 -> 45869 | AD15: =DATE(2025,7,1)-WEEKDAY(DATE(2025,7,1),2)+33 -> 45870 | AE15: =DATE(2025,7,1)-WEEKDAY(DATE(2025,7,1),2)+34 -> 45871 | AF15: =DATE(2025,7,1)-WEEKDAY(DATE(2025,7,1),2)+35 -> 45872
B16: =IF(MONTH(B15)=4,IF(IFERROR(CHOOSE($A$3,INDEX('データ'!$B$880:$J$1244,MATCH(B15,'データ'!$A$880:$A$1244,0),$A$2),INDEX('データ'!$L$880:$T$1244,MATCH(B15,'データ'!$A$880:$A$1244,0),$A$2),INDEX('データ'!$V$880:$AD$1244,MATCH(B15,'データ'!$A$880:$A$1244,0),$A$2)),0)=0,"",CHOOSE($A$3,INDEX('データ'!$B$880:$J$1244,MATCH(B15,'データ'!$A$880:$A$1244,0),$A$2),INDEX('データ'!$L$880:$T$1244,MATCH(B15,'データ'!$A$880:$A$1244,0),$A$2),INDEX('データ'!$V$880:$AD$1244,MATCH(B15,'データ'!$A$880:$A$1244,0),$A$2))),"") -> 4494 | C16: =IF(MONTH(C15)=4,IF(IFERROR(CHOOSE($A$3,INDEX('データ'!$B$880:$J$1244,MATCH(C15,'データ'!$A$880:$A$1244,0),$A$2),INDEX('データ'!$L$880:$T$1244,MATCH(C15,'データ'!$A$880:$A$1244,0),$A$2),INDEX('データ'!$V$880:$AD$1244,MATCH(C15,'データ'!$A$880:$A$1244,0),$A$2)),0)=0,"",CHOOSE($A$3,INDEX('データ'!$B$880:$J$1244,MATCH(C15,'データ'!$A$880:$A$1244,0),$A$2),INDEX('データ'!$L$880:$T$1244,MATCH(C15,'データ'!$A$880:$A$1244,0),$A$2),INDEX('データ'!$V$880:$AD$1244,MATCH(C15,'データ'!$A$880:$A$1244,0),$A$2))),"") | D16: =IF(MONTH(D15)=4,IF(IFERROR(CHOOSE($A$3,INDEX('データ'!$B$880:$J$1244,MATCH(D15,'データ'!$A$880:$A$1244,0),$A$2),INDEX('データ'!$L$880:$T$1244,MATCH(D15,'データ'!$A$880:$A$1244,0),$A$2),INDEX('データ'!$V$880:$AD$1244,MATCH(D15,'データ'!$A$880:$A$1244,0),$A$2)),0)=0,"",CHOOSE($A$3,INDEX('データ'!$B$880:$J$1244,MATCH(D15,'データ'!$A$880:$A$1244,0),$A$2),INDEX('データ'!$L$880:$T$1244,MATCH(D15,'データ'!$A$880:$A$1244,0),$A$2),INDEX('データ'!$V$880:$AD$1244,MATCH(D15,'データ'!$A$880:$A$1244,0),$A$2))),"") -> 4200 | E16: =IF(MONTH(E15)=4,IF(IFERROR(CHOOSE($A$3,INDEX('データ'!$B$880:$J$1244,MATCH(E15,'データ'!$A$880:$A$1244,0),$A$2),INDEX('データ'!$L$880:$T$1244,MATCH(E15,'データ'!$A$880:$A$1244,0),$A$2),INDEX('データ'!$V$880:$AD$1244,MATCH(E15,'データ'!$A$880:$A$1244,0),$A$2)),0)=0,"",CHOOSE($A$3,INDEX('データ'!$B$880:$J$1244,MATCH(E15,'データ'!$A$880:$A$1244,0),$A$2),INDEX('データ'!$L$880:$T$1244,MATCH(E15,'データ'!$A$880:$A$1244,0),$A$2),INDEX('データ'!$V$880:$AD$1244,MATCH(E15,'データ'!$A$880:$A$1244,0),$A$2))),"") | F16: =IF(MONTH(F15)=4,IF(IFERROR(CHOOSE($A$3,INDEX('データ'!$B$880:$J$1244,MATCH(F15,'データ'!$A$880:$A$1244,0),$A$2),INDEX('データ'!$L$880:$T$1244,MATCH(F15,'データ'!$A$880:$A$1244,0),$A$2),INDEX('データ'!$V$880:$AD$1244,MATCH(F15,'データ'!$A$880:$A$1244,0),$A$2)),0)=0,"",CHOOSE($A$3,INDEX('データ'!$B$880:$J$1244,MATCH(F15,'データ'!$A$880:$A$1244,0),$A$2),INDEX('データ'!$L$880:$T$1244,MATCH(F15,'データ'!$A$880:$A$1244,0),$A$2),INDEX('データ'!$V$880:$AD$1244,MATCH(F15,'データ'!$A$880:$A$1244,0),$A$2))),"") | G16: =IF(MONTH(G15)=4,IF(IFERROR(CHOOSE($A$3,INDEX('データ'!$B$880:$J$1244,MATCH(G15,'データ'!$A$880:$A$1244,0),$A$2),INDEX('データ'!$L$880:$T$1244,MATCH(G15,'データ'!$A$880:$A$1244,0),$A$2),INDEX('データ'!$V$880:$AD$1244,MATCH(G15,'データ'!$A$880:$A$1244,0),$A$2)),0)=0,"",CHOOSE($A$3,INDEX('データ'!$B$880:$J$1244,MATCH(G15,'データ'!$A$880:$A$1244,0),$A$2),INDEX('データ'!$L$880:$T$1244,MATCH(G15,'データ'!$A$880:$A$1244,0),$A$2),INDEX('データ'!$V$880:$AD$1244,MATCH(G15,'データ'!$A$880:$A$1244,0),$A$2))),"") | H16: =IF(MONTH(H15)=4,IF(IFERROR(CHOOSE($A$3,INDEX('データ'!$B$880:$J$1244,MATCH(H15,'データ'!$A$880:$A$1244,0),$A$2),INDEX('データ'!$L$880:$T$1244,MATCH(H15,'データ'!$A$880:$A$1244,0),$A$2),INDEX('データ'!$V$880:$AD$1244,MATCH(H15,'データ'!$A$880:$A$1244,0),$A$2)),0)=0,"",CHOOSE($A$3,INDEX('データ'!$B$880:$J$1244,MATCH(H15,'データ'!$A$880:$A$1244,0),$A$2),INDEX('データ'!$L$880:$T$1244,MATCH(H15,'データ'!$A$880:$A$1244,0),$A$2),INDEX('データ'!$V$880:$AD$1244,MATCH(H15,'データ'!$A$880:$A$1244,0),$A$2))),"") | J16: =IF(MONTH(J15)=5,IF(IFERROR(CHOOSE($A$3,INDEX('データ'!$B$880:$J$1244,MATCH(J15,'データ'!$A$880:$A$1244,0),$A$2),INDEX('データ'!$L$880:$T$1244,MATCH(J15,'データ'!$A$880:$A$1244,0),$A$2),INDEX('データ'!$V$880:$AD$1244,MATCH(J15,'データ'!$A$880:$A$1244,0),$A$2)),0)=0,"",CHOOSE($A$3,INDEX('データ'!$B$880:$J$1244,MATCH(J15,'データ'!$A$880:$A$1244,0),$A$2),INDEX('データ'!$L$880:$T$1244,MATCH(J15,'データ'!$A$880:$A$1244,0),$A$2),INDEX('データ'!$V$880:$AD$1244,MATCH(J15,'データ'!$A$880:$A$1244,0),$A$2))),"") -> 3543 | K16: =IF(MONTH(K15)=5,IF(IFERROR(CHOOSE($A$3,INDEX('データ'!$B$880:$J$1244,MATCH(K15,'データ'!$A$880:$A$1244,0),$A$2),INDEX('データ'!$L$880:$T$1244,MATCH(K15,'データ'!$A$880:$A$1244,0),$A$2),INDEX('データ'!$V$880:$AD$1244,MATCH(K15,'データ'!$A$880:$A$1244,0),$A$2)),0)=0,"",CHOOSE($A$3,INDEX('データ'!$B$880:$J$1244,MATCH(K15,'データ'!$A$880:$A$1244,0),$A$2),INDEX('データ'!$L$880:$T$1244,MATCH(K15,'データ'!$A$880:$A$1244,0),$A$2),INDEX('データ'!$V$880:$AD$1244,MATCH(K15,'データ'!$A$880:$A$1244,0),$A$2))),"") -> 3016 | L16: =IF(MONTH(L15)=5,IF(IFERROR(CHOOSE($A$3,INDEX('データ'!$B$880:$J$1244,MATCH(L15,'データ'!$A$880:$A$1244,0),$A$2),INDEX('データ'!$L$880:$T$1244,MATCH(L15,'データ'!$A$880:$A$1244,0),$A$2),INDEX('データ'!$V$880:$AD$1244,MATCH(L15,'データ'!$A$880:$A$1244,0),$A$2)),0)=0,"",CHOOSE($A$3,INDEX('データ'!$B$880:$J$1244,MATCH(L15,'データ'!$A$880:$A$1244,0),$A$2),INDEX('データ'!$L$880:$T$1244,MATCH(L15,'データ'!$A$880:$A$1244,0),$A$2),INDEX('データ'!$V$880:$AD$1244,MATCH(L15,'データ'!$A$880:$A$1244,0),$A$2))),"") -> 2859 | M16: =IF(MONTH(M15)=5,IF(IFERROR(CHOOSE($A$3,INDEX('データ'!$B$880:$J$1244,MATCH(M15,'データ'!$A$880:$A$1244,0),$A$2),INDEX('データ'!$L$880:$T$1244,MATCH(M15,'データ'!$A$880:$A$1244,0),$A$2),INDEX('データ'!$V$880:$AD$1244,MATCH(M15,'データ'!$A$880:$A$1244,0),$A$2)),0)=0,"",CHOOSE($A$3,INDEX('データ'!$B$880:$J$1244,MATCH(M15,'データ'!$A$880:$A$1244,0),$A$2),INDEX('データ'!$L$880:$T$1244,MATCH(M15,'データ'!$A$880:$A$1244,0),$A$2),INDEX('データ'!$V$880:$AD$1244,MATCH(M15,'データ'!$A$880:$A$1244,0),$A$2))),"") -> 2828 | N16: =IF(MONTH(N15)=5,IF(IFERROR(CHOOSE($A$3,INDEX('データ'!$B$880:$J$1244,MATCH(N15,'データ'!$A$880:$A$1244,0),$A$2),INDEX('データ'!$L$880:$T$1244,MATCH(N15,'データ'!$A$880:$A$1244,0),$A$2),INDEX('データ'!$V$880:$AD$1244,MATCH(N15,'データ'!$A$880:$A$1244,0),$A$2)),0)=0,"",CHOOSE($A$3,INDEX('データ'!$B$880:$J$1244,MATCH(N15,'データ'!$A$880:$A$1244,0),$A$2),INDEX('データ'!$L$880:$T$1244,MATCH(N15,'データ'!$A$880:$A$1244,0),$A$2),INDEX('データ'!$V$880:$AD$1244,MATCH(N15,'データ'!$A$880:$A$1244,0),$A$2))),"") -> 2824 | O16: =IF(MONTH(O15)=5,IF(IFERROR(CHOOSE($A$3,INDEX('データ'!$B$880:$J$1244,MATCH(O15,'データ'!$A$880:$A$1244,0),$A$2),INDEX('データ'!$L$880:$T$1244,MATCH(O15,'データ'!$A$880:$A$1244,0),$A$2),INDEX('データ'!$V$880:$AD$1244,MATCH(O15,'データ'!$A$880:$A$1244,0),$A$2)),0)=0,"",CHOOSE($A$3,INDEX('データ'!$B$880:$J$1244,MATCH(O15,'データ'!$A$880:$A$1244,0),$A$2),INDEX('データ'!$L$880:$T$1244,MATCH(O15,'データ'!$A$880:$A$1244,0),$A$2),INDEX('データ'!$V$880:$AD$1244,MATCH(O15,'データ'!$A$880:$A$1244,0),$A$2))),"") | P16: =IF(MONTH(P15)=5,IF(IFERROR(CHOOSE($A$3,INDEX('データ'!$B$880:$J$1244,MATCH(P15,'データ'!$A$880:$A$1244,0),$A$2),INDEX('データ'!$L$880:$T$1244,MATCH(P15,'データ'!$A$880:$A$1244,0),$A$2),INDEX('データ'!$V$880:$AD$1244,MATCH(P15,'データ'!$A$880:$A$1244,0),$A$2)),0)=0,"",CHOOSE($A$3,INDEX('データ'!$B$880:$J$1244,MATCH(P15,'データ'!$A$880:$A$1244,0),$A$2),INDEX('データ'!$L$880:$T$1244,MATCH(P15,'データ'!$A$880:$A$1244,0),$A$2),INDEX('データ'!$V$880:$AD$1244,MATCH(P15,'データ'!$A$880:$A$1244,0),$A$2))),"") | R16: =IF(MONTH(R15)=6,IF(IFERROR(CHOOSE($A$3,INDEX('データ'!$B$880:$J$1244,MATCH(R15,'データ'!$A$880:$A$1244,0),$A$2),INDEX('データ'!$L$880:$T$1244,MATCH(R15,'データ'!$A$880:$A$1244,0),$A$2),INDEX('データ'!$V$880:$AD$1244,MATCH(R15,'データ'!$A$880:$A$1244,0),$A$2)),0)=0,"",CHOOSE($A$3,INDEX('データ'!$B$880:$J$1244,MATCH(R15,'データ'!$A$880:$A$1244,0),$A$2),INDEX('データ'!$L$880:$T$1244,MATCH(R15,'データ'!$A$880:$A$1244,0),$A$2),INDEX('データ'!$V$880:$AD$1244,MATCH(R15,'データ'!$A$880:$A$1244,0),$A$2))),"") -> 3103 | S16: =IF(MONTH(S15)=6,IF(IFERROR(CHOOSE($A$3,INDEX('データ'!$B$880:$J$1244,MATCH(S15,'データ'!$A$880:$A$1244,0),$A$2),INDEX('データ'!$L$880:$T$1244,MATCH(S15,'データ'!$A$880:$A$1244,0),$A$2),INDEX('データ'!$V$880:$AD$1244,MATCH(S15,'データ'!$A$880:$A$1244,0),$A$2)),0)=0,"",CHOOSE($A$3,INDEX('データ'!$B$880:$J$1244,MATCH(S15,'データ'!$A$880:$A$1244,0),$A$2),INDEX('データ'!$L$880:$T$1244,MATCH(S15,'データ'!$A$880:$A$1244,0),$A$2),INDEX('データ'!$V$880:$AD$1244,MATCH(S15,'データ'!$A$880:$A$1244,0),$A$2))),"") -> 2485 | T16: =IF(MONTH(T15)=6,IF(IFERROR(CHOOSE($A$3,INDEX('データ'!$B$880:$J$1244,MATCH(T15,'データ'!$A$880:$A$1244,0),$A$2),INDEX('データ'!$L$880:$T$1244,MATCH(T15,'データ'!$A$880:$A$1244,0),$A$2),INDEX('データ'!$V$880:$AD$1244,MATCH(T15,'データ'!$A$880:$A$1244,0),$A$2)),0)=0,"",CHOOSE($A$3,INDEX('データ'!$B$880:$J$1244,MATCH(T15,'データ'!$A$880:$A$1244,0),$A$2),INDEX('データ'!$L$880:$T$1244,MATCH(T15,'データ'!$A$880:$A$1244,0),$A$2),INDEX('データ'!$V$880:$AD$1244,MATCH(T15,'データ'!$A$880:$A$1244,0),$A$2))),"") -> 2831 | U16: =IF(MONTH(U15)=6,IF(IFERROR(CHOOSE($A$3,INDEX('データ'!$B$880:$J$1244,MATCH(U15,'データ'!$A$880:$A$1244,0),$A$2),INDEX('データ'!$L$880:$T$1244,MATCH(U15,'データ'!$A$880:$A$1244,0),$A$2),INDEX('データ'!$V$880:$AD$1244,MATCH(U15,'データ'!$A$880:$A$1244,0),$A$2)),0)=0,"",CHOOSE($A$3,INDEX('データ'!$B$880:$J$1244,MATCH(U15,'データ'!$A$880:$A$1244,0),$A$2),INDEX('データ'!$L$880:$T$1244,MATCH(U15,'データ'!$A$880:$A$1244,0),$A$2),INDEX('データ'!$V$880:$AD$1244,MATCH(U15,'データ'!$A$880:$A$1244,0),$A$2))),"") -> 2855 | V16: =IF(MONTH(V15)=6,IF(IFERROR(CHOOSE($A$3,INDEX('データ'!$B$880:$J$1244,MATCH(V15,'データ'!$A$880:$A$1244,0),$A$2),INDEX('データ'!$L$880:$T$1244,MATCH(V15,'データ'!$A$880:$A$1244,0),$A$2),INDEX('データ'!$V$880:$AD$1244,MATCH(V15,'データ'!$A$880:$A$1244,0),$A$2)),0)=0,"",CHOOSE($A$3,INDEX('データ'!$B$880:$J$1244,MATCH(V15,'データ'!$A$880:$A$1244,0),$A$2),INDEX('データ'!$L$880:$T$1244,MATCH(V15,'データ'!$A$880:$A$1244,0),$A$2),INDEX('データ'!$V$880:$AD$1244,MATCH(V15,'データ'!$A$880:$A$1244,0),$A$2))),"") -> 3235 | W16: =IF(MONTH(W15)=6,IF(IFERROR(CHOOSE($A$3,INDEX('データ'!$B$880:$J$1244,MATCH(W15,'データ'!$A$880:$A$1244,0),$A$2),INDEX('データ'!$L$880:$T$1244,MATCH(W15,'データ'!$A$880:$A$1244,0),$A$2),INDEX('データ'!$V$880:$AD$1244,MATCH(W15,'データ'!$A$880:$A$1244,0),$A$2)),0)=0,"",CHOOSE($A$3,INDEX('データ'!$B$880:$J$1244,MATCH(W15,'データ'!$A$880:$A$1244,0),$A$2),INDEX('データ'!$L$880:$T$1244,MATCH(W15,'データ'!$A$880:$A$1244,0),$A$2),INDEX('データ'!$V$880:$AD$1244,MATCH(W15,'データ'!$A$880:$A$1244,0),$A$2))),"") | X16: =IF(MONTH(X15)=6,IF(IFERROR(CHOOSE($A$3,INDEX('データ'!$B$880:$J$1244,MATCH(X15,'データ'!$A$880:$A$1244,0),$A$2),INDEX('データ'!$L$880:$T$1244,MATCH(X15,'データ'!$A$880:$A$1244,0),$A$2),INDEX('データ'!$V$880:$AD$1244,MATCH(X15,'データ'!$A$880:$A$1244,0),$A$2)),0)=0,"",CHOOSE($A$3,INDEX('データ'!$B$880:$J$1244,MATCH(X15,'データ'!$A$880:$A$1244,0),$A$2),INDEX('データ'!$L$880:$T$1244,MATCH(X15,'データ'!$A$880:$A$1244,0),$A$2),INDEX('データ'!$V$880:$AD$1244,MATCH(X15,'データ'!$A$880:$A$1244,0),$A$2))),"") | Z16: =IF(MONTH(Z15)=7,IF(IFERROR(CHOOSE($A$3,INDEX('データ'!$B$880:$J$1244,MATCH(Z15,'データ'!$A$880:$A$1244,0),$A$2),INDEX('データ'!$L$880:$T$1244,MATCH(Z15,'データ'!$A$880:$A$1244,0),$A$2),INDEX('データ'!$V$880:$AD$1244,MATCH(Z15,'データ'!$A$880:$A$1244,0),$A$2)),0)=0,"",CHOOSE($A$3,INDEX('データ'!$B$880:$J$1244,MATCH(Z15,'データ'!$A$880:$A$1244,0),$A$2),INDEX('データ'!$L$880:$T$1244,MATCH(Z15,'データ'!$A$880:$A$1244,0),$A$2),INDEX('データ'!$V$880:$AD$1244,MATCH(Z15,'データ'!$A$880:$A$1244,0),$A$2))),"") -> 3634 | AA16: =IF(MONTH(AA15)=7,IF(IFERROR(CHOOSE($A$3,INDEX('データ'!$B$880:$J$1244,MATCH(AA15,'データ'!$A$880:$A$1244,0),$A$2),INDEX('データ'!$L$880:$T$1244,MATCH(AA15,'データ'!$A$880:$A$1244,0),$A$2),INDEX('データ'!$V$880:$AD$1244,MATCH(AA15,'データ'!$A$880:$A$1244,0),$A$2)),0)=0,"",CHOOSE($A$3,INDEX('データ'!$B$880:$J$1244,MATCH(AA15,'データ'!$A$880:$A$1244,0),$A$2),INDEX('データ'!$L$880:$T$1244,MATCH(AA15,'データ'!$A$880:$A$1244,0),$A$2),INDEX('データ'!$V$880:$AD$1244,MATCH(AA15,'データ'!$A$880:$A$1244,0),$A$2))),"") -> 3178 | AB16: =IF(MONTH(AB15)=7,IF(IFERROR(CHOOSE($A$3,INDEX('データ'!$B$880:$J$1244,MATCH(AB15,'データ'!$A$880:$A$1244,0),$A$2),INDEX('データ'!$L$880:$T$1244,MATCH(AB15,'データ'!$A$880:$A$1244,0),$A$2),INDEX('データ'!$V$880:$AD$1244,MATCH(AB15,'データ'!$A$880:$A$1244,0),$A$2)),0)=0,"",CHOOSE($A$3,INDEX('データ'!$B$880:$J$1244,MATCH(AB15,'データ'!$A$880:$A$1244,0),$A$2),INDEX('データ'!$L$880:$T$1244,MATCH(AB15,'データ'!$A$880:$A$1244,0),$A$2),INDEX('データ'!$V$880:$AD$1244,MATCH(AB15,'データ'!$A$880:$A$1244,0),$A$2))),"") -> 3046 | AC16: =IF(MONTH(AC15)=7,IF(IFERROR(CHOOSE($A$3,INDEX('データ'!$B$880:$J$1244,MATCH(AC15,'データ'!$A$880:$A$1244,0),$A$2),INDEX('データ'!$L$880:$T$1244,MATCH(AC15,'データ'!$A$880:$A$1244,0),$A$2),INDEX('データ'!$V$880:$AD$1244,MATCH(AC15,'データ'!$A$880:$A$1244,0),$A$2)),0)=0,"",CHOOSE($A$3,INDEX('データ'!$B$880:$J$1244,MATCH(AC15,'データ'!$A$880:$A$1244,0),$A$2),INDEX('データ'!$L$880:$T$1244,MATCH(AC15,'データ'!$A$880:$A$1244,0),$A$2),INDEX('データ'!$V$880:$AD$1244,MATCH(AC15,'データ'!$A$880:$A$1244,0),$A$2))),"") -> 2763 | AD16: =IF(MONTH(AD15)=7,IF(IFERROR(CHOOSE($A$3,INDEX('データ'!$B$880:$J$1244,MATCH(AD15,'データ'!$A$880:$A$1244,0),$A$2),INDEX('データ'!$L$880:$T$1244,MATCH(AD15,'データ'!$A$880:$A$1244,0),$A$2),INDEX('データ'!$V$880:$AD$1244,MATCH(AD15,'データ'!$A$880:$A$1244,0),$A$2)),0)=0,"",CHOOSE($A$3,INDEX('データ'!$B$880:$J$1244,MATCH(AD15,'データ'!$A$880:$A$1244,0),$A$2),INDEX('データ'!$L$880:$T$1244,MATCH(AD15,'データ'!$A$880:$A$1244,0),$A$2),INDEX('データ'!$V$880:$AD$1244,MATCH(AD15,'データ'!$A$880:$A$1244,0),$A$2))),"") | AE16: =IF(MONTH(AE15)=7,IF(IFERROR(CHOOSE($A$3,INDEX('データ'!$B$880:$J$1244,MATCH(AE15,'データ'!$A$880:$A$1244,0),$A$2),INDEX('データ'!$L$880:$T$1244,MATCH(AE15,'データ'!$A$880:$A$1244,0),$A$2),INDEX('データ'!$V$880:$AD$1244,MATCH(AE15,'データ'!$A$880:$A$1244,0),$A$2)),0)=0,"",CHOOSE($A$3,INDEX('データ'!$B$880:$J$1244,MATCH(AE15,'データ'!$A$880:$A$1244,0),$A$2),INDEX('データ'!$L$880:$T$1244,MATCH(AE15,'データ'!$A$880:$A$1244,0),$A$2),INDEX('データ'!$V$880:$AD$1244,MATCH(AE15,'データ'!$A$880:$A$1244,0),$A$2))),"") | AF16: =IF(MONTH(AF15)=7,IF(IFERROR(CHOOSE($A$3,INDEX('データ'!$B$880:$J$1244,MATCH(AF15,'データ'!$A$880:$A$1244,0),$A$2),INDEX('データ'!$L$880:$T$1244,MATCH(AF15,'データ'!$A$880:$A$1244,0),$A$2),INDEX('データ'!$V$880:$AD$1244,MATCH(AF15,'データ'!$A$880:$A$1244,0),$A$2)),0)=0,"",CHOOSE($A$3,INDEX('データ'!$B$880:$J$1244,MATCH(AF15,'データ'!$A$880:$A$1244,0),$A$2),INDEX('データ'!$L$880:$T$1244,MATCH(AF15,'データ'!$A$880:$A$1244,0),$A$2),INDEX('データ'!$V$880:$AD$1244,MATCH(AF15,'データ'!$A$880:$A$1244,0),$A$2))),"")
