Workbook

Sheet 年度
A2: 5 | B2: 年度

Sheet 全伝票
I1: 179962946555 | J1: 0 | K1: 0 | L1: 1408906 | M1: 537718 | N1: 44539401683 | O1: 4535078073 | P1: 130886520175 | Q1: 0
A2: 事業 | B2: 予算コード | C2: 予算コード | D2: 款 | E2: 項 | F2: 目 | G2: 節 | H2: 細節 | I2: 執行額 | J2: 課税 | O2: 非課税 | P2: 不課税
J3: 3 | K3: 5 | L3: 8 | M3: 8 | N3: 10 | O3: 21 | P3: 31
A4: 1 | B4: 1120110 | C4: 112011010 | D4: 資本的収入 | E4: 企業債 | F4: 建設企業債 | G4: 公共下水道事業債 | H4: 一般債 | I4: 8822500000 | J4: 0 | K4: 0 | L4: 0 | M4: 0 | N4: 0 | O4: 0 | P4: 8822500000 | Q4: 0
A5: 1 | B5: 1120110 | C5: 112011011 | D5: 資本的収入 | E5: 企業債 | F5: 建設企業債 | G5: 公共下水道事業債 | H5: 特別債 | I5: 0 | J5: 0 | K5: 0 | L5: 0 | M5: 0 | N5: 0 | O5: 0 | P5: 0 | Q5: 0
A6: 1 | B6: 1120110 | C6: 112011012 | D6: 資本的収入 | E6: 企業債 | F6: 建設企業債 | G6: 公共下水道事業債 | H6: 一般債（復興関連） | I6: 0 | J6: 0 | K6: 0 | L6: 0 | M6: 0 | N6: 0 | O6: 0 | P6: 0 | Q6: 0
A7: 1 | B7: 1120111 | C7: 112011100 | D7: 資本的収入 | E7: 企業債 | F7: 建設企業債 | G7: 特定資金公共事業債 | I7: 0 | J7: 0 | K7: 0 | L7: 0 | M7: 0 | N7: 0 | O7: 0 | P7: 0 | Q7: 0
A8: 1 | B8: 1120112 | C8: 112011200 | D8: 資本的収入 | E8: 企業債 | F8: 建設企業債 | G8: 流域下水道事業債 | I8: 120200000 | J8: 0 | K8: 0 | L8: 0 | M8: 0 | N8: 0 | O8: 0 | P8: 120200000 | Q8: 0
A9: 1 | B9: 1120113 | C9: 112011300 | D9: 資本的収入 | E9: 企業債 | F9: 建設企業債 | G9: 資本費平準化債 | I9: 5632100000 | J9: 0 | K9: 0 | L9: 0 | M9: 0 | N9: 0 | O9: 0 | P9: 5632100000 | Q9: 0
A10: 1 | B10: 1120114 | C10: 112011400 | D10: 資本的収入 | E10: 企業債 | F10: 建設企業債 | G10: その他事業債 | I10: 0 | J10: 0 | K10: 0 | L10: 0 | M10: 0 | N10: 0 | O10: 0 | P10: 0 | Q10: 0
A11: 1 | B11: 1120116 | C11: 112011600 | D11: 資本的収入 | E11: 企業債 | F11: 建設企業債 | G11: 災害復旧事業債 | I11: 0 | J11: 0 | K11: 0 | L11: 0 | M11: 0 | N11: 0 | O11: 0 | P11: 0 | Q11: 0
A12: 1 | B12: 1120210 | C12: 112021000 | D12: 資本的収入 | E12: 企業債 | F12: 借換債 | G12: 公共下水道事業借換債 | I12: 0 | J12: 0 | K12: 0 | L12: 0 | M12: 0 | N12: 0 | O12: 0 | P12: 0 | Q12: 0
A13: 1 | B13: 1120220 | C13: 112022000 | D13: 資本的収入 | E13: 企業債 | F13: 借換債 | G13: 公営企業借換債 | I13: 0 | J13: 0 | K13: 0 | L13: 0 | M13: 0 | N13: 0 | O13: 0 | P13: 0 | Q13: 0
A14: 1 | B14: 1120230 | C14: 112023000 | D14: 資本的収入 | E14: 企業債 | F14: 借換債 | G14: 補償金免除繰上償還借換債 | I14: 0 | J14: 0 | K14: 0 | L14: 0 | M14: 0 | N14: 0 | O14: 0 | P14: 0 | Q14: 0
A15: 1 | B15: 1120240 | C15: 112024000 | D15: 資本的収入 | E15: 企業債 | F15: 借換債 | G15: 資本費平準化債（拡大分）借換債 | I15: 17007700000 | J15: 0 | K15: 0 | L15: 0 | M15: 0 | N15: 0 | O15: 0 | P15: 17007700000 | Q15: 0
A16: 1 | B16: 1120310 | C16: 112031000 | D16: 資本的収入 | E16: 企業債 | F16: 出資債 | G16: 公営企業出資債 | I16: 0 | J16: 0 | K16: 0 | L16: 0 | M16: 0 | N16: 0 | O16: 0 | P16: 0 | Q16: 0
A17: 1 | B17: 1140303 | C17: 114030300 | D17: 資本的収入 | E17: 長期借入金 | F17: 一般会計借入金 | G17: 一般会計借入金 | I17: 0 | J17: 0 | K17: 0 | L17: 0 | M17: 0 | N17: 0 | O17: 0 | P17: 0 | Q17: 0
A18: 1 | B18: 1160101 | C18: 116010100 | D18: 資本的収入 | E18: 一般会計出資金 | F18: 下水道建設費出資金 | G18: 下水道建設費出資金 | I18: 3566242000 | J18: 0 | K18: 0 | L18: 0 | M18: 0 | N18: 0 | O18: 0 | P18: 3566242000 | Q18: 0
A19: 1 | B19: 1160202 | C19: 116020200 | D19: 資本的収入 | E19: 一般会計出資金 | F19: その他出資金 | G19: その他出資金 | I19: 0 | J19: 0 | K19: 0 | L19: 0 | M19: 0 | N19: 0 | O19: 0 | P19: 0 | Q19: 0
A20: 1 | B20: 1180401 | C20: 118040101 | D20: 資本的収入 | E20: 国庫補助金 | F20: 国庫補助金 | G20: 公共下水道整備国庫補助金 | H20: 公共下水道整備国庫補助金 | I20: 5683800000 | J20: 0 | K20: 0 | L20: 0 | M20: 0 | N20: 0 | O20: 0 | P20: 5683800000 | Q20: 0
A21: 1 | B21: 1180401 | C21: 118040102 | D21: 資本的収入 | E21: 国庫補助金 | F21: 国庫補助金 | G21: 公共下水道整備国庫補助金 | H21: 公共下水道整備国庫補助金（復興関連） | I21: 0 | J21: 0 | K21: 0 | L21: 0 | M21: 0 | N21: 0 | O21: 0 | P21: 0 | Q21: 0
A22: 1 | B22: 1180402 | C22: 118040200 | D22: 資本的収入 | E22: 国庫補助金 | F22: 国庫補助金 | G22: その他国庫補助金 | I22: 0 | J22: 0 | K22: 0 | L22: 0 | M22: 0 | N22: 0 | O22: 0 | P22: 0 | Q22: 0
A23: 1 | B23: 1200630 | C23: 120063000 | D23: 資本的収入 | E23: 国庫委託金 | F23: 国庫委託金 | G23: 国庫委託金 | I23: 0 | J23: 0 | K23: 0 | L23: 0 | M23: 0 | N23: 0 | O23: 0 | P23: 0 | Q23: 0
A24: 1 | B24: 1300831 | C24: 130083100 | D24: 資本的収入 | E24: 県委託金 | F24: 県委託金 | G24: 県委託金 | I24: 0 | J24: 0 | K24: 0 | L24: 0 | M24: 0 | N24: 0 | O24: 0 | P24: 0 | Q24: 0
A25: 1 | B25: 1401010 | C25: 140101000 | D25: 資本的収入 | E25: 一般会計補助金 | F25: 一般会計補助金 | G25: 一般会計補助金 | I25: 0 | J25: 0 | K25: 0 | L25: 0 | M25: 0 | N25: 0 | O25: 0 | P25: 0 | Q25: 0
A26: 1 | B26: 1600101 | C26: 160010100 | D26: 資本的収入 | E26: 工事受託金 | F26: 工事受託金 | G26: 工事受託金 | I26: 24373083 | J26: 0 | K26: 0 | L26: 0 | M26: 0 | N26: 24373083 | O26: 0 | P26: 0 | Q26: 0
A27: 1 | B27: 1800606 | C27: 180060600 | D27: 資本的収入 | E27: 負担金 | F27: 受益者負担金 | G27: 受益者負担金 | I27: 8799605 | J27: 0 | K27: 0 | L27: 0 | M27: 0 | N27: 0 | O27: 0 | P27: 8799605 | Q27: 0
A28: 1 | B28: 1800808 | C28: 180080800 | D28: 資本的収入 | E28: 負担金 | F28: 工事負担金 | G28: 工事負担金 | I28: 530286509 | J28: 0 | K28: 0 | L28: 0 | M28: 0 | N28: 15318327 | O28: 0 | P28: 514968182 | Q28: 0
A29: 1 | B29: 1820101 | C29: 182010100 | D29: 資本的収入 | E29: 寄附金 | F29: 建設費寄附金 | G29: 建設費寄附金 | I29: 0 | J29: 0 | K29: 0 | L29: 0 | M29: 0 | N29: 0 | O29: 0 | P29: 0 | Q29: 0
A30: 1 | B30: 1840102 | C30: 184010200 | D30: 資本的収入 | E30: 水洗化貸付事業収入 | F30: 貸付企業債 | G30: 水洗便所貸付資金事業債 | I30: 0 | J30: 0 | K30: 0 | L30: 0 | M30: 0 | N30: 0 | O30: 0 | P30: 0 | Q30: 0
A31: 1 | B31: 1840304 | C31: 184030400 | D31: 資本的収入 | E31: 水洗化貸付事業収入 | F31: 一般会計借入金 | G31: 水洗便所改造資金貸付借入金 | I31: 0 | J31: 0 | K31: 0 | L31: 0 | M31: 0 | N31: 0 | O31: 0 | P31: 0 | Q31: 0
A32: 1 | B32: 1840305 | C32: 184030500 | D32: 資本的収入 | E32: 水洗化貸付事業収入 | F32: 一般会計借入金 | G32: し尿浄化槽廃止資金貸付借入金 | I32: 0 | J32: 0 | K32: 0 | L32: 0 | M32: 0 | N32: 0 | O32: 0 | P32: 0 | Q32: 0
A33: 1 | B33: 1840306 | C33: 184030600 | D33: 資本的収入 | E33: 水洗化貸付事業収入 | F33: 一般会計借入金 | G33: 排水設備改修資金貸付借入金 | I33: 0 | J33: 0 | K33: 0 | L33: 0 | M33: 0 | N33: 0 | O33: 0 | P33: 0 | Q33: 0
... A43: 1 | B43: 4810202 | C43: 481020200 | D43: 下水道事業収益 | E43: 営業収益 | F43: 下水道使用料 | G43: 下水道使用料 | I43: 20339840861 | J43: 0 | K43: 0 | L43: 0 | M43: 0 | N43: 20339840861 | O43: 0 | P43: 0 | Q43: 0
A44: 1 | B44: 4810404 | C44: 481040411 | D44: 下水道事業収益 | E44: 営業収益 | F44: 一般会計負担金 | G44: 雨水処理負担金 | H44: 維持管理費分 | I44: 2754671000 | J44: 0 | K44: 0 | L44: 0 | M44: 0 | N44: 0 | O44: 0 | P44: 2754671000 | Q44: 0
A45: 1 | B45: 4810404 | C45: 481040412 | D45: 下水道事業収益 | E45: 営業収益 | F45: 一般会計負担金 | G45: 雨水処理負担金 | H45: 減価償却費分 | I45: 7912710000 | J45: 0 | K45: 0 | L45: 0 | M45: 0 | N45: 0 | O45: 0 | P45: 7912710000 | Q45: 0
A46: 1 | B46: 4810404 | C46: 481040413 | D46: 下水道事業収益 | E46: 営業収益 | F46: 一般会計負担金 | G46: 雨水処理負担金 | H46: 支払利息分 | I46: 2138644000 | J46: 0 | K46: 0 | L46: 0 | M46: 0 | N46: 0 | O46: 0 | P46: 2138644000 | Q46: 0
A47: 1 | B47: 4810404 | C47: 481040415 | D47: 下水道事業収益 | E47: 営業収益 | F47: 一般会計負担金 | G47: 雨水処理負担金 | H47: 災害復旧応援分 | I47: 0 | J47: 0 | K47: 0 | L47: 0 | M47: 0 | N47: 0 | O47: 0 | P47: 0 | Q47: 0
A48: 1 | B48: 4810406 | C48: 481040600 | D48: 下水道事業収益 | E48: 営業収益 | F48: 一般会計負担金 | G48: 水質指導費負担金 | I48: 61778000 | J48: 0 | K48: 0 | L48: 0 | M48: 0 | N48: 0 | O48: 0 | P48: 61778000 | Q48: 0
A49: 1 | B49: 4810408 | C49: 481040800 | D49: 下水道事業収益 | E49: 営業収益 | F49: 一般会計負担金 | G49: 普及促進費負担金 | I49: 40039000 | J49: 0 | K49: 0 | L49: 0 | M49: 0 | N49: 0 | O49: 0 | P49: 40039000 | Q49: 0
A50: 1 | B50: 4810409 | C50: 481040900 | D50: 下水道事業収益 | E50: 営業収益 | F50: 一般会計負担金 | G50: 貸付事業費負担金 | I50: 14763000 | J50: 0 | K50: 0 | L50: 0 | M50: 0 | N50: 0 | O50: 0 | P50: 14763000 | Q50: 0
A51: 1 | B51: 4810415 | C51: 481041500 | D51: 下水道事業収益 | E51: 営業収益 | F51: 一般会計負担金 | G51: その他負担金 | I51: 0 | J51: 0 | K51: 0 | L51: 0 | M51: 0 | N51: 0 | O51: 0 | P51: 0 | Q51: 0
A52: 1 | B52: 4811214 | C52: 481121400 | D52: 下水道事業収益 | E52: 営業収益 | F52: 受託工事収益 | G52: 受託工事収益 | I52: 0 | J52: 0 | K52: 0 | L52: 0 | M52: 0 | N52: 0 | O52: 0 | P52: 0 | Q52: 0
A53: 1 | B53: 4811415 | C53: 481141500 | D53: 下水道事業収益 | E53: 営業収益 | F53: その他営業収益 | G53: 産物売却代金 | I53: 187826166 | J53: 0 | K53: 0 | L53: 0 | M53: 0 | N53: 187826166 | O53: 0 | P53: 0 | Q53: 0
A54: 1 | B54: 4811416 | C54: 481141600 | D54: 下水道事業収益 | E54: 営業収益 | F54: その他営業収益 | G54: 下水処理負担金 | I54: 0 | J54: 0 | K54: 0 | L54: 0 | M54: 0 | N54: 0 | O54: 0 | P54: 0 | Q54: 0
A55: 1 | B55: 4811417 | C55: 481141700 | D55: 下水道事業収益 | E55: 営業収益 | F55: その他営業収益 | G55: 業務受託収益 | I55: 1409733 | J55: 0 | K55: 0 | L55: 0 | M55: 0 | N55: 1409733 | O55: 0 | P55: 0 | Q55: 0
A56: 1 | B56: 4811418 | C56: 481141800 | D56: 下水道事業収益 | E56: 営業収益 | F56: その他営業収益 | G56: 補償金 | I56: 0 | J56: 0 | K56: 0 | L56: 0 | M56: 0 | N56: 0 | O56: 0 | P56: 0 | Q56: 0
A57: 1 | B57: 4811419 | C57: 481141915 | D57: 下水道事業収益 | E57: 営業収益 | F57: その他営業収益 | G57: 手数料 | H57: 証明手数料 | I57: 71970 | J57: 0 | K57: 0 | L57: 0 | M57: 0 | N57: 0 | O57: 71970 | P57: 0 | Q57: 0
A58: 1 | B58: 4811419 | C58: 481141916 | D58: 下水道事業収益 | E58: 営業収益 | F58: その他営業収益 | G58: 手数料 | H58: 指定業者登録等手数料 | I58: 539000 | J58: 0 | K58: 0 | L58: 0 | M58: 0 | N58: 0 | O58: 539000 | P58: 0 | Q58: 0
A59: 1 | B59: 4811419 | C59: 481141917 | D59: 下水道事業収益 | E59: 営業収益 | F59: その他営業収益 | G59: 手数料 | H59: その他手数料 | I59: 0 | J59: 0 | K59: 0 | L59: 0 | M59: 0 | N59: 0 | O59: 0 | P59: 0 | Q59: 0
A60: 1 | B60: 4811420 | C60: 481142000 | D60: 下水道事業収益 | E60: 営業収益 | F60: その他営業収益 | G60: 雑収益 | I60: 0 | J60: 0 | K60: 0 | L60: 0 | M60: 0 | N60: 0 | O60: 0 | P60: 0 | Q60: 0
A61: 1 | B61: 4820221 | C61: 482022100 | D61: 下水道事業収益 | E61: 営業外収益 | F61: 受取利息 | G61: 預金利息 | I61: 88770 | J61: 0 | K61: 0 | L61: 0 | M61: 0 | N61: 0 | O61: 88770 | P61: 0 | Q61: 0
A62: 1 | B62: 4820222 | C62: 482022200 | D62: 下水道事業収益 | E62: 営業外収益 | F62: 受取利息 | G62: 貸付金利息 | I62: 0 | J62: 0 | K62: 0 | L62: 0 | M62: 0 | N62: 0 | O62: 0 | P62: 0 | Q62: 0
A63: 1 | B63: 4820224 | C63: 482022400 | D63: 下水道事業収益 | E63: 営業外収益 | F63: 受取利息 | G63: 有価証券利息 | I63: 0 | J63: 0 | K63: 0 | L63: 0 | M63: 0 | N63: 0 | O63: 0 | P63: 0 | Q63: 0
A64: 1 | B64: 4820427 | C64: 482042700 | D64: 下水道事業収益 | E64: 営業外収益 | F64: 国庫補助金 | G64: 下水道緊急整備費国庫補助金 | I64: 0 | J64: 0 | K64: 0 | L64: 0 | M64: 0 | N64: 0 | O64: 0 | P64: 0 | Q64: 0
A65: 1 | B65: 4820428 | C65: 482042800 | D65: 下水道事業収益 | E65: 営業外収益 | F65: 国庫補助金 | G65: 水洗便所改造国庫補助金 | I65: 0 | J65: 0 | K65: 0 | L65: 0 | M65: 0 | N65: 0 | O65: 0 | P65: 0 | Q65: 0
A66: 1 | B66: 4820429 | C66: 482042900 | D66: 下水道事業収益 | E66: 営業外収益 | F66: 国庫補助金 | G66: その他国庫補助金 | I66: 0 | J66: 0 | K66: 0 | L66: 0 | M66: 0 | N66: 0 | O66: 0 | P66: 0 | Q66: 0
A67: 1 | B67: 4820501 | C67: 482050100 | D67: 下水道事業収益 | E67: 営業外収益 | F67: 県補助金 | G67: 県補助金 | I67: 0 | J67: 0 | K67: 0 | L67: 0 | M67: 0 | N67: 0 | O67: 0 | P67: 0 | Q67: 0
A68: 1 | B68: 4820630 | C68: 482063000 | D68: 下水道事業収益 | E68: 営業外収益 | F68: 国庫委託金 | G68: 国庫委託金 | I68: 0 | J68: 0 | K68: 0 | L68: 0 | M68: 0 | N68: 0 | O68: 0 | P68: 0 | Q68: 0
A69: 1 | B69: 4820831 | C69: 482083100 | D69: 下水道事業収益 | E69: 営業外収益 | F69: 県委託金 | G69: 県委託金 | I69: 0 | J69: 0 | K69: 0 | L69: 0 | M69: 0 | N69: 0 | O69: 0 | P69: 0 | Q69: 0
A70: 1 | B70: 4820932 | C70: 482093200 | D70: 下水道事業収益 | E70: 営業外収益 | F70: 負担金 | G70: 施設管理負担金 | I70: 37016600 | J70: 0 | K70: 0 | L70: 0 | M70: 0 | N70: 37016600 | O70: 0 | P70: 0 | Q70: 0
A71: 1 | B71: 4820933 | C71: 482093300 | D71: 下水道事業収益 | E71: 営業外収益 | F71: 負担金 | G71: 他会計負担金 | I71: 16476593 | J71: 0 | K71: 0 | L71: 0 | M71: 0 | N71: 0 | O71: 0 | P71: 16476593 | Q71: 0
A72: 1 | B72: 4821034 | C72: 482103411 | D72: 下水道事業収益 | E72: 営業外収益 | F72: 一般会計補助金 | G72: 汚水処理補助金 | H72: 維持管理費分 | I72: 0 | J72: 0 | K72: 0 | L72: 0 | M72: 0 | N72: 0 | O72: 0 | P72: 0 | Q72: 0
A73: 1 | B73: 4821034 | C73: 482103412 | D73: 下水道事業収益 | E73: 営業外収益 | F73: 一般会計補助金 | G73: 汚水処理補助金 | H73: 減価償却費分 | I73: 0 | J73: 0 | K73: 0 | L73: 0 | M73: 0 | N73: 0 | O73: 0 | P73: 0 | Q73: 0
A74: 1 | B74: 4821034 | C74: 482103413 | D74: 下水道事業収益 | E74: 営業外収益 | F74: 一般会計補助金 | G74: 汚水処理補助金 | H74: 支払利息分 | I74: 0 | J74: 0 | K74: 0 | L74: 0 | M74: 0 | N74: 0 | O74: 0 | P74: 0 | Q74: 0
A75: 1 | B75: 4821034 | C75: 482103414 | D75: 下水道事業収益 | E75: 営業外収益 | F75: 一般会計補助金 | G75: 汚水処理補助金 | H75: 下水道使用料減免分 | I75: 0 | J75: 0 | K75: 0 | L75: 0 | M75: 0 | N75: 0 | O75: 0 | P75: 0 | Q75: 0
A76: 1 | B76: 4821035 | C76: 482103500 | D76: 下水道事業収益 | E76: 営業外収益 | F76: 一般会計補助金 | G76: 災害復旧補助金 | I76: 0 | J76: 0 | K76: 0 | L76: 0 | M76: 0 | N76: 0 | O76: 0 | P76: 0 | Q76: 0
A77: 1 | B77: 4821040 | C77: 482104000 | D77: 下水道事業収益 | E77: 営業外収益 | F77: 一般会計補助金 | G77: その他補助金 | I77: 0 | J77: 0 | K77: 0 | L77: 0 | M77: 0 | N77: 0 | O77: 0 | P77: 0 | Q77: 0
A78: 1 | B78: 4821137 | C78: 482113700 | D78: 下水道事業収益 | E78: 営業外収益 | F78: 消費税及び地方消費税還付金 | G78: 消費税及び地方消費税還付金 | I78: 0 | J78: 0 | K78: 0 | L78: 0 | M78: 0 | N78: 0 | O78: 0 | P78: 0 | Q78: 0
A79: 1 | B79: 4821236 | C79: 482123600 | D79: 下水道事業収益 | E79: 営業外収益 | F79: 雑収益 | G79: 不用品売却収益 | I79: 408100 | J79: 0 | K79: 0 | L79: 0 | M79: 0 | N79: 408100 | O79: 0 | P79: 0 | Q79: 0
A80: 1 | B80: 4821240 | C80: 482124000 | D80: 下水道事業収益 | E80: 営業外収益 | F80: 雑収益 | G80: その他雑収益 | I80: 35949984 | J80: 0 | K80: 0 | L80: 0 | M80: 0 | N80: 12905830 | O80: 21841940 | P80: 1202214 | Q80: 0
A81: 1 | B81: 4821301 | C81: 482130103 | D81: 下水道事業収益 | E81: 営業外収益 | F81: 長期前受金戻入 | G81: 長期前受金戻入 | H81: 受贈財産評価額 | I81: 1393301969 | J81: 0 | K81: 0 | L81: 0 | M81: 0 | N81: 0 | O81: 0 | P81: 1393301969 | Q81: 0
A82: 1 | B82: 4821301 | C82: 482130104 | D82: 下水道事業収益 | E82: 営業外収益 | F82: 長期前受金戻入 | G82: 長期前受金戻入 | H82: 国庫補助金 | I82: 6705381537 | J82: 0 | K82: 0 | L82: 0 | M82: 0 | N82: 0 | O82: 0 | P82: 6705381537 | Q82: 0 | S82: 2024/5/12 とりあえず手入力
A83: 1 | B83: 4821301 | C83: 482130106 | D83: 下水道事業収益 | E83: 営業外収益 | F83: 長期前受金戻入 | G83: 長期前受金戻入 | H83: 受益者負担金 | I83: 193254317 | J83: 0 | K83: 0 | L83: 0 | M83: 0 | N83: 0 | O83: 0 | P83: 193254317 | Q83: 0
A84: 1 | B84: 4821301 | C84: 482130108 | D84: 下水道事業収益 | E84: 営業外収益 | F84: 長期前受金戻入 | G84: 長期前受金戻入 | H84: 工事負担金 | I84: 841304822 | J84: 0 | K84: 0 | L84: 0 | M84: 0 | N84: 0 | O84: 0 | P84: 841304822 | Q84: 0
A85: 1 | B85: 4821301 | C85: 482130110 | D85: 下水道事業収益 | E85: 営業外収益 | F85: 長期前受金戻入 | G85: 長期前受金戻入 | H85: 一般会計補助金 | I85: 0 | J85: 0 | K85: 0 | L85: 0 | M85: 0 | N85: 0 | O85: 0 | P85: 0 | Q85: 0
A86: 1 | B86: 4821301 | C86: 482130120 | D86: 下水道事業収益 | E86: 営業外収益 | F86: 長期前受金戻入 | G86: 長期前受金戻入 | H86: その他資本剰余金 | I86: 4429743 | J86: 0 | K86: 0 | L86: 0 | M86: 0 | N86: 0 | O86: 0 | P86: 4429743 | Q86: 0
A87: 1 | B87: 4830202 | C87: 483020200 | D87: 下水道事業収益 | E87: 特別利益 | F87: 固定資産売却益 | G87: 固定資産売却益 | I87: 0 | J87: 0 | K87: 0 | L87: 0 | M87: 0 | N87: 0 | O87: 0 | P87: 0 | Q87: 0
A88: 1 | B88: 4830404 | C88: 483040400 | D88: 下水道事業収益 | E88: 特別利益 | F88: 過年度損益修正益 | G88: 過年度損益修正益 | I88: 2710875 | J88: 0 | K88: 0 | L88: 36536 | M88: 0 | N88: 1518254 | O88: 910 | P88: 1155175 | Q88: 0
A89: 1 | B89: 4830606 | C89: 483060600 | D89: 下水道事業収益 | E89: 特別利益 | F89: その他特別利益 | G89: その他特別利益 | I89: 864807 | J89: 0 | K89: 0 | L89: 0 | M89: 0 | N89: 0 | O89: 0 | P89: 864807 | Q89: 0
A90: 1 | B90: 4830607 | C90: 483060700 | D90: 下水道事業収益 | E90: 特別利益 | F90: その他特別利益 | G90: 貸倒引当金戻入益 | I90: 428075 | J90: 0 | K90: 0 | L90: 0 | M90: 0 | N90: 0 | O90: 0 | P90: 428075 | Q90: 0
A91: 1 | B91: 4830608 | C91: 483060800 | D91: 下水道事業収益 | E91: 特別利益 | F91: その他特別利益 | G91: 賞与引当金戻入益 | I91: 109000 | J91: 0 | K91: 0 | L91: 0 | M91: 0 | N91: 0 | O91: 0 | P91: 109000 | Q91: 0
A92: 1 | B92: 4830808 | C92: 483080800 | D92: 下水道事業収益 | E92: 特別利益 | F92: 長期前受金戻入益 | G92: 長期前受金戻入益 | I92: 0 | J92: 0 | K92: 0 | L92: 0 | M92: 0 | N92: 0 | O92: 0 | P92: 0 | Q92: 0
A93: 1 | B93: 6153201 | C93: 615320102 | D93: 資本的支出 | E93: 建設改良費 | F93: 公共下水道整備費 | G93: 報酬 | H93: 委員報酬 | I93: 0 | J93: 0 | K93: 0 | L93: 0 | M93: 0 | N93: 0 | O93: 0 | P93: 0 | Q93: 0
A94: 1 | B94: 6153201 | C94: 615320103 | D94: 資本的支出 | E94: 建設改良費 | F94: 公共下水道整備費 | G94: 報酬 | H94: 非常勤嘱託員報酬 | I94: 0 | J94: 0 | K94: 0 | L94: 0 | M94: 0 | N94: 0 | O94: 0 | P94: 0 | Q94: 0
A95: 1 | B95: 6153201 | C95: 615320104 | D95: 資本的支出 | E95: 建設改良費 | F95: 公共下水道整備費 | G95: 報酬 | H95: 常勤嘱託員報酬 | I95: 0 | J95: 0 | K95: 0 | L95: 0 | M95: 0 | N95: 0 | O95: 0 | P95: 0 | Q95: 0
A96: 1 | B96: 6153201 | C96: 615320105 | D96: 資本的支出 | E96: 建設改良費 | F96: 公共下水道整備費 | G96: 報酬 | H96: 会計年度任用職員報酬 | I96: 13722776 | J96: 0 | K96: 0 | L96: 0 | M96: 0 | N96: 0 | O96: 0 | P96: 13722776 | Q96: 0
A97: 1 | B97: 6153202 | C97: 615320202 | D97: 資本的支出 | E97: 建設改良費 | F97: 公共下水道整備費 | G97: 給料 | H97: 一般職給 | I97: 285882615 | J97: 0 | K97: 0 | L97: 0 | M97: 0 | N97: 0 | O97: 0 | P97: 285882615 | Q97: 0
A98: 1 | B98: 6153203 | C98: 615320301 | D98: 資本的支出 | E98: 建設改良費 | F98: 公共下水道整備費 | G98: 手当等 | H98: 地域手当 | I98: 30683384 | J98: 0 | K98: 0 | L98: 0 | M98: 0 | N98: 0 | O98: 0 | P98: 30683384 | Q98: 0
A99: 1 | B99: 6153203 | C99: 615320302 | D99: 資本的支出 | E99: 建設改良費 | F99: 公共下水道整備費 | G99: 手当等 | H99: 扶養手当 | I99: 10330091 | J99: 0 | K99: 0 | L99: 0 | M99: 0 | N99: 0 | O99: 0 | P99: 10330091 | Q99: 0
A100: 1 | B100: 6153203 | C100: 615320303 | D100: 資本的支出 | E100: 建設改良費 | F100: 公共下水道整備費 | G100: 手当等 | H100: 期末勤勉手当 | I100: 135518157 | J100: 0 | K100: 0 | L100: 0 | M100: 0 | N100: 0 | O100: 0 | P100: 135518157 | Q100: 0
A101: 1 | B101: 6153203 | C101: 615320304 | D101: 資本的支出 | E101: 建設改良費 | F101: 公共下水道整備費 | G101: 手当等 | H101: 通勤手当 | I101: 8735510 | J101: 0 | K101: 0 | L101: 0 | M101: 0 | N101: 8735510 | O101: 0 | P101: 0 | Q101: 0
A102: 1 | B102: 6153203 | C102: 615320305 | D102: 資本的支出 | E102: 建設改良費 | F102: 公共下水道整備費 | G102: 手当等 | H102: 管理職手当 | I102: 10621200 | J102: 0 | K102: 0 | L102: 0 | M102: 0 | N102: 0 | O102: 0 | P102: 10621200 | Q102: 0
A103: 1 | B103: 6153203 | C103: 615320306 | D103: 資本的支出 | E103: 建設改良費 | F103: 公共下水道整備費 | G103: 手当等 | H103: 初任給調整手当 | I103: 0 | J103: 0 | K103: 0 | L103: 0 | M103: 0 | N103: 0 | O103: 0 | P103: 0 | Q103: 0
A104: 1 | B104: 6153203 | C104: 615320307 | D104: 資本的支出 | E104: 建設改良費 | F104: 公共下水道整備費 | G104: 手当等 | H104: 特殊勤務手当 | I104: 46428 | J104: 0 | K104: 0 | L104: 0 | M104: 0 | N104: 0 | O104: 0 | P104: 46428 | Q104: 0
... A119: 1 | B119: 6153204 | C119: 615320411 | D119: 資本的支出 | E119: 建設改良費 | F119: 公共下水道整備費 | G119: 法定福利費 | H119: 労災保険料 | I119: 0 | J119: 0 | K119: 0 | L119: 0 | M119: 0 | N119: 0 | O119: 0 | P119: 0 | Q119: 0
A120: 1 | B120: 6153205 | C120: 615320500 | D120: 資本的支出 | E120: 建設改良費 | F120: 公共下水道整備費 | G120: 災害補償費 | I120: 0 | J120: 0 | K120: 0 | L120: 0 | M120: 0 | N120: 0 | O120: 0 | P120: 0 | Q120: 0
A121: 1 | B121: 6153207 | C121: 615320700 | D121: 資本的支出 | E121: 建設改良費 | F121: 公共下水道整備費 | G121: 賃金 | I121: 0 | J121: 0 | K121: 0 | L121: 0 | M121: 0 | N121: 0 | O121: 0 | P121: 0 | Q121: 0
A122: 1 | B122: 6153208 | C122: 615320800 | D122: 資本的支出 | E122: 建設改良費 | F122: 公共下水道整備費 | G122: 報償費 | I122: 0 | J122: 0 | K122: 0 | L122: 0 | M122: 0 | N122: 0 | O122: 0 | P122: 0 | Q122: 0
A123: 1 | B123: 6153210 | C123: 615321001 | D123: 資本的支出 | E123: 建設改良費 | F123: 公共下水道整備費 | G123: 旅費 | H123: 普通旅費 | I123: 2021074 | J123: 0 | K123: 0 | L123: 0 | M123: 0 | N123: 2021074 | O123: 0 | P123: 0 | Q123: 0
...

Sheet 災害伝票
R1: 集計表（全体）
AU2: 1 | AV2: 現年分 | AW2: 税率別税込額 | BC2: 4 | BD2: 事故繰分 | BE2: 税率別税込額
Y3: 執行額 | AU3: 3 | AV3: 5 | AW3: 8 | AX3: 8 | AY3: 10 | AZ3: 非課税 | BA3: 不課税 | BB3: 計 | BC3: 3 | BD3: 5 | BE3: 8 | BF3: 8 | BG3: 10 | BH3: 非課税 | BI3: 不課税 | BJ3: 計 | BK3: チェック
N4: 1 | O4: 下水道事業費用 | P4: 営業費用 | Q4: 管きょ費 | Y4: =+SUMIFS(Y$15:Y$47,$Q$15:$Q$47,$Q4) -> 0 | AU4: =+SUMIFS($Y$15:$Y$47,$Q$15:$Q$47,$Q4,$AT$15:$AT$47,AU$3,$M$15:$M$47,$AU$2) -> 0 | AV4: =+SUMIFS($Y$15:$Y$47,$Q$15:$Q$47,$Q4,$AT$15:$AT$47,AV$3,$M$15:$M$47,$AU$2) -> 0 | AW4: =+SUMIFS($Y$15:$Y$47,$Q$15:$Q$47,$Q4,$AT$15:$AT$47,AW$3,$M$15:$M$47,$AU$2) -> 0 | AX4: =+SUMIFS($Y$15:$Y$47,$Q$15:$Q$47,$Q4,$AT$15:$AT$47,AX$3,$M$15:$M$47,$AU$2) -> 0 | AY4: =+SUMIFS($Y$15:$Y$47,$Q$15:$Q$47,$Q4,$AT$15:$AT$47,AY$3,$M$15:$M$47,$AU$2) -> 0 | AZ4: =+SUMIFS($Y$15:$Y$47,$Q$15:$Q$47,$Q4,$AT$15:$AT$47,AZ$3,$M$15:$M$47,$AU$2) -> 0 | BA4: =+SUMIFS($Y$15:$Y$47,$Q$15:$Q$47,$Q4,$AT$15:$AT$47,BA$3,$M$15:$M$47,$AU$2) -> 0 | BB4: =SUM(AU4:BA4) -> 0 | BC4: =+SUMIFS($Y$15:$Y$47,$Q$15:$Q$47,$Q4,$AT$15:$AT$47,BC$3,$M$15:$M$47,$BC$2) -> 0 | BD4: =+SUMIFS($Y$15:$Y$47,$Q$15:$Q$47,$Q4,$AT$15:$AT$47,BD$3,$M$15:$M$47,$BC$2) -> 0 | BE4: =+SUMIFS($Y$15:$Y$47,$Q$15:$Q$47,$Q4,$AT$15:$AT$47,BE$3,$M$15:$M$47,$BC$2)-BF4 -> 0 | BF4: =+SUMIFS($Y$15:$Y$47,$Q$15:$Q$47,$Q4,$AT$15:$AT$47,BF$3,$M$15:$M$47,$BC$2) -> 0 | BG4: =+SUMIFS($Y$15:$Y$47,$Q$15:$Q$47,$Q4,$AT$15:$AT$47,BG$3,$M$15:$M$47,$BC$2) -> 0 | BH4: =+SUMIFS($Y$15:$Y$47,$Q$15:$Q$47,$Q4,$AT$15:$AT$47,BH$3,$M$15:$M$47,$BC$2) -> 0 | BI4: =+SUMIFS($Y$15:$Y$47,$Q$15:$Q$47,$Q4,$AT$15:$AT$47,BI$3,$M$15:$M$47,$BC$2) -> 0 | BJ4: =SUM(BC4:BI4) -> 0 | BK4: =+IF(Y4=(BB4+BJ4),"OK","エラー") -> OK
N5: 1 | O5: 下水道事業費用 | P5: 営業費用 | Q5: ポンプ場費 | Y5: =+SUMIFS(Y$15:Y$47,$Q$15:$Q$47,$Q5) -> 0 | AU5: =+SUMIFS($Y$15:$Y$47,$Q$15:$Q$47,$Q5,$AT$15:$AT$47,AU$3,$M$15:$M$47,$AU$2) -> 0 | AV5: =+SUMIFS($Y$15:$Y$47,$Q$15:$Q$47,$Q5,$AT$15:$AT$47,AV$3,$M$15:$M$47,$AU$2) -> 0 | AW5: =+SUMIFS($Y$15:$Y$47,$Q$15:$Q$47,$Q5,$AT$15:$AT$47,AW$3,$M$15:$M$47,$AU$2) -> 0 | AX5: =+SUMIFS($Y$15:$Y$47,$Q$15:$Q$47,$Q5,$AT$15:$AT$47,AX$3,$M$15:$M$47,$AU$2) -> 0 | AY5: =+SUMIFS($Y$15:$Y$47,$Q$15:$Q$47,$Q5,$AT$15:$AT$47,AY$3,$M$15:$M$47,$AU$2) -> 0 | AZ5: =+SUMIFS($Y$15:$Y$47,$Q$15:$Q$47,$Q5,$AT$15:$AT$47,AZ$3,$M$15:$M$47,$AU$2) -> 0 | BA5: =+SUMIFS($Y$15:$Y$47,$Q$15:$Q$47,$Q5,$AT$15:$AT$47,BA$3,$M$15:$M$47,$AU$2) -> 0 | BB5: =SUM(AU5:BA5) -> 0 | BC5: =+SUMIFS($Y$15:$Y$47,$Q$15:$Q$47,$Q5,$AT$15:$AT$47,BC$3,$M$15:$M$47,$BC$2) -> 0 | BD5: =+SUMIFS($Y$15:$Y$47,$Q$15:$Q$47,$Q5,$AT$15:$AT$47,BD$3,$M$15:$M$47,$BC$2) -> 0 | BE5: =+SUMIFS($Y$15:$Y$47,$Q$15:$Q$47,$Q5,$AT$15:$AT$47,BE$3,$M$15:$M$47,$BC$2)-BF5 -> 0 | BF5: =+SUMIFS($Y$15:$Y$47,$Q$15:$Q$47,$Q5,$AT$15:$AT$47,BF$3,$M$15:$M$47,$BC$2) -> 0 | BG5: =+SUMIFS($Y$15:$Y$47,$Q$15:$Q$47,$Q5,$AT$15:$AT$47,BG$3,$M$15:$M$47,$BC$2) -> 0 | BH5: =+SUMIFS($Y$15:$Y$47,$Q$15:$Q$47,$Q5,$AT$15:$AT$47,BH$3,$M$15:$M$47,$BC$2) -> 0 | BI5: =+SUMIFS($Y$15:$Y$47,$Q$15:$Q$47,$Q5,$AT$15:$AT$47,BI$3,$M$15:$M$47,$BC$2) -> 0 | BJ5: =SUM(BC5:BI5) -> 0 | BK5: =+IF(Y5=(BB5+BJ5),"OK","エラー") -> OK
N6: 1 | O6: 下水道事業費用 | P6: 営業費用 | Q6: 処理場費 | Y6: =+SUMIFS(Y$15:Y$47,$Q$15:$Q$47,$Q6) -> 0 | AU6: =+SUMIFS($Y$15:$Y$47,$Q$15:$Q$47,$Q6,$AT$15:$AT$47,AU$3,$M$15:$M$47,$AU$2) -> 0 | AV6: =+SUMIFS($Y$15:$Y$47,$Q$15:$Q$47,$Q6,$AT$15:$AT$47,AV$3,$M$15:$M$47,$AU$2) -> 0 | AW6: =+SUMIFS($Y$15:$Y$47,$Q$15:$Q$47,$Q6,$AT$15:$AT$47,AW$3,$M$15:$M$47,$AU$2) -> 0 | AX6: =+SUMIFS($Y$15:$Y$47,$Q$15:$Q$47,$Q6,$AT$15:$AT$47,AX$3,$M$15:$M$47,$AU$2) -> 0 | AY6: =+SUMIFS($Y$15:$Y$47,$Q$15:$Q$47,$Q6,$AT$15:$AT$47,AY$3,$M$15:$M$47,$AU$2) -> 0 | AZ6: =+SUMIFS($Y$15:$Y$47,$Q$15:$Q$47,$Q6,$AT$15:$AT$47,AZ$3,$M$15:$M$47,$AU$2) -> 0 | BA6: =+SUMIFS($Y$15:$Y$47,$Q$15:$Q$47,$Q6,$AT$15:$AT$47,BA$3,$M$15:$M$47,$AU$2) -> 0 | BB6: =SUM(AU6:BA6) -> 0 | BC6: =+SUMIFS($Y$15:$Y$47,$Q$15:$Q$47,$Q6,$AT$15:$AT$47,BC$3,$M$15:$M$47,$BC$2) -> 0 | BD6: =+SUMIFS($Y$15:$Y$47,$Q$15:$Q$47,$Q6,$AT$15:$AT$47,BD$3,$M$15:$M$47,$BC$2) -> 0 | BE6: =+SUMIFS($Y$15:$Y$47,$Q$15:$Q$47,$Q6,$AT$15:$AT$47,BE$3,$M$15:$M$47,$BC$2)-BF6 -> 0 | BF6: =+SUMIFS($Y$15:$Y$47,$Q$15:$Q$47,$Q6,$AT$15:$AT$47,BF$3,$M$15:$M$47,$BC$2) -> 0 | BG6: =+SUMIFS($Y$15:$Y$47,$Q$15:$Q$47,$Q6,$AT$15:$AT$47,BG$3,$M$15:$M$47,$BC$2) -> 0 | BH6: =+SUMIFS($Y$15:$Y$47,$Q$15:$Q$47,$Q6,$AT$15:$AT$47,BH$3,$M$15:$M$47,$BC$2) -> 0 | BI6: =+SUMIFS($Y$15:$Y$47,$Q$15:$Q$47,$Q6,$AT$15:$AT$47,BI$3,$M$15:$M$47,$BC$2) -> 0 | BJ6: =SUM(BC6:BI6) -> 0 | BK6: =+IF(Y6=(BB6+BJ6),"OK","エラー") -> OK
N7: 2 | O7: 下水道事業費用 | P7: 営業費用 | Q7: 特環公共下水道費 | Y7: =+SUMIFS(Y$15:Y$47,$Q$15:$Q$47,$Q7) -> 0 | AU7: =+SUMIFS($Y$15:$Y$47,$Q$15:$Q$47,$Q7,$AT$15:$AT$47,AU$3,$M$15:$M$47,$AU$2) -> 0 | AV7: =+SUMIFS($Y$15:$Y$47,$Q$15:$Q$47,$Q7,$AT$15:$AT$47,AV$3,$M$15:$M$47,$AU$2) -> 0 | AW7: =+SUMIFS($Y$15:$Y$47,$Q$15:$Q$47,$Q7,$AT$15:$AT$47,AW$3,$M$15:$M$47,$AU$2) -> 0 | AX7: =+SUMIFS($Y$15:$Y$47,$Q$15:$Q$47,$Q7,$AT$15:$AT$47,AX$3,$M$15:$M$47,$AU$2) -> 0 | AY7: =+SUMIFS($Y$15:$Y$47,$Q$15:$Q$47,$Q7,$AT$15:$AT$47,AY$3,$M$15:$M$47,$AU$2) -> 0 | AZ7: =+SUMIFS($Y$15:$Y$47,$Q$15:$Q$47,$Q7,$AT$15:$AT$47,AZ$3,$M$15:$M$47,$AU$2) -> 0 | BA7: =+SUMIFS($Y$15:$Y$47,$Q$15:$Q$47,$Q7,$AT$15:$AT$47,BA$3,$M$15:$M$47,$AU$2) -> 0 | BB7: =SUM(AU7:BA7) -> 0 | BC7: =+SUMIFS($Y$15:$Y$47,$Q$15:$Q$47,$Q7,$AT$15:$AT$47,BC$3,$M$15:$M$47,$BC$2) -> 0 | BD7: =+SUMIFS($Y$15:$Y$47,$Q$15:$Q$47,$Q7,$AT$15:$AT$47,BD$3,$M$15:$M$47,$BC$2) -> 0 | BE7: =+SUMIFS($Y$15:$Y$47,$Q$15:$Q$47,$Q7,$AT$15:$AT$47,BE$3,$M$15:$M$47,$BC$2)-BF7 -> 0 | BF7: =+SUMIFS($Y$15:$Y$47,$Q$15:$Q$47,$Q7,$AT$15:$AT$47,BF$3,$M$15:$M$47,$BC$2) -> 0 | BG7: =+SUMIFS($Y$15:$Y$47,$Q$15:$Q$47,$Q7,$AT$15:$AT$47,BG$3,$M$15:$M$47,$BC$2) -> 0 | BH7: =+SUMIFS($Y$15:$Y$47,$Q$15:$Q$47,$Q7,$AT$15:$AT$47,BH$3,$M$15:$M$47,$BC$2) -> 0 | BI7: =+SUMIFS($Y$15:$Y$47,$Q$15:$Q$47,$Q7,$AT$15:$AT$47,BI$3,$M$15:$M$47,$BC$2) -> 0 | BJ7: =SUM(BC7:BI7) -> 0 | BK7: =+IF(Y7=(BB7+BJ7),"OK","エラー") -> OK
N8: 3 | O8: 下水道事業費用 | P8: 営業費用 | Q8: 農業集落排水費 | Y8: =+SUMIFS(Y$15:Y$47,$Q$15:$Q$47,$Q8) -> 0 | AU8: =+SUMIFS($Y$15:$Y$47,$Q$15:$Q$47,$Q8,$AT$15:$AT$47,AU$3,$M$15:$M$47,$AU$2) -> 0 | AV8: =+SUMIFS($Y$15:$Y$47,$Q$15:$Q$47,$Q8,$AT$15:$AT$47,AV$3,$M$15:$M$47,$AU$2) -> 0 | AW8: =+SUMIFS($Y$15:$Y$47,$Q$15:$Q$47,$Q8,$AT$15:$AT$47,AW$3,$M$15:$M$47,$AU$2) -> 0 | AX8: =+SUMIFS($Y$15:$Y$47,$Q$15:$Q$47,$Q8,$AT$15:$AT$47,AX$3,$M$15:$M$47,$AU$2) -> 0 | AY8: =+SUMIFS($Y$15:$Y$47,$Q$15:$Q$47,$Q8,$AT$15:$AT$47,AY$3,$M$15:$M$47,$AU$2) -> 0 | AZ8: =+SUMIFS($Y$15:$Y$47,$Q$15:$Q$47,$Q8,$AT$15:$AT$47,AZ$3,$M$15:$M$47,$AU$2) -> 0 | BA8: =+SUMIFS($Y$15:$Y$47,$Q$15:$Q$47,$Q8,$AT$15:$AT$47,BA$3,$M$15:$M$47,$AU$2) -> 0 | BB8: =SUM(AU8:BA8) -> 0 | BC8: =+SUMIFS($Y$15:$Y$47,$Q$15:$Q$47,$Q8,$AT$15:$AT$47,BC$3,$M$15:$M$47,$BC$2) -> 0 | BD8: =+SUMIFS($Y$15:$Y$47,$Q$15:$Q$47,$Q8,$AT$15:$AT$47,BD$3,$M$15:$M$47,$BC$2) -> 0 | BE8: =+SUMIFS($Y$15:$Y$47,$Q$15:$Q$47,$Q8,$AT$15:$AT$47,BE$3,$M$15:$M$47,$BC$2)-BF8 -> 0 | BF8: =+SUMIFS($Y$15:$Y$47,$Q$15:$Q$47,$Q8,$AT$15:$AT$47,BF$3,$M$15:$M$47,$BC$2) -> 0 | BG8: =+SUMIFS($Y$15:$Y$47,$Q$15:$Q$47,$Q8,$AT$15:$AT$47,BG$3,$M$15:$M$47,$BC$2) -> 0 | BH8: =+SUMIFS($Y$15:$Y$47,$Q$15:$Q$47,$Q8,$AT$15:$AT$47,BH$3,$M$15:$M$47,$BC$2) -> 0 | BI8: =+SUMIFS($Y$15:$Y$47,$Q$15:$Q$47,$Q8,$AT$15:$AT$47,BI$3,$M$15:$M$47,$BC$2) -> 0 | BJ8: =SUM(BC8:BI8) -> 0 | BK8: =+IF(Y8=(BB8+BJ8),"OK","エラー") -> OK
N9: 4 | O9: 下水道事業費用 | P9: 営業費用 | Q9: 浄化槽費 | Y9: =+SUMIFS(Y$15:Y$47,$Q$15:$Q$47,$Q9) -> 0 | AU9: =+SUMIFS($Y$15:$Y$47,$Q$15:$Q$47,$Q9,$AT$15:$AT$47,AU$3,$M$15:$M$47,$AU$2) -> 0 | AV9: =+SUMIFS($Y$15:$Y$47,$Q$15:$Q$47,$Q9,$AT$15:$AT$47,AV$3,$M$15:$M$47,$AU$2) -> 0 | AW9: =+SUMIFS($Y$15:$Y$47,$Q$15:$Q$47,$Q9,$AT$15:$AT$47,AW$3,$M$15:$M$47,$AU$2) -> 0 | AX9: =+SUMIFS($Y$15:$Y$47,$Q$15:$Q$47,$Q9,$AT$15:$AT$47,AX$3,$M$15:$M$47,$AU$2) -> 0 | AY9: =+SUMIFS($Y$15:$Y$47,$Q$15:$Q$47,$Q9,$AT$15:$AT$47,AY$3,$M$15:$M$47,$AU$2) -> 0 | AZ9: =+SUMIFS($Y$15:$Y$47,$Q$15:$Q$47,$Q9,$AT$15:$AT$47,AZ$3,$M$15:$M$47,$AU$2) -> 0 | BA9: =+SUMIFS($Y$15:$Y$47,$Q$15:$Q$47,$Q9,$AT$15:$AT$47,BA$3,$M$15:$M$47,$AU$2) -> 0 | BB9: =SUM(AU9:BA9) -> 0 | BC9: =+SUMIFS($Y$15:$Y$47,$Q$15:$Q$47,$Q9,$AT$15:$AT$47,BC$3,$M$15:$M$47,$BC$2) -> 0 | BD9: =+SUMIFS($Y$15:$Y$47,$Q$15:$Q$47,$Q9,$AT$15:$AT$47,BD$3,$M$15:$M$47,$BC$2) -> 0 | BE9: =+SUMIFS($Y$15:$Y$47,$Q$15:$Q$47,$Q9,$AT$15:$AT$47,BE$3,$M$15:$M$47,$BC$2)-BF9 -> 0 | BF9: =+SUMIFS($Y$15:$Y$47,$Q$15:$Q$47,$Q9,$AT$15:$AT$47,BF$3,$M$15:$M$47,$BC$2) -> 0 | BG9: =+SUMIFS($Y$15:$Y$47,$Q$15:$Q$47,$Q9,$AT$15:$AT$47,BG$3,$M$15:$M$47,$BC$2) -> 0 | BH9: =+SUMIFS($Y$15:$Y$47,$Q$15:$Q$47,$Q9,$AT$15:$AT$47,BH$3,$M$15:$M$47,$BC$2) -> 0 | BI9: =+SUMIFS($Y$15:$Y$47,$Q$15:$Q$47,$Q9,$AT$15:$AT$47,BI$3,$M$15:$M$47,$BC$2) -> 0 | BJ9: =SUM(BC9:BI9) -> 0 | BK9: =+IF(Y9=(BB9+BJ9),"OK","エラー") -> OK
Y10: =SUM(Y4:Y9) -> 0
AL14: ---- | AS14: 0 | AT14: 0
A15: 事業区分 | B15: 所属 | C15: 所属名 | D15: 主管課 | E15: 主管課名 | F15: 年月日 | G15: 振替年月日 | H15: 事項 | I15: 種別 | J15: 伝票番号 | K15: 枝番 | L15: 内訳番号 | M15: 現繰 | N15: 予算科目 | O15: 款名称 | P15: 項名称 | Q15: 目名称 | R15: 節名称 | S15: 細節名称 | T15: 事業コード | U15: 事業名 | V15: 予算額 | W15: 概算額 | X15: 確定額 | Y15: 執行額 | Z15: 借方勘定 | AA15: 借方勘定科目 | AB15: 借方金額 | AC15: 貸方勘定 | AD15: 貸方勘定科目 | AE15: 貸方金額 | AF15: 税区分 | AG15: 税率 | AH15: 税額 | AI15: 税抜金額 | AJ15: 債権者 | AL15: 複合伝票番号 | AM15: 1 | AN15: 0 | AO15: 0 | AP15: 0 | AQ15: 重複 | AS15: 集計用課税区分 | AT15: 集計用税率 | AV15: 雨 区域内 | AW15: 雨 区域外 | AX15: 雨 一般行政 | AY15: 雨水 計 | AZ15: 汚 基準内 | BA15: 汚 基準外 | BB15: 汚水 計 | BC15: 合計 | BD15: チェック | BE15: 備考 | BG15: 雨汚水分け対象1 | BH15: 雨汚水分け対象2 | BI15: 雨汚水分け対象3 | BJ15: 判定

Sheet 3条支出
D1: =+CONCATENATE("令和",DBCS(年度!A2),"年度決算 消費税算出資料") -> 令和５年度決算 消費税算出資料
D2: 【３条支出総括】
A3: 事業 | B3: 節 | C3: 細節 | D3: 費目 | E3: 税込決算額 | F3: 課税支出 | L3: 非課税支出 | M3: 不課税支出 | N3: 消費税 | T3: 税抜決算額 | U3: 消費税 端数確認 | Z3: 消費税端数調整ランク | AE3: 消費税 調整額
F4: 3 | G4: 5 | H4: 8 | I4: 8 | J4: 10 | K4: 計 | N4: 3 | O4: 5 | P4: 8 | Q4: 8 | R4: 10 | S4: 計 | U4: 3 | V4: 5 | W4: 8 | X4: 8 | Y4: 10 | Z4: 3 | AA4: 5 | AB4: 8 | AC4: 8 | AD4: 10 | AE4: 3 | AF4: 5 | AG4: 8 | AH4: 8 | AI4: 10
D5: 営業費用 | E5: =+SUM(E6:E20) -> 38667489041 | F5: =+SUM(F6:F20) -> 0 | G5: =+SUM(G6:G20) -> 0 | H5: =+SUM(H6:H20) -> 1196802 | I5: =+SUM(I6:I20) -> 500878 | J5: =+SUM(J6:J20) -> 9029006226 | K5: =+SUM(K6:K20) -> 9030703906 | L5: =+SUM(L6:L20) -> 417951500 | ... T5: =+SUM(T6:T20) -> 37846544540
D6: 管きょ費 | E6: =+管!E36 -> 611819957 | F6: =+管!F36 -> 0 | G6: =+管!G36 -> 0 | H6: =+管!H36 -> 678402 | I6: =+管!I36 -> 0 | J6: =+管!J36 -> 518156070 | K6: =+管!K36 -> 518834472 | L6: =+管!L36 -> 20454735 | M6: =+管!M36 -> 72530750 | N6: =+ROUND(F6*F$4/(100+F$4),0)+AE6 -> 0 | O6: =+ROUND(G6*G$4/(100+G$4),0)+AF6 -> 0 | P6: =+ROUND(H6*H$4/(100+H$4),0)+AG6 -> 50252 | Q6: =+ROUND(I6*I$4/(100+I$4),0)+AH6 -> 0 | R6: =+ROUND(J6*J$4/(100+J$4),0)+AI6 -> 47105097 | S6: =SUM(N6:R6) -> 47155349 | T6: =+E6-S6 -> 564664608 | U6: =N6-F6*F$4/(100+F$4) -> 0 | V6: =O6-G6*G$4/(100+G$4) -> 0 | W6: =P6-H6*H$4/(100+H$4) -> 0 | X6: =Q6-I6*I$4/(100+I$4) -> 0 | Y6: =R6-J6*J$4/(100+J$4) -> -0.27272727 | Z6: =+IF(N$43=0,0,IF(N$43<0,-RANK(U6,U$5:U$40,0),RANK(U6,U$5:U$40,1))) -> 0 | AA6: =+IF(O$43=0,0,IF(O$43<0,-RANK(V6,V$5:V$40,0),RANK(V6,V$5:V$40,1))) -> 0 | AB6: =+IF(P$43=0,0,IF(P$43<0,-RANK(W6,W$5:W$40,0),RANK(W6,W$5:W$40,1))) -> 0 | AC6: =+IF(Q$43=0,0,IF(Q$43<0,-RANK(X6,X$5:X$40,0),RANK(X6,X$5:X$40,1))) -> 0 | AD6: =+IF(R$43=0,0,IF(R$43<0,-RANK(Y6,Y$5:Y$40,0),RANK(Y6,Y$5:Y$40,1))) -> 0
D7: 水質指導費 | E7: =+水質!E36 -> 52443869 | F7: =+水質!F36 -> 0 | G7: =+水質!G36 -> 0 | H7: =+水質!H36 -> 0 | I7: =+水質!I36 -> 0 | J7: =+水質!J36 -> 12436317 | K7: =+水質!K36 -> 12436317 | L7: =+水質!L36 -> 6197563 | M7: =+水質!M36 -> 33809989 | N7: =+ROUND(F7*F$4/(100+F$4),0)+AE7 -> 0 | O7: =+ROUND(G7*G$4/(100+G$4),0)+AF7 -> 0 | P7: =+ROUND(H7*H$4/(100+H$4),0)+AG7 -> 0 | Q7: =+ROUND(I7*I$4/(100+I$4),0)+AH7 -> 0 | R7: =+ROUND(J7*J$4/(100+J$4),0)+AI7 -> 1130574 | S7: =SUM(N7:R7) -> 1130574 | T7: =+E7-S7 -> 51313295 | U7: =N7-F7*F$4/(100+F$4)-AE7 -> 0 | V7: =O7-G7*G$4/(100+G$4)-AF7 -> 0 | W7: =P7-H7*H$4/(100+H$4)-AG7 -> 0 | X7: =Q7-I7*I$4/(100+I$4)-AH7 -> 0 | Y7: =R7-J7*J$4/(100+J$4)-AI7 -> -0.27272727 | Z7: =+IF(N$43=0,0,IF(N$43<0,-RANK(U7,U$5:U$40,0),RANK(U7,U$5:U$40,1))) -> 0 | AA7: =+IF(O$43=0,0,IF(O$43<0,-RANK(V7,V$5:V$40,0),RANK(V7,V$5:V$40,1))) -> 0 | AB7: =+IF(P$43=0,0,IF(P$43<0,-RANK(W7,W$5:W$40,0),RANK(W7,W$5:W$40,1))) -> 0 | AC7: =+IF(Q$43=0,0,IF(Q$43<0,-RANK(X7,X$5:X$40,0),RANK(X7,X$5:X$40,1))) -> 0 | AD7: =+IF(R$43=0,0,IF(R$43<0,-RANK(Y7,Y$5:Y$40,0),RANK(Y7,Y$5:Y$40,1))) -> 0
D8: ポンプ場費 | E8: =+ポ!E36 -> 2356040225 | F8: =+ポ!F36 -> 0 | G8: =+ポ!G36 -> 0 | H8: =+ポ!H36 -> 0 | I8: =+ポ!I36 -> 30357 | J8: =+ポ!J36 -> 1148180103 | K8: =+ポ!K36 -> 1148210460 | L8: =+ポ!L36 -> 188585576 | M8: =+ポ!M36 -> 1019244189 | N8: =+ROUND(F8*F$4/(100+F$4),0)+AE8 -> 0 | O8: =+ROUND(G8*G$4/(100+G$4),0)+AF8 -> 0 | P8: =+ROUND(H8*H$4/(100+H$4),0)+AG8 -> 0 | Q8: =+ROUND(I8*I$4/(100+I$4),0)+AH8 -> 2249 | R8: =+ROUND(J8*J$4/(100+J$4),0)+AI8 -> 104380009 | S8: =SUM(N8:R8) -> 104382258 | T8: =+E8-S8 -> 2251657967 | U8: =N8-F8*F$4/(100+F$4)-AE8 -> 0 | V8: =O8-G8*G$4/(100+G$4)-AF8 -> 0 | W8: =P8-H8*H$4/(100+H$4)-AG8 -> 0 | X8: =Q8-I8*I$4/(100+I$4)-AH8 -> 0.33333333 | Y8: =R8-J8*J$4/(100+J$4)-AI8 -> -0.36363636 | Z8: =+IF(N$43=0,0,IF(N$43<0,-RANK(U8,U$5:U$40,0),RANK(U8,U$5:U$40,1))) -> 0 | AA8: =+IF(O$43=0,0,IF(O$43<0,-RANK(V8,V$5:V$40,0),RANK(V8,V$5:V$40,1))) -> 0 | AB8: =+IF(P$43=0,0,IF(P$43<0,-RANK(W8,W$5:W$40,0),RANK(W8,W$5:W$40,1))) -> 0 | AC8: =+IF(Q$43=0,0,IF(Q$43<0,-RANK(X8,X$5:X$40,0),RANK(X8,X$5:X$40,1))) -> 0 | AD8: =+IF(R$43=0,0,IF(R$43<0,-RANK(Y8,Y$5:Y$40,0),RANK(Y8,Y$5:Y$40,1))) -> 0
D9: 処理場費 | E9: =+処!E36 -> 6557703864 | F9: =+処!F36 -> 0 | G9: =+処!G36 -> 0 | H9: =+処!H36 -> 518400 | I9: =+処!I36 -> 144600 | J9: =+処!J36 -> 5718291420 | K9: =+処!K36 -> 5718954420 | L9: =+処!L36 -> 130669187 | M9: =+処!M36 -> 708080257 | N9: =+ROUND(F9*F$4/(100+F$4),0)+AE9 -> 0 | O9: =+ROUND(G9*G$4/(100+G$4),0)+AF9 -> 0 | P9: =+ROUND(H9*H$4/(100+H$4),0)+AG9 -> 38400 | Q9: =+ROUND(I9*I$4/(100+I$4),0)+AH9 -> 10711 | R9: =+ROUND(J9*J$4/(100+J$4),0)+AI9 -> 519844675 | S9: =SUM(N9:R9) -> 519893786 | T9: =+E9-S9 -> 6037810078 | U9: =N9-F9*F$4/(100+F$4)-AE9 -> 0 | V9: =O9-G9*G$4/(100+G$4)-AF9 -> 0 | W9: =P9-H9*H$4/(100+H$4)-AG9 -> 0 | X9: =Q9-I9*I$4/(100+I$4)-AH9 -> -0.11111111 | Y9: =R9-J9*J$4/(100+J$4)-AI9 -> 0.45454544 | Z9: =+IF(N$43=0,0,IF(N$43<0,-RANK(U9,U$5:U$40,0),RANK(U9,U$5:U$40,1))) -> 0 | AA9: =+IF(O$43=0,0,IF(O$43<0,-RANK(V9,V$5:V$40,0),RANK(V9,V$5:V$40,1))) -> 0 | AB9: =+IF(P$43=0,0,IF(P$43<0,-RANK(W9,W$5:W$40,0),RANK(W9,W$5:W$40,1))) -> 0 | AC9: =+IF(Q$43=0,0,IF(Q$43<0,-RANK(X9,X$5:X$40,0),RANK(X9,X$5:X$40,1))) -> 0 | AD9: =+IF(R$43=0,0,IF(R$43<0,-RANK(Y9,Y$5:Y$40,0),RANK(Y9,Y$5:Y$40,1))) -> 0
D10: 受託工事費 | E10: =+受工!E36 -> 0 | F10: =+受工!F36 -> 0 | G10: =+受工!G36 -> 0 | H10: =+受工!H36 -> 0 | I10: =+受工!I36 -> 0 | J10: =+受工!J36 -> 0 | K10: =+受工!K36 -> 0 | L10: =+受工!L36 -> 0 | M10: =+受工!M36 -> 0 | N10: =+ROUND(F10*F$4/(100+F$4),0)+AE10 -> 0 | O10: =+ROUND(G10*G$4/(100+G$4),0)+AF10 -> 0 | P10: =+ROUND(H10*H$4/(100+H$4),0)+AG10 -> 0 | Q10: =+ROUND(I10*I$4/(100+I$4),0)+AH10 -> 0 | R10: =+ROUND(J10*J$4/(100+J$4),0)+AI10 -> 0 | S10: =SUM(N10:R10) -> 0 | T10: =+E10-S10 -> 0 | U10: =N10-F10*F$4/(100+F$4)-AE10 -> 0 | V10: =O10-G10*G$4/(100+G$4)-AF10 -> 0 | W10: =P10-H10*H$4/(100+H$4)-AG10 -> 0 | X10: =Q10-I10*I$4/(100+I$4)-AH10 -> 0 | Y10: =R10-J10*J$4/(100+J$4)-AI10 -> 0 | Z10: =+IF(N$43=0,0,IF(N$43<0,-RANK(U10,U$5:U$40,0),RANK(U10,U$5:U$40,1))) -> 0 | AA10: =+IF(O$43=0,0,IF(O$43<0,-RANK(V10,V$5:V$40,0),RANK(V10,V$5:V$40,1))) -> 0 | AB10: =+IF(P$43=0,0,IF(P$43<0,-RANK(W10,W$5:W$40,0),RANK(W10,W$5:W$40,1))) -> 0 | AC10: =+IF(Q$43=0,0,IF(Q$43<0,-RANK(X10,X$5:X$40,0),RANK(X10,X$5:X$40,1))) -> 0 | AD10: =+IF(R$43=0,0,IF(R$43<0,-RANK(Y10,Y$5:Y$40,0),RANK(Y10,Y$5:Y$40,1))) -> 0
D11: 普及促進費 | E11: =+普及!E36 -> 88849549 | F11: =+普及!F36 -> 0 | G11: =+普及!G36 -> 0 | H11: =+普及!H36 -> 0 | I11: =+普及!I36 -> 0 | J11: =+普及!J36 -> 18870469 | K11: =+普及!K36 -> 18870469 | L11: =+普及!L36 -> 9614092 | M11: =+普及!M36 -> 60364988 | N11: =+ROUND(F11*F$4/(100+F$4),0)+AE11 -> 0 | O11: =+ROUND(G11*G$4/(100+G$4),0)+AF11 -> 0 | P11: =+ROUND(H11*H$4/(100+H$4),0)+AG11 -> 0 | Q11: =+ROUND(I11*I$4/(100+I$4),0)+AH11 -> 0 | R11: =+ROUND(J11*J$4/(100+J$4),0)+AI11 -> 1715497 | S11: =SUM(N11:R11) -> 1715497 | T11: =+E11-S11 -> 87134052 | U11: =N11-F11*F$4/(100+F$4)-AE11 -> 0 | V11: =O11-G11*G$4/(100+G$4)-AF11 -> 0 | W11: =P11-H11*H$4/(100+H$4)-AG11 -> 0 | X11: =Q11-I11*I$4/(100+I$4)-AH11 -> 0 | Y11: =R11-J11*J$4/(100+J$4)-AI11 -> -0.18181818 | Z11: =+IF(N$43=0,0,IF(N$43<0,-RANK(U11,U$5:U$40,0),RANK(U11,U$5:U$40,1))) -> 0 | AA11: =+IF(O$43=0,0,IF(O$43<0,-RANK(V11,V$5:V$40,0),RANK(V11,V$5:V$40,1))) -> 0 | AB11: =+IF(P$43=0,0,IF(P$43<0,-RANK(W11,W$5:W$40,0),RANK(W11,W$5:W$40,1))) -> 0 | AC11: =+IF(Q$43=0,0,IF(Q$43<0,-RANK(X11,X$5:X$40,0),RANK(X11,X$5:X$40,1))) -> 0 | AD11: =+IF(R$43=0,0,IF(R$43<0,-RANK(Y11,Y$5:Y$40,0),RANK(Y11,Y$5:Y$40,1))) -> 0
D12: 水洗化貸付事業費 | E12: =+貸付!E36 -> 10483859 | F12: =+貸付!F36 -> 0 | G12: =+貸付!G36 -> 0 | H12: =+貸付!H36 -> 0 | I12: =+貸付!I36 -> 0 | J12: =+貸付!J36 -> 963485 | K12: =+貸付!K36 -> 963485 | L12: =+貸付!L36 -> 1672623 | M12: =+貸付!M36 -> 7847751 | N12: =+ROUND(F12*F$4/(100+F$4),0)+AE12 -> 0 | O12: =+ROUND(G12*G$4/(100+G$4),0)+AF12 -> 0 | P12: =+ROUND(H12*H$4/(100+H$4),0)+AG12 -> 0 | Q12: =+ROUND(I12*I$4/(100+I$4),0)+AH12 -> 0 | R12: =+ROUND(J12*J$4/(100+J$4),0)+AI12 -> 87589 | S12: =SUM(N12:R12) -> 87589 | T12: =+E12-S12 -> 10396270 | U12: =N12-F12*F$4/(100+F$4)-AE12 -> 0 | V12: =O12-G12*G$4/(100+G$4)-AF12 -> 0 | W12: =P12-H12*H$4/(100+H$4)-AG12 -> 0 | X12: =Q12-I12*I$4/(100+I$4)-AH12 -> 0 | Y12: =R12-J12*J$4/(100+J$4)-AI12 -> 0.45454545 | Z12: =+IF(N$43=0,0,IF(N$43<0,-RANK(U12,U$5:U$40,0),RANK(U12,U$5:U$40,1))) -> 0 | AA12: =+IF(O$43=0,0,IF(O$43<0,-RANK(V12,V$5:V$40,0),RANK(V12,V$5:V$40,1))) -> 0 | AB12: =+IF(P$43=0,0,IF(P$43<0,-RANK(W12,W$5:W$40,0),RANK(W12,W$5:W$40,1))) -> 0 | AC12: =+IF(Q$43=0,0,IF(Q$43<0,-RANK(X12,X$5:X$40,0),RANK(X12,X$5:X$40,1))) -> 0 | AD12: =+IF(R$43=0,0,IF(R$43<0,-RANK(Y12,Y$5:Y$40,0),RANK(Y12,Y$5:Y$40,1))) -> 0 | AI12: -1
D13: 業務費 | E13: =+業務!E36 -> 1019945143 | F13: =+業務!F36 -> 0 | G13: =+業務!G36 -> 0 | H13: =+業務!H36 -> 0 | I13: =+業務!I36 -> 0 | J13: =+業務!J36 -> 992787715 | K13: =+業務!K36 -> 992787715 | L13: =+業務!L36 -> 4195233 | M13: =+業務!M36 -> 22962195 | N13: =+ROUND(F13*F$4/(100+F$4),0)+AE13 -> 0 | O13: =+ROUND(G13*G$4/(100+G$4),0)+AF13 -> 0 | P13: =+ROUND(H13*H$4/(100+H$4),0)+AG13 -> 0 | Q13: =+ROUND(I13*I$4/(100+I$4),0)+AH13 -> 0 | R13: =+ROUND(J13*J$4/(100+J$4),0)+AI13 -> 90253429 | S13: =SUM(N13:R13) -> 90253429 | T13: =+E13-S13 -> 929691714 | U13: =N13-F13*F$4/(100+F$4)-AE13 -> 0 | V13: =O13-G13*G$4/(100+G$4)-AF13 -> 0 | W13: =P13-H13*H$4/(100+H$4)-AG13 -> 0 | X13: =Q13-I13*I$4/(100+I$4)-AH13 -> 0 | Y13: =R13-J13*J$4/(100+J$4)-AI13 -> 0.36363636 | Z13: =+IF(N$43=0,0,IF(N$43<0,-RANK(U13,U$5:U$40,0),RANK(U13,U$5:U$40,1))) -> 0 | AA13: =+IF(O$43=0,0,IF(O$43<0,-RANK(V13,V$5:V$40,0),RANK(V13,V$5:V$40,1))) -> 0 | AB13: =+IF(P$43=0,0,IF(P$43<0,-RANK(W13,W$5:W$40,0),RANK(W13,W$5:W$40,1))) -> 0 | AC13: =+IF(Q$43=0,0,IF(Q$43<0,-RANK(X13,X$5:X$40,0),RANK(X13,X$5:X$40,1))) -> 0 | AD13: =+IF(R$43=0,0,IF(R$43<0,-RANK(Y13,Y$5:Y$40,0),RANK(Y13,Y$5:Y$40,1))) -> 0
D14: 総係費 | E14: =+総係!E37 -> 483965214 | F14: =+総係!F37 -> 0 | G14: =+総係!G37 -> 0 | H14: =+総係!H37 -> 0 | I14: =+総係!I37 -> 317198 | J14: =+総係!J37 -> 194208395 | K14: =+総係!K37 -> 194525593 | L14: =+総係!L37 -> 50827352 | M14: =+総係!M37 -> 238612269 | N14: =+ROUND(F14*F$4/(100+F$4),0)+AE14 -> 0 | O14: =+ROUND(G14*G$4/(100+G$4),0)+AF14 -> 0 | P14: =+ROUND(H14*H$4/(100+H$4),0)+AG14 -> 0 | Q14: =+ROUND(I14*I$4/(100+I$4),0)+AH14 -> 23496 | R14: =+ROUND(J14*J$4/(100+J$4),0)+AI14 -> 17655309 | S14: =SUM(N14:R14) -> 17678805 | T14: =+E14-S14 -> 466286409 | U14: =N14-F14*F$4/(100+F$4)-AE14 -> 0 | V14: =O14-G14*G$4/(100+G$4)-AF14 -> 0 | W14: =P14-H14*H$4/(100+H$4)-AG14 -> 0 | X14: =Q14-I14*I$4/(100+I$4)-AH14 -> -0.14814815 | Y14: =R14-J14*J$4/(100+J$4)-AI14 -> 0.36363636 | Z14: =+IF(N$43=0,0,IF(N$43<0,-RANK(U14,U$5:U$40,0),RANK(U14,U$5:U$40,1))) -> 0 | AA14: =+IF(O$43=0,0,IF(O$43<0,-RANK(V14,V$5:V$40,0),RANK(V14,V$5:V$40,1))) -> 0 | AB14: =+IF(P$43=0,0,IF(P$43<0,-RANK(W14,W$5:W$40,0),RANK(W14,W$5:W$40,1))) -> 0 | AC14: =+IF(Q$43=0,0,IF(Q$43<0,-RANK(X14,X$5:X$40,0),RANK(X14,X$5:X$40,1))) -> 0 | AD14: =+IF(R$43=0,0,IF(R$43<0,-RANK(Y14,Y$5:Y$40,0),RANK(Y14,Y$5:Y$40,1))) -> 0
D15: 特環費 | E15: =+特環!E37 -> 106990906 | F15: =+特環!F37 -> 0 | G15: =+特環!G37 -> 0 | H15: =+特環!H37 -> 0 | I15: =+特環!I37 -> 2121 | J15: =+特環!J37 -> 106852098 | K15: =+特環!K37 -> 106854219 | L15: =+特環!L37 -> 104407 | M15: =+特環!M37 -> 32280 | N15: =+ROUND(F15*F$4/(100+F$4),0)+AE15 -> 0 | O15: =+ROUND(G15*G$4/(100+G$4),0)+AF15 -> 0 | P15: =+ROUND(H15*H$4/(100+H$4),0)+AG15 -> 0 | Q15: =+ROUND(I15*I$4/(100+I$4),0)+AH15 -> 157 | R15: =+ROUND(J15*J$4/(100+J$4),0)+AI15 -> 9713827 | S15: =SUM(N15:R15) -> 9713984 | T15: =+E15-S15 -> 97276922
D16: 農集費 | E16: =+農集!E37 -> 247654024 | F16: =+農集!F37 -> 0 | G16: =+農集!G37 -> 0 | H16: =+農集!H37 -> 0 | I16: =+農集!I37 -> 5073 | J16: =+農集!J37 -> 247344387 | K16: =+農集!K37 -> 247349460 | L16: =+農集!L37 -> 182965 | M16: =+農集!M37 -> 121599 | N16: =+ROUND(F16*F$4/(100+F$4),0)+AE16 -> 0 | O16: =+ROUND(G16*G$4/(100+G$4),0)+AF16 -> 0 | P16: =+ROUND(H16*H$4/(100+H$4),0)+AG16 -> 0 | Q16: =+ROUND(I16*I$4/(100+I$4),0)+AH16 -> 376 | R16: =+ROUND(J16*J$4/(100+J$4),0)+AI16 -> 22485853 | S16: =SUM(N16:R16) -> 22486229 | T16: =+E16-S16 -> 225167795
D17: 浄化槽費 | E17: =+浄化!E37 -> 76388330 | F17: =+浄化!F37 -> 0 | G17: =+浄化!G37 -> 0 | H17: =+浄化!H37 -> 0 | I17: =+浄化!I37 -> 1529 | J17: =+浄化!J37 -> 70915767 | K17: =+浄化!K37 -> 70917296 | L17: =+浄化!L37 -> 5447767 | M17: =+浄化!M37 -> 23267 | N17: =+ROUND(F17*F$4/(100+F$4),0)+AE17 -> 0 | O17: =+ROUND(G17*G$4/(100+G$4),0)+AF17 -> 0 | P17: =+ROUND(H17*H$4/(100+H$4),0)+AG17 -> 0 | Q17: =+ROUND(I17*I$4/(100+I$4),0)+AH17 -> 113 | R17: =+ROUND(J17*J$4/(100+J$4),0)+AI17 -> 6446888 | S17: =SUM(N17:R17) -> 6447001 | T17: =+E17-S17 -> 69941329
D18: 災害復旧費 | E18: =+災!E36 -> 0 | F18: =+災!F36 -> 0 | G18: =+災!G36 -> 0 | H18: =+災!H36 -> 0 | I18: =+災!I36 -> 0 | J18: =+災!J36 -> 0 | K18: =+災!K36 -> 0 | L18: =+災!L36 -> 0 | M18: =+災!M36 -> 0 | N18: =+ROUND(F18*F$4/(100+F$4),0)+AE18 -> 0 | O18: =+ROUND(G18*G$4/(100+G$4),0)+AF18 -> 0 | P18: =+ROUND(H18*H$4/(100+H$4),0)+AG18 -> 0 | Q18: =+ROUND(I18*I$4/(100+I$4),0)+AH18 -> 0 | R18: =+ROUND(J18*J$4/(100+J$4),0)+AI18 -> 0 | S18: =SUM(N18:R18) -> 0 | T18: =+E18-S18 -> 0 | U18: =N18-F18*F$4/(100+F$4)-AE18 -> 0 | V18: =O18-G18*G$4/(100+G$4)-AF18 -> 0 | W18: =P18-H18*H$4/(100+H$4)-AG18 -> 0 | X18: =Q18-I18*I$4/(100+I$4)-AH18 -> 0 | Y18: =R18-J18*J$4/(100+J$4)-AI18 -> 0 | Z18: =+IF(N$43=0,0,IF(N$43<0,-RANK(U18,U$5:U$40,0),RANK(U18,U$5:U$40,1))) -> 0 | AA18: =+IF(O$43=0,0,IF(O$43<0,-RANK(V18,V$5:V$40,0),RANK(V18,V$5:V$40,1))) -> 0 | AB18: =+IF(P$43=0,0,IF(P$43<0,-RANK(W18,W$5:W$40,0),RANK(W18,W$5:W$40,1))) -> 0 | AC18: =+IF(Q$43=0,0,IF(Q$43<0,-RANK(X18,X$5:X$40,0),RANK(X18,X$5:X$40,1))) -> 0 | AD18: =+IF(R$43=0,0,IF(R$43<0,-RANK(Y18,Y$5:Y$40,0),RANK(Y18,Y$5:Y$40,1))) -> 0
D19: 減価償却費 | E19: =+減価!E36 -> 26551442230 | F19: =+減価!F36 -> 0 | G19: =+減価!G36 -> 0 | H19: =+減価!H36 -> 0 | I19: =+減価!I36 -> 0 | J19: =+減価!J36 -> 0 | K19: =+減価!K36 -> 0 | L19: =+減価!L36 -> 0 | M19: =+減価!M36 -> 26551442230 | N19: =+ROUND(F19*F$4/(100+F$4),0)+AE19 -> 0 | O19: =+ROUND(G19*G$4/(100+G$4),0)+AF19 -> 0 | P19: =+ROUND(H19*H$4/(100+H$4),0)+AG19 -> 0 | Q19: =+ROUND(I19*I$4/(100+I$4),0)+AH19 -> 0 | R19: =+ROUND(J19*J$4/(100+J$4),0)+AI19 -> 0 | S19: =SUM(N19:R19) -> 0 | T19: =+E19-S19 -> 26551442230 | U19: =N19-F19*F$4/(100+F$4)-AE19 -> 0 | V19: =O19-G19*G$4/(100+G$4)-AF19 -> 0 | W19: =P19-H19*H$4/(100+H$4)-AG19 -> 0 | X19: =Q19-I19*I$4/(100+I$4)-AH19 -> 0 | Y19: =R19-J19*J$4/(100+J$4)-AI19 -> 0 | Z19: =+IF(N$43=0,0,IF(N$43<0,-RANK(U19,U$5:U$40,0),RANK(U19,U$5:U$40,1))) -> 0 | AA19: =+IF(O$43=0,0,IF(O$43<0,-RANK(V19,V$5:V$40,0),RANK(V19,V$5:V$40,1))) -> 0 | AB19: =+IF(P$43=0,0,IF(P$43<0,-RANK(W19,W$5:W$40,0),RANK(W19,W$5:W$40,1))) -> 0 | AC19: =+IF(Q$43=0,0,IF(Q$43<0,-RANK(X19,X$5:X$40,0),RANK(X19,X$5:X$40,1))) -> 0 | AD19: =+IF(R$43=0,0,IF(R$43<0,-RANK(Y19,Y$5:Y$40,0),RANK(Y19,Y$5:Y$40,1))) -> 0
D20: 資産減耗費 | E20: =+減耗!E36 -> 503761871 | F20: =+減耗!F36 -> 0 | G20: =+減耗!G36 -> 0 | H20: =+減耗!H36 -> 0 | I20: =+減耗!I36 -> 0 | J20: =+減耗!J36 -> 0 | K20: =+減耗!K36 -> 0 | L20: =+減耗!L36 -> 0 | M20: =+減耗!M36 -> 503761871 | N20: =+ROUND(F20*F$4/(100+F$4),0)+AE20 -> 0 | O20: =+ROUND(G20*G$4/(100+G$4),0)+AF20 -> 0 | P20: =+ROUND(H20*H$4/(100+H$4),0)+AG20 -> 0 | Q20: =+ROUND(I20*I$4/(100+I$4),0)+AH20 -> 0 | R20: =+ROUND(J20*J$4/(100+J$4),0)+AI20 -> 0 | S20: =SUM(N20:R20) -> 0 | T20: =+E20-S20 -> 503761871 | U20: =N20-F20*F$4/(100+F$4)-AE20 -> 0 | V20: =O20-G20*G$4/(100+G$4)-AF20 -> 0 | W20: =P20-H20*H$4/(100+H$4)-AG20 -> 0 | X20: =Q20-I20*I$4/(100+I$4)-AH20 -> 0 | Y20: =R20-J20*J$4/(100+J$4)-AI20 -> 0 | Z20: =+IF(N$43=0,0,IF(N$43<0,-RANK(U20,U$5:U$40,0),RANK(U20,U$5:U$40,1))) -> 0 | AA20: =+IF(O$43=0,0,IF(O$43<0,-RANK(V20,V$5:V$40,0),RANK(V20,V$5:V$40,1))) -> 0 | AB20: =+IF(P$43=0,0,IF(P$43<0,-RANK(W20,W$5:W$40,0),RANK(W20,W$5:W$40,1))) -> 0 | AC20: =+IF(Q$43=0,0,IF(Q$43<0,-RANK(X20,X$5:X$40,0),RANK(X20,X$5:X$40,1))) -> 0 | AD20: =+IF(R$43=0,0,IF(R$43<0,-RANK(Y20,Y$5:Y$40,0),RANK(Y20,Y$5:Y$40,1))) -> 0
D22: 営業外費用 | E22: =+SUM(E23:E25) -> 3955185318 | F22: =+SUM(F23:F25) -> 0 | G22: =+SUM(G23:G25) -> 0 | H22: =+SUM(H23:H25) -> 23932 | I22: =+SUM(I23:I25) -> 0 | J22: =+SUM(J23:J25) -> 67182291 | K22: =+SUM(K23:K25) -> 67206223 | L22: =+SUM(L23:L25) -> 3884147396 | ... T22: =+SUM(T23:T25) -> 4161563541 | U22: =N22-F22*F$4/(100+F$4)-AE22 -> 0 | V22: =O22-G22*G$4/(100+G$4)-AF22 -> 0 | W22: =P22-H22*H$4/(100+H$4)-AG22 -> 0.25925926 | X22: =Q22-I22*I$4/(100+I$4)-AH22 -> 0 | Y22: =R22-J22*J$4/(100+J$4)-AI22 -> 0 | Z22: =+IF(N$43=0,0,IF(N$43<0,-RANK(U22,U$5:U$40,0),RANK(U22,U$5:U$40,1))) -> 0 | AA22: =+IF(O$43=0,0,IF(O$43<0,-RANK(V22,V$5:V$40,0),RANK(V22,V$5:V$40,1))) -> 0 | AB22: =+IF(P$43=0,0,IF(P$43<0,-RANK(W22,W$5:W$40,0),RANK(W22,W$5:W$40,1))) -> 0 | AC22: =+IF(Q$43=0,0,IF(Q$43<0,-RANK(X22,X$5:X$40,0),RANK(X22,X$5:X$40,1))) -> 0 | AD22: =+IF(R$43=0,0,IF(R$43<0,-RANK(Y22,Y$5:Y$40,0),RANK(Y22,Y$5:Y$40,1))) -> 0
D23: 支払利息・取扱費 | E23: =+営外!E5 -> 3945961149 | F23: =+営外!F5 -> 0 | G23: =+営外!G5 -> 0 | H23: =+営外!H5 -> 0 | I23: =+営外!I5 -> 0 | J23: =+営外!J5 -> 61813753 | K23: =+営外!K5 -> 61813753 | L23: =+営外!L5 -> 3884147396 | M23: =+営外!M5 -> 0 | N23: =+ROUND(F23*F$4/(100+F$4),0)+AE23 -> 0 | O23: =+ROUND(G23*G$4/(100+G$4),0)+AF23 -> 0 | P23: =+ROUND(H23*H$4/(100+H$4),0)+AG23 -> 0 | Q23: =+ROUND(I23*I$4/(100+I$4),0)+AH23 -> 0 | R23: =+ROUND(J23*J$4/(100+J$4),0)+AI23 -> 5619432 | S23: =SUM(N23:R23) -> 5619432 | T23: =+E23-S23 -> 3940341717 | U23: =N23-F23*F$4/(100+F$4)-AE23 -> 0 | V23: =O23-G23*G$4/(100+G$4)-AF23 -> 0 | W23: =P23-H23*H$4/(100+H$4)-AG23 -> 0 | X23: =Q23-I23*I$4/(100+I$4)-AH23 -> 0 | Y23: =R23-J23*J$4/(100+J$4)-AI23 -> -0.090909091 | Z23: =+IF(N$43=0,0,IF(N$43<0,-RANK(U23,U$5:U$40,0),RANK(U23,U$5:U$40,1))) -> 0 | AA23: =+IF(O$43=0,0,IF(O$43<0,-RANK(V23,V$5:V$40,0),RANK(V23,V$5:V$40,1))) -> 0 | AB23: =+IF(P$43=0,0,IF(P$43<0,-RANK(W23,W$5:W$40,0),RANK(W23,W$5:W$40,1))) -> 0 | AC23: =+IF(Q$43=0,0,IF(Q$43<0,-RANK(X23,X$5:X$40,0),RANK(X23,X$5:X$40,1))) -> 0 | AD23: =+IF(R$43=0,0,IF(R$43<0,-RANK(Y23,Y$5:Y$40,0),RANK(Y23,Y$5:Y$40,1))) -> 0
D24: 雑支出 | E24: =+営外!E14 -> 9224169 | F24: =+営外!F14 -> 0 | G24: =+営外!G14 -> 0 | H24: =+営外!H14 -> 23932 | I24: =+営外!I14 -> 0 | J24: =+営外!J14 -> 5368538 | K24: =+営外!K14 -> 5392470 | L24: =+営外!L14 -> 0 | M24: =+営外!M14 -> 3831699 | N24: =+ROUND(F24*F$4/(100+F$4),0)+AE24 -> 0 | O24: =+ROUND(G24*G$4/(100+G$4),0)+AF24 -> 0 | P24: =+ROUND(H24*H$4/(100+H$4),0)+AG24 -> 1773 | Q24: =+ROUND(I24*I$4/(100+I$4),0)+AH24 -> 0 | R24: =+ROUND(J24*J$4/(100+J$4),0)+AI24 -> 488049 | S24: =SUM(N24:R24) -> 489822 | T24: =+E24-S24 -> 8734347 | U24: =N24-F24*F$4/(100+F$4)-AE24 -> 0 | V24: =O24-G24*G$4/(100+G$4)-AF24 -> 0 | W24: =P24-H24*H$4/(100+H$4)-AG24 -> 0.25925926 | X24: =Q24-I24*I$4/(100+I$4)-AH24 -> 0 | Y24: =R24-J24*J$4/(100+J$4)-AI24 -> 0.090909091 | Z24: =+IF(N$43=0,0,IF(N$43<0,-RANK(U24,U$5:U$40,0),RANK(U24,U$5:U$40,1))) -> 0 | AA24: =+IF(O$43=0,0,IF(O$43<0,-RANK(V24,V$5:V$40,0),RANK(V24,V$5:V$40,1))) -> 0 | AB24: =+IF(P$43=0,0,IF(P$43<0,-RANK(W24,W$5:W$40,0),RANK(W24,W$5:W$40,1))) -> 0 | AC24: =+IF(Q$43=0,0,IF(Q$43<0,-RANK(X24,X$5:X$40,0),RANK(X24,X$5:X$40,1))) -> 0 | AD24: =+IF(R$43=0,0,IF(R$43<0,-RANK(Y24,Y$5:Y$40,0),RANK(Y24,Y$5:Y$40,1))) -> 0
D25: 消費税雑支出 | T25: =+SUM(営外!T17:T19) -> 212487477
D27: 特別損失 | E27: =+SUM(E28:E31) -> 20995298 | F27: =+SUM(F28:F31) -> 0 | G27: =+SUM(G28:G31) -> 0 | H27: =+SUM(H28:H31) -> 15407 | I27: =+SUM(I28:I31) -> 0 | J27: =+SUM(J28:J31) -> 10640333 | K27: =+SUM(K28:K31) -> 10655740 | L27: =+SUM(L28:L31) -> 6023 | ... T27: =+SUM(T28:T31) -> 20026854 | U27: =N27-F27*F$4/(100+F$4)-AE27 -> 0 | V27: =O27-G27*G$4/(100+G$4)-AF27 -> 0 | W27: =P27-H27*H$4/(100+H$4)-AG27 -> -0.25925926 | X27: =Q27-I27*I$4/(100+I$4)-AH27 -> 0 | Y27: =R27-J27*J$4/(100+J$4)-AI27 -> 0
D28: 過年度損益修正損 | E28: =+特損!E5 -> 10679943 | F28: =+特損!F5 -> 0 | G28: =+特損!G5 -> 0 | H28: =+特損!H5 -> 15407 | I28: =+特損!I5 -> 0 | J28: =+特損!J5 -> 10640333 | K28: =+特損!K5 -> 10655740 | L28: =+特損!L5 -> 6023 | M28: =+特損!M5 -> 18180 | N28: =+ROUND(F28*F$4/(100+F$4),0)+AE28 -> 0 | O28: =+ROUND(G28*G$4/(100+G$4),0)+AF28 -> 0 | P28: =+ROUND(H28*H$4/(100+H$4),0)+AG28 -> 1141 | Q28: =+ROUND(I28*I$4/(100+I$4),0)+AH28 -> 0 | R28: =+ROUND(J28*J$4/(100+J$4),0)+AI28 -> 967303 | S28: =SUM(N28:R28) -> 968444 | T28: =+E28-S28 -> 9711499 | U28: =N28-F28*F$4/(100+F$4)-AE28 -> 0 | V28: =O28-G28*G$4/(100+G$4)-AF28 -> 0 | W28: =P28-H28*H$4/(100+H$4)-AG28 -> -0.25925926 | X28: =Q28-I28*I$4/(100+I$4)-AH28 -> 0 | Y28: =R28-J28*J$4/(100+J$4)-AI28 -> 0 | Z28: =+IF(N$43=0,0,IF(N$43<0,-RANK(U28,U$5:U$40,0),RANK(U28,U$5:U$40,1))) -> 0 | AA28: =+IF(O$43=0,0,IF(O$43<0,-RANK(V28,V$5:V$40,0),RANK(V28,V$5:V$40,1))) -> 0 | AB28: =+IF(P$43=0,0,IF(P$43<0,-RANK(W28,W$5:W$40,0),RANK(W28,W$5:W$40,1))) -> 0 | AC28: =+IF(Q$43=0,0,IF(Q$43<0,-RANK(X28,X$5:X$40,0),RANK(X28,X$5:X$40,1))) -> 0 | AD28: =+IF(R$43=0,0,IF(R$43<0,-RANK(Y28,Y$5:Y$40,0),RANK(Y28,Y$5:Y$40,1))) -> 0
D29: その他特別損失 | E29: =+特損!E14 -> 0 | F29: =+特損!F14 -> 0 | G29: =+特損!G14 -> 0 | H29: =+特損!H14 -> 0 | I29: =+特損!I14 -> 0 | J29: =+特損!J14 -> 0 | K29: =+特損!K14 -> 0 | L29: =+特損!L14 -> 0 | M29: =+特損!M14 -> 0 | N29: =+ROUND(F29*F$4/(100+F$4),0)+AE29 -> 0 | O29: =+ROUND(G29*G$4/(100+G$4),0)+AF29 -> 0 | P29: =+ROUND(H29*H$4/(100+H$4),0)+AG29 -> 0 | Q29: =+ROUND(I29*I$4/(100+I$4),0)+AH29 -> 0 | R29: =+ROUND(J29*J$4/(100+J$4),0)+AI29 -> 0 | S29: =SUM(N29:R29) -> 0 | T29: =+E29-S29 -> 0 | U29: =N29-F29*F$4/(100+F$4)-AE29 -> 0 | V29: =O29-G29*G$4/(100+G$4)-AF29 -> 0 | W29: =P29-H29*H$4/(100+H$4)-AG29 -> 0 | X29: =Q29-I29*I$4/(100+I$4)-AH29 -> 0 | Y29: =R29-J29*J$4/(100+J$4)-AI29 -> 0 | Z29: =+IF(N$43=0,0,IF(N$43<0,-RANK(U29,U$5:U$40,0),RANK(U29,U$5:U$40,1))) -> 0 | AA29: =+IF(O$43=0,0,IF(O$43<0,-RANK(V29,V$5:V$40,0),RANK(V29,V$5:V$40,1))) -> 0 | AB29: =+IF(P$43=0,0,IF(P$43<0,-RANK(W29,W$5:W$40,0),RANK(W29,W$5:W$40,1))) -> 0 | AC29: =+IF(Q$43=0,0,IF(Q$43<0,-RANK(X29,X$5:X$40,0),RANK(X29,X$5:X$40,1))) -> 0 | AD29: =+IF(R$43=0,0,IF(R$43<0,-RANK(Y29,Y$5:Y$40,0),RANK(Y29,Y$5:Y$40,1))) -> 0
D30: 固定資産売却損 | E30: =+特損!E32 -> 10315355 | F30: =+特損!F32 -> 0 | G30: =+特損!G32 -> 0 | H30: =+特損!H32 -> 0 | I30: =+特損!I32 -> 0 | J30: =+特損!J32 -> 0 | K30: =+特損!K32 -> 0 | L30: =+特損!L32 -> 0 | M30: =+特損!M32 -> 10315355 | N30: =+ROUND(F30*F$4/(100+F$4),0)+AE30 -> 0 | O30: =+ROUND(G30*G$4/(100+G$4),0)+AF30 -> 0 | P30: =+ROUND(H30*H$4/(100+H$4),0)+AG30 -> 0 | Q30: =+ROUND(I30*I$4/(100+I$4),0)+AH30 -> 0 | R30: =+ROUND(J30*J$4/(100+J$4),0)+AI30 -> 0 | S30: =SUM(N30:R30) -> 0 | T30: =+E30-S30 -> 10315355 | U30: =N30-F30*F$4/(100+F$4)-AE30 -> 0 | V30: =O30-G30*G$4/(100+G$4)-AF30 -> 0 | W30: =P30-H30*H$4/(100+H$4)-AG30 -> 0 | X30: =Q30-I30*I$4/(100+I$4)-AH30 -> 0 | Y30: =R30-J30*J$4/(100+J$4)-AI30 -> 0 | Z30: =+IF(N$43=0,0,IF(N$43<0,-RANK(U30,U$5:U$40,0),RANK(U30,U$5:U$40,1))) -> 0 | AA30: =+IF(O$43=0,0,IF(O$43<0,-RANK(V30,V$5:V$40,0),RANK(V30,V$5:V$40,1))) -> 0 | AB30: =+IF(P$43=0,0,IF(P$43<0,-RANK(W30,W$5:W$40,0),RANK(W30,W$5:W$40,1))) -> 0 | AC30: =+IF(Q$43=0,0,IF(Q$43<0,-RANK(X30,X$5:X$40,0),RANK(X30,X$5:X$40,1))) -> 0 | AD30: =+IF(R$43=0,0,IF(R$43<0,-RANK(Y30,Y$5:Y$40,0),RANK(Y30,Y$5:Y$40,1))) -> 0
D31: 減損損失 | E31: =+特損!E34 -> 0 | F31: =+特損!F34 -> 0 | G31: =+特損!G34 -> 0 | H31: =+特損!H34 -> 0 | I31: =+特損!I34 -> 0 | J31: =+特損!J34 -> 0 | K31: =+特損!K34 -> 0 | L31: =+特損!L34 -> 0 | M31: =+特損!M34 -> 0 | N31: =+ROUND(F31*F$4/(100+F$4),0)+AE31 -> 0 | O31: =+ROUND(G31*G$4/(100+G$4),0)+AF31 -> 0 | P31: =+ROUND(H31*H$4/(100+H$4),0)+AG31 -> 0 | Q31: =+ROUND(I31*I$4/(100+I$4),0)+AH31 -> 0 | R31: =+ROUND(J31*J$4/(100+J$4),0)+AI31 -> 0 | S31: =SUM(N31:R31) -> 0 | T31: =+E31-S31 -> 0 | U31: =N31-F31*F$4/(100+F$4)-AE31 -> 0 | V31: =O31-G31*G$4/(100+G$4)-AF31 -> 0 | W31: =P31-H31*H$4/(100+H$4)-AG31 -> 0 | X31: =Q31-I31*I$4/(100+I$4)-AH31 -> 0 | Y31: =R31-J31*J$4/(100+J$4)-AI31 -> 0 | Z31: =+IF(N$43=0,0,IF(N$43<0,-RANK(U31,U$5:U$40,0),RANK(U31,U$5:U$40,1))) -> 0 | AA31: =+IF(O$43=0,0,IF(O$43<0,-RANK(V31,V$5:V$40,0),RANK(V31,V$5:V$40,1))) -> 0 | AB31: =+IF(P$43=0,0,IF(P$43<0,-RANK(W31,W$5:W$40,0),RANK(W31,W$5:W$40,1))) -> 0 | AC31: =+IF(Q$43=0,0,IF(Q$43<0,-RANK(X31,X$5:X$40,0),RANK(X31,X$5:X$40,1))) -> 0 | AD31: =+IF(R$43=0,0,IF(R$43<0,-RANK(Y31,Y$5:Y$40,0),RANK(Y31,Y$5:Y$40,1))) -> 0
U36: =+IF(F36=0,"",ROUND(F36*F$4/(100+F$4),7)-N36) | V36: =+IF(G36=0,"",ROUND(G36*G$4/(100+G$4),7)-O36) | Y36: =+IF(J36=0,"",ROUND(J36*J$4/(100+J$4),7)-R36) | AB36: =+IF(SUM(U36:Y36)=0,"",SUM(U36:Y36))
U37: =+IF(F37=0,"",ROUND(F37*F$4/(100+F$4),7)-N37) | V37: =+IF(G37=0,"",ROUND(G37*G$4/(100+G$4),7)-O37)
U38: =+IF(F38=0,"",ROUND(F38*F$4/(100+F$4),7)-N38) | V38: =+IF(G38=0,"",ROUND(G38*G$4/(100+G$4),7)-O38) | W38: =+IF(H38=0,"",ROUND(H38*H$4/(100+H$4),7)-P38) | Y38: =+IF(J38=0,"",ROUND(J38*J$4/(100+J$4),7)-R38) | AB38: =+IF(SUM(U38:Y38)=0,"",SUM(U38:Y38))
U39: =+IF(F39=0,"",ROUND(F39*F$4/(100+F$4),7)-N39) | V39: =+IF(G39=0,"",ROUND(G39*G$4/(100+G$4),7)-O39) | W39: =+IF(H39=0,"",ROUND(H39*H$4/(100+H$4),7)-P39) | Y39: =+IF(J39=0,"",ROUND(J39*J$4/(100+J$4),7)-R39) | AB39: =+IF(SUM(U39:Y39)=0,"",SUM(U39:Y39))
U40: =+IF(F40=0,"",ROUND(F40*F$4/(100+F$4),7)-N40)
D41: 計 | E41: =+SUM(E5,E22,E27) -> 42643669657 | F41: =+SUM(F5,F22,F27) -> 0 | G41: =+SUM(G5,G22,G27) -> 0 | H41: =+SUM(H5,H22,H27) -> 1236141 | I41: =+SUM(I5,I22,I27) -> 500878 | J41: =+SUM(J5,J22,J27) -> 9106828850 | K41: =+SUM(K5,K22,K27) -> 9108565869 | L41: =+SUM(L5,L22,L27) -> 4302104919 | ... T41: =+SUM(T5,T22,T27) -> 42028134935
D42: 総額検算 | E42: =+E41 -> 42643669657 | F42: =+F41 -> 0 | G42: =+G41 -> 0 | H42: =+H41 -> 1236141 | I42: =+I41 -> 500878 | J42: =+J41 -> 9106828850 | K42: =SUM(F42:J42) -> 9108565869 | L42: =+L41 -> 4302104919 | M42: =+M41 -> 29232998869 | N42: =+ROUNDDOWN(F42*F$4/(100+F$4),0) -> 0 | O42: =+ROUNDDOWN(G42*G$4/(100+G$4),0) -> 0 | P42: =+ROUNDDOWN(H42*H$4/(100+H$4),0) -> 91566 | Q42: =+ROUNDDOWN(I42*I$4/(100+I$4),0) -> 37102 | R42: =+ROUNDDOWN(J42*J$4/(100+J$4),0) -> 827893531 | S42: =SUM(N42:R42) -> 828022199 | T42: =+E42-S42 -> 41815647458
E43: =+E42-E41 -> 0 | F43: =+F42-F41 -> 0 | G43: =+G42-G41 -> 0 | H43: =+H42-H41 -> 0 | I43: =+I42-I41 -> 0 | J43: =+J42-J41 -> 0 | K43: =+K42-K41 -> 0 | L43: =+L42-L41 -> 0 | ... T43: =+T42-T41 -> -212487477
D45: 消費税及び地方消費税 | E45: =[1]消費税!$Z$118+[1]消費税!$AF$118 -> 343538729 | F45: 消費税中間 | G45: =+営外!E39 -> 42630200 | P45: 仕入税額控除不可消費税 | S45: ='[2]3条収入'!AH69 -> 210253123
D46: 税込決算額 | E46: =+E41+E45 -> 42987208386 | S46: =S42 -> 828022199 | T46: =T41+S46 -> 42856157134
T47: =E41-T46+S45 -> -2234354 | U47: ←仕入控除税額の算定にあたり、仮払消費税額×課税売上割合しか計上できないことにより控除できない額（マイナス表示）
D49: 【特定収入に係る課税仕入れ・課税仕入れ以外の特定のために使用する課税支出割合算出表】
D50: 費目 | E50: 雨水+汚水基準内+一般行政経費（水質・普及・水洗化を除く） | L50: 汚水基準外 | N50: 水質・普及・水洗化
E51: 税込決算額 | F51: 課税支出 | L51: 税込決算額 | M51: 課税支出 | N51: 税込決算額 | O51: 課税支出
F52: 3 | G52: 5 | H52: 8 | I52: 8 | J52: 10 | K52: 計
D53: 営業費用 | E53: =+SUM(E54:E67) -> 3688023972 | F53: =+SUM(F54:F67) -> 0 | G53: =+SUM(G54:G67) -> 0 | H53: =+SUM(H54:H67) -> 496314 | I53: =+SUM(I54:I67) -> 142297 | J53: =+SUM(J54:J67) -> 2459472462 | K53: =+SUM(K54:K67) -> 2460111073 | L53: =+SUM(L54:L67) -> 7816908465 | ... O53: =+SUM(O54:O67) -> 22835037
D54: 管きょ費 | E54: =+E6-L54 -> 345781722 | F54: =+IFERROR(ROUND(F6*$K54/SUM($F6:$J6),0),0) -> 0 | G54: =+IFERROR(ROUND(G6*$K54/SUM($F6:$J6),0),0) -> 0 | H54: =+IFERROR(ROUND(H6*$K54/SUM($F6:$J6),0),0) -> 383412 | I54: =+IFERROR(ROUND(I6*$K54/SUM($F6:$J6),0),0) -> 0 | J54: =+IFERROR(ROUND(J6*$K54/SUM($F6:$J6),0),0) -> 292845789 | K54: =+K6-M54 -> 293229201 | L54: =+[3]雨汚水!K7 -> 266038235 | M54: =+IFERROR(ROUND(L54*K6/E6,0),0) -> 225605271
D55: 水質指導費 | L55: =+[3]雨汚水!K8 -> 0 | M55: =+IFERROR(ROUND(L55*K7/E7,0),0) -> 0 | N55: =+E7 -> 52443869 | O55: =+K7 -> 12436317
D56: ポンプ場費 | E56: =+E8-L56 -> 1779977149 | F56: =+IFERROR(ROUND(F8*$K56/SUM($F8:$J8),0),0) -> 0 | G56: =+IFERROR(ROUND(G8*$K56/SUM($F8:$J8),0),0) -> 0 | H56: =+IFERROR(ROUND(H8*$K56/SUM($F8:$J8),0),0) -> 0 | I56: =+IFERROR(ROUND(I8*$K56/SUM($F8:$J8),0),0) -> 22935 | J56: =+IFERROR(ROUND(J8*$K56/SUM($F8:$J8),0),0) -> 867444589 | K56: =+K8-M56 -> 867467524 | L56: =+[3]雨汚水!K9 -> 576063076 | M56: =+IFERROR(ROUND(L56*K8/E8,0),0) -> 280742936
D57: 処理場費 | E57: =+E9-L57 -> 1428197863 | F57: =+IFERROR(ROUND(F9*$K57/SUM($F9:$J9),0),0) -> 0 | G57: =+IFERROR(ROUND(G9*$K57/SUM($F9:$J9),0),0) -> 0 | H57: =+IFERROR(ROUND(H9*$K57/SUM($F9:$J9),0),0) -> 112902 | I57: =+IFERROR(ROUND(I9*$K57/SUM($F9:$J9),0),0) -> 31492 | J57: =+IFERROR(ROUND(J9*$K57/SUM($F9:$J9),0),0) -> 1245382798 | K57: =+K9-M57 -> 1245527192 | L57: =+[3]雨汚水!K10 -> 5129506001 | M57: =+IFERROR(ROUND(L57*K9/E9,0),0) -> 4473427228
D58: 受託工事費 | E58: =+E10-L58 -> 0 | F58: =+IFERROR(ROUND(F10*$K58/SUM($F10:$J10),0),0) -> 0 | G58: =+IFERROR(ROUND(G10*$K58/SUM($F10:$J10),0),0) -> 0 | H58: =+IFERROR(ROUND(H10*$K58/SUM($F10:$J10),0),0) -> 0 | I58: =+IFERROR(ROUND(I10*$K58/SUM($F10:$J10),0),0) -> 0 | J58: =+IFERROR(ROUND(J10*$K58/SUM($F10:$J10),0),0) -> 0 | K58: =+K10-M58 -> 0 | L58: =+[3]雨汚水!K11 -> 0 | M58: =+IFERROR(ROUND(L58*K10/E10,0),0) -> 0
D59: 普及促進費 | L59: =+[3]雨汚水!K12 -> 44424774 | M59: =+IFERROR(ROUND(L59*K11/E11,0),0) -> 9435234 | N59: =+E11-L59 -> 44424775 | O59: =+K11-M59 -> 9435235
D60: 水洗化貸付事業費 | L60: =+[3]雨汚水!K13 -> 0 | M60: =+IFERROR(ROUND(L60*K12/E12,0),0) -> 0 | N60: =+E12 -> 10483859 | O60: =+K12 -> 963485
D61: 業務費 | E61: =+E13-L61 -> 0 | F61: =+IFERROR(ROUND(F13*$K61/SUM($F13:$J13),0),0) -> 0 | G61: =+IFERROR(ROUND(G13*$K61/SUM($F13:$J13),0),0) -> 0 | H61: =+IFERROR(ROUND(H13*$K61/SUM($F13:$J13),0),0) -> 0 | I61: =+IFERROR(ROUND(I13*$K61/SUM($F13:$J13),0),0) -> 0 | J61: =+IFERROR(ROUND(J13*$K61/SUM($F13:$J13),0),0) -> 0 | K61: =+K13-M61 -> 0 | L61: =+[3]雨汚水!K14 -> 1019945143 | M61: =+IFERROR(ROUND(L61*K13/E13,0),0) -> 992787715
D62: 総係費 | E62: =+E14-L62 -> 134067238 | F62: =+IFERROR(ROUND(F14*$K62/SUM($F14:$J14),0),0) -> 0 | G62: =+IFERROR(ROUND(G14*$K62/SUM($F14:$J14),0),0) -> 0 | H62: =+IFERROR(ROUND(H14*$K62/SUM($F14:$J14),0),0) -> 0 | I62: =+IFERROR(ROUND(I14*$K62/SUM($F14:$J14),0),0) -> 87870 | J62: =+IFERROR(ROUND(J14*$K62/SUM($F14:$J14),0),0) -> 53799286 | K62: =+K14-M62 -> 53887156 | L62: =+[3]雨汚水!K15 -> 349897976 | M62: =+IFERROR(ROUND(L62*K14/E14,0),0) -> 140638437
D63: 特環費 | E63: =+E15-L63 -> 0 | F63: =+IFERROR(ROUND(F15*$K63/SUM($F15:$J15),0),0) -> 0 | G63: =+IFERROR(ROUND(G15*$K63/SUM($F15:$J15),0),0) -> 0 | H63: =+IFERROR(ROUND(H15*$K63/SUM($F15:$J15),0),0) -> 0 | I63: =+IFERROR(ROUND(I15*$K63/SUM($F15:$J15),0),0) -> 0 | J63: =+IFERROR(ROUND(J15*$K63/SUM($F15:$J15),0),0) -> 0 | K63: =+K15-M63 -> 0 | L63: =+[3]雨汚水!K16 -> 106990906 | M63: =+IFERROR(ROUND(L63*K15/E15,0),0) -> 106854219
D64: 農集費 | E64: =+E16-L64 -> 0 | F64: =+IFERROR(ROUND(F16*$K64/SUM($F16:$J16),0),0) -> 0 | G64: =+IFERROR(ROUND(G16*$K64/SUM($F16:$J16),0),0) -> 0 | H64: =+IFERROR(ROUND(H16*$K64/SUM($F16:$J16),0),0) -> 0 | I64: =+IFERROR(ROUND(I16*$K64/SUM($F16:$J16),0),0) -> 0 | J64: =+IFERROR(ROUND(J16*$K64/SUM($F16:$J16),0),0) -> 0 | K64: =+K16-M64 -> 0 | L64: =+[3]雨汚水!K17 -> 247654024 | M64: =+IFERROR(ROUND(L64*K16/E16,0),0) -> 247349460
D65: 浄化槽費 | E65: =+E17-L65 -> 0 | F65: =+IFERROR(ROUND(F17*$K65/SUM($F17:$J17),0),0) -> 0 | G65: =+IFERROR(ROUND(G17*$K65/SUM($F17:$J17),0),0) -> 0 | H65: =+IFERROR(ROUND(H17*$K65/SUM($F17:$J17),0),0) -> 0 | I65: =+IFERROR(ROUND(I17*$K65/SUM($F17:$J17),0),0) -> 0 | J65: =+IFERROR(ROUND(J17*$K65/SUM($F17:$J17),0),0) -> 0 | K65: =+K17-M65 -> 0 | L65: =+[3]雨汚水!K18 -> 76388330 | M65: =+IFERROR(ROUND(L65*K17/E17,0),0) -> 70917296
D66: 災害復旧費 | E66: =+E18-L66 -> 0 | F66: =+IFERROR(ROUND(F18*$K66/SUM($F18:$J18),0),0) -> 0 | G66: =+IFERROR(ROUND(G18*$K66/SUM($F18:$J18),0),0) -> 0 | H66: =+IFERROR(ROUND(H18*$K66/SUM($F18:$J18),0),0) -> 0 | I66: =+IFERROR(ROUND(I18*$K66/SUM($F18:$J18),0),0) -> 0 | J66: =+IFERROR(ROUND(J18*$K66/SUM($F18:$J18),0),0) -> 0 | K66: =+K18-M66 -> 0 | L66: =+[3]雨汚水!K19 -> 0 | M66: =+IFERROR(ROUND(L66*K18/E18,0),0) -> 0
D67: 資産減耗費（撤去費） | E67: =+[3]雨汚水!F20 -> 0 | F67: =+IFERROR(ROUND(F20*$K67/SUM($F20:$J20),0),0) -> 0 | G67: =+IFERROR(ROUND(G20*$K67/SUM($F20:$J20),0),0) -> 0 | H67: =+IFERROR(ROUND(H20*$K67/SUM($F20:$J20),0),0) -> 0 | I67: =+IFERROR(ROUND(I20*$K67/SUM($F20:$J20),0),0) -> 0 | J67: =+IFERROR(ROUND(J20*$K67/SUM($F20:$J20),0),0) -> 0 | K67: =+K20-M67 -> 0 | L67: =+[3]雨汚水!K20 -> 0 | M67: =+IFERROR(ROUND(L67*K20/E20,0),0) -> 0
D69: 営業外費用 | E69: =+SUM(E70:E71) -> 0 | F69: =+SUM(F70:F71) -> 0 | G69: =+SUM(G70:G71) -> 0 | H69: =+SUM(H70:H71) -> 0 | I69: =+SUM(I70:I71) -> 0 | J69: =+SUM(J70:J71) -> 0 | K69: =+SUM(K70:K71) -> 0 | L69: =+SUM(L70:L71) -> 9226652 | ... O69: =+SUM(O70:O71) -> 0
D70: 一時借入金利息 | E70: =+[3]雨汚水!E22-L70 -> 0 | F70: 0 | G70: 0 | H70: 0 | I70: 0 | J70: 0 | L70: =+[3]雨汚水!K22 -> 2483 | M70: 0
D71: 雑支出 | E71: =+E24-L71 -> 0 | F71: =+IFERROR(ROUND(F24*$K71/SUM($F24:$J24),0),0) -> 0 | G71: =+IFERROR(ROUND(G24*$K71/SUM($F24:$J24),0),0) -> 0 | H71: =+IFERROR(ROUND(H24*$K71/SUM($F24:$J24),0),0) -> 0 | I71: =+IFERROR(ROUND(I24*$K71/SUM($F24:$J24),0),0) -> 0 | J71: =+IFERROR(ROUND(J24*$K71/SUM($F24:$J24),0),0) -> 0 | K71: =+K24-M71 -> 0 | L71: =+[3]雨汚水!K23+[3]雨汚水!K24 -> 9224169 | M71: =+IFERROR(ROUND(L71*K24/E24,0),0) -> 5392470
D73: 特別損失 | E73: =+SUM(E74:E75) -> 6760 | F73: =+SUM(F74:F75) -> 0 | G73: =+SUM(G74:G75) -> 0 | H73: =+SUM(H74:H75) -> 10 | I73: =+SUM(I74:I75) -> 0 | J73: =+SUM(J74:J75) -> 6735 | K73: =+SUM(K74:K75) -> 6745 | L73: =+SUM(L74:L75) -> 10673183 | ... O73: =+SUM(O74:O75) -> 0
D74: 過年度損益修正損 | E74: =+E28-L74 -> 6760 | F74: =+IFERROR(ROUND(F28*$K74/SUM($F28:$J28),0),0) -> 0 | G74: =+IFERROR(ROUND(G28*$K74/SUM($F28:$J28),0),0) -> 0 | H74: =+IFERROR(ROUND(H28*$K74/SUM($F28:$J28),0),0) -> 10 | I74: =+IFERROR(ROUND(I28*$K74/SUM($F28:$J28),0),0) -> 0 | J74: =+IFERROR(ROUND(J28*$K74/SUM($F28:$J28),0),0) -> 6735 | K74: =+K28-M74 -> 6745 | L74: =+[3]雨汚水!K29 -> 10673183 | M74: =+IFERROR(ROUND(L74*K28/E28,0),0) -> 10648995
D75: その他特別損失 | E75: =+E29-L75 -> 0 | F75: =+IFERROR(ROUND(F29*$K75/SUM($F29:$J29),0),0) -> 0 | G75: =+IFERROR(ROUND(G29*$K75/SUM($F29:$J29),0),0) -> 0 | H75: =+IFERROR(ROUND(H29*$K75/SUM($F29:$J29),0),0) -> 0 | I75: =+IFERROR(ROUND(I29*$K75/SUM($F29:$J29),0),0) -> 0 | J75: =+IFERROR(ROUND(J29*$K75/SUM($F29:$J29),0),0) -> 0 | K75: =+K29-M75 -> 0 | L75: =+[3]雨汚水!E30 -> 0 | M75: =+IFERROR(ROUND(L75*K29/E29,0),0) -> 0
D77: 計 | E77: =+SUM(E53,E69,E73) -> 3688030732 | F77: =+SUM(F53,F69,F73) -> 0 | G77: =+SUM(G53,G69,G73) -> 0 | H77: =+SUM(H53,H69,H73) -> 496324 | I77: =+SUM(I53,I69,I73) -> 142297 | J77: =+SUM(J53,J69,J73) -> 2459479197 | K77: =+SUM(K53,K69,K73) -> 2460117818 | L77: =+SUM(L53,L69,L73) -> 7836808300 | ... O77: =+SUM(O53,O69,O73) -> 22835037
D78: 総額検算 | E78: =+E77 -> 3688030732 | F78: =+F77 -> 0 | G78: =+G77 -> 0 | H78: =+H77 -> 496324 | I78: =+I77 -> 142297 | J78: =+J77 -> 2459479197 | K78: =+K77 -> 2460117818 | L78: =+L77 -> 7836808300 | ... O78: =+O77 -> 22835037
E79: =+E78-E77 -> 0 | F79: =+F78-F77 -> 0 | G79: =+G78-G77 -> 0 | H79: =+H78-H77 -> 0 | I79: =+I78-I77 -> 0 | J79: =+J78-J77 -> 0 | K79: =+K78-K77 -> 0 | L79: =+L78-L77 -> 0 | ... O79: =+O78-O77 -> 0
N81: 税込決算額
N82: =+E77+L77+N77-[3]雨汚水!E47 -> -10315355
D84: うち、災害復旧事業分（現年分）
D85: 費目
E86: 税込決算額 | F86: 課税支出
F87: 3 | G87: 5 | H87: 8 | I87: 8 | J87: 10 | K87: 計
D88: 管きょ費 | E88: =+災害伝票!BB4 -> 0 | F88: =+災害伝票!AU4 -> 0 | G88: =+災害伝票!AV4 -> 0 | H88: =+災害伝票!AW4 -> 0 | I88: =+災害伝票!AX4 -> 0 | J88: =+災害伝票!AY4 -> 0 | K88: =SUM(F88:J88) -> 0
D89: ポンプ場費 | E89: =+災害伝票!BB5 -> 0 | F89: =+災害伝票!AU5 -> 0 | G89: =+災害伝票!AV5 -> 0 | H89: =+災害伝票!AW5 -> 0 | I89: =+災害伝票!AX5 -> 0 | J89: =+災害伝票!AY5 -> 0 | K89: =SUM(F89:J89) -> 0
D90: 処理場費 | E90: =+災害伝票!BB6 -> 0 | F90: =+災害伝票!AU6 -> 0 | G90: =+災害伝票!AV6 -> 0 | H90: =+災害伝票!AW6 -> 0 | I90: =+災害伝票!AX6 -> 0 | J90: =+災害伝票!AY6 -> 0 | K90: =SUM(F90:J90) -> 0
D91: 特環費 | E91: =+災害伝票!BB7 -> 0 | F91: =+災害伝票!AU7 -> 0 | G91: =+災害伝票!AV7 -> 0 | H91: =+災害伝票!AW7 -> 0 | I91: =+災害伝票!AX7 -> 0 | J91: =+災害伝票!AY7 -> 0 | K91: =SUM(F91:J91) -> 0
D92: 農集費 | E92: =+災害伝票!BB8 -> 0 | F92: =+災害伝票!AU8 -> 0 | G92: =+災害伝票!AV8 -> 0 | H92: =+災害伝票!AW8 -> 0 | I92: =+災害伝票!AX8 -> 0 | J92: =+災害伝票!AY8 -> 0 | K92: =SUM(F92:J92) -> 0
D93: 浄化槽費 | E93: =+災害伝票!BB9 -> 0 | F93: =+災害伝票!AU9 -> 0 | G93: =+災害伝票!AV9 -> 0 | H93: =+災害伝票!AW9 -> 0 | I93: =+災害伝票!AX9 -> 0 | J93: =+災害伝票!AY9 -> 0 | K93: =SUM(F93:J93) -> 0
D94: 計 | E94: =SUM(E88:E93) -> 0 | F94: =SUM(F88:F93) -> 0 | G94: =SUM(G88:G93) -> 0 | H94: =SUM(H88:H93) -> 0 | I94: =SUM(I88:I93) -> 0 | J94: =SUM(J88:J93) -> 0 | K94: =SUM(K88:K93) -> 0
D97: うち、災害復旧事業分（事故繰越分）
D98: 費目
E99: 税込決算額 | F99: 課税支出
F100: 3 | G100: 5 | H100: 8 | I100: 8 | J100: 10 | K100: 計
D101: 管きょ費 | E101: =+災害伝票!BJ4 -> 0 | F101: =+災害伝票!BC4 -> 0 | G101: =+災害伝票!BD4 -> 0 | H101: =+災害伝票!BE4 -> 0 | I101: =+災害伝票!BF4 -> 0 | J101: =+災害伝票!BG4 -> 0 | K101: =SUM(F101:J101) -> 0
D102: ポンプ場費 | E102: =+災害伝票!BJ5 -> 0 | F102: =+災害伝票!BC5 -> 0 | G102: =+災害伝票!BD5 -> 0 | H102: =+災害伝票!BE5 -> 0 | I102: =+災害伝票!BF5 -> 0 | J102: =+災害伝票!BG5 -> 0 | K102: =SUM(F102:J102) -> 0
D103: 処理場費 | E103: =+災害伝票!BJ6 -> 0 | F103: =+災害伝票!BC6 -> 0 | G103: =+災害伝票!BD6 -> 0 | H103: =+災害伝票!BE6 -> 0 | I103: =+災害伝票!BF6 -> 0 | J103: =+災害伝票!BG6 -> 0 | K103: =SUM(F103:J103) -> 0
D104: 特環費 | E104: =+災害伝票!BJ7 -> 0 | F104: =+災害伝票!BC7 -> 0 | G104: =+災害伝票!BD7 -> 0 | H104: =+災害伝票!BE7 -> 0 | I104: =+災害伝票!BF7 -> 0 | J104: =+災害伝票!BG7 -> 0 | K104: =SUM(F104:J104) -> 0
D105: 農集費 | E105: =+災害伝票!BJ8 -> 0 | F105: =+災害伝票!BC8 -> 0 | G105: =+災害伝票!BD8 -> 0 | H105: =+災害伝票!BE8 -> 0 | I105: =+災害伝票!BF8 -> 0 | J105: =+災害伝票!BG8 -> 0 | K105: =SUM(F105:J105) -> 0
D106: 浄化槽費 | E106: =+災害伝票!BJ9 -> 0 | F106: =+災害伝票!BC9 -> 0 | G106: =+災害伝票!BD9 -> 0 | H106: =+災害伝票!BE9 -> 0 | I106: =+災害伝票!BF9 -> 0 | J106: =+災害伝票!BG9 -> 0 | K106: =SUM(F106:J106) -> 0
D107: 計 | E107: =SUM(E101:E106) -> 0 | F107: =SUM(F101:F106) -> 0 | G107: =SUM(G101:G106) -> 0 | H107: =SUM(H101:H106) -> 0 | I107: =SUM(I101:I106) -> 0 | J107: =SUM(J101:J106) -> 0 | K107: =SUM(K101:K106) -> 0

Sheet 管
D1: =+'3条支出'!D1 -> 令和５年度決算 消費税算出資料
D2: 【管きょ費】
A3: 事業 | B3: 節 | C3: 細節 | D3: 費目 | E3: 税込決算額 | F3: 課税支出 | L3: 非課税支出 | M3: 不課税支出 | N3: 消費税 | T3: 税抜決算額 | U3: 消費税 端数確認 | Z3: 消費税端数調整ランク | AE3: 消費税 調整額
F4: 3 | G4: 5 | H4: 8 | I4: 8 | J4: 10 | K4: 計 | N4: 3 | O4: 5 | P4: 8 | Q4: 8 | R4: 10 | S4: 計 | U4: 3 | V4: 5 | W4: 8 | X4: 8 | Y4: 10 | Z4: 3 | AA4: 5 | AB4: 8 | AC4: 8 | AD4: 10 | AE4: 3 | AF4: 5 | AG4: 8 | AH4: 8 | AI4: 10
A5: 1 | B5: 8830201 | D5: 報酬 | E5: =+IF($A5="",IF($C5="",SUMIFS(全伝票!I:I,全伝票!$B:$B,$B5),SUMIFS(全伝票!I:I,全伝票!$C:$C,$C5)),IF($C5="",SUMIFS(全伝票!I:I,全伝票!$A:$A,$A5,全伝票!$B:$B,$B5),SUMIFS(全伝票!I:I,全伝票!$A:$A,$A5,全伝票!$C:$C,$C5))) -> 0 | F5: =+IF($A5="",IF($C5="",SUMIFS(全伝票!J:J,全伝票!$B:$B,$B5),SUMIFS(全伝票!J:J,全伝票!$C:$C,$C5)),IF($C5="",SUMIFS(全伝票!J:J,全伝票!$A:$A,$A5,全伝票!$B:$B,$B5),SUMIFS(全伝票!J:J,全伝票!$A:$A,$A5,全伝票!$C:$C,$C5))) -> 0 | G5: =+IF($A5="",IF($C5="",SUMIFS(全伝票!K:K,全伝票!$B:$B,$B5),SUMIFS(全伝票!K:K,全伝票!$C:$C,$C5)),IF($C5="",SUMIFS(全伝票!K:K,全伝票!$A:$A,$A5,全伝票!$B:$B,$B5),SUMIFS(全伝票!K:K,全伝票!$A:$A,$A5,全伝票!$C:$C,$C5))) -> 0 | H5: =+IF($A5="",IF($C5="",SUMIFS(全伝票!L:L,全伝票!$B:$B,$B5),SUMIFS(全伝票!L:L,全伝票!$C:$C,$C5)),IF($C5="",SUMIFS(全伝票!L:L,全伝票!$A:$A,$A5,全伝票!$B:$B,$B5),SUMIFS(全伝票!L:L,全伝票!$A:$A,$A5,全伝票!$C:$C,$C5))) -> 0 | I5: =+IF($A5="",IF($C5="",SUMIFS(全伝票!M:M,全伝票!$B:$B,$B5),SUMIFS(全伝票!M:M,全伝票!$C:$C,$C5)),IF($C5="",SUMIFS(全伝票!M:M,全伝票!$A:$A,$A5,全伝票!$B:$B,$B5),SUMIFS(全伝票!M:M,全伝票!$A:$A,$A5,全伝票!$C:$C,$C5))) -> 0 | J5: =+IF($A5="",IF($C5="",SUMIFS(全伝票!N:N,全伝票!$B:$B,$B5),SUMIFS(全伝票!N:N,全伝票!$C:$C,$C5)),IF($C5="",SUMIFS(全伝票!N:N,全伝票!$A:$A,$A5,全伝票!$B:$B,$B5),SUMIFS(全伝票!N:N,全伝票!$A:$A,$A5,全伝票!$C:$C,$C5))) -> 0 | K5: =SUM(F5:J5) -> 0 | L5: =+IF($A5="",IF($C5="",SUMIFS(全伝票!O:O,全伝票!$B:$B,$B5),SUMIFS(全伝票!O:O,全伝票!$C:$C,$C5)),IF($C5="",SUMIFS(全伝票!O:O,全伝票!$A:$A,$A5,全伝票!$B:$B,$B5),SUMIFS(全伝票!O:O,全伝票!$A:$A,$A5,全伝票!$C:$C,$C5))) -> 0 | M5: =+IF($A5="",IF($C5="",SUMIFS(全伝票!P:P,全伝票!$B:$B,$B5),SUMIFS(全伝票!P:P,全伝票!$C:$C,$C5)),IF($C5="",SUMIFS(全伝票!P:P,全伝票!$A:$A,$A5,全伝票!$B:$B,$B5),SUMIFS(全伝票!P:P,全伝票!$A:$A,$A5,全伝票!$C:$C,$C5))) -> 0 | N5: =+ROUND(F5*F$4/(100+F$4),0)+AE5 -> 0 | O5: =+ROUND(G5*G$4/(100+G$4),0)+AF5 -> 0 | P5: =+ROUND(H5*H$4/(100+H$4),0)+AG5 -> 0 | Q5: =+ROUND(I5*I$4/(100+I$4),0)+AH5 -> 0 | R5: =+ROUND(J5*J$4/(100+J$4),0)+AI5 -> 0 | S5: =SUM(N5:R5) -> 0 | T5: =+E5-S5 -> 0 | U5: =N5-F5*F$4/(100+F$4) -> 0 | V5: =O5-G5*G$4/(100+G$4) -> 0 | W5: =P5-H5*H$4/(100+H$4) -> 0 | X5: =Q5-I5*I$4/(100+I$4) -> 0 | Y5: =R5-J5*J$4/(100+J$4) -> 0 | Z5: =+IF(N$38=0,0,IF(N$38<0,-RANK(U5,U$5:U$35,0),RANK(U5,U$5:U$35,1))) -> 0 | AA5: =+IF(O$38=0,0,IF(O$38<0,-RANK(V5,V$5:V$35,0),RANK(V5,V$5:V$35,1))) -> 0 | AB5: =+IF(P$38=0,0,IF(P$38<0,-RANK(W5,W$5:W$35,0),RANK(W5,W$5:W$35,1))) -> 0 | AC5: =+IF(Q$38=0,0,IF(Q$38<0,-RANK(X5,X$5:X$35,0),RANK(X5,X$5:X$35,1))) -> 0 | AD5: =+IF(R$38=0,0,IF(R$38<0,-RANK(Y5,Y$5:Y$35,0),RANK(Y5,Y$5:Y$35,1))) -> 0
A6: 1 | B6: 8830202 | D6: 給料 | E6: =+IF($A6="",IF($C6="",SUMIFS(全伝票!I:I,全伝票!$B:$B,$B6),SUMIFS(全伝票!I:I,全伝票!$C:$C,$C6)),IF($C6="",SUMIFS(全伝票!I:I,全伝票!$A:$A,$A6,全伝票!$B:$B,$B6),SUMIFS(全伝票!I:I,全伝票!$A:$A,$A6,全伝票!$C:$C,$C6))) -> 39580800 | F6: =+IF($A6="",IF($C6="",SUMIFS(全伝票!J:J,全伝票!$B:$B,$B6),SUMIFS(全伝票!J:J,全伝票!$C:$C,$C6)),IF($C6="",SUMIFS(全伝票!J:J,全伝票!$A:$A,$A6,全伝票!$B:$B,$B6),SUMIFS(全伝票!J:J,全伝票!$A:$A,$A6,全伝票!$C:$C,$C6))) -> 0 | G6: =+IF($A6="",IF($C6="",SUMIFS(全伝票!K:K,全伝票!$B:$B,$B6),SUMIFS(全伝票!K:K,全伝票!$C:$C,$C6)),IF($C6="",SUMIFS(全伝票!K:K,全伝票!$A:$A,$A6,全伝票!$B:$B,$B6),SUMIFS(全伝票!K:K,全伝票!$A:$A,$A6,全伝票!$C:$C,$C6))) -> 0 | H6: =+IF($A6="",IF($C6="",SUMIFS(全伝票!L:L,全伝票!$B:$B,$B6),SUMIFS(全伝票!L:L,全伝票!$C:$C,$C6)),IF($C6="",SUMIFS(全伝票!L:L,全伝票!$A:$A,$A6,全伝票!$B:$B,$B6),SUMIFS(全伝票!L:L,全伝票!$A:$A,$A6,全伝票!$C:$C,$C6))) -> 0 | I6: =+IF($A6="",IF($C6="",SUMIFS(全伝票!M:M,全伝票!$B:$B,$B6),SUMIFS(全伝票!M:M,全伝票!$C:$C,$C6)),IF($C6="",SUMIFS(全伝票!M:M,全伝票!$A:$A,$A6,全伝票!$B:$B,$B6),SUMIFS(全伝票!M:M,全伝票!$A:$A,$A6,全伝票!$C:$C,$C6))) -> 0 | J6: =+IF($A6="",IF($C6="",SUMIFS(全伝票!N:N,全伝票!$B:$B,$B6),SUMIFS(全伝票!N:N,全伝票!$C:$C,$C6)),IF($C6="",SUMIFS(全伝票!N:N,全伝票!$A:$A,$A6,全伝票!$B:$B,$B6),SUMIFS(全伝票!N:N,全伝票!$A:$A,$A6,全伝票!$C:$C,$C6))) -> 0 | K6: =SUM(F6:J6) -> 0 | L6: =+IF($A6="",IF($C6="",SUMIFS(全伝票!O:O,全伝票!$B:$B,$B6),SUMIFS(全伝票!O:O,全伝票!$C:$C,$C6)),IF($C6="",SUMIFS(全伝票!O:O,全伝票!$A:$A,$A6,全伝票!$B:$B,$B6),SUMIFS(全伝票!O:O,全伝票!$A:$A,$A6,全伝票!$C:$C,$C6))) -> 0 | M6: =+IF($A6="",IF($C6="",SUMIFS(全伝票!P:P,全伝票!$B:$B,$B6),SUMIFS(全伝票!P:P,全伝票!$C:$C,$C6)),IF($C6="",SUMIFS(全伝票!P:P,全伝票!$A:$A,$A6,全伝票!$B:$B,$B6),SUMIFS(全伝票!P:P,全伝票!$A:$A,$A6,全伝票!$C:$C,$C6))) -> 39580800 | N6: =+ROUND(F6*F$4/(100+F$4),0)+AE6 -> 0 | O6: =+ROUND(G6*G$4/(100+G$4),0)+AF6 -> 0 | P6: =+ROUND(H6*H$4/(100+H$4),0)+AG6 -> 0 | Q6: =+ROUND(I6*I$4/(100+I$4),0)+AH6 -> 0 | R6: =+ROUND(J6*J$4/(100+J$4),0)+AI6 -> 0 | S6: =SUM(N6:R6) -> 0 | T6: =+E6-S6 -> 39580800 | U6: =N6-F6*F$4/(100+F$4) -> 0 | V6: =O6-G6*G$4/(100+G$4) -> 0 | W6: =P6-H6*H$4/(100+H$4) -> 0 | X6: =Q6-I6*I$4/(100+I$4) -> 0 | Y6: =R6-J6*J$4/(100+J$4) -> 0 | Z6: =+IF(N$38=0,0,IF(N$38<0,-RANK(U6,U$5:U$35,0),RANK(U6,U$5:U$35,1))) -> 0 | AA6: =+IF(O$38=0,0,IF(O$38<0,-RANK(V6,V$5:V$35,0),RANK(V6,V$5:V$35,1))) -> 0 | AB6: =+IF(P$38=0,0,IF(P$38<0,-RANK(W6,W$5:W$35,0),RANK(W6,W$5:W$35,1))) -> 0 | AC6: =+IF(Q$38=0,0,IF(Q$38<0,-RANK(X6,X$5:X$35,0),RANK(X6,X$5:X$35,1))) -> 0 | AD6: =+IF(R$38=0,0,IF(R$38<0,-RANK(Y6,Y$5:Y$35,0),RANK(Y6,Y$5:Y$35,1))) -> 0
A7: 1 | B7: 8830203 | D7: 手当等 | E7: =+IF($A7="",IF($C7="",SUMIFS(全伝票!I:I,全伝票!$B:$B,$B7),SUMIFS(全伝票!I:I,全伝票!$C:$C,$C7)),IF($C7="",SUMIFS(全伝票!I:I,全伝票!$A:$A,$A7,全伝票!$B:$B,$B7),SUMIFS(全伝票!I:I,全伝票!$A:$A,$A7,全伝票!$C:$C,$C7))) -> 28582995 | F7: =+IF($A7="",IF($C7="",SUMIFS(全伝票!J:J,全伝票!$B:$B,$B7),SUMIFS(全伝票!J:J,全伝票!$C:$C,$C7)),IF($C7="",SUMIFS(全伝票!J:J,全伝票!$A:$A,$A7,全伝票!$B:$B,$B7),SUMIFS(全伝票!J:J,全伝票!$A:$A,$A7,全伝票!$C:$C,$C7))) -> 0 | G7: =+IF($A7="",IF($C7="",SUMIFS(全伝票!K:K,全伝票!$B:$B,$B7),SUMIFS(全伝票!K:K,全伝票!$C:$C,$C7)),IF($C7="",SUMIFS(全伝票!K:K,全伝票!$A:$A,$A7,全伝票!$B:$B,$B7),SUMIFS(全伝票!K:K,全伝票!$A:$A,$A7,全伝票!$C:$C,$C7))) -> 0 | H7: =+IF($A7="",IF($C7="",SUMIFS(全伝票!L:L,全伝票!$B:$B,$B7),SUMIFS(全伝票!L:L,全伝票!$C:$C,$C7)),IF($C7="",SUMIFS(全伝票!L:L,全伝票!$A:$A,$A7,全伝票!$B:$B,$B7),SUMIFS(全伝票!L:L,全伝票!$A:$A,$A7,全伝票!$C:$C,$C7))) -> 0 | I7: =+IF($A7="",IF($C7="",SUMIFS(全伝票!M:M,全伝票!$B:$B,$B7),SUMIFS(全伝票!M:M,全伝票!$C:$C,$C7)),IF($C7="",SUMIFS(全伝票!M:M,全伝票!$A:$A,$A7,全伝票!$B:$B,$B7),SUMIFS(全伝票!M:M,全伝票!$A:$A,$A7,全伝票!$C:$C,$C7))) -> 0 | J7: =+IF($A7="",IF($C7="",SUMIFS(全伝票!N:N,全伝票!$B:$B,$B7),SUMIFS(全伝票!N:N,全伝票!$C:$C,$C7)),IF($C7="",SUMIFS(全伝票!N:N,全伝票!$A:$A,$A7,全伝票!$B:$B,$B7),SUMIFS(全伝票!N:N,全伝票!$A:$A,$A7,全伝票!$C:$C,$C7))) -> 1117260 | K7: =SUM(F7:J7) -> 1117260 | L7: =+IF($A7="",IF($C7="",SUMIFS(全伝票!O:O,全伝票!$B:$B,$B7),SUMIFS(全伝票!O:O,全伝票!$C:$C,$C7)),IF($C7="",SUMIFS(全伝票!O:O,全伝票!$A:$A,$A7,全伝票!$B:$B,$B7),SUMIFS(全伝票!O:O,全伝票!$A:$A,$A7,全伝票!$C:$C,$C7))) -> 0 | M7: =+IF($A7="",IF($C7="",SUMIFS(全伝票!P:P,全伝票!$B:$B,$B7),SUMIFS(全伝票!P:P,全伝票!$C:$C,$C7)),IF($C7="",SUMIFS(全伝票!P:P,全伝票!$A:$A,$A7,全伝票!$B:$B,$B7),SUMIFS(全伝票!P:P,全伝票!$A:$A,$A7,全伝票!$C:$C,$C7))) -> 27465735 | N7: =+ROUND(F7*F$4/(100+F$4),0)+AE7 -> 0 | O7: =+ROUND(G7*G$4/(100+G$4),0)+AF7 -> 0 | P7: =+ROUND(H7*H$4/(100+H$4),0)+AG7 -> 0 | Q7: =+ROUND(I7*I$4/(100+I$4),0)+AH7 -> 0 | R7: =+ROUND(J7*J$4/(100+J$4),0)+AI7 -> 101569 | S7: =SUM(N7:R7) -> 101569 | T7: =+E7-S7 -> 28481426 | U7: =N7-F7*F$4/(100+F$4) -> 0 | V7: =O7-G7*G$4/(100+G$4) -> 0 | W7: =P7-H7*H$4/(100+H$4) -> 0 | X7: =Q7-I7*I$4/(100+I$4) -> 0 | Y7: =R7-J7*J$4/(100+J$4) -> -0.090909091 | Z7: =+IF(N$38=0,0,IF(N$38<0,-RANK(U7,U$5:U$35,0),RANK(U7,U$5:U$35,1))) -> 0 | AA7: =+IF(O$38=0,0,IF(O$38<0,-RANK(V7,V$5:V$35,0),RANK(V7,V$5:V$35,1))) -> 0 | AB7: =+IF(P$38=0,0,IF(P$38<0,-RANK(W7,W$5:W$35,0),RANK(W7,W$5:W$35,1))) -> 0 | AC7: =+IF(Q$38=0,0,IF(Q$38<0,-RANK(X7,X$5:X$35,0),RANK(X7,X$5:X$35,1))) -> 0 | AD7: =+IF(R$38=0,0,IF(R$38<0,-RANK(Y7,Y$5:Y$35,0),RANK(Y7,Y$5:Y$35,1))) -> 0
A8: 1 | B8: 8830204 | D8: 法定福利費 | E8: =+IF($A8="",IF($C8="",SUMIFS(全伝票!I:I,全伝票!$B:$B,$B8),SUMIFS(全伝票!I:I,全伝票!$C:$C,$C8)),IF($C8="",SUMIFS(全伝票!I:I,全伝票!$A:$A,$A8,全伝票!$B:$B,$B8),SUMIFS(全伝票!I:I,全伝票!$A:$A,$A8,全伝票!$C:$C,$C8))) -> 13837163 | F8: =+IF($A8="",IF($C8="",SUMIFS(全伝票!J:J,全伝票!$B:$B,$B8),SUMIFS(全伝票!J:J,全伝票!$C:$C,$C8)),IF($C8="",SUMIFS(全伝票!J:J,全伝票!$A:$A,$A8,全伝票!$B:$B,$B8),SUMIFS(全伝票!J:J,全伝票!$A:$A,$A8,全伝票!$C:$C,$C8))) -> 0 | G8: =+IF($A8="",IF($C8="",SUMIFS(全伝票!K:K,全伝票!$B:$B,$B8),SUMIFS(全伝票!K:K,全伝票!$C:$C,$C8)),IF($C8="",SUMIFS(全伝票!K:K,全伝票!$A:$A,$A8,全伝票!$B:$B,$B8),SUMIFS(全伝票!K:K,全伝票!$A:$A,$A8,全伝票!$C:$C,$C8))) -> 0 | H8: =+IF($A8="",IF($C8="",SUMIFS(全伝票!L:L,全伝票!$B:$B,$B8),SUMIFS(全伝票!L:L,全伝票!$C:$C,$C8)),IF($C8="",SUMIFS(全伝票!L:L,全伝票!$A:$A,$A8,全伝票!$B:$B,$B8),SUMIFS(全伝票!L:L,全伝票!$A:$A,$A8,全伝票!$C:$C,$C8))) -> 0 | I8: =+IF($A8="",IF($C8="",SUMIFS(全伝票!M:M,全伝票!$B:$B,$B8),SUMIFS(全伝票!M:M,全伝票!$C:$C,$C8)),IF($C8="",SUMIFS(全伝票!M:M,全伝票!$A:$A,$A8,全伝票!$B:$B,$B8),SUMIFS(全伝票!M:M,全伝票!$A:$A,$A8,全伝票!$C:$C,$C8))) -> 0 | J8: =+IF($A8="",IF($C8="",SUMIFS(全伝票!N:N,全伝票!$B:$B,$B8),SUMIFS(全伝票!N:N,全伝票!$C:$C,$C8)),IF($C8="",SUMIFS(全伝票!N:N,全伝票!$A:$A,$A8,全伝票!$B:$B,$B8),SUMIFS(全伝票!N:N,全伝票!$A:$A,$A8,全伝票!$C:$C,$C8))) -> 0 | K8: =SUM(F8:J8) -> 0 | L8: =+IF($A8="",IF($C8="",SUMIFS(全伝票!O:O,全伝票!$B:$B,$B8),SUMIFS(全伝票!O:O,全伝票!$C:$C,$C8)),IF($C8="",SUMIFS(全伝票!O:O,全伝票!$A:$A,$A8,全伝票!$B:$B,$B8),SUMIFS(全伝票!O:O,全伝票!$A:$A,$A8,全伝票!$C:$C,$C8))) -> 13772507 | M8: =+IF($A8="",IF($C8="",SUMIFS(全伝票!P:P,全伝票!$B:$B,$B8),SUMIFS(全伝票!P:P,全伝票!$C:$C,$C8)),IF($C8="",SUMIFS(全伝票!P:P,全伝票!$A:$A,$A8,全伝票!$B:$B,$B8),SUMIFS(全伝票!P:P,全伝票!$A:$A,$A8,全伝票!$C:$C,$C8))) -> 64656 | N8: =+ROUND(F8*F$4/(100+F$4),0)+AE8 -> 0 | O8: =+ROUND(G8*G$4/(100+G$4),0)+AF8 -> 0 | P8: =+ROUND(H8*H$4/(100+H$4),0)+AG8 -> 0 | Q8: =+ROUND(I8*I$4/(100+I$4),0)+AH8 -> 0 | R8: =+ROUND(J8*J$4/(100+J$4),0)+AI8 -> 0 | S8: =SUM(N8:R8) -> 0 | T8: =+E8-S8 -> 13837163 | U8: =N8-F8*F$4/(100+F$4) -> 0 | V8: =O8-G8*G$4/(100+G$4) -> 0 | W8: =P8-H8*H$4/(100+H$4) -> 0 | X8: =Q8-I8*I$4/(100+I$4) -> 0 | Y8: =R8-J8*J$4/(100+J$4) -> 0 | Z8: =+IF(N$38=0,0,IF(N$38<0,-RANK(U8,U$5:U$35,0),RANK(U8,U$5:U$35,1))) -> 0 | AA8: =+IF(O$38=0,0,IF(O$38<0,-RANK(V8,V$5:V$35,0),RANK(V8,V$5:V$35,1))) -> 0 | AB8: =+IF(P$38=0,0,IF(P$38<0,-RANK(W8,W$5:W$35,0),RANK(W8,W$5:W$35,1))) -> 0 | AC8: =+IF(Q$38=0,0,IF(Q$38<0,-RANK(X8,X$5:X$35,0),RANK(X8,X$5:X$35,1))) -> 0 | AD8: =+IF(R$38=0,0,IF(R$38<0,-RANK(Y8,Y$5:Y$35,0),RANK(Y8,Y$5:Y$35,1))) -> 0
A9: 1 | B9: 8830205 | D9: 災害補償費 | E9: =+IF($A9="",IF($C9="",SUMIFS(全伝票!I:I,全伝票!$B:$B,$B9),SUMIFS(全伝票!I:I,全伝票!$C:$C,$C9)),IF($C9="",SUMIFS(全伝票!I:I,全伝票!$A:$A,$A9,全伝票!$B:$B,$B9),SUMIFS(全伝票!I:I,全伝票!$A:$A,$A9,全伝票!$C:$C,$C9))) -> 0 | F9: =+IF($A9="",IF($C9="",SUMIFS(全伝票!J:J,全伝票!$B:$B,$B9),SUMIFS(全伝票!J:J,全伝票!$C:$C,$C9)),IF($C9="",SUMIFS(全伝票!J:J,全伝票!$A:$A,$A9,全伝票!$B:$B,$B9),SUMIFS(全伝票!J:J,全伝票!$A:$A,$A9,全伝票!$C:$C,$C9))) -> 0 | G9: =+IF($A9="",IF($C9="",SUMIFS(全伝票!K:K,全伝票!$B:$B,$B9),SUMIFS(全伝票!K:K,全伝票!$C:$C,$C9)),IF($C9="",SUMIFS(全伝票!K:K,全伝票!$A:$A,$A9,全伝票!$B:$B,$B9),SUMIFS(全伝票!K:K,全伝票!$A:$A,$A9,全伝票!$C:$C,$C9))) -> 0 | H9: =+IF($A9="",IF($C9="",SUMIFS(全伝票!L:L,全伝票!$B:$B,$B9),SUMIFS(全伝票!L:L,全伝票!$C:$C,$C9)),IF($C9="",SUMIFS(全伝票!L:L,全伝票!$A:$A,$A9,全伝票!$B:$B,$B9),SUMIFS(全伝票!L:L,全伝票!$A:$A,$A9,全伝票!$C:$C,$C9))) -> 0 | I9: =+IF($A9="",IF($C9="",SUMIFS(全伝票!M:M,全伝票!$B:$B,$B9),SUMIFS(全伝票!M:M,全伝票!$C:$C,$C9)),IF($C9="",SUMIFS(全伝票!M:M,全伝票!$A:$A,$A9,全伝票!$B:$B,$B9),SUMIFS(全伝票!M:M,全伝票!$A:$A,$A9,全伝票!$C:$C,$C9))) -> 0 | J9: =+IF($A9="",IF($C9="",SUMIFS(全伝票!N:N,全伝票!$B:$B,$B9),SUMIFS(全伝票!N:N,全伝票!$C:$C,$C9)),IF($C9="",SUMIFS(全伝票!N:N,全伝票!$A:$A,$A9,全伝票!$B:$B,$B9),SUMIFS(全伝票!N:N,全伝票!$A:$A,$A9,全伝票!$C:$C,$C9))) -> 0 | K9: =SUM(F9:J9) -> 0 | L9: =+IF($A9="",IF($C9="",SUMIFS(全伝票!O:O,全伝票!$B:$B,$B9),SUMIFS(全伝票!O:O,全伝票!$C:$C,$C9)),IF($C9="",SUMIFS(全伝票!O:O,全伝票!$A:$A,$A9,全伝票!$B:$B,$B9),SUMIFS(全伝票!O:O,全伝票!$A:$A,$A9,全伝票!$C:$C,$C9))) -> 0 | M9: =+IF($A9="",IF($C9="",SUMIFS(全伝票!P:P,全伝票!$B:$B,$B9),SUMIFS(全伝票!P:P,全伝票!$C:$C,$C9)),IF($C9="",SUMIFS(全伝票!P:P,全伝票!$A:$A,$A9,全伝票!$B:$B,$B9),SUMIFS(全伝票!P:P,全伝票!$A:$A,$A9,全伝票!$C:$C,$C9))) -> 0 | N9: =+ROUND(F9*F$4/(100+F$4),0)+AE9 -> 0 | O9: =+ROUND(G9*G$4/(100+G$4),0)+AF9 -> 0 | P9: =+ROUND(H9*H$4/(100+H$4),0)+AG9 -> 0 | Q9: =+ROUND(I9*I$4/(100+I$4),0)+AH9 -> 0 | R9: =+ROUND(J9*J$4/(100+J$4),0)+AI9 -> 0 | S9: =SUM(N9:R9) -> 0 | T9: =+E9-S9 -> 0 | U9: =N9-F9*F$4/(100+F$4) -> 0 | V9: =O9-G9*G$4/(100+G$4) -> 0 | W9: =P9-H9*H$4/(100+H$4) -> 0 | X9: =Q9-I9*I$4/(100+I$4) -> 0 | Y9: =R9-J9*J$4/(100+J$4) -> 0 | Z9: =+IF(N$38=0,0,IF(N$38<0,-RANK(U9,U$5:U$35,0),RANK(U9,U$5:U$35,1))) -> 0 | AA9: =+IF(O$38=0,0,IF(O$38<0,-RANK(V9,V$5:V$35,0),RANK(V9,V$5:V$35,1))) -> 0 | AB9: =+IF(P$38=0,0,IF(P$38<0,-RANK(W9,W$5:W$35,0),RANK(W9,W$5:W$35,1))) -> 0 | AC9: =+IF(Q$38=0,0,IF(Q$38<0,-RANK(X9,X$5:X$35,0),RANK(X9,X$5:X$35,1))) -> 0 | AD9: =+IF(R$38=0,0,IF(R$38<0,-RANK(Y9,Y$5:Y$35,0),RANK(Y9,Y$5:Y$35,1))) -> 0
A10: 1 | B10: 8830207 | D10: 賃金 | E10: =+IF($A10="",IF($C10="",SUMIFS(全伝票!I:I,全伝票!$B:$B,$B10),SUMIFS(全伝票!I:I,全伝票!$C:$C,$C10)),IF($C10="",SUMIFS(全伝票!I:I,全伝票!$A:$A,$A10,全伝票!$B:$B,$B10),SUMIFS(全伝票!I:I,全伝票!$A:$A,$A10,全伝票!$C:$C,$C10))) -> 0 | F10: =+IF($A10="",IF($C10="",SUMIFS(全伝票!J:J,全伝票!$B:$B,$B10),SUMIFS(全伝票!J:J,全伝票!$C:$C,$C10)),IF($C10="",SUMIFS(全伝票!J:J,全伝票!$A:$A,$A10,全伝票!$B:$B,$B10),SUMIFS(全伝票!J:J,全伝票!$A:$A,$A10,全伝票!$C:$C,$C10))) -> 0 | G10: =+IF($A10="",IF($C10="",SUMIFS(全伝票!K:K,全伝票!$B:$B,$B10),SUMIFS(全伝票!K:K,全伝票!$C:$C,$C10)),IF($C10="",SUMIFS(全伝票!K:K,全伝票!$A:$A,$A10,全伝票!$B:$B,$B10),SUMIFS(全伝票!K:K,全伝票!$A:$A,$A10,全伝票!$C:$C,$C10))) -> 0 | H10: =+IF($A10="",IF($C10="",SUMIFS(全伝票!L:L,全伝票!$B:$B,$B10),SUMIFS(全伝票!L:L,全伝票!$C:$C,$C10)),IF($C10="",SUMIFS(全伝票!L:L,全伝票!$A:$A,$A10,全伝票!$B:$B,$B10),SUMIFS(全伝票!L:L,全伝票!$A:$A,$A10,全伝票!$C:$C,$C10))) -> 0 | I10: =+IF($A10="",IF($C10="",SUMIFS(全伝票!M:M,全伝票!$B:$B,$B10),SUMIFS(全伝票!M:M,全伝票!$C:$C,$C10)),IF($C10="",SUMIFS(全伝票!M:M,全伝票!$A:$A,$A10,全伝票!$B:$B,$B10),SUMIFS(全伝票!M:M,全伝票!$A:$A,$A10,全伝票!$C:$C,$C10))) -> 0 | J10: =+IF($A10="",IF($C10="",SUMIFS(全伝票!N:N,全伝票!$B:$B,$B10),SUMIFS(全伝票!N:N,全伝票!$C:$C,$C10)),IF($C10="",SUMIFS(全伝票!N:N,全伝票!$A:$A,$A10,全伝票!$B:$B,$B10),SUMIFS(全伝票!N:N,全伝票!$A:$A,$A10,全伝票!$C:$C,$C10))) -> 0 | K10: =SUM(F10:J10) -> 0 | L10: =+IF($A10="",IF($C10="",SUMIFS(全伝票!O:O,全伝票!$B:$B,$B10),SUMIFS(全伝票!O:O,全伝票!$C:$C,$C10)),IF($C10="",SUMIFS(全伝票!O:O,全伝票!$A:$A,$A10,全伝票!$B:$B,$B10),SUMIFS(全伝票!O:O,全伝票!$A:$A,$A10,全伝票!$C:$C,$C10))) -> 0 | M10: =+IF($A10="",IF($C10="",SUMIFS(全伝票!P:P,全伝票!$B:$B,$B10),SUMIFS(全伝票!P:P,全伝票!$C:$C,$C10)),IF($C10="",SUMIFS(全伝票!P:P,全伝票!$A:$A,$A10,全伝票!$B:$B,$B10),SUMIFS(全伝票!P:P,全伝票!$A:$A,$A10,全伝票!$C:$C,$C10))) -> 0 | N10: =+ROUND(F10*F$4/(100+F$4),0)+AE10 -> 0 | O10: =+ROUND(G10*G$4/(100+G$4),0)+AF10 -> 0 | P10: =+ROUND(H10*H$4/(100+H$4),0)+AG10 -> 0 | Q10: =+ROUND(I10*I$4/(100+I$4),0)+AH10 -> 0 | R10: =+ROUND(J10*J$4/(100+J$4),0)+AI10 -> 0 | S10: =SUM(N10:R10) -> 0 | T10: =+E10-S10 -> 0 | U10: =N10-F10*F$4/(100+F$4) -> 0 | V10: =O10-G10*G$4/(100+G$4) -> 0 | W10: =P10-H10*H$4/(100+H$4) -> 0 | X10: =Q10-I10*I$4/(100+I$4) -> 0 | Y10: =R10-J10*J$4/(100+J$4) -> 0 | Z10: =+IF(N$38=0,0,IF(N$38<0,-RANK(U10,U$5:U$35,0),RANK(U10,U$5:U$35,1))) -> 0 | AA10: =+IF(O$38=0,0,IF(O$38<0,-RANK(V10,V$5:V$35,0),RANK(V10,V$5:V$35,1))) -> 0 | AB10: =+IF(P$38=0,0,IF(P$38<0,-RANK(W10,W$5:W$35,0),RANK(W10,W$5:W$35,1))) -> 0 | AC10: =+IF(Q$38=0,0,IF(Q$38<0,-RANK(X10,X$5:X$35,0),RANK(X10,X$5:X$35,1))) -> 0 | AD10: =+IF(R$38=0,0,IF(R$38<0,-RANK(Y10,Y$5:Y$35,0),RANK(Y10,Y$5:Y$35,1))) -> 0
A11: 1 | B11: 8830208 | D11: 報償費 | E11: =+IF($A11="",IF($C11="",SUMIFS(全伝票!I:I,全伝票!$B:$B,$B11),SUMIFS(全伝票!I:I,全伝票!$C:$C,$C11)),IF($C11="",SUMIFS(全伝票!I:I,全伝票!$A:$A,$A11,全伝票!$B:$B,$B11),SUMIFS(全伝票!I:I,全伝票!$A:$A,$A11,全伝票!$C:$C,$C11))) -> 45200 | F11: =+IF($A11="",IF($C11="",SUMIFS(全伝票!J:J,全伝票!$B:$B,$B11),SUMIFS(全伝票!J:J,全伝票!$C:$C,$C11)),IF($C11="",SUMIFS(全伝票!J:J,全伝票!$A:$A,$A11,全伝票!$B:$B,$B11),SUMIFS(全伝票!J:J,全伝票!$A:$A,$A11,全伝票!$C:$C,$C11))) -> 0 | G11: =+IF($A11="",IF($C11="",SUMIFS(全伝票!K:K,全伝票!$B:$B,$B11),SUMIFS(全伝票!K:K,全伝票!$C:$C,$C11)),IF($C11="",SUMIFS(全伝票!K:K,全伝票!$A:$A,$A11,全伝票!$B:$B,$B11),SUMIFS(全伝票!K:K,全伝票!$A:$A,$A11,全伝票!$C:$C,$C11))) -> 0 | H11: =+IF($A11="",IF($C11="",SUMIFS(全伝票!L:L,全伝票!$B:$B,$B11),SUMIFS(全伝票!L:L,全伝票!$C:$C,$C11)),IF($C11="",SUMIFS(全伝票!L:L,全伝票!$A:$A,$A11,全伝票!$B:$B,$B11),SUMIFS(全伝票!L:L,全伝票!$A:$A,$A11,全伝票!$C:$C,$C11))) -> 0 | I11: =+IF($A11="",IF($C11="",SUMIFS(全伝票!M:M,全伝票!$B:$B,$B11),SUMIFS(全伝票!M:M,全伝票!$C:$C,$C11)),IF($C11="",SUMIFS(全伝票!M:M,全伝票!$A:$A,$A11,全伝票!$B:$B,$B11),SUMIFS(全伝票!M:M,全伝票!$A:$A,$A11,全伝票!$C:$C,$C11))) -> 0 | J11: =+IF($A11="",IF($C11="",SUMIFS(全伝票!N:N,全伝票!$B:$B,$B11),SUMIFS(全伝票!N:N,全伝票!$C:$C,$C11)),IF($C11="",SUMIFS(全伝票!N:N,全伝票!$A:$A,$A11,全伝票!$B:$B,$B11),SUMIFS(全伝票!N:N,全伝票!$A:$A,$A11,全伝票!$C:$C,$C11))) -> 45200 | K11: =SUM(F11:J11) -> 45200 | L11: =+IF($A11="",IF($C11="",SUMIFS(全伝票!O:O,全伝票!$B:$B,$B11),SUMIFS(全伝票!O:O,全伝票!$C:$C,$C11)),IF($C11="",SUMIFS(全伝票!O:O,全伝票!$A:$A,$A11,全伝票!$B:$B,$B11),SUMIFS(全伝票!O:O,全伝票!$A:$A,$A11,全伝票!$C:$C,$C11))) -> 0 | M11: =+IF($A11="",IF($C11="",SUMIFS(全伝票!P:P,全伝票!$B:$B,$B11),SUMIFS(全伝票!P:P,全伝票!$C:$C,$C11)),IF($C11="",SUMIFS(全伝票!P:P,全伝票!$A:$A,$A11,全伝票!$B:$B,$B11),SUMIFS(全伝票!P:P,全伝票!$A:$A,$A11,全伝票!$C:$C,$C11))) -> 0 | N11: =+ROUND(F11*F$4/(100+F$4),0)+AE11 -> 0 | O11: =+ROUND(G11*G$4/(100+G$4),0)+AF11 -> 0 | P11: =+ROUND(H11*H$4/(100+H$4),0)+AG11 -> 0 | Q11: =+ROUND(I11*I$4/(100+I$4),0)+AH11 -> 0 | R11: =+ROUND(J11*J$4/(100+J$4),0)+AI11 -> 4109 | S11: =SUM(N11:R11) -> 4109 | T11: =+E11-S11 -> 41091 | U11: =N11-F11*F$4/(100+F$4) -> 0 | V11: =O11-G11*G$4/(100+G$4) -> 0 | W11: =P11-H11*H$4/(100+H$4) -> 0 | X11: =Q11-I11*I$4/(100+I$4) -> 0 | Y11: =R11-J11*J$4/(100+J$4) -> -0.090909091 | Z11: =+IF(N$38=0,0,IF(N$38<0,-RANK(U11,U$5:U$35,0),RANK(U11,U$5:U$35,1))) -> 0 | AA11: =+IF(O$38=0,0,IF(O$38<0,-RANK(V11,V$5:V$35,0),RANK(V11,V$5:V$35,1))) -> 0 | AB11: =+IF(P$38=0,0,IF(P$38<0,-RANK(W11,W$5:W$35,0),RANK(W11,W$5:W$35,1))) -> 0 | AC11: =+IF(Q$38=0,0,IF(Q$38<0,-RANK(X11,X$5:X$35,0),RANK(X11,X$5:X$35,1))) -> 0 | AD11: =+IF(R$38=0,0,IF(R$38<0,-RANK(Y11,Y$5:Y$35,0),RANK(Y11,Y$5:Y$35,1))) -> 0
A12: 1 | B12: 8830210 | C12: 883021001 | D12: 普通旅費 | E12: =+IF($A12="",IF($C12="",SUMIFS(全伝票!I:I,全伝票!$B:$B,$B12),SUMIFS(全伝票!I:I,全伝票!$C:$C,$C12)),IF($C12="",SUMIFS(全伝票!I:I,全伝票!$A:$A,$A12,全伝票!$B:$B,$B12),SUMIFS(全伝票!I:I,全伝票!$A:$A,$A12,全伝票!$C:$C,$C12))) -> 0 | F12: =+IF($A12="",IF($C12="",SUMIFS(全伝票!J:J,全伝票!$B:$B,$B12),SUMIFS(全伝票!J:J,全伝票!$C:$C,$C12)),IF($C12="",SUMIFS(全伝票!J:J,全伝票!$A:$A,$A12,全伝票!$B:$B,$B12),SUMIFS(全伝票!J:J,全伝票!$A:$A,$A12,全伝票!$C:$C,$C12))) -> 0 | G12: =+IF($A12="",IF($C12="",SUMIFS(全伝票!K:K,全伝票!$B:$B,$B12),SUMIFS(全伝票!K:K,全伝票!$C:$C,$C12)),IF($C12="",SUMIFS(全伝票!K:K,全伝票!$A:$A,$A12,全伝票!$B:$B,$B12),SUMIFS(全伝票!K:K,全伝票!$A:$A,$A12,全伝票!$C:$C,$C12))) -> 0 | H12: =+IF($A12="",IF($C12="",SUMIFS(全伝票!L:L,全伝票!$B:$B,$B12),SUMIFS(全伝票!L:L,全伝票!$C:$C,$C12)),IF($C12="",SUMIFS(全伝票!L:L,全伝票!$A:$A,$A12,全伝票!$B:$B,$B12),SUMIFS(全伝票!L:L,全伝票!$A:$A,$A12,全伝票!$C:$C,$C12))) -> 0 | I12: =+IF($A12="",IF($C12="",SUMIFS(全伝票!M:M,全伝票!$B:$B,$B12),SUMIFS(全伝票!M:M,全伝票!$C:$C,$C12)),IF($C12="",SUMIFS(全伝票!M:M,全伝票!$A:$A,$A12,全伝票!$B:$B,$B12),SUMIFS(全伝票!M:M,全伝票!$A:$A,$A12,全伝票!$C:$C,$C12))) -> 0 | J12: =+IF($A12="",IF($C12="",SUMIFS(全伝票!N:N,全伝票!$B:$B,$B12),SUMIFS(全伝票!N:N,全伝票!$C:$C,$C12)),IF($C12="",SUMIFS(全伝票!N:N,全伝票!$A:$A,$A12,全伝票!$B:$B,$B12),SUMIFS(全伝票!N:N,全伝票!$A:$A,$A12,全伝票!$C:$C,$C12))) -> 0 | K12: =SUM(F12:J12) -> 0 | L12: =+IF($A12="",IF($C12="",SUMIFS(全伝票!O:O,全伝票!$B:$B,$B12),SUMIFS(全伝票!O:O,全伝票!$C:$C,$C12)),IF($C12="",SUMIFS(全伝票!O:O,全伝票!$A:$A,$A12,全伝票!$B:$B,$B12),SUMIFS(全伝票!O:O,全伝票!$A:$A,$A12,全伝票!$C:$C,$C12))) -> 0 | M12: =+IF($A12="",IF($C12="",SUMIFS(全伝票!P:P,全伝票!$B:$B,$B12),SUMIFS(全伝票!P:P,全伝票!$C:$C,$C12)),IF($C12="",SUMIFS(全伝票!P:P,全伝票!$A:$A,$A12,全伝票!$B:$B,$B12),SUMIFS(全伝票!P:P,全伝票!$A:$A,$A12,全伝票!$C:$C,$C12))) -> 0 | N12: =+ROUND(F12*F$4/(100+F$4),0)+AE12 -> 0 | O12: =+ROUND(G12*G$4/(100+G$4),0)+AF12 -> 0 | P12: =+ROUND(H12*H$4/(100+H$4),0)+AG12 -> 0 | Q12: =+ROUND(I12*I$4/(100+I$4),0)+AH12 -> 0 | R12: =+ROUND(J12*J$4/(100+J$4),0)+AI12 -> 0 | S12: =SUM(N12:R12) -> 0 | T12: =+E12-S12 -> 0 | U12: =N12-F12*F$4/(100+F$4) -> 0 | V12: =O12-G12*G$4/(100+G$4) -> 0 | W12: =P12-H12*H$4/(100+H$4) -> 0 | X12: =Q12-I12*I$4/(100+I$4) -> 0 | Y12: =R12-J12*J$4/(100+J$4) -> 0 | Z12: =+IF(N$38=0,0,IF(N$38<0,-RANK(U12,U$5:U$35,0),RANK(U12,U$5:U$35,1))) -> 0 | AA12: =+IF(O$38=0,0,IF(O$38<0,-RANK(V12,V$5:V$35,0),RANK(V12,V$5:V$35,1))) -> 0 | AB12: =+IF(P$38=0,0,IF(P$38<0,-RANK(W12,W$5:W$35,0),RANK(W12,W$5:W$35,1))) -> 0 | AC12: =+IF(Q$38=0,0,IF(Q$38<0,-RANK(X12,X$5:X$35,0),RANK(X12,X$5:X$35,1))) -> 0 | AD12: =+IF(R$38=0,0,IF(R$38<0,-RANK(Y12,Y$5:Y$35,0),RANK(Y12,Y$5:Y$35,1))) -> 0
A13: 1 | B13: 8830210 | C13: 883021002 | D13: 特別旅費 | E13: =+IF($A13="",IF($C13="",SUMIFS(全伝票!I:I,全伝票!$B:$B,$B13),SUMIFS(全伝票!I:I,全伝票!$C:$C,$C13)),IF($C13="",SUMIFS(全伝票!I:I,全伝票!$A:$A,$A13,全伝票!$B:$B,$B13),SUMIFS(全伝票!I:I,全伝票!$A:$A,$A13,全伝票!$C:$C,$C13))) -> 0 | F13: =+IF($A13="",IF($C13="",SUMIFS(全伝票!J:J,全伝票!$B:$B,$B13),SUMIFS(全伝票!J:J,全伝票!$C:$C,$C13)),IF($C13="",SUMIFS(全伝票!J:J,全伝票!$A:$A,$A13,全伝票!$B:$B,$B13),SUMIFS(全伝票!J:J,全伝票!$A:$A,$A13,全伝票!$C:$C,$C13))) -> 0 | G13: =+IF($A13="",IF($C13="",SUMIFS(全伝票!K:K,全伝票!$B:$B,$B13),SUMIFS(全伝票!K:K,全伝票!$C:$C,$C13)),IF($C13="",SUMIFS(全伝票!K:K,全伝票!$A:$A,$A13,全伝票!$B:$B,$B13),SUMIFS(全伝票!K:K,全伝票!$A:$A,$A13,全伝票!$C:$C,$C13))) -> 0 | H13: =+IF($A13="",IF($C13="",SUMIFS(全伝票!L:L,全伝票!$B:$B,$B13),SUMIFS(全伝票!L:L,全伝票!$C:$C,$C13)),IF($C13="",SUMIFS(全伝票!L:L,全伝票!$A:$A,$A13,全伝票!$B:$B,$B13),SUMIFS(全伝票!L:L,全伝票!$A:$A,$A13,全伝票!$C:$C,$C13))) -> 0 | I13: =+IF($A13="",IF($C13="",SUMIFS(全伝票!M:M,全伝票!$B:$B,$B13),SUMIFS(全伝票!M:M,全伝票!$C:$C,$C13)),IF($C13="",SUMIFS(全伝票!M:M,全伝票!$A:$A,$A13,全伝票!$B:$B,$B13),SUMIFS(全伝票!M:M,全伝票!$A:$A,$A13,全伝票!$C:$C,$C13))) -> 0 | J13: =+IF($A13="",IF($C13="",SUMIFS(全伝票!N:N,全伝票!$B:$B,$B13),SUMIFS(全伝票!N:N,全伝票!$C:$C,$C13)),IF($C13="",SUMIFS(全伝票!N:N,全伝票!$A:$A,$A13,全伝票!$B:$B,$B13),SUMIFS(全伝票!N:N,全伝票!$A:$A,$A13,全伝票!$C:$C,$C13))) -> 0 | K13: =SUM(F13:J13) -> 0 | L13: =+IF($A13="",IF($C13="",SUMIFS(全伝票!O:O,全伝票!$B:$B,$B13),SUMIFS(全伝票!O:O,全伝票!$C:$C,$C13)),IF($C13="",SUMIFS(全伝票!O:O,全伝票!$A:$A,$A13,全伝票!$B:$B,$B13),SUMIFS(全伝票!O:O,全伝票!$A:$A,$A13,全伝票!$C:$C,$C13))) -> 0 | M13: =+IF($A13="",IF($C13="",SUMIFS(全伝票!P:P,全伝票!$B:$B,$B13),SUMIFS(全伝票!P:P,全伝票!$C:$C,$C13)),IF($C13="",SUMIFS(全伝票!P:P,全伝票!$A:$A,$A13,全伝票!$B:$B,$B13),SUMIFS(全伝票!P:P,全伝票!$A:$A,$A13,全伝票!$C:$C,$C13))) -> 0 | N13: =+ROUND(F13*F$4/(100+F$4),0)+AE13 -> 0 | O13: =+ROUND(G13*G$4/(100+G$4),0)+AF13 -> 0 | P13: =+ROUND(H13*H$4/(100+H$4),0)+AG13 -> 0 | Q13: =+ROUND(I13*I$4/(100+I$4),0)+AH13 -> 0 | R13: =+ROUND(J13*J$4/(100+J$4),0)+AI13 -> 0 | S13: =SUM(N13:R13) -> 0 | T13: =+E13-S13 -> 0 | U13: =N13-F13*F$4/(100+F$4) -> 0 | V13: =O13-G13*G$4/(100+G$4) -> 0 | W13: =P13-H13*H$4/(100+H$4) -> 0 | X13: =Q13-I13*I$4/(100+I$4) -> 0 | Y13: =R13-J13*J$4/(100+J$4) -> 0 | Z13: =+IF(N$38=0,0,IF(N$38<0,-RANK(U13,U$5:U$35,0),RANK(U13,U$5:U$35,1))) -> 0 | AA13: =+IF(O$38=0,0,IF(O$38<0,-RANK(V13,V$5:V$35,0),RANK(V13,V$5:V$35,1))) -> 0 | AB13: =+IF(P$38=0,0,IF(P$38<0,-RANK(W13,W$5:W$35,0),RANK(W13,W$5:W$35,1))) -> 0 | AC13: =+IF(Q$38=0,0,IF(Q$38<0,-RANK(X13,X$5:X$35,0),RANK(X13,X$5:X$35,1))) -> 0 | AD13: =+IF(R$38=0,0,IF(R$38<0,-RANK(Y13,Y$5:Y$35,0),RANK(Y13,Y$5:Y$35,1))) -> 0
A14: 1 | B14: 8830213 | D14: 備消品費 | E14: =+IF($A14="",IF($C14="",SUMIFS(全伝票!I:I,全伝票!$B:$B,$B14),SUMIFS(全伝票!I:I,全伝票!$C:$C,$C14)),IF($C14="",SUMIFS(全伝票!I:I,全伝票!$A:$A,$A14,全伝票!$B:$B,$B14),SUMIFS(全伝票!I:I,全伝票!$A:$A,$A14,全伝票!$C:$C,$C14))) -> 2612281 | F14: =+IF($A14="",IF($C14="",SUMIFS(全伝票!J:J,全伝票!$B:$B,$B14),SUMIFS(全伝票!J:J,全伝票!$C:$C,$C14)),IF($C14="",SUMIFS(全伝票!J:J,全伝票!$A:$A,$A14,全伝票!$B:$B,$B14),SUMIFS(全伝票!J:J,全伝票!$A:$A,$A14,全伝票!$C:$C,$C14))) -> 0 | G14: =+IF($A14="",IF($C14="",SUMIFS(全伝票!K:K,全伝票!$B:$B,$B14),SUMIFS(全伝票!K:K,全伝票!$C:$C,$C14)),IF($C14="",SUMIFS(全伝票!K:K,全伝票!$A:$A,$A14,全伝票!$B:$B,$B14),SUMIFS(全伝票!K:K,全伝票!$A:$A,$A14,全伝票!$C:$C,$C14))) -> 0 | H14: =+IF($A14="",IF($C14="",SUMIFS(全伝票!L:L,全伝票!$B:$B,$B14),SUMIFS(全伝票!L:L,全伝票!$C:$C,$C14)),IF($C14="",SUMIFS(全伝票!L:L,全伝票!$A:$A,$A14,全伝票!$B:$B,$B14),SUMIFS(全伝票!L:L,全伝票!$A:$A,$A14,全伝票!$C:$C,$C14))) -> 0 | I14: =+IF($A14="",IF($C14="",SUMIFS(全伝票!M:M,全伝票!$B:$B,$B14),SUMIFS(全伝票!M:M,全伝票!$C:$C,$C14)),IF($C14="",SUMIFS(全伝票!M:M,全伝票!$A:$A,$A14,全伝票!$B:$B,$B14),SUMIFS(全伝票!M:M,全伝票!$A:$A,$A14,全伝票!$C:$C,$C14))) -> 0 | J14: =+IF($A14="",IF($C14="",SUMIFS(全伝票!N:N,全伝票!$B:$B,$B14),SUMIFS(全伝票!N:N,全伝票!$C:$C,$C14)),IF($C14="",SUMIFS(全伝票!N:N,全伝票!$A:$A,$A14,全伝票!$B:$B,$B14),SUMIFS(全伝票!N:N,全伝票!$A:$A,$A14,全伝票!$C:$C,$C14))) -> 2612281 | K14: =SUM(F14:J14) -> 2612281 | L14: =+IF($A14="",IF($C14="",SUMIFS(全伝票!O:O,全伝票!$B:$B,$B14),SUMIFS(全伝票!O:O,全伝票!$C:$C,$C14)),IF($C14="",SUMIFS(全伝票!O:O,全伝票!$A:$A,$A14,全伝票!$B:$B,$B14),SUMIFS(全伝票!O:O,全伝票!$A:$A,$A14,全伝票!$C:$C,$C14))) -> 0 | M14: =+IF($A14="",IF($C14="",SUMIFS(全伝票!P:P,全伝票!$B:$B,$B14),SUMIFS(全伝票!P:P,全伝票!$C:$C,$C14)),IF($C14="",SUMIFS(全伝票!P:P,全伝票!$A:$A,$A14,全伝票!$B:$B,$B14),SUMIFS(全伝票!P:P,全伝票!$A:$A,$A14,全伝票!$C:$C,$C14))) -> 0 | N14: =+ROUND(F14*F$4/(100+F$4),0)+AE14 -> 0 | O14: =+ROUND(G14*G$4/(100+G$4),0)+AF14 -> 0 | P14: =+ROUND(H14*H$4/(100+H$4),0)+AG14 -> 0 | Q14: =+ROUND(I14*I$4/(100+I$4),0)+AH14 -> 0 | R14: =+ROUND(J14*J$4/(100+J$4),0)+AI14 -> 237480 | S14: =SUM(N14:R14) -> 237480 | T14: =+E14-S14 -> 2374801 | U14: =N14-F14*F$4/(100+F$4) -> 0 | V14: =O14-G14*G$4/(100+G$4) -> 0 | W14: =P14-H14*H$4/(100+H$4) -> 0 | X14: =Q14-I14*I$4/(100+I$4) -> 0 | Y14: =R14-J14*J$4/(100+J$4) -> -0.090909091 | Z14: =+IF(N$38=0,0,IF(N$38<0,-RANK(U14,U$5:U$35,0),RANK(U14,U$5:U$35,1))) -> 0 | AA14: =+IF(O$38=0,0,IF(O$38<0,-RANK(V14,V$5:V$35,0),RANK(V14,V$5:V$35,1))) -> 0 | AB14: =+IF(P$38=0,0,IF(P$38<0,-RANK(W14,W$5:W$35,0),RANK(W14,W$5:W$35,1))) -> 0 | AC14: =+IF(Q$38=0,0,IF(Q$38<0,-RANK(X14,X$5:X$35,0),RANK(X14,X$5:X$35,1))) -> 0 | AD14: =+IF(R$38=0,0,IF(R$38<0,-RANK(Y14,Y$5:Y$35,0),RANK(Y14,Y$5:Y$35,1))) -> 0
A15: 1 | B15: 8830214 | D15: 燃料費 | E15: =+IF($A15="",IF($C15="",SUMIFS(全伝票!I:I,全伝票!$B:$B,$B15),SUMIFS(全伝票!I:I,全伝票!$C:$C,$C15)),IF($C15="",SUMIFS(全伝票!I:I,全伝票!$A:$A,$A15,全伝票!$B:$B,$B15),SUMIFS(全伝票!I:I,全伝票!$A:$A,$A15,全伝票!$C:$C,$C15))) -> 474482 | F15: =+IF($A15="",IF($C15="",SUMIFS(全伝票!J:J,全伝票!$B:$B,$B15),SUMIFS(全伝票!J:J,全伝票!$C:$C,$C15)),IF($C15="",SUMIFS(全伝票!J:J,全伝票!$A:$A,$A15,全伝票!$B:$B,$B15),SUMIFS(全伝票!J:J,全伝票!$A:$A,$A15,全伝票!$C:$C,$C15))) -> 0 | G15: =+IF($A15="",IF($C15="",SUMIFS(全伝票!K:K,全伝票!$B:$B,$B15),SUMIFS(全伝票!K:K,全伝票!$C:$C,$C15)),IF($C15="",SUMIFS(全伝票!K:K,全伝票!$A:$A,$A15,全伝票!$B:$B,$B15),SUMIFS(全伝票!K:K,全伝票!$A:$A,$A15,全伝票!$C:$C,$C15))) -> 0 | H15: =+IF($A15="",IF($C15="",SUMIFS(全伝票!L:L,全伝票!$B:$B,$B15),SUMIFS(全伝票!L:L,全伝票!$C:$C,$C15)),IF($C15="",SUMIFS(全伝票!L:L,全伝票!$A:$A,$A15,全伝票!$B:$B,$B15),SUMIFS(全伝票!L:L,全伝票!$A:$A,$A15,全伝票!$C:$C,$C15))) -> 0 | I15: =+IF($A15="",IF($C15="",SUMIFS(全伝票!M:M,全伝票!$B:$B,$B15),SUMIFS(全伝票!M:M,全伝票!$C:$C,$C15)),IF($C15="",SUMIFS(全伝票!M:M,全伝票!$A:$A,$A15,全伝票!$B:$B,$B15),SUMIFS(全伝票!M:M,全伝票!$A:$A,$A15,全伝票!$C:$C,$C15))) -> 0 | J15: =+IF($A15="",IF($C15="",SUMIFS(全伝票!N:N,全伝票!$B:$B,$B15),SUMIFS(全伝票!N:N,全伝票!$C:$C,$C15)),IF($C15="",SUMIFS(全伝票!N:N,全伝票!$A:$A,$A15,全伝票!$B:$B,$B15),SUMIFS(全伝票!N:N,全伝票!$A:$A,$A15,全伝票!$C:$C,$C15))) -> 474482 | K15: =SUM(F15:J15) -> 474482 | L15: =+IF($A15="",IF($C15="",SUMIFS(全伝票!O:O,全伝票!$B:$B,$B15),SUMIFS(全伝票!O:O,全伝票!$C:$C,$C15)),IF($C15="",SUMIFS(全伝票!O:O,全伝票!$A:$A,$A15,全伝票!$B:$B,$B15),SUMIFS(全伝票!O:O,全伝票!$A:$A,$A15,全伝票!$C:$C,$C15))) -> 0 | M15: =+IF($A15="",IF($C15="",SUMIFS(全伝票!P:P,全伝票!$B:$B,$B15),SUMIFS(全伝票!P:P,全伝票!$C:$C,$C15)),IF($C15="",SUMIFS(全伝票!P:P,全伝票!$A:$A,$A15,全伝票!$B:$B,$B15),SUMIFS(全伝票!P:P,全伝票!$A:$A,$A15,全伝票!$C:$C,$C15))) -> 0 | N15: =+ROUND(F15*F$4/(100+F$4),0)+AE15 -> 0 | O15: =+ROUND(G15*G$4/(100+G$4),0)+AF15 -> 0 | P15: =+ROUND(H15*H$4/(100+H$4),0)+AG15 -> 0 | Q15: =+ROUND(I15*I$4/(100+I$4),0)+AH15 -> 0 | R15: =+ROUND(J15*J$4/(100+J$4),0)+AI15 -> 43135 | S15: =SUM(N15:R15) -> 43135 | T15: =+E15-S15 -> 431347 | U15: =N15-F15*F$4/(100+F$4) -> 0 | V15: =O15-G15*G$4/(100+G$4) -> 0 | W15: =P15-H15*H$4/(100+H$4) -> 0 | X15: =Q15-I15*I$4/(100+I$4) -> 0 | Y15: =R15-J15*J$4/(100+J$4) -> 0.27272727 | Z15: =+IF(N$38=0,0,IF(N$38<0,-RANK(U15,U$5:U$35,0),RANK(U15,U$5:U$35,1))) -> 0 | AA15: =+IF(O$38=0,0,IF(O$38<0,-RANK(V15,V$5:V$35,0),RANK(V15,V$5:V$35,1))) -> 0 | AB15: =+IF(P$38=0,0,IF(P$38<0,-RANK(W15,W$5:W$35,0),RANK(W15,W$5:W$35,1))) -> 0 | AC15: =+IF(Q$38=0,0,IF(Q$38<0,-RANK(X15,X$5:X$35,0),RANK(X15,X$5:X$35,1))) -> 0 | AD15: =+IF(R$38=0,0,IF(R$38<0,-RANK(Y15,Y$5:Y$35,0),RANK(Y15,Y$5:Y$35,1))) -> 0
A16: 1 | B16: 8830215 | D16: 光熱水費 | E16: =+IF($A16="",IF($C16="",SUMIFS(全伝票!I:I,全伝票!$B:$B,$B16),SUMIFS(全伝票!I:I,全伝票!$C:$C,$C16)),IF($C16="",SUMIFS(全伝票!I:I,全伝票!$A:$A,$A16,全伝票!$B:$B,$B16),SUMIFS(全伝票!I:I,全伝票!$A:$A,$A16,全伝票!$C:$C,$C16))) -> 0 | F16: =+IF($A16="",IF($C16="",SUMIFS(全伝票!J:J,全伝票!$B:$B,$B16),SUMIFS(全伝票!J:J,全伝票!$C:$C,$C16)),IF($C16="",SUMIFS(全伝票!J:J,全伝票!$A:$A,$A16,全伝票!$B:$B,$B16),SUMIFS(全伝票!J:J,全伝票!$A:$A,$A16,全伝票!$C:$C,$C16))) -> 0 | G16: =+IF($A16="",IF($C16="",SUMIFS(全伝票!K:K,全伝票!$B:$B,$B16),SUMIFS(全伝票!K:K,全伝票!$C:$C,$C16)),IF($C16="",SUMIFS(全伝票!K:K,全伝票!$A:$A,$A16,全伝票!$B:$B,$B16),SUMIFS(全伝票!K:K,全伝票!$A:$A,$A16,全伝票!$C:$C,$C16))) -> 0 | H16: =+IF($A16="",IF($C16="",SUMIFS(全伝票!L:L,全伝票!$B:$B,$B16),SUMIFS(全伝票!L:L,全伝票!$C:$C,$C16)),IF($C16="",SUMIFS(全伝票!L:L,全伝票!$A:$A,$A16,全伝票!$B:$B,$B16),SUMIFS(全伝票!L:L,全伝票!$A:$A,$A16,全伝票!$C:$C,$C16))) -> 0 | I16: =+IF($A16="",IF($C16="",SUMIFS(全伝票!M:M,全伝票!$B:$B,$B16),SUMIFS(全伝票!M:M,全伝票!$C:$C,$C16)),IF($C16="",SUMIFS(全伝票!M:M,全伝票!$A:$A,$A16,全伝票!$B:$B,$B16),SUMIFS(全伝票!M:M,全伝票!$A:$A,$A16,全伝票!$C:$C,$C16))) -> 0 | J16: =+IF($A16="",IF($C16="",SUMIFS(全伝票!N:N,全伝票!$B:$B,$B16),SUMIFS(全伝票!N:N,全伝票!$C:$C,$C16)),IF($C16="",SUMIFS(全伝票!N:N,全伝票!$A:$A,$A16,全伝票!$B:$B,$B16),SUMIFS(全伝票!N:N,全伝票!$A:$A,$A16,全伝票!$C:$C,$C16))) -> 0 | K16: =SUM(F16:J16) -> 0 | L16: =+IF($A16="",IF($C16="",SUMIFS(全伝票!O:O,全伝票!$B:$B,$B16),SUMIFS(全伝票!O:O,全伝票!$C:$C,$C16)),IF($C16="",SUMIFS(全伝票!O:O,全伝票!$A:$A,$A16,全伝票!$B:$B,$B16),SUMIFS(全伝票!O:O,全伝票!$A:$A,$A16,全伝票!$C:$C,$C16))) -> 0 | M16: =+IF($A16="",IF($C16="",SUMIFS(全伝票!P:P,全伝票!$B:$B,$B16),SUMIFS(全伝票!P:P,全伝票!$C:$C,$C16)),IF($C16="",SUMIFS(全伝票!P:P,全伝票!$A:$A,$A16,全伝票!$B:$B,$B16),SUMIFS(全伝票!P:P,全伝票!$A:$A,$A16,全伝票!$C:$C,$C16))) -> 0 | N16: =+ROUND(F16*F$4/(100+F$4),0)+AE16 -> 0 | O16: =+ROUND(G16*G$4/(100+G$4),0)+AF16 -> 0 | P16: =+ROUND(H16*H$4/(100+H$4),0)+AG16 -> 0 | Q16: =+ROUND(I16*I$4/(100+I$4),0)+AH16 -> 0 | R16: =+ROUND(J16*J$4/(100+J$4),0)+AI16 -> 0 | S16: =SUM(N16:R16) -> 0 | T16: =+E16-S16 -> 0 | U16: =N16-F16*F$4/(100+F$4) -> 0 | V16: =O16-G16*G$4/(100+G$4) -> 0 | W16: =P16-H16*H$4/(100+H$4) -> 0 | X16: =Q16-I16*I$4/(100+I$4) -> 0 | Y16: =R16-J16*J$4/(100+J$4) -> 0 | Z16: =+IF(N$38=0,0,IF(N$38<0,-RANK(U16,U$5:U$35,0),RANK(U16,U$5:U$35,1))) -> 0 | AA16: =+IF(O$38=0,0,IF(O$38<0,-RANK(V16,V$5:V$35,0),RANK(V16,V$5:V$35,1))) -> 0 | AB16: =+IF(P$38=0,0,IF(P$38<0,-RANK(W16,W$5:W$35,0),RANK(W16,W$5:W$35,1))) -> 0 | AC16: =+IF(Q$38=0,0,IF(Q$38<0,-RANK(X16,X$5:X$35,0),RANK(X16,X$5:X$35,1))) -> 0 | AD16: =+IF(R$38=0,0,IF(R$38<0,-RANK(Y16,Y$5:Y$35,0),RANK(Y16,Y$5:Y$35,1))) -> 0
A17: 1 | B17: 8830217 | D17: 通信運搬費 | E17: =+IF($A17="",IF($C17="",SUMIFS(全伝票!I:I,全伝票!$B:$B,$B17),SUMIFS(全伝票!I:I,全伝票!$C:$C,$C17)),IF($C17="",SUMIFS(全伝票!I:I,全伝票!$A:$A,$A17,全伝票!$B:$B,$B17),SUMIFS(全伝票!I:I,全伝票!$A:$A,$A17,全伝票!$C:$C,$C17))) -> 650162 | F17: =+IF($A17="",IF($C17="",SUMIFS(全伝票!J:J,全伝票!$B:$B,$B17),SUMIFS(全伝票!J:J,全伝票!$C:$C,$C17)),IF($C17="",SUMIFS(全伝票!J:J,全伝票!$A:$A,$A17,全伝票!$B:$B,$B17),SUMIFS(全伝票!J:J,全伝票!$A:$A,$A17,全伝票!$C:$C,$C17))) -> 0 | G17: =+IF($A17="",IF($C17="",SUMIFS(全伝票!K:K,全伝票!$B:$B,$B17),SUMIFS(全伝票!K:K,全伝票!$C:$C,$C17)),IF($C17="",SUMIFS(全伝票!K:K,全伝票!$A:$A,$A17,全伝票!$B:$B,$B17),SUMIFS(全伝票!K:K,全伝票!$A:$A,$A17,全伝票!$C:$C,$C17))) -> 0 | H17: =+IF($A17="",IF($C17="",SUMIFS(全伝票!L:L,全伝票!$B:$B,$B17),SUMIFS(全伝票!L:L,全伝票!$C:$C,$C17)),IF($C17="",SUMIFS(全伝票!L:L,全伝票!$A:$A,$A17,全伝票!$B:$B,$B17),SUMIFS(全伝票!L:L,全伝票!$A:$A,$A17,全伝票!$C:$C,$C17))) -> 0 | I17: =+IF($A17="",IF($C17="",SUMIFS(全伝票!M:M,全伝票!$B:$B,$B17),SUMIFS(全伝票!M:M,全伝票!$C:$C,$C17)),IF($C17="",SUMIFS(全伝票!M:M,全伝票!$A:$A,$A17,全伝票!$B:$B,$B17),SUMIFS(全伝票!M:M,全伝票!$A:$A,$A17,全伝票!$C:$C,$C17))) -> 0 | J17: =+IF($A17="",IF($C17="",SUMIFS(全伝票!N:N,全伝票!$B:$B,$B17),SUMIFS(全伝票!N:N,全伝票!$C:$C,$C17)),IF($C17="",SUMIFS(全伝票!N:N,全伝票!$A:$A,$A17,全伝票!$B:$B,$B17),SUMIFS(全伝票!N:N,全伝票!$A:$A,$A17,全伝票!$C:$C,$C17))) -> 650162 | K17: =SUM(F17:J17) -> 650162 | L17: =+IF($A17="",IF($C17="",SUMIFS(全伝票!O:O,全伝票!$B:$B,$B17),SUMIFS(全伝票!O:O,全伝票!$C:$C,$C17)),IF($C17="",SUMIFS(全伝票!O:O,全伝票!$A:$A,$A17,全伝票!$B:$B,$B17),SUMIFS(全伝票!O:O,全伝票!$A:$A,$A17,全伝票!$C:$C,$C17))) -> 0 | M17: =+IF($A17="",IF($C17="",SUMIFS(全伝票!P:P,全伝票!$B:$B,$B17),SUMIFS(全伝票!P:P,全伝票!$C:$C,$C17)),IF($C17="",SUMIFS(全伝票!P:P,全伝票!$A:$A,$A17,全伝票!$B:$B,$B17),SUMIFS(全伝票!P:P,全伝票!$A:$A,$A17,全伝票!$C:$C,$C17))) -> 0 | N17: =+ROUND(F17*F$4/(100+F$4),0)+AE17 -> 0 | O17: =+ROUND(G17*G$4/(100+G$4),0)+AF17 -> 0 | P17: =+ROUND(H17*H$4/(100+H$4),0)+AG17 -> 0 | Q17: =+ROUND(I17*I$4/(100+I$4),0)+AH17 -> 0 | R17: =+ROUND(J17*J$4/(100+J$4),0)+AI17 -> 59106 | S17: =SUM(N17:R17) -> 59106 | T17: =+E17-S17 -> 591056 | U17: =N17-F17*F$4/(100+F$4) -> 0 | V17: =O17-G17*G$4/(100+G$4) -> 0 | W17: =P17-H17*H$4/(100+H$4) -> 0 | X17: =Q17-I17*I$4/(100+I$4) -> 0 | Y17: =R17-J17*J$4/(100+J$4) -> 0.36363636 | Z17: =+IF(N$38=0,0,IF(N$38<0,-RANK(U17,U$5:U$35,0),RANK(U17,U$5:U$35,1))) -> 0 | AA17: =+IF(O$38=0,0,IF(O$38<0,-RANK(V17,V$5:V$35,0),RANK(V17,V$5:V$35,1))) -> 0 | AB17: =+IF(P$38=0,0,IF(P$38<0,-RANK(W17,W$5:W$35,0),RANK(W17,W$5:W$35,1))) -> 0 | AC17: =+IF(Q$38=0,0,IF(Q$38<0,-RANK(X17,X$5:X$35,0),RANK(X17,X$5:X$35,1))) -> 0 | AD17: =+IF(R$38=0,0,IF(R$38<0,-RANK(Y17,Y$5:Y$35,0),RANK(Y17,Y$5:Y$35,1))) -> 0
A18: 1 | B18: 8830219 | D18: 手数料 | E18: =+IF($A18="",IF($C18="",SUMIFS(全伝票!I:I,全伝票!$B:$B,$B18),SUMIFS(全伝票!I:I,全伝票!$C:$C,$C18)),IF($C18="",SUMIFS(全伝票!I:I,全伝票!$A:$A,$A18,全伝票!$B:$B,$B18),SUMIFS(全伝票!I:I,全伝票!$A:$A,$A18,全伝票!$C:$C,$C18))) -> 19480 | F18: =+IF($A18="",IF($C18="",SUMIFS(全伝票!J:J,全伝票!$B:$B,$B18),SUMIFS(全伝票!J:J,全伝票!$C:$C,$C18)),IF($C18="",SUMIFS(全伝票!J:J,全伝票!$A:$A,$A18,全伝票!$B:$B,$B18),SUMIFS(全伝票!J:J,全伝票!$A:$A,$A18,全伝票!$C:$C,$C18))) -> 0 | G18: =+IF($A18="",IF($C18="",SUMIFS(全伝票!K:K,全伝票!$B:$B,$B18),SUMIFS(全伝票!K:K,全伝票!$C:$C,$C18)),IF($C18="",SUMIFS(全伝票!K:K,全伝票!$A:$A,$A18,全伝票!$B:$B,$B18),SUMIFS(全伝票!K:K,全伝票!$A:$A,$A18,全伝票!$C:$C,$C18))) -> 0 | H18: =+IF($A18="",IF($C18="",SUMIFS(全伝票!L:L,全伝票!$B:$B,$B18),SUMIFS(全伝票!L:L,全伝票!$C:$C,$C18)),IF($C18="",SUMIFS(全伝票!L:L,全伝票!$A:$A,$A18,全伝票!$B:$B,$B18),SUMIFS(全伝票!L:L,全伝票!$A:$A,$A18,全伝票!$C:$C,$C18))) -> 0 | I18: =+IF($A18="",IF($C18="",SUMIFS(全伝票!M:M,全伝票!$B:$B,$B18),SUMIFS(全伝票!M:M,全伝票!$C:$C,$C18)),IF($C18="",SUMIFS(全伝票!M:M,全伝票!$A:$A,$A18,全伝票!$B:$B,$B18),SUMIFS(全伝票!M:M,全伝票!$A:$A,$A18,全伝票!$C:$C,$C18))) -> 0 | J18: =+IF($A18="",IF($C18="",SUMIFS(全伝票!N:N,全伝票!$B:$B,$B18),SUMIFS(全伝票!N:N,全伝票!$C:$C,$C18)),IF($C18="",SUMIFS(全伝票!N:N,全伝票!$A:$A,$A18,全伝票!$B:$B,$B18),SUMIFS(全伝票!N:N,全伝票!$A:$A,$A18,全伝票!$C:$C,$C18))) -> 11880 | K18: =SUM(F18:J18) -> 11880 | L18: =+IF($A18="",IF($C18="",SUMIFS(全伝票!O:O,全伝票!$B:$B,$B18),SUMIFS(全伝票!O:O,全伝票!$C:$C,$C18)),IF($C18="",SUMIFS(全伝票!O:O,全伝票!$A:$A,$A18,全伝票!$B:$B,$B18),SUMIFS(全伝票!O:O,全伝票!$A:$A,$A18,全伝票!$C:$C,$C18))) -> 7600 | M18: =+IF($A18="",IF($C18="",SUMIFS(全伝票!P:P,全伝票!$B:$B,$B18),SUMIFS(全伝票!P:P,全伝票!$C:$C,$C18)),IF($C18="",SUMIFS(全伝票!P:P,全伝票!$A:$A,$A18,全伝票!$B:$B,$B18),SUMIFS(全伝票!P:P,全伝票!$A:$A,$A18,全伝票!$C:$C,$C18))) -> 0 | N18: =+ROUND(F18*F$4/(100+F$4),0)+AE18 -> 0 | O18: =+ROUND(G18*G$4/(100+G$4),0)+AF18 -> 0 | P18: =+ROUND(H18*H$4/(100+H$4),0)+AG18 -> 0 | Q18: =+ROUND(I18*I$4/(100+I$4),0)+AH18 -> 0 | R18: =+ROUND(J18*J$4/(100+J$4),0)+AI18 -> 1080 | S18: =SUM(N18:R18) -> 1080 | T18: =+E18-S18 -> 18400 | U18: =N18-F18*F$4/(100+F$4) -> 0 | V18: =O18-G18*G$4/(100+G$4) -> 0 | W18: =P18-H18*H$4/(100+H$4) -> 0 | X18: =Q18-I18*I$4/(100+I$4) -> 0 | Y18: =R18-J18*J$4/(100+J$4) -> 0 | Z18: =+IF(N$38=0,0,IF(N$38<0,-RANK(U18,U$5:U$35,0),RANK(U18,U$5:U$35,1))) -> 0 | AA18: =+IF(O$38=0,0,IF(O$38<0,-RANK(V18,V$5:V$35,0),RANK(V18,V$5:V$35,1))) -> 0 | AB18: =+IF(P$38=0,0,IF(P$38<0,-RANK(W18,W$5:W$35,0),RANK(W18,W$5:W$35,1))) -> 0 | AC18: =+IF(Q$38=0,0,IF(Q$38<0,-RANK(X18,X$5:X$35,0),RANK(X18,X$5:X$35,1))) -> 0 | AD18: =+IF(R$38=0,0,IF(R$38<0,-RANK(Y18,Y$5:Y$35,0),RANK(Y18,Y$5:Y$35,1))) -> 0
A19: 1 | B19: 8830220 | D19: 賃借料 | E19: =+IF($A19="",IF($C19="",SUMIFS(全伝票!I:I,全伝票!$B:$B,$B19),SUMIFS(全伝票!I:I,全伝票!$C:$C,$C19)),IF($C19="",SUMIFS(全伝票!I:I,全伝票!$A:$A,$A19,全伝票!$B:$B,$B19),SUMIFS(全伝票!I:I,全伝票!$A:$A,$A19,全伝票!$C:$C,$C19))) -> 6446706 | F19: =+IF($A19="",IF($C19="",SUMIFS(全伝票!J:J,全伝票!$B:$B,$B19),SUMIFS(全伝票!J:J,全伝票!$C:$C,$C19)),IF($C19="",SUMIFS(全伝票!J:J,全伝票!$A:$A,$A19,全伝票!$B:$B,$B19),SUMIFS(全伝票!J:J,全伝票!$A:$A,$A19,全伝票!$C:$C,$C19))) -> 0 | G19: =+IF($A19="",IF($C19="",SUMIFS(全伝票!K:K,全伝票!$B:$B,$B19),SUMIFS(全伝票!K:K,全伝票!$C:$C,$C19)),IF($C19="",SUMIFS(全伝票!K:K,全伝票!$A:$A,$A19,全伝票!$B:$B,$B19),SUMIFS(全伝票!K:K,全伝票!$A:$A,$A19,全伝票!$C:$C,$C19))) -> 0 | H19: =+IF($A19="",IF($C19="",SUMIFS(全伝票!L:L,全伝票!$B:$B,$B19),SUMIFS(全伝票!L:L,全伝票!$C:$C,$C19)),IF($C19="",SUMIFS(全伝票!L:L,全伝票!$A:$A,$A19,全伝票!$B:$B,$B19),SUMIFS(全伝票!L:L,全伝票!$A:$A,$A19,全伝票!$C:$C,$C19))) -> 678402 | I19: =+IF($A19="",IF($C19="",SUMIFS(全伝票!M:M,全伝票!$B:$B,$B19),SUMIFS(全伝票!M:M,全伝票!$C:$C,$C19)),IF($C19="",SUMIFS(全伝票!M:M,全伝票!$A:$A,$A19,全伝票!$B:$B,$B19),SUMIFS(全伝票!M:M,全伝票!$A:$A,$A19,全伝票!$C:$C,$C19))) -> 0 | J19: =+IF($A19="",IF($C19="",SUMIFS(全伝票!N:N,全伝票!$B:$B,$B19),SUMIFS(全伝票!N:N,全伝票!$C:$C,$C19)),IF($C19="",SUMIFS(全伝票!N:N,全伝票!$A:$A,$A19,全伝票!$B:$B,$B19),SUMIFS(全伝票!N:N,全伝票!$A:$A,$A19,全伝票!$C:$C,$C19))) -> 114697 | K19: =SUM(F19:J19) -> 793099 | L19: =+IF($A19="",IF($C19="",SUMIFS(全伝票!O:O,全伝票!$B:$B,$B19),SUMIFS(全伝票!O:O,全伝票!$C:$C,$C19)),IF($C19="",SUMIFS(全伝票!O:O,全伝票!$A:$A,$A19,全伝票!$B:$B,$B19),SUMIFS(全伝票!O:O,全伝票!$A:$A,$A19,全伝票!$C:$C,$C19))) -> 5653607 | M19: =+IF($A19="",IF($C19="",SUMIFS(全伝票!P:P,全伝票!$B:$B,$B19),SUMIFS(全伝票!P:P,全伝票!$C:$C,$C19)),IF($C19="",SUMIFS(全伝票!P:P,全伝票!$A:$A,$A19,全伝票!$B:$B,$B19),SUMIFS(全伝票!P:P,全伝票!$A:$A,$A19,全伝票!$C:$C,$C19))) -> 0 | N19: =+ROUND(F19*F$4/(100+F$4),0)+AE19 -> 0 | O19: =+ROUND(G19*G$4/(100+G$4),0)+AF19 -> 0 | P19: =+ROUND(H19*H$4/(100+H$4),0)+AG19 -> 50252 | Q19: =+ROUND(I19*I$4/(100+I$4),0)+AH19 -> 0 | R19: =+ROUND(J19*J$4/(100+J$4),0)+AI19 -> 10427 | S19: =SUM(N19:R19) -> 60679 | T19: =+E19-S19 -> 6386027 | U19: =N19-F19*F$4/(100+F$4) -> 0 | V19: =O19-G19*G$4/(100+G$4) -> 0 | W19: =P19-H19*H$4/(100+H$4) -> 0 | X19: =Q19-I19*I$4/(100+I$4) -> 0 | Y19: =R19-J19*J$4/(100+J$4) -> 0 | Z19: =+IF(N$38=0,0,IF(N$38<0,-RANK(U19,U$5:U$35,0),RANK(U19,U$5:U$35,1))) -> 0 | AA19: =+IF(O$38=0,0,IF(O$38<0,-RANK(V19,V$5:V$35,0),RANK(V19,V$5:V$35,1))) -> 0 | AB19: =+IF(P$38=0,0,IF(P$38<0,-RANK(W19,W$5:W$35,0),RANK(W19,W$5:W$35,1))) -> 0 | AC19: =+IF(Q$38=0,0,IF(Q$38<0,-RANK(X19,X$5:X$35,0),RANK(X19,X$5:X$35,1))) -> 0 | AD19: =+IF(R$38=0,0,IF(R$38<0,-RANK(Y19,Y$5:Y$35,0),RANK(Y19,Y$5:Y$35,1))) -> 0
A20: 1 | B20: 8830221 | D20: 委託料 | E20: =+IF($A20="",IF($C20="",SUMIFS(全伝票!I:I,全伝票!$B:$B,$B20),SUMIFS(全伝票!I:I,全伝票!$C:$C,$C20)),IF($C20="",SUMIFS(全伝票!I:I,全伝票!$A:$A,$A20,全伝票!$B:$B,$B20),SUMIFS(全伝票!I:I,全伝票!$A:$A,$A20,全伝票!$C:$C,$C20))) -> 163512706 | F20: =+IF($A20="",IF($C20="",SUMIFS(全伝票!J:J,全伝票!$B:$B,$B20),SUMIFS(全伝票!J:J,全伝票!$C:$C,$C20)),IF($C20="",SUMIFS(全伝票!J:J,全伝票!$A:$A,$A20,全伝票!$B:$B,$B20),SUMIFS(全伝票!J:J,全伝票!$A:$A,$A20,全伝票!$C:$C,$C20))) -> 0 | G20: =+IF($A20="",IF($C20="",SUMIFS(全伝票!K:K,全伝票!$B:$B,$B20),SUMIFS(全伝票!K:K,全伝票!$C:$C,$C20)),IF($C20="",SUMIFS(全伝票!K:K,全伝票!$A:$A,$A20,全伝票!$B:$B,$B20),SUMIFS(全伝票!K:K,全伝票!$A:$A,$A20,全伝票!$C:$C,$C20))) -> 0 | H20: =+IF($A20="",IF($C20="",SUMIFS(全伝票!L:L,全伝票!$B:$B,$B20),SUMIFS(全伝票!L:L,全伝票!$C:$C,$C20)),IF($C20="",SUMIFS(全伝票!L:L,全伝票!$A:$A,$A20,全伝票!$B:$B,$B20),SUMIFS(全伝票!L:L,全伝票!$A:$A,$A20,全伝票!$C:$C,$C20))) -> 0 | I20: =+IF($A20="",IF($C20="",SUMIFS(全伝票!M:M,全伝票!$B:$B,$B20),SUMIFS(全伝票!M:M,全伝票!$C:$C,$C20)),IF($C20="",SUMIFS(全伝票!M:M,全伝票!$A:$A,$A20,全伝票!$B:$B,$B20),SUMIFS(全伝票!M:M,全伝票!$A:$A,$A20,全伝票!$C:$C,$C20))) -> 0 | J20: =+IF($A20="",IF($C20="",SUMIFS(全伝票!N:N,全伝票!$B:$B,$B20),SUMIFS(全伝票!N:N,全伝票!$C:$C,$C20)),IF($C20="",SUMIFS(全伝票!N:N,全伝票!$A:$A,$A20,全伝票!$B:$B,$B20),SUMIFS(全伝票!N:N,全伝票!$A:$A,$A20,全伝票!$C:$C,$C20))) -> 163512706 | K20: =SUM(F20:J20) -> 163512706 | L20: =+IF($A20="",IF($C20="",SUMIFS(全伝票!O:O,全伝票!$B:$B,$B20),SUMIFS(全伝票!O:O,全伝票!$C:$C,$C20)),IF($C20="",SUMIFS(全伝票!O:O,全伝票!$A:$A,$A20,全伝票!$B:$B,$B20),SUMIFS(全伝票!O:O,全伝票!$A:$A,$A20,全伝票!$C:$C,$C20))) -> 0 | M20: =+IF($A20="",IF($C20="",SUMIFS(全伝票!P:P,全伝票!$B:$B,$B20),SUMIFS(全伝票!P:P,全伝票!$C:$C,$C20)),IF($C20="",SUMIFS(全伝票!P:P,全伝票!$A:$A,$A20,全伝票!$B:$B,$B20),SUMIFS(全伝票!P:P,全伝票!$A:$A,$A20,全伝票!$C:$C,$C20))) -> 0 | N20: =+ROUND(F20*F$4/(100+F$4),0)+AE20 -> 0 | O20: =+ROUND(G20*G$4/(100+G$4),0)+AF20 -> 0 | P20: =+ROUND(H20*H$4/(100+H$4),0)+AG20 -> 0 | Q20: =+ROUND(I20*I$4/(100+I$4),0)+AH20 -> 0 | R20: =+ROUND(J20*J$4/(100+J$4),0)+AI20 -> 14864791 | S20: =SUM(N20:R20) -> 14864791 | T20: =+E20-S20 -> 148647915 | U20: =N20-F20*F$4/(100+F$4) -> 0 | V20: =O20-G20*G$4/(100+G$4) -> 0 | W20: =P20-H20*H$4/(100+H$4) -> 0 | X20: =Q20-I20*I$4/(100+I$4) -> 0 | Y20: =R20-J20*J$4/(100+J$4) -> -0.45454546 | Z20: =+IF(N$38=0,0,IF(N$38<0,-RANK(U20,U$5:U$35,0),RANK(U20,U$5:U$35,1))) -> 0 | AA20: =+IF(O$38=0,0,IF(O$38<0,-RANK(V20,V$5:V$35,0),RANK(V20,V$5:V$35,1))) -> 0 | AB20: =+IF(P$38=0,0,IF(P$38<0,-RANK(W20,W$5:W$35,0),RANK(W20,W$5:W$35,1))) -> 0 | AC20: =+IF(Q$38=0,0,IF(Q$38<0,-RANK(X20,X$5:X$35,0),RANK(X20,X$5:X$35,1))) -> 0 | AD20: =+IF(R$38=0,0,IF(R$38<0,-RANK(Y20,Y$5:Y$35,0),RANK(Y20,Y$5:Y$35,1))) -> 0
A21: 1 | B21: 8830223 | D21: 修繕費 | E21: =+IF($A21="",IF($C21="",SUMIFS(全伝票!I:I,全伝票!$B:$B,$B21),SUMIFS(全伝票!I:I,全伝票!$C:$C,$C21)),IF($C21="",SUMIFS(全伝票!I:I,全伝票!$A:$A,$A21,全伝票!$B:$B,$B21),SUMIFS(全伝票!I:I,全伝票!$A:$A,$A21,全伝票!$C:$C,$C21))) -> 12499689 | F21: =+IF($A21="",IF($C21="",SUMIFS(全伝票!J:J,全伝票!$B:$B,$B21),SUMIFS(全伝票!J:J,全伝票!$C:$C,$C21)),IF($C21="",SUMIFS(全伝票!J:J,全伝票!$A:$A,$A21,全伝票!$B:$B,$B21),SUMIFS(全伝票!J:J,全伝票!$A:$A,$A21,全伝票!$C:$C,$C21))) -> 0 | G21: =+IF($A21="",IF($C21="",SUMIFS(全伝票!K:K,全伝票!$B:$B,$B21),SUMIFS(全伝票!K:K,全伝票!$C:$C,$C21)),IF($C21="",SUMIFS(全伝票!K:K,全伝票!$A:$A,$A21,全伝票!$B:$B,$B21),SUMIFS(全伝票!K:K,全伝票!$A:$A,$A21,全伝票!$C:$C,$C21))) -> 0 | H21: =+IF($A21="",IF($C21="",SUMIFS(全伝票!L:L,全伝票!$B:$B,$B21),SUMIFS(全伝票!L:L,全伝票!$C:$C,$C21)),IF($C21="",SUMIFS(全伝票!L:L,全伝票!$A:$A,$A21,全伝票!$B:$B,$B21),SUMIFS(全伝票!L:L,全伝票!$A:$A,$A21,全伝票!$C:$C,$C21))) -> 0 | I21: =+IF($A21="",IF($C21="",SUMIFS(全伝票!M:M,全伝票!$B:$B,$B21),SUMIFS(全伝票!M:M,全伝票!$C:$C,$C21)),IF($C21="",SUMIFS(全伝票!M:M,全伝票!$A:$A,$A21,全伝票!$B:$B,$B21),SUMIFS(全伝票!M:M,全伝票!$A:$A,$A21,全伝票!$C:$C,$C21))) -> 0 | J21: =+IF($A21="",IF($C21="",SUMIFS(全伝票!N:N,全伝票!$B:$B,$B21),SUMIFS(全伝票!N:N,全伝票!$C:$C,$C21)),IF($C21="",SUMIFS(全伝票!N:N,全伝票!$A:$A,$A21,全伝票!$B:$B,$B21),SUMIFS(全伝票!N:N,全伝票!$A:$A,$A21,全伝票!$C:$C,$C21))) -> 12499689 | K21: =SUM(F21:J21) -> 12499689 | L21: =+IF($A21="",IF($C21="",SUMIFS(全伝票!O:O,全伝票!$B:$B,$B21),SUMIFS(全伝票!O:O,全伝票!$C:$C,$C21)),IF($C21="",SUMIFS(全伝票!O:O,全伝票!$A:$A,$A21,全伝票!$B:$B,$B21),SUMIFS(全伝票!O:O,全伝票!$A:$A,$A21,全伝票!$C:$C,$C21))) -> 0 | M21: =+IF($A21="",IF($C21="",SUMIFS(全伝票!P:P,全伝票!$B:$B,$B21),SUMIFS(全伝票!P:P,全伝票!$C:$C,$C21)),IF($C21="",SUMIFS(全伝票!P:P,全伝票!$A:$A,$A21,全伝票!$B:$B,$B21),SUMIFS(全伝票!P:P,全伝票!$A:$A,$A21,全伝票!$C:$C,$C21))) -> 0 | N21: =+ROUND(F21*F$4/(100+F$4),0)+AE21 -> 0 | O21: =+ROUND(G21*G$4/(100+G$4),0)+AF21 -> 0 | P21: =+ROUND(H21*H$4/(100+H$4),0)+AG21 -> 0 | Q21: =+ROUND(I21*I$4/(100+I$4),0)+AH21 -> 0 | R21: =+ROUND(J21*J$4/(100+J$4),0)+AI21 -> 1136335 | S21: =SUM(N21:R21) -> 1136335 | T21: =+E21-S21 -> 11363354 | U21: =N21-F21*F$4/(100+F$4) -> 0 | V21: =O21-G21*G$4/(100+G$4) -> 0 | W21: =P21-H21*H$4/(100+H$4) -> 0 | X21: =Q21-I21*I$4/(100+I$4) -> 0 | Y21: =R21-J21*J$4/(100+J$4) -> -0.36363636 | Z21: =+IF(N$38=0,0,IF(N$38<0,-RANK(U21,U$5:U$35,0),RANK(U21,U$5:U$35,1))) -> 0 | AA21: =+IF(O$38=0,0,IF(O$38<0,-RANK(V21,V$5:V$35,0),RANK(V21,V$5:V$35,1))) -> 0 | AB21: =+IF(P$38=0,0,IF(P$38<0,-RANK(W21,W$5:W$35,0),RANK(W21,W$5:W$35,1))) -> 0 | AC21: =+IF(Q$38=0,0,IF(Q$38<0,-RANK(X21,X$5:X$35,0),RANK(X21,X$5:X$35,1))) -> 0 | AD21: =+IF(R$38=0,0,IF(R$38<0,-RANK(Y21,Y$5:Y$35,0),RANK(Y21,Y$5:Y$35,1))) -> 0
A22: 1 | B22: 8830224 | D22: 材料費 | E22: =+IF($A22="",IF($C22="",SUMIFS(全伝票!I:I,全伝票!$B:$B,$B22),SUMIFS(全伝票!I:I,全伝票!$C:$C,$C22)),IF($C22="",SUMIFS(全伝票!I:I,全伝票!$A:$A,$A22,全伝票!$B:$B,$B22),SUMIFS(全伝票!I:I,全伝票!$A:$A,$A22,全伝票!$C:$C,$C22))) -> 2121075 | F22: =+IF($A22="",IF($C22="",SUMIFS(全伝票!J:J,全伝票!$B:$B,$B22),SUMIFS(全伝票!J:J,全伝票!$C:$C,$C22)),IF($C22="",SUMIFS(全伝票!J:J,全伝票!$A:$A,$A22,全伝票!$B:$B,$B22),SUMIFS(全伝票!J:J,全伝票!$A:$A,$A22,全伝票!$C:$C,$C22))) -> 0 | G22: =+IF($A22="",IF($C22="",SUMIFS(全伝票!K:K,全伝票!$B:$B,$B22),SUMIFS(全伝票!K:K,全伝票!$C:$C,$C22)),IF($C22="",SUMIFS(全伝票!K:K,全伝票!$A:$A,$A22,全伝票!$B:$B,$B22),SUMIFS(全伝票!K:K,全伝票!$A:$A,$A22,全伝票!$C:$C,$C22))) -> 0 | H22: =+IF($A22="",IF($C22="",SUMIFS(全伝票!L:L,全伝票!$B:$B,$B22),SUMIFS(全伝票!L:L,全伝票!$C:$C,$C22)),IF($C22="",SUMIFS(全伝票!L:L,全伝票!$A:$A,$A22,全伝票!$B:$B,$B22),SUMIFS(全伝票!L:L,全伝票!$A:$A,$A22,全伝票!$C:$C,$C22))) -> 0 | I22: =+IF($A22="",IF($C22="",SUMIFS(全伝票!M:M,全伝票!$B:$B,$B22),SUMIFS(全伝票!M:M,全伝票!$C:$C,$C22)),IF($C22="",SUMIFS(全伝票!M:M,全伝票!$A:$A,$A22,全伝票!$B:$B,$B22),SUMIFS(全伝票!M:M,全伝票!$A:$A,$A22,全伝票!$C:$C,$C22))) -> 0 | J22: =+IF($A22="",IF($C22="",SUMIFS(全伝票!N:N,全伝票!$B:$B,$B22),SUMIFS(全伝票!N:N,全伝票!$C:$C,$C22)),IF($C22="",SUMIFS(全伝票!N:N,全伝票!$A:$A,$A22,全伝票!$B:$B,$B22),SUMIFS(全伝票!N:N,全伝票!$A:$A,$A22,全伝票!$C:$C,$C22))) -> 2121075 | K22: =SUM(F22:J22) -> 2121075 | L22: =+IF($A22="",IF($C22="",SUMIFS(全伝票!O:O,全伝票!$B:$B,$B22),SUMIFS(全伝票!O:O,全伝票!$C:$C,$C22)),IF($C22="",SUMIFS(全伝票!O:O,全伝票!$A:$A,$A22,全伝票!$B:$B,$B22),SUMIFS(全伝票!O:O,全伝票!$A:$A,$A22,全伝票!$C:$C,$C22))) -> 0 | M22: =+IF($A22="",IF($C22="",SUMIFS(全伝票!P:P,全伝票!$B:$B,$B22),SUMIFS(全伝票!P:P,全伝票!$C:$C,$C22)),IF($C22="",SUMIFS(全伝票!P:P,全伝票!$A:$A,$A22,全伝票!$B:$B,$B22),SUMIFS(全伝票!P:P,全伝票!$A:$A,$A22,全伝票!$C:$C,$C22))) -> 0 | N22: =+ROUND(F22*F$4/(100+F$4),0)+AE22 -> 0 | O22: =+ROUND(G22*G$4/(100+G$4),0)+AF22 -> 0 | P22: =+ROUND(H22*H$4/(100+H$4),0)+AG22 -> 0 | Q22: =+ROUND(I22*I$4/(100+I$4),0)+AH22 -> 0 | R22: =+ROUND(J22*J$4/(100+J$4),0)+AI22 -> 192825 | S22: =SUM(N22:R22) -> 192825 | T22: =+E22-S22 -> 1928250 | U22: =N22-F22*F$4/(100+F$4) -> 0 | V22: =O22-G22*G$4/(100+G$4) -> 0 | W22: =P22-H22*H$4/(100+H$4) -> 0 | X22: =Q22-I22*I$4/(100+I$4) -> 0 | Y22: =R22-J22*J$4/(100+J$4) -> 0 | Z22: =+IF(N$38=0,0,IF(N$38<0,-RANK(U22,U$5:U$35,0),RANK(U22,U$5:U$35,1))) -> 0 | AA22: =+IF(O$38=0,0,IF(O$38<0,-RANK(V22,V$5:V$35,0),RANK(V22,V$5:V$35,1))) -> 0 | AB22: =+IF(P$38=0,0,IF(P$38<0,-RANK(W22,W$5:W$35,0),RANK(W22,W$5:W$35,1))) -> 0 | AC22: =+IF(Q$38=0,0,IF(Q$38<0,-RANK(X22,X$5:X$35,0),RANK(X22,X$5:X$35,1))) -> 0 | AD22: =+IF(R$38=0,0,IF(R$38<0,-RANK(Y22,Y$5:Y$35,0),RANK(Y22,Y$5:Y$35,1))) -> 0
A23: 1 | B23: 8830225 | D23: 工事請負費 | E23: =+IF($A23="",IF($C23="",SUMIFS(全伝票!I:I,全伝票!$B:$B,$B23),SUMIFS(全伝票!I:I,全伝票!$C:$C,$C23)),IF($C23="",SUMIFS(全伝票!I:I,全伝票!$A:$A,$A23,全伝票!$B:$B,$B23),SUMIFS(全伝票!I:I,全伝票!$A:$A,$A23,全伝票!$C:$C,$C23))) -> 299926084 | F23: =+IF($A23="",IF($C23="",SUMIFS(全伝票!J:J,全伝票!$B:$B,$B23),SUMIFS(全伝票!J:J,全伝票!$C:$C,$C23)),IF($C23="",SUMIFS(全伝票!J:J,全伝票!$A:$A,$A23,全伝票!$B:$B,$B23),SUMIFS(全伝票!J:J,全伝票!$A:$A,$A23,全伝票!$C:$C,$C23))) -> 0 | G23: =+IF($A23="",IF($C23="",SUMIFS(全伝票!K:K,全伝票!$B:$B,$B23),SUMIFS(全伝票!K:K,全伝票!$C:$C,$C23)),IF($C23="",SUMIFS(全伝票!K:K,全伝票!$A:$A,$A23,全伝票!$B:$B,$B23),SUMIFS(全伝票!K:K,全伝票!$A:$A,$A23,全伝票!$C:$C,$C23))) -> 0 | H23: =+IF($A23="",IF($C23="",SUMIFS(全伝票!L:L,全伝票!$B:$B,$B23),SUMIFS(全伝票!L:L,全伝票!$C:$C,$C23)),IF($C23="",SUMIFS(全伝票!L:L,全伝票!$A:$A,$A23,全伝票!$B:$B,$B23),SUMIFS(全伝票!L:L,全伝票!$A:$A,$A23,全伝票!$C:$C,$C23))) -> 0 | I23: =+IF($A23="",IF($C23="",SUMIFS(全伝票!M:M,全伝票!$B:$B,$B23),SUMIFS(全伝票!M:M,全伝票!$C:$C,$C23)),IF($C23="",SUMIFS(全伝票!M:M,全伝票!$A:$A,$A23,全伝票!$B:$B,$B23),SUMIFS(全伝票!M:M,全伝票!$A:$A,$A23,全伝票!$C:$C,$C23))) -> 0 | J23: =+IF($A23="",IF($C23="",SUMIFS(全伝票!N:N,全伝票!$B:$B,$B23),SUMIFS(全伝票!N:N,全伝票!$C:$C,$C23)),IF($C23="",SUMIFS(全伝票!N:N,全伝票!$A:$A,$A23,全伝票!$B:$B,$B23),SUMIFS(全伝票!N:N,全伝票!$A:$A,$A23,全伝票!$C:$C,$C23))) -> 299926084 | K23: =SUM(F23:J23) -> 299926084 | L23: =+IF($A23="",IF($C23="",SUMIFS(全伝票!O:O,全伝票!$B:$B,$B23),SUMIFS(全伝票!O:O,全伝票!$C:$C,$C23)),IF($C23="",SUMIFS(全伝票!O:O,全伝票!$A:$A,$A23,全伝票!$B:$B,$B23),SUMIFS(全伝票!O:O,全伝票!$A:$A,$A23,全伝票!$C:$C,$C23))) -> 0 | M23: =+IF($A23="",IF($C23="",SUMIFS(全伝票!P:P,全伝票!$B:$B,$B23),SUMIFS(全伝票!P:P,全伝票!$C:$C,$C23)),IF($C23="",SUMIFS(全伝票!P:P,全伝票!$A:$A,$A23,全伝票!$B:$B,$B23),SUMIFS(全伝票!P:P,全伝票!$A:$A,$A23,全伝票!$C:$C,$C23))) -> 0 | N23: =+ROUND(F23*F$4/(100+F$4),0)+AE23 -> 0 | O23: =+ROUND(G23*G$4/(100+G$4),0)+AF23 -> 0 | P23: =+ROUND(H23*H$4/(100+H$4),0)+AG23 -> 0 | Q23: =+ROUND(I23*I$4/(100+I$4),0)+AH23 -> 0 | R23: =+ROUND(J23*J$4/(100+J$4),0)+AI23 -> 27266008 | S23: =SUM(N23:R23) -> 27266008 | T23: =+E23-S23 -> 272660076 | U23: =N23-F23*F$4/(100+F$4) -> 0 | V23: =O23-G23*G$4/(100+G$4) -> 0 | W23: =P23-H23*H$4/(100+H$4) -> 0 | X23: =Q23-I23*I$4/(100+I$4) -> 0 | Y23: =R23-J23*J$4/(100+J$4) -> 0.36363636 | Z23: =+IF(N$38=0,0,IF(N$38<0,-RANK(U23,U$5:U$35,0),RANK(U23,U$5:U$35,1))) -> 0 | AA23: =+IF(O$38=0,0,IF(O$38<0,-RANK(V23,V$5:V$35,0),RANK(V23,V$5:V$35,1))) -> 0 | AB23: =+IF(P$38=0,0,IF(P$38<0,-RANK(W23,W$5:W$35,0),RANK(W23,W$5:W$35,1))) -> 0 | AC23: =+IF(Q$38=0,0,IF(Q$38<0,-RANK(X23,X$5:X$35,0),RANK(X23,X$5:X$35,1))) -> 0 | AD23: =+IF(R$38=0,0,IF(R$38<0,-RANK(Y23,Y$5:Y$35,0),RANK(Y23,Y$5:Y$35,1))) -> 0
A24: 1 | B24: 8830226 | D24: 路面復旧費 | E24: =+IF($A24="",IF($C24="",SUMIFS(全伝票!I:I,全伝票!$B:$B,$B24),SUMIFS(全伝票!I:I,全伝票!$C:$C,$C24)),IF($C24="",SUMIFS(全伝票!I:I,全伝票!$A:$A,$A24,全伝票!$B:$B,$B24),SUMIFS(全伝票!I:I,全伝票!$A:$A,$A24,全伝票!$C:$C,$C24))) -> 3840 | F24: =+IF($A24="",IF($C24="",SUMIFS(全伝票!J:J,全伝票!$B:$B,$B24),SUMIFS(全伝票!J:J,全伝票!$C:$C,$C24)),IF($C24="",SUMIFS(全伝票!J:J,全伝票!$A:$A,$A24,全伝票!$B:$B,$B24),SUMIFS(全伝票!J:J,全伝票!$A:$A,$A24,全伝票!$C:$C,$C24))) -> 0 | G24: =+IF($A24="",IF($C24="",SUMIFS(全伝票!K:K,全伝票!$B:$B,$B24),SUMIFS(全伝票!K:K,全伝票!$C:$C,$C24)),IF($C24="",SUMIFS(全伝票!K:K,全伝票!$A:$A,$A24,全伝票!$B:$B,$B24),SUMIFS(全伝票!K:K,全伝票!$A:$A,$A24,全伝票!$C:$C,$C24))) -> 0 | H24: =+IF($A24="",IF($C24="",SUMIFS(全伝票!L:L,全伝票!$B:$B,$B24),SUMIFS(全伝票!L:L,全伝票!$C:$C,$C24)),IF($C24="",SUMIFS(全伝票!L:L,全伝票!$A:$A,$A24,全伝票!$B:$B,$B24),SUMIFS(全伝票!L:L,全伝票!$A:$A,$A24,全伝票!$C:$C,$C24))) -> 0 | I24: =+IF($A24="",IF($C24="",SUMIFS(全伝票!M:M,全伝票!$B:$B,$B24),SUMIFS(全伝票!M:M,全伝票!$C:$C,$C24)),IF($C24="",SUMIFS(全伝票!M:M,全伝票!$A:$A,$A24,全伝票!$B:$B,$B24),SUMIFS(全伝票!M:M,全伝票!$A:$A,$A24,全伝票!$C:$C,$C24))) -> 0 | J24: =+IF($A24="",IF($C24="",SUMIFS(全伝票!N:N,全伝票!$B:$B,$B24),SUMIFS(全伝票!N:N,全伝票!$C:$C,$C24)),IF($C24="",SUMIFS(全伝票!N:N,全伝票!$A:$A,$A24,全伝票!$B:$B,$B24),SUMIFS(全伝票!N:N,全伝票!$A:$A,$A24,全伝票!$C:$C,$C24))) -> 0 | K24: =SUM(F24:J24) -> 0 | L24: =+IF($A24="",IF($C24="",SUMIFS(全伝票!O:O,全伝票!$B:$B,$B24),SUMIFS(全伝票!O:O,全伝票!$C:$C,$C24)),IF($C24="",SUMIFS(全伝票!O:O,全伝票!$A:$A,$A24,全伝票!$B:$B,$B24),SUMIFS(全伝票!O:O,全伝票!$A:$A,$A24,全伝票!$C:$C,$C24))) -> 3840 | M24: =+IF($A24="",IF($C24="",SUMIFS(全伝票!P:P,全伝票!$B:$B,$B24),SUMIFS(全伝票!P:P,全伝票!$C:$C,$C24)),IF($C24="",SUMIFS(全伝票!P:P,全伝票!$A:$A,$A24,全伝票!$B:$B,$B24),SUMIFS(全伝票!P:P,全伝票!$A:$A,$A24,全伝票!$C:$C,$C24))) -> 0 | N24: =+ROUND(F24*F$4/(100+F$4),0)+AE24 -> 0 | O24: =+ROUND(G24*G$4/(100+G$4),0)+AF24 -> 0 | P24: =+ROUND(H24*H$4/(100+H$4),0)+AG24 -> 0 | Q24: =+ROUND(I24*I$4/(100+I$4),0)+AH24 -> 0 | R24: =+ROUND(J24*J$4/(100+J$4),0)+AI24 -> 0 | S24: =SUM(N24:R24) -> 0 | T24: =+E24-S24 -> 3840 | U24: =N24-F24*F$4/(100+F$4) -> 0 | V24: =O24-G24*G$4/(100+G$4) -> 0 | W24: =P24-H24*H$4/(100+H$4) -> 0 | X24: =Q24-I24*I$4/(100+I$4) -> 0 | Y24: =R24-J24*J$4/(100+J$4) -> 0 | Z24: =+IF(N$38=0,0,IF(N$38<0,-RANK(U24,U$5:U$35,0),RANK(U24,U$5:U$35,1))) -> 0 | AA24: =+IF(O$38=0,0,IF(O$38<0,-RANK(V24,V$5:V$35,0),RANK(V24,V$5:V$35,1))) -> 0 | AB24: =+IF(P$38=0,0,IF(P$38<0,-RANK(W24,W$5:W$35,0),RANK(W24,W$5:W$35,1))) -> 0 | AC24: =+IF(Q$38=0,0,IF(Q$38<0,-RANK(X24,X$5:X$35,0),RANK(X24,X$5:X$35,1))) -> 0 | AD24: =+IF(R$38=0,0,IF(R$38<0,-RANK(Y24,Y$5:Y$35,0),RANK(Y24,Y$5:Y$35,1))) -> 0
A25: 1 | B25: 8830228 | C25: 883022866 | D25: 電力費 | E25: =+IF($A25="",IF($C25="",SUMIFS(全伝票!I:I,全伝票!$B:$B,$B25),SUMIFS(全伝票!I:I,全伝票!$C:$C,$C25)),IF($C25="",SUMIFS(全伝票!I:I,全伝票!$A:$A,$A25,全伝票!$B:$B,$B25),SUMIFS(全伝票!I:I,全伝票!$A:$A,$A25,全伝票!$C:$C,$C25))) -> 1471468 | F25: =+IF($A25="",IF($C25="",SUMIFS(全伝票!J:J,全伝票!$B:$B,$B25),SUMIFS(全伝票!J:J,全伝票!$C:$C,$C25)),IF($C25="",SUMIFS(全伝票!J:J,全伝票!$A:$A,$A25,全伝票!$B:$B,$B25),SUMIFS(全伝票!J:J,全伝票!$A:$A,$A25,全伝票!$C:$C,$C25))) -> 0 | G25: =+IF($A25="",IF($C25="",SUMIFS(全伝票!K:K,全伝票!$B:$B,$B25),SUMIFS(全伝票!K:K,全伝票!$C:$C,$C25)),IF($C25="",SUMIFS(全伝票!K:K,全伝票!$A:$A,$A25,全伝票!$B:$B,$B25),SUMIFS(全伝票!K:K,全伝票!$A:$A,$A25,全伝票!$C:$C,$C25))) -> 0 | H25: =+IF($A25="",IF($C25="",SUMIFS(全伝票!L:L,全伝票!$B:$B,$B25),SUMIFS(全伝票!L:L,全伝票!$C:$C,$C25)),IF($C25="",SUMIFS(全伝票!L:L,全伝票!$A:$A,$A25,全伝票!$B:$B,$B25),SUMIFS(全伝票!L:L,全伝票!$A:$A,$A25,全伝票!$C:$C,$C25))) -> 0 | I25: =+IF($A25="",IF($C25="",SUMIFS(全伝票!M:M,全伝票!$B:$B,$B25),SUMIFS(全伝票!M:M,全伝票!$C:$C,$C25)),IF($C25="",SUMIFS(全伝票!M:M,全伝票!$A:$A,$A25,全伝票!$B:$B,$B25),SUMIFS(全伝票!M:M,全伝票!$A:$A,$A25,全伝票!$C:$C,$C25))) -> 0 | J25: =+IF($A25="",IF($C25="",SUMIFS(全伝票!N:N,全伝票!$B:$B,$B25),SUMIFS(全伝票!N:N,全伝票!$C:$C,$C25)),IF($C25="",SUMIFS(全伝票!N:N,全伝票!$A:$A,$A25,全伝票!$B:$B,$B25),SUMIFS(全伝票!N:N,全伝票!$A:$A,$A25,全伝票!$C:$C,$C25))) -> 1471468 | K25: =SUM(F25:J25) -> 1471468 | L25: =+IF($A25="",IF($C25="",SUMIFS(全伝票!O:O,全伝票!$B:$B,$B25),SUMIFS(全伝票!O:O,全伝票!$C:$C,$C25)),IF($C25="",SUMIFS(全伝票!O:O,全伝票!$A:$A,$A25,全伝票!$B:$B,$B25),SUMIFS(全伝票!O:O,全伝票!$A:$A,$A25,全伝票!$C:$C,$C25))) -> 0 | M25: =+IF($A25="",IF($C25="",SUMIFS(全伝票!P:P,全伝票!$B:$B,$B25),SUMIFS(全伝票!P:P,全伝票!$C:$C,$C25)),IF($C25="",SUMIFS(全伝票!P:P,全伝票!$A:$A,$A25,全伝票!$B:$B,$B25),SUMIFS(全伝票!P:P,全伝票!$A:$A,$A25,全伝票!$C:$C,$C25))) -> 0 | N25: =+ROUND(F25*F$4/(100+F$4),0)+AE25 -> 0 | O25: =+ROUND(G25*G$4/(100+G$4),0)+AF25 -> 0 | P25: =+ROUND(H25*H$4/(100+H$4),0)+AG25 -> 0 | Q25: =+ROUND(I25*I$4/(100+I$4),0)+AH25 -> 0 | R25: =+ROUND(J25*J$4/(100+J$4),0)+AI25 -> 133770 | S25: =SUM(N25:R25) -> 133770 | T25: =+E25-S25 -> 1337698 | U25: =N25-F25*F$4/(100+F$4) -> 0 | V25: =O25-G25*G$4/(100+G$4) -> 0 | W25: =P25-H25*H$4/(100+H$4) -> 0 | X25: =Q25-I25*I$4/(100+I$4) -> 0 | Y25: =R25-J25*J$4/(100+J$4) -> 0.18181818 | Z25: =+IF(N$38=0,0,IF(N$38<0,-RANK(U25,U$5:U$35,0),RANK(U25,U$5:U$35,1))) -> 0 | AA25: =+IF(O$38=0,0,IF(O$38<0,-RANK(V25,V$5:V$35,0),RANK(V25,V$5:V$35,1))) -> 0 | AB25: =+IF(P$38=0,0,IF(P$38<0,-RANK(W25,W$5:W$35,0),RANK(W25,W$5:W$35,1))) -> 0 | AC25: =+IF(Q$38=0,0,IF(Q$38<0,-RANK(X25,X$5:X$35,0),RANK(X25,X$5:X$35,1))) -> 0 | AD25: =+IF(R$38=0,0,IF(R$38<0,-RANK(Y25,Y$5:Y$35,0),RANK(Y25,Y$5:Y$35,1))) -> 0
A26: 1 | B26: 8830228 | C26: 883022867 | D26: 動力用燃料費 | E26: =+IF($A26="",IF($C26="",SUMIFS(全伝票!I:I,全伝票!$B:$B,$B26),SUMIFS(全伝票!I:I,全伝票!$C:$C,$C26)),IF($C26="",SUMIFS(全伝票!I:I,全伝票!$A:$A,$A26,全伝票!$B:$B,$B26),SUMIFS(全伝票!I:I,全伝票!$A:$A,$A26,全伝票!$C:$C,$C26))) -> 0 | F26: =+IF($A26="",IF($C26="",SUMIFS(全伝票!J:J,全伝票!$B:$B,$B26),SUMIFS(全伝票!J:J,全伝票!$C:$C,$C26)),IF($C26="",SUMIFS(全伝票!J:J,全伝票!$A:$A,$A26,全伝票!$B:$B,$B26),SUMIFS(全伝票!J:J,全伝票!$A:$A,$A26,全伝票!$C:$C,$C26))) -> 0 | G26: =+IF($A26="",IF($C26="",SUMIFS(全伝票!K:K,全伝票!$B:$B,$B26),SUMIFS(全伝票!K:K,全伝票!$C:$C,$C26)),IF($C26="",SUMIFS(全伝票!K:K,全伝票!$A:$A,$A26,全伝票!$B:$B,$B26),SUMIFS(全伝票!K:K,全伝票!$A:$A,$A26,全伝票!$C:$C,$C26))) -> 0 | H26: =+IF($A26="",IF($C26="",SUMIFS(全伝票!L:L,全伝票!$B:$B,$B26),SUMIFS(全伝票!L:L,全伝票!$C:$C,$C26)),IF($C26="",SUMIFS(全伝票!L:L,全伝票!$A:$A,$A26,全伝票!$B:$B,$B26),SUMIFS(全伝票!L:L,全伝票!$A:$A,$A26,全伝票!$C:$C,$C26))) -> 0 | I26: =+IF($A26="",IF($C26="",SUMIFS(全伝票!M:M,全伝票!$B:$B,$B26),SUMIFS(全伝票!M:M,全伝票!$C:$C,$C26)),IF($C26="",SUMIFS(全伝票!M:M,全伝票!$A:$A,$A26,全伝票!$B:$B,$B26),SUMIFS(全伝票!M:M,全伝票!$A:$A,$A26,全伝票!$C:$C,$C26))) -> 0 | J26: =+IF($A26="",IF($C26="",SUMIFS(全伝票!N:N,全伝票!$B:$B,$B26),SUMIFS(全伝票!N:N,全伝票!$C:$C,$C26)),IF($C26="",SUMIFS(全伝票!N:N,全伝票!$A:$A,$A26,全伝票!$B:$B,$B26),SUMIFS(全伝票!N:N,全伝票!$A:$A,$A26,全伝票!$C:$C,$C26))) -> 0 | K26: =SUM(F26:J26) -> 0 | L26: =+IF($A26="",IF($C26="",SUMIFS(全伝票!O:O,全伝票!$B:$B,$B26),SUMIFS(全伝票!O:O,全伝票!$C:$C,$C26)),IF($C26="",SUMIFS(全伝票!O:O,全伝票!$A:$A,$A26,全伝票!$B:$B,$B26),SUMIFS(全伝票!O:O,全伝票!$A:$A,$A26,全伝票!$C:$C,$C26))) -> 0 | M26: =+IF($A26="",IF($C26="",SUMIFS(全伝票!P:P,全伝票!$B:$B,$B26),SUMIFS(全伝票!P:P,全伝票!$C:$C,$C26)),IF($C26="",SUMIFS(全伝票!P:P,全伝票!$A:$A,$A26,全伝票!$B:$B,$B26),SUMIFS(全伝票!P:P,全伝票!$A:$A,$A26,全伝票!$C:$C,$C26))) -> 0 | N26: =+ROUND(F26*F$4/(100+F$4),0)+AE26 -> 0 | O26: =+ROUND(G26*G$4/(100+G$4),0)+AF26 -> 0 | P26: =+ROUND(H26*H$4/(100+H$4),0)+AG26 -> 0 | Q26: =+ROUND(I26*I$4/(100+I$4),0)+AH26 -> 0 | R26: =+ROUND(J26*J$4/(100+J$4),0)+AI26 -> 0 | S26: =SUM(N26:R26) -> 0 | T26: =+E26-S26 -> 0 | U26: =N26-F26*F$4/(100+F$4) -> 0 | V26: =O26-G26*G$4/(100+G$4) -> 0 | W26: =P26-H26*H$4/(100+H$4) -> 0 | X26: =Q26-I26*I$4/(100+I$4) -> 0 | Y26: =R26-J26*J$4/(100+J$4) -> 0 | Z26: =+IF(N$38=0,0,IF(N$38<0,-RANK(U26,U$5:U$35,0),RANK(U26,U$5:U$35,1))) -> 0 | AA26: =+IF(O$38=0,0,IF(O$38<0,-RANK(V26,V$5:V$35,0),RANK(V26,V$5:V$35,1))) -> 0 | AB26: =+IF(P$38=0,0,IF(P$38<0,-RANK(W26,W$5:W$35,0),RANK(W26,W$5:W$35,1))) -> 0 | AC26: =+IF(Q$38=0,0,IF(Q$38<0,-RANK(X26,X$5:X$35,0),RANK(X26,X$5:X$35,1))) -> 0 | AD26: =+IF(R$38=0,0,IF(R$38<0,-RANK(Y26,Y$5:Y$35,0),RANK(Y26,Y$5:Y$35,1))) -> 0
A27: 1 | B27: 8830229 | D27: 薬品費 | E27: =+IF($A27="",IF($C27="",SUMIFS(全伝票!I:I,全伝票!$B:$B,$B27),SUMIFS(全伝票!I:I,全伝票!$C:$C,$C27)),IF($C27="",SUMIFS(全伝票!I:I,全伝票!$A:$A,$A27,全伝票!$B:$B,$B27),SUMIFS(全伝票!I:I,全伝票!$A:$A,$A27,全伝票!$C:$C,$C27))) -> 0 | F27: =+IF($A27="",IF($C27="",SUMIFS(全伝票!J:J,全伝票!$B:$B,$B27),SUMIFS(全伝票!J:J,全伝票!$C:$C,$C27)),IF($C27="",SUMIFS(全伝票!J:J,全伝票!$A:$A,$A27,全伝票!$B:$B,$B27),SUMIFS(全伝票!J:J,全伝票!$A:$A,$A27,全伝票!$C:$C,$C27))) -> 0 | G27: =+IF($A27="",IF($C27="",SUMIFS(全伝票!K:K,全伝票!$B:$B,$B27),SUMIFS(全伝票!K:K,全伝票!$C:$C,$C27)),IF($C27="",SUMIFS(全伝票!K:K,全伝票!$A:$A,$A27,全伝票!$B:$B,$B27),SUMIFS(全伝票!K:K,全伝票!$A:$A,$A27,全伝票!$C:$C,$C27))) -> 0 | H27: =+IF($A27="",IF($C27="",SUMIFS(全伝票!L:L,全伝票!$B:$B,$B27),SUMIFS(全伝票!L:L,全伝票!$C:$C,$C27)),IF($C27="",SUMIFS(全伝票!L:L,全伝票!$A:$A,$A27,全伝票!$B:$B,$B27),SUMIFS(全伝票!L:L,全伝票!$A:$A,$A27,全伝票!$C:$C,$C27))) -> 0 | I27: =+IF($A27="",IF($C27="",SUMIFS(全伝票!M:M,全伝票!$B:$B,$B27),SUMIFS(全伝票!M:M,全伝票!$C:$C,$C27)),IF($C27="",SUMIFS(全伝票!M:M,全伝票!$A:$A,$A27,全伝票!$B:$B,$B27),SUMIFS(全伝票!M:M,全伝票!$A:$A,$A27,全伝票!$C:$C,$C27))) -> 0 | J27: =+IF($A27="",IF($C27="",SUMIFS(全伝票!N:N,全伝票!$B:$B,$B27),SUMIFS(全伝票!N:N,全伝票!$C:$C,$C27)),IF($C27="",SUMIFS(全伝票!N:N,全伝票!$A:$A,$A27,全伝票!$B:$B,$B27),SUMIFS(全伝票!N:N,全伝票!$A:$A,$A27,全伝票!$C:$C,$C27))) -> 0 | K27: =SUM(F27:J27) -> 0 | L27: =+IF($A27="",IF($C27="",SUMIFS(全伝票!O:O,全伝票!$B:$B,$B27),SUMIFS(全伝票!O:O,全伝票!$C:$C,$C27)),IF($C27="",SUMIFS(全伝票!O:O,全伝票!$A:$A,$A27,全伝票!$B:$B,$B27),SUMIFS(全伝票!O:O,全伝票!$A:$A,$A27,全伝票!$C:$C,$C27))) -> 0 | M27: =+IF($A27="",IF($C27="",SUMIFS(全伝票!P:P,全伝票!$B:$B,$B27),SUMIFS(全伝票!P:P,全伝票!$C:$C,$C27)),IF($C27="",SUMIFS(全伝票!P:P,全伝票!$A:$A,$A27,全伝票!$B:$B,$B27),SUMIFS(全伝票!P:P,全伝票!$A:$A,$A27,全伝票!$C:$C,$C27))) -> 0 | N27: =+ROUND(F27*F$4/(100+F$4),0)+AE27 -> 0 | O27: =+ROUND(G27*G$4/(100+G$4),0)+AF27 -> 0 | P27: =+ROUND(H27*H$4/(100+H$4),0)+AG27 -> 0 | Q27: =+ROUND(I27*I$4/(100+I$4),0)+AH27 -> 0 | R27: =+ROUND(J27*J$4/(100+J$4),0)+AI27 -> 0 | S27: =SUM(N27:R27) -> 0 | T27: =+E27-S27 -> 0 | U27: =N27-F27*F$4/(100+F$4) -> 0 | V27: =O27-G27*G$4/(100+G$4) -> 0 | W27: =P27-H27*H$4/(100+H$4) -> 0 | X27: =Q27-I27*I$4/(100+I$4) -> 0 | Y27: =R27-J27*J$4/(100+J$4) -> 0 | Z27: =+IF(N$38=0,0,IF(N$38<0,-RANK(U27,U$5:U$35,0),RANK(U27,U$5:U$35,1))) -> 0 | AA27: =+IF(O$38=0,0,IF(O$38<0,-RANK(V27,V$5:V$35,0),RANK(V27,V$5:V$35,1))) -> 0 | AB27: =+IF(P$38=0,0,IF(P$38<0,-RANK(W27,W$5:W$35,0),RANK(W27,W$5:W$35,1))) -> 0 | AC27: =+IF(Q$38=0,0,IF(Q$38<0,-RANK(X27,X$5:X$35,0),RANK(X27,X$5:X$35,1))) -> 0 | AD27: =+IF(R$38=0,0,IF(R$38<0,-RANK(Y27,Y$5:Y$35,0),RANK(Y27,Y$5:Y$35,1))) -> 0
A28: 1 | B28: 8830230 | D28: 補償金 | E28: =+IF($A28="",IF($C28="",SUMIFS(全伝票!I:I,全伝票!$B:$B,$B28),SUMIFS(全伝票!I:I,全伝票!$C:$C,$C28)),IF($C28="",SUMIFS(全伝票!I:I,全伝票!$A:$A,$A28,全伝票!$B:$B,$B28),SUMIFS(全伝票!I:I,全伝票!$A:$A,$A28,全伝票!$C:$C,$C28))) -> 693759 | F28: =+IF($A28="",IF($C28="",SUMIFS(全伝票!J:J,全伝票!$B:$B,$B28),SUMIFS(全伝票!J:J,全伝票!$C:$C,$C28)),IF($C28="",SUMIFS(全伝票!J:J,全伝票!$A:$A,$A28,全伝票!$B:$B,$B28),SUMIFS(全伝票!J:J,全伝票!$A:$A,$A28,全伝票!$C:$C,$C28))) -> 0 | G28: =+IF($A28="",IF($C28="",SUMIFS(全伝票!K:K,全伝票!$B:$B,$B28),SUMIFS(全伝票!K:K,全伝票!$C:$C,$C28)),IF($C28="",SUMIFS(全伝票!K:K,全伝票!$A:$A,$A28,全伝票!$B:$B,$B28),SUMIFS(全伝票!K:K,全伝票!$A:$A,$A28,全伝票!$C:$C,$C28))) -> 0 | H28: =+IF($A28="",IF($C28="",SUMIFS(全伝票!L:L,全伝票!$B:$B,$B28),SUMIFS(全伝票!L:L,全伝票!$C:$C,$C28)),IF($C28="",SUMIFS(全伝票!L:L,全伝票!$A:$A,$A28,全伝票!$B:$B,$B28),SUMIFS(全伝票!L:L,全伝票!$A:$A,$A28,全伝票!$C:$C,$C28))) -> 0 | I28: =+IF($A28="",IF($C28="",SUMIFS(全伝票!M:M,全伝票!$B:$B,$B28),SUMIFS(全伝票!M:M,全伝票!$C:$C,$C28)),IF($C28="",SUMIFS(全伝票!M:M,全伝票!$A:$A,$A28,全伝票!$B:$B,$B28),SUMIFS(全伝票!M:M,全伝票!$A:$A,$A28,全伝票!$C:$C,$C28))) -> 0 | J28: =+IF($A28="",IF($C28="",SUMIFS(全伝票!N:N,全伝票!$B:$B,$B28),SUMIFS(全伝票!N:N,全伝票!$C:$C,$C28)),IF($C28="",SUMIFS(全伝票!N:N,全伝票!$A:$A,$A28,全伝票!$B:$B,$B28),SUMIFS(全伝票!N:N,全伝票!$A:$A,$A28,全伝票!$C:$C,$C28))) -> 0 | K28: =SUM(F28:J28) -> 0 | L28: =+IF($A28="",IF($C28="",SUMIFS(全伝票!O:O,全伝票!$B:$B,$B28),SUMIFS(全伝票!O:O,全伝票!$C:$C,$C28)),IF($C28="",SUMIFS(全伝票!O:O,全伝票!$A:$A,$A28,全伝票!$B:$B,$B28),SUMIFS(全伝票!O:O,全伝票!$A:$A,$A28,全伝票!$C:$C,$C28))) -> 0 | M28: =+IF($A28="",IF($C28="",SUMIFS(全伝票!P:P,全伝票!$B:$B,$B28),SUMIFS(全伝票!P:P,全伝票!$C:$C,$C28)),IF($C28="",SUMIFS(全伝票!P:P,全伝票!$A:$A,$A28,全伝票!$B:$B,$B28),SUMIFS(全伝票!P:P,全伝票!$A:$A,$A28,全伝票!$C:$C,$C28))) -> 693759 | N28: =+ROUND(F28*F$4/(100+F$4),0)+AE28 -> 0 | O28: =+ROUND(G28*G$4/(100+G$4),0)+AF28 -> 0 | P28: =+ROUND(H28*H$4/(100+H$4),0)+AG28 -> 0 | Q28: =+ROUND(I28*I$4/(100+I$4),0)+AH28 -> 0 | R28: =+ROUND(J28*J$4/(100+J$4),0)+AI28 -> 0 | S28: =SUM(N28:R28) -> 0 | T28: =+E28-S28 -> 693759 | U28: =N28-F28*F$4/(100+F$4) -> 0 | V28: =O28-G28*G$4/(100+G$4) -> 0 | W28: =P28-H28*H$4/(100+H$4) -> 0 | X28: =Q28-I28*I$4/(100+I$4) -> 0 | Y28: =R28-J28*J$4/(100+J$4) -> 0 | Z28: =+IF(N$38=0,0,IF(N$38<0,-RANK(U28,U$5:U$35,0),RANK(U28,U$5:U$35,1))) -> 0 | AA28: =+IF(O$38=0,0,IF(O$38<0,-RANK(V28,V$5:V$35,0),RANK(V28,V$5:V$35,1))) -> 0 | AB28: =+IF(P$38=0,0,IF(P$38<0,-RANK(W28,W$5:W$35,0),RANK(W28,W$5:W$35,1))) -> 0 | AC28: =+IF(Q$38=0,0,IF(Q$38<0,-RANK(X28,X$5:X$35,0),RANK(X28,X$5:X$35,1))) -> 0 | AD28: =+IF(R$38=0,0,IF(R$38<0,-RANK(Y28,Y$5:Y$35,0),RANK(Y28,Y$5:Y$35,1))) -> 0
A29: 1 | B29: 8830231 | D29: 負担金、補助及び交付金 | E29: =+IF($A29="",IF($C29="",SUMIFS(全伝票!I:I,全伝票!$B:$B,$B29),SUMIFS(全伝票!I:I,全伝票!$C:$C,$C29)),IF($C29="",SUMIFS(全伝票!I:I,全伝票!$A:$A,$A29,全伝票!$B:$B,$B29),SUMIFS(全伝票!I:I,全伝票!$A:$A,$A29,全伝票!$C:$C,$C29))) -> 34481445 | F29: =+IF($A29="",IF($C29="",SUMIFS(全伝票!J:J,全伝票!$B:$B,$B29),SUMIFS(全伝票!J:J,全伝票!$C:$C,$C29)),IF($C29="",SUMIFS(全伝票!J:J,全伝票!$A:$A,$A29,全伝票!$B:$B,$B29),SUMIFS(全伝票!J:J,全伝票!$A:$A,$A29,全伝票!$C:$C,$C29))) -> 0 | G29: =+IF($A29="",IF($C29="",SUMIFS(全伝票!K:K,全伝票!$B:$B,$B29),SUMIFS(全伝票!K:K,全伝票!$C:$C,$C29)),IF($C29="",SUMIFS(全伝票!K:K,全伝票!$A:$A,$A29,全伝票!$B:$B,$B29),SUMIFS(全伝票!K:K,全伝票!$A:$A,$A29,全伝票!$C:$C,$C29))) -> 0 | H29: =+IF($A29="",IF($C29="",SUMIFS(全伝票!L:L,全伝票!$B:$B,$B29),SUMIFS(全伝票!L:L,全伝票!$C:$C,$C29)),IF($C29="",SUMIFS(全伝票!L:L,全伝票!$A:$A,$A29,全伝票!$B:$B,$B29),SUMIFS(全伝票!L:L,全伝票!$A:$A,$A29,全伝票!$C:$C,$C29))) -> 0 | I29: =+IF($A29="",IF($C29="",SUMIFS(全伝票!M:M,全伝票!$B:$B,$B29),SUMIFS(全伝票!M:M,全伝票!$C:$C,$C29)),IF($C29="",SUMIFS(全伝票!M:M,全伝票!$A:$A,$A29,全伝票!$B:$B,$B29),SUMIFS(全伝票!M:M,全伝票!$A:$A,$A29,全伝票!$C:$C,$C29))) -> 0 | J29: =+IF($A29="",IF($C29="",SUMIFS(全伝票!N:N,全伝票!$B:$B,$B29),SUMIFS(全伝票!N:N,全伝票!$C:$C,$C29)),IF($C29="",SUMIFS(全伝票!N:N,全伝票!$A:$A,$A29,全伝票!$B:$B,$B29),SUMIFS(全伝票!N:N,全伝票!$A:$A,$A29,全伝票!$C:$C,$C29))) -> 33599086 | K29: =SUM(F29:J29) -> 33599086 | L29: =+IF($A29="",IF($C29="",SUMIFS(全伝票!O:O,全伝票!$B:$B,$B29),SUMIFS(全伝票!O:O,全伝票!$C:$C,$C29)),IF($C29="",SUMIFS(全伝票!O:O,全伝票!$A:$A,$A29,全伝票!$B:$B,$B29),SUMIFS(全伝票!O:O,全伝票!$A:$A,$A29,全伝票!$C:$C,$C29))) -> 882359 | M29: =+IF($A29="",IF($C29="",SUMIFS(全伝票!P:P,全伝票!$B:$B,$B29),SUMIFS(全伝票!P:P,全伝票!$C:$C,$C29)),IF($C29="",SUMIFS(全伝票!P:P,全伝票!$A:$A,$A29,全伝票!$B:$B,$B29),SUMIFS(全伝票!P:P,全伝票!$A:$A,$A29,全伝票!$C:$C,$C29))) -> 0 | N29: =+ROUND(F29*F$4/(100+F$4),0)+AE29 -> 0 | O29: =+ROUND(G29*G$4/(100+G$4),0)+AF29 -> 0 | P29: =+ROUND(H29*H$4/(100+H$4),0)+AG29 -> 0 | Q29: =+ROUND(I29*I$4/(100+I$4),0)+AH29 -> 0 | R29: =+ROUND(J29*J$4/(100+J$4),0)+AI29 -> 3054462 | S29: =SUM(N29:R29) -> 3054462 | T29: =+E29-S29 -> 31426983 | U29: =N29-F29*F$4/(100+F$4) -> 0 | V29: =O29-G29*G$4/(100+G$4) -> 0 | W29: =P29-H29*H$4/(100+H$4) -> 0 | X29: =Q29-I29*I$4/(100+I$4) -> 0 | Y29: =R29-J29*J$4/(100+J$4) -> -0.36363636 | Z29: =+IF(N$38=0,0,IF(N$38<0,-RANK(U29,U$5:U$35,0),RANK(U29,U$5:U$35,1))) -> 0 | AA29: =+IF(O$38=0,0,IF(O$38<0,-RANK(V29,V$5:V$35,0),RANK(V29,V$5:V$35,1))) -> 0 | AB29: =+IF(P$38=0,0,IF(P$38<0,-RANK(W29,W$5:W$35,0),RANK(W29,W$5:W$35,1))) -> 0 | AC29: =+IF(Q$38=0,0,IF(Q$38<0,-RANK(X29,X$5:X$35,0),RANK(X29,X$5:X$35,1))) -> 0 | AD29: =+IF(R$38=0,0,IF(R$38<0,-RANK(Y29,Y$5:Y$35,0),RANK(Y29,Y$5:Y$35,1))) -> 0
A30: 1 | B30: 8830237 | D30: 食糧費 | E30: =+IF($A30="",IF($C30="",SUMIFS(全伝票!I:I,全伝票!$B:$B,$B30),SUMIFS(全伝票!I:I,全伝票!$C:$C,$C30)),IF($C30="",SUMIFS(全伝票!I:I,全伝票!$A:$A,$A30,全伝票!$B:$B,$B30),SUMIFS(全伝票!I:I,全伝票!$A:$A,$A30,全伝票!$C:$C,$C30))) -> 0 | F30: =+IF($A30="",IF($C30="",SUMIFS(全伝票!J:J,全伝票!$B:$B,$B30),SUMIFS(全伝票!J:J,全伝票!$C:$C,$C30)),IF($C30="",SUMIFS(全伝票!J:J,全伝票!$A:$A,$A30,全伝票!$B:$B,$B30),SUMIFS(全伝票!J:J,全伝票!$A:$A,$A30,全伝票!$C:$C,$C30))) -> 0 | G30: =+IF($A30="",IF($C30="",SUMIFS(全伝票!K:K,全伝票!$B:$B,$B30),SUMIFS(全伝票!K:K,全伝票!$C:$C,$C30)),IF($C30="",SUMIFS(全伝票!K:K,全伝票!$A:$A,$A30,全伝票!$B:$B,$B30),SUMIFS(全伝票!K:K,全伝票!$A:$A,$A30,全伝票!$C:$C,$C30))) -> 0 | H30: =+IF($A30="",IF($C30="",SUMIFS(全伝票!L:L,全伝票!$B:$B,$B30),SUMIFS(全伝票!L:L,全伝票!$C:$C,$C30)),IF($C30="",SUMIFS(全伝票!L:L,全伝票!$A:$A,$A30,全伝票!$B:$B,$B30),SUMIFS(全伝票!L:L,全伝票!$A:$A,$A30,全伝票!$C:$C,$C30))) -> 0 | I30: =+IF($A30="",IF($C30="",SUMIFS(全伝票!M:M,全伝票!$B:$B,$B30),SUMIFS(全伝票!M:M,全伝票!$C:$C,$C30)),IF($C30="",SUMIFS(全伝票!M:M,全伝票!$A:$A,$A30,全伝票!$B:$B,$B30),SUMIFS(全伝票!M:M,全伝票!$A:$A,$A30,全伝票!$C:$C,$C30))) -> 0 | J30: =+IF($A30="",IF($C30="",SUMIFS(全伝票!N:N,全伝票!$B:$B,$B30),SUMIFS(全伝票!N:N,全伝票!$C:$C,$C30)),IF($C30="",SUMIFS(全伝票!N:N,全伝票!$A:$A,$A30,全伝票!$B:$B,$B30),SUMIFS(全伝票!N:N,全伝票!$A:$A,$A30,全伝票!$C:$C,$C30))) -> 0 | K30: =SUM(F30:J30) -> 0 | L30: =+IF($A30="",IF($C30="",SUMIFS(全伝票!O:O,全伝票!$B:$B,$B30),SUMIFS(全伝票!O:O,全伝票!$C:$C,$C30)),IF($C30="",SUMIFS(全伝票!O:O,全伝票!$A:$A,$A30,全伝票!$B:$B,$B30),SUMIFS(全伝票!O:O,全伝票!$A:$A,$A30,全伝票!$C:$C,$C30))) -> 0 | M30: =+IF($A30="",IF($C30="",SUMIFS(全伝票!P:P,全伝票!$B:$B,$B30),SUMIFS(全伝票!P:P,全伝票!$C:$C,$C30)),IF($C30="",SUMIFS(全伝票!P:P,全伝票!$A:$A,$A30,全伝票!$B:$B,$B30),SUMIFS(全伝票!P:P,全伝票!$A:$A,$A30,全伝票!$C:$C,$C30))) -> 0 | N30: =+ROUND(F30*F$4/(100+F$4),0)+AE30 -> 0 | O30: =+ROUND(G30*G$4/(100+G$4),0)+AF30 -> 0 | P30: =+ROUND(H30*H$4/(100+H$4),0)+AG30 -> 0 | Q30: =+ROUND(I30*I$4/(100+I$4),0)+AH30 -> 0 | R30: =+ROUND(J30*J$4/(100+J$4),0)+AI30 -> 0 | S30: =SUM(N30:R30) -> 0 | T30: =+E30-S30 -> 0 | U30: =N30-F30*F$4/(100+F$4) -> 0 | V30: =O30-G30*G$4/(100+G$4) -> 0 | W30: =P30-H30*H$4/(100+H$4) -> 0 | X30: =Q30-I30*I$4/(100+I$4) -> 0 | Y30: =R30-J30*J$4/(100+J$4) -> 0 | Z30: =+IF(N$38=0,0,IF(N$38<0,-RANK(U30,U$5:U$35,0),RANK(U30,U$5:U$35,1))) -> 0 | AA30: =+IF(O$38=0,0,IF(O$38<0,-RANK(V30,V$5:V$35,0),RANK(V30,V$5:V$35,1))) -> 0 | AB30: =+IF(P$38=0,0,IF(P$38<0,-RANK(W30,W$5:W$35,0),RANK(W30,W$5:W$35,1))) -> 0 | AC30: =+IF(Q$38=0,0,IF(Q$38<0,-RANK(X30,X$5:X$35,0),RANK(X30,X$5:X$35,1))) -> 0 | AD30: =+IF(R$38=0,0,IF(R$38<0,-RANK(Y30,Y$5:Y$35,0),RANK(Y30,Y$5:Y$35,1))) -> 0
A31: 1 | B31: 8830239 | D31: 損害保険料 | E31: =+IF($A31="",IF($C31="",SUMIFS(全伝票!I:I,全伝票!$B:$B,$B31),SUMIFS(全伝票!I:I,全伝票!$C:$C,$C31)),IF($C31="",SUMIFS(全伝票!I:I,全伝票!$A:$A,$A31,全伝票!$B:$B,$B31),SUMIFS(全伝票!I:I,全伝票!$A:$A,$A31,全伝票!$C:$C,$C31))) -> 134822 | F31: =+IF($A31="",IF($C31="",SUMIFS(全伝票!J:J,全伝票!$B:$B,$B31),SUMIFS(全伝票!J:J,全伝票!$C:$C,$C31)),IF($C31="",SUMIFS(全伝票!J:J,全伝票!$A:$A,$A31,全伝票!$B:$B,$B31),SUMIFS(全伝票!J:J,全伝票!$A:$A,$A31,全伝票!$C:$C,$C31))) -> 0 | G31: =+IF($A31="",IF($C31="",SUMIFS(全伝票!K:K,全伝票!$B:$B,$B31),SUMIFS(全伝票!K:K,全伝票!$C:$C,$C31)),IF($C31="",SUMIFS(全伝票!K:K,全伝票!$A:$A,$A31,全伝票!$B:$B,$B31),SUMIFS(全伝票!K:K,全伝票!$A:$A,$A31,全伝票!$C:$C,$C31))) -> 0 | H31: =+IF($A31="",IF($C31="",SUMIFS(全伝票!L:L,全伝票!$B:$B,$B31),SUMIFS(全伝票!L:L,全伝票!$C:$C,$C31)),IF($C31="",SUMIFS(全伝票!L:L,全伝票!$A:$A,$A31,全伝票!$B:$B,$B31),SUMIFS(全伝票!L:L,全伝票!$A:$A,$A31,全伝票!$C:$C,$C31))) -> 0 | I31: =+IF($A31="",IF($C31="",SUMIFS(全伝票!M:M,全伝票!$B:$B,$B31),SUMIFS(全伝票!M:M,全伝票!$C:$C,$C31)),IF($C31="",SUMIFS(全伝票!M:M,全伝票!$A:$A,$A31,全伝票!$B:$B,$B31),SUMIFS(全伝票!M:M,全伝票!$A:$A,$A31,全伝票!$C:$C,$C31))) -> 0 | J31: =+IF($A31="",IF($C31="",SUMIFS(全伝票!N:N,全伝票!$B:$B,$B31),SUMIFS(全伝票!N:N,全伝票!$C:$C,$C31)),IF($C31="",SUMIFS(全伝票!N:N,全伝票!$A:$A,$A31,全伝票!$B:$B,$B31),SUMIFS(全伝票!N:N,全伝票!$A:$A,$A31,全伝票!$C:$C,$C31))) -> 0 | K31: =SUM(F31:J31) -> 0 | L31: =+IF($A31="",IF($C31="",SUMIFS(全伝票!O:O,全伝票!$B:$B,$B31),SUMIFS(全伝票!O:O,全伝票!$C:$C,$C31)),IF($C31="",SUMIFS(全伝票!O:O,全伝票!$A:$A,$A31,全伝票!$B:$B,$B31),SUMIFS(全伝票!O:O,全伝票!$A:$A,$A31,全伝票!$C:$C,$C31))) -> 134822 | M31: =+IF($A31="",IF($C31="",SUMIFS(全伝票!P:P,全伝票!$B:$B,$B31),SUMIFS(全伝票!P:P,全伝票!$C:$C,$C31)),IF($C31="",SUMIFS(全伝票!P:P,全伝票!$A:$A,$A31,全伝票!$B:$B,$B31),SUMIFS(全伝票!P:P,全伝票!$A:$A,$A31,全伝票!$C:$C,$C31))) -> 0 | N31: =+ROUND(F31*F$4/(100+F$4),0)+AE31 -> 0 | O31: =+ROUND(G31*G$4/(100+G$4),0)+AF31 -> 0 | P31: =+ROUND(H31*H$4/(100+H$4),0)+AG31 -> 0 | Q31: =+ROUND(I31*I$4/(100+I$4),0)+AH31 -> 0 | R31: =+ROUND(J31*J$4/(100+J$4),0)+AI31 -> 0 | S31: =SUM(N31:R31) -> 0 | T31: =+E31-S31 -> 134822 | U31: =N31-F31*F$4/(100+F$4) -> 0 | V31: =O31-G31*G$4/(100+G$4) -> 0 | W31: =P31-H31*H$4/(100+H$4) -> 0 | X31: =Q31-I31*I$4/(100+I$4) -> 0 | Y31: =R31-J31*J$4/(100+J$4) -> 0 | Z31: =+IF(N$38=0,0,IF(N$38<0,-RANK(U31,U$5:U$35,0),RANK(U31,U$5:U$35,1))) -> 0 | AA31: =+IF(O$38=0,0,IF(O$38<0,-RANK(V31,V$5:V$35,0),RANK(V31,V$5:V$35,1))) -> 0 | AB31: =+IF(P$38=0,0,IF(P$38<0,-RANK(W31,W$5:W$35,0),RANK(W31,W$5:W$35,1))) -> 0 | AC31: =+IF(Q$38=0,0,IF(Q$38<0,-RANK(X31,X$5:X$35,0),RANK(X31,X$5:X$35,1))) -> 0 | AD31: =+IF(R$38=0,0,IF(R$38<0,-RANK(Y31,Y$5:Y$35,0),RANK(Y31,Y$5:Y$35,1))) -> 0
A32: 1 | B32: 8830240 | D32: 公課費 | E32: =+IF($A32="",IF($C32="",SUMIFS(全伝票!I:I,全伝票!$B:$B,$B32),SUMIFS(全伝票!I:I,全伝票!$C:$C,$C32)),IF($C32="",SUMIFS(全伝票!I:I,全伝票!$A:$A,$A32,全伝票!$B:$B,$B32),SUMIFS(全伝票!I:I,全伝票!$A:$A,$A32,全伝票!$C:$C,$C32))) -> 24800 | F32: =+IF($A32="",IF($C32="",SUMIFS(全伝票!J:J,全伝票!$B:$B,$B32),SUMIFS(全伝票!J:J,全伝票!$C:$C,$C32)),IF($C32="",SUMIFS(全伝票!J:J,全伝票!$A:$A,$A32,全伝票!$B:$B,$B32),SUMIFS(全伝票!J:J,全伝票!$A:$A,$A32,全伝票!$C:$C,$C32))) -> 0 | G32: =+IF($A32="",IF($C32="",SUMIFS(全伝票!K:K,全伝票!$B:$B,$B32),SUMIFS(全伝票!K:K,全伝票!$C:$C,$C32)),IF($C32="",SUMIFS(全伝票!K:K,全伝票!$A:$A,$A32,全伝票!$B:$B,$B32),SUMIFS(全伝票!K:K,全伝票!$A:$A,$A32,全伝票!$C:$C,$C32))) -> 0 | H32: =+IF($A32="",IF($C32="",SUMIFS(全伝票!L:L,全伝票!$B:$B,$B32),SUMIFS(全伝票!L:L,全伝票!$C:$C,$C32)),IF($C32="",SUMIFS(全伝票!L:L,全伝票!$A:$A,$A32,全伝票!$B:$B,$B32),SUMIFS(全伝票!L:L,全伝票!$A:$A,$A32,全伝票!$C:$C,$C32))) -> 0 | I32: =+IF($A32="",IF($C32="",SUMIFS(全伝票!M:M,全伝票!$B:$B,$B32),SUMIFS(全伝票!M:M,全伝票!$C:$C,$C32)),IF($C32="",SUMIFS(全伝票!M:M,全伝票!$A:$A,$A32,全伝票!$B:$B,$B32),SUMIFS(全伝票!M:M,全伝票!$A:$A,$A32,全伝票!$C:$C,$C32))) -> 0 | J32: =+IF($A32="",IF($C32="",SUMIFS(全伝票!N:N,全伝票!$B:$B,$B32),SUMIFS(全伝票!N:N,全伝票!$C:$C,$C32)),IF($C32="",SUMIFS(全伝票!N:N,全伝票!$A:$A,$A32,全伝票!$B:$B,$B32),SUMIFS(全伝票!N:N,全伝票!$A:$A,$A32,全伝票!$C:$C,$C32))) -> 0 | K32: =SUM(F32:J32) -> 0 | L32: =+IF($A32="",IF($C32="",SUMIFS(全伝票!O:O,全伝票!$B:$B,$B32),SUMIFS(全伝票!O:O,全伝票!$C:$C,$C32)),IF($C32="",SUMIFS(全伝票!O:O,全伝票!$A:$A,$A32,全伝票!$B:$B,$B32),SUMIFS(全伝票!O:O,全伝票!$A:$A,$A32,全伝票!$C:$C,$C32))) -> 0 | M32: =+IF($A32="",IF($C32="",SUMIFS(全伝票!P:P,全伝票!$B:$B,$B32),SUMIFS(全伝票!P:P,全伝票!$C:$C,$C32)),IF($C32="",SUMIFS(全伝票!P:P,全伝票!$A:$A,$A32,全伝票!$B:$B,$B32),SUMIFS(全伝票!P:P,全伝票!$A:$A,$A32,全伝票!$C:$C,$C32))) -> 24800 | N32: =+ROUND(F32*F$4/(100+F$4),0)+AE32 -> 0 | O32: =+ROUND(G32*G$4/(100+G$4),0)+AF32 -> 0 | P32: =+ROUND(H32*H$4/(100+H$4),0)+AG32 -> 0 | Q32: =+ROUND(I32*I$4/(100+I$4),0)+AH32 -> 0 | R32: =+ROUND(J32*J$4/(100+J$4),0)+AI32 -> 0 | S32: =SUM(N32:R32) -> 0 | T32: =+E32-S32 -> 24800 | U32: =N32-F32*F$4/(100+F$4) -> 0 | V32: =O32-G32*G$4/(100+G$4) -> 0 | W32: =P32-H32*H$4/(100+H$4) -> 0 | X32: =Q32-I32*I$4/(100+I$4) -> 0 | Y32: =R32-J32*J$4/(100+J$4) -> 0 | Z32: =+IF(N$38=0,0,IF(N$38<0,-RANK(U32,U$5:U$35,0),RANK(U32,U$5:U$35,1))) -> 0 | AA32: =+IF(O$38=0,0,IF(O$38<0,-RANK(V32,V$5:V$35,0),RANK(V32,V$5:V$35,1))) -> 0 | AB32: =+IF(P$38=0,0,IF(P$38<0,-RANK(W32,W$5:W$35,0),RANK(W32,W$5:W$35,1))) -> 0 | AC32: =+IF(Q$38=0,0,IF(Q$38<0,-RANK(X32,X$5:X$35,0),RANK(X32,X$5:X$35,1))) -> 0 | AD32: =+IF(R$38=0,0,IF(R$38<0,-RANK(Y32,Y$5:Y$35,0),RANK(Y32,Y$5:Y$35,1))) -> 0
A33: 1 | B33: 8830210 | C33: 883021003 | D33: 費用弁償 | E33: =+IF($A33="",IF($C33="",SUMIFS(全伝票!I:I,全伝票!$B:$B,$B33),SUMIFS(全伝票!I:I,全伝票!$C:$C,$C33)),IF($C33="",SUMIFS(全伝票!I:I,全伝票!$A:$A,$A33,全伝票!$B:$B,$B33),SUMIFS(全伝票!I:I,全伝票!$A:$A,$A33,全伝票!$C:$C,$C33))) -> 0 | F33: =+IF($A33="",IF($C33="",SUMIFS(全伝票!J:J,全伝票!$B:$B,$B33),SUMIFS(全伝票!J:J,全伝票!$C:$C,$C33)),IF($C33="",SUMIFS(全伝票!J:J,全伝票!$A:$A,$A33,全伝票!$B:$B,$B33),SUMIFS(全伝票!J:J,全伝票!$A:$A,$A33,全伝票!$C:$C,$C33))) -> 0 | G33: =+IF($A33="",IF($C33="",SUMIFS(全伝票!K:K,全伝票!$B:$B,$B33),SUMIFS(全伝票!K:K,全伝票!$C:$C,$C33)),IF($C33="",SUMIFS(全伝票!K:K,全伝票!$A:$A,$A33,全伝票!$B:$B,$B33),SUMIFS(全伝票!K:K,全伝票!$A:$A,$A33,全伝票!$C:$C,$C33))) -> 0 | H33: =+IF($A33="",IF($C33="",SUMIFS(全伝票!L:L,全伝票!$B:$B,$B33),SUMIFS(全伝票!L:L,全伝票!$C:$C,$C33)),IF($C33="",SUMIFS(全伝票!L:L,全伝票!$A:$A,$A33,全伝票!$B:$B,$B33),SUMIFS(全伝票!L:L,全伝票!$A:$A,$A33,全伝票!$C:$C,$C33))) -> 0 | I33: =+IF($A33="",IF($C33="",SUMIFS(全伝票!M:M,全伝票!$B:$B,$B33),SUMIFS(全伝票!M:M,全伝票!$C:$C,$C33)),IF($C33="",SUMIFS(全伝票!M:M,全伝票!$A:$A,$A33,全伝票!$B:$B,$B33),SUMIFS(全伝票!M:M,全伝票!$A:$A,$A33,全伝票!$C:$C,$C33))) -> 0 | J33: =+IF($A33="",IF($C33="",SUMIFS(全伝票!N:N,全伝票!$B:$B,$B33),SUMIFS(全伝票!N:N,全伝票!$C:$C,$C33)),IF($C33="",SUMIFS(全伝票!N:N,全伝票!$A:$A,$A33,全伝票!$B:$B,$B33),SUMIFS(全伝票!N:N,全伝票!$A:$A,$A33,全伝票!$C:$C,$C33))) -> 0 | K33: =SUM(F33:J33) -> 0 | L33: =+IF($A33="",IF($C33="",SUMIFS(全伝票!O:O,全伝票!$B:$B,$B33),SUMIFS(全伝票!O:O,全伝票!$C:$C,$C33)),IF($C33="",SUMIFS(全伝票!O:O,全伝票!$A:$A,$A33,全伝票!$B:$B,$B33),SUMIFS(全伝票!O:O,全伝票!$A:$A,$A33,全伝票!$C:$C,$C33))) -> 0 | M33: =+IF($A33="",IF($C33="",SUMIFS(全伝票!P:P,全伝票!$B:$B,$B33),SUMIFS(全伝票!P:P,全伝票!$C:$C,$C33)),IF($C33="",SUMIFS(全伝票!P:P,全伝票!$A:$A,$A33,全伝票!$B:$B,$B33),SUMIFS(全伝票!P:P,全伝票!$A:$A,$A33,全伝票!$C:$C,$C33))) -> 0 | N33: =+ROUND(F33*F$4/(100+F$4),0)+AE33 -> 0 | O33: =+ROUND(G33*G$4/(100+G$4),0)+AF33 -> 0 | P33: =+ROUND(H33*H$4/(100+H$4),0)+AG33 -> 0 | Q33: =+ROUND(I33*I$4/(100+I$4),0)+AH33 -> 0 | R33: =+ROUND(J33*J$4/(100+J$4),0)+AI33 -> 0 | S33: =SUM(N33:R33) -> 0 | T33: =+E33-S33 -> 0 | U33: =N33-F33*F$4/(100+F$4) -> 0 | V33: =O33-G33*G$4/(100+G$4) -> 0 | W33: =P33-H33*H$4/(100+H$4) -> 0 | X33: =Q33-I33*I$4/(100+I$4) -> 0 | Y33: =R33-J33*J$4/(100+J$4) -> 0 | Z33: =+IF(N$38=0,0,IF(N$38<0,-RANK(U33,U$5:U$35,0),RANK(U33,U$5:U$35,1))) -> 0 | AA33: =+IF(O$38=0,0,IF(O$38<0,-RANK(V33,V$5:V$35,0),RANK(V33,V$5:V$35,1))) -> 0 | AB33: =+IF(P$38=0,0,IF(P$38<0,-RANK(W33,W$5:W$35,0),RANK(W33,W$5:W$35,1))) -> 0 | AC33: =+IF(Q$38=0,0,IF(Q$38<0,-RANK(X33,X$5:X$35,0),RANK(X33,X$5:X$35,1))) -> 0 | AD33: =+IF(R$38=0,0,IF(R$38<0,-RANK(Y33,Y$5:Y$35,0),RANK(Y33,Y$5:Y$35,1))) -> 0
A34: 1 | B34: 8830242 | D34: 賞与引当金繰入額 | E34: =+IF($A34="",IF($C34="",SUMIFS(全伝票!I:I,全伝票!$B:$B,$B34),SUMIFS(全伝票!I:I,全伝票!$C:$C,$C34)),IF($C34="",SUMIFS(全伝票!I:I,全伝票!$A:$A,$A34,全伝票!$B:$B,$B34),SUMIFS(全伝票!I:I,全伝票!$A:$A,$A34,全伝票!$C:$C,$C34))) -> 4701000 | F34: =+IF($A34="",IF($C34="",SUMIFS(全伝票!J:J,全伝票!$B:$B,$B34),SUMIFS(全伝票!J:J,全伝票!$C:$C,$C34)),IF($C34="",SUMIFS(全伝票!J:J,全伝票!$A:$A,$A34,全伝票!$B:$B,$B34),SUMIFS(全伝票!J:J,全伝票!$A:$A,$A34,全伝票!$C:$C,$C34))) -> 0 | G34: =+IF($A34="",IF($C34="",SUMIFS(全伝票!K:K,全伝票!$B:$B,$B34),SUMIFS(全伝票!K:K,全伝票!$C:$C,$C34)),IF($C34="",SUMIFS(全伝票!K:K,全伝票!$A:$A,$A34,全伝票!$B:$B,$B34),SUMIFS(全伝票!K:K,全伝票!$A:$A,$A34,全伝票!$C:$C,$C34))) -> 0 | H34: =+IF($A34="",IF($C34="",SUMIFS(全伝票!L:L,全伝票!$B:$B,$B34),SUMIFS(全伝票!L:L,全伝票!$C:$C,$C34)),IF($C34="",SUMIFS(全伝票!L:L,全伝票!$A:$A,$A34,全伝票!$B:$B,$B34),SUMIFS(全伝票!L:L,全伝票!$A:$A,$A34,全伝票!$C:$C,$C34))) -> 0 | I34: =+IF($A34="",IF($C34="",SUMIFS(全伝票!M:M,全伝票!$B:$B,$B34),SUMIFS(全伝票!M:M,全伝票!$C:$C,$C34)),IF($C34="",SUMIFS(全伝票!M:M,全伝票!$A:$A,$A34,全伝票!$B:$B,$B34),SUMIFS(全伝票!M:M,全伝票!$A:$A,$A34,全伝票!$C:$C,$C34))) -> 0 | J34: =+IF($A34="",IF($C34="",SUMIFS(全伝票!N:N,全伝票!$B:$B,$B34),SUMIFS(全伝票!N:N,全伝票!$C:$C,$C34)),IF($C34="",SUMIFS(全伝票!N:N,全伝票!$A:$A,$A34,全伝票!$B:$B,$B34),SUMIFS(全伝票!N:N,全伝票!$A:$A,$A34,全伝票!$C:$C,$C34))) -> 0 | K34: =SUM(F34:J34) -> 0 | L34: =+IF($A34="",IF($C34="",SUMIFS(全伝票!O:O,全伝票!$B:$B,$B34),SUMIFS(全伝票!O:O,全伝票!$C:$C,$C34)),IF($C34="",SUMIFS(全伝票!O:O,全伝票!$A:$A,$A34,全伝票!$B:$B,$B34),SUMIFS(全伝票!O:O,全伝票!$A:$A,$A34,全伝票!$C:$C,$C34))) -> 0 | M34: =+IF($A34="",IF($C34="",SUMIFS(全伝票!P:P,全伝票!$B:$B,$B34),SUMIFS(全伝票!P:P,全伝票!$C:$C,$C34)),IF($C34="",SUMIFS(全伝票!P:P,全伝票!$A:$A,$A34,全伝票!$B:$B,$B34),SUMIFS(全伝票!P:P,全伝票!$A:$A,$A34,全伝票!$C:$C,$C34))) -> 4701000 | N34: =+ROUND(F34*F$4/(100+F$4),0)+AE34 -> 0 | O34: =+ROUND(G34*G$4/(100+G$4),0)+AF34 -> 0 | P34: =+ROUND(H34*H$4/(100+H$4),0)+AG34 -> 0 | Q34: =+ROUND(I34*I$4/(100+I$4),0)+AH34 -> 0 | R34: =+ROUND(J34*J$4/(100+J$4),0)+AI34 -> 0 | S34: =SUM(N34:R34) -> 0 | T34: =+E34-S34 -> 4701000 | U34: =N34-F34*F$4/(100+F$4) -> 0 | V34: =O34-G34*G$4/(100+G$4) -> 0 | W34: =P34-H34*H$4/(100+H$4) -> 0 | X34: =Q34-I34*I$4/(100+I$4) -> 0 | Y34: =R34-J34*J$4/(100+J$4) -> 0 | Z34: =+IF(N$38=0,0,IF(N$38<0,-RANK(U34,U$5:U$35,0),RANK(U34,U$5:U$35,1))) -> 0 | AA34: =+IF(O$38=0,0,IF(O$38<0,-RANK(V34,V$5:V$35,0),RANK(V34,V$5:V$35,1))) -> 0 | AB34: =+IF(P$38=0,0,IF(P$38<0,-RANK(W34,W$5:W$35,0),RANK(W34,W$5:W$35,1))) -> 0 | AC34: =+IF(Q$38=0,0,IF(Q$38<0,-RANK(X34,X$5:X$35,0),RANK(X34,X$5:X$35,1))) -> 0 | AD34: =+IF(R$38=0,0,IF(R$38<0,-RANK(Y34,Y$5:Y$35,0),RANK(Y34,Y$5:Y$35,1))) -> 0
B35: 8830243 | D35: 貸倒引当金繰入額 | E35: =+IF($A35="",IF($C35="",SUMIFS(全伝票!I:I,全伝票!$B:$B,$B35),SUMIFS(全伝票!I:I,全伝票!$C:$C,$C35)),IF($C35="",SUMIFS(全伝票!I:I,全伝票!$A:$A,$A35,全伝票!$B:$B,$B35),SUMIFS(全伝票!I:I,全伝票!$A:$A,$A35,全伝票!$C:$C,$C35))) -> 0 | F35: =+IF($A35="",IF($C35="",SUMIFS(全伝票!J:J,全伝票!$B:$B,$B35),SUMIFS(全伝票!J:J,全伝票!$C:$C,$C35)),IF($C35="",SUMIFS(全伝票!J:J,全伝票!$A:$A,$A35,全伝票!$B:$B,$B35),SUMIFS(全伝票!J:J,全伝票!$A:$A,$A35,全伝票!$C:$C,$C35))) -> 0 | G35: =+IF($A35="",IF($C35="",SUMIFS(全伝票!K:K,全伝票!$B:$B,$B35),SUMIFS(全伝票!K:K,全伝票!$C:$C,$C35)),IF($C35="",SUMIFS(全伝票!K:K,全伝票!$A:$A,$A35,全伝票!$B:$B,$B35),SUMIFS(全伝票!K:K,全伝票!$A:$A,$A35,全伝票!$C:$C,$C35))) -> 0 | H35: =+IF($A35="",IF($C35="",SUMIFS(全伝票!L:L,全伝票!$B:$B,$B35),SUMIFS(全伝票!L:L,全伝票!$C:$C,$C35)),IF($C35="",SUMIFS(全伝票!L:L,全伝票!$A:$A,$A35,全伝票!$B:$B,$B35),SUMIFS(全伝票!L:L,全伝票!$A:$A,$A35,全伝票!$C:$C,$C35))) -> 0 | I35: =+IF($A35="",IF($C35="",SUMIFS(全伝票!M:M,全伝票!$B:$B,$B35),SUMIFS(全伝票!M:M,全伝票!$C:$C,$C35)),IF($C35="",SUMIFS(全伝票!M:M,全伝票!$A:$A,$A35,全伝票!$B:$B,$B35),SUMIFS(全伝票!M:M,全伝票!$A:$A,$A35,全伝票!$C:$C,$C35))) -> 0 | J35: =+IF($A35="",IF($C35="",SUMIFS(全伝票!N:N,全伝票!$B:$B,$B35),SUMIFS(全伝票!N:N,全伝票!$C:$C,$C35)),IF($C35="",SUMIFS(全伝票!N:N,全伝票!$A:$A,$A35,全伝票!$B:$B,$B35),SUMIFS(全伝票!N:N,全伝票!$A:$A,$A35,全伝票!$C:$C,$C35))) -> 0 | K35: =SUM(F35:J35) -> 0 | L35: =+IF($A35="",IF($C35="",SUMIFS(全伝票!O:O,全伝票!$B:$B,$B35),SUMIFS(全伝票!O:O,全伝票!$C:$C,$C35)),IF($C35="",SUMIFS(全伝票!O:O,全伝票!$A:$A,$A35,全伝票!$B:$B,$B35),SUMIFS(全伝票!O:O,全伝票!$A:$A,$A35,全伝票!$C:$C,$C35))) -> 0 | M35: =+IF($A35="",IF($C35="",SUMIFS(全伝票!P:P,全伝票!$B:$B,$B35),SUMIFS(全伝票!P:P,全伝票!$C:$C,$C35)),IF($C35="",SUMIFS(全伝票!P:P,全伝票!$A:$A,$A35,全伝票!$B:$B,$B35),SUMIFS(全伝票!P:P,全伝票!$A:$A,$A35,全伝票!$C:$C,$C35))) -> 0 | N35: =+ROUND(F35*F$4/(100+F$4),0)+AE35 -> 0 | O35: =+ROUND(G35*G$4/(100+G$4),0)+AF35 -> 0 | P35: =+ROUND(H35*H$4/(100+H$4),0)+AG35 -> 0 | Q35: =+ROUND(I35*I$4/(100+I$4),0)+AH35 -> 0 | R35: =+ROUND(J35*J$4/(100+J$4),0)+AI35 -> 0 | S35: =SUM(N35:R35) -> 0 | T35: =+E35-S35 -> 0 | U35: =N35-F35*F$4/(100+F$4) -> 0 | V35: =O35-G35*G$4/(100+G$4) -> 0 | W35: =P35-H35*H$4/(100+H$4) -> 0 | X35: =Q35-I35*I$4/(100+I$4) -> 0 | Y35: =R35-J35*J$4/(100+J$4) -> 0 | Z35: =+IF(N$38=0,0,IF(N$38<0,-RANK(U35,U$5:U$35,0),RANK(U35,U$5:U$35,1))) -> 0 | AA35: =+IF(O$38=0,0,IF(O$38<0,-RANK(V35,V$5:V$35,0),RANK(V35,V$5:V$35,1))) -> 0 | AB35: =+IF(P$38=0,0,IF(P$38<0,-RANK(W35,W$5:W$35,0),RANK(W35,W$5:W$35,1))) -> 0 | AC35: =+IF(Q$38=0,0,IF(Q$38<0,-RANK(X35,X$5:X$35,0),RANK(X35,X$5:X$35,1))) -> 0 | AD35: =+IF(R$38=0,0,IF(R$38<0,-RANK(Y35,Y$5:Y$35,0),RANK(Y35,Y$5:Y$35,1))) -> 0
D36: 計 | E36: =SUM(E5:E35) -> 611819957 | F36: =SUM(F5:F35) -> 0 | G36: =SUM(G5:G35) -> 0 | H36: =SUM(H5:H35) -> 678402 | I36: =SUM(I5:I35) -> 0 | J36: =SUM(J5:J35) -> 518156070 | K36: =SUM(K5:K35) -> 518834472 | L36: =SUM(L5:L35) -> 20454735 | ... T36: =SUM(T5:T35) -> 564664608 | U36: =+IF(F36=0,"",ROUND(F36*F$4/(100+F$4),7)-N36)
D37: 総額検算 | E37: =+E36 -> 611819957 | F37: =+F36 -> 0 | G37: =+G36 -> 0 | H37: =+H36 -> 678402 | I37: =+I36 -> 0 | J37: =+J36 -> 518156070 | K37: =SUM(F37:J37) -> 518834472 | L37: =+L36 -> 20454735 | M37: =+M36 -> 72530750 | N37: =+'3条支出'!N6 -> 0 | O37: =+'3条支出'!O6 -> 0 | P37: =+'3条支出'!P6 -> 50252 | Q37: =+'3条支出'!Q6 -> 0 | R37: =+'3条支出'!R6 -> 47105097 | S37: =+'3条支出'!S6 -> 47155349 | T37: =+'3条支出'!T6 -> 564664608 | U37: =+IF(F37=0,"",ROUND(F37*F$4/(100+F$4),7)-N37)
E38: =+E37-E36 -> 0 | F38: =+F37-F36 -> 0 | G38: =+G37-G36 -> 0 | H38: =+H37-H36 -> 0 | I38: =+I37-I36 -> 0 | J38: =+J37-J36 -> 0 | K38: =+K37-K36 -> 0 | L38: =+L37-L36 -> 0 | ... T38: =+T37-T36 -> 0 | U38: =+IF(F38=0,"",ROUND(F38*F$4/(100+F$4),7)-N38) | V38: =+IF(G38=0,"",ROUND(G38*G$4/(100+G$4),7)-O38) | W38: =+IF(H38=0,"",ROUND(H38*H$4/(100+H$4),7)-P38) | Y38: =+IF(J38=0,"",ROUND(J38*J$4/(100+J$4),7)-R38) | AB38: =+IF(SUM(U38:Y38)=0,"",SUM(U38:Y38))
U39: =+IF(F39=0,"",ROUND(F39*F$4/(100+F$4),7)-N39) | V39: =+IF(G39=0,"",ROUND(G39*G$4/(100+G$4),7)-O39) | W39: =+IF(H39=0,"",ROUND(H39*H$4/(100+H$4),7)-P39) | Y39: =+IF(J39=0,"",ROUND(J39*J$4/(100+J$4),7)-R39) | AB39: =+IF(SUM(U39:Y39)=0,"",SUM(U39:Y39))
U40: =+IF(F40=0,"",ROUND(F40*F$4/(100+F$4),7)-N40)

Sheet 水質
D1: =+'3条支出'!D1 -> 令和５年度決算 消費税算出資料
D2: 【水質指導費】
A3: 事業 | B3: 節 | C3: 細節 | D3: 費目 | E3: 税込決算額 | F3: 課税支出 | L3: 非課税支出 | M3: 不課税支出 | N3: 消費税 | T3: 税抜決算額 | U3: 消費税 端数確認 | Z3: 消費税端数調整ランク | AE3: 消費税 調整額
F4: 3 | G4: 5 | H4: 8 | I4: 8 | J4: 10 | K4: 計 | N4: 3 | O4: 5 | P4: 8 | Q4: 8 | R4: 10 | S4: 計 | U4: 3 | V4: 5 | W4: 8 | X4: 8 | Y4: 10 | Z4: 3 | AA4: 5 | AB4: 8 | AC4: 8 | AD4: 10 | AE4: 3 | AF4: 5 | AG4: 8 | AH4: 8 | AI4: 10
A5: 1 | B5: 8830401 | D5: 報酬 | E5: =+IF($A5="",IF($C5="",SUMIFS(全伝票!I:I,全伝票!$B:$B,$B5),SUMIFS(全伝票!I:I,全伝票!$C:$C,$C5)),IF($C5="",SUMIFS(全伝票!I:I,全伝票!$A:$A,$A5,全伝票!$B:$B,$B5),SUMIFS(全伝票!I:I,全伝票!$A:$A,$A5,全伝票!$C:$C,$C5))) -> 115000 | F5: =+IF($A5="",IF($C5="",SUMIFS(全伝票!J:J,全伝票!$B:$B,$B5),SUMIFS(全伝票!J:J,全伝票!$C:$C,$C5)),IF($C5="",SUMIFS(全伝票!J:J,全伝票!$A:$A,$A5,全伝票!$B:$B,$B5),SUMIFS(全伝票!J:J,全伝票!$A:$A,$A5,全伝票!$C:$C,$C5))) -> 0 | G5: =+IF($A5="",IF($C5="",SUMIFS(全伝票!K:K,全伝票!$B:$B,$B5),SUMIFS(全伝票!K:K,全伝票!$C:$C,$C5)),IF($C5="",SUMIFS(全伝票!K:K,全伝票!$A:$A,$A5,全伝票!$B:$B,$B5),SUMIFS(全伝票!K:K,全伝票!$A:$A,$A5,全伝票!$C:$C,$C5))) -> 0 | H5: =+IF($A5="",IF($C5="",SUMIFS(全伝票!L:L,全伝票!$B:$B,$B5),SUMIFS(全伝票!L:L,全伝票!$C:$C,$C5)),IF($C5="",SUMIFS(全伝票!L:L,全伝票!$A:$A,$A5,全伝票!$B:$B,$B5),SUMIFS(全伝票!L:L,全伝票!$A:$A,$A5,全伝票!$C:$C,$C5))) -> 0 | I5: =+IF($A5="",IF($C5="",SUMIFS(全伝票!M:M,全伝票!$B:$B,$B5),SUMIFS(全伝票!M:M,全伝票!$C:$C,$C5)),IF($C5="",SUMIFS(全伝票!M:M,全伝票!$A:$A,$A5,全伝票!$B:$B,$B5),SUMIFS(全伝票!M:M,全伝票!$A:$A,$A5,全伝票!$C:$C,$C5))) -> 0 | J5: =+IF($A5="",IF($C5="",SUMIFS(全伝票!N:N,全伝票!$B:$B,$B5),SUMIFS(全伝票!N:N,全伝票!$C:$C,$C5)),IF($C5="",SUMIFS(全伝票!N:N,全伝票!$A:$A,$A5,全伝票!$B:$B,$B5),SUMIFS(全伝票!N:N,全伝票!$A:$A,$A5,全伝票!$C:$C,$C5))) -> 0 | K5: =SUM(F5:J5) -> 0 | L5: =+IF($A5="",IF($C5="",SUMIFS(全伝票!O:O,全伝票!$B:$B,$B5),SUMIFS(全伝票!O:O,全伝票!$C:$C,$C5)),IF($C5="",SUMIFS(全伝票!O:O,全伝票!$A:$A,$A5,全伝票!$B:$B,$B5),SUMIFS(全伝票!O:O,全伝票!$A:$A,$A5,全伝票!$C:$C,$C5))) -> 0 | M5: =+IF($A5="",IF($C5="",SUMIFS(全伝票!P:P,全伝票!$B:$B,$B5),SUMIFS(全伝票!P:P,全伝票!$C:$C,$C5)),IF($C5="",SUMIFS(全伝票!P:P,全伝票!$A:$A,$A5,全伝票!$B:$B,$B5),SUMIFS(全伝票!P:P,全伝票!$A:$A,$A5,全伝票!$C:$C,$C5))) -> 115000 | N5: =+ROUND(F5*F$4/(100+F$4),0)+AE5 -> 0 | O5: =+ROUND(G5*G$4/(100+G$4),0)+AF5 -> 0 | P5: =+ROUND(H5*H$4/(100+H$4),0)+AG5 -> 0 | Q5: =+ROUND(I5*I$4/(100+I$4),0)+AH5 -> 0 | R5: =+ROUND(J5*J$4/(100+J$4),0)+AI5 -> 0 | S5: =SUM(N5:R5) -> 0 | T5: =+E5-S5 -> 115000 | U5: =N5-F5*F$4/(100+F$4) -> 0 | V5: =O5-G5*G$4/(100+G$4) -> 0 | W5: =P5-H5*H$4/(100+H$4) -> 0 | X5: =Q5-I5*I$4/(100+I$4) -> 0 | Y5: =R5-J5*J$4/(100+J$4) -> 0 | Z5: =+IF(N$38=0,0,IF(N$38<0,-RANK(U5,U$5:U$35,0),RANK(U5,U$5:U$35,1))) -> 0 | AA5: =+IF(O$38=0,0,IF(O$38<0,-RANK(V5,V$5:V$35,0),RANK(V5,V$5:V$35,1))) -> 0 | AB5: =+IF(P$38=0,0,IF(P$38<0,-RANK(W5,W$5:W$35,0),RANK(W5,W$5:W$35,1))) -> 0 | AC5: =+IF(Q$38=0,0,IF(Q$38<0,-RANK(X5,X$5:X$35,0),RANK(X5,X$5:X$35,1))) -> 0 | AD5: =+IF(R$38=0,0,IF(R$38<0,-RANK(Y5,Y$5:Y$35,0),RANK(Y5,Y$5:Y$35,1))) -> 0
A6: 1 | B6: 8830402 | D6: 給料 | E6: =+IF($A6="",IF($C6="",SUMIFS(全伝票!I:I,全伝票!$B:$B,$B6),SUMIFS(全伝票!I:I,全伝票!$C:$C,$C6)),IF($C6="",SUMIFS(全伝票!I:I,全伝票!$A:$A,$A6,全伝票!$B:$B,$B6),SUMIFS(全伝票!I:I,全伝票!$A:$A,$A6,全伝票!$C:$C,$C6))) -> 19311700 | F6: =+IF($A6="",IF($C6="",SUMIFS(全伝票!J:J,全伝票!$B:$B,$B6),SUMIFS(全伝票!J:J,全伝票!$C:$C,$C6)),IF($C6="",SUMIFS(全伝票!J:J,全伝票!$A:$A,$A6,全伝票!$B:$B,$B6),SUMIFS(全伝票!J:J,全伝票!$A:$A,$A6,全伝票!$C:$C,$C6))) -> 0 | G6: =+IF($A6="",IF($C6="",SUMIFS(全伝票!K:K,全伝票!$B:$B,$B6),SUMIFS(全伝票!K:K,全伝票!$C:$C,$C6)),IF($C6="",SUMIFS(全伝票!K:K,全伝票!$A:$A,$A6,全伝票!$B:$B,$B6),SUMIFS(全伝票!K:K,全伝票!$A:$A,$A6,全伝票!$C:$C,$C6))) -> 0 | H6: =+IF($A6="",IF($C6="",SUMIFS(全伝票!L:L,全伝票!$B:$B,$B6),SUMIFS(全伝票!L:L,全伝票!$C:$C,$C6)),IF($C6="",SUMIFS(全伝票!L:L,全伝票!$A:$A,$A6,全伝票!$B:$B,$B6),SUMIFS(全伝票!L:L,全伝票!$A:$A,$A6,全伝票!$C:$C,$C6))) -> 0 | I6: =+IF($A6="",IF($C6="",SUMIFS(全伝票!M:M,全伝票!$B:$B,$B6),SUMIFS(全伝票!M:M,全伝票!$C:$C,$C6)),IF($C6="",SUMIFS(全伝票!M:M,全伝票!$A:$A,$A6,全伝票!$B:$B,$B6),SUMIFS(全伝票!M:M,全伝票!$A:$A,$A6,全伝票!$C:$C,$C6))) -> 0 | J6: =+IF($A6="",IF($C6="",SUMIFS(全伝票!N:N,全伝票!$B:$B,$B6),SUMIFS(全伝票!N:N,全伝票!$C:$C,$C6)),IF($C6="",SUMIFS(全伝票!N:N,全伝票!$A:$A,$A6,全伝票!$B:$B,$B6),SUMIFS(全伝票!N:N,全伝票!$A:$A,$A6,全伝票!$C:$C,$C6))) -> 0 | K6: =SUM(F6:J6) -> 0 | L6: =+IF($A6="",IF($C6="",SUMIFS(全伝票!O:O,全伝票!$B:$B,$B6),SUMIFS(全伝票!O:O,全伝票!$C:$C,$C6)),IF($C6="",SUMIFS(全伝票!O:O,全伝票!$A:$A,$A6,全伝票!$B:$B,$B6),SUMIFS(全伝票!O:O,全伝票!$A:$A,$A6,全伝票!$C:$C,$C6))) -> 0 | M6: =+IF($A6="",IF($C6="",SUMIFS(全伝票!P:P,全伝票!$B:$B,$B6),SUMIFS(全伝票!P:P,全伝票!$C:$C,$C6)),IF($C6="",SUMIFS(全伝票!P:P,全伝票!$A:$A,$A6,全伝票!$B:$B,$B6),SUMIFS(全伝票!P:P,全伝票!$A:$A,$A6,全伝票!$C:$C,$C6))) -> 19311700 | N6: =+ROUND(F6*F$4/(100+F$4),0)+AE6 -> 0 | O6: =+ROUND(G6*G$4/(100+G$4),0)+AF6 -> 0 | P6: =+ROUND(H6*H$4/(100+H$4),0)+AG6 -> 0 | Q6: =+ROUND(I6*I$4/(100+I$4),0)+AH6 -> 0 | R6: =+ROUND(J6*J$4/(100+J$4),0)+AI6 -> 0 | S6: =SUM(N6:R6) -> 0 | T6: =+E6-S6 -> 19311700 | U6: =N6-F6*F$4/(100+F$4) -> 0 | V6: =O6-G6*G$4/(100+G$4) -> 0 | W6: =P6-H6*H$4/(100+H$4) -> 0 | X6: =Q6-I6*I$4/(100+I$4) -> 0 | Y6: =R6-J6*J$4/(100+J$4) -> 0 | Z6: =+IF(N$38=0,0,IF(N$38<0,-RANK(U6,U$5:U$35,0),RANK(U6,U$5:U$35,1))) -> 0 | AA6: =+IF(O$38=0,0,IF(O$38<0,-RANK(V6,V$5:V$35,0),RANK(V6,V$5:V$35,1))) -> 0 | AB6: =+IF(P$38=0,0,IF(P$38<0,-RANK(W6,W$5:W$35,0),RANK(W6,W$5:W$35,1))) -> 0 | AC6: =+IF(Q$38=0,0,IF(Q$38<0,-RANK(X6,X$5:X$35,0),RANK(X6,X$5:X$35,1))) -> 0 | AD6: =+IF(R$38=0,0,IF(R$38<0,-RANK(Y6,Y$5:Y$35,0),RANK(Y6,Y$5:Y$35,1))) -> 0
A7: 1 | B7: 8830403 | D7: 手当等 | E7: =+IF($A7="",IF($C7="",SUMIFS(全伝票!I:I,全伝票!$B:$B,$B7),SUMIFS(全伝票!I:I,全伝票!$C:$C,$C7)),IF($C7="",SUMIFS(全伝票!I:I,全伝票!$A:$A,$A7,全伝票!$B:$B,$B7),SUMIFS(全伝票!I:I,全伝票!$A:$A,$A7,全伝票!$C:$C,$C7))) -> 12220055 | F7: =+IF($A7="",IF($C7="",SUMIFS(全伝票!J:J,全伝票!$B:$B,$B7),SUMIFS(全伝票!J:J,全伝票!$C:$C,$C7)),IF($C7="",SUMIFS(全伝票!J:J,全伝票!$A:$A,$A7,全伝票!$B:$B,$B7),SUMIFS(全伝票!J:J,全伝票!$A:$A,$A7,全伝票!$C:$C,$C7))) -> 0 | G7: =+IF($A7="",IF($C7="",SUMIFS(全伝票!K:K,全伝票!$B:$B,$B7),SUMIFS(全伝票!K:K,全伝票!$C:$C,$C7)),IF($C7="",SUMIFS(全伝票!K:K,全伝票!$A:$A,$A7,全伝票!$B:$B,$B7),SUMIFS(全伝票!K:K,全伝票!$A:$A,$A7,全伝票!$C:$C,$C7))) -> 0 | H7: =+IF($A7="",IF($C7="",SUMIFS(全伝票!L:L,全伝票!$B:$B,$B7),SUMIFS(全伝票!L:L,全伝票!$C:$C,$C7)),IF($C7="",SUMIFS(全伝票!L:L,全伝票!$A:$A,$A7,全伝票!$B:$B,$B7),SUMIFS(全伝票!L:L,全伝票!$A:$A,$A7,全伝票!$C:$C,$C7))) -> 0 | I7: =+IF($A7="",IF($C7="",SUMIFS(全伝票!M:M,全伝票!$B:$B,$B7),SUMIFS(全伝票!M:M,全伝票!$C:$C,$C7)),IF($C7="",SUMIFS(全伝票!M:M,全伝票!$A:$A,$A7,全伝票!$B:$B,$B7),SUMIFS(全伝票!M:M,全伝票!$A:$A,$A7,全伝票!$C:$C,$C7))) -> 0 | J7: =+IF($A7="",IF($C7="",SUMIFS(全伝票!N:N,全伝票!$B:$B,$B7),SUMIFS(全伝票!N:N,全伝票!$C:$C,$C7)),IF($C7="",SUMIFS(全伝票!N:N,全伝票!$A:$A,$A7,全伝票!$B:$B,$B7),SUMIFS(全伝票!N:N,全伝票!$A:$A,$A7,全伝票!$C:$C,$C7))) -> 371190 | K7: =SUM(F7:J7) -> 371190 | L7: =+IF($A7="",IF($C7="",SUMIFS(全伝票!O:O,全伝票!$B:$B,$B7),SUMIFS(全伝票!O:O,全伝票!$C:$C,$C7)),IF($C7="",SUMIFS(全伝票!O:O,全伝票!$A:$A,$A7,全伝票!$B:$B,$B7),SUMIFS(全伝票!O:O,全伝票!$A:$A,$A7,全伝票!$C:$C,$C7))) -> 0 | M7: =+IF($A7="",IF($C7="",SUMIFS(全伝票!P:P,全伝票!$B:$B,$B7),SUMIFS(全伝票!P:P,全伝票!$C:$C,$C7)),IF($C7="",SUMIFS(全伝票!P:P,全伝票!$A:$A,$A7,全伝票!$B:$B,$B7),SUMIFS(全伝票!P:P,全伝票!$A:$A,$A7,全伝票!$C:$C,$C7))) -> 11848865 | N7: =+ROUND(F7*F$4/(100+F$4),0)+AE7 -> 0 | O7: =+ROUND(G7*G$4/(100+G$4),0)+AF7 -> 0 | P7: =+ROUND(H7*H$4/(100+H$4),0)+AG7 -> 0 | Q7: =+ROUND(I7*I$4/(100+I$4),0)+AH7 -> 0 | R7: =+ROUND(J7*J$4/(100+J$4),0)+AI7 -> 33745 | S7: =SUM(N7:R7) -> 33745 | T7: =+E7-S7 -> 12186310 | U7: =N7-F7*F$4/(100+F$4) -> 0 | V7: =O7-G7*G$4/(100+G$4) -> 0 | W7: =P7-H7*H$4/(100+H$4) -> 0 | X7: =Q7-I7*I$4/(100+I$4) -> 0 | Y7: =R7-J7*J$4/(100+J$4) -> 0.45454545 | Z7: =+IF(N$38=0,0,IF(N$38<0,-RANK(U7,U$5:U$35,0),RANK(U7,U$5:U$35,1))) -> 0 | AA7: =+IF(O$38=0,0,IF(O$38<0,-RANK(V7,V$5:V$35,0),RANK(V7,V$5:V$35,1))) -> 0 | AB7: =+IF(P$38=0,0,IF(P$38<0,-RANK(W7,W$5:W$35,0),RANK(W7,W$5:W$35,1))) -> 0 | AC7: =+IF(Q$38=0,0,IF(Q$38<0,-RANK(X7,X$5:X$35,0),RANK(X7,X$5:X$35,1))) -> 0 | AD7: =+IF(R$38=0,0,IF(R$38<0,-RANK(Y7,Y$5:Y$35,0),RANK(Y7,Y$5:Y$35,1))) -> 0
A8: 1 | B8: 8830404 | D8: 法定福利費 | E8: =+IF($A8="",IF($C8="",SUMIFS(全伝票!I:I,全伝票!$B:$B,$B8),SUMIFS(全伝票!I:I,全伝票!$C:$C,$C8)),IF($C8="",SUMIFS(全伝票!I:I,全伝票!$A:$A,$A8,全伝票!$B:$B,$B8),SUMIFS(全伝票!I:I,全伝票!$A:$A,$A8,全伝票!$C:$C,$C8))) -> 6205907 | F8: =+IF($A8="",IF($C8="",SUMIFS(全伝票!J:J,全伝票!$B:$B,$B8),SUMIFS(全伝票!J:J,全伝票!$C:$C,$C8)),IF($C8="",SUMIFS(全伝票!J:J,全伝票!$A:$A,$A8,全伝票!$B:$B,$B8),SUMIFS(全伝票!J:J,全伝票!$A:$A,$A8,全伝票!$C:$C,$C8))) -> 0 | G8: =+IF($A8="",IF($C8="",SUMIFS(全伝票!K:K,全伝票!$B:$B,$B8),SUMIFS(全伝票!K:K,全伝票!$C:$C,$C8)),IF($C8="",SUMIFS(全伝票!K:K,全伝票!$A:$A,$A8,全伝票!$B:$B,$B8),SUMIFS(全伝票!K:K,全伝票!$A:$A,$A8,全伝票!$C:$C,$C8))) -> 0 | H8: =+IF($A8="",IF($C8="",SUMIFS(全伝票!L:L,全伝票!$B:$B,$B8),SUMIFS(全伝票!L:L,全伝票!$C:$C,$C8)),IF($C8="",SUMIFS(全伝票!L:L,全伝票!$A:$A,$A8,全伝票!$B:$B,$B8),SUMIFS(全伝票!L:L,全伝票!$A:$A,$A8,全伝票!$C:$C,$C8))) -> 0 | I8: =+IF($A8="",IF($C8="",SUMIFS(全伝票!M:M,全伝票!$B:$B,$B8),SUMIFS(全伝票!M:M,全伝票!$C:$C,$C8)),IF($C8="",SUMIFS(全伝票!M:M,全伝票!$A:$A,$A8,全伝票!$B:$B,$B8),SUMIFS(全伝票!M:M,全伝票!$A:$A,$A8,全伝票!$C:$C,$C8))) -> 0 | J8: =+IF($A8="",IF($C8="",SUMIFS(全伝票!N:N,全伝票!$B:$B,$B8),SUMIFS(全伝票!N:N,全伝票!$C:$C,$C8)),IF($C8="",SUMIFS(全伝票!N:N,全伝票!$A:$A,$A8,全伝票!$B:$B,$B8),SUMIFS(全伝票!N:N,全伝票!$A:$A,$A8,全伝票!$C:$C,$C8))) -> 0 | K8: =SUM(F8:J8) -> 0 | L8: =+IF($A8="",IF($C8="",SUMIFS(全伝票!O:O,全伝票!$B:$B,$B8),SUMIFS(全伝票!O:O,全伝票!$C:$C,$C8)),IF($C8="",SUMIFS(全伝票!O:O,全伝票!$A:$A,$A8,全伝票!$B:$B,$B8),SUMIFS(全伝票!O:O,全伝票!$A:$A,$A8,全伝票!$C:$C,$C8))) -> 6176483 | M8: =+IF($A8="",IF($C8="",SUMIFS(全伝票!P:P,全伝票!$B:$B,$B8),SUMIFS(全伝票!P:P,全伝票!$C:$C,$C8)),IF($C8="",SUMIFS(全伝票!P:P,全伝票!$A:$A,$A8,全伝票!$B:$B,$B8),SUMIFS(全伝票!P:P,全伝票!$A:$A,$A8,全伝票!$C:$C,$C8))) -> 29424 | N8: =+ROUND(F8*F$4/(100+F$4),0)+AE8 -> 0 | O8: =+ROUND(G8*G$4/(100+G$4),0)+AF8 -> 0 | P8: =+ROUND(H8*H$4/(100+H$4),0)+AG8 -> 0 | Q8: =+ROUND(I8*I$4/(100+I$4),0)+AH8 -> 0 | R8: =+ROUND(J8*J$4/(100+J$4),0)+AI8 -> 0 | S8: =SUM(N8:R8) -> 0 | T8: =+E8-S8 -> 6205907 | U8: =N8-F8*F$4/(100+F$4) -> 0 | V8: =O8-G8*G$4/(100+G$4) -> 0 | W8: =P8-H8*H$4/(100+H$4) -> 0 | X8: =Q8-I8*I$4/(100+I$4) -> 0 | Y8: =R8-J8*J$4/(100+J$4) -> 0 | Z8: =+IF(N$38=0,0,IF(N$38<0,-RANK(U8,U$5:U$35,0),RANK(U8,U$5:U$35,1))) -> 0 | AA8: =+IF(O$38=0,0,IF(O$38<0,-RANK(V8,V$5:V$35,0),RANK(V8,V$5:V$35,1))) -> 0 | AB8: =+IF(P$38=0,0,IF(P$38<0,-RANK(W8,W$5:W$35,0),RANK(W8,W$5:W$35,1))) -> 0 | AC8: =+IF(Q$38=0,0,IF(Q$38<0,-RANK(X8,X$5:X$35,0),RANK(X8,X$5:X$35,1))) -> 0 | AD8: =+IF(R$38=0,0,IF(R$38<0,-RANK(Y8,Y$5:Y$35,0),RANK(Y8,Y$5:Y$35,1))) -> 0
A9: 1 | B9: 8830405 | D9: 災害補償費 | E9: =+IF($A9="",IF($C9="",SUMIFS(全伝票!I:I,全伝票!$B:$B,$B9),SUMIFS(全伝票!I:I,全伝票!$C:$C,$C9)),IF($C9="",SUMIFS(全伝票!I:I,全伝票!$A:$A,$A9,全伝票!$B:$B,$B9),SUMIFS(全伝票!I:I,全伝票!$A:$A,$A9,全伝票!$C:$C,$C9))) -> 0 | F9: =+IF($A9="",IF($C9="",SUMIFS(全伝票!J:J,全伝票!$B:$B,$B9),SUMIFS(全伝票!J:J,全伝票!$C:$C,$C9)),IF($C9="",SUMIFS(全伝票!J:J,全伝票!$A:$A,$A9,全伝票!$B:$B,$B9),SUMIFS(全伝票!J:J,全伝票!$A:$A,$A9,全伝票!$C:$C,$C9))) -> 0 | G9: =+IF($A9="",IF($C9="",SUMIFS(全伝票!K:K,全伝票!$B:$B,$B9),SUMIFS(全伝票!K:K,全伝票!$C:$C,$C9)),IF($C9="",SUMIFS(全伝票!K:K,全伝票!$A:$A,$A9,全伝票!$B:$B,$B9),SUMIFS(全伝票!K:K,全伝票!$A:$A,$A9,全伝票!$C:$C,$C9))) -> 0 | H9: =+IF($A9="",IF($C9="",SUMIFS(全伝票!L:L,全伝票!$B:$B,$B9),SUMIFS(全伝票!L:L,全伝票!$C:$C,$C9)),IF($C9="",SUMIFS(全伝票!L:L,全伝票!$A:$A,$A9,全伝票!$B:$B,$B9),SUMIFS(全伝票!L:L,全伝票!$A:$A,$A9,全伝票!$C:$C,$C9))) -> 0 | I9: =+IF($A9="",IF($C9="",SUMIFS(全伝票!M:M,全伝票!$B:$B,$B9),SUMIFS(全伝票!M:M,全伝票!$C:$C,$C9)),IF($C9="",SUMIFS(全伝票!M:M,全伝票!$A:$A,$A9,全伝票!$B:$B,$B9),SUMIFS(全伝票!M:M,全伝票!$A:$A,$A9,全伝票!$C:$C,$C9))) -> 0 | J9: =+IF($A9="",IF($C9="",SUMIFS(全伝票!N:N,全伝票!$B:$B,$B9),SUMIFS(全伝票!N:N,全伝票!$C:$C,$C9)),IF($C9="",SUMIFS(全伝票!N:N,全伝票!$A:$A,$A9,全伝票!$B:$B,$B9),SUMIFS(全伝票!N:N,全伝票!$A:$A,$A9,全伝票!$C:$C,$C9))) -> 0 | K9: =SUM(F9:J9) -> 0 | L9: =+IF($A9="",IF($C9="",SUMIFS(全伝票!O:O,全伝票!$B:$B,$B9),SUMIFS(全伝票!O:O,全伝票!$C:$C,$C9)),IF($C9="",SUMIFS(全伝票!O:O,全伝票!$A:$A,$A9,全伝票!$B:$B,$B9),SUMIFS(全伝票!O:O,全伝票!$A:$A,$A9,全伝票!$C:$C,$C9))) -> 0 | M9: =+IF($A9="",IF($C9="",SUMIFS(全伝票!P:P,全伝票!$B:$B,$B9),SUMIFS(全伝票!P:P,全伝票!$C:$C,$C9)),IF($C9="",SUMIFS(全伝票!P:P,全伝票!$A:$A,$A9,全伝票!$B:$B,$B9),SUMIFS(全伝票!P:P,全伝票!$A:$A,$A9,全伝票!$C:$C,$C9))) -> 0 | N9: =+ROUND(F9*F$4/(100+F$4),0)+AE9 -> 0 | O9: =+ROUND(G9*G$4/(100+G$4),0)+AF9 -> 0 | P9: =+ROUND(H9*H$4/(100+H$4),0)+AG9 -> 0 | Q9: =+ROUND(I9*I$4/(100+I$4),0)+AH9 -> 0 | R9: =+ROUND(J9*J$4/(100+J$4),0)+AI9 -> 0 | S9: =SUM(N9:R9) -> 0 | T9: =+E9-S9 -> 0 | U9: =N9-F9*F$4/(100+F$4) -> 0 | V9: =O9-G9*G$4/(100+G$4) -> 0 | W9: =P9-H9*H$4/(100+H$4) -> 0 | X9: =Q9-I9*I$4/(100+I$4) -> 0 | Y9: =R9-J9*J$4/(100+J$4) -> 0 | Z9: =+IF(N$38=0,0,IF(N$38<0,-RANK(U9,U$5:U$35,0),RANK(U9,U$5:U$35,1))) -> 0 | AA9: =+IF(O$38=0,0,IF(O$38<0,-RANK(V9,V$5:V$35,0),RANK(V9,V$5:V$35,1))) -> 0 | AB9: =+IF(P$38=0,0,IF(P$38<0,-RANK(W9,W$5:W$35,0),RANK(W9,W$5:W$35,1))) -> 0 | AC9: =+IF(Q$38=0,0,IF(Q$38<0,-RANK(X9,X$5:X$35,0),RANK(X9,X$5:X$35,1))) -> 0 | AD9: =+IF(R$38=0,0,IF(R$38<0,-RANK(Y9,Y$5:Y$35,0),RANK(Y9,Y$5:Y$35,1))) -> 0
A10: 1 | B10: 8830407 | D10: 賃金 | E10: =+IF($A10="",IF($C10="",SUMIFS(全伝票!I:I,全伝票!$B:$B,$B10),SUMIFS(全伝票!I:I,全伝票!$C:$C,$C10)),IF($C10="",SUMIFS(全伝票!I:I,全伝票!$A:$A,$A10,全伝票!$B:$B,$B10),SUMIFS(全伝票!I:I,全伝票!$A:$A,$A10,全伝票!$C:$C,$C10))) -> 0 | F10: =+IF($A10="",IF($C10="",SUMIFS(全伝票!J:J,全伝票!$B:$B,$B10),SUMIFS(全伝票!J:J,全伝票!$C:$C,$C10)),IF($C10="",SUMIFS(全伝票!J:J,全伝票!$A:$A,$A10,全伝票!$B:$B,$B10),SUMIFS(全伝票!J:J,全伝票!$A:$A,$A10,全伝票!$C:$C,$C10))) -> 0 | G10: =+IF($A10="",IF($C10="",SUMIFS(全伝票!K:K,全伝票!$B:$B,$B10),SUMIFS(全伝票!K:K,全伝票!$C:$C,$C10)),IF($C10="",SUMIFS(全伝票!K:K,全伝票!$A:$A,$A10,全伝票!$B:$B,$B10),SUMIFS(全伝票!K:K,全伝票!$A:$A,$A10,全伝票!$C:$C,$C10))) -> 0 | H10: =+IF($A10="",IF($C10="",SUMIFS(全伝票!L:L,全伝票!$B:$B,$B10),SUMIFS(全伝票!L:L,全伝票!$C:$C,$C10)),IF($C10="",SUMIFS(全伝票!L:L,全伝票!$A:$A,$A10,全伝票!$B:$B,$B10),SUMIFS(全伝票!L:L,全伝票!$A:$A,$A10,全伝票!$C:$C,$C10))) -> 0 | I10: =+IF($A10="",IF($C10="",SUMIFS(全伝票!M:M,全伝票!$B:$B,$B10),SUMIFS(全伝票!M:M,全伝票!$C:$C,$C10)),IF($C10="",SUMIFS(全伝票!M:M,全伝票!$A:$A,$A10,全伝票!$B:$B,$B10),SUMIFS(全伝票!M:M,全伝票!$A:$A,$A10,全伝票!$C:$C,$C10))) -> 0 | J10: =+IF($A10="",IF($C10="",SUMIFS(全伝票!N:N,全伝票!$B:$B,$B10),SUMIFS(全伝票!N:N,全伝票!$C:$C,$C10)),IF($C10="",SUMIFS(全伝票!N:N,全伝票!$A:$A,$A10,全伝票!$B:$B,$B10),SUMIFS(全伝票!N:N,全伝票!$A:$A,$A10,全伝票!$C:$C,$C10))) -> 0 | K10: =SUM(F10:J10) -> 0 | L10: =+IF($A10="",IF($C10="",SUMIFS(全伝票!O:O,全伝票!$B:$B,$B10),SUMIFS(全伝票!O:O,全伝票!$C:$C,$C10)),IF($C10="",SUMIFS(全伝票!O:O,全伝票!$A:$A,$A10,全伝票!$B:$B,$B10),SUMIFS(全伝票!O:O,全伝票!$A:$A,$A10,全伝票!$C:$C,$C10))) -> 0 | M10: =+IF($A10="",IF($C10="",SUMIFS(全伝票!P:P,全伝票!$B:$B,$B10),SUMIFS(全伝票!P:P,全伝票!$C:$C,$C10)),IF($C10="",SUMIFS(全伝票!P:P,全伝票!$A:$A,$A10,全伝票!$B:$B,$B10),SUMIFS(全伝票!P:P,全伝票!$A:$A,$A10,全伝票!$C:$C,$C10))) -> 0 | N10: =+ROUND(F10*F$4/(100+F$4),0)+AE10 -> 0 | O10: =+ROUND(G10*G$4/(100+G$4),0)+AF10 -> 0 | P10: =+ROUND(H10*H$4/(100+H$4),0)+AG10 -> 0 | Q10: =+ROUND(I10*I$4/(100+I$4),0)+AH10 -> 0 | R10: =+ROUND(J10*J$4/(100+J$4),0)+AI10 -> 0 | S10: =SUM(N10:R10) -> 0 | T10: =+E10-S10 -> 0 | U10: =N10-F10*F$4/(100+F$4) -> 0 | V10: =O10-G10*G$4/(100+G$4) -> 0 | W10: =P10-H10*H$4/(100+H$4) -> 0 | X10: =Q10-I10*I$4/(100+I$4) -> 0 | Y10: =R10-J10*J$4/(100+J$4) -> 0 | Z10: =+IF(N$38=0,0,IF(N$38<0,-RANK(U10,U$5:U$35,0),RANK(U10,U$5:U$35,1))) -> 0 | AA10: =+IF(O$38=0,0,IF(O$38<0,-RANK(V10,V$5:V$35,0),RANK(V10,V$5:V$35,1))) -> 0 | AB10: =+IF(P$38=0,0,IF(P$38<0,-RANK(W10,W$5:W$35,0),RANK(W10,W$5:W$35,1))) -> 0 | AC10: =+IF(Q$38=0,0,IF(Q$38<0,-RANK(X10,X$5:X$35,0),RANK(X10,X$5:X$35,1))) -> 0 | AD10: =+IF(R$38=0,0,IF(R$38<0,-RANK(Y10,Y$5:Y$35,0),RANK(Y10,Y$5:Y$35,1))) -> 0
A11: 1 | B11: 8830408 | D11: 報償費 | E11: =+IF($A11="",IF($C11="",SUMIFS(全伝票!I:I,全伝票!$B:$B,$B11),SUMIFS(全伝票!I:I,全伝票!$C:$C,$C11)),IF($C11="",SUMIFS(全伝票!I:I,全伝票!$A:$A,$A11,全伝票!$B:$B,$B11),SUMIFS(全伝票!I:I,全伝票!$A:$A,$A11,全伝票!$C:$C,$C11))) -> 0 | F11: =+IF($A11="",IF($C11="",SUMIFS(全伝票!J:J,全伝票!$B:$B,$B11),SUMIFS(全伝票!J:J,全伝票!$C:$C,$C11)),IF($C11="",SUMIFS(全伝票!J:J,全伝票!$A:$A,$A11,全伝票!$B:$B,$B11),SUMIFS(全伝票!J:J,全伝票!$A:$A,$A11,全伝票!$C:$C,$C11))) -> 0 | G11: =+IF($A11="",IF($C11="",SUMIFS(全伝票!K:K,全伝票!$B:$B,$B11),SUMIFS(全伝票!K:K,全伝票!$C:$C,$C11)),IF($C11="",SUMIFS(全伝票!K:K,全伝票!$A:$A,$A11,全伝票!$B:$B,$B11),SUMIFS(全伝票!K:K,全伝票!$A:$A,$A11,全伝票!$C:$C,$C11))) -> 0 | H11: =+IF($A11="",IF($C11="",SUMIFS(全伝票!L:L,全伝票!$B:$B,$B11),SUMIFS(全伝票!L:L,全伝票!$C:$C,$C11)),IF($C11="",SUMIFS(全伝票!L:L,全伝票!$A:$A,$A11,全伝票!$B:$B,$B11),SUMIFS(全伝票!L:L,全伝票!$A:$A,$A11,全伝票!$C:$C,$C11))) -> 0 | I11: =+IF($A11="",IF($C11="",SUMIFS(全伝票!M:M,全伝票!$B:$B,$B11),SUMIFS(全伝票!M:M,全伝票!$C:$C,$C11)),IF($C11="",SUMIFS(全伝票!M:M,全伝票!$A:$A,$A11,全伝票!$B:$B,$B11),SUMIFS(全伝票!M:M,全伝票!$A:$A,$A11,全伝票!$C:$C,$C11))) -> 0 | J11: =+IF($A11="",IF($C11="",SUMIFS(全伝票!N:N,全伝票!$B:$B,$B11),SUMIFS(全伝票!N:N,全伝票!$C:$C,$C11)),IF($C11="",SUMIFS(全伝票!N:N,全伝票!$A:$A,$A11,全伝票!$B:$B,$B11),SUMIFS(全伝票!N:N,全伝票!$A:$A,$A11,全伝票!$C:$C,$C11))) -> 0 | K11: =SUM(F11:J11) -> 0 | L11: =+IF($A11="",IF($C11="",SUMIFS(全伝票!O:O,全伝票!$B:$B,$B11),SUMIFS(全伝票!O:O,全伝票!$C:$C,$C11)),IF($C11="",SUMIFS(全伝票!O:O,全伝票!$A:$A,$A11,全伝票!$B:$B,$B11),SUMIFS(全伝票!O:O,全伝票!$A:$A,$A11,全伝票!$C:$C,$C11))) -> 0 | M11: =+IF($A11="",IF($C11="",SUMIFS(全伝票!P:P,全伝票!$B:$B,$B11),SUMIFS(全伝票!P:P,全伝票!$C:$C,$C11)),IF($C11="",SUMIFS(全伝票!P:P,全伝票!$A:$A,$A11,全伝票!$B:$B,$B11),SUMIFS(全伝票!P:P,全伝票!$A:$A,$A11,全伝票!$C:$C,$C11))) -> 0 | N11: =+ROUND(F11*F$4/(100+F$4),0)+AE11 -> 0 | O11: =+ROUND(G11*G$4/(100+G$4),0)+AF11 -> 0 | P11: =+ROUND(H11*H$4/(100+H$4),0)+AG11 -> 0 | Q11: =+ROUND(I11*I$4/(100+I$4),0)+AH11 -> 0 | R11: =+ROUND(J11*J$4/(100+J$4),0)+AI11 -> 0 | S11: =SUM(N11:R11) -> 0 | T11: =+E11-S11 -> 0 | U11: =N11-F11*F$4/(100+F$4) -> 0 | V11: =O11-G11*G$4/(100+G$4) -> 0 | W11: =P11-H11*H$4/(100+H$4) -> 0 | X11: =Q11-I11*I$4/(100+I$4) -> 0 | Y11: =R11-J11*J$4/(100+J$4) -> 0 | Z11: =+IF(N$38=0,0,IF(N$38<0,-RANK(U11,U$5:U$35,0),RANK(U11,U$5:U$35,1))) -> 0 | AA11: =+IF(O$38=0,0,IF(O$38<0,-RANK(V11,V$5:V$35,0),RANK(V11,V$5:V$35,1))) -> 0 | AB11: =+IF(P$38=0,0,IF(P$38<0,-RANK(W11,W$5:W$35,0),RANK(W11,W$5:W$35,1))) -> 0 | AC11: =+IF(Q$38=0,0,IF(Q$38<0,-RANK(X11,X$5:X$35,0),RANK(X11,X$5:X$35,1))) -> 0 | AD11: =+IF(R$38=0,0,IF(R$38<0,-RANK(Y11,Y$5:Y$35,0),RANK(Y11,Y$5:Y$35,1))) -> 0
A12: 1 | B12: 8830410 | C12: 883041001 | D12: 普通旅費 | E12: =+IF($A12="",IF($C12="",SUMIFS(全伝票!I:I,全伝票!$B:$B,$B12),SUMIFS(全伝票!I:I,全伝票!$C:$C,$C12)),IF($C12="",SUMIFS(全伝票!I:I,全伝票!$A:$A,$A12,全伝票!$B:$B,$B12),SUMIFS(全伝票!I:I,全伝票!$A:$A,$A12,全伝票!$C:$C,$C12))) -> 0 | F12: =+IF($A12="",IF($C12="",SUMIFS(全伝票!J:J,全伝票!$B:$B,$B12),SUMIFS(全伝票!J:J,全伝票!$C:$C,$C12)),IF($C12="",SUMIFS(全伝票!J:J,全伝票!$A:$A,$A12,全伝票!$B:$B,$B12),SUMIFS(全伝票!J:J,全伝票!$A:$A,$A12,全伝票!$C:$C,$C12))) -> 0 | G12: =+IF($A12="",IF($C12="",SUMIFS(全伝票!K:K,全伝票!$B:$B,$B12),SUMIFS(全伝票!K:K,全伝票!$C:$C,$C12)),IF($C12="",SUMIFS(全伝票!K:K,全伝票!$A:$A,$A12,全伝票!$B:$B,$B12),SUMIFS(全伝票!K:K,全伝票!$A:$A,$A12,全伝票!$C:$C,$C12))) -> 0 | H12: =+IF($A12="",IF($C12="",SUMIFS(全伝票!L:L,全伝票!$B:$B,$B12),SUMIFS(全伝票!L:L,全伝票!$C:$C,$C12)),IF($C12="",SUMIFS(全伝票!L:L,全伝票!$A:$A,$A12,全伝票!$B:$B,$B12),SUMIFS(全伝票!L:L,全伝票!$A:$A,$A12,全伝票!$C:$C,$C12))) -> 0 | I12: =+IF($A12="",IF($C12="",SUMIFS(全伝票!M:M,全伝票!$B:$B,$B12),SUMIFS(全伝票!M:M,全伝票!$C:$C,$C12)),IF($C12="",SUMIFS(全伝票!M:M,全伝票!$A:$A,$A12,全伝票!$B:$B,$B12),SUMIFS(全伝票!M:M,全伝票!$A:$A,$A12,全伝票!$C:$C,$C12))) -> 0 | J12: =+IF($A12="",IF($C12="",SUMIFS(全伝票!N:N,全伝票!$B:$B,$B12),SUMIFS(全伝票!N:N,全伝票!$C:$C,$C12)),IF($C12="",SUMIFS(全伝票!N:N,全伝票!$A:$A,$A12,全伝票!$B:$B,$B12),SUMIFS(全伝票!N:N,全伝票!$A:$A,$A12,全伝票!$C:$C,$C12))) -> 0 | K12: =SUM(F12:J12) -> 0 | L12: =+IF($A12="",IF($C12="",SUMIFS(全伝票!O:O,全伝票!$B:$B,$B12),SUMIFS(全伝票!O:O,全伝票!$C:$C,$C12)),IF($C12="",SUMIFS(全伝票!O:O,全伝票!$A:$A,$A12,全伝票!$B:$B,$B12),SUMIFS(全伝票!O:O,全伝票!$A:$A,$A12,全伝票!$C:$C,$C12))) -> 0 | M12: =+IF($A12="",IF($C12="",SUMIFS(全伝票!P:P,全伝票!$B:$B,$B12),SUMIFS(全伝票!P:P,全伝票!$C:$C,$C12)),IF($C12="",SUMIFS(全伝票!P:P,全伝票!$A:$A,$A12,全伝票!$B:$B,$B12),SUMIFS(全伝票!P:P,全伝票!$A:$A,$A12,全伝票!$C:$C,$C12))) -> 0 | N12: =+ROUND(F12*F$4/(100+F$4),0)+AE12 -> 0 | O12: =+ROUND(G12*G$4/(100+G$4),0)+AF12 -> 0 | P12: =+ROUND(H12*H$4/(100+H$4),0)+AG12 -> 0 | Q12: =+ROUND(I12*I$4/(100+I$4),0)+AH12 -> 0 | R12: =+ROUND(J12*J$4/(100+J$4),0)+AI12 -> 0 | S12: =SUM(N12:R12) -> 0 | T12: =+E12-S12 -> 0 | U12: =N12-F12*F$4/(100+F$4) -> 0 | V12: =O12-G12*G$4/(100+G$4) -> 0 | W12: =P12-H12*H$4/(100+H$4) -> 0 | X12: =Q12-I12*I$4/(100+I$4) -> 0 | Y12: =R12-J12*J$4/(100+J$4) -> 0 | Z12: =+IF(N$38=0,0,IF(N$38<0,-RANK(U12,U$5:U$35,0),RANK(U12,U$5:U$35,1))) -> 0 | AA12: =+IF(O$38=0,0,IF(O$38<0,-RANK(V12,V$5:V$35,0),RANK(V12,V$5:V$35,1))) -> 0 | AB12: =+IF(P$38=0,0,IF(P$38<0,-RANK(W12,W$5:W$35,0),RANK(W12,W$5:W$35,1))) -> 0 | AC12: =+IF(Q$38=0,0,IF(Q$38<0,-RANK(X12,X$5:X$35,0),RANK(X12,X$5:X$35,1))) -> 0 | AD12: =+IF(R$38=0,0,IF(R$38<0,-RANK(Y12,Y$5:Y$35,0),RANK(Y12,Y$5:Y$35,1))) -> 0
A13: 1 | B13: 8830410 | C13: 883041002 | D13: 特別旅費 | E13: =+IF($A13="",IF($C13="",SUMIFS(全伝票!I:I,全伝票!$B:$B,$B13),SUMIFS(全伝票!I:I,全伝票!$C:$C,$C13)),IF($C13="",SUMIFS(全伝票!I:I,全伝票!$A:$A,$A13,全伝票!$B:$B,$B13),SUMIFS(全伝票!I:I,全伝票!$A:$A,$A13,全伝票!$C:$C,$C13))) -> 0 | F13: =+IF($A13="",IF($C13="",SUMIFS(全伝票!J:J,全伝票!$B:$B,$B13),SUMIFS(全伝票!J:J,全伝票!$C:$C,$C13)),IF($C13="",SUMIFS(全伝票!J:J,全伝票!$A:$A,$A13,全伝票!$B:$B,$B13),SUMIFS(全伝票!J:J,全伝票!$A:$A,$A13,全伝票!$C:$C,$C13))) -> 0 | G13: =+IF($A13="",IF($C13="",SUMIFS(全伝票!K:K,全伝票!$B:$B,$B13),SUMIFS(全伝票!K:K,全伝票!$C:$C,$C13)),IF($C13="",SUMIFS(全伝票!K:K,全伝票!$A:$A,$A13,全伝票!$B:$B,$B13),SUMIFS(全伝票!K:K,全伝票!$A:$A,$A13,全伝票!$C:$C,$C13))) -> 0 | H13: =+IF($A13="",IF($C13="",SUMIFS(全伝票!L:L,全伝票!$B:$B,$B13),SUMIFS(全伝票!L:L,全伝票!$C:$C,$C13)),IF($C13="",SUMIFS(全伝票!L:L,全伝票!$A:$A,$A13,全伝票!$B:$B,$B13),SUMIFS(全伝票!L:L,全伝票!$A:$A,$A13,全伝票!$C:$C,$C13))) -> 0 | I13: =+IF($A13="",IF($C13="",SUMIFS(全伝票!M:M,全伝票!$B:$B,$B13),SUMIFS(全伝票!M:M,全伝票!$C:$C,$C13)),IF($C13="",SUMIFS(全伝票!M:M,全伝票!$A:$A,$A13,全伝票!$B:$B,$B13),SUMIFS(全伝票!M:M,全伝票!$A:$A,$A13,全伝票!$C:$C,$C13))) -> 0 | J13: =+IF($A13="",IF($C13="",SUMIFS(全伝票!N:N,全伝票!$B:$B,$B13),SUMIFS(全伝票!N:N,全伝票!$C:$C,$C13)),IF($C13="",SUMIFS(全伝票!N:N,全伝票!$A:$A,$A13,全伝票!$B:$B,$B13),SUMIFS(全伝票!N:N,全伝票!$A:$A,$A13,全伝票!$C:$C,$C13))) -> 0 | K13: =SUM(F13:J13) -> 0 | L13: =+IF($A13="",IF($C13="",SUMIFS(全伝票!O:O,全伝票!$B:$B,$B13),SUMIFS(全伝票!O:O,全伝票!$C:$C,$C13)),IF($C13="",SUMIFS(全伝票!O:O,全伝票!$A:$A,$A13,全伝票!$B:$B,$B13),SUMIFS(全伝票!O:O,全伝票!$A:$A,$A13,全伝票!$C:$C,$C13))) -> 0 | M13: =+IF($A13="",IF($C13="",SUMIFS(全伝票!P:P,全伝票!$B:$B,$B13),SUMIFS(全伝票!P:P,全伝票!$C:$C,$C13)),IF($C13="",SUMIFS(全伝票!P:P,全伝票!$A:$A,$A13,全伝票!$B:$B,$B13),SUMIFS(全伝票!P:P,全伝票!$A:$A,$A13,全伝票!$C:$C,$C13))) -> 0 | N13: =+ROUND(F13*F$4/(100+F$4),0)+AE13 -> 0 | O13: =+ROUND(G13*G$4/(100+G$4),0)+AF13 -> 0 | P13: =+ROUND(H13*H$4/(100+H$4),0)+AG13 -> 0 | Q13: =+ROUND(I13*I$4/(100+I$4),0)+AH13 -> 0 | R13: =+ROUND(J13*J$4/(100+J$4),0)+AI13 -> 0 | S13: =SUM(N13:R13) -> 0 | T13: =+E13-S13 -> 0 | U13: =N13-F13*F$4/(100+F$4) -> 0 | V13: =O13-G13*G$4/(100+G$4) -> 0 | W13: =P13-H13*H$4/(100+H$4) -> 0 | X13: =Q13-I13*I$4/(100+I$4) -> 0 | Y13: =R13-J13*J$4/(100+J$4) -> 0 | Z13: =+IF(N$38=0,0,IF(N$38<0,-RANK(U13,U$5:U$35,0),RANK(U13,U$5:U$35,1))) -> 0 | AA13: =+IF(O$38=0,0,IF(O$38<0,-RANK(V13,V$5:V$35,0),RANK(V13,V$5:V$35,1))) -> 0 | AB13: =+IF(P$38=0,0,IF(P$38<0,-RANK(W13,W$5:W$35,0),RANK(W13,W$5:W$35,1))) -> 0 | AC13: =+IF(Q$38=0,0,IF(Q$38<0,-RANK(X13,X$5:X$35,0),RANK(X13,X$5:X$35,1))) -> 0 | AD13: =+IF(R$38=0,0,IF(R$38<0,-RANK(Y13,Y$5:Y$35,0),RANK(Y13,Y$5:Y$35,1))) -> 0
A14: 1 | B14: 8830413 | D14: 備消品費 | E14: =+IF($A14="",IF($C14="",SUMIFS(全伝票!I:I,全伝票!$B:$B,$B14),SUMIFS(全伝票!I:I,全伝票!$C:$C,$C14)),IF($C14="",SUMIFS(全伝票!I:I,全伝票!$A:$A,$A14,全伝票!$B:$B,$B14),SUMIFS(全伝票!I:I,全伝票!$A:$A,$A14,全伝票!$C:$C,$C14))) -> 123964 | F14: =+IF($A14="",IF($C14="",SUMIFS(全伝票!J:J,全伝票!$B:$B,$B14),SUMIFS(全伝票!J:J,全伝票!$C:$C,$C14)),IF($C14="",SUMIFS(全伝票!J:J,全伝票!$A:$A,$A14,全伝票!$B:$B,$B14),SUMIFS(全伝票!J:J,全伝票!$A:$A,$A14,全伝票!$C:$C,$C14))) -> 0 | G14: =+IF($A14="",IF($C14="",SUMIFS(全伝票!K:K,全伝票!$B:$B,$B14),SUMIFS(全伝票!K:K,全伝票!$C:$C,$C14)),IF($C14="",SUMIFS(全伝票!K:K,全伝票!$A:$A,$A14,全伝票!$B:$B,$B14),SUMIFS(全伝票!K:K,全伝票!$A:$A,$A14,全伝票!$C:$C,$C14))) -> 0 | H14: =+IF($A14="",IF($C14="",SUMIFS(全伝票!L:L,全伝票!$B:$B,$B14),SUMIFS(全伝票!L:L,全伝票!$C:$C,$C14)),IF($C14="",SUMIFS(全伝票!L:L,全伝票!$A:$A,$A14,全伝票!$B:$B,$B14),SUMIFS(全伝票!L:L,全伝票!$A:$A,$A14,全伝票!$C:$C,$C14))) -> 0 | I14: =+IF($A14="",IF($C14="",SUMIFS(全伝票!M:M,全伝票!$B:$B,$B14),SUMIFS(全伝票!M:M,全伝票!$C:$C,$C14)),IF($C14="",SUMIFS(全伝票!M:M,全伝票!$A:$A,$A14,全伝票!$B:$B,$B14),SUMIFS(全伝票!M:M,全伝票!$A:$A,$A14,全伝票!$C:$C,$C14))) -> 0 | J14: =+IF($A14="",IF($C14="",SUMIFS(全伝票!N:N,全伝票!$B:$B,$B14),SUMIFS(全伝票!N:N,全伝票!$C:$C,$C14)),IF($C14="",SUMIFS(全伝票!N:N,全伝票!$A:$A,$A14,全伝票!$B:$B,$B14),SUMIFS(全伝票!N:N,全伝票!$A:$A,$A14,全伝票!$C:$C,$C14))) -> 123964 | K14: =SUM(F14:J14) -> 123964 | L14: =+IF($A14="",IF($C14="",SUMIFS(全伝票!O:O,全伝票!$B:$B,$B14),SUMIFS(全伝票!O:O,全伝票!$C:$C,$C14)),IF($C14="",SUMIFS(全伝票!O:O,全伝票!$A:$A,$A14,全伝票!$B:$B,$B14),SUMIFS(全伝票!O:O,全伝票!$A:$A,$A14,全伝票!$C:$C,$C14))) -> 0 | M14: =+IF($A14="",IF($C14="",SUMIFS(全伝票!P:P,全伝票!$B:$B,$B14),SUMIFS(全伝票!P:P,全伝票!$C:$C,$C14)),IF($C14="",SUMIFS(全伝票!P:P,全伝票!$A:$A,$A14,全伝票!$B:$B,$B14),SUMIFS(全伝票!P:P,全伝票!$A:$A,$A14,全伝票!$C:$C,$C14))) -> 0 | N14: =+ROUND(F14*F$4/(100+F$4),0)+AE14 -> 0 | O14: =+ROUND(G14*G$4/(100+G$4),0)+AF14 -> 0 | P14: =+ROUND(H14*H$4/(100+H$4),0)+AG14 -> 0 | Q14: =+ROUND(I14*I$4/(100+I$4),0)+AH14 -> 0 | R14: =+ROUND(J14*J$4/(100+J$4),0)+AI14 -> 11269 | S14: =SUM(N14:R14) -> 11269 | T14: =+E14-S14 -> 112695 | U14: =N14-F14*F$4/(100+F$4) -> 0 | V14: =O14-G14*G$4/(100+G$4) -> 0 | W14: =P14-H14*H$4/(100+H$4) -> 0 | X14: =Q14-I14*I$4/(100+I$4) -> 0 | Y14: =R14-J14*J$4/(100+J$4) -> -0.45454545 | Z14: =+IF(N$38=0,0,IF(N$38<0,-RANK(U14,U$5:U$35,0),RANK(U14,U$5:U$35,1))) -> 0 | AA14: =+IF(O$38=0,0,IF(O$38<0,-RANK(V14,V$5:V$35,0),RANK(V14,V$5:V$35,1))) -> 0 | AB14: =+IF(P$38=0,0,IF(P$38<0,-RANK(W14,W$5:W$35,0),RANK(W14,W$5:W$35,1))) -> 0 | AC14: =+IF(Q$38=0,0,IF(Q$38<0,-RANK(X14,X$5:X$35,0),RANK(X14,X$5:X$35,1))) -> 0 | AD14: =+IF(R$38=0,0,IF(R$38<0,-RANK(Y14,Y$5:Y$35,0),RANK(Y14,Y$5:Y$35,1))) -> 0
A15: 1 | B15: 8830414 | D15: 燃料費 | E15: =+IF($A15="",IF($C15="",SUMIFS(全伝票!I:I,全伝票!$B:$B,$B15),SUMIFS(全伝票!I:I,全伝票!$C:$C,$C15)),IF($C15="",SUMIFS(全伝票!I:I,全伝票!$A:$A,$A15,全伝票!$B:$B,$B15),SUMIFS(全伝票!I:I,全伝票!$A:$A,$A15,全伝票!$C:$C,$C15))) -> 67172 | F15: =+IF($A15="",IF($C15="",SUMIFS(全伝票!J:J,全伝票!$B:$B,$B15),SUMIFS(全伝票!J:J,全伝票!$C:$C,$C15)),IF($C15="",SUMIFS(全伝票!J:J,全伝票!$A:$A,$A15,全伝票!$B:$B,$B15),SUMIFS(全伝票!J:J,全伝票!$A:$A,$A15,全伝票!$C:$C,$C15))) -> 0 | G15: =+IF($A15="",IF($C15="",SUMIFS(全伝票!K:K,全伝票!$B:$B,$B15),SUMIFS(全伝票!K:K,全伝票!$C:$C,$C15)),IF($C15="",SUMIFS(全伝票!K:K,全伝票!$A:$A,$A15,全伝票!$B:$B,$B15),SUMIFS(全伝票!K:K,全伝票!$A:$A,$A15,全伝票!$C:$C,$C15))) -> 0 | H15: =+IF($A15="",IF($C15="",SUMIFS(全伝票!L:L,全伝票!$B:$B,$B15),SUMIFS(全伝票!L:L,全伝票!$C:$C,$C15)),IF($C15="",SUMIFS(全伝票!L:L,全伝票!$A:$A,$A15,全伝票!$B:$B,$B15),SUMIFS(全伝票!L:L,全伝票!$A:$A,$A15,全伝票!$C:$C,$C15))) -> 0 | I15: =+IF($A15="",IF($C15="",SUMIFS(全伝票!M:M,全伝票!$B:$B,$B15),SUMIFS(全伝票!M:M,全伝票!$C:$C,$C15)),IF($C15="",SUMIFS(全伝票!M:M,全伝票!$A:$A,$A15,全伝票!$B:$B,$B15),SUMIFS(全伝票!M:M,全伝票!$A:$A,$A15,全伝票!$C:$C,$C15))) -> 0 | J15: =+IF($A15="",IF($C15="",SUMIFS(全伝票!N:N,全伝票!$B:$B,$B15),SUMIFS(全伝票!N:N,全伝票!$C:$C,$C15)),IF($C15="",SUMIFS(全伝票!N:N,全伝票!$A:$A,$A15,全伝票!$B:$B,$B15),SUMIFS(全伝票!N:N,全伝票!$A:$A,$A15,全伝票!$C:$C,$C15))) -> 67172 | K15: =SUM(F15:J15) -> 67172 | L15: =+IF($A15="",IF($C15="",SUMIFS(全伝票!O:O,全伝票!$B:$B,$B15),SUMIFS(全伝票!O:O,全伝票!$C:$C,$C15)),IF($C15="",SUMIFS(全伝票!O:O,全伝票!$A:$A,$A15,全伝票!$B:$B,$B15),SUMIFS(全伝票!O:O,全伝票!$A:$A,$A15,全伝票!$C:$C,$C15))) -> 0 | M15: =+IF($A15="",IF($C15="",SUMIFS(全伝票!P:P,全伝票!$B:$B,$B15),SUMIFS(全伝票!P:P,全伝票!$C:$C,$C15)),IF($C15="",SUMIFS(全伝票!P:P,全伝票!$A:$A,$A15,全伝票!$B:$B,$B15),SUMIFS(全伝票!P:P,全伝票!$A:$A,$A15,全伝票!$C:$C,$C15))) -> 0 | N15: =+ROUND(F15*F$4/(100+F$4),0)+AE15 -> 0 | O15: =+ROUND(G15*G$4/(100+G$4),0)+AF15 -> 0 | P15: =+ROUND(H15*H$4/(100+H$4),0)+AG15 -> 0 | Q15: =+ROUND(I15*I$4/(100+I$4),0)+AH15 -> 0 | R15: =+ROUND(J15*J$4/(100+J$4),0)+AI15 -> 6107 | S15: =SUM(N15:R15) -> 6107 | T15: =+E15-S15 -> 61065 | U15: =N15-F15*F$4/(100+F$4) -> 0 | V15: =O15-G15*G$4/(100+G$4) -> 0 | W15: =P15-H15*H$4/(100+H$4) -> 0 | X15: =Q15-I15*I$4/(100+I$4) -> 0 | Y15: =R15-J15*J$4/(100+J$4) -> 0.45454545 | Z15: =+IF(N$38=0,0,IF(N$38<0,-RANK(U15,U$5:U$35,0),RANK(U15,U$5:U$35,1))) -> 0 | AA15: =+IF(O$38=0,0,IF(O$38<0,-RANK(V15,V$5:V$35,0),RANK(V15,V$5:V$35,1))) -> 0 | AB15: =+IF(P$38=0,0,IF(P$38<0,-RANK(W15,W$5:W$35,0),RANK(W15,W$5:W$35,1))) -> 0 | AC15: =+IF(Q$38=0,0,IF(Q$38<0,-RANK(X15,X$5:X$35,0),RANK(X15,X$5:X$35,1))) -> 0 | AD15: =+IF(R$38=0,0,IF(R$38<0,-RANK(Y15,Y$5:Y$35,0),RANK(Y15,Y$5:Y$35,1))) -> 0
A16: 1 | B16: 8830415 | D16: 光熱水費 | E16: =+IF($A16="",IF($C16="",SUMIFS(全伝票!I:I,全伝票!$B:$B,$B16),SUMIFS(全伝票!I:I,全伝票!$C:$C,$C16)),IF($C16="",SUMIFS(全伝票!I:I,全伝票!$A:$A,$A16,全伝票!$B:$B,$B16),SUMIFS(全伝票!I:I,全伝票!$A:$A,$A16,全伝票!$C:$C,$C16))) -> 0 | F16: =+IF($A16="",IF($C16="",SUMIFS(全伝票!J:J,全伝票!$B:$B,$B16),SUMIFS(全伝票!J:J,全伝票!$C:$C,$C16)),IF($C16="",SUMIFS(全伝票!J:J,全伝票!$A:$A,$A16,全伝票!$B:$B,$B16),SUMIFS(全伝票!J:J,全伝票!$A:$A,$A16,全伝票!$C:$C,$C16))) -> 0 | G16: =+IF($A16="",IF($C16="",SUMIFS(全伝票!K:K,全伝票!$B:$B,$B16),SUMIFS(全伝票!K:K,全伝票!$C:$C,$C16)),IF($C16="",SUMIFS(全伝票!K:K,全伝票!$A:$A,$A16,全伝票!$B:$B,$B16),SUMIFS(全伝票!K:K,全伝票!$A:$A,$A16,全伝票!$C:$C,$C16))) -> 0 | H16: =+IF($A16="",IF($C16="",SUMIFS(全伝票!L:L,全伝票!$B:$B,$B16),SUMIFS(全伝票!L:L,全伝票!$C:$C,$C16)),IF($C16="",SUMIFS(全伝票!L:L,全伝票!$A:$A,$A16,全伝票!$B:$B,$B16),SUMIFS(全伝票!L:L,全伝票!$A:$A,$A16,全伝票!$C:$C,$C16))) -> 0 | I16: =+IF($A16="",IF($C16="",SUMIFS(全伝票!M:M,全伝票!$B:$B,$B16),SUMIFS(全伝票!M:M,全伝票!$C:$C,$C16)),IF($C16="",SUMIFS(全伝票!M:M,全伝票!$A:$A,$A16,全伝票!$B:$B,$B16),SUMIFS(全伝票!M:M,全伝票!$A:$A,$A16,全伝票!$C:$C,$C16))) -> 0 | J16: =+IF($A16="",IF($C16="",SUMIFS(全伝票!N:N,全伝票!$B:$B,$B16),SUMIFS(全伝票!N:N,全伝票!$C:$C,$C16)),IF($C16="",SUMIFS(全伝票!N:N,全伝票!$A:$A,$A16,全伝票!$B:$B,$B16),SUMIFS(全伝票!N:N,全伝票!$A:$A,$A16,全伝票!$C:$C,$C16))) -> 0 | K16: =SUM(F16:J16) -> 0 | L16: =+IF($A16="",IF($C16="",SUMIFS(全伝票!O:O,全伝票!$B:$B,$B16),SUMIFS(全伝票!O:O,全伝票!$C:$C,$C16)),IF($C16="",SUMIFS(全伝票!O:O,全伝票!$A:$A,$A16,全伝票!$B:$B,$B16),SUMIFS(全伝票!O:O,全伝票!$A:$A,$A16,全伝票!$C:$C,$C16))) -> 0 | M16: =+IF($A16="",IF($C16="",SUMIFS(全伝票!P:P,全伝票!$B:$B,$B16),SUMIFS(全伝票!P:P,全伝票!$C:$C,$C16)),IF($C16="",SUMIFS(全伝票!P:P,全伝票!$A:$A,$A16,全伝票!$B:$B,$B16),SUMIFS(全伝票!P:P,全伝票!$A:$A,$A16,全伝票!$C:$C,$C16))) -> 0 | N16: =+ROUND(F16*F$4/(100+F$4),0)+AE16 -> 0 | O16: =+ROUND(G16*G$4/(100+G$4),0)+AF16 -> 0 | P16: =+ROUND(H16*H$4/(100+H$4),0)+AG16 -> 0 | Q16: =+ROUND(I16*I$4/(100+I$4),0)+AH16 -> 0 | R16: =+ROUND(J16*J$4/(100+J$4),0)+AI16 -> 0 | S16: =SUM(N16:R16) -> 0 | T16: =+E16-S16 -> 0 | U16: =N16-F16*F$4/(100+F$4) -> 0 | V16: =O16-G16*G$4/(100+G$4) -> 0 | W16: =P16-H16*H$4/(100+H$4) -> 0 | X16: =Q16-I16*I$4/(100+I$4) -> 0 | Y16: =R16-J16*J$4/(100+J$4) -> 0 | Z16: =+IF(N$38=0,0,IF(N$38<0,-RANK(U16,U$5:U$35,0),RANK(U16,U$5:U$35,1))) -> 0 | AA16: =+IF(O$38=0,0,IF(O$38<0,-RANK(V16,V$5:V$35,0),RANK(V16,V$5:V$35,1))) -> 0 | AB16: =+IF(P$38=0,0,IF(P$38<0,-RANK(W16,W$5:W$35,0),RANK(W16,W$5:W$35,1))) -> 0 | AC16: =+IF(Q$38=0,0,IF(Q$38<0,-RANK(X16,X$5:X$35,0),RANK(X16,X$5:X$35,1))) -> 0 | AD16: =+IF(R$38=0,0,IF(R$38<0,-RANK(Y16,Y$5:Y$35,0),RANK(Y16,Y$5:Y$35,1))) -> 0
A17: 1 | B17: 8830417 | D17: 通信運搬費 | E17: =+IF($A17="",IF($C17="",SUMIFS(全伝票!I:I,全伝票!$B:$B,$B17),SUMIFS(全伝票!I:I,全伝票!$C:$C,$C17)),IF($C17="",SUMIFS(全伝票!I:I,全伝票!$A:$A,$A17,全伝票!$B:$B,$B17),SUMIFS(全伝票!I:I,全伝票!$A:$A,$A17,全伝票!$C:$C,$C17))) -> 87858 | F17: =+IF($A17="",IF($C17="",SUMIFS(全伝票!J:J,全伝票!$B:$B,$B17),SUMIFS(全伝票!J:J,全伝票!$C:$C,$C17)),IF($C17="",SUMIFS(全伝票!J:J,全伝票!$A:$A,$A17,全伝票!$B:$B,$B17),SUMIFS(全伝票!J:J,全伝票!$A:$A,$A17,全伝票!$C:$C,$C17))) -> 0 | G17: =+IF($A17="",IF($C17="",SUMIFS(全伝票!K:K,全伝票!$B:$B,$B17),SUMIFS(全伝票!K:K,全伝票!$C:$C,$C17)),IF($C17="",SUMIFS(全伝票!K:K,全伝票!$A:$A,$A17,全伝票!$B:$B,$B17),SUMIFS(全伝票!K:K,全伝票!$A:$A,$A17,全伝票!$C:$C,$C17))) -> 0 | H17: =+IF($A17="",IF($C17="",SUMIFS(全伝票!L:L,全伝票!$B:$B,$B17),SUMIFS(全伝票!L:L,全伝票!$C:$C,$C17)),IF($C17="",SUMIFS(全伝票!L:L,全伝票!$A:$A,$A17,全伝票!$B:$B,$B17),SUMIFS(全伝票!L:L,全伝票!$A:$A,$A17,全伝票!$C:$C,$C17))) -> 0 | I17: =+IF($A17="",IF($C17="",SUMIFS(全伝票!M:M,全伝票!$B:$B,$B17),SUMIFS(全伝票!M:M,全伝票!$C:$C,$C17)),IF($C17="",SUMIFS(全伝票!M:M,全伝票!$A:$A,$A17,全伝票!$B:$B,$B17),SUMIFS(全伝票!M:M,全伝票!$A:$A,$A17,全伝票!$C:$C,$C17))) -> 0 | J17: =+IF($A17="",IF($C17="",SUMIFS(全伝票!N:N,全伝票!$B:$B,$B17),SUMIFS(全伝票!N:N,全伝票!$C:$C,$C17)),IF($C17="",SUMIFS(全伝票!N:N,全伝票!$A:$A,$A17,全伝票!$B:$B,$B17),SUMIFS(全伝票!N:N,全伝票!$A:$A,$A17,全伝票!$C:$C,$C17))) -> 87858 | K17: =SUM(F17:J17) -> 87858 | L17: =+IF($A17="",IF($C17="",SUMIFS(全伝票!O:O,全伝票!$B:$B,$B17),SUMIFS(全伝票!O:O,全伝票!$C:$C,$C17)),IF($C17="",SUMIFS(全伝票!O:O,全伝票!$A:$A,$A17,全伝票!$B:$B,$B17),SUMIFS(全伝票!O:O,全伝票!$A:$A,$A17,全伝票!$C:$C,$C17))) -> 0 | M17: =+IF($A17="",IF($C17="",SUMIFS(全伝票!P:P,全伝票!$B:$B,$B17),SUMIFS(全伝票!P:P,全伝票!$C:$C,$C17)),IF($C17="",SUMIFS(全伝票!P:P,全伝票!$A:$A,$A17,全伝票!$B:$B,$B17),SUMIFS(全伝票!P:P,全伝票!$A:$A,$A17,全伝票!$C:$C,$C17))) -> 0 | N17: =+ROUND(F17*F$4/(100+F$4),0)+AE17 -> 0 | O17: =+ROUND(G17*G$4/(100+G$4),0)+AF17 -> 0 | P17: =+ROUND(H17*H$4/(100+H$4),0)+AG17 -> 0 | Q17: =+ROUND(I17*I$4/(100+I$4),0)+AH17 -> 0 | R17: =+ROUND(J17*J$4/(100+J$4),0)+AI17 -> 7987 | S17: =SUM(N17:R17) -> 7987 | T17: =+E17-S17 -> 79871 | U17: =N17-F17*F$4/(100+F$4) -> 0 | V17: =O17-G17*G$4/(100+G$4) -> 0 | W17: =P17-H17*H$4/(100+H$4) -> 0 | X17: =Q17-I17*I$4/(100+I$4) -> 0 | Y17: =R17-J17*J$4/(100+J$4) -> -0.090909091 | Z17: =+IF(N$38=0,0,IF(N$38<0,-RANK(U17,U$5:U$35,0),RANK(U17,U$5:U$35,1))) -> 0 | AA17: =+IF(O$38=0,0,IF(O$38<0,-RANK(V17,V$5:V$35,0),RANK(V17,V$5:V$35,1))) -> 0 | AB17: =+IF(P$38=0,0,IF(P$38<0,-RANK(W17,W$5:W$35,0),RANK(W17,W$5:W$35,1))) -> 0 | AC17: =+IF(Q$38=0,0,IF(Q$38<0,-RANK(X17,X$5:X$35,0),RANK(X17,X$5:X$35,1))) -> 0 | AD17: =+IF(R$38=0,0,IF(R$38<0,-RANK(Y17,Y$5:Y$35,0),RANK(Y17,Y$5:Y$35,1))) -> 0
A18: 1 | B18: 8830419 | D18: 手数料 | E18: =+IF($A18="",IF($C18="",SUMIFS(全伝票!I:I,全伝票!$B:$B,$B18),SUMIFS(全伝票!I:I,全伝票!$C:$C,$C18)),IF($C18="",SUMIFS(全伝票!I:I,全伝票!$A:$A,$A18,全伝票!$B:$B,$B18),SUMIFS(全伝票!I:I,全伝票!$A:$A,$A18,全伝票!$C:$C,$C18))) -> 0 | F18: =+IF($A18="",IF($C18="",SUMIFS(全伝票!J:J,全伝票!$B:$B,$B18),SUMIFS(全伝票!J:J,全伝票!$C:$C,$C18)),IF($C18="",SUMIFS(全伝票!J:J,全伝票!$A:$A,$A18,全伝票!$B:$B,$B18),SUMIFS(全伝票!J:J,全伝票!$A:$A,$A18,全伝票!$C:$C,$C18))) -> 0 | G18: =+IF($A18="",IF($C18="",SUMIFS(全伝票!K:K,全伝票!$B:$B,$B18),SUMIFS(全伝票!K:K,全伝票!$C:$C,$C18)),IF($C18="",SUMIFS(全伝票!K:K,全伝票!$A:$A,$A18,全伝票!$B:$B,$B18),SUMIFS(全伝票!K:K,全伝票!$A:$A,$A18,全伝票!$C:$C,$C18))) -> 0 | H18: =+IF($A18="",IF($C18="",SUMIFS(全伝票!L:L,全伝票!$B:$B,$B18),SUMIFS(全伝票!L:L,全伝票!$C:$C,$C18)),IF($C18="",SUMIFS(全伝票!L:L,全伝票!$A:$A,$A18,全伝票!$B:$B,$B18),SUMIFS(全伝票!L:L,全伝票!$A:$A,$A18,全伝票!$C:$C,$C18))) -> 0 | I18: =+IF($A18="",IF($C18="",SUMIFS(全伝票!M:M,全伝票!$B:$B,$B18),SUMIFS(全伝票!M:M,全伝票!$C:$C,$C18)),IF($C18="",SUMIFS(全伝票!M:M,全伝票!$A:$A,$A18,全伝票!$B:$B,$B18),SUMIFS(全伝票!M:M,全伝票!$A:$A,$A18,全伝票!$C:$C,$C18))) -> 0 | J18: =+IF($A18="",IF($C18="",SUMIFS(全伝票!N:N,全伝票!$B:$B,$B18),SUMIFS(全伝票!N:N,全伝票!$C:$C,$C18)),IF($C18="",SUMIFS(全伝票!N:N,全伝票!$A:$A,$A18,全伝票!$B:$B,$B18),SUMIFS(全伝票!N:N,全伝票!$A:$A,$A18,全伝票!$C:$C,$C18))) -> 0 | K18: =SUM(F18:J18) -> 0 | L18: =+IF($A18="",IF($C18="",SUMIFS(全伝票!O:O,全伝票!$B:$B,$B18),SUMIFS(全伝票!O:O,全伝票!$C:$C,$C18)),IF($C18="",SUMIFS(全伝票!O:O,全伝票!$A:$A,$A18,全伝票!$B:$B,$B18),SUMIFS(全伝票!O:O,全伝票!$A:$A,$A18,全伝票!$C:$C,$C18))) -> 0 | M18: =+IF($A18="",IF($C18="",SUMIFS(全伝票!P:P,全伝票!$B:$B,$B18),SUMIFS(全伝票!P:P,全伝票!$C:$C,$C18)),IF($C18="",SUMIFS(全伝票!P:P,全伝票!$A:$A,$A18,全伝票!$B:$B,$B18),SUMIFS(全伝票!P:P,全伝票!$A:$A,$A18,全伝票!$C:$C,$C18))) -> 0 | N18: =+ROUND(F18*F$4/(100+F$4),0)+AE18 -> 0 | O18: =+ROUND(G18*G$4/(100+G$4),0)+AF18 -> 0 | P18: =+ROUND(H18*H$4/(100+H$4),0)+AG18 -> 0 | Q18: =+ROUND(I18*I$4/(100+I$4),0)+AH18 -> 0 | R18: =+ROUND(J18*J$4/(100+J$4),0)+AI18 -> 0 | S18: =SUM(N18:R18) -> 0 | T18: =+E18-S18 -> 0 | U18: =N18-F18*F$4/(100+F$4) -> 0 | V18: =O18-G18*G$4/(100+G$4) -> 0 | W18: =P18-H18*H$4/(100+H$4) -> 0 | X18: =Q18-I18*I$4/(100+I$4) -> 0 | Y18: =R18-J18*J$4/(100+J$4) -> 0 | Z18: =+IF(N$38=0,0,IF(N$38<0,-RANK(U18,U$5:U$35,0),RANK(U18,U$5:U$35,1))) -> 0 | AA18: =+IF(O$38=0,0,IF(O$38<0,-RANK(V18,V$5:V$35,0),RANK(V18,V$5:V$35,1))) -> 0 | AB18: =+IF(P$38=0,0,IF(P$38<0,-RANK(W18,W$5:W$35,0),RANK(W18,W$5:W$35,1))) -> 0 | AC18: =+IF(Q$38=0,0,IF(Q$38<0,-RANK(X18,X$5:X$35,0),RANK(X18,X$5:X$35,1))) -> 0 | AD18: =+IF(R$38=0,0,IF(R$38<0,-RANK(Y18,Y$5:Y$35,0),RANK(Y18,Y$5:Y$35,1))) -> 0
A19: 1 | B19: 8830420 | D19: 賃借料 | E19: =+IF($A19="",IF($C19="",SUMIFS(全伝票!I:I,全伝票!$B:$B,$B19),SUMIFS(全伝票!I:I,全伝票!$C:$C,$C19)),IF($C19="",SUMIFS(全伝票!I:I,全伝票!$A:$A,$A19,全伝票!$B:$B,$B19),SUMIFS(全伝票!I:I,全伝票!$A:$A,$A19,全伝票!$C:$C,$C19))) -> 1820 | F19: =+IF($A19="",IF($C19="",SUMIFS(全伝票!J:J,全伝票!$B:$B,$B19),SUMIFS(全伝票!J:J,全伝票!$C:$C,$C19)),IF($C19="",SUMIFS(全伝票!J:J,全伝票!$A:$A,$A19,全伝票!$B:$B,$B19),SUMIFS(全伝票!J:J,全伝票!$A:$A,$A19,全伝票!$C:$C,$C19))) -> 0 | G19: =+IF($A19="",IF($C19="",SUMIFS(全伝票!K:K,全伝票!$B:$B,$B19),SUMIFS(全伝票!K:K,全伝票!$C:$C,$C19)),IF($C19="",SUMIFS(全伝票!K:K,全伝票!$A:$A,$A19,全伝票!$B:$B,$B19),SUMIFS(全伝票!K:K,全伝票!$A:$A,$A19,全伝票!$C:$C,$C19))) -> 0 | H19: =+IF($A19="",IF($C19="",SUMIFS(全伝票!L:L,全伝票!$B:$B,$B19),SUMIFS(全伝票!L:L,全伝票!$C:$C,$C19)),IF($C19="",SUMIFS(全伝票!L:L,全伝票!$A:$A,$A19,全伝票!$B:$B,$B19),SUMIFS(全伝票!L:L,全伝票!$A:$A,$A19,全伝票!$C:$C,$C19))) -> 0 | I19: =+IF($A19="",IF($C19="",SUMIFS(全伝票!M:M,全伝票!$B:$B,$B19),SUMIFS(全伝票!M:M,全伝票!$C:$C,$C19)),IF($C19="",SUMIFS(全伝票!M:M,全伝票!$A:$A,$A19,全伝票!$B:$B,$B19),SUMIFS(全伝票!M:M,全伝票!$A:$A,$A19,全伝票!$C:$C,$C19))) -> 0 | J19: =+IF($A19="",IF($C19="",SUMIFS(全伝票!N:N,全伝票!$B:$B,$B19),SUMIFS(全伝票!N:N,全伝票!$C:$C,$C19)),IF($C19="",SUMIFS(全伝票!N:N,全伝票!$A:$A,$A19,全伝票!$B:$B,$B19),SUMIFS(全伝票!N:N,全伝票!$A:$A,$A19,全伝票!$C:$C,$C19))) -> 1820 | K19: =SUM(F19:J19) -> 1820 | L19: =+IF($A19="",IF($C19="",SUMIFS(全伝票!O:O,全伝票!$B:$B,$B19),SUMIFS(全伝票!O:O,全伝票!$C:$C,$C19)),IF($C19="",SUMIFS(全伝票!O:O,全伝票!$A:$A,$A19,全伝票!$B:$B,$B19),SUMIFS(全伝票!O:O,全伝票!$A:$A,$A19,全伝票!$C:$C,$C19))) -> 0 | M19: =+IF($A19="",IF($C19="",SUMIFS(全伝票!P:P,全伝票!$B:$B,$B19),SUMIFS(全伝票!P:P,全伝票!$C:$C,$C19)),IF($C19="",SUMIFS(全伝票!P:P,全伝票!$A:$A,$A19,全伝票!$B:$B,$B19),SUMIFS(全伝票!P:P,全伝票!$A:$A,$A19,全伝票!$C:$C,$C19))) -> 0 | N19: =+ROUND(F19*F$4/(100+F$4),0)+AE19 -> 0 | O19: =+ROUND(G19*G$4/(100+G$4),0)+AF19 -> 0 | P19: =+ROUND(H19*H$4/(100+H$4),0)+AG19 -> 0 | Q19: =+ROUND(I19*I$4/(100+I$4),0)+AH19 -> 0 | R19: =+ROUND(J19*J$4/(100+J$4),0)+AI19 -> 165 | S19: =SUM(N19:R19) -> 165 | T19: =+E19-S19 -> 1655 | U19: =N19-F19*F$4/(100+F$4) -> 0 | V19: =O19-G19*G$4/(100+G$4) -> 0 | W19: =P19-H19*H$4/(100+H$4) -> 0 | X19: =Q19-I19*I$4/(100+I$4) -> 0 | Y19: =R19-J19*J$4/(100+J$4) -> -0.45454545 | Z19: =+IF(N$38=0,0,IF(N$38<0,-RANK(U19,U$5:U$35,0),RANK(U19,U$5:U$35,1))) -> 0 | AA19: =+IF(O$38=0,0,IF(O$38<0,-RANK(V19,V$5:V$35,0),RANK(V19,V$5:V$35,1))) -> 0 | AB19: =+IF(P$38=0,0,IF(P$38<0,-RANK(W19,W$5:W$35,0),RANK(W19,W$5:W$35,1))) -> 0 | AC19: =+IF(Q$38=0,0,IF(Q$38<0,-RANK(X19,X$5:X$35,0),RANK(X19,X$5:X$35,1))) -> 0 | AD19: =+IF(R$38=0,0,IF(R$38<0,-RANK(Y19,Y$5:Y$35,0),RANK(Y19,Y$5:Y$35,1))) -> 0
A20: 1 | B20: 8830421 | D20: 委託料 | E20: =+IF($A20="",IF($C20="",SUMIFS(全伝票!I:I,全伝票!$B:$B,$B20),SUMIFS(全伝票!I:I,全伝票!$C:$C,$C20)),IF($C20="",SUMIFS(全伝票!I:I,全伝票!$A:$A,$A20,全伝票!$B:$B,$B20),SUMIFS(全伝票!I:I,全伝票!$A:$A,$A20,全伝票!$C:$C,$C20))) -> 11727105 | F20: =+IF($A20="",IF($C20="",SUMIFS(全伝票!J:J,全伝票!$B:$B,$B20),SUMIFS(全伝票!J:J,全伝票!$C:$C,$C20)),IF($C20="",SUMIFS(全伝票!J:J,全伝票!$A:$A,$A20,全伝票!$B:$B,$B20),SUMIFS(全伝票!J:J,全伝票!$A:$A,$A20,全伝票!$C:$C,$C20))) -> 0 | G20: =+IF($A20="",IF($C20="",SUMIFS(全伝票!K:K,全伝票!$B:$B,$B20),SUMIFS(全伝票!K:K,全伝票!$C:$C,$C20)),IF($C20="",SUMIFS(全伝票!K:K,全伝票!$A:$A,$A20,全伝票!$B:$B,$B20),SUMIFS(全伝票!K:K,全伝票!$A:$A,$A20,全伝票!$C:$C,$C20))) -> 0 | H20: =+IF($A20="",IF($C20="",SUMIFS(全伝票!L:L,全伝票!$B:$B,$B20),SUMIFS(全伝票!L:L,全伝票!$C:$C,$C20)),IF($C20="",SUMIFS(全伝票!L:L,全伝票!$A:$A,$A20,全伝票!$B:$B,$B20),SUMIFS(全伝票!L:L,全伝票!$A:$A,$A20,全伝票!$C:$C,$C20))) -> 0 | I20: =+IF($A20="",IF($C20="",SUMIFS(全伝票!M:M,全伝票!$B:$B,$B20),SUMIFS(全伝票!M:M,全伝票!$C:$C,$C20)),IF($C20="",SUMIFS(全伝票!M:M,全伝票!$A:$A,$A20,全伝票!$B:$B,$B20),SUMIFS(全伝票!M:M,全伝票!$A:$A,$A20,全伝票!$C:$C,$C20))) -> 0 | J20: =+IF($A20="",IF($C20="",SUMIFS(全伝票!N:N,全伝票!$B:$B,$B20),SUMIFS(全伝票!N:N,全伝票!$C:$C,$C20)),IF($C20="",SUMIFS(全伝票!N:N,全伝票!$A:$A,$A20,全伝票!$B:$B,$B20),SUMIFS(全伝票!N:N,全伝票!$A:$A,$A20,全伝票!$C:$C,$C20))) -> 11727105 | K20: =SUM(F20:J20) -> 11727105 | L20: =+IF($A20="",IF($C20="",SUMIFS(全伝票!O:O,全伝票!$B:$B,$B20),SUMIFS(全伝票!O:O,全伝票!$C:$C,$C20)),IF($C20="",SUMIFS(全伝票!O:O,全伝票!$A:$A,$A20,全伝票!$B:$B,$B20),SUMIFS(全伝票!O:O,全伝票!$A:$A,$A20,全伝票!$C:$C,$C20))) -> 0 | M20: =+IF($A20="",IF($C20="",SUMIFS(全伝票!P:P,全伝票!$B:$B,$B20),SUMIFS(全伝票!P:P,全伝票!$C:$C,$C20)),IF($C20="",SUMIFS(全伝票!P:P,全伝票!$A:$A,$A20,全伝票!$B:$B,$B20),SUMIFS(全伝票!P:P,全伝票!$A:$A,$A20,全伝票!$C:$C,$C20))) -> 0 | N20: =+ROUND(F20*F$4/(100+F$4),0)+AE20 -> 0 | O20: =+ROUND(G20*G$4/(100+G$4),0)+AF20 -> 0 | P20: =+ROUND(H20*H$4/(100+H$4),0)+AG20 -> 0 | Q20: =+ROUND(I20*I$4/(100+I$4),0)+AH20 -> 0 | R20: =+ROUND(J20*J$4/(100+J$4),0)+AI20 -> 1066100 | S20: =SUM(N20:R20) -> 1066100 | T20: =+E20-S20 -> 10661005 | U20: =N20-F20*F$4/(100+F$4) -> 0 | V20: =O20-G20*G$4/(100+G$4) -> 0 | W20: =P20-H20*H$4/(100+H$4) -> 0 | X20: =Q20-I20*I$4/(100+I$4) -> 0 | Y20: =R20-J20*J$4/(100+J$4) -> -0.45454545 | Z20: =+IF(N$38=0,0,IF(N$38<0,-RANK(U20,U$5:U$35,0),RANK(U20,U$5:U$35,1))) -> 0 | AA20: =+IF(O$38=0,0,IF(O$38<0,-RANK(V20,V$5:V$35,0),RANK(V20,V$5:V$35,1))) -> 0 | AB20: =+IF(P$38=0,0,IF(P$38<0,-RANK(W20,W$5:W$35,0),RANK(W20,W$5:W$35,1))) -> 0 | AC20: =+IF(Q$38=0,0,IF(Q$38<0,-RANK(X20,X$5:X$35,0),RANK(X20,X$5:X$35,1))) -> 0 | AD20: =+IF(R$38=0,0,IF(R$38<0,-RANK(Y20,Y$5:Y$35,0),RANK(Y20,Y$5:Y$35,1))) -> 0
A21: 1 | B21: 8830423 | D21: 修繕費 | E21: =+IF($A21="",IF($C21="",SUMIFS(全伝票!I:I,全伝票!$B:$B,$B21),SUMIFS(全伝票!I:I,全伝票!$C:$C,$C21)),IF($C21="",SUMIFS(全伝票!I:I,全伝票!$A:$A,$A21,全伝票!$B:$B,$B21),SUMIFS(全伝票!I:I,全伝票!$A:$A,$A21,全伝票!$C:$C,$C21))) -> 49808 | F21: =+IF($A21="",IF($C21="",SUMIFS(全伝票!J:J,全伝票!$B:$B,$B21),SUMIFS(全伝票!J:J,全伝票!$C:$C,$C21)),IF($C21="",SUMIFS(全伝票!J:J,全伝票!$A:$A,$A21,全伝票!$B:$B,$B21),SUMIFS(全伝票!J:J,全伝票!$A:$A,$A21,全伝票!$C:$C,$C21))) -> 0 | G21: =+IF($A21="",IF($C21="",SUMIFS(全伝票!K:K,全伝票!$B:$B,$B21),SUMIFS(全伝票!K:K,全伝票!$C:$C,$C21)),IF($C21="",SUMIFS(全伝票!K:K,全伝票!$A:$A,$A21,全伝票!$B:$B,$B21),SUMIFS(全伝票!K:K,全伝票!$A:$A,$A21,全伝票!$C:$C,$C21))) -> 0 | H21: =+IF($A21="",IF($C21="",SUMIFS(全伝票!L:L,全伝票!$B:$B,$B21),SUMIFS(全伝票!L:L,全伝票!$C:$C,$C21)),IF($C21="",SUMIFS(全伝票!L:L,全伝票!$A:$A,$A21,全伝票!$B:$B,$B21),SUMIFS(全伝票!L:L,全伝票!$A:$A,$A21,全伝票!$C:$C,$C21))) -> 0 | I21: =+IF($A21="",IF($C21="",SUMIFS(全伝票!M:M,全伝票!$B:$B,$B21),SUMIFS(全伝票!M:M,全伝票!$C:$C,$C21)),IF($C21="",SUMIFS(全伝票!M:M,全伝票!$A:$A,$A21,全伝票!$B:$B,$B21),SUMIFS(全伝票!M:M,全伝票!$A:$A,$A21,全伝票!$C:$C,$C21))) -> 0 | J21: =+IF($A21="",IF($C21="",SUMIFS(全伝票!N:N,全伝票!$B:$B,$B21),SUMIFS(全伝票!N:N,全伝票!$C:$C,$C21)),IF($C21="",SUMIFS(全伝票!N:N,全伝票!$A:$A,$A21,全伝票!$B:$B,$B21),SUMIFS(全伝票!N:N,全伝票!$A:$A,$A21,全伝票!$C:$C,$C21))) -> 49808 | K21: =SUM(F21:J21) -> 49808 | L21: =+IF($A21="",IF($C21="",SUMIFS(全伝票!O:O,全伝票!$B:$B,$B21),SUMIFS(全伝票!O:O,全伝票!$C:$C,$C21)),IF($C21="",SUMIFS(全伝票!O:O,全伝票!$A:$A,$A21,全伝票!$B:$B,$B21),SUMIFS(全伝票!O:O,全伝票!$A:$A,$A21,全伝票!$C:$C,$C21))) -> 0 | M21: =+IF($A21="",IF($C21="",SUMIFS(全伝票!P:P,全伝票!$B:$B,$B21),SUMIFS(全伝票!P:P,全伝票!$C:$C,$C21)),IF($C21="",SUMIFS(全伝票!P:P,全伝票!$A:$A,$A21,全伝票!$B:$B,$B21),SUMIFS(全伝票!P:P,全伝票!$A:$A,$A21,全伝票!$C:$C,$C21))) -> 0 | N21: =+ROUND(F21*F$4/(100+F$4),0)+AE21 -> 0 | O21: =+ROUND(G21*G$4/(100+G$4),0)+AF21 -> 0 | P21: =+ROUND(H21*H$4/(100+H$4),0)+AG21 -> 0 | Q21: =+ROUND(I21*I$4/(100+I$4),0)+AH21 -> 0 | R21: =+ROUND(J21*J$4/(100+J$4),0)+AI21 -> 4528 | S21: =SUM(N21:R21) -> 4528 | T21: =+E21-S21 -> 45280 | U21: =N21-F21*F$4/(100+F$4) -> 0 | V21: =O21-G21*G$4/(100+G$4) -> 0 | W21: =P21-H21*H$4/(100+H$4) -> 0 | X21: =Q21-I21*I$4/(100+I$4) -> 0 | Y21: =R21-J21*J$4/(100+J$4) -> 0 | Z21: =+IF(N$38=0,0,IF(N$38<0,-RANK(U21,U$5:U$35,0),RANK(U21,U$5:U$35,1))) -> 0 | AA21: =+IF(O$38=0,0,IF(O$38<0,-RANK(V21,V$5:V$35,0),RANK(V21,V$5:V$35,1))) -> 0 | AB21: =+IF(P$38=0,0,IF(P$38<0,-RANK(W21,W$5:W$35,0),RANK(W21,W$5:W$35,1))) -> 0 | AC21: =+IF(Q$38=0,0,IF(Q$38<0,-RANK(X21,X$5:X$35,0),RANK(X21,X$5:X$35,1))) -> 0 | AD21: =+IF(R$38=0,0,IF(R$38<0,-RANK(Y21,Y$5:Y$35,0),RANK(Y21,Y$5:Y$35,1))) -> 0
A22: 1 | B22: 8830424 | D22: 材料費 | E22: =+IF($A22="",IF($C22="",SUMIFS(全伝票!I:I,全伝票!$B:$B,$B22),SUMIFS(全伝票!I:I,全伝票!$C:$C,$C22)),IF($C22="",SUMIFS(全伝票!I:I,全伝票!$A:$A,$A22,全伝票!$B:$B,$B22),SUMIFS(全伝票!I:I,全伝票!$A:$A,$A22,全伝票!$C:$C,$C22))) -> 0 | F22: =+IF($A22="",IF($C22="",SUMIFS(全伝票!J:J,全伝票!$B:$B,$B22),SUMIFS(全伝票!J:J,全伝票!$C:$C,$C22)),IF($C22="",SUMIFS(全伝票!J:J,全伝票!$A:$A,$A22,全伝票!$B:$B,$B22),SUMIFS(全伝票!J:J,全伝票!$A:$A,$A22,全伝票!$C:$C,$C22))) -> 0 | G22: =+IF($A22="",IF($C22="",SUMIFS(全伝票!K:K,全伝票!$B:$B,$B22),SUMIFS(全伝票!K:K,全伝票!$C:$C,$C22)),IF($C22="",SUMIFS(全伝票!K:K,全伝票!$A:$A,$A22,全伝票!$B:$B,$B22),SUMIFS(全伝票!K:K,全伝票!$A:$A,$A22,全伝票!$C:$C,$C22))) -> 0 | H22: =+IF($A22="",IF($C22="",SUMIFS(全伝票!L:L,全伝票!$B:$B,$B22),SUMIFS(全伝票!L:L,全伝票!$C:$C,$C22)),IF($C22="",SUMIFS(全伝票!L:L,全伝票!$A:$A,$A22,全伝票!$B:$B,$B22),SUMIFS(全伝票!L:L,全伝票!$A:$A,$A22,全伝票!$C:$C,$C22))) -> 0 | I22: =+IF($A22="",IF($C22="",SUMIFS(全伝票!M:M,全伝票!$B:$B,$B22),SUMIFS(全伝票!M:M,全伝票!$C:$C,$C22)),IF($C22="",SUMIFS(全伝票!M:M,全伝票!$A:$A,$A22,全伝票!$B:$B,$B22),SUMIFS(全伝票!M:M,全伝票!$A:$A,$A22,全伝票!$C:$C,$C22))) -> 0 | J22: =+IF($A22="",IF($C22="",SUMIFS(全伝票!N:N,全伝票!$B:$B,$B22),SUMIFS(全伝票!N:N,全伝票!$C:$C,$C22)),IF($C22="",SUMIFS(全伝票!N:N,全伝票!$A:$A,$A22,全伝票!$B:$B,$B22),SUMIFS(全伝票!N:N,全伝票!$A:$A,$A22,全伝票!$C:$C,$C22))) -> 0 | K22: =SUM(F22:J22) -> 0 | L22: =+IF($A22="",IF($C22="",SUMIFS(全伝票!O:O,全伝票!$B:$B,$B22),SUMIFS(全伝票!O:O,全伝票!$C:$C,$C22)),IF($C22="",SUMIFS(全伝票!O:O,全伝票!$A:$A,$A22,全伝票!$B:$B,$B22),SUMIFS(全伝票!O:O,全伝票!$A:$A,$A22,全伝票!$C:$C,$C22))) -> 0 | M22: =+IF($A22="",IF($C22="",SUMIFS(全伝票!P:P,全伝票!$B:$B,$B22),SUMIFS(全伝票!P:P,全伝票!$C:$C,$C22)),IF($C22="",SUMIFS(全伝票!P:P,全伝票!$A:$A,$A22,全伝票!$B:$B,$B22),SUMIFS(全伝票!P:P,全伝票!$A:$A,$A22,全伝票!$C:$C,$C22))) -> 0 | N22: =+ROUND(F22*F$4/(100+F$4),0)+AE22 -> 0 | O22: =+ROUND(G22*G$4/(100+G$4),0)+AF22 -> 0 | P22: =+ROUND(H22*H$4/(100+H$4),0)+AG22 -> 0 | Q22: =+ROUND(I22*I$4/(100+I$4),0)+AH22 -> 0 | R22: =+ROUND(J22*J$4/(100+J$4),0)+AI22 -> 0 | S22: =SUM(N22:R22) -> 0 | T22: =+E22-S22 -> 0 | U22: =N22-F22*F$4/(100+F$4) -> 0 | V22: =O22-G22*G$4/(100+G$4) -> 0 | W22: =P22-H22*H$4/(100+H$4) -> 0 | X22: =Q22-I22*I$4/(100+I$4) -> 0 | Y22: =R22-J22*J$4/(100+J$4) -> 0 | Z22: =+IF(N$38=0,0,IF(N$38<0,-RANK(U22,U$5:U$35,0),RANK(U22,U$5:U$35,1))) -> 0 | AA22: =+IF(O$38=0,0,IF(O$38<0,-RANK(V22,V$5:V$35,0),RANK(V22,V$5:V$35,1))) -> 0 | AB22: =+IF(P$38=0,0,IF(P$38<0,-RANK(W22,W$5:W$35,0),RANK(W22,W$5:W$35,1))) -> 0 | AC22: =+IF(Q$38=0,0,IF(Q$38<0,-RANK(X22,X$5:X$35,0),RANK(X22,X$5:X$35,1))) -> 0 | AD22: =+IF(R$38=0,0,IF(R$38<0,-RANK(Y22,Y$5:Y$35,0),RANK(Y22,Y$5:Y$35,1))) -> 0
A23: 1 | B23: 8830425 | D23: 工事請負費 | E23: =+IF($A23="",IF($C23="",SUMIFS(全伝票!I:I,全伝票!$B:$B,$B23),SUMIFS(全伝票!I:I,全伝票!$C:$C,$C23)),IF($C23="",SUMIFS(全伝票!I:I,全伝票!$A:$A,$A23,全伝票!$B:$B,$B23),SUMIFS(全伝票!I:I,全伝票!$A:$A,$A23,全伝票!$C:$C,$C23))) -> 0 | F23: =+IF($A23="",IF($C23="",SUMIFS(全伝票!J:J,全伝票!$B:$B,$B23),SUMIFS(全伝票!J:J,全伝票!$C:$C,$C23)),IF($C23="",SUMIFS(全伝票!J:J,全伝票!$A:$A,$A23,全伝票!$B:$B,$B23),SUMIFS(全伝票!J:J,全伝票!$A:$A,$A23,全伝票!$C:$C,$C23))) -> 0 | G23: =+IF($A23="",IF($C23="",SUMIFS(全伝票!K:K,全伝票!$B:$B,$B23),SUMIFS(全伝票!K:K,全伝票!$C:$C,$C23)),IF($C23="",SUMIFS(全伝票!K:K,全伝票!$A:$A,$A23,全伝票!$B:$B,$B23),SUMIFS(全伝票!K:K,全伝票!$A:$A,$A23,全伝票!$C:$C,$C23))) -> 0 | H23: =+IF($A23="",IF($C23="",SUMIFS(全伝票!L:L,全伝票!$B:$B,$B23),SUMIFS(全伝票!L:L,全伝票!$C:$C,$C23)),IF($C23="",SUMIFS(全伝票!L:L,全伝票!$A:$A,$A23,全伝票!$B:$B,$B23),SUMIFS(全伝票!L:L,全伝票!$A:$A,$A23,全伝票!$C:$C,$C23))) -> 0 | I23: =+IF($A23="",IF($C23="",SUMIFS(全伝票!M:M,全伝票!$B:$B,$B23),SUMIFS(全伝票!M:M,全伝票!$C:$C,$C23)),IF($C23="",SUMIFS(全伝票!M:M,全伝票!$A:$A,$A23,全伝票!$B:$B,$B23),SUMIFS(全伝票!M:M,全伝票!$A:$A,$A23,全伝票!$C:$C,$C23))) -> 0 | J23: =+IF($A23="",IF($C23="",SUMIFS(全伝票!N:N,全伝票!$B:$B,$B23),SUMIFS(全伝票!N:N,全伝票!$C:$C,$C23)),IF($C23="",SUMIFS(全伝票!N:N,全伝票!$A:$A,$A23,全伝票!$B:$B,$B23),SUMIFS(全伝票!N:N,全伝票!$A:$A,$A23,全伝票!$C:$C,$C23))) -> 0 | K23: =SUM(F23:J23) -> 0 | L23: =+IF($A23="",IF($C23="",SUMIFS(全伝票!O:O,全伝票!$B:$B,$B23),SUMIFS(全伝票!O:O,全伝票!$C:$C,$C23)),IF($C23="",SUMIFS(全伝票!O:O,全伝票!$A:$A,$A23,全伝票!$B:$B,$B23),SUMIFS(全伝票!O:O,全伝票!$A:$A,$A23,全伝票!$C:$C,$C23))) -> 0 | M23: =+IF($A23="",IF($C23="",SUMIFS(全伝票!P:P,全伝票!$B:$B,$B23),SUMIFS(全伝票!P:P,全伝票!$C:$C,$C23)),IF($C23="",SUMIFS(全伝票!P:P,全伝票!$A:$A,$A23,全伝票!$B:$B,$B23),SUMIFS(全伝票!P:P,全伝票!$A:$A,$A23,全伝票!$C:$C,$C23))) -> 0 | N23: =+ROUND(F23*F$4/(100+F$4),0)+AE23 -> 0 | O23: =+ROUND(G23*G$4/(100+G$4),0)+AF23 -> 0 | P23: =+ROUND(H23*H$4/(100+H$4),0)+AG23 -> 0 | Q23: =+ROUND(I23*I$4/(100+I$4),0)+AH23 -> 0 | R23: =+ROUND(J23*J$4/(100+J$4),0)+AI23 -> 0 | S23: =SUM(N23:R23) -> 0 | T23: =+E23-S23 -> 0 | U23: =N23-F23*F$4/(100+F$4) -> 0 | V23: =O23-G23*G$4/(100+G$4) -> 0 | W23: =P23-H23*H$4/(100+H$4) -> 0 | X23: =Q23-I23*I$4/(100+I$4) -> 0 | Y23: =R23-J23*J$4/(100+J$4) -> 0 | Z23: =+IF(N$38=0,0,IF(N$38<0,-RANK(U23,U$5:U$35,0),RANK(U23,U$5:U$35,1))) -> 0 | AA23: =+IF(O$38=0,0,IF(O$38<0,-RANK(V23,V$5:V$35,0),RANK(V23,V$5:V$35,1))) -> 0 | AB23: =+IF(P$38=0,0,IF(P$38<0,-RANK(W23,W$5:W$35,0),RANK(W23,W$5:W$35,1))) -> 0 | AC23: =+IF(Q$38=0,0,IF(Q$38<0,-RANK(X23,X$5:X$35,0),RANK(X23,X$5:X$35,1))) -> 0 | AD23: =+IF(R$38=0,0,IF(R$38<0,-RANK(Y23,Y$5:Y$35,0),RANK(Y23,Y$5:Y$35,1))) -> 0
A24: 1 | B24: 8830426 | D24: 路面復旧費 | E24: =+IF($A24="",IF($C24="",SUMIFS(全伝票!I:I,全伝票!$B:$B,$B24),SUMIFS(全伝票!I:I,全伝票!$C:$C,$C24)),IF($C24="",SUMIFS(全伝票!I:I,全伝票!$A:$A,$A24,全伝票!$B:$B,$B24),SUMIFS(全伝票!I:I,全伝票!$A:$A,$A24,全伝票!$C:$C,$C24))) -> 0 | F24: =+IF($A24="",IF($C24="",SUMIFS(全伝票!J:J,全伝票!$B:$B,$B24),SUMIFS(全伝票!J:J,全伝票!$C:$C,$C24)),IF($C24="",SUMIFS(全伝票!J:J,全伝票!$A:$A,$A24,全伝票!$B:$B,$B24),SUMIFS(全伝票!J:J,全伝票!$A:$A,$A24,全伝票!$C:$C,$C24))) -> 0 | G24: =+IF($A24="",IF($C24="",SUMIFS(全伝票!K:K,全伝票!$B:$B,$B24),SUMIFS(全伝票!K:K,全伝票!$C:$C,$C24)),IF($C24="",SUMIFS(全伝票!K:K,全伝票!$A:$A,$A24,全伝票!$B:$B,$B24),SUMIFS(全伝票!K:K,全伝票!$A:$A,$A24,全伝票!$C:$C,$C24))) -> 0 | H24: =+IF($A24="",IF($C24="",SUMIFS(全伝票!L:L,全伝票!$B:$B,$B24),SUMIFS(全伝票!L:L,全伝票!$C:$C,$C24)),IF($C24="",SUMIFS(全伝票!L:L,全伝票!$A:$A,$A24,全伝票!$B:$B,$B24),SUMIFS(全伝票!L:L,全伝票!$A:$A,$A24,全伝票!$C:$C,$C24))) -> 0 | I24: =+IF($A24="",IF($C24="",SUMIFS(全伝票!M:M,全伝票!$B:$B,$B24),SUMIFS(全伝票!M:M,全伝票!$C:$C,$C24)),IF($C24="",SUMIFS(全伝票!M:M,全伝票!$A:$A,$A24,全伝票!$B:$B,$B24),SUMIFS(全伝票!M:M,全伝票!$A:$A,$A24,全伝票!$C:$C,$C24))) -> 0 | J24: =+IF($A24="",IF($C24="",SUMIFS(全伝票!N:N,全伝票!$B:$B,$B24),SUMIFS(全伝票!N:N,全伝票!$C:$C,$C24)),IF($C24="",SUMIFS(全伝票!N:N,全伝票!$A:$A,$A24,全伝票!$B:$B,$B24),SUMIFS(全伝票!N:N,全伝票!$A:$A,$A24,全伝票!$C:$C,$C24))) -> 0 | K24: =SUM(F24:J24) -> 0 | L24: =+IF($A24="",IF($C24="",SUMIFS(全伝票!O:O,全伝票!$B:$B,$B24),SUMIFS(全伝票!O:O,全伝票!$C:$C,$C24)),IF($C24="",SUMIFS(全伝票!O:O,全伝票!$A:$A,$A24,全伝票!$B:$B,$B24),SUMIFS(全伝票!O:O,全伝票!$A:$A,$A24,全伝票!$C:$C,$C24))) -> 0 | M24: =+IF($A24="",IF($C24="",SUMIFS(全伝票!P:P,全伝票!$B:$B,$B24),SUMIFS(全伝票!P:P,全伝票!$C:$C,$C24)),IF($C24="",SUMIFS(全伝票!P:P,全伝票!$A:$A,$A24,全伝票!$B:$B,$B24),SUMIFS(全伝票!P:P,全伝票!$A:$A,$A24,全伝票!$C:$C,$C24))) -> 0 | N24: =+ROUND(F24*F$4/(100+F$4),0)+AE24 -> 0 | O24: =+ROUND(G24*G$4/(100+G$4),0)+AF24 -> 0 | P24: =+ROUND(H24*H$4/(100+H$4),0)+AG24 -> 0 | Q24: =+ROUND(I24*I$4/(100+I$4),0)+AH24 -> 0 | R24: =+ROUND(J24*J$4/(100+J$4),0)+AI24 -> 0 | S24: =SUM(N24:R24) -> 0 | T24: =+E24-S24 -> 0 | U24: =N24-F24*F$4/(100+F$4) -> 0 | V24: =O24-G24*G$4/(100+G$4) -> 0 | W24: =P24-H24*H$4/(100+H$4) -> 0 | X24: =Q24-I24*I$4/(100+I$4) -> 0 | Y24: =R24-J24*J$4/(100+J$4) -> 0 | Z24: =+IF(N$38=0,0,IF(N$38<0,-RANK(U24,U$5:U$35,0),RANK(U24,U$5:U$35,1))) -> 0 | AA24: =+IF(O$38=0,0,IF(O$38<0,-RANK(V24,V$5:V$35,0),RANK(V24,V$5:V$35,1))) -> 0 | AB24: =+IF(P$38=0,0,IF(P$38<0,-RANK(W24,W$5:W$35,0),RANK(W24,W$5:W$35,1))) -> 0 | AC24: =+IF(Q$38=0,0,IF(Q$38<0,-RANK(X24,X$5:X$35,0),RANK(X24,X$5:X$35,1))) -> 0 | AD24: =+IF(R$38=0,0,IF(R$38<0,-RANK(Y24,Y$5:Y$35,0),RANK(Y24,Y$5:Y$35,1))) -> 0
