Workbook

Sheet 4条収入
D1: =+'[1]3条支出'!$D$1 -> 令和５年度決算 消費税算出資料
D2: 【４条収入内訳】
A3: 事業 | B3: 節 | C3: 細節 | D3: 費目 | E3: 税込決算額 | F3: 課税売上げ | L3: 非課税 売上げ | M3: 免税 売上げ | N3: 不課税収入（資産の譲渡等の対価以外の収入（対価性のない収入）） | W3: 仮受消費税 | AC3: 特定収入に係る課税仕入れ等に係る消費税額 | AI3: 税抜決算額 | AJ3: 仮受け消費税の調整 | AY3: 課税支出に係る特定収入に係る消費税の調整
N4: 特定収入 | U4: 特定収入以外 の不課税収入
N5: 課税仕入れ等に係る特定収入 | T5: 課税仕入れ等に係る特定収入以外 | V5: 計 | AJ5: 消費税 端数確認 | AO5: 消費税端数調整ランク | AT5: 消費税 調整額 | AY5: 消費税 端数確認 | BD5: 消費税端数調整ランク | BI5: 消費税 調整額
F6: 3 | G6: 5 | H6: 8 | I6: 8 | J6: 10 | K6: 計 | N6: 3 | O6: 5 | P6: 8 | Q6: 8 | R6: 10 | S6: 計 | W6: 3 | X6: 5 | Y6: 8 | Z6: 8 | AA6: 10 | AB6: 計 | AC6: 3 | AD6: 5 | AE6: 8 | AF6: 8 | AG6: 10 | AH6: 計 | AJ6: 3 | AK6: 5 | AL6: 8 | AM6: 8 | AN6: 10 | AO6: 3 | AP6: 5 | AQ6: 8 | AR6: 8 | AS6: 10 | AT6: 3 | AU6: 5 | AV6: 8 | AW6: 8 | AX6: 10 | AY6: 3 | AZ6: 5 | BA6: 8 | BB6: 8 | BC6: 10 | BD6: 3 | BE6: 5 | BF6: 8 | BG6: 8 | BH6: 10 | BI6: 3 | BJ6: 5 | BK6: 8 | BL6: 8 | BM6: 10
D7: 企業債 | E7: =+SUM(E8,E16,E20) -> 32373300000 | F7: =+SUM(F8,F16,F20) -> 0 | G7: =+SUM(G8,G16,G20) -> 0 | H7: =+SUM(H8,H16,H20) -> 0 | I7: =+SUM(I8,I16,I20) -> 0 | J7: =+SUM(J8,J16,J20) -> 0 | K7: =+SUM(K8,K16,K20) -> 0 | L7: =+SUM(L8,L16,L20) -> 0 | ... AI7: =+SUM(AI8,AI16,AI20) -> 32373300000
D8: 建設企業債 | E8: =+SUM(E9,E12:E15) -> 15365600000 | F8: =+SUM(F9,F12:F15) -> 0 | G8: =+SUM(G9,G12:G15) -> 0 | H8: =+SUM(H9,H12:H15) -> 0 | I8: =+SUM(I9,I12:I15) -> 0 | J8: =+SUM(J9,J12:J15) -> 0 | K8: =+SUM(K9,K12:K15) -> 0 | L8: =+SUM(L9,L12:L15) -> 0 | ... AI8: =+SUM(AI9,AI12:AI15) -> 15365600000
D9: 公共下水道事業債 | E9: =+SUM(E10:E11) -> 8822500000 | F9: =+SUM(F10:F11) -> 0 | G9: =+SUM(G10:G11) -> 0 | H9: =+SUM(H10:H11) -> 0 | I9: =+SUM(I10:I11) -> 0 | J9: =+SUM(J10:J11) -> 0 | K9: =+SUM(K10:K11) -> 0 | L9: =+SUM(L10:L11) -> 0 | ... AI9: =+SUM(AI10:AI11) -> 8822500000
C10: 112011010 | D10: 一般債 | E10: =+SUMIFS([1]全伝票!I:I,[1]全伝票!$C:$C,$C10) -> 8822500000 | K10: =SUM(F10:J10) -> 0 | S10: =SUM(N10:R10) -> 0 | U10: =+V10-SUM(S10:T10) -> 8822500000 | V10: =+SUMIFS([1]全伝票!P:P,[1]全伝票!$C:$C,$C10) -> 8822500000 | W10: =+ROUND(F10*F$6/(100+F$6),0)+AT10 -> 0 | X10: =+ROUND(G10*G$6/(100+G$6),0)+AU10 -> 0 | Y10: =+ROUND(H10*H$6/(100+H$6),0)+AV10 -> 0 | Z10: =+ROUND(I10*I$6/(100+I$6),0)+AW10 -> 0 | AA10: =+ROUND(J10*J$6/(100+J$6),0)+AX10 -> 0 | AB10: =SUM(W10:AA10) -> 0 | AC10: =+ROUND(N10*AC$6/(100+AC$6),0)+BI10 -> 0 | AD10: =+ROUND(O10*AD$6/(100+AD$6),0)+BJ10 -> 0 | AE10: =+ROUND(P10*AE$6/(100+AE$6),0)+BK10 -> 0 | AF10: =+ROUND(Q10*AF$6/(100+AF$6),0)+BL10 -> 0 | AG10: =+ROUND(R10*AG$6/(100+AG$6),0)+BM10 -> 0 | AH10: =SUM(AC10:AG10) -> 0 | AI10: =+E10-AB10 -> 8822500000
C11: 112011011 | D11: 特別債 | E11: =+SUMIFS([1]全伝票!I:I,[1]全伝票!$C:$C,$C11) -> 0 | K11: =SUM(F11:J11) -> 0 | S11: =SUM(N11:R11) -> 0 | U11: =+V11-SUM(S11:T11) -> 0 | V11: =+SUMIFS([1]全伝票!P:P,[1]全伝票!$C:$C,$C11) -> 0 | W11: =+ROUND(F11*F$6/(100+F$6),0)+AT11 -> 0 | X11: =+ROUND(G11*G$6/(100+G$6),0)+AU11 -> 0 | Y11: =+ROUND(H11*H$6/(100+H$6),0)+AV11 -> 0 | Z11: =+ROUND(I11*I$6/(100+I$6),0)+AW11 -> 0 | AA11: =+ROUND(J11*J$6/(100+J$6),0)+AX11 -> 0 | AB11: =SUM(W11:AA11) -> 0 | AC11: =+ROUND(N11*AC$6/(100+AC$6),0)+BI11 -> 0 | AD11: =+ROUND(O11*AD$6/(100+AD$6),0)+BJ11 -> 0 | AE11: =+ROUND(P11*AE$6/(100+AE$6),0)+BK11 -> 0 | AF11: =+ROUND(Q11*AF$6/(100+AF$6),0)+BL11 -> 0 | AG11: =+ROUND(R11*AG$6/(100+AG$6),0)+BM11 -> 0 | AH11: =SUM(AC11:AG11) -> 0 | AI11: =+E11-AB11 -> 0
C12: 112011500 | D12: 市街化区域外事業債 | E12: =+SUMIFS([1]全伝票!I:I,[1]全伝票!$C:$C,$C12) -> 493400000 | K12: =SUM(F12:J12) -> 0 | S12: =SUM(N12:R12) -> 0 | U12: =+V12-SUM(S12:T12) -> 493400000 | V12: =+SUMIFS([1]全伝票!P:P,[1]全伝票!$C:$C,$C12) -> 493400000 | W12: =+ROUND(F12*F$6/(100+F$6),0)+AT12 -> 0 | X12: =+ROUND(G12*G$6/(100+G$6),0)+AU12 -> 0 | Y12: =+ROUND(H12*H$6/(100+H$6),0)+AV12 -> 0 | Z12: =+ROUND(I12*I$6/(100+I$6),0)+AW12 -> 0 | AA12: =+ROUND(J12*J$6/(100+J$6),0)+AX12 -> 0 | AB12: =SUM(W12:AA12) -> 0 | AC12: =+ROUND(N12*AC$6/(100+AC$6),0)+BI12 -> 0 | AD12: =+ROUND(O12*AD$6/(100+AD$6),0)+BJ12 -> 0 | AE12: =+ROUND(P12*AE$6/(100+AE$6),0)+BK12 -> 0 | AF12: =+ROUND(Q12*AF$6/(100+AF$6),0)+BL12 -> 0 | AG12: =+ROUND(R12*AG$6/(100+AG$6),0)+BM12 -> 0 | AH12: =SUM(AC12:AG12) -> 0 | AI12: =+E12-AB12 -> 493400000
C13: 112011200 | D13: 流域下水道事業債 | E13: =+SUMIFS([1]全伝票!I:I,[1]全伝票!$C:$C,$C13) -> 120200000 | K13: =SUM(F13:J13) -> 0 | S13: =SUM(N13:R13) -> 0 | U13: =+V13-SUM(S13:T13) -> 120200000 | V13: =+SUMIFS([1]全伝票!P:P,[1]全伝票!$C:$C,$C13) -> 120200000 | W13: =+ROUND(F13*F$6/(100+F$6),0)+AT13 -> 0 | X13: =+ROUND(G13*G$6/(100+G$6),0)+AU13 -> 0 | Y13: =+ROUND(H13*H$6/(100+H$6),0)+AV13 -> 0 | Z13: =+ROUND(I13*I$6/(100+I$6),0)+AW13 -> 0 | AA13: =+ROUND(J13*J$6/(100+J$6),0)+AX13 -> 0 | AB13: =SUM(W13:AA13) -> 0 | AC13: =+ROUND(N13*AC$6/(100+AC$6),0)+BI13 -> 0 | AD13: =+ROUND(O13*AD$6/(100+AD$6),0)+BJ13 -> 0 | AE13: =+ROUND(P13*AE$6/(100+AE$6),0)+BK13 -> 0 | AF13: =+ROUND(Q13*AF$6/(100+AF$6),0)+BL13 -> 0 | AG13: =+ROUND(R13*AG$6/(100+AG$6),0)+BM13 -> 0 | AH13: =SUM(AC13:AG13) -> 0 | AI13: =+E13-AB13 -> 120200000
C14: 112011300 | D14: 資本費平準化債 | E14: =+SUMIFS([1]全伝票!I:I,[1]全伝票!$C:$C,$C14) -> 5929500000 | K14: =SUM(F14:J14) -> 0 | S14: =SUM(N14:R14) -> 0 | U14: =+V14-SUM(S14:T14) -> 5929500000 | V14: =+SUMIFS([1]全伝票!P:P,[1]全伝票!$C:$C,$C14) -> 5929500000 | W14: =+ROUND(F14*F$6/(100+F$6),0)+AT14 -> 0 | X14: =+ROUND(G14*G$6/(100+G$6),0)+AU14 -> 0 | Y14: =+ROUND(H14*H$6/(100+H$6),0)+AV14 -> 0 | Z14: =+ROUND(I14*I$6/(100+I$6),0)+AW14 -> 0 | AA14: =+ROUND(J14*J$6/(100+J$6),0)+AX14 -> 0 | AB14: =SUM(W14:AA14) -> 0 | AC14: =+ROUND(N14*AC$6/(100+AC$6),0)+BI14 -> 0 | AD14: =+ROUND(O14*AD$6/(100+AD$6),0)+BJ14 -> 0 | AE14: =+ROUND(P14*AE$6/(100+AE$6),0)+BK14 -> 0 | AF14: =+ROUND(Q14*AF$6/(100+AF$6),0)+BL14 -> 0 | AG14: =+ROUND(R14*AG$6/(100+AG$6),0)+BM14 -> 0 | AH14: =SUM(AC14:AG14) -> 0 | AI14: =+E14-AB14 -> 5929500000
C15: 112011600 | D15: 災害復旧事業債 | E15: =+SUMIFS([1]全伝票!I:I,[1]全伝票!$C:$C,$C15) -> 0 | K15: =SUM(F15:J15) -> 0 | S15: =SUM(N15:R15) -> 0 | U15: =+V15-SUM(S15:T15) -> 0 | V15: =+SUMIFS([1]全伝票!P:P,[1]全伝票!$C:$C,$C15) -> 0 | W15: =+ROUND(F15*F$6/(100+F$6),0)+AT15 -> 0 | X15: =+ROUND(G15*G$6/(100+G$6),0)+AU15 -> 0 | Y15: =+ROUND(H15*H$6/(100+H$6),0)+AV15 -> 0 | Z15: =+ROUND(I15*I$6/(100+I$6),0)+AW15 -> 0 | AA15: =+ROUND(J15*J$6/(100+J$6),0)+AX15 -> 0 | AB15: =SUM(W15:AA15) -> 0 | AC15: =+ROUND(N15*AC$6/(100+AC$6),0)+BI15 -> 0 | AD15: =+ROUND(O15*AD$6/(100+AD$6),0)+BJ15 -> 0 | AE15: =+ROUND(P15*AE$6/(100+AE$6),0)+BK15 -> 0 | AF15: =+ROUND(Q15*AF$6/(100+AF$6),0)+BL15 -> 0 | AG15: =+ROUND(R15*AG$6/(100+AG$6),0)+BM15 -> 0 | AH15: =SUM(AC15:AG15) -> 0 | AI15: =+E15-AB15 -> 0
D16: 公共下水道事業借換債 | E16: =+SUM(E17:E19) -> 17007700000 | F16: =+SUM(F17:F19) -> 0 | G16: =+SUM(G17:G19) -> 0 | H16: =+SUM(H17:H19) -> 0 | I16: =+SUM(I17:I19) -> 0 | J16: =+SUM(J17:J19) -> 0 | K16: =+SUM(K17:K19) -> 0 | L16: =+SUM(L17:L19) -> 0 | ... AI16: =+SUM(AI17:AI19) -> 17007700000
C17: 112021000 | D17: 公共下水道事業借換債 | E17: =+SUMIFS([1]全伝票!I:I,[1]全伝票!$C:$C,$C17) -> 0 | K17: =SUM(F17:J17) -> 0 | S17: =SUM(N17:R17) -> 0 | U17: =+V17-SUM(S17:T17) -> 0 | V17: =+SUMIFS([1]全伝票!P:P,[1]全伝票!$C:$C,$C17) -> 0 | W17: =+ROUND(F17*F$6/(100+F$6),0)+AT17 -> 0 | X17: =+ROUND(G17*G$6/(100+G$6),0)+AU17 -> 0 | Y17: =+ROUND(H17*H$6/(100+H$6),0)+AV17 -> 0 | Z17: =+ROUND(I17*I$6/(100+I$6),0)+AW17 -> 0 | AA17: =+ROUND(J17*J$6/(100+J$6),0)+AX17 -> 0 | AB17: =SUM(W17:AA17) -> 0 | AC17: =+ROUND(N17*AC$6/(100+AC$6),0)+BI17 -> 0 | AD17: =+ROUND(O17*AD$6/(100+AD$6),0)+BJ17 -> 0 | AE17: =+ROUND(P17*AE$6/(100+AE$6),0)+BK17 -> 0 | AF17: =+ROUND(Q17*AF$6/(100+AF$6),0)+BL17 -> 0 | AG17: =+ROUND(R17*AG$6/(100+AG$6),0)+BM17 -> 0 | AH17: =SUM(AC17:AG17) -> 0 | AI17: =+E17-AB17 -> 0
C18: 112023000 | D18: 補償金免除繰上償還借換債 | E18: =+SUMIFS([1]全伝票!I:I,[1]全伝票!$C:$C,$C18) -> 0 | K18: =SUM(F18:J18) -> 0 | S18: =SUM(N18:R18) -> 0 | U18: =+V18-SUM(S18:T18) -> 0 | V18: =+SUMIFS([1]全伝票!P:P,[1]全伝票!$C:$C,$C18) -> 0 | W18: =+ROUND(F18*F$6/(100+F$6),0)+AT18 -> 0 | X18: =+ROUND(G18*G$6/(100+G$6),0)+AU18 -> 0 | Y18: =+ROUND(H18*H$6/(100+H$6),0)+AV18 -> 0 | Z18: =+ROUND(I18*I$6/(100+I$6),0)+AW18 -> 0 | AA18: =+ROUND(J18*J$6/(100+J$6),0)+AX18 -> 0 | AB18: =SUM(W18:AA18) -> 0 | AC18: =+ROUND(N18*AC$6/(100+AC$6),0)+BI18 -> 0 | AD18: =+ROUND(O18*AD$6/(100+AD$6),0)+BJ18 -> 0 | AE18: =+ROUND(P18*AE$6/(100+AE$6),0)+BK18 -> 0 | AF18: =+ROUND(Q18*AF$6/(100+AF$6),0)+BL18 -> 0 | AG18: =+ROUND(R18*AG$6/(100+AG$6),0)+BM18 -> 0 | AH18: =SUM(AC18:AG18) -> 0 | AI18: =+E18-AB18 -> 0
C19: 112024000 | D19: 資本費平準化債(拡大分)借換債 | E19: =+SUMIFS([1]全伝票!I:I,[1]全伝票!$C:$C,$C19) -> 17007700000 | K19: =SUM(F19:J19) -> 0 | S19: =SUM(N19:R19) -> 0 | U19: =+V19-SUM(S19:T19) -> 17007700000 | V19: =+SUMIFS([1]全伝票!P:P,[1]全伝票!$C:$C,$C19) -> 17007700000 | W19: =+ROUND(F19*F$6/(100+F$6),0)+AT19 -> 0 | X19: =+ROUND(G19*G$6/(100+G$6),0)+AU19 -> 0 | Y19: =+ROUND(H19*H$6/(100+H$6),0)+AV19 -> 0 | Z19: =+ROUND(I19*I$6/(100+I$6),0)+AW19 -> 0 | AA19: =+ROUND(J19*J$6/(100+J$6),0)+AX19 -> 0 | AB19: =SUM(W19:AA19) -> 0 | AC19: =+ROUND(N19*AC$6/(100+AC$6),0)+BI19 -> 0 | AD19: =+ROUND(O19*AD$6/(100+AD$6),0)+BJ19 -> 0 | AE19: =+ROUND(P19*AE$6/(100+AE$6),0)+BK19 -> 0 | AF19: =+ROUND(Q19*AF$6/(100+AF$6),0)+BL19 -> 0 | AG19: =+ROUND(R19*AG$6/(100+AG$6),0)+BM19 -> 0 | AH19: =SUM(AC19:AG19) -> 0 | AI19: =+E19-AB19 -> 17007700000
C20: 112031000 | D20: 出資債 | E20: =+SUMIFS([1]全伝票!I:I,[1]全伝票!$C:$C,$C20) -> 0 | K20: =SUM(F20:J20) -> 0 | S20: =SUM(N20:R20) -> 0 | U20: =+V20-SUM(S20:T20) -> 0 | V20: =+SUMIFS([1]全伝票!P:P,[1]全伝票!$C:$C,$C20) -> 0 | W20: =+ROUND(F20*F$6/(100+F$6),0)+AT20 -> 0 | X20: =+ROUND(G20*G$6/(100+G$6),0)+AU20 -> 0 | Y20: =+ROUND(H20*H$6/(100+H$6),0)+AV20 -> 0 | Z20: =+ROUND(I20*I$6/(100+I$6),0)+AW20 -> 0 | AA20: =+ROUND(J20*J$6/(100+J$6),0)+AX20 -> 0 | AB20: =SUM(W20:AA20) -> 0 | AC20: =+ROUND(N20*AC$6/(100+AC$6),0)+BI20 -> 0 | AD20: =+ROUND(O20*AD$6/(100+AD$6),0)+BJ20 -> 0 | AE20: =+ROUND(P20*AE$6/(100+AE$6),0)+BK20 -> 0 | AF20: =+ROUND(Q20*AF$6/(100+AF$6),0)+BL20 -> 0 | AG20: =+ROUND(R20*AG$6/(100+AG$6),0)+BM20 -> 0 | AH20: =SUM(AC20:AG20) -> 0 | AI20: =+E20-AB20 -> 0
D21: 一般会計出資金 | E21: =+E22 -> 3285504551 | F21: =+F22 -> 0 | G21: =+G22 -> 0 | H21: =+H22 -> 0 | I21: =+I22 -> 0 | J21: =+J22 -> 0 | K21: =+K22 -> 0 | L21: =+L22 -> 0 | ... AI21: =+AI22 -> 3285504551
C22: 116010100 | D22: 下水道建設費出資金 | E22: =+'[2](繰)案'!E39 -> 3285504551 | K22: =SUM(F22:J22) -> 0 | S22: =SUM(N22:R22) -> 0 | U22: =+V22-SUM(S22:T22) -> 3285504551 | V22: =+E22 -> 3285504551 | W22: =+ROUND(F22*F$6/(100+F$6),0)+AT22 -> 0 | X22: =+ROUND(G22*G$6/(100+G$6),0)+AU22 -> 0 | Y22: =+ROUND(H22*H$6/(100+H$6),0)+AV22 -> 0 | Z22: =+ROUND(I22*I$6/(100+I$6),0)+AW22 -> 0 | AA22: =+ROUND(J22*J$6/(100+J$6),0)+AX22 -> 0 | AB22: =SUM(W22:AA22) -> 0 | AC22: =+ROUND(N22*AC$6/(100+AC$6),0)+BI22 -> 0 | AD22: =+ROUND(O22*AD$6/(100+AD$6),0)+BJ22 -> 0 | AE22: =+ROUND(P22*AE$6/(100+AE$6),0)+BK22 -> 0 | AF22: =+ROUND(Q22*AF$6/(100+AF$6),0)+BL22 -> 0 | AG22: =+ROUND(R22*AG$6/(100+AG$6),0)+BM22 -> 0 | AH22: =SUM(AC22:AG22) -> 0 | AI22: =+E22-AB22 -> 3285504551
D23: 国庫補助金 | E23: =+E24 -> 5717788000 | F23: =+F24 -> 0 | G23: =+G24 -> 0 | H23: =+H24 -> 0 | I23: =+I24 -> 0 | J23: =+J24 -> 0 | K23: =+K24 -> 0 | L23: =+L24 -> 0 | ... AI23: =+AI24 -> 5717788000
D24: 国庫補助金 | E24: =SUM(E25:E26,E31) -> 5717788000 | F24: =SUM(F25:F26,F31) -> 0 | G24: =SUM(G25:G26,G31) -> 0 | H24: =SUM(H25:H26,H31) -> 0 | I24: =SUM(I25:I26,I31) -> 0 | J24: =SUM(J25:J26,J31) -> 0 | K24: =SUM(K25:K26,K31) -> 0 | L24: =SUM(L25:L26,L31) -> 0 | ... AI24: =SUM(AI25:AI26,AI31) -> 5717788000
C25: 118040101 | D25: 公共下水道事整備国庫補助金 | E25: =+SUMIFS([1]全伝票!I:I,[1]全伝票!$C:$C,$C25) -> 5683800000 | K25: =SUM(F25:J25) -> 0 | L25: =+SUMIFS([1]全伝票!O:O,[1]全伝票!$C:$C,$C25) -> 0 | O25: =+'[3]4条補助（公）'!K$6 -> 0 | P25: =+'[3]4条補助（公）'!L$6 -> 0 | Q25: =+'[3]4条補助（公）'!M$6 -> 0 | R25: =+'[3]4条補助（公）'!N$6 -> 5678297006 | S25: =SUM(N25:R25) -> 5678297006 | T25: =SUM('[3]4条補助（公）'!$I$6) -> 5502994 | U25: =+V25-SUM(S25:T25) -> 0 | V25: =+SUMIFS([1]全伝票!P:P,[1]全伝票!$C:$C,$C25) -> 5683800000 | W25: =+ROUND(F25*F$6/(100+F$6),0)+AT25 -> 0 | X25: =+ROUND(G25*G$6/(100+G$6),0)+AU25 -> 0 | Y25: =+ROUND(H25*H$6/(100+H$6),0)+AV25 -> 0 | Z25: =+ROUND(I25*I$6/(100+I$6),0)+AW25 -> 0 | AA25: =+ROUND(J25*J$6/(100+J$6),0)+AX25 -> 0 | AB25: =SUM(W25:AA25) -> 0 | AC25: =+ROUND(N25*AC$6/(100+AC$6),0)+BI25 -> 0 | AD25: =+ROUND(O25*AD$6/(100+AD$6),0)+BJ25 -> 0 | AE25: =+ROUND(P25*AE$6/(100+AE$6),0)+BK25 -> 0 | AF25: =+ROUND(Q25*AF$6/(100+AF$6),0)+BL25 -> 0 | AG25: =+ROUND(R25*AG$6/(100+AG$6),0)+BM25 -> 516208819 | AH25: =SUM(AC25:AG25) -> 516208819 | AI25: =+E25-AB25 -> 5683800000 | AY25: =AC25-N25*AC$6/(100+AC$6) -> 0 | AZ25: =AD25-O25*AD$6/(100+AD$6) -> 0 | BA25: =AE25-P25*AE$6/(100+AE$6) -> 0 | BB25: =AF25-Q25*AF$6/(100+AF$6) -> 0 | BC25: =AG25-R25*AG$6/(100+AG$6) -> 0.27272725 | BD25: =+IF(AC$93=0,0,IF(AC$93<0,-RANK(AY25,AY$7:AY$90,0),RANK(AY25,AY$7:AY$90,1))) -> 0 | BE25: =+IF(AD$93=0,0,IF(AD$93<0,-RANK(AZ25,AZ$7:AZ$90,0),RANK(AZ25,AZ$7:AZ$90,1))) -> 0 | BF25: =+IF(AE$93=0,0,IF(AE$93<0,-RANK(BA25,BA$7:BA$90,0),RANK(BA25,BA$7:BA$90,1))) -> 0 | BG25: =+IF(AF$93=0,0,IF(AF$93<0,-RANK(BB25,BB$7:BB$90,0),RANK(BB25,BB$7:BB$90,1))) -> 0 | BH25: =+IF(AG$93=0,0,IF(AG$93<0,-RANK(BC25,BC$7:BC$90,0),RANK(BC25,BC$7:BC$90,1))) -> 0
D26: その他国庫補助金 | E26: =SUM(E27:E30) -> 0 | K26: =SUM(K27:K30) -> 0 | L26: =SUM(L27:L30) -> 0 | M26: =SUM(M27:M30) -> 0 | N26: =SUM(N27:N30) -> 0 | O26: =SUM(O27:O30) -> 0 | P26: =SUM(P27:P30) -> 0 | Q26: =SUM(Q27:Q30) -> 0 | R26: =SUM(R27:R30) -> 0 | ... AA26: =SUM(AA27:AA30) -> 0 | AB26: =SUM(W26:AA26) -> 0 | AC26: =SUM(AC27:AC30) -> 0 | AD26: =SUM(AD27:AD30) -> 0 | AE26: =SUM(AE27:AE30) -> 0 | AF26: =SUM(AF27:AF30) -> 0 | AG26: =SUM(AG27:AG30) -> 0 | AH26: =SUM(AC26:AG26) -> 0 | AI26: =SUM(AI27:AI30) -> 0
A27: 1 | C27: 118040200 | D27: 公共 | E27: =SUMIFS([1]全伝票!I:I,[1]全伝票!$C:$C,$C27,[1]全伝票!$A:$A,$A27) -> 0 | K27: =SUM(F27:J27) -> 0 | O27: ='[3]4条その他'!K$9 -> 0 | P27: ='[3]4条その他'!L$9 -> 0 | Q27: ='[3]4条その他'!M$9 -> 0 | R27: ='[3]4条その他'!N$9 -> 0 | S27: =SUM(N27:R27) -> 0 | T27: ='[3]4条その他'!I$8 -> 0 | U27: =+V27-SUM(S27:T27) -> 0 | V27: =SUMIFS([1]全伝票!P:P,[1]全伝票!$C:$C,$C27,[1]全伝票!$A:$A,$A27) -> 0 | W27: =+ROUND(F27*F$6/(100+F$6),0)+AT27 -> 0 | X27: =+ROUND(G27*G$6/(100+G$6),0)+AU27 -> 0 | Y27: =+ROUND(H27*H$6/(100+H$6),0)+AV27 -> 0 | Z27: =+ROUND(I27*I$6/(100+I$6),0)+AW27 -> 0 | AA27: =+ROUND(J27*J$6/(100+J$6),0)+AX27 -> 0 | AB27: =SUM(W27:AA27) -> 0 | AC27: =+ROUND(N27*AC$6/(100+AC$6),0)+BI27 -> 0 | AD27: =+ROUND(O27*AD$6/(100+AD$6),0)+BJ27 -> 0 | AE27: =+ROUND(P27*AE$6/(100+AE$6),0)+BK27 -> 0 | AF27: =+ROUND(Q27*AF$6/(100+AF$6),0)+BL27 -> 0 | AG27: =+ROUND(R27*AG$6/(100+AG$6),0)+BM27 -> 0 | AH27: =SUM(AC27:AG27) -> 0 | AI27: =+E27-AB27 -> 0 | AY27: =AC27-N27*AC$6/(100+AC$6) -> 0 | AZ27: =AD27-O27*AD$6/(100+AD$6) -> 0 | BA27: =AE27-P27*AE$6/(100+AE$6) -> 0 | BB27: =AF27-Q27*AF$6/(100+AF$6) -> 0 | BC27: =AG27-R27*AG$6/(100+AG$6) -> 0 | BD27: =+IF(AC$93=0,0,IF(AC$93<0,-RANK(AY27,AY$7:AY$90,0),RANK(AY27,AY$7:AY$90,1))) -> 0 | BE27: =+IF(AD$93=0,0,IF(AD$93<0,-RANK(AZ27,AZ$7:AZ$90,0),RANK(AZ27,AZ$7:AZ$90,1))) -> 0 | BF27: =+IF(AE$93=0,0,IF(AE$93<0,-RANK(BA27,BA$7:BA$90,0),RANK(BA27,BA$7:BA$90,1))) -> 0 | BG27: =+IF(AF$93=0,0,IF(AF$93<0,-RANK(BB27,BB$7:BB$90,0),RANK(BB27,BB$7:BB$90,1))) -> 0 | BH27: =+IF(AG$93=0,0,IF(AG$93<0,-RANK(BC27,BC$7:BC$90,0),RANK(BC27,BC$7:BC$90,1))) -> 0
A28: 2 | C28: 118040200 | D28: 特環 | E28: =SUMIFS([1]全伝票!I:I,[1]全伝票!$C:$C,$C28,[1]全伝票!$A:$A,$A28) -> 0 | K28: =SUM(F28:J28) -> 0 | O28: ='[3]4条その他'!K$23 -> 0 | P28: ='[3]4条その他'!L$23 -> 0 | Q28: ='[3]4条その他'!M$23 -> 0 | R28: ='[3]4条その他'!N$23 -> 0 | S28: =SUM(N28:R28) -> 0 | T28: ='[3]4条その他'!I$22 -> 0 | U28: =+V28-SUM(S28:T28) -> 0 | V28: =SUMIFS([1]全伝票!P:P,[1]全伝票!$C:$C,$C28,[1]全伝票!$A:$A,$A28) -> 0 | W28: =+ROUND(F28*F$6/(100+F$6),0)+AT28 -> 0 | X28: =+ROUND(G28*G$6/(100+G$6),0)+AU28 -> 0 | Y28: =+ROUND(H28*H$6/(100+H$6),0)+AV28 -> 0 | Z28: =+ROUND(I28*I$6/(100+I$6),0)+AW28 -> 0 | AA28: =+ROUND(J28*J$6/(100+J$6),0)+AX28 -> 0 | AB28: =SUM(W28:AA28) -> 0 | AC28: =+ROUND(N28*AC$6/(100+AC$6),0)+BI28 -> 0 | AD28: =+ROUND(O28*AD$6/(100+AD$6),0)+BJ28 -> 0 | AE28: =+ROUND(P28*AE$6/(100+AE$6),0)+BK28 -> 0 | AF28: =+ROUND(Q28*AF$6/(100+AF$6),0)+BL28 -> 0 | AG28: =+ROUND(R28*AG$6/(100+AG$6),0)+BM28 -> 0 | AH28: =SUM(AC28:AG28) -> 0 | AI28: =+E28-AB28 -> 0 | AY28: =AC28-N28*AC$6/(100+AC$6) -> 0 | AZ28: =AD28-O28*AD$6/(100+AD$6) -> 0 | BA28: =AE28-P28*AE$6/(100+AE$6) -> 0 | BB28: =AF28-Q28*AF$6/(100+AF$6) -> 0 | BC28: =AG28-R28*AG$6/(100+AG$6) -> 0 | BD28: =+IF(AC$93=0,0,IF(AC$93<0,-RANK(AY28,AY$7:AY$90,0),RANK(AY28,AY$7:AY$90,1))) -> 0 | BE28: =+IF(AD$93=0,0,IF(AD$93<0,-RANK(AZ28,AZ$7:AZ$90,0),RANK(AZ28,AZ$7:AZ$90,1))) -> 0 | BF28: =+IF(AE$93=0,0,IF(AE$93<0,-RANK(BA28,BA$7:BA$90,0),RANK(BA28,BA$7:BA$90,1))) -> 0 | BG28: =+IF(AF$93=0,0,IF(AF$93<0,-RANK(BB28,BB$7:BB$90,0),RANK(BB28,BB$7:BB$90,1))) -> 0 | BH28: =+IF(AG$93=0,0,IF(AG$93<0,-RANK(BC28,BC$7:BC$90,0),RANK(BC28,BC$7:BC$90,1))) -> 0
A29: 3 | C29: 118040200 | D29: 農集 | E29: =SUMIFS([1]全伝票!I:I,[1]全伝票!$C:$C,$C29,[1]全伝票!$A:$A,$A29) -> 0 | K29: =SUM(F29:J29) -> 0 | O29: ='[3]4条その他'!K$37 -> 0 | P29: ='[3]4条その他'!L$37 -> 0 | Q29: ='[3]4条その他'!M$37 -> 0 | R29: ='[3]4条その他'!N$37 -> 0 | S29: =SUM(N29:R29) -> 0 | T29: ='[3]4条その他'!I$36 -> 0 | U29: =+V29-SUM(S29:T29) -> 0 | V29: =SUMIFS([1]全伝票!P:P,[1]全伝票!$C:$C,$C29,[1]全伝票!$A:$A,$A29) -> 0 | W29: =+ROUND(F29*F$6/(100+F$6),0)+AT29 -> 0 | X29: =+ROUND(G29*G$6/(100+G$6),0)+AU29 -> 0 | Y29: =+ROUND(H29*H$6/(100+H$6),0)+AV29 -> 0 | Z29: =+ROUND(I29*I$6/(100+I$6),0)+AW29 -> 0 | AA29: =+ROUND(J29*J$6/(100+J$6),0)+AX29 -> 0 | AB29: =SUM(W29:AA29) -> 0 | AC29: =+ROUND(N29*AC$6/(100+AC$6),0)+BI29 -> 0 | AD29: =+ROUND(O29*AD$6/(100+AD$6),0)+BJ29 -> 0 | AE29: =+ROUND(P29*AE$6/(100+AE$6),0)+BK29 -> 0 | AF29: =+ROUND(Q29*AF$6/(100+AF$6),0)+BL29 -> 0 | AG29: =+ROUND(R29*AG$6/(100+AG$6),0)+BM29 -> 0 | AH29: =SUM(AC29:AG29) -> 0 | AI29: =+E29-AB29 -> 0 | AY29: =AC29-N29*AC$6/(100+AC$6) -> 0 | AZ29: =AD29-O29*AD$6/(100+AD$6) -> 0 | BA29: =AE29-P29*AE$6/(100+AE$6) -> 0 | BB29: =AF29-Q29*AF$6/(100+AF$6) -> 0 | BC29: =AG29-R29*AG$6/(100+AG$6) -> 0 | BD29: =+IF(AC$93=0,0,IF(AC$93<0,-RANK(AY29,AY$7:AY$90,0),RANK(AY29,AY$7:AY$90,1))) -> 0 | BE29: =+IF(AD$93=0,0,IF(AD$93<0,-RANK(AZ29,AZ$7:AZ$90,0),RANK(AZ29,AZ$7:AZ$90,1))) -> 0 | BF29: =+IF(AE$93=0,0,IF(AE$93<0,-RANK(BA29,BA$7:BA$90,0),RANK(BA29,BA$7:BA$90,1))) -> 0 | BG29: =+IF(AF$93=0,0,IF(AF$93<0,-RANK(BB29,BB$7:BB$90,0),RANK(BB29,BB$7:BB$90,1))) -> 0 | BH29: =+IF(AG$93=0,0,IF(AG$93<0,-RANK(BC29,BC$7:BC$90,0),RANK(BC29,BC$7:BC$90,1))) -> 0
A30: 4 | C30: 118040200 | D30: 浄化槽 | E30: =SUMIFS([1]全伝票!I:I,[1]全伝票!$C:$C,$C30,[1]全伝票!$A:$A,$A30) -> 0 | K30: =SUM(F30:J30) -> 0 | O30: ='[3]4条その他'!K$51 -> 0 | P30: ='[3]4条その他'!L$51 -> 0 | Q30: ='[3]4条その他'!M$51 -> 0 | R30: ='[3]4条その他'!N$51 -> 0 | S30: =SUM(N30:R30) -> 0 | T30: ='[3]4条その他'!I$50 -> 0 | U30: =+V30-SUM(S30:T30) -> 0 | V30: =SUMIFS([1]全伝票!P:P,[1]全伝票!$C:$C,$C30,[1]全伝票!$A:$A,$A30) -> 0 | W30: =+ROUND(F30*F$6/(100+F$6),0)+AT30 -> 0 | X30: =+ROUND(G30*G$6/(100+G$6),0)+AU30 -> 0 | Y30: =+ROUND(H30*H$6/(100+H$6),0)+AV30 -> 0 | Z30: =+ROUND(I30*I$6/(100+I$6),0)+AW30 -> 0 | AA30: =+ROUND(J30*J$6/(100+J$6),0)+AX30 -> 0 | AB30: =SUM(W30:AA30) -> 0 | AC30: =+ROUND(N30*AC$6/(100+AC$6),0)+BI30 -> 0 | AD30: =+ROUND(O30*AD$6/(100+AD$6),0)+BJ30 -> 0 | AE30: =+ROUND(P30*AE$6/(100+AE$6),0)+BK30 -> 0 | AF30: =+ROUND(Q30*AF$6/(100+AF$6),0)+BL30 -> 0 | AG30: =+ROUND(R30*AG$6/(100+AG$6),0)+BM30 -> 0 | AH30: =SUM(AC30:AG30) -> 0 | AI30: =+E30-AB30 -> 0 | AY30: =AC30-N30*AC$6/(100+AC$6) -> 0 | AZ30: =AD30-O30*AD$6/(100+AD$6) -> 0 | BA30: =AE30-P30*AE$6/(100+AE$6) -> 0 | BB30: =AF30-Q30*AF$6/(100+AF$6) -> 0 | BC30: =AG30-R30*AG$6/(100+AG$6) -> 0 | BD30: =+IF(AC$93=0,0,IF(AC$93<0,-RANK(AY30,AY$7:AY$90,0),RANK(AY30,AY$7:AY$90,1))) -> 0 | BE30: =+IF(AD$93=0,0,IF(AD$93<0,-RANK(AZ30,AZ$7:AZ$90,0),RANK(AZ30,AZ$7:AZ$90,1))) -> 0 | BF30: =+IF(AE$93=0,0,IF(AE$93<0,-RANK(BA30,BA$7:BA$90,0),RANK(BA30,BA$7:BA$90,1))) -> 0 | BG30: =+IF(AF$93=0,0,IF(AF$93<0,-RANK(BB30,BB$7:BB$90,0),RANK(BB30,BB$7:BB$90,1))) -> 0 | BH30: =+IF(AG$93=0,0,IF(AG$93<0,-RANK(BC30,BC$7:BC$90,0),RANK(BC30,BC$7:BC$90,1))) -> 0
D31: 公共下水道事整備国庫補助金ほか | E31: =+SUM(E32:E34) -> 33988000 | F31: =+SUM(F32:F34) -> 0 | G31: =+SUM(G32:G34) -> 0 | H31: =+SUM(H32:H34) -> 0 | I31: =+SUM(I32:I34) -> 0 | J31: =+SUM(J32:J34) -> 0 | K31: =+SUM(K32:K34) -> 0 | L31: =+SUM(L32:L34) -> 0 | ... V31: =+SUM(V32:V34) -> 33988000 | W31: =+ROUND(F31*F$6/(100+F$6),0)+AT31 -> 0 | X31: =+ROUND(G31*G$6/(100+G$6),0)+AU31 -> 0 | Y31: =+ROUND(H31*H$6/(100+H$6),0)+AV31 -> 0 | Z31: =+ROUND(I31*I$6/(100+I$6),0)+AW31 -> 0 | AA31: =+ROUND(J31*J$6/(100+J$6),0)+AX31 -> 0 | AB31: =SUM(W31:AA31) -> 0 | AC31: =+SUM(AC32:AC34) -> 0 | AD31: =+SUM(AD32:AD34) -> 0 | AE31: =+SUM(AE32:AE34) -> 0 | AF31: =+SUM(AF32:AF34) -> 0 | AG31: =+SUM(AG32:AG34) -> 3089818 | AH31: =SUM(AC31:AG31) -> 3089818 | AI31: =+E31-AB31 -> 33988000
A32: 2 | C32: 118040103 | D32: 特環 | E32: =+SUMIFS([1]全伝票!I:I,[1]全伝票!$C:$C,$C32,[1]全伝票!$A:$A,'4条収入'!$A32) -> 30500000 | K32: =SUM(F32:J32) -> 0 | O32: =+'[3]4条補助（特）'!K$6 -> 0 | P32: =+'[3]4条補助（特）'!L$6 -> 0 | Q32: =+'[3]4条補助（特）'!M$6 -> 0 | R32: =+'[3]4条補助（特）'!N$6 -> 30500000 | S32: =SUM(N32:R32) -> 30500000 | T32: =+'[3]4条補助（特）'!$I$6 -> 0 | U32: =+V32-SUM(S32:T32) -> 0 | V32: =+SUMIFS([1]全伝票!P:P,[1]全伝票!$C:$C,$C32,[1]全伝票!$A:$A,'4条収入'!$A32) -> 30500000 | W32: =+ROUND(F32*F$6/(100+F$6),0)+AT32 -> 0 | X32: =+ROUND(G32*G$6/(100+G$6),0)+AU32 -> 0 | Y32: =+ROUND(H32*H$6/(100+H$6),0)+AV32 -> 0 | Z32: =+ROUND(I32*I$6/(100+I$6),0)+AW32 -> 0 | AA32: =+ROUND(J32*J$6/(100+J$6),0)+AX32 -> 0 | AB32: =SUM(W32:AA32) -> 0 | AC32: =+ROUND(N32*AC$6/(100+AC$6),0)+BI32 -> 0 | AD32: =+ROUND(O32*AD$6/(100+AD$6),0)+BJ32 -> 0 | AE32: =+ROUND(P32*AE$6/(100+AE$6),0)+BK32 -> 0 | AF32: =+ROUND(Q32*AF$6/(100+AF$6),0)+BL32 -> 0 | AG32: =+ROUND(R32*AG$6/(100+AG$6),0)+BM32 -> 2772727 | AH32: =SUM(AC32:AG32) -> 2772727 | AI32: =+E32-AB32 -> 30500000
A33: 3 | C33: 118040400 | D33: 農集 | E33: =+SUMIFS([1]全伝票!I:I,[1]全伝票!$C:$C,$C33,[1]全伝票!$A:$A,'4条収入'!$A33) -> 0 | K33: =SUM(F33:J33) -> 0 | O33: =+'[3]4条補助（農）'!K$6 -> 0 | P33: =+'[3]4条補助（農）'!L$6 -> 0 | Q33: =+'[3]4条補助（農）'!M$6 -> 0 | R33: =+'[3]4条補助（農）'!N$6 -> 0 | S33: =SUM(N33:R33) -> 0 | T33: =+'[3]4条補助（農）'!$I$6 -> 0 | U33: =+V33-SUM(S33:T33) -> 0 | V33: =+SUMIFS([1]全伝票!P:P,[1]全伝票!$C:$C,$C33,[1]全伝票!$A:$A,'4条収入'!$A33) -> 0 | W33: =+ROUND(F33*F$6/(100+F$6),0)+AT33 -> 0 | X33: =+ROUND(G33*G$6/(100+G$6),0)+AU33 -> 0 | Y33: =+ROUND(H33*H$6/(100+H$6),0)+AV33 -> 0 | Z33: =+ROUND(I33*I$6/(100+I$6),0)+AW33 -> 0 | AA33: =+ROUND(J33*J$6/(100+J$6),0)+AX33 -> 0 | AB33: =SUM(W33:AA33) -> 0 | AC33: =+ROUND(N33*AC$6/(100+AC$6),0)+BI33 -> 0 | AD33: =+ROUND(O33*AD$6/(100+AD$6),0)+BJ33 -> 0 | AE33: =+ROUND(P33*AE$6/(100+AE$6),0)+BK33 -> 0 | AF33: =+ROUND(Q33*AF$6/(100+AF$6),0)+BL33 -> 0 | AG33: =+ROUND(R33*AG$6/(100+AG$6),0)+BM33 -> 0 | AH33: =SUM(AC33:AG33) -> 0 | AI33: =+E33-AB33 -> 0
A34: 4 | C34: 118040400 | D34: 浄化槽 | E34: =+SUMIFS([1]全伝票!I:I,[1]全伝票!$C:$C,$C34,[1]全伝票!$A:$A,'4条収入'!$A34) -> 3488000 | K34: =SUM(F34:J34) -> 0 | O34: =+'[3]4条補助（浄）'!K$6 -> 0 | P34: =+'[3]4条補助（浄）'!L$6 -> 0 | Q34: =+'[3]4条補助（浄）'!M$6 -> 0 | R34: =+'[3]4条補助（浄）'!N$6 -> 3488000 | S34: =SUM(N34:R34) -> 3488000 | T34: =+'[3]4条補助（浄）'!$I$6 -> 0 | U34: =+V34-SUM(S34:T34) -> 0 | V34: =+SUMIFS([1]全伝票!P:P,[1]全伝票!$C:$C,$C34,[1]全伝票!$A:$A,'4条収入'!$A34) -> 3488000 | W34: =+ROUND(F34*F$6/(100+F$6),0)+AT34 -> 0 | X34: =+ROUND(G34*G$6/(100+G$6),0)+AU34 -> 0 | Y34: =+ROUND(H34*H$6/(100+H$6),0)+AV34 -> 0 | Z34: =+ROUND(I34*I$6/(100+I$6),0)+AW34 -> 0 | AA34: =+ROUND(J34*J$6/(100+J$6),0)+AX34 -> 0 | AB34: =SUM(W34:AA34) -> 0 | AC34: =+ROUND(N34*AC$6/(100+AC$6),0)+BI34 -> 0 | AD34: =+ROUND(O34*AD$6/(100+AD$6),0)+BJ34 -> 0 | AE34: =+ROUND(P34*AE$6/(100+AE$6),0)+BK34 -> 0 | AF34: =+ROUND(Q34*AF$6/(100+AF$6),0)+BL34 -> 0 | AG34: =+ROUND(R34*AG$6/(100+AG$6),0)+BM34 -> 317091 | AH34: =SUM(AC34:AG34) -> 317091 | AI34: =+E34-AB34 -> 3488000
D35: 県補助金 | E35: =+E36 -> 0 | F35: =+F36 -> 0 | G35: =+G36 -> 0 | H35: =+H36 -> 0 | I35: =+I36 -> 0 | J35: =+J36 -> 0 | K35: =+K36 -> 0 | L35: =+L36 -> 0 | ... AI35: =+AI36 -> 0
C36: 119040100 | D36: 県補助金 | E36: =+SUMIFS([1]全伝票!I:I,[1]全伝票!$C:$C,$C36) -> 0 | K36: =SUM(F36:J36) -> 0 | S36: =SUM(N36:R36) -> 0 | U36: =+V36-SUM(S36:T36) -> 0 | V36: =+SUMIFS([1]全伝票!P:P,[1]全伝票!$C:$C,$C36) -> 0 | W36: =+ROUND(F36*F$6/(100+F$6),0)+AT36 -> 0 | X36: =+ROUND(G36*G$6/(100+G$6),0)+AU36 -> 0 | Y36: =+ROUND(H36*H$6/(100+H$6),0)+AV36 -> 0 | Z36: =+ROUND(I36*I$6/(100+I$6),0)+AW36 -> 0 | AA36: =+ROUND(J36*J$6/(100+J$6),0)+AX36 -> 0 | AB36: =SUM(W36:AA36) -> 0 | AC36: =+ROUND(N36*AC$6/(100+AC$6),0)+BI36 -> 0 | AD36: =+ROUND(O36*AD$6/(100+AD$6),0)+BJ36 -> 0 | AE36: =+ROUND(P36*AE$6/(100+AE$6),0)+BK36 -> 0 | AF36: =+ROUND(Q36*AF$6/(100+AF$6),0)+BL36 -> 0 | AG36: =+ROUND(R36*AG$6/(100+AG$6),0)+BM36 -> 0 | AH36: =SUM(AC36:AG36) -> 0 | AI36: =+E36-AB36 -> 0 | AY36: =AC36-N36*AC$6/(100+AC$6) -> 0 | AZ36: =AD36-O36*AD$6/(100+AD$6) -> 0 | BA36: =AE36-P36*AE$6/(100+AE$6) -> 0 | BB36: =AF36-Q36*AF$6/(100+AF$6) -> 0 | BC36: =AG36-R36*AG$6/(100+AG$6) -> 0 | BD36: =+IF(AC$93=0,0,IF(AC$93<0,-RANK(AY36,AY$7:AY$90,0),RANK(AY36,AY$7:AY$90,1))) -> 0 | BE36: =+IF(AD$93=0,0,IF(AD$93<0,-RANK(AZ36,AZ$7:AZ$90,0),RANK(AZ36,AZ$7:AZ$90,1))) -> 0 | BF36: =+IF(AE$93=0,0,IF(AE$93<0,-RANK(BA36,BA$7:BA$90,0),RANK(BA36,BA$7:BA$90,1))) -> 0 | BG36: =+IF(AF$93=0,0,IF(AF$93<0,-RANK(BB36,BB$7:BB$90,0),RANK(BB36,BB$7:BB$90,1))) -> 0 | BH36: =+IF(AG$93=0,0,IF(AG$93<0,-RANK(BC36,BC$7:BC$90,0),RANK(BC36,BC$7:BC$90,1))) -> 0
D37: 工事受託金 | E37: =+E38 -> 24373083 | F37: =+F38 -> 0 | G37: =+G38 -> 0 | H37: =+H38 -> 0 | I37: =+I38 -> 0 | J37: =+J38 -> 24373083 | K37: =+K38 -> 24373083 | L37: =+L38 -> 0 | ... AI37: =+AI38 -> 22157348
D38: 工事受託金 | E38: =+SUM(E39:E41) -> 24373083 | F38: =+SUM(F39:F41) -> 0 | G38: =+SUM(G39:G41) -> 0 | H38: =+SUM(H39:H41) -> 0 | I38: =+SUM(I39:I41) -> 0 | J38: =+SUM(J39:J41) -> 24373083 | K38: =+SUM(K39:K41) -> 24373083 | L38: =+SUM(L39:L41) -> 0 | ... AA38: =+SUM(AA39:AA41) -> 2215735 | AB38: =SUM(W38:AA38) -> 2215735 | AC38: =+ROUND(N38*AC$6/(100+AC$6),0)+BI38 -> 0 | AD38: =+ROUND(O38*AD$6/(100+AD$6),0)+BJ38 -> 0 | AE38: =+ROUND(P38*AE$6/(100+AE$6),0)+BK38 -> 0 | AF38: =+ROUND(Q38*AF$6/(100+AF$6),0)+BL38 -> 0 | AG38: =+ROUND(R38*AG$6/(100+AG$6),0)+BM38 -> 0 | AH38: =SUM(AC38:AG38) -> 0 | AI38: =+E38-AB38 -> 22157348
A39: 1 | C39: 160010100 | D39: 公共 | E39: =+SUMIFS([1]全伝票!I:I,[1]全伝票!$C:$C,$C39,[1]全伝票!$A:$A,$A39) -> 24373083 | F39: =+SUMIFS([1]全伝票!J:J,[1]全伝票!$C:$C,$C39,[1]全伝票!$A:$A,$A39) -> 0 | G39: =+SUMIFS([1]全伝票!K:K,[1]全伝票!$C:$C,$C39,[1]全伝票!$A:$A,$A39) -> 0 | H39: =+SUMIFS([1]全伝票!L:L,[1]全伝票!$C:$C,$C39,[1]全伝票!$A:$A,$A39) -> 0 | I39: =+SUMIFS([1]全伝票!M:M,[1]全伝票!$C:$C,$C39,[1]全伝票!$A:$A,$A39) -> 0 | J39: =+SUMIFS([1]全伝票!N:N,[1]全伝票!$C:$C,$C39,[1]全伝票!$A:$A,$A39) -> 24373083 | K39: =SUM(F39:J39) -> 24373083 | L39: =+SUMIFS([1]全伝票!O:O,[1]全伝票!$C:$C,$C39,[1]全伝票!$A:$A,$A39) -> 0 | S39: =SUM(N39:R39) -> 0 | U39: =+V39-SUM(S39:T39) -> 0 | V39: =+SUMIFS([1]全伝票!P:P,[1]全伝票!$C:$C,$C39,[1]全伝票!$A:$A,'4条収入'!$A39) -> 0 | W39: =+ROUND(F39*F$6/(100+F$6),0)+AT39 -> 0 | X39: =+ROUND(G39*G$6/(100+G$6),0)+AU39 -> 0 | Y39: =+ROUND(H39*H$6/(100+H$6),0)+AV39 -> 0 | Z39: =+ROUND(I39*I$6/(100+I$6),0)+AW39 -> 0 | AA39: =+ROUND(J39*J$6/(100+J$6),0)+AX39 -> 2215735 | AB39: =SUM(W39:AA39) -> 2215735 | AC39: =+ROUND(N39*AC$6/(100+AC$6),0)+BI39 -> 0 | AD39: =+ROUND(O39*AD$6/(100+AD$6),0)+BJ39 -> 0 | AE39: =+ROUND(P39*AE$6/(100+AE$6),0)+BK39 -> 0 | AF39: =+ROUND(Q39*AF$6/(100+AF$6),0)+BL39 -> 0 | AG39: =+ROUND(R39*AG$6/(100+AG$6),0)+BM39 -> 0 | AH39: =SUM(AC39:AG39) -> 0 | AI39: =+E39-AB39 -> 22157348 | AJ39: =W39-F39*W$6/(100+W$6) -> 0 | AK39: =X39-G39*X$6/(100+X$6) -> 0 | AL39: =Y39-H39*Y$6/(100+Y$6) -> 0 | AM39: =Z39-I39*Z$6/(100+Z$6) -> 0 | AN39: =AA39-J39*AA$6/(100+AA$6) -> 0.18181818 | AO39: =+IF(W$93=0,0,IF(W$93<0,-RANK(AJ39,AJ$7:AJ$90,0),RANK(AJ39,AJ$7:AJ$90,1))) -> 0 | AP39: =+IF(X$93=0,0,IF(X$93<0,-RANK(AK39,AK$7:AK$90,0),RANK(AK39,AK$7:AK$90,1))) -> 0 | AQ39: =+IF(Y$93=0,0,IF(Y$93<0,-RANK(AL39,AL$7:AL$90,0),RANK(AL39,AL$7:AL$90,1))) -> 0 | AR39: =+IF(Z$93=0,0,IF(Z$93<0,-RANK(AM39,AM$7:AM$90,0),RANK(AM39,AM$7:AM$90,1))) -> 0 | AS39: =+IF(AA$93=0,0,IF(AA$93<0,-RANK(AN39,AN$7:AN$90,0),RANK(AN39,AN$7:AN$90,1))) -> 0 | AY39: =AC39-N39*AC$6/(100+AC$6) -> 0 | AZ39: =AD39-O39*AD$6/(100+AD$6) -> 0 | BA39: =AE39-P39*AE$6/(100+AE$6) -> 0 | BB39: =AF39-Q39*AF$6/(100+AF$6) -> 0 | BC39: =AG39-R39*AG$6/(100+AG$6) -> 0 | BD39: =+IF(AC$93=0,0,IF(AC$93<0,-RANK(AY39,AY$7:AY$90,0),RANK(AY39,AY$7:AY$90,1))) -> 0 | BE39: =+IF(AD$93=0,0,IF(AD$93<0,-RANK(AZ39,AZ$7:AZ$90,0),RANK(AZ39,AZ$7:AZ$90,1))) -> 0 | BF39: =+IF(AE$93=0,0,IF(AE$93<0,-RANK(BA39,BA$7:BA$90,0),RANK(BA39,BA$7:BA$90,1))) -> 0 | BG39: =+IF(AF$93=0,0,IF(AF$93<0,-RANK(BB39,BB$7:BB$90,0),RANK(BB39,BB$7:BB$90,1))) -> 0 | BH39: =+IF(AG$93=0,0,IF(AG$93<0,-RANK(BC39,BC$7:BC$90,0),RANK(BC39,BC$7:BC$90,1))) -> 0
A40: 2 | C40: 160010100 | D40: 特環 | E40: =+SUMIFS([1]全伝票!I:I,[1]全伝票!$C:$C,$C40,[1]全伝票!$A:$A,$A40) -> 0 | F40: =+SUMIFS([1]全伝票!J:J,[1]全伝票!$C:$C,$C40,[1]全伝票!$A:$A,$A40) -> 0 | G40: =+SUMIFS([1]全伝票!K:K,[1]全伝票!$C:$C,$C40,[1]全伝票!$A:$A,$A40) -> 0 | H40: =+SUMIFS([1]全伝票!L:L,[1]全伝票!$C:$C,$C40,[1]全伝票!$A:$A,$A40) -> 0 | I40: =+SUMIFS([1]全伝票!M:M,[1]全伝票!$C:$C,$C40,[1]全伝票!$A:$A,$A40) -> 0 | J40: =+SUMIFS([1]全伝票!N:N,[1]全伝票!$C:$C,$C40,[1]全伝票!$A:$A,$A40) -> 0 | K40: =SUM(F40:J40) -> 0 | L40: =+SUMIFS([1]全伝票!O:O,[1]全伝票!$C:$C,$C40,[1]全伝票!$A:$A,$A40) -> 0 | S40: =SUM(N40:R40) -> 0 | U40: =+V40-SUM(S40:T40) -> 0 | V40: =+SUMIFS([1]全伝票!P:P,[1]全伝票!$C:$C,$C40,[1]全伝票!$A:$A,'4条収入'!$A40) -> 0 | W40: =+ROUND(F40*F$6/(100+F$6),0)+AT40 -> 0 | X40: =+ROUND(G40*G$6/(100+G$6),0)+AU40 -> 0 | Y40: =+ROUND(H40*H$6/(100+H$6),0)+AV40 -> 0 | Z40: =+ROUND(I40*I$6/(100+I$6),0)+AW40 -> 0 | AA40: =+ROUND(J40*J$6/(100+J$6),0)+AX40 -> 0 | AB40: =SUM(W40:AA40) -> 0 | AC40: =+ROUND(N40*AC$6/(100+AC$6),0)+BI40 -> 0 | AD40: =+ROUND(O40*AD$6/(100+AD$6),0)+BJ40 -> 0 | AE40: =+ROUND(P40*AE$6/(100+AE$6),0)+BK40 -> 0 | AF40: =+ROUND(Q40*AF$6/(100+AF$6),0)+BL40 -> 0 | AG40: =+ROUND(R40*AG$6/(100+AG$6),0)+BM40 -> 0 | AH40: =SUM(AC40:AG40) -> 0 | AI40: =+E40-AB40 -> 0
A41: 3 | C41: 160010100 | D41: 農集 | E41: =+SUMIFS([1]全伝票!I:I,[1]全伝票!$C:$C,$C41,[1]全伝票!$A:$A,$A41) -> 0 | F41: =+SUMIFS([1]全伝票!J:J,[1]全伝票!$C:$C,$C41,[1]全伝票!$A:$A,$A41) -> 0 | G41: =+SUMIFS([1]全伝票!K:K,[1]全伝票!$C:$C,$C41,[1]全伝票!$A:$A,$A41) -> 0 | H41: =+SUMIFS([1]全伝票!L:L,[1]全伝票!$C:$C,$C41,[1]全伝票!$A:$A,$A41) -> 0 | I41: =+SUMIFS([1]全伝票!M:M,[1]全伝票!$C:$C,$C41,[1]全伝票!$A:$A,$A41) -> 0 | J41: =+SUMIFS([1]全伝票!N:N,[1]全伝票!$C:$C,$C41,[1]全伝票!$A:$A,$A41) -> 0 | K41: =SUM(F41:J41) -> 0 | L41: =+SUMIFS([1]全伝票!O:O,[1]全伝票!$C:$C,$C41,[1]全伝票!$A:$A,$A41) -> 0 | S41: =SUM(N41:R41) -> 0 | U41: =+V41-SUM(S41:T41) -> 0 | V41: =+SUMIFS([1]全伝票!P:P,[1]全伝票!$C:$C,$C41,[1]全伝票!$A:$A,'4条収入'!$A41) -> 0 | W41: =+ROUND(F41*F$6/(100+F$6),0)+AT41 -> 0 | X41: =+ROUND(G41*G$6/(100+G$6),0)+AU41 -> 0 | Y41: =+ROUND(H41*H$6/(100+H$6),0)+AV41 -> 0 | Z41: =+ROUND(I41*I$6/(100+I$6),0)+AW41 -> 0 | AA41: =+ROUND(J41*J$6/(100+J$6),0)+AX41 -> 0 | AB41: =SUM(W41:AA41) -> 0 | AC41: =+ROUND(N41*AC$6/(100+AC$6),0)+BI41 -> 0 | AD41: =+ROUND(O41*AD$6/(100+AD$6),0)+BJ41 -> 0 | AE41: =+ROUND(P41*AE$6/(100+AE$6),0)+BK41 -> 0 | AF41: =+ROUND(Q41*AF$6/(100+AF$6),0)+BL41 -> 0 | AG41: =+ROUND(R41*AG$6/(100+AG$6),0)+BM41 -> 0 | AH41: =SUM(AC41:AG41) -> 0 | AI41: =+E41-AB41 -> 0
D42: 負担金 | E42: =+SUM(E43,E45,E50) -> 574304394 | F42: =+SUM(F43,F45,F50) -> 0 | G42: =+SUM(G43,G45,G50) -> 0 | H42: =+SUM(H43,H45,H50) -> 0 | I42: =+SUM(I43,I45,I50) -> 0 | J42: =+SUM(J43,J45,J50) -> 15318327 | K42: =+SUM(K43,K45,K50) -> 15318327 | L42: =+SUM(L43,L45,L50) -> 0 | ... AI42: =+SUM(AI43,AI45,AI50) -> 572911819
D43: 受益者負担金 | E43: =+E44 -> 8799605 | F43: =+F44 -> 0 | G43: =+G44 -> 0 | H43: =+H44 -> 0 | I43: =+I44 -> 0 | J43: =+J44 -> 0 | K43: =+K44 -> 0 | L43: =+L44 -> 0 | ... AI43: =+AI44 -> 8799605
C44: 180060600 | D44: 受益者負担金 | E44: =+SUMIFS([1]全伝票!I:I,[1]全伝票!$C:$C,$C44) -> 8799605 | K44: =SUM(F44:J44) -> 0 | O44: =+'[3]受益（公）'!K$6 -> 0 | P44: =+'[3]受益（公）'!L$6 -> 338 | Q44: =+'[3]受益（公）'!M$6 -> 99 | R44: =+'[3]受益（公）'!N$6 -> 8524652 | S44: =SUM(N44:R44) -> 8525089 | T44: ='[3]受益（公）'!$I$6 -> 274516 | U44: =+V44-SUM(S44:T44) -> 0 | V44: =+SUMIFS([1]全伝票!P:P,[1]全伝票!$C:$C,$C44) -> 8799605 | W44: =+ROUND(F44*F$6/(100+F$6),0)+AT44 -> 0 | X44: =+ROUND(G44*G$6/(100+G$6),0)+AU44 -> 0 | Y44: =+ROUND(H44*H$6/(100+H$6),0)+AV44 -> 0 | Z44: =+ROUND(I44*I$6/(100+I$6),0)+AW44 -> 0 | AA44: =+ROUND(J44*J$6/(100+J$6),0)+AX44 -> 0 | AB44: =SUM(W44:AA44) -> 0 | AC44: =+ROUND(N44*AC$6/(100+AC$6),0)+BI44 -> 0 | AD44: =+ROUND(O44*AD$6/(100+AD$6),0)+BJ44 -> 0 | AE44: =+ROUND(P44*AE$6/(100+AE$6),0)+BK44 -> 25 | AF44: =+ROUND(Q44*AF$6/(100+AF$6),0)+BL44 -> 7 | AG44: =+ROUND(R44*AG$6/(100+AG$6),0)+BM44 -> 774968 | AH44: =SUM(AC44:AG44) -> 775000 | AI44: =+E44-AB44 -> 8799605 | AY44: =AC44-N44*AC$6/(100+AC$6) -> 0 | AZ44: =AD44-O44*AD$6/(100+AD$6) -> 0 | BA44: =AE44-P44*AE$6/(100+AE$6) -> -0.037037037 | BB44: =AF44-Q44*AF$6/(100+AF$6) -> -0.33333333 | BC44: =AG44-R44*AG$6/(100+AG$6) -> -0.36363636 | BD44: =+IF(AC$93=0,0,IF(AC$93<0,-RANK(AY44,AY$7:AY$90,0),RANK(AY44,AY$7:AY$90,1))) -> 0 | BE44: =+IF(AD$93=0,0,IF(AD$93<0,-RANK(AZ44,AZ$7:AZ$90,0),RANK(AZ44,AZ$7:AZ$90,1))) -> 0 | BF44: =+IF(AE$93=0,0,IF(AE$93<0,-RANK(BA44,BA$7:BA$90,0),RANK(BA44,BA$7:BA$90,1))) -> 0 | BG44: =+IF(AF$93=0,0,IF(AF$93<0,-RANK(BB44,BB$7:BB$90,0),RANK(BB44,BB$7:BB$90,1))) -> 0 | BH44: =+IF(AG$93=0,0,IF(AG$93<0,-RANK(BC44,BC$7:BC$90,0),RANK(BC44,BC$7:BC$90,1))) -> 0
D45: 受益者分担金 | E45: =+E46 -> 35218280 | F45: =+F46 -> 0 | G45: =+G46 -> 0 | H45: =+H46 -> 0 | I45: =+I46 -> 0 | J45: =+J46 -> 0 | K45: =+K46 -> 0 | L45: =+L46 -> 0 | ... AI45: =+AI46 -> 35218280
D46: 受益者分担金 | E46: =+SUM(E47:E49) -> 35218280 | F46: =+SUM(F47:F49) -> 0 | G46: =+SUM(G47:G49) -> 0 | H46: =+SUM(H47:H49) -> 0 | I46: =+SUM(I47:I49) -> 0 | J46: =+SUM(J47:J49) -> 0 | K46: =+SUM(K47:K49) -> 0 | L46: =+SUM(L47:L49) -> 0 | ... AG46: =+SUM(AG47:AG49) -> 3041767 | AH46: =SUM(AC46:AG46) -> 3041767 | AI46: =+E46-AB46 -> 35218280
A47: 2 | C47: 180070700 | D47: 特環 | E47: =+SUMIFS([1]全伝票!I:I,[1]全伝票!$C:$C,$C47,[1]全伝票!$A:$A,'4条収入'!$A47) -> 17022400 | K47: =SUM(F47:J47) -> 0 | O47: =+'[3]受益（区域外）'!K$26 -> 0 | P47: =+'[3]受益（区域外）'!L$26 -> 0 | Q47: =+'[3]受益（区域外）'!M$26 -> 0 | R47: =+'[3]受益（区域外）'!N$26 -> 15741150 | S47: =SUM(N47:R47) -> 15741150 | T47: =+'[3]受益（区域外）'!$I$26 -> 1281250 | U47: =+V47-SUM(S47:T47) -> 0 | V47: =+SUMIFS([1]全伝票!P:P,[1]全伝票!$C:$C,$C47,[1]全伝票!$A:$A,'4条収入'!$A47) -> 17022400 | W47: =+ROUND(F47*F$6/(100+F$6),0)+AT47 -> 0 | X47: =+ROUND(G47*G$6/(100+G$6),0)+AU47 -> 0 | Y47: =+ROUND(H47*H$6/(100+H$6),0)+AV47 -> 0 | Z47: =+ROUND(I47*I$6/(100+I$6),0)+AW47 -> 0 | AA47: =+ROUND(J47*J$6/(100+J$6),0)+AX47 -> 0 | AB47: =SUM(W47:AA47) -> 0 | AC47: =+ROUND(N47*AC$6/(100+AC$6),0)+BI47 -> 0 | AD47: =+ROUND(O47*AD$6/(100+AD$6),0)+BJ47 -> 0 | AE47: =+ROUND(P47*AE$6/(100+AE$6),0)+BK47 -> 0 | AF47: =+ROUND(Q47*AF$6/(100+AF$6),0)+BL47 -> 0 | AG47: =+ROUND(R47*AG$6/(100+AG$6),0)+BM47 -> 1431014 | AH47: =SUM(AC47:AG47) -> 1431014 | AI47: =+E47-AB47 -> 17022400
A48: 3 | C48: 180070700 | D48: 農集 | E48: =+SUMIFS([1]全伝票!I:I,[1]全伝票!$C:$C,$C48,[1]全伝票!$A:$A,'4条収入'!$A48) -> 14115880 | K48: =SUM(F48:J48) -> 0 | O48: =+'[3]受益（区域外）'!K$46 -> 0 | P48: =+'[3]受益（区域外）'!L$46 -> 0 | Q48: =+'[3]受益（区域外）'!M$46 -> 0 | R48: =+'[3]受益（区域外）'!N$46 -> 13788037 | S48: =SUM(N48:R48) -> 13788037 | T48: =+'[3]受益（区域外）'!$I$46 -> 327843 | U48: =+V48-SUM(S48:T48) -> 0 | V48: =+SUMIFS([1]全伝票!P:P,[1]全伝票!$C:$C,$C48,[1]全伝票!$A:$A,'4条収入'!$A48) -> 14115880 | W48: =+ROUND(F48*F$6/(100+F$6),0)+AT48 -> 0 | X48: =+ROUND(G48*G$6/(100+G$6),0)+AU48 -> 0 | Y48: =+ROUND(H48*H$6/(100+H$6),0)+AV48 -> 0 | Z48: =+ROUND(I48*I$6/(100+I$6),0)+AW48 -> 0 | AA48: =+ROUND(J48*J$6/(100+J$6),0)+AX48 -> 0 | AB48: =SUM(W48:AA48) -> 0 | AC48: =+ROUND(N48*AC$6/(100+AC$6),0)+BI48 -> 0 | AD48: =+ROUND(O48*AD$6/(100+AD$6),0)+BJ48 -> 0 | AE48: =+ROUND(P48*AE$6/(100+AE$6),0)+BK48 -> 0 | AF48: =+ROUND(Q48*AF$6/(100+AF$6),0)+BL48 -> 0 | AG48: =+ROUND(R48*AG$6/(100+AG$6),0)+BM48 -> 1253458 | AH48: =SUM(AC48:AG48) -> 1253458 | AI48: =+E48-AB48 -> 14115880
A49: 4 | C49: 180070700 | D49: 浄化槽 | E49: =+SUMIFS([1]全伝票!I:I,[1]全伝票!$C:$C,$C49,[1]全伝票!$A:$A,'4条収入'!$A49) -> 4080000 | K49: =SUM(F49:J49) -> 0 | O49: =+'[3]受益（区域外）'!K$66 -> 0 | P49: =+'[3]受益（区域外）'!L$66 -> 0 | Q49: =+'[3]受益（区域外）'!M$66 -> 0 | R49: =+'[3]受益（区域外）'!N$66 -> 3930244 | S49: =SUM(N49:R49) -> 3930244 | T49: =+'[3]受益（区域外）'!$I$66 -> 149756 | U49: =+V49-SUM(S49:T49) -> 0 | V49: =+SUMIFS([1]全伝票!P:P,[1]全伝票!$C:$C,$C49,[1]全伝票!$A:$A,'4条収入'!$A49) -> 4080000 | W49: =+ROUND(F49*F$6/(100+F$6),0)+AT49 -> 0 | X49: =+ROUND(G49*G$6/(100+G$6),0)+AU49 -> 0 | Y49: =+ROUND(H49*H$6/(100+H$6),0)+AV49 -> 0 | Z49: =+ROUND(I49*I$6/(100+I$6),0)+AW49 -> 0 | AA49: =+ROUND(J49*J$6/(100+J$6),0)+AX49 -> 0 | AB49: =SUM(W49:AA49) -> 0 | AC49: =+ROUND(N49*AC$6/(100+AC$6),0)+BI49 -> 0 | AD49: =+ROUND(O49*AD$6/(100+AD$6),0)+BJ49 -> 0 | AE49: =+ROUND(P49*AE$6/(100+AE$6),0)+BK49 -> 0 | AF49: =+ROUND(Q49*AF$6/(100+AF$6),0)+BL49 -> 0 | AG49: =+ROUND(R49*AG$6/(100+AG$6),0)+BM49 -> 357295 | AH49: =SUM(AC49:AG49) -> 357295 | AI49: =+E49-AB49 -> 4080000
D50: 工事負担金 | E50: =SUM(E51:E54) -> 530286509 | F50: =SUM(F51:F54) -> 0 | G50: =SUM(G51:G54) -> 0 | H50: =SUM(H51:H54) -> 0 | I50: =SUM(I51:I54) -> 0 | J50: =SUM(J51:J54) -> 15318327 | K50: =SUM(K51:K54) -> 15318327 | L50: =SUM(L51:L54) -> 0 | ... AI50: =SUM(AI51:AI54) -> 528893934
A51: 1 | C51: 180080800 | D51: 公共 | E51: =+SUMIFS([1]全伝票!I:I,[1]全伝票!$C:$C,$C51,[1]全伝票!$A:$A,'4条収入'!$A51) -> 530286509 | F51: =+SUMIFS([1]全伝票!J:J,[1]全伝票!$C:$C,$C51,[1]全伝票!$A:$A,$A51) -> 0 | G51: =+SUMIFS([1]全伝票!K:K,[1]全伝票!$C:$C,$C51,[1]全伝票!$A:$A,$A51) -> 0 | H51: =+SUMIFS([1]全伝票!L:L,[1]全伝票!$C:$C,$C51,[1]全伝票!$A:$A,$A51) -> 0 | I51: =+SUMIFS([1]全伝票!M:M,[1]全伝票!$C:$C,$C51,[1]全伝票!$A:$A,$A51) -> 0 | J51: =+SUMIFS([1]全伝票!N:N,[1]全伝票!$C:$C,$C51,[1]全伝票!$A:$A,$A51) -> 15318327 | K51: =SUM(F51:J51) -> 15318327 | L51: =+SUMIFS([1]全伝票!O:O,[1]全伝票!$C:$C,$C51) -> 0 | O51: =+'[3]4条工事負担金'!K$6-'[3]4条工事負担金'!K$17 -> 131982078 | P51: =+'[3]4条工事負担金'!L$6-'[3]4条工事負担金'!L$17 -> 1246566 | Q51: =+'[3]4条工事負担金'!M$6-'[3]4条工事負担金'!M$17 -> 0 | R51: =+'[3]4条工事負担金'!N$6-'[3]4条工事負担金'!N$17 -> 218135713 | S51: =SUM(N51:R51) -> 351364357 | T51: =+'[3]4条工事負担金'!$I$6-'[3]4条工事負担金'!$I$16 -> 163603825 | U51: =+V51-SUM(S51:T51) -> 0 | V51: =+SUMIFS([1]全伝票!P:P,[1]全伝票!$C:$C,$C51,[1]全伝票!$A:$A,'4条収入'!$A51) -> 514968182 | W51: =+ROUND(F51*F$6/(100+F$6),0)+AT51 -> 0 | X51: =+ROUND(G51*G$6/(100+G$6),0)+AU51 -> 0 | Y51: =+ROUND(H51*H$6/(100+H$6),0)+AV51 -> 0 | Z51: =+ROUND(I51*I$6/(100+I$6),0)+AW51 -> 0 | AA51: =+ROUND(J51*J$6/(100+J$6),0)+AX51 -> 1392575 | AB51: =SUM(W51:AA51) -> 1392575 | AC51: =+ROUND(N51*AC$6/(100+AC$6),0)+BI51 -> 0 | AD51: =+ROUND(O51*AD$6/(100+AD$6),0)+BJ51 -> 6284860 | AE51: =+ROUND(P51*AE$6/(100+AE$6),0)+BK51 -> 92338 | AF51: =+ROUND(Q51*AF$6/(100+AF$6),0)+BL51 -> 0 | AG51: =+ROUND(R51*AG$6/(100+AG$6),0)+BM51 -> 19830519 | AH51: =SUM(AC51:AG51) -> 26207717 | AI51: =+E51-AB51 -> 528893934 | AJ51: =W51-F51*W$6/(100+W$6) -> 0 | AK51: =X51-G51*X$6/(100+X$6) -> 0 | AL51: =Y51-H51*Y$6/(100+Y$6) -> 0 | AM51: =Z51-I51*Z$6/(100+Z$6) -> 0 | AN51: =AA51-J51*AA$6/(100+AA$6) -> -0.18181818 | AO51: =+IF(W$93=0,0,IF(W$93<0,-RANK(AJ51,AJ$7:AJ$90,0),RANK(AJ51,AJ$7:AJ$90,1))) -> 0 | AP51: =+IF(X$93=0,0,IF(X$93<0,-RANK(AK51,AK$7:AK$90,0),RANK(AK51,AK$7:AK$90,1))) -> 0 | AQ51: =+IF(Y$93=0,0,IF(Y$93<0,-RANK(AL51,AL$7:AL$90,0),RANK(AL51,AL$7:AL$90,1))) -> 0 | AR51: =+IF(Z$93=0,0,IF(Z$93<0,-RANK(AM51,AM$7:AM$90,0),RANK(AM51,AM$7:AM$90,1))) -> 0 | AS51: =+IF(AA$93=0,0,IF(AA$93<0,-RANK(AN51,AN$7:AN$90,0),RANK(AN51,AN$7:AN$90,1))) -> 0 | AY51: =AC51-N51*AC$6/(100+AC$6) -> 0 | AZ51: =AD51-O51*AD$6/(100+AD$6) -> -0.85714286 | BA51: =AE51-P51*AE$6/(100+AE$6) -> -0.22222222 | BB51: =AF51-Q51*AF$6/(100+AF$6) -> 0 | BC51: =AG51-R51*AG$6/(100+AG$6) -> -0.36363636 | BD51: =+IF(AC$93=0,0,IF(AC$93<0,-RANK(AY51,AY$7:AY$90,0),RANK(AY51,AY$7:AY$90,1))) -> 0 | BE51: =+IF(AD$93=0,0,IF(AD$93<0,-RANK(AZ51,AZ$7:AZ$90,0),RANK(AZ51,AZ$7:AZ$90,1))) -> 0 | BF51: =+IF(AE$93=0,0,IF(AE$93<0,-RANK(BA51,BA$7:BA$90,0),RANK(BA51,BA$7:BA$90,1))) -> 0 | BG51: =+IF(AF$93=0,0,IF(AF$93<0,-RANK(BB51,BB$7:BB$90,0),RANK(BB51,BB$7:BB$90,1))) -> 0 | BH51: =+IF(AG$93=0,0,IF(AG$93<0,-RANK(BC51,BC$7:BC$90,0),RANK(BC51,BC$7:BC$90,1))) -> 0 | BJ51: -1
A52: 2 | C52: 180080800 | D52: 特環 | E52: =+SUMIFS([1]全伝票!I:I,[1]全伝票!$C:$C,$C52,[1]全伝票!$A:$A,'4条収入'!$A52) -> 0 | F52: =+SUMIFS([1]全伝票!J:J,[1]全伝票!$C:$C,$C52,[1]全伝票!$A:$A,$A52) -> 0 | G52: =+SUMIFS([1]全伝票!K:K,[1]全伝票!$C:$C,$C52,[1]全伝票!$A:$A,$A52) -> 0 | H52: =+SUMIFS([1]全伝票!L:L,[1]全伝票!$C:$C,$C52,[1]全伝票!$A:$A,$A52) -> 0 | I52: =+SUMIFS([1]全伝票!M:M,[1]全伝票!$C:$C,$C52,[1]全伝票!$A:$A,$A52) -> 0 | J52: =+SUMIFS([1]全伝票!N:N,[1]全伝票!$C:$C,$C52,[1]全伝票!$A:$A,$A52) -> 0 | K52: =SUM(F52:J52) -> 0 | L52: =+SUMIFS([1]全伝票!O:O,[1]全伝票!$C:$C,$C52) -> 0 | O52: =+'[3]4条工事負担金'!K$19 -> 0 | P52: =+'[3]4条工事負担金'!L$19 -> 0 | Q52: =+'[3]4条工事負担金'!M$19 -> 0 | R52: =+'[3]4条工事負担金'!N$19 -> 0 | S52: =SUM(N52:R52) -> 0 | T52: =+'[3]4条工事負担金'!$I$18 -> 0 | U52: =+V52-SUM(S52:T52) -> 0 | V52: =+SUMIFS([1]全伝票!P:P,[1]全伝票!$C:$C,$C52,[1]全伝票!$A:$A,'4条収入'!$A52) -> 0 | W52: =+ROUND(F52*F$6/(100+F$6),0)+AT52 -> 0 | X52: =+ROUND(G52*G$6/(100+G$6),0)+AU52 -> 0 | Y52: =+ROUND(H52*H$6/(100+H$6),0)+AV52 -> 0 | Z52: =+ROUND(I52*I$6/(100+I$6),0)+AW52 -> 0 | AA52: =+ROUND(J52*J$6/(100+J$6),0)+AX52 -> 0 | AB52: =SUM(W52:AA52) -> 0 | AC52: =+ROUND(N52*AC$6/(100+AC$6),0)+BI52 -> 0 | AD52: =+ROUND(O52*AD$6/(100+AD$6),0)+BJ52 -> 0 | AE52: =+ROUND(P52*AE$6/(100+AE$6),0)+BK52 -> 0 | AF52: =+ROUND(Q52*AF$6/(100+AF$6),0)+BL52 -> 0 | AG52: =+ROUND(R52*AG$6/(100+AG$6),0)+BM52 -> 0 | AH52: =SUM(AC52:AG52) -> 0 | AI52: =+E52-AB52 -> 0 | AJ52: =W52-F52*W$6/(100+W$6) -> 0 | AK52: =X52-G52*X$6/(100+X$6) -> 0 | AL52: =Y52-H52*Y$6/(100+Y$6) -> 0 | AM52: =Z52-I52*Z$6/(100+Z$6) -> 0 | AN52: =AA52-J52*AA$6/(100+AA$6) -> 0 | AO52: =+IF(W$93=0,0,IF(W$93<0,-RANK(AJ52,AJ$7:AJ$90,0),RANK(AJ52,AJ$7:AJ$90,1))) -> 0 | AP52: =+IF(X$93=0,0,IF(X$93<0,-RANK(AK52,AK$7:AK$90,0),RANK(AK52,AK$7:AK$90,1))) -> 0 | AQ52: =+IF(Y$93=0,0,IF(Y$93<0,-RANK(AL52,AL$7:AL$90,0),RANK(AL52,AL$7:AL$90,1))) -> 0 | AR52: =+IF(Z$93=0,0,IF(Z$93<0,-RANK(AM52,AM$7:AM$90,0),RANK(AM52,AM$7:AM$90,1))) -> 0 | AS52: =+IF(AA$93=0,0,IF(AA$93<0,-RANK(AN52,AN$7:AN$90,0),RANK(AN52,AN$7:AN$90,1))) -> 0 | AY52: =AC52-N52*AC$6/(100+AC$6) -> 0 | AZ52: =AD52-O52*AD$6/(100+AD$6) -> 0 | BA52: =AE52-P52*AE$6/(100+AE$6) -> 0 | BB52: =AF52-Q52*AF$6/(100+AF$6) -> 0 | BC52: =AG52-R52*AG$6/(100+AG$6) -> 0 | BD52: =+IF(AC$93=0,0,IF(AC$93<0,-RANK(AY52,AY$7:AY$90,0),RANK(AY52,AY$7:AY$90,1))) -> 0 | BE52: =+IF(AD$93=0,0,IF(AD$93<0,-RANK(AZ52,AZ$7:AZ$90,0),RANK(AZ52,AZ$7:AZ$90,1))) -> 0 | BF52: =+IF(AE$93=0,0,IF(AE$93<0,-RANK(BA52,BA$7:BA$90,0),RANK(BA52,BA$7:BA$90,1))) -> 0 | BG52: =+IF(AF$93=0,0,IF(AF$93<0,-RANK(BB52,BB$7:BB$90,0),RANK(BB52,BB$7:BB$90,1))) -> 0 | BH52: =+IF(AG$93=0,0,IF(AG$93<0,-RANK(BC52,BC$7:BC$90,0),RANK(BC52,BC$7:BC$90,1))) -> 0
A53: 3 | C53: 180080800 | D53: 農集 | E53: =+SUMIFS([1]全伝票!I:I,[1]全伝票!$C:$C,$C53,[1]全伝票!$A:$A,'4条収入'!$A53) -> 0 | F53: =+SUMIFS([1]全伝票!J:J,[1]全伝票!$C:$C,$C53,[1]全伝票!$A:$A,$A53) -> 0 | G53: =+SUMIFS([1]全伝票!K:K,[1]全伝票!$C:$C,$C53,[1]全伝票!$A:$A,$A53) -> 0 | H53: =+SUMIFS([1]全伝票!L:L,[1]全伝票!$C:$C,$C53,[1]全伝票!$A:$A,$A53) -> 0 | I53: =+SUMIFS([1]全伝票!M:M,[1]全伝票!$C:$C,$C53,[1]全伝票!$A:$A,$A53) -> 0 | J53: =+SUMIFS([1]全伝票!N:N,[1]全伝票!$C:$C,$C53,[1]全伝票!$A:$A,$A53) -> 0 | K53: =SUM(F53:J53) -> 0 | L53: =+SUMIFS([1]全伝票!O:O,[1]全伝票!$C:$C,$C53) -> 0 | O53: =+'[3]4条工事負担金'!K$21 -> 0 | P53: =+'[3]4条工事負担金'!L$21 -> 0 | Q53: =+'[3]4条工事負担金'!M$21 -> 0 | R53: =+'[3]4条工事負担金'!N$21 -> 0 | S53: =SUM(N53:R53) -> 0 | T53: =+'[3]4条工事負担金'!I20 -> 0 | U53: =+V53-SUM(S53:T53) -> 0 | V53: =+SUMIFS([1]全伝票!P:P,[1]全伝票!$C:$C,$C53,[1]全伝票!$A:$A,'4条収入'!$A53) -> 0 | W53: =+ROUND(F53*F$6/(100+F$6),0)+AT53 -> 0 | X53: =+ROUND(G53*G$6/(100+G$6),0)+AU53 -> 0 | Y53: =+ROUND(H53*H$6/(100+H$6),0)+AV53 -> 0 | Z53: =+ROUND(I53*I$6/(100+I$6),0)+AW53 -> 0 | AA53: =+ROUND(J53*J$6/(100+J$6),0)+AX53 -> 0 | AB53: =SUM(W53:AA53) -> 0 | AC53: =+ROUND(N53*AC$6/(100+AC$6),0)+BI53 -> 0 | AD53: =+ROUND(O53*AD$6/(100+AD$6),0)+BJ53 -> 0 | AE53: =+ROUND(P53*AE$6/(100+AE$6),0)+BK53 -> 0 | AF53: =+ROUND(Q53*AF$6/(100+AF$6),0)+BL53 -> 0 | AG53: =+ROUND(R53*AG$6/(100+AG$6),0)+BM53 -> 0 | AH53: =SUM(AC53:AG53) -> 0 | AI53: =+E53-AB53 -> 0 | AJ53: =W53-F53*W$6/(100+W$6) -> 0 | AK53: =X53-G53*X$6/(100+X$6) -> 0 | AL53: =Y53-H53*Y$6/(100+Y$6) -> 0 | AM53: =Z53-I53*Z$6/(100+Z$6) -> 0 | AN53: =AA53-J53*AA$6/(100+AA$6) -> 0 | AO53: =+IF(W$93=0,0,IF(W$93<0,-RANK(AJ53,AJ$7:AJ$90,0),RANK(AJ53,AJ$7:AJ$90,1))) -> 0 | AP53: =+IF(X$93=0,0,IF(X$93<0,-RANK(AK53,AK$7:AK$90,0),RANK(AK53,AK$7:AK$90,1))) -> 0 | AQ53: =+IF(Y$93=0,0,IF(Y$93<0,-RANK(AL53,AL$7:AL$90,0),RANK(AL53,AL$7:AL$90,1))) -> 0 | AR53: =+IF(Z$93=0,0,IF(Z$93<0,-RANK(AM53,AM$7:AM$90,0),RANK(AM53,AM$7:AM$90,1))) -> 0 | AS53: =+IF(AA$93=0,0,IF(AA$93<0,-RANK(AN53,AN$7:AN$90,0),RANK(AN53,AN$7:AN$90,1))) -> 0 | AY53: =AC53-N53*AC$6/(100+AC$6) -> 0 | AZ53: =AD53-O53*AD$6/(100+AD$6) -> 0 | BA53: =AE53-P53*AE$6/(100+AE$6) -> 0 | BB53: =AF53-Q53*AF$6/(100+AF$6) -> 0 | BC53: =AG53-R53*AG$6/(100+AG$6) -> 0 | BD53: =+IF(AC$93=0,0,IF(AC$93<0,-RANK(AY53,AY$7:AY$90,0),RANK(AY53,AY$7:AY$90,1))) -> 0 | BE53: =+IF(AD$93=0,0,IF(AD$93<0,-RANK(AZ53,AZ$7:AZ$90,0),RANK(AZ53,AZ$7:AZ$90,1))) -> 0 | BF53: =+IF(AE$93=0,0,IF(AE$93<0,-RANK(BA53,BA$7:BA$90,0),RANK(BA53,BA$7:BA$90,1))) -> 0 | BG53: =+IF(AF$93=0,0,IF(AF$93<0,-RANK(BB53,BB$7:BB$90,0),RANK(BB53,BB$7:BB$90,1))) -> 0 | BH53: =+IF(AG$93=0,0,IF(AG$93<0,-RANK(BC53,BC$7:BC$90,0),RANK(BC53,BC$7:BC$90,1))) -> 0
A54: 4 | C54: 180080800 | D54: 浄化槽 | E54: =+SUMIFS([1]全伝票!I:I,[1]全伝票!$C:$C,$C54,[1]全伝票!$A:$A,'4条収入'!$A54) -> 0 | F54: =+SUMIFS([1]全伝票!J:J,[1]全伝票!$C:$C,$C54,[1]全伝票!$A:$A,$A54) -> 0 | G54: =+SUMIFS([1]全伝票!K:K,[1]全伝票!$C:$C,$C54,[1]全伝票!$A:$A,$A54) -> 0 | H54: =+SUMIFS([1]全伝票!L:L,[1]全伝票!$C:$C,$C54,[1]全伝票!$A:$A,$A54) -> 0 | I54: =+SUMIFS([1]全伝票!M:M,[1]全伝票!$C:$C,$C54,[1]全伝票!$A:$A,$A54) -> 0 | J54: =+SUMIFS([1]全伝票!N:N,[1]全伝票!$C:$C,$C54,[1]全伝票!$A:$A,$A54) -> 0 | K54: =SUM(F54:J54) -> 0 | L54: =+SUMIFS([1]全伝票!O:O,[1]全伝票!$C:$C,$C54) -> 0 | O54: =+'[3]4条工事負担金'!K$23 -> 0 | P54: =+'[3]4条工事負担金'!L$23 -> 0 | Q54: =+'[3]4条工事負担金'!M$23 -> 0 | R54: =+'[3]4条工事負担金'!N$23 -> 0 | S54: =SUM(N54:R54) -> 0 | T54: =+'[3]4条工事負担金'!$I$22 -> 0 | U54: =+V54-SUM(S54:T54) -> 0 | V54: =+SUMIFS([1]全伝票!P:P,[1]全伝票!$C:$C,$C54,[1]全伝票!$A:$A,'4条収入'!$A54) -> 0 | W54: =+ROUND(F54*F$6/(100+F$6),0)+AT54 -> 0 | X54: =+ROUND(G54*G$6/(100+G$6),0)+AU54 -> 0 | Y54: =+ROUND(H54*H$6/(100+H$6),0)+AV54 -> 0 | Z54: =+ROUND(I54*I$6/(100+I$6),0)+AW54 -> 0 | AA54: =+ROUND(J54*J$6/(100+J$6),0)+AX54 -> 0 | AB54: =SUM(W54:AA54) -> 0 | AC54: =+ROUND(N54*AC$6/(100+AC$6),0)+BI54 -> 0 | AD54: =+ROUND(O54*AD$6/(100+AD$6),0)+BJ54 -> 0 | AE54: =+ROUND(P54*AE$6/(100+AE$6),0)+BK54 -> 0 | AF54: =+ROUND(Q54*AF$6/(100+AF$6),0)+BL54 -> 0 | AG54: =+ROUND(R54*AG$6/(100+AG$6),0)+BM54 -> 0 | AH54: =SUM(AC54:AG54) -> 0 | AI54: =+E54-AB54 -> 0 | AJ54: =W54-F54*W$6/(100+W$6) -> 0 | AK54: =X54-G54*X$6/(100+X$6) -> 0 | AL54: =Y54-H54*Y$6/(100+Y$6) -> 0 | AM54: =Z54-I54*Z$6/(100+Z$6) -> 0 | AN54: =AA54-J54*AA$6/(100+AA$6) -> 0 | AO54: =+IF(W$93=0,0,IF(W$93<0,-RANK(AJ54,AJ$7:AJ$90,0),RANK(AJ54,AJ$7:AJ$90,1))) -> 0 | AP54: =+IF(X$93=0,0,IF(X$93<0,-RANK(AK54,AK$7:AK$90,0),RANK(AK54,AK$7:AK$90,1))) -> 0 | AQ54: =+IF(Y$93=0,0,IF(Y$93<0,-RANK(AL54,AL$7:AL$90,0),RANK(AL54,AL$7:AL$90,1))) -> 0 | AR54: =+IF(Z$93=0,0,IF(Z$93<0,-RANK(AM54,AM$7:AM$90,0),RANK(AM54,AM$7:AM$90,1))) -> 0 | AS54: =+IF(AA$93=0,0,IF(AA$93<0,-RANK(AN54,AN$7:AN$90,0),RANK(AN54,AN$7:AN$90,1))) -> 0 | AY54: =AC54-N54*AC$6/(100+AC$6) -> 0 | AZ54: =AD54-O54*AD$6/(100+AD$6) -> 0 | BA54: =AE54-P54*AE$6/(100+AE$6) -> 0 | BB54: =AF54-Q54*AF$6/(100+AF$6) -> 0 | BC54: =AG54-R54*AG$6/(100+AG$6) -> 0 | BD54: =+IF(AC$93=0,0,IF(AC$93<0,-RANK(AY54,AY$7:AY$90,0),RANK(AY54,AY$7:AY$90,1))) -> 0 | BE54: =+IF(AD$93=0,0,IF(AD$93<0,-RANK(AZ54,AZ$7:AZ$90,0),RANK(AZ54,AZ$7:AZ$90,1))) -> 0 | BF54: =+IF(AE$93=0,0,IF(AE$93<0,-RANK(BA54,BA$7:BA$90,0),RANK(BA54,BA$7:BA$90,1))) -> 0 | BG54: =+IF(AF$93=0,0,IF(AF$93<0,-RANK(BB54,BB$7:BB$90,0),RANK(BB54,BB$7:BB$90,1))) -> 0 | BH54: =+IF(AG$93=0,0,IF(AG$93<0,-RANK(BC54,BC$7:BC$90,0),RANK(BC54,BC$7:BC$90,1))) -> 0
D55: 水洗化貸付事業収入 | E55: =+SUM(E56,E58,E71) -> 3987000 | F55: =+SUM(F56,F58,F71) -> 0 | G55: =+SUM(G56,G58,G71) -> 0 | H55: =+SUM(H56,H58,H71) -> 0 | I55: =+SUM(I56,I58,I71) -> 0 | J55: =+SUM(J56,J58,J71) -> 0 | K55: =+SUM(K56,K58,K71) -> 0 | L55: =+SUM(L56,L58,L71) -> 0 | ... AI55: =+SUM(AI56,AI58,AI71) -> 3987000
D56: 貸付企業債 | E56: =+E57 -> 0 | F56: =+F57 -> 0 | G56: =+G57 -> 0 | H56: =+H57 -> 0 | I56: =+I57 -> 0 | J56: =+J57 -> 0 | K56: =+K57 -> 0 | L56: =+L57 -> 0 | ... AI56: =+AI57 -> 0
C57: 184010200 | D57: 水洗便所貸付事業債 | E57: =+SUMIFS([1]全伝票!I:I,[1]全伝票!$C:$C,$C57) -> 0 | F57: =+SUMIFS([1]全伝票!J:J,[1]全伝票!$C:$C,$C57) -> 0 | G57: =+SUMIFS([1]全伝票!K:K,[1]全伝票!$C:$C,$C57) -> 0 | H57: =+SUMIFS([1]全伝票!L:L,[1]全伝票!$C:$C,$C57) -> 0 | I57: =+SUMIFS([1]全伝票!M:M,[1]全伝票!$C:$C,$C57) -> 0 | J57: =+SUMIFS([1]全伝票!N:N,[1]全伝票!$C:$C,$C57) -> 0 | K57: =SUM(F57:J57) -> 0 | L57: =+SUMIFS([1]全伝票!O:O,[1]全伝票!$C:$C,$C57) -> 0 | S57: =SUM(N57:R57) -> 0 | U57: =+V57-SUM(S57:T57) -> 0 | V57: =+SUMIFS([1]全伝票!P:P,[1]全伝票!$C:$C,$C57) -> 0 | W57: =+ROUND(F57*F$6/(100+F$6),0)+AT57 -> 0 | X57: =+ROUND(G57*G$6/(100+G$6),0)+AU57 -> 0 | Y57: =+ROUND(H57*H$6/(100+H$6),0)+AV57 -> 0 | Z57: =+ROUND(I57*I$6/(100+I$6),0)+AW57 -> 0 | AA57: =+ROUND(J57*J$6/(100+J$6),0)+AX57 -> 0 | AB57: =SUM(W57:AA57) -> 0 | AC57: =+ROUND(N57*AC$6/(100+AC$6),0)+BI57 -> 0 | AD57: =+ROUND(O57*AD$6/(100+AD$6),0)+BJ57 -> 0 | AE57: =+ROUND(P57*AE$6/(100+AE$6),0)+BK57 -> 0 | AF57: =+ROUND(Q57*AF$6/(100+AF$6),0)+BL57 -> 0 | AG57: =+ROUND(R57*AG$6/(100+AG$6),0)+BM57 -> 0 | AH57: =SUM(AC57:AG57) -> 0 | AI57: =+E57-AB57 -> 0
D58: 一般会計借入金 | E58: =+SUM(E59,E63,E67) -> 0 | F58: =+SUM(F59,F63,F67) -> 0 | G58: =+SUM(G59,G63,G67) -> 0 | H58: =+SUM(H59,H63,H67) -> 0 | I58: =+SUM(I59,I63,I67) -> 0 | J58: =+SUM(J59,J63,J67) -> 0 | K58: =+SUM(K59,K63,K67) -> 0 | L58: =+SUM(L59,L63,L67) -> 0 | ... AI58: =+SUM(AI59,AI63,AI67) -> 0
D59: 水洗便所貸付借入金 | E59: =+SUM(E60:E62) -> 0 | F59: =+SUM(F60:F62) -> 0 | G59: =+SUM(G60:G62) -> 0 | H59: =+SUM(H60:H62) -> 0 | I59: =+SUM(I60:I62) -> 0 | J59: =+SUM(J60:J62) -> 0 | K59: =+SUM(K60:K62) -> 0 | L59: =+SUM(L60:L62) -> 0 | ... AI59: =+SUM(AI60:AI62) -> 0
A60: 2 | C60: 184030400 | D60: 特環 | E60: 0 | S60: =SUM(N60:R60) -> 0 | V60: =+E60 -> 0 | W60: =+ROUND(F60*F$6/(100+F$6),0)+AT60 -> 0 | X60: =+ROUND(G60*G$6/(100+G$6),0)+AU60 -> 0 | Y60: =+ROUND(H60*H$6/(100+H$6),0)+AV60 -> 0 | Z60: =+ROUND(I60*I$6/(100+I$6),0)+AW60 -> 0 | AA60: =+ROUND(J60*J$6/(100+J$6),0)+AX60 -> 0 | AB60: =SUM(W60:AA60) -> 0 | AC60: =+ROUND(N60*AC$6/(100+AC$6),0)+BI60 -> 0 | AD60: =+ROUND(O60*AD$6/(100+AD$6),0)+BJ60 -> 0 | AE60: =+ROUND(P60*AE$6/(100+AE$6),0)+BK60 -> 0 | AF60: =+ROUND(Q60*AF$6/(100+AF$6),0)+BL60 -> 0 | AG60: =+ROUND(R60*AG$6/(100+AG$6),0)+BM60 -> 0 | AH60: =SUM(AC60:AG60) -> 0 | AI60: =+E60-AB60 -> 0
A61: 3 | C61: 184030400 | D61: 農集 | E61: 0 | S61: =SUM(N61:R61) -> 0 | V61: =+E61 -> 0 | W61: =+ROUND(F61*F$6/(100+F$6),0)+AT61 -> 0 | X61: =+ROUND(G61*G$6/(100+G$6),0)+AU61 -> 0 | Y61: =+ROUND(H61*H$6/(100+H$6),0)+AV61 -> 0 | Z61: =+ROUND(I61*I$6/(100+I$6),0)+AW61 -> 0 | AA61: =+ROUND(J61*J$6/(100+J$6),0)+AX61 -> 0 | AB61: =SUM(W61:AA61) -> 0 | AC61: =+ROUND(N61*AC$6/(100+AC$6),0)+BI61 -> 0 | AD61: =+ROUND(O61*AD$6/(100+AD$6),0)+BJ61 -> 0 | AE61: =+ROUND(P61*AE$6/(100+AE$6),0)+BK61 -> 0 | AF61: =+ROUND(Q61*AF$6/(100+AF$6),0)+BL61 -> 0 | AG61: =+ROUND(R61*AG$6/(100+AG$6),0)+BM61 -> 0 | AH61: =SUM(AC61:AG61) -> 0 | AI61: =+E61-AB61 -> 0
A62: 4 | C62: 184030400 | D62: 浄化槽 | E62: 0 | S62: =SUM(N62:R62) -> 0 | V62: =+E62 -> 0 | W62: =+ROUND(F62*F$6/(100+F$6),0)+AT62 -> 0 | X62: =+ROUND(G62*G$6/(100+G$6),0)+AU62 -> 0 | Y62: =+ROUND(H62*H$6/(100+H$6),0)+AV62 -> 0 | Z62: =+ROUND(I62*I$6/(100+I$6),0)+AW62 -> 0 | AA62: =+ROUND(J62*J$6/(100+J$6),0)+AX62 -> 0 | AB62: =SUM(W62:AA62) -> 0 | AC62: =+ROUND(N62*AC$6/(100+AC$6),0)+BI62 -> 0 | AD62: =+ROUND(O62*AD$6/(100+AD$6),0)+BJ62 -> 0 | AE62: =+ROUND(P62*AE$6/(100+AE$6),0)+BK62 -> 0 | AF62: =+ROUND(Q62*AF$6/(100+AF$6),0)+BL62 -> 0 | AG62: =+ROUND(R62*AG$6/(100+AG$6),0)+BM62 -> 0 | AH62: =SUM(AC62:AG62) -> 0 | AI62: =+E62-AB62 -> 0
D63: し尿浄化槽廃止貸付借入金 | E63: =+SUM(E64:E66) -> 0 | F63: =+SUM(F64:F66) -> 0 | G63: =+SUM(G64:G66) -> 0 | H63: =+SUM(H64:H66) -> 0 | I63: =+SUM(I64:I66) -> 0 | J63: =+SUM(J64:J66) -> 0 | K63: =+SUM(K64:K66) -> 0 | L63: =+SUM(L64:L66) -> 0 | ... AI63: =+SUM(AI64:AI66) -> 0
A64: 2 | C64: 184030500 | D64: 特環 | E64: 0 | S64: =SUM(N64:R64) -> 0 | V64: =+E64 -> 0 | W64: =+ROUND(F64*F$6/(100+F$6),0)+AT64 -> 0 | X64: =+ROUND(G64*G$6/(100+G$6),0)+AU64 -> 0 | Y64: =+ROUND(H64*H$6/(100+H$6),0)+AV64 -> 0 | Z64: =+ROUND(I64*I$6/(100+I$6),0)+AW64 -> 0 | AA64: =+ROUND(J64*J$6/(100+J$6),0)+AX64 -> 0 | AB64: =SUM(W64:AA64) -> 0 | AC64: =+ROUND(N64*AC$6/(100+AC$6),0)+BI64 -> 0 | AD64: =+ROUND(O64*AD$6/(100+AD$6),0)+BJ64 -> 0 | AE64: =+ROUND(P64*AE$6/(100+AE$6),0)+BK64 -> 0 | AF64: =+ROUND(Q64*AF$6/(100+AF$6),0)+BL64 -> 0 | AG64: =+ROUND(R64*AG$6/(100+AG$6),0)+BM64 -> 0 | AH64: =SUM(AC64:AG64) -> 0 | AI64: =+E64-AB64 -> 0
A65: 3 | C65: 184030500 | D65: 農集 | E65: 0 | S65: =SUM(N65:R65) -> 0 | V65: =+E65 -> 0 | W65: =+ROUND(F65*F$6/(100+F$6),0)+AT65 -> 0 | X65: =+ROUND(G65*G$6/(100+G$6),0)+AU65 -> 0 | Y65: =+ROUND(H65*H$6/(100+H$6),0)+AV65 -> 0 | Z65: =+ROUND(I65*I$6/(100+I$6),0)+AW65 -> 0 | AA65: =+ROUND(J65*J$6/(100+J$6),0)+AX65 -> 0 | AB65: =SUM(W65:AA65) -> 0 | AC65: =+ROUND(N65*AC$6/(100+AC$6),0)+BI65 -> 0 | AD65: =+ROUND(O65*AD$6/(100+AD$6),0)+BJ65 -> 0 | AE65: =+ROUND(P65*AE$6/(100+AE$6),0)+BK65 -> 0 | AF65: =+ROUND(Q65*AF$6/(100+AF$6),0)+BL65 -> 0 | AG65: =+ROUND(R65*AG$6/(100+AG$6),0)+BM65 -> 0 | AH65: =SUM(AC65:AG65) -> 0 | AI65: =+E65-AB65 -> 0
A66: 4 | C66: 184030500 | D66: 浄化槽 | E66: 0 | S66: =SUM(N66:R66) -> 0 | V66: =+E66 -> 0 | W66: =+ROUND(F66*F$6/(100+F$6),0)+AT66 -> 0 | X66: =+ROUND(G66*G$6/(100+G$6),0)+AU66 -> 0 | Y66: =+ROUND(H66*H$6/(100+H$6),0)+AV66 -> 0 | Z66: =+ROUND(I66*I$6/(100+I$6),0)+AW66 -> 0 | AA66: =+ROUND(J66*J$6/(100+J$6),0)+AX66 -> 0 | AB66: =SUM(W66:AA66) -> 0 | AC66: =+ROUND(N66*AC$6/(100+AC$6),0)+BI66 -> 0 | AD66: =+ROUND(O66*AD$6/(100+AD$6),0)+BJ66 -> 0 | AE66: =+ROUND(P66*AE$6/(100+AE$6),0)+BK66 -> 0 | AF66: =+ROUND(Q66*AF$6/(100+AF$6),0)+BL66 -> 0 | AG66: =+ROUND(R66*AG$6/(100+AG$6),0)+BM66 -> 0 | AH66: =SUM(AC66:AG66) -> 0 | AI66: =+E66-AB66 -> 0
D67: 排水設備改造貸付借入金 | E67: =+SUM(E68:E70) -> 0 | F67: =+SUM(F68:F70) -> 0 | G67: =+SUM(G68:G70) -> 0 | H67: =+SUM(H68:H70) -> 0 | I67: =+SUM(I68:I70) -> 0 | J67: =+SUM(J68:J70) -> 0 | K67: =+SUM(K68:K70) -> 0 | L67: =+SUM(L68:L70) -> 0 | ... AI67: =+SUM(AI68:AI70) -> 0
A68: 2 | C68: 184030500 | D68: 特環 | E68: 0 | K68: =SUM(F68:J68) -> 0 | S68: =SUM(N68:R68) -> 0 | U68: =+V68-SUM(S68:T68) -> 0 | V68: =+E68 -> 0 | W68: =+ROUND(F68*F$6/(100+F$6),0)+AT68 -> 0 | X68: =+ROUND(G68*G$6/(100+G$6),0)+AU68 -> 0 | Y68: =+ROUND(H68*H$6/(100+H$6),0)+AV68 -> 0 | Z68: =+ROUND(I68*I$6/(100+I$6),0)+AW68 -> 0 | AA68: =+ROUND(J68*J$6/(100+J$6),0)+AX68 -> 0 | AB68: =SUM(W68:AA68) -> 0 | AC68: =+ROUND(N68*AC$6/(100+AC$6),0)+BI68 -> 0 | AD68: =+ROUND(O68*AD$6/(100+AD$6),0)+BJ68 -> 0 | AE68: =+ROUND(P68*AE$6/(100+AE$6),0)+BK68 -> 0 | AF68: =+ROUND(Q68*AF$6/(100+AF$6),0)+BL68 -> 0 | AG68: =+ROUND(R68*AG$6/(100+AG$6),0)+BM68 -> 0 | AH68: =SUM(AC68:AG68) -> 0 | AI68: =+E68-AB68 -> 0
A69: 3 | C69: 184030500 | D69: 農集 | E69: 0 | K69: =SUM(F69:J69) -> 0 | S69: =SUM(N69:R69) -> 0 | U69: =+V69-SUM(S69:T69) -> 0 | V69: =+E69 -> 0 | W69: =+ROUND(F69*F$6/(100+F$6),0)+AT69 -> 0 | X69: =+ROUND(G69*G$6/(100+G$6),0)+AU69 -> 0 | Y69: =+ROUND(H69*H$6/(100+H$6),0)+AV69 -> 0 | Z69: =+ROUND(I69*I$6/(100+I$6),0)+AW69 -> 0 | AA69: =+ROUND(J69*J$6/(100+J$6),0)+AX69 -> 0 | AB69: =SUM(W69:AA69) -> 0 | AC69: =+ROUND(N69*AC$6/(100+AC$6),0)+BI69 -> 0 | AD69: =+ROUND(O69*AD$6/(100+AD$6),0)+BJ69 -> 0 | AE69: =+ROUND(P69*AE$6/(100+AE$6),0)+BK69 -> 0 | AF69: =+ROUND(Q69*AF$6/(100+AF$6),0)+BL69 -> 0 | AG69: =+ROUND(R69*AG$6/(100+AG$6),0)+BM69 -> 0 | AH69: =SUM(AC69:AG69) -> 0 | AI69: =+E69-AB69 -> 0
A70: 4 | C70: 184030500 | D70: 浄化槽 | E70: 0 | K70: =SUM(F70:J70) -> 0 | S70: =SUM(N70:R70) -> 0 | U70: =+V70-SUM(S70:T70) -> 0 | V70: =+E70 -> 0 | W70: =+ROUND(F70*F$6/(100+F$6),0)+AT70 -> 0 | X70: =+ROUND(G70*G$6/(100+G$6),0)+AU70 -> 0 | Y70: =+ROUND(H70*H$6/(100+H$6),0)+AV70 -> 0 | Z70: =+ROUND(I70*I$6/(100+I$6),0)+AW70 -> 0 | AA70: =+ROUND(J70*J$6/(100+J$6),0)+AX70 -> 0 | AB70: =SUM(W70:AA70) -> 0 | AC70: =+ROUND(N70*AC$6/(100+AC$6),0)+BI70 -> 0 | AD70: =+ROUND(O70*AD$6/(100+AD$6),0)+BJ70 -> 0 | AE70: =+ROUND(P70*AE$6/(100+AE$6),0)+BK70 -> 0 | AF70: =+ROUND(Q70*AF$6/(100+AF$6),0)+BL70 -> 0 | AG70: =+ROUND(R70*AG$6/(100+AG$6),0)+BM70 -> 0 | AH70: =SUM(AC70:AG70) -> 0 | AI70: =+E70-AB70 -> 0
D71: 貸付金回収金 | E71: =+SUM(E72,E77,E82) -> 3987000 | F71: =+SUM(F72,F77,F82) -> 0 | G71: =+SUM(G72,G77,G82) -> 0 | H71: =+SUM(H72,H77,H82) -> 0 | I71: =+SUM(I72,I77,I82) -> 0 | J71: =+SUM(J72,J77,J82) -> 0 | K71: =+SUM(K72,K77,K82) -> 0 | L71: =+SUM(L72,L77,L82) -> 0 | ... AI71: =+SUM(AI72,AI77,AI82) -> 3987000
D72: 水洗便所改造資金貸付回収金 | E72: =+SUM(E73:E76) -> 2118000 | F72: =+SUM(F73:F76) -> 0 | G72: =+SUM(G73:G76) -> 0 | H72: =+SUM(H73:H76) -> 0 | I72: =+SUM(I73:I76) -> 0 | J72: =+SUM(J73:J76) -> 0 | K72: =+SUM(K73:K76) -> 0 | L72: =+SUM(L73:L76) -> 0 | ... AI72: =+SUM(AI73:AI76) -> 2118000
A73: 1 | C73: 184050600 | D73: 公共 | E73: =+SUMIFS([1]全伝票!I:I,[1]全伝票!$C:$C,$C73) -> 640000 | K73: =SUM(F73:J73) -> 0 | S73: =SUM(N73:R73) -> 0 | U73: =+V73-SUM(S73:T73) -> 640000 | V73: =+SUMIFS([1]全伝票!P:P,[1]全伝票!$C:$C,$C73) -> 640000 | W73: =+ROUND(F73*F$6/(100+F$6),0)+AT73 -> 0 | X73: =+ROUND(G73*G$6/(100+G$6),0)+AU73 -> 0 | Y73: =+ROUND(H73*H$6/(100+H$6),0)+AV73 -> 0 | Z73: =+ROUND(I73*I$6/(100+I$6),0)+AW73 -> 0 | AA73: =+ROUND(J73*J$6/(100+J$6),0)+AX73 -> 0 | AB73: =SUM(W73:AA73) -> 0 | AC73: =+ROUND(N73*AC$6/(100+AC$6),0)+BI73 -> 0 | AD73: =+ROUND(O73*AD$6/(100+AD$6),0)+BJ73 -> 0 | AE73: =+ROUND(P73*AE$6/(100+AE$6),0)+BK73 -> 0 | AF73: =+ROUND(Q73*AF$6/(100+AF$6),0)+BL73 -> 0 | AG73: =+ROUND(R73*AG$6/(100+AG$6),0)+BM73 -> 0 | AH73: =SUM(AC73:AG73) -> 0 | AI73: =+E73-AB73 -> 640000
A74: 2 | C74: 184050900 | D74: 特環 | E74: =+SUMIFS([1]全伝票!I:I,[1]全伝票!$C:$C,$C74) -> 580000 | K74: =SUM(F74:J74) -> 0 | S74: =SUM(N74:R74) -> 0 | U74: =+V74-SUM(S74:T74) -> 580000 | V74: =+SUMIFS([1]全伝票!P:P,[1]全伝票!$C:$C,$C74) -> 580000 | W74: =+ROUND(F74*F$6/(100+F$6),0)+AT74 -> 0 | X74: =+ROUND(G74*G$6/(100+G$6),0)+AU74 -> 0 | Y74: =+ROUND(H74*H$6/(100+H$6),0)+AV74 -> 0 | Z74: =+ROUND(I74*I$6/(100+I$6),0)+AW74 -> 0 | AA74: =+ROUND(J74*J$6/(100+J$6),0)+AX74 -> 0 | AB74: =SUM(W74:AA74) -> 0 | AC74: =+ROUND(N74*AC$6/(100+AC$6),0)+BI74 -> 0 | AD74: =+ROUND(O74*AD$6/(100+AD$6),0)+BJ74 -> 0 | AE74: =+ROUND(P74*AE$6/(100+AE$6),0)+BK74 -> 0 | AF74: =+ROUND(Q74*AF$6/(100+AF$6),0)+BL74 -> 0 | AG74: =+ROUND(R74*AG$6/(100+AG$6),0)+BM74 -> 0 | AH74: =SUM(AC74:AG74) -> 0 | AI74: =+E74-AB74 -> 580000
A75: 3 | C75: 184051200 | D75: 農集 | E75: =+SUMIFS([1]全伝票!I:I,[1]全伝票!$C:$C,$C75) -> 738000 | K75: =SUM(F75:J75) -> 0 | S75: =SUM(N75:R75) -> 0 | U75: =+V75-SUM(S75:T75) -> 738000 | V75: =+SUMIFS([1]全伝票!P:P,[1]全伝票!$C:$C,$C75) -> 738000 | W75: =+ROUND(F75*F$6/(100+F$6),0)+AT75 -> 0 | X75: =+ROUND(G75*G$6/(100+G$6),0)+AU75 -> 0 | Y75: =+ROUND(H75*H$6/(100+H$6),0)+AV75 -> 0 | Z75: =+ROUND(I75*I$6/(100+I$6),0)+AW75 -> 0 | AA75: =+ROUND(J75*J$6/(100+J$6),0)+AX75 -> 0 | AB75: =SUM(W75:AA75) -> 0 | AC75: =+ROUND(N75*AC$6/(100+AC$6),0)+BI75 -> 0 | AD75: =+ROUND(O75*AD$6/(100+AD$6),0)+BJ75 -> 0 | AE75: =+ROUND(P75*AE$6/(100+AE$6),0)+BK75 -> 0 | AF75: =+ROUND(Q75*AF$6/(100+AF$6),0)+BL75 -> 0 | AG75: =+ROUND(R75*AG$6/(100+AG$6),0)+BM75 -> 0 | AH75: =SUM(AC75:AG75) -> 0 | AI75: =+E75-AB75 -> 738000
A76: 4 | C76: 184051500 | D76: 浄化槽 | E76: =+SUMIFS([1]全伝票!I:I,[1]全伝票!$C:$C,$C76) -> 160000 | K76: =SUM(F76:J76) -> 0 | S76: =SUM(N76:R76) -> 0 | U76: =+V76-SUM(S76:T76) -> 160000 | V76: =+SUMIFS([1]全伝票!P:P,[1]全伝票!$C:$C,$C76) -> 160000 | W76: =+ROUND(F76*F$6/(100+F$6),0)+AT76 -> 0 | X76: =+ROUND(G76*G$6/(100+G$6),0)+AU76 -> 0 | Y76: =+ROUND(H76*H$6/(100+H$6),0)+AV76 -> 0 | Z76: =+ROUND(I76*I$6/(100+I$6),0)+AW76 -> 0 | AA76: =+ROUND(J76*J$6/(100+J$6),0)+AX76 -> 0 | AB76: =SUM(W76:AA76) -> 0 | AC76: =+ROUND(N76*AC$6/(100+AC$6),0)+BI76 -> 0 | AD76: =+ROUND(O76*AD$6/(100+AD$6),0)+BJ76 -> 0 | AE76: =+ROUND(P76*AE$6/(100+AE$6),0)+BK76 -> 0 | AF76: =+ROUND(Q76*AF$6/(100+AF$6),0)+BL76 -> 0 | AG76: =+ROUND(R76*AG$6/(100+AG$6),0)+BM76 -> 0 | AH76: =SUM(AC76:AG76) -> 0 | AI76: =+E76-AB76 -> 160000
D77: し尿浄化槽廃止資金貸付回収金 | E77: =+SUM(E78:E81) -> 1869000 | F77: =+SUM(F78:F81) -> 0 | G77: =+SUM(G78:G81) -> 0 | H77: =+SUM(H78:H81) -> 0 | I77: =+SUM(I78:I81) -> 0 | J77: =+SUM(J78:J81) -> 0 | K77: =+SUM(K78:K81) -> 0 | L77: =+SUM(L78:L81) -> 0 | ... AI77: =+SUM(AI78:AI81) -> 1869000
A78: 1 | C78: 184050700 | D78: 公共 | E78: =+SUMIFS([1]全伝票!I:I,[1]全伝票!$C:$C,$C78) -> 1079000 | K78: =SUM(F78:J78) -> 0 | S78: =SUM(N78:R78) -> 0 | U78: =+V78-SUM(S78:T78) -> 1079000 | V78: =+SUMIFS([1]全伝票!P:P,[1]全伝票!$C:$C,$C78) -> 1079000 | W78: =+ROUND(F78*F$6/(100+F$6),0)+AT78 -> 0 | X78: =+ROUND(G78*G$6/(100+G$6),0)+AU78 -> 0 | Y78: =+ROUND(H78*H$6/(100+H$6),0)+AV78 -> 0 | Z78: =+ROUND(I78*I$6/(100+I$6),0)+AW78 -> 0 | AA78: =+ROUND(J78*J$6/(100+J$6),0)+AX78 -> 0 | AB78: =SUM(W78:AA78) -> 0 | AC78: =+ROUND(N78*AC$6/(100+AC$6),0)+BI78 -> 0 | AD78: =+ROUND(O78*AD$6/(100+AD$6),0)+BJ78 -> 0 | AE78: =+ROUND(P78*AE$6/(100+AE$6),0)+BK78 -> 0 | AF78: =+ROUND(Q78*AF$6/(100+AF$6),0)+BL78 -> 0 | AG78: =+ROUND(R78*AG$6/(100+AG$6),0)+BM78 -> 0 | AH78: =SUM(AC78:AG78) -> 0 | AI78: =+E78-AB78 -> 1079000
A79: 2 | C79: 184051000 | D79: 特環 | E79: =+SUMIFS([1]全伝票!I:I,[1]全伝票!$C:$C,$C79) -> 440000 | K79: =SUM(F79:J79) -> 0 | S79: =SUM(N79:R79) -> 0 | U79: =+V79-SUM(S79:T79) -> 440000 | V79: =+SUMIFS([1]全伝票!P:P,[1]全伝票!$C:$C,$C79) -> 440000 | W79: =+ROUND(F79*F$6/(100+F$6),0)+AT79 -> 0 | X79: =+ROUND(G79*G$6/(100+G$6),0)+AU79 -> 0 | Y79: =+ROUND(H79*H$6/(100+H$6),0)+AV79 -> 0 | Z79: =+ROUND(I79*I$6/(100+I$6),0)+AW79 -> 0 | AA79: =+ROUND(J79*J$6/(100+J$6),0)+AX79 -> 0 | AB79: =SUM(W79:AA79) -> 0 | AC79: =+ROUND(N79*AC$6/(100+AC$6),0)+BI79 -> 0 | AD79: =+ROUND(O79*AD$6/(100+AD$6),0)+BJ79 -> 0 | AE79: =+ROUND(P79*AE$6/(100+AE$6),0)+BK79 -> 0 | AF79: =+ROUND(Q79*AF$6/(100+AF$6),0)+BL79 -> 0 | AG79: =+ROUND(R79*AG$6/(100+AG$6),0)+BM79 -> 0 | AH79: =SUM(AC79:AG79) -> 0 | AI79: =+E79-AB79 -> 440000
A80: 3 | C80: 184051300 | D80: 農集 | E80: =+SUMIFS([1]全伝票!I:I,[1]全伝票!$C:$C,$C80) -> 350000 | K80: =SUM(F80:J80) -> 0 | S80: =SUM(N80:R80) -> 0 | U80: =+V80-SUM(S80:T80) -> 350000 | V80: =+SUMIFS([1]全伝票!P:P,[1]全伝票!$C:$C,$C80) -> 350000 | W80: =+ROUND(F80*F$6/(100+F$6),0)+AT80 -> 0 | X80: =+ROUND(G80*G$6/(100+G$6),0)+AU80 -> 0 | Y80: =+ROUND(H80*H$6/(100+H$6),0)+AV80 -> 0 | Z80: =+ROUND(I80*I$6/(100+I$6),0)+AW80 -> 0 | AA80: =+ROUND(J80*J$6/(100+J$6),0)+AX80 -> 0 | AB80: =SUM(W80:AA80) -> 0 | AC80: =+ROUND(N80*AC$6/(100+AC$6),0)+BI80 -> 0 | AD80: =+ROUND(O80*AD$6/(100+AD$6),0)+BJ80 -> 0 | AE80: =+ROUND(P80*AE$6/(100+AE$6),0)+BK80 -> 0 | AF80: =+ROUND(Q80*AF$6/(100+AF$6),0)+BL80 -> 0 | AG80: =+ROUND(R80*AG$6/(100+AG$6),0)+BM80 -> 0 | AH80: =SUM(AC80:AG80) -> 0 | AI80: =+E80-AB80 -> 350000
A81: 4 | C81: 184051600 | D81: 浄化槽 | E81: =+SUMIFS([1]全伝票!I:I,[1]全伝票!$C:$C,$C81) -> 0 | K81: =SUM(F81:J81) -> 0 | S81: =SUM(N81:R81) -> 0 | U81: =+V81-SUM(S81:T81) -> 0 | V81: =+SUMIFS([1]全伝票!P:P,[1]全伝票!$C:$C,$C81) -> 0 | W81: =+ROUND(F81*F$6/(100+F$6),0)+AT81 -> 0 | X81: =+ROUND(G81*G$6/(100+G$6),0)+AU81 -> 0 | Y81: =+ROUND(H81*H$6/(100+H$6),0)+AV81 -> 0 | Z81: =+ROUND(I81*I$6/(100+I$6),0)+AW81 -> 0 | AA81: =+ROUND(J81*J$6/(100+J$6),0)+AX81 -> 0 | AB81: =SUM(W81:AA81) -> 0 | AC81: =+ROUND(N81*AC$6/(100+AC$6),0)+BI81 -> 0 | AD81: =+ROUND(O81*AD$6/(100+AD$6),0)+BJ81 -> 0 | AE81: =+ROUND(P81*AE$6/(100+AE$6),0)+BK81 -> 0 | AF81: =+ROUND(Q81*AF$6/(100+AF$6),0)+BL81 -> 0 | AG81: =+ROUND(R81*AG$6/(100+AG$6),0)+BM81 -> 0 | AH81: =SUM(AC81:AG81) -> 0 | AI81: =+E81-AB81 -> 0
D82: 排水設備改修資金貸付回収金 | E82: =+SUM(E83:E86) -> 0 | F82: =+SUM(F83:F86) -> 0 | G82: =+SUM(G83:G86) -> 0 | H82: =+SUM(H83:H86) -> 0 | I82: =+SUM(I83:I86) -> 0 | J82: =+SUM(J83:J86) -> 0 | K82: =+SUM(K83:K86) -> 0 | L82: =+SUM(L83:L86) -> 0 | ... AI82: =+SUM(AI83:AI86) -> 0
A83: 1 | C83: 184050800 | D83: 公共 | E83: =+SUMIFS([1]全伝票!I:I,[1]全伝票!$C:$C,$C83) -> 0 | K83: =SUM(F83:J83) -> 0 | S83: =SUM(N83:R83) -> 0 | U83: =+V83-SUM(S83:T83) -> 0 | V83: =+SUMIFS([1]全伝票!P:P,[1]全伝票!$C:$C,$C83) -> 0 | W83: =+ROUND(F83*F$6/(100+F$6),0)+AT83 -> 0 | X83: =+ROUND(G83*G$6/(100+G$6),0)+AU83 -> 0 | Y83: =+ROUND(H83*H$6/(100+H$6),0)+AV83 -> 0 | Z83: =+ROUND(I83*I$6/(100+I$6),0)+AW83 -> 0 | AA83: =+ROUND(J83*J$6/(100+J$6),0)+AX83 -> 0 | AB83: =SUM(W83:AA83) -> 0 | AC83: =+ROUND(N83*AC$6/(100+AC$6),0)+BI83 -> 0 | AD83: =+ROUND(O83*AD$6/(100+AD$6),0)+BJ83 -> 0 | AE83: =+ROUND(P83*AE$6/(100+AE$6),0)+BK83 -> 0 | AF83: =+ROUND(Q83*AF$6/(100+AF$6),0)+BL83 -> 0 | AG83: =+ROUND(R83*AG$6/(100+AG$6),0)+BM83 -> 0 | AH83: =SUM(AC83:AG83) -> 0 | AI83: =+E83-AB83 -> 0
A84: 2 | C84: 184051100 | D84: 特環 | E84: =+SUMIFS([1]全伝票!I:I,[1]全伝票!$C:$C,$C84) -> 0 | K84: =SUM(F84:J84) -> 0 | S84: =SUM(N84:R84) -> 0 | U84: =+V84-SUM(S84:T84) -> 0 | V84: =+SUMIFS([1]全伝票!P:P,[1]全伝票!$C:$C,$C84) -> 0 | W84: =+ROUND(F84*F$6/(100+F$6),0)+AT84 -> 0 | X84: =+ROUND(G84*G$6/(100+G$6),0)+AU84 -> 0 | Y84: =+ROUND(H84*H$6/(100+H$6),0)+AV84 -> 0 | Z84: =+ROUND(I84*I$6/(100+I$6),0)+AW84 -> 0 | AA84: =+ROUND(J84*J$6/(100+J$6),0)+AX84 -> 0 | AB84: =SUM(W84:AA84) -> 0 | AC84: =+ROUND(N84*AC$6/(100+AC$6),0)+BI84 -> 0 | AD84: =+ROUND(O84*AD$6/(100+AD$6),0)+BJ84 -> 0 | AE84: =+ROUND(P84*AE$6/(100+AE$6),0)+BK84 -> 0 | AF84: =+ROUND(Q84*AF$6/(100+AF$6),0)+BL84 -> 0 | AG84: =+ROUND(R84*AG$6/(100+AG$6),0)+BM84 -> 0 | AH84: =SUM(AC84:AG84) -> 0 | AI84: =+E84-AB84 -> 0
A85: 3 | C85: 184051400 | D85: 農集 | E85: =+SUMIFS([1]全伝票!I:I,[1]全伝票!$C:$C,$C85) -> 0 | K85: =SUM(F85:J85) -> 0 | S85: =SUM(N85:R85) -> 0 | U85: =+V85-SUM(S85:T85) -> 0 | V85: =+SUMIFS([1]全伝票!P:P,[1]全伝票!$C:$C,$C85) -> 0 | W85: =+ROUND(F85*F$6/(100+F$6),0)+AT85 -> 0 | X85: =+ROUND(G85*G$6/(100+G$6),0)+AU85 -> 0 | Y85: =+ROUND(H85*H$6/(100+H$6),0)+AV85 -> 0 | Z85: =+ROUND(I85*I$6/(100+I$6),0)+AW85 -> 0 | AA85: =+ROUND(J85*J$6/(100+J$6),0)+AX85 -> 0 | AB85: =SUM(W85:AA85) -> 0 | AC85: =+ROUND(N85*AC$6/(100+AC$6),0)+BI85 -> 0 | AD85: =+ROUND(O85*AD$6/(100+AD$6),0)+BJ85 -> 0 | AE85: =+ROUND(P85*AE$6/(100+AE$6),0)+BK85 -> 0 | AF85: =+ROUND(Q85*AF$6/(100+AF$6),0)+BL85 -> 0 | AG85: =+ROUND(R85*AG$6/(100+AG$6),0)+BM85 -> 0 | AH85: =SUM(AC85:AG85) -> 0 | AI85: =+E85-AB85 -> 0
A86: 4 | C86: 184051700 | D86: 浄化槽 | E86: =+SUMIFS([1]全伝票!I:I,[1]全伝票!$C:$C,$C86) -> 0 | K86: =SUM(F86:J86) -> 0 | S86: =SUM(N86:R86) -> 0 | U86: =+V86-SUM(S86:T86) -> 0 | V86: =+SUMIFS([1]全伝票!P:P,[1]全伝票!$C:$C,$C86) -> 0 | W86: =+ROUND(F86*F$6/(100+F$6),0)+AT86 -> 0 | X86: =+ROUND(G86*G$6/(100+G$6),0)+AU86 -> 0 | Y86: =+ROUND(H86*H$6/(100+H$6),0)+AV86 -> 0 | Z86: =+ROUND(I86*I$6/(100+I$6),0)+AW86 -> 0 | AA86: =+ROUND(J86*J$6/(100+J$6),0)+AX86 -> 0 | AB86: =SUM(W86:AA86) -> 0 | AC86: =+ROUND(N86*AC$6/(100+AC$6),0)+BI86 -> 0 | AD86: =+ROUND(O86*AD$6/(100+AD$6),0)+BJ86 -> 0 | AE86: =+ROUND(P86*AE$6/(100+AE$6),0)+BK86 -> 0 | AF86: =+ROUND(Q86*AF$6/(100+AF$6),0)+BL86 -> 0 | AG86: =+ROUND(R86*AG$6/(100+AG$6),0)+BM86 -> 0 | AH86: =SUM(AC86:AG86) -> 0 | AI86: =+E86-AB86 -> 0
D87: 固定資産売却代金 | E87: =+E88 -> 45948113 | F87: =+F88 -> 0 | G87: =+G88 -> 0 | H87: =+H88 -> 0 | I87: =+I88 -> 0 | J87: =+J88 -> 0 | K87: =+K88 -> 0 | L87: =+L88 -> 45948113 | ... AI87: =+AI88 -> 45948113
C88: 188010100 | D88: 土地売却代金 | E88: =+SUMIFS([1]全伝票!I:I,[1]全伝票!$C:$C,$C88) -> 45948113 | K88: =SUM(F88:J88) -> 0 | L88: =+SUMIFS([1]全伝票!O:O,[1]全伝票!$C:$C,$C88) -> 45948113 | S88: =SUM(N88:R88) -> 0 | U88: =+V88-SUM(S88:T88) -> 0 | V88: =+SUMIFS([1]全伝票!P:P,[1]全伝票!$C:$C,$C88) -> 0 | W88: =+ROUND(F88*F$6/(100+F$6),0)+AT88 -> 0 | X88: =+ROUND(G88*G$6/(100+G$6),0)+AU88 -> 0 | Y88: =+ROUND(H88*H$6/(100+H$6),0)+AV88 -> 0 | Z88: =+ROUND(I88*I$6/(100+I$6),0)+AW88 -> 0 | AA88: =+ROUND(J88*J$6/(100+J$6),0)+AX88 -> 0 | AB88: =SUM(W88:AA88) -> 0 | AC88: =+ROUND(N88*AC$6/(100+AC$6),0)+BI88 -> 0 | AD88: =+ROUND(O88*AD$6/(100+AD$6),0)+BJ88 -> 0 | AE88: =+ROUND(P88*AE$6/(100+AE$6),0)+BK88 -> 0 | AF88: =+ROUND(Q88*AF$6/(100+AF$6),0)+BL88 -> 0 | AG88: =+ROUND(R88*AG$6/(100+AG$6),0)+BM88 -> 0 | AH88: =SUM(AC88:AG88) -> 0 | AI88: =+E88-AB88 -> 45948113 | AJ88: =W88-F88*W$6/(100+W$6) -> 0 | AK88: =X88-G88*X$6/(100+X$6) -> 0 | AL88: =Y88-H88*Y$6/(100+Y$6) -> 0 | AM88: =Z88-I88*Z$6/(100+Z$6) -> 0 | AN88: =AA88-J88*AA$6/(100+AA$6) -> 0 | AO88: =+IF(W$87=0,0,IF(W$87<0,-RANK(AJ88,AJ$7:AJ$84,0),RANK(AJ88,AJ$7:AJ$84,1))) -> 0 | AP88: =+IF(X$87=0,0,IF(X$87<0,-RANK(AK88,AK$7:AK$84,0),RANK(AK88,AK$7:AK$84,1))) -> 0 | AQ88: =+IF(Y$87=0,0,IF(Y$87<0,-RANK(AL88,AL$7:AL$84,0),RANK(AL88,AL$7:AL$84,1))) -> 0 | AR88: =+IF(Z$87=0,0,IF(Z$87<0,-RANK(AM88,AM$7:AM$84,0),RANK(AM88,AM$7:AM$84,1))) -> 0 | AS88: =+IF(AA$87=0,0,IF(AA$87<0,-RANK(AN88,AN$7:AN$84,0),RANK(AN88,AN$7:AN$84,1))) -> 0
D89: その他資本的収入 | E89: =+E90 -> 0 | F89: =+F90 -> 0 | G89: =+G90 -> 0 | H89: =+H90 -> 0 | I89: =+I90 -> 0 | J89: =+J90 -> 0 | K89: =+K90 -> 0 | L89: =+L90 -> 0 | ... AI89: =+AI90 -> 0
C90: 190030300 | D90: その他資本的収入 | E90: =+SUMIFS([1]全伝票!I:I,[1]全伝票!$C:$C,$C90) -> 0 | F90: =+SUMIFS([1]全伝票!J:J,[1]全伝票!$C:$C,$C90) -> 0 | G90: =+SUMIFS([1]全伝票!K:K,[1]全伝票!$C:$C,$C90) -> 0 | H90: =+SUMIFS([1]全伝票!L:L,[1]全伝票!$C:$C,$C90) -> 0 | I90: =+SUMIFS([1]全伝票!M:M,[1]全伝票!$C:$C,$C90) -> 0 | J90: =+SUMIFS([1]全伝票!N:N,[1]全伝票!$C:$C,$C90) -> 0 | K90: =SUM(F90:J90) -> 0 | L90: =+SUMIFS([1]全伝票!O:O,[1]全伝票!$C:$C,$C90) -> 0 | S90: =SUM(N90:R90) -> 0 | U90: =+V90-SUM(S90:T90) -> 0 | V90: =+SUMIFS([1]全伝票!P:P,[1]全伝票!$C:$C,$C90) -> 0 | W90: =+ROUND(F90*F$6/(100+F$6),0)+AT90 -> 0 | X90: =+ROUND(G90*G$6/(100+G$6),0)+AU90 -> 0 | Y90: =+ROUND(H90*H$6/(100+H$6),0)+AV90 -> 0 | Z90: =+ROUND(I90*I$6/(100+I$6),0)+AW90 -> 0 | AA90: =+ROUND(J90*J$6/(100+J$6),0)+AX90 -> 0 | AB90: =SUM(W90:AA90) -> 0 | AC90: =+ROUND(N90*AC$6/(100+AC$6),0)+BI90 -> 0 | AD90: =+ROUND(O90*AD$6/(100+AD$6),0)+BJ90 -> 0 | AE90: =+ROUND(P90*AE$6/(100+AE$6),0)+BK90 -> 0 | AF90: =+ROUND(Q90*AF$6/(100+AF$6),0)+BL90 -> 0 | AG90: =+ROUND(R90*AG$6/(100+AG$6),0)+BM90 -> 0 | AH90: =SUM(AC90:AG90) -> 0 | AI90: =+E90-AB90 -> 0 | AJ90: =W90-F90*W$6/(100+W$6) -> 0 | AK90: =X90-G90*X$6/(100+X$6) -> 0 | AL90: =Y90-H90*Y$6/(100+Y$6) -> 0 | AM90: =Z90-I90*Z$6/(100+Z$6) -> 0 | AN90: =AA90-J90*AA$6/(100+AA$6) -> 0 | AO90: =+IF(W$87=0,0,IF(W$87<0,-RANK(AJ90,AJ$7:AJ$84,0),RANK(AJ90,AJ$7:AJ$84,1))) -> 0 | AP90: =+IF(X$87=0,0,IF(X$87<0,-RANK(AK90,AK$7:AK$84,0),RANK(AK90,AK$7:AK$84,1))) -> 0 | AQ90: =+IF(Y$87=0,0,IF(Y$87<0,-RANK(AL90,AL$7:AL$84,0),RANK(AL90,AL$7:AL$84,1))) -> 0 | AR90: =+IF(Z$87=0,0,IF(Z$87<0,-RANK(AM90,AM$7:AM$84,0),RANK(AM90,AM$7:AM$84,1))) -> 0 | AS90: =+IF(AA$87=0,0,IF(AA$87<0,-RANK(AN90,AN$7:AN$84,0),RANK(AN90,AN$7:AN$84,1))) -> 0
D91: 計 | E91: =+SUM(E7,E21,E23,E35,E37,E42,E55,E87,E89) -> 42025205141 | F91: =+SUM(F7,F21,F23,F35,F37,F42,F55,F87,F89) -> 0 | G91: =+SUM(G7,G21,G23,G35,G37,G42,G55,G87,G89) -> 0 | H91: =+SUM(H7,H21,H23,H35,H37,H42,H55,H87,H89) -> 0 | I91: =+SUM(I7,I21,I23,I35,I37,I42,I55,I87,I89) -> 0 | J91: =+SUM(J7,J21,J23,J35,J37,J42,J55,J87,J89) -> 39691410 | K91: =+SUM(K7,K21,K23,K35,K37,K42,K55,K87,K89) -> 39691410 | L91: =+SUM(L7,L21,L23,L35,L37,L42,L55,L87,L89) -> 45948113 | ... AI91: =+SUM(AI7,AI21,AI23,AI35,AI37,AI42,AI55,AI87,AI89) -> 42021596831
D92: 総額検算 | E92: =+E91 -> 42025205141 | F92: =+F91 -> 0 | G92: =+G91 -> 0 | H92: =+H91 -> 0 | I92: =+I91 -> 0 | J92: =+J91 -> 39691410 | K92: =SUM(F92:J92) -> 39691410 | L92: =+L91 -> 45948113 | M92: =+M91 -> 0 | N92: =+N91 -> 0 | O92: =+O91 -> 131982078 | P92: =+P91 -> 1246904 | Q92: =+Q91 -> 99 | R92: =+R91 -> 5972404802 | S92: =SUM(N92:R92) -> 6105633883 | T92: =+T91 -> 171140184 | U92: =+U91 -> 35662791551 | V92: =+V91 -> 41939565618 | W92: =+ROUNDDOWN(F92*F$6/(100+F$6),0) -> 0 | X92: =+ROUNDDOWN(G92*G$6/(100+G$6),0) -> 0 | Y92: =+ROUNDDOWN(H92*H$6/(100+H$6),0) -> 0 | Z92: =+ROUNDDOWN(I92*I$6/(100+I$6),0) -> 0 | AA92: =+ROUNDDOWN(J92*J$6/(100+J$6),0) -> 3608310 | AB92: =SUM(W92:AA92) -> 3608310 | AC92: =+[4]消費税!AA$86 -> 0 | AD92: =+[4]消費税!AB$91 -> 6284860 | AE92: =+[4]消費税!AC$91 -> 92363 | AF92: =+[4]消費税!AD$91 -> 7 | AG92: =+[4]消費税!AE$91 -> 542945891 | AH92: =SUM(AC92:AG92) -> 549323121 | AI92: =+E92-AB92 -> 42021596831
E93: =+E92-E91 -> 0 | F93: =+F92-F91 -> 0 | G93: =+G92-G91 -> 0 | H93: =+H92-H91 -> 0 | I93: =+I92-I91 -> 0 | J93: =+J92-J91 -> 0 | K93: =+K92-K91 -> 0 | L93: =+L92-L91 -> 0 | ... AI93: =+AI92-AI91 -> 0 | AJ93: =+IF(F93=0,"",ROUND(F93*F$6/(100+F$6),7)-W93) | AK93: =+IF(G93=0,"",ROUND(G93*G$6/(100+G$6),7)-X93) | AL93: =+IF(H93=0,"",ROUND(H93*H$6/(100+H$6),7)-Y93) | AM93: =+IF(I93=0,"",ROUND(I93*I$6/(100+I$6),7)-Z93) | AN93: =+IF(J93=0,"",ROUND(J93*J$6/(100+J$6),7)-AA93) | AO93: =+IF(SUM(AJ93:AN93)=0,"",SUM(AJ93:AN93))
AJ94: =+IF(F94=0,"",ROUND(F94*F$6/(100+F$6),7)-W94) | AK94: =+IF(G94=0,"",ROUND(G94*G$6/(100+G$6),7)-X94) | AL94: =+IF(H94=0,"",ROUND(H94*H$6/(100+H$6),7)-Y94) | AN94: =+IF(J94=0,"",ROUND(J94*J$6/(100+J$6),7)-AA94) | AO94: =+IF(SUM(AJ94:AN94)=0,"",SUM(AJ94:AN94))
AJ95: =+IF(F95=0,"",ROUND(F95*F$6/(100+F$6),7)-W95) | AK95: =+IF(G95=0,"",ROUND(G95*G$6/(100+G$6),7)-X95) | AL95: =+IF(H95=0,"",ROUND(H95*H$6/(100+H$6),7)-Y95) | AN95: =+IF(J95=0,"",ROUND(J95*J$6/(100+J$6),7)-AA95) | AO95: =+IF(SUM(AJ95:AN95)=0,"",SUM(AJ95:AN95))
