Workbook

Sheet 雨汚水
D1: =+'[1]3条支出'!$D$1 -> 令和５年度決算 消費税算出資料 | N1: =+$D$1 -> 令和５年度決算 消費税算出資料 | X1: =+$D$1 -> 令和５年度決算 消費税算出資料
D2: 【３条支出雨汚水分け表】 | M2: =+IF(COUNTIF(M7:M45,0)=COUNT(M7:M45),"","↓エラーあり") | N2: 【３条支出雨汚水分け表】 | W2: =+IF(COUNTIF(W7:W45,0)=COUNT(W7:W45),"","↓エラーあり") | X2: 【３条支出雨汚水分け表】（消費税雑支出加算後） | AL2: =+IF(COUNTIF(AL7:AL45,0)=COUNT(AL7:AL45),"","↓エラーあり")
B3: 区分 | D3: 費目 | E3: ３条支出 税込み | N3: 費目 | O3: ３条支出 税抜き | X3: 費目 | AD3: ３条支出 税抜き
E4: 税込決算額 | F4: 雨水 | J4: 汚水 | M4: チェック | O4: 税抜決算額 | P4: 雨水 | T4: 汚水 | W4: チェック | AD4: 税抜決算額 | AE4: 雨水 | AI4: 汚水 | AL4: チェック
F5: 繰出基準内 | G5: 繰出基準内 | H5: 繰出基準外 | I5: 計 | J5: 繰出基準内 | K5: 繰出基準外 | L5: 計 | P5: 繰出基準内 | Q5: 繰出基準内 | R5: 繰出基準外 | S5: 計 | T5: 繰出基準内 | U5: 繰出基準外 | V5: 計 | AE5: 繰出基準内 | AF5: 繰出基準内 | AG5: 繰出基準外 | AH5: 計 | AI5: 繰出基準内 | AJ5: 繰出基準外 | AK5: 計 | AM5: 4月決見 | AQ5: 当初予算
F6: 使用料徴収区域内 | G6: 使用料徴収区域外 | H6: 一般行政経費 | J6: 使用料徴収区域内 | K6: 使用料徴収区域内 | P6: 使用料徴収区域内 | Q6: 使用料徴収区域外 | R6: 一般行政経費 | T6: 使用料徴収区域内 | U6: 使用料徴収区域内 | AE6: 使用料徴収区域内 | AF6: 使用料徴収区域外 | AG6: 一般行政経費 | AI6: 使用料徴収区域内 | AJ6: 使用料徴収区域内 | AM6: 一般会計負担金分 | AN6: 決算見込 | AQ6: 当初予算 | AT6: 決算見込
B7: 維持 | C7: 営業 | D7: 管きょ費 | E7: =+'[1]3条支出'!E6 -> 611819957 | F7: 285727057 | G7: 60054665 | H7: 0 | I7: =+SUM(F7:H7) -> 345781722 | K7: 266038235 | L7: =+SUM(J7:K7) -> 266038235 | M7: =E7-SUM(I7,L7) -> 0 | N7: 管きょ費 | O7: =+'[1]3条支出'!T6 -> 564664608 | P7: =+IFERROR(ROUND(F7*$O7/$E7,0),0) -> 263704959 | Q7: =+IFERROR(ROUND(G7*$O7/$E7,0),0) -> 55426018 | R7: =+IFERROR(ROUND(H7*$O7/$E7,0),0) -> 0 | S7: =+SUM(P7:R7) -> 319130977 | T7: =+IFERROR(ROUND(J7*$O7/$E7,0),0) -> 0 | U7: =+O7-S7-T7 -> 245533631 | V7: =+SUM(T7:U7) -> 245533631 | W7: =O7-SUM(S7,V7) -> 0 | X7: 管きょ費 | AD7: =+O7 -> 564664608 | AE7: =+P7 -> 263704959 | AF7: =+Q7 -> 55426018 | AG7: =+R7 -> 0 | AH7: =+SUM(AE7:AG7) -> 319130977 | AI7: =+T7 -> 0 | AJ7: =+U7 -> 245533631 | AK7: =+SUM(AI7:AJ7) -> 245533631 | AL7: =AD7-SUM(AH7,AK7) -> 0 | AM7: =SUM(AE7:AG7,AI7) -> 319130977 | AN7: 336288000 | AO7: =AM7-AN7 -> -17157023 | AQ7: 345982000 | AR7: =AM7-AQ7 -> -26851023 | AT7: #=SUM('[4-04 集計表.xlsx]3条集計(税抜)'!R24:T24)
B8: 維持 | C8: 営業 | D8: 水質指導費 | E8: =+'[1]3条支出'!E7 -> 52443869 | I8: =+SUM(F8:H8) -> 0 | J8: =+E8 -> 52443869 | K8: =+E8-I8-J8 -> 0 | L8: =+SUM(J8:K8) -> 52443869 | M8: =E8-SUM(I8,L8) -> 0 | N8: 水質指導費 | O8: =+'[1]3条支出'!T7 -> 51313295 | P8: =+IFERROR(ROUND(F8*$O8/$E8,0),0) -> 0 | Q8: =+IFERROR(ROUND(G8*$O8/$E8,0),0) -> 0 | R8: =+IFERROR(ROUND(H8*$O8/$E8,0),0) -> 0 | S8: =+SUM(P8:R8) -> 0 | T8: =+IFERROR(ROUND(J8*$O8/$E8,0),0) -> 51313295 | U8: =+O8-S8-T8 -> 0 | V8: =+SUM(T8:U8) -> 51313295 | W8: =O8-SUM(S8,V8) -> 0 | X8: 水質指導費 | AD8: =+O8 -> 51313295 | AE8: =+P8 -> 0 | AF8: =+Q8 -> 0 | AG8: =+R8 -> 0 | AH8: =+SUM(AE8:AG8) -> 0 | AI8: =+T8 -> 51313295 | AJ8: =+U8 -> 0 | AK8: =+SUM(AI8:AJ8) -> 51313295 | AL8: =AD8-SUM(AH8,AK8) -> 0 | AM8: =SUM(AE8:AG8,AI8) -> 51313295 | AN8: 51456000 | AO8: =AM8-AN8 -> -142705 | AQ8: 60255000 | AR8: =AM8-AQ8 -> -8941705 | AT8: #=SUM('[4-04 集計表.xlsx]3条集計(税抜)'!R25:T25)
B9: 維持 | C9: 営業 | D9: ポンプ場費 | E9: =+'[1]3条支出'!E8 -> 2356040225 | F9: 1724925338 | G9: 55051811 | I9: =+SUM(F9:H9) -> 1779977149 | K9: 576063076 | L9: =+SUM(J9:K9) -> 576063076 | M9: =E9-SUM(I9,L9) -> 0 | N9: ポンプ場費 | O9: =+'[1]3条支出'!T8 -> 2251657967 | P9: =+IFERROR(ROUND(F9*$O9/$E9,0),0) -> 1648504061 | Q9: =+IFERROR(ROUND(G9*$O9/$E9,0),0) -> 52612790 | R9: =+IFERROR(ROUND(H9*$O9/$E9,0),0) -> 0 | S9: =+SUM(P9:R9) -> 1701116851 | T9: =+IFERROR(ROUND(J9*$O9/$E9,0),0) -> 0 | U9: =+O9-S9-T9 -> 550541116 | V9: =+SUM(T9:U9) -> 550541116 | W9: =O9-SUM(S9,V9) -> 0 | X9: ポンプ場費 | AD9: =+O9 -> 2251657967 | AE9: =+P9 -> 1648504061 | AF9: =+Q9 -> 52612790 | AG9: =+R9 -> 0 | AH9: =+SUM(AE9:AG9) -> 1701116851 | AI9: =+T9 -> 0 | AJ9: =+U9 -> 550541116 | AK9: =+SUM(AI9:AJ9) -> 550541116 | AL9: =AD9-SUM(AH9,AK9) -> 0 | AM9: =SUM(AE9:AG9,AI9) -> 1701116851 | AN9: 1645552000 | AO9: =AM9-AN9 -> 55564851 | AQ9: 1697315000 | AR9: =AM9-AQ9 -> 3801851 | AT9: #=SUM('[4-04 集計表.xlsx]3条集計(税抜)'!R26:T26)
B10: 維持 | C10: 営業 | D10: 処理場費 | E10: =+'[1]3条支出'!E9 -> 6557703864 | F10: 703775367 | G10: 144110894 | H10: 445816778 | I10: =+SUM(F10:H10) -> 1293703039 | J10: =83018974+51475850 -> 134494824 | K10: =5180981851-51475850 -> 5129506001 | L10: =+SUM(J10:K10) -> 5264000825 | M10: =E10-SUM(I10,L10) -> 0 | N10: 処理場費 | O10: =+'[1]3条支出'!T9 -> 6037810078 | P10: =+IFERROR(ROUND(F10*$O10/$E10,0),0) -> 647980161 | Q10: =+IFERROR(ROUND(G10*$O10/$E10,0),0) -> 132685804 | R10: =+IFERROR(ROUND(H10*$O10/$E10,0),0) -> 410472490 | S10: =+SUM(P10:R10) -> 1191138455 | T10: =+IFERROR(ROUND(J10*$O10/$E10,0),0) -> 123832094 | U10: =+O10-S10-T10 -> 4722839529 | V10: =+SUM(T10:U10) -> 4846671623 | W10: =O10-SUM(S10,V10) -> 0 | X10: 処理場費 | AD10: =+O10 -> 6037810078 | AE10: =+P10 -> 647980161 | AF10: =+Q10 -> 132685804 | AG10: =+R10 -> 410472490 | AH10: =+SUM(AE10:AG10) -> 1191138455 | AI10: =+T10 -> 123832094 | AJ10: =+U10 -> 4722839529 | AK10: =+SUM(AI10:AJ10) -> 4846671623 | AL10: =AD10-SUM(AH10,AK10) -> 0 | AM10: =SUM(AE10:AG10,AI10) -> 1314970549 | AN10: 1151544454 | AO10: =AM10-AN10 -> 163426095 | AQ10: 1274316000 | AR10: =AM10-AQ10 -> 40654549 | AT10: #=SUM('[4-04 集計表.xlsx]3条集計(税抜)'!R27:T27)
B11: 維持 | C11: 営業 | D11: 受託工事費 | E11: =+'[1]3条支出'!E10 -> 0 | I11: =+SUM(F11:H11) -> 0 | K11: =+E11-I11-J11 -> 0 | L11: =+SUM(J11:K11) -> 0 | M11: =E11-SUM(I11,L11) -> 0 | N11: 受託工事費 | O11: =+'[1]3条支出'!T10 -> 0 | P11: =+IFERROR(ROUND(F11*$O11/$E11,0),0) -> 0 | Q11: =+IFERROR(ROUND(G11*$O11/$E11,0),0) -> 0 | R11: =+IFERROR(ROUND(H11*$O11/$E11,0),0) -> 0 | S11: =+SUM(P11:R11) -> 0 | T11: =+IFERROR(ROUND(J11*$O11/$E11,0),0) -> 0 | U11: =+O11-S11-T11 -> 0 | V11: =+SUM(T11:U11) -> 0 | W11: =O11-SUM(S11,V11) -> 0 | X11: 受託工事費 | AD11: =+O11 -> 0 | AE11: =+P11 -> 0 | AF11: =+Q11 -> 0 | AG11: =+R11 -> 0 | AH11: =+SUM(AE11:AG11) -> 0 | AI11: =+T11 -> 0 | AJ11: =+U11 -> 0 | AK11: =+SUM(AI11:AJ11) -> 0 | AL11: =AD11-SUM(AH11,AK11) -> 0 | AM11: =SUM(AE11:AG11,AI11) -> 0 | AO11: =AM11-AN11 -> 0 | AR11: =AM11-AQ11 -> 0
B12: 維持 | C12: 営業 | D12: 普及促進費 | E12: =+'[1]3条支出'!E11 -> 88849549 | H12: =+補助補給!Y4 -> 0 | I12: =+SUM(F12:H12) -> 0 | J12: =ROUND((E12-H12)/2,0) -> 44424775 | K12: =+E12-I12-J12 -> 44424774 | L12: =+SUM(J12:K12) -> 88849549 | M12: =E12-SUM(I12,L12) -> 0 | N12: 普及促進費 | O12: =+'[1]3条支出'!T11 -> 87134052 | R12: =+補助補給!AZ4 -> 0 | S12: =+SUM(P12:R12) -> 0 | T12: =+ROUND((O12-R12)/2,0) -> 43567026 | U12: =+O12-S12-T12 -> 43567026 | V12: =+SUM(T12:U12) -> 87134052 | W12: =O12-SUM(S12,V12) -> 0 | X12: 普及促進費 | AD12: =+O12 -> 87134052 | AE12: =+P12 -> 0 | AF12: =+Q12 -> 0 | AG12: =+R12 -> 0 | AH12: =+SUM(AE12:AG12) -> 0 | AI12: =+T12 -> 43567026 | AJ12: =+U12 -> 43567026 | AK12: =+SUM(AI12:AJ12) -> 87134052 | AL12: =AD12-SUM(AH12,AK12) -> 0 | AM12: =SUM(AE12:AG12,AI12) -> 43567026 | AN12: 42873000 | AO12: =AM12-AN12 -> 694026 | AQ12: 39027000 | AR12: =AM12-AQ12 -> 4540026 | AT12: #=SUM('[4-04 集計表.xlsx]3条集計(税抜)'!R28:T28)
B13: 維持 | C13: 営業 | D13: 水洗化貸付事業費 | E13: =+'[1]3条支出'!E12 -> 10483859 | H13: =+E13 -> 10483859 | I13: =+SUM(F13:H13) -> 10483859 | K13: =+E13-I13-J13 -> 0 | L13: =+SUM(J13:K13) -> 0 | M13: =E13-SUM(I13,L13) -> 0 | N13: 水洗化貸付事業費 | O13: =+'[1]3条支出'!T12 -> 10396270 | R13: =+O13 -> 10396270 | S13: =+SUM(P13:R13) -> 10396270 | U13: =+O13-S13-T13 -> 0 | V13: =+SUM(T13:U13) -> 0 | W13: =O13-SUM(S13,V13) -> 0 | X13: 水洗化貸付事業費 | AD13: =+O13 -> 10396270 | AE13: =+P13 -> 0 | AF13: =+Q13 -> 0 | AG13: =+R13 -> 10396270 | AH13: =+SUM(AE13:AG13) -> 10396270 | AI13: =+T13 -> 0 | AJ13: =+U13 -> 0 | AK13: =+SUM(AI13:AJ13) -> 0 | AL13: =AD13-SUM(AH13,AK13) -> 0 | AM13: =SUM(AE13:AG13,AI13) -> 10396270 | AN13: 10612000 | AO13: =AM13-AN13 -> -215730 | AQ13: 14660000 | AR13: =AM13-AQ13 -> -4263730 | AT13: #=SUM('[4-04 集計表.xlsx]3条集計(税抜)'!R29:T29)
B14: 維持 | C14: 営業 | D14: 業務費 | E14: =+'[1]3条支出'!E13 -> 1019945143 | I14: =+SUM(F14:H14) -> 0 | K14: =+E14-I14-J14 -> 1019945143 | L14: =+SUM(J14:K14) -> 1019945143 | M14: =E14-SUM(I14,L14) -> 0 | N14: 業務費 | O14: =+'[1]3条支出'!T13 -> 929691714 | R14: =+IFERROR(ROUND(H14/SUM([1]業務!E5:E9,[1]業務!E34)*SUM([1]業務!T5:T9,[1]業務!T34),0),0) -> 0 | S14: =+SUM(P14:R14) -> 0 | U14: =+O14-S14-T14 -> 929691714 | V14: =+SUM(T14:U14) -> 929691714 | W14: =O14-SUM(S14,V14) -> 0 | X14: 業務費 | AD14: =+O14 -> 929691714 | AE14: =+P14 -> 0 | AF14: =+Q14 -> 0 | AG14: =+R14 -> 0 | AH14: =+SUM(AE14:AG14) -> 0 | AI14: =+T14 -> 0 | AJ14: =+U14 -> 929691714 | AK14: =+SUM(AI14:AJ14) -> 929691714 | AL14: =AD14-SUM(AH14,AK14) -> 0 | AM14: =SUM(AE14:AG14,AI14) -> 0 | AN14: 0 | AO14: =AM14-AN14 -> 0 | AQ14: 0 | AR14: =AM14-AQ14 -> 0 | AT14: #=SUM('[4-04 集計表.xlsx]3条集計(税抜)'!R30:T30)
B15: 維持 | C15: 営業 | D15: 総係費 | E15: =+'[1]3条支出'!E14 -> 483965214 | F15: =+IFERROR(ROUND(([1]総係!$E$37-[1]総係!$E$36)*SUM(F7:F14)/SUM($F$7:$H$14,$J$7:$K$14),0),0) -> 122380384 | G15: =+IFERROR(ROUND(([1]総係!$E$37-[1]総係!$E$36)*SUM(G7:G14)/SUM($F$7:$H$14,$J$7:$K$14),0),0) -> 11686854 | I15: =+SUM(F15:H15) -> 134067238 | K15: =+E15-I15-J15 -> 349897976 | L15: =+SUM(J15:K15) -> 349897976 | M15: =E15-SUM(I15,L15) -> 0 | N15: 総係費 | O15: =+'[1]3条支出'!T14 -> 466286409 | P15: =+IFERROR(ROUND(([1]総係!$T$37-[1]総係!$T$36)*SUM(P7:P14)/SUM($P$7:$R$14,$T$7:$U$14),0),0) -> 119755277 | Q15: =+IFERROR(ROUND(([1]総係!$T$37-[1]総係!$T$36)*SUM(Q7:Q14)/SUM($P$7:$R$14,$T$7:$U$14),0),0) -> 11260122 | S15: =+SUM(P15:R15) -> 131015399 | U15: =+O15-S15-T15 -> 335271010 | V15: =+SUM(T15:U15) -> 335271010 | W15: =O15-SUM(S15,V15) -> 0 | X15: 総係費 | AD15: =+O15 -> 466286409 | AE15: =+P15 -> 119755277 | AF15: =+Q15 -> 11260122 | AG15: =+R15 -> 0 | AH15: =+SUM(AE15:AG15) -> 131015399 | AI15: =+T15 -> 0 | AJ15: =+U15 -> 335271010 | AK15: =+SUM(AI15:AJ15) -> 335271010 | AL15: =AD15-SUM(AH15,AK15) -> 0 | AM15: =SUM(AE15:AG15,AI15) -> 131015399 | AN15: 121395000 | AO15: =AM15-AN15 -> 9620399 | AQ15: 135565000 | AR15: =AM15-AQ15 -> -4549601 | AT15: #=SUM('[4-04 集計表.xlsx]3条集計(税抜)'!R31:T31)
B16: 維持 | C16: 営業 | D16: 特環公共下水道費 | E16: =+'[1]3条支出'!E15 -> 106990906 | I16: =+SUM(F16:H16) -> 0 | J16: 0 | K16: =+E16-I16-J16 -> 106990906 | L16: =+SUM(J16:K16) -> 106990906 | M16: =E16-SUM(I16,L16) -> 0 | N16: 特環公共下水道費 | O16: =+'[1]3条支出'!T15 -> 97276922 | R16: =+補助補給!AZ5 -> 0 | S16: =+SUM(P16:R16) -> 0 | U16: =+O16-S16-T16 -> 97276922 | V16: =+SUM(T16:U16) -> 97276922 | W16: =O16-SUM(S16,V16) -> 0 | X16: 特環費 | AD16: =+O16 -> 97276922 | AE16: =+P16 -> 0 | AF16: =+Q16 -> 0 | AG16: =+R16 -> 0 | AH16: =+SUM(AE16:AG16) -> 0 | AI16: =+T16 -> 0 | AJ16: =+U16 -> 97276922 | AK16: =+SUM(AI16:AJ16) -> 97276922 | AL16: =AD16-SUM(AH16,AK16) -> 0 | AM16: =SUM(AE16:AG16,AI16) -> 0 | AN16: 566363 | AO16: =AM16-AN16 -> -566363 | AQ16: 0 | AR16: =AM16-AQ16 -> 0 | AT16: #=SUM('[4-04 集計表.xlsx]3条集計(税抜)'!R32:T32)
B17: 維持 | C17: 営業 | D17: 農業集落排水費 | E17: =+'[1]3条支出'!E16 -> 247654024 | I17: =+SUM(F17:H17) -> 0 | J17: 0 | K17: =+E17-I17-J17 -> 247654024 | L17: =+SUM(J17:K17) -> 247654024 | M17: =E17-SUM(I17,L17) -> 0 | N17: 農業集落排水費 | O17: =+'[1]3条支出'!T16 -> 225167795 | R17: =+補助補給!AZ6 -> 0 | S17: =+SUM(P17:R17) -> 0 | U17: =+O17-S17-T17 -> 225167795 | V17: =+SUM(T17:U17) -> 225167795 | W17: =O17-SUM(S17,V17) -> 0 | X17: 農集費 | AD17: =+O17 -> 225167795 | AE17: =+P17 -> 0 | AF17: =+Q17 -> 0 | AG17: =+R17 -> 0 | AH17: =+SUM(AE17:AG17) -> 0 | AI17: =+T17 -> 0 | AJ17: =+U17 -> 225167795 | AK17: =+SUM(AI17:AJ17) -> 225167795 | AL17: =AD17-SUM(AH17,AK17) -> 0 | AM17: =SUM(AE17:AG17,AI17) -> 0 | AN17: 3919090 | AO17: =AM17-AN17 -> -3919090 | AQ17: 0 | AR17: =AM17-AQ17 -> 0 | AT17: #=SUM('[4-04 集計表.xlsx]3条集計(税抜)'!R33:T33)
B18: 維持 | C18: 営業 | D18: 浄化槽費 | E18: =+'[1]3条支出'!E17 -> 76388330 | I18: =+SUM(F18:H18) -> 0 | K18: =+E18-I18-J18 -> 76388330 | L18: =+SUM(J18:K18) -> 76388330 | M18: =E18-SUM(I18,L18) -> 0 | N18: 浄化槽費 | O18: =+'[1]3条支出'!T17 -> 69941329 | R18: =+補助補給!AZ7 -> 0 | S18: =+SUM(P18:R18) -> 0 | U18: =+O18-S18-T18 -> 69941329 | V18: =+SUM(T18:U18) -> 69941329 | W18: =O18-SUM(S18,V18) -> 0 | X18: 浄化槽費 | AD18: =+O18 -> 69941329 | AE18: =+P18 -> 0 | AF18: =+Q18 -> 0 | AG18: =+R18 -> 0 | AH18: =+SUM(AE18:AG18) -> 0 | AI18: =+T18 -> 0 | AJ18: =+U18 -> 69941329 | AK18: =+SUM(AI18:AJ18) -> 69941329 | AL18: =AD18-SUM(AH18,AK18) -> 0 | AM18: =SUM(AE18:AG18,AI18) -> 0 | AN18: 0 | AO18: =AM18-AN18 -> 0 | AQ18: 0 | AR18: =AM18-AQ18 -> 0 | AT18: #=SUM('[4-04 集計表.xlsx]3条集計(税抜)'!R34:T34)
B19: 維持 | C19: 営業 | D19: 災害復旧費 | E19: =+'[1]3条支出'!E18 -> 0 | I19: =+SUM(F19:H19) -> 0 | K19: =+E19-I19-J19 -> 0 | L19: =+SUM(J19:K19) -> 0 | M19: =E19-SUM(I19,L19) -> 0 | N19: 災害復旧費 | O19: =+'[1]3条支出'!T18 -> 0 | S19: =+SUM(P19:R19) -> 0 | U19: =+O19-S19-T19 -> 0 | V19: =+SUM(T19:U19) -> 0 | W19: =O19-SUM(S19,V19) -> 0 | X19: 災害復旧費 | AD19: =+O19 -> 0 | AE19: =+P19 -> 0 | AF19: =+Q19 -> 0 | AG19: =+R19 -> 0 | AH19: =+SUM(AE19:AG19) -> 0 | AI19: =+T19 -> 0 | AJ19: =+U19 -> 0 | AK19: =+SUM(AI19:AJ19) -> 0 | AL19: =AD19-SUM(AH19,AK19) -> 0 | AM19: =SUM(AE19:AG19,AI19) -> 0 | AO19: =AM19-AN19 -> 0 | AR19: =AM19-AQ19 -> 0
B20: 維持 | C20: 営業 | D20: 資産減耗費（固定資産撤去費） | E20: =+[1]減耗!$E$7 -> 0 | F20: 0 | I20: =+SUM(F20:H20) -> 0 | K20: 0 | L20: =+SUM(J20:K20) -> 0 | M20: =E20-SUM(I20,L20) -> 0 | N20: 資産減耗費（固定資産撤去費） | O20: =+[1]減耗!T7 -> 0 | P20: =+IFERROR(ROUND(F20*$O20/$E20,0),0) -> 0 | Q20: =+IFERROR(ROUND(G20*$O20/$E20,0),0) -> 0 | R20: =+IFERROR(ROUND(H20*$O20/$E20,0),0) -> 0 | S20: =+SUM(P20:R20) -> 0 | T20: =+IFERROR(ROUND(J20*$O20/$E20,0),0) -> 0 | U20: =+O20-S20-T20 -> 0 | V20: =+SUM(T20:U20) -> 0 | W20: =O20-SUM(S20,V20) -> 0 | X20: 資産減耗費（固定資産撤去費） | AD20: =+O20 -> 0 | AE20: =+P20 -> 0 | AF20: =+Q20 -> 0 | AG20: =+R20 -> 0 | AH20: =+SUM(AE20:AG20) -> 0 | AI20: =+T20 -> 0 | AJ20: =+U20 -> 0 | AK20: =+SUM(AI20:AJ20) -> 0 | AL20: =AD20-SUM(AH20,AK20) -> 0 | AM20: =SUM(AE20:AG20,AI20) -> 0 | AO20: =AM20-AN20 -> 0 | AR20: =AM20-AQ20 -> 0
AM21: =SUM(AE21:AG21,AI21) -> 0 | AO21: =AM21-AN21 -> 0 | AR21: =AM21-AQ21 -> 0
B22: 維持 | C22: 営外 | D22: 一時借入金利息 | E22: =+[1]営外!E11 -> 2483 | F22: =+雨汚支出!AV3 -> 0 | G22: =+雨汚支出!AW3 -> 0 | H22: =+雨汚支出!AX3 -> 0 | I22: =+SUM(F22:H22) -> 0 | J22: =+雨汚支出!AZ3 -> 0 | K22: =+雨汚支出!BA3 -> 2483 | L22: =+SUM(J22:K22) -> 2483 | M22: =E22-SUM(I22,L22) -> 0 | N22: 一時借入金利息 | O22: =+[1]営外!T11 -> 2483 | P22: =+雨汚支出!BF3 -> 0 | Q22: =+雨汚支出!BG3 -> 0 | R22: =+雨汚支出!BH3 -> 0 | S22: =+SUM(P22:R22) -> 0 | T22: =+雨汚支出!BJ3 -> 0 | U22: =+雨汚支出!BK3 -> 2483 | V22: =+SUM(T22:U22) -> 2483 | W22: =O22-SUM(S22,V22) -> 0 | X22: 一時借入金利息 | AD22: =+O22 -> 2483 | AE22: =+P22 -> 0 | AF22: =+Q22 -> 0 | AG22: =+R22 -> 0 | AH22: =+SUM(AE22:AG22) -> 0 | AI22: =+T22 -> 0 | AJ22: =+U22 -> 2483 | AK22: =+SUM(AI22:AJ22) -> 2483 | AL22: =AD22-SUM(AH22,AK22) -> 0 | AM22: =SUM(AE22:AG22,AI22) -> 0 | AO22: =AM22-AN22 -> 0 | AR22: =AM22-AQ22 -> 0
B23: 維持 | C23: 営外 | D23: 雑支出（還付加算金+その他） | E23: =+[1]営外!E15+[1]営外!E16-E24 -> 25896 | F23: =+雨汚支出!AV4+雨汚支出!AV5-F24 -> 0 | G23: =+雨汚支出!AW4+雨汚支出!AW5-G24 -> 0 | H23: =+雨汚支出!AX4+雨汚支出!AX5-H24 -> 0 | I23: =+SUM(F23:H23) -> 0 | J23: =+雨汚支出!AZ4+雨汚支出!AZ5-J24 -> 0 | K23: =+雨汚支出!BA4+雨汚支出!BA5-K24 -> 25896 | L23: =+SUM(J23:K23) -> 25896 | M23: =E23-SUM(I23,L23) -> 0 | N23: 雑支出（還付加算金+その他） | O23: =+[1]営外!T15+[1]営外!T16-O24 -> 24123 | P23: =+雨汚支出!BF4+雨汚支出!BF5-P24 -> 0 | Q23: =+雨汚支出!BG4+雨汚支出!BG5-Q24 -> 0 | R23: =+雨汚支出!BH4+雨汚支出!BH5-R24 -> 0 | S23: =+SUM(P23:R23) -> 0 | T23: =+雨汚支出!BJ4+雨汚支出!BJ5-T24 -> 0 | U23: =+雨汚支出!BK4+雨汚支出!BK5-U24 -> 24123 | V23: =+SUM(T23:U23) -> 24123 | W23: =O23-SUM(S23,V23) -> 0 | X23: 雑支出（還付加算金+その他） | AD23: =+O23 -> 24123 | AE23: =+P23 -> 0 | AF23: =+Q23 -> 0 | AG23: =+R23 -> 0 | AH23: =+SUM(AE23:AG23) -> 0 | AI23: =+T23 -> 0 | AJ23: =+U23 -> 24123 | AK23: =+SUM(AI23:AJ23) -> 24123 | AL23: =AD23-SUM(AH23,AK23) -> 0 | AM23: =SUM(AE23:AG23,AI23) -> 0 | AO23: =AM23-AN23 -> 0 | AR23: =AM23-AQ23 -> 0
B24: 維持 | C24: 営外 | D24: 雑支出（災害支援経費等） | E24: =+[1]営外!E20 -> 9198273 | I24: =+SUM(F24:H24) -> 0 | K24: =+E24-I24-J24 -> 9198273 | L24: =+SUM(J24:K24) -> 9198273 | M24: =E24-SUM(I24,L24) -> 0 | N24: 雑支出（災害支援経費等） | O24: =+[1]営外!T20 -> 8710224 | S24: =+SUM(P24:R24) -> 0 | U24: =+O24-S24-T24 -> 8710224 | V24: =+SUM(T24:U24) -> 8710224 | W24: =O24-SUM(S24,V24) -> 0 | X24: 雑支出（災害支援経費等） | AD24: =+O24 -> 8710224 | AE24: =+P24 -> 0 | AF24: =+Q24 -> 0 | AG24: =+R24 -> 0 | AH24: =+SUM(AE24:AG24) -> 0 | AI24: =+T24 -> 0 | AJ24: =+U24 -> 8710224 | AK24: =+SUM(AI24:AJ24) -> 8710224 | AL24: =AD24-SUM(AH24,AK24) -> 0 | AM24: =SUM(AE24:AG24,AI24) -> 0 | AN24: 7273000 | AO24: =AM24-AN24 -> -7273000 | AQ24: 0 | AR24: =AM24-AQ24 -> 0 | AT24: #=SUM('[4-04 集計表.xlsx]3条集計(税抜)'!R39:T39)
B25: 維持 | C25: 営外 | D25: 雑支出（控除不可消費税等）維持費分 | I25: =+SUM(F25:H25) -> 0 | K25: =+E25-I25-J25 -> 0 | L25: =+SUM(J25:K25) -> 0 | M25: =E25-SUM(I25,L25) -> 0 | N25: 雑支出（控除不可消費税等）維持費分 | S25: =+SUM(P25:R25) -> 0 | U25: =+O25-S25-T25 -> 0 | V25: =+SUM(T25:U25) -> 0 | W25: =O25-SUM(S25,V25) -> 0 | X25: 雑支出（控除不可消費税等）維持費分 | AD25: =+AD130-AD39 -> 209933209 | AE25: =+AE130-AE39 -> 161840742 | AF25: =+AF130-AF39 -> 15449991 | AG25: =+AG130-AG39 -> 23053301 | AH25: =+SUM(AE25:AG25) -> 200344034 | AI25: =+AI130-AI39 -> 9576435 | AJ25: =+AJ130-AJ39 -> 12740 | AK25: =+SUM(AI25:AJ25) -> 9589175 | AL25: =AD25-SUM(AH25,AK25) -> 0 | AM25: =SUM(AE25:AG25,AI25) -> 209920469 | AN25: 191121651 | AO25: =AM25-AN25 -> 18798818 | AQ25: 210556000 | AR25: =AM25-AQ25 -> -635531 | AT25: #=SUM('[4-04 集計表.xlsx]3条集計(税抜)'!R40:T40)
B26: 維持 | C26: 営外 | D26: 雑支出（免税事業者に係る控除不能額） | N26: 雑支出（免税事業者に係る控除不能額） | X26: 雑支出（免税事業者に係る控除不能額） | AD26: =[1]営外!$T$19 -> 629 | AH26: =+SUM(AE26:AG26) -> 0 | AJ26: =[1]営外!$T$19 -> 629 | AK26: =+SUM(AI26:AJ26) -> 629 | AL26: =AD26-SUM(AH26,AK26) -> 0 | AM26: =SUM(AE26:AG26,AI26) -> 0 | AO26: =AM26-AN26 -> 0 | AR26: =AM26-AQ26 -> 0
AM27: =SUM(AE27:AG27,AI27) -> 0 | AO27: =AM27-AN27 -> 0 | AR27: =AM27-AQ27 -> 0
B28: 維持 | C28: 特別 | D28: 固定資産売却損 | E28: =+'[1]3条支出'!$E$30 -> 10315355 | F28: =+雨汚支出!AV6 -> 0 | G28: =+雨汚支出!AW6 -> 0 | H28: =+雨汚支出!AX6 -> 0 | I28: =+SUM(F28:H28) -> 0 | J28: =+雨汚支出!AZ6 -> 0 | K28: =+雨汚支出!BA6 -> 10315355 | L28: =+SUM(J28:K28) -> 10315355 | M28: =E28-SUM(I28,L28) -> 0 | N28: 固定資産売却損 | O28: =+'[1]3条支出'!$T$30 -> 10315355 | P28: =+F28 -> 0 | Q28: =+G28 -> 0 | S28: =+SUM(P28:R28) -> 0 | T28: =+J28 -> 0 | U28: =+O28-S28-T28 -> 10315355 | V28: =+SUM(T28:U28) -> 10315355 | W28: =O28-SUM(S28,V28) -> 0 | X28: 固定資産売却損 | AD28: =+O28 -> 10315355 | AE28: =+P28 -> 0 | AF28: =+Q28 -> 0 | AG28: =+R28 -> 0 | AH28: =+SUM(AE28:AG28) -> 0 | AI28: =+T28 -> 0 | AJ28: =+U28 -> 10315355 | AK28: =+SUM(AI28:AJ28) -> 10315355 | AL28: =AD28-SUM(AH28,AK28) -> 0 | AM28: =SUM(AE28:AG28,AI28) -> 0 | AO28: =AM28-AN28 -> 0 | AR28: =AM28-AQ28 -> 0
B29: 維持 | C29: 特別 | D29: 過年度損益修正損 | E29: =+'[1]3条支出'!$E$28-E42 -> 10679943 | F29: =+雨汚支出!AV7-F42 -> 6760 | G29: =+雨汚支出!AW7-G42 -> 0 | H29: =+雨汚支出!AX7-H42 -> 0 | I29: =+SUM(F29:H29) -> 6760 | J29: =+雨汚支出!AZ7-J42 -> 0 | K29: =+雨汚支出!BA7-K42 -> 10673183 | L29: =+SUM(J29:K29) -> 10673183 | M29: =E29-SUM(I29,L29) -> 0 | N29: 過年度損益修正損 | O29: =+'[1]3条支出'!$T$28-O42 -> 9711499 | P29: =+雨汚支出!BF7-P42 -> 6733 | Q29: =+雨汚支出!BG7-Q42 -> 0 | R29: =+雨汚支出!BH7-R42 -> 0 | S29: =+SUM(P29:R29) -> 6733 | T29: =+雨汚支出!BJ7-T42 -> 0 | U29: =+雨汚支出!BK7-U42 -> 9704766 | V29: =+SUM(T29:U29) -> 9704766 | W29: =O29-SUM(S29,V29) -> 0 | X29: 過年度損益修正損 | AD29: =+O29 -> 9711499 | AE29: =+P29 -> 6733 | AF29: =+Q29 -> 0 | AG29: =+R29 -> 0 | AH29: =+SUM(AE29:AG29) -> 6733 | AI29: =+T29 -> 0 | AJ29: =+U29 -> 9704766 | AK29: =+SUM(AI29:AJ29) -> 9704766 | AL29: =AD29-SUM(AH29,AK29) -> 0 | AM29: =SUM(AE29:AG29,AI29) -> 6733 | AO29: =AM29-AN29 -> 6733 | AR29: =AM29-AQ29 -> 6733
B30: 維持 | C30: 特別 | D30: その他特別損失 | E30: =+'[1]3条支出'!$E$29-E43 -> 0 | F30: =+雨汚支出!AV8-F43 -> 0 | G30: =+雨汚支出!AW8-G43 -> 0 | H30: =+雨汚支出!AX8-H43 -> 0 | I30: =+SUM(F30:H30) -> 0 | J30: =+雨汚支出!AZ8-J43 -> 0 | K30: =+雨汚支出!BA8-K43 -> 0 | L30: =+SUM(J30:K30) -> 0 | M30: =E30-SUM(I30,L30) -> 0 | N30: その他特別損失 | O30: =+'[1]3条支出'!$T$29-O43 -> 0 | P30: =+雨汚支出!BF8-P43 -> 0 | Q30: =+雨汚支出!BG8-Q43 -> 0 | R30: =+雨汚支出!BH8-R43 -> 0 | S30: =+SUM(P30:R30) -> 0 | T30: =+雨汚支出!BJ8-T43 -> 0 | U30: =+雨汚支出!BK8-U43 -> 0 | V30: =+SUM(T30:U30) -> 0 | W30: =O30-SUM(S30,V30) -> 0 | X30: その他特別損失 | AD30: =+O30 -> 0 | AE30: =+P30 -> 0 | AF30: =+Q30 -> 0 | AG30: =+R30 -> 0 | AH30: =+SUM(AE30:AG30) -> 0 | AI30: =+T30 -> 0 | AJ30: =+U30 -> 0 | AK30: =+SUM(AI30:AJ30) -> 0 | AL30: =AD30-SUM(AH30,AK30) -> 0 | AM30: =SUM(AE30:AG30,AI30) -> 0 | AO30: =AM30-AN30 -> 0 | AR30: =AM30-AQ30 -> 0
B31: 維持 | C31: 特別 | I31: =+SUM(F31:H31) -> 0 | K31: =+E31-I31-J31 -> 0 | L31: =+SUM(J31:K31) -> 0 | M31: =E31-SUM(I31,L31) -> 0 | S31: =+SUM(P31:R31) -> 0 | U31: =+O31-S31-T31 -> 0 | V31: =+SUM(T31:U31) -> 0 | W31: =O31-SUM(S31,V31) -> 0 | AD31: =+O31 -> 0 | AE31: =+P31 -> 0 | AF31: =+Q31 -> 0 | AG31: =+R31 -> 0 | AH31: =+SUM(AE31:AG31) -> 0 | AI31: =+T31 -> 0 | AJ31: =+U31 -> 0 | AK31: =+SUM(AI31:AJ31) -> 0 | AL31: =AD31-SUM(AH31,AK31) -> 0 | AM31: =SUM(AE31:AG31,AI31) -> 0 | AO31: =AM31-AN31 -> 0 | AR31: =AM31-AQ31 -> 0
B32: 維持 | C32: 特別 | I32: =+SUM(F32:H32) -> 0 | K32: =+E32-I32-J32 -> 0 | L32: =+SUM(J32:K32) -> 0 | M32: =E32-SUM(I32,L32) -> 0 | S32: =+SUM(P32:R32) -> 0 | U32: =+O32-S32-T32 -> 0 | V32: =+SUM(T32:U32) -> 0 | W32: =O32-SUM(S32,V32) -> 0 | AD32: =+O32 -> 0 | AE32: =+P32 -> 0 | AF32: =+Q32 -> 0 | AG32: =+R32 -> 0 | AH32: =+SUM(AE32:AG32) -> 0 | AI32: =+T32 -> 0 | AJ32: =+U32 -> 0 | AK32: =+SUM(AI32:AJ32) -> 0 | AL32: =AD32-SUM(AH32,AK32) -> 0 | AM32: =SUM(AE32:AG32,AI32) -> 0 | AO32: =AM32-AN32 -> 0 | AR32: =AM32-AQ32 -> 0
AM33: =SUM(AE33:AG33,AI33) -> 0 | AO33: =AM33-AN33 -> 0 | AR33: =AM33-AQ33 -> 0
B34: 資本 | C34: 営業 | D34: 減価償却費 | E34: ='[1]3条支出'!$E$19 -> 26551442230 | F34: 12571100990 | G34: 122404286 | I34: =+SUM(F34:H34) -> 12693505276 | J34: 17206476 | K34: =13857936954-17206476 -> 13840730478 | L34: =+SUM(J34:K34) -> 13857936954 | M34: =E34-SUM(I34,L34) -> 0 | N34: 減価償却費 | O34: =+'[1]3条支出'!$T$19 -> 26551442230 | P34: =+F34 -> 12571100990 | Q34: =+G34 -> 122404286 | R34: =+H34 -> 0 | S34: =+SUM(P34:R34) -> 12693505276 | T34: =+J34 -> 17206476 | U34: =+K34 -> 13840730478 | V34: =+SUM(T34:U34) -> 13857936954 | W34: =O34-SUM(S34,V34) -> 0 | X34: 減価償却費 | AD34: =+O34 -> 26551442230 | AE34: =+P34 -> 12571100990 | AF34: =+Q34 -> 122404286 | AG34: =+R34 -> 0 | AH34: =+SUM(AE34:AG34) -> 12693505276 | AI34: =+T34 -> 17206476 | AJ34: =+U34 -> 13840730478 | AK34: =+SUM(AI34:AJ34) -> 13857936954 | AL34: =AD34-SUM(AH34,AK34) -> 0 | AM34: =SUM(AE34:AG34,AI34) -> 12710711752 | AN34: 12722677000 | AO34: =AM34-AN34 -> -11965248 | AQ34: 12322171000 | AR34: =AM34-AQ34 -> 388540752 | AT34: #=SUM('[4-04 集計表.xlsx]3条集計(税抜)'!R42:T42)
B35: 資本 | C35: 営業 | D35: 資産減耗費（固定資産除却費） | E35: ='[1]3条支出'!$E$20-E20 -> 503761871 | F35: =+E35-L35-G35 -> 304154336 | G35: =+IFERROR(ROUND((E35-L35)*G34/I34,0),0) -> 2961538 | I35: =+SUM(F35:H35) -> 307115874 | K35: =4976419+191669578 -> 196645997 | L35: =+SUM(J35:K35) -> 196645997 | M35: =E35-SUM(I35,L35) -> 0 | N35: 資産減耗費（固定資産除却費） | O35: =+'[1]3条支出'!$T$20-O20 -> 503761871 | P35: =+F35 -> 304154336 | Q35: =+G35 -> 2961538 | S35: =+SUM(P35:R35) -> 307115874 | T35: =+J35 -> 0 | U35: =+K35 -> 196645997 | V35: =+SUM(T35:U35) -> 196645997 | W35: =O35-SUM(S35,V35) -> 0 | X35: 資産減耗費（固定資産除却費） | AD35: =+O35 -> 503761871 | AE35: =+P35 -> 304154336 | AF35: =+Q35 -> 2961538 | AG35: =+R35 -> 0 | AH35: =+SUM(AE35:AG35) -> 307115874 | AI35: =+T35 -> 0 | AJ35: =+U35 -> 196645997 | AK35: =+SUM(AI35:AJ35) -> 196645997 | AL35: =AD35-SUM(AH35,AK35) -> 0 | AM35: =SUM(AE35:AG35,AI35) -> 307115874 | AN35: 285010000 | AO35: =AM35-AN35 -> 22105874 | AQ35: 162051000 | AR35: =AM35-AQ35 -> 145064874 | AT35: #=SUM('[4-04 集計表.xlsx]3条集計(税抜)'!R43:T43)
AM36: =SUM(AE36:AG36,AI36) -> 0 | AO36: =AM36-AN36 -> 0 | AR36: =AM36-AQ36 -> 0
B37: 資本 | C37: 営外 | D37: 企業債利息 | E37: =+[1]営外!E6 -> 3884144913 | F37: 1638072143 | G37: 0 | H37: 36375158 | I37: =+SUM(F37:H37) -> 1674447301 | J37: 315322238 | K37: 1894375374 | L37: =+SUM(J37:K37) -> 2209697612 | M37: =E37-SUM(I37,L37) -> 0 | N37: 企業債利息 | O37: =+[1]営外!T6 -> 3884144913 | P37: =+F37 -> 1638072143 | Q37: =+G37 -> 0 | R37: =+H37 -> 36375158 | S37: =+SUM(P37:R37) -> 1674447301 | T37: =+J37 -> 315322238 | U37: =+O37-S37-T37 -> 1894375374 | V37: =+SUM(T37:U37) -> 2209697612 | W37: =O37-SUM(S37,V37) -> 0 | X37: 支払利息及び企業債取扱諸費 | AD37: =+O37 -> 3884144913 | AE37: =+P37 -> 1638072143 | AF37: =+Q37 -> 0 | AG37: =+R37 -> 36375158 | AH37: =+SUM(AE37:AG37) -> 1674447301 | AI37: =+T37 -> 315322238 | AJ37: =+U37 -> 1894375374 | AK37: =+SUM(AI37:AJ37) -> 2209697612 | AL37: =AD37-SUM(AH37,AK37) -> 0 | AM37: =SUM(AE37:AG37,AI37) -> 1989769539 | AN37: 1991724000 | AO37: =AM37-AN37 -> -1954461 | AQ37: 2104635000 | AR37: =AM37-AQ37 -> -114865461 | AT37: #=SUM('[4-04 集計表.xlsx]3条集計(税抜)'!R44:T44)
B38: 資本 | C38: 営外 | D38: 企業債手数料及び取扱費 | E38: =+[1]営外!E9 -> 61813753 | F38: 30574206 | I38: =+SUM(F38:H38) -> 30574206 | K38: 31239547 | L38: =+SUM(J38:K38) -> 31239547 | M38: =E38-SUM(I38,L38) -> 0 | N38: 企業債手数料及び取扱費 | O38: =+[1]営外!T9 -> 56194321 | P38: =+IFERROR(ROUND(F38*$O38/$E38,0),0) -> 27794733 | Q38: =+IFERROR(ROUND(G38*$O38/$E38,0),0) -> 0 | R38: =+IFERROR(ROUND(H38*$O38/$E38,0),0) -> 0 | S38: =+SUM(P38:R38) -> 27794733 | T38: =+IFERROR(ROUND(J38*$O38/$E38,0),0) -> 0 | U38: =+O38-S38-T38 -> 28399588 | V38: =+SUM(T38:U38) -> 28399588 | W38: =O38-SUM(S38,V38) -> 0 | X38: 企業債手数料及び取扱費 | AD38: =+O38 -> 56194321 | AE38: =+P38 -> 27794733 | AF38: =+Q38 -> 0 | AG38: =+R38 -> 0 | AH38: =+SUM(AE38:AG38) -> 27794733 | AI38: =+T38 -> 0 | AJ38: =+U38 -> 28399588 | AK38: =+SUM(AI38:AJ38) -> 28399588 | AL38: =AD38-SUM(AH38,AK38) -> 0 | AM38: =SUM(AE38:AG38,AI38) -> 27794733 | AN38: 27828000 | AO38: =AM38-AN38 -> -33267 | AQ38: 38809000 | AR38: =AM38-AQ38 -> -11014267 | AT38: #=SUM('[4-04 集計表.xlsx]3条集計(税抜)'!R45:T45)
B39: 資本 | C39: 営外 | D39: 雑支出（控除不可消費税等）資本費分 | I39: =+SUM(F39:H39) -> 0 | K39: =+E39-I39-J39 -> 0 | L39: =+SUM(J39:K39) -> 0 | M39: =E39-SUM(I39,L39) -> 0 | N39: 雑支出（控除不可消費税等）資本費分 | S39: =+SUM(P39:R39) -> 0 | U39: =+O39-S39-T39 -> 0 | V39: =+SUM(T39:U39) -> 0 | W39: =O39-SUM(S39,V39) -> 0 | X39: 雑支出（控除不可消費税等）資本費分 | AD39: =+SUM(AD113,AD124) -> 2553639 | AE39: =+SUM(AE113,AE124) -> 2553639 | AF39: =+SUM(AF113,AF124) -> 0 | AG39: =+SUM(AG113,AG124) -> 0 | AH39: =+SUM(AE39:AG39) -> 2553639 | AI39: =+SUM(AI113,AI124) -> 0 | AJ39: =+SUM(AJ113,AJ124) -> 0 | AK39: =+SUM(AI39:AJ39) -> 0 | AL39: =AD39-SUM(AH39,AK39) -> 0 | AM39: =SUM(AE39:AG39,AI39) -> 2553639 | AN39: 2774706 | AO39: =AM39-AN39 -> -221067 | AQ39: 3873000 | AR39: =AM39-AQ39 -> -1319361 | AT39: #=SUM('[4-04 集計表.xlsx]3条集計(税抜)'!R47:T47)
AM40: =SUM(AE40:AG40,AI40) -> 0 | AO40: =AM40-AN40 -> 0 | AR40: =AM40-AQ40 -> 0
B41: 資本 | C41: 特別 | I41: =+SUM(F41:H41) -> 0 | L41: =+SUM(J41:K41) -> 0 | M41: =E41-SUM(I41,L41) -> 0 | S41: =+SUM(P41:R41) -> 0 | U41: =+O41-S41-T41 -> 0 | V41: =+SUM(T41:U41) -> 0 | W41: =O41-SUM(S41,V41) -> 0 | AD41: =+O41 -> 0 | AE41: =+P41 -> 0 | AF41: =+Q41 -> 0 | AG41: =+R41 -> 0 | AH41: =+SUM(AE41:AG41) -> 0 | AI41: =+T41 -> 0 | AJ41: =+U41 -> 0 | AK41: =+SUM(AI41:AJ41) -> 0 | AL41: =AD41-SUM(AH41,AK41) -> 0 | AM41: =SUM(AE41:AG41,AI41) -> 0 | AO41: =AM41-AN41 -> 0 | AR41: =AM41-AQ41 -> 0
B42: 資本 | C42: 特別 | D42: 過年度損益修正損 | E42: =+SUM(I42,L42:L42) -> 0 | F42: 0 | G42: 0 | I42: =+SUM(F42:H42) -> 0 | J42: 0 | K42: 0 | L42: =+SUM(J42:K42) -> 0 | M42: =E42-SUM(I42,L42) -> 0 | N42: 過年度損益修正損 | O42: =+E42 -> 0 | P42: =+F42 -> 0 | Q42: =+G42 -> 0 | S42: =+SUM(P42:R42) -> 0 | T42: =+J42 -> 0 | U42: =+O42-S42-T42 -> 0 | V42: =+SUM(T42:U42) -> 0 | W42: =O42-SUM(S42,V42) -> 0 | X42: 過年度損益修正損 | AD42: =+O42 -> 0 | AE42: =+P42 -> 0 | AF42: =+Q42 -> 0 | AG42: =+R42 -> 0 | AH42: =+SUM(AE42:AG42) -> 0 | AI42: =+T42 -> 0 | AJ42: =+U42 -> 0 | AK42: =+SUM(AI42:AJ42) -> 0 | AL42: =AD42-SUM(AH42,AK42) -> 0 | AM42: =SUM(AE42:AG42,AI42) -> 0 | AO42: =AM42-AN42 -> 0 | AR42: =AM42-AQ42 -> 0
B43: 資本 | C43: 特別 | D43: その他特別損失 | E43: =+SUM(I43,L43:L43) -> 0 | I43: =+SUM(F43:H43) -> 0 | L43: =+SUM(J43:K43) -> 0 | M43: =E43-SUM(I43,L43) -> 0 | N43: その他特別損失 | O43: =+E43 -> 0 | P43: =+F43 -> 0 | Q43: =+G43 -> 0 | S43: =+SUM(P43:R43) -> 0 | T43: =+J43 -> 0 | U43: =+O43-S43-T43 -> 0 | V43: =+SUM(T43:U43) -> 0 | W43: =O43-SUM(S43,V43) -> 0 | X43: その他特別損失 | AD43: =+O43 -> 0 | AE43: =+P43 -> 0 | AF43: =+Q43 -> 0 | AG43: =+R43 -> 0 | AH43: =+SUM(AE43:AG43) -> 0 | AI43: =+T43 -> 0 | AJ43: =+U43 -> 0 | AK43: =+SUM(AI43:AJ43) -> 0 | AL43: =AD43-SUM(AH43,AK43) -> 0 | AM43: =SUM(AE43:AG43,AI43) -> 0 | AO43: =AM43-AN43 -> 0 | AR43: =AM43-AQ43 -> 0
B44: 資本 | C44: 特別 | D44: 減損損失 | E44: =+'[1]3条支出'!$E$31 -> 0 | F44: 0 | I44: =+SUM(F44:H44) -> 0 | K44: 0 | L44: =+SUM(J44:K44) -> 0 | M44: =E44-SUM(I44,L44) -> 0 | N44: 減損損失 | O44: ='[1]3条支出'!$T$31 -> 0 | P44: =+F44 -> 0 | S44: =+SUM(P44:R44) -> 0 | U44: =+O44-S44-T44 -> 0 | V44: =+SUM(T44:U44) -> 0 | W44: =O44-SUM(S44,V44) -> 0 | X44: 減損損失 | AD44: =+O44 -> 0 | AE44: =+P44 -> 0 | AF44: =+Q44 -> 0 | AG44: =+R44 -> 0 | AH44: =+SUM(AE44:AG44) -> 0 | AI44: =+T44 -> 0 | AJ44: =+U44 -> 0 | AK44: =+SUM(AI44:AJ44) -> 0 | AL44: =AD44-SUM(AH44,AK44) -> 0 | AM44: =SUM(AE44:AG44,AI44) -> 0 | AO44: =AM44-AN44 -> 0 | AR44: =AM44-AQ44 -> 0
AM45: =SUM(AE45:AG45,AI45) -> 0 | AO45: =AM45-AN45 -> 0 | AR45: =AM45-AQ45 -> 0
D46: 合 計 | E46: =+SUM(E7:E45) -> 42643669657 | F46: =+SUM(F7:F45) -> 17380716581 | G46: =+SUM(G7:G45) -> 396270048 | H46: =+SUM(H7:H45) -> 492675795 | I46: =+SUM(I7:I45) -> 18269662424 | J46: =+SUM(J7:J45) -> 563892182 | K46: =+SUM(K7:K45) -> 23810115051 | L46: =+SUM(L7:L45) -> 24374007233 | M46: =+SUM(M7:M45) -> 0 | N46: 合 計 | O46: =+SUM(O7:O45) -> 41815647458 | P46: =+SUM(P7:P45) -> 17221073393 | Q46: =+SUM(Q7:Q45) -> 377350558 | R46: =+SUM(R7:R45) -> 457243918 | S46: =+SUM(S7:S45) -> 18055667869 | T46: =+SUM(T7:T45) -> 551241129 | U46: =+SUM(U7:U45) -> 23208738460 | V46: =+SUM(V7:V45) -> 23759979589 | W46: =+SUM(W7:W45) -> 0 | X46: 合 計 | AD46: =+SUM(AD7:AD45) -> 42028134935 | AE46: =+SUM(AE7:AE45) -> 17385467774 | AF46: =+SUM(AF7:AF45) -> 392800549 | AG46: =+SUM(AG7:AG45) -> 480297219 | AH46: =+SUM(AH7:AH45) -> 18258565542 | AI46: =+SUM(AI7:AI45) -> 560817564 | AJ46: =+SUM(AJ7:AJ45) -> 23208751829 | AK46: =+SUM(AK7:AK45) -> 23769569393 | AL46: =+SUM(AL7:AL45) -> 0 | AO46: =AM46-AN46 -> 0 | AR46: =AM46-AQ46 -> 0
B47: 維持 | D47: うち、維持管理費分 計 | E47: =+SUMIFS(E$7:E$45,$B$7:$B$45,$B47) -> 11642506890 | F47: =+SUMIFS(F$7:F$45,$B$7:$B$45,$B47) -> 2836814906 | G47: =+SUMIFS(G$7:G$45,$B$7:$B$45,$B47) -> 270904224 | H47: =+SUMIFS(H$7:H$45,$B$7:$B$45,$B47) -> 456300637 | I47: =+SUMIFS(I$7:I$45,$B$7:$B$45,$B47) -> 3564019767 | J47: =+SUMIFS(J$7:J$45,$B$7:$B$45,$B47) -> 231363468 | K47: =+SUMIFS(K$7:K$45,$B$7:$B$45,$B47) -> 7847123655 | L47: =+SUMIFS(L$7:L$45,$B$7:$B$45,$B47) -> 8078487123 | M47: =+SUMIFS(M$7:M$45,$B$7:$B$45,$B47) -> 0 | N47: うち、維持管理費分 計 | O47: =+SUMIFS(O$7:O$45,$B$7:$B$45,$B47) -> 10820104123 | P47: =+SUMIFS(P$7:P$45,$B$7:$B$45,$B47) -> 2679951191 | Q47: =+SUMIFS(Q$7:Q$45,$B$7:$B$45,$B47) -> 251984734 | R47: =+SUMIFS(R$7:R$45,$B$7:$B$45,$B47) -> 420868760 | S47: =+SUMIFS(S$7:S$45,$B$7:$B$45,$B47) -> 3352804685 | T47: =+SUMIFS(T$7:T$45,$B$7:$B$45,$B47) -> 218712415 | U47: =+SUMIFS(U$7:U$45,$B$7:$B$45,$B47) -> 7248587023 | V47: =+SUMIFS(V$7:V$45,$B$7:$B$45,$B47) -> 7467299438 | W47: =+SUMIFS(W$7:W$45,$B$7:$B$45,$B47) -> 0 | X47: うち、維持管理費分 計 | AD47: =+SUMIFS(AD$7:AD$45,$B$7:$B$45,$B47) -> 11030037961 | AE47: =+SUMIFS(AE$7:AE$45,$B$7:$B$45,$B47) -> 2841791933 | AF47: =+SUMIFS(AF$7:AF$45,$B$7:$B$45,$B47) -> 267434725 | AG47: =+SUMIFS(AG$7:AG$45,$B$7:$B$45,$B47) -> 443922061 | AH47: =+SUMIFS(AH$7:AH$45,$B$7:$B$45,$B47) -> 3553148719 | AI47: =+SUMIFS(AI$7:AI$45,$B$7:$B$45,$B47) -> 228288850 | AJ47: =+SUMIFS(AJ$7:AJ$45,$B$7:$B$45,$B47) -> 7248600392 | AK47: =+SUMIFS(AK$7:AK$45,$B$7:$B$45,$B47) -> 7476889242 | AL47: =+SUMIFS(AL$7:AL$45,$B$7:$B$45,$B47) -> 0 | AO47: =AM47-AN47 -> 0 | AR47: =AM47-AQ47 -> 0
B48: 資本 | D48: うち、資本費分 計 | E48: =+SUMIFS(E$7:E$45,$B$7:$B$45,$B48) -> 31001162767 | F48: =+SUMIFS(F$7:F$45,$B$7:$B$45,$B48) -> 14543901675 | G48: =+SUMIFS(G$7:G$45,$B$7:$B$45,$B48) -> 125365824 | H48: =+SUMIFS(H$7:H$45,$B$7:$B$45,$B48) -> 36375158 | I48: =+SUMIFS(I$7:I$45,$B$7:$B$45,$B48) -> 14705642657 | J48: =+SUMIFS(J$7:J$45,$B$7:$B$45,$B48) -> 332528714 | K48: =+SUMIFS(K$7:K$45,$B$7:$B$45,$B48) -> 15962991396 | L48: =+SUMIFS(L$7:L$45,$B$7:$B$45,$B48) -> 16295520110 | M48: =+SUMIFS(M$7:M$45,$B$7:$B$45,$B48) -> 0 | N48: うち、資本費分 計 | O48: =+SUMIFS(O$7:O$45,$B$7:$B$45,$B48) -> 30995543335 | P48: =+SUMIFS(P$7:P$45,$B$7:$B$45,$B48) -> 14541122202 | Q48: =+SUMIFS(Q$7:Q$45,$B$7:$B$45,$B48) -> 125365824 | R48: =+SUMIFS(R$7:R$45,$B$7:$B$45,$B48) -> 36375158 | S48: =+SUMIFS(S$7:S$45,$B$7:$B$45,$B48) -> 14702863184 | T48: =+SUMIFS(T$7:T$45,$B$7:$B$45,$B48) -> 332528714 | U48: =+SUMIFS(U$7:U$45,$B$7:$B$45,$B48) -> 15960151437 | V48: =+SUMIFS(V$7:V$45,$B$7:$B$45,$B48) -> 16292680151 | W48: =+SUMIFS(W$7:W$45,$B$7:$B$45,$B48) -> 0 | X48: うち、資本費分 計 | AD48: =+SUMIFS(AD$7:AD$45,$B$7:$B$45,$B48) -> 30998096974 | AE48: =+SUMIFS(AE$7:AE$45,$B$7:$B$45,$B48) -> 14543675841 | AF48: =+SUMIFS(AF$7:AF$45,$B$7:$B$45,$B48) -> 125365824 | AG48: =+SUMIFS(AG$7:AG$45,$B$7:$B$45,$B48) -> 36375158 | AH48: =+SUMIFS(AH$7:AH$45,$B$7:$B$45,$B48) -> 14705416823 | AI48: =+SUMIFS(AI$7:AI$45,$B$7:$B$45,$B48) -> 332528714 | AJ48: =+SUMIFS(AJ$7:AJ$45,$B$7:$B$45,$B48) -> 15960151437 | AK48: =+SUMIFS(AK$7:AK$45,$B$7:$B$45,$B48) -> 16292680151 | AL48: =+SUMIFS(AL$7:AL$45,$B$7:$B$45,$B48) -> 0 | AO48: =AM48-AN48 -> 0 | AR48: =AM48-AQ48 -> 0
D49: 総額検算 | E49: =+SUM(E7:E45) -> 42643669657 | F49: =+SUM(F7:F45) -> 17380716581 | G49: =+SUM(G7:G45) -> 396270048 | H49: =+SUM(H7:H45) -> 492675795 | I49: =+SUM(I7:I45) -> 18269662424 | J49: =+SUM(J7:J45) -> 563892182 | K49: =+SUM(K7:K45) -> 23810115051 | L49: =+SUM(L7:L45) -> 24374007233 | M49: =+SUM(M7:M45) -> 0 | N49: 総額検算 | O49: =+SUM(O7:O45) -> 41815647458 | P49: =+SUM(P7:P45) -> 17221073393 | Q49: =+SUM(Q7:Q45) -> 377350558 | R49: =+SUM(R7:R45) -> 457243918 | S49: =+SUM(S7:S45) -> 18055667869 | T49: =+SUM(T7:T45) -> 551241129 | U49: =+SUM(U7:U45) -> 23208738460 | V49: =+SUM(V7:V45) -> 23759979589 | W49: =+SUM(W7:W21,W22:W27,W28:W33,W34:W36,W37:W40,W41:W45) -> 0 | X49: 総額検算 | AD49: =+SUM(AD7:AD45) -> 42028134935 | AE49: =+SUM(AE7:AE45) -> 17385467774 | AF49: =+SUM(AF7:AF45) -> 392800549 | AG49: =+SUM(AG7:AG45) -> 480297219 | AH49: =+SUM(AH7:AH45) -> 18258565542 | AI49: =+SUM(AI7:AI45) -> 560817564 | AJ49: =+SUM(AJ7:AJ45) -> 23208751829 | AK49: =+SUM(AK7:AK45) -> 23769569393 | AL49: =+SUM(AL7:AL21,AL22:AL27,AL28:AL33,AL34:AL36,AL37:AL40,AL41:AL45) -> 0 | AO49: =AM49-AN49 -> 0 | AR49: =AM49-AQ49 -> 0
E50: =E49-'[1]3条支出'!$E$42 -> 0 | O50: =+O49-'[1]3条支出'!$T$42 -> 0 | AD50: =+AD49-'[1]3条支出'!$T$41 -> 0 | AO50: =AM50-AN50 -> 0 | AR50: =AM50-AQ50 -> 0
D52: =+$D$1 -> 令和５年度決算 消費税算出資料 | N52: =+$D$1 -> 令和５年度決算 消費税算出資料 | X52: =+$D$1 -> 令和５年度決算 消費税算出資料
D53: 【３条収入雨汚水分け表】 | M53: =+IF(COUNTIF(M58:M96,0)=COUNT(M58:M96),"","↓エラーあり") | N53: 【３条収入雨汚水分け表】 | W53: =+IF(COUNTIF(W58:W96,0)=COUNT(W58:W96),"","↓エラーあり") | X53: 【３条収入雨汚水分け表】（消費税雑収益加算後） | AL53: =+IF(COUNTIF(AL58:AL96,0)=COUNT(AL58:AL96),"","↓エラーあり")
D54: 費目 | E54: ３条収入 税込み | N54: 費目 | O54: ３条収入 税抜き | X54: 費目 | AD54: ３条収入 税抜き
E55: 税込決算額 | F55: 雨水 | J55: 汚水 | M55: チェック | O55: 税抜決算額 | P55: 雨水 | T55: 汚水 | W55: チェック | AD55: 税抜決算額 | AE55: 雨水 | AI55: 汚水 | AL55: チェック
F56: 繰出基準内 | G56: 繰出基準内 | H56: 繰出基準外 | I56: 計 | J56: 繰出基準内 | K56: 繰出基準外 | L56: 計 | P56: 繰出基準内 | Q56: 繰出基準内 | R56: 繰出基準外 | S56: 計 | T56: 繰出基準内 | U56: 繰出基準外 | V56: 計 | AE56: 繰出基準内 | AF56: 繰出基準内 | AG56: 繰出基準外 | AH56: 計 | AI56: 繰出基準内 | AJ56: 繰出基準外 | AK56: 計
F57: 使用料徴収区域内 | G57: 使用料徴収区域外 | H57: 一般行政経費 | J57: 使用料徴収区域内 | K57: 使用料徴収区域内 | P57: 使用料徴収区域内 | Q57: 使用料徴収区域外 | R57: 一般行政経費 | T57: 使用料徴収区域内 | U57: 使用料徴収区域内 | AE57: 使用料徴収区域内 | AF57: 使用料徴収区域外 | AG57: 一般行政経費 | AI57: 使用料徴収区域内 | AJ57: 使用料徴収区域内
B58: 維持 | C58: 営業 | D58: 下水道使用料 | E58: =+'[2]3条収入'!E8 -> 20488962528 | I58: =+SUM(F58:H58) -> 0 | K58: =+E58 -> 20488962528 | L58: =+SUM(J58:K58) -> 20488962528 | M58: =E58-SUM(I58,L58) -> 0 | N58: 下水道使用料 | O58: =+'[2]3条収入'!AI8 -> 18626337467 | P58: =+IFERROR(ROUND(F58*$O58/$E58,0),0) -> 0 | Q58: =+IFERROR(ROUND(G58*$O58/$E58,0),0) -> 0 | R58: =+IFERROR(ROUND(H58*$O58/$E58,0),0) -> 0 | S58: =+SUM(P58:R58) -> 0 | T58: =+IFERROR(ROUND(J58*$O58/$E58,0),0) -> 0 | U58: =+O58-S58-T58 -> 18626337467 | V58: =+SUM(T58:U58) -> 18626337467 | W58: =O58-SUM(S58,V58) -> 0 | X58: 下水道使用料 | AD58: =+O58 -> 18626337467 | AE58: =+P58 -> 0 | AF58: =+Q58 -> 0 | AG58: =+R58 -> 0 | AH58: =+SUM(AE58:AG58) -> 0 | AI58: =+T58 -> 0 | AJ58: =+U58 -> 18626337467 | AK58: =+SUM(AI58:AJ58) -> 18626337467 | AL58: =AD58-SUM(AH58,AK58) -> 0 | AM58: =SUM(AE58:AG58,AI58) -> 0 | AN58: 0 | AO58: =-(AM58-AN58) -> 0 | AQ58: 0 | AR58: =-(AM58-AQ58) -> 0 | AT58: #=SUM('[4-04 集計表.xlsx]3条集計(税抜)'!R5:T5)
AM59: =SUM(AE59:AG59,AI59) -> 0 | AO59: =-(AM59-AN59) -> 0 | AR59: =-(AM59-AQ59) -> 0
B60: 維持 | C60: 営業 | D60: 受託工事収益 | E60: =+'[2]3条収入'!E17 -> 0 | F60: =+雨汚収入!AV3 -> 0 | G60: =+雨汚収入!AW3 -> 0 | H60: =+雨汚収入!AX3 -> 0 | I60: =+SUM(F60:H60) -> 0 | J60: =+雨汚収入!AZ3 -> 0 | K60: =+雨汚収入!BA3 -> 0 | L60: =+SUM(J60:K60) -> 0 | M60: =E60-SUM(I60,L60) -> 0 | N60: 受託工事収益 | O60: =+'[2]3条収入'!AI17 -> 0 | P60: =+雨汚収入!BF3 -> 0 | Q60: =+雨汚収入!BG3 -> 0 | R60: =+雨汚収入!BH3 -> 0 | S60: =+SUM(P60:R60) -> 0 | T60: =+雨汚収入!BJ3 -> 0 | U60: =+雨汚収入!BK3 -> 0 | V60: =+SUM(T60:U60) -> 0 | W60: =O60-SUM(S60,V60) -> 0 | X60: 受託工事収益 | AD60: =+O60 -> 0 | AE60: =+P60 -> 0 | AF60: =+Q60 -> 0 | AG60: =+R60 -> 0 | AH60: =+SUM(AE60:AG60) -> 0 | AI60: =+T60 -> 0 | AJ60: =+U60 -> 0 | AK60: =+SUM(AI60:AJ60) -> 0 | AL60: =AD60-SUM(AH60,AK60) -> 0 | AM60: =SUM(AE60:AG60,AI60) -> 0 | AO60: =-(AM60-AN60) -> 0 | AR60: =-(AM60-AQ60) -> 0
B61: 維持 | C61: 営業 | D61: その他 産物売却代金 | E61: =+'[2]3条収入'!E20 -> 187826166 | F61: =+雨汚収入!AV4 -> 0 | G61: =+雨汚収入!AW4 -> 0 | H61: =+雨汚収入!AX4 -> 37753060 | I61: =+SUM(F61:H61) -> 37753060 | J61: =+雨汚収入!AZ4 -> 0 | K61: =+雨汚収入!BA4 -> 150073106 | L61: =+SUM(J61:K61) -> 150073106 | M61: =E61-SUM(I61,L61) -> 0 | N61: その他 産物売却代金 | O61: =+'[2]3条収入'!AI20 -> 170751060 | P61: =+雨汚収入!BF4 -> 0 | Q61: =+雨汚収入!BG4 -> 0 | R61: =+雨汚収入!BH4 -> 34320964 | S61: =+SUM(P61:R61) -> 34320964 | T61: =+雨汚収入!BJ4 -> 0 | U61: =+雨汚収入!BK4 -> 136430096 | V61: =+SUM(T61:U61) -> 136430096 | W61: =O61-SUM(S61,V61) -> 0 | X61: その他 産物売却代金 | AD61: =+O61 -> 170751060 | AE61: =+P61 -> 0 | AF61: =+Q61 -> 0 | AG61: =+R61 -> 34320964 | AH61: =+SUM(AE61:AG61) -> 34320964 | AI61: =+T61 -> 0 | AJ61: =+U61 -> 136430096 | AK61: =+SUM(AI61:AJ61) -> 136430096 | AL61: =AD61-SUM(AH61,AK61) -> 0 | AM61: =SUM(AE61:AG61,AI61) -> 34320964 | AN61: 0 | AO61: =-(AM61-AN61) -> -34320964 | AQ61: 0 | AR61: =-(AM61-AQ61) -> -34320964 | AT61: #=SUM('[4-04 集計表.xlsx]3条集計(税抜)'!R7:T7)
B62: 維持 | C62: 営業 | D62: その他 業務受託収入 | E62: =+'[2]3条収入'!E21 -> 1409733 | F62: =+雨汚収入!AV5 -> 902422 | G62: =+雨汚収入!AW5 -> 507311 | H62: =+雨汚収入!AX5 -> 0 | I62: =+SUM(F62:H62) -> 1409733 | J62: =+雨汚収入!AZ5 -> 0 | K62: =+雨汚収入!BA5 -> 0 | L62: =+SUM(J62:K62) -> 0 | M62: =E62-SUM(I62,L62) -> 0 | N62: その他 業務受託収入 | O62: =+'[2]3条収入'!AI21 -> 1281576 | P62: =+雨汚収入!BF5 -> 820384 | Q62: =+雨汚収入!BG5 -> 461192 | R62: =+雨汚収入!BH5 -> 0 | S62: =+SUM(P62:R62) -> 1281576 | T62: =+雨汚収入!BJ5 -> 0 | U62: =+雨汚収入!BK5 -> 0 | V62: =+SUM(T62:U62) -> 0 | W62: =O62-SUM(S62,V62) -> 0 | X62: その他 業務受託収入 | AD62: =+O62 -> 1281576 | AE62: =+P62 -> 820384 | AF62: =+Q62 -> 461192 | AG62: =+R62 -> 0 | AH62: =+SUM(AE62:AG62) -> 1281576 | AI62: =+T62 -> 0 | AJ62: =+U62 -> 0 | AK62: =+SUM(AI62:AJ62) -> 0 | AL62: =AD62-SUM(AH62,AK62) -> 0 | AM62: =SUM(AE62:AG62,AI62) -> 1281576 | AN62: 1456000 | AO62: =-(AM62-AN62) -> 174424 | AQ62: 1599000 | AR62: =-(AM62-AQ62) -> 317424 | AT62: #=SUM('[4-04 集計表.xlsx]3条集計(税抜)'!R8:T8)
B63: 維持 | C63: 営業 | D63: その他 手数料（境界証明等） | E63: =+'[2]3条収入'!E23 -> 71970 | F63: =+雨汚収入!AV6 -> 32943 | G63: =+雨汚収入!AW6 -> 0 | H63: =+雨汚収入!AX6 -> 0 | I63: =+SUM(F63:H63) -> 32943 | J63: =+雨汚収入!AZ6 -> 0 | K63: =+雨汚収入!BA6 -> 39027 | L63: =+SUM(J63:K63) -> 39027 | M63: =E63-SUM(I63,L63) -> 0 | N63: その他 手数料（境界証明等） | O63: =+'[2]3条収入'!AI23 -> 71970 | P63: =+雨汚収入!BF6 -> 32943 | Q63: =+雨汚収入!BG6 -> 0 | R63: =+雨汚収入!BH6 -> 0 | S63: =+SUM(P63:R63) -> 32943 | T63: =+雨汚収入!BJ6 -> 0 | U63: =+雨汚収入!BK6 -> 39027 | V63: =+SUM(T63:U63) -> 39027 | W63: =O63-SUM(S63,V63) -> 0 | X63: その他 手数料（境界証明等） | AD63: =+O63 -> 71970 | AE63: =+P63 -> 32943 | AF63: =+Q63 -> 0 | AG63: =+R63 -> 0 | AH63: =+SUM(AE63:AG63) -> 32943 | AI63: =+T63 -> 0 | AJ63: =+U63 -> 39027 | AK63: =+SUM(AI63:AJ63) -> 39027 | AL63: =AD63-SUM(AH63,AK63) -> 0 | AM63: =SUM(AE63:AG63,AI63) -> 32943 | AO63: =-(AM63-AN63) -> -32943 | AR63: =-(AM63-AQ63) -> -32943
B64: 維持 | C64: 営業 | D64: その他 手数料（指定工事店登録） | E64: =+'[2]3条収入'!E24 -> 539000 | F64: =+雨汚収入!AV7 -> 0 | G64: =+雨汚収入!AW7 -> 0 | H64: =+雨汚収入!AX7 -> 0 | I64: =+SUM(F64:H64) -> 0 | J64: =+雨汚収入!AZ7 -> 269500 | K64: =+雨汚収入!BA7 -> 269500 | L64: =+SUM(J64:K64) -> 539000 | M64: =E64-SUM(I64,L64) -> 0 | N64: その他 手数料（指定工事店登録） | O64: =+'[2]3条収入'!AI24 -> 539000 | P64: =+雨汚収入!BF7 -> 0 | Q64: =+雨汚収入!BG7 -> 0 | R64: =+雨汚収入!BH7 -> 0 | S64: =+SUM(P64:R64) -> 0 | T64: =+雨汚収入!BJ7 -> 269500 | U64: =+雨汚収入!BK7 -> 269500 | V64: =+SUM(T64:U64) -> 539000 | W64: =O64-SUM(S64,V64) -> 0 | X64: その他 手数料（指定工事店登録） | AD64: =+O64 -> 539000 | AE64: =+P64 -> 0 | AF64: =+Q64 -> 0 | AG64: =+R64 -> 0 | AH64: =+SUM(AE64:AG64) -> 0 | AI64: =+T64 -> 269500 | AJ64: =+U64 -> 269500 | AK64: =+SUM(AI64:AJ64) -> 539000 | AL64: =AD64-SUM(AH64,AK64) -> 0 | AM64: =SUM(AE64:AG64,AI64) -> 269500 | AN64: 0 | AO64: =-(AM64-AN64) -> -269500 | AQ64: 0 | AR64: =-(AM64-AQ64) -> -269500 | AT64: #=SUM('[4-04 集計表.xlsx]3条集計(税抜)'!R9:T9)
B65: 維持 | C65: 営業 | D65: 雑収益 | E65: =+'[2]3条収入'!E26 -> 0 | F65: =+雨汚収入!AV8 -> 0 | G65: =+雨汚収入!AW8 -> 0 | H65: =+雨汚収入!AX8 -> 0 | I65: =+SUM(F65:H65) -> 0 | J65: =+雨汚収入!AZ8 -> 0 | K65: =+雨汚収入!BA8 -> 0 | L65: =+SUM(J65:K65) -> 0 | M65: =E65-SUM(I65,L65) -> 0 | N65: 雑収益 | O65: =+'[2]3条収入'!AI26 -> 0 | P65: =+雨汚収入!BF8 -> 0 | Q65: =+雨汚収入!BG8 -> 0 | R65: =+雨汚収入!BH8 -> 0 | S65: =+SUM(P65:R65) -> 0 | T65: =+雨汚収入!BJ8 -> 0 | U65: =+雨汚収入!BK8 -> 0 | V65: =+SUM(T65:U65) -> 0 | W65: =O65-SUM(S65,V65) -> 0 | X65: 雑収益 | AD65: =+O65 -> 0 | AE65: =+P65 -> 0 | AF65: =+Q65 -> 0 | AG65: =+R65 -> 0 | AH65: =+SUM(AE65:AG65) -> 0 | AI65: =+T65 -> 0 | AJ65: =+U65 -> 0 | AK65: =+SUM(AI65:AJ65) -> 0 | AL65: =AD65-SUM(AH65,AK65) -> 0 | AM65: =SUM(AE65:AG65,AI65) -> 0 | AO65: =-(AM65-AN65) -> 0 | AR65: =-(AM65-AQ65) -> 0
AM66: =SUM(AE66:AG66,AI66) -> 0 | AO66: =-(AM66-AN66) -> 0 | AR66: =-(AM66-AQ66) -> 0
AM67: =SUM(AE67:AG67,AI67) -> 0 | AO67: =-(AM67-AN67) -> 0 | AR67: =-(AM67-AQ67) -> 0
B68: 維持 | C68: 営外 | D68: 受取利息 | E68: =+'[2]3条収入'!E29 -> 88770 | F68: =+雨汚収入!AV9 -> 44385 | G68: =+雨汚収入!AW9 -> 0 | H68: =+雨汚収入!AX9 -> 0 | I68: =+SUM(F68:H68) -> 44385 | J68: =+雨汚収入!AZ9 -> 0 | K68: =+雨汚収入!BA9 -> 44385 | L68: =+SUM(J68:K68) -> 44385 | M68: =E68-SUM(I68,L68) -> 0 | N68: 受取利息 | O68: =+'[2]3条収入'!AI29 -> 88770 | P68: =+雨汚収入!BF9 -> 44385 | Q68: =+雨汚収入!BG9 -> 0 | R68: =+雨汚収入!BH9 -> 0 | S68: =+SUM(P68:R68) -> 44385 | T68: =+雨汚収入!BJ9 -> 0 | U68: =+雨汚収入!BK9 -> 44385 | V68: =+SUM(T68:U68) -> 44385 | W68: =O68-SUM(S68,V68) -> 0 | X68: 受取利息 | AD68: =+O68 -> 88770 | AE68: =+P68 -> 44385 | AF68: =+Q68 -> 0 | AG68: =+R68 -> 0 | AH68: =+SUM(AE68:AG68) -> 44385 | AI68: =+T68 -> 0 | AJ68: =+U68 -> 44385 | AK68: =+SUM(AI68:AJ68) -> 44385 | AL68: =AD68-SUM(AH68,AK68) -> 0 | AM68: =SUM(AE68:AG68,AI68) -> 44385 | AN68: 0 | AO68: =-(AM68-AN68) -> -44385 | AQ68: 0 | AR68: =-(AM68-AQ68) -> -44385 | AT68: #=SUM('[4-04 集計表.xlsx]3条集計(税抜)'!R10:T10)
B69: 維持 | C69: 営外 | D69: 国庫補助金(災害) | E69: =+'[2]3条収入'!E34 -> 0 | F69: =+雨汚収入!AV10 -> 0 | G69: =+雨汚収入!AW10 -> 0 | H69: =+雨汚収入!AX10 -> 0 | I69: =+SUM(F69:H69) -> 0 | J69: =+雨汚収入!AZ10 -> 0 | K69: =+雨汚収入!BA10 -> 0 | L69: =+SUM(J69:K69) -> 0 | M69: =E69-SUM(I69,L69) -> 0 | N69: 国庫補助金(災害) | O69: =+'[2]3条収入'!AI34 -> 0 | P69: =+雨汚収入!BF10 -> 0 | Q69: =+雨汚収入!BG10 -> 0 | R69: =+雨汚収入!BH10 -> 0 | S69: =+SUM(P69:R69) -> 0 | T69: =+雨汚収入!BJ10 -> 0 | U69: =+雨汚収入!BK10 -> 0 | V69: =+SUM(T69:U69) -> 0 | W69: =O69-SUM(S69,V69) -> 0 | X69: 国庫補助金(災害) | AD69: =+O69 -> 0 | AE69: =+P69 -> 0 | AF69: =+Q69 -> 0 | AG69: =+R69 -> 0 | AH69: =+SUM(AE69:AG69) -> 0 | AI69: =+T69 -> 0 | AJ69: =+U69 -> 0 | AK69: =+SUM(AI69:AJ69) -> 0 | AL69: =AD69-SUM(AH69,AK69) -> 0 | AM69: =SUM(AE69:AG69,AI69) -> 0 | AO69: =-(AM69-AN69) -> 0 | AR69: =-(AM69-AQ69) -> 0
B70: 維持 | C70: 営外 | D70: 施設管理負担金 | E70: =+'[2]3条収入'!E40 -> 37016600 | F70: =+雨汚収入!AV11 -> 36785219 | G70: =+雨汚収入!AW11 -> 0 | H70: =+雨汚収入!AX11 -> 0 | I70: =+SUM(F70:H70) -> 36785219 | J70: =+雨汚収入!AZ11 -> 0 | K70: =+雨汚収入!BA11 -> 231381 | L70: =+SUM(J70:K70) -> 231381 | M70: =E70-SUM(I70,L70) -> 0 | N70: 施設管理負担金 | O70: =+'[2]3条収入'!AI40 -> 33651455 | P70: =+雨汚収入!BF11 -> 33441108 | Q70: =+雨汚収入!BG11 -> 0 | R70: =+雨汚収入!BH11 -> 0 | S70: =+SUM(P70:R70) -> 33441108 | T70: =+雨汚収入!BJ11 -> 0 | U70: =+雨汚収入!BK11 -> 210347 | V70: =+SUM(T70:U70) -> 210347 | W70: =O70-SUM(S70,V70) -> 0 | X70: 施設管理負担金 | AD70: =+O70 -> 33651455 | AE70: =+P70 -> 33441108 | AF70: =+Q70 -> 0 | AG70: =+R70 -> 0 | AH70: =+SUM(AE70:AG70) -> 33441108 | AI70: =+T70 -> 0 | AJ70: =+U70 -> 210347 | AK70: =+SUM(AI70:AJ70) -> 210347 | AL70: =AD70-SUM(AH70,AK70) -> 0 | AM70: =SUM(AE70:AG70,AI70) -> 33441108 | AN70: 29944000 | AO70: =-(AM70-AN70) -> -3497108 | AQ70: 29944000 | AR70: =-(AM70-AQ70) -> -3497108 | AT70: #=SUM('[4-04 集計表.xlsx]3条集計(税抜)'!R11:T11)
B71: 維持 | I71: =+SUM(F71:H71) -> 0 | M71: =E71-SUM(I71,L71) -> 0 | P71: =+IFERROR(ROUND(F71*$O71/$E71,0),0) -> 0 | Q71: =+IFERROR(ROUND(G71*$O71/$E71,0),0) -> 0 | R71: =+IFERROR(ROUND(H71*$O71/$E71,0),0) -> 0 | S71: =+SUM(P71:R71) -> 0 | T71: =+IFERROR(ROUND(J71*$O71/$E71,0),0) -> 0 | U71: =+O71-S71-T71 -> 0 | V71: =+SUM(T71:U71) -> 0 | W71: =O71-SUM(S71,V71) -> 0 | AD71: =+O71 -> 0 | AE71: =+P71 -> 0 | AF71: =+Q71 -> 0 | AG71: =+R71 -> 0 | AH71: =+SUM(AE71:AG71) -> 0 | AI71: =+T71 -> 0 | AJ71: =+U71 -> 0 | AK71: =+SUM(AI71:AJ71) -> 0 | AL71: =AD71-SUM(AH71,AK71) -> 0 | AM71: =SUM(AE71:AG71,AI71) -> 0 | AO71: =-(AM71-AN71) -> 0 | AR71: =-(AM71-AQ71) -> 0
B72: 維持 | I72: =+SUM(F72:H72) -> 0 | M72: =E72-SUM(I72,L72) -> 0 | P72: =+IFERROR(ROUND(F72*$O72/$E72,0),0) -> 0 | Q72: =+IFERROR(ROUND(G72*$O72/$E72,0),0) -> 0 | R72: =+IFERROR(ROUND(H72*$O72/$E72,0),0) -> 0 | S72: =+SUM(P72:R72) -> 0 | T72: =+IFERROR(ROUND(J72*$O72/$E72,0),0) -> 0 | U72: =+O72-S72-T72 -> 0 | V72: =+SUM(T72:U72) -> 0 | W72: =O72-SUM(S72,V72) -> 0 | AD72: =+O72 -> 0 | AE72: =+P72 -> 0 | AF72: =+Q72 -> 0 | AG72: =+R72 -> 0 | AH72: =+SUM(AE72:AG72) -> 0 | AI72: =+T72 -> 0 | AJ72: =+U72 -> 0 | AK72: =+SUM(AI72:AJ72) -> 0 | AL72: =AD72-SUM(AH72,AK72) -> 0 | AM72: =SUM(AE72:AG72,AI72) -> 0 | AO72: =-(AM72-AN72) -> 0 | AR72: =-(AM72-AQ72) -> 0
B73: 維持 | C73: 営外 | D73: 消費税及び地方消費税還付金 | E73: =+'[2]3条収入'!E50 -> 0 | F73: =+雨汚収入!AV13 -> 0 | G73: =+雨汚収入!AW13 -> 0 | H73: =+雨汚収入!AX13 -> 0 | I73: =+SUM(F73:H73) -> 0 | J73: =+雨汚収入!AZ13 -> 0 | K73: =+雨汚収入!BA13 -> 0 | L73: =+SUM(J73:K73) -> 0 | M73: =E73-SUM(I73,L73) -> 0 | N73: 消費税及び地方消費税還付金 | O73: =+'[2]3条収入'!AI50 -> 0 | P73: =+雨汚収入!BF13 -> 0 | Q73: =+雨汚収入!BG13 -> 0 | R73: =+雨汚収入!BH13 -> 0 | S73: =+SUM(P73:R73) -> 0 | T73: =+雨汚収入!BJ13 -> 0 | U73: =+雨汚収入!BK13 -> 0 | V73: =+SUM(T73:U73) -> 0 | W73: =O73-SUM(S73,V73) -> 0 | X73: 消費税及び地方消費税還付金 | AD73: =+O73 -> 0 | AE73: =+P73 -> 0 | AF73: =+Q73 -> 0 | AG73: =+R73 -> 0 | AH73: =+SUM(AE73:AG73) -> 0 | AI73: =+T73 -> 0 | AJ73: =+U73 -> 0 | AK73: =+SUM(AI73:AJ73) -> 0 | AL73: =AD73-SUM(AH73,AK73) -> 0 | AM73: =SUM(AE73:AG73,AI73) -> 0 | AO73: =-(AM73-AN73) -> 0 | AR73: =-(AM73-AQ73) -> 0
B74: 維持 | C74: 営外 | I74: =+SUM(F74:H74) -> 0 | L74: =+SUM(J74:K74) -> 0 | M74: =E74-SUM(I74,L74) -> 0 | P74: =+IFERROR(ROUND(F74*$O74/$E74,0),0) -> 0 | Q74: =+IFERROR(ROUND(G74*$O74/$E74,0),0) -> 0 | R74: =+IFERROR(ROUND(H74*$O74/$E74,0),0) -> 0 | S74: =+SUM(P74:R74) -> 0 | T74: =+IFERROR(ROUND(J74*$O74/$E74,0),0) -> 0 | U74: =+O74-S74-T74 -> 0 | V74: =+SUM(T74:U74) -> 0 | W74: =O74-SUM(S74,V74) -> 0 | AD74: =+O74 -> 0 | AE74: =+P74 -> 0 | AF74: =+Q74 -> 0 | AG74: =+R74 -> 0 | AH74: =+SUM(AE74:AG74) -> 0 | AI74: =+T74 -> 0 | AJ74: =+U74 -> 0 | AK74: =+SUM(AI74:AJ74) -> 0 | AL74: =AD74-SUM(AH74,AK74) -> 0 | AM74: =SUM(AE74:AG74,AI74) -> 0 | AO74: =-(AM74-AN74) -> 0 | AR74: =-(AM74-AQ74) -> 0
B75: 維持 | C75: 営外 | D75: 不用品売却収益 | E75: =+'[2]3条収入'!E52 -> 408100 | F75: =+雨汚収入!AV14 -> 0 | G75: =+雨汚収入!AW14 -> 0 | H75: =+雨汚収入!AX14 -> 408100 | I75: =+SUM(F75:H75) -> 408100 | J75: =+雨汚収入!AZ14 -> 0 | K75: =+雨汚収入!BA14 -> 0 | L75: =+SUM(J75:K75) -> 0 | M75: =E75-SUM(I75,L75) -> 0 | N75: 不用品売却収益 | O75: =+'[2]3条収入'!AI52 -> 371000 | P75: =+雨汚収入!BF14 -> 0 | Q75: =+雨汚収入!BG14 -> 0 | R75: =+雨汚収入!BH14 -> 371000 | S75: =+SUM(P75:R75) -> 371000 | T75: =+雨汚収入!BJ14 -> 0 | U75: =+雨汚収入!BK14 -> 0 | V75: =+SUM(T75:U75) -> 0 | W75: =O75-SUM(S75,V75) -> 0 | X75: 不用品売却収益 | AD75: =+O75 -> 371000 | AE75: =+P75 -> 0 | AF75: =+Q75 -> 0 | AG75: =+R75 -> 371000 | AH75: =+SUM(AE75:AG75) -> 371000 | AI75: =+T75 -> 0 | AJ75: =+U75 -> 0 | AK75: =+SUM(AI75:AJ75) -> 0 | AL75: =AD75-SUM(AH75,AK75) -> 0 | AM75: =SUM(AE75:AG75,AI75) -> 371000 | AO75: =-(AM75-AN75) -> -371000 | AR75: =-(AM75-AQ75) -> -371000
B76: 維持 | C76: 営外 | D76: その他雑収益 | E76: =+'[2]3条収入'!E53 -> 36052234 | F76: =+雨汚収入!AV15 -> 10360569 | G76: =+雨汚収入!AW15 -> 0 | H76: =+雨汚収入!AX15 -> 1399670 | I76: =+SUM(F76:H76) -> 11760239 | J76: =+雨汚収入!AZ15 -> 0 | K76: =+雨汚収入!BA15 -> 24291995 | L76: =+SUM(J76:K76) -> 24291995 | M76: =E76-SUM(I76,L76) -> 0 | N76: その他雑収益 | O76: =+'[2]3条収入'!AI53 -> 34878977 | P76: =+雨汚収入!BF15 -> 10155799 | Q76: =+雨汚収入!BG15 -> 0 | R76: =+雨汚収入!BH15 -> 1397864 | S76: =+SUM(P76:R76) -> 11553663 | T76: =+雨汚収入!BJ15 -> 0 | U76: =+雨汚収入!BK15 -> 23325314 | V76: =+SUM(T76:U76) -> 23325314 | W76: =O76-SUM(S76,V76) -> 0 | X76: その他雑収益 | AD76: =+O76 -> 34878977 | AE76: =+P76 -> 10155799 | AF76: =+Q76 -> 0 | AG76: =+R76 -> 1397864 | AH76: =+SUM(AE76:AG76) -> 11553663 | AI76: =+T76 -> 0 | AJ76: =+U76 -> 23325314 | AK76: =+SUM(AI76:AJ76) -> 23325314 | AL76: =AD76-SUM(AH76,AK76) -> 0 | AM76: =SUM(AE76:AG76,AI76) -> 11553663 | AN76: 31400000 | AO76: =-(AM76-AN76) -> 19846337 | AQ76: 31543000 | AR76: =-(AM76-AQ76) -> 19989337 | AT76: #=SUM('[4-04 集計表.xlsx]3条集計(税抜)'!R17:T17)
B77: 維持 | C77: 営外 | D77: その他雑収益（消費税） | I77: =+SUM(F77:H77) -> 0 | L77: =+SUM(J77:K77) -> 0 | M77: =E77-SUM(I77,L77) -> 0 | N77: その他雑収益（消費税） | S77: =+SUM(P77:R77) -> 0 | V77: =+SUM(T77:U77) -> 0 | W77: =O77-SUM(S77,V77) -> 0 | X77: その他雑収益（消費税） | AD77: =+SUM(AH77,AK77:AK77) -> 1880565 | AG77: =+[3]対価返還!AX14-[3]対価返還!BH14 -> 0 | AH77: =+SUM(AE77:AG77) -> 0 | AJ77: =+[3]消費税!Z125 -> 1880565 | AK77: =+SUM(AI77:AJ77) -> 1880565 | AL77: =AD77-SUM(AH77,AK77) -> 0 | AM77: =SUM(AE77:AG77,AI77) -> 0 | AO77: =-(AM77-AN77) -> 0 | AR77: =-(AM77-AQ77) -> 0
AM78: =SUM(AE78:AG78,AI78) -> 0 | AO78: =-(AM78-AN78) -> 0 | AR78: =-(AM78-AQ78) -> 0
B79: 維持 | C79: 特別 | D79: 固定資産売却益 | E79: =+'[2]3条収入'!E59 -> 0 | F79: =+雨汚収入!AV16 -> 0 | G79: =+雨汚収入!AW16 -> 0 | H79: =+雨汚収入!AX16 -> 0 | I79: =+SUM(F79:H79) -> 0 | J79: =+雨汚収入!AZ16 -> 0 | K79: =+雨汚収入!BA16 -> 0 | L79: =+SUM(J79:K79) -> 0 | M79: =E79-SUM(I79,L79) -> 0 | N79: 固定資産売却益 | O79: =+'[2]3条収入'!AI59 -> 0 | P79: =+雨汚収入!BF16 -> 0 | Q79: =+雨汚収入!BG16 -> 0 | R79: =+雨汚収入!BH16 -> 0 | S79: =+SUM(P79:R79) -> 0 | T79: =+雨汚収入!BJ16 -> 0 | U79: =+雨汚収入!BK16 -> 0 | V79: =+SUM(T79:U79) -> 0 | W79: =O79-SUM(S79,V79) -> 0 | X79: 固定資産売却益 | AD79: =+O79 -> 0 | AE79: =+P79 -> 0 | AF79: =+Q79 -> 0 | AG79: =+R79 -> 0 | AH79: =+SUM(AE79:AG79) -> 0 | AI79: =+T79 -> 0 | AJ79: =+U79 -> 0 | AK79: =+SUM(AI79:AJ79) -> 0 | AL79: =AD79-SUM(AH79,AK79) -> 0 | AM79: =SUM(AE79:AG79,AI79) -> 0 | AO79: =-(AM79-AN79) -> 0 | AR79: =-(AM79-AQ79) -> 0
B80: 維持 | C80: 特別 | D80: 過年度損益修正益 | E80: =+'[2]3条収入'!E61-E93 -> 2435350 | F80: =+雨汚収入!AV17-F93 -> 70892 | G80: =+雨汚収入!AW17-G93 -> 0 | H80: =+雨汚収入!AX17-H93 -> 487974 | I80: =+SUM(F80:H80) -> 558866 | J80: =+雨汚収入!AZ17-J93 -> 29260 | K80: =+雨汚収入!BA17-K93 -> 1847224 | L80: =+SUM(J80:K80) -> 1876484 | M80: =E80-SUM(I80,L80) -> 0 | N80: 過年度損益修正益 | O80: =+'[2]3条収入'!AI61-O93 -> 2289462 | P80: =+雨汚収入!BF17-P93 -> 70892 | Q80: =+雨汚収入!BG17-Q93 -> 0 | R80: =+雨汚収入!BH17-R93 -> 487974 | S80: =+SUM(P80:R80) -> 558866 | T80: =+雨汚収入!BJ17-T93 -> 29260 | U80: =+雨汚収入!BK17-U93 -> 1701336 | V80: =+SUM(T80:U80) -> 1730596 | W80: =O80-SUM(S80,V80) -> 0 | X80: 過年度損益修正益 | AD80: =+O80 -> 2289462 | AE80: =+P80 -> 70892 | AF80: =+Q80 -> 0 | AG80: =+R80 -> 487974 | AH80: =+SUM(AE80:AG80) -> 558866 | AI80: =+T80 -> 29260 | AJ80: =+U80 -> 1701336 | AK80: =+SUM(AI80:AJ80) -> 1730596 | AL80: =AD80-SUM(AH80,AK80) -> 0 | AM80: =SUM(AE80:AG80,AI80) -> 588126 | AO80: =-(AM80-AN80) -> -588126 | AR80: =-(AM80-AQ80) -> -588126
B81: 維持 | C81: 特別 | D81: その他特利（その他） | E81: =+'[2]3条収入'!E63-E94 -> 864807 | F81: =+雨汚収入!AV18-F94 -> 588069 | G81: =+雨汚収入!AW18-G94 -> 0 | H81: =+雨汚収入!AX18-H94 -> 0 | I81: =+SUM(F81:H81) -> 588069 | J81: =+雨汚収入!AZ18-J94 -> 0 | K81: =+雨汚収入!BA18-K94 -> 276738 | L81: =+SUM(J81:K81) -> 276738 | M81: =E81-SUM(I81,L81) -> 0 | N81: その他特利（その他） | O81: =+'[2]3条収入'!AI63-O94 -> 864807 | P81: =+雨汚収入!BF18-P94 -> 588069 | Q81: =+雨汚収入!BG18-Q94 -> 0 | R81: =+雨汚収入!BH18-R94 -> 0 | S81: =+SUM(P81:R81) -> 588069 | T81: =+雨汚収入!BJ18-T94 -> 0 | U81: =+雨汚収入!BK18-U94 -> 276738 | V81: =+SUM(T81:U81) -> 276738 | W81: =O81-SUM(S81,V81) -> 0 | X81: その他特利（その他） | AD81: =+O81 -> 864807 | AE81: =+P81 -> 588069 | AF81: =+Q81 -> 0 | AG81: =+R81 -> 0 | AH81: =+SUM(AE81:AG81) -> 588069 | AI81: =+T81 -> 0 | AJ81: =+U81 -> 276738 | AK81: =+SUM(AI81:AJ81) -> 276738 | AL81: =AD81-SUM(AH81,AK81) -> 0 | AM81: =SUM(AE81:AG81,AI81) -> 588069 | AO81: =-(AM81-AN81) -> -588069 | AR81: =-(AM81-AQ81) -> -588069
B82: 維持 | C82: 特別 | D82: その他特利（貸倒引当戻入） | E82: =+'[2]3条収入'!E64 -> 455622 | F82: =+雨汚収入!AV19 -> 0 | G82: =+雨汚収入!AW19 -> 0 | H82: =+雨汚収入!AX19 -> 16334 | I82: =+SUM(F82:H82) -> 16334 | J82: =+雨汚収入!AZ19 -> 0 | K82: =+雨汚収入!BA19 -> 439288 | L82: =+SUM(J82:K82) -> 439288 | M82: =E82-SUM(I82,L82) -> 0 | N82: その他特利（貸倒引当戻入） | O82: =+'[2]3条収入'!AI64 -> 455622 | P82: =+雨汚収入!BF19 -> 0 | Q82: =+雨汚収入!BG19 -> 0 | R82: =+雨汚収入!BH19 -> 16334 | S82: =+SUM(P82:R82) -> 16334 | T82: =+雨汚収入!BJ19 -> 0 | U82: =+雨汚収入!BK19 -> 439288 | V82: =+SUM(T82:U82) -> 439288 | W82: =O82-SUM(S82,V82) -> 0 | X82: その他特利（貸倒引当戻入） | AD82: =+O82 -> 455622 | AE82: =+P82 -> 0 | AF82: =+Q82 -> 0 | AG82: =+R82 -> 16334 | AH82: =+SUM(AE82:AG82) -> 16334 | AI82: =+T82 -> 0 | AJ82: =+U82 -> 439288 | AK82: =+SUM(AI82:AJ82) -> 439288 | AL82: =AD82-SUM(AH82,AK82) -> 0 | AM82: =SUM(AE82:AG82,AI82) -> 16334 | AO82: =-(AM82-AN82) -> -16334 | AR82: =-(AM82-AQ82) -> -16334
B83: 維持 | C83: 特別 | D83: その他特利（賞与引当戻入） | E83: =+'[2]3条収入'!E65 -> 109000 | F83: =+雨汚収入!AV20 -> 54500 | G83: =+雨汚収入!AW20 -> 0 | H83: =+雨汚収入!AX20 -> 0 | I83: =+SUM(F83:H83) -> 54500 | J83: =+雨汚収入!AZ20 -> 0 | K83: =+雨汚収入!BA20 -> 54500 | L83: =+SUM(J83:K83) -> 54500 | M83: =E83-SUM(I83,L83) -> 0 | N83: その他特利（賞与引当戻入） | O83: =+'[2]3条収入'!AI65 -> 109000 | P83: =+雨汚収入!BF20 -> 54500 | Q83: =+雨汚収入!BG20 -> 0 | R83: =+雨汚収入!BH20 -> 0 | S83: =+SUM(P83:R83) -> 54500 | T83: =+雨汚収入!BJ20 -> 0 | U83: =+雨汚収入!BK20 -> 54500 | V83: =+SUM(T83:U83) -> 54500 | W83: =O83-SUM(S83,V83) -> 0 | X83: その他特利（賞与引当戻入） | AD83: =+O83 -> 109000 | AE83: =+P83 -> 54500 | AF83: =+Q83 -> 0 | AG83: =+R83 -> 0 | AH83: =+SUM(AE83:AG83) -> 54500 | AI83: =+T83 -> 0 | AJ83: =+U83 -> 54500 | AK83: =+SUM(AI83:AJ83) -> 54500 | AL83: =AD83-SUM(AH83,AK83) -> 0 | AM83: =SUM(AE83:AG83,AI83) -> 54500 | AO83: =-(AM83-AN83) -> -54500 | AR83: =-(AM83-AQ83) -> -54500
AM84: =SUM(AE84:AG84,AI84) -> 0 | AO84: =-(AM84-AN84) -> 0 | AR84: =-(AM84-AQ84) -> 0
B85: 資本 | C85: 営業 | D85: 長期前受金戻入額（償却分） | E85: =+'[2]3条収入'!E56-E86 -> 9364620277 | F85: 4482094461 | G85: 2428480 | I85: =+SUM(F85:H85) -> 4484522941 | J85: =ROUND(17206476/13857936954*4880097336,0) -> 6059291 | K85: =4880097336-J85 -> 4874038045 | L85: =+SUM(J85:K85) -> 4880097336 | M85: =E85-SUM(I85,L85) -> 0 | N85: 長期前受金戻入額（償却分） | O85: =+'[2]3条収入'!AI56-O86 -> 9364620277 | P85: =+F85 -> 4482094461 | Q85: =+G85 -> 2428480 | R85: =+H85 -> 0 | S85: =+SUM(P85:R85) -> 4484522941 | T85: =+J85 -> 6059291 | U85: =+O85-S85-T85 -> 4874038045 | V85: =+SUM(T85:U85) -> 4880097336 | W85: =O85-SUM(S85,V85) -> 0 | X85: 長期前受金戻入額（償却分） | AD85: =+O85 -> 9364620277 | AE85: =+P85 -> 4482094461 | AF85: =+Q85 -> 2428480 | AG85: =+R85 -> 0 | AH85: =+SUM(AE85:AG85) -> 4484522941 | AI85: =+T85 -> 6059291 | AJ85: =+U85 -> 4874038045 | AK85: =+SUM(AI85:AJ85) -> 4880097336 | AL85: =AD85-SUM(AH85,AK85) -> 0 | AM85: =SUM(AE85:AG85,AI85) -> 4490582232 | AO85: =-(AM85-AN85) -> -4490582232 | AQ85: 4526816000 | AR85: =-(AM85-AQ85) -> 36233768
B86: 資本 | C86: 営業 | D86: 長期前受金戻入額 （除却分） | E86: 120734725 | F86: =+E86-L86-G86 -> 49928323 | G86: =+IFERROR(ROUND((E86-L86)*G35/I35,0),0) -> 486150 | I86: =+SUM(F86:H86) -> 50414473 | K86: 70320252 | L86: =+SUM(J86:K86) -> 70320252 | M86: =E86-SUM(I86,L86) -> 0 | N86: 長期前受金戻入額 （除却分） | O86: =+E86 -> 120734725 | P86: =+F86 -> 49928323 | Q86: =+G86 -> 486150 | R86: =+H86 -> 0 | S86: =+SUM(P86:R86) -> 50414473 | T86: =+J86 -> 0 | U86: =+O86-S86-T86 -> 70320252 | V86: =+SUM(T86:U86) -> 70320252 | W86: =O86-SUM(S86,V86) -> 0 | X86: 長期前受金戻入額 （除却分） | AD86: =+O86 -> 120734725 | AE86: =+P86 -> 49928323 | AF86: =+Q86 -> 486150 | AG86: =+R86 -> 0 | AH86: =+SUM(AE86:AG86) -> 50414473 | AI86: =+T86 -> 0 | AJ86: =+U86 -> 70320252 | AK86: =+SUM(AI86:AJ86) -> 70320252 | AL86: =AD86-SUM(AH86,AK86) -> 0 | AM86: =SUM(AE86:AG86,AI86) -> 50414473 | AO86: =-(AM86-AN86) -> -50414473 | AQ86: 44696000 | AR86: =-(AM86-AQ86) -> -5718473
B87: 資本 | I87: =+SUM(F87:H87) -> 0 | L87: =+SUM(J87:K87) -> 0 | M87: =E87-SUM(I87,L87) -> 0 | S87: =+SUM(P87:R87) -> 0 | V87: =+SUM(T87:U87) -> 0 | W87: =O87-SUM(S87,V87) -> 0 | AD87: =+O87 -> 0 | AE87: =+P87 -> 0 | AF87: =+Q87 -> 0 | AG87: =+R87 -> 0 | AH87: =+SUM(AE87:AG87) -> 0 | AI87: =+T87 -> 0 | AJ87: =+U87 -> 0 | AK87: =+SUM(AI87:AJ87) -> 0 | AL87: =AD87-SUM(AH87,AK87) -> 0 | AM87: =SUM(AE87:AG87,AI87) -> 0 | AO87: =-(AM87-AN87) -> 0 | AR87: =-(AM87-AQ87) -> 0
B88: 資本 | C88: 営外 | D88: 他会計負担金（利息償還分） | E88: =+'[2]3条収入'!E41-E89 -> 16476593 | F88: =+E88-K88 -> 8440628 | I88: =+SUM(F88:H88) -> 8440628 | K88: =+ROUND(E88*K37/E37,0) -> 8035965 | L88: =+SUM(J88:K88) -> 8035965 | M88: =E88-SUM(I88,L88) -> 0 | N88: 他会計負担金（利息償還分） | O88: =E88 -> 16476593 | P88: =+F88 -> 8440628 | S88: =+SUM(P88:R88) -> 8440628 | U88: =+O88-S88-T88 -> 8035965 | V88: =+SUM(T88:U88) -> 8035965 | W88: =O88-SUM(S88,V88) -> 0 | X88: 他会計負担金（利息償還分） | AD88: =+O88 -> 16476593 | AE88: =+P88 -> 8440628 | AF88: =+Q88 -> 0 | AG88: =+R88 -> 0 | AH88: =+SUM(AE88:AG88) -> 8440628 | AI88: =+T88 -> 0 | AJ88: =+U88 -> 8035965 | AK88: =+SUM(AI88:AJ88) -> 8035965 | AL88: =AD88-SUM(AH88,AK88) -> 0 | AM88: =SUM(AE88:AG88,AI88) -> 8440628 | AO88: =-(AM88-AN88) -> -8440628 | AR88: =-(AM88-AQ88) -> -8440628
B89: 資本 | C89: 営外 | D89: 他会計負担金（減免分） | E89: =+K89 -> 0 | F89: =+雨汚収入!AV12 -> 0 | G89: =+雨汚収入!AW12 -> 0 | H89: =+雨汚収入!AX12 -> 0 | I89: =+SUM(F89:H89) -> 0 | J89: =+雨汚収入!AZ12 -> 0 | K89: =+雨汚収入!BA12 -> 0 | L89: =+SUM(J89:K89) -> 0 | M89: =E89-SUM(I89,L89) -> 0 | N89: 他会計負担金（減免分） | O89: =+'[2]3条収入'!AI41-O88 -> 0 | P89: =+雨汚収入!BF12 -> 0 | Q89: =+雨汚収入!BG12 -> 0 | R89: =+雨汚収入!BH12 -> 0 | S89: =+SUM(P89:R89) -> 0 | T89: =+雨汚収入!BJ12 -> 0 | U89: =+雨汚収入!BK12 -> 0 | V89: =+SUM(T89:U89) -> 0 | W89: =O89-SUM(S89,V89) -> 0 | X89: 他会計負担金（減免分） | AD89: =+O89 -> 0 | AE89: =+P89 -> 0 | AF89: =+Q89 -> 0 | AG89: =+R89 -> 0 | AH89: =+SUM(AE89:AG89) -> 0 | AI89: =+T89 -> 0 | AJ89: =+U89 -> 0 | AK89: =+SUM(AI89:AJ89) -> 0 | AL89: =AD89-SUM(AH89,AK89) -> 0 | AM89: =SUM(AE89:AG89,AI89) -> 0 | AO89: =-(AM89-AN89) -> 0 | AR89: =-(AM89-AQ89) -> 0
B90: 資本 | C90: 営外 | I90: =+SUM(F90:H90) -> 0 | L90: =+SUM(J90:K90) -> 0 | M90: =E90-SUM(I90,L90) -> 0 | S90: =+SUM(P90:R90) -> 0 | V90: =+SUM(T90:U90) -> 0 | W90: =O90-SUM(S90,V90) -> 0 | AD90: =+O90 -> 0 | AE90: =+P90 -> 0 | AF90: =+Q90 -> 0 | AG90: =+R90 -> 0 | AH90: =+SUM(AE90:AG90) -> 0 | AI90: =+T90 -> 0 | AJ90: =+U90 -> 0 | AK90: =+SUM(AI90:AJ90) -> 0 | AL90: =AD90-SUM(AH90,AK90) -> 0 | AM90: =SUM(AE90:AG90,AI90) -> 0 | AO90: =-(AM90-AN90) -> 0 | AR90: =-(AM90-AQ90) -> 0
AM91: =SUM(AE91:AG91,AI91) -> 0 | AO91: =-(AM91-AN91) -> 0 | AR91: =-(AM91-AQ91) -> 0
B92: 資本 | C92: 特別 | I92: =+SUM(F92:H92) -> 0 | L92: =+SUM(J92:K92) -> 0 | M92: =E92-SUM(I92,L92) -> 0 | S92: =+SUM(P92:R92) -> 0 | V92: =+SUM(T92:U92) -> 0 | W92: =O92-SUM(S92,V92) -> 0 | AD92: =+O92 -> 0 | AE92: =+P92 -> 0 | AF92: =+Q92 -> 0 | AG92: =+R92 -> 0 | AH92: =+SUM(AE92:AG92) -> 0 | AI92: =+T92 -> 0 | AJ92: =+U92 -> 0 | AK92: =+SUM(AI92:AJ92) -> 0 | AL92: =AD92-SUM(AH92,AK92) -> 0 | AM92: =SUM(AE92:AG92,AI92) -> 0 | AO92: =-(AM92-AN92) -> 0 | AR92: =-(AM92-AQ92) -> 0
B93: 資本 | C93: 特別 | D93: 過年度損益修正益 | E93: 334220 | F93: 281270 | I93: =+SUM(F93:H93) -> 281270 | K93: 52950 | L93: =+SUM(J93:K93) -> 52950 | M93: =E93-SUM(I93,L93) -> 0 | N93: 過年度損益修正益 | O93: =+E93 -> 334220 | P93: =+F93 -> 281270 | Q93: =+G93 -> 0 | S93: =+SUM(P93:R93) -> 281270 | T93: =+J93 -> 0 | U93: =+O93-S93-T93 -> 52950 | V93: =+SUM(T93:U93) -> 52950 | W93: =O93-SUM(S93,V93) -> 0 | X93: 過年度損益修正益 | AD93: =+O93 -> 334220 | AE93: =+P93 -> 281270 | AF93: =+Q93 -> 0 | AG93: =+R93 -> 0 | AH93: =+SUM(AE93:AG93) -> 281270 | AI93: =+T93 -> 0 | AJ93: =+U93 -> 52950 | AK93: =+SUM(AI93:AJ93) -> 52950 | AL93: =AD93-SUM(AH93,AK93) -> 0 | AM93: =SUM(AE93:AG93,AI93) -> 281270 | AO93: =-(AM93-AN93) -> -281270 | AR93: =-(AM93-AQ93) -> -281270
B94: 資本 | C94: 特別 | D94: その他特別利益 | I94: =+SUM(F94:H94) -> 0 | L94: =+SUM(J94:K94) -> 0 | M94: =E94-SUM(I94,L94) -> 0 | N94: その他特別利益 | O94: =+E94 -> 0 | P94: =+F94 -> 0 | Q94: =+G94 -> 0 | S94: =+SUM(P94:R94) -> 0 | T94: =+J94 -> 0 | U94: =+O94-S94-T94 -> 0 | V94: =+SUM(T94:U94) -> 0 | W94: =O94-SUM(S94,V94) -> 0 | X94: その他特別利益 | AD94: =+O94 -> 0 | AE94: =+P94 -> 0 | AF94: =+Q94 -> 0 | AG94: =+R94 -> 0 | AH94: =+SUM(AE94:AG94) -> 0 | AI94: =+T94 -> 0 | AJ94: =+U94 -> 0 | AK94: =+SUM(AI94:AJ94) -> 0 | AL94: =AD94-SUM(AH94,AK94) -> 0 | AM94: =SUM(AE94:AG94,AI94) -> 0 | AO94: =-(AM94-AN94) -> 0 | AR94: =-(AM94-AQ94) -> 0
B95: 資本 | C95: 特別 | D95: 長期前受金戻入益（減損分） | E95: =+'[2]3条収入'!E66 -> 0 | F95: 0 | I95: =+SUM(F95:H95) -> 0 | K95: 0 | L95: =+SUM(J95:K95) -> 0 | M95: =E95-SUM(I95,L95) -> 0 | N95: 長期前受金戻入益（減損分） | O95: =+'[2]3条収入'!AI66 -> 0 | P95: =+F95 -> 0 | S95: =+SUM(P95:R95) -> 0 | U95: =+O95-S95-T95 -> 0 | V95: =+SUM(T95:U95) -> 0 | W95: =O95-SUM(S95,V95) -> 0 | X95: 長期前受金戻入益（減損分） | AD95: =+O95 -> 0 | AE95: =+P95 -> 0 | AF95: =+Q95 -> 0 | AG95: =+R95 -> 0 | AH95: =+SUM(AE95:AG95) -> 0 | AI95: =+T95 -> 0 | AJ95: =+U95 -> 0 | AK95: =+SUM(AI95:AJ95) -> 0 | AL95: =AD95-SUM(AH95,AK95) -> 0 | AM95: =SUM(AE95:AG95,AI95) -> 0 | AO95: =-(AM95-AN95) -> 0 | AR95: =-(AM95-AQ95) -> 0
AM96: =SUM(AE96:AG96,AI96) -> 0 | AO96: =-(AM96-AN96) -> 0 | AR96: =-(AM96-AQ96) -> 0
D97: 合 計 | E97: =+SUM(E58:E96) -> 30258405695 | F97: =+SUM(F58:F96) -> 4589583681 | G97: =+SUM(G58:G96) -> 3421941 | H97: =+SUM(H58:H96) -> 40065138 | I97: =+SUM(I58:I96) -> 4633070760 | J97: =+SUM(J58:J96) -> 6358051 | K97: =+SUM(K58:K96) -> 25618976884 | L97: =+SUM(L58:L96) -> 25625334935 | M97: =+SUM(M58:M96) -> 0 | N97: 合 計 | O97: =+SUM(O58:O96) -> 28373855981 | P97: =+SUM(P58:P96) -> 4585952762 | Q97: =+SUM(Q58:Q96) -> 3375822 | R97: =+SUM(R58:R96) -> 36594136 | S97: =+SUM(S58:S96) -> 4625922720 | T97: =+SUM(T58:T96) -> 6358051 | U97: =+SUM(U58:U96) -> 23741575210 | V97: =+SUM(V58:V96) -> 23747933261 | W97: =+SUM(W58:W96) -> 0 | X97: 合 計 | AD97: =+SUM(AD58:AD96) -> 28375736546 | AE97: =+SUM(AE58:AE96) -> 4585952762 | AF97: =+SUM(AF58:AF96) -> 3375822 | AG97: =+SUM(AG58:AG96) -> 36594136 | AH97: =+SUM(AH58:AH96) -> 4625922720 | AI97: =+SUM(AI58:AI96) -> 6358051 | AJ97: =+SUM(AJ58:AJ96) -> 23743455775 | AK97: =+SUM(AK58:AK96) -> 23749813826 | AL97: =+SUM(AL58:AL96) -> 0
B98: 維持 | D98: うち、維持管理費分 計 | E98: =+SUMIFS(E$58:E$96,$B$58:$B$96,$B98) -> 20756239880 | F98: =+SUMIFS(F$58:F$96,$B$58:$B$96,$B98) -> 48838999 | G98: =+SUMIFS(G$58:G$96,$B$58:$B$96,$B98) -> 507311 | H98: =+SUMIFS(H$58:H$96,$B$58:$B$96,$B98) -> 40065138 | I98: =+SUMIFS(I$58:I$96,$B$58:$B$96,$B98) -> 89411448 | J98: =+SUMIFS(J$58:J$96,$B$58:$B$96,$B98) -> 298760 | K98: =+SUMIFS(K$58:K$96,$B$58:$B$96,$B98) -> 20666529672 | L98: =+SUMIFS(L$58:L$96,$B$58:$B$96,$B98) -> 20666828432 | M98: =+SUMIFS(M$58:M$96,$B$58:$B$96,$B98) -> 0 | N98: うち、維持管理費分 計 | O98: =+SUMIFS(O$58:O$96,$B$58:$B$96,$B98) -> 18871690166 | P98: =+SUMIFS(P$58:P$96,$B$58:$B$96,$B98) -> 45208080 | Q98: =+SUMIFS(Q$58:Q$96,$B$58:$B$96,$B98) -> 461192 | R98: =+SUMIFS(R$58:R$96,$B$58:$B$96,$B98) -> 36594136 | S98: =+SUMIFS(S$58:S$96,$B$58:$B$96,$B98) -> 82263408 | T98: =+SUMIFS(T$58:T$96,$B$58:$B$96,$B98) -> 298760 | U98: =+SUMIFS(U$58:U$96,$B$58:$B$96,$B98) -> 18789127998 | V98: =+SUMIFS(V$58:V$96,$B$58:$B$96,$B98) -> 18789426758 | W98: =+SUMIFS(W$58:W$96,$B$58:$B$96,$B98) -> 0 | X98: うち、維持管理費分 計 | AD98: =+SUMIFS(AD$58:AD$96,$B$58:$B$96,$B98) -> 18873570731 | AE98: =+SUMIFS(AE$58:AE$96,$B$58:$B$96,$B98) -> 45208080 | AF98: =+SUMIFS(AF$58:AF$96,$B$58:$B$96,$B98) -> 461192 | AG98: =+SUMIFS(AG$58:AG$96,$B$58:$B$96,$B98) -> 36594136 | AH98: =+SUMIFS(AH$58:AH$96,$B$58:$B$96,$B98) -> 82263408 | AI98: =+SUMIFS(AI$58:AI$96,$B$58:$B$96,$B98) -> 298760 | AJ98: =+SUMIFS(AJ$58:AJ$96,$B$58:$B$96,$B98) -> 18791008563 | AK98: =+SUMIFS(AK$58:AK$96,$B$58:$B$96,$B98) -> 18791307323 | AL98: =+SUMIFS(AL$58:AL$96,$B$58:$B$96,$B98) -> 0
B99: 資本 | D99: うち、資本費分 計 | E99: =+SUMIFS(E$58:E$96,$B$58:$B$96,$B99) -> 9502165815 | F99: =+SUMIFS(F$58:F$96,$B$58:$B$96,$B99) -> 4540744682 | G99: =+SUMIFS(G$58:G$96,$B$58:$B$96,$B99) -> 2914630 | H99: =+SUMIFS(H$58:H$96,$B$58:$B$96,$B99) -> 0 | I99: =+SUMIFS(I$58:I$96,$B$58:$B$96,$B99) -> 4543659312 | J99: =+SUMIFS(J$58:J$96,$B$58:$B$96,$B99) -> 6059291 | K99: =+SUMIFS(K$58:K$96,$B$58:$B$96,$B99) -> 4952447212 | L99: =+SUMIFS(L$58:L$96,$B$58:$B$96,$B99) -> 4958506503 | M99: =+SUMIFS(M$58:M$96,$B$58:$B$96,$B99) -> 0 | N99: うち、資本費分 計 | O99: =+SUMIFS(O$58:O$96,$B$58:$B$96,$B99) -> 9502165815 | P99: =+SUMIFS(P$58:P$96,$B$58:$B$96,$B99) -> 4540744682 | Q99: =+SUMIFS(Q$58:Q$96,$B$58:$B$96,$B99) -> 2914630 | R99: =+SUMIFS(R$58:R$96,$B$58:$B$96,$B99) -> 0 | S99: =+SUMIFS(S$58:S$96,$B$58:$B$96,$B99) -> 4543659312 | T99: =+SUMIFS(T$58:T$96,$B$58:$B$96,$B99) -> 6059291 | U99: =+SUMIFS(U$58:U$96,$B$58:$B$96,$B99) -> 4952447212 | V99: =+SUMIFS(V$58:V$96,$B$58:$B$96,$B99) -> 4958506503 | W99: =+SUMIFS(W$58:W$96,$B$58:$B$96,$B99) -> 0 | X99: うち、資本費分 計 | AD99: =+SUMIFS(AD$58:AD$96,$B$58:$B$96,$B99) -> 9502165815 | AE99: =+SUMIFS(AE$58:AE$96,$B$58:$B$96,$B99) -> 4540744682 | AF99: =+SUMIFS(AF$58:AF$96,$B$58:$B$96,$B99) -> 2914630 | AG99: =+SUMIFS(AG$58:AG$96,$B$58:$B$96,$B99) -> 0 | AH99: =+SUMIFS(AH$58:AH$96,$B$58:$B$96,$B99) -> 4543659312 | AI99: =+SUMIFS(AI$58:AI$96,$B$58:$B$96,$B99) -> 6059291 | AJ99: =+SUMIFS(AJ$58:AJ$96,$B$58:$B$96,$B99) -> 4952447212 | AK99: =+SUMIFS(AK$58:AK$96,$B$58:$B$96,$B99) -> 4958506503 | AL99: =+SUMIFS(AL$58:AL$96,$B$58:$B$96,$B99) -> 0
D100: 総額検算 | E100: =+SUM(E58:E96) -> 30258405695 | F100: =+SUM(F58:F96) -> 4589583681 | G100: =+SUM(G58:G96) -> 3421941 | H100: =+SUM(H58:H96) -> 40065138 | I100: =+SUM(I58:I96) -> 4633070760 | J100: =+SUM(J58:J96) -> 6358051 | K100: =+SUM(K58:K96) -> 25618976884 | L100: =+SUM(L58:L96) -> 25625334935 | M100: =+SUM(M58:M74,M68:M78,M79:M84,M85:M87,M88:M91,M92:M96) -> 0 | N100: 総額検算 | O100: =+SUM(O58:O96) -> 28373855981 | P100: =+SUM(P58:P96) -> 4585952762 | Q100: =+SUM(Q58:Q96) -> 3375822 | R100: =+SUM(R58:R96) -> 36594136 | S100: =+SUM(S58:S96) -> 4625922720 | T100: =+SUM(T58:T96) -> 6358051 | U100: =+SUM(U58:U96) -> 23741575210 | V100: =+SUM(V58:V96) -> 23747933261 | W100: =+SUM(W58:W74,W68:W78,W79:W84,W85:W87,W88:W91,W92:W96) -> 0 | X100: 総額検算 | AD100: =+SUM(AD58:AD96) -> 28375736546 | AE100: =+SUM(AE58:AE96) -> 4585952762 | AF100: =+SUM(AF58:AF96) -> 3375822 | AG100: =+SUM(AG58:AG96) -> 36594136 | AH100: =+SUM(AH58:AH96) -> 4625922720 | AI100: =+SUM(AI58:AI96) -> 6358051 | AJ100: =+SUM(AJ58:AJ96) -> 23743455775 | AK100: =+SUM(AK58:AK96) -> 23749813826 | AL100: =+SUM(AL58:AL72,AL73:AL78,AL79:AL84,AL85:AL87,AL88:AL91,AL92:AL96) -> 0
E101: =+E100-('[2]3条収入'!$E$70-'[2]3条収入'!$E$9-'[2]3条収入'!$E$42) -> 0 | O101: =+O100-('[2]3条収入'!$AI$70-'[2]3条収入'!$AI$9-'[2]3条収入'!$AI$42) -> 0 | AD101: =+AD100-('[2]3条収入'!$AI$69-'[2]3条収入'!$AI$9-'[2]3条収入'!$AI$42) -> 0
...

Sheet 雨汚収入
R1: 集計表（全体）↓ | AV1: 雨水（税込） | AZ1: 汚水（税込） | BC1: 合計 （税込） | BD1: チェック | BF1: 雨水（税抜） | BJ1: 汚水（税抜） | BM1: 合計 （税抜） | BN1: 税抜き 要調整額 | BO1: 3条収入ｼｰﾄ集計値
Y2: 執行額 | AV2: 区域内 | AW2: 区域外 | AX2: 一般行政 | AY2: 計 | AZ2: 基準内 | BA2: 基準外 | BB2: 計 | BF2: 区域内 | BG2: 区域外 | BH2: 一般行政 | BI2: 計 | BJ2: 基準内 | BK2: 基準外 | BL2: 計
N3: 481121400 | O3: 下水道事業収益 | P3: 営業収益 | Q3: 受託工事収益 | R3: 受託工事収益 | Y3: =+SUMIFS(Y$69:Y$891,$N$69:$N$891,$N3) -> 0 | AV3: =+SUMIFS(AV$69:AV$894,$N$69:$N$894,$N3) -> 0 | AW3: =+SUMIFS(AW$69:AW$894,$N$69:$N$894,$N3) -> 0 | AX3: =+SUMIFS(AX$69:AX$894,$N$69:$N$894,$N3) -> 0 | AY3: =+SUMIFS(AY$69:AY$894,$N$69:$N$894,$N3) -> 0 | AZ3: =+SUMIFS(AZ$69:AZ$894,$N$69:$N$894,$N3) -> 0 | BA3: =+SUMIFS(BA$69:BA$894,$N$69:$N$894,$N3) -> 0 | BB3: =+SUMIFS(BB$69:BB$894,$N$69:$N$894,$N3) -> 0 | BC3: =+SUMIFS(BC$69:BC$894,$N$69:$N$894,$N3) -> 0 | BD3: =+SUMIFS(BD$69:BD$784,$N$69:$N$784,$N3) -> 0 | BF3: =+SUMIFS(BF$69:BF$891,$N$69:$N$891,$N3) -> 0 | BG3: =+SUMIFS(BG$69:BG$891,$N$69:$N$891,$N3) -> 0 | BH3: =+SUMIFS(BH$69:BH$891,$N$69:$N$891,$N3) -> 0 | BI3: =+SUMIFS(BI$69:BI$891,$N$69:$N$891,$N3) -> 0 | BJ3: =+SUMIFS(BJ$69:BJ$891,$N$69:$N$891,$N3) -> 0 | BK3: =+SUMIFS(BK$69:BK$891,$N$69:$N$891,$N3) -> 0 | BL3: =+SUMIFS(BL$69:BL$891,$N$69:$N$891,$N3) -> 0 | BM3: =+SUMIFS(BM$69:BM$894,$N$69:$N$894,$N3) -> 0 | BN3: =+BO3-BM3 -> 0 | BO3: =+SUMIFS('[2]3条収入'!$AI$6:$AI$70,'[2]3条収入'!$C$6:$C$70,雨汚収入!N3) -> 0
N4: 481141500 | O4: 下水道事業収益 | P4: 営業収益 | Q4: その他営業収益 | R4: 産物売却代金 | Y4: =+SUMIFS(Y$69:Y$891,$N$69:$N$891,$N4) -> 187826166 | AV4: =+SUMIFS(AV$69:AV$894,$N$69:$N$894,$N4) -> 0 | AW4: =+SUMIFS(AW$69:AW$894,$N$69:$N$894,$N4) -> 0 | AX4: =+SUMIFS(AX$69:AX$894,$N$69:$N$894,$N4) -> 37753060 | AY4: =+SUMIFS(AY$69:AY$894,$N$69:$N$894,$N4) -> 37753060 | AZ4: =+SUMIFS(AZ$69:AZ$894,$N$69:$N$894,$N4) -> 0 | BA4: =+SUMIFS(BA$69:BA$894,$N$69:$N$894,$N4) -> 150073106 | BB4: =+SUMIFS(BB$69:BB$894,$N$69:$N$894,$N4) -> 150073106 | BC4: =+SUMIFS(BC$69:BC$894,$N$69:$N$894,$N4) -> 187826166 | BD4: =+SUMIFS(BD$69:BD$784,$N$69:$N$784,$N4) -> 0 | BF4: =+SUMIFS(BF$69:BF$891,$N$69:$N$891,$N4) -> 0 | BG4: =+SUMIFS(BG$69:BG$891,$N$69:$N$891,$N4) -> 0 | BH4: =+SUMIFS(BH$69:BH$891,$N$69:$N$891,$N4) -> 34320964 | BI4: =+SUMIFS(BI$69:BI$891,$N$69:$N$891,$N4) -> 34320964 | BJ4: =+SUMIFS(BJ$69:BJ$891,$N$69:$N$891,$N4) -> 0 | BK4: =+SUMIFS(BK$69:BK$891,$N$69:$N$891,$N4) -> 136430096 | BL4: =+SUMIFS(BL$69:BL$891,$N$69:$N$891,$N4) -> 136430096 | BM4: =+SUMIFS(BM$69:BM$894,$N$69:$N$894,$N4) -> 170751060 | BN4: =+BO4-BM4 -> 0 | BO4: =+SUMIFS('[2]3条収入'!$AI$6:$AI$70,'[2]3条収入'!$C$6:$C$70,雨汚収入!N4) -> 170751060
N5: 481141700 | O5: 下水道事業収益 | P5: 営業収益 | Q5: その他営業収益 | R5: 業務受託収益 | Y5: =+SUMIFS(Y$69:Y$891,$N$69:$N$891,$N5) -> 1409733 | AV5: =+SUMIFS(AV$69:AV$894,$N$69:$N$894,$N5) -> 902422 | AW5: =+SUMIFS(AW$69:AW$894,$N$69:$N$894,$N5) -> 507311 | AX5: =+SUMIFS(AX$69:AX$894,$N$69:$N$894,$N5) -> 0 | AY5: =+SUMIFS(AY$69:AY$894,$N$69:$N$894,$N5) -> 1409733 | AZ5: =+SUMIFS(AZ$69:AZ$894,$N$69:$N$894,$N5) -> 0 | BA5: =+SUMIFS(BA$69:BA$894,$N$69:$N$894,$N5) -> 0 | BB5: =+SUMIFS(BB$69:BB$894,$N$69:$N$894,$N5) -> 0 | BC5: =+SUMIFS(BC$69:BC$894,$N$69:$N$894,$N5) -> 1409733 | BD5: =+SUMIFS(BD$69:BD$784,$N$69:$N$784,$N5) -> 0 | BF5: =+SUMIFS(BF$69:BF$891,$N$69:$N$891,$N5) -> 820384 | BG5: =+SUMIFS(BG$69:BG$891,$N$69:$N$891,$N5) -> 461192 | BH5: =+SUMIFS(BH$69:BH$891,$N$69:$N$891,$N5) -> 0 | BI5: =+SUMIFS(BI$69:BI$891,$N$69:$N$891,$N5) -> 1281576 | BJ5: =+SUMIFS(BJ$69:BJ$891,$N$69:$N$891,$N5) -> 0 | BK5: =+SUMIFS(BK$69:BK$891,$N$69:$N$891,$N5) -> 0 | BL5: =+SUMIFS(BL$69:BL$891,$N$69:$N$891,$N5) -> 0 | BM5: =+SUMIFS(BM$69:BM$894,$N$69:$N$894,$N5) -> 1281576 | BN5: =+BO5-BM5 -> 0 | BO5: =+SUMIFS('[2]3条収入'!$AI$6:$AI$70,'[2]3条収入'!$C$6:$C$70,雨汚収入!N5) -> 1281576
N6: 481141915 | O6: 下水道事業収益 | P6: 営業収益 | Q6: その他営業収益 | R6: 手数料 | S6: 証明手数料 | Y6: =+SUMIFS(Y$69:Y$891,$N$69:$N$891,$N6) -> 71970 | AV6: =+SUMIFS(AV$69:AV$894,$N$69:$N$894,$N6) -> 32943 | AW6: =+SUMIFS(AW$69:AW$894,$N$69:$N$894,$N6) -> 0 | AX6: =+SUMIFS(AX$69:AX$894,$N$69:$N$894,$N6) -> 0 | AY6: =+SUMIFS(AY$69:AY$894,$N$69:$N$894,$N6) -> 32943 | AZ6: =+SUMIFS(AZ$69:AZ$894,$N$69:$N$894,$N6) -> 0 | BA6: =+SUMIFS(BA$69:BA$894,$N$69:$N$894,$N6) -> 39027 | BB6: =+SUMIFS(BB$69:BB$894,$N$69:$N$894,$N6) -> 39027 | BC6: =+SUMIFS(BC$69:BC$894,$N$69:$N$894,$N6) -> 71970 | BD6: =+SUMIFS(BD$69:BD$784,$N$69:$N$784,$N6) -> 0 | BF6: =+SUMIFS(BF$69:BF$891,$N$69:$N$891,$N6) -> 32943 | BG6: =+SUMIFS(BG$69:BG$891,$N$69:$N$891,$N6) -> 0 | BH6: =+SUMIFS(BH$69:BH$891,$N$69:$N$891,$N6) -> 0 | BI6: =+SUMIFS(BI$69:BI$891,$N$69:$N$891,$N6) -> 32943 | BJ6: =+SUMIFS(BJ$69:BJ$891,$N$69:$N$891,$N6) -> 0 | BK6: =+SUMIFS(BK$69:BK$891,$N$69:$N$891,$N6) -> 39027 | BL6: =+SUMIFS(BL$69:BL$891,$N$69:$N$891,$N6) -> 39027 | BM6: =+SUMIFS(BM$69:BM$894,$N$69:$N$894,$N6) -> 71970 | BN6: =+BO6-BM6 -> 0 | BO6: =+SUMIFS('[2]3条収入'!$AI$6:$AI$70,'[2]3条収入'!$C$6:$C$70,雨汚収入!N6) -> 71970
N7: 481141916 | O7: 下水道事業収益 | P7: 営業収益 | Q7: その他営業収益 | R7: 手数料 | S7: 指定業者登録等手数料 | Y7: =+SUMIFS(Y$69:Y$891,$N$69:$N$891,$N7) -> 539000 | AV7: =+SUMIFS(AV$69:AV$894,$N$69:$N$894,$N7) -> 0 | AW7: =+SUMIFS(AW$69:AW$894,$N$69:$N$894,$N7) -> 0 | AX7: =+SUMIFS(AX$69:AX$894,$N$69:$N$894,$N7) -> 0 | AY7: =+SUMIFS(AY$69:AY$894,$N$69:$N$894,$N7) -> 0 | AZ7: =+SUMIFS(AZ$69:AZ$894,$N$69:$N$894,$N7) -> 269500 | BA7: =+SUMIFS(BA$69:BA$894,$N$69:$N$894,$N7) -> 269500 | BB7: =+SUMIFS(BB$69:BB$894,$N$69:$N$894,$N7) -> 539000 | BC7: =+SUMIFS(BC$69:BC$894,$N$69:$N$894,$N7) -> 539000 | BD7: =+SUMIFS(BD$69:BD$784,$N$69:$N$784,$N7) -> 0 | BF7: =+SUMIFS(BF$69:BF$891,$N$69:$N$891,$N7) -> 0 | BG7: =+SUMIFS(BG$69:BG$891,$N$69:$N$891,$N7) -> 0 | BH7: =+SUMIFS(BH$69:BH$891,$N$69:$N$891,$N7) -> 0 | BI7: =+SUMIFS(BI$69:BI$891,$N$69:$N$891,$N7) -> 0 | BJ7: =+SUMIFS(BJ$69:BJ$891,$N$69:$N$891,$N7) -> 269500 | BK7: =+SUMIFS(BK$69:BK$891,$N$69:$N$891,$N7) -> 269500 | BL7: =+SUMIFS(BL$69:BL$891,$N$69:$N$891,$N7) -> 539000 | BM7: =+SUMIFS(BM$69:BM$894,$N$69:$N$894,$N7) -> 539000 | BN7: =+BO7-BM7 -> 0 | BO7: =+SUMIFS('[2]3条収入'!$AI$6:$AI$70,'[2]3条収入'!$C$6:$C$70,雨汚収入!N7) -> 539000
N8: 481142000 | O8: 下水道事業収益 | P8: 営業外収益 | Q8: 雑収益 | Y8: =+SUMIFS(Y$69:Y$891,$N$69:$N$891,$N8) -> 0 | AV8: =+SUMIFS(AV$69:AV$894,$N$69:$N$894,$N8) -> 0 | AW8: =+SUMIFS(AW$69:AW$894,$N$69:$N$894,$N8) -> 0 | AX8: =+SUMIFS(AX$69:AX$894,$N$69:$N$894,$N8) -> 0 | AY8: =+SUMIFS(AY$69:AY$894,$N$69:$N$894,$N8) -> 0 | AZ8: =+SUMIFS(AZ$69:AZ$894,$N$69:$N$894,$N8) -> 0 | BA8: =+SUMIFS(BA$69:BA$894,$N$69:$N$894,$N8) -> 0 | BB8: =+SUMIFS(BB$69:BB$894,$N$69:$N$894,$N8) -> 0 | BC8: =+SUMIFS(BC$69:BC$894,$N$69:$N$894,$N8) -> 0 | BD8: =+SUMIFS(BD$69:BD$784,$N$69:$N$784,$N8) -> 0 | BF8: =+SUMIFS(BF$69:BF$891,$N$69:$N$891,$N8) -> 0 | BG8: =+SUMIFS(BG$69:BG$891,$N$69:$N$891,$N8) -> 0 | BH8: =+SUMIFS(BH$69:BH$891,$N$69:$N$891,$N8) -> 0 | BI8: =+SUMIFS(BI$69:BI$891,$N$69:$N$891,$N8) -> 0 | BJ8: =+SUMIFS(BJ$69:BJ$891,$N$69:$N$891,$N8) -> 0 | BK8: =+SUMIFS(BK$69:BK$891,$N$69:$N$891,$N8) -> 0 | BL8: =+SUMIFS(BL$69:BL$891,$N$69:$N$891,$N8) -> 0 | BM8: =+SUMIFS(BM$69:BM$894,$N$69:$N$894,$N8) -> 0 | BN8: =+BO8-BM8 -> 0 | BO8: =+SUMIFS('[2]3条収入'!$AI$6:$AI$70,'[2]3条収入'!$C$6:$C$70,雨汚収入!N8) -> 0
N9: 482022100 | O9: 下水道事業収益 | P9: 営業外収益 | Q9: 受取利息 | R9: 預金利息 | Y9: =+SUMIFS(Y$69:Y$891,$N$69:$N$891,$N9) -> 88770 | AV9: =+SUMIFS(AV$69:AV$894,$N$69:$N$894,$N9) -> 44385 | AW9: =+SUMIFS(AW$69:AW$894,$N$69:$N$894,$N9) -> 0 | AX9: =+SUMIFS(AX$69:AX$894,$N$69:$N$894,$N9) -> 0 | AY9: =+SUMIFS(AY$69:AY$894,$N$69:$N$894,$N9) -> 44385 | AZ9: =+SUMIFS(AZ$69:AZ$894,$N$69:$N$894,$N9) -> 0 | BA9: =+SUMIFS(BA$69:BA$894,$N$69:$N$894,$N9) -> 44385 | BB9: =+SUMIFS(BB$69:BB$894,$N$69:$N$894,$N9) -> 44385 | BC9: =+SUMIFS(BC$69:BC$894,$N$69:$N$894,$N9) -> 88770 | BD9: =+SUMIFS(BD$69:BD$784,$N$69:$N$784,$N9) -> 0 | BF9: =+SUMIFS(BF$69:BF$891,$N$69:$N$891,$N9) -> 44385 | BG9: =+SUMIFS(BG$69:BG$891,$N$69:$N$891,$N9) -> 0 | BH9: =+SUMIFS(BH$69:BH$891,$N$69:$N$891,$N9) -> 0 | BI9: =+SUMIFS(BI$69:BI$891,$N$69:$N$891,$N9) -> 44385 | BJ9: =+SUMIFS(BJ$69:BJ$891,$N$69:$N$891,$N9) -> 0 | BK9: =+SUMIFS(BK$69:BK$891,$N$69:$N$891,$N9) -> 44385 | BL9: =+SUMIFS(BL$69:BL$891,$N$69:$N$891,$N9) -> 44385 | BM9: =+SUMIFS(BM$69:BM$894,$N$69:$N$894,$N9) -> 88770 | BN9: =+BO9-BM9 -> 0 | BO9: =+SUMIFS('[2]3条収入'!$AI$6:$AI$70,'[2]3条収入'!$C$6:$C$70,雨汚収入!N9) -> 88770
N10: 482042900 | O10: 下水道事業収益 | P10: 営業外収益 | Q10: 国庫補助金 | R10: その他国庫補助金(災害) | Y10: =+SUMIFS(Y$69:Y$891,$N$69:$N$891,$N10) -> 0 | AV10: =+SUMIFS(AV$69:AV$894,$N$69:$N$894,$N10) -> 0 | AW10: =+SUMIFS(AW$69:AW$894,$N$69:$N$894,$N10) -> 0 | AX10: =+SUMIFS(AX$69:AX$894,$N$69:$N$894,$N10) -> 0 | AY10: =+SUMIFS(AY$69:AY$894,$N$69:$N$894,$N10) -> 0 | AZ10: =+SUMIFS(AZ$69:AZ$894,$N$69:$N$894,$N10) -> 0 | BA10: =+SUMIFS(BA$69:BA$894,$N$69:$N$894,$N10) -> 0 | BB10: =+SUMIFS(BB$69:BB$894,$N$69:$N$894,$N10) -> 0 | BC10: =+SUMIFS(BC$69:BC$894,$N$69:$N$894,$N10) -> 0 | BD10: =+SUMIFS(BD$69:BD$784,$N$69:$N$784,$N10) -> 0 | BF10: =+SUMIFS(BF$69:BF$891,$N$69:$N$891,$N10) -> 0 | BG10: =+SUMIFS(BG$69:BG$891,$N$69:$N$891,$N10) -> 0 | BH10: =+SUMIFS(BH$69:BH$891,$N$69:$N$891,$N10) -> 0 | BI10: =+SUMIFS(BI$69:BI$891,$N$69:$N$891,$N10) -> 0 | BJ10: =+SUMIFS(BJ$69:BJ$891,$N$69:$N$891,$N10) -> 0 | BK10: =+SUMIFS(BK$69:BK$891,$N$69:$N$891,$N10) -> 0 | BL10: =+SUMIFS(BL$69:BL$891,$N$69:$N$891,$N10) -> 0 | BM10: =+SUMIFS(BM$69:BM$894,$N$69:$N$894,$N10) -> 0 | BN10: =+BO10-BM10 -> 0 | BO10: =+SUMIFS('[2]3条収入'!$AI$6:$AI$70,'[2]3条収入'!$C$6:$C$70,雨汚収入!N10) -> 0
N11: 482093200 | O11: 下水道事業収益 | P11: 営業外収益 | Q11: 負担金 | R11: 施設管理負担金 | Y11: =+SUMIFS(Y$69:Y$891,$N$69:$N$891,$N11) -> 37016600 | AV11: =+SUMIFS(AV$69:AV$894,$N$69:$N$894,$N11) -> 36785219 | AW11: =+SUMIFS(AW$69:AW$894,$N$69:$N$894,$N11) -> 0 | AX11: =+SUMIFS(AX$69:AX$894,$N$69:$N$894,$N11) -> 0 | AY11: =+SUMIFS(AY$69:AY$894,$N$69:$N$894,$N11) -> 36785219 | AZ11: =+SUMIFS(AZ$69:AZ$894,$N$69:$N$894,$N11) -> 0 | BA11: =+SUMIFS(BA$69:BA$894,$N$69:$N$894,$N11) -> 231381 | BB11: =+SUMIFS(BB$69:BB$894,$N$69:$N$894,$N11) -> 231381 | BC11: =+SUMIFS(BC$69:BC$894,$N$69:$N$894,$N11) -> 37016600 | BD11: =+SUMIFS(BD$69:BD$784,$N$69:$N$784,$N11) -> 0 | BF11: =+SUMIFS(BF$69:BF$891,$N$69:$N$891,$N11) -> 33441108 | BG11: =+SUMIFS(BG$69:BG$891,$N$69:$N$891,$N11) -> 0 | BH11: =+SUMIFS(BH$69:BH$891,$N$69:$N$891,$N11) -> 0 | BI11: =+SUMIFS(BI$69:BI$891,$N$69:$N$891,$N11) -> 33441108 | BJ11: =+SUMIFS(BJ$69:BJ$891,$N$69:$N$891,$N11) -> 0 | BK11: =+SUMIFS(BK$69:BK$891,$N$69:$N$891,$N11) -> 210347 | BL11: =+SUMIFS(BL$69:BL$891,$N$69:$N$891,$N11) -> 210347 | BM11: =+SUMIFS(BM$69:BM$894,$N$69:$N$894,$N11) -> 33651455 | BN11: =+BO11-BM11 -> 0 | BO11: =+SUMIFS('[2]3条収入'!$AI$6:$AI$70,'[2]3条収入'!$C$6:$C$70,雨汚収入!N11) -> 33651455
N12: 482093300 | O12: 下水道事業収益 | P12: 営業外収益 | Q12: 負担金 | R12: 他会計負担金 | Y12: =+SUMIFS(Y$69:Y$891,$N$69:$N$891,$N12) -> 0 | AV12: =+SUMIFS(AV$69:AV$894,$N$69:$N$894,$N12) -> 0 | AW12: =+SUMIFS(AW$69:AW$894,$N$69:$N$894,$N12) -> 0 | AX12: =+SUMIFS(AX$69:AX$894,$N$69:$N$894,$N12) -> 0 | AY12: =+SUMIFS(AY$69:AY$894,$N$69:$N$894,$N12) -> 0 | AZ12: =+SUMIFS(AZ$69:AZ$894,$N$69:$N$894,$N12) -> 0 | BA12: =+SUMIFS(BA$69:BA$894,$N$69:$N$894,$N12) -> 0 | BB12: =+SUMIFS(BB$69:BB$894,$N$69:$N$894,$N12) -> 0 | BC12: =+SUMIFS(BC$69:BC$894,$N$69:$N$894,$N12) -> 0 | BD12: =+SUMIFS(BD$69:BD$784,$N$69:$N$784,$N12) -> 0 | BF12: =+SUMIFS(BF$69:BF$891,$N$69:$N$891,$N12) -> 0 | BG12: =+SUMIFS(BG$69:BG$891,$N$69:$N$891,$N12) -> 0 | BH12: =+SUMIFS(BH$69:BH$891,$N$69:$N$891,$N12) -> 0 | BI12: =+SUMIFS(BI$69:BI$891,$N$69:$N$891,$N12) -> 0 | BJ12: =+SUMIFS(BJ$69:BJ$891,$N$69:$N$891,$N12) -> 0 | BK12: =+SUMIFS(BK$69:BK$891,$N$69:$N$891,$N12) -> 0 | BL12: =+SUMIFS(BL$69:BL$891,$N$69:$N$891,$N12) -> 0 | BM12: =+SUMIFS(BM$69:BM$894,$N$69:$N$894,$N12) -> 0 | BN12: =+BO12-BM12 -> 16476593 | BO12: =+SUMIFS('[2]3条収入'!$AI$6:$AI$70,'[2]3条収入'!$C$6:$C$70,雨汚収入!N12) -> 16476593
N13: 482113700 | O13: 下水道事業収益 | P13: 営業外収益 | Q13: 消費税及び地方消費税還付金 | R13: 消費税及び地方消費税還付金 | Y13: =+SUMIFS(Y$69:Y$891,$N$69:$N$891,$N13) -> 0 | AV13: =+SUMIFS(AV$69:AV$894,$N$69:$N$894,$N13) -> 0 | AW13: =+SUMIFS(AW$69:AW$894,$N$69:$N$894,$N13) -> 0 | AX13: =+SUMIFS(AX$69:AX$894,$N$69:$N$894,$N13) -> 0 | AY13: =+SUMIFS(AY$69:AY$894,$N$69:$N$894,$N13) -> 0 | AZ13: =+SUMIFS(AZ$69:AZ$894,$N$69:$N$894,$N13) -> 0 | BA13: =+SUMIFS(BA$69:BA$894,$N$69:$N$894,$N13) -> 0 | BB13: =+SUMIFS(BB$69:BB$894,$N$69:$N$894,$N13) -> 0 | BC13: =+SUMIFS(BC$69:BC$894,$N$69:$N$894,$N13) -> 0 | BD13: =+SUMIFS(BD$69:BD$784,$N$69:$N$784,$N13) -> 0 | BF13: =+SUMIFS(BF$69:BF$891,$N$69:$N$891,$N13) -> 0 | BG13: =+SUMIFS(BG$69:BG$891,$N$69:$N$891,$N13) -> 0 | BH13: =+SUMIFS(BH$69:BH$891,$N$69:$N$891,$N13) -> 0 | BI13: =+SUMIFS(BI$69:BI$891,$N$69:$N$891,$N13) -> 0 | BJ13: =+SUMIFS(BJ$69:BJ$891,$N$69:$N$891,$N13) -> 0 | BK13: =+SUMIFS(BK$69:BK$891,$N$69:$N$891,$N13) -> 0 | BL13: =+SUMIFS(BL$69:BL$891,$N$69:$N$891,$N13) -> 0 | BM13: =+SUMIFS(BM$69:BM$894,$N$69:$N$894,$N13) -> 0 | BN13: =+BO13-BM13 -> 0 | BO13: =+SUMIFS('[2]3条収入'!$AI$6:$AI$70,'[2]3条収入'!$C$6:$C$70,雨汚収入!N13) -> 0
N14: 482123600 | O14: 下水道事業収益 | P14: 営業外収益 | Q14: 雑収益 | R14: 不用品売却収益 | Y14: =+SUMIFS(Y$69:Y$891,$N$69:$N$891,$N14) -> 408100 | AV14: =+SUMIFS(AV$69:AV$894,$N$69:$N$894,$N14) -> 0 | AW14: =+SUMIFS(AW$69:AW$894,$N$69:$N$894,$N14) -> 0 | AX14: =+SUMIFS(AX$69:AX$894,$N$69:$N$894,$N14) -> 408100 | AY14: =+SUMIFS(AY$69:AY$894,$N$69:$N$894,$N14) -> 408100 | AZ14: =+SUMIFS(AZ$69:AZ$894,$N$69:$N$894,$N14) -> 0 | BA14: =+SUMIFS(BA$69:BA$894,$N$69:$N$894,$N14) -> 0 | BB14: =+SUMIFS(BB$69:BB$894,$N$69:$N$894,$N14) -> 0 | BC14: =+SUMIFS(BC$69:BC$894,$N$69:$N$894,$N14) -> 408100 | BD14: =+SUMIFS(BD$69:BD$784,$N$69:$N$784,$N14) -> 0 | BF14: =+SUMIFS(BF$69:BF$891,$N$69:$N$891,$N14) -> 0 | BG14: =+SUMIFS(BG$69:BG$891,$N$69:$N$891,$N14) -> 0 | BH14: =+SUMIFS(BH$69:BH$891,$N$69:$N$891,$N14) -> 371000 | BI14: =+SUMIFS(BI$69:BI$891,$N$69:$N$891,$N14) -> 371000 | BJ14: =+SUMIFS(BJ$69:BJ$891,$N$69:$N$891,$N14) -> 0 | BK14: =+SUMIFS(BK$69:BK$891,$N$69:$N$891,$N14) -> 0 | BL14: =+SUMIFS(BL$69:BL$891,$N$69:$N$891,$N14) -> 0 | BM14: =+SUMIFS(BM$69:BM$894,$N$69:$N$894,$N14) -> 371000 | BN14: =+BO14-BM14 -> 0 | BO14: =+SUMIFS('[2]3条収入'!$AI$6:$AI$70,'[2]3条収入'!$C$6:$C$70,雨汚収入!N14) -> 371000
N15: 482124000 | O15: 下水道事業収益 | P15: 営業外収益 | Q15: 雑収益 | R15: その他雑収益 | Y15: =+SUMIFS(Y$69:Y$891,$N$69:$N$891,$N15) -> 36052234 | AV15: =+SUMIFS(AV$69:AV$894,$N$69:$N$894,$N15) -> 10360569 | AW15: =+SUMIFS(AW$69:AW$894,$N$69:$N$894,$N15) -> 0 | AX15: =+SUMIFS(AX$69:AX$894,$N$69:$N$894,$N15) -> 1399670 | AY15: =+SUMIFS(AY$69:AY$894,$N$69:$N$894,$N15) -> 11760239 | AZ15: =+SUMIFS(AZ$69:AZ$894,$N$69:$N$894,$N15) -> 0 | BA15: =+SUMIFS(BA$69:BA$894,$N$69:$N$894,$N15) -> 24291995 | BB15: =+SUMIFS(BB$69:BB$894,$N$69:$N$894,$N15) -> 24291995 | BC15: =+SUMIFS(BC$69:BC$894,$N$69:$N$894,$N15) -> 36052234 | BD15: =+SUMIFS(BD$69:BD$784,$N$69:$N$784,$N15) -> 0 | BF15: =+SUMIFS(BF$69:BF$891,$N$69:$N$891,$N15) -> 10155799 | BG15: =+SUMIFS(BG$69:BG$891,$N$69:$N$891,$N15) -> 0 | BH15: =+SUMIFS(BH$69:BH$891,$N$69:$N$891,$N15) -> 1397864 | BI15: =+SUMIFS(BI$69:BI$891,$N$69:$N$891,$N15) -> 11553663 | BJ15: =+SUMIFS(BJ$69:BJ$891,$N$69:$N$891,$N15) -> 0 | BK15: =+SUMIFS(BK$69:BK$891,$N$69:$N$891,$N15) -> 23325314 | BL15: =+SUMIFS(BL$69:BL$891,$N$69:$N$891,$N15) -> 23325314 | BM15: =+SUMIFS(BM$69:BM$894,$N$69:$N$894,$N15) -> 34878977 | BN15: =+BO15-BM15 -> 0 | BO15: =+SUMIFS('[2]3条収入'!$AI$6:$AI$70,'[2]3条収入'!$C$6:$C$70,雨汚収入!N15) -> 34878977
N16: 483020200 | O16: 下水道事業収益 | P16: 特別利益 | Q16: 固定資産売却益 | R16: 固定資産売却益 | Y16: =+SUMIFS(Y$69:Y$891,$N$69:$N$891,$N16) -> 0 | AV16: =+SUMIFS(AV$69:AV$894,$N$69:$N$894,$N16) -> 0 | AW16: =+SUMIFS(AW$69:AW$894,$N$69:$N$894,$N16) -> 0 | AX16: =+SUMIFS(AX$69:AX$894,$N$69:$N$894,$N16) -> 0 | AY16: =+SUMIFS(AY$69:AY$894,$N$69:$N$894,$N16) -> 0 | AZ16: =+SUMIFS(AZ$69:AZ$894,$N$69:$N$894,$N16) -> 0 | BA16: =+SUMIFS(BA$69:BA$894,$N$69:$N$894,$N16) -> 0 | BB16: =+SUMIFS(BB$69:BB$894,$N$69:$N$894,$N16) -> 0 | BC16: =+SUMIFS(BC$69:BC$894,$N$69:$N$894,$N16) -> 0 | BD16: =+SUMIFS(BD$69:BD$784,$N$69:$N$784,$N16) -> 0 | BF16: =+SUMIFS(BF$69:BF$891,$N$69:$N$891,$N16) -> 0 | BG16: =+SUMIFS(BG$69:BG$891,$N$69:$N$891,$N16) -> 0 | BH16: =+SUMIFS(BH$69:BH$891,$N$69:$N$891,$N16) -> 0 | BI16: =+SUMIFS(BI$69:BI$891,$N$69:$N$891,$N16) -> 0 | BJ16: =+SUMIFS(BJ$69:BJ$891,$N$69:$N$891,$N16) -> 0 | BK16: =+SUMIFS(BK$69:BK$891,$N$69:$N$891,$N16) -> 0 | BL16: =+SUMIFS(BL$69:BL$891,$N$69:$N$891,$N16) -> 0 | BM16: =+SUMIFS(BM$69:BM$894,$N$69:$N$894,$N16) -> 0 | BN16: =+BO16-BM16 -> 0 | BO16: =+SUMIFS('[2]3条収入'!$AI$6:$AI$70,'[2]3条収入'!$C$6:$C$70,雨汚収入!N16) -> 0
N17: 483040400 | O17: 下水道事業収益 | P17: 特別利益 | Q17: 過年度損益修正益 | R17: 過年度損益修正益 | Y17: =+SUMIFS(Y$69:Y$891,$N$69:$N$891,$N17) -> 2769570 | AV17: =+SUMIFS(AV$69:AV$894,$N$69:$N$894,$N17) -> 352162 | AW17: =+SUMIFS(AW$69:AW$894,$N$69:$N$894,$N17) -> 0 | AX17: =+SUMIFS(AX$69:AX$894,$N$69:$N$894,$N17) -> 487974 | AY17: =+SUMIFS(AY$69:AY$894,$N$69:$N$894,$N17) -> 840136 | AZ17: =+SUMIFS(AZ$69:AZ$894,$N$69:$N$894,$N17) -> 29260 | BA17: =+SUMIFS(BA$69:BA$894,$N$69:$N$894,$N17) -> 1900174 | BB17: =+SUMIFS(BB$69:BB$894,$N$69:$N$894,$N17) -> 1929434 | BC17: =+SUMIFS(BC$69:BC$894,$N$69:$N$894,$N17) -> 2769570 | BD17: =+SUMIFS(BD$69:BD$784,$N$69:$N$784,$N17) -> 0 | BF17: =+SUMIFS(BF$69:BF$891,$N$69:$N$891,$N17) -> 352162 | BG17: =+SUMIFS(BG$69:BG$891,$N$69:$N$891,$N17) -> 0 | BH17: =+SUMIFS(BH$69:BH$891,$N$69:$N$891,$N17) -> 487974 | BI17: =+SUMIFS(BI$69:BI$891,$N$69:$N$891,$N17) -> 840136 | BJ17: =+SUMIFS(BJ$69:BJ$891,$N$69:$N$891,$N17) -> 29260 | BK17: =+SUMIFS(BK$69:BK$891,$N$69:$N$891,$N17) -> 1754286 | BL17: =+SUMIFS(BL$69:BL$891,$N$69:$N$891,$N17) -> 1783546 | BM17: =+SUMIFS(BM$69:BM$894,$N$69:$N$894,$N17) -> 2623682 | BN17: =+BO17-BM17 -> 0 | BO17: =+SUMIFS('[2]3条収入'!$AI$6:$AI$70,'[2]3条収入'!$C$6:$C$70,雨汚収入!N17) -> 2623682
N18: 483060600 | O18: 下水道事業収益 | P18: 特別利益 | Q18: その他特別利益 | R18: その他特別利益 | Y18: =+SUMIFS(Y$69:Y$891,$N$69:$N$891,$N18) -> 864807 | AV18: =+SUMIFS(AV$69:AV$894,$N$69:$N$894,$N18) -> 588069 | AW18: =+SUMIFS(AW$69:AW$894,$N$69:$N$894,$N18) -> 0 | AX18: =+SUMIFS(AX$69:AX$894,$N$69:$N$894,$N18) -> 0 | AY18: =+SUMIFS(AY$69:AY$894,$N$69:$N$894,$N18) -> 588069 | AZ18: =+SUMIFS(AZ$69:AZ$894,$N$69:$N$894,$N18) -> 0 | BA18: =+SUMIFS(BA$69:BA$894,$N$69:$N$894,$N18) -> 276738 | BB18: =+SUMIFS(BB$69:BB$894,$N$69:$N$894,$N18) -> 276738 | BC18: =+SUMIFS(BC$69:BC$894,$N$69:$N$894,$N18) -> 864807 | BD18: =+SUMIFS(BD$69:BD$784,$N$69:$N$784,$N18) -> 0 | BF18: =+SUMIFS(BF$69:BF$891,$N$69:$N$891,$N18) -> 588069 | BG18: =+SUMIFS(BG$69:BG$891,$N$69:$N$891,$N18) -> 0 | BH18: =+SUMIFS(BH$69:BH$891,$N$69:$N$891,$N18) -> 0 | BI18: =+SUMIFS(BI$69:BI$891,$N$69:$N$891,$N18) -> 588069 | BJ18: =+SUMIFS(BJ$69:BJ$891,$N$69:$N$891,$N18) -> 0 | BK18: =+SUMIFS(BK$69:BK$891,$N$69:$N$891,$N18) -> 276738 | BL18: =+SUMIFS(BL$69:BL$891,$N$69:$N$891,$N18) -> 276738 | BM18: =+SUMIFS(BM$69:BM$894,$N$69:$N$894,$N18) -> 864807 | BN18: =+BO18-BM18 -> 0 | BO18: =+SUMIFS('[2]3条収入'!$AI$6:$AI$70,'[2]3条収入'!$C$6:$C$70,雨汚収入!N18) -> 864807
N19: 483060700 | O19: 下水道事業収益 | P19: 特別利益 | Q19: その他特別利益 | R19: 貸倒引当金戻入益 | Y19: =+SUMIFS(Y$69:Y$891,$N$69:$N$891,$N19) -> 455622 | AV19: =+SUMIFS(AV$69:AV$894,$N$69:$N$894,$N19) -> 0 | AW19: =+SUMIFS(AW$69:AW$894,$N$69:$N$894,$N19) -> 0 | AX19: =+SUMIFS(AX$69:AX$894,$N$69:$N$894,$N19) -> 16334 | AY19: =+SUMIFS(AY$69:AY$894,$N$69:$N$894,$N19) -> 16334 | AZ19: =+SUMIFS(AZ$69:AZ$894,$N$69:$N$894,$N19) -> 0 | BA19: =+SUMIFS(BA$69:BA$894,$N$69:$N$894,$N19) -> 439288 | BB19: =+SUMIFS(BB$69:BB$894,$N$69:$N$894,$N19) -> 439288 | BC19: =+SUMIFS(BC$69:BC$894,$N$69:$N$894,$N19) -> 455622 | BD19: =+SUMIFS(BD$69:BD$784,$N$69:$N$784,$N19) -> 0 | BF19: =+SUMIFS(BF$69:BF$891,$N$69:$N$891,$N19) -> 0 | BG19: =+SUMIFS(BG$69:BG$891,$N$69:$N$891,$N19) -> 0 | BH19: =+SUMIFS(BH$69:BH$891,$N$69:$N$891,$N19) -> 16334 | BI19: =+SUMIFS(BI$69:BI$891,$N$69:$N$891,$N19) -> 16334 | BJ19: =+SUMIFS(BJ$69:BJ$891,$N$69:$N$891,$N19) -> 0 | BK19: =+SUMIFS(BK$69:BK$891,$N$69:$N$891,$N19) -> 439288 | BL19: =+SUMIFS(BL$69:BL$891,$N$69:$N$891,$N19) -> 439288 | BM19: =+SUMIFS(BM$69:BM$894,$N$69:$N$894,$N19) -> 455622 | BN19: =+BO19-BM19 -> 0 | BO19: =+SUMIFS('[2]3条収入'!$AI$6:$AI$70,'[2]3条収入'!$C$6:$C$70,雨汚収入!N19) -> 455622
N20: 483060800 | O20: 下水道事業収益 | P20: 特別利益 | Q20: その他特別利益 | R20: 賞与引当金戻入益 | Y20: =+SUMIFS(Y$69:Y$891,$N$69:$N$891,$N20) -> 109000 | AV20: =+SUMIFS(AV$69:AV$894,$N$69:$N$894,$N20) -> 54500 | AW20: =+SUMIFS(AW$69:AW$894,$N$69:$N$894,$N20) -> 0 | AX20: =+SUMIFS(AX$69:AX$894,$N$69:$N$894,$N20) -> 0 | AY20: =+SUMIFS(AY$69:AY$894,$N$69:$N$894,$N20) -> 54500 | AZ20: =+SUMIFS(AZ$69:AZ$894,$N$69:$N$894,$N20) -> 0 | BA20: =+SUMIFS(BA$69:BA$894,$N$69:$N$894,$N20) -> 54500 | BB20: =+SUMIFS(BB$69:BB$894,$N$69:$N$894,$N20) -> 54500 | BC20: =+SUMIFS(BC$69:BC$894,$N$69:$N$894,$N20) -> 109000 | BD20: =+SUMIFS(BD$69:BD$784,$N$69:$N$784,$N20) -> 0 | BF20: =+SUMIFS(BF$69:BF$891,$N$69:$N$891,$N20) -> 54500 | BG20: =+SUMIFS(BG$69:BG$891,$N$69:$N$891,$N20) -> 0 | BH20: =+SUMIFS(BH$69:BH$891,$N$69:$N$891,$N20) -> 0 | BI20: =+SUMIFS(BI$69:BI$891,$N$69:$N$891,$N20) -> 54500 | BJ20: =+SUMIFS(BJ$69:BJ$891,$N$69:$N$891,$N20) -> 0 | BK20: =+SUMIFS(BK$69:BK$891,$N$69:$N$891,$N20) -> 54500 | BL20: =+SUMIFS(BL$69:BL$891,$N$69:$N$891,$N20) -> 54500 | BM20: =+SUMIFS(BM$69:BM$894,$N$69:$N$894,$N20) -> 109000 | BN20: =+BO20-BM20 -> 0 | BO20: =+SUMIFS('[2]3条収入'!$AI$6:$AI$70,'[2]3条収入'!$C$6:$C$70,雨汚収入!N20) -> 109000
R23: 集計表（うち、不課税分）↓ | AV23: 雨水（税込） | AZ23: 汚水（税込） | BC23: 合計 （税込） | BD23: チェック | BF23: 雨水（税抜） | BJ23: 汚水（税抜） | BM23: 合計 （税抜） | BN23: 税抜き 要調整額 | BO23: 3条収入ｼｰﾄ集計値
AV24: 区域内 | AW24: 区域外 | AX24: 一般行政 | AY24: 計 | AZ24: 基準内 | BA24: 基準外 | BB24: 計 | BF24: 区域内 | BG24: 区域外 | BH24: 一般行政 | BI24: 計 | BJ24: 基準内 | BK24: 基準外 | BL24: 計
N25: 481121400 | O25: 下水道事業収益 | P25: 営業収益 | Q25: 受託工事収益 | R25: 受託工事収益 | Y25: =+SUMIFS(Y$69:Y$891,$N$69:$N$891,$N25,$AS$69:$AS$891,31) -> 0 | AV25: =+SUMIFS(AV$69:AV$894,$N$69:$N$894,$N25,$AS$69:$AS$894,31) -> 0 | AW25: =+SUMIFS(AW$69:AW$894,$N$69:$N$894,$N25,$AS$69:$AS$894,31) -> 0 | AX25: =+SUMIFS(AX$69:AX$894,$N$69:$N$894,$N25,$AS$69:$AS$894,31) -> 0 | AY25: =+SUMIFS(AY$69:AY$894,$N$69:$N$894,$N25,$AS$69:$AS$894,31) -> 0 | AZ25: =+SUMIFS(AZ$69:AZ$894,$N$69:$N$894,$N25,$AS$69:$AS$894,31) -> 0 | BA25: =+SUMIFS(BA$69:BA$894,$N$69:$N$894,$N25,$AS$69:$AS$894,31) -> 0 | BB25: =+SUMIFS(BB$69:BB$894,$N$69:$N$894,$N25,$AS$69:$AS$894,31) -> 0 | BC25: =+SUMIFS(BC$69:BC$894,$N$69:$N$894,$N25,$AS$69:$AS$894,31) -> 0 | BD25: =+SUMIFS(BD$69:BD$784,$N$69:$N$784,$N25,$AS$69:$AS$784,31) -> 0 | BE25: =+SUMIFS(BE$69:BE$784,$N$69:$N$784,$N25,$AS$69:$AS$784,31) -> 0 | BF25: =+SUMIFS(BF$69:BF$891,$N$69:$N$891,$N25,$AS$69:$AS$891,31) -> 0 | BG25: =+SUMIFS(BG$69:BG$891,$N$69:$N$891,$N25,$AS$69:$AS$891,31) -> 0 | BH25: =+SUMIFS(BH$69:BH$891,$N$69:$N$891,$N25,$AS$69:$AS$891,31) -> 0 | BI25: =+SUMIFS(BI$69:BI$891,$N$69:$N$891,$N25,$AS$69:$AS$891,31) -> 0 | BJ25: =+SUMIFS(BJ$69:BJ$891,$N$69:$N$891,$N25,$AS$69:$AS$891,31) -> 0 | BK25: =+SUMIFS(BK$69:BK$891,$N$69:$N$891,$N25,$AS$69:$AS$891,31) -> 0 | BL25: =+SUMIFS(BL$69:BL$891,$N$69:$N$891,$N25,$AS$69:$AS$891,31) -> 0 | BM25: =+SUMIFS(BM$69:BM$894,$N$69:$N$894,$N25,$AS$69:$AS$894,31) -> 0 | BN25: =+SUMIFS(BN$69:BN$784,$N$69:$N$784,$N25,$AS$69:$AS$784,31) -> 0
N26: 481141500 | O26: 下水道事業収益 | P26: 営業収益 | Q26: その他営業収益 | R26: 産物売却代金 | Y26: =+SUMIFS(Y$69:Y$891,$N$69:$N$891,$N26,$AS$69:$AS$891,31) -> 0 | AV26: =+SUMIFS(AV$69:AV$894,$N$69:$N$894,$N26,$AS$69:$AS$894,31) -> 0 | AW26: =+SUMIFS(AW$69:AW$894,$N$69:$N$894,$N26,$AS$69:$AS$894,31) -> 0 | AX26: =+SUMIFS(AX$69:AX$894,$N$69:$N$894,$N26,$AS$69:$AS$894,31) -> 0 | AY26: =+SUMIFS(AY$69:AY$894,$N$69:$N$894,$N26,$AS$69:$AS$894,31) -> 0 | AZ26: =+SUMIFS(AZ$69:AZ$894,$N$69:$N$894,$N26,$AS$69:$AS$894,31) -> 0 | BA26: =+SUMIFS(BA$69:BA$894,$N$69:$N$894,$N26,$AS$69:$AS$894,31) -> 0 | BB26: =+SUMIFS(BB$69:BB$894,$N$69:$N$894,$N26,$AS$69:$AS$894,31) -> 0 | BC26: =+SUMIFS(BC$69:BC$894,$N$69:$N$894,$N26,$AS$69:$AS$894,31) -> 0 | BD26: =+SUMIFS(BD$69:BD$784,$N$69:$N$784,$N26,$AS$69:$AS$784,31) -> 0 | BE26: =+SUMIFS(BE$69:BE$784,$N$69:$N$784,$N26,$AS$69:$AS$784,31) -> 0 | BF26: =+SUMIFS(BF$69:BF$891,$N$69:$N$891,$N26,$AS$69:$AS$891,31) -> 0 | BG26: =+SUMIFS(BG$69:BG$891,$N$69:$N$891,$N26,$AS$69:$AS$891,31) -> 0 | BH26: =+SUMIFS(BH$69:BH$891,$N$69:$N$891,$N26,$AS$69:$AS$891,31) -> 0 | BI26: =+SUMIFS(BI$69:BI$891,$N$69:$N$891,$N26,$AS$69:$AS$891,31) -> 0 | BJ26: =+SUMIFS(BJ$69:BJ$891,$N$69:$N$891,$N26,$AS$69:$AS$891,31) -> 0 | BK26: =+SUMIFS(BK$69:BK$891,$N$69:$N$891,$N26,$AS$69:$AS$891,31) -> 0 | BL26: =+SUMIFS(BL$69:BL$891,$N$69:$N$891,$N26,$AS$69:$AS$891,31) -> 0 | BM26: =+SUMIFS(BM$69:BM$894,$N$69:$N$894,$N26,$AS$69:$AS$894,31) -> 0 | BN26: =+SUMIFS(BN$69:BN$784,$N$69:$N$784,$N26,$AS$69:$AS$784,31) -> 0
N27: 481141700 | O27: 下水道事業収益 | P27: 営業収益 | Q27: その他営業収益 | R27: 業務受託収益 | Y27: =+SUMIFS(Y$69:Y$891,$N$69:$N$891,$N27,$AS$69:$AS$891,31) -> 0 | AV27: =+SUMIFS(AV$69:AV$894,$N$69:$N$894,$N27,$AS$69:$AS$894,31) -> 0 | AW27: =+SUMIFS(AW$69:AW$894,$N$69:$N$894,$N27,$AS$69:$AS$894,31) -> 0 | AX27: =+SUMIFS(AX$69:AX$894,$N$69:$N$894,$N27,$AS$69:$AS$894,31) -> 0 | AY27: =+SUMIFS(AY$69:AY$894,$N$69:$N$894,$N27,$AS$69:$AS$894,31) -> 0 | AZ27: =+SUMIFS(AZ$69:AZ$894,$N$69:$N$894,$N27,$AS$69:$AS$894,31) -> 0 | BA27: =+SUMIFS(BA$69:BA$894,$N$69:$N$894,$N27,$AS$69:$AS$894,31) -> 0 | BB27: =+SUMIFS(BB$69:BB$894,$N$69:$N$894,$N27,$AS$69:$AS$894,31) -> 0 | BC27: =+SUMIFS(BC$69:BC$894,$N$69:$N$894,$N27,$AS$69:$AS$894,31) -> 0 | BD27: =+SUMIFS(BD$69:BD$784,$N$69:$N$784,$N27,$AS$69:$AS$784,31) -> 0 | BE27: =+SUMIFS(BE$69:BE$784,$N$69:$N$784,$N27,$AS$69:$AS$784,31) -> 0 | BF27: =+SUMIFS(BF$69:BF$891,$N$69:$N$891,$N27,$AS$69:$AS$891,31) -> 0 | BG27: =+SUMIFS(BG$69:BG$891,$N$69:$N$891,$N27,$AS$69:$AS$891,31) -> 0 | BH27: =+SUMIFS(BH$69:BH$891,$N$69:$N$891,$N27,$AS$69:$AS$891,31) -> 0 | BI27: =+SUMIFS(BI$69:BI$891,$N$69:$N$891,$N27,$AS$69:$AS$891,31) -> 0 | BJ27: =+SUMIFS(BJ$69:BJ$891,$N$69:$N$891,$N27,$AS$69:$AS$891,31) -> 0 | BK27: =+SUMIFS(BK$69:BK$891,$N$69:$N$891,$N27,$AS$69:$AS$891,31) -> 0 | BL27: =+SUMIFS(BL$69:BL$891,$N$69:$N$891,$N27,$AS$69:$AS$891,31) -> 0 | BM27: =+SUMIFS(BM$69:BM$894,$N$69:$N$894,$N27,$AS$69:$AS$894,31) -> 0 | BN27: =+SUMIFS(BN$69:BN$784,$N$69:$N$784,$N27,$AS$69:$AS$784,31) -> 0
N28: 481141915 | O28: 下水道事業収益 | P28: 営業収益 | Q28: その他営業収益 | R28: 手数料 | S28: 証明手数料 | Y28: =+SUMIFS(Y$69:Y$891,$N$69:$N$891,$N28,$AS$69:$AS$891,31) -> 0 | AV28: =+SUMIFS(AV$69:AV$894,$N$69:$N$894,$N28,$AS$69:$AS$894,31) -> 0 | AW28: =+SUMIFS(AW$69:AW$894,$N$69:$N$894,$N28,$AS$69:$AS$894,31) -> 0 | AX28: =+SUMIFS(AX$69:AX$894,$N$69:$N$894,$N28,$AS$69:$AS$894,31) -> 0 | AY28: =+SUMIFS(AY$69:AY$894,$N$69:$N$894,$N28,$AS$69:$AS$894,31) -> 0 | AZ28: =+SUMIFS(AZ$69:AZ$894,$N$69:$N$894,$N28,$AS$69:$AS$894,31) -> 0 | BA28: =+SUMIFS(BA$69:BA$894,$N$69:$N$894,$N28,$AS$69:$AS$894,31) -> 0 | BB28: =+SUMIFS(BB$69:BB$894,$N$69:$N$894,$N28,$AS$69:$AS$894,31) -> 0 | BC28: =+SUMIFS(BC$69:BC$894,$N$69:$N$894,$N28,$AS$69:$AS$894,31) -> 0 | BD28: =+SUMIFS(BD$69:BD$784,$N$69:$N$784,$N28,$AS$69:$AS$784,31) -> 0 | BE28: =+SUMIFS(BE$69:BE$784,$N$69:$N$784,$N28,$AS$69:$AS$784,31) -> 0 | BF28: =+SUMIFS(BF$69:BF$891,$N$69:$N$891,$N28,$AS$69:$AS$891,31) -> 0 | BG28: =+SUMIFS(BG$69:BG$891,$N$69:$N$891,$N28,$AS$69:$AS$891,31) -> 0 | BH28: =+SUMIFS(BH$69:BH$891,$N$69:$N$891,$N28,$AS$69:$AS$891,31) -> 0 | BI28: =+SUMIFS(BI$69:BI$891,$N$69:$N$891,$N28,$AS$69:$AS$891,31) -> 0 | BJ28: =+SUMIFS(BJ$69:BJ$891,$N$69:$N$891,$N28,$AS$69:$AS$891,31) -> 0 | BK28: =+SUMIFS(BK$69:BK$891,$N$69:$N$891,$N28,$AS$69:$AS$891,31) -> 0 | BL28: =+SUMIFS(BL$69:BL$891,$N$69:$N$891,$N28,$AS$69:$AS$891,31) -> 0 | BM28: =+SUMIFS(BM$69:BM$894,$N$69:$N$894,$N28,$AS$69:$AS$894,31) -> 0 | BN28: =+SUMIFS(BN$69:BN$784,$N$69:$N$784,$N28,$AS$69:$AS$784,31) -> 0
N29: 481141916 | O29: 下水道事業収益 | P29: 営業収益 | Q29: その他営業収益 | R29: 手数料 | S29: 指定業者登録等手数料 | Y29: =+SUMIFS(Y$69:Y$891,$N$69:$N$891,$N29,$AS$69:$AS$891,31) -> 0 | AV29: =+SUMIFS(AV$69:AV$894,$N$69:$N$894,$N29,$AS$69:$AS$894,31) -> 0 | AW29: =+SUMIFS(AW$69:AW$894,$N$69:$N$894,$N29,$AS$69:$AS$894,31) -> 0 | AX29: =+SUMIFS(AX$69:AX$894,$N$69:$N$894,$N29,$AS$69:$AS$894,31) -> 0 | AY29: =+SUMIFS(AY$69:AY$894,$N$69:$N$894,$N29,$AS$69:$AS$894,31) -> 0 | AZ29: =+SUMIFS(AZ$69:AZ$894,$N$69:$N$894,$N29,$AS$69:$AS$894,31) -> 0 | BA29: =+SUMIFS(BA$69:BA$894,$N$69:$N$894,$N29,$AS$69:$AS$894,31) -> 0 | BB29: =+SUMIFS(BB$69:BB$894,$N$69:$N$894,$N29,$AS$69:$AS$894,31) -> 0 | BC29: =+SUMIFS(BC$69:BC$894,$N$69:$N$894,$N29,$AS$69:$AS$894,31) -> 0 | BD29: =+SUMIFS(BD$69:BD$784,$N$69:$N$784,$N29,$AS$69:$AS$784,31) -> 0 | BE29: =+SUMIFS(BE$69:BE$784,$N$69:$N$784,$N29,$AS$69:$AS$784,31) -> 0 | BF29: =+SUMIFS(BF$69:BF$891,$N$69:$N$891,$N29,$AS$69:$AS$891,31) -> 0 | BG29: =+SUMIFS(BG$69:BG$891,$N$69:$N$891,$N29,$AS$69:$AS$891,31) -> 0 | BH29: =+SUMIFS(BH$69:BH$891,$N$69:$N$891,$N29,$AS$69:$AS$891,31) -> 0 | BI29: =+SUMIFS(BI$69:BI$891,$N$69:$N$891,$N29,$AS$69:$AS$891,31) -> 0 | BJ29: =+SUMIFS(BJ$69:BJ$891,$N$69:$N$891,$N29,$AS$69:$AS$891,31) -> 0 | BK29: =+SUMIFS(BK$69:BK$891,$N$69:$N$891,$N29,$AS$69:$AS$891,31) -> 0 | BL29: =+SUMIFS(BL$69:BL$891,$N$69:$N$891,$N29,$AS$69:$AS$891,31) -> 0 | BM29: =+SUMIFS(BM$69:BM$894,$N$69:$N$894,$N29,$AS$69:$AS$894,31) -> 0 | BN29: =+SUMIFS(BN$69:BN$784,$N$69:$N$784,$N29,$AS$69:$AS$784,31) -> 0
N30: 481142000 | O30: 下水道事業収益 | P30: 営業外収益 | Q30: 雑収益 | Y30: =+SUMIFS(Y$69:Y$891,$N$69:$N$891,$N30,$AS$69:$AS$891,31) -> 0 | AV30: =+SUMIFS(AV$69:AV$894,$N$69:$N$894,$N30,$AS$69:$AS$894,31) -> 0 | AW30: =+SUMIFS(AW$69:AW$894,$N$69:$N$894,$N30,$AS$69:$AS$894,31) -> 0 | AX30: =+SUMIFS(AX$69:AX$894,$N$69:$N$894,$N30,$AS$69:$AS$894,31) -> 0 | AY30: =+SUMIFS(AY$69:AY$894,$N$69:$N$894,$N30,$AS$69:$AS$894,31) -> 0 | AZ30: =+SUMIFS(AZ$69:AZ$894,$N$69:$N$894,$N30,$AS$69:$AS$894,31) -> 0 | BA30: =+SUMIFS(BA$69:BA$894,$N$69:$N$894,$N30,$AS$69:$AS$894,31) -> 0 | BB30: =+SUMIFS(BB$69:BB$894,$N$69:$N$894,$N30,$AS$69:$AS$894,31) -> 0 | BC30: =+SUMIFS(BC$69:BC$894,$N$69:$N$894,$N30,$AS$69:$AS$894,31) -> 0 | BD30: =+SUMIFS(BD$69:BD$784,$N$69:$N$784,$N30,$AS$69:$AS$784,31) -> 0 | BE30: =+SUMIFS(BE$69:BE$784,$N$69:$N$784,$N30,$AS$69:$AS$784,31) -> 0 | BF30: =+SUMIFS(BF$69:BF$891,$N$69:$N$891,$N30,$AS$69:$AS$891,31) -> 0 | BG30: =+SUMIFS(BG$69:BG$891,$N$69:$N$891,$N30,$AS$69:$AS$891,31) -> 0 | BH30: =+SUMIFS(BH$69:BH$891,$N$69:$N$891,$N30,$AS$69:$AS$891,31) -> 0 | BI30: =+SUMIFS(BI$69:BI$891,$N$69:$N$891,$N30,$AS$69:$AS$891,31) -> 0 | BJ30: =+SUMIFS(BJ$69:BJ$891,$N$69:$N$891,$N30,$AS$69:$AS$891,31) -> 0 | BK30: =+SUMIFS(BK$69:BK$891,$N$69:$N$891,$N30,$AS$69:$AS$891,31) -> 0 | BL30: =+SUMIFS(BL$69:BL$891,$N$69:$N$891,$N30,$AS$69:$AS$891,31) -> 0 | BM30: =+SUMIFS(BM$69:BM$894,$N$69:$N$894,$N30,$AS$69:$AS$894,31) -> 0 | BN30: =+SUMIFS(BN$69:BN$784,$N$69:$N$784,$N30,$AS$69:$AS$784,31) -> 0
N31: 482022100 | O31: 下水道事業収益 | P31: 営業外収益 | Q31: 受取利息 | R31: 預金利息 | Y31: =+SUMIFS(Y$69:Y$891,$N$69:$N$891,$N31,$AS$69:$AS$891,31) -> 0 | AV31: =+SUMIFS(AV$69:AV$894,$N$69:$N$894,$N31,$AS$69:$AS$894,31) -> 0 | AW31: =+SUMIFS(AW$69:AW$894,$N$69:$N$894,$N31,$AS$69:$AS$894,31) -> 0 | AX31: =+SUMIFS(AX$69:AX$894,$N$69:$N$894,$N31,$AS$69:$AS$894,31) -> 0 | AY31: =+SUMIFS(AY$69:AY$894,$N$69:$N$894,$N31,$AS$69:$AS$894,31) -> 0 | AZ31: =+SUMIFS(AZ$69:AZ$894,$N$69:$N$894,$N31,$AS$69:$AS$894,31) -> 0 | BA31: =+SUMIFS(BA$69:BA$894,$N$69:$N$894,$N31,$AS$69:$AS$894,31) -> 0 | BB31: =+SUMIFS(BB$69:BB$894,$N$69:$N$894,$N31,$AS$69:$AS$894,31) -> 0 | BC31: =+SUMIFS(BC$69:BC$894,$N$69:$N$894,$N31,$AS$69:$AS$894,31) -> 0 | BD31: =+SUMIFS(BD$69:BD$784,$N$69:$N$784,$N31,$AS$69:$AS$784,31) -> 0 | BE31: =+SUMIFS(BE$69:BE$784,$N$69:$N$784,$N31,$AS$69:$AS$784,31) -> 0 | BF31: =+SUMIFS(BF$69:BF$891,$N$69:$N$891,$N31,$AS$69:$AS$891,31) -> 0 | BG31: =+SUMIFS(BG$69:BG$891,$N$69:$N$891,$N31,$AS$69:$AS$891,31) -> 0 | BH31: =+SUMIFS(BH$69:BH$891,$N$69:$N$891,$N31,$AS$69:$AS$891,31) -> 0 | BI31: =+SUMIFS(BI$69:BI$891,$N$69:$N$891,$N31,$AS$69:$AS$891,31) -> 0 | BJ31: =+SUMIFS(BJ$69:BJ$891,$N$69:$N$891,$N31,$AS$69:$AS$891,31) -> 0 | BK31: =+SUMIFS(BK$69:BK$891,$N$69:$N$891,$N31,$AS$69:$AS$891,31) -> 0 | BL31: =+SUMIFS(BL$69:BL$891,$N$69:$N$891,$N31,$AS$69:$AS$891,31) -> 0 | BM31: =+SUMIFS(BM$69:BM$894,$N$69:$N$894,$N31,$AS$69:$AS$894,31) -> 0 | BN31: =+SUMIFS(BN$69:BN$784,$N$69:$N$784,$N31,$AS$69:$AS$784,31) -> 0
N32: 482042900 | O32: 下水道事業収益 | P32: 営業外収益 | Q32: 国庫補助金 | R32: その他国庫補助金(災害) | Y32: =+SUMIFS(Y$69:Y$891,$N$69:$N$891,$N32,$AS$69:$AS$891,31) -> 0 | AV32: =+SUMIFS(AV$69:AV$894,$N$69:$N$894,$N32,$AS$69:$AS$894,31) -> 0 | AW32: =+SUMIFS(AW$69:AW$894,$N$69:$N$894,$N32,$AS$69:$AS$894,31) -> 0 | AX32: =+SUMIFS(AX$69:AX$894,$N$69:$N$894,$N32,$AS$69:$AS$894,31) -> 0 | AY32: =+SUMIFS(AY$69:AY$894,$N$69:$N$894,$N32,$AS$69:$AS$894,31) -> 0 | AZ32: =+SUMIFS(AZ$69:AZ$894,$N$69:$N$894,$N32,$AS$69:$AS$894,31) -> 0 | BA32: =+SUMIFS(BA$69:BA$894,$N$69:$N$894,$N32,$AS$69:$AS$894,31) -> 0 | BB32: =+SUMIFS(BB$69:BB$894,$N$69:$N$894,$N32,$AS$69:$AS$894,31) -> 0 | BC32: =+SUMIFS(BC$69:BC$894,$N$69:$N$894,$N32,$AS$69:$AS$894,31) -> 0 | BD32: =+SUMIFS(BD$69:BD$784,$N$69:$N$784,$N32,$AS$69:$AS$784,31) -> 0 | BE32: =+SUMIFS(BE$69:BE$784,$N$69:$N$784,$N32,$AS$69:$AS$784,31) -> 0 | BF32: =+SUMIFS(BF$69:BF$891,$N$69:$N$891,$N32,$AS$69:$AS$891,31) -> 0 | BG32: =+SUMIFS(BG$69:BG$891,$N$69:$N$891,$N32,$AS$69:$AS$891,31) -> 0 | BH32: =+SUMIFS(BH$69:BH$891,$N$69:$N$891,$N32,$AS$69:$AS$891,31) -> 0 | BI32: =+SUMIFS(BI$69:BI$891,$N$69:$N$891,$N32,$AS$69:$AS$891,31) -> 0 | BJ32: =+SUMIFS(BJ$69:BJ$891,$N$69:$N$891,$N32,$AS$69:$AS$891,31) -> 0 | BK32: =+SUMIFS(BK$69:BK$891,$N$69:$N$891,$N32,$AS$69:$AS$891,31) -> 0 | BL32: =+SUMIFS(BL$69:BL$891,$N$69:$N$891,$N32,$AS$69:$AS$891,31) -> 0 | BM32: =+SUMIFS(BM$69:BM$894,$N$69:$N$894,$N32,$AS$69:$AS$894,31) -> 0 | BN32: =+SUMIFS(BN$69:BN$784,$N$69:$N$784,$N32,$AS$69:$AS$784,31) -> 0
N33: 482093200 | O33: 下水道事業収益 | P33: 営業外収益 | Q33: 負担金 | R33: 施設管理負担金 | Y33: =+SUMIFS(Y$69:Y$891,$N$69:$N$891,$N33,$AS$69:$AS$891,31) -> 0 | AV33: =+SUMIFS(AV$69:AV$894,$N$69:$N$894,$N33,$AS$69:$AS$894,31) -> 0 | AW33: =+SUMIFS(AW$69:AW$894,$N$69:$N$894,$N33,$AS$69:$AS$894,31) -> 0 | AX33: =+SUMIFS(AX$69:AX$894,$N$69:$N$894,$N33,$AS$69:$AS$894,31) -> 0 | AY33: =+SUMIFS(AY$69:AY$894,$N$69:$N$894,$N33,$AS$69:$AS$894,31) -> 0 | AZ33: =+SUMIFS(AZ$69:AZ$894,$N$69:$N$894,$N33,$AS$69:$AS$894,31) -> 0 | BA33: =+SUMIFS(BA$69:BA$894,$N$69:$N$894,$N33,$AS$69:$AS$894,31) -> 0 | BB33: =+SUMIFS(BB$69:BB$894,$N$69:$N$894,$N33,$AS$69:$AS$894,31) -> 0 | BC33: =+SUMIFS(BC$69:BC$894,$N$69:$N$894,$N33,$AS$69:$AS$894,31) -> 0 | BD33: =+SUMIFS(BD$69:BD$784,$N$69:$N$784,$N33,$AS$69:$AS$784,31) -> 0 | BE33: =+SUMIFS(BE$69:BE$784,$N$69:$N$784,$N33,$AS$69:$AS$784,31) -> 0 | BF33: =+SUMIFS(BF$69:BF$891,$N$69:$N$891,$N33,$AS$69:$AS$891,31) -> 0 | BG33: =+SUMIFS(BG$69:BG$891,$N$69:$N$891,$N33,$AS$69:$AS$891,31) -> 0 | BH33: =+SUMIFS(BH$69:BH$891,$N$69:$N$891,$N33,$AS$69:$AS$891,31) -> 0 | BI33: =+SUMIFS(BI$69:BI$891,$N$69:$N$891,$N33,$AS$69:$AS$891,31) -> 0 | BJ33: =+SUMIFS(BJ$69:BJ$891,$N$69:$N$891,$N33,$AS$69:$AS$891,31) -> 0 | BK33: =+SUMIFS(BK$69:BK$891,$N$69:$N$891,$N33,$AS$69:$AS$891,31) -> 0 | BL33: =+SUMIFS(BL$69:BL$891,$N$69:$N$891,$N33,$AS$69:$AS$891,31) -> 0 | BM33: =+SUMIFS(BM$69:BM$894,$N$69:$N$894,$N33,$AS$69:$AS$894,31) -> 0 | BN33: =+SUMIFS(BN$69:BN$784,$N$69:$N$784,$N33,$AS$69:$AS$784,31) -> 0
N34: 482093300 | O34: 下水道事業収益 | P34: 営業外収益 | Q34: 負担金 | R34: 他会計負担金 | Y34: =+SUMIFS(Y$69:Y$891,$N$69:$N$891,$N34,$AS$69:$AS$891,31) -> 0 | AV34: =+SUMIFS(AV$69:AV$894,$N$69:$N$894,$N34,$AS$69:$AS$894,31) -> 0 | AW34: =+SUMIFS(AW$69:AW$894,$N$69:$N$894,$N34,$AS$69:$AS$894,31) -> 0 | AX34: =+SUMIFS(AX$69:AX$894,$N$69:$N$894,$N34,$AS$69:$AS$894,31) -> 0 | AY34: =+SUMIFS(AY$69:AY$894,$N$69:$N$894,$N34,$AS$69:$AS$894,31) -> 0 | AZ34: =+SUMIFS(AZ$69:AZ$894,$N$69:$N$894,$N34,$AS$69:$AS$894,31) -> 0 | BA34: =+SUMIFS(BA$69:BA$894,$N$69:$N$894,$N34,$AS$69:$AS$894,31) -> 0 | BB34: =+SUMIFS(BB$69:BB$894,$N$69:$N$894,$N34,$AS$69:$AS$894,31) -> 0 | BC34: =+SUMIFS(BC$69:BC$894,$N$69:$N$894,$N34,$AS$69:$AS$894,31) -> 0 | BD34: =+SUMIFS(BD$69:BD$784,$N$69:$N$784,$N34,$AS$69:$AS$784,31) -> 0 | BE34: =+SUMIFS(BE$69:BE$784,$N$69:$N$784,$N34,$AS$69:$AS$784,31) -> 0 | BF34: =+SUMIFS(BF$69:BF$891,$N$69:$N$891,$N34,$AS$69:$AS$891,31) -> 0 | BG34: =+SUMIFS(BG$69:BG$891,$N$69:$N$891,$N34,$AS$69:$AS$891,31) -> 0 | BH34: =+SUMIFS(BH$69:BH$891,$N$69:$N$891,$N34,$AS$69:$AS$891,31) -> 0 | BI34: =+SUMIFS(BI$69:BI$891,$N$69:$N$891,$N34,$AS$69:$AS$891,31) -> 0 | BJ34: =+SUMIFS(BJ$69:BJ$891,$N$69:$N$891,$N34,$AS$69:$AS$891,31) -> 0 | BK34: =+SUMIFS(BK$69:BK$891,$N$69:$N$891,$N34,$AS$69:$AS$891,31) -> 0 | BL34: =+SUMIFS(BL$69:BL$891,$N$69:$N$891,$N34,$AS$69:$AS$891,31) -> 0 | BM34: =+SUMIFS(BM$69:BM$894,$N$69:$N$894,$N34,$AS$69:$AS$894,31) -> 0 | BN34: =+SUMIFS(BN$69:BN$784,$N$69:$N$784,$N34,$AS$69:$AS$784,31) -> 0
N35: 482113700 | O35: 下水道事業収益 | P35: 営業外収益 | Q35: 消費税及び地方消費税還付金 | R35: 消費税及び地方消費税還付金 | Y35: =+SUMIFS(Y$69:Y$891,$N$69:$N$891,$N35,$AS$69:$AS$891,31) -> 0 | AV35: =+SUMIFS(AV$69:AV$894,$N$69:$N$894,$N35,$AS$69:$AS$894,31) -> 0 | AW35: =+SUMIFS(AW$69:AW$894,$N$69:$N$894,$N35,$AS$69:$AS$894,31) -> 0 | AX35: =+SUMIFS(AX$69:AX$894,$N$69:$N$894,$N35,$AS$69:$AS$894,31) -> 0 | AY35: =+SUMIFS(AY$69:AY$894,$N$69:$N$894,$N35,$AS$69:$AS$894,31) -> 0 | AZ35: =+SUMIFS(AZ$69:AZ$894,$N$69:$N$894,$N35,$AS$69:$AS$894,31) -> 0 | BA35: =+SUMIFS(BA$69:BA$894,$N$69:$N$894,$N35,$AS$69:$AS$894,31) -> 0 | BB35: =+SUMIFS(BB$69:BB$894,$N$69:$N$894,$N35,$AS$69:$AS$894,31) -> 0 | BC35: =+SUMIFS(BC$69:BC$894,$N$69:$N$894,$N35,$AS$69:$AS$894,31) -> 0 | BD35: =+SUMIFS(BD$69:BD$784,$N$69:$N$784,$N35,$AS$69:$AS$784,31) -> 0 | BE35: =+SUMIFS(BE$69:BE$784,$N$69:$N$784,$N35,$AS$69:$AS$784,31) -> 0 | BF35: =+SUMIFS(BF$69:BF$891,$N$69:$N$891,$N35,$AS$69:$AS$891,31) -> 0 | BG35: =+SUMIFS(BG$69:BG$891,$N$69:$N$891,$N35,$AS$69:$AS$891,31) -> 0 | BH35: =+SUMIFS(BH$69:BH$891,$N$69:$N$891,$N35,$AS$69:$AS$891,31) -> 0 | BI35: =+SUMIFS(BI$69:BI$891,$N$69:$N$891,$N35,$AS$69:$AS$891,31) -> 0 | BJ35: =+SUMIFS(BJ$69:BJ$891,$N$69:$N$891,$N35,$AS$69:$AS$891,31) -> 0 | BK35: =+SUMIFS(BK$69:BK$891,$N$69:$N$891,$N35,$AS$69:$AS$891,31) -> 0 | BL35: =+SUMIFS(BL$69:BL$891,$N$69:$N$891,$N35,$AS$69:$AS$891,31) -> 0 | BM35: =+SUMIFS(BM$69:BM$894,$N$69:$N$894,$N35,$AS$69:$AS$894,31) -> 0 | BN35: =+SUMIFS(BN$69:BN$784,$N$69:$N$784,$N35,$AS$69:$AS$784,31) -> 0
N36: 482123600 | O36: 下水道事業収益 | P36: 営業外収益 | Q36: 雑収益 | R36: 不用品売却収益 | Y36: =+SUMIFS(Y$69:Y$891,$N$69:$N$891,$N36,$AS$69:$AS$891,31) -> 0 | AV36: =+SUMIFS(AV$69:AV$894,$N$69:$N$894,$N36,$AS$69:$AS$894,31) -> 0 | AW36: =+SUMIFS(AW$69:AW$894,$N$69:$N$894,$N36,$AS$69:$AS$894,31) -> 0 | AX36: =+SUMIFS(AX$69:AX$894,$N$69:$N$894,$N36,$AS$69:$AS$894,31) -> 0 | AY36: =+SUMIFS(AY$69:AY$894,$N$69:$N$894,$N36,$AS$69:$AS$894,31) -> 0 | AZ36: =+SUMIFS(AZ$69:AZ$894,$N$69:$N$894,$N36,$AS$69:$AS$894,31) -> 0 | BA36: =+SUMIFS(BA$69:BA$894,$N$69:$N$894,$N36,$AS$69:$AS$894,31) -> 0 | BB36: =+SUMIFS(BB$69:BB$894,$N$69:$N$894,$N36,$AS$69:$AS$894,31) -> 0 | BC36: =+SUMIFS(BC$69:BC$894,$N$69:$N$894,$N36,$AS$69:$AS$894,31) -> 0 | BD36: =+SUMIFS(BD$69:BD$784,$N$69:$N$784,$N36,$AS$69:$AS$784,31) -> 0 | BE36: =+SUMIFS(BE$69:BE$784,$N$69:$N$784,$N36,$AS$69:$AS$784,31) -> 0 | BF36: =+SUMIFS(BF$69:BF$891,$N$69:$N$891,$N36,$AS$69:$AS$891,31) -> 0 | BG36: =+SUMIFS(BG$69:BG$891,$N$69:$N$891,$N36,$AS$69:$AS$891,31) -> 0 | BH36: =+SUMIFS(BH$69:BH$891,$N$69:$N$891,$N36,$AS$69:$AS$891,31) -> 0 | BI36: =+SUMIFS(BI$69:BI$891,$N$69:$N$891,$N36,$AS$69:$AS$891,31) -> 0 | BJ36: =+SUMIFS(BJ$69:BJ$891,$N$69:$N$891,$N36,$AS$69:$AS$891,31) -> 0 | BK36: =+SUMIFS(BK$69:BK$891,$N$69:$N$891,$N36,$AS$69:$AS$891,31) -> 0 | BL36: =+SUMIFS(BL$69:BL$891,$N$69:$N$891,$N36,$AS$69:$AS$891,31) -> 0 | BM36: =+SUMIFS(BM$69:BM$894,$N$69:$N$894,$N36,$AS$69:$AS$894,31) -> 0 | BN36: =+SUMIFS(BN$69:BN$784,$N$69:$N$784,$N36,$AS$69:$AS$784,31) -> 0
N37: 482124000 | O37: 下水道事業収益 | P37: 営業外収益 | Q37: 雑収益 | R37: その他雑収益 | Y37: =+SUMIFS(Y$69:Y$891,$N$69:$N$891,$N37,$AS$69:$AS$891,31) -> 1202214 | AV37: =+SUMIFS(AV$69:AV$894,$N$69:$N$894,$N37,$AS$69:$AS$894,31) -> 553018 | AW37: =+SUMIFS(AW$69:AW$894,$N$69:$N$894,$N37,$AS$69:$AS$894,31) -> 0 | AX37: =+SUMIFS(AX$69:AX$894,$N$69:$N$894,$N37,$AS$69:$AS$894,31) -> 0 | AY37: =+SUMIFS(AY$69:AY$894,$N$69:$N$894,$N37,$AS$69:$AS$894,31) -> 553018 | AZ37: =+SUMIFS(AZ$69:AZ$894,$N$69:$N$894,$N37,$AS$69:$AS$894,31) -> 0 | BA37: =+SUMIFS(BA$69:BA$894,$N$69:$N$894,$N37,$AS$69:$AS$894,31) -> 649196 | BB37: =+SUMIFS(BB$69:BB$894,$N$69:$N$894,$N37,$AS$69:$AS$894,31) -> 649196 | BC37: =+SUMIFS(BC$69:BC$894,$N$69:$N$894,$N37,$AS$69:$AS$894,31) -> 1202214 | BD37: =+SUMIFS(BD$69:BD$784,$N$69:$N$784,$N37,$AS$69:$AS$784,31) -> 0 | BE37: =+SUMIFS(BE$69:BE$784,$N$69:$N$784,$N37,$AS$69:$AS$784,31) -> 0 | BF37: =+SUMIFS(BF$69:BF$891,$N$69:$N$891,$N37,$AS$69:$AS$891,31) -> 553018 | BG37: =+SUMIFS(BG$69:BG$891,$N$69:$N$891,$N37,$AS$69:$AS$891,31) -> 0 | BH37: =+SUMIFS(BH$69:BH$891,$N$69:$N$891,$N37,$AS$69:$AS$891,31) -> 0 | BI37: =+SUMIFS(BI$69:BI$891,$N$69:$N$891,$N37,$AS$69:$AS$891,31) -> 553018 | BJ37: =+SUMIFS(BJ$69:BJ$891,$N$69:$N$891,$N37,$AS$69:$AS$891,31) -> 0 | BK37: =+SUMIFS(BK$69:BK$891,$N$69:$N$891,$N37,$AS$69:$AS$891,31) -> 649196 | BL37: =+SUMIFS(BL$69:BL$891,$N$69:$N$891,$N37,$AS$69:$AS$891,31) -> 649196 | BM37: =+SUMIFS(BM$69:BM$894,$N$69:$N$894,$N37,$AS$69:$AS$894,31) -> 1202214 | BN37: =+SUMIFS(BN$69:BN$784,$N$69:$N$784,$N37,$AS$69:$AS$784,31) -> 0
N38: 483020200 | O38: 下水道事業収益 | P38: 特別利益 | Q38: 固定資産売却益 | R38: 固定資産売却益 | Y38: =+SUMIFS(Y$69:Y$891,$N$69:$N$891,$N38,$AS$69:$AS$891,31) -> 0 | AV38: =+SUMIFS(AV$69:AV$894,$N$69:$N$894,$N38,$AS$69:$AS$894,31) -> 0 | AW38: =+SUMIFS(AW$69:AW$894,$N$69:$N$894,$N38,$AS$69:$AS$894,31) -> 0 | AX38: =+SUMIFS(AX$69:AX$894,$N$69:$N$894,$N38,$AS$69:$AS$894,31) -> 0 | AY38: =+SUMIFS(AY$69:AY$894,$N$69:$N$894,$N38,$AS$69:$AS$894,31) -> 0 | AZ38: =+SUMIFS(AZ$69:AZ$894,$N$69:$N$894,$N38,$AS$69:$AS$894,31) -> 0 | BA38: =+SUMIFS(BA$69:BA$894,$N$69:$N$894,$N38,$AS$69:$AS$894,31) -> 0 | BB38: =+SUMIFS(BB$69:BB$894,$N$69:$N$894,$N38,$AS$69:$AS$894,31) -> 0 | BC38: =+SUMIFS(BC$69:BC$894,$N$69:$N$894,$N38,$AS$69:$AS$894,31) -> 0 | BD38: =+SUMIFS(BD$69:BD$784,$N$69:$N$784,$N38,$AS$69:$AS$784,31) -> 0 | BE38: =+SUMIFS(BE$69:BE$784,$N$69:$N$784,$N38,$AS$69:$AS$784,31) -> 0 | BF38: =+SUMIFS(BF$69:BF$891,$N$69:$N$891,$N38,$AS$69:$AS$891,31) -> 0 | BG38: =+SUMIFS(BG$69:BG$891,$N$69:$N$891,$N38,$AS$69:$AS$891,31) -> 0 | BH38: =+SUMIFS(BH$69:BH$891,$N$69:$N$891,$N38,$AS$69:$AS$891,31) -> 0 | BI38: =+SUMIFS(BI$69:BI$891,$N$69:$N$891,$N38,$AS$69:$AS$891,31) -> 0 | BJ38: =+SUMIFS(BJ$69:BJ$891,$N$69:$N$891,$N38,$AS$69:$AS$891,31) -> 0 | BK38: =+SUMIFS(BK$69:BK$891,$N$69:$N$891,$N38,$AS$69:$AS$891,31) -> 0 | BL38: =+SUMIFS(BL$69:BL$891,$N$69:$N$891,$N38,$AS$69:$AS$891,31) -> 0 | BM38: =+SUMIFS(BM$69:BM$894,$N$69:$N$894,$N38,$AS$69:$AS$894,31) -> 0 | BN38: =+SUMIFS(BN$69:BN$784,$N$69:$N$784,$N38,$AS$69:$AS$784,31) -> 0
N39: 483040400 | O39: 下水道事業収益 | P39: 特別利益 | Q39: 過年度損益修正益 | R39: 過年度損益修正益 | Y39: =+SUMIFS(Y$69:Y$891,$N$69:$N$891,$N39,$AS$69:$AS$891,31) -> 1155175 | AV39: =+SUMIFS(AV$69:AV$894,$N$69:$N$894,$N39,$AS$69:$AS$894,31) -> 351708 | AW39: =+SUMIFS(AW$69:AW$894,$N$69:$N$894,$N39,$AS$69:$AS$894,31) -> 0 | AX39: =+SUMIFS(AX$69:AX$894,$N$69:$N$894,$N39,$AS$69:$AS$894,31) -> 487974 | AY39: =+SUMIFS(AY$69:AY$894,$N$69:$N$894,$N39,$AS$69:$AS$894,31) -> 839682 | AZ39: =+SUMIFS(AZ$69:AZ$894,$N$69:$N$894,$N39,$AS$69:$AS$894,31) -> 29260 | BA39: =+SUMIFS(BA$69:BA$894,$N$69:$N$894,$N39,$AS$69:$AS$894,31) -> 286233 | BB39: =+SUMIFS(BB$69:BB$894,$N$69:$N$894,$N39,$AS$69:$AS$894,31) -> 315493 | BC39: =+SUMIFS(BC$69:BC$894,$N$69:$N$894,$N39,$AS$69:$AS$894,31) -> 1155175 | BD39: =+SUMIFS(BD$69:BD$784,$N$69:$N$784,$N39,$AS$69:$AS$784,31) -> 0 | BE39: =+SUMIFS(BE$69:BE$784,$N$69:$N$784,$N39,$AS$69:$AS$784,31) -> 0 | BF39: =+SUMIFS(BF$69:BF$891,$N$69:$N$891,$N39,$AS$69:$AS$891,31) -> 351708 | BG39: =+SUMIFS(BG$69:BG$891,$N$69:$N$891,$N39,$AS$69:$AS$891,31) -> 0 | BH39: =+SUMIFS(BH$69:BH$891,$N$69:$N$891,$N39,$AS$69:$AS$891,31) -> 487974 | BI39: =+SUMIFS(BI$69:BI$891,$N$69:$N$891,$N39,$AS$69:$AS$891,31) -> 839682 | BJ39: =+SUMIFS(BJ$69:BJ$891,$N$69:$N$891,$N39,$AS$69:$AS$891,31) -> 29260 | BK39: =+SUMIFS(BK$69:BK$891,$N$69:$N$891,$N39,$AS$69:$AS$891,31) -> 286233 | BL39: =+SUMIFS(BL$69:BL$891,$N$69:$N$891,$N39,$AS$69:$AS$891,31) -> 315493 | BM39: =+SUMIFS(BM$69:BM$894,$N$69:$N$894,$N39,$AS$69:$AS$894,31) -> 1155175 | BN39: =+SUMIFS(BN$69:BN$784,$N$69:$N$784,$N39,$AS$69:$AS$784,31) -> 0
N40: 483060600 | O40: 下水道事業収益 | P40: 特別利益 | Q40: その他特別利益 | R40: その他特別利益 | Y40: =+SUMIFS(Y$69:Y$891,$N$69:$N$891,$N40,$AS$69:$AS$891,31) -> 864807 | AV40: =+SUMIFS(AV$69:AV$894,$N$69:$N$894,$N40,$AS$69:$AS$894,31) -> 588069 | AW40: =+SUMIFS(AW$69:AW$894,$N$69:$N$894,$N40,$AS$69:$AS$894,31) -> 0 | AX40: =+SUMIFS(AX$69:AX$894,$N$69:$N$894,$N40,$AS$69:$AS$894,31) -> 0 | AY40: =+SUMIFS(AY$69:AY$894,$N$69:$N$894,$N40,$AS$69:$AS$894,31) -> 588069 | AZ40: =+SUMIFS(AZ$69:AZ$894,$N$69:$N$894,$N40,$AS$69:$AS$894,31) -> 0 | BA40: =+SUMIFS(BA$69:BA$894,$N$69:$N$894,$N40,$AS$69:$AS$894,31) -> 276738 | BB40: =+SUMIFS(BB$69:BB$894,$N$69:$N$894,$N40,$AS$69:$AS$894,31) -> 276738 | BC40: =+SUMIFS(BC$69:BC$894,$N$69:$N$894,$N40,$AS$69:$AS$894,31) -> 864807 | BD40: =+SUMIFS(BD$69:BD$784,$N$69:$N$784,$N40,$AS$69:$AS$784,31) -> 0 | BE40: =+SUMIFS(BE$69:BE$784,$N$69:$N$784,$N40,$AS$69:$AS$784,31) -> 0 | BF40: =+SUMIFS(BF$69:BF$891,$N$69:$N$891,$N40,$AS$69:$AS$891,31) -> 588069 | BG40: =+SUMIFS(BG$69:BG$891,$N$69:$N$891,$N40,$AS$69:$AS$891,31) -> 0 | BH40: =+SUMIFS(BH$69:BH$891,$N$69:$N$891,$N40,$AS$69:$AS$891,31) -> 0 | BI40: =+SUMIFS(BI$69:BI$891,$N$69:$N$891,$N40,$AS$69:$AS$891,31) -> 588069 | BJ40: =+SUMIFS(BJ$69:BJ$891,$N$69:$N$891,$N40,$AS$69:$AS$891,31) -> 0 | BK40: =+SUMIFS(BK$69:BK$891,$N$69:$N$891,$N40,$AS$69:$AS$891,31) -> 276738 | BL40: =+SUMIFS(BL$69:BL$891,$N$69:$N$891,$N40,$AS$69:$AS$891,31) -> 276738 | BM40: =+SUMIFS(BM$69:BM$894,$N$69:$N$894,$N40,$AS$69:$AS$894,31) -> 864807 | BN40: =+SUMIFS(BN$69:BN$784,$N$69:$N$784,$N40,$AS$69:$AS$784,31) -> 0
N41: 483060700 | O41: 下水道事業収益 | P41: 特別利益 | Q41: その他特別利益 | R41: 貸倒引当金戻入益 | Y41: =+SUMIFS(Y$69:Y$891,$N$69:$N$891,$N41,$AS$69:$AS$891,31) -> 455622 | AV41: =+SUMIFS(AV$69:AV$894,$N$69:$N$894,$N41,$AS$69:$AS$894,31) -> 0 | AW41: =+SUMIFS(AW$69:AW$894,$N$69:$N$894,$N41,$AS$69:$AS$894,31) -> 0 | AX41: =+SUMIFS(AX$69:AX$894,$N$69:$N$894,$N41,$AS$69:$AS$894,31) -> 16334 | AY41: =+SUMIFS(AY$69:AY$894,$N$69:$N$894,$N41,$AS$69:$AS$894,31) -> 16334 | AZ41: =+SUMIFS(AZ$69:AZ$894,$N$69:$N$894,$N41,$AS$69:$AS$894,31) -> 0 | BA41: =+SUMIFS(BA$69:BA$894,$N$69:$N$894,$N41,$AS$69:$AS$894,31) -> 439288 | BB41: =+SUMIFS(BB$69:BB$894,$N$69:$N$894,$N41,$AS$69:$AS$894,31) -> 439288 | BC41: =+SUMIFS(BC$69:BC$894,$N$69:$N$894,$N41,$AS$69:$AS$894,31) -> 455622 | BD41: =+SUMIFS(BD$69:BD$784,$N$69:$N$784,$N41,$AS$69:$AS$784,31) -> 0 | BE41: =+SUMIFS(BE$69:BE$784,$N$69:$N$784,$N41,$AS$69:$AS$784,31) -> 0 | BF41: =+SUMIFS(BF$69:BF$891,$N$69:$N$891,$N41,$AS$69:$AS$891,31) -> 0 | BG41: =+SUMIFS(BG$69:BG$891,$N$69:$N$891,$N41,$AS$69:$AS$891,31) -> 0 | BH41: =+SUMIFS(BH$69:BH$891,$N$69:$N$891,$N41,$AS$69:$AS$891,31) -> 16334 | BI41: =+SUMIFS(BI$69:BI$891,$N$69:$N$891,$N41,$AS$69:$AS$891,31) -> 16334 | BJ41: =+SUMIFS(BJ$69:BJ$891,$N$69:$N$891,$N41,$AS$69:$AS$891,31) -> 0 | BK41: =+SUMIFS(BK$69:BK$891,$N$69:$N$891,$N41,$AS$69:$AS$891,31) -> 439288 | BL41: =+SUMIFS(BL$69:BL$891,$N$69:$N$891,$N41,$AS$69:$AS$891,31) -> 439288 | BM41: =+SUMIFS(BM$69:BM$894,$N$69:$N$894,$N41,$AS$69:$AS$894,31) -> 455622 | BN41: =+SUMIFS(BN$69:BN$784,$N$69:$N$784,$N41,$AS$69:$AS$784,31) -> 0
N42: 483060800 | O42: 下水道事業収益 | P42: 特別利益 | Q42: その他特別利益 | R42: 賞与引当金戻入益 | Y42: =+SUMIFS(Y$69:Y$891,$N$69:$N$891,$N42,$AS$69:$AS$891,31) -> 109000 | AV42: =+SUMIFS(AV$69:AV$894,$N$69:$N$894,$N42,$AS$69:$AS$894,31) -> 54500 | AW42: =+SUMIFS(AW$69:AW$894,$N$69:$N$894,$N42,$AS$69:$AS$894,31) -> 0 | AX42: =+SUMIFS(AX$69:AX$894,$N$69:$N$894,$N42,$AS$69:$AS$894,31) -> 0 | AY42: =+SUMIFS(AY$69:AY$894,$N$69:$N$894,$N42,$AS$69:$AS$894,31) -> 54500 | AZ42: =+SUMIFS(AZ$69:AZ$894,$N$69:$N$894,$N42,$AS$69:$AS$894,31) -> 0 | BA42: =+SUMIFS(BA$69:BA$894,$N$69:$N$894,$N42,$AS$69:$AS$894,31) -> 54500 | BB42: =+SUMIFS(BB$69:BB$894,$N$69:$N$894,$N42,$AS$69:$AS$894,31) -> 54500 | BC42: =+SUMIFS(BC$69:BC$894,$N$69:$N$894,$N42,$AS$69:$AS$894,31) -> 109000 | BD42: =+SUMIFS(BD$69:BD$784,$N$69:$N$784,$N42,$AS$69:$AS$784,31) -> 0 | BE42: =+SUMIFS(BE$69:BE$784,$N$69:$N$784,$N42,$AS$69:$AS$784,31) -> 0 | BF42: =+SUMIFS(BF$69:BF$891,$N$69:$N$891,$N42,$AS$69:$AS$891,31) -> 54500 | BG42: =+SUMIFS(BG$69:BG$891,$N$69:$N$891,$N42,$AS$69:$AS$891,31) -> 0 | BH42: =+SUMIFS(BH$69:BH$891,$N$69:$N$891,$N42,$AS$69:$AS$891,31) -> 0 | BI42: =+SUMIFS(BI$69:BI$891,$N$69:$N$891,$N42,$AS$69:$AS$891,31) -> 54500 | BJ42: =+SUMIFS(BJ$69:BJ$891,$N$69:$N$891,$N42,$AS$69:$AS$891,31) -> 0 | BK42: =+SUMIFS(BK$69:BK$891,$N$69:$N$891,$N42,$AS$69:$AS$891,31) -> 54500 | BL42: =+SUMIFS(BL$69:BL$891,$N$69:$N$891,$N42,$AS$69:$AS$891,31) -> 54500 | BM42: =+SUMIFS(BM$69:BM$894,$N$69:$N$894,$N42,$AS$69:$AS$894,31) -> 109000 | BN42: =+SUMIFS(BN$69:BN$784,$N$69:$N$784,$N42,$AS$69:$AS$784,31) -> 0
R45: 不課税分に係る特定収入仮払消費税額の配賦表↓ | AV45: 雨水（税込） | AZ45: 汚水（税込） | BC45: 合計 （税込） | BD45: チェック | BF45: 雨水（税抜） | BJ45: 汚水（税抜） | BM45: 合計 （税抜） | BN45: 税抜き 要調整額 | BO45: 3条収入ｼｰﾄ集計値
AV46: 区域内 | AW46: 区域外 | AX46: 一般行政 | AY46: 計 | AZ46: 基準内 | BA46: 基準外 | BB46: 計 | BF46: 区域内 | BG46: 区域外 | BH46: 一般行政 | BI46: 計 | BJ46: 基準内 | BK46: 基準外 | BL46: 計
N47: 481121400 | O47: 下水道事業収益 | P47: 営業収益 | Q47: 受託工事収益 | R47: 受託工事収益 | BF47: =+IFERROR(ROUND($BO47*BF25/$BM25,0),0) -> 0 | BG47: =+IFERROR(ROUND($BO47*BG25/$BM25,0),0) -> 0 | BH47: =+IFERROR(ROUND($BO47*BH25/$BM25,0),0) -> 0 | BI47: =SUM(BF47:BG47) -> 0 | BJ47: =+IFERROR(ROUND($BO47*BJ25/$BM25,0),0) -> 0 | BK47: =+IFERROR(ROUND($BO47*BK25/$BM25,0),0) -> 0 | BL47: =SUM(BJ47:BK47) -> 0 | BM47: =+BI47+BL47+BH47 -> 0 | BN47: =+BO47-BM47 -> 0 | BO47: =+SUMIFS('[2]3条収入'!$AH$6:$AH$70,'[2]3条収入'!$C$6:$C$70,雨汚収入!N47) -> 0
N48: 481141500 | O48: 下水道事業収益 | P48: 営業収益 | Q48: その他営業収益 | R48: 産物売却代金 | BF48: =+IFERROR(ROUND($BO48*BF26/$BM26,0),0) -> 0 | BG48: =+IFERROR(ROUND($BO48*BG26/$BM26,0),0) -> 0 | BH48: =+IFERROR(ROUND($BO48*BH26/$BM26,0),0) -> 0 | BI48: =SUM(BF48:BG48) -> 0 | BJ48: =+IFERROR(ROUND($BO48*BJ26/$BM26,0),0) -> 0 | BK48: =+IFERROR(ROUND($BO48*BK26/$BM26,0),0) -> 0 | BL48: =SUM(BJ48:BK48) -> 0 | BM48: =+BI48+BL48+BH48 -> 0 | BN48: =+BO48-BM48 -> 0 | BO48: =+SUMIFS('[2]3条収入'!$AH$6:$AH$70,'[2]3条収入'!$C$6:$C$70,雨汚収入!N48) -> 0
N49: 481141700 | O49: 下水道事業収益 | P49: 営業収益 | Q49: その他営業収益 | R49: 業務受託収益 | BF49: =+IFERROR(ROUND($BO49*BF27/$BM27,0),0) -> 0 | BG49: =+IFERROR(ROUND($BO49*BG27/$BM27,0),0) -> 0 | BH49: =+IFERROR(ROUND($BO49*BH27/$BM27,0),0) -> 0 | BI49: =SUM(BF49:BG49) -> 0 | BJ49: =+IFERROR(ROUND($BO49*BJ27/$BM27,0),0) -> 0 | BK49: =+IFERROR(ROUND($BO49*BK27/$BM27,0),0) -> 0 | BL49: =SUM(BJ49:BK49) -> 0 | BM49: =+BI49+BL49+BH49 -> 0 | BN49: =+BO49-BM49 -> 0 | BO49: =+SUMIFS('[2]3条収入'!$AH$6:$AH$70,'[2]3条収入'!$C$6:$C$70,雨汚収入!N49) -> 0
N50: 481141915 | O50: 下水道事業収益 | P50: 営業収益 | Q50: その他営業収益 | R50: 手数料 | S50: 証明手数料 | BF50: =+IFERROR(ROUND($BO50*BF28/$BM28,0),0) -> 0 | BG50: =+IFERROR(ROUND($BO50*BG28/$BM28,0),0) -> 0 | BH50: =+IFERROR(ROUND($BO50*BH28/$BM28,0),0) -> 0 | BI50: =SUM(BF50:BG50) -> 0 | BJ50: =+IFERROR(ROUND($BO50*BJ28/$BM28,0),0) -> 0 | BK50: =+IFERROR(ROUND($BO50*BK28/$BM28,0),0) -> 0 | BL50: =SUM(BJ50:BK50) -> 0 | BM50: =+BI50+BL50+BH50 -> 0 | BN50: =+BO50-BM50 -> 0 | BO50: =+SUMIFS('[2]3条収入'!$AH$6:$AH$70,'[2]3条収入'!$C$6:$C$70,雨汚収入!N50) -> 0
N51: 481141916 | O51: 下水道事業収益 | P51: 営業収益 | Q51: その他営業収益 | R51: 手数料 | S51: 指定業者登録等手数料 | BF51: =+IFERROR(ROUND($BO51*BF29/$BM29,0),0) -> 0 | BG51: =+IFERROR(ROUND($BO51*BG29/$BM29,0),0) -> 0 | BH51: =+IFERROR(ROUND($BO51*BH29/$BM29,0),0) -> 0 | BI51: =SUM(BF51:BG51) -> 0 | BJ51: =+IFERROR(ROUND($BO51*BJ29/$BM29,0),0) -> 0 | BK51: =+IFERROR(ROUND($BO51*BK29/$BM29,0),0) -> 0 | BL51: =SUM(BJ51:BK51) -> 0 | BM51: =+BI51+BL51+BH51 -> 0 | BN51: =+BO51-BM51 -> 0 | BO51: =+SUMIFS('[2]3条収入'!$AH$6:$AH$70,'[2]3条収入'!$C$6:$C$70,雨汚収入!N51) -> 0
N52: 481142000 | O52: 下水道事業収益 | P52: 営業外収益 | Q52: 雑収益 | BF52: =+IFERROR(ROUND($BO52*BF30/$BM30,0),0) -> 0 | BG52: =+IFERROR(ROUND($BO52*BG30/$BM30,0),0) -> 0 | BH52: =+IFERROR(ROUND($BO52*BH30/$BM30,0),0) -> 0 | BI52: =SUM(BF52:BG52) -> 0 | BJ52: =+IFERROR(ROUND($BO52*BJ30/$BM30,0),0) -> 0 | BK52: =+IFERROR(ROUND($BO52*BK30/$BM30,0),0) -> 0 | BL52: =SUM(BJ52:BK52) -> 0 | BM52: =+BI52+BL52+BH52 -> 0 | BN52: =+BO52-BM52 -> 0 | BO52: =+SUMIFS('[2]3条収入'!$AH$6:$AH$70,'[2]3条収入'!$C$6:$C$70,雨汚収入!N52) -> 0
N53: 482022100 | O53: 下水道事業収益 | P53: 営業外収益 | Q53: 受取利息 | R53: 預金利息 | BF53: =+IFERROR(ROUND($BO53*BF31/$BM31,0),0) -> 0 | BG53: =+IFERROR(ROUND($BO53*BG31/$BM31,0),0) -> 0 | BH53: =+IFERROR(ROUND($BO53*BH31/$BM31,0),0) -> 0 | BI53: =SUM(BF53:BG53) -> 0 | BJ53: =+IFERROR(ROUND($BO53*BJ31/$BM31,0),0) -> 0 | BK53: =+IFERROR(ROUND($BO53*BK31/$BM31,0),0) -> 0 | BL53: =SUM(BJ53:BK53) -> 0 | BM53: =+BI53+BL53+BH53 -> 0 | BN53: =+BO53-BM53 -> 0 | BO53: =+SUMIFS('[2]3条収入'!$AH$6:$AH$70,'[2]3条収入'!$C$6:$C$70,雨汚収入!N53) -> 0
N54: 482042900 | O54: 下水道事業収益 | P54: 営業外収益 | Q54: 国庫補助金 | R54: その他国庫補助金(災害) | BF54: =+IFERROR(ROUND($BO54*BF32/$BM32,0),0) -> 0 | BG54: =+IFERROR(ROUND($BO54*BG32/$BM32,0),0) -> 0 | BH54: =+IFERROR(ROUND($BO54*BH32/$BM32,0),0) -> 0 | BI54: =SUM(BF54:BG54) -> 0 | BJ54: =+IFERROR(ROUND($BO54*BJ32/$BM32,0),0) -> 0 | BK54: =+IFERROR(ROUND($BO54*BK32/$BM32,0),0) -> 0 | BL54: =SUM(BJ54:BK54) -> 0 | BM54: =+BI54+BL54+BH54 -> 0 | BN54: =+BO54-BM54 -> 0 | BO54: =+SUMIFS('[2]3条収入'!$AH$6:$AH$70,'[2]3条収入'!$C$6:$C$70,雨汚収入!N54) -> 0
N55: 482093200 | O55: 下水道事業収益 | P55: 営業外収益 | Q55: 負担金 | R55: 施設管理負担金 | BF55: =+IFERROR(ROUND($BO55*BF33/$BM33,0),0) -> 0 | BG55: =+IFERROR(ROUND($BO55*BG33/$BM33,0),0) -> 0 | BH55: =+IFERROR(ROUND($BO55*BH33/$BM33,0),0) -> 0 | BI55: =SUM(BF55:BG55) -> 0 | BJ55: =+IFERROR(ROUND($BO55*BJ33/$BM33,0),0) -> 0 | BK55: =+IFERROR(ROUND($BO55*BK33/$BM33,0),0) -> 0 | BL55: =SUM(BJ55:BK55) -> 0 | BM55: =+BI55+BL55+BH55 -> 0 | BN55: =+BO55-BM55 -> 0 | BO55: =+SUMIFS('[2]3条収入'!$AH$6:$AH$70,'[2]3条収入'!$C$6:$C$70,雨汚収入!N55) -> 0
N56: 482093300 | O56: 下水道事業収益 | P56: 営業外収益 | Q56: 負担金 | R56: 他会計負担金 | BF56: =+IFERROR(ROUND($BO56*BF34/$BM34,0),0) -> 0 | BG56: =+IFERROR(ROUND($BO56*BG34/$BM34,0),0) -> 0 | BH56: =+IFERROR(ROUND($BO56*BH34/$BM34,0),0) -> 0 | BI56: =SUM(BF56:BG56) -> 0 | BJ56: =+IFERROR(ROUND($BO56*BJ34/$BM34,0),0) -> 0 | BK56: =+IFERROR(ROUND($BO56*BK34/$BM34,0),0) -> 0 | BL56: =SUM(BJ56:BK56) -> 0 | BM56: =+BI56+BL56+BH56 -> 0 | BN56: =+BO56-BM56 -> 0 | BO56: =+SUMIFS('[2]3条収入'!$AH$6:$AH$70,'[2]3条収入'!$C$6:$C$70,雨汚収入!N56) -> 0
N57: 482113700 | O57: 下水道事業収益 | P57: 営業外収益 | Q57: 消費税及び地方消費税還付金 | R57: 消費税及び地方消費税還付金 | BF57: =+IFERROR(ROUND($BO57*BF35/$BM35,0),0) -> 0 | BG57: =+IFERROR(ROUND($BO57*BG35/$BM35,0),0) -> 0 | BH57: =+IFERROR(ROUND($BO57*BH35/$BM35,0),0) -> 0 | BI57: =SUM(BF57:BG57) -> 0 | BJ57: =+IFERROR(ROUND($BO57*BJ35/$BM35,0),0) -> 0 | BK57: =+IFERROR(ROUND($BO57*BK35/$BM35,0),0) -> 0 | BL57: =SUM(BJ57:BK57) -> 0 | BM57: =+BI57+BL57+BH57 -> 0 | BN57: =+BO57-BM57 -> 0 | BO57: =+SUMIFS('[2]3条収入'!$AH$6:$AH$70,'[2]3条収入'!$C$6:$C$70,雨汚収入!N57) -> 0
N58: 482123600 | O58: 下水道事業収益 | P58: 営業外収益 | Q58: 雑収益 | R58: 不用品売却収益 | BF58: =+IFERROR(ROUND($BO58*BF36/$BM36,0),0) -> 0 | BG58: =+IFERROR(ROUND($BO58*BG36/$BM36,0),0) -> 0 | BH58: =+IFERROR(ROUND($BO58*BH36/$BM36,0),0) -> 0 | BI58: =SUM(BF58:BG58) -> 0 | BJ58: =+IFERROR(ROUND($BO58*BJ36/$BM36,0),0) -> 0 | BK58: =+IFERROR(ROUND($BO58*BK36/$BM36,0),0) -> 0 | BL58: =SUM(BJ58:BK58) -> 0 | BM58: =+BI58+BL58+BH58 -> 0 | BN58: =+BO58-BM58 -> 0 | BO58: =+SUMIFS('[2]3条収入'!$AH$6:$AH$70,'[2]3条収入'!$C$6:$C$70,雨汚収入!N58) -> 0
N59: 482124000 | O59: 下水道事業収益 | P59: 営業外収益 | Q59: 雑収益 | R59: その他雑収益 | BF59: =+IFERROR(ROUND($BO59*BF37/$BM37,0),0) -> 10738 | BG59: =+IFERROR(ROUND($BO59*BG37/$BM37,0),0) -> 0 | BH59: =+IFERROR(ROUND($BO59*BH37/$BM37,0),0) -> 0 | BI59: =SUM(BF59:BG59) -> 10738 | BJ59: =+IFERROR(ROUND($BO59*BJ37/$BM37,0),0) -> 0 | BK59: =+IFERROR(ROUND($BO59*BK37/$BM37,0),0) -> 12606 | BL59: =SUM(BJ59:BK59) -> 12606 | BM59: =+BI59+BL59+BH59 -> 23344 | BN59: =+BO59-BM59 -> 0 | BO59: =+SUMIFS('[2]3条収入'!$AH$6:$AH$70,'[2]3条収入'!$C$6:$C$70,雨汚収入!N59) -> 23344
N60: 483020200 | O60: 下水道事業収益 | P60: 特別利益 | Q60: 固定資産売却益 | R60: 固定資産売却益 | BF60: =+IFERROR(ROUND($BO60*BF38/$BM38,0),0) -> 0 | BG60: =+IFERROR(ROUND($BO60*BG38/$BM38,0),0) -> 0 | BH60: =+IFERROR(ROUND($BO60*BH38/$BM38,0),0) -> 0 | BI60: =SUM(BF60:BG60) -> 0 | BJ60: =+IFERROR(ROUND($BO60*BJ38/$BM38,0),0) -> 0 | BK60: =+IFERROR(ROUND($BO60*BK38/$BM38,0),0) -> 0 | BL60: =SUM(BJ60:BK60) -> 0 | BM60: =+BI60+BL60+BH60 -> 0 | BN60: =+BO60-BM60 -> 0 | BO60: =+SUMIFS('[2]3条収入'!$AH$6:$AH$70,'[2]3条収入'!$C$6:$C$70,雨汚収入!N60) -> 0
N61: 483040400 | O61: 下水道事業収益 | P61: 特別利益 | Q61: 過年度損益修正益 | R61: 過年度損益修正益 | BF61: =+IFERROR(ROUND($BO61*BF39/$BM39,0),0) -> 0 | BG61: =+IFERROR(ROUND($BO61*BG39/$BM39,0),0) -> 0 | BH61: =+IFERROR(ROUND($BO61*BH39/$BM39,0),0) -> 0 | BI61: =SUM(BF61:BG61) -> 0 | BJ61: =+IFERROR(ROUND($BO61*BJ39/$BM39,0),0) -> 0 | BK61: =+IFERROR(ROUND($BO61*BK39/$BM39,0),0) -> 0 | BL61: =SUM(BJ61:BK61) -> 0 | BM61: =+BI61+BL61+BH61 -> 0 | BN61: =+BO61-BM61 -> 0 | BO61: =+SUMIFS('[2]3条収入'!$AH$6:$AH$70,'[2]3条収入'!$C$6:$C$70,雨汚収入!N61) -> 0
N62: 483060600 | O62: 下水道事業収益 | P62: 特別利益 | Q62: その他特別利益 | R62: その他特別利益 | BF62: =+IFERROR(ROUND($BO62*BF40/$BM40,0),0) -> 0 | BG62: =+IFERROR(ROUND($BO62*BG40/$BM40,0),0) -> 0 | BH62: =+IFERROR(ROUND($BO62*BH40/$BM40,0),0) -> 0 | BI62: =SUM(BF62:BG62) -> 0 | BJ62: =+IFERROR(ROUND($BO62*BJ40/$BM40,0),0) -> 0 | BK62: =+IFERROR(ROUND($BO62*BK40/$BM40,0),0) -> 0 | BL62: =SUM(BJ62:BK62) -> 0 | BM62: =+BI62+BL62+BH62 -> 0 | BN62: =+BO62-BM62 -> 0 | BO62: =+SUMIFS('[2]3条収入'!$AH$6:$AH$70,'[2]3条収入'!$C$6:$C$70,雨汚収入!N62) -> 0
N63: 483060700 | O63: 下水道事業収益 | P63: 特別利益 | Q63: その他特別利益 | R63: 貸倒引当金戻入益 | BF63: =+IFERROR(ROUND($BO63*BF41/$BM41,0),0) -> 0 | BG63: =+IFERROR(ROUND($BO63*BG41/$BM41,0),0) -> 0 | BH63: =+IFERROR(ROUND($BO63*BH41/$BM41,0),0) -> 0 | BI63: =SUM(BF63:BG63) -> 0 | BJ63: =+IFERROR(ROUND($BO63*BJ41/$BM41,0),0) -> 0 | BK63: =+IFERROR(ROUND($BO63*BK41/$BM41,0),0) -> 0 | BL63: =SUM(BJ63:BK63) -> 0 | BM63: =+BI63+BL63+BH63 -> 0 | BN63: =+BO63-BM63 -> 0 | BO63: =+SUMIFS('[2]3条収入'!$AH$6:$AH$70,'[2]3条収入'!$C$6:$C$70,雨汚収入!N63) -> 0
N64: 483060800 | O64: 下水道事業収益 | P64: 特別利益 | Q64: その他特別利益 | R64: 賞与引当金戻入益 | BF64: =+IFERROR(ROUND($BO64*BF42/$BM42,0),0) -> 0 | BG64: =+IFERROR(ROUND($BO64*BG42/$BM42,0),0) -> 0 | BH64: =+IFERROR(ROUND($BO64*BH42/$BM42,0),0) -> 0 | BI64: =SUM(BF64:BG64) -> 0 | BJ64: =+IFERROR(ROUND($BO64*BJ42/$BM42,0),0) -> 0 | BK64: =+IFERROR(ROUND($BO64*BK42/$BM42,0),0) -> 0 | BL64: =SUM(BJ64:BK64) -> 0 | BM64: =+BI64+BL64+BH64 -> 0 | BN64: =+BO64-BM64 -> 0 | BO64: =+SUMIFS('[2]3条収入'!$AH$6:$AH$70,'[2]3条収入'!$C$6:$C$70,雨汚収入!N64) -> 0
R65: 計 | BF65: =+SUM(BF47:BF64) -> 10738 | BG65: =+SUM(BG47:BG64) -> 0 | BH65: =+SUM(BH47:BH64) -> 0 | BI65: =+SUM(BI47:BI64) -> 10738 | BJ65: =+SUM(BJ47:BJ64) -> 0 | BK65: =+SUM(BK47:BK64) -> 12606 | BL65: =+SUM(BL47:BL64) -> 12606 | BM65: =+SUM(BM47:BM64) -> 23344 | ... BO65: =+SUM(BO47:BO64) -> 23344
Y67: =+SUBTOTAL(109,Y69:Y1000) -> 267611572 | AV67: =+SUBTOTAL(109,AV69:AV1000) -> 49120269 | AW67: =+SUBTOTAL(109,AW69:AW1000) -> 507311 | AX67: =+SUBTOTAL(109,AX69:AX1000) -> 40065138 | AY67: =+SUBTOTAL(109,AY69:AY1000) -> 89692718 | AZ67: =+SUBTOTAL(109,AZ69:AZ1000) -> 298760 | BA67: =+SUBTOTAL(109,BA69:BA1000) -> 177620094 | BB67: =+SUBTOTAL(109,BB69:BB1000) -> 177918854 | BC67: =+SUBTOTAL(109,BC69:BC1000) -> 267611572 | ... BM67: =+SUBTOTAL(109,BM69:BM1000) -> 245686919
AL68: ---- | AS68: 0 | AT68: 0 | AV68: 雨水（税込） | AZ68: 汚水（税込） | BC68: 合計 （税込） | BD68: チェック | BF68: 雨水（税抜） | BJ68: 汚水（税抜） | BM68: 合計 （税抜） | BN68: 備考
A69: 事業区分 | B69: 所属 | C69: 所属名 | D69: 主管課 | E69: 主管課名 | F69: 年月日 | G69: 振替年月日 | H69: 事項 | I69: 種別 | J69: 伝票番号 | K69: 枝番 | L69: 内訳番号 | M69: 現繰 | N69: 予算科目 | O69: 款名称 | P69: 項名称 | Q69: 目名称 | R69: 節名称 | S69: 細節名称 | T69: 事業コード | U69: 事業名 | V69: 予算額 | W69: 概算額 | X69: 確定額 | Y69: 執行額 | Z69: 借方勘定 | AA69: 借方勘定科目 | AB69: 借方金額 | AC69: 貸方勘定 | AD69: 貸方勘定科目 | AE69: 貸方金額 | AF69: 税区分 | AG69: 税率 | AH69: 税額 | AI69: 税抜金額 | AJ69: 債権者 | AL69: 複合伝票番号 | AM69: 確認状況 | AN69: 正しい課税区分 | AO69: 正しい税率 | AP69: 備考 | AQ69: 重複 | AS69: 集計用課税区分 | AT69: 集計用税率 | AV69: 区域内 | AW69: 区域外 | AX69: 一般行政 | AY69: 計 | AZ69: 基準内 | BA69: 基準外 | BB69: 計 | BF69: 区域内 | BG69: 区域外 | BH69: 一般行政 | BI69: 計 | BJ69: 基準内 | BK69: 基準外 | BL69: 計 | BO69: AA | BP69: AA
A70: 1 | D70: 1502113000 | E70: 西部水資源再生センター | F70: R05/11/10 | G70: R05/11/10 | H70: 消化ガス売却収入（令和５年１０月分） | I70: 振替伝票（調定） | J70: 20000946 | K70: 000 | L70: 001 | M70: 1 | N70: 0481141500 | O70: 下水道事業収益 | P70: 営業収益 | Q70: その他営業収益 | R70: 産物売却代金 | T70: 999999 | U70: 共通 | V70: 0 | W70: 0 | X70: 0 | Y70: 13722588 | Z70: 021402001010010000 | AA70: 未収その他営業収益 | AB70: 13722588 | AC70: 048114001015000000 | AD70: 産物売却代金 | AE70: 13722588 | AF70: 17 | AG70: 10 | AH70: 1247508 | AI70: 12475080 | AJ70: 月島ＪＦＥアクアソリューション株式会社 中国支店 | AL70: 20000946-000-001-1-0481141500-999999-17 | AM70: 1 | AN70: 0 | AO70: 0 | AP70: 0 | AS70: 17 | AT70: 10 | AV70: 0 | AW70: 0 | AX70: 2758240 | AY70: 2758240 | AZ70: 0 | BA70: 10964348 | BB70: 10964348 | BC70: 13722588 | BD70: 0 | BF70: =+IFERROR(ROUND(AV70*100/(100+$AT70),0),AV70) -> 0 | BG70: =+IFERROR(ROUND(AW70*100/(100+$AT70),0),AW70) -> 0 | BH70: =+IFERROR(ROUND(AX70*100/(100+$AT70),0),AX70) -> 2507491 | BI70: =SUM(BF70:BH70) -> 2507491 | BJ70: =+IFERROR(ROUND(AZ70*100/(100+$AT70),0),AZ70) -> 0 | BK70: =+IFERROR(ROUND(BA70*100/(100+$AT70),0),BA70) -> 9967589 | BL70: =SUM(BJ70:BK70) -> 9967589 | BM70: =+BI70+BL70 -> 12475080 | BQ70: =AY70*100/(100+$AT70)-BI70 -> -0.090909091 | BR70: =BB70*100/(100+$AT70)-BL70 -> 0.090909092 | BS70: =AZ70*100/(100+$AT70)-BJ70 -> 0 | BT70: =BA70*100/(100+$AT70)-BK70 -> 0.090909092
A71: 1 | D71: 1502113000 | E71: 西部水資源再生センター | F71: R05/12/08 | G71: R05/12/08 | H71: 消化ガス売却収入（令和５年１１月分） | I71: 振替伝票（調定） | J71: 20001038 | K71: 000 | L71: 001 | M71: 1 | N71: 0481141500 | O71: 下水道事業収益 | P71: 営業収益 | Q71: その他営業収益 | R71: 産物売却代金 | T71: 999999 | U71: 共通 | V71: 0 | W71: 0 | X71: 0 | Y71: 16825396 | Z71: 021402001010010000 | AA71: 未収その他営業収益 | AB71: 16825396 | AC71: 048114001015000000 | AD71: 産物売却代金 | AE71: 16825396 | AF71: 17 | AG71: 10 | AH71: 1529581 | AI71: 15295815 | AJ71: 月島ＪＦＥアクアソリューション株式会社 中国支店 | AL71: 20001038-000-001-1-0481141500-999999-17 | AM71: 1 | AN71: 0 | AO71: 0 | AP71: 0 | AS71: 17 | AT71: 10 | AV71: 0 | AW71: 0 | AX71: 3381905 | AY71: 3381905 | AZ71: 0 | BA71: 13443491 | BB71: 13443491 | BC71: 16825396 | BD71: 0 | BF71: =+IFERROR(ROUND(AV71*100/(100+$AT71),0),AV71) -> 0 | BG71: =+IFERROR(ROUND(AW71*100/(100+$AT71),0),AW71) -> 0 | BH71: =+IFERROR(ROUND(AX71*100/(100+$AT71),0),AX71) -> 3074459 | BI71: =SUM(BF71:BH71) -> 3074459 | BJ71: =+IFERROR(ROUND(AZ71*100/(100+$AT71),0),AZ71) -> 0 | BK71: =+IFERROR(ROUND(BA71*100/(100+$AT71),0),BA71)+1 -> 12221356 | BL71: =SUM(BJ71:BK71) -> 12221356 | BM71: =+BI71+BL71 -> 15295815 | BQ71: =AY71*100/(100+$AT71)-BI71 -> 0.090909091 | BR71: =BB71*100/(100+$AT71)-BL71 -> -0.54545454 | BS71: =AZ71*100/(100+$AT71)-BJ71 -> 0 | BT71: =BA71*100/(100+$AT71)-BK71 -> -0.54545454
A72: 1 | D72: 1502113000 | E72: 西部水資源再生センター | F72: R06/01/10 | G72: R06/01/10 | H72: 消化ガス売却収入（令和５年１２月分） | I72: 振替伝票（調定） | J72: 20001162 | K72: 000 | L72: 001 | M72: 1 | N72: 0481141500 | O72: 下水道事業収益 | P72: 営業収益 | Q72: その他営業収益 | R72: 産物売却代金 | T72: 999999 | U72: 共通 | V72: 0 | W72: 0 | X72: 0 | Y72: 13836537 | Z72: 021402001010010000 | AA72: 未収その他営業収益 | AB72: 13836537 | AC72: 048114001015000000 | AD72: 産物売却代金 | AE72: 13836537 | AF72: 17 | AG72: 10 | AH72: 1257867 | AI72: 12578670 | AJ72: 月島ＪＦＥアクアソリューション株式会社 中国支店 | AL72: 20001162-000-001-1-0481141500-999999-17 | AM72: 1 | AN72: 0 | AO72: 0 | AP72: 0 | AS72: 17 | AT72: 10 | AV72: 0 | AW72: 0 | AX72: 2781144 | AY72: 2781144 | AZ72: 0 | BA72: 11055393 | BB72: 11055393 | BC72: 13836537 | BD72: 0 | BF72: =+IFERROR(ROUND(AV72*100/(100+$AT72),0),AV72) -> 0 | BG72: =+IFERROR(ROUND(AW72*100/(100+$AT72),0),AW72) -> 0 | BH72: =+IFERROR(ROUND(AX72*100/(100+$AT72),0),AX72) -> 2528313 | BI72: =SUM(BF72:BH72) -> 2528313 | BJ72: =+IFERROR(ROUND(AZ72*100/(100+$AT72),0),AZ72) -> 0 | BK72: =+IFERROR(ROUND(BA72*100/(100+$AT72),0),BA72) -> 10050357 | BL72: =SUM(BJ72:BK72) -> 10050357 | BM72: =+BI72+BL72 -> 12578670 | BQ72: =AY72*100/(100+$AT72)-BI72 -> -0.27272727 | BR72: =BB72*100/(100+$AT72)-BL72 -> 0.27272727 | BS72: =AZ72*100/(100+$AT72)-BJ72 -> 0 | BT72: =BA72*100/(100+$AT72)-BK72 -> 0.27272727
A73: 1 | D73: 1502113000 | E73: 西部水資源再生センター | F73: R05/05/10 | G73: R05/05/10 | H73: 消化ガス売却収入（令和５年４月分） | I73: 振替伝票（調定） | J73: 20000142 | K73: 000 | L73: 001 | M73: 1 | N73: 0481141500 | O73: 下水道事業収益 | P73: 営業収益 | Q73: その他営業収益 | R73: 産物売却代金 | T73: 999999 | U73: 共通 | V73: 0 | W73: 0 | X73: 0 | Y73: 17239761 | Z73: 021402001010010000 | AA73: 未収その他営業収益 | AB73: 17239761 | AC73: 048114001015000000 | AD73: 産物売却代金 | AE73: 17239761 | AF73: 17 | AG73: 10 | AH73: 1567251 | AI73: 15672510 | AJ73: 月島アクアソリューション株式会社 広島営業所 | AL73: 20000142-000-001-1-0481141500-999999-17 | AM73: 1 | AN73: 0 | AO73: 0 | AP73: 0 | AS73: 17 | AT73: 10 | AV73: 0 | AW73: 0 | AX73: 3465192 | AY73: 3465192 | AZ73: 0 | BA73: 13774569 | BB73: 13774569 | BC73: 17239761 | BD73: 0 | BF73: =+IFERROR(ROUND(AV73*100/(100+$AT73),0),AV73) -> 0 | BG73: =+IFERROR(ROUND(AW73*100/(100+$AT73),0),AW73) -> 0 | BH73: =+IFERROR(ROUND(AX73*100/(100+$AT73),0),AX73) -> 3150175 | BI73: =SUM(BF73:BH73) -> 3150175 | BJ73: =+IFERROR(ROUND(AZ73*100/(100+$AT73),0),AZ73) -> 0 | BK73: =+IFERROR(ROUND(BA73*100/(100+$AT73),0),BA73)+1 -> 12522336 | BL73: =SUM(BJ73:BK73) -> 12522336 | BM73: =+BI73+BL73 -> 15672511 | BQ73: =AY73*100/(100+$AT73)-BI73 -> -0.45454545 | BR73: =BB73*100/(100+$AT73)-BL73 -> -0.54545454 | BS73: =AZ73*100/(100+$AT73)-BJ73 -> 0 | BT73: =BA73*100/(100+$AT73)-BK73 -> -0.54545454
A74: 1 | D74: 1502113000 | E74: 西部水資源再生センター | F74: R05/06/09 | G74: R05/06/09 | H74: 消化ガス売却収入（令和５年５月分） | I74: 振替伝票（調定） | J74: 20000304 | K74: 000 | L74: 001 | M74: 1 | N74: 0481141500 | O74: 下水道事業収益 | P74: 営業収益 | Q74: その他営業収益 | R74: 産物売却代金 | T74: 999999 | U74: 共通 | V74: 0 | W74: 0 | X74: 0 | Y74: 20232135 | Z74: 021402001010010000 | AA74: 未収その他営業収益 | AB74: 20232135 | AC74: 048114001015000000 | AD74: 産物売却代金 | AE74: 20232135 | AF74: 17 | AG74: 10 | AH74: 1839285 | AI74: 18392850 | AJ74: 月島アクアソリューション株式会社 広島営業所 | AL74: 20000304-000-001-1-0481141500-999999-17 | AM74: 1 | AN74: 0 | AO74: 0 | AP74: 0 | AS74: 17 | AT74: 10 | AV74: 0 | AW74: 0 | AX74: 4066659 | AY74: 4066659 | AZ74: 0 | BA74: 16165476 | BB74: 16165476 | BC74: 20232135 | BD74: 0 | BF74: =+IFERROR(ROUND(AV74*100/(100+$AT74),0),AV74) -> 0 | BG74: =+IFERROR(ROUND(AW74*100/(100+$AT74),0),AW74) -> 0 | BH74: =+IFERROR(ROUND(AX74*100/(100+$AT74),0),AX74) -> 3696963 | BI74: =SUM(BF74:BH74) -> 3696963 | BJ74: =+IFERROR(ROUND(AZ74*100/(100+$AT74),0),AZ74) -> 0 | BK74: =+IFERROR(ROUND(BA74*100/(100+$AT74),0),BA74) -> 14695887 | BL74: =SUM(BJ74:BK74) -> 14695887 | BM74: =+BI74+BL74 -> 18392850 | BQ74: =AY74*100/(100+$AT74)-BI74 -> -0.27272727 | BR74: =BB74*100/(100+$AT74)-BL74 -> 0.27272727 | BS74: =AZ74*100/(100+$AT74)-BJ74 -> 0 | BT74: =BA74*100/(100+$AT74)-BK74 -> 0.27272727
A75: 1 | D75: 1502113000 | E75: 西部水資源再生センター | F75: R05/07/10 | G75: R05/07/10 | H75: 消化ガス売却収入（令和５年６月分） | I75: 振替伝票（調定） | J75: 20000438 | K75: 000 | L75: 001 | M75: 1 | N75: 0481141500 | O75: 下水道事業収益 | P75: 営業収益 | Q75: その他営業収益 | R75: 産物売却代金 | T75: 999999 | U75: 共通 | V75: 0 | W75: 0 | X75: 0 | Y75: 18357223 | Z75: 021402001010010000 | AA75: 未収その他営業収益 | AB75: 18357223 | AC75: 048114001015000000 | AD75: 産物売却代金 | AE75: 18357223 | AF75: 17 | AG75: 10 | AH75: 1668838 | AI75: 16688385 | AJ75: 月島アクアソリューション株式会社 広島営業所 | AL75: 20000438-000-001-1-0481141500-999999-17 | AM75: 1 | AN75: 0 | AO75: 0 | AP75: 0 | AS75: 17 | AT75: 10 | AV75: 0 | AW75: 0 | AX75: 3689802 | AY75: 3689802 | AZ75: 0 | BA75: 14667421 | BB75: 14667421 | BC75: 18357223 | BD75: 0 | BF75: =+IFERROR(ROUND(AV75*100/(100+$AT75),0),AV75) -> 0 | BG75: =+IFERROR(ROUND(AW75*100/(100+$AT75),0),AW75) -> 0 | BH75: =+IFERROR(ROUND(AX75*100/(100+$AT75),0),AX75)+1 -> 3354366 | BI75: =SUM(BF75:BH75) -> 3354366 | BJ75: =+IFERROR(ROUND(AZ75*100/(100+$AT75),0),AZ75) -> 0 | BK75: =+IFERROR(ROUND(BA75*100/(100+$AT75),0),BA75) -> 13334019 | BL75: =SUM(BJ75:BK75) -> 13334019 | BM75: =+BI75+BL75 -> 16688385 | BQ75: =AY75*100/(100+$AT75)-BI75 -> -0.54545455 | BR75: =BB75*100/(100+$AT75)-BL75 -> 0.090909092 | BS75: =AZ75*100/(100+$AT75)-BJ75 -> 0 | BT75: =BA75*100/(100+$AT75)-BK75 -> 0.090909092
A76: 1 | D76: 1502113000 | E76: 西部水資源再生センター | F76: R05/08/10 | G76: R05/08/10 | H76: 消化ガス売却収入（令和５年７月分） | I76: 振替伝票（調定） | J76: 20000540 | K76: 000 | L76: 001 | M76: 1 | N76: 0481141500 | O76: 下水道事業収益 | P76: 営業収益 | Q76: その他営業収益 | R76: 産物売却代金 | T76: 999999 | U76: 共通 | V76: 0 | W76: 0 | X76: 0 | Y76: 17858956 | Z76: 021402001010010000 | AA76: 未収その他営業収益 | AB76: 17858956 | AC76: 048114001015000000 | AD76: 産物売却代金 | AE76: 17858956 | AF76: 17 | AG76: 10 | AH76: 1623541 | AI76: 16235415 | AJ76: 月島アクアソリューション株式会社 広島営業所 | AL76: 20000540-000-001-1-0481141500-999999-17 | AM76: 1 | AN76: 0 | AO76: 0 | AP76: 0 | AS76: 17 | AT76: 10 | AV76: 0 | AW76: 0 | AX76: 3589650 | AY76: 3589650 | AZ76: 0 | BA76: 14269306 | BB76: 14269306 | BC76: 17858956 | BD76: 0 | BF76: =+IFERROR(ROUND(AV76*100/(100+$AT76),0),AV76) -> 0 | BG76: =+IFERROR(ROUND(AW76*100/(100+$AT76),0),AW76) -> 0 | BH76: =+IFERROR(ROUND(AX76*100/(100+$AT76),0),AX76) -> 3263318 | BI76: =SUM(BF76:BH76) -> 3263318 | BJ76: =+IFERROR(ROUND(AZ76*100/(100+$AT76),0),AZ76) -> 0 | BK76: =+IFERROR(ROUND(BA76*100/(100+$AT76),0),BA76) -> 12972096 | BL76: =SUM(BJ76:BK76) -> 12972096 | BM76: =+BI76+BL76 -> 16235414 | BQ76: =AY76*100/(100+$AT76)-BI76 -> 0.18181818 | BR76: =BB76*100/(100+$AT76)-BL76 -> 0.36363636 | BS76: =AZ76*100/(100+$AT76)-BJ76 -> 0 | BT76: =BA76*100/(100+$AT76)-BK76 -> 0.36363636
A77: 1 | D77: 1502113000 | E77: 西部水資源再生センター | F77: R05/09/08 | G77: R05/09/08 | H77: 消化ガス売却収入（令和５年８月分） | I77: 振替伝票（調定） | J77: 20000686 | K77: 000 | L77: 001 | M77: 1 | N77: 0481141500 | O77: 下水道事業収益 | P77: 営業収益 | Q77: その他営業収益 | R77: 産物売却代金 | T77: 999999 | U77: 共通 | V77: 0 | W77: 0 | X77: 0 | Y77: 14627596 | Z77: 021402001010010000 | AA77: 未収その他営業収益 | AB77: 14627596 | AC77: 048114001015000000 | AD77: 産物売却代金 | AE77: 14627596 | AF77: 17 | AG77: 10 | AH77: 1329781 | AI77: 13297815 | AJ77: 月島アクアソリューション株式会社 広島営業所 | AL77: 20000686-000-001-1-0481141500-999999-17 | AM77: 1 | AN77: 0 | AO77: 0 | AP77: 0 | AS77: 17 | AT77: 10 | AV77: 0 | AW77: 0 | AX77: 2940147 | AY77: 2940147 | AZ77: 0 | BA77: 11687449 | BB77: 11687449 | BC77: 14627596 | BD77: 0 | BF77: =+IFERROR(ROUND(AV77*100/(100+$AT77),0),AV77) -> 0 | BG77: =+IFERROR(ROUND(AW77*100/(100+$AT77),0),AW77) -> 0 | BH77: =+IFERROR(ROUND(AX77*100/(100+$AT77),0),AX77) -> 2672861 | BI77: =SUM(BF77:BH77) -> 2672861 | BJ77: =+IFERROR(ROUND(AZ77*100/(100+$AT77),0),AZ77) -> 0 | BK77: =+IFERROR(ROUND(BA77*100/(100+$AT77),0),BA77) -> 10624954 | BL77: =SUM(BJ77:BK77) -> 10624954 | BM77: =+BI77+BL77 -> 13297815 | BQ77: =AY77*100/(100+$AT77)-BI77 -> -0.090909091 | BR77: =BB77*100/(100+$AT77)-BL77 -> -0.36363636 | BS77: =AZ77*100/(100+$AT77)-BJ77 -> 0 | BT77: =BA77*100/(100+$AT77)-BK77 -> -0.36363636
A78: 1 | D78: 1502113000 | E78: 西部水資源再生センター | F78: R05/10/10 | G78: R05/10/10 | H78: 消化ガス売却収入（令和５年９月分） | I78: 振替伝票（調定） | J78: 20000824 | K78: 000 | L78: 001 | M78: 1 | N78: 0481141500 | O78: 下水道事業収益 | P78: 営業収益 | Q78: その他営業収益 | R78: 産物売却代金 | T78: 999999 | U78: 共通 | V78: 0 | W78: 0 | X78: 0 | Y78: 17104279 | Z78: 021402001010010000 | AA78: 未収その他営業収益 | AB78: 17104279 | AC78: 048114001015000000 | AD78: 産物売却代金 | AE78: 17104279 | AF78: 17 | AG78: 10 | AH78: 1554934 | AI78: 15549345 | AJ78: 月島ＪＦＥアクアソリューション株式会社 中国支店 | AL78: 20000824-000-001-1-0481141500-999999-17 | AM78: 1 | AN78: 0 | AO78: 0 | AP78: 0 | AS78: 17 | AT78: 10 | AV78: 0 | AW78: 0 | AX78: 3437960 | AY78: 3437960 | AZ78: 0 | BA78: 13666319 | BB78: 13666319 | BC78: 17104279 | BD78: 0 | BF78: =+IFERROR(ROUND(AV78*100/(100+$AT78),0),AV78) -> 0 | BG78: =+IFERROR(ROUND(AW78*100/(100+$AT78),0),AW78) -> 0 | BH78: =+IFERROR(ROUND(AX78*100/(100+$AT78),0),AX78) -> 3125418 | BI78: =SUM(BF78:BH78) -> 3125418 | BJ78: =+IFERROR(ROUND(AZ78*100/(100+$AT78),0),AZ78) -> 0 | BK78: =+IFERROR(ROUND(BA78*100/(100+$AT78),0),BA78) -> 12423926 | BL78: =SUM(BJ78:BK78) -> 12423926 | BM78: =+BI78+BL78 -> 15549344 | BQ78: =AY78*100/(100+$AT78)-BI78 -> 0.18181818 | BR78: =BB78*100/(100+$AT78)-BL78 -> 0.36363636 | BS78: =AZ78*100/(100+$AT78)-BJ78 -> 0 | BT78: =BA78*100/(100+$AT78)-BK78 -> 0.36363636
A79: 1 | D79: 1502113000 | E79: 西部水資源再生センター | F79: R06/02/09 | G79: R06/02/09 | H79: 消化ガス売却収入（令和６年１月分） | I79: 振替伝票（調定） | J79: 20001276 | K79: 000 | L79: 001 | M79: 1 | N79: 0481141500 | O79: 下水道事業収益 | P79: 営業収益 | Q79: その他営業収益 | R79: 産物売却代金 | T79: 999999 | U79: 共通 | V79: 0 | W79: 0 | X79: 0 | Y79: 19530905 | Z79: 021402001010010000 | AA79: 未収その他営業収益 | AB79: 19530905 | AC79: 048114001015000000 | AD79: 産物売却代金 | AE79: 19530905 | AF79: 17 | AG79: 10 | AH79: 1775536 | AI79: 17755369 | AJ79: 月島ＪＦＥアクアソリューション株式会社 中国支店 | AL79: 20001276-000-001-1-0481141500-999999-17 | AM79: 1 | AN79: 0 | AO79: 0 | AP79: 0 | AS79: 17 | AT79: 10 | AV79: 0 | AW79: 0 | AX79: 3925712 | AY79: 3925712 | AZ79: 0 | BA79: 15605193 | BB79: 15605193 | BC79: 19530905 | BD79: 0 | BF79: =+IFERROR(ROUND(AV79*100/(100+$AT79),0),AV79) -> 0 | BG79: =+IFERROR(ROUND(AW79*100/(100+$AT79),0),AW79) -> 0 | BH79: =+IFERROR(ROUND(AX79*100/(100+$AT79),0),AX79) -> 3568829 | BI79: =SUM(BF79:BH79) -> 3568829 | BJ79: =+IFERROR(ROUND(AZ79*100/(100+$AT79),0),AZ79) -> 0 | BK79: =+IFERROR(ROUND(BA79*100/(100+$AT79),0),BA79) -> 14186539 | BL79: =SUM(BJ79:BK79) -> 14186539 | BM79: =+BI79+BL79 -> 17755368 | BQ79: =AY79*100/(100+$AT79)-BI79 -> 0.090909091 | BR79: =BB79*100/(100+$AT79)-BL79 -> 0.090909092 | BS79: =AZ79*100/(100+$AT79)-BJ79 -> 0 | BT79: =BA79*100/(100+$AT79)-BK79 -> 0.090909092
A80: 1 | D80: 1502113000 | E80: 西部水資源再生センター | F80: R06/03/08 | G80: R06/03/08 | H80: 消化ガス売却収入（令和６年２月分） | I80: 振替伝票（調定） | J80: 20001431 | K80: 000 | L80: 001 | M80: 1 | N80: 0481141500 | O80: 下水道事業収益 | P80: 営業収益 | Q80: その他営業収益 | R80: 産物売却代金 | T80: 999999 | U80: 共通 | V80: 0 | W80: 0 | X80: 0 | Y80: 9157891 | Z80: 021402001010010000 | AA80: 未収その他営業収益 | AB80: 9157891 | AC80: 048114001015000000 | AD80: 産物売却代金 | AE80: 9157891 | AF80: 17 | AG80: 10 | AH80: 832535 | AI80: 8325356 | AJ80: 月島ＪＦＥアクアソリューション株式会社 中国支店 | AL80: 20001431-000-001-1-0481141500-999999-17 | AM80: 1 | AN80: 0 | AO80: 0 | AP80: 0 | AS80: 17 | AT80: 10 | AV80: 0 | AW80: 0 | AX80: 1840736 | AY80: 1840736 | AZ80: 0 | BA80: 7317155 | BB80: 7317155 | BC80: 9157891 | BD80: 0 | BF80: =+IFERROR(ROUND(AV80*100/(100+$AT80),0),AV80) -> 0 | BG80: =+IFERROR(ROUND(AW80*100/(100+$AT80),0),AW80) -> 0 | BH80: =+IFERROR(ROUND(AX80*100/(100+$AT80),0),AX80) -> 1673396 | BI80: =SUM(BF80:BH80) -> 1673396 | BJ80: =+IFERROR(ROUND(AZ80*100/(100+$AT80),0),AZ80) -> 0 | BK80: =+IFERROR(ROUND(BA80*100/(100+$AT80),0),BA80) -> 6651959 | BL80: =SUM(BJ80:BK80) -> 6651959 | BM80: =+BI80+BL80 -> 8325355 | BQ80: =AY80*100/(100+$AT80)-BI80 -> 0.36363636 | BR80: =BB80*100/(100+$AT80)-BL80 -> 0.090909091 | BS80: =AZ80*100/(100+$AT80)-BJ80 -> 0 | BT80: =BA80*100/(100+$AT80)-BK80 -> 0.090909091
A81: 1 | D81: 1502113000 | E81: 西部水資源再生センター | F81: R06/03/31 | G81: R06/03/31 | H81: 消化ガス売却収入（令和６年３月分） | I81: 振替伝票（調定） | J81: 20001612 | K81: 000 | L81: 001 | M81: 1 | N81: 0481141500 | O81: 下水道事業収益 | P81: 営業収益 | Q81: その他営業収益 | R81: 産物売却代金 | T81: 999999 | U81: 共通 | V81: 0 | W81: 0 | X81: 0 | Y81: 8765528 | Z81: 021402001010010000 | AA81: 未収その他営業収益 | AB81: 8765528 | AC81: 048114001015000000 | AD81: 産物売却代金 | AE81: 8765528 | AF81: 17 | AG81: 10 | AH81: 796866 | AI81: 7968662 | AJ81: 月島ＪＦＥアクアソリューション株式会社中国支店 | AL81: 20001612-000-001-1-0481141500-999999-17 | AM81: 1 | AN81: 0 | AO81: 0 | AP81: 0 | AS81: 17 | AT81: 10 | AV81: 0 | AW81: 0 | AX81: 1761871 | AY81: 1761871 | AZ81: 0 | BA81: 7003657 | BB81: 7003657 | BC81: 8765528 | BD81: 0 | BF81: =+IFERROR(ROUND(AV81*100/(100+$AT81),0),AV81) -> 0 | BG81: =+IFERROR(ROUND(AW81*100/(100+$AT81),0),AW81) -> 0 | BH81: =+IFERROR(ROUND(AX81*100/(100+$AT81),0),AX81) -> 1601701 | BI81: =SUM(BF81:BH81) -> 1601701 | BJ81: =+IFERROR(ROUND(AZ81*100/(100+$AT81),0),AZ81) -> 0 | BK81: =+IFERROR(ROUND(BA81*100/(100+$AT81),0),BA81) -> 6366961 | BL81: =SUM(BJ81:BK81) -> 6366961 | BM81: =+BI81+BL81 -> 7968662 | BQ81: =AY81*100/(100+$AT81)-BI81 -> -0.090909091 | BR81: =BB81*100/(100+$AT81)-BL81 -> -0.090909091 | BS81: =AZ81*100/(100+$AT81)-BJ81 -> 0 | BT81: =BA81*100/(100+$AT81)-BK81 -> -0.090909091
A82: 1 | D82: 1502113000 | E82: 西部水資源再生センター | F82: R05/11/10 | G82: R05/11/10 | H82: 燃料化物の売払い収入（令和５年１０月分） | I82: 振替伝票（調定） | J82: 20000925 | K82: 000 | L82: 001 | M82: 1 | N82: 0481141500 | O82: 下水道事業収益 | P82: 営業収益 | Q82: その他営業収益 | R82: 産物売却代金 | T82: 999999 | U82: 共通 | V82: 0 | W82: 0 | X82: 0 | Y82: 52595 | Z82: 021402001010010000 | AA82: 未収その他営業収益 | AB82: 52595 | AC82: 048114001015000000 | AD82: 産物売却代金 | AE82: 52595 | AF82: 17 | AG82: 10 | AH82: 4781 | AI82: 47814 | AJ82: （株）バイオコール広島西部 | AL82: 20000925-000-001-1-0481141500-999999-17 | AM82: 1 | AN82: 0 | AO82: 0 | AP82: 0 | AS82: 17 | AT82: 10 | AV82: 0 | AW82: 0 | AX82: 10572 | AY82: 10572 | AZ82: 0 | BA82: 42023 | BB82: 42023 | BC82: 52595 | BD82: 0 | BF82: =+IFERROR(ROUND(AV82*100/(100+$AT82),0),AV82) -> 0 | BG82: =+IFERROR(ROUND(AW82*100/(100+$AT82),0),AW82) -> 0 | BH82: =+IFERROR(ROUND(AX82*100/(100+$AT82),0),AX82) -> 9611 | BI82: =SUM(BF82:BH82) -> 9611 | BJ82: =+IFERROR(ROUND(AZ82*100/(100+$AT82),0),AZ82) -> 0 | BK82: =+IFERROR(ROUND(BA82*100/(100+$AT82),0),BA82) -> 38203 | BL82: =SUM(BJ82:BK82) -> 38203 | BM82: =+BI82+BL82 -> 47814 | BQ82: =AY82*100/(100+$AT82)-BI82 -> -0.090909091 | BR82: =BB82*100/(100+$AT82)-BL82 -> -0.27272727 | BS82: =AZ82*100/(100+$AT82)-BJ82 -> 0 | BT82: =BA82*100/(100+$AT82)-BK82 -> -0.27272727
A83: 1 | D83: 1502113000 | E83: 西部水資源再生センター | F83: R05/12/08 | G83: R05/12/08 | H83: 燃料化物の売払い収入（令和５年１１月分） | I83: 振替伝票（調定） | J83: 20001043 | K83: 000 | L83: 001 | M83: 1 | N83: 0481141500 | O83: 下水道事業収益 | P83: 営業収益 | Q83: その他営業収益 | R83: 産物売却代金 | T83: 999999 | U83: 共通 | V83: 0 | W83: 0 | X83: 0 | Y83: 49018 | Z83: 021402001010010000 | AA83: 未収その他営業収益 | AB83: 49018 | AC83: 048114001015000000 | AD83: 産物売却代金 | AE83: 49018 | AF83: 17 | AG83: 10 | AH83: 4456 | AI83: 44562 | AJ83: （株）バイオコール広島西部 | AL83: 20001043-000-001-1-0481141500-999999-17 | AM83: 1 | AN83: 0 | AO83: 0 | AP83: 0 | AS83: 17 | AT83: 10 | AV83: 0 | AW83: 0 | AX83: 9853 | AY83: 9853 | AZ83: 0 | BA83: 39165 | BB83: 39165 | BC83: 49018 | BD83: 0 | BF83: =+IFERROR(ROUND(AV83*100/(100+$AT83),0),AV83) -> 0 | BG83: =+IFERROR(ROUND(AW83*100/(100+$AT83),0),AW83) -> 0 | BH83: =+IFERROR(ROUND(AX83*100/(100+$AT83),0),AX83) -> 8957 | BI83: =SUM(BF83:BH83) -> 8957 | BJ83: =+IFERROR(ROUND(AZ83*100/(100+$AT83),0),AZ83) -> 0 | BK83: =+IFERROR(ROUND(BA83*100/(100+$AT83),0),BA83) -> 35605 | BL83: =SUM(BJ83:BK83) -> 35605 | BM83: =+BI83+BL83 -> 44562 | BQ83: =AY83*100/(100+$AT83)-BI83 -> 0.27272727 | BR83: =BB83*100/(100+$AT83)-BL83 -> -0.45454545 | BS83: =AZ83*100/(100+$AT83)-BJ83 -> 0 | BT83: =BA83*100/(100+$AT83)-BK83 -> -0.45454545
A84: 1 | D84: 1502113000 | E84: 西部水資源再生センター | F84: R06/01/10 | G84: R06/01/10 | H84: 燃料化物の売払い収入（令和５年１２月分） | I84: 振替伝票（調定） | J84: 20001186 | K84: 000 | L84: 001 | M84: 1 | N84: 0481141500 | O84: 下水道事業収益 | P84: 営業収益 | Q84: その他営業収益 | R84: 産物売却代金 | T84: 999999 | U84: 共通 | V84: 0 | W84: 0 | X84: 0 | Y84: 45690 | Z84: 021402001010010000 | AA84: 未収その他営業収益 | AB84: 45690 | AC84: 048114001015000000 | AD84: 産物売却代金 | AE84: 45690 | AF84: 17 | AG84: 10 | AH84: 4153 | AI84: 41537 | AJ84: （株）バイオコール広島西部 | AL84: 20001186-000-001-1-0481141500-999999-17 | AM84: 1 | AN84: 0 | AO84: 0 | AP84: 0 | AS84: 17 | AT84: 10 | AV84: 0 | AW84: 0 | AX84: 9184 | AY84: 9184 | AZ84: 0 | BA84: 36506 | BB84: 36506 | BC84: 45690 | BD84: 0 | BF84: =+IFERROR(ROUND(AV84*100/(100+$AT84),0),AV84) -> 0 | BG84: =+IFERROR(ROUND(AW84*100/(100+$AT84),0),AW84) -> 0 | BH84: =+IFERROR(ROUND(AX84*100/(100+$AT84),0),AX84) -> 8349 | BI84: =SUM(BF84:BH84) -> 8349 | BJ84: =+IFERROR(ROUND(AZ84*100/(100+$AT84),0),AZ84) -> 0 | BK84: =+IFERROR(ROUND(BA84*100/(100+$AT84),0),BA84) -> 33187 | BL84: =SUM(BJ84:BK84) -> 33187 | BM84: =+BI84+BL84 -> 41536 | BQ84: =AY84*100/(100+$AT84)-BI84 -> 0.090909091 | BR84: =BB84*100/(100+$AT84)-BL84 -> 0.27272727 | BS84: =AZ84*100/(100+$AT84)-BJ84 -> 0 | BT84: =BA84*100/(100+$AT84)-BK84 -> 0.27272727
A85: 1 | D85: 1502113000 | E85: 西部水資源再生センター | F85: R05/05/10 | G85: R05/05/10 | H85: 燃料化物の売払い収入（令和５年４月分） | I85: 振替伝票（調定） | J85: 20000159 | K85: 000 | L85: 001 | M85: 1 | N85: 0481141500 | O85: 下水道事業収益 | P85: 営業収益 | Q85: その他営業収益 | R85: 産物売却代金 | T85: 999999 | U85: 共通 | V85: 0 | W85: 0 | X85: 0 | Y85: 44855 | Z85: 021402001010010000 | AA85: 未収その他営業収益 | AB85: 44855 | AC85: 048114001015000000 | AD85: 産物売却代金 | AE85: 44855 | AF85: 17 | AG85: 10 | AH85: 4077 | AI85: 40778 | AJ85: （株）バイオコール広島西部 | AL85: 20000159-000-001-1-0481141500-999999-17 | AM85: 1 | AN85: 0 | AO85: 0 | AP85: 0 | AS85: 17 | AT85: 10 | AV85: 0 | AW85: 0 | AX85: 9016 | AY85: 9016 | AZ85: 0 | BA85: 35839 | BB85: 35839 | BC85: 44855 | BD85: 0 | BF85: =+IFERROR(ROUND(AV85*100/(100+$AT85),0),AV85) -> 0 | BG85: =+IFERROR(ROUND(AW85*100/(100+$AT85),0),AW85) -> 0 | BH85: =+IFERROR(ROUND(AX85*100/(100+$AT85),0),AX85) -> 8196 | BI85: =SUM(BF85:BH85) -> 8196 | BJ85: =+IFERROR(ROUND(AZ85*100/(100+$AT85),0),AZ85) -> 0 | BK85: =+IFERROR(ROUND(BA85*100/(100+$AT85),0),BA85) -> 32581 | BL85: =SUM(BJ85:BK85) -> 32581 | BM85: =+BI85+BL85 -> 40777 | BQ85: =AY85*100/(100+$AT85)-BI85 -> 0.36363636 | BR85: =BB85*100/(100+$AT85)-BL85 -> -0.090909091 | BS85: =AZ85*100/(100+$AT85)-BJ85 -> 0 | BT85: =BA85*100/(100+$AT85)-BK85 -> -0.090909091
A86: 1 | D86: 1502113000 | E86: 西部水資源再生センター | F86: R05/06/09 | G86: R05/06/09 | H86: 燃料化物の売払い収入（令和５年５月分） | I86: 振替伝票（調定） | J86: 20000285 | K86: 000 | L86: 001 | M86: 1 | N86: 0481141500 | O86: 下水道事業収益 | P86: 営業収益 | Q86: その他営業収益 | R86: 産物売却代金 | T86: 999999 | U86: 共通 | V86: 0 | W86: 0 | X86: 0 | Y86: 48544 | Z86: 021402001010010000 | AA86: 未収その他営業収益 | AB86: 48544 | AC86: 048114001015000000 | AD86: 産物売却代金 | AE86: 48544 | AF86: 17 | AG86: 10 | AH86: 4413 | AI86: 44131 | AJ86: （株）バイオコール広島西部 | AL86: 20000285-000-001-1-0481141500-999999-17 | AM86: 1 | AN86: 0 | AO86: 0 | AP86: 0 | AS86: 17 | AT86: 10 | AV86: 0 | AW86: 0 | AX86: 9757 | AY86: 9757 | AZ86: 0 | BA86: 38787 | BB86: 38787 | BC86: 48544 | BD86: 0 | BF86: =+IFERROR(ROUND(AV86*100/(100+$AT86),0),AV86) -> 0 | BG86: =+IFERROR(ROUND(AW86*100/(100+$AT86),0),AW86) -> 0 | BH86: =+IFERROR(ROUND(AX86*100/(100+$AT86),0),AX86) -> 8870 | BI86: =SUM(BF86:BH86) -> 8870 | BJ86: =+IFERROR(ROUND(AZ86*100/(100+$AT86),0),AZ86) -> 0 | BK86: =+IFERROR(ROUND(BA86*100/(100+$AT86),0),BA86) -> 35261 | BL86: =SUM(BJ86:BK86) -> 35261 | BM86: =+BI86+BL86 -> 44131 | BQ86: =AY86*100/(100+$AT86)-BI86 -> 0 | BR86: =BB86*100/(100+$AT86)-BL86 -> -0.090909091 | BS86: =AZ86*100/(100+$AT86)-BJ86 -> 0 | BT86: =BA86*100/(100+$AT86)-BK86 -> -0.090909091
A87: 1 | D87: 1502113000 | E87: 西部水資源再生センター | F87: R05/07/10 | G87: R05/07/10 | H87: 燃料化物の売払い収入（令和５年６月分） | I87: 振替伝票（調定） | J87: 20000444 | K87: 000 | L87: 001 | M87: 1 | N87: 0481141500 | O87: 下水道事業収益 | P87: 営業収益 | Q87: その他営業収益 | R87: 産物売却代金 | T87: 999999 | U87: 共通 | V87: 0 | W87: 0 | X87: 0 | Y87: 45016 | Z87: 021402001010010000 | AA87: 未収その他営業収益 | AB87: 45016 | AC87: 048114001015000000 | AD87: 産物売却代金 | AE87: 45016 | AF87: 17 | AG87: 10 | AH87: 4092 | AI87: 40924 | AJ87: （株）バイオコール広島西部 | AL87: 20000444-000-001-1-0481141500-999999-17 | AM87: 1 | AN87: 0 | AO87: 0 | AP87: 0 | AS87: 17 | AT87: 10 | AV87: 0 | AW87: 0 | AX87: 9048 | AY87: 9048 | AZ87: 0 | BA87: 35968 | BB87: 35968 | BC87: 45016 | BD87: 0 | BF87: =+IFERROR(ROUND(AV87*100/(100+$AT87),0),AV87) -> 0 | BG87: =+IFERROR(ROUND(AW87*100/(100+$AT87),0),AW87) -> 0 | BH87: =+IFERROR(ROUND(AX87*100/(100+$AT87),0),AX87)+1 -> 8226 | BI87: =SUM(BF87:BH87) -> 8226 | BJ87: =+IFERROR(ROUND(AZ87*100/(100+$AT87),0),AZ87) -> 0 | BK87: =+IFERROR(ROUND(BA87*100/(100+$AT87),0),BA87) -> 32698 | BL87: =SUM(BJ87:BK87) -> 32698 | BM87: =+BI87+BL87 -> 40924 | BQ87: =AY87*100/(100+$AT87)-BI87 -> -0.54545455 | BR87: =BB87*100/(100+$AT87)-BL87 -> 0.18181818 | BS87: =AZ87*100/(100+$AT87)-BJ87 -> 0 | BT87: =BA87*100/(100+$AT87)-BK87 -> 0.18181818
A88: 1 | D88: 1502113000 | E88: 西部水資源再生センター | F88: R05/08/10 | G88: R05/08/10 | H88: 燃料化物の売払い収入（令和５年７月分） | I88: 振替伝票（調定） | J88: 20000552 | K88: 000 | L88: 001 | M88: 1 | N88: 0481141500 | O88: 下水道事業収益 | P88: 営業収益 | Q88: その他営業収益 | R88: 産物売却代金 | T88: 999999 | U88: 共通 | V88: 0 | W88: 0 | X88: 0 | Y88: 41636 | Z88: 021402001010010000 | AA88: 未収その他営業収益 | AB88: 41636 | AC88: 048114001015000000 | AD88: 産物売却代金 | AE88: 41636 | AF88: 17 | AG88: 10 | AH88: 3785 | AI88: 37851 | AJ88: （株）バイオコール広島西部 | AL88: 20000552-000-001-1-0481141500-999999-17 | AM88: 1 | AN88: 0 | AO88: 0 | AP88: 0 | AS88: 17 | AT88: 10 | AV88: 0 | AW88: 0 | AX88: 8369 | AY88: 8369 | AZ88: 0 | BA88: 33267 | BB88: 33267 | BC88: 41636 | BD88: 0 | BF88: =+IFERROR(ROUND(AV88*100/(100+$AT88),0),AV88) -> 0 | BG88: =+IFERROR(ROUND(AW88*100/(100+$AT88),0),AW88) -> 0 | BH88: =+IFERROR(ROUND(AX88*100/(100+$AT88),0),AX88) -> 7608 | BI88: =SUM(BF88:BH88) -> 7608 | BJ88: =+IFERROR(ROUND(AZ88*100/(100+$AT88),0),AZ88) -> 0 | BK88: =+IFERROR(ROUND(BA88*100/(100+$AT88),0),BA88) -> 30243 | BL88: =SUM(BJ88:BK88) -> 30243 | BM88: =+BI88+BL88 -> 37851 | BQ88: =AY88*100/(100+$AT88)-BI88 -> 0.18181818 | BR88: =BB88*100/(100+$AT88)-BL88 -> -0.27272727 | BS88: =AZ88*100/(100+$AT88)-BJ88 -> 0 | BT88: =BA88*100/(100+$AT88)-BK88 -> -0.27272727
A89: 1 | D89: 1502113000 | E89: 西部水資源再生センター | F89: R05/09/08 | G89: R05/09/08 | H89: 燃料化物の売払い収入（令和５年８月分） | I89: 振替伝票（調定） | J89: 20000680 | K89: 000 | L89: 001 | M89: 1 | N89: 0481141500 | O89: 下水道事業収益 | P89: 営業収益 | Q89: その他営業収益 | R89: 産物売却代金 | T89: 999999 | U89: 共通 | V89: 0 | W89: 0 | X89: 0 | Y89: 51280 | Z89: 021402001010010000 | AA89: 未収その他営業収益 | AB89: 51280 | AC89: 048114001015000000 | AD89: 産物売却代金 | AE89: 51280 | AF89: 17 | AG89: 10 | AH89: 4661 | AI89: 46619 | AJ89: （株）バイオコール広島西部 | AL89: 20000680-000-001-1-0481141500-999999-17 | AM89: 1 | AN89: 0 | AO89: 0 | AP89: 0 | AS89: 17 | AT89: 10 | AV89: 0 | AW89: 0 | AX89: 10307 | AY89: 10307 | AZ89: 0 | BA89: 40973 | BB89: 40973 | BC89: 51280 | BD89: 0 | BF89: =+IFERROR(ROUND(AV89*100/(100+$AT89),0),AV89) -> 0 | BG89: =+IFERROR(ROUND(AW89*100/(100+$AT89),0),AW89) -> 0 | BH89: =+IFERROR(ROUND(AX89*100/(100+$AT89),0),AX89) -> 9370 | BI89: =SUM(BF89:BH89) -> 9370 | BJ89: =+IFERROR(ROUND(AZ89*100/(100+$AT89),0),AZ89) -> 0 | BK89: =+IFERROR(ROUND(BA89*100/(100+$AT89),0),BA89) -> 37248 | BL89: =SUM(BJ89:BK89) -> 37248 | BM89: =+BI89+BL89 -> 46618 | BQ89: =AY89*100/(100+$AT89)-BI89 -> 0 | BR89: =BB89*100/(100+$AT89)-BL89 -> 0.18181818 | BS89: =AZ89*100/(100+$AT89)-BJ89 -> 0 | BT89: =BA89*100/(100+$AT89)-BK89 -> 0.18181818
A90: 1 | D90: 1502113000 | E90: 西部水資源再生センター | F90: R05/10/10 | G90: R05/10/10 | H90: 燃料化物の売払い収入（令和５年９月分） | I90: 振替伝票（調定） | J90: 20000814 | K90: 000 | L90: 001 | M90: 1 | N90: 0481141500 | O90: 下水道事業収益 | P90: 営業収益 | Q90: その他営業収益 | R90: 産物売却代金 | T90: 999999 | U90: 共通 | V90: 0 | W90: 0 | X90: 0 | Y90: 53982 | Z90: 021402001010010000 | AA90: 未収その他営業収益 | AB90: 53982 | AC90: 048114001015000000 | AD90: 産物売却代金 | AE90: 53982 | AF90: 17 | AG90: 10 | AH90: 4907 | AI90: 49075 | AJ90: （株）バイオコール広島西部 | AL90: 20000814-000-001-1-0481141500-999999-17 | AM90: 1 | AN90: 0 | AO90: 0 | AP90: 0 | AS90: 17 | AT90: 10 | AV90: 0 | AW90: 0 | AX90: 10850 | AY90: 10850 | AZ90: 0 | BA90: 43132 | BB90: 43132 | BC90: 53982 | BD90: 0 | BF90: =+IFERROR(ROUND(AV90*100/(100+$AT90),0),AV90) -> 0 | BG90: =+IFERROR(ROUND(AW90*100/(100+$AT90),0),AW90) -> 0 | BH90: =+IFERROR(ROUND(AX90*100/(100+$AT90),0),AX90) -> 9864 | BI90: =SUM(BF90:BH90) -> 9864 | BJ90: =+IFERROR(ROUND(AZ90*100/(100+$AT90),0),AZ90) -> 0 | BK90: =+IFERROR(ROUND(BA90*100/(100+$AT90),0),BA90) -> 39211 | BL90: =SUM(BJ90:BK90) -> 39211 | BM90: =+BI90+BL90 -> 49075 | BQ90: =AY90*100/(100+$AT90)-BI90 -> -0.36363636 | BR90: =BB90*100/(100+$AT90)-BL90 -> -0.090909091 | BS90: =AZ90*100/(100+$AT90)-BJ90 -> 0 | BT90: =BA90*100/(100+$AT90)-BK90 -> -0.090909091
A91: 1 | D91: 1502113000 | E91: 西部水資源再生センター | F91: R06/02/09 | G91: R06/02/09 | H91: 燃料化物の売払い収入（令和６年１月分） | I91: 振替伝票（調定） | J91: 20001280 | K91: 000 | L91: 001 | M91: 1 | N91: 0481141500 | O91: 下水道事業収益 | P91: 営業収益 | Q91: その他営業収益 | R91: 産物売却代金 | T91: 999999 | U91: 共通 | V91: 0 | W91: 0 | X91: 0 | Y91: 35334 | Z91: 021402001010010000 | AA91: 未収その他営業収益 | AB91: 35334 | AC91: 048114001015000000 | AD91: 産物売却代金 | AE91: 35334 | AF91: 17 | AG91: 10 | AH91: 3212 | AI91: 32122 | AJ91: （株）バイオコール広島西部 | AL91: 20001280-000-001-1-0481141500-999999-17 | AM91: 1 | AN91: 0 | AO91: 0 | AP91: 0 | AS91: 17 | AT91: 10 | AV91: 0 | AW91: 0 | AX91: 7102 | AY91: 7102 | AZ91: 0 | BA91: 28232 | BB91: 28232 | BC91: 35334 | BD91: 0 | BF91: =+IFERROR(ROUND(AV91*100/(100+$AT91),0),AV91) -> 0 | BG91: =+IFERROR(ROUND(AW91*100/(100+$AT91),0),AW91) -> 0 | BH91: =+IFERROR(ROUND(AX91*100/(100+$AT91),0),AX91) -> 6456 | BI91: =SUM(BF91:BH91) -> 6456 | BJ91: =+IFERROR(ROUND(AZ91*100/(100+$AT91),0),AZ91) -> 0 | BK91: =+IFERROR(ROUND(BA91*100/(100+$AT91),0),BA91) -> 25665 | BL91: =SUM(BJ91:BK91) -> 25665 | BM91: =+BI91+BL91 -> 32121 | BQ91: =AY91*100/(100+$AT91)-BI91 -> 0.36363636 | BR91: =BB91*100/(100+$AT91)-BL91 -> 0.45454545 | BS91: =AZ91*100/(100+$AT91)-BJ91 -> 0 | BT91: =BA91*100/(100+$AT91)-BK91 -> 0.45454545
A92: 1 | D92: 1502113000 | E92: 西部水資源再生センター | F92: R06/03/08 | G92: R06/03/08 | H92: 燃料化物の売払い収入（令和６年２月分） | I92: 振替伝票（調定） | J92: 20001437 | K92: 000 | L92: 001 | M92: 1 | N92: 0481141500 | O92: 下水道事業収益 | P92: 営業収益 | Q92: その他営業収益 | R92: 産物売却代金 | T92: 999999 | U92: 共通 | V92: 0 | W92: 0 | X92: 0 | Y92: 55605 | Z92: 021402001010010000 | AA92: 未収その他営業収益 | AB92: 55605 | AC92: 048114001015000000 | AD92: 産物売却代金 | AE92: 55605 | AF92: 17 | AG92: 10 | AH92: 5055 | AI92: 50550 | AJ92: （株）バイオコール広島西部 | AL92: 20001437-000-001-1-0481141500-999999-17 | AM92: 1 | AN92: 0 | AO92: 0 | AP92: 0 | AS92: 17 | AT92: 10 | AV92: 0 | AW92: 0 | AX92: 11177 | AY92: 11177 | AZ92: 0 | BA92: 44428 | BB92: 44428 | BC92: 55605 | BD92: 0 | BF92: =+IFERROR(ROUND(AV92*100/(100+$AT92),0),AV92) -> 0 | BG92: =+IFERROR(ROUND(AW92*100/(100+$AT92),0),AW92) -> 0 | BH92: =+IFERROR(ROUND(AX92*100/(100+$AT92),0),AX92) -> 10161 | BI92: =SUM(BF92:BH92) -> 10161 | BJ92: =+IFERROR(ROUND(AZ92*100/(100+$AT92),0),AZ92) -> 0 | BK92: =+IFERROR(ROUND(BA92*100/(100+$AT92),0),BA92) -> 40389 | BL92: =SUM(BJ92:BK92) -> 40389 | BM92: =+BI92+BL92 -> 50550 | BQ92: =AY92*100/(100+$AT92)-BI92 -> -0.090909091 | BR92: =BB92*100/(100+$AT92)-BL92 -> 0.090909091 | BS92: =AZ92*100/(100+$AT92)-BJ92 -> 0 | BT92: =BA92*100/(100+$AT92)-BK92 -> 0.090909091
A93: 1 | D93: 1502113000 | E93: 西部水資源再生センター | F93: R06/03/31 | G93: R06/03/31 | H93: 燃料化物の売払い収入（令和６年３月分） | I93: 振替伝票（調定） | J93: 20001593 | K93: 000 | L93: 001 | M93: 1 | N93: 0481141500 | O93: 下水道事業収益 | P93: 営業収益 | Q93: その他営業収益 | R93: 産物売却代金 | T93: 999999 | U93: 共通 | V93: 0 | W93: 0 | X93: 0 | Y93: 43816 | Z93: 021402001010010000 | AA93: 未収その他営業収益 | AB93: 43816 | AC93: 048114001015000000 | AD93: 産物売却代金 | AE93: 43816 | AF93: 17 | AG93: 10 | AH93: 3983 | AI93: 39833 | AJ93: （株）バイオコール広島西部 | AL93: 20001593-000-001-1-0481141500-999999-17 | AM93: 1 | AN93: 0 | AO93: 0 | AP93: 0 | AS93: 17 | AT93: 10 | AV93: 0 | AW93: 0 | AX93: 8807 | AY93: 8807 | AZ93: 0 | BA93: 35009 | BB93: 35009 | BC93: 43816 | BD93: 0 | BF93: =+IFERROR(ROUND(AV93*100/(100+$AT93),0),AV93) -> 0 | BG93: =+IFERROR(ROUND(AW93*100/(100+$AT93),0),AW93) -> 0 | BH93: =+IFERROR(ROUND(AX93*100/(100+$AT93),0),AX93) -> 8006 | BI93: =SUM(BF93:BH93) -> 8006 | BJ93: =+IFERROR(ROUND(AZ93*100/(100+$AT93),0),AZ93) -> 0 | BK93: =+IFERROR(ROUND(BA93*100/(100+$AT93),0),BA93) -> 31826 | BL93: =SUM(BJ93:BK93) -> 31826 | BM93: =+BI93+BL93 -> 39832 | BQ93: =AY93*100/(100+$AT93)-BI93 -> 0.36363636 | BR93: =BB93*100/(100+$AT93)-BL93 -> 0.36363636 | BS93: =AZ93*100/(100+$AT93)-BJ93 -> 0 | BT93: =BA93*100/(100+$AT93)-BK93 -> 0.36363636
A94: 1 | D94: 1863110500 | E94: 安佐北・維持管理 | F94: R06/03/31 | G94: R06/03/31 | H94: 一級河川太田川水系指定区間落合川に存する河川管理施設（玖村樋門）操作受託収入 | I94: 振替伝票（調定） | J94: 20001588 | K94: 000 | L94: 001 | M94: 1 | N94: 0481141700 | O94: 下水道事業収益 | P94: 営業収益 | Q94: その他営業収益 | R94: 業務受託収益 | T94: 999999 | U94: 共通 | V94: 0 | W94: 0 | X94: 0 | Y94: 122020 | Z94: 021402001010010000 | AA94: 未収その他営業収益 | AB94: 122020 | AC94: 048114001017000000 | AD94: 業務受託収益 | AE94: 122020 | AF94: 17 | AG94: 10 | AH94: 11092 | AI94: 110928 | AJ94: 広島県西部建設事務所長 | AL94: 20001588-000-001-1-0481141700-999999-17 | AM94: 1 | AN94: 0 | AO94: 0 | AP94: 0 | AS94: 17 | AT94: 10 | AV94: 0 | AW94: 122020 | AX94: 0 | AY94: 122020 | AZ94: 0 | BA94: 0 | BB94: 0 | BC94: 122020 | BD94: 0 | BF94: =+IFERROR(ROUND(AV94*100/(100+$AT94),0),AV94) -> 0 | BG94: =+IFERROR(ROUND(AW94*100/(100+$AT94),0),AW94) -> 110927 | BH94: =+IFERROR(ROUND(AX94*100/(100+$AT94),0),AX94) -> 0 | BI94: =SUM(BF94:BH94) -> 110927 | BJ94: =+IFERROR(ROUND(AZ94*100/(100+$AT94),0),AZ94) -> 0 | BK94: =+IFERROR(ROUND(BA94*100/(100+$AT94),0),BA94) -> 0 | BL94: =SUM(BJ94:BK94) -> 0 | BM94: =+BI94+BL94 -> 110927 | BQ94: =AY94*100/(100+$AT94)-BI94 -> 0.27272727 | BR94: =BB94*100/(100+$AT94)-BL94 -> 0 | BS94: =AZ94*100/(100+$AT94)-BJ94 -> 0 | BT94: =BA94*100/(100+$AT94)-BK94 -> 0
A95: 1 | D95: 1873110500 | E95: 安芸・維持管理 | F95: R06/03/31 | G95: R06/03/31 | H95: 貫道排水樋門操作受託収入 | I95: 振替伝票（調定） | J95: 20001525 | K95: 000 | L95: 001 | M95: 1 | N95: 0481141700 | O95: 下水道事業収益 | P95: 営業収益 | Q95: その他営業収益 | R95: 業務受託収益 | T95: 999999 | U95: 共通 | V95: 0 | W95: 0 | X95: 0 | Y95: 385291 | Z95: 021402001010010000 | AA95: 未収その他営業収益 | AB95: 385291 | AC95: 048114001017000000 | AD95: 業務受託収益 | AE95: 385291 | AF95: 17 | AG95: 10 | AH95: 35026 | AI95: 350265 | AJ95: 広島県西部建設事務所長 | AL95: 20001525-000-001-1-0481141700-999999-17 | AM95: 1 | AN95: 0 | AO95: 0 | AP95: 0 | AS95: 17 | AT95: 10 | AV95: 0 | AW95: 385291 | AX95: 0 | AY95: 385291 | AZ95: 0 | BA95: 0 | BB95: 0 | BC95: 385291 | BD95: 0 | BF95: =+IFERROR(ROUND(AV95*100/(100+$AT95),0),AV95) -> 0 | BG95: =+IFERROR(ROUND(AW95*100/(100+$AT95),0),AW95) -> 350265 | BH95: =+IFERROR(ROUND(AX95*100/(100+$AT95),0),AX95) -> 0 | BI95: =SUM(BF95:BH95) -> 350265 | BJ95: =+IFERROR(ROUND(AZ95*100/(100+$AT95),0),AZ95) -> 0 | BK95: =+IFERROR(ROUND(BA95*100/(100+$AT95),0),BA95) -> 0 | BL95: =SUM(BJ95:BK95) -> 0 | BM95: =+BI95+BL95 -> 350265 | BQ95: =AY95*100/(100+$AT95)-BI95 -> -0.45454545 | BR95: =BB95*100/(100+$AT95)-BL95 -> 0 | BS95: =AZ95*100/(100+$AT95)-BJ95 -> 0 | BT95: =BA95*100/(100+$AT95)-BK95 -> 0
A96: 1 | D96: 1502111000 | E96: 維持課 | F96: R06/03/31 | G96: R06/03/31 | H96: 樋門の操作及び点検費用（下半期） | I96: 振替伝票（調定） | J96: 20001500 | K96: 000 | L96: 001 | M96: 1 | N96: 0481141700 | O96: 下水道事業収益 | P96: 営業収益 | Q96: その他営業収益 | R96: 業務受託収益 | T96: 999999 | U96: 共通 | V96: 0 | W96: 0 | X96: 0 | Y96: 316123 | Z96: 021402001010010000 | AA96: 未収その他営業収益 | AB96: 316123 | AC96: 048114001017000000 | AD96: 業務受託収益 | AE96: 316123 | AF96: 17 | AG96: 10 | AH96: 28738 | AI96: 287385 | AJ96: 国土交通省中国地方整備局太田川河川事務所 | AL96: 20001500-000-001-1-0481141700-999999-17 | AM96: 1 | AN96: 0 | AO96: 0 | AP96: 上半期は税区分が旧コードになっていた | AS96: 17 | AT96: 10 | AV96: 316123 | AW96: 0 | AX96: 0 | AY96: 316123 | AZ96: 0 | BA96: 0 | BB96: 0 | BC96: 316123 | BD96: 0 | BF96: =+IFERROR(ROUND(AV96*100/(100+$AT96),0),AV96) -> 287385 | BG96: =+IFERROR(ROUND(AW96*100/(100+$AT96),0),AW96) -> 0 | BH96: =+IFERROR(ROUND(AX96*100/(100+$AT96),0),AX96) -> 0 | BI96: =SUM(BF96:BH96) -> 287385 | BJ96: =+IFERROR(ROUND(AZ96*100/(100+$AT96),0),AZ96) -> 0 | BK96: =+IFERROR(ROUND(BA96*100/(100+$AT96),0),BA96) -> 0 | BL96: =SUM(BJ96:BK96) -> 0 | BM96: =+BI96+BL96 -> 287385 | BQ96: =AY96*100/(100+$AT96)-BI96 -> -0.45454545 | BR96: =BB96*100/(100+$AT96)-BL96 -> 0 | BS96: =AZ96*100/(100+$AT96)-BJ96 -> 0 | BT96: =BA96*100/(100+$AT96)-BK96 -> 0
A97: 1 | D97: 1502111000 | E97: 維持課 | F97: R05/11/16 | G97: R05/11/16 | H97: 樋門の操作及び点検費用（上半期） | I97: 振替伝票（調定） | J97: 20000970 | K97: 000 | L97: 001 | M97: 1 | N97: 0481141700 | O97: 下水道事業収益 | P97: 営業収益 | Q97: その他営業収益 | R97: 業務受託収益 | T97: 999999 | U97: 共通 | V97: 0 | W97: 0 | X97: 0 | Y97: 586299 | Z97: 021402001010010000 | AA97: 未収その他営業収益 | AB97: 586299 | AC97: 048114001017000000 | AD97: 業務受託収益 | AE97: 586299 | AF97: 14 | AG97: 10 | AH97: 53299 | AI97: 533000 | AJ97: 国土交通省中国地方整備局太田川河川事務所 | AL97: 20000970-000-001-1-0481141700-999999-14 | AM97: 2 | AN97: 17 | AO97: 10 | AP97: 下半期は問題なし | AS97: 17 | AT97: 10 | AV97: 586299 | AW97: 0 | AX97: 0 | AY97: 586299 | AZ97: 0 | BA97: 0 | BB97: 0 | BC97: 586299 | BD97: 0 | BF97: =+IFERROR(ROUND(AV97*100/(100+$AT97),0),AV97) -> 532999 | BG97: =+IFERROR(ROUND(AW97*100/(100+$AT97),0),AW97) -> 0 | BH97: =+IFERROR(ROUND(AX97*100/(100+$AT97),0),AX97) -> 0 | BI97: =SUM(BF97:BH97) -> 532999 | BJ97: =+IFERROR(ROUND(AZ97*100/(100+$AT97),0),AZ97) -> 0 | BK97: =+IFERROR(ROUND(BA97*100/(100+$AT97),0),BA97) -> 0 | BL97: =SUM(BJ97:BK97) -> 0 | BM97: =+BI97+BL97 -> 532999 | BQ97: =AY97*100/(100+$AT97)-BI97 -> 0.090909091 | BR97: =BB97*100/(100+$AT97)-BL97 -> 0 | BS97: =AZ97*100/(100+$AT97)-BJ97 -> 0 | BT97: =BA97*100/(100+$AT97)-BK97 -> 0
A98: 1 | D98: 1883110500 | E98: 佐伯・維持管理 | F98: R06/03/29 | G98: R06/03/29 | H98: 下水道境界証明手数料 | I98: 収入伝票（事後調定・予算外） | J98: 20001573 | K98: 000 | L98: 001 | M98: 1 | N98: 0481141915 | O98: 下水道事業収益 | P98: 営業収益 | Q98: その他営業収益 | R98: 手数料 | S98: 証明手数料 | T98: 999999 | U98: 共通 | V98: 0 | W98: 0 | X98: 0 | Y98: 300 | Z98: 021202001001000000 | AA98: 現金 | AB98: 300 | AC98: 048114001019015000 | AD98: 証明手数料 | AE98: 300 | AF98: 21 | AG98: 0 | AH98: 0 | AI98: 300 | AJ98: 藤井 英喜 | AL98: 20001573-000-001-1-0481141915-999999-21 | AM98: 1 | AN98: 0 | AO98: 0 | AP98: 0 | AS98: 21 | AT98: 0 | AV98: 138 | AW98: 0 | AX98: 0 | AY98: 138 | AZ98: 0 | BA98: 162 | BB98: 162 | BC98: 300 | BD98: 0 | BF98: =+IFERROR(ROUND(AV98*100/(100+$AT98),0),AV98) -> 138 | BG98: =+IFERROR(ROUND(AW98*100/(100+$AT98),0),AW98) -> 0 | BH98: =+IFERROR(ROUND(AX98*100/(100+$AT98),0),AX98) -> 0 | BI98: =SUM(BF98:BH98) -> 138 | BJ98: =+IFERROR(ROUND(AZ98*100/(100+$AT98),0),AZ98) -> 0 | BK98: =+IFERROR(ROUND(BA98*100/(100+$AT98),0),BA98) -> 162 | BL98: =SUM(BJ98:BK98) -> 162 | BM98: =+BI98+BL98 -> 300 | BQ98: =AY98*100/(100+$AT98)-BI98 -> 0 | BR98: =BB98*100/(100+$AT98)-BL98 -> 0 | BS98: =AZ98*100/(100+$AT98)-BJ98 -> 0 | BT98: =BA98*100/(100+$AT98)-BK98 -> 0
A99: 1 | D99: 1883110500 | E99: 佐伯・維持管理 | F99: R06/03/29 | G99: R06/03/29 | H99: 下水道境界証明手数料 | I99: 収入伝票（事後調定・予算外） | J99: 20001573 | K99: 000 | L99: 002 | M99: 1 | N99: 0481141915 | O99: 下水道事業収益 | P99: 営業収益 | Q99: その他営業収益 | R99: 手数料 | S99: 証明手数料 | T99: 999999 | U99: 共通 | V99: 0 | W99: 0 | X99: 0 | Y99: 300 | Z99: 021202001001000000 | AA99: 現金 | AB99: 300 | AC99: 048114001019015000 | AD99: 証明手数料 | AE99: 300 | AF99: 21 | AG99: 0 | AH99: 0 | AI99: 300 | AJ99: 橋本 浩子 | AL99: 20001573-000-002-1-0481141915-999999-21 | AM99: 1 | AN99: 0 | AO99: 0 | AP99: 0 | AS99: 21 | AT99: 0 | AV99: 138 | AW99: 0 | AX99: 0 | AY99: 138 | AZ99: 0 | BA99: 162 | BB99: 162 | BC99: 300 | BD99: 0 | BF99: =+IFERROR(ROUND(AV99*100/(100+$AT99),0),AV99) -> 138 | BG99: =+IFERROR(ROUND(AW99*100/(100+$AT99),0),AW99) -> 0 | BH99: =+IFERROR(ROUND(AX99*100/(100+$AT99),0),AX99) -> 0 | BI99: =SUM(BF99:BH99) -> 138 | BJ99: =+IFERROR(ROUND(AZ99*100/(100+$AT99),0),AZ99) -> 0 | BK99: =+IFERROR(ROUND(BA99*100/(100+$AT99),0),BA99) -> 162 | BL99: =SUM(BJ99:BK99) -> 162 | BM99: =+BI99+BL99 -> 300 | BQ99: =AY99*100/(100+$AT99)-BI99 -> 0 | BR99: =BB99*100/(100+$AT99)-BL99 -> 0 | BS99: =AZ99*100/(100+$AT99)-BJ99 -> 0 | BT99: =BA99*100/(100+$AT99)-BK99 -> 0
A100: 1 | D100: 1883110500 | E100: 佐伯・維持管理 | F100: R06/03/29 | G100: R06/03/29 | H100: 下水道境界証明手数料 | I100: 収入伝票（事後調定・予算外） | J100: 20001573 | K100: 000 | L100: 003 | M100: 1 | N100: 0481141915 | O100: 下水道事業収益 | P100: 営業収益 | Q100: その他営業収益 | R100: 手数料 | S100: 証明手数料 | T100: 999999 | U100: 共通 | V100: 0 | W100: 0 | X100: 0 | Y100: 600 | Z100: 021202001001000000 | AA100: 現金 | AB100: 600 | AC100: 048114001019015000 | AD100: 証明手数料 | AE100: 600 | AF100: 21 | AG100: 0 | AH100: 0 | AI100: 600 | AJ100: 岸川 佳弘 | AL100: 20001573-000-003-1-0481141915-999999-21 | AM100: 1 | AN100: 0 | AO100: 0 | AP100: 0 | AS100: 21 | AT100: 0 | AV100: 276 | AW100: 0 | AX100: 0 | AY100: 276 | AZ100: 0 | BA100: 324 | BB100: 324 | BC100: 600 | BD100: 0 | BF100: =+IFERROR(ROUND(AV100*100/(100+$AT100),0),AV100) -> 276 | BG100: =+IFERROR(ROUND(AW100*100/(100+$AT100),0),AW100) -> 0 | BH100: =+IFERROR(ROUND(AX100*100/(100+$AT100),0),AX100) -> 0 | BI100: =SUM(BF100:BH100) -> 276 | BJ100: =+IFERROR(ROUND(AZ100*100/(100+$AT100),0),AZ100) -> 0 | BK100: =+IFERROR(ROUND(BA100*100/(100+$AT100),0),BA100) -> 324 | BL100: =SUM(BJ100:BK100) -> 324 | BM100: =+BI100+BL100 -> 600 | BQ100: =AY100*100/(100+$AT100)-BI100 -> 0 | BR100: =BB100*100/(100+$AT100)-BL100 -> 0 | BS100: =AZ100*100/(100+$AT100)-BJ100 -> 0 | BT100: =BA100*100/(100+$AT100)-BK100 -> 0
A101: 1 | D101: 1883110500 | E101: 佐伯・維持管理 | F101: R06/03/29 | G101: R06/03/29 | H101: 下水道境界証明手数料 | I101: 収入伝票（事後調定・予算外） | J101: 20001573 | K101: 000 | L101: 004 | M101: 1 | N101: 0481141915 | O101: 下水道事業収益 | P101: 営業収益 | Q101: その他営業収益 | R101: 手数料 | S101: 証明手数料 | T101: 999999 | U101: 共通 | V101: 0 | W101: 0 | X101: 0 | Y101: 200 | Z101: 021202001001000000 | AA101: 現金 | AB101: 200 | AC101: 048114001019015000 | AD101: 証明手数料 | AE101: 200 | AF101: 21 | AG101: 0 | AH101: 0 | AI101: 200 | AJ101: 中本 淨子 | AL101: 20001573-000-004-1-0481141915-999999-21 | AM101: 1 | AN101: 0 | AO101: 0 | AP101: 0 | AS101: 21 | AT101: 0 | AV101: 92 | AW101: 0 | AX101: 0 | AY101: 92 | AZ101: 0 | BA101: 108 | BB101: 108 | BC101: 200 | BD101: 0 | BF101: =+IFERROR(ROUND(AV101*100/(100+$AT101),0),AV101) -> 92 | BG101: =+IFERROR(ROUND(AW101*100/(100+$AT101),0),AW101) -> 0 | BH101: =+IFERROR(ROUND(AX101*100/(100+$AT101),0),AX101) -> 0 | BI101: =SUM(BF101:BH101) -> 92 | BJ101: =+IFERROR(ROUND(AZ101*100/(100+$AT101),0),AZ101) -> 0 | BK101: =+IFERROR(ROUND(BA101*100/(100+$AT101),0),BA101) -> 108 | BL101: =SUM(BJ101:BK101) -> 108 | BM101: =+BI101+BL101 -> 200 | BQ101: =AY101*100/(100+$AT101)-BI101 -> 0 | BR101: =BB101*100/(100+$AT101)-BL101 -> 0 | BS101: =AZ101*100/(100+$AT101)-BJ101 -> 0 | BT101: =BA101*100/(100+$AT101)-BK101 -> 0
A102: 1 | D102: 1883110500 | E102: 佐伯・維持管理 | F102: R06/02/27 | G102: R06/02/27 | H102: 下水道境界証明手数料 | I102: 収入伝票（事後調定・予算外） | J102: 20001415 | K102: 000 | L102: 001 | M102: 1 | N102: 0481141915 | O102: 下水道事業収益 | P102: 営業収益 | Q102: その他営業収益 | R102: 手数料 | S102: 証明手数料 | T102: 999999 | U102: 共通 | V102: 0 | W102: 0 | X102: 0 | Y102: 600 | Z102: 021202001001000000 | AA102: 現金 | AB102: 600 | AC102: 048114001019015000 | AD102: 証明手数料 | AE102: 600 | AF102: 21 | AG102: 0 | AH102: 0 | AI102: 600 | AJ102: 堀尾 哲雄 | AL102: 20001415-000-001-1-0481141915-999999-21 | AM102: 1 | AN102: 0 | AO102: 0 | AP102: 0 | AS102: 21 | AT102: 0 | AV102: 276 | AW102: 0 | AX102: 0 | AY102: 276 | AZ102: 0 | BA102: 324 | BB102: 324 | BC102: 600 | BD102: 0 | BF102: =+IFERROR(ROUND(AV102*100/(100+$AT102),0),AV102) -> 276 | BG102: =+IFERROR(ROUND(AW102*100/(100+$AT102),0),AW102) -> 0 | BH102: =+IFERROR(ROUND(AX102*100/(100+$AT102),0),AX102) -> 0 | BI102: =SUM(BF102:BH102) -> 276 | BJ102: =+IFERROR(ROUND(AZ102*100/(100+$AT102),0),AZ102) -> 0 | BK102: =+IFERROR(ROUND(BA102*100/(100+$AT102),0),BA102) -> 324 | BL102: =SUM(BJ102:BK102) -> 324 | BM102: =+BI102+BL102 -> 600 | BQ102: =AY102*100/(100+$AT102)-BI102 -> 0 | BR102: =BB102*100/(100+$AT102)-BL102 -> 0 | BS102: =AZ102*100/(100+$AT102)-BJ102 -> 0 | BT102: =BA102*100/(100+$AT102)-BK102 -> 0
A103: 1 | D103: 1833110500 | E103: 南・維持管理課 | F103: R06/03/05 | G103: R06/03/05 | H103: 下水道境界証明手数料 | I103: 収入伝票（事後調定・予算外） | J103: 20001450 | K103: 000 | L103: 001 | M103: 1 | N103: 0481141915 | O103: 下水道事業収益 | P103: 営業収益 | Q103: その他営業収益 | R103: 手数料 | S103: 証明手数料 | T103: 999999 | U103: 共通 | V103: 0 | W103: 0 | X103: 0 | Y103: 940 | Z103: 021202001001000000 | AA103: 現金 | AB103: 940 | AC103: 048114001019015000 | AD103: 証明手数料 | AE103: 940 | AF103: 21 | AG103: 0 | AH103: 0 | AI103: 940 | AL103: 20001450-000-001-1-0481141915-999999-21 | AM103: 1 | AN103: 0 | AO103: 0 | AP103: 0 | AS103: 21 | AT103: 0 | AV103: 432 | AW103: 0 | AX103: 0 | AY103: 432 | AZ103: 0 | BA103: 508 | BB103: 508 | BC103: 940 | BD103: 0 | BF103: =+IFERROR(ROUND(AV103*100/(100+$AT103),0),AV103) -> 432 | BG103: =+IFERROR(ROUND(AW103*100/(100+$AT103),0),AW103) -> 0 | BH103: =+IFERROR(ROUND(AX103*100/(100+$AT103),0),AX103) -> 0 | BI103: =SUM(BF103:BH103) -> 432 | BJ103: =+IFERROR(ROUND(AZ103*100/(100+$AT103),0),AZ103) -> 0 | BK103: =+IFERROR(ROUND(BA103*100/(100+$AT103),0),BA103) -> 508 | BL103: =SUM(BJ103:BK103) -> 508 | BM103: =+BI103+BL103 -> 940 | BQ103: =AY103*100/(100+$AT103)-BI103 -> 0 | BR103: =BB103*100/(100+$AT103)-BL103 -> 0 | BS103: =AZ103*100/(100+$AT103)-BJ103 -> 0 | BT103: =BA103*100/(100+$AT103)-BK103 -> 0
A104: 1 | D104: 1883110500 | E104: 佐伯・維持管理 | F104: R05/07/13 | G104: R05/07/13 | H104: 下水道境界証明手数料 | I104: 収入伝票（事後調定・予算外） | J104: 20000487 | K104: 000 | L104: 001 | M104: 1 | N104: 0481141915 | O104: 下水道事業収益 | P104: 営業収益 | Q104: その他営業収益 | R104: 手数料 | S104: 証明手数料 | T104: 999999 | U104: 共通 | V104: 0 | W104: 0 | X104: 0 | Y104: 300 | Z104: 021202001001000000 | AA104: 現金 | AB104: 300 | AC104: 048114001019015000 | AD104: 証明手数料 | AE104: 300 | AF104: 21 | AG104: 0 | AH104: 0 | AI104: 300 | AJ104: 末石 道江 | AL104: 20000487-000-001-1-0481141915-999999-21 | AM104: 1 | AN104: 0 | AO104: 0 | AP104: 0 | AS104: 21 | AT104: 0 | AV104: 138 | AW104: 0 | AX104: 0 | AY104: 138 | AZ104: 0 | BA104: 162 | BB104: 162 | BC104: 300 | BD104: 0 | BF104: =+IFERROR(ROUND(AV104*100/(100+$AT104),0),AV104) -> 138 | BG104: =+IFERROR(ROUND(AW104*100/(100+$AT104),0),AW104) -> 0 | BH104: =+IFERROR(ROUND(AX104*100/(100+$AT104),0),AX104) -> 0 | BI104: =SUM(BF104:BH104) -> 138 | BJ104: =+IFERROR(ROUND(AZ104*100/(100+$AT104),0),AZ104) -> 0 | BK104: =+IFERROR(ROUND(BA104*100/(100+$AT104),0),BA104) -> 162 | BL104: =SUM(BJ104:BK104) -> 162 | BM104: =+BI104+BL104 -> 300 | BQ104: =AY104*100/(100+$AT104)-BI104 -> 0 | BR104: =BB104*100/(100+$AT104)-BL104 -> 0 | BS104: =AZ104*100/(100+$AT104)-BJ104 -> 0 | BT104: =BA104*100/(100+$AT104)-BK104 -> 0
A105: 1 | D105: 1883110500 | E105: 佐伯・維持管理 | F105: R05/06/05 | G105: R05/06/05 | H105: 下水道境界証明手数料 | I105: 収入伝票（事後調定・予算外） | J105: 20000319 | K105: 000 | L105: 001 | M105: 1 | N105: 0481141915 | O105: 下水道事業収益 | P105: 営業収益 | Q105: その他営業収益 | R105: 手数料 | S105: 証明手数料 | T105: 999999 | U105: 共通 | V105: 0 | W105: 0 | X105: 0 | Y105: 300 | Z105: 021202001001000000 | AA105: 現金 | AB105: 300 | AC105: 048114001019015000 | AD105: 証明手数料 | AE105: 300 | AF105: 21 | AG105: 0 | AH105: 0 | AI105: 300 | AJ105: 金澤 キヌエ | AL105: 20000319-000-001-1-0481141915-999999-21 | AM105: 1 | AN105: 0 | AO105: 0 | AP105: 0 | AS105: 21 | AT105: 0 | AV105: 138 | AW105: 0 | AX105: 0 | AY105: 138 | AZ105: 0 | BA105: 162 | BB105: 162 | BC105: 300 | BD105: 0 | BF105: =+IFERROR(ROUND(AV105*100/(100+$AT105),0),AV105) -> 138 | BG105: =+IFERROR(ROUND(AW105*100/(100+$AT105),0),AW105) -> 0 | BH105: =+IFERROR(ROUND(AX105*100/(100+$AT105),0),AX105) -> 0 | BI105: =SUM(BF105:BH105) -> 138 | BJ105: =+IFERROR(ROUND(AZ105*100/(100+$AT105),0),AZ105) -> 0 | BK105: =+IFERROR(ROUND(BA105*100/(100+$AT105),0),BA105) -> 162 | BL105: =SUM(BJ105:BK105) -> 162 | BM105: =+BI105+BL105 -> 300 | BQ105: =AY105*100/(100+$AT105)-BI105 -> 0 | BR105: =BB105*100/(100+$AT105)-BL105 -> 0 | BS105: =AZ105*100/(100+$AT105)-BJ105 -> 0 | BT105: =BA105*100/(100+$AT105)-BK105 -> 0
...

Sheet 雨汚支出
R1: 集計表（全体） | AV1: 雨水（税込） | AZ1: 汚水（税込） | BC1: 合計 （税込） | BD1: チェック | BF1: 雨水（税抜） | BJ1: 汚水（税抜） | BM1: 合計 （税抜） | BN1: 税抜き 要調整額 | BO1: 3条支出ｼｰﾄ集計値
AV2: 区域内 | AW2: 区域外 | AX2: 一般行政 | AY2: 計 | AZ2: 基準内 | BA2: 基準外 | BB2: 計 | BF2: 区域内 | BG2: 区域外 | BH2: 一般行政 | BI2: 計 | BJ2: 基準内 | BK2: 基準外 | BL2: 計
N3: 884025400 | O3: 下水道事業費用 | P3: 営業外費用 | Q3: 支払利息及び企業債取扱諸費 | R3: 一時借入金利息 | Y3: =+SUMIFS(Y$12:Y$380,$N$12:$N$380,$N3) -> 2483 | AV3: =+SUMIFS(AV$12:AV$135,$N$12:$N$135,$N3) -> 0 | AW3: =+SUMIFS(AW$12:AW$135,$N$12:$N$135,$N3) -> 0 | AX3: =+SUMIFS(AX$12:AX$135,$N$12:$N$135,$N3) -> 0 | AY3: =+SUMIFS(AY$12:AY$135,$N$12:$N$135,$N3) -> 0 | AZ3: =+SUMIFS(AZ$12:AZ$135,$N$12:$N$135,$N3) -> 0 | BA3: =+SUMIFS(BA$12:BA$135,$N$12:$N$135,$N3) -> 2483 | BB3: =+SUMIFS(BB$12:BB$135,$N$12:$N$135,$N3) -> 2483 | BC3: =+SUMIFS(BC$12:BC$135,$N$12:$N$135,$N3) -> 2483 | BD3: =+SUMIFS(BD$12:BD$135,$N$12:$N$135,$N3) -> 0 | BF3: =+SUMIFS(BF$12:BF$135,$N$12:$N$135,$N3) -> 0 | BG3: =+SUMIFS(BG$12:BG$135,$N$12:$N$135,$N3) -> 0 | BH3: =+SUMIFS(BH$12:BH$135,$N$12:$N$135,$N3) -> 0 | BI3: =+SUMIFS(BI$12:BI$135,$N$12:$N$135,$N3) -> 0 | BJ3: =+SUMIFS(BJ$12:BJ$135,$N$12:$N$135,$N3) -> 0 | BK3: =+SUMIFS(BK$12:BK$135,$N$12:$N$135,$N3) -> 2483 | BL3: =+SUMIFS(BL$12:BL$135,$N$12:$N$135,$N3) -> 2483 | BM3: =+SUMIFS(BM$12:BM$135,$N$12:$N$135,$N3) -> 2483 | BN3: =+BO3-BM3 -> 0 | BO3: =+[1]営外!T11 -> 2483
N4: 884066200 | O4: 下水道事業費用 | P4: 営業外費用 | Q4: 雑支出 | R4: 還付加算金 | Y4: =+SUMIFS(Y$12:Y$380,$N$12:$N$380,$N4) -> 0 | AV4: =+SUMIFS(AV$12:AV$135,$N$12:$N$135,$N4) -> 0 | AW4: =+SUMIFS(AW$12:AW$135,$N$12:$N$135,$N4) -> 0 | AX4: =+SUMIFS(AX$12:AX$135,$N$12:$N$135,$N4) -> 0 | AY4: =+SUMIFS(AY$12:AY$135,$N$12:$N$135,$N4) -> 0 | AZ4: =+SUMIFS(AZ$12:AZ$135,$N$12:$N$135,$N4) -> 0 | BA4: =+SUMIFS(BA$12:BA$135,$N$12:$N$135,$N4) -> 0 | BB4: =+SUMIFS(BB$12:BB$135,$N$12:$N$135,$N4) -> 0 | BC4: =+SUMIFS(BC$12:BC$135,$N$12:$N$135,$N4) -> 0 | BD4: =+SUMIFS(BD$12:BD$135,$N$12:$N$135,$N4) -> 0 | BF4: =+SUMIFS(BF$12:BF$135,$N$12:$N$135,$N4) -> 0 | BG4: =+SUMIFS(BG$12:BG$135,$N$12:$N$135,$N4) -> 0 | BH4: =+SUMIFS(BH$12:BH$135,$N$12:$N$135,$N4) -> 0 | BI4: =+SUMIFS(BI$12:BI$135,$N$12:$N$135,$N4) -> 0 | BJ4: =+SUMIFS(BJ$12:BJ$135,$N$12:$N$135,$N4) -> 0 | BK4: =+SUMIFS(BK$12:BK$135,$N$12:$N$135,$N4) -> 0 | BL4: =+SUMIFS(BL$12:BL$135,$N$12:$N$135,$N4) -> 0 | BM4: =+SUMIFS(BM$12:BM$135,$N$12:$N$135,$N4) -> 0 | BN4: =+BO4-BM4 -> 0 | BO4: =+[1]営外!T15 -> 0
N5: 884066300 | O5: 下水道事業費用 | P5: 営業外費用 | Q5: 雑支出 | R5: その他雑支出 | Y5: =+SUMIFS(Y$12:Y$380,$N$12:$N$380,$N5) -> 9224169 | AV5: =+SUMIFS(AV$12:AV$135,$N$12:$N$135,$N5) -> 0 | AW5: =+SUMIFS(AW$12:AW$135,$N$12:$N$135,$N5) -> 0 | AX5: =+SUMIFS(AX$12:AX$135,$N$12:$N$135,$N5) -> 0 | AY5: =+SUMIFS(AY$12:AY$135,$N$12:$N$135,$N5) -> 0 | AZ5: =+SUMIFS(AZ$12:AZ$135,$N$12:$N$135,$N5) -> 0 | BA5: =+SUMIFS(BA$12:BA$135,$N$12:$N$135,$N5) -> 9224169 | BB5: =+SUMIFS(BB$12:BB$135,$N$12:$N$135,$N5) -> 9224169 | BC5: =+SUMIFS(BC$12:BC$135,$N$12:$N$135,$N5) -> 9224169 | BD5: =+SUMIFS(BD$12:BD$135,$N$12:$N$135,$N5) -> 0 | BF5: =+SUMIFS(BF$12:BF$135,$N$12:$N$135,$N5) -> 0 | BG5: =+SUMIFS(BG$12:BG$135,$N$12:$N$135,$N5) -> 0 | BH5: =+SUMIFS(BH$12:BH$135,$N$12:$N$135,$N5) -> 0 | BI5: =+SUMIFS(BI$12:BI$135,$N$12:$N$135,$N5) -> 0 | BJ5: =+SUMIFS(BJ$12:BJ$135,$N$12:$N$135,$N5) -> 0 | BK5: =+SUMIFS(BK$12:BK$135,$N$12:$N$135,$N5) -> 8734347 | BL5: =+SUMIFS(BL$12:BL$135,$N$12:$N$135,$N5) -> 8734347 | BM5: =+SUMIFS(BM$12:BM$135,$N$12:$N$135,$N5) -> 8734347 | BN5: =+BO5-BM5 -> 0 | BO5: =+[1]営外!T16 -> 8734347
N6: 885020200 | O6: 下水道事業費用 | P6: 特別損失 | Q6: 固定資産売却損 | R6: 固定資産売却損 | Y6: =+SUMIFS(Y$12:Y$380,$N$12:$N$380,$N6) -> 10315355 | AV6: =+SUMIFS(AV$12:AV$135,$N$12:$N$135,$N6) -> 0 | AW6: =+SUMIFS(AW$12:AW$135,$N$12:$N$135,$N6) -> 0 | AX6: =+SUMIFS(AX$12:AX$135,$N$12:$N$135,$N6) -> 0 | AY6: =+SUMIFS(AY$12:AY$135,$N$12:$N$135,$N6) -> 0 | AZ6: =+SUMIFS(AZ$12:AZ$135,$N$12:$N$135,$N6) -> 0 | BA6: =+SUMIFS(BA$12:BA$135,$N$12:$N$135,$N6) -> 10315355 | BB6: =+SUMIFS(BB$12:BB$135,$N$12:$N$135,$N6) -> 10315355 | BC6: =+SUMIFS(BC$12:BC$135,$N$12:$N$135,$N6) -> 10315355 | BD6: =+SUMIFS(BD$12:BD$135,$N$12:$N$135,$N6) -> 0 | BF6: =+SUMIFS(BF$12:BF$135,$N$12:$N$135,$N6) -> 0 | BG6: =+SUMIFS(BG$12:BG$135,$N$12:$N$135,$N6) -> 0 | BH6: =+SUMIFS(BH$12:BH$135,$N$12:$N$135,$N6) -> 0 | BI6: =+SUMIFS(BI$12:BI$135,$N$12:$N$135,$N6) -> 0 | BJ6: =+SUMIFS(BJ$12:BJ$135,$N$12:$N$135,$N6) -> 0 | BK6: =+SUMIFS(BK$12:BK$135,$N$12:$N$135,$N6) -> 10315355 | BL6: =+SUMIFS(BL$12:BL$135,$N$12:$N$135,$N6) -> 10315355 | BM6: =+SUMIFS(BM$12:BM$135,$N$12:$N$135,$N6) -> 10315355 | BN6: =+BO6-BM6 -> 0 | BO6: =+[1]特損!T32 -> 10315355
N7: 885060600 | O7: 下水道事業費用 | P7: 特別損失 | Q7: 過年度損益修正損 | R7: 過年度損益修正損 | Y7: =+SUMIFS(Y$12:Y$380,$N$12:$N$380,$N7) -> 10679943 | AV7: =+SUMIFS(AV$12:AV$135,$N$12:$N$135,$N7) -> 6760 | AW7: =+SUMIFS(AW$12:AW$135,$N$12:$N$135,$N7) -> 0 | AX7: =+SUMIFS(AX$12:AX$135,$N$12:$N$135,$N7) -> 0 | AY7: =+SUMIFS(AY$12:AY$135,$N$12:$N$135,$N7) -> 6760 | AZ7: =+SUMIFS(AZ$12:AZ$135,$N$12:$N$135,$N7) -> 0 | BA7: =+SUMIFS(BA$12:BA$135,$N$12:$N$135,$N7) -> 10673183 | BB7: =+SUMIFS(BB$12:BB$135,$N$12:$N$135,$N7) -> 10673183 | BC7: =+SUMIFS(BC$12:BC$135,$N$12:$N$135,$N7) -> 10679943 | BD7: =+SUMIFS(BD$12:BD$135,$N$12:$N$135,$N7) -> 0 | BF7: =+SUMIFS(BF$12:BF$135,$N$12:$N$135,$N7) -> 6733 | BG7: =+SUMIFS(BG$12:BG$135,$N$12:$N$135,$N7) -> 0 | BH7: =+SUMIFS(BH$12:BH$135,$N$12:$N$135,$N7) -> 0 | BI7: =+SUMIFS(BI$12:BI$135,$N$12:$N$135,$N7) -> 6733 | BJ7: =+SUMIFS(BJ$12:BJ$135,$N$12:$N$135,$N7) -> 0 | BK7: =+SUMIFS(BK$12:BK$135,$N$12:$N$135,$N7) -> 9704766 | BL7: =+SUMIFS(BL$12:BL$135,$N$12:$N$135,$N7) -> 9704766 | BM7: =+SUMIFS(BM$12:BM$135,$N$12:$N$135,$N7) -> 9711499 | BN7: =+BO7-BM7 -> 0 | BO7: =+[1]特損!T5 -> 9711499
N8: 885080800 | O8: 下水道事業費用 | P8: 特別損失 | Q8: その他特別損失 | R8: その他特別損失 | Y8: =+SUMIFS(Y$12:Y$380,$N$12:$N$380,$N8) -> 0 | AV8: =+SUMIFS(AV$12:AV$135,$N$12:$N$135,$N8) -> 0 | AW8: =+SUMIFS(AW$12:AW$135,$N$12:$N$135,$N8) -> 0 | AX8: =+SUMIFS(AX$12:AX$135,$N$12:$N$135,$N8) -> 0 | AY8: =+SUMIFS(AY$12:AY$135,$N$12:$N$135,$N8) -> 0 | AZ8: =+SUMIFS(AZ$12:AZ$135,$N$12:$N$135,$N8) -> 0 | BA8: =+SUMIFS(BA$12:BA$135,$N$12:$N$135,$N8) -> 0 | BB8: =+SUMIFS(BB$12:BB$135,$N$12:$N$135,$N8) -> 0 | BC8: =+SUMIFS(BC$12:BC$135,$N$12:$N$135,$N8) -> 0 | BD8: =+SUMIFS(BD$12:BD$135,$N$12:$N$135,$N8) -> 0 | BF8: =+SUMIFS(BF$12:BF$135,$N$12:$N$135,$N8) -> 0 | BG8: =+SUMIFS(BG$12:BG$135,$N$12:$N$135,$N8) -> 0 | BH8: =+SUMIFS(BH$12:BH$135,$N$12:$N$135,$N8) -> 0 | BI8: =+SUMIFS(BI$12:BI$135,$N$12:$N$135,$N8) -> 0 | BJ8: =+SUMIFS(BJ$12:BJ$135,$N$12:$N$135,$N8) -> 0 | BK8: =+SUMIFS(BK$12:BK$135,$N$12:$N$135,$N8) -> 0 | BL8: =+SUMIFS(BL$12:BL$135,$N$12:$N$135,$N8) -> 0 | BM8: =+SUMIFS(BM$12:BM$135,$N$12:$N$135,$N8) -> 0 | BN8: =+BO8-BM8 -> 0 | BO8: =+[1]特損!T14 -> 0
Y10: =+SUBTOTAL(109,Y12:Y135) -> 10679082 | AV10: =+SUBTOTAL(109,AV12:AV135) -> 0 | AW10: =+SUBTOTAL(109,AW12:AW135) -> 0 | AX10: =+SUBTOTAL(109,AX12:AX135) -> 0 | AY10: =+SUBTOTAL(109,AY12:AY135) -> 0 | AZ10: =+SUBTOTAL(109,AZ12:AZ135) -> 0 | BA10: =+SUBTOTAL(109,BA12:BA135) -> 10679082 | BB10: =+SUBTOTAL(109,BB12:BB135) -> 10679082 | BC10: =+SUBTOTAL(109,BC12:BC135) -> 10679082 | BD10: =+SUBTOTAL(109,BD12:BD135) -> 0 | BF10: =+SUBTOTAL(109,BF12:BF135) -> 0 | BG10: =+SUBTOTAL(109,BG12:BG135) -> 0 | BH10: =+SUBTOTAL(109,BH12:BH135) -> 0 | BI10: =+SUBTOTAL(109,BI12:BI135) -> 0 | BJ10: =+SUBTOTAL(109,BJ12:BJ135) -> 0 | BK10: =+SUBTOTAL(109,BK12:BK135) -> 9708919 | BL10: =+SUBTOTAL(109,BL12:BL135) -> 9708919 | BM10: =+SUBTOTAL(109,BM12:BM135) -> 9708919
AL11: ---- | AS11: 0 | AT11: 0 | AV11: 雨水（税込） | AZ11: 汚水（税込） | BC11: 合計 （税込） | BD11: チェック | BF11: 雨水（税抜） | BJ11: 汚水（税抜） | BM11: 合計 （税抜） | BN11: 備考
A12: 事業区分 | B12: 所属 | C12: 所属名 | D12: 主管課 | E12: 主管課名 | F12: 年月日 | G12: 振替年月日 | H12: 事項 | I12: 種別 | J12: 伝票番号 | K12: 枝番 | L12: 内訳番号 | M12: 現繰 | N12: 予算科目 | O12: 款名称 | P12: 項名称 | Q12: 目名称 | R12: 節名称 | S12: 細節名称 | T12: 事業コード | U12: 事業名 | V12: 予算額 | W12: 概算額 | X12: 確定額 | Y12: 執行額 | Z12: 借方勘定 | AA12: 借方勘定科目 | AB12: 借方金額 | AC12: 貸方勘定 | AD12: 貸方勘定科目 | AE12: 貸方金額 | AF12: 税区分 | AG12: 税率 | AH12: 税額 | AI12: 税抜金額 | AJ12: 債権者 | AL12: 複合伝票番号 | AM12: 確認状況 | AN12: 正しい課税区分 | AO12: 正しい税率 | AP12: 備考 | AQ12: 重複 | AS12: 集計用課税区分 | AT12: 集計用税率 | AV12: 区域内 | AW12: 区域外 | AX12: 一般行政 | AY12: 計 | AZ12: 基準内 | BA12: 基準外 | BB12: 計 | BF12: 区域内 | BG12: 区域外 | BH12: 一般行政 | BI12: 計 | BJ12: 基準内 | BK12: 基準外 | BL12: 計
A13: 1 | D13: 1501110500 | E13: 経営企画課 | F13: R06/03/31 | G13: R06/03/31 | H13: 歳計現金の一時繰替金利子 | I13: 振替伝票（未払計上） | J13: 34007041 | K13: 000 | L13: 001 | M13: 1 | N13: 0884025400 | O13: 下水道事業費用 | P13: 営業外費用 | Q13: 支払利息及び企業債取扱諸費 | R13: 一時借入金利息 | T13: 912464 | U13: 局の経理事務（一時借入金利息） | V13: 0 | W13: 0 | X13: 0 | Y13: 2477 | Z13: 088402001054000000 | AA13: 一時借入金利息 | AB13: 2477 | AC13: 051410001001000000 | AD13: その他未払金 | AE13: 2477 | AF13: 21 | AG13: 0 | AH13: 0 | AI13: 2477 | AJ13: 広島市長 松井 一實 | AL13: 34007041-000-001-1-0884025400-912464-21 | AM13: 1 | AN13: 0 | AO13: 0 | AP13: 0 | AS13: 21 | AT13: 0 | AV13: 0 | AW13: 0 | AX13: 0 | AY13: 0 | AZ13: 0 | BA13: 2477 | BB13: 2477 | BC13: 2477 | BD13: 0 | BF13: =+IFERROR(ROUND(AV13*100/(100+$AT13),0),AV13) -> 0 | BG13: =+IFERROR(ROUND(AW13*100/(100+$AT13),0),AW13) -> 0 | BH13: =+IFERROR(ROUND(AX13*100/(100+$AT13),0),AX13) -> 0 | BI13: =SUM(BF13:BH13) -> 0 | BJ13: =+IFERROR(ROUND(AZ13*100/(100+$AT13),0),AZ13) -> 0 | BK13: =+IFERROR(ROUND(BA13*100/(100+$AT13),0),BA13) -> 2477 | BL13: =SUM(BJ13:BK13) -> 2477 | BM13: =+BI13+BL13 -> 2477 | BO13: =AV13*100/(100+$AT13)-BF13 -> 0 | BP13: =AW13*100/(100+$AT13)-BG13 -> 0 | BQ13: =AX13*100/(100+$AT13)-BH13 -> 0 | BR13: =AY13*100/(100+$AT13)-BI13 -> 0 | BS13: =AZ13*100/(100+$AT13)-BJ13 -> 0 | BT13: =BA13*100/(100+$AT13)-BK13 -> 0 | BU13: =BB13*100/(100+$AT13)-BL13 -> 0
A14: 4 | D14: 1501110500 | E14: 経営企画課 | F14: R06/03/31 | G14: R06/03/31 | H14: 歳計現金の一時繰替金利子 | I14: 振替伝票（未払計上） | J14: 34007041 | K14: 000 | L14: 002 | M14: 1 | N14: 0884025400 | O14: 下水道事業費用 | P14: 営業外費用 | Q14: 支払利息及び企業債取扱諸費 | R14: 一時借入金利息 | T14: 912496 | U14: 局の経理事務（一時借入金利息） | V14: 0 | W14: 0 | X14: 0 | Y14: 6 | Z14: 088402001054000000 | AA14: 一時借入金利息 | AB14: 6 | AC14: 051410001001000000 | AD14: その他未払金 | AE14: 6 | AF14: 21 | AG14: 0 | AH14: 0 | AI14: 6 | AJ14: 広島市長 松井 一實 | AL14: 34007041-000-002-1-0884025400-912496-21 | AM14: 1 | AN14: 0 | AO14: 0 | AP14: 0 | AS14: 21 | AT14: 0 | AV14: 0 | AW14: 0 | AX14: 0 | AY14: 0 | AZ14: 0 | BA14: 6 | BB14: 6 | BC14: 6 | BD14: 0 | BF14: =+IFERROR(ROUND(AV14*100/(100+$AT14),0),AV14) -> 0 | BG14: =+IFERROR(ROUND(AW14*100/(100+$AT14),0),AW14) -> 0 | BH14: =+IFERROR(ROUND(AX14*100/(100+$AT14),0),AX14) -> 0 | BI14: =SUM(BF14:BH14) -> 0 | BJ14: =+IFERROR(ROUND(AZ14*100/(100+$AT14),0),AZ14) -> 0 | BK14: =+IFERROR(ROUND(BA14*100/(100+$AT14),0),BA14) -> 6 | BL14: =SUM(BJ14:BK14) -> 6 | BM14: =+BI14+BL14 -> 6 | BO14: =AV14*100/(100+$AT14)-BF14 -> 0 | BP14: =AW14*100/(100+$AT14)-BG14 -> 0 | BQ14: =AX14*100/(100+$AT14)-BH14 -> 0 | BR14: =AY14*100/(100+$AT14)-BI14 -> 0 | BS14: =AZ14*100/(100+$AT14)-BJ14 -> 0 | BT14: =BA14*100/(100+$AT14)-BK14 -> 0 | BU14: =BB14*100/(100+$AT14)-BL14 -> 0
A15: 1 | D15: 1502110500 | E15: 管理課 | F15: R06/01/10 | G15: R06/01/10 | H15: 下水道使用料返還金の支出 | I15: 振替伝票（未払計上） | J15: 34005121 | K15: 000 | L15: 001 | M15: 1 | N15: 0884066300 | O15: 下水道事業費用 | P15: 営業外費用 | Q15: 雑支出 | R15: その他雑支出 | T15: 921472 | U15: 下水道使用料賦課（返還金） | V15: 0 | W15: 0 | X15: 0 | Y15: 23932 | Z15: 088406001063000000 | AA15: その他雑支出 | AB15: 23932 | AC15: 051410001001000000 | AD15: その他未払金 | AE15: 23932 | AF15: 15 | AG15: 8 | AH15: 1767 | AI15: 22165 | AJ15: 田畑 美香 | AL15: 34005121-000-001-1-0884066300-921472-15 | AM15: 1 | AN15: 0 | AO15: 0 | AP15: 0 | AS15: 15 | AT15: 8 | AV15: 0 | AW15: 0 | AX15: 0 | AY15: 0 | AZ15: 0 | BA15: 23932 | BB15: 23932 | BC15: 23932 | BD15: 0 | BF15: =+IFERROR(ROUND(AV15*100/(100+$AT15),0),AV15) -> 0 | BG15: =+IFERROR(ROUND(AW15*100/(100+$AT15),0),AW15) -> 0 | BH15: =+IFERROR(ROUND(AX15*100/(100+$AT15),0),AX15) -> 0 | BI15: =SUM(BF15:BH15) -> 0 | BJ15: =+IFERROR(ROUND(AZ15*100/(100+$AT15),0),AZ15) -> 0 | BK15: =+IFERROR(ROUND(BA15*100/(100+$AT15),0),BA15) -> 22159 | BL15: =SUM(BJ15:BK15) -> 22159 | BM15: =+BI15+BL15 -> 22159 | BO15: =AV15*100/(100+$AT15)-BF15 -> 0 | BP15: =AW15*100/(100+$AT15)-BG15 -> 0 | BQ15: =AX15*100/(100+$AT15)-BH15 -> 0 | BR15: =AY15*100/(100+$AT15)-BI15 -> 0 | BS15: =AZ15*100/(100+$AT15)-BJ15 -> 0 | BT15: =BA15*100/(100+$AT15)-BK15 -> 0.25925926 | BU15: =BB15*100/(100+$AT15)-BL15 -> 0.25925926
A16: 1 | D16: 1502110500 | E16: 管理課 | F16: R06/01/10 | G16: R06/01/10 | H16: 下水道使用料返還金の支出 | I16: 振替伝票（未払計上） | J16: 34005121 | K16: 000 | L16: 002 | M16: 1 | N16: 0884066300 | O16: 下水道事業費用 | P16: 営業外費用 | Q16: 雑支出 | R16: その他雑支出 | T16: 921472 | U16: 下水道使用料賦課（返還金） | V16: 0 | W16: 0 | X16: 0 | Y16: 1964 | Z16: 088406001063000000 | AA16: その他雑支出 | AB16: 1964 | AC16: 051410001001000000 | AD16: その他未払金 | AE16: 1964 | AF16: 31 | AG16: 0 | AH16: 0 | AI16: 1964 | AJ16: 田畑 美香 | AL16: 34005121-000-002-1-0884066300-921472-31 | AM16: 1 | AN16: 0 | AO16: 0 | AP16: 0 | AS16: 31 | AT16: 0 | AV16: 0 | AW16: 0 | AX16: 0 | AY16: 0 | AZ16: 0 | BA16: 1964 | BB16: 1964 | BC16: 1964 | BD16: 0 | BF16: =+IFERROR(ROUND(AV16*100/(100+$AT16),0),AV16) -> 0 | BG16: =+IFERROR(ROUND(AW16*100/(100+$AT16),0),AW16) -> 0 | BH16: =+IFERROR(ROUND(AX16*100/(100+$AT16),0),AX16) -> 0 | BI16: =SUM(BF16:BH16) -> 0 | BJ16: =+IFERROR(ROUND(AZ16*100/(100+$AT16),0),AZ16) -> 0 | BK16: =+IFERROR(ROUND(BA16*100/(100+$AT16),0),BA16) -> 1964 | BL16: =SUM(BJ16:BK16) -> 1964 | BM16: =+BI16+BL16 -> 1964 | BO16: =AV16*100/(100+$AT16)-BF16 -> 0 | BP16: =AW16*100/(100+$AT16)-BG16 -> 0 | BQ16: =AX16*100/(100+$AT16)-BH16 -> 0 | BR16: =AY16*100/(100+$AT16)-BI16 -> 0 | BS16: =AZ16*100/(100+$AT16)-BJ16 -> 0 | BT16: =BA16*100/(100+$AT16)-BK16 -> 0 | BU16: =BB16*100/(100+$AT16)-BL16 -> 0
A17: 1 | D17: 1501110500 | E17: 経営企画課 | F17: R06/03/31 | G17: R06/03/31 | H17: 令和６年能登半島地震の応援派遣に伴う経費（時間外勤務手当） | I17: 振替伝票（予算振替） | J17: 37000606 | K17: 000 | L17: 001 | M17: 1 | N17: 0884066300 | O17: 下水道事業費用 | P17: 営業外費用 | Q17: 雑支出 | R17: その他雑支出 | T17: 912477 | U17: 災害派遣対応 | V17: 0 | W17: 2866935 | X17: 2866935 | Y17: 2866935 | Z17: 088406001063000000 | AA17: その他雑支出 | AB17: 2866935 | AC17: 011632001003010000 | AD17: 時間外勤務手当 | AE17: 2866935 | AF17: 31 | AG17: 0 | AH17: 0 | AI17: 2866935 | AL17: 37000606-000-001-1-0884066300-912477-31 | AM17: 1 | AN17: 0 | AO17: 0 | AP17: 0 | AS17: 31 | AT17: 0 | AV17: 0 | AW17: 0 | AX17: 0 | AY17: 0 | AZ17: 0 | BA17: 2866935 | BB17: 2866935 | BC17: 2866935 | BD17: 0 | BF17: =+IFERROR(ROUND(AV17*100/(100+$AT17),0),AV17) -> 0 | BG17: =+IFERROR(ROUND(AW17*100/(100+$AT17),0),AW17) -> 0 | BH17: =+IFERROR(ROUND(AX17*100/(100+$AT17),0),AX17) -> 0 | BI17: =SUM(BF17:BH17) -> 0 | BJ17: =+IFERROR(ROUND(AZ17*100/(100+$AT17),0),AZ17) -> 0 | BK17: =+IFERROR(ROUND(BA17*100/(100+$AT17),0),BA17) -> 2866935 | BL17: =SUM(BJ17:BK17) -> 2866935 | BM17: =+BI17+BL17 -> 2866935 | BO17: =AV17*100/(100+$AT17)-BF17 -> 0 | BP17: =AW17*100/(100+$AT17)-BG17 -> 0 | BQ17: =AX17*100/(100+$AT17)-BH17 -> 0 | BR17: =AY17*100/(100+$AT17)-BI17 -> 0 | BS17: =AZ17*100/(100+$AT17)-BJ17 -> 0 | BT17: =BA17*100/(100+$AT17)-BK17 -> 0 | BU17: =BB17*100/(100+$AT17)-BL17 -> 0
A18: 1 | D18: 1501110500 | E18: 経営企画課 | F18: R06/03/31 | G18: R06/03/31 | H18: 令和６年能登半島地震の応援派遣に伴う経費（時間外勤務手当） | I18: 振替伝票（予算振替） | J18: 37000606 | K18: 000 | L18: 002 | M18: 1 | N18: 0884066300 | O18: 下水道事業費用 | P18: 営業外費用 | Q18: 雑支出 | R18: その他雑支出 | T18: 912477 | U18: 災害派遣対応 | V18: 0 | W18: 398682 | X18: 398682 | Y18: 398682 | Z18: 088406001063000000 | AA18: その他雑支出 | AB18: 398682 | AC18: 011642001003010000 | AD18: 時間外勤務手当 | AE18: 398682 | AF18: 31 | AG18: 0 | AH18: 0 | AI18: 398682 | AL18: 37000606-000-002-1-0884066300-912477-31 | AM18: 1 | AN18: 0 | AO18: 0 | AP18: 0 | AS18: 31 | AT18: 0 | AV18: 0 | AW18: 0 | AX18: 0 | AY18: 0 | AZ18: 0 | BA18: 398682 | BB18: 398682 | BC18: 398682 | BD18: 0 | BF18: =+IFERROR(ROUND(AV18*100/(100+$AT18),0),AV18) -> 0 | BG18: =+IFERROR(ROUND(AW18*100/(100+$AT18),0),AW18) -> 0 | BH18: =+IFERROR(ROUND(AX18*100/(100+$AT18),0),AX18) -> 0 | BI18: =SUM(BF18:BH18) -> 0 | BJ18: =+IFERROR(ROUND(AZ18*100/(100+$AT18),0),AZ18) -> 0 | BK18: =+IFERROR(ROUND(BA18*100/(100+$AT18),0),BA18) -> 398682 | BL18: =SUM(BJ18:BK18) -> 398682 | BM18: =+BI18+BL18 -> 398682 | BO18: =AV18*100/(100+$AT18)-BF18 -> 0 | BP18: =AW18*100/(100+$AT18)-BG18 -> 0 | BQ18: =AX18*100/(100+$AT18)-BH18 -> 0 | BR18: =AY18*100/(100+$AT18)-BI18 -> 0 | BS18: =AZ18*100/(100+$AT18)-BJ18 -> 0 | BT18: =BA18*100/(100+$AT18)-BK18 -> 0 | BU18: =BB18*100/(100+$AT18)-BL18 -> 0
A19: 1 | D19: 1501110500 | E19: 経営企画課 | F19: R06/03/31 | G19: R06/03/31 | H19: 令和６年能登半島地震の応援派遣に伴う経費（時間外勤務手当） | I19: 振替伝票（予算振替） | J19: 37000606 | K19: 000 | L19: 003 | M19: 1 | N19: 0884066300 | O19: 下水道事業費用 | P19: 営業外費用 | Q19: 雑支出 | R19: その他雑支出 | T19: 912477 | U19: 災害派遣対応 | V19: 0 | W19: 547871 | X19: 547871 | Y19: 547871 | Z19: 088406001063000000 | AA19: その他雑支出 | AB19: 547871 | AC19: 088302001003010000 | AD19: 時間外勤務手当 | AE19: 547871 | AF19: 31 | AG19: 0 | AH19: 0 | AI19: 547871 | AL19: 37000606-000-003-1-0884066300-912477-31 | AM19: 1 | AN19: 0 | AO19: 0 | AP19: 0 | AS19: 31 | AT19: 0 | AV19: 0 | AW19: 0 | AX19: 0 | AY19: 0 | AZ19: 0 | BA19: 547871 | BB19: 547871 | BC19: 547871 | BD19: 0 | BF19: =+IFERROR(ROUND(AV19*100/(100+$AT19),0),AV19) -> 0 | BG19: =+IFERROR(ROUND(AW19*100/(100+$AT19),0),AW19) -> 0 | BH19: =+IFERROR(ROUND(AX19*100/(100+$AT19),0),AX19) -> 0 | BI19: =SUM(BF19:BH19) -> 0 | BJ19: =+IFERROR(ROUND(AZ19*100/(100+$AT19),0),AZ19) -> 0 | BK19: =+IFERROR(ROUND(BA19*100/(100+$AT19),0),BA19) -> 547871 | BL19: =SUM(BJ19:BK19) -> 547871 | BM19: =+BI19+BL19 -> 547871 | BO19: =AV19*100/(100+$AT19)-BF19 -> 0 | BP19: =AW19*100/(100+$AT19)-BG19 -> 0 | BQ19: =AX19*100/(100+$AT19)-BH19 -> 0 | BR19: =AY19*100/(100+$AT19)-BI19 -> 0 | BS19: =AZ19*100/(100+$AT19)-BJ19 -> 0 | BT19: =BA19*100/(100+$AT19)-BK19 -> 0 | BU19: =BB19*100/(100+$AT19)-BL19 -> 0
A20: 1 | D20: 1501110500 | E20: 経営企画課 | F20: R06/03/31 | G20: R06/03/31 | H20: 令和６年能登半島地震の応援派遣に伴う経費（旅費等）その２ | I20: 振替伝票（予算振替） | J20: 37000612 | K20: 000 | L20: 001 | M20: 1 | N20: 0884066300 | O20: 下水道事業費用 | P20: 営業外費用 | Q20: 雑支出 | R20: その他雑支出 | T20: 912477 | U20: 災害派遣対応 | V20: 0 | W20: 5368538 | X20: 5368538 | Y20: 5368538 | Z20: 088406001063000000 | AA20: その他雑支出 | AB20: 5368538 | AC20: 051402001002000000 | AD20: 諸経費未払金 | AE20: 5368538 | AF20: 18 | AG20: 10 | AH20: 488017 | AI20: 4880521 | AL20: 37000612-000-001-1-0884066300-912477-18 | AM20: 1 | AN20: 0 | AO20: 0 | AP20: 0 | AS20: 18 | AT20: 10 | AV20: 0 | AW20: 0 | AX20: 0 | AY20: 0 | AZ20: 0 | BA20: 5368538 | BB20: 5368538 | BC20: 5368538 | BD20: 0 | BF20: =+IFERROR(ROUND(AV20*100/(100+$AT20),0),AV20) -> 0 | BG20: =+IFERROR(ROUND(AW20*100/(100+$AT20),0),AW20) -> 0 | BH20: =+IFERROR(ROUND(AX20*100/(100+$AT20),0),AX20) -> 0 | BI20: =SUM(BF20:BH20) -> 0 | BJ20: =+IFERROR(ROUND(AZ20*100/(100+$AT20),0),AZ20) -> 0 | BK20: =+IFERROR(ROUND(BA20*100/(100+$AT20),0),BA20) -> 4880489 | BL20: =SUM(BJ20:BK20) -> 4880489 | BM20: =+BI20+BL20 -> 4880489 | BO20: =AV20*100/(100+$AT20)-BF20 -> 0 | BP20: =AW20*100/(100+$AT20)-BG20 -> 0 | BQ20: =AX20*100/(100+$AT20)-BH20 -> 0 | BR20: =AY20*100/(100+$AT20)-BI20 -> 0 | BS20: =AZ20*100/(100+$AT20)-BJ20 -> 0 | BT20: =BA20*100/(100+$AT20)-BK20 -> 0.090909091 | BU20: =BB20*100/(100+$AT20)-BL20 -> 0.090909091
A21: 1 | D21: 1501110500 | E21: 経営企画課 | F21: R06/03/31 | G21: R06/03/31 | H21: 令和６年能登半島地震の応援派遣に伴う経費（旅費等）その２ | I21: 振替伝票（予算振替） | J21: 37000612 | K21: 000 | L21: 002 | M21: 1 | N21: 0884066300 | O21: 下水道事業費用 | P21: 営業外費用 | Q21: 雑支出 | R21: その他雑支出 | T21: 912477 | U21: 災害派遣対応 | V21: 0 | W21: 16247 | X21: 16247 | Y21: 16247 | Z21: 088406001063000000 | AA21: その他雑支出 | AB21: 16247 | AC21: 051402001002000000 | AD21: 諸経費未払金 | AE21: 16247 | AF21: 31 | AG21: 0 | AH21: 0 | AI21: 16247 | AL21: 37000612-000-002-1-0884066300-912477-31 | AM21: 1 | AN21: 0 | AO21: 0 | AP21: 軽油取引税分 | AS21: 31 | AT21: 0 | AV21: 0 | AW21: 0 | AX21: 0 | AY21: 0 | AZ21: 0 | BA21: 16247 | BB21: 16247 | BC21: 16247 | BD21: 0 | BF21: =+IFERROR(ROUND(AV21*100/(100+$AT21),0),AV21) -> 0 | BG21: =+IFERROR(ROUND(AW21*100/(100+$AT21),0),AW21) -> 0 | BH21: =+IFERROR(ROUND(AX21*100/(100+$AT21),0),AX21) -> 0 | BI21: =SUM(BF21:BH21) -> 0 | BJ21: =+IFERROR(ROUND(AZ21*100/(100+$AT21),0),AZ21) -> 0 | BK21: =+IFERROR(ROUND(BA21*100/(100+$AT21),0),BA21) -> 16247 | BL21: =SUM(BJ21:BK21) -> 16247 | BM21: =+BI21+BL21 -> 16247 | BO21: =AV21*100/(100+$AT21)-BF21 -> 0 | BP21: =AW21*100/(100+$AT21)-BG21 -> 0 | BQ21: =AX21*100/(100+$AT21)-BH21 -> 0 | BR21: =AY21*100/(100+$AT21)-BI21 -> 0 | BS21: =AZ21*100/(100+$AT21)-BJ21 -> 0 | BT21: =BA21*100/(100+$AT21)-BK21 -> 0 | BU21: =BB21*100/(100+$AT21)-BL21 -> 0
A22: 1 | D22: 1501110500 | E22: 経営企画課 | F22: R06/03/01 | G22: R06/03/01 | H22: 市有地公募売却に伴う固定資産売却損（東区戸坂新町二丁目３０８番２６４外１筆） | I22: 振替伝票（予算振替） | J22: 37000359 | K22: 000 | L22: 001 | M22: 1 | N22: 0885020200 | O22: 下水道事業費用 | P22: 特別損失 | Q22: 固定資産売却損 | R22: 固定資産売却損 | T22: 912475 | U22: 旧団地処理場等施設管理運営 | V22: 0 | W22: 10315355 | X22: 10315355 | Y22: 10315355 | Z22: 088502001002000000 | AA22: 固定資産売却損 | AB22: 10315355 | AC22: 011502001006000000 | AD22: 施設用用地 | AE22: 10315355 | AF22: 31 | AG22: 0 | AH22: 0 | AI22: 10315355 | AL22: 37000359-000-001-1-0885020200-912475-31 | AM22: 1 | AN22: 0 | AO22: 0 | AP22: 0 | AS22: 31 | AT22: 0 | AV22: 0 | AW22: 0 | AX22: 0 | AY22: 0 | AZ22: 0 | BA22: 10315355 | BB22: 10315355 | BC22: 10315355 | BD22: 0 | BF22: =+IFERROR(ROUND(AV22*100/(100+$AT22),0),AV22) -> 0 | BG22: =+IFERROR(ROUND(AW22*100/(100+$AT22),0),AW22) -> 0 | BH22: =+IFERROR(ROUND(AX22*100/(100+$AT22),0),AX22) -> 0 | BI22: =SUM(BF22:BH22) -> 0 | BJ22: =+IFERROR(ROUND(AZ22*100/(100+$AT22),0),AZ22) -> 0 | BK22: =+IFERROR(ROUND(BA22*100/(100+$AT22),0),BA22) -> 10315355 | BL22: =SUM(BJ22:BK22) -> 10315355 | BM22: =+BI22+BL22 -> 10315355 | BO22: =AV22*100/(100+$AT22)-BF22 -> 0 | BP22: =AW22*100/(100+$AT22)-BG22 -> 0 | BQ22: =AX22*100/(100+$AT22)-BH22 -> 0 | BR22: =AY22*100/(100+$AT22)-BI22 -> 0 | BS22: =AZ22*100/(100+$AT22)-BJ22 -> 0 | BT22: =BA22*100/(100+$AT22)-BK22 -> 0 | BU22: =BB22*100/(100+$AT22)-BL22 -> 0
A23: 1 | D23: 1502110500 | E23: 管理課 | F23: R05/11/01 | G23: R05/11/01 | H23: 下水道使用料過誤納還付金の精算（１０月分） | I23: 振替伝票（予算振替） | J23: 37000234 | K23: 000 | L23: 001 | M23: 1 | N23: 0885060600 | O23: 下水道事業費用 | P23: 特別損失 | Q23: 過年度損益修正損 | R23: 過年度損益修正損 | T23: 921481 | U23: 下水道使用料賦課徴収 | V23: 0 | W23: 0 | X23: 0 | Y23: 7639 | Z23: 088506001006000000 | AA23: 過年度損益修正損 | AB23: 7639 | AC23: 022602001006000000 | AD23: 下水道使用料還付前渡資金 | AE23: 7639 | AF23: 18 | AG23: 10 | AH23: 694 | AI23: 6945 | AL23: 37000234-000-001-1-0885060600-921481-18 | AM23: 1 | AN23: 0 | AO23: 0 | AP23: 0 | AS23: 18 | AT23: 10 | AV23: 0 | AW23: 0 | AX23: 0 | AY23: 0 | AZ23: 0 | BA23: 7639 | BB23: 7639 | BC23: 7639 | BD23: 0 | BF23: =+IFERROR(ROUND(AV23*100/(100+$AT23),0),AV23) -> 0 | BG23: =+IFERROR(ROUND(AW23*100/(100+$AT23),0),AW23) -> 0 | BH23: =+IFERROR(ROUND(AX23*100/(100+$AT23),0),AX23) -> 0 | BI23: =SUM(BF23:BH23) -> 0 | BJ23: =+IFERROR(ROUND(AZ23*100/(100+$AT23),0),AZ23) -> 0 | BK23: =+IFERROR(ROUND(BA23*100/(100+$AT23),0),BA23) -> 6945 | BL23: =SUM(BJ23:BK23) -> 6945 | BM23: =+BI23+BL23 -> 6945 | BO23: =AV23*100/(100+$AT23)-BF23 -> 0 | BP23: =AW23*100/(100+$AT23)-BG23 -> 0 | BQ23: =AX23*100/(100+$AT23)-BH23 -> 0 | BR23: =AY23*100/(100+$AT23)-BI23 -> 0 | BS23: =AZ23*100/(100+$AT23)-BJ23 -> 0 | BT23: =BA23*100/(100+$AT23)-BK23 -> -0.45454545 | BU23: =BB23*100/(100+$AT23)-BL23 -> -0.45454545
