Workbook

Sheet 税務署提出用
I3: (単位：円)
A4: 区分 | E4: 対象経費 | F4: 按分方法 | G4: 不課税収入額 | H4: 特定収入 | I4: 特定収入 以外
A6: 収 益 的 収 入 | B6: 一般会計負担金 | G6: =G8+G16+G18+G20 -> 13974628227 | H6: =H8+H16+H18+H20 -> 2307267553 | I6: =I8+I16+I18+I20 -> 11667360674
C8: 雨水処理負担金 | G8: =G10+G12+G14 -> 13869351636 | H8: =H10+H12+H14 -> 2284890841 | I8: =I10+I12+I14 -> 11584460795
D10: 維持管理費分 | E10: 雨水処理に係る 維持管理費分 | F10: 雨水処理に係る維持管理費 の課税支出割合 | G10: ='3条一般会計'!G10 -> 3383678341 | H10: ='3条一般会計'!H10 -> 2257096108 | I10: =G10-H10 -> 1126582233
D12: 減価償却費分 | E12: 雨水施設に係る 減価償却費分 | F12: 減価償却費に対する負担金 のため特定収入以外 | G12: ='3条一般会計'!G12 -> 8476549651 | H12: ='3条一般会計'!H12 -> 0 | I12: =G12-H12 -> 8476549651
D14: 支払利息分 | E14: 雨水施設に係る 支払利息等充当分 | F14: 課税支出である企業債 手数料（雨水分）の額 | G14: ='3条一般会計'!G18 -> 2009123644 | H14: ='3条一般会計'!H18 -> 27794733 | I14: =G14-H14 -> 1981328911
C16: 水質指導費負担金 | E16: 水質規制に係る経費 | F16: 水質規制に係る経費の 課税支出割合 | G16: ='3条一般会計'!G20 -> 51313295 | H16: ='3条一般会計'!H20 -> 12168217 | I16: =G16-H16 -> 39145078
C18: 普及促進費負担金 | E18: 水洗化普及促進に係る経費 | F18: 水洗化普及促進に係る経費 の課税支出割合 | G18: ='3条一般会計'!G22 -> 43567026 | H18: ='3条一般会計'!H22 -> 9253060 | I18: =G18-H18 -> 34313966
C20: 貸付事業費負担金 | E20: 水洗化貸付業務に係る経費 | F20: 水洗化貸付業務に係る経費 (利子を除く)の課税支出割合 | G20: ='3条一般会計'!G28 -> 10396270 | H20: ='3条一般会計'!H28 -> 955435 | I20: =G20-H20 -> 9440835
B22: 国庫補助金 | G22: =G24+G26 -> 0 | H22: =H24+H26 -> 0 | I22: =I24+I26 -> 0
C24: 下水道緊急整備費 国庫補助金 | E24: 下水道緊急整備費に 対する利子補給 | F24: 支払利息に対する補給金 のため特定収入以外 | G24: 0 | H24: 0 | I24: =G24-H24 -> 0
C26: 災害復旧費国庫補助金 | E26: 災害復旧に係る経費 に対する国庫補助金 | F26: 災害復旧に係る経費 の課税支出割合 | G26: =SUM(G28:G43) -> 0 | H26: =SUM(H28:H43) -> 0 | I26: =SUM(I28:I43) -> 0
C28: 公共 | D28: =総括表!E28 -> 公共土木施設災害 復旧事業費国庫負担金 | E28: =総括表!F28 -> 対象事業費×２／３ | F28: =総括表!G28 -> 3年度分 公共土木施設災害復旧事業費(補助事業現年分)の課税支出割合 | G28: =総括表!H28 -> 0 | H28: =総括表!I28 -> 0 | I28: =総括表!J28 -> 0
D30: =総括表!E30 -> 公共土木施設災害 復旧事業費国庫負担金 | E30: =総括表!F30 -> 対象事業費×２／３ | F30: =総括表!G30 -> 2年度分 公共土木施設災害復旧事業費(補助事業繰越分)の課税支出割合 | G30: =総括表!H30 -> 0 | H30: =総括表!I30 -> 0 | I30: =総括表!J30 -> 0
C32: 特環 | D32: =総括表!E32 -> 公共土木施設災害 復旧事業費国庫負担金 | E32: =総括表!F32 -> 対象事業費×２／３ | F32: =総括表!G32 -> 3年度分 公共土木施設災害復旧事業費(補助事業現年分)の課税支出割合 | G32: =総括表!H32 -> 0 | H32: =総括表!I32 -> 0 | I32: =総括表!J32 -> 0
D34: =総括表!E34 -> 公共土木施設災害 復旧事業費国庫負担金 | E34: =総括表!F34 -> 対象事業費×２／３ | F34: =総括表!G34 -> 2年度分 公共土木施設災害復旧事業費(補助事業繰越分)の課税支出割合 | G34: =総括表!H34 -> 0 | H34: =総括表!I34 -> 0 | I34: =総括表!J34 -> 0
C36: 農集 | D36: =総括表!E36 -> 災害関連農村生活環境 施設復旧事業国庫補助金 | E36: =総括表!F36 -> 0 | F36: =総括表!G36 -> 3年度分 災害関連農村生活環境施設復旧事業(補助事業現年分)の課税支出割合 | G36: =総括表!H36 -> 0 | H36: =総括表!I36 -> 0 | I36: =総括表!J36 -> 0
D38: =総括表!E38 -> 災害関連農村生活環境 施設復旧事業国庫補助金 | E38: =総括表!F38 -> 対象事業費×１／２ | F38: =総括表!G38 -> 2年度分 災害関連農村生活環境施設復旧事業(補助事業繰越分)の課税支出割合 | G38: =総括表!H38 -> 0 | H38: =総括表!I38 -> 0 | I38: =総括表!J38 -> 0
C40: 浄化槽 | D40: =総括表!E40 -> 0 | E40: =総括表!F40 -> 0 | F40: =総括表!G40 -> 0 | G40: =総括表!H40 -> 0 | H40: =総括表!I40 -> 0 | I40: =総括表!J40 -> 0
D42: =総括表!E42 -> 0 | E42: =総括表!F42 -> 0 | F42: =総括表!G42 -> 0 | G42: =総括表!H42 -> 0 | H42: =総括表!I42 -> 0 | I42: =総括表!J42 -> 0
B44: 負担金 | G44: =G46 -> 16476593 | H44: =H46 -> 0 | I44: =I46 -> 16476593
C46: 他会計負担金 | E46: 企業債利息償還金に 対する他町負担金 | F46: 支払利息に対する負担金 のため特定収入以外 | G46: =+'3条他会計'!G6 -> 16476593 | H46: =+'3条他会計'!H6 -> 0 | I46: =G46-H46 -> 16476593
B48: 一般会計補助金 | G48: =G50+G58 -> 9203253 | H48: =H50+H58 -> 5368538 | I48: =I50+I58 -> 3834715
C50: 汚水処理補助金 | G50: =SUM(G52:G57) -> 4980 | H50: =SUM(H52:H57) -> 0 | I50: =SUM(I52:I57) -> 4980
D52: 減価償却費分 | E52: 汚水施設に係る 減価償却費分 | F52: 減価償却費に対する負担金 のため特定収入以外 | G52: ='3条補助金'!G10 -> 0 | H52: ='3条補助金'!H10 -> 0 | I52: =G52-H52 -> 0
D54: 支払利息分 | E54: 汚水施設に係る 支払利息等充当分 | F54: 課税支出である企業債 手数料（汚水分）の額 | G54: ='3条補助金'!G16 -> 0 | H54: ='3条補助金'!H16 -> 0 | I54: =G54-H54 -> 0
D56: 使用料減免分 | E56: 下水道使用料減免分 | F56: 減価償却費・支払利息に対する 負担金のため特定収入以外 | G56: ='3条補助金'!G18 -> 4980 | H56: ='3条補助金'!H18 -> 0 | I56: =G56-H56 -> 4980
C58: その他補助金 | E58: 熊本地震被災地支援経費 に対する一般会計負担額 | F58: 被災地支援に係る経費 の課税支出割合 | G58: ='3条補助金'!G20 -> 9198273 | H58: ='3条補助金'!H20 -> 5368538 | I58: =G58-H58 -> 3829735
B60: その他の収益的収入中の不課税収入 | F60: 収益的支出の課税支出割合 | G60: =+総括表!H60 -> 9701615928 | H60: =+総括表!I60 -> 256789 | I60: =G60-H60 -> 9701359139
B62: 計 | G62: =G6+G22+G44+G48+G60 -> 23701924001 | H62: =H6+H22+H44+H48+H60 -> 2312892880 | I62: =I6+I22+I44+I48+I60 -> 21389031121
A64: 資 本 的 収 入 | B64: 国庫補助金 | G64: =G66+G94 -> 5717788000 | H64: =H66+H94 -> 5712285006 | I64: =I66+I94 -> 5502994
C66: 社会資本整備総合交付金 | G66: ='4条補助（公）'!G6 -> 5683800000 | H66: ='4条補助（公）'!H6 -> 5678297006 | I66: ='4条補助（公）'!I6 -> 5502994
C68: 公 共 下 水 道 | D68: ='4条補助（公）'!C8 -> 管路等・一般 | E68: ='4条補助（公）'!D8 -> 4,762,313.150千円×５／１０ | F68: ='4条補助（公）'!E8 -> 5年度分 公共下水道整備事業 (補助事業現年分)の 課税支出割合 | G68: ='4条補助（公）'!G8 -> 2411526000 | H68: ='4条補助（公）'!H19 -> 2527700000 | I68: ='4条補助（公）'!I19 -> 0
D70: ='4条補助（公）'!C10 -> 管路等・補助裏単市 | E70: ='4条補助（公）'!D10 -> 60,375.850千円×５／１０ | G70: ='4条補助（公）'!G10 -> 0
D72: ='4条補助（公）'!C18 -> 管路等・促進・工事国債 | E72: ='4条補助（公）'!D18 -> 0 | G72: ='4条補助（公）'!G18 -> 0
D74: ='4条補助（公）'!C20 -> 処理場・一般・高率 | E74: ='4条補助（公）'!D20 -> 191,660千円×５．５／１０ | G74: ='4条補助（公）'!G20 -> 105413000
D76: ='4条補助（公）'!C22 -> 処理場・一般・低率 | E76: ='4条補助（公）'!D22 -> 21,525千円×５／１０ | G76: ='4条補助（公）'!G22 -> 10761000
D78: ='4条補助（公）'!C30 -> 過年度補助金 | E78: ='4条補助（公）'!D30 -> 0 | G78: ='4条補助（公）'!G30 -> 0
D80: ='4条補助（公）'!C32 -> 管路等・一般(繰越分) | E80: ='4条補助（公）'!D32 -> 4,286,012.1千円×５／１０ | F80: =+'4条補助（公）'!E32 -> 4年度分 公共下水道整備事業 (補助事業繰越分)の 課税支出割合 | G80: ='4条補助（公）'!G32 -> 2201500000 | H80: ='4条補助（公）'!H37 -> 3150597006 | I80: ='4条補助（公）'!I37 -> 5502994
D82: ='4条補助（公）'!C34 -> 管路等・補助裏単市 （繰越分） | E82: ='4条補助（公）'!D34 -> 13,187.9千円×５／１０
D84: ='4条補助（公）'!C36 -> 管路等・一般(高率分) | E84: ='4条補助（公）'!D36 -> 0 | G84: ='4条補助（公）'!G36 -> 0
D86: ='4条補助（公）'!C38 -> 処理場・一般・高率 (繰越分) | E86: ='4条補助（公）'!D38 -> 1,292,000千円×５．５／１０ | G86: ='4条補助（公）'!G38 -> 710600000
D88: ='4条補助（公）'!C40 -> 処理場・一般・低率 (繰越分) | E88: ='4条補助（公）'!D40 -> 488,000千円×５／１０ | G88: ='4条補助（公）'!G40 -> 244000000
B90: 企業債（特定資金公共事業債） | G90: =G92 -> 0 | H90: =H92 -> 0 | I90: =I92 -> 0
C92: 公共下水道 補助事業充当分 | F92: 14年度分補助事業 （繰越分）の課税支出割合 | G92: 0 | H92: 0 | I92: 0
C94: 汚水処理施設整備交付金 | G94: =SUM(G96:G115) -> 33988000 | H94: =SUM(H96:H115) -> 33988000 | I94: =SUM(I96:I115) -> 0
C96: 特環 | D96: ='4条補助（特）'!C8 -> 管路等・一般 | E96: ='4条補助（特）'!D8 -> 25,200千円×５／１０ | F96: =+'4条補助（特）'!E8 -> 5年度分 特定環境保全公共下水道整備事業 (補助事業現年分)の 課税支出割合 | G96: ='4条補助（特）'!G8 -> 12600000 | H96: ='4条補助（特）'!H19 -> 12600000 | I96: ='4条補助（特）'!I19 -> 0
D98: ='4条補助（公）'!C50 -> 0
D100: ='4条補助（特）'!C32 -> 管路等・一般(繰越分) | E100: ='4条補助（特）'!D32 -> 5,000千円×５／１０ | F100: =+'4条補助（特）'!E32 -> 4年度分 特定環境保全公共下水道整備事業 (補助事業繰越分)の 課税支出割合 | G100: ='4条補助（特）'!G32 -> 2500000 | H100: ='4条補助（特）'!H37 -> 17900000 | I100: ='4条補助（特）'!I37 -> 0
D102: ='4条補助（公）'!C54 -> 0 | E102: ='4条補助（公）'!D54 -> 0 | G102: =総括表!H109 -> 15400000
C104: 農集 | D104: ='4条補助（農）'!C8 -> 管路等・一般 | E104: ='4条補助（農）'!D8 -> 0 | F104: =+'4条補助（農）'!E8 -> 5年度分 農業集落排水事業 (補助事業現年分)の 課税支出割合 | G104: ='4条補助（農）'!G8 -> 0 | H104: ='4条補助（農）'!H19 -> 0 | I104: ='4条補助（農）'!I19 -> 0
D108: ='4条補助（農）'!C32 -> 管路等・一般(繰越分) | E108: ='4条補助（農）'!D32 -> 75,000千円×５／１０ | F108: ='4条補助（農）'!E32 -> 4年度分 農業集落排水事業 (補助事業繰越分)の 課税支出割合 | G108: ='4条補助（農）'!G32 -> 0 | H108: ='4条補助（農）'!H37 -> 0 | I108: ='4条補助（農）'!I37 -> 0
C112: 浄化槽 | D112: ='4条補助（浄）'!C8 -> 浄化槽 | E112: ='4条補助（浄）'!D8 -> 12,726.2千円×１／３ | F112: =+'4条補助（浄）'!E8 -> 5年度分 市営浄化槽事業 (補助事業現年分)の 課税支出割合 | G112: ='4条補助（浄）'!G6 -> 3488000 | H112: ='4条補助（浄）'!H6 -> 3488000 | I112: ='4条補助（浄）'!I6 -> 0
B116: その他国庫補助金 | G116: =SUM(G118:G133) -> 0 | H116: =SUM(H118:H133) -> 0 | I116: =SUM(I118:I133) -> 0
C118: 公共 | D118: =総括表!E122 -> 公共土木施設災害 復旧事業費国庫負担金 | E118: =総括表!F122 -> 対象事業費×２／３ | F118: =総括表!G122 -> 4年度分 公共土木施設災害復旧事業費(補助事業現年分)の課税支出割合 | G118: =総括表!H122 -> 0 | H118: =総括表!I122 -> 0 | I118: =総括表!J122 -> 0
D120: =総括表!E124 -> 公共土木施設災害 復旧事業費国庫負担金 | E120: =総括表!F124 -> 対象事業費×２／３ | F120: =総括表!G124 -> 3年度分 公共土木施設災害復旧事業費(補助事業繰越分)の課税支出割合 | G120: =総括表!H124 -> 0 | H120: =総括表!I124 -> 0 | I120: =総括表!J124 -> 0
C122: 特環 | D122: =総括表!E126 -> 公共土木施設災害 復旧事業費国庫負担金 | E122: =総括表!F126 -> 対象事業費×２／３ | F122: =総括表!G126 -> 4年度分 公共土木施設災害復旧事業費(補助事業現年分)の課税支出割合 | G122: =総括表!H126 -> 0 | H122: =総括表!I126 -> 0 | I122: =総括表!J126 -> 0
D124: =総括表!E128 -> 公共土木施設災害 復旧事業費国庫負担金 | E124: =総括表!F128 -> 対象事業費×２／３ | F124: =総括表!G128 -> 3年度分 公共土木施設災害復旧事業費(補助事業繰越分)の課税支出割合 | G124: =総括表!H128 -> 0 | H124: =総括表!I128 -> 0 | I124: =総括表!J128 -> 0
C126: 農集 | D126: =総括表!E130 -> 災害関連農村生活環境 施設復旧事業国庫補助金 | E126: =総括表!F130 -> 対象事業費×１／２ | F126: =総括表!G130 -> 4年度分 災害関連農村生活環境施設復旧事業(補助事業現年分)の課税支出割合 | G126: =総括表!H130 -> 0 | H126: =総括表!I130 -> 0 | I126: =総括表!J130 -> 0
D128: =総括表!E132 -> 災害関連農村生活環境 施設復旧事業国庫補助金 | E128: =総括表!F132 -> 対象事業費×１／２ | F128: =総括表!G132 -> 3年度分 災害関連農村生活環境施設復旧事業(補助事業繰越分)の課税支出割合 | G128: =総括表!H132 -> 0 | H128: =総括表!I132 -> 0 | I128: =総括表!J132 -> 0
C130: 浄化槽 | D130: =総括表!E134 -> 0 | E130: =総括表!F134 -> 0 | F130: =総括表!G134 -> 0 | G130: =総括表!H134 -> 0 | H130: =総括表!I134 -> 0 | I130: =総括表!J134 -> 0
D132: =総括表!E136 -> 0 | E132: =総括表!F136 -> 0 | F132: =総括表!G136 -> 0 | G132: =総括表!H136 -> 0 | H132: =総括表!I136 -> 0 | I132: =総括表!J136 -> 0
B134: 受益者負担金 | G134: ='受益（公）'!G6 -> 8799605 | H134: ='受益（公）'!H6 -> 8525089 | I134: ='受益（公）'!I6 -> 274516
C136: 公共下水道 補助事業充当分 | F136: =+'受益（公）'!E8 -> 5年度分補助事業 の課税支出割合 （現年） | G136: ='受益（公）'!G8 -> 5005000 | H136: ='受益（公）'!H8 -> 5005000 | I136: ='受益（公）'!I8 -> 0
C138: 公共下水道 起債事業充当分 | F138: =+'受益（公）'!E10 -> 5年度分起債事業 の課税支出割合 （現年） | G138: ='受益（公）'!G10 -> 3794605 | H138: ='受益（公）'!H10 -> 3520089 | I138: ='受益（公）'!I10 -> 274516
B140: 受益者分担金 | G140: =SUM(G142:G145) -> 35218280 | H140: =SUM(H142:H145) -> 33459431 | I140: =SUM(I142:I145) -> 1758849
C142: 汚水処理施設整備 交付事業充当分 | F142: =+F136 -> 5年度分補助事業 の課税支出割合 （現年） | G142: ='受益（区域外）'!G8 -> 1842000 | H142: ='受益（区域外）'!H8 -> 1842000 | I142: ='受益（区域外）'!I8 -> 0
C144: 汚水処理施設整備 起債事業充当分 | F144: =+F138 -> 5年度分起債事業 の課税支出割合 （現年） | G144: ='受益（区域外）'!G10 -> 33376280 | H144: ='受益（区域外）'!H10 -> 31617431 | I144: ='受益（区域外）'!I10 -> 1758849
B146: 工事負担金 | G146: ='4条工事負担金'!G6 -> 514968182 | H146: ='4条工事負担金'!H6 -> 351364357 | I146: ='4条工事負担金'!I6 -> 163603825
C148: 公共下水道 単市事業充当分 | F148: =+'4条工事負担金'!E8 -> 5年度分単市事業 の課税支出割合 (現年＋繰越) | G148: ='4条工事負担金'!G8 -> 0 | H148: ='4条工事負担金'!H8 -> 0 | I148: ='4条工事負担金'!I8 -> 0
C150: 排水設備整備事業 充当分 | F150: =+'4条工事負担金'!E10 -> 5年度分排水設備事業 の課税支出割合 | G150: ='4条工事負担金'!G10 -> 279746516 | H150: ='4条工事負担金'!H10 -> 218135713 | I150: ='4条工事負担金'!I10 -> 61610803
C152: 諸設備新設改良事業 充当分 | F152: =+'4条工事負担金'!E12 -> 5年度分諸設備新設改良 事業の課税支出割合 | G152: ='4条工事負担金'!G12 -> 0 | H152: ='4条工事負担金'!H12 -> 0 | I152: ='4条工事負担金'!I12 -> 0
C154: 【特環】市街化区域外汚水処理施設 整備事業充当分 | F154: =+'4条工事負担金'!E18 -> 5年度分(特環)市街化区域外汚水処理施設整備事業の課税支出割合 | G154: ='4条工事負担金'!G18 -> 0 | H154: ='4条工事負担金'!H18 -> 0 | I154: ='4条工事負担金'!I18 -> 0
C156: 【農集】市街化区域外汚水処理施設 整備事業充当分 | F156: =+'4条工事負担金'!E20 -> 5年度分(農集)市街化区域外汚水処理施設整備事業の課税支出割合 | G156: ='4条工事負担金'!G20 -> 0 | H156: ='4条工事負担金'!H20 -> 0 | I156: ='4条工事負担金'!I20 -> 0
C158: 【浄化槽】市街化区域外汚水処理 施設整備事業充当分 | F158: =+'4条工事負担金'!E22 -> 5年度分(浄化槽)市街化区域外汚水処理施設整備事業の課税支出割合 | G158: ='4条工事負担金'!G22 -> 0 | H158: ='4条工事負担金'!H22 -> 0 | I158: ='4条工事負担金'!I22 -> 0
C160: 元金償還金充当分 | F160: 起債年度の課税支出割合 | G160: ='4条工事負担金'!G14 -> 235221666 | H160: ='4条工事負担金'!H14 -> 133228644 | I160: ='4条工事負担金'!I14 -> 101993022
B162: 計 | G162: =G64+G90+G134+G146+G116+G140 -> 6276774067 | H162: =H64+H90+H134+H146+H140+H116 -> 6105633883 | I162: =I64+I90+I134+I146+I140+I116 -> 171140184
A164: 合計 | G164: =G62+G162 -> 29978698068 | H164: =H62+H162 -> 8418526763 | I164: =I62+I162 -> 21560171305

Sheet 総括表
A2: =+CONCATENATE("令和",DBCS([1]年度!$A$2),"年度決算 不課税収入区分表") -> 令和５年度決算 不課税収入区分表
J3: (単位：円)
A4: 区分 | F4: 対象経費 | G4: 按分方法 | H4: 不課税収入額 | I4: 特定収入 | J4: 特定収入 以外 | K4: 特定収入内訳（上段：課税支出額、下段特定収入の按分）
K5: 0.03 | L5: 0.05 | M5: 0.08 | N5: 0.08 | O5: 0.1
A6: 収 益 的 収 入 | B6: 一般会計負担金 | H6: =H8+H16+H18+H20 -> 13974628227 | I6: =I8+I16+I18+I20 -> 2307267553 | J6: =J8+J16+J18+J20 -> 11667360674
C8: 雨水処理負担金 | H8: =H10+H12+H14 -> 13869351636 | I8: =I10+I12+I14 -> 2284890841 | J8: =J10+J12+J14 -> 11584460795
D10: 維持管理費分 | F10: 雨水処理に係る 維持管理費分 | G10: 雨水処理に係る維持管理費 の課税支出割合 | H10: ='3条一般会計'!G10 -> 3383678341 | I10: ='3条一般会計'!H10 -> 2257096108 | J10: =H10-I10 -> 1126582233
D12: 減価償却費分 | F12: 雨水施設に係る 減価償却費分 | G12: 減価償却費に対する負担金 のため特定収入以外 | H12: ='3条一般会計'!G12 -> 8476549651 | I12: ='3条一般会計'!H12 -> 0 | J12: =H12-I12 -> 8476549651
D14: 支払利息分 | F14: 雨水施設に係る 支払利息等充当分 | G14: 課税支出である企業債 手数料（雨水分）の額 | H14: ='3条一般会計'!G18 -> 2009123644 | I14: ='3条一般会計'!H18 -> 27794733 | J14: =H14-I14 -> 1981328911
C16: 水質指導費負担金 | F16: 水質規制に係る経費 | G16: 水質規制に係る経費の 課税支出割合 | H16: ='3条一般会計'!G20 -> 51313295 | I16: ='3条一般会計'!H20 -> 12168217 | J16: =H16-I16 -> 39145078
C18: 普及促進費負担金 | F18: 水洗化普及促進に係る経費 | G18: 水洗化普及促進に係る経費 の課税支出割合 | H18: ='3条一般会計'!G22 -> 43567026 | I18: ='3条一般会計'!H22 -> 9253060 | J18: =H18-I18 -> 34313966
C20: 貸付事業費負担金 | F20: 水洗化貸付業務に係る経費 | G20: 水洗化貸付業務に係る経費 (利子を除く)の課税支出割合 | H20: ='3条一般会計'!G28 -> 10396270 | I20: ='3条一般会計'!H28 -> 955435 | J20: =H20-I20 -> 9440835
B22: 国庫補助金 | H22: =H24+H26 -> 0 | I22: =I24+I26 -> 0 | J22: =J24+J26 -> 0
C24: 下水道緊急整備費 国庫補助金 | F24: 下水道緊急整備費に 対する利子補給 | G24: 支払利息に対する補給金 のため特定収入以外 | H24: 0 | I24: 0 | J24: =H24-I24 -> 0
C26: 災害復旧費国庫補助金 | F26: 災害復旧に係る経費 に対する国庫補助金 | G26: 災害復旧に係る経費 の課税支出割合 | H26: =SUM(H28:H43) -> 0 | I26: =SUM(I28:I43) -> 0 | J26: =SUM(J28:J43) -> 0
D28: 公共 | E28: =+'3条災害補助'!$C$10 -> 公共土木施設災害 復旧事業費国庫負担金 | F28: =+'3条災害補助'!$D$10 -> 対象事業費×２／３ | G28: =+'3条災害補助'!$E$10 -> 3年度分 公共土木施設災害復旧事業費(補助事業現年分)の課税支出割合 | H28: =+'3条災害補助'!$G$10 -> 0 | I28: =+'3条災害補助'!H$12 -> 0 | J28: =+'3条災害補助'!I$12 -> 0
E30: =+'3条災害補助'!$C$16 -> 公共土木施設災害 復旧事業費国庫負担金 | F30: =+'3条災害補助'!$D$16 -> 対象事業費×２／３ | G30: =+'3条災害補助'!$E$16 -> 2年度分 公共土木施設災害復旧事業費(補助事業繰越分)の課税支出割合 | H30: =+'3条災害補助'!$G$16 -> 0 | I30: =+'3条災害補助'!H$18 -> 0 | J30: =+'3条災害補助'!I$18 -> 0
D32: 特環 | E32: =+'3条災害補助'!$C$24 -> 公共土木施設災害 復旧事業費国庫負担金 | F32: =+'3条災害補助'!$D$24 -> 対象事業費×２／３ | G32: =+'3条災害補助'!$E$24 -> 3年度分 公共土木施設災害復旧事業費(補助事業現年分)の課税支出割合 | H32: =+'3条災害補助'!$G$24 -> 0 | I32: =+'3条災害補助'!H$26 -> 0 | J32: =+'3条災害補助'!I$26 -> 0
E34: =+'3条災害補助'!$C$30 -> 公共土木施設災害 復旧事業費国庫負担金 | F34: =+'3条災害補助'!$D$30 -> 対象事業費×２／３ | G34: =+'3条災害補助'!$E$30 -> 2年度分 公共土木施設災害復旧事業費(補助事業繰越分)の課税支出割合 | H34: =+'3条災害補助'!$G$30 -> 0 | I34: =+'3条災害補助'!H$32 -> 0 | J34: =+'3条災害補助'!I$32 -> 0
D36: 農集 | E36: =+'3条災害補助'!$C$38 -> 災害関連農村生活環境 施設復旧事業国庫補助金 | F36: =+'3条災害補助'!$D$38 -> 0 | G36: =+'3条災害補助'!$E$38 -> 3年度分 災害関連農村生活環境施設復旧事業(補助事業現年分)の課税支出割合 | H36: =+'3条災害補助'!$G$38 -> 0 | I36: =+'3条災害補助'!H$40 -> 0 | J36: =+'3条災害補助'!I$40 -> 0
E38: =+'3条災害補助'!$C$44 -> 災害関連農村生活環境 施設復旧事業国庫補助金 | F38: =+'3条災害補助'!$D$44 -> 対象事業費×１／２ | G38: =+'3条災害補助'!$E$44 -> 2年度分 災害関連農村生活環境施設復旧事業(補助事業繰越分)の課税支出割合 | H38: =+'3条災害補助'!$G$44 -> 0 | I38: =+'3条災害補助'!H$46 -> 0 | J38: =+'3条災害補助'!I$46 -> 0
D40: 浄化槽 | E40: =+'3条災害補助'!$C$52 -> 0 | F40: =+'3条災害補助'!$D$52 -> 0 | G40: =+'3条災害補助'!$E$52 -> 0 | H40: =+'3条災害補助'!$G$52 -> 0 | I40: =+'3条災害補助'!H$54 -> 0 | J40: =+'3条災害補助'!I$54 -> 0
E42: =+'3条災害補助'!$C$58 -> 0 | F42: =+'3条災害補助'!$D$58 -> 0 | G42: =+'3条災害補助'!$E$58 -> 0 | H42: =+'3条災害補助'!$G$58 -> 0 | I42: =+'3条災害補助'!H$60 -> 0 | J42: =+'3条災害補助'!I$60 -> 0
B44: 負担金 | H44: =H46 -> 16476593 | I44: =I46 -> 0 | J44: =J46 -> 16476593
C46: 他会計負担金 | F46: 企業債利息償還金に 対する他町負担金 | G46: 支払利息に対する負担金 のため特定収入以外 | H46: =+'3条他会計'!G6 -> 16476593 | I46: =+'3条他会計'!H8 -> 0 | J46: =H46-I46 -> 16476593
B48: 一般会計補助金 | H48: =H50+H58 -> 9203253 | I48: =I50+I58 -> 5368538 | J48: =J50+J58 -> 3834715
C50: 汚水処理補助金 | H50: =SUM(H52:H57) -> 4980 | I50: =SUM(I52:I57) -> 0 | J50: =SUM(J52:J57) -> 4980
D52: 減価償却費分 | F52: 汚水施設に係る 減価償却費分 | G52: 減価償却費に対する負担金 のため特定収入以外 | H52: ='3条補助金'!G10 -> 0 | I52: ='3条補助金'!H10 -> 0 | J52: =H52-I52 -> 0
D54: 支払利息分 | F54: 汚水施設に係る 支払利息等充当分 | G54: 課税支出である企業債 手数料（汚水分）の額 | H54: ='3条補助金'!G16 -> 0 | I54: ='3条補助金'!H16 -> 0 | J54: =H54-I54 -> 0
D56: 使用料減免分 | F56: 下水道使用料減免分 | G56: 減価償却費・支払利息に対する 負担金のため特定収入以外 | H56: ='3条補助金'!G18 -> 4980 | I56: ='3条補助金'!H18 -> 0 | J56: =H56-I56 -> 4980
C58: その他補助金 | F58: 熊本地震被災地支援経費 に対する一般会計負担額 | G58: 被災地支援に係る経費 の課税支出割合 | H58: =+'3条補助金'!G20 -> 9198273 | I58: =+'3条補助金'!H20 -> 5368538 | J58: =H58-I58 -> 3829735
B60: その他の収益的収入中の不課税収入 | G60: 収益的支出の課税支出割合 | H60: =+'3条その他'!G6+'[2]3条収入'!$U$69 -> 9701615928 | I60: =+'3条その他'!H6 -> 256789 | J60: =H60-I60 -> 9701359139
B62: 計 | H62: =H6+H22+H44+H48+H60 -> 23701924001 | I62: =I6+I22+I44+I48+I60 -> 2312892880 | J62: =J6+J22+J44+J48+J60 -> 21389031121 | K62: =+SUM('3条一般会計:3条災害補助'!J6) -> 0 | L62: =+SUM('3条一般会計:3条災害補助'!K6) -> 0 | M62: =+SUM('3条一般会計:3条災害補助'!L6) -> 455392 | N62: =+SUM('3条一般会計:3条災害補助'!M6) -> 130568 | O62: =+SUM('3条一般会計:3条災害補助'!N6) -> 2312306920
A64: 資 本 的 収 入 | B64: 国庫補助金 | H64: =H66+H104 -> 5717788000 | I64: =I66+I104 -> 5712285006 | J64: =J66+J104 -> 5502994
C66: 社会資本整備総合交付金 | H66: ='4条補助（公）'!G6 -> 5683800000 | I66: ='4条補助（公）'!H6 -> 5678297006 | J66: ='4条補助（公）'!I6 -> 5502994
D68: 公 共 下 水 道 | E68: 管路等・一般 | F68: ='4条補助（公）'!D8 -> 4,762,313.150千円×５／１０ | G68: ='4条補助（公）'!E8 -> 5年度分 公共下水道整備事業 (補助事業現年分)の 課税支出割合 | H68: ='4条補助（公）'!G8 -> 2411526000 | I68: ='4条補助（公）'!H19 -> 2527700000 | J68: ='4条補助（公）'!I19 -> 0
E70: 管路等・一般 | F70: ='4条補助（公）'!D10 -> 60,375.850千円×５／１０
E72: 管路等・用地国債 | F72: ='4条補助（公）'!D12 -> 0 | H72: ='4条補助（公）'!G12 -> 0
E74: 管路等・特債 | F74: ='4条補助（公）'!D14 -> 0 | H74: ='4条補助（公）'!G14 -> 0
E76: 管路等・都市水 | F76: ='4条補助（公）'!D16 -> 0 | H76: ='4条補助（公）'!G16 -> 0
E78: 管路等・促進・工事国債 | F78: ='4条補助（公）'!D18 -> 0 | H78: ='4条補助（公）'!G18 -> 0
E80: 処理場・一般・高率 | F80: ='4条補助（公）'!D20 -> 191,660千円×５．５／１０ | H80: ='4条補助（公）'!G20 -> 105413000
E82: 処理場・一般・低率 | F82: ='4条補助（公）'!D22 -> 21,525千円×５／１０ | H82: ='4条補助（公）'!G22 -> 10761000
E84: 処理場・用地国債 | F84: ='4条補助（公）'!D24 -> 0 | H84: ='4条補助（公）'!G24 -> 0
E86: 処理場・特債・高率 | F86: ='4条補助（公）'!D26 -> 0 | H86: ='4条補助（公）'!G26 -> 0
E88: 処理場・特債・低率 | F88: ='4条補助（公）'!D28 -> 0 | H88: ='4条補助（公）'!G28 -> 0
E90: 過年度補助金 | H90: ='4条補助（公）'!G30 -> 0
E92: 管路等・一般(繰越分) | F92: ='4条補助（公）'!D32 -> 4,286,012.1千円×５／１０ | G92: ='4条補助（公）'!E32 -> 4年度分 公共下水道整備事業 (補助事業繰越分)の 課税支出割合 | H92: ='4条補助（公）'!G32 -> 2201500000 | I92: ='4条補助（公）'!H37 -> 3150597006 | J92: ='4条補助（公）'!I37 -> 5502994
E94: 管路等・補助裏単市（繰越分） | F94: ='4条補助（公）'!D34 -> 13,187.9千円×５／１０
E96: 管路等・特債(繰越分） | F96: ='4条補助（公）'!D36 -> 0 | H96: ='4条補助（公）'!G36 -> 0
E98: 処理場・一般・高率 (繰越分) | F98: ='4条補助（公）'!D38 -> 1,292,000千円×５．５／１０ | H98: ='4条補助（公）'!G38 -> 710600000
E100: 処理場・一般・低率 (繰越分) | F100: ='4条補助（公）'!D40 -> 488,000千円×５／１０ | H100: ='4条補助（公）'!G40 -> 244000000
E102: 処理場・特債・高率 (繰越分) | F102: ='4条補助（公）'!D42 -> 0 | H102: ='4条補助（公）'!G42 -> 0
C104: 汚水処理施設整備交付金 | H104: =SUM(H106:H119) -> 33988000 | I104: =SUM(I106:I119) -> 33988000 | J104: =SUM(J106:J119) -> 0
D106: 特 環 | E106: 管路等・一般 | F106: ='4条補助（特）'!D8 -> 25,200千円×５／１０ | G106: =+'4条補助（特）'!E8 -> 5年度分 特定環境保全公共下水道整備事業 (補助事業現年分)の 課税支出割合 | H106: ='4条補助（特）'!G8 -> 12600000 | I106: ='4条補助（特）'!H19 -> 12600000 | J106: ='4条補助（特）'!I19 -> 0
E108: 管路等・一般(繰越分) | F108: ='4条補助（特）'!D32 -> 5,000千円×５／１０ | G108: =+'4条補助（特）'!E32 -> 4年度分 特定環境保全公共下水道整備事業 (補助事業繰越分)の 課税支出割合 | H108: ='4条補助（特）'!G32 -> 2500000 | I108: ='4条補助（特）'!H37 -> 17900000 | J108: ='4条補助（特）'!I37 -> 0
E109: 処理場・一般・高率 （繰越分） | F109: ='4条補助（特）'!D38 -> 28,000千円×５．５／１０ | H109: ='4条補助（特）'!G38 -> 15400000
D110: 農 集 | E110: 管路等・一般 | F110: ='4条補助（農）'!D8 -> 0 | G110: =+'4条補助（農）'!E8 -> 5年度分 農業集落排水事業 (補助事業現年分)の 課税支出割合 | H110: ='4条補助（農）'!G8 -> 0 | I110: ='4条補助（農）'!H19 -> 0 | J110: ='4条補助（農）'!I19 -> 0
E114: 管路等・一般(繰越分) | F114: ='4条補助（農）'!D32 -> 75,000千円×５／１０ | G114: =+'4条補助（農）'!E32 -> 4年度分 農業集落排水事業 (補助事業繰越分)の 課税支出割合 | H114: ='4条補助（農）'!G32 -> 0 | I114: ='4条補助（農）'!H37 -> 0 | J114: ='4条補助（農）'!I37 -> 0
D118: 浄 化 槽 | E118: 浄化槽 | F118: ='4条補助（浄）'!D8 -> 12,726.2千円×１／３ | G118: =+'4条補助（浄）'!E8 -> 5年度分 市営浄化槽事業 (補助事業現年分)の 課税支出割合 | H118: ='4条補助（浄）'!G8 -> 3488000 | I118: ='4条補助（浄）'!H19 -> 3488000 | J118: ='4条補助（浄）'!I6 -> 0
B120: その他国庫補助金 | H120: =SUM(H122:H137) -> 0 | I120: =SUM(I122:I137) -> 0 | J120: =SUM(J122:J137) -> 0
D122: 公共 | E122: ='4条その他'!C$10 -> 公共土木施設災害 復旧事業費国庫負担金 | F122: ='4条その他'!D$10 -> 対象事業費×２／３ | G122: ='4条その他'!E$10 -> 4年度分 公共土木施設災害復旧事業費(補助事業現年分)の課税支出割合 | H122: ='4条その他'!G$10 -> 0 | I122: ='4条その他'!H$12 -> 0 | J122: ='4条その他'!I$12 -> 0
E124: ='4条その他'!C$16 -> 公共土木施設災害 復旧事業費国庫負担金 | F124: ='4条その他'!D$16 -> 対象事業費×２／３ | G124: ='4条その他'!E$16 -> 3年度分 公共土木施設災害復旧事業費(補助事業繰越分)の課税支出割合 | H124: ='4条その他'!G$16 -> 0 | I124: ='4条その他'!H$18 -> 0 | J124: ='4条その他'!I$18 -> 0
D126: 特環 | E126: ='4条その他'!C$24 -> 公共土木施設災害 復旧事業費国庫負担金 | F126: ='4条その他'!D$24 -> 対象事業費×２／３ | G126: ='4条その他'!E$24 -> 4年度分 公共土木施設災害復旧事業費(補助事業現年分)の課税支出割合 | H126: ='4条その他'!G$24 -> 0 | I126: ='4条その他'!H$26 -> 0 | J126: ='4条その他'!I$26 -> 0
E128: ='4条その他'!C$30 -> 公共土木施設災害 復旧事業費国庫負担金 | F128: ='4条その他'!D$30 -> 対象事業費×２／３ | G128: ='4条その他'!E$30 -> 3年度分 公共土木施設災害復旧事業費(補助事業繰越分)の課税支出割合 | H128: ='4条その他'!G$30 -> 0 | I128: ='4条その他'!H$32 -> 0 | J128: ='4条その他'!I$32 -> 0
D130: 農集 | E130: ='4条その他'!C$38 -> 災害関連農村生活環境 施設復旧事業国庫補助金 | F130: ='4条その他'!D$38 -> 対象事業費×１／２ | G130: ='4条その他'!E$38 -> 4年度分 災害関連農村生活環境施設復旧事業(補助事業現年分)の課税支出割合 | H130: ='4条その他'!G$38 -> 0 | I130: ='4条その他'!H$40 -> 0 | J130: ='4条その他'!I$40 -> 0
E132: ='4条その他'!C$44 -> 災害関連農村生活環境 施設復旧事業国庫補助金 | F132: ='4条その他'!D$44 -> 対象事業費×１／２ | G132: ='4条その他'!E$44 -> 3年度分 災害関連農村生活環境施設復旧事業(補助事業繰越分)の課税支出割合 | H132: ='4条その他'!G$44 -> 0 | I132: ='4条その他'!H$46 -> 0 | J132: ='4条その他'!I$46 -> 0
D134: 浄化槽 | E134: ='4条その他'!C$52 -> 0 | F134: ='4条その他'!D$52 -> 0 | G134: ='4条その他'!E$52 -> 0 | H134: ='4条その他'!G$52 -> 0 | I134: ='4条その他'!H$54 -> 0 | J134: ='4条その他'!I$54 -> 0
E136: ='4条その他'!C$58 -> 0 | F136: ='4条その他'!D$58 -> 0 | G136: ='4条その他'!E$58 -> 0 | H136: ='4条その他'!G$58 -> 0 | I136: ='4条その他'!H$60 -> 0 | J136: ='4条その他'!I$60 -> 0
B138: 企業債（特定資金公共事業債） | H138: =H140 -> 0 | I138: =I140 -> 0 | J138: =J140 -> 0
D140: 公共下水道 補助事業充当分 | G140: 15年度分補助事業 （繰越分）の課税支出割合 | H140: 0 | I140: 0 | J140: 0
B142: 受益者負担金 | H142: ='受益（公）'!G6 -> 8799605 | I142: ='受益（公）'!H6 -> 8525089 | J142: ='受益（公）'!I6 -> 274516
D144: 公共下水道 補助事業充当分 | G144: =+'受益（公）'!E8 -> 5年度分補助事業 の課税支出割合 （現年） | H144: ='受益（公）'!G8 -> 5005000 | I144: ='受益（公）'!H8 -> 5005000 | J144: ='受益（公）'!I8 -> 0
D146: 公共下水道 起債事業充当分 | G146: =+'受益（公）'!E10 -> 5年度分起債事業 の課税支出割合 （現年） | H146: ='受益（公）'!G10 -> 3794605 | I146: ='受益（公）'!H10 -> 3520089 | J146: ='受益（公）'!I10 -> 274516
B148: 受益者分担金 | H148: ='受益（区域外）'!G6 -> 35218280 | I148: ='受益（区域外）'!H6 -> 33459431 | J148: ='受益（区域外）'!I6 -> 1758849
D150: 汚水処理施設整備 交付事業充当分 | G150: =+G144 -> 5年度分補助事業 の課税支出割合 （現年） | H150: ='受益（区域外）'!G8 -> 1842000 | I150: ='受益（区域外）'!H8 -> 1842000 | J150: ='受益（区域外）'!I8 -> 0
D152: 汚水処理処理施設整備 起債事業充当分 | G152: =+G146 -> 5年度分起債事業 の課税支出割合 （現年） | H152: ='受益（区域外）'!G10 -> 33376280 | I152: ='受益（区域外）'!H10 -> 31617431 | J152: ='受益（区域外）'!I10 -> 1758849
B154: 工事負担金 | H154: ='4条工事負担金'!G6 -> 514968182 | I154: ='4条工事負担金'!H6 -> 351364357 | J154: ='4条工事負担金'!I6 -> 163603825
D156: 公共下水道 単市事業充当分 | G156: =+'4条工事負担金'!E8 -> 5年度分単市事業 の課税支出割合 (現年＋繰越) | H156: ='4条工事負担金'!G8 -> 0 | I156: ='4条工事負担金'!H8 -> 0 | J156: ='4条工事負担金'!I8 -> 0
D158: 排水設備整備事業 充当分 | G158: =+'4条工事負担金'!E10 -> 5年度分排水設備事業 の課税支出割合 | H158: ='4条工事負担金'!G10 -> 279746516 | I158: ='4条工事負担金'!H10 -> 218135713 | J158: ='4条工事負担金'!I10 -> 61610803
D160: 諸設備新設改良事業 充当分 | G160: =+'4条工事負担金'!E12 -> 5年度分諸設備新設改良 事業の課税支出割合 | H160: ='4条工事負担金'!G12 -> 0 | I160: ='4条工事負担金'!H12 -> 0 | J160: ='4条工事負担金'!I12 -> 0
D162: 【特環】市街化区域外汚水処理 施設整備事業充当分 | G162: =+'4条工事負担金'!E18 -> 5年度分(特環)市街化区域外汚水処理施設整備事業の課税支出割合 | H162: ='4条工事負担金'!G18 -> 0 | I162: ='4条工事負担金'!H18 -> 0 | J162: ='4条工事負担金'!I18 -> 0
D164: 【農集】市街化区域外汚水処理 施設整備事業充当分 | G164: =+'4条工事負担金'!E20 -> 5年度分(農集)市街化区域外汚水処理施設整備事業の課税支出割合 | H164: ='4条工事負担金'!G20 -> 0 | I164: ='4条工事負担金'!H20 -> 0 | J164: ='4条工事負担金'!I20 -> 0
D166: 【浄化槽】市街化区域外汚水 処理施設整備事業充当分 | G166: =+'4条工事負担金'!E22 -> 5年度分(浄化槽)市街化区域外汚水処理施設整備事業の課税支出割合 | H166: ='4条工事負担金'!G22 -> 0 | I166: ='4条工事負担金'!H22 -> 0 | J166: ='4条工事負担金'!I22 -> 0
D168: 元金償還金充当分 | G168: 起債年度の課税支出割合 | H168: ='4条工事負担金'!G14 -> 235221666 | I168: ='4条工事負担金'!H14 -> 133228644 | J168: ='4条工事負担金'!I14 -> 101993022
B170: 計 | H170: =H64+H120+H138+H142+H148+H154 -> 6276774067 | I170: =I64+I120+I138+I142+I148+I154 -> 6105633883 | J170: =J64+J120+J138+J142+J148+J154 -> 171140184
A172: 合計 | H172: =H62+H170 -> 29978698068 | I172: =I62+I170 -> 8418526763 | J172: =J62+J170 -> 21560171305 | K172: =+SUM('4条補助（公）:4条工事負担金'!J6) -> 0 | L172: =+SUM('4条補助（公）:4条工事負担金'!K6) -> 131982078 | M172: =+SUM('4条補助（公）:4条工事負担金'!L6) -> 1246904 | N172: =+SUM('4条補助（公）:4条工事負担金'!M6) -> 99 | O172: =+SUM('4条補助（公）:4条工事負担金'!N6) -> 5972404802

Sheet 3条一般会計
A1: =+"令和"&MID(総括表!A2,3,1)&"年度決算 不課税収入区分表(一般会計負担金)" -> 令和５年度決算 不課税収入区分表(一般会計負担金)
I3: (単位：円)
A4: 区分 | D4: 対象経費 | E4: 按分方法 | F4: 課税支出額 | G4: 不課税収入額 | H4: 特定収入 | I4: 特定収入 以外 | J4: 特定収入内訳（上段：課税支出額、下段特定収入の按分）
F5: 支出額合計 | J5: 0.03 | K5: 0.05 | L5: 0.08 | M5: 0.08 | N5: 0.1
A6: 一般会計負担金 | G6: =G8+G20+G22+G28 -> 13974628227 | H6: =H8+H20+H22+H28 -> 2307267553 | I6: =I8+I20+I22+I28 -> 11667360674 | J6: =+SUM(J11,J15,J21,J23,J25) -> 0 | K6: =+SUM(K11,K15,K21,K23,K25) -> 0 | L6: =+SUM(L11,L15,L21,L23,L25) -> 455357 | M6: =+SUM(M11,M15,M21,M23,M25) -> 130554 | N6: =+SUM(N11,N15,N21,N23,N25) -> 2306681642
B8: 雨水処理負担金 | G8: =G10+G12+G18 -> 13869351636 | H8: =H10+H12+H18 -> 2284890841 | I8: =I10+I12+I18 -> 11584460795
C10: 維持管理費分 | D10: 雨水処理に係る 維持管理費分 | E10: 雨水処理に係る維持管理費 の課税支出割合 | F10: =+'[1]3条支出'!$K$53 -> 2460111073 | G10: =+[3]雨汚水!$O$111 -> 3383678341 | H10: =IFERROR(ROUND((G10)*F10/F11,0),0) -> 2257096108 | I10: =G10-H10 -> 1126582233 | L10: =+'[1]3条支出'!F$53+'[1]3条支出'!G$53+'[1]3条支出'!H$53 -> 496314 | M10: =+'[1]3条支出'!I$53 -> 142297 | N10: =+'[1]3条支出'!J$53 -> 2459472462
F11: ='[1]3条支出'!$E$53 -> 3688023972 | L11: =+H10-SUM(J11:K11,M11:N11) -> 455357 | M11: =IFERROR(ROUND(M10/$F10*$H10,0),0) -> 130554 | N11: =IFERROR(ROUND(N10/$F10*$H10,0),0) -> 2256510197
C12: 減価償却費分 | D12: 雨水施設に係る 減価償却費分 | E12: 減価償却費に対する負担金 のため特定収入以外 | G12: =+[3]雨汚水!$O$112 -> 8476549651 | H12: =IFERROR(ROUND((G12)*F12/F13,0),0) -> 0 | I12: =G12-H12 -> 8476549651
C14: 支払利息分 | D14: 雨水施設に係る 支払利息等充当分 | E14: 課税支出である企業債手数料 （雨水分）の額 | F14: =+[1]営外!$K$9 -> 61813753 | G14: =+[3]雨汚水!$O$115 -> 27794733 | H14: =G14 -> 27794733 | I14: =G14-H14 -> 0 | L14: =+[1]営外!F$9+[1]営外!G$9+[1]営外!H$9 -> 0 | M14: =+[1]営外!I$9 -> 0 | N14: =+[1]営外!J$9 -> 61813753
F15: =+[1]営外!$E$9 -> 61813753 | L15: =+H14-SUM(J15:K15,M15:N15) -> 0 | M15: =IFERROR(ROUND(M14/$F14*$H14,0),0) -> 0 | N15: =IFERROR(ROUND(N14/$F14*$H14,0),0) -> 27794733
E16: その他(特定収入以外) | G16: =+[3]雨汚水!$O$114 -> 1981328911 | H16: =IFERROR(ROUND((G16)*F16/F17,0),0) -> 0 | I16: =G16-H16 -> 1981328911
E18: 小 計 | G18: =G14+G16 -> 2009123644 | H18: =H14+H16 -> 27794733 | I18: =I14+I16 -> 1981328911
B20: 水質指導費負担金 | D20: 水質規制に係る経費 | E20: 水質規制に係る経費の 課税支出割合 | F20: =+'[1]3条支出'!$K$7 -> 12436317 | G20: =+[3]雨汚水!$O$116 -> 51313295 | H20: =IFERROR(ROUND((G20)*F20/F21,0),0) -> 12168217 | I20: =G20-H20 -> 39145078 | L20: =+'[1]3条支出'!F$7+'[1]3条支出'!G$7+'[1]3条支出'!H$7 -> 0 | M20: =+'[1]3条支出'!I$7 -> 0 | N20: =+'[1]3条支出'!J$7 -> 12436317
F21: =+'[1]3条支出'!$E$7 -> 52443869 | L21: =+H20-SUM(J21:K21,M21:N21) -> 0 | M21: =IFERROR(ROUND(M20/$F20*$H20,0),0) -> 0 | N21: =IFERROR(ROUND(N20/$F20*$H20,0),0) -> 12168217
B22: 普及促進費負担金 | D22: 水洗化普及促進に係る経費 | E22: 水洗化普及促進に係る経費 の課税支出割合 | F22: =+'[1]3条支出'!$K$11 -> 18870469 | G22: =+[3]雨汚水!$O$117 -> 43567026 | H22: =IFERROR(ROUND((G22)*F22/F23,0),0) -> 9253060 | I22: =G22-H22 -> 34313966 | L22: =+'[1]3条支出'!F$11+'[1]3条支出'!G$11+'[1]3条支出'!H$11 -> 0 | M22: =+'[1]3条支出'!I$11 -> 0 | N22: =+'[1]3条支出'!J$11 -> 18870469
F23: =+'[1]3条支出'!$E$11 -> 88849549 | L23: =+H22-SUM(J23:K23,M23:N23) -> 0 | M23: =IFERROR(ROUND(M22/$F22*$H22,0),0) -> 0 | N23: =IFERROR(ROUND(N22/$F22*$H22,0),0) -> 9253060
B24: 貸付事業費負担金 | D24: 水洗化貸付業務に係る経費 | E24: 水洗化貸付業務に係る経費 (利子を除く)の課税支出割合 | F24: =+'[1]3条支出'!$K$12 -> 963485 | G24: =+[3]雨汚水!$O$118 -> 10396270 | H24: =IFERROR(ROUND((G24)*F24/F25,0),0) -> 955435 | I24: =G24-H24 -> 9440835 | L24: =+'[1]3条支出'!F$12+'[1]3条支出'!G$12+'[1]3条支出'!H$12 -> 0 | M24: =+'[1]3条支出'!I$12 -> 0 | N24: =+'[1]3条支出'!J$12 -> 963485
F25: =+'[1]3条支出'!$E$12 -> 10483859 | L25: =+H24-SUM(J25:K25,M25:N25) -> 0 | M25: =IFERROR(ROUND(M24/$F24*$H24,0),0) -> 0 | N25: =IFERROR(ROUND(N24/$F24*$H24,0),0) -> 955435
E26: 支払利息分〈特定収入以外〉 | G26: =G28-G24 -> 0 | H26: =IFERROR(ROUND((G26)*F26/F27,0),0) -> 0 | I26: =G26-H26 -> 0
E28: 小 計 | G28: =+G24 -> 10396270 | H28: =H24+H26 -> 955435 | I28: =I24+I26 -> 9440835
F30: 雨汚水シート 一般会計繰入金 税抜き決算額 （控除不可消費税等の雑支出の配分前） | G30: =+[3]雨汚水!$O$109 -> 13974628227
F31: チェック | G31: =+G6-G30 -> 0

Sheet 3条補助金
A1: =+"令和"&MID(総括表!A2,3,1)&"年度決算 不課税収入区分表(一般会計補助金)" -> 令和５年度決算 不課税収入区分表(一般会計補助金)
I3: (単位：円)
A4: 区分 | D4: 対象経費 | E4: 按分方法 | F4: 課税支出額 | G4: 不課税収入額 | H4: 特定収入 | I4: 特定収入 以外 | J4: 特定収入内訳（上段：課税支出額、下段特定収入の按分）
F5: 支出額合計 | J5: 0.03 | K5: 0.05 | L5: 0.08 | M5: 0.08 | N5: 0.1
A6: 一般会計補助金 | G6: =G8+G20 -> 9203253 | H6: =H8+H20 -> 5368538 | I6: =I8+I20 -> 3834715 | J6: =+J13+J21 -> 0 | K6: =+K13+K21 -> 0 | L6: =+L13+L21 -> 0 | M6: =+M13+M21 -> 0 | N6: =+N13+N21 -> 5368538
B8: 汚水処理補助金 | G8: =G10+G16+G18 -> 4980 | H8: =H10+H16+H18 -> 0 | I8: =I10+I16+I18 -> 4980
C10: 減価償却費分 | D10: 汚水施設に係る 減価償却費分 | E10: 減価償却費に対する負担金 のため特定収入以外 | G10: =+[3]雨汚水!$O$123 -> 0 | H10: =IFERROR(ROUND((G10)*F10/F11,0),0) -> 0 | I10: =G10-H10 -> 0
C12: 支払利息分 | D12: 汚水施設に係る 支払利息等充当分 | E12: 課税支出である企業債手数料 （汚水分）に対する一般会計 補助金の支払利息充当割合 | F12: =+[1]営外!$K$9 -> 61813753 | G12: 0 | H12: =IFERROR(ROUND((G12)*F12/F13,0),0) -> 0 | I12: =G12-H12 -> 0 | L12: =+[1]営外!F$9+[1]営外!G$9+[1]営外!H$9 -> 0 | M12: =+[1]営外!I$9 -> 0 | N12: =+[1]営外!J$9 -> 61813753
F13: =+[1]営外!$E$9 -> 61813753 | L13: =+H12-SUM(J13:K13,M13:N13) -> 0 | M13: =IFERROR(ROUND(M12/$F12*$H12,0),0) -> 0 | N13: =IFERROR(ROUND(N12/$F12*$H12,0),0) -> 0
E14: その他(特定収入以外) | G14: =G16-G12 -> 0 | H14: =IFERROR(ROUND((G14)*F14/F15,0),0) -> 0 | I14: =G14-H14 -> 0
E16: 小 計 | G16: =+[3]雨汚水!$O$124 -> 0 | H16: =H12+H14 -> 0 | I16: =I12+I14 -> 0
C18: 使用料減免分 | D18: 下水道使用料減免分 | E18: 減価償却費・支払利息に対する 負担金のため特定収入以外 | G18: =+[3]雨汚水!$O$125 -> 4980 | H18: =IFERROR(ROUND((G18)*F18/F19,0),0) -> 0 | I18: =G18-H18 -> 4980
B20: その他補助金 | D20: 能登半島地震被災地支援経費 に対する一般会計負担額 | E20: 被災地支援に係る経費 の課税支出割合 | F20: =+[1]営外!$K$20 -> 5368538 | G20: =+[3]雨汚水!$O$126 -> 9198273 | H20: =IFERROR(ROUND((G20)*F20/F21,0),0) -> 5368538 | I20: =G20-H20 -> 3829735 | L20: =+[1]営外!$F$20+[1]営外!$F$20+[1]営外!$F$20 -> 0 | M20: =+[1]営外!$F$20 -> 0 | N20: =+[1]営外!$F$20 -> 0
F21: =+[1]営外!$E$20 -> 9198273 | L21: =+H20-SUM(J21:K21,M21:N21) -> 0 | M21: =IFERROR(ROUND(M20/$F20*$H20,0),0) -> 0 | N21: 5368538
F22: 雨汚水シート 一般会計繰入金 税抜き決算額 （控除不可消費税等の雑支出の配分前） | G22: =+[3]雨汚水!$O$120 -> 9203253
F23: チェック | G23: =+G6-G22 -> 0

Sheet 3条他会計
A1: =+"令和"&MID(総括表!A2,3,1)&"年度決算 不課税収入区分表(他会計負担金)" -> 令和５年度決算 不課税収入区分表(他会計負担金)
I3: (単位：円)
A4: 区分 | D4: 対象経費 | E4: 按分方法 | F4: 課税支出額 | G4: 不課税収入額 | H4: 特定収入 | I4: 特定収入 以外 | J4: 特定収入内訳（上段：課税支出額、下段特定収入の按分）
F5: 支出額合計 | J5: 0.03 | K5: 0.05 | L5: 0.08 | M5: 0.08 | N5: 0.1
A6: 負担金 | G6: =+SUM(G8:G11) -> 16476593 | H6: =+SUM(H8:H11) -> 0 | I6: =+SUM(I8:I11) -> 16476593
B8: 他会計負担金 | D8: 企業債利息償還金に 対する他町負担金 | E8: 支払利息に対する負担金 のため特定収入以外 | G8: =+[3]雨汚水!$E$88 -> 16476593 | H8: =IFERROR(ROUND((G8)*F8/F9,0),0) -> 0 | I8: =G8-H8 -> 16476593
B10: 他会計負担金 | D10: 下水道使用料減免分 | E10: 減価償却費・支払利息に対する 負担金のため特定収入以外 | G10: =+[3]雨汚水!$E$89 -> 0 | H10: =IFERROR(ROUND((G10)*F10/F11,0),0) -> 0 | I10: =G10-H10 -> 0
F12: 3条収入シート 他会計負担金 | G12: =+'[2]3条収入'!$V$41 -> 16476593
F13: チェック | G13: =G6-G12 -> 0

Sheet 3条その他
A1: =+"令和"&MID(総括表!A2,3,1)&"年度決算(その他の収入)" -> 令和５年度決算(その他の収入) | K1: =+IFERROR(VLOOKUP($E1,$P$2:$W$5,5,0),"-") -> - | L1: =+IFERROR(VLOOKUP($E1,$P$2:$W$5,6,0),"-") -> - | M1: =+IFERROR(VLOOKUP($E1,$P$2:$W$5,7,0),"-") -> - | N1: =+IFERROR(VLOOKUP($E1,$P$2:$W$5,8,0),"-") -> - | O1: ←コピペ用数式 | P1: 按分方法 | Q1: 課税支出額 | R1: 支出額合計 | S1: 0.03 | T1: 0.05 | U1: 0.08 | V1: 0.08 | W1: 0.1
P2: 収益的支出の 課税支出割合 | Q2: =+'[1]3条支出'!$K$41 -> 9108565869 | R2: =+'[1]3条支出'!$E$41 -> 42643669657 | S2: 0 | T2: 0 | U2: =+SUM('[1]3条支出'!$F$41:$G$41)+'[1]3条支出'!H$41 -> 1236141 | V2: =+'[1]3条支出'!I$41 -> 500878 | W2: =+'[1]3条支出'!J$41 -> 9106828850
I3: (単位：円) | P3: 課税支出に対応する不課税収入のため特定収入 | Q3: 1 | R3: 1 | S3: - | T3: - | U3: 該当税率に「1」 | V3: 該当税率に「1」 | W3: 該当税率に「1」
A4: 区分 | D4: 対象経費 | E4: 按分方法 | F4: 課税支出額 | G4: 不課税収入額 | H4: 特定収入 | I4: 特定収入 以外 | J4: 特定収入内訳（上段：課税支出額、下段特定収入の按分） | P4: 不課税支出に対応する不課税収入のため特定収入以外 | Q4: - | R4: - | S4: - | T4: - | U4: - | V4: - | W4: -
F5: 支出額合計 | J5: 0.03 | K5: 0.05 | L5: 0.08 | M5: 0.08 | N5: 0.1 | P5: 特定収入以外 | Q5: - | R5: - | S5: - | T5: - | U5: - | V5: - | W5: -
A6: その他の収入 | G6: =+G18+G32+G48 -> 3786818 | H6: =+H18+H32+H48 -> 256789 | I6: =+I18+I32+I48 -> 3530029 | L6: =+SUM(L19,L33,L21,L49) -> 35 | M6: =+SUM(M19,M33,M21,M49) -> 14 | N6: =+SUM(N19,N33,N21,N49) -> 256740
A8: その他雑収益 | B8: 自動車損害共済 共済金 | E8: 収益的支出の 課税支出割合 | F8: =+IFERROR(VLOOKUP($E8,$P$2:$W$5,2,0),"-") -> 9108565869 | G8: 1202214 | H8: =IFERROR(ROUND((G8)*F8/F9,0),0) -> 256789 | I8: =G8-H8 -> 945425 | L8: =+IFERROR(VLOOKUP($E8,$P$2:$W$5,6,0),"-") -> 1236141 | M8: =+IFERROR(VLOOKUP($E8,$P$2:$W$5,7,0),"-") -> 500878 | N8: =+IFERROR(VLOOKUP($E8,$P$2:$W$5,8,0),"-") -> 9106828850
F9: =+IFERROR(VLOOKUP($E8,$P$2:$W$5,3,0),"-") -> 42643669657 | L9: =+H8-SUM(J9:K9,M9:N9) -> 35 | M9: =IFERROR(ROUND(M8/$F8*$H8,0),0) -> 14 | N9: =IFERROR(ROUND(N8/$F8*$H8,0),0) -> 256740
B10: 建物損害共済 共済金 | E10: 収益的支出の 課税支出割合 | F10: =+IFERROR(VLOOKUP($E10,$P$2:$W$5,2,0),"-") -> 9108565869 | G10: 0 | H10: =IFERROR(ROUND((G10)*F10/F11,0),0) -> 0 | I10: =G10-H10 -> 0 | L10: =+IFERROR(VLOOKUP($E10,$P$2:$W$5,6,0),"-") -> 1236141 | M10: =+IFERROR(VLOOKUP($E10,$P$2:$W$5,7,0),"-") -> 500878 | N10: =+IFERROR(VLOOKUP($E10,$P$2:$W$5,8,0),"-") -> 9106828850
F11: =+IFERROR(VLOOKUP($E10,$P$2:$W$5,3,0),"-") -> 42643669657 | L11: =+H10-SUM(J11:K11,M11:N11) -> 0 | M11: =IFERROR(ROUND(M10/$F10*$H10,0),0) -> 0 | N11: =IFERROR(ROUND(N10/$F10*$H10,0),0) -> 0
B12: 下水道損害賠償保険 保険金 | E12: 収益的支出の 課税支出割合 | F12: =+IFERROR(VLOOKUP($E12,$P$2:$W$5,2,0),"-") -> 9108565869 | G12: 0 | H12: =IFERROR(ROUND((G12)*F12/F13,0),0) -> 0 | I12: =G12-H12 -> 0 | L12: =+IFERROR(VLOOKUP($E12,$P$2:$W$5,6,0),"-") -> 1236141 | M12: =+IFERROR(VLOOKUP($E12,$P$2:$W$5,7,0),"-") -> 500878 | N12: =+IFERROR(VLOOKUP($E12,$P$2:$W$5,8,0),"-") -> 9106828850
F13: =+IFERROR(VLOOKUP($E12,$P$2:$W$5,3,0),"-") -> 42643669657 | L13: =+H12-SUM(J13:K13,M13:N13) -> 0 | M13: =IFERROR(ROUND(M12/$F12*$H12,0),0) -> 0 | N13: =IFERROR(ROUND(N12/$F12*$H12,0),0) -> 0
B14: 消費税還付に伴う還付加算金 | E14: 特定収入以外 | F14: =+IFERROR(VLOOKUP($E14,$P$2:$W$5,2,0),"-") -> - | G14: 0 | H14: =IFERROR(ROUND((G14)*F14/F15,0),0) -> 0 | I14: =G14-H14 -> 0 | L14: =+IFERROR(VLOOKUP($E14,$P$2:$W$5,6,0),"-") -> - | M14: =+IFERROR(VLOOKUP($E14,$P$2:$W$5,7,0),"-") -> - | N14: =+IFERROR(VLOOKUP($E14,$P$2:$W$5,8,0),"-") -> -
F15: =+IFERROR(VLOOKUP($E14,$P$2:$W$5,3,0),"-") -> - | L15: =+H14-SUM(J15:K15,M15:N15) -> 0 | M15: =IFERROR(ROUND(M14/$F14*$H14,0),0) -> 0 | N15: =IFERROR(ROUND(N14/$F14*$H14,0),0) -> 0
B16: 支障公共施設の移転に関する補償金 | E16: 不課税支出に対応する不課税収入のため特定収入以外 | F16: =+IFERROR(VLOOKUP($E16,$P$2:$W$5,2,0),"-") -> - | G16: 0 | H16: =IFERROR(ROUND((G16)*F16/F17,0),0) -> 0 | I16: =G16-H16 -> 0 | L16: =+IFERROR(VLOOKUP($E16,$P$2:$W$5,6,0),"-") -> - | M16: =+IFERROR(VLOOKUP($E16,$P$2:$W$5,7,0),"-") -> - | N16: =+IFERROR(VLOOKUP($E16,$P$2:$W$5,8,0),"-") -> -
F17: =+IFERROR(VLOOKUP($E16,$P$2:$W$5,3,0),"-") -> - | L17: =+H16-SUM(J17:K17,M17:N17) -> 0 | M17: =IFERROR(ROUND(M16/$F16*$H16,0),0) -> 0 | N17: =IFERROR(ROUND(N16/$F16*$H16,0),0) -> 0
B18: 計 | G18: =SUM(G8:G17) -> 1202214 | H18: =+SUM(H8:H17) -> 256789 | I18: =G18-H18 -> 945425
L19: =+SUM(L9,L11,L13,L15,L17) -> 35 | M19: =+SUM(M9,M11,M13,M15,M17) -> 14 | N19: =+SUM(N9,N11,N13,N15,N17) -> 256740
A20: 消費税及び地方消費税 還付金 | E20: 特定収入以外 | F20: =+IFERROR(VLOOKUP($E20,$P$2:$W$5,2,0),"-") -> - | G20: =+'[2]3条収入'!$E$50 -> 0 | H20: =IFERROR(ROUND((G20)*F20/F21,0),0) -> 0 | I20: =G20-H20 -> 0 | L20: =+IFERROR(VLOOKUP($E20,$P$2:$W$5,6,0),"-") -> - | M20: =+IFERROR(VLOOKUP($E20,$P$2:$W$5,7,0),"-") -> - | N20: =+IFERROR(VLOOKUP($E20,$P$2:$W$5,8,0),"-") -> -
F21: =+IFERROR(VLOOKUP($E20,$P$2:$W$5,3,0),"-") -> - | L21: =+H20-SUM(J21:K21,M21:N21) -> 0 | M21: =IFERROR(ROUND(M20/$F20*$H20,0),0) -> 0 | N21: =IFERROR(ROUND(N20/$F20*$H20,0),0) -> 0
A22: 過年度損益修正益 | B22: 過年度分手当等の戻入 | D22: 過年度手当等支出の返還 | E22: 不課税支出に対応する不課税収入のため特定収入以外 | F22: =+IFERROR(VLOOKUP($E22,$P$2:$W$5,2,0),"-") -> - | G22: 820795 | H22: =IFERROR(ROUND((G22)*F22/F23,0),0) -> 0 | I22: =G22-H22 -> 820795 | L22: =+IFERROR(VLOOKUP($E22,$P$2:$W$5,6,0),"-") -> - | M22: =+IFERROR(VLOOKUP($E22,$P$2:$W$5,7,0),"-") -> - | N22: =+IFERROR(VLOOKUP($E22,$P$2:$W$5,8,0),"-") -> -
F23: =+IFERROR(VLOOKUP($E22,$P$2:$W$5,3,0),"-") -> - | L23: =+H22-SUM(J23:K23,M23:N23) -> 0 | M23: =IFERROR(ROUND(M22/$F22*$H22,0),0) -> 0 | N23: =IFERROR(ROUND(N22/$F22*$H22,0),0) -> 0
B24: 消費税算出額と申告額の差額 | E24: 特定収入以外 | F24: =+IFERROR(VLOOKUP($E24,$P$2:$W$5,2,0),"-") -> - | G24: 160 | H24: =IFERROR(ROUND((G24)*F24/F25,0),0) -> 0 | I24: =G24-H24 -> 160 | L24: =+IFERROR(VLOOKUP($E24,$P$2:$W$5,6,0),"-") -> - | M24: =+IFERROR(VLOOKUP($E24,$P$2:$W$5,7,0),"-") -> - | N24: =+IFERROR(VLOOKUP($E24,$P$2:$W$5,8,0),"-") -> -
F25: =+IFERROR(VLOOKUP($E24,$P$2:$W$5,3,0),"-") -> - | L25: =+H24-SUM(J25:K25,M25:N25) -> 0 | M25: =IFERROR(ROUND(M24/$F24*$H24,0),0) -> 0 | N25: =IFERROR(ROUND(N24/$F24*$H24,0),0) -> 0
B26: 未収金貸倒引当金の更正に伴う特別利益 | E26: 不課税支出に対応する不課税収入のため特定収入以外 | F26: =+IFERROR(VLOOKUP($E26,$P$2:$W$5,2,0),"-") -> - | G26: 0 | H26: =IFERROR(ROUND((G26)*F26/F27,0),0) -> 0 | I26: =G26-H26 -> 0 | L26: =+IFERROR(VLOOKUP($E26,$P$2:$W$5,6,0),"-") -> - | M26: =+IFERROR(VLOOKUP($E26,$P$2:$W$5,7,0),"-") -> - | N26: =+IFERROR(VLOOKUP($E26,$P$2:$W$5,7,0),"-") -> -
F27: =+IFERROR(VLOOKUP($E26,$P$2:$W$5,3,0),"-") -> - | L27: =+H26-SUM(J27:K27,N27) -> 0 | M27: =IFERROR(ROUND(M26/E26*G26,0),0) -> 0 | N27: =IFERROR(ROUND(N26/F26*H26,0),0) -> 0
B28: 過年度に購入した固定資産の取得に伴う振替 | E28: 特定収入以外 | F28: =+IFERROR(VLOOKUP($E28,$P$2:$W$5,2,0),"-") -> - | G28: 334220 | H28: =IFERROR(ROUND((G28)*F28/F29,0),0) -> 0 | I28: =G28-H28 -> 334220 | L28: =+IFERROR(VLOOKUP($E28,$P$2:$W$5,6,0),"-") -> - | M28: =+IFERROR(VLOOKUP($E28,$P$2:$W$5,7,0),"-") -> - | N28: =+IFERROR(VLOOKUP($E28,$P$2:$W$5,7,0),"-") -> -
F29: =+IFERROR(VLOOKUP($E28,$P$2:$W$5,3,0),"-") -> - | L29: =+H28-SUM(J29:K29,N29) -> 0 | M29: =IFERROR(ROUND(M28/E28*G28,0),0) -> 0 | N29: =IFERROR(ROUND(N28/F28*H28,0),0) -> 0
F30: =+IFERROR(VLOOKUP($E30,$P$2:$W$5,2,0),"-") -> - | H30: =IFERROR(ROUND((G30)*F30/F31,0),0) -> 0 | I30: =G30-H30 -> 0 | L30: =+IFERROR(VLOOKUP($E30,$P$2:$W$5,6,0),"-") -> - | M30: =+IFERROR(VLOOKUP($E30,$P$2:$W$5,7,0),"-") -> - | N30: =+IFERROR(VLOOKUP($E30,$P$2:$W$5,7,0),"-") -> -
F31: =+IFERROR(VLOOKUP($E30,$P$2:$W$5,3,0),"-") -> - | L31: =+H30-SUM(J31:K31,N31) -> 0 | M31: =IFERROR(ROUND(M30/E30*G30,0),0) -> 0 | N31: =IFERROR(ROUND(N30/F30*H30,0),0) -> 0
B32: 計 | G32: =SUM(G22:G31) -> 1155175 | H32: =+SUM(H22:H31) -> 0 | I32: =G32-H32 -> 1155175
L33: =+SUM(L23,L25,L27,L29,L31) -> 0 | M33: =+SUM(M23,M25,M27,M29,M31) -> 0 | N33: =+SUM(N23,N25,N27,N29,N31) -> 0
A34: その他特別利益 | B34: 手当等の戻入 | E34: 不課税支出に対応する不課税収入のため特定収入以外 | F34: =+IFERROR(VLOOKUP($E34,$P$2:$W$5,2,0),"-") -> - | G34: 0 | H34: =IFERROR(ROUND((G34)*F34/F35,0),0) -> 0 | I34: =G34-H34 -> 0 | L34: =+IFERROR(VLOOKUP($E34,$P$2:$W$5,6,0),"-") -> - | M34: =+IFERROR(VLOOKUP($E34,$P$2:$W$5,7,0),"-") -> - | N34: =+IFERROR(VLOOKUP($E34,$P$2:$W$5,8,0),"-") -> -
F35: =+IFERROR(VLOOKUP($E34,$P$2:$W$5,3,0),"-") -> - | L35: =+H34-SUM(J35:K35,M35:N35) -> 0 | M35: =IFERROR(ROUND(M34/$F34*$H34,0),0) -> 0 | N35: =IFERROR(ROUND(N34/$F34*$H34,0),0) -> 0
B36: 契約解除に伴う履行保証保険金 | E36: 特定収入以外 | F36: =+IFERROR(VLOOKUP($E36,$P$2:$W$5,2,0),"-") -> - | G36: 0 | H36: =IFERROR(ROUND((G36)*F36/F37,0),0) -> 0 | I36: =G36-H36 -> 0 | L36: =+IFERROR(VLOOKUP($E36,$P$2:$W$5,6,0),"-") -> - | M36: =+IFERROR(VLOOKUP($E36,$P$2:$W$5,7,0),"-") -> - | N36: =+IFERROR(VLOOKUP($E36,$P$2:$W$5,8,0),"-") -> -
F37: =+IFERROR(VLOOKUP($E36,$P$2:$W$5,3,0),"-") -> - | L37: =+H36-SUM(J37:K37,M37:N37) -> 0 | M37: =IFERROR(ROUND(M36/$F36*$H36,0),0) -> 0 | N37: =IFERROR(ROUND(N36/$F36*$H36,0),0) -> 0
B38: 契約解除違約金 | E38: 特定収入以外 | F38: =+IFERROR(VLOOKUP($E38,$P$2:$W$5,2,0),"-") -> - | G38: 0 | H38: =IFERROR(ROUND((G38)*F38/F39,0),0) -> 0 | I38: =G38-H38 -> 0 | L38: =+IFERROR(VLOOKUP($E38,$P$2:$W$5,6,0),"-") -> - | M38: =+IFERROR(VLOOKUP($E38,$P$2:$W$5,7,0),"-") -> - | N38: =+IFERROR(VLOOKUP($E38,$P$2:$W$5,8,0),"-") -> -
F39: =+IFERROR(VLOOKUP($E38,$P$2:$W$5,3,0),"-") -> - | L39: =+H38-SUM(J39:K39,M39:N39) -> 0 | M39: =IFERROR(ROUND(M38/$F38*$H38,0),0) -> 0 | N39: =IFERROR(ROUND(N38/$F38*$H38,0),0) -> 0
B40: 償却資産の所管替えに伴う除却損相当額 | E40: 特定収入以外 | G40: 864807 | H40: =IFERROR(ROUND((G40)*F40/F41,0),0) -> 0 | I40: =G40-H40 -> 864807 | L40: =+IFERROR(VLOOKUP($E40,$P$2:$W$5,6,0),"-") -> - | M40: =+IFERROR(VLOOKUP($E40,$P$2:$W$5,7,0),"-") -> - | N40: =+IFERROR(VLOOKUP($E40,$P$2:$W$5,8,0),"-") -> -
L41: =+H40-SUM(J41:K41,M41:N41) -> 0 | M41: =IFERROR(ROUND(M40/$F40*$H40,0),0) -> 0 | N41: =IFERROR(ROUND(N40/$F40*$H40,0),0) -> 0
B42: その他特別利益 小計 | G42: =SUM(G34:G41) -> 864807 | H42: =SUM(H34:H41) -> 0 | I42: =SUM(I34:I41) -> 864807
L43: =+SUM(L35,L37,L39) -> 0 | M43: =+SUM(M35,M37,M39) -> 0 | N43: =+SUM(N35,N37,N39) -> 0
B44: 貸倒引当金戻入益 | D44: 過年度貸倒引当金 繰入額支出の返還 | E44: 不課税支出に対応する不課税収入のため特定収入以外 | F44: =+IFERROR(VLOOKUP($E44,$P$2:$W$5,2,0),"-") -> - | G44: =+'[2]3条収入'!$E$64 -> 455622 | H44: =IFERROR(ROUND((G44)*F44/F45,0),0) -> 0 | I44: =G44-H44 -> 455622 | L44: =+IFERROR(VLOOKUP($E44,$P$2:$W$5,6,0),"-") -> - | M44: =+IFERROR(VLOOKUP($E44,$P$2:$W$5,7,0),"-") -> - | N44: =+IFERROR(VLOOKUP($E44,$P$2:$W$5,8,0),"-") -> -
F45: =+IFERROR(VLOOKUP($E44,$P$2:$W$5,3,0),"-") -> - | L45: =+H44-SUM(J45:K45,M45:N45) -> 0 | M45: =IFERROR(ROUND(M44/$F44*$H44,0),0) -> 0 | N45: =IFERROR(ROUND(N44/$F44*$H44,0),0) -> 0
B46: 賞与引当金戻入益 | D46: 過年度賞与引当金 繰入額支出の返還 | E46: 不課税支出に対応する不課税収入のため特定収入以外 | F46: =+IFERROR(VLOOKUP($E46,$P$2:$W$5,2,0),"-") -> - | G46: =+'[2]3条収入'!$E$65 -> 109000 | H46: =IFERROR(ROUND((G46)*F46/F47,0),0) -> 0 | I46: =G46-H46 -> 109000 | L46: =+IFERROR(VLOOKUP($E46,$P$2:$W$5,6,0),"-") -> - | M46: =+IFERROR(VLOOKUP($E46,$P$2:$W$5,7,0),"-") -> - | N46: =+IFERROR(VLOOKUP($E46,$P$2:$W$5,8,0),"-") -> -
F47: =+IFERROR(VLOOKUP($E46,$P$2:$W$5,3,0),"-") -> - | L47: =+H46-SUM(J47:K47,M47:N47) -> 0 | M47: =IFERROR(ROUND(M46/$F46*$H46,0),0) -> 0 | N47: =IFERROR(ROUND(N46/$F46*$H46,0),0) -> 0
B48: 計 | G48: =SUM(G42:G47) -> 1429429 | H48: =SUM(H42:H47) -> 0 | I48: =SUM(I42:I47) -> 1429429
L49: =+SUM(L43,L45,L47) -> 0 | M49: =+SUM(M43,M45,M47) -> 0 | N49: =+SUM(N43,N45,N47) -> 0
G50: 3条収入シート | H50: チェック
F51: 雑収益 | G51: =+'[2]3条収入'!$V$51 -> 1202214 | H51: =+G18-G51 -> 0
F52: 消費税還付 | G52: =+'[2]3条収入'!$V$49 -> 0 | H52: =+G20-G52 -> 0
F53: 過年度修正益 | G53: =+'[2]3条収入'!$V$60 -> 1155175 | H53: =+G32-G53 -> 0
F54: その他特利 | G54: =+'[2]3条収入'!$V$62 -> 1429429 | H54: =+G48-G54 -> 0
F55: 計 | G55: =SUM(G51:G54) -> 3786818 | H55: =+G6-G55 -> 0

Sheet 3条災害補助
A1: =+"令和"&MID(総括表!A2,3,1)&"年度決算 不課税収入区分表（国庫補助金〔３条〕）" -> 令和５年度決算 不課税収入区分表（国庫補助金〔３条〕）
I3: (単位：円)
A4: 区分 | D4: 対象経費 | E4: 按分方法 | F4: 課税支出額 | G4: 不課税収入額 | H4: 特定収入 | I4: 特定収入 以外 | J4: 特定収入内訳（上段：課税支出額、下段特定収入の按分）
F5: 支出額合計 | J5: 0.03 | K5: 0.05 | L5: 0.08 | M5: 0.08 | N5: 0.1
A6: その他国庫補助金 | G6: =SUM(G8,G22,G36,G50) -> 0 | H6: =SUM(H8,H22,H36,H50) -> 0 | I6: =SUM(I8,I22,I36,I50) -> 0 | J6: =SUM(J9,J23,J37,J51) -> 0 | K6: =SUM(K9,K23,K37,K51) -> 0 | L6: =SUM(L9,L23,L37,L51) -> 0 | M6: =SUM(M9,M23,M37,M51) -> 0 | N6: =SUM(N9,N23,N37,N51) -> 0
B8: その他国庫補助金(公共） | G8: =SUM(G10:G21) -> 0 | H8: =SUM(H10:H21) -> 0 | I8: =SUM(I10:I21) -> 0
L9: =+L13+L19 -> 0 | M9: =+M13+M19 -> 0 | N9: =+N13+N19 -> 0
B10: 公共下水道事業 | C10: 公共土木施設災害 復旧事業費国庫負担金 | D10: 対象事業費×２／３ | E10: 3年度分 公共土木施設災害復旧事業費(補助事業現年分)の課税支出割合 | G10: 0
F12: =+SUM('[1]3条支出'!$K$88:$K$90) -> 0 | H12: =IFERROR(ROUND(SUM(G10:G15)*F12/F13,0),0) -> 0 | I12: =SUM(G10:G15)-H12 -> 0 | L12: =SUM('[1]3条支出'!$F$88:$G$90)+SUM('[1]3条支出'!H88:H90) -> 0 | M12: =SUM('[1]3条支出'!I88:I90) -> 0 | N12: =SUM('[1]3条支出'!J88:J90) -> 0
F13: =+SUM('[1]3条支出'!$E$88:$E$90) -> 0 | L13: =+H12-SUM(J13:K13,M13:N13) -> 0 | M13: =IFERROR(ROUND(M12/F12*H12,0),0) -> 0 | N13: =IFERROR(ROUND(N12/F12*H12,0),0) -> 0
C16: 公共土木施設災害 復旧事業費国庫負担金 | D16: 対象事業費×２／３ | E16: 2年度分 公共土木施設災害復旧事業費(補助事業繰越分)の課税支出割合
F18: =+SUM('[1]3条支出'!$K$101:$K$103) -> 0 | H18: =IFERROR(ROUND(SUM(G16:G21)*F18/F19,0),0) -> 0 | I18: =SUM(G16:G21)-H18 -> 0 | L18: =SUM('[1]3条支出'!$F$101:$G$103)+SUM('[1]3条支出'!H101:H103) -> 0 | M18: =SUM('[1]3条支出'!I101:I103) -> 0 | N18: =SUM('[1]3条支出'!J101:J103) -> 0
F19: =+SUM('[1]3条支出'!$E$101:$E$103) -> 0 | L19: =+H18-SUM(J19:K19,M19:N19) -> 0 | M19: =IFERROR(ROUND(M18/F18*H18,0),0) -> 0 | N19: =IFERROR(ROUND(N18/F18*H18,0),0) -> 0
B22: その他国庫補助金(特環） | G22: =SUM(G24:G35) -> 0 | H22: =SUM(H24:H35) -> 0 | I22: =SUM(I24:I35) -> 0
L23: =+L27+L33 -> 0 | M23: =+M27+M33 -> 0 | N23: =+N27+N33 -> 0
B24: 特定環境保全公共下水道 | C24: 公共土木施設災害 復旧事業費国庫負担金 | D24: 対象事業費×２／３ | E24: =+E10 -> 3年度分 公共土木施設災害復旧事業費(補助事業現年分)の課税支出割合 | G24: 0
F26: =+'[1]3条支出'!$K$91 -> 0 | H26: =IFERROR(ROUND(SUM(G24:G29)*F26/F27,0),0) -> 0 | I26: =SUM(G24:G29)-H26 -> 0 | L26: =SUM('[1]3条支出'!$F$91:$G$91)+SUM('[1]3条支出'!H91) -> 0 | M26: =SUM('[1]3条支出'!I91) -> 0 | N26: =SUM('[1]3条支出'!J91) -> 0
F27: =+'[1]3条支出'!$E$91 -> 0 | L27: =+H26-SUM(J27:K27,M27:N27) -> 0 | M27: =IFERROR(ROUND(M26/F26*H26,0),0) -> 0 | N27: =IFERROR(ROUND(N26/F26*H26,0),0) -> 0
C30: 公共土木施設災害 復旧事業費国庫負担金 | D30: 対象事業費×２／３ | E30: =+E16 -> 2年度分 公共土木施設災害復旧事業費(補助事業繰越分)の課税支出割合
F32: =+'[1]3条支出'!$K$104 -> 0 | H32: =IFERROR(ROUND(SUM(G30:G35)*F32/F33,0),0) -> 0 | I32: =SUM(G30:G35)-H32 -> 0 | L32: =SUM('[1]3条支出'!$F$104:$G$104)+SUM('[1]3条支出'!H104) -> 0 | M32: =SUM('[1]3条支出'!I104) -> 0 | N32: =SUM('[1]3条支出'!J104) -> 0
F33: =+'[1]3条支出'!$E$104 -> 0 | L33: =+H32-SUM(J33:K33,M33:N33) -> 0 | M33: =IFERROR(ROUND(M32/F32*H32,0),0) -> 0 | N33: =IFERROR(ROUND(N32/F32*H32,0),0) -> 0
B36: その他国庫補助金(農集） | G36: =SUM(G38:G49) -> 0 | H36: =SUM(H38:H49) -> 0 | I36: =SUM(I38:I49) -> 0
L37: =+L41+L47 -> 0 | M37: =+M41+M47 -> 0 | N37: =+N41+N47 -> 0
B38: 農業集落排水事業 | C38: 災害関連農村生活環境 施設復旧事業国庫補助金 | E38: 3年度分 災害関連農村生活環境施設復旧事業(補助事業現年分)の課税支出割合
F40: =+'[1]3条支出'!$K$92 -> 0 | H40: =IFERROR(ROUND(SUM(G38:G43)*F40/F41,0),0) -> 0 | I40: =SUM(G38:G43)-H40 -> 0 | L40: =SUM('[1]3条支出'!$F$92:$G$92)+SUM('[1]3条支出'!H92) -> 0 | M40: =SUM('[1]3条支出'!I92) -> 0 | N40: =SUM('[1]3条支出'!J92) -> 0
F41: =+'[1]3条支出'!$E$92 -> 0 | L41: =+H40-SUM(J41:K41,M41:N41) -> 0 | M41: =IFERROR(ROUND(M40/F40*H40,0),0) -> 0 | N41: =IFERROR(ROUND(N40/F40*H40,0),0) -> 0
C44: 災害関連農村生活環境 施設復旧事業国庫補助金 | D44: 対象事業費×１／２ | E44: 2年度分 災害関連農村生活環境施設復旧事業(補助事業繰越分)の課税支出割合
F46: =+'[1]3条支出'!$K$105 -> 0 | H46: =IFERROR(ROUND(SUM(G44:G49)*F46/F47,0),0) -> 0 | I46: =SUM(G44:G49)-H46 -> 0 | L46: =SUM('[1]3条支出'!$F$105:$G$105)+SUM('[1]3条支出'!H105) -> 0 | M46: =SUM('[1]3条支出'!I105) -> 0 | N46: =SUM('[1]3条支出'!J105) -> 0
F47: =+'[1]3条支出'!$E$105 -> 0 | L47: =+H46-SUM(J47:K47,M47:N47) -> 0 | M47: =IFERROR(ROUND(M46/F46*H46,0),0) -> 0 | N47: =IFERROR(ROUND(N46/F46*H46,0),0) -> 0
B50: その他国庫補助金(浄化槽） | G50: =SUM(G52:G63) -> 0 | H50: =SUM(H52:H63) -> 0 | I50: =SUM(I52:I63) -> 0
L51: =+L55+L61 -> 0 | M51: =+M55+M61 -> 0 | N51: =+N55+N61 -> 0
B52: 市営浄化槽事業
F54: =+'[1]3条支出'!$K$93 -> 0 | H54: =IFERROR(ROUND(SUM(G52:G57)*F54/F55,0),0) -> 0 | I54: =SUM(G52:G57)-H54 -> 0 | L54: =SUM('[1]3条支出'!$F$93:$G$93)+SUM('[1]3条支出'!H93) -> 0 | M54: =SUM('[1]3条支出'!I93) -> 0 | N54: =SUM('[1]3条支出'!J93) -> 0
F55: =+'[1]3条支出'!$E$93 -> 0 | L55: =+H54-SUM(J55:K55,M55:N55) -> 0 | M55: =IFERROR(ROUND(M54/F54*H54,0),0) -> 0 | N55: =IFERROR(ROUND(N54/F54*H54,0),0) -> 0
F60: =+'[1]3条支出'!$K$106 -> 0 | H60: =IFERROR(ROUND(SUM(G58:G63)*F60/F61,0),0) -> 0 | I60: =SUM(G58:G63)-H60 -> 0 | L60: =SUM('[1]3条支出'!$F$106:$G$106)+SUM('[1]3条支出'!H106) -> 0 | M60: =SUM('[1]3条支出'!I106) -> 0 | N60: =SUM('[1]3条支出'!J106) -> 0
F61: =+'[1]3条支出'!$E$106 -> 0 | L61: =+H60-SUM(J61:K61,M61:N61) -> 0 | M61: =IFERROR(ROUND(M60/F60*H60,0),0) -> 0 | N61: =IFERROR(ROUND(N60/F60*H60,0),0) -> 0
F64: 3条収入シート その他国庫補助金（災害） | G64: =+'[2]3条収入'!$E$34 -> 0
F65: チェック | G65: =+G6-G64 -> 0

Sheet 4条補助（公）
A1: =+"令和"&MID(総括表!A2,3,1)&"年度決算 不課税収入区分表(公共下水道整備国庫補助金)" -> 令和５年度決算 不課税収入区分表(公共下水道整備国庫補助金)
I3: (単位：円)
A4: 区分 | D4: 対象経費 | E4: 按分方法 | F4: 課税支出額 | G4: 不課税収入額 | H4: 特定収入 | I4: 特定収入 以外 | J4: 特定収入内訳（上段：課税支出額、下段特定収入の按分） | P4: 特定収入に係る課税仕入れ等に係る消費税額
F5: 支出額合計 | J5: 0.03 | K5: 0.05 | L5: 0.08 | M5: 0.08 | N5: 0.1 | P5: 0.05 | Q5: 0.08 | R5: 0.08 | S5: 0.1 | T5: 計 | U5: ④４条収入とのチェック
A6: 国庫補助金 | G6: =SUM(G8:G43) -> 5683800000 | H6: =H19+H37 -> 5678297006 | I6: =I19+I37 -> 5502994 | J6: =+J20+J38 -> 0 | K6: =+K20+K38 -> 0 | L6: =+L20+L38 -> 0 | M6: =+M20+M38 -> 0 | N6: =+N20+N38 -> 5678297006 | P6: =+P20+P38 -> 0 | Q6: =+Q20+Q38 -> 0 | R6: =+R20+R38 -> 0 | S6: =+S20+S38 -> 516208819 | T6: =+T20+T38 -> 516208819 | U6: =+T6-'[4]4条収入'!$AH$25 -> 0
B8: 公 共 下 水 道 | C8: 管路等・一般 | D8: 4,762,313.150千円×５／１０ | E8: 5年度分 公共下水道整備事業 (補助事業現年分)の 課税支出割合 | G8: =4762313.15*1000*5/10+60735.85*1000*5/10+1500 -> 2411526000
C10: 管路等・補助裏単市 | D10: 60,375.850千円×５／１０
C12: 管路等・工事国債
C14: 管路等・特債
C16: 管路等・都市水
C18: 管路等・促進・工事国債
F19: 5036234000 | H19: =IFERROR(ROUND(SUM(G8:G31)*F19/F20,0),0) -> 2527700000 | I19: =SUM(G8:G31)-H19 -> 0 | L19: 0 | N19: =F19-SUM(L19:M19) -> 5036234000
C20: 処理場・一般・高率 | D20: 191,660千円×５．５／１０ | F20: 5036234000 | G20: =191660*1000*5.5/10 -> 105413000 | L20: =+H19-SUM(J20:K20,M20:N20) -> 0 | M20: =IFERROR(ROUND(M19/F19*H19,0),0) -> 0 | N20: =IFERROR(ROUND(N19/F19*H19,0),0) -> 2527700000 | P20: =+ROUND(K20*P$5/(1+P$5),0) -> 0 | Q20: =+ROUND(L20*Q$5/(1+Q$5),0) -> 0 | R20: =+ROUND(M20*R$5/(1+R$5),0) -> 0 | S20: =+ROUND(N20*S$5/(1+S$5),0) -> 229790909 | T20: =SUM(P20:S20) -> 229790909
C22: 処理場・一般・低率 | D22: 21,525千円×５／１０ | G22: =21525*1000*5/10-1500 -> 10761000
C24: 処理場・用地国債
C26: 処理場・特債・高率
C28: 処理場・特債・低率
C30: 過年度補助金
C32: 管路等・一般(繰越分) | D32: 4,286,012.1千円×５／１０ | E32: 4年度分 公共下水道整備事業 (補助事業繰越分)の 課税支出割合 | G32: =(3089012.1+103800+1197000)*1000*5/10+13187900*5/10 -> 2201500000
C34: 管路等・補助裏単市 （繰越分） | D34: 13,187.9千円×５／１０
C36: 管路等・一般(高率分)
F37: 6172219286 | H37: =IFERROR(ROUND(SUM(G32:G43)*F37/F38,0),0) -> 3150597006 | I37: =SUM(G32:G43)-H37 -> 5502994 | L37: 0 | M37: 0 | N37: =F37-SUM(L37:M37) -> 6172219286
C38: 処理場・一般・高率 (繰越分) | D38: 1,292,000千円×５．５／１０ | F38: 6183000000 | G38: =(1142500+149500)*1000*5.5/10 -> 710600000 | L38: =+H37-SUM(J38:K38,M38:N38) -> 0 | M38: =IFERROR(ROUND(M37/F37*H37,0),0) -> 0 | N38: =IFERROR(ROUND(N37/F37*H37,0),0) -> 3150597006 | P38: =+ROUND(K38*P$5/(1+P$5),0) -> 0 | Q38: =+ROUND(L38*Q$5/(1+Q$5),0) -> 0 | R38: =+ROUND(M38*R$5/(1+R$5),0) -> 0 | S38: =+ROUND(N38*S$5/(1+S$5),0) -> 286417910 | T38: =SUM(P38:S38) -> 286417910
C40: 処理場・一般・低率 (繰越分) | D40: 488,000千円×５／１０ | G40: =488000000*5/10 -> 244000000
C42: 処理場・特債・高率 (繰越分)

Sheet 4条補助（特）
A1: =+"令和"&MID(総括表!A2,3,1)&"年度決算 不課税収入区分表(汚水処理施設整備交付金)（特環）" -> 令和５年度決算 不課税収入区分表(汚水処理施設整備交付金)（特環）
I3: (単位：円)
A4: 区分 | D4: 対象経費 | E4: 按分方法 | F4: 課税支出額 | G4: 不課税収入額 | H4: 特定収入 | I4: 特定収入 以外 | J4: 特定収入内訳（上段：課税支出額、下段特定収入の按分） | P4: 特定収入に係る課税仕入れ等に係る消費税額
F5: 支出額合計 | J5: 0.03 | K5: 0.05 | L5: 0.08 | M5: 0.08 | N5: 0.1 | P5: 0.05 | Q5: 0.08 | R5: 0.08 | S5: 0.1 | T5: 計 | U5: ④４条収入とのチェック
A6: 国庫補助金 | G6: =SUM(G8:G43) -> 30500000 | H6: =H19+H37 -> 30500000 | I6: =I19+I37 -> 0 | J6: =+J20+J38 -> 0 | K6: =+K20+K38 -> 0 | L6: =+L20+L38 -> 0 | M6: =+M20+M38 -> 0 | N6: =+N20+N38 -> 30500000 | P6: =+P20+P38 -> 0 | Q6: =+Q20+Q38 -> 0 | R6: =+R20+R38 -> 0 | S6: =+S20+S38 -> 2772727 | T6: =+T20+T38 -> 2772727 | U6: =+T6-'[4]4条収入'!$AH$32 -> 0
B8: 特 定 環 境 保 全 公 共 下 水 道 | C8: 管路等・一般 | D8: 25,200千円×５／１０ | E8: 5年度分 特定環境保全公共下水道整備事業 (補助事業現年分)の 課税支出割合 | G8: =659000+11941000 -> 12600000
C10: 管路等・一般
C12: 管路等・用地国債
C14: 管路等・特債
C16: 管路等・都市水
C18: 管路等・促進・工事国債
F19: 25200000 | H19: =IFERROR(ROUND(SUM(G8:G21)*F19/F20,0),0) -> 12600000 | I19: =SUM(G8:G31)-H19 -> 0 | L19: 0 | M19: 0 | N19: =F19-SUM(L19:M19) -> 25200000
C20: 処理場・一般 | F20: 25200000 | L20: =+H19-SUM(J20:K20,M20:N20) -> 0 | M20: =IFERROR(ROUND(M19/F19*H19,0),0) -> 0 | N20: =IFERROR(ROUND(N19/F19*H19,0),0) -> 12600000 | P20: =+ROUND(K20*P$5/(1+P$5),0) -> 0 | Q20: =+ROUND(L20*Q$5/(1+Q$5),0) -> 0 | R20: =+ROUND(M20*R$5/(1+R$5),0) -> 0 | S20: =+ROUND(N20*S$5/(1+S$5),0)-1 -> 1145454 | T20: =SUM(P20:S20) -> 1145454
C22: 処理場・一般
C24: 処理場・用地国債
C26: 処理場・特債・高率
C28: 処理場・特債・低率
C30: 過年度補助金
C32: 管路等・一般(繰越分) | D32: 5,000千円×５／１０ | E32: 4年度分 特定環境保全公共下水道整備事業 (補助事業繰越分)の 課税支出割合 | G32: 2500000
C34: 管路等・都市水
C36: 管路等・特債(繰越分）
F37: 33015490 | H37: =IFERROR(ROUND(SUM(G32:G39)*F37/F38,0),0) -> 17900000 | I37: =SUM(G32:G43)-H37 -> 0 | L37: 0 | M37: 0 | N37: =F37-SUM(L37:M37) -> 33015490
C38: 処理場・一般・高率 (繰越分) | D38: 28,000千円×５．５／１０ | F38: 33015490 | G38: 15400000 | L38: =+H37-SUM(J38:K38,M38:N38) -> 0 | M38: =IFERROR(ROUND(M37/F37*H37,0),0) -> 0 | N38: =IFERROR(ROUND(N37/F37*H37,0),0) -> 17900000 | P38: =+ROUND(K38*P$5/(1+P$5),0) -> 0 | Q38: =+ROUND(L38*Q$5/(1+Q$5),0) -> 0 | R38: =+ROUND(M38*R$5/(1+R$5),0) -> 0 | S38: =+ROUND(N38*S$5/(1+S$5),0) -> 1627273 | T38: =SUM(P38:S38) -> 1627273
C40: 処理場・一般・低率 (繰越分)
C42: 処理場・特債・高率 (繰越分)

Sheet 4条補助（農）
A1: =+"令和"&MID(総括表!A2,3,1)&"年度決算 不課税収入区分表(汚水処理施設整備交付金)（農集）" -> 令和５年度決算 不課税収入区分表(汚水処理施設整備交付金)（農集）
I3: (単位：円)
A4: 区分 | D4: 対象経費 | E4: 按分方法 | F4: 課税支出額 | G4: 不課税収入額 | H4: 特定収入 | I4: 特定収入 以外 | J4: 特定収入内訳（上段：課税支出額、下段特定収入の按分） | P4: 特定収入に係る課税仕入れ等に係る消費税額
F5: 支出額合計 | J5: 0.03 | K5: 0.05 | L5: 0.08 | M5: 0.08 | N5: 0.1 | P5: 0.05 | Q5: 0.08 | R5: 0.08 | S5: 0.1 | T5: 計 | U5: ④４条収入とのチェック
A6: 国庫補助金 | G6: =SUM(G8:G43) -> 0 | H6: =H19+H37 -> 0 | I6: =I19+I37 -> 0 | J6: =+J20+J38 -> 0 | K6: =+K20+K38 -> 0 | L6: =+L20+L38 -> 0 | M6: =+M20+M38 -> 0 | N6: =+N20+N38 -> 0 | P6: =+P20+P38 -> 0 | Q6: =+Q20+Q38 -> 0 | R6: =+R20+R38 -> 0 | S6: =+S20+S38 -> 0 | T6: =+T20+T38 -> 0 | U6: =+T6-'[4]4条収入'!$AH$33 -> 0
B8: 農 業 集 落 排 水 | C8: 管路等・一般 | E8: 5年度分 農業集落排水事業 (補助事業現年分)の 課税支出割合
C10: 管路等・一般 | D10: ●千円×１０／１０
C12: 管路等・用地国債
C14: 管路等・特債
C16: 管路等・都市水
C18: 管路等・促進・工事国債
H19: =IFERROR(ROUND(SUM(G8:G21)*F19/F20,0),0) -> 0 | I19: =SUM(G8:G31)-H19 -> 0 | L19: 0 | M19: 0 | N19: =F19-SUM(L19:M19) -> 0
C20: 処理場・一般 | L20: =+H19-SUM(J20:K20,M20:N20) -> 0 | M20: =IFERROR(ROUND(M19/F19*H19,0),0) -> 0 | N20: =IFERROR(ROUND(N19/F19*H19,0),0) -> 0 | P20: =+ROUND(K20*P$5/(1+P$5),0) -> 0 | Q20: =+ROUND(L20*Q$5/(1+Q$5),0) -> 0 | R20: =+ROUND(M20*R$5/(1+R$5),0) -> 0 | S20: =+ROUND(N20*S$5/(1+S$5),0) -> 0 | T20: =SUM(P20:S20) -> 0
C22: 処理場・一般
C24: 処理場・用地国債
C26: 処理場・特債・高率
C28: 処理場・特債・低率
C30: 過年度補助金
C32: 管路等・一般(繰越分) | D32: 75,000千円×５／１０ | E32: 4年度分 農業集落排水事業 (補助事業繰越分)の 課税支出割合
C34: 管路等高率
C36: 管路等・特債(繰越分）
H37: =IFERROR(ROUND(SUM(G32:G39)*F37/F38,0),0) -> 0 | I37: =SUM(G32:G43)-H37 -> 0 | L37: 0 | M37: 0 | N37: =F37-SUM(L37:M37) -> 0
C38: 処理場・一般 (繰越分) | L38: =+H37-SUM(J38:K38,M38:N38) -> 0 | M38: =IFERROR(ROUND(M37/F37*H37,0),0) -> 0 | N38: =IFERROR(ROUND(N37/F37*H37,0),0) -> 0 | P38: =+ROUND(K38*P$5/(1+P$5),0) -> 0 | Q38: =+ROUND(L38*Q$5/(1+Q$5),0) -> 0 | R38: =+ROUND(M38*R$5/(1+R$5),0) -> 0 | S38: =+ROUND(N38*S$5/(1+S$5),0) -> 0 | T38: =SUM(P38:S38) -> 0
C40: 処理場・一般 (繰越分) | D40: ●千円×５／１０
C42: 処理場・特債・高率 (繰越分)

Sheet 4条補助（浄）
A1: =+"令和"&MID(総括表!A2,3,1)&"年度決算 不課税収入区分表(汚水処理施設整備交付金)（浄化槽）" -> 令和５年度決算 不課税収入区分表(汚水処理施設整備交付金)（浄化槽）
I3: (単位：円)
A4: 区分 | D4: 対象経費 | E4: 按分方法 | F4: 課税支出額 | G4: 不課税収入額 | H4: 特定収入 | I4: 特定収入 以外 | J4: 特定収入内訳（上段：課税支出額、下段特定収入の按分） | P4: 特定収入に係る課税仕入れ等に係る消費税額
F5: 支出額合計 | J5: 0.03 | K5: 0.05 | L5: 0.08 | M5: 0.08 | N5: 0.1 | P5: 0.05 | Q5: 0.08 | R5: 0.08 | S5: 0.1 | T5: 計 | U5: ④４条収入とのチェック
A6: 国庫補助金 | G6: =SUM(G8:G43) -> 3488000 | H6: =H19+H37 -> 3488000 | I6: =I19+I37 -> 0 | J6: =+J20+J38 -> 0 | K6: =+K20+K38 -> 0 | L6: =+L20+L38 -> 0 | M6: =+M20+M38 -> 0 | N6: =+N20+N38 -> 3488000 | P6: =+P20+P38 -> 0 | Q6: =+Q20+Q38 -> 0 | R6: =+R20+R38 -> 0 | S6: =+S20+S38 -> 317091 | T6: =+T20+T38 -> 317091 | U6: =+T6-'[4]4条収入'!$AH$34 -> 0
B8: 市 営 浄 化 槽 | C8: 浄化槽 | D8: 12,726.2千円×１／３ | E8: 5年度分 市営浄化槽事業 (補助事業現年分)の 課税支出割合 | G8: 3488000
F19: 12760200 | H19: =IFERROR(ROUND(SUM(G8:G21)*F19/F20,0),0) -> 3488000 | I19: =SUM(G8:G31)-H19 -> 0 | L19: 0 | M19: 0 | N19: =F19-SUM(L19:M19) -> 12760200
F20: 12760200 | L20: =+H19-SUM(J20:K20,M20:N20) -> 0 | M20: =IFERROR(ROUND(M19/F19*H19,0),0) -> 0 | N20: =IFERROR(ROUND(N19/F19*H19,0),0) -> 3488000 | P20: =+ROUND(K20*P$5/(1+P$5),0) -> 0 | Q20: =+ROUND(L20*Q$5/(1+Q$5),0) -> 0 | R20: =+ROUND(M20*R$5/(1+R$5),0) -> 0 | S20: =+ROUND(N20*S$5/(1+S$5),0) -> 317091 | T20: =SUM(P20:S20) -> 317091
C32: 浄化槽 | D32: R4→R5 繰越なし | E32: 4年度分 市営浄化槽事業 (補助事業繰越分)の 課税支出割合 | G32: 0
F37: 0 | H37: =IFERROR(ROUND(SUM(G32:G39)*F37/F38,0),0) -> 0 | I37: =SUM(G32:G43)-H37 -> 0 | L37: =+F37-SUM(J37:K37,M37:N37) -> 0
F38: 0 | L38: =+H37-SUM(J38:K38,M38:N38) -> 0 | M38: =IFERROR(ROUND(M37/F37*H37,0),0) -> 0 | N38: =IFERROR(ROUND(N37/F37*H37,0),0) -> 0 | P38: =+ROUND(K38*P$5/(1+P$5),0) -> 0 | Q38: =+ROUND(L38*Q$5/(1+Q$5),0) -> 0 | R38: =+ROUND(M38*R$5/(1+R$5),0) -> 0 | S38: =+ROUND(N38*S$5/(1+S$5),0) -> 0 | T38: =SUM(P38:S38) -> 0

Sheet 受益（公）
A1: =+"令和"&MID(総括表!A2,3,1)&"年度決算 不課税収入区分表(受益者負担金)" -> 令和５年度決算 不課税収入区分表(受益者負担金)
I3: (単位：円)
A4: 区分 | D4: 対象経費 | E4: 按分方法 | F4: 課税支出額 | G4: 不課税収入額 | H4: 特定収入 | I4: 特定収入 以外 | J4: 特定収入内訳（上段：課税支出額、下段特定収入の按分） | P4: 特定収入に係る課税仕入れ等に係る消費税額
F5: 支出額合計 | J5: 0.03 | K5: 0.05 | L5: 0.08 | M5: 0.08 | N5: 0.1 | P5: 0.05 | Q5: 0.08 | R5: 0.08 | S5: 0.1 | T5: 計 | U5: ④４条収入とのチェック
A6: 受益者負担金 | G6: =G10+G8 -> 8799605 | H6: =H10+H8 -> 8525089 | I6: =I10+I8 -> 274516 | K6: =K9+K11 -> 0 | L6: =L9+L11 -> 338 | M6: =M9+M11 -> 99 | N6: =N9+N11 -> 8524652 | P6: =P9+P11 -> 0 | Q6: =Q9+Q11 -> 25 | R6: =R9+R11 -> 7 | S6: =S9+S11 -> 774968 | T6: =T9+T11 -> 775000 | U6: =+T6-'[4]4条収入'!$AH$44 -> 0
B8: 公共下水道 補助事業充当分 | E8: 5年度分補助事業 の課税支出割合 （現年） | F8: ='4条補助（公）'!F19 -> 5036234000 | G8: =E15 -> 5005000 | H8: =IFERROR(ROUND(F8/F9*G8,0),0) -> 5005000 | I8: =G8-H8 -> 0 | L8: ='4条補助（公）'!K19+'4条補助（公）'!L19 -> 0 | M8: ='4条補助（公）'!M19 -> 0 | N8: ='4条補助（公）'!N19 -> 5036234000
F9: =D15 -> 5036234000 | L9: =+H8-SUM(J9:K9,M9:N9) -> 0 | M9: =IFERROR(ROUND(M8/F8*H8,0),0) -> 0 | N9: =IFERROR(ROUND(N8/F8*H8,0),0) -> 5005000 | P9: =+ROUND(K9*P$5/(1+P$5),0) -> 0 | Q9: =+ROUND(L9*Q$5/(1+Q$5),0) -> 0 | R9: =+ROUND(M9*R$5/(1+R$5),0) -> 0 | S9: =+ROUND(N9*S$5/(1+S$5),0) -> 455000 | T9: =SUM(P9:S9) -> 455000
B10: 公共下水道 起債事業充当分 | E10: 5年度分起債事業 の課税支出割合 （現年） | F10: 1308137124 | G10: =E16 -> 3794605 | H10: =IFERROR(ROUND(F10/F11*G10,0),0) -> 3520089 | I10: =G10-H10 -> 274516 | L10: 125712 | M10: 36840 | N10: =F10-SUM(L10:M10) -> 1307974572
F11: =D16 -> 1410153000 | L11: =+H10-SUM(J11:K11,M11:N11) -> 338 | M11: =IFERROR(ROUND(M10/F10*H10,0),0) -> 99 | N11: =IFERROR(ROUND(N10/F10*H10,0),0) -> 3519652 | P11: =+ROUND(K11*P$5/(1+P$5),0) -> 0 | Q11: =+ROUND(L11*Q$5/(1+Q$5),0) -> 25 | R11: =+ROUND(M11*R$5/(1+R$5),0) -> 7 | S11: =+ROUND(N11*S$5/(1+S$5),0) -> 319968 | T11: =SUM(P11:S11) -> 320000
C14: 区分 | D14: 支出額 | E14: 受益者負担金の事業別金額
C15: 補助事業分(現年) | D15: ='4条補助（公）'!F20 -> 5036234000 | E15: 5005000
C16: 起債事業分(現年) | D16: 1410153000 | E16: =3390885+403720 -> 3794605
C17: 計 | D17: =D15+D16 -> 6446387000 | E17: =E15+E16 -> 8799605
E18: =E17-E15-E16 -> 0

Sheet 受益（区域外）
A1: =+"令和"&MID(総括表!A2,3,1)&"年度決算 不課税収入区分表(受益者分担金)（汚水処理施設整備）全体" -> 令和５年度決算 不課税収入区分表(受益者分担金)（汚水処理施設整備）全体
I3: (単位：円)
A4: 区分 | D4: 対象経費 | E4: 按分方法 | F4: 課税支出額 | G4: 不課税収入額 | H4: 特定収入 | I4: 特定収入 以外 | J4: 特定収入内訳（上段：課税支出額、下段特定収入の按分） | P4: 特定収入に係る課税仕入れ等に係る消費税額
F5: 支出額合計 | J5: 0.03 | K5: 0.05 | L5: 0.08 | M5: 0.08 | N5: 0.1 | P5: 0.05 | Q5: 0.08 | R5: 0.08 | S5: 0.1 | T5: 計 | U5: ④４条収入とのチェック
A6: 受益者分担金 | G6: =G10+G8 -> 35218280 | H6: =H10+H8 -> 33459431 | I6: =I10+I8 -> 1758849 | J6: =SUM(J26,J46,J66) -> 0 | K6: =SUM(K26,K46,K66) -> 0 | L6: =SUM(L26,L46,L66) -> 0 | M6: =SUM(M26,M46,M66) -> 0 | N6: =SUM(N26,N46,N66) -> 33459431 | P6: =SUM(P26,P46,P66) -> 0 | Q6: =SUM(Q26,Q46,Q66) -> 0 | R6: =SUM(R26,R46,R66) -> 0 | S6: =SUM(S26,S46,S66) -> 3041767 | T6: =SUM(T26,T46,T66) -> 3041767 | U6: =+T6-'[4]4条収入'!$AH$46 -> 0
B8: 汚水処理施設整備 補助事業充当分 | E8: 5年度分補助事業 の課税支出割合 （現年） | F8: =SUM(F28,F48,F68) -> 37960200 | G8: =SUM(G28,G48,G68) -> 1842000 | H8: =SUM(H28,H48,H68) -> 1842000 | I8: =G8-H8 -> 0 | J8: =SUM(J28,J48,J68) -> 0 | K8: =SUM(K28,K48,K68) -> 0 | L8: =SUM(L28,L48,L68) -> 0 | M8: =SUM(M28,M48,M68) -> 0 | N8: =SUM(N28,N48,N68) -> 37960200
F9: =D15 -> 37960200 | J9: =SUM(J29,J49,J69) -> 0 | K9: =SUM(K29,K49,K69) -> 0 | L9: =SUM(L29,L49,L69) -> 0 | M9: =SUM(M29,M49,M69) -> 0 | N9: =SUM(N29,N49,N69) -> 1842000 | P9: =SUM(P29,P49,P69) -> 0 | Q9: =SUM(Q29,Q49,Q69) -> 0 | R9: =SUM(R29,R49,R69) -> 0 | S9: =SUM(S29,S49,S69) -> 167455 | T9: =SUM(T29,T49,T69) -> 167455
B10: 汚水処理施設整備 起債事業充当分 | E10: 5年度分起債事業 の課税支出割合 （現年） | F10: =SUM(F30,F50,F70) -> 222348632 | G10: =SUM(G30,G50,G70) -> 33376280 | H10: =SUM(H30,H50,H70) -> 31617431 | I10: =G10-H10 -> 1758849 | J10: =SUM(J30,J50,J70) -> 0 | K10: =SUM(K30,K50,K70) -> 0 | L10: =SUM(L30,L50,L70) -> 0 | M10: =SUM(M30,M50,M70) -> 0 | N10: =SUM(N30,N50,N70) -> 222348632
F11: =D16 -> 235300000 | J11: =SUM(J31,J51,J71) -> 0 | K11: =SUM(K31,K51,K71) -> 0 | L11: =SUM(L31,L51,L71) -> 0 | M11: =SUM(M31,M51,M71) -> 0 | N11: =SUM(N31,N51,N71) -> 31617431 | P11: =SUM(P31,P51,P71) -> 0 | Q11: =SUM(Q31,Q51,Q71) -> 0 | R11: =SUM(R31,R51,R71) -> 0 | S11: =SUM(S31,S51,S71) -> 2874312 | T11: =SUM(T31,T51,T71) -> 2874312
C14: 区分 | D14: 支出額 | E14: 受益者分担金の事業別金額
C15: 補助事業分(現年) | D15: =SUM(D35,D55,D75) -> 37960200 | E15: =SUM(E35,E55,E75) -> 1842000
C16: 起債事業分(現年) | D16: =SUM(D36,D56,D76) -> 235300000 | E16: =SUM(E36,E56,E76) -> 33376280
C17: 計 | D17: =D15+D16 -> 273260200 | E17: =E15+E16 -> 35218280
E18: =E17-E15-E16 -> 0
A21: =+"令和"&MID(総括表!A2,3,2)&"年度決算 不課税収入区分表(受益者分担金)（汚水処理施設整備）特環" -> 令和５年年度決算 不課税収入区分表(受益者分担金)（汚水処理施設整備）特環
I23: (単位：円)
A24: 区分 | D24: 対象経費 | E24: 按分方法 | F24: 課税支出額 | G24: 不課税収入額 | H24: 特定収入 | I24: 特定収入 以外
F25: 支出額合計
A26: 受益者分担金 | G26: =G30+G28 -> 17022400 | H26: =H30+H28 -> 15741150 | I26: =I30+I28 -> 1281250 | L26: =L29+L31 -> 0 | M26: =M29+M31 -> 0 | N26: =N29+N31 -> 15741150 | P26: =P29+P31 -> 0 | Q26: =Q29+Q31 -> 0 | R26: =R29+R31 -> 0 | S26: =S29+S31 -> 1431014 | T26: =T29+T31 -> 1431014 | U26: =+T26-'[4]4条収入'!$AH$47 -> 0
B28: 汚水処理施設整備 補助事業充当分 | E28: =+$E$8 -> 5年度分補助事業 の課税支出割合 （現年） | F28: ='4条補助（特）'!F19 -> 25200000 | G28: =E35 -> 1246000 | H28: =IFERROR(ROUND(F28/F29*G28,0),0) -> 1246000 | I28: =G28-H28 -> 0 | L28: =+'4条補助（特）'!K19+'4条補助（特）'!L19 -> 0 | M28: =+'4条補助（特）'!M19 -> 0 | N28: =+'4条補助（特）'!N19 -> 25200000
F29: =D35 -> 25200000 | L29: =+H28-SUM(J29:K29,M29:N29) -> 0 | M29: =IFERROR(ROUND(M28/F28*H28,0),0) -> 0 | N29: =IFERROR(ROUND(N28/F28*H28,0),0) -> 1246000 | P29: =+ROUND(K29*P$5/(1+P$5),0) -> 0 | Q29: =+ROUND(L29*Q$5/(1+Q$5),0) -> 0 | R29: =+ROUND(M29*R$5/(1+R$5),0) -> 0 | S29: =+ROUND(N29*S$5/(1+S$5),0) -> 113273 | T29: =SUM(P29:S29) -> 113273
B30: 汚水処理施設整備 起債事業充当分 | E30: =+$E$10 -> 5年度分起債事業 の課税支出割合 （現年） | F30: 105752376 | G30: =E36 -> 15776400 | H30: =IFERROR(ROUND(F30/F31*G30,0),0) -> 14495150 | I30: =G30-H30 -> 1281250 | L30: 0 | M30: 0 | N30: =F30-SUM(L30:M30) -> 105752376
F31: =D36 -> 115100000 | L31: =+H30-SUM(J31:K31,M31:N31) -> 0 | M31: =IFERROR(ROUND(M30/F30*H30,0),0) -> 0 | N31: =IFERROR(ROUND(N30/F30*H30,0),0) -> 14495150 | P31: =+ROUND(K31*P$5/(1+P$5),0) -> 0 | Q31: =+ROUND(L31*Q$5/(1+Q$5),0) -> 0 | R31: =+ROUND(M31*R$5/(1+R$5),0) -> 0 | S31: =+ROUND(N31*S$5/(1+S$5),0) -> 1317741 | T31: =SUM(P31:S31) -> 1317741
C34: 区分 | D34: 支出額 | E34: 受益者分担金の事業別金額
C35: 補助事業分(現年) | D35: ='4条補助（特）'!F20 -> 25200000 | E35: =223000+1023000 -> 1246000
C36: 起債事業分(現年) | D36: 115100000 | E36: =431600+15344800 -> 15776400
C37: 計 | D37: =D35+D36 -> 140300000 | E37: =E35+E36 -> 17022400
E38: =E37-E35-E36 -> 0
A41: =+"令和"&MID(総括表!A2,3,2)&"度決算 不課税収入区分表(受益者分担金)（汚水処理施設整備）農集" -> 令和５年度決算 不課税収入区分表(受益者分担金)（汚水処理施設整備）農集
I43: (単位：円)
A44: 区分 | D44: 対象経費 | E44: 按分方法 | F44: 課税支出額 | G44: 不課税収入額 | H44: 特定収入 | I44: 特定収入 以外
F45: 支出額合計
A46: 受益者分担金 | G46: =G50+G48 -> 14115880 | H46: =H50+H48 -> 13788037 | I46: =I50+I48 -> 327843 | L46: =L49+L51 -> 0 | M46: =M49+M51 -> 0 | N46: =N49+N51 -> 13788037 | P46: =P49+P51 -> 0 | Q46: =Q49+Q51 -> 0 | R46: =R49+R51 -> 0 | S46: =S49+S51 -> 1253458 | T46: =T49+T51 -> 1253458 | U46: =+T46-'[4]4条収入'!$AH$48 -> 0
B48: 汚水処理施設整備 補助事業充当分 | E48: =+$E$8 -> 5年度分補助事業 の課税支出割合 （現年） | F48: ='4条補助（農）'!F19 -> 0 | G48: =E55 -> 0 | H48: =IFERROR(ROUND(F48/F49*G48,0),0) -> 0 | I48: =G48-H48 -> 0 | L48: =+'4条補助（農）'!K19+'4条補助（農）'!L19 -> 0 | M48: =+'4条補助（農）'!M19 -> 0 | N48: =+'4条補助（農）'!N19 -> 0
F49: =D55 -> 0 | L49: =+H48-SUM(J49:K49,M49:N49) -> 0 | M49: =IFERROR(ROUND(M48/F48*H48,0),0) -> 0 | N49: =IFERROR(ROUND(N48/F48*H48,0),0) -> 0 | P49: =+ROUND(K49*P$5/(1+P$5),0) -> 0 | Q49: =+ROUND(L49*Q$5/(1+Q$5),0) -> 0 | R49: =+ROUND(M49*R$5/(1+R$5),0) -> 0 | S49: =+ROUND(N49*S$5/(1+S$5),0) -> 0 | T49: =SUM(P49:S49) -> 0
B50: 汚水処理施設整備 起債事業充当分 | E50: =+$E$10 -> 5年度分起債事業 の課税支出割合 （現年） | F50: 77262892 | G50: =E56 -> 14115880 | H50: =IFERROR(ROUND(F50/F51*G50,0),0) -> 13788037 | I50: =G50-H50 -> 327843 | L50: 0 | M50: 0 | N50: =F50-SUM(L50:M50) -> 77262892
F51: =D56 -> 79100000 | L51: =+H50-SUM(J51:K51,M51:N51) -> 0 | M51: =IFERROR(ROUND(M50/F50*H50,0),0) -> 0 | N51: =IFERROR(ROUND(N50/F50*H50,0),0) -> 13788037 | P51: =+ROUND(K51*P$5/(1+P$5),0) -> 0 | Q51: =+ROUND(L51*Q$5/(1+Q$5),0) -> 0 | R51: =+ROUND(M51*R$5/(1+R$5),0) -> 0 | S51: =+ROUND(N51*S$5/(1+S$5),0) -> 1253458 | T51: =SUM(P51:S51) -> 1253458
C54: 区分 | D54: 支出額 | E54: 受益者分担金の事業別金額
C55: 補助事業分(現年) | D55: ='4条補助（農）'!F20 -> 0 | E55: 0
C56: 起債事業分(現年) | D56: 79100000 | E56: 14115880
C57: 計 | D57: =D55+D56 -> 79100000 | E57: =E55+E56 -> 14115880
E58: =E57-E55-E56 -> 0
A61: =+"令和"&MID(総括表!A2,3,2)&"度決算 不課税収入区分表(受益者分担金)（汚水処理施設整備）浄化槽" -> 令和５年度決算 不課税収入区分表(受益者分担金)（汚水処理施設整備）浄化槽
I63: (単位：円)
A64: 区分 | D64: 対象経費 | E64: 按分方法 | F64: 課税支出額 | G64: 不課税収入額 | H64: 特定収入 | I64: 特定収入 以外
F65: 支出額合計
A66: 受益者分担金 | G66: =G70+G68 -> 4080000 | H66: =H70+H68 -> 3930244 | I66: =I70+I68 -> 149756 | L66: =L69+L71 -> 0 | M66: =M69+M71 -> 0 | N66: =N69+N71 -> 3930244 | P66: =P69+P71 -> 0 | Q66: =Q69+Q71 -> 0 | R66: =R69+R71 -> 0 | S66: =S69+S71 -> 357295 | T66: =T69+T71 -> 357295 | U66: =+T66-'[4]4条収入'!$AH$49 -> 0
B68: 汚水処理施設整備 補助事業充当分 | E68: =+$E$8 -> 5年度分補助事業 の課税支出割合 （現年） | F68: ='4条補助（浄）'!F19 -> 12760200 | G68: =E75 -> 596000 | H68: =IFERROR(ROUND(F68/F69*G68,0),0) -> 596000 | I68: =G68-H68 -> 0 | L68: =+'4条補助（浄）'!K19+'4条補助（浄）'!L19 -> 0 | M68: =+'4条補助（浄）'!M19 -> 0 | N68: =+'4条補助（浄）'!N19 -> 12760200
F69: =D75 -> 12760200 | L69: =+H68-SUM(J69:K69,M69:N69) -> 0 | M69: =IFERROR(ROUND(M68/F68*H68,0),0) -> 0 | N69: =IFERROR(ROUND(N68/F68*H68,0),0) -> 596000 | P69: =+ROUND(K69*P$5/(1+P$5),0) -> 0 | Q69: =+ROUND(L69*Q$5/(1+Q$5),0) -> 0 | R69: =+ROUND(M69*R$5/(1+R$5),0) -> 0 | S69: =+ROUND(N69*S$5/(1+S$5),0) -> 54182 | T69: =SUM(P69:S69) -> 54182
B70: 汚水処理施設整備 起債事業充当分 | E70: =+$E$10 -> 5年度分起債事業 の課税支出割合 （現年） | F70: 39333364 | G70: =E76 -> 3484000 | H70: =IFERROR(ROUND(F70/F71*G70,0),0) -> 3334244 | I70: =G70-H70 -> 149756 | L70: 0 | M70: 0 | N70: =F70-SUM(L70:M70) -> 39333364
F71: =D76 -> 41100000 | L71: =+H70-SUM(J71:K71,M71:N71) -> 0 | M71: =IFERROR(ROUND(M70/F70*H70,0),0) -> 0 | N71: =IFERROR(ROUND(N70/F70*H70,0),0) -> 3334244 | P71: =+ROUND(K71*P$5/(1+P$5),0) -> 0 | Q71: =+ROUND(L71*Q$5/(1+Q$5),0) -> 0 | R71: =+ROUND(M71*R$5/(1+R$5),0) -> 0 | S71: =+ROUND(N71*S$5/(1+S$5),0) -> 303113 | T71: =SUM(P71:S71) -> 303113
C74: 区分 | D74: 支出額 | E74: 受益者分担金の事業別金額
C75: 補助事業分(現年) | D75: ='4条補助（浄）'!F20 -> 12760200 | E75: 596000
C76: 起債事業分(現年) | D76: 41100000 | E76: 3484000
C77: 計 | D77: =D75+D76 -> 53860200 | E77: =E75+E76 -> 4080000

Sheet 4条その他
A1: =+"令和"&MID(総括表!A2,3,1)&"年度決算 不課税収入区分表(その他国庫補金）" -> 令和５年度決算 不課税収入区分表(その他国庫補金）
I3: (単位：円)
A4: 区分 | D4: 対象経費 | E4: 按分方法 | F4: 課税支出額 | G4: 不課税収入額 | H4: 特定収入 | I4: 特定収入 以外 | J4: 特定収入内訳（上段：課税支出額、下段特定収入の按分） | P4: 特定収入に係る課税仕入れ等に係る消費税額
F5: 支出額合計 | J5: 0.03 | K5: 0.05 | L5: 0.08 | M5: 0.08 | N5: 0.1 | P5: 0.05 | Q5: 0.08 | R5: 0.08 | S5: 0.1 | T5: 計 | U5: ④４条収入とのチェック
A6: その他国庫補助金 | G6: =SUM(G8,G22,G36,G50) -> 0 | H6: =SUM(H8,H22,H36,H50) -> 0 | I6: =SUM(I8,I22,I36,I50) -> 0 | J6: =SUM(J9,J23,J37,J51) -> 0 | K6: =SUM(K9,K23,K37,K51) -> 0 | L6: =SUM(L9,L23,L37,L51) -> 0 | M6: =SUM(M9,M23,M37,M51) -> 0 | N6: =SUM(N9,N23,N37,N51) -> 0 | P6: =SUM(P9,P23,P37,P51) -> 0 | Q6: =SUM(Q9,Q23,Q37,Q51) -> 0 | R6: =SUM(R9,R23,R37,R51) -> 0 | S6: =SUM(S9,S23,S37,S51) -> 0 | T6: =SUM(T9,T23,T37,T51) -> 0 | U6: =+T6-'[4]4条収入'!$AH$26 -> 0
B8: その他国庫補助金(公共） | G8: =SUM(G10:G21) -> 0 | H8: =SUM(H10:H21) -> 0 | I8: =SUM(I10:I21) -> 0
L9: =+L13+L19 -> 0 | M9: =+M13+M19 -> 0 | N9: =+N13+N19 -> 0 | P9: =+P13+P19 -> 0 | Q9: =+Q13+Q19 -> 0 | R9: =+R13+R19 -> 0 | S9: =+S13+S19 -> 0 | T9: =+T13+T19 -> 0 | U9: =+T9-'[4]4条収入'!$AH$27 -> 0
B10: 公共下水道事業 | C10: 公共土木施設災害 復旧事業費国庫負担金 | D10: 対象事業費×２／３ | E10: 4年度分 公共土木施設災害復旧事業費(補助事業現年分)の課税支出割合 | G10: 0
F12: 0 | H12: =IFERROR(ROUND(SUM(G10:G15)*F12/F13,0),0) -> 0 | I12: =SUM(G10:G15)-H12 -> 0 | L12: 0 | M12: 0 | N12: =F12-SUM(L12:M12) -> 0
F13: 0 | L13: =+H12-SUM(J13:K13,M13:N13) -> 0 | M13: =IFERROR(ROUND(M12/F12*H12,0),0) -> 0 | N13: =IFERROR(ROUND(N12/F12*H12,0),0) -> 0 | P13: =+ROUND(K13*P$5/(1+P$5),0) -> 0 | Q13: =+ROUND(L13*Q$5/(1+Q$5),0) -> 0 | R13: =+ROUND(M13*R$5/(1+R$5),0) -> 0 | S13: =+ROUND(N13*S$5/(1+S$5),0) -> 0 | T13: =SUM(P13:S13) -> 0
C16: 公共土木施設災害 復旧事業費国庫負担金 | D16: 対象事業費×２／３ | E16: 3年度分 公共土木施設災害復旧事業費(補助事業繰越分)の課税支出割合 | G16: 0
F18: 0 | H18: =IFERROR(ROUND(SUM(G16:G21)*F18/F19,0),0) -> 0 | I18: =SUM(G16:G21)-H18 -> 0 | N18: =F18-SUM(L18:M18) -> 0
F19: 0 | L19: =+H18-SUM(J19:K19,M19:N19) -> 0 | M19: =IFERROR(ROUND(M18/F18*H18,0),0) -> 0 | N19: =IFERROR(ROUND(N18/F18*H18,0),0) -> 0 | P19: =+ROUND(K19*P$5/(1+P$5),0) -> 0 | Q19: =+ROUND(L19*Q$5/(1+Q$5),0) -> 0 | R19: =+ROUND(M19*R$5/(1+R$5),0) -> 0 | S19: =+ROUND(N19*S$5/(1+S$5),0) -> 0 | T19: =SUM(P19:S19) -> 0
B22: その他国庫補助金(特環） | G22: =SUM(G24:G35) -> 0 | H22: =SUM(H24:H35) -> 0 | I22: =SUM(I24:I35) -> 0
L23: =+L27+L33 -> 0 | M23: =+M27+M33 -> 0 | N23: =+N27+N33 -> 0 | P23: =+P27+P33 -> 0 | Q23: =+Q27+Q33 -> 0 | R23: =+R27+R33 -> 0 | S23: =+S27+S33 -> 0 | T23: =+T27+T33 -> 0 | U23: =+T23-'[4]4条収入'!$AH$28 -> 0
B24: 特定環境保全公共下水道 | C24: 公共土木施設災害 復旧事業費国庫負担金 | D24: 対象事業費×２／３ | E24: =+E10 -> 4年度分 公共土木施設災害復旧事業費(補助事業現年分)の課税支出割合 | G24: 0
F26: 0 | H26: =IFERROR(ROUND(SUM(G24:G29)*F26/F27,0),0) -> 0 | I26: =SUM(G24:G29)-H26 -> 0 | N26: =F26-SUM(L26:M26) -> 0
F27: 0 | L27: =+H26-SUM(J27:K27,M27:N27) -> 0 | M27: =IFERROR(ROUND(M26/F26*H26,0),0) -> 0 | N27: =IFERROR(ROUND(N26/F26*H26,0),0) -> 0 | P27: =+ROUND(K27*P$5/(1+P$5),0) -> 0 | Q27: =+ROUND(L27*Q$5/(1+Q$5),0) -> 0 | R27: =+ROUND(M27*R$5/(1+R$5),0) -> 0 | S27: =+ROUND(N27*S$5/(1+S$5),0) -> 0 | T27: =SUM(P27:S27) -> 0
C30: 公共土木施設災害 復旧事業費国庫負担金 | D30: 対象事業費×２／３ | E30: =+E16 -> 3年度分 公共土木施設災害復旧事業費(補助事業繰越分)の課税支出割合 | G30: 0
F32: 0 | H32: =IFERROR(ROUND(SUM(G30:G35)*F32/F33,0),0) -> 0 | I32: =SUM(G30:G35)-H32 -> 0 | N32: =F32-SUM(L32:M32) -> 0
F33: 0 | L33: =+H32-SUM(J33:K33,M33:N33) -> 0 | M33: =IFERROR(ROUND(M32/F32*H32,0),0) -> 0 | N33: =IFERROR(ROUND(N32/F32*H32,0),0) -> 0 | P33: =+ROUND(K33*P$5/(1+P$5),0) -> 0 | Q33: =+ROUND(L33*Q$5/(1+Q$5),0) -> 0 | R33: =+ROUND(M33*R$5/(1+R$5),0) -> 0 | S33: =+ROUND(N33*S$5/(1+S$5),0) -> 0 | T33: =SUM(P33:S33) -> 0
B36: その他国庫補助金(農集） | G36: =SUM(G38:G49) -> 0 | H36: =SUM(H38:H49) -> 0 | I36: =SUM(I38:I49) -> 0
L37: =+L41+L47 -> 0 | M37: =+M41+M47 -> 0 | N37: =+N41+N47 -> 0 | P37: =+P41+P47 -> 0 | Q37: =+Q41+Q47 -> 0 | R37: =+R41+R47 -> 0 | S37: =+S41+S47 -> 0 | T37: =+T41+T47 -> 0 | U37: =+T37-'[4]4条収入'!$AH$29 -> 0
B38: 農業集落排水事業 | C38: 災害関連農村生活環境 施設復旧事業国庫補助金 | D38: 対象事業費×１／２ | E38: 4年度分 災害関連農村生活環境施設復旧事業(補助事業現年分)の課税支出割合 | G38: 0
F40: 0 | H40: =IFERROR(ROUND(SUM(G38:G43)*F40/F41,0),0) -> 0 | I40: =SUM(G38:G43)-H40 -> 0 | L40: 0 | M40: 0 | N40: =F40-SUM(L40:M40) -> 0
F41: 0 | L41: =+H40-SUM(J41:K41,M41:N41) -> 0 | M41: =IFERROR(ROUND(M40/F40*H40,0),0) -> 0 | N41: =IFERROR(ROUND(N40/F40*H40,0),0) -> 0 | P41: =+ROUND(K41*P$5/(1+P$5),0) -> 0 | Q41: =+ROUND(L41*Q$5/(1+Q$5),0) -> 0 | R41: =+ROUND(M41*R$5/(1+R$5),0) -> 0 | S41: =+ROUND(N41*S$5/(1+S$5),0) -> 0 | T41: =SUM(P41:S41) -> 0
C44: 災害関連農村生活環境 施設復旧事業国庫補助金 | D44: 対象事業費×１／２ | E44: 3年度分 災害関連農村生活環境施設復旧事業(補助事業繰越分)の課税支出割合 | G44: 0
F46: 0 | H46: =IFERROR(ROUND(SUM(G44:G49)*F46/F47,0),0) -> 0 | I46: =SUM(G44:G49)-H46 -> 0 | N46: =F46-SUM(L46:M46) -> 0
F47: 0 | L47: =+H46-SUM(J47:K47,M47:N47) -> 0 | M47: =IFERROR(ROUND(M46/F46*H46,0),0) -> 0 | N47: =IFERROR(ROUND(N46/F46*H46,0),0) -> 0 | P47: =+ROUND(K47*P$5/(1+P$5),0) -> 0 | Q47: =+ROUND(L47*Q$5/(1+Q$5),0) -> 0 | R47: =+ROUND(M47*R$5/(1+R$5),0) -> 0 | S47: =+ROUND(N47*S$5/(1+S$5),0) -> 0 | T47: =SUM(P47:S47) -> 0
B50: その他国庫補助金(浄化槽） | G50: =SUM(G52:G63) -> 0 | H50: =SUM(H52:H63) -> 0 | I50: =SUM(I52:I63) -> 0
L51: =+L55+L61 -> 0 | M51: =+M55+M61 -> 0 | N51: =+N55+N61 -> 0 | P51: =+P55+P61 -> 0 | Q51: =+Q55+Q61 -> 0 | R51: =+R55+R61 -> 0 | S51: =+S55+S61 -> 0 | T51: =+T55+T61 -> 0 | U51: =+T51-'[4]4条収入'!$AH$30 -> 0
B52: 市営浄化槽事業
H54: =IFERROR(ROUND(SUM(G52:G57)*F54/F55,0),0) -> 0 | I54: =SUM(G52:G57)-H54 -> 0 | N54: =F54-SUM(L54:M54) -> 0
L55: =+H54-SUM(J55:K55,M55:N55) -> 0 | M55: =IFERROR(ROUND(M54/F54*H54,0),0) -> 0 | N55: =IFERROR(ROUND(N54/F54*H54,0),0) -> 0 | P55: =+ROUND(K55*P$5/(1+P$5),0) -> 0 | Q55: =+ROUND(L55*Q$5/(1+Q$5),0) -> 0 | R55: =+ROUND(M55*R$5/(1+R$5),0) -> 0 | S55: =+ROUND(N55*S$5/(1+S$5),0) -> 0 | T55: =SUM(P55:S55) -> 0
H60: =IFERROR(ROUND(SUM(G58:G63)*F60/F61,0),0) -> 0 | I60: =SUM(G58:G63)-H60 -> 0 | N60: =F60-SUM(L60:M60) -> 0
L61: =+H60-SUM(J61:K61,M61:N61) -> 0 | M61: =IFERROR(ROUND(M60/F60*H60,0),0) -> 0 | N61: =IFERROR(ROUND(N60/F60*H60,0),0) -> 0 | P61: =+ROUND(K61*P$5/(1+P$5),0) -> 0 | Q61: =+ROUND(L61*Q$5/(1+Q$5),0) -> 0 | R61: =+ROUND(M61*R$5/(1+R$5),0) -> 0 | S61: =+ROUND(N61*S$5/(1+S$5),0) -> 0 | T61: =SUM(P61:S61) -> 0
F64: 4条収入シート その他国庫補助金 | G64: =+'[4]4条収入'!$E$26 -> 0
F65: チェック | G65: =+G6-G64 -> 0

Sheet 4条工事負担金
A1: =+"令和"&MID(総括表!A2,3,1)&"年度決算 不課税収入区分表(工事負担金)" -> 令和５年度決算 不課税収入区分表(工事負担金)
I3: (単位：円)
A4: 区分 | D4: 対象経費 | E4: 按分方法 | F4: 課税支出額 | G4: 不課税収入額 | H4: 特定収入 | I4: 特定収入 以外 | J4: 特定収入内訳（上段：課税支出額、下段特定収入の按分） | P4: 特定収入に係る課税仕入れ等に係る消費税額
F5: 支出額合計 | J5: 0.03 | K5: 0.05 | L5: 0.08 | M5: 0.08 | N5: 0.1 | P5: 0.05 | Q5: 0.08 | R5: 0.08 | S5: 0.1 | T5: 計 | U5: ④４条収入とのチェック
A6: 工事負担金 | G6: =SUM(G8:G17) -> 514968182 | H6: =SUM(H8:H17) -> 351364357 | I6: =SUM(I8:I17) -> 163603825 | J6: =+SUM(J9,J11,J13,J15,J17) -> 0 | K6: =+SUM(K9,K11,K13,K15,K17) -> 131982078 | L6: =+SUM(L9,L11,L13,L15,L17) -> 1246566 | M6: =+SUM(M9,M11,M13,M15,M17) -> 0 | N6: =+SUM(N9,N11,N13,N15,N17) -> 218135713 | P6: =+SUM(P9,P11,P13,P15,P17) -> 6284861 | Q6: =+SUM(Q9,Q11,Q13,Q15,Q17) -> 92338 | R6: =+SUM(R9,R11,R13,R15,R17) -> 0 | S6: =+SUM(S9,S11,S13,S15,S17) -> 19830519 | T6: =+SUM(T9,T11,T13,T15,T17) -> 26207718 | U6: =+T6-'[4]4条収入'!$AH$50 -> 1
B8: 公共下水道 単市事業充当分 （西風新都を含む） | E8: 5年度分単市事業 の課税支出割合 (現年＋繰越) | F8: =F33 -> 465460043 | G8: ='工事負担金（所属別内訳）'!G76 -> 0 | H8: =IFERROR(ROUND(F8/F9*G8,0),0) -> 0 | I8: =G8-H8 -> 0 | L8: 0 | M8: 0 | N8: =F8-SUM(L8:M8) -> 465460043
F9: =F34 -> 1093621564 | L9: =+H8-SUM(J9:K9,M9:N9) -> 0 | M9: =IFERROR(ROUND(M8/F8*H8,0),0) -> 0 | N9: =IFERROR(ROUND(N8/F8*H8,0),0) -> 0 | P9: =+ROUND(K9*P$5/(1+P$5),0) -> 0 | Q9: =+ROUND(L9*Q$5/(1+Q$5),0) -> 0 | R9: =+ROUND(M9*R$5/(1+R$5),0) -> 0 | S9: =+ROUND(N9*S$5/(1+S$5),0) -> 0 | T9: =SUM(P9:S9) -> 0 | U9: =+SUM(T9:T13)+T17 -> 19830519 | V9: ←工事費充当分の計
B10: 排水設備整備事業 充当分 | E10: 5年度分排水設備事業 の課税支出割合 | F10: =+'[5]4条支出'!$K$8 -> 518619849 | G10: ='工事負担金（所属別内訳）'!G80 -> 279746516 | H10: =IFERROR(ROUND(F10/F11*G10,0),0) -> 218135713 | I10: =G10-H10 -> 61610803 | L10: =+[5]排水!F$41+[5]排水!G$41+[5]排水!H$41 -> 0 | M10: =+[5]排水!I$41 -> 0 | N10: =+[5]排水!J$41 -> 518619849
F11: =+'[5]4条支出'!$E$8 -> 665100151 | L11: =+H10-SUM(J11:K11,M11:N11) -> 0 | M11: =IFERROR(ROUND(M10/F10*H10,0),0) -> 0 | N11: =IFERROR(ROUND(N10/F10*H10,0),0) -> 218135713 | P11: =+ROUND(K11*P$5/(1+P$5),0) -> 0 | Q11: =+ROUND(L11*Q$5/(1+Q$5),0) -> 0 | R11: =+ROUND(M11*R$5/(1+R$5),0) -> 0 | S11: =+ROUND(N11*S$5/(1+S$5),0) -> 19830519 | T11: =SUM(P11:S11) -> 19830519
B12: 諸設備新設改良事業 充当分 | E12: 5年度分諸設備新設改良 事業の課税支出割合 | F12: =+'[5]4条支出'!$K$11 -> 59178010 | G12: ='工事負担金（所属別内訳）'!G83 -> 0 | H12: =IFERROR(ROUND(F12/F13*G12,0),0) -> 0 | I12: =G12-H12 -> 0 | L12: =+[5]諸公!F$41+[5]諸公!G$41+[5]諸公!H$41 -> 0 | M12: =+[5]諸公!I$41 -> 0 | N12: =+[5]諸公!J$41 -> 59178010
F13: =+'[5]4条支出'!$E$11 -> 59178010 | L13: =+H12-SUM(J13:K13,M13:N13) -> 0 | M13: =IFERROR(ROUND(M12/F12*H12,0),0) -> 0 | N13: =IFERROR(ROUND(N12/F12*H12,0),0) -> 0 | P13: =+ROUND(K13*P$5/(1+P$5),0) -> 0 | Q13: =+ROUND(L13*Q$5/(1+Q$5),0) -> 0 | R13: =+ROUND(M13*R$5/(1+R$5),0) -> 0 | S13: =+ROUND(N13*S$5/(1+S$5),0) -> 0 | T13: =SUM(P13:S13) -> 0
B14: 元金償還金充当分 | E14: 起債年度の課税支出割合 (別紙算出表) | G14: ='工事負担金（元金償還分)'!G14 -> 235221666 | H14: ='工事負担金（元金償還分)'!H14 -> 133228644 | I14: ='工事負担金（元金償還分)'!I14 -> 101993022
K15: =+SUM(西風:廿日市!K51:K52) -> 131982078 | L15: =+SUM(西風:廿日市!K53) -> 1246566 | N15: =+SUM(西風:廿日市!K54) -> 0 | P15: =+ROUND(K15*P$5/(1+P$5),0) -> 6284861 | Q15: =+ROUND(L15*Q$5/(1+Q$5),0) -> 92338 | R15: =+ROUND(M15*R$5/(1+R$5),0) -> 0 | S15: =+ROUND(N15*S$5/(1+S$5),0) -> 0 | T15: =SUM(P15:S15) -> 6377199
B16: 市街化区域外汚水処理施設 整備事業充当分 | E16: 5年度分市街化区域外汚水処理施設整備事業の課税支出割合 | G16: =SUM(G18:G23) -> 0 | H16: =SUM(H18:H23) -> 0 | I16: =G16-H16 -> 0 | L16: =L18+L20+L22 -> 0 | M16: =M18+M20+M22 -> 0 | N16: =N18+N20+N22 -> 656665462
L17: =L19+L21+L23 -> 0 | M17: =M19+M21+M23 -> 0 | N17: =N19+N21+N23 -> 0 | P17: =P19+P21+P23 -> 0 | Q17: =Q19+Q21+Q23 -> 0 | R17: =R19+R21+R23 -> 0 | S17: =S19+S21+S23 -> 0 | T17: =SUM(P17:S17) -> 0
C18: 特 環 | E18: 5年度分(特環)市街化区域外汚水処理施設整備事業の課税支出割合 | F18: =+'[5]4条支出'!$K$17 -> 440688000 | G18: ='工事負担金（所属別内訳）'!G87 -> 0 | H18: =IFERROR(ROUND(F18/F19*G18,0),0) -> 0 | I18: =G18-H18 -> 0 | L18: =+[5]特整!F$41+[5]特整!G$41+[5]特整!H$41 -> 0 | M18: =+[5]特整!I$41 -> 0 | N18: =+[5]特整!J$41 -> 440688000
F19: =+'[5]4条支出'!$E$17 -> 453738774 | L19: =+H18-SUM(J19:K19,M19:N19) -> 0 | M19: =IFERROR(ROUND(M18/F18*H18,0),0) -> 0 | N19: =IFERROR(ROUND(N18/F18*H18,0),0) -> 0 | P19: =+ROUND(K19*P$5/(1+P$5),0) -> 0 | Q19: =+ROUND(L19*Q$5/(1+Q$5),0) -> 0 | R19: =+ROUND(M19*R$5/(1+R$5),0) -> 0 | S19: =+ROUND(N19*S$5/(1+S$5),0) -> 0 | T19: =SUM(P19:S19) -> 0
C20: 農 集 | E20: 5年度分(農集)市街化区域外汚水処理施設整備事業の課税支出割合 | F20: =+'[5]4条支出'!$K$18 -> 136580009 | G20: ='工事負担金（所属別内訳）'!G91 -> 0 | H20: =IFERROR(ROUND(F20/F21*G20,0),0) -> 0 | I20: =G20-H20 -> 0 | L20: =+[5]農整!F$41+[5]農整!G$41+[5]農整!H$41 -> 0 | M20: =+[5]農整!I$41 -> 0 | N20: =+[5]農整!J$41 -> 136580009
F21: =+'[5]4条支出'!$E$18 -> 146106803 | L21: =+H20-SUM(J21:K21,M21:N21) -> 0 | M21: =IFERROR(ROUND(M20/F20*H20,0),0) -> 0 | N21: =IFERROR(ROUND(N20/F20*H20,0),0) -> 0 | P21: =+ROUND(K21*P$5/(1+P$5),0) -> 0 | Q21: =+ROUND(L21*Q$5/(1+Q$5),0) -> 0 | R21: =+ROUND(M21*R$5/(1+R$5),0) -> 0 | S21: =+ROUND(N21*S$5/(1+S$5),0) -> 0 | T21: =SUM(P21:S21) -> 0
C22: 浄化槽 | E22: 5年度分(浄化槽)市街化区域外汚水処理施設整備事業の課税支出割合 | F22: =+'[5]4条支出'!$K$19 -> 79397453 | G22: ='工事負担金（所属別内訳）'!G95 -> 0 | H22: =IFERROR(ROUND(F22/F23*G22,0),0) -> 0 | I22: =G22-H22 -> 0 | L22: =+[5]浄整!F$41+[5]浄整!G$41+[5]浄整!H$41 -> 0 | M22: =+[5]浄整!I$41 -> 0 | N22: =+[5]浄整!J$41 -> 79397453
F23: =+'[5]4条支出'!$E$19 -> 88399847 | L23: =+H22-SUM(J23:K23,M23:N23) -> 0 | M23: =IFERROR(ROUND(M22/F22*H22,0),0) -> 0 | N23: =IFERROR(ROUND(N22/F22*H22,0),0) -> 0 | P23: =+ROUND(K23*P$5/(1+P$5),0) -> 0 | Q23: =+ROUND(L23*Q$5/(1+Q$5),0) -> 0 | R23: =+ROUND(M23*R$5/(1+R$5),0) -> 0 | S23: =+ROUND(N23*S$5/(1+S$5),0) -> 0 | T23: =SUM(P23:S23) -> 0
F24: 4条収入シート 工事負担金 | G24: =+'[4]4条収入'!$V$50 -> 514968182
F25: チェック | G25: =G6-G24 -> 0
D27: 公共下水道単市事業（現年） | E27: 課税支出額 | F27: 229171001
E28: 支出額合計 | F28: 853309762
D30: 公共下水道単市事業（繰越） | E30: 課税支出額 | F30: 236289042
E31: 支出額合計 | F31: 240311802
D33: 合計 | E33: 課税支出額 | F33: =F27+F30 -> 465460043
E34: 支出額合計 | F34: =F28+F31 -> 1093621564
J43: =+SUM(西風:廿日市!$K$50) -> 0 | K43: =+SUM(西風:廿日市!$K$51) -> 115347434 | L43: =+SUM(西風:廿日市!$K$52) -> 16634644 | N43: =+SUM(西風:廿日市!$K$53) -> 1246566

Sheet 工事負担金（所属別内訳）
R1: （単位：円）
A2: 所属名 | B2: 区分 | C2: 建設負担金充当先 整備事業 | D2: 事項 | E2: 決算額 | F2: 整備費財源分 | M2: 企業債元金償還金財源分 | P2: 合計の消費税区分
F3: 課税 | G3: 不課税 | H3: 計 | I3: 財源充当事業 | M3: 課税 | N3: 不課税 | O3: 計 | P3: 課税 | Q3: 不課税 | R3: 計
I4: 補助 | J4: 起債 | K4: 単市 | L4: 計
A6: 管路課 | B6: 建設負担金 | C6: 公共下水道整備事業 流域下水道整備事業 | H6: =SUM(F6:G6) -> 0 | L6: =SUM(I6:K6) -> 0 | O6: =SUM(M6:N6) -> 0 | P6: =F6+M6 -> 0 | Q6: =G6+N6 -> 0 | R6: =SUM(P6:Q6) -> 0 | S6: =H6-L6 -> 0 | T6: =E6-R6 -> 0
H7: =SUM(F7:G7) -> 0 | L7: =SUM(I7:K7) -> 0 | O7: =SUM(M7:N7) -> 0 | P7: =F7+M7 -> 0 | Q7: =G7+N7 -> 0 | R7: =SUM(P7:Q7) -> 0 | S7: =H7-L7 -> 0 | T7: =E7-R7 -> 0
H8: =SUM(F8:G8) -> 0 | L8: =SUM(I8:K8) -> 0 | O8: =SUM(M8:N8) -> 0 | P8: =F8+M8 -> 0 | Q8: =G8+N8 -> 0 | R8: =SUM(P8:Q8) -> 0 | S8: =H8-L8 -> 0 | T8: =E8-R8 -> 0
H9: =SUM(F9:G9) -> 0 | L9: =SUM(I9:K9) -> 0 | O9: =SUM(M9:N9) -> 0 | P9: =F9+M9 -> 0 | Q9: =G9+N9 -> 0 | R9: =SUM(P9:Q9) -> 0 | S9: =H9-L9 -> 0 | T9: =E9-R9 -> 0
D10: 府中町大須地区に係る流域下水道負担金 | E10: 951438 | F10: 951438 | H10: =SUM(F10:G10) -> 951438 | J10: 951438 | L10: =SUM(I10:K10) -> 951438 | O10: =SUM(M10:N10) -> 0 | P10: =F10+M10 -> 951438 | Q10: =G10+N10 -> 0 | R10: =SUM(P10:Q10) -> 951438 | S10: =H10-L10 -> 0 | T10: =E10-R10 -> 0
D11: 青崎土地区画整理事業（青崎2-5） | E11: 10295497 | F11: 10295497 | H11: =SUM(F11:G11) -> 10295497 | K11: 10295497 | L11: =SUM(I11:K11) -> 10295497 | O11: =SUM(M11:N11) -> 0 | P11: =F11+M11 -> 10295497 | Q11: =G11+N11 -> 0 | R11: =SUM(P11:Q11) -> 10295497 | S11: =H11-L11 -> 0 | T11: =E11-R11 -> 0
D12: 府中町大須地区に係る流域下水道負担金_R2年度分 | H12: =SUM(F12:G12) -> 0 | L12: =SUM(I12:K12) -> 0 | O12: =SUM(M12:N12) -> 0 | P12: =F12+M12 -> 0 | Q12: =G12+N12 -> 0 | R12: =SUM(P12:Q12) -> 0 | S12: =H12-L12 -> 0 | T12: =E12-R12 -> 0
D13: 公共下水道整備事業に係る負担金 | H13: =SUM(F13:G13) -> 0 | L13: =SUM(I13:K13) -> 0 | O13: =SUM(M13:N13) -> 0 | P13: =F13+M13 -> 0 | Q13: =G13+N13 -> 0 | R13: =SUM(P13:Q13) -> 0 | S13: =H13-L13 -> 0 | T13: =E13-R13 -> 0
D14: 特別支援学校校舎増築に伴う下水道工事に係る負担金 | H14: =SUM(F14:G14) -> 0 | L14: =SUM(I14:K14) -> 0 | O14: =SUM(M14:N14) -> 0 | P14: =F14+M14 -> 0 | Q14: =G14+N14 -> 0 | R14: =SUM(P14:Q14) -> 0 | S14: =H14-L14 -> 0 | T14: =E14-R14 -> 0
H15: =SUM(F15:G15) -> 0 | L15: =SUM(I15:K15) -> 0 | O15: =SUM(M15:N15) -> 0 | P15: =F15+M15 -> 0 | Q15: =G15+N15 -> 0 | R15: =SUM(P15:Q15) -> 0 | S15: =H15-L15 -> 0 | T15: =E15-R15 -> 0
D16: 計 | E16: =SUM(E6:E15) -> 11246935 | F16: =SUM(F6:F15) -> 11246935 | G16: =SUM(G6:G15) -> 0 | H16: =SUM(H6:H15) -> 11246935 | I16: =SUM(I6:I15) -> 0 | J16: =SUM(J6:J15) -> 951438 | K16: =SUM(K6:K15) -> 10295497 | L16: =SUM(L6:L15) -> 11246935 | ... R16: =SUM(R6:R15) -> 11246935 | S16: =H16-L16 -> 0 | T16: =E16-R16 -> 0
B17: 元金償還負担金 | D17: 府中町大須地区（共通分） | E17: =+'工事負担金（元金償還分)'!G12 -> 3167277 | H17: =SUM(F17:G17) -> 0 | L17: =SUM(I17:K17) -> 0 | N17: =E17 -> 3167277 | O17: =SUM(M17:N17) -> 3167277 | P17: =F17+M17 -> 0 | Q17: =G17+N17 -> 3167277 | R17: =SUM(P17:Q17) -> 3167277 | S17: =H17-L17 -> 0 | T17: =E17-R17 -> 0
D18: 府中町大須地区 | E18: =+'工事負担金（元金償還分)'!G11 -> 3205201 | H18: =SUM(F18:G18) -> 0 | L18: =SUM(I18:K18) -> 0 | N18: =E18 -> 3205201 | O18: =SUM(M18:N18) -> 3205201 | P18: =F18+M18 -> 0 | Q18: =G18+N18 -> 3205201 | R18: =SUM(P18:Q18) -> 3205201 | S18: =H18-L18 -> 0 | T18: =E18-R18 -> 0
D19: 海田町海田地区 | E19: =+'工事負担金（元金償還分)'!G7 -> 31164274 | H19: =SUM(F19:G19) -> 0 | L19: =SUM(I19:K19) -> 0 | N19: =E19 -> 31164274 | O19: =SUM(M19:N19) -> 31164274 | P19: =F19+M19 -> 0 | Q19: =G19+N19 -> 31164274 | R19: =SUM(P19:Q19) -> 31164274 | S19: =H19-L19 -> 0 | T19: =E19-R19 -> 0
D20: 廿日市市 | E20: =+'工事負担金（元金償還分)'!G13 -> 27021331 | H20: =SUM(F20:G20) -> 0 | L20: =SUM(I20:K20) -> 0 | N20: =E20 -> 27021331 | O20: =SUM(M20:N20) -> 27021331 | P20: =F20+M20 -> 0 | Q20: =G20+N20 -> 27021331 | R20: =SUM(P20:Q20) -> 27021331 | S20: =H20-L20 -> 0 | T20: =E20-R20 -> 0
D21: 府中町青崎地区 | E21: =+'工事負担金（元金償還分)'!G10 -> 7611447 | H21: =SUM(F21:G21) -> 0 | L21: =SUM(I21:K21) -> 0 | N21: =E21 -> 7611447 | O21: =SUM(M21:N21) -> 7611447 | P21: =F21+M21 -> 0 | Q21: =G21+N21 -> 7611447 | R21: =SUM(P21:Q21) -> 7611447 | S21: =H21-L21 -> 0 | T21: =E21-R21 -> 0
D22: 計 | E22: =SUM(E17:E21) -> 72169530 | F22: =SUM(F17:F21) -> 0 | G22: =SUM(G17:G21) -> 0 | H22: =SUM(H17:H21) -> 0 | I22: =SUM(I17:I21) -> 0 | J22: =SUM(J17:J21) -> 0 | K22: =SUM(K17:K21) -> 0 | L22: =SUM(L17:L21) -> 0 | ... R22: =SUM(R17:R21) -> 72169530 | S22: =H22-L22 -> 0 | T22: =E22-R22 -> 0
B23: 課合計 | E23: =E16+E22 -> 83416465 | F23: =F16+F22 -> 11246935 | G23: =G16+G22 -> 0 | H23: =H16+H22 -> 11246935 | I23: =I16+I22 -> 0 | J23: =J16+J22 -> 951438 | K23: =K16+K22 -> 10295497 | L23: =L16+L22 -> 11246935 | ... R23: =R16+R22 -> 83416465 | S23: =H23-L23 -> 0 | T23: =E23-R23 -> 0
A24: 経営企画課 | B24: 建設負担金 | C24: 公共下水道整備事業 | H24: =SUM(F24:G24) -> 0 | L24: =SUM(I24:K24) -> 0 | O24: =SUM(M24:N24) -> 0 | P24: =F24+M24 -> 0 | Q24: =G24+N24 -> 0 | R24: =SUM(P24:Q24) -> 0 | S24: =H24-L24 -> 0 | T24: =E24-R24 -> 0
H25: =SUM(F25:G25) -> 0 | L25: =SUM(I25:K25) -> 0 | O25: =SUM(M25:N25) -> 0 | P25: =F25+M25 -> 0 | Q25: =G25+N25 -> 0 | R25: =SUM(P25:Q25) -> 0 | S25: =H25-L25 -> 0 | T25: =E25-R25 -> 0
D26: 計 | E26: =SUM(E24:E25) -> 0 | F26: =SUM(F24:F25) -> 0 | G26: =SUM(G24:G25) -> 0 | H26: =SUM(H24:H25) -> 0 | I26: =SUM(I24:I25) -> 0 | J26: =SUM(J24:J25) -> 0 | K26: =SUM(K24:K25) -> 0 | L26: =SUM(L24:L25) -> 0 | ... R26: =SUM(R24:R25) -> 0 | S26: =H26-L26 -> 0 | T26: =E26-R26 -> 0
B27: 元金償還負担金 | D27: 西風新都開発者負担金 | E27: ='工事負担金（元金償還分)'!G6 -> 163052136 | H27: =SUM(F27:G27) -> 0 | L27: =SUM(I27:K27) -> 0 | N27: =E27 -> 163052136 | O27: =SUM(M27:N27) -> 163052136 | P27: =F27+M27 -> 0 | Q27: =G27+N27 -> 163052136 | R27: =SUM(P27:Q27) -> 163052136 | S27: =H27-L27 -> 0 | T27: =E27-R27 -> 0
D28: 計 | E28: =E27 -> 163052136 | F28: =F27 -> 0 | G28: =G27 -> 0 | H28: =H27 -> 0 | I28: =I27 -> 0 | J28: =J27 -> 0 | K28: =K27 -> 0 | L28: =L27 -> 0 | ... R28: =R27 -> 163052136 | S28: =H28-L28 -> 0 | T28: =E28-R28 -> 0
B29: 課合計 | E29: =E26+E28 -> 163052136 | F29: =F26+F28 -> 0 | G29: =G26+G28 -> 0 | H29: =H26+H28 -> 0 | I29: =I26+I28 -> 0 | J29: =J26+J28 -> 0 | K29: =K26+K28 -> 0 | L29: =L26+L28 -> 0 | ... R29: =R26+R28 -> 163052136 | S29: =H29-L29 -> 0 | T29: =E29-R29 -> 0
A30: 管理課 | B30: 建設負担金 | C30: 諸設備新設改良事業 | D30: 府中町 | E30: 4003456 | F30: 4003456 | H30: =SUM(F30:G30) -> 4003456 | K30: 4003456 | L30: =SUM(I30:K30) -> 4003456 | O30: =SUM(M30:N30) -> 0 | P30: =F30+M30 -> 4003456 | Q30: =G30+N30 -> 0 | R30: =SUM(P30:Q30) -> 4003456 | S30: =H30-L30 -> 0 | T30: =E30-R30 -> 0
D31: 府中町（大須地区） | E31: 0 | F31: 0 | H31: =SUM(F31:G31) -> 0 | K31: 0 | L31: =SUM(I31:K31) -> 0 | O31: =SUM(M31:N31) -> 0 | P31: =F31+M31 -> 0 | Q31: =G31+N31 -> 0 | R31: =SUM(P31:Q31) -> 0 | S31: =H31-L31 -> 0 | T31: =E31-R31 -> 0
D32: 廿日市市 | E32: 3161 | F32: 3161 | H32: =SUM(F32:G32) -> 3161 | K32: 3161 | L32: =SUM(I32:K32) -> 3161 | O32: =SUM(M32:N32) -> 0 | P32: =F32+M32 -> 3161 | Q32: =G32+N32 -> 0 | R32: =SUM(P32:Q32) -> 3161 | S32: =H32-L32 -> 0 | T32: =E32-R32 -> 0
D33: 海田町 | E33: 947 | F33: 947 | H33: =SUM(F33:G33) -> 947 | K33: 947 | L33: =SUM(I33:K33) -> 947 | O33: =SUM(M33:N33) -> 0 | P33: =F33+M33 -> 947 | Q33: =G33+N33 -> 0 | R33: =SUM(P33:Q33) -> 947 | S33: =H33-L33 -> 0 | T33: =E33-R33 -> 0
H34: =SUM(F34:G34) -> 0 | L34: =SUM(I34:K34) -> 0 | O34: =SUM(M34:N34) -> 0 | P34: =F34+M34 -> 0 | Q34: =G34+N34 -> 0 | R34: =SUM(P34:Q34) -> 0 | S34: =H34-L34 -> 0 | T34: =E34-R34 -> 0
H35: =SUM(F35:G35) -> 0 | L35: =SUM(I35:K35) -> 0 | O35: =SUM(M35:N35) -> 0 | P35: =F35+M35 -> 0 | Q35: =G35+N35 -> 0 | R35: =SUM(P35:Q35) -> 0 | S35: =H35-L35 -> 0 | T35: =E35-R35 -> 0
H36: =SUM(F36:G36) -> 0 | L36: =SUM(I36:K36) -> 0 | O36: =SUM(M36:N36) -> 0 | P36: =F36+M36 -> 0 | Q36: =G36+N36 -> 0 | R36: =SUM(P36:Q36) -> 0 | S36: =H36-L36 -> 0 | T36: =E36-R36 -> 0
H37: =SUM(F37:G37) -> 0 | L37: =SUM(I37:K37) -> 0 | O37: =SUM(M37:N37) -> 0 | P37: =F37+M37 -> 0 | Q37: =G37+N37 -> 0 | R37: =SUM(P37:Q37) -> 0 | S37: =H37-L37 -> 0 | T37: =E37-R37 -> 0
B38: 課合計 | E38: =SUM(E30:E37) -> 4007564 | F38: =SUM(F30:F37) -> 4007564 | G38: =SUM(G30:G37) -> 0 | H38: =SUM(H30:H37) -> 4007564 | I38: =SUM(I30:I37) -> 0 | J38: =SUM(J30:J37) -> 0 | K38: =SUM(K30:K37) -> 4007564 | L38: =SUM(L30:L37) -> 4007564 | ... R38: =SUM(R30:R37) -> 4007564 | S38: =H38-L38 -> 0 | T38: =E38-R38 -> 0
A39: 管路課 | B39: 建設負担金 | C39: 排水設備整備事業 | D39: 温品二葉の里線・府中祇園線整備事業に係る移設等補償費 | E39: 0 | H39: =SUM(F39:G39) -> 0 | L39: =SUM(I39:K39) -> 0 | O39: =SUM(M39:N39) -> 0 | P39: =F39+M39 -> 0 | Q39: =G39+N39 -> 0 | R39: =SUM(P39:Q39) -> 0 | S39: =H39-L39 -> 0 | T39: =E39-R39 -> 0
D40: 西広島駅北口土地区画整理事業の施行における委託業務に係る負担金(2/16) | E40: 8460015 | G40: 8460015 | H40: =SUM(F40:G40) -> 8460015 | K40: 8460015 | L40: =SUM(I40:K40) -> 8460015 | O40: =SUM(M40:N40) -> 0 | P40: =F40+M40 -> 0 | Q40: =G40+N40 -> 8460015 | R40: =SUM(P40:Q40) -> 8460015 | S40: =H40-L40 -> 0 | T40: =E40-R40 -> 0
D41: 西広島駅北口土地区画整理事業の施行における下水道工事に係る負担金(2/16) | E41: 80236477 | G41: 80236477 | H41: =SUM(F41:G41) -> 80236477 | K41: 80236477 | L41: =SUM(I41:K41) -> 80236477 | O41: =SUM(M41:N41) -> 0 | P41: =F41+M41 -> 0 | Q41: =G41+N41 -> 80236477 | R41: =SUM(P41:Q41) -> 80236477 | S41: =H41-L41 -> 0 | T41: =E41-R41 -> 0
D42: 西広島駅北口土地区画整理事業の施行における下水道工事に係る負担金（3/29) | E42: 177635024 | G42: 177635024 | H42: =SUM(F42:G42) -> 177635024 | K42: 177635024 | L42: =SUM(I42:K42) -> 177635024 | O42: =SUM(M42:N42) -> 0 | P42: =F42+M42 -> 0 | Q42: =G42+N42 -> 177635024 | R42: =SUM(P42:Q42) -> 177635024 | S42: =H42-L42 -> 0 | T42: =E42-R42 -> 0
D43: 霞庚午線（９工区）電線共同溝整備事業に係る移設等補償費 | H43: =SUM(F43:G43) -> 0 | L43: =SUM(I43:K43) -> 0 | O43: =SUM(M43:N43) -> 0 | P43: =F43+M43 -> 0 | Q43: =G43+N43 -> 0 | R43: =SUM(P43:Q43) -> 0 | S43: =H43-L43 -> 0 | T43: =E43-R43 -> 0
D44: 公共下水道整備事業に係る負担金 | E44: 63828 | F44: 63828 | H44: =SUM(F44:G44) -> 63828 | K44: 63828 | L44: =SUM(I44:K44) -> 63828 | O44: =SUM(M44:N44) -> 0 | P44: =F44+M44 -> 63828 | Q44: =G44+N44 -> 0 | R44: =SUM(P44:Q44) -> 63828 | S44: =H44-L44 -> 0 | T44: =E44-R44 -> 0
D45: 広島市東部地区連続立体交差事業に係る移設補償費 | E45: 13415000 | G45: 13415000 | H45: =SUM(F45:G45) -> 13415000 | K45: 13415000 | L45: =SUM(I45:K45) -> 13415000 | O45: =SUM(M45:N45) -> 0 | P45: =F45+M45 -> 0 | Q45: =G45+N45 -> 13415000 | R45: =SUM(P45:Q45) -> 13415000 | S45: =H45-L45 -> 0 | T45: =E45-R45 -> 0
H46: =SUM(F46:G46) -> 0 | L46: =SUM(I46:K46) -> 0 | O46: =SUM(M46:N46) -> 0 | P46: =F46+M46 -> 0 | Q46: =G46+N46 -> 0 | R46: =SUM(P46:Q46) -> 0 | S46: =H46-L46 -> 0 | T46: =E46-R46 -> 0
H47: =SUM(F47:G47) -> 0 | L47: =SUM(I47:K47) -> 0 | O47: =SUM(M47:N47) -> 0 | P47: =F47+M47 -> 0 | Q47: =G47+N47 -> 0 | R47: =SUM(P47:Q47) -> 0 | S47: =H47-L47 -> 0 | T47: =E47-R47 -> 0
H48: =SUM(F48:G48) -> 0 | L48: =SUM(I48:K48) -> 0 | O48: =SUM(M48:N48) -> 0 | P48: =F48+M48 -> 0 | Q48: =G48+N48 -> 0 | R48: =SUM(P48:Q48) -> 0 | S48: =H48-L48 -> 0 | T48: =E48-R48 -> 0
H49: =SUM(F49:G49) -> 0 | L49: =SUM(I49:K49) -> 0 | O49: =SUM(M49:N49) -> 0 | P49: =F49+M49 -> 0 | Q49: =G49+N49 -> 0 | R49: =SUM(P49:Q49) -> 0 | S49: =H49-L49 -> 0 | T49: =E49-R49 -> 0
H50: =SUM(F50:G50) -> 0 | L50: =SUM(I50:K50) -> 0 | O50: =SUM(M50:N50) -> 0 | P50: =F50+M50 -> 0 | Q50: =G50+N50 -> 0 | R50: =SUM(P50:Q50) -> 0 | S50: =H50-L50 -> 0 | T50: =E50-R50 -> 0
H51: =SUM(F51:G51) -> 0 | L51: =SUM(I51:K51) -> 0 | O51: =SUM(M51:N51) -> 0 | P51: =F51+M51 -> 0 | Q51: =G51+N51 -> 0 | R51: =SUM(P51:Q51) -> 0 | S51: =H51-L51 -> 0 | T51: =E51-R51 -> 0
H52: =SUM(F52:G52) -> 0 | L52: =SUM(I52:K52) -> 0 | O52: =SUM(M52:N52) -> 0 | P52: =F52+M52 -> 0 | Q52: =G52+N52 -> 0 | R52: =SUM(P52:Q52) -> 0 | S52: =H52-L52 -> 0 | T52: =E52-R52 -> 0
B53: 課合計 | E53: =SUM(E39:E52) -> 279810344 | F53: =SUM(F39:F52) -> 63828 | G53: =SUM(G39:G52) -> 279746516 | H53: =SUM(H39:H52) -> 279810344 | I53: =SUM(I39:I52) -> 0 | J53: =SUM(J39:J52) -> 0 | K53: =SUM(K39:K52) -> 279810344 | L53: =SUM(L39:L52) -> 279810344 | ... R53: =SUM(R39:R52) -> 279810344 | S53: =H53-L53 -> 0 | T53: =E53-R53 -> 0
A54: 区役所 地域整備課 | B54: 建設負担金 | C54: 【特環】 市街化区域外汚水処理施設整備事業 | H54: =SUM(F54:G54) -> 0 | L54: =SUM(I54:K54) -> 0 | O54: =SUM(M54:N54) -> 0 | P54: =F54+M54 -> 0 | Q54: =G54+N54 -> 0 | R54: =SUM(P54:Q54) -> 0 | S54: =H54-L54 -> 0 | T54: =E54-R54 -> 0
H55: =SUM(F55:G55) -> 0 | L55: =SUM(I55:K55) -> 0 | O55: =SUM(M55:N55) -> 0 | P55: =F55+M55 -> 0 | Q55: =G55+N55 -> 0 | R55: =SUM(P55:Q55) -> 0 | S55: =H55-L55 -> 0 | T55: =E55-R55 -> 0
H56: =SUM(F56:G56) -> 0 | L56: =SUM(I56:K56) -> 0 | O56: =SUM(M56:N56) -> 0 | P56: =F56+M56 -> 0 | Q56: =G56+N56 -> 0 | R56: =SUM(P56:Q56) -> 0 | S56: =H56-L56 -> 0 | T56: =E56-R56 -> 0
H57: =SUM(F57:G57) -> 0 | L57: =SUM(I57:K57) -> 0 | O57: =SUM(M57:N57) -> 0 | P57: =F57+M57 -> 0 | Q57: =G57+N57 -> 0 | R57: =SUM(P57:Q57) -> 0 | S57: =H57-L57 -> 0 | T57: =E57-R57 -> 0
H58: =SUM(F58:G58) -> 0 | L58: =SUM(I58:K58) -> 0 | O58: =SUM(M58:N58) -> 0 | P58: =F58+M58 -> 0 | Q58: =G58+N58 -> 0 | R58: =SUM(P58:Q58) -> 0 | S58: =H58-L58 -> 0 | T58: =E58-R58 -> 0
B59: 課合計 | E59: =SUM(E54:E58) -> 0 | F59: =SUM(F54:F58) -> 0 | G59: =SUM(G54:G58) -> 0 | H59: =SUM(H54:H58) -> 0 | I59: =SUM(I54:I58) -> 0 | J59: =SUM(J54:J58) -> 0 | K59: =SUM(K54:K58) -> 0 | L59: =SUM(L54:L58) -> 0 | ... R59: =SUM(R54:R58) -> 0 | S59: =H59-L59 -> 0 | T59: =E59-R59 -> 0
B60: 建設負担金 | C60: 【農集】 市街化区域外汚水処理施設整備事業 | H60: =SUM(F60:G60) -> 0 | L60: =SUM(I60:K60) -> 0 | O60: =SUM(M60:N60) -> 0 | P60: =F60+M60 -> 0 | Q60: =G60+N60 -> 0 | R60: =SUM(P60:Q60) -> 0 | S60: =H60-L60 -> 0 | T60: =E60-R60 -> 0
H61: =SUM(F61:G61) -> 0 | L61: =SUM(I61:K61) -> 0 | O61: =SUM(M61:N61) -> 0 | P61: =F61+M61 -> 0 | Q61: =G61+N61 -> 0 | R61: =SUM(P61:Q61) -> 0 | S61: =H61-L61 -> 0 | T61: =E61-R61 -> 0
H62: =SUM(F62:G62) -> 0 | L62: =SUM(I62:K62) -> 0 | O62: =SUM(M62:N62) -> 0 | P62: =F62+M62 -> 0 | Q62: =G62+N62 -> 0 | R62: =SUM(P62:Q62) -> 0 | S62: =H62-L62 -> 0 | T62: =E62-R62 -> 0
H63: =SUM(F63:G63) -> 0 | L63: =SUM(I63:K63) -> 0 | O63: =SUM(M63:N63) -> 0 | P63: =F63+M63 -> 0 | Q63: =G63+N63 -> 0 | R63: =SUM(P63:Q63) -> 0 | S63: =H63-L63 -> 0 | T63: =E63-R63 -> 0
H64: =SUM(F64:G64) -> 0 | L64: =SUM(I64:K64) -> 0 | O64: =SUM(M64:N64) -> 0 | P64: =F64+M64 -> 0 | Q64: =G64+N64 -> 0 | R64: =SUM(P64:Q64) -> 0 | S64: =H64-L64 -> 0 | T64: =E64-R64 -> 0
B65: 課合計 | E65: =SUM(E60:E64) -> 0 | F65: =SUM(F60:F64) -> 0 | G65: =SUM(G60:G64) -> 0 | H65: =SUM(H60:H64) -> 0 | I65: =SUM(I60:I64) -> 0 | J65: =SUM(J60:J64) -> 0 | K65: =SUM(K60:K64) -> 0 | L65: =SUM(L60:L64) -> 0 | ... R65: =SUM(R60:R64) -> 0 | S65: =H65-L65 -> 0 | T65: =E65-R65 -> 0
B66: 建設負担金 | C66: 【浄化槽】 市街化区域外汚水処理施設整備事業 | H66: =SUM(F66:G66) -> 0 | L66: =SUM(I66:K66) -> 0 | O66: =SUM(M66:N66) -> 0 | P66: =F66+M66 -> 0 | Q66: =G66+N66 -> 0 | R66: =SUM(P66:Q66) -> 0 | S66: =H66-L66 -> 0 | T66: =E66-R66 -> 0
H67: =SUM(F67:G67) -> 0 | L67: =SUM(I67:K67) -> 0 | O67: =SUM(M67:N67) -> 0 | P67: =F67+M67 -> 0 | Q67: =G67+N67 -> 0 | R67: =SUM(P67:Q67) -> 0 | S67: =H67-L67 -> 0 | T67: =E67-R67 -> 0
H68: =SUM(F68:G68) -> 0 | L68: =SUM(I68:K68) -> 0 | O68: =SUM(M68:N68) -> 0 | P68: =F68+M68 -> 0 | Q68: =G68+N68 -> 0 | R68: =SUM(P68:Q68) -> 0 | S68: =H68-L68 -> 0 | T68: =E68-R68 -> 0
H69: =SUM(F69:G69) -> 0 | L69: =SUM(I69:K69) -> 0 | O69: =SUM(M69:N69) -> 0 | P69: =F69+M69 -> 0 | Q69: =G69+N69 -> 0 | R69: =SUM(P69:Q69) -> 0 | S69: =H69-L69 -> 0 | T69: =E69-R69 -> 0
H70: =SUM(F70:G70) -> 0 | L70: =SUM(I70:K70) -> 0 | O70: =SUM(M70:N70) -> 0 | P70: =F70+M70 -> 0 | Q70: =G70+N70 -> 0 | R70: =SUM(P70:Q70) -> 0 | S70: =H70-L70 -> 0 | T70: =E70-R70 -> 0
B71: 課合計 | E71: =SUM(E66:E70) -> 0 | F71: =SUM(F66:F70) -> 0 | G71: =SUM(G66:G70) -> 0 | H71: =SUM(H66:H70) -> 0 | I71: =SUM(I66:I70) -> 0 | J71: =SUM(J66:J70) -> 0 | K71: =SUM(K66:K70) -> 0 | L71: =SUM(L66:L70) -> 0 | ... R71: =SUM(R66:R70) -> 0 | S71: =H71-L71 -> 0 | T71: =E71-R71 -> 0
A72: 総合計 | E72: =E23+E29+E38+E53+E59+E65+E71 -> 530286509 | F72: =F23+F29+F38+F53+F59+F65+F71 -> 15318327 | G72: =G23+G29+G38+G53+G59+G65+G71 -> 279746516 | H72: =H23+H29+H38+H53+H59+H65+H71 -> 295064843 | I72: =I23+I29+I38+I53+I59+I65+I71 -> 0 | J72: =J23+J29+J38+J53+J59+J65+J71 -> 951438 | K72: =K23+K29+K38+K53+K59+K65+K71 -> 294113405 | L72: =L23+L29+L38+L53+L59+L65+L71 -> 295064843 | ... R72: =R23+R29+R38+R53+R59+R65+R71 -> 530286509 | S72: =H72-L72 -> 0 | T72: =E72-R72 -> 0
A73: 内 訳 | B73: 建設負担金 | C73: 公共下水道整備事業 流域下水道整備事業 | D73: 現年分 | E73: =E76-E75-E74 -> 11246935 | F73: =F76-F75-F74 -> 11246935 | G73: =G76-G75-G74 -> 0 | H73: =H76-H75-H74 -> 11246935 | I73: =I76-I75-I74 -> 0 | J73: =J76-J75-J74 -> 951438 | K73: =K76-K75-K74 -> 10295497 | L73: =L76-L75-L74 -> 11246935 | ... R73: =R76-R75-R74 -> 11246935 | S73: =H73-L73 -> 0 | T73: =E73-R73 -> 0
D74: 前年度からの繰越分 | E74: 0 | F74: 0 | G74: =SUM(G10,G12) -> 0 | H74: 0 | I74: =SUM(I10,I12) -> 0 | J74: 0 | K74: =SUM(K10,K12) -> 0 | L74: 0 | M74: =SUM(M10,M12) -> 0 | N74: =SUM(N10,N12) -> 0 | O74: =SUM(O10,O12) -> 0 | P74: 0 | Q74: =SUM(Q10,Q12) -> 0 | R74: 0 | S74: =H74-L74 -> 0 | T74: =E74-R74 -> 0
D75: 前々年度からの繰越分 | S75: =H75-L75 -> 0 | T75: =E75-R75 -> 0
D76: 計 | E76: =E16+E26 -> 11246935 | F76: =F16+F26 -> 11246935 | G76: =G16+G26 -> 0 | H76: =H16+H26 -> 11246935 | I76: =I16+I26 -> 0 | J76: =J16+J26 -> 951438 | K76: =K16+K26 -> 10295497 | L76: =L16+L26 -> 11246935 | ... R76: =R16+R26 -> 11246935 | S76: =H76-L76 -> 0 | T76: =E76-R76 -> 0
C77: 排水設備整備事業 | D77: 現年分 | E77: =E80-E79-E78 -> 279810344 | F77: =F80-F79-F78 -> 63828 | G77: =G80-G79-G78 -> 279746516 | H77: =H80-H79-H78 -> 279810344 | I77: =I80-I79-I78 -> 0 | J77: =J80-J79-J78 -> 0 | K77: =K80-K79-K78 -> 279810344 | L77: =L80-L79-L78 -> 279810344 | ... R77: =R80-R79-R78 -> 279810344 | S77: =H77-L77 -> 0 | T77: =E77-R77 -> 0
D78: 前年度からの繰越分 | S78: =H78-L78 -> 0 | T78: =E78-R78 -> 0
D79: 前々年度からの繰越分 | S79: =H79-L79 -> 0 | T79: =E79-R79 -> 0
D80: 計 | E80: =E53 -> 279810344 | F80: =F53 -> 63828 | G80: =G53 -> 279746516 | H80: =H53 -> 279810344 | I80: =I53 -> 0 | J80: =J53 -> 0 | K80: =K53 -> 279810344 | L80: =L53 -> 279810344 | ... R80: =R53 -> 279810344 | S80: =H80-L80 -> 0 | T80: =E80-R80 -> 0
C81: 諸設備新設改良事業 | D81: 現年分 | E81: =E38 -> 4007564 | F81: =F38 -> 4007564 | G81: =G38 -> 0 | H81: =H38 -> 4007564 | I81: =I38 -> 0 | J81: =J38 -> 0 | K81: =K38 -> 4007564 | L81: =L38 -> 4007564 | ... R81: =R38 -> 4007564 | S81: =H81-L81 -> 0 | T81: =E81-R81 -> 0
S82: =H82-L82 -> 0 | T82: =E82-R82 -> 0
D83: 計 | E83: =E81+E82 -> 4007564 | F83: =F81+F82 -> 4007564 | G83: =G81+G82 -> 0 | H83: =H81+H82 -> 4007564 | I83: =I81+I82 -> 0 | J83: =J81+J82 -> 0 | K83: =K81+K82 -> 4007564 | L83: =L81+L82 -> 4007564 | ... R83: =R81+R82 -> 4007564 | S83: =H83-L83 -> 0 | T83: =E83-R83 -> 0
C84: 市街化区域外汚水処理施設整備事業 【特環】 | D84: 現年分 | E84: =E87-E86-E85 -> 0 | F84: =F87-F86-F85 -> 0 | G84: =G87-G86-G85 -> 0 | H84: =H87-H86-H85 -> 0 | I84: =I87-I86-I85 -> 0 | J84: =J87-J86-J85 -> 0 | K84: =K87-K86-K85 -> 0 | L84: =L87-L86-L85 -> 0 | ... R84: =R87-R86-R85 -> 0 | S84: =H84-L84 -> 0 | T84: =E84-R84 -> 0
D85: 前年度からの繰越分 | S85: =H85-L85 -> 0 | T85: =E85-R85 -> 0
D86: 前々年度からの繰越分 | S86: =H86-L86 -> 0 | T86: =E86-R86 -> 0
D87: 計 | E87: =E59 -> 0 | F87: =F59 -> 0 | G87: =G59 -> 0 | H87: =H59 -> 0 | I87: =I59 -> 0 | J87: =J59 -> 0 | K87: =K59 -> 0 | L87: =L59 -> 0 | ... R87: =R59 -> 0 | S87: =H87-L87 -> 0 | T87: =E87-R87 -> 0
C88: 市街化区域外汚水処理施設整備事業 【農集】 | D88: 現年分 | E88: =E91-E90-E89 -> 0 | F88: =F91-F90-F89 -> 0 | G88: =G91-G90-G89 -> 0 | H88: =H91-H90-H89 -> 0 | I88: =I91-I90-I89 -> 0 | J88: =J91-J90-J89 -> 0 | K88: =K91-K90-K89 -> 0 | L88: =L91-L90-L89 -> 0 | ... R88: =R91-R90-R89 -> 0 | S88: =H88-L88 -> 0 | T88: =E88-R88 -> 0
D89: 前年度からの繰越分 | S89: =H89-L89 -> 0 | T89: =E89-R89 -> 0
D90: 前々年度からの繰越分 | S90: =H90-L90 -> 0 | T90: =E90-R90 -> 0
D91: 計 | E91: =E65 -> 0 | F91: =F65 -> 0 | G91: =G65 -> 0 | H91: =H65 -> 0 | I91: =I65 -> 0 | J91: =J65 -> 0 | K91: =K65 -> 0 | L91: =L65 -> 0 | ... R91: =R65 -> 0 | S91: =H91-L91 -> 0 | T91: =E91-R91 -> 0
C92: 市街化区域外汚水処理施設整備事業 【浄化槽】 | D92: 現年分 | E92: =E95-E94-E93 -> 0 | F92: =F95-F94-F93 -> 0 | G92: =G95-G94-G93 -> 0 | H92: =H95-H94-H93 -> 0 | I92: =I95-I94-I93 -> 0 | J92: =J95-J94-J93 -> 0 | K92: =K95-K94-K93 -> 0 | L92: =L95-L94-L93 -> 0 | ... R92: =R95-R94-R93 -> 0 | S92: =H92-L92 -> 0 | T92: =E92-R92 -> 0
D93: 前年度からの繰越分 | S93: =H93-L93 -> 0 | T93: =E93-R93 -> 0
D94: 前々年度からの繰越分 | S94: =H94-L94 -> 0 | T94: =E94-R94 -> 0
D95: 計 | E95: =E71 -> 0 | F95: =F71 -> 0 | G95: =G71 -> 0 | H95: =H71 -> 0 | I95: =I71 -> 0 | J95: =J71 -> 0 | K95: =K71 -> 0 | L95: =L71 -> 0 | ... R95: =R71 -> 0 | S95: =H95-L95 -> 0 | T95: =E95-R95 -> 0
C96: 合計 | D96: 現年分 | E96: =E73+E77+E81+E84+E88+E92 -> 295064843 | F96: =F73+F77+F81+F84+F88+F92 -> 15318327 | G96: =G73+G77+G81+G84+G88+G92 -> 279746516 | H96: =H73+H77+H81+H84+H88+H92 -> 295064843 | I96: =I73+I77+I81+I84+I88+I92 -> 0 | J96: =J73+J77+J81+J84+J88+J92 -> 951438 | K96: =K73+K77+K81+K84+K88+K92 -> 294113405 | L96: =L73+L77+L81+L84+L88+L92 -> 295064843 | ... R96: =R73+R77+R81+R84+R88+R92 -> 295064843 | S96: =H96-L96 -> 0 | T96: =E96-R96 -> 0
D97: 前年度からの繰越分 | E97: =E74+E78+E85+E89+E93 -> 0 | F97: =F74+F78+F85+F89+F93 -> 0 | G97: =G74+G78+G85+G89+G93 -> 0 | H97: =H74+H78+H85+H89+H93 -> 0 | I97: =I74+I78+I85+I89+I93 -> 0 | J97: =J74+J78+J85+J89+J93 -> 0 | K97: =K74+K78+K85+K89+K93 -> 0 | L97: =L74+L78+L85+L89+L93 -> 0 | ... R97: =R74+R78+R85+R89+R93 -> 0 | S97: =H97-L97 -> 0 | T97: =E97-R97 -> 0
D98: 前々年度からの繰越分 | E98: =E75+E79+E86+E90+E94 -> 0 | F98: =F75+F79+F86+F90+F94 -> 0 | G98: =G75+G79+G86+G90+G94 -> 0 | H98: =H75+H79+H86+H90+H94 -> 0 | I98: =I75+I79+I86+I90+I94 -> 0 | J98: =J75+J79+J86+J90+J94 -> 0 | K98: =K75+K79+K86+K90+K94 -> 0 | L98: =L75+L79+L86+L90+L94 -> 0 | ... R98: =R75+R79+R86+R90+R94 -> 0 | S98: =H98-L98 -> 0 | T98: =E98-R98 -> 0
D99: 計 | E99: =SUM(E96:E98) -> 295064843 | F99: =SUM(F96:F98) -> 15318327 | G99: =SUM(G96:G98) -> 279746516 | H99: =SUM(H96:H98) -> 295064843 | I99: =SUM(I96:I98) -> 0 | J99: =SUM(J96:J98) -> 951438 | K99: =SUM(K96:K98) -> 294113405 | L99: =SUM(L96:L98) -> 295064843 | ... R99: =SUM(R96:R98) -> 295064843 | S99: =H99-L99 -> 0 | T99: =E99-R99 -> 0
B100: 元金償還負担金 | D100: 現年分 | E100: =E22+E28 -> 235221666 | F100: =F22+F28 -> 0 | G100: =G22+G28 -> 0 | H100: =H22+H28 -> 0 | I100: =I22+I28 -> 0 | J100: =J22+J28 -> 0 | K100: =K22+K28 -> 0 | L100: =L22+L28 -> 0 | ... R100: =R22+R28 -> 235221666 | S100: =H100-L100 -> 0 | T100: =E100-R100 -> 0
D101: 計 | E101: =E100 -> 235221666 | F101: =F100 -> 0 | G101: =G100 -> 0 | H101: =H100 -> 0 | I101: =I100 -> 0 | J101: =J100 -> 0 | K101: =K100 -> 0 | L101: =L100 -> 0 | ... R101: =R100 -> 235221666 | S101: =H101-L101 -> 0 | T101: =E101-R101 -> 0
...

Sheet 工事負担金（元金償還分)
A1: =+"令和"&MID(総括表!A2,3,1)&"年度決算 不課税収入区分表(工事負担金・元金償還金分)" -> 令和５年度決算 不課税収入区分表(工事負担金・元金償還金分)
I3: (単位：円)
A4: 区分 | C4: 起債償還額 | E4: 普通交付税 相当額 | F4: 元金分普通 交付税相当額 | G4: 元金償還 負担額 | H4: 特定収入 | I4: 特定収入 以外
C5: 元金 | D5: 合計
A6: 西風新都開発者 | G6: =+西風!H48 -> 163052136 | H6: =+西風!K48 -> 95865398 | I6: =+西風!L48 -> 67186738
A7: 海田町 | C7: =C8 -> 33756370 | D7: =D8 -> 36370238 | E7: =E8 -> 2819794 | F7: =F8 -> 2592096 | G7: =G8 -> 31164274 | H7: =H8 -> 17621740 | I7: =I8 -> 13542534 | J7: =G7-H7-I7 -> 0
B8: 海田地区 | C8: =+海田!C48 -> 33756370 | D8: =+海田!E48 -> 36370238 | E8: =+海田!F48 -> 2819794 | F8: =+海田!G48 -> 2592096 | G8: =+海田!H48 -> 31164274 | H8: =+海田!K48 -> 17621740 | I8: =+海田!L48 -> 13542534 | J8: =G8-H8-I8 -> 0
A9: 府中町 | C9: =SUM(C10:C12) -> 15405363 | D9: =SUM(D10:D12) -> 17852430 | E9: =SUM(E10:E12) -> 1679862 | F9: =SUM(F10:F12) -> 1421438 | G9: =SUM(G10:G12) -> 13983925 | H9: =SUM(H10:H12) -> 6307988 | I9: =SUM(I10:I12) -> 7675937 | J9: =G9-H9-I9 -> 0
B10: 青崎地区 | C10: =+府中青崎!C48 -> 8328317 | D10: =+府中青崎!E48 -> 9176829 | E10: =+府中青崎!F48 -> 800620 | F10: =+府中青崎!G48 -> 716870 | G10: =+府中青崎!H48 -> 7611447 | H10: =+府中青崎!K48 -> 4073632 | I10: =+府中青崎!L48 -> 3537815 | J10: =G10-H10-I10 -> 0
B11: 大須地区 | C11: =+府中大須!C48 -> 3610379 | D11: =+府中大須!E48 -> 4777679 | E11: =+府中大須!F48 -> 536182 | F11: =+府中大須!G48 -> 405178 | G11: =+府中大須!H48 -> 3205201 | H11: =+府中大須!K48 -> 726081 | I11: =+府中大須!L48 -> 2479120 | J11: =G11-H11-I11 -> 0
B12: 大須地区(共通分） | C12: =+'大須（共通）'!C48 -> 3466667 | D12: =+'大須（共通）'!E48 -> 3897922 | E12: =+'大須（共通）'!F48 -> 343060 | F12: =+'大須（共通）'!G48 -> 299390 | G12: =+'大須（共通）'!H48 -> 3167277 | H12: =+'大須（共通）'!K48 -> 1508275 | I12: =+'大須（共通）'!L48 -> 1659002 | J12: =G12-H12-I12 -> 0
A13: 廿日市市 | C13: =+廿日市!C48 -> 30103640 | D13: =+廿日市!E48 -> 33354894 | E13: =+廿日市!F48 -> 3428259 | F13: =+廿日市!G48 -> 3082309 | G13: =+廿日市!H48 -> 27021331 | H13: =+廿日市!K48 -> 13433518 | I13: =+廿日市!L48 -> 13587813 | J13: =G13-H13-I13 -> 0
A14: 合計 | C14: =C7+C9+C13 -> 79265373 | D14: =D7+D9+D13 -> 87577562 | E14: =E7+E9+E13 -> 7927915 | F14: =F7+F9+F13 -> 7095843 | G14: =G7+G9+G13+G6 -> 235221666 | H14: =H7+H9+H13+H6 -> 133228644 | I14: =I7+I9+I13+I6 -> 101993022 | J14: =G14-H14-I14 -> 0

Sheet 西風
A2: =+"令和"&MID(総括表!A2,3,1)&"年度決算 西風新都開発者" -> 令和５年度決算 西風新都開発者
O3: イ | P3: 起債借入に伴う償還金
A4: 区分 | B4: 年度 | H4: 元金償還 負担額 | I4: 課税支出額 | J4: 支出額合計 | K4: 特定収入 | L4: 特定収入 以外 | N4: 税 率 | P4: 区 分 | R4: 元金
A6: 合 計 | B6: 昭和57年度 | K6: =IFERROR(ROUND(H6*I6/J6,0),0) -> 0 | L6: =H6-K6 -> 0 | N6: =+海田!N6 -> 0 | P6: ２年度
B7: 昭和58年度 | K7: =IFERROR(ROUND(H7*I7/J7,0),0) -> 0 | L7: =H7-K7 -> 0 | N7: =+海田!N7 -> 0 | O7: ① | P7: （運用部） | Q7: 年 間
B8: 昭和59年度 | K8: =IFERROR(ROUND(H8*I8/J8,0),0) -> 0 | L8: =H8-K8 -> 0 | N8: =+海田!N8 -> 0 | P8: 借入分 | Q8: 計
B9: 昭和60年度 | K9: =IFERROR(ROUND(H9*I9/J9,0),0) -> 0 | L9: =H9-K9 -> 0 | N9: =+海田!N9 -> 0 | P9: ３年度
B10: 昭和61年度 | K10: =IFERROR(ROUND(H10*I10/J10,0),0) -> 0 | L10: =H10-K10 -> 0 | N10: =+海田!N10 -> 0 | O10: ② | P10: （運用部） | Q10: 年 間
B11: 昭和62年度 | K11: =IFERROR(ROUND(H11*I11/J11,0),0) -> 0 | L11: =H11-K11 -> 0 | N11: =+海田!N11 -> 0 | P11: 借入分 | Q11: 計
B12: 昭和63年度 | K12: =IFERROR(ROUND(H12*I12/J12,0),0) -> 0 | L12: =H12-K12 -> 0 | N12: =+海田!N12 -> 0 | P12: ４年度 | R12: 91516054
B13: 平成元年度 | I13: =+VLOOKUP($B13,年度別調書!$A$4:$M$37,10,0) -> 30622955900 | J13: =+VLOOKUP($B13,年度別調書!$A$4:$M$37,13,0) -> 62903610340 | K13: =IFERROR(ROUND(H13*I13/J13,0),0) -> 0 | L13: =H13-K13 -> 0 | N13: =+海田!N13 -> 3 | O13: ③ | P13: （運用部） | Q13: 年 間
B14: 平成2年度 | H14: =+R6 -> 0 | I14: =+VLOOKUP($B14,年度別調書!$A$4:$M$37,10,0) -> 36785805618 | J14: =+VLOOKUP($B14,年度別調書!$A$4:$M$37,13,0) -> 65207626364 | K14: =IFERROR(ROUND(H14*I14/J14,0),0) -> 0 | L14: =H14-K14 -> 0 | N14: =+海田!N14 -> 3 | P14: 借入分 | Q14: 計
B15: 平成3年度 | H15: =+R9 -> 0 | I15: =+VLOOKUP($B15,年度別調書!$A$4:$M$37,10,0) -> 42048127236 | J15: =+VLOOKUP($B15,年度別調書!$A$4:$M$37,13,0) -> 72538415314 | K15: =IFERROR(ROUND(H15*I15/J15,0),0) -> 0 | L15: =H15-K15 -> 0 | N15: =+海田!N15 -> 3 | P15: ５年度 | R15: 49292071
B16: 平成4年度 | H16: =+R12 -> 91516054 | I16: =+VLOOKUP($B16,年度別調書!$A$4:$M$37,10,0) -> 49320557603 | J16: =+VLOOKUP($B16,年度別調書!$A$4:$M$37,13,0) -> 82028053042 | K16: =IFERROR(ROUND(H16*I16/J16,0),0) -> 55025356 | L16: =H16-K16 -> 36490698 | N16: =+海田!N16 -> 3 | O16: ④ | P16: （運用部） | Q16: 年 間
B17: 平成5年度 | H17: =+R15 -> 49292071 | I17: =+VLOOKUP($B17,年度別調書!$A$4:$M$37,10,0) -> 54853236126 | J17: =+VLOOKUP($B17,年度別調書!$A$4:$M$37,13,0) -> 94393962571 | K17: =IFERROR(ROUND(H17*I17/J17,0),0) -> 28644095 | L17: =H17-K17 -> 20647976 | N17: =+海田!N17 -> 3 | P17: 借入分 | Q17: 計
B18: 平成6年度 | H18: =+R18 -> 10038016 | I18: =+VLOOKUP($B18,年度別調書!$A$4:$M$37,10,0) -> 52459905451 | J18: =+VLOOKUP($B18,年度別調書!$A$4:$M$37,13,0) -> 92179213936 | K18: =IFERROR(ROUND(H18*I18/J18,0),0) -> 5712713 | L18: =H18-K18 -> 4325303 | N18: =+海田!N18 -> 3 | P18: ６年度 | R18: 10038016
B19: 平成7年度 | H19: =+R21 -> 3356773 | I19: =+VLOOKUP($B19,年度別調書!$A$4:$M$37,10,0) -> 58579778590 | J19: =+VLOOKUP($B19,年度別調書!$A$4:$M$37,13,0) -> 98916143476 | K19: =IFERROR(ROUND(H19*I19/J19,0),0) -> 1987937 | L19: =H19-K19 -> 1368836 | N19: =+海田!N19 -> 3 | O19: ⑤ | P19: （運用部） | Q19: 年 間
B20: 平成8年度 | H20: =+R24 -> 2068736 | I20: =+VLOOKUP($B20,年度別調書!$A$4:$M$37,10,0) -> 59855732510 | J20: =+VLOOKUP($B20,年度別調書!$A$4:$M$37,13,0) -> 105086070753 | K20: =IFERROR(ROUND(H20*I20/J20,0),0) -> 1178327 | L20: =H20-K20 -> 890409 | N20: =+海田!N20 -> 3 | P20: 借入分 | Q20: 計
B21: 平成9年度 | H21: =+R27 -> 420875 | I21: =+VLOOKUP($B21,年度別調書!$A$4:$M$37,10,0) -> 65491097789 | J21: =+VLOOKUP($B21,年度別調書!$A$4:$M$37,13,0) -> 112544371375 | K21: =IFERROR(ROUND(H21*I21/J21,0),0) -> 244913 | L21: =H21-K21 -> 175962 | N21: =+海田!N21 -> 5 | P21: ７年度 | R21: 3356773
B22: 平成10年度 | H22: =+R30 -> 1634139 | I22: =+VLOOKUP($B22,年度別調書!$A$4:$M$37,10,0) -> 66701247191 | J22: =+VLOOKUP($B22,年度別調書!$A$4:$M$37,13,0) -> 118194473653 | K22: =IFERROR(ROUND(H22*I22/J22,0),0) -> 922201 | L22: =H22-K22 -> 711938 | N22: =+海田!N22 -> 5 | O22: ⑥ | P22: （運用部） | Q22: 年 間
B23: 平成11年度 | H23: =+R33 -> 1507746 | I23: =+VLOOKUP($B23,年度別調書!$A$4:$M$37,10,0) -> 58274420372 | J23: =+VLOOKUP($B23,年度別調書!$A$4:$M$37,13,0) -> 110790062218 | K23: =IFERROR(ROUND(H23*I23/J23,0),0) -> 793059 | L23: =H23-K23 -> 714687 | N23: =+海田!N23 -> 5 | P23: 借入分 | Q23: 計
B24: 平成12年度 | H24: =+R36+R39 -> 1433385 | I24: =+VLOOKUP($B24,年度別調書!$A$4:$M$37,10,0) -> 48353931386 | J24: =+VLOOKUP($B24,年度別調書!$A$4:$M$37,13,0) -> 104173607652 | K24: =IFERROR(ROUND(H24*I24/J24,0),0) -> 665330 | L24: =H24-K24 -> 768055 | N24: =+海田!N24 -> 5 | P24: ８年度 | R24: 2068736
B25: 平成13年度 | H25: =+R42+R45 -> 1056567 | I25: =+VLOOKUP($B25,年度別調書!$A$4:$M$37,10,0) -> 42742028940 | J25: =+VLOOKUP($B25,年度別調書!$A$4:$M$37,13,0) -> 101075943440 | K25: =IFERROR(ROUND(H25*I25/J25,0),0) -> 446791 | L25: =H25-K25 -> 609776 | N25: =+海田!N25 -> 5 | O25: ⑦ | P25: （運用部） | Q25: 年 間
B26: 平成14年度 | H26: =+R48 -> 480134 | I26: =+VLOOKUP($B26,年度別調書!$A$4:$M$37,10,0) -> 38694694218 | J26: =+VLOOKUP($B26,年度別調書!$A$4:$M$37,13,0) -> 98151426478 | K26: =IFERROR(ROUND(H26*I26/J26,0),0) -> 189285 | L26: =H26-K26 -> 290849 | N26: =+海田!N26 -> 5 | P26: 借入分 | Q26: 計
B27: 平成15年度 | I27: =+VLOOKUP($B27,年度別調書!$A$4:$M$37,10,0) -> 37621895854 | J27: =+VLOOKUP($B27,年度別調書!$A$4:$M$37,13,0) -> 100825076572 | K27: =IFERROR(ROUND(H27*I27/J27,0),0) -> 0 | L27: =H27-K27 -> 0 | N27: =+海田!N27 -> 5 | P27: ９年度 | R27: 420875
B28: 平成16年度 | I28: =+VLOOKUP($B28,年度別調書!$A$4:$M$37,10,0) -> 29085465357 | J28: =+VLOOKUP($B28,年度別調書!$A$4:$M$37,13,0) -> 101305165124 | K28: =IFERROR(ROUND(H28*I28/J28,0),0) -> 0 | L28: =H28-K28 -> 0 | N28: =+海田!N28 -> 5 | O28: ⑧ | P28: （運用部） | Q28: 年 間
B29: 平成17年度 | I29: =+VLOOKUP($B29,年度別調書!$A$4:$M$37,10,0) -> 25082997134 | J29: =+VLOOKUP($B29,年度別調書!$A$4:$M$37,13,0) -> 96528725584 | K29: =IFERROR(ROUND(H29*I29/J29,0),0) -> 0 | L29: =H29-K29 -> 0 | N29: =+海田!N29 -> 5 | P29: 借入分 | Q29: 計
B30: 平成18年度 | I30: =+VLOOKUP($B30,年度別調書!$A$4:$M$37,10,0) -> 21657707574 | J30: =+VLOOKUP($B30,年度別調書!$A$4:$M$37,13,0) -> 84768578867 | K30: =IFERROR(ROUND(H30*I30/J30,0),0) -> 0 | L30: =H30-K30 -> 0 | N30: =+海田!N30 -> 5 | P30: １０年度 | R30: 1634139
B31: 平成19年度 | I31: =+VLOOKUP($B31,年度別調書!$A$4:$M$37,10,0) -> 25422571996 | J31: =+VLOOKUP($B31,年度別調書!$A$4:$M$37,13,0) -> 105576318079 | K31: =IFERROR(ROUND(H31*I31/J31,0),0) -> 0 | L31: =H31-K31 -> 0 | N31: =+海田!N31 -> 5 | O31: ⑨ | P31: （運用部） | Q31: 年 間
B32: 平成20年度 | H32: =+R51 -> 247640 | I32: =+VLOOKUP($B32,年度別調書!$A$4:$M$37,10,0) -> 24693835462 | J32: =+VLOOKUP($B32,年度別調書!$A$4:$M$37,13,0) -> 110401232854 | K32: =IFERROR(ROUND(H32*I32/J32,0),0) -> 55391 | L32: =H32-K32 -> 192249 | N32: =+海田!N32 -> 5 | P32: 借入分 | Q32: 計
B33: 平成21年度 | I33: =+VLOOKUP($B33,年度別調書!$A$4:$M$37,10,0) -> 22324372880 | J33: =+VLOOKUP($B33,年度別調書!$A$4:$M$37,13,0) -> 88097108350 | K33: =IFERROR(ROUND(H33*I33/J33,0),0) -> 0 | L33: =H33-K33 -> 0 | N33: =+海田!N33 -> 5 | P33: １１年度 | R33: 1507746
B34: 平成22年度 | I34: =+VLOOKUP($B34,年度別調書!$A$4:$M$37,10,0) -> 26326163485 | J34: =+VLOOKUP($B34,年度別調書!$A$4:$M$37,13,0) -> 102723057143 | K34: =IFERROR(ROUND(H34*I34/J34,0),0) -> 0 | L34: =H34-K34 -> 0 | N34: =+海田!N34 -> 5 | O34: ⑩ | P34: （公 庫） | Q34: 年 間
B35: 平成23年度 | I35: =+VLOOKUP($B35,年度別調書!$A$4:$M$37,10,0) -> 26883440277 | J35: =+VLOOKUP($B35,年度別調書!$A$4:$M$37,13,0) -> 99758377045 | K35: =IFERROR(ROUND(H35*I35/J35,0),0) -> 0 | L35: =H35-K35 -> 0 | N35: =+海田!N35 -> 5 | P35: 借入分 | Q35: 計
B36: 平成24年度 | I36: =+VLOOKUP($B36,年度別調書!$A$4:$M$37,10,0) -> 20821234544 | J36: =+VLOOKUP($B36,年度別調書!$A$4:$M$37,13,0) -> 101115908424 | K36: =IFERROR(ROUND(H36*I36/J36,0),0) -> 0 | L36: =H36-K36 -> 0 | N36: =+海田!N36 -> 5 | P36: １２年度 | R36: 760784
B37: 平成25年度 | I37: =+VLOOKUP($B37,年度別調書!$A$4:$M$37,10,0) -> 22169870622 | J37: =+VLOOKUP($B37,年度別調書!$A$4:$M$37,13,0) -> 87897420767 | K37: =IFERROR(ROUND(H37*I37/J37,0),0) -> 0 | L37: =H37-K37 -> 0 | N37: =+海田!N37 -> 5 | O37: ⑪ | P37: （H11→12繰越） | Q37: 年 間
B38: 平成26年度 | I38: =+VLOOKUP($B38,年度別調書!$A$4:$M$37,10,0) -> 20924492616 | J38: =+VLOOKUP($B38,年度別調書!$A$4:$M$37,13,0) -> 99556890040 | K38: =IFERROR(ROUND(H38*I38/J38,0),0) -> 0 | L38: =H38-K38 -> 0 | N38: =+海田!N38 -> 8 | P38: 公庫借入分 | Q38: 計
B39: 平成27年度 | I39: =+VLOOKUP($B39,年度別調書!$A$4:$M$37,10,0) -> 21176145645 | J39: =+VLOOKUP($B39,年度別調書!$A$4:$M$37,13,0) -> 104805589178 | K39: =IFERROR(ROUND(H39*I39/J39,0),0) -> 0 | L39: =H39-K39 -> 0 | N39: =+海田!N39 -> 8 | P39: １２年度 | R39: 672601
B40: 平成28年度 | I40: =+VLOOKUP($B40,年度別調書!$A$4:$M$37,10,0) -> 23487276785 | J40: =+VLOOKUP($B40,年度別調書!$A$4:$M$37,13,0) -> 105396818589 | K40: =IFERROR(ROUND(H40*I40/J40,0),0) -> 0 | L40: =H40-K40 -> 0 | N40: =+海田!N40 -> 8 | O40: ⑫ | P40: （現年分） | Q40: 年 間
B41: 平成29年度 | I41: =+VLOOKUP($B41,年度別調書!$A$4:$M$37,10,0) -> 19481573724 | J41: =+VLOOKUP($B41,年度別調書!$A$4:$M$37,13,0) -> 99607043975 | K41: =IFERROR(ROUND(H41*I41/J41,0),0) -> 0 | L41: =H41-K41 -> 0 | N41: =+海田!N41 -> 8 | P41: 公庫借入分 | Q41: 計
B42: 平成30年度 | I42: =+VLOOKUP($B42,年度別調書!$A$4:$M$37,10,0) -> 19871916207 | J42: =+VLOOKUP($B42,年度別調書!$A$4:$M$37,13,0) -> 98551757388 | K42: =IFERROR(ROUND(H42*I42/J42,0),0) -> 0 | L42: =H42-K42 -> 0 | N42: =+海田!N42 -> 8 | P42: １３年度 | R42: 372194
B43: 令和元年度 | I43: =+VLOOKUP($B43,年度別調書!$A$4:$M$37,10,0) -> 21889958229 | J43: =+VLOOKUP($B43,年度別調書!$A$4:$M$37,13,0) -> 101214576030 | K43: =IFERROR(ROUND(H43*I43/J43,0),0) -> 0 | L43: =H43-K43 -> 0 | N43: =+海田!N43 -> 8 | O43: ⑬ | P43: （H12→13繰越） | Q43: 年 間
I44: =+VLOOKUP($B43,年度別調書!$A$4:$M$37,10,0) -> 21889958229 | J44: =+VLOOKUP($B43,年度別調書!$A$4:$M$37,13,0) -> 101214576030 | K44: =IFERROR(ROUND(H44*I44/J44,0),0) -> 0 | L44: =H44-K44 -> 0 | N44: =+海田!N44 -> 10 | P44: 公庫借入分 | Q44: 計
B45: 令和2年度 | I45: =+VLOOKUP($B45,年度別調書!$A$4:$M$37,10,0) -> 25568719436 | J45: =+VLOOKUP($B45,年度別調書!$A$4:$M$37,13,0) -> 105092548853 | K45: =IFERROR(ROUND(H45*I45/J45,0),0) -> 0 | L45: =H45-K45 -> 0 | N45: =+海田!N45 -> 10 | P45: １3年度 | R45: 684373
B46: 令和3年度 | I46: =+VLOOKUP($B46,年度別調書!$A$4:$M$37,10,0) -> 25732995336 | J46: =+VLOOKUP($B46,年度別調書!$A$4:$M$37,13,0) -> 106246537477 | K46: =IFERROR(ROUND(H46*I46/J46,0),0) -> 0 | L46: =H46-K46 -> 0 | N46: =+海田!N46 -> 10 | O46: ⑭ | P46: （現年分） | Q46: 年 間
B47: 令和4年度 | I47: =+VLOOKUP($B47,年度別調書!$A$4:$M$37,10,0) -> 22974897869 | J47: =+VLOOKUP($B47,年度別調書!$A$4:$M$37,13,0) -> 102361733085 | K47: =IFERROR(ROUND(H47*I47/J47,0),0) -> 0 | L47: =H47-K47 -> 0 | N47: =+海田!N47 -> 10 | P47: 公庫借入分 | Q47: 計
B48: 計 | H48: =SUM(H6:H47) -> 163052136 | K48: =SUM(K6:K47) -> 95865398 | L48: =SUM(L6:L47) -> 67186738 | N48: =+海田!N48 -> 0 | P48: １４年度 | R48: 480134
O49: ⑮ | P49: （現年分） | Q49: 年 間
J50: 税率 | K50: 税率別特定収入 | P50: 公庫借入分 | Q50: 計
J51: 3 | K51: =+SUMIFS($K$4:$K$48,$N$4:$N$48,$J51) -> 92548428 | P51: ２０年度 | R51: 247640
J52: 5 | K52: =+SUMIFS($K$4:$K$48,$N$4:$N$48,$J52) -> 3316970 | O52: ⑯ | P52: （H19→20繰越） | Q52: 年 間
J53: 8 | K53: =+SUMIFS($K$4:$K$48,$N$4:$N$48,$J53) -> 0 | P53: 公庫借入分 | Q53: 計
J54: 10 | K54: =+SUMIFS($K$4:$K$48,$N$4:$N$48,$J54) -> 0
J55: 計 | K55: =SUM(K51:K54) -> 95865398 | P55: 計 | Q55: 年 間 | R55: =SUM(R6:R53) -> 163052136
J56: チェック | K56: =+K48-K55 -> 0 | Q56: 計

Sheet 海田
A2: =+"令和"&MID(総括表!A2,3,1)&"年度決算 海田町海田地区" -> 令和５年度決算 海田町海田地区 | O2: =+A2 -> 令和５年度決算 海田町海田地区
A4: 区分 | B4: 年度 | C4: 起債償還額 | F4: 普通交付税 相当額 | G4: 元金分普通 交付税相当額 | H4: 元金償還 負担額 | I4: 課税支出額 | J4: 支出額合計 | K4: 特定収入 | L4: 特定収入 以外 | M4: 端数 調整 | N4: 税 率 | O4: 区分 | P4: 年度 | Q4: 起債償還額 | T4: 普通交付税 相当額 | U4: 元金分普通 交付税相当額 | W4: 区分 | X4: 年度 | Y4: 起債償還額 | AB4: 普通交付税 相当額 | AC4: 元金分普通 交付税相当額
C5: 元金 | D5: 利息 | E5: 合計 | Q5: 元金 | R5: 利息 | S5: 合計 | Y5: 元金 | Z5: 利息 | AA5: 合計
A6: 合 計 | B6: 昭和57年度 | C6: =+Q6+Y6 -> 0 | D6: =+R6+Z6 -> 0 | E6: =+S6+AA6 -> 0 | F6: =+T6+AB6 -> 0 | G6: =ROUND(C6/C$48*G$48,0) -> 0 | H6: =C6-G6 -> 0 | K6: 0 | L6: =H6-K6 -> 0 | M6: =ROUND(C6/C$48*G$48,3)-ROUND(C6/C$48*G$48,0) -> 0 | N6: 0 | O6: ９ 月 分 | P6: =+B6 -> 昭和57年度 | Q6: 0 | R6: 0 | S6: 0 | T6: 0 | W6: ３ 月 分 | X6: =+B6 -> 昭和57年度 | Y6: 0 | Z6: 0 | AA6: 0 | AB6: 0
B7: 昭和58年度 | C7: =+Q7+Y7 -> 0 | D7: =+R7+Z7 -> 0 | E7: =+S7+AA7 -> 0 | F7: =+T7+AB7 -> 0 | G7: =ROUND(C7/C$48*G$48,0) -> 0 | H7: =C7-G7 -> 0 | K7: 0 | L7: =H7-K7 -> 0 | M7: =ROUND(C7/C$48*G$48,3)-ROUND(C7/C$48*G$48,0) -> 0 | N7: 0 | P7: =+B7 -> 昭和58年度 | Q7: 0 | R7: 0 | S7: 0 | T7: 0 | X7: =+B7 -> 昭和58年度 | Y7: 0 | Z7: 0 | AA7: 0 | AB7: 0
B8: 昭和59年度 | C8: =+Q8+Y8 -> 0 | D8: =+R8+Z8 -> 0 | E8: =+S8+AA8 -> 0 | F8: =+T8+AB8 -> 0 | G8: =ROUND(C8/C$48*G$48,0) -> 0 | H8: =C8-G8 -> 0 | K8: 0 | L8: =H8-K8 -> 0 | M8: =ROUND(C8/C$48*G$48,3)-ROUND(C8/C$48*G$48,0) -> 0 | N8: 0 | P8: =+B8 -> 昭和59年度 | Q8: 0 | R8: 0 | S8: 0 | T8: 0 | X8: =+B8 -> 昭和59年度 | Y8: 0 | Z8: 0 | AA8: 0 | AB8: 0
B9: 昭和60年度 | C9: =+Q9+Y9 -> 0 | D9: =+R9+Z9 -> 0 | E9: =+S9+AA9 -> 0 | F9: =+T9+AB9 -> 0 | G9: =ROUND(C9/C$48*G$48,0) -> 0 | H9: =C9-G9 -> 0 | K9: 0 | L9: =H9-K9 -> 0 | M9: =ROUND(C9/C$48*G$48,3)-ROUND(C9/C$48*G$48,0) -> 0 | N9: 0 | P9: =+B9 -> 昭和60年度 | Q9: 0 | R9: 0 | S9: 0 | T9: 0 | X9: =+B9 -> 昭和60年度 | Y9: 0 | Z9: 0 | AA9: 0 | AB9: 0
B10: 昭和61年度 | C10: =+Q10+Y10 -> 0 | D10: =+R10+Z10 -> 0 | E10: =+S10+AA10 -> 0 | F10: =+T10+AB10 -> 0 | G10: =ROUND(C10/C$48*G$48,0) -> 0 | H10: =C10-G10 -> 0 | K10: 0 | L10: =H10-K10 -> 0 | M10: =ROUND(C10/C$48*G$48,3)-ROUND(C10/C$48*G$48,0) -> 0 | N10: 0 | P10: =+B10 -> 昭和61年度 | Q10: 0 | R10: 0 | S10: 0 | T10: 0 | X10: =+B10 -> 昭和61年度 | Y10: 0 | Z10: 0 | AA10: 0 | AB10: 0
B11: 昭和62年度 | C11: =+Q11+Y11 -> 0 | D11: =+R11+Z11 -> 0 | E11: =+S11+AA11 -> 0 | F11: =+T11+AB11 -> 0 | G11: =ROUND(C11/C$48*G$48,0) -> 0 | H11: =C11-G11 -> 0 | K11: 0 | L11: =H11-K11 -> 0 | M11: =ROUND(C11/C$48*G$48,3)-ROUND(C11/C$48*G$48,0) -> 0 | N11: 0 | P11: =+B11 -> 昭和62年度 | Q11: 0 | R11: 0 | S11: 0 | T11: 0 | X11: =+B11 -> 昭和62年度 | Y11: 0 | Z11: 0 | AA11: 0 | AB11: 0
B12: 昭和63年度 | C12: =+Q12+Y12 -> 0 | D12: =+R12+Z12 -> 0 | E12: =+S12+AA12 -> 0 | F12: =+T12+AB12 -> 0 | G12: =ROUND(C12/C$48*G$48,0) -> 0 | H12: =C12-G12 -> 0 | K12: 0 | L12: =H12-K12 -> 0 | M12: =ROUND(C12/C$48*G$48,3)-ROUND(C12/C$48*G$48,0) -> 0 | N12: 0 | P12: =+B12 -> 昭和63年度 | Q12: 0 | R12: 0 | S12: 0 | T12: 0 | X12: =+B12 -> 昭和63年度 | Y12: 0 | Z12: 0 | AA12: 0 | AB12: 0
B13: 平成元年度 | C13: =+Q13+Y13 -> 0 | D13: =+R13+Z13 -> 0 | E13: =+S13+AA13 -> 0 | F13: =+T13+AB13 -> 0 | G13: =ROUND(C13/C$48*G$48,0) -> 0 | H13: =C13-G13 -> 0 | I13: =+VLOOKUP($B13,年度別調書!$A$4:$M$37,10,0) -> 30622955900 | J13: =+VLOOKUP($B13,年度別調書!$A$4:$M$37,13,0) -> 62903610340 | K13: =IFERROR(ROUND(H13*I13/J13,0),0) -> 0 | L13: =H13-K13 -> 0 | M13: =ROUND(C13/C$48*G$48,3)-ROUND(C13/C$48*G$48,0) -> 0 | N13: 3 | P13: =+B13 -> 平成元年度 | Q13: 0 | R13: 0 | S13: 0 | T13: 0 | X13: =+B13 -> 平成元年度 | Y13: 0 | Z13: 0 | AA13: 0 | AB13: 0
B14: 平成2年度 | C14: =+Q14+Y14 -> 0 | D14: =+R14+Z14 -> 0 | E14: =+S14+AA14 -> 0 | F14: =+T14+AB14 -> 0 | G14: =ROUND(C14/C$48*G$48,0) -> 0 | H14: =C14-G14 -> 0 | I14: =+VLOOKUP($B14,年度別調書!$A$4:$M$37,10,0) -> 36785805618 | J14: =+VLOOKUP($B14,年度別調書!$A$4:$M$37,13,0) -> 65207626364 | K14: =IFERROR(ROUND(H14*I14/J14,0),0) -> 0 | L14: =H14-K14 -> 0 | M14: =ROUND(C14/C$48*G$48,3)-ROUND(C14/C$48*G$48,0) -> 0 | N14: 3 | P14: =+B14 -> 平成2年度 | Q14: 0 | R14: 0 | S14: 0 | T14: 0 | X14: =+B14 -> 平成2年度 | Y14: 0 | Z14: 0 | AA14: 0 | AB14: 0
B15: 平成3年度 | C15: =+Q15+Y15 -> 0 | D15: =+R15+Z15 -> 0 | E15: =+S15+AA15 -> 0 | F15: =+T15+AB15 -> 0 | G15: =ROUND(C15/C$48*G$48,0) -> 0 | H15: =C15-G15 -> 0 | I15: =+VLOOKUP($B15,年度別調書!$A$4:$M$37,10,0) -> 42048127236 | J15: =+VLOOKUP($B15,年度別調書!$A$4:$M$37,13,0) -> 72538415314 | K15: =IFERROR(ROUND(H15*I15/J15,0),0) -> 0 | L15: =H15-K15 -> 0 | M15: =ROUND(C15/C$48*G$48,3)-ROUND(C15/C$48*G$48,0) -> 0 | N15: 3 | P15: =+B15 -> 平成3年度 | Q15: 0 | R15: 0 | S15: 0 | T15: 0 | X15: =+B15 -> 平成3年度 | Y15: 0 | Z15: 0 | AA15: 0 | AB15: 0
B16: 平成4年度 | C16: =+Q16+Y16 -> 2013138 | D16: =+R16+Z16 -> 55276 | E16: =+S16+AA16 -> 2068414 | F16: =+T16+AB16 -> 161080 | G16: =ROUND(C16/C$48*G$48,0) -> 154586 | H16: =C16-G16 -> 1858552 | I16: =+VLOOKUP($B16,年度別調書!$A$4:$M$37,10,0) -> 49320557603 | J16: =+VLOOKUP($B16,年度別調書!$A$4:$M$37,13,0) -> 82028053042 | K16: =IFERROR(ROUND(H16*I16/J16,0),0) -> 1117481 | L16: =H16-K16 -> 741071 | M16: =ROUND(C16/C$48*G$48,3)-ROUND(C16/C$48*G$48,0) -> -0.452 | N16: 3 | P16: =+B16 -> 平成4年度 | Q16: 997467 | R16: 36740 | S16: 1034207 | T16: 80540 | X16: =+B16 -> 平成4年度 | Y16: 1015671 | Z16: 18536 | AA16: 1034207 | AB16: 80540
B17: 平成5年度 | C17: =+Q17+Y17 -> 0 | D17: =+R17+Z17 -> 0 | E17: =+S17+AA17 -> 0 | F17: =+T17+AB17 -> 0 | G17: =ROUND(C17/C$48*G$48,0) -> 0 | H17: =C17-G17 -> 0 | I17: =+VLOOKUP($B17,年度別調書!$A$4:$M$37,10,0) -> 54853236126 | J17: =+VLOOKUP($B17,年度別調書!$A$4:$M$37,13,0) -> 94393962571 | K17: =IFERROR(ROUND(H17*I17/J17,0),0) -> 0 | L17: =H17-K17 -> 0 | M17: =ROUND(C17/C$48*G$48,3)-ROUND(C17/C$48*G$48,0) -> 0 | N17: 3 | P17: =+B17 -> 平成5年度 | Q17: 0 | R17: 0 | S17: 0 | T17: 0 | X17: =+B17 -> 平成5年度 | Y17: 0 | Z17: 0 | AA17: 0 | AB17: 0
B18: 平成6年度 | C18: =+Q18+Y18 -> 2836357 | D18: =+R18+Z18 -> 223639 | E18: =+S18+AA18 -> 3059996 | F18: =+T18+AB18 -> 87342 | G18: =ROUND(C18/C$48*G$48,0) -> 217799 | H18: =C18-G18 -> 2618558 | I18: =+VLOOKUP($B18,年度別調書!$A$4:$M$37,10,0) -> 52459905451 | J18: =+VLOOKUP($B18,年度別調書!$A$4:$M$37,13,0) -> 92179213936 | K18: =IFERROR(ROUND(H18*I18/J18,0),0) -> 1490242 | L18: =H18-K18 -> 1128316 | M18: =ROUND(C18/C$48*G$48,3)-ROUND(C18/C$48*G$48,0) -> 0.178 | N18: 3 | P18: =+B18 -> 平成6年度 | Q18: 1404324 | R18: 125674 | S18: 1529998 | T18: 43671 | X18: =+B18 -> 平成6年度 | Y18: 1432033 | Z18: 97965 | AA18: 1529998 | AB18: 43671
B19: 平成7年度 | C19: =+Q19+Y19 -> 15303179 | D19: =+R19+Z19 -> 807691 | E19: =+S19+AA19 -> 16110870 | F19: =+T19+AB19 -> 848330 | G19: =ROUND(C19/C$48*G$48,0) -> 1175106 | H19: =C19-G19 -> 14128073 | I19: =+VLOOKUP($B19,年度別調書!$A$4:$M$37,10,0) -> 58579778590 | J19: =+VLOOKUP($B19,年度別調書!$A$4:$M$37,13,0) -> 98916143476 | K19: =IFERROR(ROUND(H19*I19/J19,0),0) -> 8366879 | L19: =H19-K19 -> 5761194 | M19: =ROUND(C19/C$48*G$48,3)-ROUND(C19/C$48*G$48,0) -> -0.114 | N19: 3 | P19: =+B19 -> 平成7年度 | Q19: 7590228 | R19: 465207 | S19: 8055435 | T19: 424165 | X19: =+B19 -> 平成7年度 | Y19: 7712951 | Z19: 342484 | AA19: 8055435 | AB19: 424165
B20: 平成8年度 | C20: =+Q20+Y20 -> 8628429 | D20: =+R20+Z20 -> 679917 | E20: =+S20+AA20 -> 9308346 | F20: =+T20+AB20 -> 1075730 | G20: =ROUND(C20/C$48*G$48,0) -> 662563 | H20: =C20-G20 -> 7965866 | I20: =+VLOOKUP($B20,年度別調書!$A$4:$M$37,10,0) -> 59855732510 | J20: =+VLOOKUP($B20,年度別調書!$A$4:$M$37,13,0) -> 105086070753 | K20: =IFERROR(ROUND(H20*I20/J20,0),0) -> 4537259 | L20: =H20-K20 -> 3428607 | M20: =ROUND(C20/C$48*G$48,3)-ROUND(C20/C$48*G$48,0) -> -0.162 | N20: 3 | P20: =+B20 -> 平成8年度 | Q20: 4285331 | R20: 368842 | S20: 4654173 | T20: 537865 | X20: =+B20 -> 平成8年度 | Y20: 4343098 | Z20: 311075 | AA20: 4654173 | AB20: 537865
B21: 平成9年度 | C21: =+Q21+Y21 -> 2641956 | D21: =+R21+Z21 -> 238742 | E21: =+S21+AA21 -> 2880698 | F21: =+T21+AB21 -> 307086 | G21: =ROUND(C21/C$48*G$48,0) -> 202871 | H21: =C21-G21 -> 2439085 | I21: =+VLOOKUP($B21,年度別調書!$A$4:$M$37,10,0) -> 65491097789 | J21: =+VLOOKUP($B21,年度別調書!$A$4:$M$37,13,0) -> 112544371375 | K21: =IFERROR(ROUND(H21*I21/J21,0),0) -> 1419337 | L21: =H21-K21 -> 1019748 | M21: =ROUND(C21/C$48*G$48,3)-ROUND(C21/C$48*G$48,0) -> 0.446 | N21: 5 | P21: =+B21 -> 平成9年度 | Q21: 1314115 | R21: 126234 | S21: 1440349 | T21: 153543 | X21: =+B21 -> 平成9年度 | Y21: 1327841 | Z21: 112508 | AA21: 1440349 | AB21: 153543
B22: 平成10年度 | C22: =+Q22+Y22 -> 2423 | D22: =+R22+Z22 -> 279 | E22: =+S22+AA22 -> 2702 | F22: =+T22+AB22 -> 296 | G22: =ROUND(C22/C$48*G$48,0) -> 186 | H22: =C22-G22 -> 2237 | I22: =+VLOOKUP($B22,年度別調書!$A$4:$M$37,10,0) -> 66701247191 | J22: =+VLOOKUP($B22,年度別調書!$A$4:$M$37,13,0) -> 118194473653 | K22: =IFERROR(ROUND(H22*I22/J22,0),0) -> 1262 | L22: =H22-K22 -> 975 | M22: =ROUND(C22/C$48*G$48,3)-ROUND(C22/C$48*G$48,0) -> 0.058 | N22: 5 | P22: =+B22 -> 平成10年度 | Q22: 1205 | R22: 146 | S22: 1351 | T22: 148 | X22: =+B22 -> 平成10年度 | Y22: 1218 | Z22: 133 | AA22: 1351 | AB22: 148
B23: 平成11年度 | C23: =+Q23+Y23 -> 0 | D23: =+R23+Z23 -> 0 | E23: =+S23+AA23 -> 0 | F23: =+T23+AB23 -> 0 | G23: =ROUND(C23/C$48*G$48,0) -> 0 | H23: =C23-G23 -> 0 | I23: =+VLOOKUP($B23,年度別調書!$A$4:$M$37,10,0) -> 58274420372 | J23: =+VLOOKUP($B23,年度別調書!$A$4:$M$37,13,0) -> 110790062218 | K23: =IFERROR(ROUND(H23*I23/J23,0),0) -> 0 | L23: =H23-K23 -> 0 | M23: =ROUND(C23/C$48*G$48,3)-ROUND(C23/C$48*G$48,0) -> 0 | N23: 5 | P23: =+B23 -> 平成11年度 | Q23: 0 | R23: 0 | S23: 0 | T23: 0 | X23: =+B23 -> 平成11年度 | Y23: 0 | Z23: 0 | AA23: 0 | AB23: 0
B24: 平成12年度 | C24: =+Q24+Y24 -> 0 | D24: =+R24+Z24 -> 0 | E24: =+S24+AA24 -> 0 | F24: =+T24+AB24 -> 0 | G24: =ROUND(C24/C$48*G$48,0) -> 0 | H24: =C24-G24 -> 0 | I24: =+VLOOKUP($B24,年度別調書!$A$4:$M$37,10,0) -> 48353931386 | J24: =+VLOOKUP($B24,年度別調書!$A$4:$M$37,13,0) -> 104173607652 | K24: =IFERROR(ROUND(H24*I24/J24,0),0) -> 0 | L24: =H24-K24 -> 0 | M24: =ROUND(C24/C$48*G$48,3)-ROUND(C24/C$48*G$48,0) -> 0 | N24: 5 | P24: =+B24 -> 平成12年度 | Q24: 0 | R24: 0 | S24: 0 | T24: 0 | X24: =+B24 -> 平成12年度 | Y24: 0 | Z24: 0 | AA24: 0 | AB24: 0
... B42: 平成30年度 | C42: =+Q42+Y42 -> 0 | D42: =+R42+Z42 -> 0 | E42: =+S42+AA42 -> 0 | F42: =+T42+AB42 -> 0 | G42: =ROUND(C42/C$48*G$48,0) -> 0 | H42: =C42-G42 -> 0 | I42: =+VLOOKUP($B42,年度別調書!$A$4:$M$37,10,0) -> 19871916207 | J42: =+VLOOKUP($B42,年度別調書!$A$4:$M$37,13,0) -> 98551757388 | K42: =IFERROR(ROUND(H42*I42/J42,0),0) -> 0 | L42: =H42-K42 -> 0 | M42: =ROUND(C42/C$48*G$48,3)-ROUND(C42/C$48*G$48,0) -> 0 | N42: 8 | P42: =+B42 -> 平成30年度 | Q42: 0 | R42: 0 | S42: 0 | T42: 0 | X42: =+B42 -> 平成30年度 | Y42: 0 | Z42: 0 | AA42: 0 | AB42: 0
B43: 令和元年度 | C43: =+Q43 -> 0 | D43: =+R43 -> 0 | E43: =+S43 -> 0 | F43: =+T43 -> 0 | G43: =ROUND(C43/C$48*G$48,0) -> 0 | H43: =C43-G43 -> 0 | I43: =+VLOOKUP($B43,年度別調書!$A$4:$M$37,10,0) -> 21889958229 | J43: =+VLOOKUP($B43,年度別調書!$A$4:$M$37,13,0) -> 101214576030 | K43: =IFERROR(ROUND(H43*I43/J43,0),0) -> 0 | L43: =H43-K43 -> 0 | M43: =ROUND(C43/C$48*G$48,3)-ROUND(C43/C$48*G$48,0) -> 0 | N43: 8 | P43: =+B43 -> 令和元年度 | Q43: 0 | R43: 0 | S43: 0 | T43: 0 | X43: =+B43 -> 令和元年度 | Y43: 0 | Z43: 0 | AA43: 0 | AB43: 0
C44: =+Y43 -> 0 | D44: =+Z43 -> 0 | E44: =+AA43 -> 0 | F44: =+AB43 -> 0 | G44: =ROUND(C44/C$48*G$48,0) -> 0 | H44: =C44-G44 -> 0 | I44: =+VLOOKUP($B43,年度別調書!$A$4:$M$37,10,0) -> 21889958229 | J44: =+VLOOKUP($B43,年度別調書!$A$4:$M$37,13,0) -> 101214576030 | K44: =IFERROR(ROUND(H44*I44/J44,0),0) -> 0 | L44: =H44-K44 -> 0 | M44: =ROUND(C44/C$48*G$48,3)-ROUND(C44/C$48*G$48,0) -> 0 | N44: 10
B45: 令和2年度 | C45: =+Q45+Y45 -> 0 | D45: =+R45+Z45 -> 1980 | E45: =+S45+AA45 -> 1980 | F45: =+T45+AB45 -> 222 | G45: =ROUND(C45/C$48*G$48,0) -> 0 | H45: =C45-G45 -> 0 | I45: =+VLOOKUP($B45,年度別調書!$A$4:$M$37,10,0) -> 25568719436 | J45: =+VLOOKUP($B45,年度別調書!$A$4:$M$37,13,0) -> 105092548853 | K45: =IFERROR(ROUND(H45*I45/J45,0),0) -> 0 | L45: =H45-K45 -> 0 | M45: =ROUND(C45/C$48*G$48,3)-ROUND(C45/C$48*G$48,0) -> 0 | N45: 10 | P45: =+B45 -> 令和2年度 | Q45: 0 | R45: 990 | S45: 990 | T45: 111 | X45: =+B45 -> 令和2年度 | Y45: 0 | Z45: 990 | AA45: 990 | AB45: 111
B46: 令和3年度 | C46: =+Q46+Y46 -> 0 | D46: =+R46+Z46 -> 0 | E46: =+S46+AA46 -> 0 | F46: =+T46+AB46 -> 0 | G46: =ROUND(C46/C$48*G$48,0) -> 0 | H46: =C46-G46 -> 0 | I46: =+VLOOKUP($B46,年度別調書!$A$4:$M$37,10,0) -> 25732995336 | J46: =+VLOOKUP($B46,年度別調書!$A$4:$M$37,13,0) -> 106246537477 | K46: =IFERROR(ROUND(H46*I46/J46,0),0) -> 0 | L46: =H46-K46 -> 0 | M46: =ROUND(C46/C$48*G$48,3)-ROUND(C46/C$48*G$48,0) -> 0 | N46: 10 | P46: =+B46 -> 令和3年度 | Q46: 0 | R46: 0 | S46: 0 | T46: 0 | X46: =+B46 -> 令和3年度 | Y46: 0 | Z46: 0 | AA46: 0 | AB46: 0
B47: 令和4年度 | C47: =+Q47+Y47 -> 0 | D47: =+R47+Z47 -> 7462 | E47: =+S47+AA47 -> 7462 | F47: =+T47+AB47 -> 838 | G47: =ROUND(C47/C$48*G$48,0) -> 0 | H47: =C47-G47 -> 0 | I47: =+VLOOKUP($B47,年度別調書!$A$4:$M$37,10,0) -> 22974897869 | J47: =+VLOOKUP($B47,年度別調書!$A$4:$M$37,13,0) -> 102361733085 | K47: =IFERROR(ROUND(H47*I47/J47,0),0) -> 0 | L47: =H47-K47 -> 0 | M47: =ROUND(C47/C$48*G$48,3)-ROUND(C47/C$48*G$48,0) -> 0 | N47: 10 | P47: =+B47 -> 令和4年度 | Q47: 0 | R47: 3276 | S47: 3276 | T47: 368 | X47: =+B47 -> 令和4年度 | Y47: 0 | Z47: 4186 | AA47: 4186 | AB47: 470
B48: 計 | C48: =SUM(C6:C47) -> 33756370 | D48: =SUM(D6:D47) -> 2613868 | E48: =SUM(E6:E47) -> 36370238 | F48: =SUM(F6:F47) -> 2819794 | G48: =+U48+AC48 -> 2592096 | H48: =SUM(H6:H47) -> 31164274 | K48: =SUM(K6:K47) -> 17621740 | L48: =SUM(L6:L47) -> 13542534 | P48: 計 | Q48: =SUM(Q6:Q47) -> 16752280 | R48: =SUM(R6:R47) -> 1432385 | S48: =SUM(S6:S47) -> 18184665 | T48: =SUM(T6:T47) -> 1409846 | U48: 1286967 | X48: 計 | Y48: =SUM(Y6:Y47) -> 17004090 | Z48: =SUM(Z6:Z47) -> 1181483 | AA48: =SUM(AA6:AA47) -> 18185573 | AB48: =SUM(AB6:AB47) -> 1409948 | AC48: 1305129
G49: =G48-SUM(G6:G47) -> 0
J50: 税率 | K50: 税率別特定収入 | P50: 海田～廿日市計 | Q50: =SUM(海田:廿日市!Q48) -> 39380544 | R50: =SUM(海田:廿日市!R48) -> 4394901 | S50: =SUM(海田:廿日市!S48) -> 43775445 | T50: =SUM(海田:廿日市!T48) -> 3962461 | U50: =SUM(海田:廿日市!U48) -> 3527598 | Y50: =SUM(海田:廿日市!Y48) -> 39884829 | Z50: =SUM(海田:廿日市!Z48) -> 3917288 | AA50: =SUM(海田:廿日市!AA48) -> 43802117 | AB50: =SUM(海田:廿日市!AB48) -> 3965454 | AC50: =SUM(海田:廿日市!AC48) -> 3568245 | AE50: ←total額が落ちていることを確認する
J51: 3 | K51: =+SUMIFS($K$4:$K$48,$N$4:$N$48,$J51) -> 15511861
J52: 5 | K52: =+SUMIFS($K$4:$K$48,$N$4:$N$48,$J52) -> 2107306
J53: 8 | K53: =+SUMIFS($K$4:$K$48,$N$4:$N$48,$J53) -> 2573
J54: 10 | K54: =+SUMIFS($K$4:$K$48,$N$4:$N$48,$J54) -> 0
J55: 計 | K55: =SUM(K51:K54) -> 17621740
J56: チェック | K56: =+K48-K55 -> 0

Sheet 府中青崎
A2: =+"令和"&MID(総括表!A2,3,1)&"年度決算 府中町青崎地区" -> 令和５年度決算 府中町青崎地区 | O2: =+A2 -> 令和５年度決算 府中町青崎地区
A4: 区分 | B4: 年度 | C4: 起債償還額 | F4: 普通交付税 相当額 | G4: 元金分普通 交付税相当額 | H4: 元金償還 負担額 | I4: 課税支出額 | J4: 支出額合計 | K4: 特定収入 | L4: 特定収入 以外 | M4: 端数 調整 | N4: 税 率 | O4: 区分 | P4: 年度 | Q4: 起債償還額 | T4: 普通交付税 相当額 | U4: 元金分普通 交付税相当額 | W4: 区分 | X4: 年度 | Y4: 起債償還額 | AB4: 普通交付税 相当額 | AC4: 元金分普通 交付税相当額
C5: 元金 | D5: 利息 | E5: 合計 | Q5: 元金 | R5: 利息 | S5: 合計 | Y5: 元金 | Z5: 利息 | AA5: 合計
A6: 合 計 | B6: 昭和57年度 | C6: =+Q6+Y6 -> 0 | D6: =+R6+Z6 -> 0 | E6: =+S6+AA6 -> 0 | F6: =+T6+AB6 -> 0 | G6: =ROUND(C6/C$48*G$48,0) -> 0 | H6: =C6-G6 -> 0 | K6: 0 | L6: =H6-K6 -> 0 | M6: =ROUND(C6/C$48*G$48,3)-ROUND(C6/C$48*G$48,0) -> 0 | N6: =+海田!N6 -> 0 | O6: ９ 月 分 | P6: =+B6 -> 昭和57年度 | W6: ３ 月 分 | X6: =+B6 -> 昭和57年度 | Y6: 0 | Z6: 0 | AA6: 0 | AB6: 0
B7: 昭和58年度 | C7: =+Q7+Y7 -> 0 | D7: =+R7+Z7 -> 0 | E7: =+S7+AA7 -> 0 | F7: =+T7+AB7 -> 0 | G7: =ROUND(C7/C$48*G$48,0) -> 0 | H7: =C7-G7 -> 0 | K7: 0 | L7: =H7-K7 -> 0 | M7: =ROUND(C7/C$48*G$48,3)-ROUND(C7/C$48*G$48,0) -> 0 | N7: =+海田!N7 -> 0 | P7: =+B7 -> 昭和58年度 | Q7: 0 | R7: 0 | S7: 0 | T7: 0 | X7: =+B7 -> 昭和58年度 | Y7: 0 | Z7: 0 | AA7: 0 | AB7: 0
B8: 昭和59年度 | C8: =+Q8+Y8 -> 0 | D8: =+R8+Z8 -> 0 | E8: =+S8+AA8 -> 0 | F8: =+T8+AB8 -> 0 | G8: =ROUND(C8/C$48*G$48,0) -> 0 | H8: =C8-G8 -> 0 | K8: 0 | L8: =H8-K8 -> 0 | M8: =ROUND(C8/C$48*G$48,3)-ROUND(C8/C$48*G$48,0) -> 0 | N8: =+海田!N8 -> 0 | P8: =+B8 -> 昭和59年度 | Q8: 0 | R8: 0 | S8: 0 | T8: 0 | X8: =+B8 -> 昭和59年度 | Y8: 0 | Z8: 0 | AA8: 0 | AB8: 0
B9: 昭和60年度 | C9: =+Q9+Y9 -> 0 | D9: =+R9+Z9 -> 0 | E9: =+S9+AA9 -> 0 | F9: =+T9+AB9 -> 0 | G9: =ROUND(C9/C$48*G$48,0) -> 0 | H9: =C9-G9 -> 0 | K9: 0 | L9: =H9-K9 -> 0 | M9: =ROUND(C9/C$48*G$48,3)-ROUND(C9/C$48*G$48,0) -> 0 | N9: =+海田!N9 -> 0 | P9: =+B9 -> 昭和60年度 | Q9: 0 | R9: 0 | S9: 0 | T9: 0 | X9: =+B9 -> 昭和60年度 | Y9: 0 | Z9: 0 | AA9: 0 | AB9: 0
B10: 昭和61年度 | C10: =+Q10+Y10 -> 0 | D10: =+R10+Z10 -> 0 | E10: =+S10+AA10 -> 0 | F10: =+T10+AB10 -> 0 | G10: =ROUND(C10/C$48*G$48,0) -> 0 | H10: =C10-G10 -> 0 | K10: 0 | L10: =H10-K10 -> 0 | M10: =ROUND(C10/C$48*G$48,3)-ROUND(C10/C$48*G$48,0) -> 0 | N10: =+海田!N10 -> 0 | P10: =+B10 -> 昭和61年度 | Q10: 0 | R10: 0 | S10: 0 | T10: 0 | X10: =+B10 -> 昭和61年度 | Y10: 0 | Z10: 0 | AA10: 0 | AB10: 0
B11: 昭和62年度 | C11: =+Q11+Y11 -> 0 | D11: =+R11+Z11 -> 0 | E11: =+S11+AA11 -> 0 | F11: =+T11+AB11 -> 0 | G11: =ROUND(C11/C$48*G$48,0) -> 0 | H11: =C11-G11 -> 0 | K11: 0 | L11: =H11-K11 -> 0 | M11: =ROUND(C11/C$48*G$48,3)-ROUND(C11/C$48*G$48,0) -> 0 | N11: =+海田!N11 -> 0 | P11: =+B11 -> 昭和62年度 | Q11: 0 | R11: 0 | S11: 0 | T11: 0 | X11: =+B11 -> 昭和62年度 | Y11: 0 | Z11: 0 | AA11: 0 | AB11: 0
B12: 昭和63年度 | C12: =+Q12+Y12 -> 0 | D12: =+R12+Z12 -> 0 | E12: =+S12+AA12 -> 0 | F12: =+T12+AB12 -> 0 | G12: =ROUND(C12/C$48*G$48,0) -> 0 | H12: =C12-G12 -> 0 | K12: 0 | L12: =H12-K12 -> 0 | M12: =ROUND(C12/C$48*G$48,3)-ROUND(C12/C$48*G$48,0) -> 0 | N12: =+海田!N12 -> 0 | P12: =+B12 -> 昭和63年度 | Q12: 0 | R12: 0 | S12: 0 | T12: 0 | X12: =+B12 -> 昭和63年度 | Y12: 0 | Z12: 0 | AA12: 0 | AB12: 0
B13: 平成元年度 | C13: =+Q13+Y13 -> 0 | D13: =+R13+Z13 -> 0 | E13: =+S13+AA13 -> 0 | F13: =+T13+AB13 -> 0 | G13: =ROUND(C13/C$48*G$48,0) -> 0 | H13: =C13-G13 -> 0 | I13: =+VLOOKUP($B13,年度別調書!$A$4:$M$37,10,0) -> 30622955900 | J13: =+VLOOKUP($B13,年度別調書!$A$4:$M$37,13,0) -> 62903610340 | K13: =IFERROR(ROUND(H13*I13/J13,0),0) -> 0 | L13: =H13-K13 -> 0 | M13: =ROUND(C13/C$48*G$48,3)-ROUND(C13/C$48*G$48,0) -> 0 | N13: =+海田!N13 -> 3 | P13: =+B13 -> 平成元年度 | Q13: 0 | R13: 0 | S13: 0 | T13: 0 | X13: =+B13 -> 平成元年度 | Y13: 0 | Z13: 0 | AA13: 0 | AB13: 0
B14: 平成2年度 | C14: =+Q14+Y14 -> 0 | D14: =+R14+Z14 -> 0 | E14: =+S14+AA14 -> 0 | F14: =+T14+AB14 -> 0 | G14: =ROUND(C14/C$48*G$48,0) -> 0 | H14: =C14-G14 -> 0 | I14: =+VLOOKUP($B14,年度別調書!$A$4:$M$37,10,0) -> 36785805618 | J14: =+VLOOKUP($B14,年度別調書!$A$4:$M$37,13,0) -> 65207626364 | K14: =IFERROR(ROUND(H14*I14/J14,0),0) -> 0 | L14: =H14-K14 -> 0 | M14: =ROUND(C14/C$48*G$48,3)-ROUND(C14/C$48*G$48,0) -> 0 | N14: =+海田!N14 -> 3 | P14: =+B14 -> 平成2年度 | Q14: 0 | R14: 0 | S14: 0 | T14: 0 | X14: =+B14 -> 平成2年度 | Y14: 0 | Z14: 0 | AA14: 0 | AB14: 0
B15: 平成3年度 | C15: =+Q15+Y15 -> 0 | D15: =+R15+Z15 -> 0 | E15: =+S15+AA15 -> 0 | F15: =+T15+AB15 -> 0 | G15: =ROUND(C15/C$48*G$48,0) -> 0 | H15: =C15-G15 -> 0 | I15: =+VLOOKUP($B15,年度別調書!$A$4:$M$37,10,0) -> 42048127236 | J15: =+VLOOKUP($B15,年度別調書!$A$4:$M$37,13,0) -> 72538415314 | K15: =IFERROR(ROUND(H15*I15/J15,0),0) -> 0 | L15: =H15-K15 -> 0 | M15: =ROUND(C15/C$48*G$48,3)-ROUND(C15/C$48*G$48,0) -> 0 | N15: =+海田!N15 -> 3 | P15: =+B15 -> 平成3年度 | Q15: 0 | R15: 0 | S15: 0 | T15: 0 | X15: =+B15 -> 平成3年度 | Y15: 0 | Z15: 0 | AA15: 0 | AB15: 0
B16: 平成4年度 | C16: =+Q16+Y16 -> 682449 | D16: =+R16+Z16 -> 18739 | E16: =+S16+AA16 -> 701188 | F16: =+T16+AB16 -> 54606 | G16: =ROUND(C16/C$48*G$48,0) -> 58743 | H16: =C16-G16 -> 623706 | I16: =+VLOOKUP($B16,年度別調書!$A$4:$M$37,10,0) -> 49320557603 | J16: =+VLOOKUP($B16,年度別調書!$A$4:$M$37,13,0) -> 82028053042 | K16: =IFERROR(ROUND(H16*I16/J16,0),0) -> 375012 | L16: =H16-K16 -> 248694 | M16: =ROUND(C16/C$48*G$48,3)-ROUND(C16/C$48*G$48,0) -> -0.374 | N16: =+海田!N16 -> 3 | P16: =+B16 -> 平成4年度 | Q16: 338139 | R16: 12455 | S16: 350594 | T16: 27303 | X16: =+B16 -> 平成4年度 | Y16: 344310 | Z16: 6284 | AA16: 350594 | AB16: 27303
B17: 平成5年度 | C17: =+Q17+Y17 -> 2744661 | D17: =+R17+Z17 -> 143447 | E17: =+S17+AA17 -> 2888108 | F17: =+T17+AB17 -> 135410 | G17: =ROUND(C17/C$48*G$48,0) -> 236250 | H17: =C17-G17 -> 2508411 | I17: =+VLOOKUP($B17,年度別調書!$A$4:$M$37,10,0) -> 54853236126 | J17: =+VLOOKUP($B17,年度別調書!$A$4:$M$37,13,0) -> 94393962571 | K17: =IFERROR(ROUND(H17*I17/J17,0),0) -> 1457662 | L17: =H17-K17 -> 1050749 | M17: =ROUND(C17/C$48*G$48,3)-ROUND(C17/C$48*G$48,0) -> 0.029 | N17: =+海田!N17 -> 3 | P17: =+B17 -> 平成5年度 | Q17: 1357280 | R17: 86774 | S17: 1444054 | T17: 67705 | X17: =+B17 -> 平成5年度 | Y17: 1387381 | Z17: 56673 | AA17: 1444054 | AB17: 67705
B18: 平成6年度 | C18: =+Q18+Y18 -> 0 | D18: =+R18+Z18 -> 0 | E18: =+S18+AA18 -> 0 | F18: =+T18+AB18 -> 0 | G18: =ROUND(C18/C$48*G$48,0) -> 0 | H18: =C18-G18 -> 0 | I18: =+VLOOKUP($B18,年度別調書!$A$4:$M$37,10,0) -> 52459905451 | J18: =+VLOOKUP($B18,年度別調書!$A$4:$M$37,13,0) -> 92179213936 | K18: =IFERROR(ROUND(H18*I18/J18,0),0) -> 0 | L18: =H18-K18 -> 0 | M18: =ROUND(C18/C$48*G$48,3)-ROUND(C18/C$48*G$48,0) -> 0 | N18: =+海田!N18 -> 3 | P18: =+B18 -> 平成6年度 | Q18: 0 | R18: 0 | S18: 0 | T18: 0 | X18: =+B18 -> 平成6年度 | Y18: 0 | Z18: 0 | AA18: 0 | AB18: 0
B19: 平成7年度 | C19: =+Q19+Y19 -> 0 | D19: =+R19+Z19 -> 0 | E19: =+S19+AA19 -> 0 | F19: =+T19+AB19 -> 0 | G19: =ROUND(C19/C$48*G$48,0) -> 0 | H19: =C19-G19 -> 0 | I19: =+VLOOKUP($B19,年度別調書!$A$4:$M$37,10,0) -> 58579778590 | J19: =+VLOOKUP($B19,年度別調書!$A$4:$M$37,13,0) -> 98916143476 | K19: =IFERROR(ROUND(H19*I19/J19,0),0) -> 0 | L19: =H19-K19 -> 0 | M19: =ROUND(C19/C$48*G$48,3)-ROUND(C19/C$48*G$48,0) -> 0 | N19: =+海田!N19 -> 3 | P19: =+B19 -> 平成7年度 | Q19: 0 | R19: 0 | S19: 0 | T19: 0 | X19: =+B19 -> 平成7年度 | Y19: 0 | Z19: 0 | AA19: 0 | AB19: 0
B20: 平成8年度 | C20: =+Q20+Y20 -> 338992 | D20: =+R20+Z20 -> 26714 | E20: =+S20+AA20 -> 365706 | F20: =+T20+AB20 -> 42264 | G20: =ROUND(C20/C$48*G$48,0) -> 29179 | H20: =C20-G20 -> 309813 | I20: =+VLOOKUP($B20,年度別調書!$A$4:$M$37,10,0) -> 59855732510 | J20: =+VLOOKUP($B20,年度別調書!$A$4:$M$37,13,0) -> 105086070753 | K20: =IFERROR(ROUND(H20*I20/J20,0),0) -> 176466 | L20: =H20-K20 -> 133347 | M20: =ROUND(C20/C$48*G$48,3)-ROUND(C20/C$48*G$48,0) -> 0.148 | N20: =+海田!N20 -> 3 | P20: =+B20 -> 平成8年度 | Q20: 168361 | R20: 14492 | S20: 182853 | T20: 21132 | X20: =+B20 -> 平成8年度 | Y20: 170631 | Z20: 12222 | AA20: 182853 | AB20: 21132
B21: 平成9年度 | C21: =+Q21+Y21 -> 2220449 | D21: =+R21+Z21 -> 200651 | E21: =+S21+AA21 -> 2421100 | F21: =+T21+AB21 -> 258094 | G21: =ROUND(C21/C$48*G$48,0) -> 191128 | H21: =C21-G21 -> 2029321 | I21: =+VLOOKUP($B21,年度別調書!$A$4:$M$37,10,0) -> 65491097789 | J21: =+VLOOKUP($B21,年度別調書!$A$4:$M$37,13,0) -> 112544371375 | K21: =IFERROR(ROUND(H21*I21/J21,0),0) -> 1180889 | L21: =H21-K21 -> 848432 | M21: =ROUND(C21/C$48*G$48,3)-ROUND(C21/C$48*G$48,0) -> -0.156 | N21: =+海田!N21 -> 5 | P21: =+B21 -> 平成9年度 | Q21: 1104456 | R21: 106094 | S21: 1210550 | T21: 129047 | X21: =+B21 -> 平成9年度 | Y21: 1115993 | Z21: 94557 | AA21: 1210550 | AB21: 129047
B22: 平成10年度 | C22: =+Q22+Y22 -> 1319568 | D22: =+R22+Z22 -> 151918 | E22: =+S22+AA22 -> 1471486 | F22: =+T22+AB22 -> 161068 | G22: =ROUND(C22/C$48*G$48,0) -> 113583 | H22: =C22-G22 -> 1205985 | I22: =+VLOOKUP($B22,年度別調書!$A$4:$M$37,10,0) -> 66701247191 | J22: =+VLOOKUP($B22,年度別調書!$A$4:$M$37,13,0) -> 118194473653 | K22: =IFERROR(ROUND(H22*I22/J22,0),0) -> 680579 | L22: =H22-K22 -> 525406 | M22: =ROUND(C22/C$48*G$48,3)-ROUND(C22/C$48*G$48,0) -> 0.418 | N22: =+海田!N22 -> 5 | P22: =+B22 -> 平成10年度 | Q22: 656381 | R22: 79362 | S22: 735743 | T22: 80534 | X22: =+B22 -> 平成10年度 | Y22: 663187 | Z22: 72556 | AA22: 735743 | AB22: 80534
B23: 平成11年度 | C23: =+Q23+Y23 -> 0 | D23: =+R23+Z23 -> 0 | E23: =+S23+AA23 -> 0 | F23: =+T23+AB23 -> 0 | G23: =ROUND(C23/C$48*G$48,0) -> 0 | H23: =C23-G23 -> 0 | I23: =+VLOOKUP($B23,年度別調書!$A$4:$M$37,10,0) -> 58274420372 | J23: =+VLOOKUP($B23,年度別調書!$A$4:$M$37,13,0) -> 110790062218 | K23: =IFERROR(ROUND(H23*I23/J23,0),0) -> 0 | L23: =H23-K23 -> 0 | M23: =ROUND(C23/C$48*G$48,3)-ROUND(C23/C$48*G$48,0) -> 0 | N23: =+海田!N23 -> 5 | P23: =+B23 -> 平成11年度 | Q23: 0 | R23: 0 | S23: 0 | T23: 0 | X23: =+B23 -> 平成11年度 | Y23: 0 | Z23: 0 | AA23: 0 | AB23: 0
B24: 平成12年度 | C24: =+Q24+Y24 -> 0 | D24: =+R24+Z24 -> 0 | E24: =+S24+AA24 -> 0 | F24: =+T24+AB24 -> 0 | G24: =ROUND(C24/C$48*G$48,0) -> 0 | H24: =C24-G24 -> 0 | I24: =+VLOOKUP($B24,年度別調書!$A$4:$M$37,10,0) -> 48353931386 | J24: =+VLOOKUP($B24,年度別調書!$A$4:$M$37,13,0) -> 104173607652 | K24: =IFERROR(ROUND(H24*I24/J24,0),0) -> 0 | L24: =H24-K24 -> 0 | M24: =ROUND(C24/C$48*G$48,3)-ROUND(C24/C$48*G$48,0) -> 0 | N24: =+海田!N24 -> 5 | P24: =+B24 -> 平成12年度 | Q24: 0 | R24: 0 | S24: 0 | T24: 0 | X24: =+B24 -> 平成12年度 | Y24: 0 | Z24: 0 | AA24: 0 | AB24: 0
... B42: 平成30年度 | C42: =+Q42+Y42 -> 0 | D42: =+R42+Z42 -> 10735 | E42: =+S42+AA42 -> 10735 | F42: =+T42+AB42 -> 1204 | G42: =ROUND(C42/C$48*G$48,0) -> 0 | H42: =C42-G42 -> 0 | I42: =+VLOOKUP($B42,年度別調書!$A$4:$M$37,10,0) -> 19871916207 | J42: =+VLOOKUP($B42,年度別調書!$A$4:$M$37,13,0) -> 98551757388 | K42: =IFERROR(ROUND(H42*I42/J42,0),0) -> 0 | L42: =H42-K42 -> 0 | M42: =ROUND(C42/C$48*G$48,3)-ROUND(C42/C$48*G$48,0) -> 0 | N42: =+海田!N42 -> 8 | P42: =+B42 -> 平成30年度 | Q42: 0 | R42: 5369 | S42: 5369 | T42: 602 | X42: =+B42 -> 平成30年度 | Y42: 0 | Z42: 5366 | AA42: 5366 | AB42: 602
B43: 令和元年度 | C43: =+Q43 -> 0 | D43: =+R43 -> 15383 | E43: =+S43 -> 15383 | F43: =+T43 -> 1726 | G43: =ROUND(C43/C$48*G$48,0) -> 0 | H43: =C43-G43 -> 0 | I43: =+VLOOKUP($B43,年度別調書!$A$4:$M$37,10,0) -> 21889958229 | J43: =+VLOOKUP($B43,年度別調書!$A$4:$M$37,13,0) -> 101214576030 | K43: =IFERROR(ROUND(H43*I43/J43,0),0) -> 0 | L43: =H43-K43 -> 0 | M43: =ROUND(C43/C$48*G$48,3)-ROUND(C43/C$48*G$48,0) -> 0 | N43: - | P43: =+B43 -> 令和元年度 | Q43: 0 | R43: 15383 | S43: 15383 | T43: 1726 | X43: =+B43 -> 令和元年度 | Y43: 0 | Z43: 15333 | AA43: 15333 | AB43: 1721
C44: =+Y43 -> 0 | D44: =+Z43 -> 15333 | E44: =+AA43 -> 15333 | F44: =+AB43 -> 1721 | G44: =ROUND(C44/C$48*G$48,0) -> 0 | H44: =C44-G44 -> 0 | I44: =+VLOOKUP($B43,年度別調書!$A$4:$M$37,10,0) -> 21889958229 | J44: =+VLOOKUP($B43,年度別調書!$A$4:$M$37,13,0) -> 101214576030 | K44: =IFERROR(ROUND(H44*I44/J44,0),0) -> 0 | L44: =H44-K44 -> 0 | M44: =ROUND(C44/C$48*G$48,3)-ROUND(C44/C$48*G$48,0) -> 0 | N44: 10
B45: 令和2年度 | C45: =+Q45+Y45 -> 0 | D45: =+R45+Z45 -> 2202 | E45: =+S45+AA45 -> 2202 | F45: =+T45+AB45 -> 248 | G45: =ROUND(C45/C$48*G$48,0) -> 0 | H45: =C45-G45 -> 0 | I45: =+VLOOKUP($B45,年度別調書!$A$4:$M$37,10,0) -> 25568719436 | J45: =+VLOOKUP($B45,年度別調書!$A$4:$M$37,13,0) -> 105092548853 | K45: =IFERROR(ROUND(H45*I45/J45,0),0) -> 0 | L45: =H45-K45 -> 0 | M45: =ROUND(C45/C$48*G$48,3)-ROUND(C45/C$48*G$48,0) -> 0 | N45: 10 | P45: =+B45 -> 令和2年度 | Q45: 0 | R45: 1101 | S45: 1101 | T45: 124 | X45: =+B45 -> 令和2年度 | Y45: 0 | Z45: 1101 | AA45: 1101 | AB45: 124
B46: 令和3年度 | C46: =+Q46+Y46 -> 0 | D46: =+R46+Z46 -> 0 | E46: =+S46+AA46 -> 0 | F46: =+T46+AB46 -> 0 | G46: =ROUND(C46/C$48*G$48,0) -> 0 | H46: =C46-G46 -> 0 | I46: =+VLOOKUP($B46,年度別調書!$A$4:$M$37,10,0) -> 25732995336 | J46: =+VLOOKUP($B46,年度別調書!$A$4:$M$37,13,0) -> 106246537477 | K46: =IFERROR(ROUND(H46*I46/J46,0),0) -> 0 | L46: =H46-K46 -> 0 | M46: =ROUND(C46/C$48*G$48,3)-ROUND(C46/C$48*G$48,0) -> 0 | N46: 10 | P46: =+B46 -> 令和3年度 | Q46: 0 | R46: 0 | S46: 0 | T46: 0 | X46: =+B46 -> 令和3年度 | Y46: 0 | Z46: 0 | AA46: 0 | AB46: 0
B47: 令和4年度 | C47: =+Q47+Y47 -> 0 | D47: =+R47+Z47 -> 11419 | E47: =+S47+AA47 -> 11419 | F47: =+T47+AB47 -> 1282 | G47: =ROUND(C47/C$48*G$48,0) -> 0 | H47: =C47-G47 -> 0 | I47: =+VLOOKUP($B47,年度別調書!$A$4:$M$37,10,0) -> 22974897869 | J47: =+VLOOKUP($B47,年度別調書!$A$4:$M$37,13,0) -> 102361733085 | K47: =IFERROR(ROUND(H47*I47/J47,0),0) -> 0 | L47: =H47-K47 -> 0 | M47: =ROUND(C47/C$48*G$48,3)-ROUND(C47/C$48*G$48,0) -> 0 | N47: 10 | P47: =+B47 -> 令和4年度 | Q47: 0 | R47: 5014 | S47: 5014 | T47: 563 | X47: =+B47 -> 令和4年度 | Y47: 0 | Z47: 6405 | AA47: 6405 | AB47: 719
B48: 計 | C48: =SUM(C6:C47) -> 8328317 | D48: =SUM(D6:D47) -> 848512 | E48: =SUM(E6:E47) -> 9176829 | F48: =SUM(F6:F47) -> 800620 | G48: =+U48+AC48 -> 716870 | H48: =SUM(H6:H47) -> 7611447 | K48: =SUM(K6:K47) -> 4073632 | L48: =SUM(L6:L47) -> 3537815 | N48: =+海田!N48 -> 0 | P48: 計 | Q48: =SUM(Q6:Q47) -> 4134986 | R48: =SUM(R6:R47) -> 452883 | S48: =SUM(S6:S47) -> 4587869 | T48: =SUM(T6:T47) -> 400248 | U48: 356288 | X48: 計 | Y48: =SUM(Y6:Y47) -> 4193331 | Z48: =SUM(Z6:Z47) -> 395629 | AA48: =SUM(AA6:AA47) -> 4588960 | AB48: =SUM(AB6:AB47) -> 400372 | AC48: 360582
G49: =G48-SUM(G6:G47) -> 0
J50: 税率 | K50: 税率別特定収入
J51: 3 | K51: =+SUMIFS($K$4:$K$48,$N$4:$N$48,$J51) -> 2009140
J52: 5 | K52: =+SUMIFS($K$4:$K$48,$N$4:$N$48,$J52) -> 1880046
J53: 8 | K53: =+SUMIFS($K$4:$K$48,$N$4:$N$48,$J53) -> 184446
J54: 10 | K54: =+SUMIFS($K$4:$K$48,$N$4:$N$48,$J54) -> 0
J55: 計 | K55: =SUM(K51:K54) -> 4073632
J56: チェック | K56: =+K48-K55 -> 0

Sheet 府中大須
A2: =+"令和"&MID(総括表!A2,3,1)&"年度決算 府中町大須地区" -> 令和５年度決算 府中町大須地区 | O2: =+A2 -> 令和５年度決算 府中町大須地区
A4: 区分 | B4: 年度 | C4: 起債償還額 | F4: 普通交付税 相当額 | G4: 元金分普通 交付税相当額 | H4: 元金償還 負担額 | I4: 課税支出額 | J4: 支出額合計 | K4: 特定収入 | L4: 特定収入 以外 | M4: 端数 調整 | N4: 税 率 | O4: 区分 | P4: 年度 | Q4: 起債償還額 | T4: 普通交付税 相当額 | U4: 元金分普通 交付税相当額 | W4: 区分 | X4: 年度 | Y4: 起債償還額 | AB4: 普通交付税 相当額 | AC4: 元金分普通 交付税相当額
C5: 元金 | D5: 利息 | E5: 合計 | Q5: 元金 | R5: 利息 | S5: 合計 | Y5: 元金 | Z5: 利息 | AA5: 合計
A6: 合 計 | B6: 昭和57年度 | C6: =+Q6+Y6 -> 0 | D6: =+R6+Z6 -> 0 | E6: =+S6+AA6 -> 0 | F6: =+T6+AB6 -> 0 | G6: =ROUND(C6/C$48*G$48,0) -> 0 | H6: =C6-G6 -> 0 | K6: 0 | L6: =H6-K6 -> 0 | M6: =ROUND(C6/C$48*G$48,3)-ROUND(C6/C$48*G$48,0) -> 0 | N6: =+海田!N6 -> 0 | O6: ９ 月 分 | P6: =+B6 -> 昭和57年度 | Q6: 0 | R6: 0 | S6: 0 | T6: 0 | W6: ３ 月 分 | X6: =+B6 -> 昭和57年度 | Y6: 0 | Z6: 0 | AA6: 0 | AB6: 0
B7: 昭和58年度 | C7: =+Q7+Y7 -> 0 | D7: =+R7+Z7 -> 0 | E7: =+S7+AA7 -> 0 | F7: =+T7+AB7 -> 0 | G7: =ROUND(C7/C$48*G$48,0) -> 0 | H7: =C7-G7 -> 0 | K7: 0 | L7: =H7-K7 -> 0 | M7: =ROUND(C7/C$48*G$48,3)-ROUND(C7/C$48*G$48,0) -> 0 | N7: =+海田!N7 -> 0 | P7: =+B7 -> 昭和58年度 | Q7: 0 | R7: 0 | S7: 0 | T7: 0 | X7: =+B7 -> 昭和58年度 | Y7: 0 | Z7: 0 | AA7: 0 | AB7: 0
B8: 昭和59年度 | C8: =+Q8+Y8 -> 0 | D8: =+R8+Z8 -> 0 | E8: =+S8+AA8 -> 0 | F8: =+T8+AB8 -> 0 | G8: =ROUND(C8/C$48*G$48,0) -> 0 | H8: =C8-G8 -> 0 | K8: 0 | L8: =H8-K8 -> 0 | M8: =ROUND(C8/C$48*G$48,3)-ROUND(C8/C$48*G$48,0) -> 0 | N8: =+海田!N8 -> 0 | P8: =+B8 -> 昭和59年度 | Q8: 0 | R8: 0 | S8: 0 | T8: 0 | X8: =+B8 -> 昭和59年度 | Y8: 0 | Z8: 0 | AA8: 0 | AB8: 0
B9: 昭和60年度 | C9: =+Q9+Y9 -> 0 | D9: =+R9+Z9 -> 0 | E9: =+S9+AA9 -> 0 | F9: =+T9+AB9 -> 0 | G9: =ROUND(C9/C$48*G$48,0) -> 0 | H9: =C9-G9 -> 0 | K9: 0 | L9: =H9-K9 -> 0 | M9: =ROUND(C9/C$48*G$48,3)-ROUND(C9/C$48*G$48,0) -> 0 | N9: =+海田!N9 -> 0 | P9: =+B9 -> 昭和60年度 | Q9: 0 | R9: 0 | S9: 0 | T9: 0 | X9: =+B9 -> 昭和60年度 | Y9: 0 | Z9: 0 | AA9: 0 | AB9: 0
B10: 昭和61年度 | C10: =+Q10+Y10 -> 0 | D10: =+R10+Z10 -> 0 | E10: =+S10+AA10 -> 0 | F10: =+T10+AB10 -> 0 | G10: =ROUND(C10/C$48*G$48,0) -> 0 | H10: =C10-G10 -> 0 | K10: 0 | L10: =H10-K10 -> 0 | M10: =ROUND(C10/C$48*G$48,3)-ROUND(C10/C$48*G$48,0) -> 0 | N10: =+海田!N10 -> 0 | P10: =+B10 -> 昭和61年度 | Q10: 0 | R10: 0 | S10: 0 | T10: 0 | X10: =+B10 -> 昭和61年度 | Y10: 0 | Z10: 0 | AA10: 0 | AB10: 0
B11: 昭和62年度 | C11: =+Q11+Y11 -> 0 | D11: =+R11+Z11 -> 0 | E11: =+S11+AA11 -> 0 | F11: =+T11+AB11 -> 0 | G11: =ROUND(C11/C$48*G$48,0) -> 0 | H11: =C11-G11 -> 0 | K11: 0 | L11: =H11-K11 -> 0 | M11: =ROUND(C11/C$48*G$48,3)-ROUND(C11/C$48*G$48,0) -> 0 | N11: =+海田!N11 -> 0 | P11: =+B11 -> 昭和62年度 | Q11: 0 | R11: 0 | S11: 0 | T11: 0 | X11: =+B11 -> 昭和62年度 | Y11: 0 | Z11: 0 | AA11: 0 | AB11: 0
B12: 昭和63年度 | C12: =+Q12+Y12 -> 0 | D12: =+R12+Z12 -> 0 | E12: =+S12+AA12 -> 0 | F12: =+T12+AB12 -> 0 | G12: =ROUND(C12/C$48*G$48,0) -> 0 | H12: =C12-G12 -> 0 | K12: 0 | L12: =H12-K12 -> 0 | M12: =ROUND(C12/C$48*G$48,3)-ROUND(C12/C$48*G$48,0) -> 0 | N12: =+海田!N12 -> 0 | P12: =+B12 -> 昭和63年度 | Q12: 0 | R12: 0 | S12: 0 | T12: 0 | X12: =+B12 -> 昭和63年度 | Y12: 0 | Z12: 0 | AA12: 0 | AB12: 0
B13: 平成元年度 | C13: =+Q13+Y13 -> 0 | D13: =+R13+Z13 -> 0 | E13: =+S13+AA13 -> 0 | F13: =+T13+AB13 -> 0 | G13: =ROUND(C13/C$48*G$48,0) -> 0 | H13: =C13-G13 -> 0 | I13: =+VLOOKUP($B13,年度別調書!$A$4:$M$37,10,0) -> 30622955900 | J13: =+VLOOKUP($B13,年度別調書!$A$4:$M$37,13,0) -> 62903610340 | K13: =IFERROR(ROUND(H13*I13/J13,0),0) -> 0 | L13: =H13-K13 -> 0 | M13: =ROUND(C13/C$48*G$48,3)-ROUND(C13/C$48*G$48,0) -> 0 | N13: =+海田!N13 -> 3 | P13: =+B13 -> 平成元年度 | Q13: 0 | R13: 0 | S13: 0 | T13: 0 | X13: =+B13 -> 平成元年度 | Y13: 0 | Z13: 0 | AA13: 0 | AB13: 0
B14: 平成2年度 | C14: =+Q14+Y14 -> 0 | D14: =+R14+Z14 -> 0 | E14: =+S14+AA14 -> 0 | F14: =+T14+AB14 -> 0 | G14: =ROUND(C14/C$48*G$48,0) -> 0 | H14: =C14-G14 -> 0 | I14: =+VLOOKUP($B14,年度別調書!$A$4:$M$37,10,0) -> 36785805618 | J14: =+VLOOKUP($B14,年度別調書!$A$4:$M$37,13,0) -> 65207626364 | K14: =IFERROR(ROUND(H14*I14/J14,0),0) -> 0 | L14: =H14-K14 -> 0 | M14: =ROUND(C14/C$48*G$48,3)-ROUND(C14/C$48*G$48,0) -> 0 | N14: =+海田!N14 -> 3 | P14: =+B14 -> 平成2年度 | Q14: 0 | R14: 0 | S14: 0 | T14: 0 | X14: =+B14 -> 平成2年度 | Y14: 0 | Z14: 0 | AA14: 0 | AB14: 0
B15: 平成3年度 | C15: =+Q15+Y15 -> 0 | D15: =+R15+Z15 -> 0 | E15: =+S15+AA15 -> 0 | F15: =+T15+AB15 -> 0 | G15: =ROUND(C15/C$48*G$48,0) -> 0 | H15: =C15-G15 -> 0 | I15: =+VLOOKUP($B15,年度別調書!$A$4:$M$37,10,0) -> 42048127236 | J15: =+VLOOKUP($B15,年度別調書!$A$4:$M$37,13,0) -> 72538415314 | K15: =IFERROR(ROUND(H15*I15/J15,0),0) -> 0 | L15: =H15-K15 -> 0 | M15: =ROUND(C15/C$48*G$48,3)-ROUND(C15/C$48*G$48,0) -> 0 | N15: =+海田!N15 -> 3 | P15: =+B15 -> 平成3年度 | Q15: 0 | R15: 0 | S15: 0 | T15: 0 | X15: =+B15 -> 平成3年度 | Y15: 0 | Z15: 0 | AA15: 0 | AB15: 0
B16: 平成4年度 | C16: =+Q16+Y16 -> 0 | D16: =+R16+Z16 -> 0 | E16: =+S16+AA16 -> 0 | F16: =+T16+AB16 -> 0 | G16: =ROUND(C16/C$48*G$48,0) -> 0 | H16: =C16-G16 -> 0 | I16: =+VLOOKUP($B16,年度別調書!$A$4:$M$37,10,0) -> 49320557603 | J16: =+VLOOKUP($B16,年度別調書!$A$4:$M$37,13,0) -> 82028053042 | K16: =IFERROR(ROUND(H16*I16/J16,0),0) -> 0 | L16: =H16-K16 -> 0 | M16: =ROUND(C16/C$48*G$48,3)-ROUND(C16/C$48*G$48,0) -> 0 | N16: =+海田!N16 -> 3 | P16: =+B16 -> 平成4年度 | Q16: 0 | R16: 0 | S16: 0 | T16: 0 | X16: =+B16 -> 平成4年度 | Y16: 0 | Z16: 0 | AA16: 0 | AB16: 0
B17: 平成5年度 | C17: =+Q17+Y17 -> 0 | D17: =+R17+Z17 -> 0 | E17: =+S17+AA17 -> 0 | F17: =+T17+AB17 -> 0 | G17: =ROUND(C17/C$48*G$48,0) -> 0 | H17: =C17-G17 -> 0 | I17: =+VLOOKUP($B17,年度別調書!$A$4:$M$37,10,0) -> 54853236126 | J17: =+VLOOKUP($B17,年度別調書!$A$4:$M$37,13,0) -> 94393962571 | K17: =IFERROR(ROUND(H17*I17/J17,0),0) -> 0 | L17: =H17-K17 -> 0 | M17: =ROUND(C17/C$48*G$48,3)-ROUND(C17/C$48*G$48,0) -> 0 | N17: =+海田!N17 -> 3 | P17: =+B17 -> 平成5年度 | Q17: 0 | R17: 0 | S17: 0 | T17: 0 | X17: =+B17 -> 平成5年度 | Y17: 0 | Z17: 0 | AA17: 0 | AB17: 0
B18: 平成6年度 | C18: =+Q18+Y18 -> 0 | D18: =+R18+Z18 -> 0 | E18: =+S18+AA18 -> 0 | F18: =+T18+AB18 -> 0 | G18: =ROUND(C18/C$48*G$48,0) -> 0 | H18: =C18-G18 -> 0 | I18: =+VLOOKUP($B18,年度別調書!$A$4:$M$37,10,0) -> 52459905451 | J18: =+VLOOKUP($B18,年度別調書!$A$4:$M$37,13,0) -> 92179213936 | K18: =IFERROR(ROUND(H18*I18/J18,0),0) -> 0 | L18: =H18-K18 -> 0 | M18: =ROUND(C18/C$48*G$48,3)-ROUND(C18/C$48*G$48,0) -> 0 | N18: =+海田!N18 -> 3 | P18: =+B18 -> 平成6年度 | Q18: 0 | R18: 0 | S18: 0 | T18: 0 | X18: =+B18 -> 平成6年度 | Y18: 0 | Z18: 0 | AA18: 0 | AB18: 0
B19: 平成7年度 | C19: =+Q19+Y19 -> 0 | D19: =+R19+Z19 -> 0 | E19: =+S19+AA19 -> 0 | F19: =+T19+AB19 -> 0 | G19: =ROUND(C19/C$48*G$48,0) -> 0 | H19: =C19-G19 -> 0 | I19: =+VLOOKUP($B19,年度別調書!$A$4:$M$37,10,0) -> 58579778590 | J19: =+VLOOKUP($B19,年度別調書!$A$4:$M$37,13,0) -> 98916143476 | K19: =IFERROR(ROUND(H19*I19/J19,0),0) -> 0 | L19: =H19-K19 -> 0 | M19: =ROUND(C19/C$48*G$48,3)-ROUND(C19/C$48*G$48,0) -> 0 | N19: =+海田!N19 -> 3 | P19: =+B19 -> 平成7年度 | Q19: 0 | R19: 0 | S19: 0 | T19: 0 | X19: =+B19 -> 平成7年度 | Y19: 0 | Z19: 0 | AA19: 0 | AB19: 0
B20: 平成8年度 | C20: =+Q20+Y20 -> 0 | D20: =+R20+Z20 -> 0 | E20: =+S20+AA20 -> 0 | F20: =+T20+AB20 -> 0 | G20: =ROUND(C20/C$48*G$48,0) -> 0 | H20: =C20-G20 -> 0 | I20: =+VLOOKUP($B20,年度別調書!$A$4:$M$37,10,0) -> 59855732510 | J20: =+VLOOKUP($B20,年度別調書!$A$4:$M$37,13,0) -> 105086070753 | K20: =IFERROR(ROUND(H20*I20/J20,0),0) -> 0 | L20: =H20-K20 -> 0 | M20: =ROUND(C20/C$48*G$48,3)-ROUND(C20/C$48*G$48,0) -> 0 | N20: =+海田!N20 -> 3 | P20: =+B20 -> 平成8年度 | Q20: 0 | R20: 0 | S20: 0 | T20: 0 | X20: =+B20 -> 平成8年度 | Y20: 0 | Z20: 0 | AA20: 0 | AB20: 0
B21: 平成9年度 | C21: =+Q21+Y21 -> 0 | D21: =+R21+Z21 -> 0 | E21: =+S21+AA21 -> 0 | F21: =+T21+AB21 -> 0 | G21: =ROUND(C21/C$48*G$48,0) -> 0 | H21: =C21-G21 -> 0 | I21: =+VLOOKUP($B21,年度別調書!$A$4:$M$37,10,0) -> 65491097789 | J21: =+VLOOKUP($B21,年度別調書!$A$4:$M$37,13,0) -> 112544371375 | K21: =IFERROR(ROUND(H21*I21/J21,0),0) -> 0 | L21: =H21-K21 -> 0 | M21: =ROUND(C21/C$48*G$48,3)-ROUND(C21/C$48*G$48,0) -> 0 | N21: =+海田!N21 -> 5 | P21: =+B21 -> 平成9年度 | Q21: 0 | R21: 0 | S21: 0 | T21: 0 | X21: =+B21 -> 平成9年度 | Y21: 0 | Z21: 0 | AA21: 0 | AB21: 0
B22: 平成10年度 | C22: =+Q22+Y22 -> 0 | D22: =+R22+Z22 -> 0 | E22: =+S22+AA22 -> 0 | F22: =+T22+AB22 -> 0 | G22: =ROUND(C22/C$48*G$48,0) -> 0 | H22: =C22-G22 -> 0 | I22: =+VLOOKUP($B22,年度別調書!$A$4:$M$37,10,0) -> 66701247191 | J22: =+VLOOKUP($B22,年度別調書!$A$4:$M$37,13,0) -> 118194473653 | K22: =IFERROR(ROUND(H22*I22/J22,0),0) -> 0 | L22: =H22-K22 -> 0 | M22: =ROUND(C22/C$48*G$48,3)-ROUND(C22/C$48*G$48,0) -> 0 | N22: =+海田!N22 -> 5 | P22: =+B22 -> 平成10年度 | Q22: 0 | R22: 0 | S22: 0 | T22: 0 | X22: =+B22 -> 平成10年度 | Y22: 0 | Z22: 0 | AA22: 0 | AB22: 0
B23: 平成11年度 | C23: =+Q23+Y23 -> 0 | D23: =+R23+Z23 -> 0 | E23: =+S23+AA23 -> 0 | F23: =+T23+AB23 -> 0 | G23: =ROUND(C23/C$48*G$48,0) -> 0 | H23: =C23-G23 -> 0 | I23: =+VLOOKUP($B23,年度別調書!$A$4:$M$37,10,0) -> 58274420372 | J23: =+VLOOKUP($B23,年度別調書!$A$4:$M$37,13,0) -> 110790062218 | K23: =IFERROR(ROUND(H23*I23/J23,0),0) -> 0 | L23: =H23-K23 -> 0 | M23: =ROUND(C23/C$48*G$48,3)-ROUND(C23/C$48*G$48,0) -> 0 | N23: =+海田!N23 -> 5 | P23: =+B23 -> 平成11年度 | Q23: 0 | R23: 0 | S23: 0 | T23: 0 | X23: =+B23 -> 平成11年度 | Y23: 0 | Z23: 0 | AA23: 0 | AB23: 0
B24: 平成12年度 | C24: =+Q24+Y24 -> 0 | D24: =+R24+Z24 -> 0 | E24: =+S24+AA24 -> 0 | F24: =+T24+AB24 -> 0 | G24: =ROUND(C24/C$48*G$48,0) -> 0 | H24: =C24-G24 -> 0 | I24: =+VLOOKUP($B24,年度別調書!$A$4:$M$37,10,0) -> 48353931386 | J24: =+VLOOKUP($B24,年度別調書!$A$4:$M$37,13,0) -> 104173607652 | K24: =IFERROR(ROUND(H24*I24/J24,0),0) -> 0 | L24: =H24-K24 -> 0 | M24: =ROUND(C24/C$48*G$48,3)-ROUND(C24/C$48*G$48,0) -> 0 | N24: =+海田!N24 -> 5 | P24: =+B24 -> 平成12年度 | Q24: 0 | R24: 0 | S24: 0 | T24: 0 | X24: =+B24 -> 平成12年度 | Y24: 0 | Z24: 0 | AA24: 0 | AB24: 0
... B42: 平成30年度 | C42: =+Q42+Y42 -> 0 | D42: =+R42+Z42 -> 45372 | E42: =+S42+AA42 -> 45372 | F42: =+T42+AB42 -> 5092 | G42: =ROUND(C42/C$48*G$48,0) -> 0 | H42: =C42-G42 -> 0 | I42: =+VLOOKUP($B42,年度別調書!$A$4:$M$37,10,0) -> 19871916207 | J42: =+VLOOKUP($B42,年度別調書!$A$4:$M$37,13,0) -> 98551757388 | K42: =IFERROR(ROUND(H42*I42/J42,0),0) -> 0 | L42: =H42-K42 -> 0 | M42: =ROUND(C42/C$48*G$48,3)-ROUND(C42/C$48*G$48,0) -> 0 | N42: =+海田!N42 -> 8 | P42: =+B42 -> 平成30年度 | Q42: 0 | R42: 22691 | S42: 22691 | T42: 2547 | X42: =+B42 -> 平成30年度 | Y42: 0 | Z42: 22681 | AA42: 22681 | AB42: 2545
B43: 令和元年度 | C43: =+Q43 -> 0 | D43: =+R43 -> 53 | E43: =+S43 -> 53 | F43: =+T43 -> 6 | G43: =ROUND(C43/C$48*G$48,0) -> 0 | H43: =C43-G43 -> 0 | I43: =+VLOOKUP($B43,年度別調書!$A$4:$M$37,10,0) -> 21889958229 | J43: =+VLOOKUP($B43,年度別調書!$A$4:$M$37,13,0) -> 101214576030 | K43: =IFERROR(ROUND(H43*I43/J43,0),0) -> 0 | L43: =H43-K43 -> 0 | M43: =ROUND(C43/C$48*G$48,3)-ROUND(C43/C$48*G$48,0) -> 0 | N43: =+海田!N43 -> 8 | P43: =+B43 -> 令和元年度 | Q43: 0 | R43: 53 | S43: 53 | T43: 6 | X43: =+B43 -> 令和元年度 | Y43: 0 | Z43: 53 | AA43: 53 | AB43: 6
C44: =+Y43 -> 0 | D44: =+Z43 -> 53 | E44: =+AA43 -> 53 | F44: =+AB43 -> 6 | G44: =ROUND(C44/C$48*G$48,0) -> 0 | H44: =C44-G44 -> 0 | I44: =+VLOOKUP($B43,年度別調書!$A$4:$M$37,10,0) -> 21889958229 | J44: =+VLOOKUP($B43,年度別調書!$A$4:$M$37,13,0) -> 101214576030 | K44: =IFERROR(ROUND(H44*I44/J44,0),0) -> 0 | L44: =H44-K44 -> 0 | M44: =ROUND(C44/C$48*G$48,3)-ROUND(C44/C$48*G$48,0) -> 0 | N44: =+海田!N44 -> 10
B45: 令和2年度 | C45: =+Q45+Y45 -> 0 | D45: =+R45+Z45 -> 5000 | E45: =+S45+AA45 -> 5000 | F45: =+T45+AB45 -> 562 | G45: =ROUND(C45/C$48*G$48,0) -> 0 | H45: =C45-G45 -> 0 | I45: =+VLOOKUP($B45,年度別調書!$A$4:$M$37,10,0) -> 25568719436 | J45: =+VLOOKUP($B45,年度別調書!$A$4:$M$37,13,0) -> 105092548853 | K45: =IFERROR(ROUND(H45*I45/J45,0),0) -> 0 | L45: =H45-K45 -> 0 | M45: =ROUND(C45/C$48*G$48,3)-ROUND(C45/C$48*G$48,0) -> 0 | N45: =+海田!N45 -> 10 | P45: =+B45 -> 令和2年度 | Q45: 0 | R45: 2500 | S45: 2500 | T45: 281 | X45: =+B45 -> 令和2年度 | Y45: 0 | Z45: 2500 | AA45: 2500 | AB45: 281
B46: 令和3年度 | C46: =+Q46+Y46 -> 0 | D46: =+R46+Z46 -> 101147 | E46: =+S46+AA46 -> 101147 | F46: =+T46+AB46 -> 11351 | G46: =ROUND(C46/C$48*G$48,0) -> 0 | H46: =C46-G46 -> 0 | I46: =+VLOOKUP($B46,年度別調書!$A$4:$M$37,10,0) -> 25732995336 | J46: =+VLOOKUP($B46,年度別調書!$A$4:$M$37,13,0) -> 106246537477 | K46: =IFERROR(ROUND(H46*I46/J46,0),0) -> 0 | L46: =H46-K46 -> 0 | M46: =ROUND(C46/C$48*G$48,3)-ROUND(C46/C$48*G$48,0) -> 0 | N46: =+海田!N46 -> 10 | P46: =+B46 -> 令和3年度 | Q46: 0 | R46: 47102 | S46: 47102 | T46: 5286 | X46: =+B46 -> 令和3年度 | Y46: 0 | Z46: 54045 | AA46: 54045 | AB46: 6065
B47: 令和4年度 | C47: =+Q47+Y47 -> 0 | D47: =+R47+Z47 -> 150510 | E47: =+S47+AA47 -> 150510 | F47: =+T47+AB47 -> 16892 | G47: =ROUND(C47/C$48*G$48,0) -> 0 | H47: =C47-G47 -> 0 | I47: =+VLOOKUP($B47,年度別調書!$A$4:$M$37,10,0) -> 22974897869 | J47: =+VLOOKUP($B47,年度別調書!$A$4:$M$37,13,0) -> 102361733085 | K47: =IFERROR(ROUND(H47*I47/J47,0),0) -> 0 | L47: =H47-K47 -> 0 | M47: =ROUND(C47/C$48*G$48,3)-ROUND(C47/C$48*G$48,0) -> 0 | N47: =+海田!N47 -> 10 | P47: =+B47 -> 令和4年度 | Q47: 0 | R47: 66087 | S47: 66087 | T47: 7417 | X47: =+B47 -> 令和4年度 | Y47: 0 | Z47: 84423 | AA47: 84423 | AB47: 9475
B48: 計 | C48: =SUM(C6:C47) -> 3610379 | D48: =SUM(D6:D47) -> 1167300 | E48: =SUM(E6:E47) -> 4777679 | F48: =SUM(F6:F47) -> 536182 | G48: =+U48+AC48 -> 405178 | H48: =SUM(H6:H47) -> 3205201 | K48: =SUM(K6:K47) -> 726081 | L48: =SUM(L6:L47) -> 2479120 | N48: =+海田!N48 -> 0 | P48: 計 | Q48: =SUM(Q6:Q47) -> 1800725 | R48: =SUM(R6:R47) -> 575538 | S48: =SUM(S6:S47) -> 2376263 | T48: =SUM(T6:T47) -> 266680 | U48: 202088 | X48: 計 | Y48: =SUM(Y6:Y47) -> 1809654 | Z48: =SUM(Z6:Z47) -> 591762 | AA48: =SUM(AA6:AA47) -> 2401416 | AB48: =SUM(AB6:AB47) -> 269502 | AC48: 203090
G49: =G48-SUM(G6:G47) -> 0
J50: 税率 | K50: 税率別特定収入
J51: 3 | K51: =+SUMIFS($K$4:$K$48,$N$4:$N$48,$J51) -> 0
J52: 5 | K52: =+SUMIFS($K$4:$K$48,$N$4:$N$48,$J52) -> 323001
J53: 8 | K53: =+SUMIFS($K$4:$K$48,$N$4:$N$48,$J53) -> 403080
J54: 10 | K54: =+SUMIFS($K$4:$K$48,$N$4:$N$48,$J54) -> 0
J55: 計 | K55: =SUM(K51:K54) -> 726081
J56: チェック | K56: =+K48-K55 -> 0

Sheet 大須（共通）
A2: =+"令和"&MID(総括表!A2,3,1)&"年度決算 府中町大須地区(共通分)" -> 令和５年度決算 府中町大須地区(共通分) | O2: =+A2 -> 令和５年度決算 府中町大須地区(共通分)
A4: 区分 | B4: 年度 | C4: 起債償還額 | F4: 普通交付税 相当額 | G4: 元金分普通 交付税相当額 | H4: 元金償還 負担額 | I4: 課税支出額 | J4: 支出額合計 | K4: 特定収入 | L4: 特定収入 以外 | M4: 端数 調整 | N4: 税 率 | O4: 区分 | P4: 年度 | Q4: 起債償還額 | T4: 普通交付税 相当額 | U4: 元金分普通 交付税相当額 | W4: 区分 | X4: 年度 | Y4: 起債償還額 | AB4: 普通交付税 相当額 | AC4: 元金分普通 交付税相当額
C5: 元金 | D5: 利息 | E5: 合計 | Q5: 元金 | R5: 利息 | S5: 合計 | Y5: 元金 | Z5: 利息 | AA5: 合計
A6: 合 計 | B6: 昭和57年度 | C6: =+Q6+Y6 -> 0 | D6: =+R6+Z6 -> 0 | E6: =+S6+AA6 -> 0 | F6: =+T6+AB6 -> 0 | G6: =ROUND(C6/C$48*G$48,0) -> 0 | H6: =C6-G6 -> 0 | K6: 0 | L6: =H6-K6 -> 0 | M6: =ROUND(C6/C$48*G$48,3)-ROUND(C6/C$48*G$48,0) -> 0 | N6: =+海田!N6 -> 0 | O6: ９ 月 分 | P6: =+B6 -> 昭和57年度 | Q6: 0 | R6: 0 | S6: 0 | T6: 0 | W6: ３ 月 分 | X6: =+B6 -> 昭和57年度 | Y6: 0 | Z6: 0 | AA6: 0 | AB6: 0
B7: 昭和58年度 | C7: =+Q7+Y7 -> 0 | D7: =+R7+Z7 -> 0 | E7: =+S7+AA7 -> 0 | F7: =+T7+AB7 -> 0 | G7: =ROUND(C7/C$48*G$48,0) -> 0 | H7: =C7-G7 -> 0 | K7: 0 | L7: =H7-K7 -> 0 | M7: =ROUND(C7/C$48*G$48,3)-ROUND(C7/C$48*G$48,0) -> 0 | N7: =+海田!N7 -> 0 | P7: =+B7 -> 昭和58年度 | Q7: 0 | R7: 0 | S7: 0 | T7: 0 | X7: =+B7 -> 昭和58年度 | Y7: 0 | Z7: 0 | AA7: 0 | AB7: 0
B8: 昭和59年度 | C8: =+Q8+Y8 -> 0 | D8: =+R8+Z8 -> 0 | E8: =+S8+AA8 -> 0 | F8: =+T8+AB8 -> 0 | G8: =ROUND(C8/C$48*G$48,0) -> 0 | H8: =C8-G8 -> 0 | K8: 0 | L8: =H8-K8 -> 0 | M8: =ROUND(C8/C$48*G$48,3)-ROUND(C8/C$48*G$48,0) -> 0 | N8: =+海田!N8 -> 0 | P8: =+B8 -> 昭和59年度 | Q8: 0 | R8: 0 | S8: 0 | T8: 0 | X8: =+B8 -> 昭和59年度 | Y8: 0 | Z8: 0 | AA8: 0 | AB8: 0
B9: 昭和60年度 | C9: =+Q9+Y9 -> 0 | D9: =+R9+Z9 -> 0 | E9: =+S9+AA9 -> 0 | F9: =+T9+AB9 -> 0 | G9: =ROUND(C9/C$48*G$48,0) -> 0 | H9: =C9-G9 -> 0 | K9: 0 | L9: =H9-K9 -> 0 | M9: =ROUND(C9/C$48*G$48,3)-ROUND(C9/C$48*G$48,0) -> 0 | N9: =+海田!N9 -> 0 | P9: =+B9 -> 昭和60年度 | Q9: 0 | R9: 0 | S9: 0 | T9: 0 | X9: =+B9 -> 昭和60年度 | Y9: 0 | Z9: 0 | AA9: 0 | AB9: 0
B10: 昭和61年度 | C10: =+Q10+Y10 -> 0 | D10: =+R10+Z10 -> 0 | E10: =+S10+AA10 -> 0 | F10: =+T10+AB10 -> 0 | G10: =ROUND(C10/C$48*G$48,0) -> 0 | H10: =C10-G10 -> 0 | K10: 0 | L10: =H10-K10 -> 0 | M10: =ROUND(C10/C$48*G$48,3)-ROUND(C10/C$48*G$48,0) -> 0 | N10: =+海田!N10 -> 0 | P10: =+B10 -> 昭和61年度 | Q10: 0 | R10: 0 | S10: 0 | T10: 0 | X10: =+B10 -> 昭和61年度 | Y10: 0 | Z10: 0 | AA10: 0 | AB10: 0
B11: 昭和62年度 | C11: =+Q11+Y11 -> 0 | D11: =+R11+Z11 -> 0 | E11: =+S11+AA11 -> 0 | F11: =+T11+AB11 -> 0 | G11: =ROUND(C11/C$48*G$48,0) -> 0 | H11: =C11-G11 -> 0 | K11: 0 | L11: =H11-K11 -> 0 | M11: =ROUND(C11/C$48*G$48,3)-ROUND(C11/C$48*G$48,0) -> 0 | N11: =+海田!N11 -> 0 | P11: =+B11 -> 昭和62年度 | Q11: 0 | R11: 0 | S11: 0 | T11: 0 | X11: =+B11 -> 昭和62年度 | Y11: 0 | Z11: 0 | AA11: 0 | AB11: 0
B12: 昭和63年度 | C12: =+Q12+Y12 -> 0 | D12: =+R12+Z12 -> 0 | E12: =+S12+AA12 -> 0 | F12: =+T12+AB12 -> 0 | G12: =ROUND(C12/C$48*G$48,0) -> 0 | H12: =C12-G12 -> 0 | K12: 0 | L12: =H12-K12 -> 0 | M12: =ROUND(C12/C$48*G$48,3)-ROUND(C12/C$48*G$48,0) -> 0 | N12: =+海田!N12 -> 0 | P12: =+B12 -> 昭和63年度 | Q12: 0 | R12: 0 | S12: 0 | T12: 0 | X12: =+B12 -> 昭和63年度 | Y12: 0 | Z12: 0 | AA12: 0 | AB12: 0
B13: 平成元年度 | C13: =+Q13+Y13 -> 0 | D13: =+R13+Z13 -> 0 | E13: =+S13+AA13 -> 0 | F13: =+T13+AB13 -> 0 | G13: =ROUND(C13/C$48*G$48,0) -> 0 | H13: =C13-G13 -> 0 | I13: =+VLOOKUP($B13,年度別調書!$A$4:$M$37,10,0) -> 30622955900 | J13: =+VLOOKUP($B13,年度別調書!$A$4:$M$37,13,0) -> 62903610340 | K13: =IFERROR(ROUND(H13*I13/J13,0),0) -> 0 | L13: =H13-K13 -> 0 | M13: =ROUND(C13/C$48*G$48,3)-ROUND(C13/C$48*G$48,0) -> 0 | N13: =+海田!N13 -> 3 | P13: =+B13 -> 平成元年度 | Q13: 0 | R13: 0 | S13: 0 | T13: 0 | X13: =+B13 -> 平成元年度 | Y13: 0 | Z13: 0 | AA13: 0 | AB13: 0
B14: 平成2年度 | C14: =+Q14+Y14 -> 0 | D14: =+R14+Z14 -> 0 | E14: =+S14+AA14 -> 0 | F14: =+T14+AB14 -> 0 | G14: =ROUND(C14/C$48*G$48,0) -> 0 | H14: =C14-G14 -> 0 | I14: =+VLOOKUP($B14,年度別調書!$A$4:$M$37,10,0) -> 36785805618 | J14: =+VLOOKUP($B14,年度別調書!$A$4:$M$37,13,0) -> 65207626364 | K14: =IFERROR(ROUND(H14*I14/J14,0),0) -> 0 | L14: =H14-K14 -> 0 | M14: =ROUND(C14/C$48*G$48,3)-ROUND(C14/C$48*G$48,0) -> 0 | N14: =+海田!N14 -> 3 | P14: =+B14 -> 平成2年度 | Q14: 0 | R14: 0 | S14: 0 | T14: 0 | X14: =+B14 -> 平成2年度 | Y14: 0 | Z14: 0 | AA14: 0 | AB14: 0
B15: 平成3年度 | C15: =+Q15+Y15 -> 0 | D15: =+R15+Z15 -> 0 | E15: =+S15+AA15 -> 0 | F15: =+T15+AB15 -> 0 | G15: =ROUND(C15/C$48*G$48,0) -> 0 | H15: =C15-G15 -> 0 | I15: =+VLOOKUP($B15,年度別調書!$A$4:$M$37,10,0) -> 42048127236 | J15: =+VLOOKUP($B15,年度別調書!$A$4:$M$37,13,0) -> 72538415314 | K15: =IFERROR(ROUND(H15*I15/J15,0),0) -> 0 | L15: =H15-K15 -> 0 | M15: =ROUND(C15/C$48*G$48,3)-ROUND(C15/C$48*G$48,0) -> 0 | N15: =+海田!N15 -> 3 | P15: =+B15 -> 平成3年度 | Q15: 0 | R15: 0 | S15: 0 | T15: 0 | X15: =+B15 -> 平成3年度 | Y15: 0 | Z15: 0 | AA15: 0 | AB15: 0
B16: 平成4年度 | C16: =+Q16+Y16 -> 396649 | D16: =+R16+Z16 -> 10891 | E16: =+S16+AA16 -> 407540 | F16: =+T16+AB16 -> 31738 | G16: =ROUND(C16/C$48*G$48,0) -> 34256 | H16: =C16-G16 -> 362393 | I16: =+VLOOKUP($B16,年度別調書!$A$4:$M$37,10,0) -> 49320557603 | J16: =+VLOOKUP($B16,年度別調書!$A$4:$M$37,13,0) -> 82028053042 | K16: =IFERROR(ROUND(H16*I16/J16,0),0) -> 217894 | L16: =H16-K16 -> 144499 | M16: =ROUND(C16/C$48*G$48,3)-ROUND(C16/C$48*G$48,0) -> -0.404 | N16: =+海田!N16 -> 3 | P16: =+B16 -> 平成4年度 | Q16: 196531 | R16: 7239 | S16: 203770 | T16: 15869 | X16: =+B16 -> 平成4年度 | Y16: 200118 | Z16: 3652 | AA16: 203770 | AB16: 15869
B17: 平成5年度 | C17: =+Q17+Y17 -> 626517 | D17: =+R17+Z17 -> 32743 | E17: =+S17+AA17 -> 659260 | F17: =+T17+AB17 -> 30910 | G17: =ROUND(C17/C$48*G$48,0) -> 54108 | H17: =C17-G17 -> 572409 | I17: =+VLOOKUP($B17,年度別調書!$A$4:$M$37,10,0) -> 54853236126 | J17: =+VLOOKUP($B17,年度別調書!$A$4:$M$37,13,0) -> 94393962571 | K17: =IFERROR(ROUND(H17*I17/J17,0),0) -> 332632 | L17: =H17-K17 -> 239777 | M17: =ROUND(C17/C$48*G$48,3)-ROUND(C17/C$48*G$48,0) -> -0.431 | N17: =+海田!N17 -> 3 | P17: =+B17 -> 平成5年度 | Q17: 309823 | R17: 19807 | S17: 329630 | T17: 15455 | X17: =+B17 -> 平成5年度 | Y17: 316694 | Z17: 12936 | AA17: 329630 | AB17: 15455
B18: 平成6年度 | C18: =+Q18+Y18 -> 489651 | D18: =+R18+Z18 -> 38607 | E18: =+S18+AA18 -> 528258 | F18: =+T18+AB18 -> 15078 | G18: =ROUND(C18/C$48*G$48,0) -> 42287 | H18: =C18-G18 -> 447364 | I18: =+VLOOKUP($B18,年度別調書!$A$4:$M$37,10,0) -> 52459905451 | J18: =+VLOOKUP($B18,年度別調書!$A$4:$M$37,13,0) -> 92179213936 | K18: =IFERROR(ROUND(H18*I18/J18,0),0) -> 254598 | L18: =H18-K18 -> 192766 | M18: =ROUND(C18/C$48*G$48,3)-ROUND(C18/C$48*G$48,0) -> 0.48 | N18: =+海田!N18 -> 3 | P18: =+B18 -> 平成6年度 | Q18: 242434 | R18: 21695 | S18: 264129 | T18: 7539 | X18: =+B18 -> 平成6年度 | Y18: 247217 | Z18: 16912 | AA18: 264129 | AB18: 7539
B19: 平成7年度 | C19: =+Q19+Y19 -> 0 | D19: =+R19+Z19 -> 0 | E19: =+S19+AA19 -> 0 | F19: =+T19+AB19 -> 0 | G19: =ROUND(C19/C$48*G$48,0) -> 0 | H19: =C19-G19 -> 0 | I19: =+VLOOKUP($B19,年度別調書!$A$4:$M$37,10,0) -> 58579778590 | J19: =+VLOOKUP($B19,年度別調書!$A$4:$M$37,13,0) -> 98916143476 | K19: =IFERROR(ROUND(H19*I19/J19,0),0) -> 0 | L19: =H19-K19 -> 0 | M19: =ROUND(C19/C$48*G$48,3)-ROUND(C19/C$48*G$48,0) -> 0 | N19: =+海田!N19 -> 3 | P19: =+B19 -> 平成7年度 | Q19: 0 | R19: 0 | S19: 0 | T19: 0 | X19: =+B19 -> 平成7年度 | Y19: 0 | Z19: 0 | AA19: 0 | AB19: 0
B20: 平成8年度 | C20: =+Q20+Y20 -> 0 | D20: =+R20+Z20 -> 0 | E20: =+S20+AA20 -> 0 | F20: =+T20+AB20 -> 0 | G20: =ROUND(C20/C$48*G$48,0) -> 0 | H20: =C20-G20 -> 0 | I20: =+VLOOKUP($B20,年度別調書!$A$4:$M$37,10,0) -> 59855732510 | J20: =+VLOOKUP($B20,年度別調書!$A$4:$M$37,13,0) -> 105086070753 | K20: =IFERROR(ROUND(H20*I20/J20,0),0) -> 0 | L20: =H20-K20 -> 0 | M20: =ROUND(C20/C$48*G$48,3)-ROUND(C20/C$48*G$48,0) -> 0 | N20: =+海田!N20 -> 3 | P20: =+B20 -> 平成8年度 | Q20: 0 | R20: 0 | S20: 0 | T20: 0 | X20: =+B20 -> 平成8年度 | Y20: 0 | Z20: 0 | AA20: 0 | AB20: 0
B21: 平成9年度 | C21: =+Q21+Y21 -> 0 | D21: =+R21+Z21 -> 0 | E21: =+S21+AA21 -> 0 | F21: =+T21+AB21 -> 0 | G21: =ROUND(C21/C$48*G$48,0) -> 0 | H21: =C21-G21 -> 0 | I21: =+VLOOKUP($B21,年度別調書!$A$4:$M$37,10,0) -> 65491097789 | J21: =+VLOOKUP($B21,年度別調書!$A$4:$M$37,13,0) -> 112544371375 | K21: =IFERROR(ROUND(H21*I21/J21,0),0) -> 0 | L21: =H21-K21 -> 0 | M21: =ROUND(C21/C$48*G$48,3)-ROUND(C21/C$48*G$48,0) -> 0 | N21: =+海田!N21 -> 5 | P21: =+B21 -> 平成9年度 | Q21: 0 | R21: 0 | S21: 0 | T21: 0 | X21: =+B21 -> 平成9年度 | Y21: 0 | Z21: 0 | AA21: 0 | AB21: 0
B22: 平成10年度 | C22: =+Q22+Y22 -> 0 | D22: =+R22+Z22 -> 0 | E22: =+S22+AA22 -> 0 | F22: =+T22+AB22 -> 0 | G22: =ROUND(C22/C$48*G$48,0) -> 0 | H22: =C22-G22 -> 0 | I22: =+VLOOKUP($B22,年度別調書!$A$4:$M$37,10,0) -> 66701247191 | J22: =+VLOOKUP($B22,年度別調書!$A$4:$M$37,13,0) -> 118194473653 | K22: =IFERROR(ROUND(H22*I22/J22,0),0) -> 0 | L22: =H22-K22 -> 0 | M22: =ROUND(C22/C$48*G$48,3)-ROUND(C22/C$48*G$48,0) -> 0 | N22: =+海田!N22 -> 5 | P22: =+B22 -> 平成10年度 | Q22: 0 | R22: 0 | S22: 0 | T22: 0 | X22: =+B22 -> 平成10年度 | Y22: 0 | Z22: 0 | AA22: 0 | AB22: 0
B23: 平成11年度 | C23: =+Q23+Y23 -> 45699 | D23: =+R23+Z23 -> 4571 | E23: =+S23+AA23 -> 50270 | F23: =+T23+AB23 -> 5502 | G23: =ROUND(C23/C$48*G$48,0) -> 3947 | H23: =C23-G23 -> 41752 | I23: =+VLOOKUP($B23,年度別調書!$A$4:$M$37,10,0) -> 58274420372 | J23: =+VLOOKUP($B23,年度別調書!$A$4:$M$37,13,0) -> 110790062218 | K23: =IFERROR(ROUND(H23*I23/J23,0),0) -> 21961 | L23: =H23-K23 -> 19791 | M23: =ROUND(C23/C$48*G$48,3)-ROUND(C23/C$48*G$48,0) -> -0.32 | N23: =+海田!N23 -> 5 | P23: =+B23 -> 平成11年度 | Q23: 22738 | R23: 2397 | S23: 25135 | T23: 2751 | X23: =+B23 -> 平成11年度 | Y23: 22961 | Z23: 2174 | AA23: 25135 | AB23: 2751
B24: 平成12年度 | C24: =+Q24+Y24 -> 218603 | D24: =+R24+Z24 -> 24463 | E24: =+S24+AA24 -> 243066 | F24: =+T24+AB24 -> 27962 | G24: =ROUND(C24/C$48*G$48,0) -> 18879 | H24: =C24-G24 -> 199724 | I24: =+VLOOKUP($B24,年度別調書!$A$4:$M$37,10,0) -> 48353931386 | J24: =+VLOOKUP($B24,年度別調書!$A$4:$M$37,13,0) -> 104173607652 | K24: =IFERROR(ROUND(H24*I24/J24,0),0) -> 92705 | L24: =H24-K24 -> 107019 | M24: =ROUND(C24/C$48*G$48,3)-ROUND(C24/C$48*G$48,0) -> 0.1 | N24: =+海田!N24 -> 5 | P24: =+B24 -> 平成12年度 | Q24: 108818 | R24: 12715 | S24: 121533 | T24: 13981 | X24: =+B24 -> 平成12年度 | Y24: 109785 | Z24: 11748 | AA24: 121533 | AB24: 13981
B25: 平成13年度 | C25: =+Q25+Y25 -> 681954 | D25: =+R25+Z25 -> 99190 | E25: =+S25+AA25 -> 781144 | F25: =+T25+AB25 -> 91932 | G25: =ROUND(C25/C$48*G$48,0) -> 58895 | H25: =C25-G25 -> 623059 | I25: =+VLOOKUP($B25,年度別調書!$A$4:$M$37,10,0) -> 42742028940 | J25: =+VLOOKUP($B25,年度別調書!$A$4:$M$37,13,0) -> 101075943440 | K25: =IFERROR(ROUND(H25*I25/J25,0),0) -> 263473 | L25: =H25-K25 -> 359586 | M25: =ROUND(C25/C$48*G$48,3)-ROUND(C25/C$48*G$48,0) -> 0.247 | N25: =+海田!N25 -> 5 | P25: =+B25 -> 平成13年度 | Q25: 339314 | R25: 51258 | S25: 390572 | T25: 45966 | X25: =+B25 -> 平成13年度 | Y25: 342640 | Z25: 47932 | AA25: 390572 | AB25: 45966
B26: 平成14年度 | C26: =+Q26+Y26 -> 577988 | D26: =+R26+Z26 -> 105070 | E26: =+S26+AA26 -> 683058 | F26: =+T26+AB26 -> 77098 | G26: =ROUND(C26/C$48*G$48,0)+1 -> 49917 | H26: =C26-G26 -> 528071 | I26: =+VLOOKUP($B26,年度別調書!$A$4:$M$37,10,0) -> 38694694218 | J26: =+VLOOKUP($B26,年度別調書!$A$4:$M$37,13,0) -> 98151426478 | K26: =IFERROR(ROUND(H26*I26/J26,0),0) -> 208184 | L26: =H26-K26 -> 319887 | M26: =ROUND(C26/C$48*G$48,3)-ROUND(C26/C$48*G$48,0) -> 0.484 | N26: =+海田!N26 -> 5 | P26: =+B26 -> 平成14年度 | Q26: 287766 | R26: 53763 | S26: 341529 | T26: 38549 | X26: =+B26 -> 平成14年度 | Y26: 290222 | Z26: 51307 | AA26: 341529 | AB26: 38549
B27: 平成15年度 | C27: =+Q27+Y27 -> 52632 | D27: =+R27+Z27 -> 12944 | E27: =+S27+AA27 -> 65576 | F27: =+T27+AB27 -> 7360 | G27: =ROUND(C27/C$48*G$48,0) -> 4545 | H27: =C27-G27 -> 48087 | I27: =+VLOOKUP($B27,年度別調書!$A$4:$M$37,10,0) -> 37621895854 | J27: =+VLOOKUP($B27,年度別調書!$A$4:$M$37,13,0) -> 100825076572 | K27: =IFERROR(ROUND(H27*I27/J27,0),0) -> 17943 | L27: =H27-K27 -> 30144 | M27: =ROUND(C27/C$48*G$48,3)-ROUND(C27/C$48*G$48,0) -> 0.431 | N27: =+海田!N27 -> 5 | P27: =+B27 -> 平成15年度 | Q27: 26181 | R27: 6607 | S27: 32788 | T27: 3680 | X27: =+B27 -> 平成15年度 | Y27: 26451 | Z27: 6337 | AA27: 32788 | AB27: 3680
B28: 平成16年度 | C28: =+Q28+Y28 -> 376974 | D28: =+R28+Z28 -> 102776 | E28: =+S28+AA28 -> 479750 | F28: =+T28+AB28 -> 55480 | G28: =ROUND(C28/C$48*G$48,0) -> 32556 | H28: =C28-G28 -> 344418 | I28: =+VLOOKUP($B28,年度別調書!$A$4:$M$37,10,0) -> 29085465357 | J28: =+VLOOKUP($B28,年度別調書!$A$4:$M$37,13,0) -> 101305165124 | K28: =IFERROR(ROUND(H28*I28/J28,0),0) -> 98885 | L28: =H28-K28 -> 245533 | M28: =ROUND(C28/C$48*G$48,3)-ROUND(C28/C$48*G$48,0) -> 0.414 | N28: =+海田!N28 -> 5 | P28: =+B28 -> 平成16年度 | Q28: 187507 | R28: 52368 | S28: 239875 | T28: 27740 | X28: =+B28 -> 平成16年度 | Y28: 189467 | Z28: 50408 | AA28: 239875 | AB28: 27740
B29: 平成17年度 | C29: =+Q29+Y29 -> 0 | D29: =+R29+Z29 -> 0 | E29: =+S29+AA29 -> 0 | F29: =+T29+AB29 -> 0 | G29: =ROUND(C29/C$48*G$48,0) -> 0 | H29: =C29-G29 -> 0 | I29: =+VLOOKUP($B29,年度別調書!$A$4:$M$37,10,0) -> 25082997134 | J29: =+VLOOKUP($B29,年度別調書!$A$4:$M$37,13,0) -> 96528725584 | K29: =IFERROR(ROUND(H29*I29/J29,0),0) -> 0 | L29: =H29-K29 -> 0 | M29: =ROUND(C29/C$48*G$48,3)-ROUND(C29/C$48*G$48,0) -> 0 | N29: =+海田!N29 -> 5 | P29: =+B29 -> 平成17年度 | Q29: 0 | R29: 0 | S29: 0 | T29: 0 | X29: =+B29 -> 平成17年度 | Y29: 0 | Z29: 0 | AA29: 0 | AB29: 0
B30: 平成18年度 | C30: =+Q30+Y30 -> 0 | D30: =+R30+Z30 -> 0 | E30: =+S30+AA30 -> 0 | F30: =+T30+AB30 -> 0 | G30: =ROUND(C30/C$48*G$48,0) -> 0 | H30: =C30-G30 -> 0 | I30: =+VLOOKUP($B30,年度別調書!$A$4:$M$37,10,0) -> 21657707574 | J30: =+VLOOKUP($B30,年度別調書!$A$4:$M$37,13,0) -> 84768578867 | K30: =IFERROR(ROUND(H30*I30/J30,0),0) -> 0 | L30: =H30-K30 -> 0 | M30: =ROUND(C30/C$48*G$48,3)-ROUND(C30/C$48*G$48,0) -> 0 | N30: =+海田!N30 -> 5 | P30: =+B30 -> 平成18年度 | Q30: 0 | R30: 0 | S30: 0 | T30: 0 | X30: =+B30 -> 平成18年度 | Y30: 0 | Z30: 0 | AA30: 0 | AB30: 0
B31: 平成19年度 | C31: =+Q31+Y31 -> 0 | D31: =+R31+Z31 -> 0 | E31: =+S31+AA31 -> 0 | F31: =+T31+AB31 -> 0 | G31: =ROUND(C31/C$48*G$48,0) -> 0 | H31: =C31-G31 -> 0 | I31: =+VLOOKUP($B31,年度別調書!$A$4:$M$37,10,0) -> 25422571996 | J31: =+VLOOKUP($B31,年度別調書!$A$4:$M$37,13,0) -> 105576318079 | K31: =IFERROR(ROUND(H31*I31/J31,0),0) -> 0 | L31: =H31-K31 -> 0 | M31: =ROUND(C31/C$48*G$48,3)-ROUND(C31/C$48*G$48,0) -> 0 | N31: =+海田!N31 -> 5 | P31: =+B31 -> 平成19年度 | Q31: 0 | R31: 0 | S31: 0 | T31: 0 | X31: =+B31 -> 平成19年度 | Y31: 0 | Z31: 0 | AA31: 0 | AB31: 0
B32: 平成20年度 | C32: =+Q32+Y32 -> 0 | D32: =+R32+Z32 -> 0 | E32: =+S32+AA32 -> 0 | F32: =+T32+AB32 -> 0 | G32: =ROUND(C32/C$48*G$48,0) -> 0 | H32: =C32-G32 -> 0 | I32: =+VLOOKUP($B32,年度別調書!$A$4:$M$37,10,0) -> 24693835462 | J32: =+VLOOKUP($B32,年度別調書!$A$4:$M$37,13,0) -> 110401232854 | K32: =IFERROR(ROUND(H32*I32/J32,0),0) -> 0 | L32: =H32-K32 -> 0 | M32: =ROUND(C32/C$48*G$48,3)-ROUND(C32/C$48*G$48,0) -> 0 | N32: =+海田!N32 -> 5 | P32: =+B32 -> 平成20年度 | Q32: 0 | R32: 0 | S32: 0 | T32: 0 | X32: =+B32 -> 平成20年度 | Y32: 0 | Z32: 0 | AA32: 0 | AB32: 0
B33: 平成21年度 | C33: =+Q33+Y33 -> 0 | D33: =+R33+Z33 -> 0 | E33: =+S33+AA33 -> 0 | F33: =+T33+AB33 -> 0 | G33: =ROUND(C33/C$48*G$48,0) -> 0 | H33: =C33-G33 -> 0 | I33: =+VLOOKUP($B33,年度別調書!$A$4:$M$37,10,0) -> 22324372880 | J33: =+VLOOKUP($B33,年度別調書!$A$4:$M$37,13,0) -> 88097108350 | K33: =IFERROR(ROUND(H33*I33/J33,0),0) -> 0 | L33: =H33-K33 -> 0 | M33: =ROUND(C33/C$48*G$48,3)-ROUND(C33/C$48*G$48,0) -> 0 | N33: =+海田!N33 -> 5 | P33: =+B33 -> 平成21年度 | Q33: 0 | R33: 0 | S33: 0 | T33: 0 | X33: =+B33 -> 平成21年度 | Y33: 0 | Z33: 0 | AA33: 0 | AB33: 0
B34: 平成22年度 | C34: =+Q34+Y34 -> 0 | D34: =+R34+Z34 -> 0 | E34: =+S34+AA34 -> 0 | F34: =+T34+AB34 -> 0 | G34: =ROUND(C34/C$48*G$48,0) -> 0 | H34: =C34-G34 -> 0 | I34: =+VLOOKUP($B34,年度別調書!$A$4:$M$37,10,0) -> 26326163485 | J34: =+VLOOKUP($B34,年度別調書!$A$4:$M$37,13,0) -> 102723057143 | K34: =IFERROR(ROUND(H34*I34/J34,0),0) -> 0 | L34: =H34-K34 -> 0 | M34: =ROUND(C34/C$48*G$48,3)-ROUND(C34/C$48*G$48,0) -> 0 | N34: =+海田!N34 -> 5 | P34: =+B34 -> 平成22年度 | Q34: 0 | R34: 0 | S34: 0 | T34: 0 | X34: =+B34 -> 平成22年度 | Y34: 0 | Z34: 0 | AA34: 0 | AB34: 0
B35: 平成23年度 | C35: =+Q35+Y35 -> 0 | D35: =+R35+Z35 -> 0 | E35: =+S35+AA35 -> 0 | F35: =+T35+AB35 -> 0 | G35: =ROUND(C35/C$48*G$48,0) -> 0 | H35: =C35-G35 -> 0 | I35: =+VLOOKUP($B35,年度別調書!$A$4:$M$37,10,0) -> 26883440277 | J35: =+VLOOKUP($B35,年度別調書!$A$4:$M$37,13,0) -> 99758377045 | K35: =IFERROR(ROUND(H35*I35/J35,0),0) -> 0 | L35: =H35-K35 -> 0 | M35: =ROUND(C35/C$48*G$48,3)-ROUND(C35/C$48*G$48,0) -> 0 | N35: =+海田!N35 -> 5 | P35: =+B35 -> 平成23年度 | Q35: 0 | R35: 0 | S35: 0 | T35: 0 | X35: =+B35 -> 平成23年度 | Y35: 0 | Z35: 0 | AA35: 0 | AB35: 0
B36: 平成24年度 | C36: =+Q36+Y36 -> 0 | D36: =+R36+Z36 -> 0 | E36: =+S36+AA36 -> 0 | F36: =+T36+AB36 -> 0 | G36: =ROUND(C36/C$48*G$48,0) -> 0 | H36: =C36-G36 -> 0 | I36: =+VLOOKUP($B36,年度別調書!$A$4:$M$37,10,0) -> 20821234544 | J36: =+VLOOKUP($B36,年度別調書!$A$4:$M$37,13,0) -> 101115908424 | K36: =IFERROR(ROUND(H36*I36/J36,0),0) -> 0 | L36: =H36-K36 -> 0 | M36: =ROUND(C36/C$48*G$48,3)-ROUND(C36/C$48*G$48,0) -> 0 | N36: =+海田!N36 -> 5 | P36: =+B36 -> 平成24年度 | Q36: 0 | R36: 0 | S36: 0 | T36: 0 | X36: =+B36 -> 平成24年度 | Y36: 0 | Z36: 0 | AA36: 0 | AB36: 0
B37: 平成25年度 | C37: =+Q37+Y37 -> 0 | D37: =+R37+Z37 -> 0 | E37: =+S37+AA37 -> 0 | F37: =+T37+AB37 -> 0 | G37: =ROUND(C37/C$48*G$48,0) -> 0 | H37: =C37-G37 -> 0 | I37: =+VLOOKUP($B37,年度別調書!$A$4:$M$37,10,0) -> 22169870622 | J37: =+VLOOKUP($B37,年度別調書!$A$4:$M$37,13,0) -> 87897420767 | K37: =IFERROR(ROUND(H37*I37/J37,0),0) -> 0 | L37: =H37-K37 -> 0 | M37: =ROUND(C37/C$48*G$48,3)-ROUND(C37/C$48*G$48,0) -> 0 | N37: =+海田!N37 -> 5 | P37: =+B37 -> 平成25年度 | Q37: 0 | R37: 0 | S37: 0 | T37: 0 | X37: =+B37 -> 平成25年度 | Y37: 0 | Z37: 0 | AA37: 0 | AB37: 0
B38: 平成26年度 | C38: =+Q38+Y38 -> 0 | D38: =+R38+Z38 -> 0 | E38: =+S38+AA38 -> 0 | F38: =+T38+AB38 -> 0 | G38: =ROUND(C38/C$48*G$48,0) -> 0 | H38: =C38-G38 -> 0 | I38: =+VLOOKUP($B38,年度別調書!$A$4:$M$37,10,0) -> 20924492616 | J38: =+VLOOKUP($B38,年度別調書!$A$4:$M$37,13,0) -> 99556890040 | K38: =IFERROR(ROUND(H38*I38/J38,0),0) -> 0 | L38: =H38-K38 -> 0 | M38: =ROUND(C38/C$48*G$48,3)-ROUND(C38/C$48*G$48,0) -> 0 | N38: =+海田!N38 -> 8 | P38: =+B38 -> 平成26年度 | Q38: 0 | R38: 0 | S38: 0 | T38: 0 | X38: =+B38 -> 平成26年度 | Y38: 0 | Z38: 0 | AA38: 0 | AB38: 0
... B42: 平成30年度 | C42: =+Q42+Y42 -> 0 | D42: =+R42+Z42 -> 0 | E42: =+S42+AA42 -> 0 | F42: =+T42+AB42 -> 0 | G42: =ROUND(C42/C$48*G$48,0) -> 0 | H42: =C42-G42 -> 0 | I42: =+VLOOKUP($B42,年度別調書!$A$4:$M$37,10,0) -> 19871916207 | J42: =+VLOOKUP($B42,年度別調書!$A$4:$M$37,13,0) -> 98551757388 | K42: =IFERROR(ROUND(H42*I42/J42,0),0) -> 0 | L42: =H42-K42 -> 0 | M42: =ROUND(C42/C$48*G$48,3)-ROUND(C42/C$48*G$48,0) -> 0 | N42: =+海田!N42 -> 8 | P42: =+B42 -> 平成30年度 | Q42: 0 | R42: 0 | S42: 0 | T42: 0 | X42: =+B42 -> 平成30年度 | Y42: 0 | Z42: 0 | AA42: 0 | AB42: 0
B43: 令和元年度 | C43: =+Q43 -> 0 | D43: =+R43 -> 0 | E43: =+S43 -> 0 | F43: =+T43 -> 0 | G43: =ROUND(C43/C$48*G$48,0) -> 0 | H43: =C43-G43 -> 0 | I43: =+VLOOKUP($B43,年度別調書!$A$4:$M$37,10,0) -> 21889958229 | J43: =+VLOOKUP($B43,年度別調書!$A$4:$M$37,13,0) -> 101214576030 | K43: =IFERROR(ROUND(H43*I43/J43,0),0) -> 0 | L43: =H43-K43 -> 0 | M43: =ROUND(C43/C$48*G$48,3)-ROUND(C43/C$48*G$48,0) -> 0 | N43: =+海田!N43 -> 8 | P43: =+B43 -> 令和元年度 | Q43: 0 | R43: 0 | S43: 0 | T43: 0 | X43: =+B43 -> 令和元年度 | Y43: 0 | Z43: 0 | AA43: 0 | AB43: 0
C44: =+Y43 -> 0 | D44: =+Z43 -> 0 | E44: =+AA43 -> 0 | F44: =+AB43 -> 0 | G44: =ROUND(C44/C$48*G$48,0) -> 0 | H44: =C44-G44 -> 0 | I44: =+VLOOKUP($B43,年度別調書!$A$4:$M$37,10,0) -> 21889958229 | J44: =+VLOOKUP($B43,年度別調書!$A$4:$M$37,13,0) -> 101214576030 | K44: =IFERROR(ROUND(H44*I44/J44,0),0) -> 0 | L44: =H44-K44 -> 0 | M44: =ROUND(C44/C$48*G$48,3)-ROUND(C44/C$48*G$48,0) -> 0 | N44: =+海田!N44 -> 10
B45: 令和2年度 | C45: =+Q45+Y45 -> 0 | D45: =+R45+Z45 -> 0 | E45: =+S45+AA45 -> 0 | F45: =+T45+AB45 -> 0 | G45: =ROUND(C45/C$48*G$48,0) -> 0 | H45: =C45-G45 -> 0 | I45: =+VLOOKUP($B45,年度別調書!$A$4:$M$37,10,0) -> 25568719436 | J45: =+VLOOKUP($B45,年度別調書!$A$4:$M$37,13,0) -> 105092548853 | K45: =IFERROR(ROUND(H45*I45/J45,0),0) -> 0 | L45: =H45-K45 -> 0 | M45: =ROUND(C45/C$48*G$48,3)-ROUND(C45/C$48*G$48,0) -> 0 | N45: =+海田!N45 -> 10 | P45: =+B45 -> 令和2年度 | Q45: 0 | R45: 0 | S45: 0 | T45: 0 | X45: =+B45 -> 令和2年度 | Y45: 0 | Z45: 0 | AA45: 0 | AB45: 0
B46: 令和3年度 | C46: =+Q46+Y46 -> 0 | D46: =+R46+Z46 -> 0 | E46: =+S46+AA46 -> 0 | F46: =+T46+AB46 -> 0 | G46: =ROUND(C46/C$48*G$48,0) -> 0 | H46: =C46-G46 -> 0 | I46: =+VLOOKUP($B46,年度別調書!$A$4:$M$37,10,0) -> 25732995336 | J46: =+VLOOKUP($B46,年度別調書!$A$4:$M$37,13,0) -> 106246537477 | K46: =IFERROR(ROUND(H46*I46/J46,0),0) -> 0 | L46: =H46-K46 -> 0 | M46: =ROUND(C46/C$48*G$48,3)-ROUND(C46/C$48*G$48,0) -> 0 | N46: =+海田!N46 -> 10 | P46: =+B46 -> 令和3年度 | Q46: 0 | R46: 0 | S46: 0 | T46: 0 | X46: =+B46 -> 令和3年度 | Y46: 0 | Z46: 0 | AA46: 0 | AB46: 0
B47: 令和4年度 | C47: =+Q47+Y47 -> 0 | D47: =+R47+Z47 -> 0 | E47: =+S47+AA47 -> 0 | F47: =+T47+AB47 -> 0 | G47: =ROUND(C47/C$48*G$48,0) -> 0 | H47: =C47-G47 -> 0 | I47: =+VLOOKUP($B47,年度別調書!$A$4:$M$37,10,0) -> 22974897869 | J47: =+VLOOKUP($B47,年度別調書!$A$4:$M$37,13,0) -> 102361733085 | K47: =IFERROR(ROUND(H47*I47/J47,0),0) -> 0 | L47: =H47-K47 -> 0 | M47: =ROUND(C47/C$48*G$48,3)-ROUND(C47/C$48*G$48,0) -> 0 | N47: =+海田!N47 -> 10 | P47: =+B47 -> 令和4年度 | Q47: 0 | R47: 0 | S47: 0 | T47: 0 | X47: =+B47 -> 令和4年度 | Y47: 0 | Z47: 0 | AA47: 0 | AB47: 0
B48: 計 | C48: =SUM(C6:C47) -> 3466667 | D48: =SUM(D6:D47) -> 431255 | E48: =SUM(E6:E47) -> 3897922 | F48: =SUM(F6:F47) -> 343060 | G48: =+U48+AC48 -> 299390 | H48: =SUM(H6:H47) -> 3167277 | K48: =SUM(K6:K47) -> 1508275 | L48: =SUM(L6:L47) -> 1659002 | N48: =+海田!N48 -> 0 | P48: 計 | Q48: =SUM(Q6:Q47) -> 1721112 | R48: =SUM(R6:R47) -> 227849 | S48: =SUM(S6:S47) -> 1948961 | T48: =SUM(T6:T47) -> 171530 | U48: 148795 | X48: 計 | Y48: =SUM(Y6:Y47) -> 1745555 | Z48: =SUM(Z6:Z47) -> 203406 | AA48: =SUM(AA6:AA47) -> 1948961 | AB48: =SUM(AB6:AB47) -> 171530 | AC48: 150595
G49: =G48-SUM(G6:G47) -> 0
J50: 税率 | K50: 税率別特定収入
J51: 3 | K51: =+SUMIFS($K$4:$K$48,$N$4:$N$48,$J51) -> 805124
J52: 5 | K52: =+SUMIFS($K$4:$K$48,$N$4:$N$48,$J52) -> 703151
J53: 8 | K53: =+SUMIFS($K$4:$K$48,$N$4:$N$48,$J53) -> 0
J54: 10 | K54: =+SUMIFS($K$4:$K$48,$N$4:$N$48,$J54) -> 0
J55: 計 | K55: =SUM(K51:K54) -> 1508275
J56: チェック | K56: =+K48-K55 -> 0

Sheet 廿日市
A2: =+"令和"&MID(総括表!A2,3,1)&"年度決算 廿日市市" -> 令和５年度決算 廿日市市 | O2: =+A2 -> 令和５年度決算 廿日市市
A4: 区分 | B4: 年度 | C4: 起債償還額 | F4: 普通交付税 相当額 | G4: 元金分普通 交付税相当額 | H4: 元金償還 負担額 | I4: 課税支出額 | J4: 支出額合計 | K4: 特定収入 | L4: 特定収入 以外 | M4: 端数 調整 | N4: 税 率 | O4: 区分 | P4: 年度 | Q4: 起債償還額 | T4: 普通交付税 相当額 | U4: 元金分普通 交付税相当額 | W4: 区分 | X4: 年度 | Y4: 起債償還額 | AB4: 普通交付税 相当額 | AC4: 元金分普通 交付税相当額
C5: 元金 | D5: 利息 | E5: 合計 | Q5: 元金 | R5: 利息 | S5: 合計 | Y5: 元金 | Z5: 利息 | AA5: 合計
A6: 合 計 | B6: 昭和57年度 | C6: =+Q6+Y6 -> 0 | D6: =+R6+Z6 -> 0 | E6: =+S6+AA6 -> 0 | F6: =+T6+AB6 -> 0 | G6: =ROUND(C6/C$48*G$48,0) -> 0 | H6: =C6-G6 -> 0 | K6: 0 | L6: =H6-K6 -> 0 | M6: =ROUND(C6/C$48*G$48,3)-ROUND(C6/C$48*G$48,0) -> 0 | N6: =+海田!N6 -> 0 | O6: ９ 月 分 | P6: =+B6 -> 昭和57年度 | Q6: 0 | R6: 0 | S6: 0 | T6: 0 | W6: ３ 月 分 | X6: =+B6 -> 昭和57年度 | Y6: 0 | Z6: 0 | AA6: 0 | AB6: 0
B7: 昭和58年度 | C7: =+Q7+Y7 -> 0 | D7: =+R7+Z7 -> 0 | E7: =+S7+AA7 -> 0 | F7: =+T7+AB7 -> 0 | G7: =ROUND(C7/C$48*G$48,0) -> 0 | H7: =C7-G7 -> 0 | K7: 0 | L7: =H7-K7 -> 0 | M7: =ROUND(C7/C$48*G$48,3)-ROUND(C7/C$48*G$48,0) -> 0 | N7: =+海田!N7 -> 0 | P7: =+B7 -> 昭和58年度 | Q7: 0 | R7: 0 | S7: 0 | T7: 0 | X7: =+B7 -> 昭和58年度 | Y7: 0 | Z7: 0 | AA7: 0 | AB7: 0
B8: 昭和59年度 | C8: =+Q8+Y8 -> 0 | D8: =+R8+Z8 -> 0 | E8: =+S8+AA8 -> 0 | F8: =+T8+AB8 -> 0 | G8: =ROUND(C8/C$48*G$48,0) -> 0 | H8: =C8-G8 -> 0 | K8: 0 | L8: =H8-K8 -> 0 | M8: =ROUND(C8/C$48*G$48,3)-ROUND(C8/C$48*G$48,0) -> 0 | N8: =+海田!N8 -> 0 | P8: =+B8 -> 昭和59年度 | Q8: 0 | R8: 0 | S8: 0 | T8: 0 | X8: =+B8 -> 昭和59年度 | Y8: 0 | Z8: 0 | AA8: 0 | AB8: 0
B9: 昭和60年度 | C9: =+Q9+Y9 -> 0 | D9: =+R9+Z9 -> 0 | E9: =+S9+AA9 -> 0 | F9: =+T9+AB9 -> 0 | G9: =ROUND(C9/C$48*G$48,0) -> 0 | H9: =C9-G9 -> 0 | K9: 0 | L9: =H9-K9 -> 0 | M9: =ROUND(C9/C$48*G$48,3)-ROUND(C9/C$48*G$48,0) -> 0 | N9: =+海田!N9 -> 0 | P9: =+B9 -> 昭和60年度 | Q9: 0 | R9: 0 | S9: 0 | T9: 0 | X9: =+B9 -> 昭和60年度 | Y9: 0 | Z9: 0 | AA9: 0 | AB9: 0
B10: 昭和61年度 | C10: =+Q10+Y10 -> 0 | D10: =+R10+Z10 -> 0 | E10: =+S10+AA10 -> 0 | F10: =+T10+AB10 -> 0 | G10: =ROUND(C10/C$48*G$48,0) -> 0 | H10: =C10-G10 -> 0 | K10: 0 | L10: =H10-K10 -> 0 | M10: =ROUND(C10/C$48*G$48,3)-ROUND(C10/C$48*G$48,0) -> 0 | N10: =+海田!N10 -> 0 | P10: =+B10 -> 昭和61年度 | Q10: 0 | R10: 0 | S10: 0 | T10: 0 | X10: =+B10 -> 昭和61年度 | Y10: 0 | Z10: 0 | AA10: 0 | AB10: 0
B11: 昭和62年度 | C11: =+Q11+Y11 -> 0 | D11: =+R11+Z11 -> 0 | E11: =+S11+AA11 -> 0 | F11: =+T11+AB11 -> 0 | G11: =ROUND(C11/C$48*G$48,0) -> 0 | H11: =C11-G11 -> 0 | K11: 0 | L11: =H11-K11 -> 0 | M11: =ROUND(C11/C$48*G$48,3)-ROUND(C11/C$48*G$48,0) -> 0 | N11: =+海田!N11 -> 0 | P11: =+B11 -> 昭和62年度 | Q11: 0 | R11: 0 | S11: 0 | T11: 0 | X11: =+B11 -> 昭和62年度 | Y11: 0 | Z11: 0 | AA11: 0 | AB11: 0
B12: 昭和63年度 | C12: =+Q12+Y12 -> 0 | D12: =+R12+Z12 -> 0 | E12: =+S12+AA12 -> 0 | F12: =+T12+AB12 -> 0 | G12: =ROUND(C12/C$48*G$48,0) -> 0 | H12: =C12-G12 -> 0 | K12: 0 | L12: =H12-K12 -> 0 | M12: =ROUND(C12/C$48*G$48,3)-ROUND(C12/C$48*G$48,0) -> 0 | N12: =+海田!N12 -> 0 | P12: =+B12 -> 昭和63年度 | Q12: 0 | R12: 0 | S12: 0 | T12: 0 | X12: =+B12 -> 昭和63年度 | Y12: 0 | Z12: 0 | AA12: 0 | AB12: 0
B13: 平成元年度 | C13: =+Q13+Y13 -> 0 | D13: =+R13+Z13 -> 0 | E13: =+S13+AA13 -> 0 | F13: =+T13+AB13 -> 0 | G13: =ROUND(C13/C$48*G$48,0) -> 0 | H13: =C13-G13 -> 0 | I13: =+VLOOKUP($B13,年度別調書!$A$4:$M$37,10,0) -> 30622955900 | J13: =+VLOOKUP($B13,年度別調書!$A$4:$M$37,13,0) -> 62903610340 | K13: =IFERROR(ROUND(H13*I13/J13,0),0) -> 0 | L13: =H13-K13 -> 0 | M13: =ROUND(C13/C$48*G$48,3)-ROUND(C13/C$48*G$48,0) -> 0 | N13: =+海田!N13 -> 3 | P13: =+B13 -> 平成元年度 | Q13: 0 | R13: 0 | S13: 0 | T13: 0 | X13: =+B13 -> 平成元年度 | Y13: 0 | Z13: 0 | AA13: 0 | AB13: 0
B14: 平成2年度 | C14: =+Q14+Y14 -> 0 | D14: =+R14+Z14 -> 0 | E14: =+S14+AA14 -> 0 | F14: =+T14+AB14 -> 0 | G14: =ROUND(C14/C$48*G$48,0) -> 0 | H14: =C14-G14 -> 0 | I14: =+VLOOKUP($B14,年度別調書!$A$4:$M$37,10,0) -> 36785805618 | J14: =+VLOOKUP($B14,年度別調書!$A$4:$M$37,13,0) -> 65207626364 | K14: =IFERROR(ROUND(H14*I14/J14,0),0) -> 0 | L14: =H14-K14 -> 0 | M14: =ROUND(C14/C$48*G$48,3)-ROUND(C14/C$48*G$48,0) -> 0 | N14: =+海田!N14 -> 3 | P14: =+B14 -> 平成2年度 | Q14: 0 | R14: 0 | S14: 0 | T14: 0 | X14: =+B14 -> 平成2年度 | Y14: 0 | Z14: 0 | AA14: 0 | AB14: 0
B15: 平成3年度 | C15: =+Q15+Y15 -> 0 | D15: =+R15+Z15 -> 0 | E15: =+S15+AA15 -> 0 | F15: =+T15+AB15 -> 0 | G15: =ROUND(C15/C$48*G$48,0) -> 0 | H15: =C15-G15 -> 0 | I15: =+VLOOKUP($B15,年度別調書!$A$4:$M$37,10,0) -> 42048127236 | J15: =+VLOOKUP($B15,年度別調書!$A$4:$M$37,13,0) -> 72538415314 | K15: =IFERROR(ROUND(H15*I15/J15,0),0) -> 0 | L15: =H15-K15 -> 0 | M15: =ROUND(C15/C$48*G$48,3)-ROUND(C15/C$48*G$48,0) -> 0 | N15: =+海田!N15 -> 3 | P15: =+B15 -> 平成3年度 | Q15: 0 | R15: 0 | S15: 0 | T15: 0 | X15: =+B15 -> 平成3年度 | Y15: 0 | Z15: 0 | AA15: 0 | AB15: 0
B16: 平成4年度 | C16: =+Q16+Y16 -> 0 | D16: =+R16+Z16 -> 0 | E16: =+S16+AA16 -> 0 | F16: =+T16+AB16 -> 0 | G16: =ROUND(C16/C$48*G$48,0) -> 0 | H16: =C16-G16 -> 0 | I16: =+VLOOKUP($B16,年度別調書!$A$4:$M$37,10,0) -> 49320557603 | J16: =+VLOOKUP($B16,年度別調書!$A$4:$M$37,13,0) -> 82028053042 | K16: =IFERROR(ROUND(H16*I16/J16,0),0) -> 0 | L16: =H16-K16 -> 0 | M16: =ROUND(C16/C$48*G$48,3)-ROUND(C16/C$48*G$48,0) -> 0 | N16: =+海田!N16 -> 3 | P16: =+B16 -> 平成4年度 | Q16: 0 | R16: 0 | S16: 0 | T16: 0 | X16: =+B16 -> 平成4年度 | Y16: 0 | Z16: 0 | AA16: 0 | AB16: 0
B17: 平成5年度 | C17: =+Q17+Y17 -> 673163 | D17: =+R17+Z17 -> 35183 | E17: =+S17+AA17 -> 708346 | F17: =+T17+AB17 -> 33212 | G17: =ROUND(C17/C$48*G$48,0) -> 68925 | H17: =C17-G17 -> 604238 | I17: =+VLOOKUP($B17,年度別調書!$A$4:$M$37,10,0) -> 54853236126 | J17: =+VLOOKUP($B17,年度別調書!$A$4:$M$37,13,0) -> 94393962571 | K17: =IFERROR(ROUND(H17*I17/J17,0),0) -> 351128 | L17: =H17-K17 -> 253110 | M17: =ROUND(C17/C$48*G$48,3)-ROUND(C17/C$48*G$48,0) -> 0.099 | N17: =+海田!N17 -> 3 | P17: =+B17 -> 平成5年度 | Q17: 332890 | R17: 21283 | S17: 354173 | T17: 16606 | X17: =+B17 -> 平成5年度 | Y17: 340273 | Z17: 13900 | AA17: 354173 | AB17: 16606
B18: 平成6年度 | C18: =+Q18+Y18 -> 1331270 | D18: =+R18+Z18 -> 104968 | E18: =+S18+AA18 -> 1436238 | F18: =+T18+AB18 -> 40994 | G18: =ROUND(C18/C$48*G$48,0) -> 136309 | H18: =C18-G18 -> 1194961 | I18: =+VLOOKUP($B18,年度別調書!$A$4:$M$37,10,0) -> 52459905451 | J18: =+VLOOKUP($B18,年度別調書!$A$4:$M$37,13,0) -> 92179213936 | K18: =IFERROR(ROUND(H18*I18/J18,0),0) -> 680062 | L18: =H18-K18 -> 514899 | M18: =ROUND(C18/C$48*G$48,3)-ROUND(C18/C$48*G$48,0) -> -0.384 | N18: =+海田!N18 -> 3 | P18: =+B18 -> 平成6年度 | Q18: 659132 | R18: 58987 | S18: 718119 | T18: 20497 | X18: =+B18 -> 平成6年度 | Y18: 672138 | Z18: 45981 | AA18: 718119 | AB18: 20497
B19: 平成7年度 | C19: =+Q19+Y19 -> 2179034 | D19: =+R19+Z19 -> 115008 | E19: =+S19+AA19 -> 2294042 | F19: =+T19+AB19 -> 120794 | G19: =ROUND(C19/C$48*G$48,0) -> 223111 | H19: =C19-G19 -> 1955923 | I19: =+VLOOKUP($B19,年度別調書!$A$4:$M$37,10,0) -> 58579778590 | J19: =+VLOOKUP($B19,年度別調書!$A$4:$M$37,13,0) -> 98916143476 | K19: =IFERROR(ROUND(H19*I19/J19,0),0) -> 1158330 | L19: =H19-K19 -> 797593 | M19: =ROUND(C19/C$48*G$48,3)-ROUND(C19/C$48*G$48,0) -> 0.096 | N19: =+海田!N19 -> 3 | P19: =+B19 -> 平成7年度 | Q19: 1080780 | R19: 66241 | S19: 1147021 | T19: 60397 | X19: =+B19 -> 平成7年度 | Y19: 1098254 | Z19: 48767 | AA19: 1147021 | AB19: 60397
B20: 平成8年度 | C20: =+Q20+Y20 -> 4466077 | D20: =+R20+Z20 -> 351925 | E20: =+S20+AA20 -> 4818002 | F20: =+T20+AB20 -> 556798 | G20: =ROUND(C20/C$48*G$48,0) -> 457281 | H20: =C20-G20 -> 4008796 | I20: =+VLOOKUP($B20,年度別調書!$A$4:$M$37,10,0) -> 59855732510 | J20: =+VLOOKUP($B20,年度別調書!$A$4:$M$37,13,0) -> 105086070753 | K20: =IFERROR(ROUND(H20*I20/J20,0),0) -> 2283361 | L20: =H20-K20 -> 1725435 | M20: =ROUND(C20/C$48*G$48,3)-ROUND(C20/C$48*G$48,0) -> 0.224 | N20: =+海田!N20 -> 3 | P20: =+B20 -> 平成8年度 | Q20: 2218088 | R20: 190913 | S20: 2409001 | T20: 278399 | X20: =+B20 -> 平成8年度 | Y20: 2247989 | Z20: 161012 | AA20: 2409001 | AB20: 278399
B21: 平成9年度 | C21: =+Q21+Y21 -> 2091411 | D21: =+R21+Z21 -> 188991 | E21: =+S21+AA21 -> 2280402 | F21: =+T21+AB21 -> 243094 | G21: =ROUND(C21/C$48*G$48,0) -> 214139 | H21: =C21-G21 -> 1877272 | I21: =+VLOOKUP($B21,年度別調書!$A$4:$M$37,10,0) -> 65491097789 | J21: =+VLOOKUP($B21,年度別調書!$A$4:$M$37,13,0) -> 112544371375 | K21: =IFERROR(ROUND(H21*I21/J21,0),0) -> 1092410 | L21: =H21-K21 -> 784862 | M21: =ROUND(C21/C$48*G$48,3)-ROUND(C21/C$48*G$48,0) -> 0.385 | N21: =+海田!N21 -> 5 | P21: =+B21 -> 平成9年度 | Q21: 1040272 | R21: 99929 | S21: 1140201 | T21: 121547 | X21: =+B21 -> 平成9年度 | Y21: 1051139 | Z21: 89062 | AA21: 1140201 | AB21: 121547
B22: 平成10年度 | C22: =+Q22+Y22 -> 4497931 | D22: =+R22+Z22 -> 517831 | E22: =+S22+AA22 -> 5015762 | F22: =+T22+AB22 -> 549022 | G22: =ROUND(C22/C$48*G$48,0) -> 460543 | H22: =C22-G22 -> 4037388 | I22: =+VLOOKUP($B22,年度別調書!$A$4:$M$37,10,0) -> 66701247191 | J22: =+VLOOKUP($B22,年度別調書!$A$4:$M$37,13,0) -> 118194473653 | K22: =IFERROR(ROUND(H22*I22/J22,0),0) -> 2278438 | L22: =H22-K22 -> 1758950 | M22: =ROUND(C22/C$48*G$48,3)-ROUND(C22/C$48*G$48,0) -> -0.248 | N22: =+海田!N22 -> 5 | P22: =+B22 -> 平成10年度 | Q22: 2237367 | R22: 270514 | S22: 2507881 | T22: 274511 | X22: =+B22 -> 平成10年度 | Y22: 2260564 | Z22: 247317 | AA22: 2507881 | AB22: 274511
B23: 平成11年度 | C23: =+Q23+Y23 -> 6143259 | D23: =+R23+Z23 -> 614559 | E23: =+S23+AA23 -> 6757818 | F23: =+T23+AB23 -> 739682 | G23: =ROUND(C23/C$48*G$48,0) -> 629008 | H23: =C23-G23 -> 5514251 | I23: =+VLOOKUP($B23,年度別調書!$A$4:$M$37,10,0) -> 58274420372 | J23: =+VLOOKUP($B23,年度別調書!$A$4:$M$37,13,0) -> 110790062218 | K23: =IFERROR(ROUND(H23*I23/J23,0),0) -> 2900439 | L23: =H23-K23 -> 2613812 | M23: =ROUND(C23/C$48*G$48,3)-ROUND(C23/C$48*G$48,0) -> -0.262 | N23: =+海田!N23 -> 5 | P23: =+B23 -> 平成11年度 | Q23: 3056646 | R23: 322263 | S23: 3378909 | T23: 369841 | X23: =+B23 -> 平成11年度 | Y23: 3086613 | Z23: 292296 | AA23: 3378909 | AB23: 369841
B24: 平成12年度 | C24: =+Q24+Y24 -> 3862736 | D24: =+R24+Z24 -> 432266 | E24: =+S24+AA24 -> 4295002 | F24: =+T24+AB24 -> 494090 | G24: =ROUND(C24/C$48*G$48,0) -> 395505 | H24: =C24-G24 -> 3467231 | I24: =+VLOOKUP($B24,年度別調書!$A$4:$M$37,10,0) -> 48353931386 | J24: =+VLOOKUP($B24,年度別調書!$A$4:$M$37,13,0) -> 104173607652 | K24: =IFERROR(ROUND(H24*I24/J24,0),0) -> 1609374 | L24: =H24-K24 -> 1857857 | M24: =ROUND(C24/C$48*G$48,3)-ROUND(C24/C$48*G$48,0) -> 0.193 | N24: =+海田!N24 -> 5 | P24: =+B24 -> 平成12年度 | Q24: 1922821 | R24: 224680 | S24: 2147501 | T24: 247045 | X24: =+B24 -> 平成12年度 | Y24: 1939915 | Z24: 207586 | AA24: 2147501 | AB24: 247045
... B42: 平成30年度 | C42: =+Q42+Y42 -> 0 | D42: =+R42+Z42 -> 18490 | E42: =+S42+AA42 -> 18490 | F42: =+T42+AB42 -> 2075 | G42: =ROUND(C42/C$48*G$48,0) -> 0 | H42: =C42-G42 -> 0 | I42: =+VLOOKUP($B42,年度別調書!$A$4:$M$37,10,0) -> 19871916207 | J42: =+VLOOKUP($B42,年度別調書!$A$4:$M$37,13,0) -> 98551757388 | K42: =IFERROR(ROUND(H42*I42/J42,0),0) -> 0 | L42: =H42-K42 -> 0 | M42: =ROUND(C42/C$48*G$48,3)-ROUND(C42/C$48*G$48,0) -> 0 | N42: =+海田!N42 -> 8 | P42: =+B42 -> 平成30年度 | Q42: 0 | R42: 9247 | S42: 9247 | T42: 1038 | X42: =+B42 -> 平成30年度 | Y42: 0 | Z42: 9243 | AA42: 9243 | AB42: 1037
B43: 令和元年度 | C43: =+Q43 -> 0 | D43: =+R43 -> 32 | E43: =+S43 -> 32 | F43: =+T43 -> 4 | G43: =ROUND(C43/C$48*G$48,0) -> 0 | H43: =C43-G43 -> 0 | I43: =+VLOOKUP($B43,年度別調書!$A$4:$M$37,10,0) -> 21889958229 | J43: =+VLOOKUP($B43,年度別調書!$A$4:$M$37,13,0) -> 101214576030 | K43: =IFERROR(ROUND(H43*I43/J43,0),0) -> 0 | L43: =H43-K43 -> 0 | M43: =ROUND(C43/C$48*G$48,3)-ROUND(C43/C$48*G$48,0) -> 0 | N43: =+海田!N43 -> 8 | P43: =+B43 -> 令和元年度 | Q43: 0 | R43: 32 | S43: 32 | T43: 4 | X43: =+B43 -> 令和元年度 | Y43: 0 | Z43: 32 | AA43: 32 | AB43: 4
C44: =+Y43 -> 0 | D44: =+Z43 -> 32 | E44: =+AA43 -> 32 | F44: =+AB43 -> 4 | G44: =ROUND(C44/C$48*G$48,0) -> 0 | H44: =C44-G44 -> 0 | I44: =+VLOOKUP($B43,年度別調書!$A$4:$M$37,10,0) -> 21889958229 | J44: =+VLOOKUP($B43,年度別調書!$A$4:$M$37,13,0) -> 101214576030 | K44: =IFERROR(ROUND(H44*I44/J44,0),0) -> 0 | L44: =H44-K44 -> 0 | M44: =ROUND(C44/C$48*G$48,3)-ROUND(C44/C$48*G$48,0) -> 0 | N44: =+海田!N44 -> 10
B45: 令和2年度 | C45: =+Q45+Y45 -> 0 | D45: =+R45+Z45 -> 3444 | E45: =+S45+AA45 -> 3444 | F45: =+T45+AB45 -> 386 | G45: =ROUND(C45/C$48*G$48,0) -> 0 | H45: =C45-G45 -> 0 | I45: =+VLOOKUP($B45,年度別調書!$A$4:$M$37,10,0) -> 25568719436 | J45: =+VLOOKUP($B45,年度別調書!$A$4:$M$37,13,0) -> 105092548853 | K45: =IFERROR(ROUND(H45*I45/J45,0),0) -> 0 | L45: =H45-K45 -> 0 | M45: =ROUND(C45/C$48*G$48,3)-ROUND(C45/C$48*G$48,0) -> 0 | N45: =+海田!N45 -> 10 | P45: =+B45 -> 令和2年度 | Q45: 0 | R45: 1722 | S45: 1722 | T45: 193 | X45: =+B45 -> 令和2年度 | Y45: 0 | Z45: 1722 | AA45: 1722 | AB45: 193
B46: 令和3年度 | C46: =+Q46+Y46 -> 0 | D46: =+R46+Z46 -> 119 | E46: =+S46+AA46 -> 119 | F46: =+T46+AB46 -> 13 | G46: =ROUND(C46/C$48*G$48,0) -> 0 | H46: =C46-G46 -> 0 | I46: =+VLOOKUP($B46,年度別調書!$A$4:$M$37,10,0) -> 25732995336 | J46: =+VLOOKUP($B46,年度別調書!$A$4:$M$37,13,0) -> 106246537477 | K46: =IFERROR(ROUND(H46*I46/J46,0),0) -> 0 | L46: =H46-K46 -> 0 | M46: =ROUND(C46/C$48*G$48,3)-ROUND(C46/C$48*G$48,0) -> 0 | N46: =+海田!N46 -> 10 | P46: =+B46 -> 令和3年度 | Q46: 0 | R46: 55 | S46: 55 | T46: 6 | X46: =+B46 -> 令和3年度 | Y46: 0 | Z46: 64 | AA46: 64 | AB46: 7
B47: 令和4年度 | C47: =+Q47+Y47 -> 0 | D47: =+R47+Z47 -> 0 | E47: =+S47+AA47 -> 0 | F47: =+T47+AB47 -> 0 | G47: =ROUND(C47/C$48*G$48,0) -> 0 | H47: =C47-G47 -> 0 | I47: =+VLOOKUP($B47,年度別調書!$A$4:$M$37,10,0) -> 22974897869 | J47: =+VLOOKUP($B47,年度別調書!$A$4:$M$37,13,0) -> 102361733085 | K47: =IFERROR(ROUND(H47*I47/J47,0),0) -> 0 | L47: =H47-K47 -> 0 | M47: =ROUND(C47/C$48*G$48,3)-ROUND(C47/C$48*G$48,0) -> 0 | N47: =+海田!N47 -> 10 | P47: =+B47 -> 令和4年度 | Q47: 0 | R47: 0 | S47: 0 | T47: 0 | X47: =+B47 -> 令和4年度 | Y47: 0 | Z47: 0 | AA47: 0 | AB47: 0
B48: 計 | C48: =SUM(C6:C47) -> 30103640 | D48: =SUM(D6:D47) -> 3251254 | E48: =SUM(E6:E47) -> 33354894 | F48: =SUM(F6:F47) -> 3428259 | G48: =+U48+AC48 -> 3082309 | H48: =SUM(H6:H47) -> 27021331 | K48: =SUM(K6:K47) -> 13433518 | L48: =SUM(L6:L47) -> 13587813 | N48: =+海田!N48 -> 0 | P48: 計 | Q48: =SUM(Q6:Q47) -> 14971441 | R48: =SUM(R6:R47) -> 1706246 | S48: =SUM(S6:S47) -> 16677687 | T48: =SUM(T6:T47) -> 1714157 | U48: 1533460 | X48: 計 | Y48: =SUM(Y6:Y47) -> 15132199 | Z48: =SUM(Z6:Z47) -> 1545008 | AA48: =SUM(AA6:AA47) -> 16677207 | AB48: =SUM(AB6:AB47) -> 1714102 | AC48: 1548849
G49: =G48-SUM(G6:G47) -> 0
J50: 税率 | K50: 税率別特定収入
J51: 3 | K51: =+SUMIFS($K$4:$K$48,$N$4:$N$48,$J51) -> 4472881
J52: 5 | K52: =+SUMIFS($K$4:$K$48,$N$4:$N$48,$J52) -> 8304170
J53: 8 | K53: =+SUMIFS($K$4:$K$48,$N$4:$N$48,$J53) -> 656467
J54: 10 | K54: =+SUMIFS($K$4:$K$48,$N$4:$N$48,$J54) -> 0
J55: 計 | K55: =SUM(K51:K54) -> 13433518
J56: チェック | K56: =+K48-K55 -> 0

Sheet 年度別調書
A2: 区分 | C2: 収益的支出 | G2: 資本的支出 | K2: 合計 | N2: 課税支出割合
B3: 課税支出額 | C3: 非課税支出額 | D3: 不課税支出額 | E3: 支出額合計 | F3: 課税支出額 | G3: 非課税支出額 | H3: 不課税支出額 | I3: 支出額合計 | J3: 課税支出額 | K3: 非課税支出額 | L3: 不課税支出額 | M3: 支出額合計
A4: 平成元年度 | B4: 6638585275 | C4: 10574729590 | D4: 6518666458 | E4: =SUM(B4:D4) -> 23731981323 | F4: 23984370625 | G4: 1228439250 | H4: 13958819142 | I4: =SUM(F4:H4) -> 39171629017 | J4: =B4+F4 -> 30622955900 | K4: =C4+G4 -> 11803168840 | L4: =D4+H4 -> 20477485600 | M4: =SUM(J4:L4) -> 62903610340 | N4: =ROUND(J4/M4,5) -> 0.48682
A5: 平成2年度 | B5: 6403463162 | C5: 12958792633 | D5: 7298770586 | E5: =SUM(B5:D5) -> 26661026381 | F5: 30382342456 | G5: 1337020167 | H5: 6827237360 | I5: =SUM(F5:H5) -> 38546599983 | J5: =B5+F5 -> 36785805618 | K5: =C5+G5 -> 14295812800 | L5: =D5+H5 -> 14126007946 | M5: =SUM(J5:L5) -> 65207626364 | N5: =ROUND(J5/M5,5) -> 0.56413
A6: 平成3年度 | B6: 7812527889 | C6: 14204408305 | D6: 7783294580 | E6: =SUM(B6:D6) -> 29800230774 | F6: 34235599347 | G6: 1845675735 | H6: 6656909458 | I6: =SUM(F6:H6) -> 42738184540 | J6: =B6+F6 -> 42048127236 | K6: =C6+G6 -> 16050084040 | L6: =D6+H6 -> 14440204038 | M6: =SUM(J6:L6) -> 72538415314 | N6: =ROUND(J6/M6,5) -> 0.57967
A7: 平成4年度 | B7: 8434098941 | C7: 15065133280 | D7: 8082608376 | E7: =SUM(B7:D7) -> 31581840597 | F7: 40886458662 | G7: 1839055667 | H7: 7720698116 | I7: =SUM(F7:H7) -> 50446212445 | J7: =B7+F7 -> 49320557603 | K7: =C7+G7 -> 16904188947 | L7: =D7+H7 -> 15803306492 | M7: =SUM(J7:L7) -> 82028053042 | N7: =ROUND(J7/M7,5) -> 0.60126
A8: 平成5年度 | B8: 8086078175 | C8: 16243780470 | D8: 8575652485 | E8: =SUM(B8:D8) -> 32905511130 | F8: 46767157951 | G8: 2854358144 | H8: 11866935346 | I8: =SUM(F8:H8) -> 61488451441 | J8: =B8+F8 -> 54853236126 | K8: =C8+G8 -> 19098138614 | L8: =D8+H8 -> 20442587831 | M8: =SUM(J8:L8) -> 94393962571 | N8: =ROUND(J8/M8,5) -> 0.58111
A9: 平成6年度 | B9: 7946348657 | C9: 16788556844 | D9: 9253794488 | E9: =SUM(B9:D9) -> 33988699989 | F9: 44513556794 | G9: 2113094390 | H9: 11563862763 | I9: =SUM(F9:H9) -> 58190513947 | J9: =B9+F9 -> 52459905451 | K9: =C9+G9 -> 18901651234 | L9: =D9+H9 -> 20817657251 | M9: =SUM(J9:L9) -> 92179213936 | N9: =ROUND(J9/M9,5) -> 0.56911
A10: 平成7年度 | B10: 8326264681 | C10: 17860310884 | D10: 9862655702 | E10: =SUM(B10:D10) -> 36049231267 | F10: 50253513909 | G10: 1106253695 | H10: 11507144605 | I10: =SUM(F10:H10) -> 62866912209 | J10: =B10+F10 -> 58579778590 | K10: =C10+G10 -> 18966564579 | L10: =D10+H10 -> 21369800307 | M10: =SUM(J10:L10) -> 98916143476 | N10: =ROUND(J10/M10,5) -> 0.59222
A11: 平成8年度 | B11: 8021766260 | C11: 18240244702 | D11: 10520009874 | E11: =SUM(B11:D11) -> 36782020836 | F11: 51833966250 | G11: 2799760859 | H11: 13670322808 | I11: =SUM(F11:H11) -> 68304049917 | J11: =B11+F11 -> 59855732510 | K11: =C11+G11 -> 21040005561 | L11: =D11+H11 -> 24190332682 | M11: =SUM(J11:L11) -> 105086070753 | N11: =ROUND(J11/M11,5) -> 0.56959
A12: 平成9年度 | B12: 8482299126 | C12: 18816255593 | D12: 11078580135 | E12: =SUM(B12:D12) -> 38377134854 | F12: 57008798663 | G12: 1908240142 | H12: 15250197716 | I12: =SUM(F12:H12) -> 74167236521 | J12: =B12+F12 -> 65491097789 | K12: =C12+G12 -> 20724495735 | L12: =D12+H12 -> 26328777851 | M12: =SUM(J12:L12) -> 112544371375 | N12: =ROUND(J12/M12,5) -> 0.58191
A13: 平成10年度 | B13: 8513945841 | C13: 19139404817 | D13: 11758371498 | E13: =SUM(B13:D13) -> 39411722156 | F13: 58187301350 | G13: 4095079093 | H13: 16500371054 | I13: =SUM(F13:H13) -> 78782751497 | J13: =B13+F13 -> 66701247191 | K13: =C13+G13 -> 23234483910 | L13: =D13+H13 -> 28258742552 | M13: =SUM(J13:L13) -> 118194473653 | N13: =ROUND(J13/M13,5) -> 0.56433
A14: 平成11年度 | B14: 8587386343 | C14: 19356965458 | D14: 12810557993 | E14: =SUM(B14:D14) -> 40754909794 | F14: 49687034029 | G14: 2277303465 | H14: 18070814930 | I14: =SUM(F14:H14) -> 70035152424 | J14: =B14+F14 -> 58274420372 | K14: =C14+G14 -> 21634268923 | L14: =D14+H14 -> 30881372923 | M14: =SUM(J14:L14) -> 110790062218 | N14: =ROUND(J14/M14,5) -> 0.52599
A15: 平成12年度 | B15: 8003528492 | C15: 20335043030 | D15: 13616766355 | E15: =SUM(B15:D15) -> 41955337877 | F15: 40350402894 | G15: 2613187479 | H15: 19254679402 | I15: =SUM(F15:H15) -> 62218269775 | J15: =B15+F15 -> 48353931386 | K15: =C15+G15 -> 22948230509 | L15: =D15+H15 -> 32871445757 | M15: =SUM(J15:L15) -> 104173607652 | N15: =ROUND(J15/M15,5) -> 0.46417
... A23: 平成20年度 | B23: 6868439956 | C23: 15595713532 | D23: 17045198968 | E23: =SUM(B23:D23) -> 39509352456 | F23: 17825395506 | G23: 2414127859 | H23: 50652357033 | I23: =SUM(F23:H23) -> 70891880398 | J23: =B23+F23 -> 24693835462 | K23: =C23+G23 -> 18009841391 | L23: =D23+H23 -> 67697556001 | M23: =SUM(J23:L23) -> 110401232854 | N23: =ROUND(J23/M23,5) -> 0.22367
A24: 平成21年度 | B24: 6894436649 | C24: 14216013334 | D24: 17141070815 | E24: =SUM(B24:D24) -> 38251520798 | F24: 15429936231 | G24: 968394665 | H24: 33447256656 | I24: =SUM(F24:H24) -> 49845587552 | J24: =B24+F24 -> 22324372880 | K24: =C24+G24 -> 15184407999 | L24: =D24+H24 -> 50588327471 | M24: =SUM(J24:L24) -> 88097108350 | N24: =ROUND(J24/M24,5) -> 0.25341 | O24: 更正有り
A25: 平成22年度 | B25: 6759860353 | C25: 13658696637 | D25: 17705768744 | E25: =SUM(B25:D25) -> 38124325734 | F25: 19566303132 | G25: 300279386 | H25: 44732148891 | I25: =SUM(F25:H25) -> 64598731409 | J25: =B25+F25 -> 26326163485 | K25: =C25+G25 -> 13958976023 | L25: =D25+H25 -> 62437917635 | M25: =SUM(J25:L25) -> 102723057143 | N25: =ROUND(J25/M25,5) -> 0.25628
A26: 平成23年度 | B26: 7166401906 | C26: 12699860108 | D26: 17657302282 | E26: =SUM(B26:D26) -> 37523564296 | F26: 19717038371 | G26: 456886518 | H26: 42060887860 | I26: =SUM(F26:H26) -> 62234812749 | J26: =B26+F26 -> 26883440277 | K26: =C26+G26 -> 13156746626 | L26: =D26+H26 -> 59718190142 | M26: =SUM(J26:L26) -> 99758377045 | N26: =ROUND(J26/M26,5) -> 0.26949
A27: 平成24年度 | B27: 6887259886 | C27: 11839132984 | D27: 18167483572 | E27: =SUM(B27:D27) -> 36893876442 | F27: 13933974658 | G27: 395800992 | H27: 49892256332 | I27: =SUM(F27:H27) -> 64222031982 | J27: =B27+F27 -> 20821234544 | K27: =C27+G27 -> 12234933976 | L27: =D27+H27 -> 68059739904 | M27: =SUM(J27:L27) -> 101115908424 | N27: =ROUND(J27/M27,5) -> 0.20591
A28: 平成25年度 | B28: 6976860328 | C28: 10707772818 | D28: =17994183596+344000000 -> 18338183596 | E28: =SUM(B28:D28) -> 36022816742 | F28: 15193010294 | G28: 263334678 | H28: 36418259053 | I28: =SUM(F28:H28) -> 51874604025 | J28: =B28+F28 -> 22169870622 | K28: =C28+G28 -> 10971107496 | L28: =D28+H28 -> 54756442649 | M28: =SUM(J28:L28) -> 87897420767 | N28: =ROUND(J28/M28,5) -> 0.25222
