Workbook

Sheet (申)3%
B1: 消費税等計算チェックシート | AZ1: 単位：円
B2: チェック項目 | E2: 検証 | AZ2: 申告書等
B3: 課税標準等 | C3: 1 | D3: 行政手数料収入を課税売上にしていないか（一部のものを除き、非課税となる） | E3: 「その他営業収益」の「手数料」をチェック
C5: 2 | D5: 土地の貸付（原則非課税）のうち、契約期間が1か月未満の場合や、駐車場その他の施設の利用に伴って土地が使用される場合は課税としているか | E5: 「雑収益」の「その他雑収益」をチェック
C8: 3 | D8: 課税の対象となる対価補償金以外の補償金を課税売上にしていないか（水道管移設保証金、ガス管移設保証金等は不課税）
C11: 4 | D11: 損害賠償金を課税売上にしていないか（一般的には不課税）
C13: 5 | D13: 建物等固定資産（土地を除く）の売却について、差益部分のみを課税売上にしていないか | E13: 「固定資産売却益」及び「土地売却代金」をチェック
C15: 6 | D15: 車両等を購入した場合、下取り価額を課税売上にしていないか
C17: 7 | D17: 土地建物一括譲渡の場合、対価の額の区分は正しいか
C19: 8 | D19: 課税売上額の計算
E20: 収益的収入のうち課税売上（税込） | R20: =基礎数値!D3 -> 0 | Y20: ※ 「決算総括表」より
E21: 資本的収入のうち課税売上（税込） | R21: =基礎数値!D4 -> 0 | Y21: ※ 「決算総括表」より | AJ21: 計 | AK21: =R20+R21 -> 0 | AQ21: A
E23: 課税売上から控除するもの
H24: 仕入対価の返還等の額 | R24: =基礎数値!D6 -> 0 | X24: B | Y24: ※ 「過年度損益修正益」「その他特別利益」のうち、課税支出が返還されたもの
H25: 売上対価の返還等の額 | R25: =基礎数値!D7 -> 0 | X25: C | Y25: ※ 「過年度損益修正損」「その他特別損失」のうち、課税収入を返還したもの
E27: 課税売上額（税抜） | R27: =ROUNDDOWN((AK21-R24-R25)*100/103,0) -> 0 | X27: D | Y27: ※ （A－B－C）×100/103 | AZ27: 付表２①
E29: 課税標準額（税抜） | R29: =ROUNDDOWN((AK21-R24)*100/103,-3) -> 0 | X29: E | Y29: ※ （A－B）×100/103 1,000円未満切捨 | AZ29: 付表１①
E31: 課税標準額に対する消費税額 | R31: =ROUNDDOWN(R29*3/100,0) -> 0 | X31: F | Y31: ※ E×3% | AZ31: 付表１②
B33: 課税売上割合 | C33: 1 | D33: 課税売上割合の計算
E34: 課税売上額
E35: 免税売上額
E36: 課税資産の譲渡等の対価の額
E38: 収益的収入のうち非課税売上（税込）
E39: 資本的収入のうち非課税売上（税込）
E40: 資産の譲渡等の対価の額
E42: 課税売上割合
B44: 課税仕入れ | C44: 1 | D44: 土地の借受（原則非課税）のうち、契約期間が1か月未満の場合や、駐車場その他の施設の利用に伴って土地を使用する場合は課税としているか | E44: 賃借料をチェック
C47: 2 | D47: 課税の対象となる対価補償金以外の補償金を課税仕入れにしていないか（水道管移設保証金、ガス管移設保証金等は不課税） | E47: 保証金をチェック
C50: 3 | D50: 損害賠償金を課税仕入れにしていないか（一般的には不課税）
C52: 4 | D52: 免税・非課税・不課税仕入れを課税仕入れにしていないか | E52: 各費目をチェック
C54: 5 | D54: 資産の譲渡損を課税仕入れにしていないか | E54: 固定資産売却損をチェック
C56: 6 | D56: 経過措置対象取引（3%取引）がある場合、課税仕入れを3%取引と4%取引に区分して計算しているか | E56: 該当なし
C58: 7 | D58: 課税仕入れ等の税額の計算
E59: 収益的支出のうち課税支出（税込） | R59: =基礎数値!D11 -> 0 | Y59: ※ 「決算総括表」より
E60: 資本的支出のうち課税支出（税込） | R60: =基礎数値!D12 -> 0 | Y60: ※ 「決算総括表」より | AJ60: 計 | AK60: =R59+R60 -> 0 | AQ60: K
E64: 課税仕入れから控除するもの
H65: 返還等対価・貸倒れの額 | R65: =基礎数値!D14 -> 0 | X65: L | Y65: ※ 「過年度損益修正損」「その他特別損失」の課税支出うち、該当分
H66: 仕入対価の返還等の額 | R66: =R24 -> 0 | Y66: ※ Bの額
E68: 課税仕入れに係る支払対価の額（税込） | T68: =AK60-R65-R66 -> 0 | AA68: ※ K-L-B | AZ68: 付表２⑧
E70: 課税仕入れに係る消費税額 | T70: =ROUNDDOWN((AK60-R65-R66)*3/103,0) -> 0 | Z70: M | AA70: ※ （K-L-B）×3/103 ＜付表２の注３による計算＞ | AZ70: 付表２⑨⑫
B72: 特定収入の 判定 | C72: 1 | D72: 通常の借入金（地方債の起債収入等）を特定収入にしていないか | E72: 「企業債」をチェック
C74: 2 | D74: 一般会計繰入金であっても、地方公営企業法適用企業が受け入れる出資金は特定収入から除かれる。出資金を特定収入にしていないか | E74: 「一般会計出資金」をチェック
C77: 3 | D77: 通常の借入金の元金返済のために一般会計から繰入金等があった場合、特定収入の判定（借入金で賄った事業のために使用されたとして使途を特定）をしているか | E77: 該当なし
C81: 4 | D81: 補助金等の一部を翌期に繰り越した場合、収入のあった課税期間で特定収入の調整（支出金額の割合により按分）を行っているか | E81: 「国庫補助金」をチェック
C84: 5 | D84: 還付加算金について、特定収入の判定をしているか
B87: 仕入税額控除 の調整 | C87: 1 | D87: 特定収入割合の計算
E88: 収益的支出のうち特定収入 | P88: =基礎数値!D18 -> 0 | W88: ※ 「決算総括表」の「不課税収入」のうち「課税仕入に特定」
E89: 資本的支出のうち特定収入 | P89: =基礎数値!D19 -> 0 | W89: ※ 「決算総括表」の「不課税収入」のうち「課税仕入に特定」 | AR89: 計 | AS89: =P88+P89 -> 0 | AY89: N
E91: 課税売上額（税抜） | P91: =ROUNDDOWN(AK21*100/103,0) -> 0 | W91: ※ A×100/103
E92: 免税売上額
E93: 非課税売上額
E95: 特定収入割合
C97: 2 | D97: 仕入税額控除の計算 | AZ97: 付表２⑰ 計算表５①
E98: 一括比例配分方式により控除する課税仕入れ等の税額 | Z98: =ROUNDDOWN(T70*'(申)計'!R36/'(申)計'!R40,0) -> 0 | AF98: O | AG98: ※ M×合計のH/合計のJ
U99: （調整前）
E100: 課税仕入れに係る特定収入 | Z100: =AS89 -> 0 | AG100: ※ Nの額 | AZ100: 計算表５②
E101: 課税仕入れに係る特定収入×4/105 | Z101: =ROUNDDOWN(Z100*4/105,0) -> 0 | AF101: P | AG101: ※ N×4/105 | AZ101: 計算表５③
E103: 課税売上割合 | Z103: ='(申)計'!R36 -> 18871966907 | AG103: Q | AH103: ※ 合計のHの額 | AZ103: 計算表５⑥
Z106: ='(申)計'!R40 -> 18940559860 | AH106: ※ 合計のJの額
E108: 特定収入に係る課税仕入れの税額 | Z108: =ROUNDDOWN(Z101*Z103/Z106,0) -> 0 | AF108: R | AG108: ※ P×Q | AZ108: 計算表５⑦
E110: 使途不特定の特定収入
F111: 課税仕入れ等の税額－特定収入に係る課税仕入れ等の税額 | AC111: =Z98-Z108 -> 0 | AI111: S | AJ111: ※ O－R | AZ111: 計算表５⑧
F113: 調整割合 | AA113: ='(申)計'!AA113 -> 0 | AH113: T | AI113: ※ 合計を参照 | AZ113: 計算表５⑨
AA116: ='(申)計'!AA116 -> 18950268779
F118: 使途不特定の特定収入の税額 | AA118: =ROUNDDOWN(AC111*AA113/AA116,0) -> 0 | AG118: U | AH118: ※ S×T | AZ118: 計算表５⑩
E120: 特定収入に係る課税仕入れ等の税額 | Z120: =Z108+AA118 -> 0 | AF120: V | AG120: ※ R＋U | AZ120: 計算表５⑪
AZ121: 計算表５⑫ 付表２⑳ 付表１④
E122: 控除対象仕入税額 | Z122: =Z98-Z120 -> 0 | AF122: W | AG122: ※ O－V
B131: 納税額等の 計算 | C131: 1 | D131: 控除税額の計算
E132: 控除税額 | J132: 控除対象仕入税額 | T132: =Z122 -> 0 | AA132: ※ Wの額
J134: 返還等対価に係る税額 | T134: =ROUNDDOWN(R25*3/103,0) -> 0 | Z134: X | AA134: ※ C×3/103 | AZ134: 付表１⑤
J136: 貸倒れに係る金額（税込） | T136: =基礎数値!D17 -> 0 | Z136: Y. | AA136: ※ 特別損失の課税支出のうち、時効欠損分
J137: 貸倒れに係る税額 | T137: =ROUNDDOWN(T136*3/103,0) -> 0 | Z137: Z | AA137: ※ Y×3/103 | AZ137: 付表１⑥
J139: 控除税額 計 | T139: =T132+T134+T137 -> 0 | Z139: AA | AB139: ※ W＋X＋Z | AZ139: 付表１⑦
C141: 2 | D141: 消費税の納付税額の計算
E142: 消費税額 | T142: =R31 -> 0 | AB142: ※ Fの額
E143: 控除税額 | T143: =T139 -> 0 | AB143: ※ AAの額
E144: 差引税額 | T144: =ROUNDDOWN(T142-T143,-2) -> 0 | Z144: AB | AB144: ※ F－AA （100円未満切捨て） | AZ144: 付表１⑨
C150: 3 | D150: 地方消費税の税額の計算
E151: 地方消費税の課税標準となる税額 | T151: =T144 -> 0 | AB151: ※ ABの額
E152: 納税額 | T152: =ROUNDDOWN(T151*0/100,-2) -> 0 | Z152: AE | AB152: ※ AB×0/100 （100円未満切捨て） | AZ152: 付表１⑮
C158: 4 | D158: 消費税及び地方消費税の合計納付税額

Sheet (申)5%
B1: 消費税等計算チェックシート | AZ1: 単位：円
B2: チェック項目 | E2: 検証 | AZ2: 申告書等
B3: 課税標準等 | C3: 1 | D3: 行政手数料収入を課税売上にしていないか（一部のものを除き、非課税となる） | E3: 「その他営業収益」の「手数料」をチェック
C5: 2 | D5: 土地の貸付（原則非課税）のうち、契約期間が1か月未満の場合や、駐車場その他の施設の利用に伴って土地が使用される場合は課税としているか | E5: 「雑収益」の「その他雑収益」をチェック
C8: 3 | D8: 課税の対象となる対価補償金以外の補償金を課税売上にしていないか（水道管移設保証金、ガス管移設保証金等は不課税）
C11: 4 | D11: 損害賠償金を課税売上にしていないか（一般的には不課税）
C13: 5 | D13: 建物等固定資産（土地を除く）の売却について、差益部分のみを課税売上にしていないか | E13: 「固定資産売却益」及び「土地売却代金」をチェック
C15: 6 | D15: 車両等を購入した場合、下取り価額を課税売上にしていないか
C17: 7 | D17: 土地建物一括譲渡の場合、対価の額の区分は正しいか
C19: 8 | D19: 課税売上額の計算
E20: 収益的収入のうち課税売上（税込） | R20: =基礎数値!E3 -> 0 | Y20: ※ 「決算総括表」より
E21: 資本的収入のうち課税売上（税込） | R21: =基礎数値!E4 -> 0 | Y21: ※ 「決算総括表」より | AJ21: 計 | AK21: =R20+R21 -> 0 | AQ21: A
E23: 課税売上から控除するもの
H24: 仕入対価の返還等の額 | R24: =基礎数値!E6 -> 0 | X24: B | Y24: ※ 「過年度損益修正益」「その他特別利益」のうち、課税支出が返還されたもの
H25: 売上対価の返還等の額 | R25: =基礎数値!E7 -> 0 | X25: C | Y25: ※ 「過年度損益修正損」「その他特別損失」のうち、課税収入を返還したもの
E27: 課税売上額（税抜） | R27: =ROUNDDOWN((AK21-R24-R25)*100/105,0) -> 0 | X27: D | Y27: ※ （A－B－C）×100/105 | AZ27: 付表２①
E29: 課税標準額（税抜） | R29: =ROUNDDOWN((AK21-R24)*100/105,-3) -> 0 | X29: E | Y29: ※ （A－B）×100/105 1,000円未満切捨 | AZ29: 付表１①
E31: 課税標準額に対する消費税額 | R31: =ROUNDDOWN(R29*4/100,0) -> 0 | X31: F | Y31: ※ E×4% | AZ31: 付表１②
B33: 課税売上割合 | C33: 1 | D33: 課税売上割合の計算
E34: 課税売上額
E35: 免税売上額
E36: 課税資産の譲渡等の対価の額
E38: 収益的収入のうち非課税売上（税込）
E39: 資本的収入のうち非課税売上（税込）
E40: 資産の譲渡等の対価の額
E42: 課税売上割合
B44: 課税仕入れ | C44: 1 | D44: 土地の借受（原則非課税）のうち、契約期間が1か月未満の場合や、駐車場その他の施設の利用に伴って土地を使用する場合は課税としているか | E44: 賃借料をチェック
C47: 2 | D47: 課税の対象となる対価補償金以外の補償金を課税仕入れにしていないか（水道管移設保証金、ガス管移設保証金等は不課税） | E47: 保証金をチェック
C50: 3 | D50: 損害賠償金を課税仕入れにしていないか（一般的には不課税）
C52: 4 | D52: 免税・非課税・不課税仕入れを課税仕入れにしていないか | E52: 各費目をチェック
C54: 5 | D54: 資産の譲渡損を課税仕入れにしていないか | E54: 固定資産売却損をチェック
C56: 6 | D56: 経過措置対象取引（3%取引）がある場合、課税仕入れを3%取引と4%取引に区分して計算しているか | E56: 該当なし
C58: 7 | D58: 課税仕入れ等の税額の計算
E59: 収益的支出のうち課税支出（税込） | R59: =基礎数値!E11 -> 1120996 | Y59: ※ 「決算総括表」より
E60: 資本的支出のうち課税支出（税込） | R60: =基礎数値!E12 -> 0 | Y60: ※ 「決算総括表」より | AJ60: 計 | AK60: =R59+R60 -> 1120996 | AQ60: K
E64: 課税仕入れから控除するもの
H65: 返還等対価・貸倒れの額 | R65: =基礎数値!E14 -> 1120996 | X65: L | Y65: ※ 「過年度損益修正損」「その他特別損失」の課税支出うち、該当分
H66: 仕入対価の返還等の額 | R66: =R24 -> 0 | Y66: ※ Bの額
E68: 課税仕入れに係る支払対価の額（税込） | T68: =AK60-R65-R66 -> 0 | AA68: ※ K-L-B | AZ68: 付表２⑨
E70: 課税仕入れに係る消費税額 | T70: =ROUNDDOWN((AK60-R65-R66)*4/105,0) -> 0 | Z70: M | AA70: ※ （K-L-B）×4/105 ＜付表２の注３による計算＞ | AZ70: 付表２⑩⑮
B72: 特定収入の 判定 | C72: 1 | D72: 通常の借入金（地方債の起債収入等）を特定収入にしていないか | E72: 「企業債」をチェック
C74: 2 | D74: 一般会計繰入金であっても、地方公営企業法適用企業が受け入れる出資金は特定収入から除かれる。出資金を特定収入にしていないか | E74: 「一般会計出資金」をチェック
C77: 3 | D77: 通常の借入金の元金返済のために一般会計から繰入金等があった場合、特定収入の判定（借入金で賄った事業のために使用されたとして使途を特定）をしているか | E77: 該当なし
C81: 4 | D81: 補助金等の一部を翌期に繰り越した場合、収入のあった課税期間で特定収入の調整（支出金額の割合により按分）を行っているか | E81: 「国庫補助金」をチェック
C84: 5 | D84: 還付加算金について、特定収入の判定をしているか
B87: 仕入税額控除 の調整 | C87: 1 | D87: 特定収入割合の計算
E88: 収益的支出のうち特定収入 | P88: =基礎数値!E18 -> 0 | W88: ※ 「決算総括表」の「不課税収入」のうち「課税仕入に特定」
E89: 資本的支出のうち特定収入 | P89: =基礎数値!E19 -> 131982078 | W89: ※ 「決算総括表」の「不課税収入」のうち「課税仕入に特定」 | AR89: 計 | AS89: =P88+P89 -> 131982078 | AY89: N
E91: 課税売上額（税抜） | P91: =ROUNDDOWN(AK21*100/105,0) -> 0 | W91: ※ A×100/105
E92: 免税売上額
E93: 非課税売上額
E95: 特定収入割合
C97: 2 | D97: 仕入税額控除の計算 | AZ97: 付表２⑳
E98: 一括比例配分方式により控除する課税仕入れ等の税額 | Z98: =ROUNDDOWN(T70*'(申)計'!R36/'(申)計'!R40,0) -> 0 | AF98: O | AG98: ※ M×合計のH/合計のJ | AZ98: 計算表５①
U99: （調整前）
E100: 課税仕入れに係る特定収入 | Z100: =AS89 -> 131982078 | AG100: ※ Nの額 | AZ100: 計算表５②
E101: 課税仕入れに係る特定収入×4/105 | Z101: =ROUNDDOWN(Z100*4/105,0) -> 5027888 | AF101: P | AG101: ※ N×4/105 | AZ101: 計算表５③
E103: 課税売上割合 | Z103: ='(申)計'!R36 -> 18871966907 | AG103: Q | AH103: ※ 合計のHの額 | AZ103: 計算表５⑩
Z106: ='(申)計'!R40 -> 18940559860 | AH106: ※ 合計のJの額
E108: 特定収入に係る課税仕入れの税額 | Z108: =ROUNDDOWN(Z101*Z103/Z106,0) -> 5009679 | AF108: R | AG108: ※ P×Q | AZ108: 計算表５⑮
E110: 使途不特定の特定収入
F111: 課税仕入れ等の税額－特定収入に係る課税仕入れ等の税額 | AC111: =Z98-Z108 -> -5009679 | AI111: S | AJ111: ※ O－R | AZ111: 計算表５⑫
F113: 調整割合 | AA113: ='(申)計'!AA113 -> 0 | AH113: T | AI113: ※ 合計を参照 | AZ113: 計算表５⑬
AA116: ='(申)計'!AA116 -> 18950268779
F118: 使途不特定の特定収入の税額 | AA118: =ROUNDDOWN(AC111*AA113/AA116,0) -> 0 | AG118: U | AH118: ※ S×T | AZ118: 計算表５⑭
AZ119: 付表２㉑
E120: 特定収入に係る課税仕入れ等の税額 | Z120: =Z108+AA118 -> 5009679 | AF120: V | AG120: ※ R＋U | AZ120: 計算表５⑮
AZ121: 計算表５⑯
E122: 控除対象仕入税額 | Z122: =Z98-Z120 -> -5009679 | AF122: W | AG122: ※ O－V | AZ122: 付表２㉔or㉕
AZ123: 付表１③or④
B131: 納税額等の 計算 | C131: 1 | D131: 控除税額の計算
E132: 控除税額 | J132: 控除対象仕入税額 | T132: =IF(0>Z122,0,Z122) -> 0 | AA132: ※ Wの額 | AZ132: Wが△の時は
AZ133: 0
J134: 返還等対価に係る税額 | T134: =ROUNDDOWN(R25*4/105,0) -> 0 | Z134: X | AA134: ※ C×4/105 | AZ134: 付表１⑤
J136: 貸倒れに係る金額（税込） | T136: =基礎数値!E17 -> 1120996 | Z136: Y. | AA136: ※ 特別損失の課税支出のうち、時効欠損分
J137: 貸倒れに係る税額 | T137: =ROUNDDOWN(T136*4/105,0) -> 42704 | Z137: Z | AA137: ※ Y×4/105 | AZ137: 付表１⑥
J139: 控除税額 計 | T139: =T132+T134+T137 -> 42704 | Z139: AA | AB139: ※ W＋X＋Z | AZ139: 付表１⑦
C141: 2 | D141: 消費税の納付税額の計算
E142: 消費税額 | T142: =R31 -> 0 | AB142: ※ Fの額
E143: 控除税額 | T143: =T139 -> 42704 | AB143: ※ AAの額
E144: 差引税額 | T144: =ROUNDDOWN(Z120-T143,0) -> 4966975 | Z144: AB | AB144: ※ F－AA | AZ144: 付表１⑧or⑨
C150: 3 | D150: 地方消費税の税額の計算
E151: 地方消費税の課税標準となる税額 | T151: =T144 -> 4966975 | AB151: ※ ABの額
E152: 納税額 | T152: =ROUNDDOWN(T151*25/100,0) -> 1241743 | Z152: AE | AB152: ※ AB×25/100 | AZ152: 付表１⑭or⑮
C158: 4 | D158: 消費税及び地方消費税の合計納付税額

Sheet (申)8%
B1: 消費税等計算チェックシート | AZ1: 単位：円
B2: チェック項目 | E2: 検証 | AZ2: 申告書等
B3: 課税標準等 | C3: 1 | D3: 行政手数料収入を課税売上にしていないか（一部のものを除き、非課税となる） | E3: 「その他営業収益」の「手数料」をチェック
C5: 2 | D5: 土地の貸付（原則非課税）のうち、契約期間が1か月未満の場合や、駐車場その他の施設の利用に伴って土地が使用される場合は課税としているか | E5: 「雑収益」の「その他雑収益」をチェック
C8: 3 | D8: 課税の対象となる対価補償金以外の補償金を課税売上にしていないか（水道管移設保証金、ガス管移設保証金等は不課税）
C11: 4 | D11: 損害賠償金を課税売上にしていないか（一般的には不課税）
C13: 5 | D13: 建物等固定資産（土地を除く）の売却について、差益部分のみを課税売上にしていないか | E13: 「固定資産売却益」及び「土地売却代金」をチェック
C15: 6 | D15: 車両等を購入した場合、下取り価額を課税売上にしていないか
C17: 7 | D17: 土地建物一括譲渡の場合、対価の額の区分は正しいか
C19: 8 | D19: 課税売上額の計算
E20: 収益的収入のうち課税売上（税込） | R20: =基礎数値!F3 -> 47053 | Y20: ※ 「決算総括表」より
E21: 資本的収入のうち課税売上（税込） | R21: =基礎数値!F4 -> 0 | Y21: ※ 「決算総括表」より | AJ21: 計 | AK21: =R20+R21 -> 47053 | AQ21: A
E23: 課税売上から控除するもの
H24: 仕入対価の返還等の額 | R24: =基礎数値!F6 -> 0 | X24: B | Y24: ※ 「過年度損益修正益」「その他特別利益」のうち、課税支出が返還されたもの
H25: 売上対価の返還等の額 | R25: =基礎数値!F7 -> 39339 | X25: C | Y25: ※ 「過年度損益修正損」「その他特別損失」のうち、課税収入を返還したもの
E27: 課税売上額（税抜） | R27: =ROUNDDOWN((AK21-R24-R25)*100/108,0) -> 7142 | X27: D | Y27: ※ （A－B－C）×100/108 | AZ27: 付表２①
E29: 課税標準額（税抜） | R29: =ROUNDDOWN((AK21-R24)*100/108,-3) -> 43000 | X29: E | Y29: ※ （A－B）×100/108 1,000円未満切捨 | AZ29: 付表１①
E31: 課税標準額に対する消費税額 | R31: =ROUNDDOWN(R29*63/1000,0) -> 2709 | X31: F | Y31: ※ E×6.3% | AZ31: 付表１②
B33: 課税売上割合 | C33: 1 | D33: 課税売上割合の計算
E34: 課税売上額
E35: 免税売上額
E36: 課税資産の譲渡等の対価の額
E38: 収益的収入のうち非課税売上（税込）
E39: 資本的収入のうち非課税売上（税込）
E40: 資産の譲渡等の対価の額
E42: 課税売上割合
B44: 課税仕入れ | C44: 1 | D44: 土地の借受（原則非課税）のうち、契約期間が1か月未満の場合や、駐車場その他の施設の利用に伴って土地を使用する場合は課税としているか | E44: 賃借料をチェック
C47: 2 | D47: 課税の対象となる対価補償金以外の補償金を課税仕入れにしていないか（水道管移設保証金、ガス管移設保証金等は不課税） | E47: 保証金をチェック
C50: 3 | D50: 損害賠償金を課税仕入れにしていないか（一般的には不課税）
C52: 4 | D52: 免税・非課税・不課税仕入れを課税仕入れにしていないか | E52: 各費目をチェック
C54: 5 | D54: 資産の譲渡損を課税仕入れにしていないか | E54: 固定資産売却損をチェック
C56: 6 | D56: 経過措置対象取引（3%取引）がある場合、課税仕入れを3%取引と4%取引に区分して計算しているか | E56: 該当なし
C58: 7 | D58: 課税仕入れ等の税額の計算
E59: 収益的支出のうち課税支出（税込） | R59: =基礎数値!F11 -> 25903142 | Y59: ※ 「決算総括表」より
E60: 資本的支出のうち課税支出（税込） | R60: =基礎数値!F12 -> 125712 | Y60: ※ 「決算総括表」より | AJ60: 計 | AK60: =R59+R60 -> 26028854 | AQ60: K
E64: 課税仕入れから控除するもの
H65: 返還等対価・貸倒れの額 | R65: =基礎数値!F14 -> 24706340 | X65: L | Y65: ※ 「過年度損益修正損」「その他特別損失」の課税支出うち、該当分
H66: 仕入対価の返還等の額 | R66: =R24 -> 0 | Y66: ※ Bの額
E68: 課税仕入れに係る支払対価の額（税込） | T68: =AK60-R65-R66 -> 1322514 | AA68: ※ K-L-B | AZ68: 付表２⑨
E70: 課税仕入れに係る消費税額 | T70: =ROUNDDOWN((AK60-R65-R66)*63/1080,0) -> 77146 | Z70: M | AA70: ※ （K-L-B）×6.3/108 ＜付表２の注３による計算＞ | AZ70: 付表２⑩⑮
B72: 特定収入の 判定 | C72: 1 | D72: 通常の借入金（地方債の起債収入等）を特定収入にしていないか | E72: 「企業債」をチェック
C74: 2 | D74: 一般会計繰入金であっても、地方公営企業法適用企業が受け入れる出資金は特定収入から除かれる。出資金を特定収入にしていないか | E74: 「一般会計出資金」をチェック
C77: 3 | D77: 通常の借入金の元金返済のために一般会計から繰入金等があった場合、特定収入の判定（借入金で賄った事業のために使用されたとして使途を特定）をしているか | E77: 該当なし
C81: 4 | D81: 補助金等の一部を翌期に繰り越した場合、収入のあった課税期間で特定収入の調整（支出金額の割合により按分）を行っているか | E81: 「国庫補助金」をチェック
C84: 5 | D84: 還付加算金について、特定収入の判定をしているか
B87: 仕入税額控除 の調整 | C87: 1 | D87: 特定収入割合の計算
E88: 収益的支出のうち特定収入 | P88: =基礎数値!F18 -> 455392 | W88: ※ 「決算総括表」の「不課税収入」のうち「課税仕入に特定」
E89: 資本的支出のうち特定収入 | P89: =基礎数値!F19 -> 1246904 | W89: ※ 「決算総括表」の「不課税収入」のうち「課税仕入に特定」 | AR89: 計 | AS89: =P88+P89 -> 1702296 | AY89: N
E91: 課税売上額（税抜） | P91: =ROUNDDOWN(AK21*100/108,0) -> 43567 | W91: ※ A×100/108
E92: 免税売上額
E93: 非課税売上額
E95: 特定収入割合
C97: 2 | D97: 仕入税額控除の計算 | AZ97: 付表２⑳
E98: 一括比例配分方式により控除する課税仕入れ等の税額 | Z98: =ROUNDDOWN(T70*'(申)計'!R36/'(申)計'!R40,0) -> 76866 | AF98: O | AG98: ※ M×合計のH/合計のJ | AZ98: 計算表５①
U99: （調整前）
E100: 課税仕入れに係る特定収入 | Z100: =AS89 -> 1702296 | AG100: ※ Nの額 | AZ100: 計算表５④
E101: 課税仕入れに係る特定収入×6.3/108 | Z101: =ROUNDDOWN(Z100*63/1080,0) -> 99300 | AF101: P | AG101: ※ N×6.3/108 | AZ101: 計算表５⑤
E103: 課税売上割合 | Z103: ='(申)計'!R36 -> 18871966907 | AG103: Q | AH103: ※ 合計のHの額 | AZ103: 計算表５⑩
Z106: ='(申)計'!R40 -> 18940559860 | AH106: ※ 合計のJの額
E108: 特定収入に係る課税仕入れの税額 | Z108: =ROUNDDOWN(Z101*Z103/Z106,0) -> 98940 | AF108: R | AG108: ※ P×Q | AZ108: 計算表５⑮
E110: 使途不特定の特定収入
F111: 課税仕入れ等の税額－特定収入に係る課税仕入れ等の税額 | AC111: =Z98-Z108 -> -22074 | AI111: S | AJ111: ※ O－R | AZ111: 計算表５⑫
F113: 調整割合 | AA113: ='(申)計'!AA113 -> 0 | AH113: T | AI113: ※ 合計を参照 | AZ113: 計算表５⑬
AA116: ='(申)計'!AA116 -> 18950268779
F118: 使途不特定の特定収入の税額 | AA118: =ROUNDDOWN(AC111*AA113/AA116,0) -> 0 | AG118: U | AH118: ※ S×T | AZ118: 計算表５⑭
AZ119: 付表２㉑
E120: 特定収入に係る課税仕入れ等の税額 | Z120: =Z108+AA118 -> 98940 | AF120: V | AG120: ※ R＋U | AZ120: 計算表５⑮
AZ121: 計算表５⑯
E122: 控除対象仕入税額 | Z122: =Z98-Z120 -> -22074 | AF122: W | AG122: ※ O－V | AZ122: 付表２㉔or㉕
AZ123: 付表１③or④
B131: 納税額等の 計算 | C131: 1 | D131: 控除税額の計算
E132: 控除税額 | J132: 控除対象仕入税額 | T132: =IF(0>Z122,0,Z122) -> 0 | AA132: ※ Wの額 | AZ132: Wが△の時は
AZ133: 0
J134: 返還等対価に係る税額 | T134: =ROUNDDOWN(R25*63/1080,0) -> 2294 | Z134: X | AA134: ※ C×6.3/108 | AZ134: 付表１⑤
J136: 貸倒れに係る金額（税込） | T136: =基礎数値!F17 -> 24667001 | Z136: Y. | AA136: ※ 特別損失の課税支出のうち、時効欠損分
J137: 貸倒れに係る税額 | T137: =ROUNDDOWN(T136*63/1080,0) -> 1438908 | Z137: Z | AA137: ※ Y×6.3/108 | AZ137: 付表１⑥
J139: 控除税額 計 | T139: =T132+T134+T137 -> 1441202 | Z139: AA | AB139: ※ W＋X＋Z | AZ139: 付表１⑦
C141: 2 | D141: 消費税の納付税額の計算
E142: 消費税額 | T142: =R31 -> 2709 | AB142: ※ Fの額
E143: 控除税額 | T143: =T139 -> 1441202 | AB143: ※ AAの額
E144: 差引税額 | T144: =IF(Z122<0,T142-T143-Z122,T142-T143) -> -1416419 | Z144: AB | AB144: ※ F－AA | AZ144: 付表１⑧or⑨
C150: 3 | D150: 地方消費税の税額の計算
E151: 地方消費税の課税標準となる税額 | T151: =T144 -> -1416419 | AB151: ※ ABの額
E152: 納税額 | T152: =ROUNDDOWN(T151*17/63,0) -> -382208 | Z152: AE | AB152: ※ AB×17/63 | AZ152: 付表１⑭or⑮
C158: 4 | D158: 消費税及び地方消費税の合計納付税額

Sheet (申)軽8%
B1: 消費税等計算チェックシート | AZ1: 単位：円
B2: チェック項目 | E2: 検証 | AZ2: 申告書等
B3: 課税標準等 | C3: 1 | D3: 行政手数料収入を課税売上にしていないか（一部のものを除き、非課税となる） | E3: 「その他営業収益」の「手数料」をチェック
C5: 2 | D5: 土地の貸付（原則非課税）のうち、契約期間が1か月未満の場合や、駐車場その他の施設の利用に伴って土地が使用される場合は課税としているか | E5: 「雑収益」の「その他雑収益」をチェック
C8: 3 | D8: 課税の対象となる対価補償金以外の補償金を課税売上にしていないか（水道管移設保証金、ガス管移設保証金等は不課税）
C11: 4 | D11: 損害賠償金を課税売上にしていないか（一般的には不課税）
C13: 5 | D13: 建物等固定資産（土地を除く）の売却について、差益部分のみを課税売上にしていないか | E13: 「固定資産売却益」及び「土地売却代金」をチェック
C15: 6 | D15: 車両等を購入した場合、下取り価額を課税売上にしていないか
C17: 7 | D17: 土地建物一括譲渡の場合、対価の額の区分は正しいか
C19: 8 | D19: 課税売上額の計算
E20: 収益的収入のうち課税売上（税込） | R20: =基礎数値!G3 -> 0 | Y20: ※ 「決算総括表」より
E21: 資本的収入のうち課税売上（税込） | R21: =基礎数値!G4 -> 0 | Y21: ※ 「決算総括表」より | AJ21: 計 | AK21: =R20+R21 -> 0 | AQ21: A
E23: 課税売上から控除するもの
H24: 仕入対価の返還等の額 | R24: =基礎数値!G6 -> 0 | X24: B | Y24: ※ 「過年度損益修正益」「その他特別利益」のうち、課税支出が返還されたもの
H25: 売上対価の返還等の額 | R25: =基礎数値!G7 -> 0 | X25: C | Y25: ※ 「過年度損益修正損」「その他特別損失」のうち、課税収入を返還したもの
E27: 課税売上額（税抜） | R27: =ROUNDDOWN((AK21-R24-R25)*100/108,0) -> 0 | X27: D | Y27: ※ （A－B－C）×100/108 | AZ27: 付表２①
E29: 課税標準額（税抜） | R29: =ROUNDDOWN((AK21-R24)*100/108,-3) -> 0 | X29: E | Y29: ※ （A－B）×100/108 1,000円未満切捨 | AZ29: 付表１①
E31: 課税標準額に対する消費税額 | R31: =ROUNDDOWN(R29*62.4/1000,0) -> 0 | X31: F | Y31: ※ E×6.24% | AZ31: 付表１②
B33: 課税売上割合 | C33: 1 | D33: 課税売上割合の計算
E34: 課税売上額
E35: 免税売上額
E36: 課税資産の譲渡等の対価の額
E38: 収益的収入のうち非課税売上（税込）
E39: 資本的収入のうち非課税売上（税込）
E40: 資産の譲渡等の対価の額
E42: 課税売上割合
B44: 課税仕入れ | C44: 1 | D44: 土地の借受（原則非課税）のうち、契約期間が1か月未満の場合や、駐車場その他の施設の利用に伴って土地を使用する場合は課税としているか | E44: 賃借料をチェック
C47: 2 | D47: 課税の対象となる対価補償金以外の補償金を課税仕入れにしていないか（水道管移設保証金、ガス管移設保証金等は不課税） | E47: 保証金をチェック
C50: 3 | D50: 損害賠償金を課税仕入れにしていないか（一般的には不課税）
C52: 4 | D52: 免税・非課税・不課税仕入れを課税仕入れにしていないか | E52: 各費目をチェック
C54: 5 | D54: 資産の譲渡損を課税仕入れにしていないか | E54: 固定資産売却損をチェック
C56: 6 | D56: 経過措置対象取引（3%取引）がある場合、課税仕入れを3%取引と4%取引に区分して計算しているか | E56: 該当なし
C58: 7 | D58: 課税仕入れ等の税額の計算
E59: 収益的支出のうち課税支出（税込） | R59: =基礎数値!G11 -> 500878 | Y59: ※ 「決算総括表」より
E60: 資本的支出のうち課税支出（税込） | R60: =基礎数値!G12 -> 36840 | Y60: ※ 「決算総括表」より | AJ60: 計 | AK60: =R59+R60 -> 537718 | AQ60: K
E64: 課税仕入れから控除するもの
H65: 返還等対価・貸倒れの額 | R65: =基礎数値!G14 -> 0 | X65: L | Y65: ※ 「過年度損益修正損」「その他特別損失」の課税支出うち、該当分
H66: 仕入対価の返還等の額 | R66: =R24 -> 0 | Y66: ※ Bの額
E68: 課税仕入れに係る支払対価の額（税込） | T68: =AK60-R65-R66 -> 537718 | AA68: ※ K-L-B | AZ68: 付表２⑨
E70: 課税仕入れに係る消費税額 | T70: =ROUNDDOWN((AK60-R65-R66)*62.4/1080,0) -> 31068 | Z70: M | AA70: ※ （K-L-B）×6.24/108 ＜付表２の注３による計算＞ | AZ70: 付表２⑩⑮
B72: 特定収入の 判定 | C72: 1 | D72: 通常の借入金（地方債の起債収入等）を特定収入にしていないか | E72: 「企業債」をチェック
C74: 2 | D74: 一般会計繰入金であっても、地方公営企業法適用企業が受け入れる出資金は特定収入から除かれる。出資金を特定収入にしていないか | E74: 「一般会計出資金」をチェック
C77: 3 | D77: 通常の借入金の元金返済のために一般会計から繰入金等があった場合、特定収入の判定（借入金で賄った事業のために使用されたとして使途を特定）をしているか | E77: 該当なし
C81: 4 | D81: 補助金等の一部を翌期に繰り越した場合、収入のあった課税期間で特定収入の調整（支出金額の割合により按分）を行っているか | E81: 「国庫補助金」をチェック
C84: 5 | D84: 還付加算金について、特定収入の判定をしているか
B87: 仕入税額控除 の調整 | C87: 1 | D87: 特定収入割合の計算
E88: 収益的支出のうち特定収入 | P88: =基礎数値!G18 -> 130568 | W88: ※ 「決算総括表」の「不課税収入」のうち「課税仕入に特定」
E89: 資本的支出のうち特定収入 | P89: =基礎数値!G19 -> 99 | W89: ※ 「決算総括表」の「不課税収入」のうち「課税仕入に特定」 | AR89: 計 | AS89: =P88+P89 -> 130667 | AY89: N
E91: 課税売上額（税抜） | P91: =ROUNDDOWN(AK21*100/108,0) -> 0 | W91: ※ A×100/108
E92: 免税売上額
E93: 非課税売上額
E95: 特定収入割合
C97: 2 | D97: 仕入税額控除の計算 | AZ97: 付表２⑳
E98: 一括比例配分方式により控除する課税仕入れ等の税額 | Z98: =ROUNDDOWN(T70*'(申)計'!R36/'(申)計'!R40,0) -> 30955 | AF98: O | AG98: ※ M×合計のH/合計のJ | AZ98: 計算表５①
U99: （調整前）
E100: 課税仕入れに係る特定収入 | Z100: =AS89 -> 130667 | AG100: ※ Nの額 | AZ100: 計算表５⑥
E101: 課税仕入れに係る特定収入×6.3/108 | Z101: =ROUNDDOWN(Z100*62.4/1080,0) -> 7549 | AF101: P | AG101: ※ N×6.24/108 | AZ101: 計算表５⑦
E103: 課税売上割合 | Z103: ='(申)計'!R36 -> 18871966907 | AG103: Q | AH103: ※ 合計のHの額 | AZ103: 計算表５⑩
Z106: ='(申)計'!R40 -> 18940559860 | AH106: ※ 合計のJの額
E108: 特定収入に係る課税仕入れの税額 | Z108: =ROUNDDOWN(Z101*Z103/Z106,0) -> 7521 | AF108: R | AG108: ※ P×Q | AZ108: 計算表５⑮
E110: 使途不特定の特定収入
F111: 課税仕入れ等の税額－特定収入に係る課税仕入れ等の税額 | AC111: =Z98-Z108 -> 23434 | AI111: S | AJ111: ※ O－R | AZ111: 計算表５⑫
F113: 調整割合 | AA113: ='(申)計'!AA113 -> 0 | AH113: T | AI113: ※ 合計を参照 | AZ113: 計算表５⑬
AA116: ='(申)計'!AA116 -> 18950268779
F118: 使途不特定の特定収入の税額 | AA118: =ROUNDDOWN(AC111*AA113/AA116,0) -> 0 | AG118: U | AH118: ※ S×T | AZ118: 計算表５⑭
AZ119: 付表２㉑
E120: 特定収入に係る課税仕入れ等の税額 | Z120: =Z108+AA118 -> 7521 | AF120: V | AG120: ※ R＋U | AZ120: 計算表５⑮
AZ121: 計算表５⑯
E122: 控除対象仕入税額 | Z122: =Z98-Z120 -> 23434 | AF122: W | AG122: ※ O－V | AZ122: 付表２㉔or㉕
AZ123: 付表１③or④
B131: 納税額等の 計算 | C131: 1 | D131: 控除税額の計算
E132: 控除税額 | J132: 控除対象仕入税額 | T132: =IF(0>Z122,0,Z122) -> 23434 | AA132: ※ Wの額 | AZ132: Wが△の時は
AZ133: 0
J134: 返還等対価に係る税額 | T134: =ROUNDDOWN(R25*62.4/1080,0) -> 0 | Z134: X | AA134: ※ C×6.24/108 | AZ134: 付表１⑤
J136: 貸倒れに係る金額（税込） | T136: =基礎数値!G17 -> 0 | Z136: Y. | AA136: ※ 特別損失の課税支出のうち、時効欠損分
J137: 貸倒れに係る税額 | T137: =ROUNDDOWN(T136*62.4/1080,0) -> 0 | Z137: Z | AA137: ※ Y×6.24/108 | AZ137: 付表１⑥
J139: 控除税額 計 | T139: =T132+T134+T137 -> 23434 | Z139: AA | AB139: ※ W＋X＋Z | AZ139: 付表１⑦
C141: 2 | D141: 消費税の納付税額の計算
E142: 消費税額 | T142: =R31 -> 0 | AB142: ※ Fの額
E143: 控除税額 | T143: =T139 -> 23434 | AB143: ※ AAの額
E144: 差引税額 | T144: =T142-T143 -> -23434 | Z144: AB | AB144: ※ F－AA | AZ144: 付表１⑧or⑨
C150: 3 | D150: 地方消費税の税額の計算
E151: 地方消費税の課税標準となる税額 | T151: =T144 -> -23434 | AB151: ※ ABの額
E152: 納税額 | T152: =ROUNDDOWN(T151*22/78,0) -> -6609 | Z152: AE | AB152: ※ AB×22/78 | AZ152: 付表１⑭or⑮
C158: 4 | D158: 消費税及び地方消費税の合計納付税額

Sheet (申)10%
B1: 消費税等計算チェックシート | AZ1: 単位：円
B2: チェック項目 | E2: 検証 | AZ2: 申告書等
B3: 課税標準等 | C3: 1 | D3: 行政手数料収入を課税売上にしていないか（一部のものを除き、非課税となる） | E3: 「その他営業収益」の「手数料」をチェック
C5: 2 | D5: 土地の貸付（原則非課税）のうち、契約期間が1か月未満の場合や、駐車場その他の施設の利用に伴って土地が使用される場合は課税としているか | E5: 「雑収益」の「その他雑収益」をチェック
C8: 3 | D8: 課税の対象となる対価補償金以外の補償金を課税売上にしていないか（水道管移設保証金、ガス管移設保証金等は不課税）
C11: 4 | D11: 損害賠償金を課税売上にしていないか（一般的には不課税）
C13: 5 | D13: 建物等固定資産（土地を除く）の売却について、差益部分のみを課税売上にしていないか | E13: 「固定資産売却益」及び「土地売却代金」をチェック
C15: 6 | D15: 車両等を購入した場合、下取り価額を課税売上にしていないか
C17: 7 | D17: 土地建物一括譲渡の場合、対価の額の区分は正しいか
C19: 8 | D19: 課税売上額の計算
E20: 収益的収入のうち課税売上（税込） | R20: =基礎数値!H3 -> 20730008529 | Y20: ※ 「決算総括表」より
E21: 資本的収入のうち課税売上（税込） | R21: =基礎数値!H4 -> 39691410 | Y21: ※ 「決算総括表」より | AJ21: 計 | AK21: =R20+R21 -> 20769699939 | AQ21: A
E23: 課税売上から控除するもの
H24: 仕入対価の返還等の額 | R24: =基礎数値!H6 -> 0 | X24: B | Y24: ※ 「過年度損益修正益」「その他特別利益」のうち、課税支出が返還されたもの
H25: 売上対価の返還等の額 | R25: =基礎数値!H7 -> 10639743 | X25: C | Y25: ※ 「過年度損益修正損」「その他特別損失」のうち、課税収入を返還したもの
E27: 課税売上額（税抜） | R27: =ROUNDDOWN((AK21-R24-R25)*100/110,0) -> 18871872905 | X27: D | Y27: ※ （A－B－C）×100/110 | AZ27: 付表２①
E29: 課税標準額（税抜） | R29: =ROUNDDOWN((AK21-R24)*100/110,-3) -> 18881545000 | X29: E | Y29: ※ （A－B）×100/110 1,000円未満切捨 | AZ29: 付表１①
E31: 課税標準額に対する消費税額 | R31: =ROUNDDOWN(R29*78/1000,0) -> 1472760510 | X31: F | Y31: ※ E×7.8% | AZ31: 付表１②
B33: 課税売上割合 | C33: 1 | D33: 課税売上割合の計算
E34: 課税売上額
E35: 免税売上額
E36: 課税資産の譲渡等の対価の額
E38: 収益的収入のうち非課税売上（税込）
E39: 資本的収入のうち非課税売上（税込）
E40: 資産の譲渡等の対価の額
E42: 課税売上割合
B44: 課税仕入れ | C44: 1 | D44: 土地の借受（原則非課税）のうち、契約期間が1か月未満の場合や、駐車場その他の施設の利用に伴って土地を使用する場合は課税としているか | E44: 賃借料をチェック
C47: 2 | D47: 課税の対象となる対価補償金以外の補償金を課税仕入れにしていないか（水道管移設保証金、ガス管移設保証金等は不課税） | E47: 保証金をチェック
C50: 3 | D50: 損害賠償金を課税仕入れにしていないか（一般的には不課税）
C52: 4 | D52: 免税・非課税・不課税仕入れを課税仕入れにしていないか | E52: 各費目をチェック
C54: 5 | D54: 資産の譲渡損を課税仕入れにしていないか | E54: 固定資産売却損をチェック
C56: 6 | D56: 経過措置対象取引（3%取引）がある場合、課税仕入れを3%取引と4%取引に区分して計算しているか | E56: 該当なし
C58: 7 | D58: 課税仕入れ等の税額の計算
E59: 収益的支出のうち課税支出（税込） | R59: =基礎数値!H11 -> 9106828850 | Y59: ※ 「決算総括表」より
E60: 資本的支出のうち課税支出（税込） | R60: =基礎数値!H12 -> 16278736624 | Y60: ※ 「決算総括表」より | AJ60: 計 | AK60: =R59+R60 -> 25385565474
E61: 免税業者との取引額 | R61: =基礎数値!H16 -> 34600 | Y61: 免税業者以外との取引額 | AI61: =基礎数値!H11-R61+基礎数値!H12 -> 25385530874
E62: 税控除できない額 | R62: =ROUNDDOWN(R61*0.2*78/1100,0) -> 490 | Y62: 課税仕入れに係る消費税額 | AI62: =ROUNDDOWN((AK60-R65-R66)*78/1100,0)-R62-R63 -> 1799310462
E63: 免税業者との取引額の税額 | R63: =ROUNDDOWN(R61*78/1100,0)-R62 -> 1963
E64: 課税仕入れから控除するもの
H65: 返還等対価・貸倒れの額 | R65: =基礎数値!H14 -> 10639743 | X65: L | Y65: ※ 「過年度損益修正損」「その他特別損失」の課税支出うち、該当分
H66: 仕入対価の返還等の額 | R66: =R24 -> 0 | Y66: ※ Bの額
E68: 課税仕入れに係る支払対価の額（税込） | T68: =AK60-R65-R66 -> 25374925731 | AA68: ※ K-L-B | AZ68: 付表２⑨
E70: 課税仕入れに係る消費税額 | T70: =ROUNDDOWN((AK60-R65-R66)*78/1100,0)-R62 -> 1799312425 | Z70: M | AA70: ※ （K-L-B）×7.8/110 ＜付表２の注３による計算＞ | AZ70: 付表２⑩⑮
B72: 特定収入の 判定 | C72: 1 | D72: 通常の借入金（地方債の起債収入等）を特定収入にしていないか | E72: 「企業債」をチェック
C74: 2 | D74: 一般会計繰入金であっても、地方公営企業法適用企業が受け入れる出資金は特定収入から除かれる。出資金を特定収入にしていないか | E74: 「一般会計出資金」をチェック
C77: 3 | D77: 通常の借入金の元金返済のために一般会計から繰入金等があった場合、特定収入の判定（借入金で賄った事業のために使用されたとして使途を特定）をしているか | E77: 該当なし
C81: 4 | D81: 補助金等の一部を翌期に繰り越した場合、収入のあった課税期間で特定収入の調整（支出金額の割合により按分）を行っているか | E81: 「国庫補助金」をチェック
C84: 5 | D84: 還付加算金について、特定収入の判定をしているか
B87: 仕入税額控除 の調整 | C87: 1 | D87: 特定収入割合の計算
E88: 収益的支出のうち特定収入 | P88: =基礎数値!H18 -> 2312306920 | W88: ※ 「決算総括表」の「不課税収入」のうち「課税仕入に特定」
E89: 資本的支出のうち特定収入 | P89: =基礎数値!H19 -> 5972404802 | W89: ※ 「決算総括表」の「不課税収入」のうち「課税仕入に特定」 | AR89: 計 | AS89: =P88+P89 -> 8284711722 | AY89: N
E91: 課税売上額（税抜） | P91: =ROUNDDOWN(AK21*100/110,0) -> 18881545399 | W91: ※ A×100/110
E92: 免税売上額
E93: 非課税売上額
E95: 特定収入割合
C97: 2 | D97: 仕入税額控除の計算 | AZ97: 付表２⑳
E98: 一括比例配分方式により控除する課税仕入れ等の税額 | Z98: =ROUNDDOWN(T70*'(申)計'!R36/'(申)計'!R40,0) -> 1792796242 | AF98: O | AG98: ※ M×合計のH/合計のJ | AZ98: 計算表５①
U99: （調整前）
E100: 課税仕入れに係る特定収入 | Z100: =AS89 -> 8284711722 | AG100: ※ Nの額 | AZ100: 計算表５⑧
E101: 課税仕入れに係る特定収入×6.3/108 | Z101: =ROUNDDOWN(Z100*78/1100,0) -> 587461376 | AF101: P | AG101: ※ N×7.8/110 | AZ101: 計算表５⑨
E103: 課税売上割合 | Z103: ='(申)計'!R36 -> 18871966907 | AG103: Q | AH103: ※ 合計のHの額 | AZ103: 計算表５⑩
Z106: ='(申)計'!R40 -> 18940559860 | AH106: ※ 合計のJの額
E108: 特定収入に係る課税仕入れの税額 | Z108: =ROUNDDOWN(Z101*Z103/Z106,0) -> 585333893 | AF108: R | AG108: ※ P×Q | AZ108: 計算表５⑮
E110: 使途不特定の特定収入
F111: 課税仕入れ等の税額－特定収入に係る課税仕入れ等の税額 | AC111: =Z98-Z108 -> 1207462349 | AI111: S | AJ111: ※ O－R | AZ111: 計算表５⑫
F113: 調整割合 | AA113: ='(申)計'!AA113 -> 0 | AH113: T | AI113: ※ 合計を参照 | AZ113: 計算表５⑬
AA116: ='(申)計'!AA116 -> 18950268779
F118: 使途不特定の特定収入の税額 | AA118: =ROUNDDOWN(AC111*AA113/AA116,0) -> 0 | AG118: U | AH118: ※ S×T | AZ118: 計算表５⑭
AZ119: 付表２㉑
E120: 特定収入に係る課税仕入れ等の税額 | Z120: =Z108+AA118 -> 585333893 | AF120: V | AG120: ※ R＋U | AZ120: 計算表５⑮
AZ121: 計算表５⑯
E122: 控除対象仕入税額 | Z122: =Z98-Z120 -> 1207462349 | AF122: W | AG122: ※ O－V | AZ122: 付表２㉔or㉕
AZ123: 付表１③or④
B131: 納税額等の 計算 | C131: 1 | D131: 控除税額の計算
E132: 控除税額 | J132: 控除対象仕入税額 | T132: =IF(0>Z122,0,Z122) -> 1207462349 | AA132: ※ Wの額 | AZ132: Wが△の時は
AZ133: 0
J134: 返還等対価に係る税額 | T134: =ROUNDDOWN(R25*78/1100,0) -> 754454 | Z134: X | AA134: ※ C×7.8/110 | AZ134: 付表１⑤
J136: 貸倒れに係る金額（税込） | T136: =基礎数値!H17 -> 0 | Z136: Y. | AA136: ※ 特別損失の課税支出のうち、時効欠損分
J137: 貸倒れに係る税額 | T137: =ROUNDDOWN(T136*78/1100,0) -> 0 | Z137: Z | AA137: ※ Y×7.8/110 | AZ137: 付表１⑥
J139: 控除税額 計 | T139: =T132+T134+T137 -> 1208216803 | Z139: AA | AB139: ※ W＋X＋Z | AZ139: 付表１⑦
C141: 2 | D141: 消費税の納付税額の計算
E142: 消費税額 | T142: =R31 -> 1472760510 | AB142: ※ Fの額
E143: 控除税額 | T143: =T139 -> 1208216803 | AB143: ※ AAの額
E144: 差引税額 | T144: =T142-T143 -> 264543707 | Z144: AB | AB144: ※ F－AA | AZ144: 付表１⑧or⑨
C150: 3 | D150: 地方消費税の税額の計算
E151: 地方消費税の課税標準となる税額 | T151: =T144 -> 264543707 | AB151: ※ ABの額
E152: 納税額 | T152: =ROUNDDOWN(T151*22/78,0) -> 74614891 | Z152: AE | AB152: ※ AB×22/78 | AZ152: 付表１⑭or⑮
C158: 4 | D158: 消費税及び地方消費税の合計納付税額

Sheet (申)計
B1: 消費税等計算チェックシート | AZ1: 単位：円
B2: チェック項目 | E2: 検証 | AZ2: 申告書等
B3: 課税標準等 | C3: 1 | D3: 行政手数料収入を課税売上にしていないか（一部のものを除き、非課税となる） | E3: 「その他営業収益」の「手数料」をチェック
C5: 2 | D5: 土地の貸付（原則非課税）のうち、契約期間が1か月未満の場合や、駐車場その他の施設の利用に伴って土地が使用される場合は課税としているか | E5: 「雑収益」の「その他雑収益」をチェック
C8: 3 | D8: 課税の対象となる対価補償金以外の補償金を課税売上にしていないか（水道管移設保証金、ガス管移設保証金等は不課税）
C11: 4 | D11: 損害賠償金を課税売上にしていないか（一般的には不課税）
C13: 5 | D13: 建物等固定資産（土地を除く）の売却について、差益部分のみを課税売上にしていないか | E13: 「固定資産売却益」及び「土地売却代金」をチェック
C15: 6 | D15: 車両等を購入した場合、下取り価額を課税売上にしていないか
C17: 7 | D17: 土地建物一括譲渡の場合、対価の額の区分は正しいか
C19: 8 | D19: 課税売上額の計算
E20: 収益的収入のうち課税売上（税込） | R20: ='(申)3%'!R20:W20+'(申)5%'!R20:W20+'(申)8%'!R20:W20+'(申)軽8%'!R20:W20+'(申)10%'!R20:W20 -> 20730055582
E21: 資本的収入のうち課税売上（税込） | R21: ='(申)3%'!R21:W21+'(申)5%'!R21:W21+'(申)8%'!R21:W21+'(申)軽8%'!R21:W21+'(申)10%'!R21:W21 -> 39691410 | AJ21: 計 | AK21: =R20+R21 -> 20769746992 | AQ21: A
E23: 課税売上から控除するもの
H24: 仕入対価の返還等の額 | R24: ='(申)3%'!R24:W24+'(申)5%'!R24:W24+'(申)8%'!R24:W24+'(申)軽8%'!R24:W24+'(申)10%'!R24:W24 -> 0 | X24: B
H25: 売上対価の返還等の額 | R25: ='(申)3%'!R25:W25+'(申)5%'!R25:W25+'(申)8%'!R25:W25+'(申)軽8%'!R25:W25+'(申)10%'!R25:W25 -> 10679082 | X25: C
E27: 課税売上額（税抜） | R27: ='(申)3%'!R27:W27+'(申)5%'!R27:W27+'(申)8%'!R27:W27+'(申)軽8%'!R27:W27+'(申)10%'!R27:W27 -> 18871880047 | X27: D | AZ27: 付表２①
E29: 課税標準額（税抜） | R29: ='(申)3%'!R29:W29+'(申)5%'!R29:W29+'(申)8%'!R29:W29+'(申)軽8%'!R29:W29+'(申)10%'!R29:W29 -> 18881588000 | X29: E | AZ29: 付表１①
AZ30: 申告書①
E31: 課税標準額に対する消費税額 | R31: ='(申)3%'!R31:W31+'(申)5%'!R31:W31+'(申)8%'!R31:W31+'(申)軽8%'!R31:W31+'(申)10%'!R31:W31 -> 1472763219 | X31: F | AZ31: 付表１②
AZ32: 申告書②
B33: 課税売上割合 | C33: 1 | D33: 課税売上割合の計算
E34: 課税売上額 | R34: =R27 -> 18871880047 | Y34: ※ Dの額
E35: 免税売上額 | R35: =基礎数値!I8 -> 86860 | X35: G | Y35: ※ 管理課資料、「決算総括表」より | AZ35: 付表２②
E36: 課税資産の譲渡等の対価の額 | R36: =R34+R35 -> 18871966907 | X36: H | Y36: ※ D＋G | AC36: 【課税売上割合の分子】 | AZ36: 申告書⑮ 付表２④⑤
E38: 収益的収入のうち非課税売上（税込） | R38: =基礎数値!I9 -> 22644840 | Y38: ※ 「決算総括表」より
E39: 資本的収入のうち非課税売上（税込） | R39: =基礎数値!I10 -> 45948113 | Y39: ※ 「決算総括表」より | AJ39: 計 | AK39: =R38+R39 -> 68592953 | AQ39: I | AZ39: 付表２⑥
E40: 資産の譲渡等の対価の額 | R40: =R36+AK39 -> 18940559860 | X40: J | Y40: ※ H＋I | AC40: 【課税売上割合の分母】 | AZ40: 申告書⑯
AZ41: 付表２⑦
E42: 課税売上割合 | R42: =ROUNDDOWN(R36/R40,4) -> 0.9963 | Y42: ※ H/J 端数切捨て | AG42: 【付表２記載値】 | AZ42: 付表２⑧
B44: 課税仕入れ | C44: 1 | D44: 土地の借受（原則非課税）のうち、契約期間が1か月未満の場合や、駐車場その他の施設の利用に伴って土地を使用する場合は課税としているか | E44: 賃借料をチェック
C47: 2 | D47: 課税の対象となる対価補償金以外の補償金を課税仕入れにしていないか（水道管移設保証金、ガス管移設保証金等は不課税） | E47: 保証金をチェック
C50: 3 | D50: 損害賠償金を課税仕入れにしていないか（一般的には不課税）
C52: 4 | D52: 免税・非課税・不課税仕入れを課税仕入れにしていないか | E52: 各費目をチェック
C54: 5 | D54: 資産の譲渡損を課税仕入れにしていないか | E54: 固定資産売却損をチェック
C56: 6 | D56: 経過措置対象取引（3%取引）がある場合、課税仕入れを3%取引と4%取引に区分して計算しているか | E56: 該当なし
C58: 7 | D58: 課税仕入れ等の税額の計算
E59: 収益的支出のうち課税支出（税込） | R59: ='(申)3%'!R59:W59+'(申)5%'!R59:W59+'(申)8%'!R59:W59+'(申)軽8%'!R59:W59+'(申)10%'!R59:W59 -> 9134353866
E60: 資本的支出のうち課税支出（税込） | R60: ='(申)3%'!R60:W60+'(申)5%'!R60:W60+'(申)8%'!R60:W60+'(申)軽8%'!R60:W60+'(申)10%'!R60:W60 -> 16278899176 | AJ60: 計 | AK60: ='(申)3%'!AK60:AP60+'(申)5%'!AK60:AP60+'(申)8%'!AK60:AP60+'(申)軽8%'!AK60:AP60+'(申)10%'!AK60:AP60 -> 25413253042 | AQ60: K
E64: 課税仕入れから控除するもの
H65: 返還等対価・貸倒れの額 | R65: ='(申)3%'!R65:W65+'(申)5%'!R65:W65+'(申)8%'!R65:W65+'(申)軽8%'!R65:W65+'(申)10%'!R65:W65 -> 36467079 | X65: L
H66: 仕入対価の返還等の額 | R66: ='(申)3%'!R66:W66+'(申)5%'!R66:W66+'(申)8%'!R66:W66+'(申)軽8%'!R66:W66+'(申)10%'!R66:W66 -> 0 | Y66: ※ Bの額
E68: 課税仕入れに係る支払対価の額（税込） | T68: ='(申)3%'!T68:Y68+'(申)5%'!T68:Y68+'(申)8%'!T68:Y68+'(申)軽8%'!T68:Y68+'(申)10%'!T68:Y68 -> 25376785963 | AA68: ※ K-L-B | AZ68: 付表２⑨ | BC68: =AK60-R65 -> 25376785963
E70: 課税仕入れに係る消費税額 | T70: ='(申)3%'!T70:Y70+'(申)5%'!T70:Y70+'(申)8%'!T70:Y70+'(申)軽8%'!T70:Y70+'(申)10%'!T70:Y70 -> 1799420639 | Z70: M | AZ70: 付表２⑩⑮
B72: 特定収入の 判定 | C72: 1 | D72: 通常の借入金（地方債の起債収入等）を特定収入にしていないか | E72: 「企業債」をチェック
C74: 2 | D74: 一般会計繰入金であっても、地方公営企業法適用企業が受け入れる出資金は特定収入から除かれる。出資金を特定収入にしていないか | E74: 「一般会計出資金」をチェック
C77: 3 | D77: 通常の借入金の元金返済のために一般会計から繰入金等があった場合、特定収入の判定（借入金で賄った事業のために使用されたとして使途を特定）をしているか | E77: 該当なし
C81: 4 | D81: 補助金等の一部を翌期に繰り越した場合、収入のあった課税期間で特定収入の調整（支出金額の割合により按分）を行っているか | E81: 「国庫補助金」をチェック
C84: 5 | D84: 還付加算金について、特定収入の判定をしているか
B87: 仕入税額控除 の調整 | C87: 1 | D87: 特定収入割合の計算 | AZ87: 税務署提出書類「資産の譲渡等の対価以外の収入の使途について」
E88: 収益的支出のうち特定収入 | P88: ='(申)3%'!P88:U88+'(申)5%'!P88:U88+'(申)8%'!P88:U88+'(申)軽8%'!P88:U88+'(申)10%'!P88:U88 -> 2312892880 | W88: ※ 「決算総括表」の「不課税収入」のうち「課税仕入に特定」
E89: 資本的支出のうち特定収入 | P89: ='(申)3%'!P89:U89+'(申)5%'!P89:U89+'(申)8%'!P89:U89+'(申)軽8%'!P89:U89+'(申)10%'!P89:U89 -> 6105633883 | W89: ※ 「決算総括表」の「不課税収入」のうち「課税仕入に特定」 | AR89: 計 | AS89: =P88+P89 -> 8418526763 | AY89: N
E91: 課税売上額（税抜） | P91: ='(申)3%'!P91:U91+'(申)5%'!P91:U91+'(申)8%'!P91:U91+'(申)軽8%'!P91:U91+'(申)10%'!P91:U91 -> 18881588966 | W91: ※ 5%分＋8%分
E92: 免税売上額 | P92: =R35 -> 86860 | W92: ※ Gの額 | AD92: 計 | AE92: =SUM(P91:U93) -> 18950268779 | AK92: 資産の譲渡等の対価の額
E93: 非課税売上額 | P93: =AK39 -> 68592953 | W93: ※ Iの額
E95: 特定収入割合 | P95: =ROUNDUP(AS89/(AS89+P91+P92+P93),3) -> 0.308 | W95: ※ N/(N+資産の譲渡等の対価の額)
X96: 小数第4位以下切上げ（「国、地方公共団体等と消費税（H25.6）P.50）
C97: 2 | D97: 仕入税額控除の計算 | AZ97: 付表２⑳
E98: 一括比例配分方式により控除する課税仕入れ等の税額 | Z98: ='(申)3%'!Z98:AE98+'(申)5%'!Z98:AE98+'(申)8%'!Z98:AE98+'(申)軽8%'!Z98:AE98+'(申)10%'!Z98:AE98 -> 1792904063 | AF98: O
U99: （調整前）
E100: 課税仕入れに係る特定収入 | Z100: ='(申)3%'!Z100:AE100+'(申)5%'!Z100:AE100+'(申)8%'!Z100:AE100+'(申)軽8%'!Z100:AE100+'(申)10%'!Z100:AE100 -> 8418526763 | AG100: ※ Nの額
E101: 課税仕入れに係る特定収入×4/105 | Z101: ='(申)3%'!Z101:AE101+'(申)5%'!Z101:AE101+'(申)8%'!Z101:AE101+'(申)軽8%'!Z101:AE101+'(申)10%'!Z101:AE101 -> 592596113 | AF101: P | BB101: =SUM('(申)3%:(申)10%'!Z101:AE101) -> 592596113
E103: 課税売上割合 | Z103: =R36 -> 18871966907 | AG103: Q | AH103: ※ Hの額 | AZ103: 計算表５⑥ | BB103: =Z103/Z106 -> 0.99637852
Z106: =R40 -> 18940559860 | AH106: ※ Jの額
E108: 特定収入に係る課税仕入れの税額 | Z108: ='(申)3%'!Z108:AE108+'(申)5%'!Z108:AE108+'(申)8%'!Z108:AE108+'(申)軽8%'!Z108:AE108+'(申)10%'!Z108:AE108 -> 590450033 | AF108: R | BB108: =BB101*BB103 -> 5.9045004e+08
E110: 使途不特定の特定収入
F111: 課税仕入れ等の税額－特定収入に係る課税仕入れ等の税額 | AC111: ='(申)3%'!AC111:AH111+'(申)5%'!AC111:AH111+'(申)8%'!AC111:AH111+'(申)軽8%'!AC111:AH111+'(申)10%'!AC111:AH111 -> 1202454030 | AI111: S | AJ111: ※ O－R | BB111: =Z98-BB108 -> 1.202454e+09
F113: 調整割合 | AA113: =基礎数値!I20 -> 0 | AH113: T | AI113: ※ 使途不特定の特定収入はないので、ゼロ | AZ113: 計算表５⑨
AA116: =AE92 -> 18950268779 | AI116: ※ 資産の譲渡等の対価の額
F118: 使途不特定の特定収入の税額 | AA118: ='(申)3%'!AA118:AF118+'(申)5%'!AA118:AF118+'(申)8%'!AA118:AF118+'(申)軽8%'!AA118:AF118+'(申)10%'!AA118:AF118 -> 0 | AG118: U | AH118: ※ S×T
E120: 特定収入に係る課税仕入れ等の税額 | Z120: ='(申)3%'!Z120:AE120+'(申)5%'!Z120:AE120+'(申)8%'!Z120:AE120+'(申)軽8%'!Z120:AE120+'(申)10%'!Z120:AE120 -> 590450033 | AF120: V | AG120: ※ R＋U | AZ120: 付表２㉑
AZ121: 付表１④ 申告書④
E122: 控除対象仕入税額 | Z122: ='(申)3%'!Z122:AE122+'(申)5%'!Z122:AE122+'(申)8%'!Z122:AE122+'(申)軽8%'!Z122:AE122+'(申)10%'!Z122:AE122 -> 1202454030 | AF122: W | AG122: ※ O－V | BB122: =Z98-Z120 -> 1202454030
B131: 納税額等の 計算 | C131: 1 | D131: 控除税額の計算
E132: 控除税額 | J132: 控除対象仕入税額 | T132: ='(申)3%'!T132:Y132+'(申)5%'!T132:Y132+'(申)8%'!T132:Y132+'(申)軽8%'!T132:Y132+'(申)10%'!T132:Y132 -> 1207485783 | BB132: =SUM('(申)3%:(申)10%'!T132) -> 1207485783
J134: 返還等対価に係る税額 | T134: ='(申)3%'!T134:Y134+'(申)5%'!T134:Y134+'(申)8%'!T134:Y134+'(申)軽8%'!T134:Y134+'(申)10%'!T134:Y134 -> 756748 | Z134: X | AZ134: 申告書⑤ | BB134: =SUM('(申)3%:(申)10%'!T134) -> 756748
J136: 貸倒れに係る金額（税込） | T136: ='(申)3%'!T136:Y136+'(申)5%'!T136:Y136+'(申)8%'!T136:Y136+'(申)軽8%'!T136:Y136+'(申)10%'!T136:Y136 -> 25787997 | Z136: Y. | BB136: =SUM('(申)3%:(申)10%'!T136) -> 25787997
J137: 貸倒れに係る税額 | T137: ='(申)3%'!T137:Y137+'(申)5%'!T137:Y137+'(申)8%'!T137:Y137+'(申)軽8%'!T137:Y137+'(申)10%'!T137:Y137 -> 1481612 | Z137: Z | AZ137: 申告書⑥
J139: 控除税額 計 | T139: ='(申)3%'!T139:Y139+'(申)5%'!T139:Y139+'(申)8%'!T139:Y139+'(申)軽8%'!T139:Y139+'(申)10%'!T139:Y139 -> 1209724143 | Z139: AA | AZ139: 申告書⑦
C141: 2 | D141: 消費税の納付税額の計算
E142: 消費税額 | T142: ='(申)3%'!T142:Y142+'(申)5%'!T142:Y142+'(申)8%'!T142:Y142+'(申)軽8%'!T142:Y142+'(申)10%'!T142:Y142 -> 1472763219
E143: 控除税額 | T143: ='(申)3%'!T143:Y143+'(申)5%'!T143:Y143+'(申)8%'!T143:Y143+'(申)軽8%'!T143:Y143+'(申)10%'!T143:Y143 -> 1209724143
E144: 差引税額 | T144: =ROUNDDOWN('(申)3%'!T144:Y144+'(申)5%'!T144:Y144+'(申)8%'!T144:Y144+'(申)軽8%'!T144:Y144+'(申)10%'!T144:Y144,-2) -> 268070800 | Z144: AB | AZ144: 申告書⑨
E146: 中間納付税額 | T146: =基礎数値!I22 -> 365767600 | Z146: AC | AB146: ※ 中間納付のうち、地方消費税分は含まない | AZ146: 申告書⑩
E148: 納付税額 | T148: =T144-T146 -> -97696800 | Z148: AD | AB148: ※ AB－AC | AH148: ※ マイナスの場合は申告書⑫ | AZ148: 申告書⑪
C150: 3 | D150: 地方消費税の税額の計算
E151: 地方消費税の課税標準となる税額 | T151: ='(申)3%'!T151:Y151+'(申)5%'!T151:Y151+'(申)8%'!T151:Y151+'(申)軽8%'!T151:Y151+'(申)10%'!T151:Y151 -> 268070829 | AZ151: 申告書⑱
E152: 納税額 | T152: =ROUNDDOWN('(申)3%'!T152:Y152+'(申)5%'!T152:Y152+'(申)8%'!T152:Y152+'(申)軽8%'!T152:Y152+'(申)10%'!T152:Y152,-2) -> 75467800 | Z152: AE | AZ152: 申告書⑳
E154: 中間納付税額 | T154: =基礎数値!I23 -> 103164600 | Z154: AF | AB154: ※ 中間納付のうち、地方消費税分 | AZ154: 申告書21
E156: 納付税額 | T156: =T152-T154 -> -27696800 | Z156: AG | AB156: ※ AE－AF | AH156: ※ マイナスの場合は申告書23 | AZ156: 申告書22
C158: 4 | D158: 消費税及び地方消費税の合計納付税額
E159: 消費税及び地方消費税の合計納付税額 | T159: =T148+T156 -> -125393600 | AB159: ※ AD＋AG | AZ159: 申告書26

Sheet 消費税旧
A1: =+CONCATENATE("令和",MID([1]雨汚水!D1,3,1),"年度決算における消費税額チェック") -> 令和５年度決算における消費税額チェック
B3: ３条税込み収入額 | D3: =+'[2]3条収入'!E69 -> 44454711283 | H3: 【消費税雑支出】
B4: ３条税抜き収入額（消費税雑収入除く。） | D4: =+'[2]3条収入'!AI69-'[2]3条収入'!AI54 -> 42570161569 | I4: 調整項目 | J4: 雑支出計上 | K4: 雑収益計上
B5: ３条仮受消費税（控除前課税標準額） | D5: =D3-D4 -> 1884549714 | E5: A | I5: 特定収入に係る課税仕入れ等の税額 | J5: ='[2]3条収入'!AH69 -> 210253123
B6: 課税標準額から控除するものに係る税額 | D6: =SUM(J49:J51) -> 0 | E6: B | I6: 仮受消費税からの控除
B7: 課税標準額に対する消費税額 | D7: =D3-D4-D6 -> 1884549714 | E7: ①=A-B | I7: 仮払消費税からの控除
B8: ３条税込み支出額（消費税除く。） | D8: =+'[3]3条支出'!E41 -> 42643669657 | I8: 課税売上割合を乗じることにより控除できなくなった額 ⑦=②-③-（④-⑤） | J8: =D12-G12-(D13-G13) -> 2233728
B9: ３条税抜き支出額（消費税雑支出除く。） | D9: =+'[3]3条支出'!T41-[3]営外!T17-[3]営外!T18-[3]営外!$T$19 -> 41815647458 | I9: 免税事業者に係る控除不能額 | J9: =-J77 -> 629
B10: ３条仮払消費税（控除前） | D10: =D8-D9 -> 828022199 | E10: C
B11: 課税仕入れから控除する税額 | D11: =SUM(J63:J72) -> 970163 | E11: D | I11: 返還等対価、貸倒れに係る税額 | K11: =-SUM(J73:J77) -> -1879936
B12: 課税仕入れに係る消費税額（控除後） | D12: =D8-D9-D11 -> 827052036 | E12: ②=C-D | F12: 課税仕入等の税額（②×課税売上割合） | G12: =ROUNDDOWN(D12*G43/G44,0) -> 824056879 | H12: ③ | I12: 計 | J12: =SUM(J5:J11) -> 212487480 | K12: =SUM(K5:K11) -> -1879936
B13: ３条の控除不可消費税（雑支出） | D13: =+'[2]3条収入'!AH69 -> 210253123 | E13: ④ | F13: 特定収入に係る課税仕入の額（④×課税売上割合） | G13: =ROUNDDOWN(D13*G43/G44,0) -> 209491694 | H13: ⑤ | J13: =+SUM(J7:J9) -> 2234357 | K13: =+IF(J13=[3]営外!T18+[3]営外!T19,"←営外シートR18と一致","←左の値を営外シートR18に直打ち入力すること") -> ←左の値を営外シートR18に直打ち入力すること
F14: 返還等対価、貸倒れに係る税額 | G14: =SUM(J68:J77) -> 2850099 | H14: E | K14: ↑現在の決算作業では、計算式により消費税シートから値が飛ぶようになっているため不要
F15: 仕入控除税額（③－⑤＋E） | G15: =G12-G13+G14 -> 617415284 | H15: ⑥
B16: ３条で納付すべき消費税 | D16: =D7-G15 -> 1267134430 | E16: ｱ=①－⑥
B18: ４条税込み収入額 | D18: =+'[4]4条収入'!E91 -> 42025205141
B19: ４条税抜き収入額 | D19: =+'[4]4条収入'!AI91 -> 42021596831
B20: ４条仮受消費税 | D20: =D18-D19 -> 3608310 | E20: ①' | I20: 課税売上割合を乗じることにより控除できなくなった額 ⑦'=②'-③'-（④'-⑤'）
B21: ４条税込み支出額 | D21: =+'[5]4条支出'!E41 -> 61875977537 | I21: =D23-G23-(D24-G24) -> 3370060
B22: ４条税抜き支出額 | D22: =+'[5]4条支出'!T41 -> 60396080350
B23: ４条仮払消費税 | D23: =D21-D22 -> 1479897187 | E23: ②' | F23: 課税仕入等の税額（②'×課税売上割合） | G23: =ROUNDDOWN(D23*G43/G44,0) -> 1474537761 | H23: ③'
B24: ４条の控除不可消費税 | D24: =+'[4]4条収入'!AH91 -> 549323121 | E24: ④' | F24: 特定収入に係る課税仕入の額（④'×課税売上割合） | G24: =ROUNDDOWN(D24*G43/G44,0) -> 547333755 | H24: ⑤'
F25: 仕入控除税額（③'－⑤'） | G25: =G23-G24 -> 927204006 | H25: ⑥'
B26: ４条で納付すべき消費税（資本的収支調整額） | D26: =D20-G25 -> -923595696 | E26: ｲ=①'－⑥'
B28: 下水道事業会計消費税納付額 | D28: =D16+D26 -> 343538734 | E28: ｱ+ｲ
B29: 決算計上消費税額 | D29: =+'[6](繰)3条支出 '!G22 -> 0
B30: 差引き | D30: =D28-D29 -> 343538734
F33: ３条課税売上額 (a) | G33: =+'[2]3条収入'!K69 -> 20730055582
F34: ３条仮受消費税額 (b) | G34: =D5 -> 1884549714
C35: 申告納付額（実際の納付額） | D35: =+'(申)計'!T146+'(申)計'!T154+'(申)計'!T159 -> 343538600 | F35: 課税売上から控除するもの (ｱ) | G35: =SUM(I49:I58) -> 9708919
C36: 差 | D36: =D28-D35 -> 134 | F36: ３条非課税収入額 (ｃ) | G36: =+'[2]3条収入'!L69 -> 22644840
F37: ４条課税売上額 (d) | G37: =+'[4]4条収入'!K91 -> 39691410
F38: ４条仮受消費税額 (e) | G38: =D20 -> 3608310
F39: ４条非課税収入額 (f) | G39: =+'[4]4条収入'!L91 -> 45948113
F40: 免税額 | G40: =+'[2]3条収入'!M69 -> 86860
F41: 課税売上割合｛(a-b-ｱ)+(d-e)｝／｛(a-b-ｱ+c)+(d-e+f)｝ | G41: =ROUNDDOWN((G33-G34-G35+G37-G38)/(G33-G34-G35+G36+G37-G38+G39),4) -> 0.9963
F43: 課税資産の譲渡等の対価の額（課税売上（税抜）+免税売上） | G43: =(G33-G34-G35)+(G37-G38)+G40 -> 18871966909
F44: 資産の譲渡等の対価の額（課税売上（税抜）+免税売上+非課税売上） | G44: =(G33-G34-G35+G36)+(G37-G38+G39)+G40 -> 18940559862
F48: ※ 課税売上から控除するもの 内訳 | G48: 税込 | I48: 税抜 | J48: 税額
F49: 仕入対価の返還等の額（3%） | G49: =+対価返還!BC3 -> 0 | H49: → | I49: =+対価返還!BM3 -> 0 | J49: =+G49-I49 -> 0
F50: 仕入対価の返還等の額（5%） | G50: =+対価返還!BC4 -> 0 | H50: → | I50: =+対価返還!BM4 -> 0 | J50: =+G50-I50 -> 0
F51: 仕入対価の返還等の額（8%） | G51: =+対価返還!BC5 -> 0 | H51: → | I51: =+対価返還!BM5 -> 0 | J51: =+G51-I51 -> 0
F52: 仕入対価の返還等の額（8%軽） | G52: =+対価返還!BC6 -> 0 | H52: → | I52: =+対価返還!BM6 -> 0 | J52: =+G52-I52 -> 0
F53: 仕入対価の返還等の額（10%） | G53: =+対価返還!BC7 -> 0 | H53: → | I53: =+対価返還!BM7 -> 0 | J53: =+G53-I53 -> 0
F54: 売上対価の返還等の額（3%） | G54: =+対価返還!BC9 -> 0 | H54: → | I54: =+対価返還!BM9 -> 0 | J54: =+G54-I54 -> 0
F55: 売上対価の返還等の額（5%） | G55: =+対価返還!BC10 -> 0 | H55: → | I55: =+対価返還!BM10 -> 0 | J55: =+G55-I55 -> 0
F56: 売上対価の返還等の額（8%） | G56: =+対価返還!BC11 -> 39339 | H56: → | I56: =+対価返還!BM11 -> 36425 | J56: =+G56-I56 -> 2914
F57: 売上対価の返還等の額（8%軽） | G57: =+対価返還!BC12 -> 0 | H57: → | I57: =+対価返還!BM12 -> 0 | J57: =+G57-I57 -> 0
F58: 売上対価の返還等の額（10%） | G58: =+対価返還!BC13 -> 10639743 | H58: → | I58: =+対価返還!BM13 -> 9672494 | J58: =+G58-I58 -> 967249
J59: =SUM(J49:J58) -> 970163
F62: ※ 仮払消費税から控除するもの 内訳 | G62: 税込 | I62: 税抜 | J62: 税額
F63: 仕入対価の返還等の額（3%） | G63: =G49 -> 0 | H63: → | J63: =J49 -> 0
F64: 仕入対価の返還等の額（5%） | G64: =G50 -> 0 | H64: → | J64: =J50 -> 0
F65: 仕入対価の返還等の額（8%） | G65: =G51 -> 0 | H65: → | J65: =J51 -> 0
F66: 仕入対価の返還等の額（8%軽） | G66: =G52 -> 0 | H66: → | J66: =J52 -> 0
F67: 仕入対価の返還等の額（10%） | G67: =G53 -> 0 | H67: → | J67: =J53 -> 0
F68: 売上対価の返還等の額（3%） | G68: =G54 -> 0 | H68: → | J68: =J54 -> 0
F69: 売上対価の返還等の額（5%） | G69: =G55 -> 0 | H69: → | J69: =J55 -> 0
F70: 売上対価の返還等の額（8%） | G70: =G56 -> 39339 | H70: → | J70: =J56 -> 2914
F71: 売上対価の返還等の額（8%軽） | G71: =G57 -> 0 | H71: → | J71: =J57 -> 0
F72: 売上対価の返還等の額（10%） | G72: =G58 -> 10639743 | H72: → | J72: =J58 -> 967249
F73: 貸倒れに係る金額（3%） | G73: =基礎数値!D17 -> 0 | H73: → | J73: =ROUNDDOWN(G73*3/103,0) -> 0
F74: 貸倒れに係る金額（5%） | G74: =基礎数値!E17 -> 1120996 | H74: → | J74: =ROUNDDOWN(G74*5/105,0) -> 53380
F75: 貸倒れに係る金額（8%） | G75: =基礎数値!F17 -> 24667001 | H75: → | J75: =ROUNDDOWN(G75*8/108,0) -> 1827185
F76: 貸倒れに係る金額（10%） | G76: =基礎数値!H17 -> 0 | H76: → | J76: =ROUNDDOWN(G76*10/110,0) -> 0
F77: 免税事業者との取引額 | G77: =基礎数値!H16*-1 -> -34600 | H77: → | J77: =ROUNDDOWN(G77*0.2*10/110,0) -> -629
H78: 計 | J78: =SUM(J63:J77) -> 2850099

Sheet 対価返還
AV1: 雨水（税込） | AZ1: 汚水 | BC1: 合計 | BD1: チェック | BF1: 雨水（税抜） | BJ1: 汚水（税抜） | BM1: 合計 | BN1: 備考
AV2: 区域内 | AW2: 区域外 | AX2: 一般行政 | AY2: 計 | AZ2: 基準内 | BA2: 基準外 | BB2: 計 | BF2: 区域内 | BG2: 区域外 | BH2: 一般行政 | BI2: 計 | BJ2: 基準内 | BK2: 基準外 | BL2: 計
AS3: 仕入対価の返還等の額（3%） | AT3: 3 | AV3: =+SUMIFS(AV$18:AV$296,$P$18:$P$296,"営業外収益",$AT$18:$AT$296,$AT3)+SUMIFS(AV$18:AV$296,$P$18:$P$296,"特別利益",$AT$18:$AT$296,$AT3) -> 0 | AW3: =+SUMIFS(AW$18:AW$296,$P$18:$P$296,"営業外収益",$AT$18:$AT$296,$AT3)+SUMIFS(AW$18:AW$296,$P$18:$P$296,"特別利益",$AT$18:$AT$296,$AT3) -> 0 | AX3: =+SUMIFS(AX$18:AX$296,$P$18:$P$296,"営業外収益",$AT$18:$AT$296,$AT3)+SUMIFS(AX$18:AX$296,$P$18:$P$296,"特別利益",$AT$18:$AT$296,$AT3) -> 0 | AY3: =+SUMIFS(AY$18:AY$296,$P$18:$P$296,"営業外収益",$AT$18:$AT$296,$AT3)+SUMIFS(AY$18:AY$296,$P$18:$P$296,"特別利益",$AT$18:$AT$296,$AT3) -> 0 | AZ3: =+SUMIFS(AZ$18:AZ$296,$P$18:$P$296,"営業外収益",$AT$18:$AT$296,$AT3)+SUMIFS(AZ$18:AZ$296,$P$18:$P$296,"特別利益",$AT$18:$AT$296,$AT3) -> 0 | BA3: =+SUMIFS(BA$18:BA$296,$P$18:$P$296,"営業外収益",$AT$18:$AT$296,$AT3)+SUMIFS(BA$18:BA$296,$P$18:$P$296,"特別利益",$AT$18:$AT$296,$AT3) -> 0 | BB3: =+SUMIFS(BB$18:BB$296,$P$18:$P$296,"営業外収益",$AT$18:$AT$296,$AT3)+SUMIFS(BB$18:BB$296,$P$18:$P$296,"特別利益",$AT$18:$AT$296,$AT3) -> 0 | BC3: =+SUMIFS(BC$18:BC$296,$P$18:$P$296,"営業外収益",$AT$18:$AT$296,$AT3)+SUMIFS(BC$18:BC$296,$P$18:$P$296,"特別利益",$AT$18:$AT$296,$AT3) -> 0 | BD3: =+SUMIFS(BD$18:BD$296,$P$18:$P$296,"営業外収益",$AT$18:$AT$296,$AT3)+SUMIFS(BD$18:BD$296,$P$18:$P$296,"特別利益",$AT$18:$AT$296,$AT3) -> 0 | BF3: =+IFERROR(ROUNDUP(AV3*100/(100+$AT3),0),AV3) -> 0 | BG3: =+IFERROR(ROUNDUP(AW3*100/(100+$AT3),0),AW3) -> 0 | BH3: =+IFERROR(ROUNDUP(AX3*100/(100+$AT3),0),AX3) -> 0 | BI3: =SUM(BF3:BH3) -> 0 | BJ3: =+IFERROR(ROUNDUP(AZ3*100/(100+$AT3),0),AZ3) -> 0 | BK3: =+IFERROR(ROUNDUP(BA3*100/(100+$AT3),0),BA3) -> 0 | BL3: =SUM(BJ3:BK3) -> 0 | BM3: =+BI3+BL3 -> 0 | BO3: =+BC3-BM3 -> 0
AS4: 仕入対価の返還等の額（5%） | AT4: 5 | AV4: =+SUMIFS(AV$18:AV$296,$P$18:$P$296,"営業外収益",$AT$18:$AT$296,$AT4)+SUMIFS(AV$18:AV$296,$P$18:$P$296,"特別利益",$AT$18:$AT$296,$AT4) -> 0 | AW4: =+SUMIFS(AW$18:AW$296,$P$18:$P$296,"営業外収益",$AT$18:$AT$296,$AT4)+SUMIFS(AW$18:AW$296,$P$18:$P$296,"特別利益",$AT$18:$AT$296,$AT4) -> 0 | AX4: =+SUMIFS(AX$18:AX$296,$P$18:$P$296,"営業外収益",$AT$18:$AT$296,$AT4)+SUMIFS(AX$18:AX$296,$P$18:$P$296,"特別利益",$AT$18:$AT$296,$AT4) -> 0 | AY4: =+SUMIFS(AY$18:AY$296,$P$18:$P$296,"営業外収益",$AT$18:$AT$296,$AT4)+SUMIFS(AY$18:AY$296,$P$18:$P$296,"特別利益",$AT$18:$AT$296,$AT4) -> 0 | AZ4: =+SUMIFS(AZ$18:AZ$296,$P$18:$P$296,"営業外収益",$AT$18:$AT$296,$AT4)+SUMIFS(AZ$18:AZ$296,$P$18:$P$296,"特別利益",$AT$18:$AT$296,$AT4) -> 0 | BA4: =+SUMIFS(BA$18:BA$296,$P$18:$P$296,"営業外収益",$AT$18:$AT$296,$AT4)+SUMIFS(BA$18:BA$296,$P$18:$P$296,"特別利益",$AT$18:$AT$296,$AT4) -> 0 | BB4: =+SUMIFS(BB$18:BB$296,$P$18:$P$296,"営業外収益",$AT$18:$AT$296,$AT4)+SUMIFS(BB$18:BB$296,$P$18:$P$296,"特別利益",$AT$18:$AT$296,$AT4) -> 0 | BC4: =+SUMIFS(BC$18:BC$296,$P$18:$P$296,"営業外収益",$AT$18:$AT$296,$AT4)+SUMIFS(BC$18:BC$296,$P$18:$P$296,"特別利益",$AT$18:$AT$296,$AT4) -> 0 | BD4: =+SUMIFS(BD$18:BD$296,$P$18:$P$296,"営業外収益",$AT$18:$AT$296,$AT4)+SUMIFS(BD$18:BD$296,$P$18:$P$296,"特別利益",$AT$18:$AT$296,$AT4) -> 0 | BF4: =+IFERROR(ROUNDUP(AV4*100/(100+$AT4),0),AV4) -> 0 | BG4: =+IFERROR(ROUNDUP(AW4*100/(100+$AT4),0),AW4) -> 0 | BH4: =+IFERROR(ROUNDUP(AX4*100/(100+$AT4),0),AX4) -> 0 | BI4: =SUM(BF4:BH4) -> 0 | BJ4: =+IFERROR(ROUNDUP(AZ4*100/(100+$AT4),0),AZ4) -> 0 | BK4: =+IFERROR(ROUNDUP(BA4*100/(100+$AT4),0),BA4) -> 0 | BL4: =SUM(BJ4:BK4) -> 0 | BM4: =+BI4+BL4 -> 0 | BO4: =+BC4-BM4 -> 0
AS5: 仕入対価の返還等の額（8%） | AT5: 8 | AV5: =+SUMIFS(AV$18:AV$296,$P$18:$P$296,"営業外収益",$AT$18:$AT$296,$AT5)+SUMIFS(AV$18:AV$296,$P$18:$P$296,"特別利益",$AT$18:$AT$296,$AT5) -> 0 | AW5: =+SUMIFS(AW$18:AW$296,$P$18:$P$296,"営業外収益",$AT$18:$AT$296,$AT5)+SUMIFS(AW$18:AW$296,$P$18:$P$296,"特別利益",$AT$18:$AT$296,$AT5) -> 0 | AX5: =+SUMIFS(AX$18:AX$296,$P$18:$P$296,"営業外収益",$AT$18:$AT$296,$AT5)+SUMIFS(AX$18:AX$296,$P$18:$P$296,"特別利益",$AT$18:$AT$296,$AT5) -> 0 | AY5: =+SUMIFS(AY$18:AY$296,$P$18:$P$296,"営業外収益",$AT$18:$AT$296,$AT5)+SUMIFS(AY$18:AY$296,$P$18:$P$296,"特別利益",$AT$18:$AT$296,$AT5) -> 0 | AZ5: =+SUMIFS(AZ$18:AZ$296,$P$18:$P$296,"営業外収益",$AT$18:$AT$296,$AT5)+SUMIFS(AZ$18:AZ$296,$P$18:$P$296,"特別利益",$AT$18:$AT$296,$AT5) -> 0 | BA5: =+SUMIFS(BA$18:BA$296,$P$18:$P$296,"営業外収益",$AT$18:$AT$296,$AT5)+SUMIFS(BA$18:BA$296,$P$18:$P$296,"特別利益",$AT$18:$AT$296,$AT5) -> 0 | BB5: =+SUMIFS(BB$18:BB$296,$P$18:$P$296,"営業外収益",$AT$18:$AT$296,$AT5)+SUMIFS(BB$18:BB$296,$P$18:$P$296,"特別利益",$AT$18:$AT$296,$AT5) -> 0 | BC5: =+SUMIFS(BC$18:BC$296,$P$18:$P$296,"営業外収益",$AT$18:$AT$296,$AT5)+SUMIFS(BC$18:BC$296,$P$18:$P$296,"特別利益",$AT$18:$AT$296,$AT5) -> 0 | BD5: =+SUMIFS(BD$18:BD$296,$P$18:$P$296,"営業外収益",$AT$18:$AT$296,$AT5)+SUMIFS(BD$18:BD$296,$P$18:$P$296,"特別利益",$AT$18:$AT$296,$AT5) -> 0 | BF5: =+IFERROR(ROUNDUP(AV5*100/(100+$AT5),0),AV5) -> 0 | BG5: =+IFERROR(ROUNDUP(AW5*100/(100+$AT5),0),AW5) -> 0 | BH5: =+IFERROR(ROUNDUP(AX5*100/(100+$AT5),0),AX5) -> 0 | BI5: =SUM(BF5:BH5) -> 0 | BJ5: =+IFERROR(ROUNDUP(AZ5*100/(100+$AT5),0),AZ5) -> 0 | BK5: =+IFERROR(ROUNDUP(BA5*100/(100+$AT5),0),BA5) -> 0 | BL5: =SUM(BJ5:BK5) -> 0 | BM5: =+BI5+BL5 -> 0 | BO5: =+BC5-BM5 -> 0
AS6: 仕入対価の返還等の額（8%（軽）） | AT6: 8 | AV6: =+SUMIFS(AV$18:AV$296,$P$18:$P$296,"営業外収益",$AS$18:$AS$296,81)+SUMIFS(AV$18:AV$296,$P$18:$P$296,"特別利益",$AS$18:$AS$296,81) -> 0 | AW6: =+SUMIFS(AW$18:AW$296,$P$18:$P$296,"営業外収益",$AS$18:$AS$296,81)+SUMIFS(AW$18:AW$296,$P$18:$P$296,"特別利益",$AS$18:$AS$296,81) -> 0 | AX6: =+SUMIFS(AX$18:AX$296,$P$18:$P$296,"営業外収益",$AS$18:$AS$296,81)+SUMIFS(AX$18:AX$296,$P$18:$P$296,"特別利益",$AS$18:$AS$296,81) -> 0 | AY6: =+SUMIFS(AY$18:AY$296,$P$18:$P$296,"営業外収益",$AS$18:$AS$296,81)+SUMIFS(AY$18:AY$296,$P$18:$P$296,"特別利益",$AS$18:$AS$296,81) -> 0 | AZ6: =+SUMIFS(AZ$18:AZ$296,$P$18:$P$296,"営業外収益",$AS$18:$AS$296,81)+SUMIFS(AZ$18:AZ$296,$P$18:$P$296,"特別利益",$AS$18:$AS$296,81) -> 0 | BA6: =+SUMIFS(BA$18:BA$296,$P$18:$P$296,"営業外収益",$AS$18:$AS$296,81)+SUMIFS(BA$18:BA$296,$P$18:$P$296,"特別利益",$AS$18:$AS$296,81) -> 0 | BB6: =+SUMIFS(BB$18:BB$296,$P$18:$P$296,"営業外収益",$AS$18:$AS$296,81)+SUMIFS(BB$18:BB$296,$P$18:$P$296,"特別利益",$AS$18:$AS$296,81) -> 0 | BC6: =+SUMIFS(BC$18:BC$296,$P$18:$P$296,"営業外収益",$AS$18:$AS$296,81)+SUMIFS(BC$18:BC$296,$P$18:$P$296,"特別利益",$AS$18:$AS$296,81) -> 0 | BD6: =+SUMIFS(BD$18:BD$296,$P$18:$P$296,"営業外収益",$AS$18:$AS$296,81)+SUMIFS(BD$18:BD$296,$P$18:$P$296,"特別利益",$AS$18:$AS$296,81) -> 0 | BF6: =+IFERROR(ROUNDUP(AV6*100/(100+$AT6),0),AV6) -> 0 | BG6: =+IFERROR(ROUNDUP(AW6*100/(100+$AT6),0),AW6) -> 0 | BH6: =+IFERROR(ROUNDUP(AX6*100/(100+$AT6),0),AX6) -> 0 | BI6: =SUM(BF6:BH6) -> 0 | BJ6: =+IFERROR(ROUNDUP(AZ6*100/(100+$AT6),0),AZ6) -> 0 | BK6: =+IFERROR(ROUNDUP(BA6*100/(100+$AT6),0),BA6) -> 0 | BL6: =SUM(BJ6:BK6) -> 0 | BM6: =+BI6+BL6 -> 0 | BO6: =+BC6-BM6 -> 0
AS7: 仕入対価の返還等の額（10%） | AT7: 10 | AV7: =+SUMIFS(AV$18:AV$296,$P$18:$P$296,"営業外収益",$AT$18:$AT$296,$AT7)+SUMIFS(AV$18:AV$296,$P$18:$P$296,"特別利益",$AT$18:$AT$296,$AT7) -> 0 | AW7: =+SUMIFS(AW$18:AW$296,$P$18:$P$296,"営業外収益",$AT$18:$AT$296,$AT7)+SUMIFS(AW$18:AW$296,$P$18:$P$296,"特別利益",$AT$18:$AT$296,$AT7) -> 0 | AX7: =+SUMIFS(AX$18:AX$296,$P$18:$P$296,"営業外収益",$AT$18:$AT$296,$AT7)+SUMIFS(AX$18:AX$296,$P$18:$P$296,"特別利益",$AT$18:$AT$296,$AT7) -> 0 | AY7: =+SUMIFS(AY$18:AY$296,$P$18:$P$296,"営業外収益",$AT$18:$AT$296,$AT7)+SUMIFS(AY$18:AY$296,$P$18:$P$296,"特別利益",$AT$18:$AT$296,$AT7) -> 0 | AZ7: =+SUMIFS(AZ$18:AZ$296,$P$18:$P$296,"営業外収益",$AT$18:$AT$296,$AT7)+SUMIFS(AZ$18:AZ$296,$P$18:$P$296,"特別利益",$AT$18:$AT$296,$AT7) -> 0 | BA7: =+SUMIFS(BA$18:BA$296,$P$18:$P$296,"営業外収益",$AT$18:$AT$296,$AT7)+SUMIFS(BA$18:BA$296,$P$18:$P$296,"特別利益",$AT$18:$AT$296,$AT7) -> 0 | BB7: =+SUMIFS(BB$18:BB$296,$P$18:$P$296,"営業外収益",$AT$18:$AT$296,$AT7)+SUMIFS(BB$18:BB$296,$P$18:$P$296,"特別利益",$AT$18:$AT$296,$AT7) -> 0 | BC7: =+SUMIFS(BC$18:BC$296,$P$18:$P$296,"営業外収益",$AT$18:$AT$296,$AT7)+SUMIFS(BC$18:BC$296,$P$18:$P$296,"特別利益",$AT$18:$AT$296,$AT7) -> 0 | BD7: =+SUMIFS(BD$18:BD$296,$P$18:$P$296,"営業外収益",$AT$18:$AT$296,$AT7)+SUMIFS(BD$18:BD$296,$P$18:$P$296,"特別利益",$AT$18:$AT$296,$AT7) -> 0 | BF7: =+IFERROR(ROUNDUP(AV7*100/(100+$AT7),0),AV7) -> 0 | BG7: =+IFERROR(ROUNDUP(AW7*100/(100+$AT7),0),AW7) -> 0 | BH7: =+IFERROR(ROUNDUP(AX7*100/(100+$AT7),0),AX7) -> 0 | BI7: =SUM(BF7:BH7) -> 0 | BJ7: =+IFERROR(ROUNDUP(AZ7*100/(100+$AT7),0),AZ7) -> 0 | BK7: =+IFERROR(ROUNDUP(BA7*100/(100+$AT7),0),BA7) -> 0 | BL7: =SUM(BJ7:BK7) -> 0 | BM7: =+BI7+BL7 -> 0 | BO7: =+BC7-BM7 -> 0
AS8: 仕入対価の返還の額 計 | AV8: =+SUM(AV3:AV7) -> 0 | AW8: =+SUM(AW3:AW7) -> 0 | AX8: =+SUM(AX3:AX7) -> 0 | AY8: =+SUM(AY3:AY7) -> 0 | AZ8: =+SUM(AZ3:AZ7) -> 0 | BA8: =+SUM(BA3:BA7) -> 0 | BB8: =+SUM(BB3:BB7) -> 0 | BC8: =+SUM(BC3:BC7) -> 0 | ... BM8: =+SUM(BM3:BM7) -> 0 | BO8: =+BC8-BM8 -> 0
AS9: 売上対価の返還等の額（3%） | AT9: 3 | AV9: =+SUMIFS(AV$18:AV$296,$P$18:$P$296,"営業外費用",$AT$18:$AT$296,$AT9)+SUMIFS(AV$18:AV$296,$P$18:$P$296,"特別損失",$AT$18:$AT$296,$AT9) -> 0 | AW9: =+SUMIFS(AW$18:AW$296,$P$18:$P$296,"営業外費用",$AT$18:$AT$296,$AT9)+SUMIFS(AW$18:AW$296,$P$18:$P$296,"特別損失",$AT$18:$AT$296,$AT9) -> 0 | AX9: =+SUMIFS(AX$18:AX$296,$P$18:$P$296,"営業外費用",$AT$18:$AT$296,$AT9)+SUMIFS(AX$18:AX$296,$P$18:$P$296,"特別損失",$AT$18:$AT$296,$AT9) -> 0 | AY9: =+SUMIFS(AY$18:AY$296,$P$18:$P$296,"営業外費用",$AT$18:$AT$296,$AT9)+SUMIFS(AY$18:AY$296,$P$18:$P$296,"特別損失",$AT$18:$AT$296,$AT9) -> 0 | AZ9: =+SUMIFS(AZ$18:AZ$296,$P$18:$P$296,"営業外費用",$AT$18:$AT$296,$AT9)+SUMIFS(AZ$18:AZ$296,$P$18:$P$296,"特別損失",$AT$18:$AT$296,$AT9) -> 0 | BA9: =+SUMIFS(BA$18:BA$296,$P$18:$P$296,"営業外費用",$AT$18:$AT$296,$AT9)+SUMIFS(BA$18:BA$296,$P$18:$P$296,"特別損失",$AT$18:$AT$296,$AT9) -> 0 | BB9: =+SUMIFS(BB$18:BB$296,$P$18:$P$296,"営業外費用",$AT$18:$AT$296,$AT9)+SUMIFS(BB$18:BB$296,$P$18:$P$296,"特別損失",$AT$18:$AT$296,$AT9) -> 0 | BC9: =+SUMIFS(BC$18:BC$296,$P$18:$P$296,"営業外費用",$AT$18:$AT$296,$AT9)+SUMIFS(BC$18:BC$296,$P$18:$P$296,"特別損失",$AT$18:$AT$296,$AT9) -> 0 | BD9: =+SUMIFS(BD$18:BD$296,$P$18:$P$296,"営業外費用",$AT$18:$AT$296,$AT9)+SUMIFS(BD$18:BD$296,$P$18:$P$296,"特別損失",$AT$18:$AT$296,$AT9) -> 0 | BF9: =+IFERROR(ROUNDUP(AV9*100/(100+$AT9),0),AV9) -> 0 | BG9: =+IFERROR(ROUNDUP(AW9*100/(100+$AT9),0),AW9) -> 0 | BH9: =+IFERROR(ROUNDUP(AX9*100/(100+$AT9),0),AX9) -> 0 | BI9: =SUM(BF9:BH9) -> 0 | BJ9: =+IFERROR(ROUNDUP(AZ9*100/(100+$AT9),0),AZ9) -> 0 | BK9: =+IFERROR(ROUNDUP(BA9*100/(100+$AT9),0),BA9) -> 0 | BL9: =SUM(BJ9:BK9) -> 0 | BM9: =+BI9+BL9 -> 0 | BO9: =+BC9-BM9 -> 0
AS10: 売上対価の返還等の額（5%） | AT10: 5 | AV10: =+SUMIFS(AV$18:AV$296,$P$18:$P$296,"営業外費用",$AT$18:$AT$296,$AT10)+SUMIFS(AV$18:AV$296,$P$18:$P$296,"特別損失",$AT$18:$AT$296,$AT10) -> 0 | AW10: =+SUMIFS(AW$18:AW$296,$P$18:$P$296,"営業外費用",$AT$18:$AT$296,$AT10)+SUMIFS(AW$18:AW$296,$P$18:$P$296,"特別損失",$AT$18:$AT$296,$AT10) -> 0 | AX10: =+SUMIFS(AX$18:AX$296,$P$18:$P$296,"営業外費用",$AT$18:$AT$296,$AT10)+SUMIFS(AX$18:AX$296,$P$18:$P$296,"特別損失",$AT$18:$AT$296,$AT10) -> 0 | AY10: =+SUMIFS(AY$18:AY$296,$P$18:$P$296,"営業外費用",$AT$18:$AT$296,$AT10)+SUMIFS(AY$18:AY$296,$P$18:$P$296,"特別損失",$AT$18:$AT$296,$AT10) -> 0 | AZ10: =+SUMIFS(AZ$18:AZ$296,$P$18:$P$296,"営業外費用",$AT$18:$AT$296,$AT10)+SUMIFS(AZ$18:AZ$296,$P$18:$P$296,"特別損失",$AT$18:$AT$296,$AT10) -> 0 | BA10: =+SUMIFS(BA$18:BA$296,$P$18:$P$296,"営業外費用",$AT$18:$AT$296,$AT10)+SUMIFS(BA$18:BA$296,$P$18:$P$296,"特別損失",$AT$18:$AT$296,$AT10) -> 0 | BB10: =+SUMIFS(BB$18:BB$296,$P$18:$P$296,"営業外費用",$AT$18:$AT$296,$AT10)+SUMIFS(BB$18:BB$296,$P$18:$P$296,"特別損失",$AT$18:$AT$296,$AT10) -> 0 | BC10: =+SUMIFS(BC$18:BC$296,$P$18:$P$296,"営業外費用",$AT$18:$AT$296,$AT10)+SUMIFS(BC$18:BC$296,$P$18:$P$296,"特別損失",$AT$18:$AT$296,$AT10) -> 0 | BD10: =+SUMIFS(BD$18:BD$296,$P$18:$P$296,"営業外費用",$AT$18:$AT$296,$AT10)+SUMIFS(BD$18:BD$296,$P$18:$P$296,"特別損失",$AT$18:$AT$296,$AT10) -> 0 | BF10: =+IFERROR(ROUNDUP(AV10*100/(100+$AT10),0),AV10) -> 0 | BG10: =+IFERROR(ROUNDUP(AW10*100/(100+$AT10),0),AW10) -> 0 | BH10: =+IFERROR(ROUNDUP(AX10*100/(100+$AT10),0),AX10) -> 0 | BI10: =SUM(BF10:BH10) -> 0 | BJ10: =+IFERROR(ROUNDUP(AZ10*100/(100+$AT10),0),AZ10) -> 0 | BK10: =+IFERROR(ROUNDUP(BA10*100/(100+$AT10),0),BA10) -> 0 | BL10: =SUM(BJ10:BK10) -> 0 | BM10: =+BI10+BL10 -> 0 | BO10: =+BC10-BM10 -> 0
AS11: 売上対価の返還等の額（8%） | AT11: 8 | AV11: =+SUMIFS(AV$18:AV$296,$P$18:$P$296,"営業外費用",$AT$18:$AT$296,$AT11)+SUMIFS(AV$18:AV$296,$P$18:$P$296,"特別損失",$AT$18:$AT$296,$AT11) -> 0 | AW11: =+SUMIFS(AW$18:AW$296,$P$18:$P$296,"営業外費用",$AT$18:$AT$296,$AT11)+SUMIFS(AW$18:AW$296,$P$18:$P$296,"特別損失",$AT$18:$AT$296,$AT11) -> 0 | AX11: =+SUMIFS(AX$18:AX$296,$P$18:$P$296,"営業外費用",$AT$18:$AT$296,$AT11)+SUMIFS(AX$18:AX$296,$P$18:$P$296,"特別損失",$AT$18:$AT$296,$AT11) -> 0 | AY11: =+SUMIFS(AY$18:AY$296,$P$18:$P$296,"営業外費用",$AT$18:$AT$296,$AT11)+SUMIFS(AY$18:AY$296,$P$18:$P$296,"特別損失",$AT$18:$AT$296,$AT11) -> 0 | AZ11: =+SUMIFS(AZ$18:AZ$296,$P$18:$P$296,"営業外費用",$AT$18:$AT$296,$AT11)+SUMIFS(AZ$18:AZ$296,$P$18:$P$296,"特別損失",$AT$18:$AT$296,$AT11) -> 0 | BA11: =+SUMIFS(BA$18:BA$296,$P$18:$P$296,"営業外費用",$AT$18:$AT$296,$AT11)+SUMIFS(BA$18:BA$296,$P$18:$P$296,"特別損失",$AT$18:$AT$296,$AT11) -> 39339 | BB11: =+SUMIFS(BB$18:BB$296,$P$18:$P$296,"営業外費用",$AT$18:$AT$296,$AT11)+SUMIFS(BB$18:BB$296,$P$18:$P$296,"特別損失",$AT$18:$AT$296,$AT11) -> 39339 | BC11: =+SUMIFS(BC$18:BC$296,$P$18:$P$296,"営業外費用",$AT$18:$AT$296,$AT11)+SUMIFS(BC$18:BC$296,$P$18:$P$296,"特別損失",$AT$18:$AT$296,$AT11) -> 39339 | BD11: =+SUMIFS(BD$18:BD$296,$P$18:$P$296,"営業外費用",$AT$18:$AT$296,$AT11)+SUMIFS(BD$18:BD$296,$P$18:$P$296,"特別損失",$AT$18:$AT$296,$AT11) -> 0 | BF11: =+IFERROR(ROUNDUP(AV11*100/(100+$AT11),0),AV11) -> 0 | BG11: =+IFERROR(ROUNDUP(AW11*100/(100+$AT11),0),AW11) -> 0 | BH11: =+IFERROR(ROUNDUP(AX11*100/(100+$AT11),0),AX11) -> 0 | BI11: =SUM(BF11:BH11) -> 0 | BJ11: =+IFERROR(ROUNDUP(AZ11*100/(100+$AT11),0),AZ11) -> 0 | BK11: =+IFERROR(ROUNDUP(BA11*100/(100+$AT11),0),BA11) -> 36425 | BL11: =SUM(BJ11:BK11) -> 36425 | BM11: =+BI11+BL11 -> 36425 | BO11: =+BC11-BM11 -> 2914
AS12: 売上対価の返還等の額（8%（軽）） | AT12: 8 | AV12: =+SUMIFS(AV$18:AV$296,$P$18:$P$296,"営業外費用",$AS$18:$AS$296,82)+SUMIFS(AV$18:AV$296,$P$18:$P$296,"特別損失",$AS$18:$AS$296,82) -> 0 | AW12: =+SUMIFS(AW$18:AW$296,$P$18:$P$296,"営業外費用",$AS$18:$AS$296,82)+SUMIFS(AW$18:AW$296,$P$18:$P$296,"特別損失",$AS$18:$AS$296,82) -> 0 | AX12: =+SUMIFS(AX$18:AX$296,$P$18:$P$296,"営業外費用",$AS$18:$AS$296,82)+SUMIFS(AX$18:AX$296,$P$18:$P$296,"特別損失",$AS$18:$AS$296,82) -> 0 | AY12: =+SUMIFS(AY$18:AY$296,$P$18:$P$296,"営業外費用",$AS$18:$AS$296,82)+SUMIFS(AY$18:AY$296,$P$18:$P$296,"特別損失",$AS$18:$AS$296,82) -> 0 | AZ12: =+SUMIFS(AZ$18:AZ$296,$P$18:$P$296,"営業外費用",$AS$18:$AS$296,82)+SUMIFS(AZ$18:AZ$296,$P$18:$P$296,"特別損失",$AS$18:$AS$296,82) -> 0 | BA12: =+SUMIFS(BA$18:BA$296,$P$18:$P$296,"営業外費用",$AS$18:$AS$296,82)+SUMIFS(BA$18:BA$296,$P$18:$P$296,"特別損失",$AS$18:$AS$296,82) -> 0 | BB12: =+SUMIFS(BB$18:BB$296,$P$18:$P$296,"営業外費用",$AS$18:$AS$296,82)+SUMIFS(BB$18:BB$296,$P$18:$P$296,"特別損失",$AS$18:$AS$296,82) -> 0 | BC12: =+SUMIFS(BC$18:BC$296,$P$18:$P$296,"営業外費用",$AS$18:$AS$296,82)+SUMIFS(BC$18:BC$296,$P$18:$P$296,"特別損失",$AS$18:$AS$296,82) -> 0 | BD12: =+SUMIFS(BD$18:BD$296,$P$18:$P$296,"営業外費用",$AS$18:$AS$296,82)+SUMIFS(BD$18:BD$296,$P$18:$P$296,"特別損失",$AS$18:$AS$296,82) -> 0 | BF12: =+IFERROR(ROUNDUP(AV12*100/(100+$AT12),0),AV12) -> 0 | BG12: =+IFERROR(ROUNDUP(AW12*100/(100+$AT12),0),AW12) -> 0 | BH12: =+IFERROR(ROUNDUP(AX12*100/(100+$AT12),0),AX12) -> 0 | BI12: =SUM(BF12:BH12) -> 0 | BJ12: =+IFERROR(ROUNDUP(AZ12*100/(100+$AT12),0),AZ12) -> 0 | BK12: =+IFERROR(ROUNDUP(BA12*100/(100+$AT12),0),BA12) -> 0 | BL12: =SUM(BJ12:BK12) -> 0 | BM12: =+BI12+BL12 -> 0 | BO12: =+BC12-BM12 -> 0
AS13: 売上対価の返還等の額（10%） | AT13: 10 | AV13: =+SUMIFS(AV$18:AV$296,$P$18:$P$296,"営業外費用",$AT$18:$AT$296,$AT13)+SUMIFS(AV$18:AV$296,$P$18:$P$296,"特別損失",$AT$18:$AT$296,$AT13) -> 0 | AW13: =+SUMIFS(AW$18:AW$296,$P$18:$P$296,"営業外費用",$AT$18:$AT$296,$AT13)+SUMIFS(AW$18:AW$296,$P$18:$P$296,"特別損失",$AT$18:$AT$296,$AT13) -> 0 | AX13: =+SUMIFS(AX$18:AX$296,$P$18:$P$296,"営業外費用",$AT$18:$AT$296,$AT13)+SUMIFS(AX$18:AX$296,$P$18:$P$296,"特別損失",$AT$18:$AT$296,$AT13) -> 0 | AY13: =+SUMIFS(AY$18:AY$296,$P$18:$P$296,"営業外費用",$AT$18:$AT$296,$AT13)+SUMIFS(AY$18:AY$296,$P$18:$P$296,"特別損失",$AT$18:$AT$296,$AT13) -> 0 | AZ13: =+SUMIFS(AZ$18:AZ$296,$P$18:$P$296,"営業外費用",$AT$18:$AT$296,$AT13)+SUMIFS(AZ$18:AZ$296,$P$18:$P$296,"特別損失",$AT$18:$AT$296,$AT13) -> 0 | BA13: =+SUMIFS(BA$18:BA$296,$P$18:$P$296,"営業外費用",$AT$18:$AT$296,$AT13)+SUMIFS(BA$18:BA$296,$P$18:$P$296,"特別損失",$AT$18:$AT$296,$AT13) -> 10639743 | BB13: =+SUMIFS(BB$18:BB$296,$P$18:$P$296,"営業外費用",$AT$18:$AT$296,$AT13)+SUMIFS(BB$18:BB$296,$P$18:$P$296,"特別損失",$AT$18:$AT$296,$AT13) -> 10639743 | BC13: =+SUMIFS(BC$18:BC$296,$P$18:$P$296,"営業外費用",$AT$18:$AT$296,$AT13)+SUMIFS(BC$18:BC$296,$P$18:$P$296,"特別損失",$AT$18:$AT$296,$AT13) -> 10639743 | BD13: =+SUMIFS(BD$18:BD$296,$P$18:$P$296,"営業外費用",$AT$18:$AT$296,$AT13)+SUMIFS(BD$18:BD$296,$P$18:$P$296,"特別損失",$AT$18:$AT$296,$AT13) -> 0 | BF13: =+IFERROR(ROUNDUP(AV13*100/(100+$AT13),0),AV13) -> 0 | BG13: =+IFERROR(ROUNDUP(AW13*100/(100+$AT13),0),AW13) -> 0 | BH13: =+IFERROR(ROUNDUP(AX13*100/(100+$AT13),0),AX13) -> 0 | BI13: =SUM(BF13:BH13) -> 0 | BJ13: =+IFERROR(ROUNDUP(AZ13*100/(100+$AT13),0),AZ13) -> 0 | BK13: =+IFERROR(ROUNDUP(BA13*100/(100+$AT13),0),BA13) -> 9672494 | BL13: =SUM(BJ13:BK13) -> 9672494 | BM13: =+BI13+BL13 -> 9672494 | BO13: =+BC13-BM13 -> 967249
AS14: 売上対価の返還の額 計 | AV14: =+SUM(AV9:AV13) -> 0 | AW14: =+SUM(AW9:AW13) -> 0 | AX14: =+SUM(AX9:AX13) -> 0 | AY14: =+SUM(AY9:AY13) -> 0 | AZ14: =+SUM(AZ9:AZ13) -> 0 | BA14: =+SUM(BA9:BA13) -> 10679082 | BB14: =+SUM(BB9:BB13) -> 10679082 | BC14: =+SUM(BC9:BC13) -> 10679082 | ... BM14: =+SUM(BM9:BM13) -> 9708919 | BO14: =+BC14-BM14 -> 970163
A15: ↓以下がコピペ領域
Y16: =+SUBTOTAL(109,Y18:Y948) -> 10679082 | AV16: =+SUBTOTAL(109,AV18:AV948) -> 0 | AW16: =+SUBTOTAL(109,AW18:AW948) -> 0 | AX16: =+SUBTOTAL(109,AX18:AX948) -> 0 | AY16: =+SUBTOTAL(109,AY18:AY948) -> 0 | AZ16: =+SUBTOTAL(109,AZ18:AZ948) -> 0 | BA16: =+SUBTOTAL(109,BA18:BA948) -> 10679082 | BB16: =+SUBTOTAL(109,BB18:BB948) -> 10679082 | BC16: =+SUBTOTAL(109,BC18:BC948) -> 10679082 | BD16: =+SUBTOTAL(109,BD18:BD948) -> 0 | BF16: =+SUBTOTAL(109,BF18:BF948) -> 0 | BG16: =+SUBTOTAL(109,BG18:BG948) -> 0 | BH16: =+SUBTOTAL(109,BH18:BH948) -> 0 | BI16: =+SUBTOTAL(109,BI18:BI948) -> 0 | BJ16: =+SUBTOTAL(109,BJ18:BJ948) -> 0 | BK16: =+SUBTOTAL(109,BK18:BK948) -> 9708919 | BL16: =+SUBTOTAL(109,BL18:BL948) -> 9708919 | BM16: =+SUBTOTAL(109,BM18:BM948) -> 9708919
AL17: ---- | AS17: 0 | AT17: 0 | AV17: 雨水（税込） | AZ17: 汚水 | BC17: 合計 | BD17: チェック | BF17: 雨水（税込） | BJ17: 汚水 | BM17: 合計 | BN17: 備考
A18: 事業区分 | B18: 所属 | C18: 所属名 | D18: 主管課 | E18: 主管課名 | F18: 年月日 | G18: 振替年月日 | H18: 事項 | I18: 種別 | J18: 伝票番号 | K18: 枝番 | L18: 内訳番号 | M18: 現繰 | N18: 予算科目 | O18: 款名称 | P18: 項名称 | Q18: 目名称 | R18: 節名称 | S18: 細節名称 | T18: 事業コード | U18: 事業名 | V18: 予算額 | W18: 概算額 | X18: 確定額 | Y18: 執行額 | Z18: 借方勘定 | AA18: 借方勘定科目 | AB18: 借方金額 | AC18: 貸方勘定 | AD18: 貸方勘定科目 | AE18: 貸方金額 | AF18: 税区分 | AG18: 税率 | AH18: 税額 | AI18: 税抜金額 | AJ18: 債権者 | AL18: 複合伝票番号 | AM18: 確認状況 | AN18: 正しい課税区分 | AO18: 正しい税率 | AP18: 備考 | AQ18: 重複 | AS18: 集計用課税区分 | AT18: 集計用税率 | AV18: 区域内 | AW18: 区域外 | AX18: 一般行政 | AY18: 計 | AZ18: 基準内 | BA18: 基準外 | BB18: 計 | BF18: 区域内 | BG18: 区域外 | BH18: 一般行政 | BI18: 計 | BJ18: 基準内 | BK18: 基準外 | BL18: 計 | BO18: AAA | BP18: AAA | BQ18: AAA | BR18: AAA | BS18: AAA | BT18: AAA
A19: 1 | D19: 1502110500 | E19: 管理課 | F19: R06/01/10 | G19: R06/01/10 | H19: 下水道使用料返還金の支出 | I19: 振替伝票（未払計上） | J19: 34005121 | K19: 000 | L19: 001 | M19: 1 | N19: 0884066300 | O19: 下水道事業費用 | P19: 営業外費用 | Q19: 雑支出 | R19: その他雑支出 | T19: 921472 | U19: 下水道使用料賦課（返還金） | V19: 0 | W19: 0 | X19: 0 | Y19: 23932 | Z19: 088406001063000000 | AA19: その他雑支出 | AB19: 23932 | AC19: 051410001001000000 | AD19: その他未払金 | AE19: 23932 | AF19: 15 | AG19: 8 | AH19: 1767 | AI19: 22165 | AJ19: 田畑 美香 | AL19: 34005121-000-001-1-0884066300-921472-15 | AM19: 1 | AN19: 0 | AO19: 0 | AP19: 0 | AS19: 15 | AT19: 8 | AV19: 0 | AW19: 0 | AX19: 0 | AY19: 0 | AZ19: 0 | BA19: 23932 | BB19: 23932 | BC19: 23932 | BD19: 0 | BF19: 0 | BG19: 0 | BH19: 0 | BI19: 0 | BJ19: 0 | BK19: 22159 | BL19: 22159 | BM19: 22159
A20: 1 | D20: 1502110500 | E20: 管理課 | F20: R05/11/01 | G20: R05/11/01 | H20: 下水道使用料過誤納還付金の精算（１０月分） | I20: 振替伝票（予算振替） | J20: 37000234 | K20: 000 | L20: 001 | M20: 1 | N20: 0885060600 | O20: 下水道事業費用 | P20: 特別損失 | Q20: 過年度損益修正損 | R20: 過年度損益修正損 | T20: 921481 | U20: 下水道使用料賦課徴収 | V20: 0 | W20: 0 | X20: 0 | Y20: 7639 | Z20: 088506001006000000 | AA20: 過年度損益修正損 | AB20: 7639 | AC20: 022602001006000000 | AD20: 下水道使用料還付前渡資金 | AE20: 7639 | AF20: 18 | AG20: 10 | AH20: 694 | AI20: 6945 | AL20: 37000234-000-001-1-0885060600-921481-18 | AM20: 1 | AN20: 0 | AO20: 0 | AP20: 0 | AS20: 18 | AT20: 10 | AV20: 0 | AW20: 0 | AX20: 0 | AY20: 0 | AZ20: 0 | BA20: 7639 | BB20: 7639 | BC20: 7639 | BD20: 0 | BF20: 0 | BG20: 0 | BH20: 0 | BI20: 0 | BJ20: 0 | BK20: 6945 | BL20: 6945 | BM20: 6945
A21: 1 | D21: 1502110500 | E21: 管理課 | F21: R05/11/01 | G21: R05/11/01 | H21: 下水道使用料過誤納還付金の精算（１０月分） | I21: 振替伝票（予算振替） | J21: 37000235 | K21: 000 | L21: 001 | M21: 1 | N21: 0885060600 | O21: 下水道事業費用 | P21: 特別損失 | Q21: 過年度損益修正損 | R21: 過年度損益修正損 | T21: 921481 | U21: 下水道使用料賦課徴収 | V21: 0 | W21: 0 | X21: 0 | Y21: 3359 | Z21: 088506001006000000 | AA21: 過年度損益修正損 | AB21: 3359 | AC21: 022602001006000000 | AD21: 下水道使用料還付前渡資金 | AE21: 3359 | AF21: 18 | AG21: 10 | AH21: 305 | AI21: 3054 | AL21: 37000235-000-001-1-0885060600-921481-18 | AM21: 1 | AN21: 0 | AO21: 0 | AP21: 0 | AS21: 18 | AT21: 10 | AV21: 0 | AW21: 0 | AX21: 0 | AY21: 0 | AZ21: 0 | BA21: 3359 | BB21: 3359 | BC21: 3359 | BD21: 0 | BF21: 0 | BG21: 0 | BH21: 0 | BI21: 0 | BJ21: 0 | BK21: 3054 | BL21: 3054 | BM21: 3054
A22: 1 | D22: 1502110500 | E22: 管理課 | F22: R05/11/01 | G22: R05/11/01 | H22: 下水道使用料過誤納還付金の精算（１０月分） | I22: 振替伝票（予算振替） | J22: 37000236 | K22: 000 | L22: 001 | M22: 1 | N22: 0885060600 | O22: 下水道事業費用 | P22: 特別損失 | Q22: 過年度損益修正損 | R22: 過年度損益修正損 | T22: 921481 | U22: 下水道使用料賦課徴収 | V22: 0 | W22: 0 | X22: 0 | Y22: 465 | Z22: 088506001006000000 | AA22: 過年度損益修正損 | AB22: 465 | AC22: 022602001006000000 | AD22: 下水道使用料還付前渡資金 | AE22: 465 | AF22: 18 | AG22: 10 | AH22: 42 | AI22: 423 | AL22: 37000236-000-001-1-0885060600-921481-18 | AM22: 1 | AN22: 0 | AO22: 0 | AP22: 0 | AS22: 18 | AT22: 10 | AV22: 0 | AW22: 0 | AX22: 0 | AY22: 0 | AZ22: 0 | BA22: 465 | BB22: 465 | BC22: 465 | BD22: 0 | BF22: 0 | BG22: 0 | BH22: 0 | BI22: 0 | BJ22: 0 | BK22: 423 | BL22: 423 | BM22: 423
A23: 1 | D23: 1502110500 | E23: 管理課 | F23: R05/12/01 | G23: R05/12/01 | H23: 下水道使用料過誤納還付金の精算（１１月分） | I23: 振替伝票（予算振替） | J23: 37000266 | K23: 000 | L23: 001 | M23: 1 | N23: 0885060600 | O23: 下水道事業費用 | P23: 特別損失 | Q23: 過年度損益修正損 | R23: 過年度損益修正損 | T23: 921481 | U23: 下水道使用料賦課徴収 | V23: 0 | W23: 0 | X23: 0 | Y23: 797 | Z23: 088506001006000000 | AA23: 過年度損益修正損 | AB23: 797 | AC23: 022602001006000000 | AD23: 下水道使用料還付前渡資金 | AE23: 797 | AF23: 18 | AG23: 10 | AH23: 72 | AI23: 725 | AL23: 37000266-000-001-1-0885060600-921481-18 | AM23: 1 | AN23: 0 | AO23: 0 | AP23: 0 | AS23: 18 | AT23: 10 | AV23: 0 | AW23: 0 | AX23: 0 | AY23: 0 | AZ23: 0 | BA23: 797 | BB23: 797 | BC23: 797 | BD23: 0 | BF23: 0 | BG23: 0 | BH23: 0 | BI23: 0 | BJ23: 0 | BK23: 725 | BL23: 725 | BM23: 725
A24: 1 | D24: 1502110500 | E24: 管理課 | F24: R05/12/01 | G24: R05/12/01 | H24: 下水道使用料過誤納還付金の精算（１１月分） | I24: 振替伝票（予算振替） | J24: 37000267 | K24: 000 | L24: 001 | M24: 1 | N24: 0885060600 | O24: 下水道事業費用 | P24: 特別損失 | Q24: 過年度損益修正損 | R24: 過年度損益修正損 | T24: 921481 | U24: 下水道使用料賦課徴収 | V24: 0 | W24: 0 | X24: 0 | Y24: 377 | Z24: 088506001006000000 | AA24: 過年度損益修正損 | AB24: 377 | AC24: 022602001006000000 | AD24: 下水道使用料還付前渡資金 | AE24: 377 | AF24: 18 | AG24: 10 | AH24: 32 | AI24: 345 | AL24: 37000267-000-001-1-0885060600-921481-18 | AM24: 1 | AN24: 0 | AO24: 0 | AP24: 0 | AS24: 18 | AT24: 10 | AV24: 0 | AW24: 0 | AX24: 0 | AY24: 0 | AZ24: 0 | BA24: 377 | BB24: 377 | BC24: 377 | BD24: 0 | BF24: 0 | BG24: 0 | BH24: 0 | BI24: 0 | BJ24: 0 | BK24: 343 | BL24: 343 | BM24: 343
A25: 1 | D25: 1502110500 | E25: 管理課 | F25: R05/12/01 | G25: R05/12/01 | H25: 下水道使用料過誤納還付金の精算（１１月分） | I25: 振替伝票（予算振替） | J25: 37000268 | K25: 000 | L25: 001 | M25: 1 | N25: 0885060600 | O25: 下水道事業費用 | P25: 特別損失 | Q25: 過年度損益修正損 | R25: 過年度損益修正損 | T25: 921481 | U25: 下水道使用料賦課徴収 | V25: 0 | W25: 0 | X25: 0 | Y25: 1117 | Z25: 088506001006000000 | AA25: 過年度損益修正損 | AB25: 1117 | AC25: 022602001006000000 | AD25: 下水道使用料還付前渡資金 | AE25: 1117 | AF25: 18 | AG25: 10 | AH25: 101 | AI25: 1016 | AL25: 37000268-000-001-1-0885060600-921481-18 | AM25: 1 | AN25: 0 | AO25: 0 | AP25: 0 | AS25: 18 | AT25: 10 | AV25: 0 | AW25: 0 | AX25: 0 | AY25: 0 | AZ25: 0 | BA25: 1117 | BB25: 1117 | BC25: 1117 | BD25: 0 | BF25: 0 | BG25: 0 | BH25: 0 | BI25: 0 | BJ25: 0 | BK25: 1015 | BL25: 1015 | BM25: 1015
A26: 1 | D26: 1502110500 | E26: 管理課 | F26: R06/01/01 | G26: R06/01/01 | H26: 下水道使用料過誤納還付金の精算（１２月分） | I26: 振替伝票（予算振替） | J26: 37000289 | K26: 000 | L26: 001 | M26: 1 | N26: 0885060600 | O26: 下水道事業費用 | P26: 特別損失 | Q26: 過年度損益修正損 | R26: 過年度損益修正損 | T26: 921481 | U26: 下水道使用料賦課徴収 | V26: 0 | W26: 0 | X26: 0 | Y26: 455 | Z26: 088506001006000000 | AA26: 過年度損益修正損 | AB26: 455 | AC26: 022602001006000000 | AD26: 下水道使用料還付前渡資金 | AE26: 455 | AF26: 18 | AG26: 10 | AH26: 41 | AI26: 414 | AL26: 37000289-000-001-1-0885060600-921481-18 | AM26: 1 | AN26: 0 | AO26: 0 | AP26: 0 | AS26: 18 | AT26: 10 | AV26: 0 | AW26: 0 | AX26: 0 | AY26: 0 | AZ26: 0 | BA26: 455 | BB26: 455 | BC26: 455 | BD26: 0 | BF26: 0 | BG26: 0 | BH26: 0 | BI26: 0 | BJ26: 0 | BK26: 414 | BL26: 414 | BM26: 414
A27: 1 | D27: 1502110500 | E27: 管理課 | F27: R06/01/01 | G27: R06/01/01 | H27: 下水道使用料過誤納還付金の精算（１２月分） | I27: 振替伝票（予算振替） | J27: 37000290 | K27: 000 | L27: 001 | M27: 1 | N27: 0885060600 | O27: 下水道事業費用 | P27: 特別損失 | Q27: 過年度損益修正損 | R27: 過年度損益修正損 | T27: 921481 | U27: 下水道使用料賦課徴収 | V27: 0 | W27: 0 | X27: 0 | Y27: 119045 | Z27: 088506001006000000 | AA27: 過年度損益修正損 | AB27: 119045 | AC27: 022602001006000000 | AD27: 下水道使用料還付前渡資金 | AE27: 119045 | AF27: 18 | AG27: 10 | AH27: 10822 | AI27: 108223 | AL27: 37000290-000-001-1-0885060600-921481-18 | AM27: 1 | AN27: 0 | AO27: 0 | AP27: 0 | AS27: 18 | AT27: 10 | AV27: 0 | AW27: 0 | AX27: 0 | AY27: 0 | AZ27: 0 | BA27: 119045 | BB27: 119045 | BC27: 119045 | BD27: 0 | BF27: 0 | BG27: 0 | BH27: 0 | BI27: 0 | BJ27: 0 | BK27: 108223 | BL27: 108223 | BM27: 108223
A28: 1 | D28: 1502110500 | E28: 管理課 | F28: R06/02/01 | G28: R06/02/01 | H28: 下水道使用料過誤納還付金の精算（１月分） | I28: 振替伝票（予算振替） | J28: 37000354 | K28: 000 | L28: 001 | M28: 1 | N28: 0885060600 | O28: 下水道事業費用 | P28: 特別損失 | Q28: 過年度損益修正損 | R28: 過年度損益修正損 | T28: 921481 | U28: 下水道使用料賦課徴収 | V28: 0 | W28: 0 | X28: 0 | Y28: 46834 | Z28: 088506001006000000 | AA28: 過年度損益修正損 | AB28: 46834 | AC28: 022602001006000000 | AD28: 下水道使用料還付前渡資金 | AE28: 46834 | AF28: 18 | AG28: 10 | AH28: 4257 | AI28: 42577 | AL28: 37000354-000-001-1-0885060600-921481-18 | AM28: 1 | AN28: 0 | AO28: 0 | AP28: 0 | AS28: 18 | AT28: 10 | AV28: 0 | AW28: 0 | AX28: 0 | AY28: 0 | AZ28: 0 | BA28: 46834 | BB28: 46834 | BC28: 46834 | BD28: 0 | BF28: 0 | BG28: 0 | BH28: 0 | BI28: 0 | BJ28: 0 | BK28: 42576 | BL28: 42576 | BM28: 42576
A29: 1 | D29: 1502110500 | E29: 管理課 | F29: R06/02/01 | G29: R06/02/01 | H29: 下水道使用料過誤納還付金の精算（１月分） | I29: 振替伝票（予算振替） | J29: 37000355 | K29: 000 | L29: 001 | M29: 1 | N29: 0885060600 | O29: 下水道事業費用 | P29: 特別損失 | Q29: 過年度損益修正損 | R29: 過年度損益修正損 | T29: 921481 | U29: 下水道使用料賦課徴収 | V29: 0 | W29: 0 | X29: 0 | Y29: 139433 | Z29: 088506001006000000 | AA29: 過年度損益修正損 | AB29: 139433 | AC29: 022602001006000000 | AD29: 下水道使用料還付前渡資金 | AE29: 139433 | AF29: 18 | AG29: 10 | AH29: 12675 | AI29: 126758 | AL29: 37000355-000-001-1-0885060600-921481-18 | AM29: 1 | AN29: 0 | AO29: 0 | AP29: 0 | AS29: 18 | AT29: 10 | AV29: 0 | AW29: 0 | AX29: 0 | AY29: 0 | AZ29: 0 | BA29: 139433 | BB29: 139433 | BC29: 139433 | BD29: 0 | BF29: 0 | BG29: 0 | BH29: 0 | BI29: 0 | BJ29: 0 | BK29: 126757 | BL29: 126757 | BM29: 126757
A30: 1 | D30: 1502110500 | E30: 管理課 | F30: R06/03/01 | G30: R06/03/01 | H30: 下水道使用料過誤納還付金の精算（２月分） | I30: 振替伝票（予算振替） | J30: 37000368 | K30: 000 | L30: 001 | M30: 1 | N30: 0885060600 | O30: 下水道事業費用 | P30: 特別損失 | Q30: 過年度損益修正損 | R30: 過年度損益修正損 | T30: 921481 | U30: 下水道使用料賦課徴収 | V30: 0 | W30: 0 | X30: 0 | Y30: 288 | Z30: 088506001006000000 | AA30: 過年度損益修正損 | AB30: 288 | AC30: 022602001006000000 | AD30: 下水道使用料還付前渡資金 | AE30: 288 | AF30: 18 | AG30: 10 | AH30: 26 | AI30: 262 | AL30: 37000368-000-001-1-0885060600-921481-18 | AM30: 1 | AN30: 0 | AO30: 0 | AP30: 0 | AS30: 18 | AT30: 10 | AV30: 0 | AW30: 0 | AX30: 0 | AY30: 0 | AZ30: 0 | BA30: 288 | BB30: 288 | BC30: 288 | BD30: 0 | BF30: 0 | BG30: 0 | BH30: 0 | BI30: 0 | BJ30: 0 | BK30: 262 | BL30: 262 | BM30: 262
A31: 1 | D31: 1502110500 | E31: 管理課 | F31: R06/03/01 | G31: R06/03/01 | H31: 下水道使用料過誤納還付金の精算（２月分） | I31: 振替伝票（予算振替） | J31: 37000369 | K31: 000 | L31: 001 | M31: 1 | N31: 0885060600 | O31: 下水道事業費用 | P31: 特別損失 | Q31: 過年度損益修正損 | R31: 過年度損益修正損 | T31: 921481 | U31: 下水道使用料賦課徴収 | V31: 0 | W31: 0 | X31: 0 | Y31: 765 | Z31: 088506001006000000 | AA31: 過年度損益修正損 | AB31: 765 | AC31: 022602001006000000 | AD31: 下水道使用料還付前渡資金 | AE31: 765 | AF31: 18 | AG31: 10 | AH31: 69 | AI31: 696 | AL31: 37000369-000-001-1-0885060600-921481-18 | AM31: 1 | AN31: 0 | AO31: 0 | AP31: 0 | AS31: 18 | AT31: 10 | AV31: 0 | AW31: 0 | AX31: 0 | AY31: 0 | AZ31: 0 | BA31: 765 | BB31: 765 | BC31: 765 | BD31: 0 | BF31: 0 | BG31: 0 | BH31: 0 | BI31: 0 | BJ31: 0 | BK31: 695 | BL31: 695 | BM31: 695
... A59: 1 | D59: 1502110500 | E59: 管理課 | F59: R05/04/18 | G59: R05/04/18 | H59: 過年度分下水道使用料過誤納還付金（口座還付分） | I59: 振替伝票（予算振替） | J59: 37000037 | K59: 000 | L59: 001 | M59: 1 | N59: 0885060600 | O59: 下水道事業費用 | P59: 特別損失 | Q59: 過年度損益修正損 | R59: 過年度損益修正損 | T59: 921481 | U59: 下水道使用料賦課徴収 | V59: 0 | W59: 0 | X59: 0 | Y59: 83432 | Z59: 088506001006000000 | AA59: 過年度損益修正損 | AB59: 83432 | AC59: 021402001002010000 | AD59: 未収下水道使用料０ | AE59: 83432 | AF59: 18 | AG59: 10 | AH59: 7584 | AI59: 75848 | AL59: 37000037-000-001-1-0885060600-921481-18 | AM59: 1 | AN59: 0 | AO59: 0 | AP59: 0 | AS59: 18 | AT59: 10 | AV59: 0 | AW59: 0 | AX59: 0 | AY59: 0 | AZ59: 0 | BA59: 83432 | BB59: 83432 | BC59: 83432 | BD59: 0 | BF59: 0 | BG59: 0 | BH59: 0 | BI59: 0 | BJ59: 0 | BK59: 75847 | BL59: 75847 | BM59: 75847
A60: 1 | D60: 1502110500 | E60: 管理課 | F60: R05/05/09 | G60: R05/05/09 | H60: 過年度分下水道使用料過誤納還付金（口座還付分） | I60: 振替伝票（予算振替） | J60: 37000038 | K60: 000 | L60: 001 | M60: 1 | N60: 0885060600 | O60: 下水道事業費用 | P60: 特別損失 | Q60: 過年度損益修正損 | R60: 過年度損益修正損 | T60: 921481 | U60: 下水道使用料賦課徴収 | V60: 0 | W60: 0 | X60: 0 | Y60: 5402 | Z60: 088506001006000000 | AA60: 過年度損益修正損 | AB60: 5402 | AC60: 021402001002010000 | AD60: 未収下水道使用料０ | AE60: 5402 | AF60: 15 | AG60: 10 | AH60: 491 | AI60: 4911 | AL60: 37000038-000-001-1-0885060600-921481-15 | AM60: 2 | AN60: 18 | AO60: 10 | AP60: 0 | AS60: 18 | AT60: 10 | AV60: 0 | AW60: 0 | AX60: 0 | AY60: 0 | AZ60: 0 | BA60: 5402 | BB60: 5402 | BC60: 5402 | BD60: 0 | BF60: 0 | BG60: 0 | BH60: 0 | BI60: 0 | BJ60: 0 | BK60: 4911 | BL60: 4911 | BM60: 4911
A61: 1 | D61: 1502110500 | E61: 管理課 | F61: R05/04/26 | G61: R05/04/26 | H61: 過年度分下水道使用料過誤納還付金（口座還付分） | I61: 振替伝票（予算振替） | J61: 37000039 | K61: 000 | L61: 001 | M61: 1 | N61: 0885060600 | O61: 下水道事業費用 | P61: 特別損失 | Q61: 過年度損益修正損 | R61: 過年度損益修正損 | T61: 921481 | U61: 下水道使用料賦課徴収 | V61: 0 | W61: 0 | X61: 0 | Y61: 5696 | Z61: 088506001006000000 | AA61: 過年度損益修正損 | AB61: 5696 | AC61: 021402001002010000 | AD61: 未収下水道使用料０ | AE61: 5696 | AF61: 15 | AG61: 10 | AH61: 518 | AI61: 5178 | AL61: 37000039-000-001-1-0885060600-921481-15 | AM61: 2 | AN61: 18 | AO61: 10 | AP61: 0 | AS61: 18 | AT61: 10 | AV61: 0 | AW61: 0 | AX61: 0 | AY61: 0 | AZ61: 0 | BA61: 5696 | BB61: 5696 | BC61: 5696 | BD61: 0 | BF61: 0 | BG61: 0 | BH61: 0 | BI61: 0 | BJ61: 0 | BK61: 5178 | BL61: 5178 | BM61: 5178
A62: 1 | D62: 1502110500 | E62: 管理課 | F62: R06/03/18 | G62: R06/03/18 | H62: 過年度分下水道使用料過誤納還付金（口座還付分） | I62: 振替伝票（予算振替） | J62: 37000411 | K62: 000 | L62: 001 | M62: 1 | N62: 0885060600 | O62: 下水道事業費用 | P62: 特別損失 | Q62: 過年度損益修正損 | R62: 過年度損益修正損 | T62: 921481 | U62: 下水道使用料賦課徴収 | V62: 0 | W62: 0 | X62: 0 | Y62: 33818 | Z62: 088506001006000000 | AA62: 過年度損益修正損 | AB62: 33818 | AC62: 021402001002010000 | AD62: 未収下水道使用料０ | AE62: 33818 | AF62: 18 | AG62: 10 | AH62: 3073 | AI62: 30745 | AL62: 37000411-000-001-1-0885060600-921481-18 | AM62: 1 | AN62: 0 | AO62: 0 | AP62: 0 | AS62: 18 | AT62: 10 | AV62: 0 | AW62: 0 | AX62: 0 | AY62: 0 | AZ62: 0 | BA62: 33818 | BB62: 33818 | BC62: 33818 | BD62: 0 | BF62: 0 | BG62: 0 | BH62: 0 | BI62: 0 | BJ62: 0 | BK62: 30744 | BL62: 30744 | BM62: 30744
A63: 1 | D63: 1502110500 | E63: 管理課 | F63: R06/02/06 | G63: R06/02/06 | H63: 過年度分下水道使用料過誤納還付金（口座還付分） | I63: 振替伝票（予算振替） | J63: 37000338 | K63: 000 | L63: 001 | M63: 1 | N63: 0885060600 | O63: 下水道事業費用 | P63: 特別損失 | Q63: 過年度損益修正損 | R63: 過年度損益修正損 | T63: 921481 | U63: 下水道使用料賦課徴収 | V63: 0 | W63: 0 | X63: 0 | Y63: 764 | Z63: 088506001006000000 | AA63: 過年度損益修正損 | AB63: 764 | AC63: 021402001002010000 | AD63: 未収下水道使用料０ | AE63: 764 | AF63: 18 | AG63: 10 | AH63: 69 | AI63: 695 | AL63: 37000338-000-001-1-0885060600-921481-18 | AM63: 1 | AN63: 0 | AO63: 0 | AP63: 0 | AS63: 18 | AT63: 10 | AV63: 0 | AW63: 0 | AX63: 0 | AY63: 0 | AZ63: 0 | BA63: 764 | BB63: 764 | BC63: 764 | BD63: 0 | BF63: 0 | BG63: 0 | BH63: 0 | BI63: 0 | BJ63: 0 | BK63: 695 | BL63: 695 | BM63: 695
A64: 1 | D64: 1502110500 | E64: 管理課 | F64: R06/01/09 | G64: R06/01/09 | H64: 過年度分下水道使用料過誤納還付金（口座還付分） | I64: 振替伝票（予算振替） | J64: 37000296 | K64: 000 | L64: 001 | M64: 1 | N64: 0885060600 | O64: 下水道事業費用 | P64: 特別損失 | Q64: 過年度損益修正損 | R64: 過年度損益修正損 | T64: 921481 | U64: 下水道使用料賦課徴収 | V64: 0 | W64: 0 | X64: 0 | Y64: 31460 | Z64: 088506001006000000 | AA64: 過年度損益修正損 | AB64: 31460 | AC64: 021402001002010000 | AD64: 未収下水道使用料０ | AE64: 31460 | AF64: 18 | AG64: 10 | AH64: 2860 | AI64: 28600 | AL64: 37000296-000-001-1-0885060600-921481-18 | AM64: 1 | AN64: 0 | AO64: 0 | AP64: 0 | AS64: 18 | AT64: 10 | AV64: 0 | AW64: 0 | AX64: 0 | AY64: 0 | AZ64: 0 | BA64: 31460 | BB64: 31460 | BC64: 31460 | BD64: 0 | BF64: 0 | BG64: 0 | BH64: 0 | BI64: 0 | BJ64: 0 | BK64: 28600 | BL64: 28600 | BM64: 28600
A65: 1 | D65: 1502110500 | E65: 管理課 | F65: R06/01/09 | G65: R06/01/09 | H65: 過年度分下水道使用料過誤納還付金（口座還付分） | I65: 振替伝票（予算振替） | J65: 37000297 | K65: 000 | L65: 001 | M65: 1 | N65: 0885060600 | O65: 下水道事業費用 | P65: 特別損失 | Q65: 過年度損益修正損 | R65: 過年度損益修正損 | T65: 921481 | U65: 下水道使用料賦課徴収 | V65: 0 | W65: 0 | X65: 0 | Y65: 9264 | Z65: 088506001006000000 | AA65: 過年度損益修正損 | AB65: 9264 | AC65: 021402001002010000 | AD65: 未収下水道使用料０ | AE65: 9264 | AF65: 15 | AG65: 8 | AH65: 684 | AI65: 8580 | AL65: 37000297-000-001-1-0885060600-921481-15 | AM65: 1 | AN65: 0 | AO65: 0 | AP65: 0 | AS65: 15 | AT65: 8 | AV65: 0 | AW65: 0 | AX65: 0 | AY65: 0 | AZ65: 0 | BA65: 9264 | BB65: 9264 | BC65: 9264 | BD65: 0 | BF65: 0 | BG65: 0 | BH65: 0 | BI65: 0 | BJ65: 0 | BK65: 8578 | BL65: 8578 | BM65: 8578
A66: 1 | D66: 1502110500 | E66: 管理課 | F66: R06/01/16 | G66: R06/01/16 | H66: 過年度分下水道使用料過誤納還付金（口座還付分） | I66: 振替伝票（予算振替） | J66: 37000302 | K66: 000 | L66: 001 | M66: 1 | N66: 0885060600 | O66: 下水道事業費用 | P66: 特別損失 | Q66: 過年度損益修正損 | R66: 過年度損益修正損 | T66: 921481 | U66: 下水道使用料賦課徴収 | V66: 0 | W66: 0 | X66: 0 | Y66: 7770 | Z66: 088506001006000000 | AA66: 過年度損益修正損 | AB66: 7770 | AC66: 021402001002010000 | AD66: 未収下水道使用料０ | AE66: 7770 | AF66: 18 | AG66: 10 | AH66: 706 | AI66: 7064 | AL66: 37000302-000-001-1-0885060600-921481-18 | AM66: 1 | AN66: 0 | AO66: 0 | AP66: 0 | AS66: 18 | AT66: 10 | AV66: 0 | AW66: 0 | AX66: 0 | AY66: 0 | AZ66: 0 | BA66: 7770 | BB66: 7770 | BC66: 7770 | BD66: 0 | BF66: 0 | BG66: 0 | BH66: 0 | BI66: 0 | BJ66: 0 | BK66: 7064 | BL66: 7064 | BM66: 7064
A67: 1 | D67: 1502110500 | E67: 管理課 | F67: R06/02/27 | G67: R06/02/27 | H67: 過年度分下水道使用料過誤納還付金（口座還付分） | I67: 振替伝票（予算振替） | J67: 37000356 | K67: 000 | L67: 001 | M67: 1 | N67: 0885060600 | O67: 下水道事業費用 | P67: 特別損失 | Q67: 過年度損益修正損 | R67: 過年度損益修正損 | T67: 921481 | U67: 下水道使用料賦課徴収 | V67: 0 | W67: 0 | X67: 0 | Y67: 4587 | Z67: 088506001006000000 | AA67: 過年度損益修正損 | AB67: 4587 | AC67: 021402001002010000 | AD67: 未収下水道使用料０ | AE67: 4587 | AF67: 18 | AG67: 10 | AH67: 417 | AI67: 4170 | AL67: 37000356-000-001-1-0885060600-921481-18 | AM67: 1 | AN67: 0 | AO67: 0 | AP67: 0 | AS67: 18 | AT67: 10 | AV67: 0 | AW67: 0 | AX67: 0 | AY67: 0 | AZ67: 0 | BA67: 4587 | BB67: 4587 | BC67: 4587 | BD67: 0 | BF67: 0 | BG67: 0 | BH67: 0 | BI67: 0 | BJ67: 0 | BK67: 4170 | BL67: 4170 | BM67: 4170
A68: 1 | D68: 1502110500 | E68: 管理課 | F68: R05/12/18 | G68: R05/12/18 | H68: 過年度分下水道使用料過誤納還付金（口座還付分） | I68: 振替伝票（予算振替） | J68: 37000269 | K68: 000 | L68: 001 | M68: 1 | N68: 0885060600 | O68: 下水道事業費用 | P68: 特別損失 | Q68: 過年度損益修正損 | R68: 過年度損益修正損 | T68: 921481 | U68: 下水道使用料賦課徴収 | V68: 0 | W68: 0 | X68: 0 | Y68: 20972 | Z68: 088506001006000000 | AA68: 過年度損益修正損 | AB68: 20972 | AC68: 021402001002010000 | AD68: 未収下水道使用料０ | AE68: 20972 | AF68: 18 | AG68: 10 | AH68: 1907 | AI68: 19065 | AL68: 37000269-000-001-1-0885060600-921481-18 | AM68: 1 | AN68: 0 | AO68: 0 | AP68: 0 | AS68: 18 | AT68: 10 | AV68: 0 | AW68: 0 | AX68: 0 | AY68: 0 | AZ68: 0 | BA68: 20972 | BB68: 20972 | BC68: 20972 | BD68: 0 | BF68: 0 | BG68: 0 | BH68: 0 | BI68: 0 | BJ68: 0 | BK68: 19066 | BL68: 19066 | BM68: 19066
A69: 1 | D69: 1502110500 | E69: 管理課 | F69: R05/11/28 | G69: R05/11/28 | H69: 過年度分下水道使用料過誤納還付金（口座還付分） | I69: 振替伝票（予算振替） | J69: 37000252 | K69: 000 | L69: 001 | M69: 1 | N69: 0885060600 | O69: 下水道事業費用 | P69: 特別損失 | Q69: 過年度損益修正損 | R69: 過年度損益修正損 | T69: 921481 | U69: 下水道使用料賦課徴収 | V69: 0 | W69: 0 | X69: 0 | Y69: 136155 | Z69: 088506001006000000 | AA69: 過年度損益修正損 | AB69: 136155 | AC69: 021402001002010000 | AD69: 未収下水道使用料０ | AE69: 136155 | AF69: 18 | AG69: 10 | AH69: 12377 | AI69: 123778 | AL69: 37000252-000-001-1-0885060600-921481-18 | AM69: 1 | AN69: 0 | AO69: 0 | AP69: 0 | AS69: 18 | AT69: 10 | AV69: 0 | AW69: 0 | AX69: 0 | AY69: 0 | AZ69: 0 | BA69: 136155 | BB69: 136155 | BC69: 136155 | BD69: 0 | BF69: 0 | BG69: 0 | BH69: 0 | BI69: 0 | BJ69: 0 | BK69: 123777 | BL69: 123777 | BM69: 123777
A70: 1 | D70: 1502110500 | E70: 管理課 | F70: R05/11/16 | G70: R05/11/16 | H70: 過年度分下水道使用料過誤納還付金（口座還付分） | I70: 振替伝票（予算振替） | J70: 37000237 | K70: 000 | L70: 001 | M70: 1 | N70: 0885060600 | O70: 下水道事業費用 | P70: 特別損失 | Q70: 過年度損益修正損 | R70: 過年度損益修正損 | T70: 921481 | U70: 下水道使用料賦課徴収 | V70: 0 | W70: 0 | X70: 0 | Y70: 789522 | Z70: 088506001006000000 | AA70: 過年度損益修正損 | AB70: 789522 | AC70: 021402001002010000 | AD70: 未収下水道使用料０ | AE70: 789522 | AF70: 15 | AG70: 10 | AH70: 71771 | AI70: 717751 | AL70: 37000237-000-001-1-0885060600-921481-15 | AM70: 2 | AN70: 18 | AO70: 10 | AP70: 0 | AS70: 18 | AT70: 10 | AV70: 0 | AW70: 0 | AX70: 0 | AY70: 0 | AZ70: 0 | BA70: 789522 | BB70: 789522 | BC70: 789522 | BD70: 0 | BF70: 0 | BG70: 0 | BH70: 0 | BI70: 0 | BJ70: 0 | BK70: 717747 | BL70: 717747 | BM70: 717747
A71: 1 | D71: 1502110500 | E71: 管理課 | F71: R05/07/01 | G71: R05/07/01 | H71: 過年度分下水道使用料過誤納還付金（口座還付分） | I71: 振替伝票（予算振替） | J71: 37000098 | K71: 000 | L71: 001 | M71: 1 | N71: 0885060600 | O71: 下水道事業費用 | P71: 特別損失 | Q71: 過年度損益修正損 | R71: 過年度損益修正損 | T71: 921481 | U71: 下水道使用料賦課徴収 | V71: 0 | W71: 0 | X71: 0 | Y71: 38149 | Z71: 088506001006000000 | AA71: 過年度損益修正損 | AB71: 38149 | AC71: 021402001002010000 | AD71: 未収下水道使用料０ | AE71: 38149 | AF71: 18 | AG71: 10 | AH71: 3466 | AI71: 34683 | AL71: 37000098-000-001-1-0885060600-921481-18 | AM71: 1 | AN71: 0 | AO71: 0 | AP71: 0 | AS71: 18 | AT71: 10 | AV71: 0 | AW71: 0 | AX71: 0 | AY71: 0 | AZ71: 0 | BA71: 38149 | BB71: 38149 | BC71: 38149 | BD71: 0 | BF71: 0 | BG71: 0 | BH71: 0 | BI71: 0 | BJ71: 0 | BK71: 34681 | BL71: 34681 | BM71: 34681
A72: 1 | D72: 1502110500 | E72: 管理課 | F72: R05/07/01 | G72: R05/07/01 | H72: 過年度分下水道使用料過誤納還付金（口座還付分） | I72: 振替伝票（予算振替） | J72: 37000099 | K72: 000 | L72: 001 | M72: 1 | N72: 0885060600 | O72: 下水道事業費用 | P72: 特別損失 | Q72: 過年度損益修正損 | R72: 過年度損益修正損 | T72: 921481 | U72: 下水道使用料賦課徴収 | V72: 0 | W72: 0 | X72: 0 | Y72: 55357 | Z72: 088506001006000000 | AA72: 過年度損益修正損 | AB72: 55357 | AC72: 021402001002010000 | AD72: 未収下水道使用料０ | AE72: 55357 | AF72: 18 | AG72: 10 | AH72: 5032 | AI72: 50325 | AL72: 37000099-000-001-1-0885060600-921481-18 | AM72: 1 | AN72: 0 | AO72: 0 | AP72: 0 | AS72: 18 | AT72: 10 | AV72: 0 | AW72: 0 | AX72: 0 | AY72: 0 | AZ72: 0 | BA72: 55357 | BB72: 55357 | BC72: 55357 | BD72: 0 | BF72: 0 | BG72: 0 | BH72: 0 | BI72: 0 | BJ72: 0 | BK72: 50325 | BL72: 50325 | BM72: 50325
A73: 1 | D73: 1502110500 | E73: 管理課 | F73: R05/07/01 | G73: R05/07/01 | H73: 過年度分下水道使用料過誤納還付金（口座還付分） | I73: 振替伝票（予算振替） | J73: 37000100 | K73: 000 | L73: 001 | M73: 1 | N73: 0885060600 | O73: 下水道事業費用 | P73: 特別損失 | Q73: 過年度損益修正損 | R73: 過年度損益修正損 | T73: 921481 | U73: 下水道使用料賦課徴収 | V73: 0 | W73: 0 | X73: 0 | Y73: 1453 | Z73: 088506001006000000 | AA73: 過年度損益修正損 | AB73: 1453 | AC73: 021402001002010000 | AD73: 未収下水道使用料０ | AE73: 1453 | AF73: 15 | AG73: 8 | AH73: 103 | AI73: 1350 | AL73: 37000100-000-001-1-0885060600-921481-15 | AM73: 1 | AN73: 0 | AO73: 0 | AP73: 0 | AS73: 15 | AT73: 8 | AV73: 0 | AW73: 0 | AX73: 0 | AY73: 0 | AZ73: 0 | BA73: 1453 | BB73: 1453 | BC73: 1453 | BD73: 0 | BF73: 0 | BG73: 0 | BH73: 0 | BI73: 0 | BJ73: 0 | BK73: 1345 | BL73: 1345 | BM73: 1345
A74: 1 | D74: 1502110500 | E74: 管理課 | F74: R05/07/01 | G74: R05/07/01 | H74: 過年度分下水道使用料過誤納還付金（口座還付分） | I74: 振替伝票（予算振替） | J74: 37000101 | K74: 000 | L74: 001 | M74: 1 | N74: 0885060600 | O74: 下水道事業費用 | P74: 特別損失 | Q74: 過年度損益修正損 | R74: 過年度損益修正損 | T74: 921481 | U74: 下水道使用料賦課徴収 | V74: 0 | W74: 0 | X74: 0 | Y74: 138909 | Z74: 088506001006000000 | AA74: 過年度損益修正損 | AB74: 138909 | AC74: 021402001002010000 | AD74: 未収下水道使用料０ | AE74: 138909 | AF74: 18 | AG74: 10 | AH74: 12621 | AI74: 126288 | AL74: 37000101-000-001-1-0885060600-921481-18 | AM74: 1 | AN74: 0 | AO74: 0 | AP74: 0 | AS74: 18 | AT74: 10 | AV74: 0 | AW74: 0 | AX74: 0 | AY74: 0 | AZ74: 0 | BA74: 138909 | BB74: 138909 | BC74: 138909 | BD74: 0 | BF74: 0 | BG74: 0 | BH74: 0 | BI74: 0 | BJ74: 0 | BK74: 126281 | BL74: 126281 | BM74: 126281
A75: 1 | D75: 1502110500 | E75: 管理課 | F75: R05/07/01 | G75: R05/07/01 | H75: 過年度分下水道使用料過誤納還付金（口座還付分） | I75: 振替伝票（予算振替） | J75: 37000102 | K75: 000 | L75: 001 | M75: 1 | N75: 0885060600 | O75: 下水道事業費用 | P75: 特別損失 | Q75: 過年度損益修正損 | R75: 過年度損益修正損 | T75: 921481 | U75: 下水道使用料賦課徴収 | V75: 0 | W75: 0 | X75: 0 | Y75: 104861 | Z75: 088506001006000000 | AA75: 過年度損益修正損 | AB75: 104861 | AC75: 021402001002010000 | AD75: 未収下水道使用料０ | AE75: 104861 | AF75: 18 | AG75: 10 | AH75: 9532 | AI75: 95329 | AL75: 37000102-000-001-1-0885060600-921481-18 | AM75: 1 | AN75: 0 | AO75: 0 | AP75: 0 | AS75: 18 | AT75: 10 | AV75: 0 | AW75: 0 | AX75: 0 | AY75: 0 | AZ75: 0 | BA75: 104861 | BB75: 104861 | BC75: 104861 | BD75: 0 | BF75: 0 | BG75: 0 | BH75: 0 | BI75: 0 | BJ75: 0 | BK75: 95328 | BL75: 95328 | BM75: 95328
A76: 1 | D76: 1502110500 | E76: 管理課 | F76: R05/07/01 | G76: R05/07/01 | H76: 過年度分下水道使用料過誤納還付金（口座還付分） | I76: 振替伝票（予算振替） | J76: 37000103 | K76: 000 | L76: 001 | M76: 1 | N76: 0885060600 | O76: 下水道事業費用 | P76: 特別損失 | Q76: 過年度損益修正損 | R76: 過年度損益修正損 | T76: 921481 | U76: 下水道使用料賦課徴収 | V76: 0 | W76: 0 | X76: 0 | Y76: 1108227 | Z76: 088506001006000000 | AA76: 過年度損益修正損 | AB76: 1108227 | AC76: 021402001002010000 | AD76: 未収下水道使用料０ | AE76: 1108227 | AF76: 18 | AG76: 10 | AH76: 100747 | AI76: 1007480 | AL76: 37000103-000-001-1-0885060600-921481-18 | AM76: 1 | AN76: 0 | AO76: 0 | AP76: 0 | AS76: 18 | AT76: 10 | AV76: 0 | AW76: 0 | AX76: 0 | AY76: 0 | AZ76: 0 | BA76: 1108227 | BB76: 1108227 | BC76: 1108227 | BD76: 0 | BF76: 0 | BG76: 0 | BH76: 0 | BI76: 0 | BJ76: 0 | BK76: 1007479 | BL76: 1007479 | BM76: 1007479
A77: 1 | D77: 1502110500 | E77: 管理課 | F77: R05/07/06 | G77: R05/07/06 | H77: 過年度分下水道使用料過誤納還付金（口座還付分） | I77: 振替伝票（予算振替） | J77: 37000104 | K77: 000 | L77: 001 | M77: 1 | N77: 0885060600 | O77: 下水道事業費用 | P77: 特別損失 | Q77: 過年度損益修正損 | R77: 過年度損益修正損 | T77: 921481 | U77: 下水道使用料賦課徴収 | V77: 0 | W77: 0 | X77: 0 | Y77: 453753 | Z77: 088506001006000000 | AA77: 過年度損益修正損 | AB77: 453753 | AC77: 021402001002010000 | AD77: 未収下水道使用料０ | AE77: 453753 | AF77: 18 | AG77: 10 | AH77: 41243 | AI77: 412510 | AL77: 37000104-000-001-1-0885060600-921481-18 | AM77: 1 | AN77: 0 | AO77: 0 | AP77: 0 | AS77: 18 | AT77: 10 | AV77: 0 | AW77: 0 | AX77: 0 | AY77: 0 | AZ77: 0 | BA77: 453753 | BB77: 453753 | BC77: 453753 | BD77: 0 | BF77: 0 | BG77: 0 | BH77: 0 | BI77: 0 | BJ77: 0 | BK77: 412503 | BL77: 412503 | BM77: 412503
A78: 1 | D78: 1502110500 | E78: 管理課 | F78: R05/09/19 | G78: R05/09/19 | H78: 過年度分下水道使用料過誤納還付金（口座還付分） | I78: 振替伝票（予算振替） | J78: 37000194 | K78: 000 | L78: 001 | M78: 1 | N78: 0885060600 | O78: 下水道事業費用 | P78: 特別損失 | Q78: 過年度損益修正損 | R78: 過年度損益修正損 | T78: 921481 | U78: 下水道使用料賦課徴収 | V78: 0 | W78: 0 | X78: 0 | Y78: 18717 | Z78: 088506001006000000 | AA78: 過年度損益修正損 | AB78: 18717 | AC78: 021402001002010000 | AD78: 未収下水道使用料０ | AE78: 18717 | AF78: 18 | AG78: 10 | AH78: 1701 | AI78: 17016 | AL78: 37000194-000-001-1-0885060600-921481-18 | AM78: 1 | AN78: 0 | AO78: 0 | AP78: 0 | AS78: 18 | AT78: 10 | AV78: 0 | AW78: 0 | AX78: 0 | AY78: 0 | AZ78: 0 | BA78: 18717 | BB78: 18717 | BC78: 18717 | BD78: 0 | BF78: 0 | BG78: 0 | BH78: 0 | BI78: 0 | BJ78: 0 | BK78: 17015 | BL78: 17015 | BM78: 17015
A79: 1 | D79: 1502110500 | E79: 管理課 | F79: R05/09/06 | G79: R05/09/06 | H79: 過年度分下水道使用料過誤納還付金（口座還付分） | I79: 振替伝票（予算振替） | J79: 37000182 | K79: 000 | L79: 001 | M79: 1 | N79: 0885060600 | O79: 下水道事業費用 | P79: 特別損失 | Q79: 過年度損益修正損 | R79: 過年度損益修正損 | T79: 921481 | U79: 下水道使用料賦課徴収 | V79: 0 | W79: 0 | X79: 0 | Y79: 17704 | Z79: 088506001006000000 | AA79: 過年度損益修正損 | AB79: 17704 | AC79: 021402001002010000 | AD79: 未収下水道使用料０ | AE79: 17704 | AF79: 18 | AG79: 10 | AH79: 1608 | AI79: 16096 | AL79: 37000182-000-001-1-0885060600-921481-18 | AM79: 1 | AN79: 0 | AO79: 0 | AP79: 0 | AS79: 18 | AT79: 10 | AV79: 0 | AW79: 0 | AX79: 0 | AY79: 0 | AZ79: 0 | BA79: 17704 | BB79: 17704 | BC79: 17704 | BD79: 0 | BF79: 0 | BG79: 0 | BH79: 0 | BI79: 0 | BJ79: 0 | BK79: 16095 | BL79: 16095 | BM79: 16095
A80: 1 | D80: 1502110500 | E80: 管理課 | F80: R05/08/01 | G80: R05/08/01 | H80: 過年度分下水道使用料過誤納還付金（口座還付分） | I80: 振替伝票（予算振替） | J80: 37000162 | K80: 000 | L80: 001 | M80: 1 | N80: 0885060600 | O80: 下水道事業費用 | P80: 特別損失 | Q80: 過年度損益修正損 | R80: 過年度損益修正損 | T80: 921481 | U80: 下水道使用料賦課徴収 | V80: 0 | W80: 0 | X80: 0 | Y80: 46382 | Z80: 088506001006000000 | AA80: 過年度損益修正損 | AB80: 46382 | AC80: 021402001002010000 | AD80: 未収下水道使用料０ | AE80: 46382 | AF80: 18 | AG80: 10 | AH80: 4217 | AI80: 42165 | AL80: 37000162-000-001-1-0885060600-921481-18 | AM80: 1 | AN80: 0 | AO80: 0 | AP80: 0 | AS80: 18 | AT80: 10 | AV80: 0 | AW80: 0 | AX80: 0 | AY80: 0 | AZ80: 0 | BA80: 46382 | BB80: 46382 | BC80: 46382 | BD80: 0 | BF80: 0 | BG80: 0 | BH80: 0 | BI80: 0 | BJ80: 0 | BK80: 42166 | BL80: 42166 | BM80: 42166
A81: 1 | D81: 1502110500 | E81: 管理課 | F81: R05/08/01 | G81: R05/08/01 | H81: 過年度分下水道使用料過誤納還付金（口座還付分） | I81: 振替伝票（予算振替） | J81: 37000163 | K81: 000 | L81: 001 | M81: 1 | N81: 0885060600 | O81: 下水道事業費用 | P81: 特別損失 | Q81: 過年度損益修正損 | R81: 過年度損益修正損 | T81: 921481 | U81: 下水道使用料賦課徴収 | V81: 0 | W81: 0 | X81: 0 | Y81: 146344 | Z81: 088506001006000000 | AA81: 過年度損益修正損 | AB81: 146344 | AC81: 021402001002010000 | AD81: 未収下水道使用料０ | AE81: 146344 | AF81: 18 | AG81: 10 | AH81: 13300 | AI81: 133044 | AL81: 37000163-000-001-1-0885060600-921481-18 | AM81: 1 | AN81: 0 | AO81: 0 | AP81: 0 | AS81: 18 | AT81: 10 | AV81: 0 | AW81: 0 | AX81: 0 | AY81: 0 | AZ81: 0 | BA81: 146344 | BB81: 146344 | BC81: 146344 | BD81: 0 | BF81: 0 | BG81: 0 | BH81: 0 | BI81: 0 | BJ81: 0 | BK81: 133040 | BL81: 133040 | BM81: 133040
A82: 1 | D82: 1502110500 | E82: 管理課 | F82: R05/08/08 | G82: R05/08/08 | H82: 過年度分下水道使用料過誤納還付金（口座還付分） | I82: 振替伝票（予算振替） | J82: 37000164 | K82: 000 | L82: 001 | M82: 1 | N82: 0885060600 | O82: 下水道事業費用 | P82: 特別損失 | Q82: 過年度損益修正損 | R82: 過年度損益修正損 | T82: 921481 | U82: 下水道使用料賦課徴収 | V82: 0 | W82: 0 | X82: 0 | Y82: 44284 | Z82: 088506001006000000 | AA82: 過年度損益修正損 | AB82: 44284 | AC82: 021402001002010000 | AD82: 未収下水道使用料０ | AE82: 44284 | AF82: 18 | AG82: 10 | AH82: 4026 | AI82: 40258 | AL82: 37000164-000-001-1-0885060600-921481-18 | AM82: 1 | AN82: 0 | AO82: 0 | AP82: 0 | AS82: 18 | AT82: 10 | AV82: 0 | AW82: 0 | AX82: 0 | AY82: 0 | AZ82: 0 | BA82: 44284 | BB82: 44284 | BC82: 44284 | BD82: 0 | BF82: 0 | BG82: 0 | BH82: 0 | BI82: 0 | BJ82: 0 | BK82: 40258 | BL82: 40258 | BM82: 40258
... A84: 1 | D84: 1502110500 | E84: 管理課 | F84: R05/08/28 | G84: R05/08/28 | H84: 過年度分下水道使用料過誤納還付金（口座還付分） | I84: 振替伝票（予算振替） | J84: 37000166 | K84: 000 | L84: 001 | M84: 1 | N84: 0885060600 | O84: 下水道事業費用 | P84: 特別損失 | Q84: 過年度損益修正損 | R84: 過年度損益修正損 | T84: 921481 | U84: 下水道使用料賦課徴収 | V84: 0 | W84: 0 | X84: 0 | Y84: 9421 | Z84: 088506001006000000 | AA84: 過年度損益修正損 | AB84: 9421 | AC84: 021402001002010000 | AD84: 未収下水道使用料０ | AE84: 9421 | AF84: 18 | AG84: 10 | AH84: 857 | AI84: 8564 | AL84: 37000166-000-001-1-0885060600-921481-18 | AM84: 1 | AN84: 0 | AO84: 0 | AP84: 0 | AS84: 18 | AT84: 10 | AV84: 0 | AW84: 0 | AX84: 0 | AY84: 0 | AZ84: 0 | BA84: 9421 | BB84: 9421 | BC84: 9421 | BD84: 0 | BF84: 0 | BG84: 0 | BH84: 0 | BI84: 0 | BJ84: 0 | BK84: 8565 | BL84: 8565 | BM84: 8565
A85: 1 | D85: 1502110500 | E85: 管理課 | F85: R05/10/26 | G85: R05/10/26 | H85: 過年度分下水道使用料過誤納還付金（口座還付分） | I85: 振替伝票（予算振替） | J85: 37000218 | K85: 000 | L85: 001 | M85: 1 | N85: 0885060600 | O85: 下水道事業費用 | P85: 特別損失 | Q85: 過年度損益修正損 | R85: 過年度損益修正損 | T85: 921481 | U85: 下水道使用料賦課徴収 | V85: 0 | W85: 0 | X85: 0 | Y85: 1529 | Z85: 088506001006000000 | AA85: 過年度損益修正損 | AB85: 1529 | AC85: 021402001002010000 | AD85: 未収下水道使用料０ | AE85: 1529 | AF85: 15 | AG85: 10 | AH85: 139 | AI85: 1390 | AL85: 37000218-000-001-1-0885060600-921481-15 | AM85: 2 | AN85: 18 | AO85: 10 | AP85: 0 | AS85: 18 | AT85: 10 | AV85: 0 | AW85: 0 | AX85: 0 | AY85: 0 | AZ85: 0 | BA85: 1529 | BB85: 1529 | BC85: 1529 | BD85: 0 | BF85: 0 | BG85: 0 | BH85: 0 | BI85: 0 | BJ85: 0 | BK85: 1390 | BL85: 1390 | BM85: 1390
A86: 1 | D86: 1502110500 | E86: 管理課 | F86: R05/09/01 | G86: R05/09/01 | H86: 平成３０年度下水道使用料減額調定 １件 | I86: 振替伝票（予算振替） | J86: 37000181 | K86: 000 | L86: 001 | M86: 1 | N86: 0885060600 | O86: 下水道事業費用 | P86: 特別損失 | Q86: 過年度損益修正損 | R86: 過年度損益修正損 | T86: 921481 | U86: 下水道使用料賦課徴収 | V86: 0 | W86: 0 | X86: 0 | Y86: 4690 | Z86: 088506001006000000 | AA86: 過年度損益修正損 | AB86: 4690 | AC86: 021402001002015000 | AD86: 未収下水道使用料５ | AE86: 4690 | AF86: 15 | AG86: 8 | AH86: 347 | AI86: 4343 | AL86: 37000181-000-001-1-0885060600-921481-15 | AM86: 1 | AN86: 0 | AO86: 0 | AP86: 0 | AS86: 15 | AT86: 8 | AV86: 0 | AW86: 0 | AX86: 0 | AY86: 0 | AZ86: 0 | BA86: 4690 | BB86: 4690 | BC86: 4690 | BD86: 0 | BF86: 0 | BG86: 0 | BH86: 0 | BI86: 0 | BJ86: 0 | BK86: 4343 | BL86: 4343 | BM86: 4343
A87: 1 | D87: 1502110500 | E87: 管理課 | F87: R06/03/15 | G87: R06/03/15 | H87: 令和２年度下水道使用料減額調定 １件 | I87: 振替伝票（予算振替） | J87: 37000471 | K87: 000 | L87: 001 | M87: 1 | N87: 0885060600 | O87: 下水道事業費用 | P87: 特別損失 | Q87: 過年度損益修正損 | R87: 過年度損益修正損 | T87: 921481 | U87: 下水道使用料賦課徴収 | V87: 0 | W87: 0 | X87: 0 | Y87: 1 | Z87: 088506001006000000 | AA87: 過年度損益修正損 | AB87: 1 | AC87: 021402001002013000 | AD87: 未収下水道使用料３ | AE87: 1 | AF87: 18 | AG87: 10 | AH87: 0 | AI87: 1 | AL87: 37000471-000-001-1-0885060600-921481-18 | AM87: 1 | AN87: 0 | AO87: 0 | AP87: 0 | AS87: 18 | AT87: 10 | AV87: 0 | AW87: 0 | AX87: 0 | AY87: 0 | AZ87: 0 | BA87: 1 | BB87: 1 | BC87: 1 | BD87: 0 | BF87: 0 | BG87: 0 | BH87: 0 | BI87: 0 | BJ87: 0 | BK87: 1 | BL87: 1 | BM87: 1
A88: 1 | D88: 1502110500 | E88: 管理課 | F88: R05/11/01 | G88: R05/11/01 | H88: 令和２年度下水道使用料減額調定 １件 | I88: 振替伝票（予算振替） | J88: 37000240 | K88: 000 | L88: 001 | M88: 1 | N88: 0885060600 | O88: 下水道事業費用 | P88: 特別損失 | Q88: 過年度損益修正損 | R88: 過年度損益修正損 | T88: 921481 | U88: 下水道使用料賦課徴収 | V88: 0 | W88: 0 | X88: 0 | Y88: 10672 | Z88: 088506001006000000 | AA88: 過年度損益修正損 | AB88: 10672 | AC88: 021402001002013000 | AD88: 未収下水道使用料３ | AE88: 10672 | AF88: 15 | AG88: 10 | AH88: 970 | AI88: 9702 | AL88: 37000240-000-001-1-0885060600-921481-15 | AM88: 2 | AN88: 18 | AO88: 10 | AP88: 0 | AS88: 18 | AT88: 10 | AV88: 0 | AW88: 0 | AX88: 0 | AY88: 0 | AZ88: 0 | BA88: 10672 | BB88: 10672 | BC88: 10672 | BD88: 0 | BF88: 0 | BG88: 0 | BH88: 0 | BI88: 0 | BJ88: 0 | BK88: 9702 | BL88: 9702 | BM88: 9702
A89: 1 | D89: 1502110500 | E89: 管理課 | F89: R05/12/01 | G89: R05/12/01 | H89: 令和２年度下水道使用料減額調定 １件 | I89: 振替伝票（予算振替） | J89: 37000245 | K89: 000 | L89: 001 | M89: 1 | N89: 0885060600 | O89: 下水道事業費用 | P89: 特別損失 | Q89: 過年度損益修正損 | R89: 過年度損益修正損 | T89: 921481 | U89: 下水道使用料賦課徴収 | V89: 0 | W89: 0 | X89: 0 | Y89: 2057 | Z89: 088506001006000000 | AA89: 過年度損益修正損 | AB89: 2057 | AC89: 021402001002013000 | AD89: 未収下水道使用料３ | AE89: 2057 | AF89: 18 | AG89: 10 | AH89: 187 | AI89: 1870 | AL89: 37000245-000-001-1-0885060600-921481-18 | AM89: 1 | AN89: 0 | AO89: 0 | AP89: 0 | AS89: 18 | AT89: 10 | AV89: 0 | AW89: 0 | AX89: 0 | AY89: 0 | AZ89: 0 | BA89: 2057 | BB89: 2057 | BC89: 2057 | BD89: 0 | BF89: 0 | BG89: 0 | BH89: 0 | BI89: 0 | BJ89: 0 | BK89: 1870 | BL89: 1870 | BM89: 1870
A90: 1 | D90: 1502110500 | E90: 管理課 | F90: R05/08/01 | G90: R05/08/01 | H90: 令和２年度下水道使用料減額調定 １件 | I90: 振替伝票（予算振替） | J90: 37000145 | K90: 000 | L90: 001 | M90: 1 | N90: 0885060600 | O90: 下水道事業費用 | P90: 特別損失 | Q90: 過年度損益修正損 | R90: 過年度損益修正損 | T90: 921481 | U90: 下水道使用料賦課徴収 | V90: 0 | W90: 0 | X90: 0 | Y90: 1529 | Z90: 088506001006000000 | AA90: 過年度損益修正損 | AB90: 1529 | AC90: 021402001002013000 | AD90: 未収下水道使用料３ | AE90: 1529 | AF90: 18 | AG90: 10 | AH90: 139 | AI90: 1390 | AL90: 37000145-000-001-1-0885060600-921481-18 | AM90: 1 | AN90: 0 | AO90: 0 | AP90: 0 | AS90: 18 | AT90: 10 | AV90: 0 | AW90: 0 | AX90: 0 | AY90: 0 | AZ90: 0 | BA90: 1529 | BB90: 1529 | BC90: 1529 | BD90: 0 | BF90: 0 | BG90: 0 | BH90: 0 | BI90: 0 | BJ90: 0 | BK90: 1390 | BL90: 1390 | BM90: 1390
A91: 1 | D91: 1502110500 | E91: 管理課 | F91: R06/01/01 | G91: R06/01/01 | H91: 令和２年度下水道使用料減額調定 ３件 | I91: 振替伝票（予算振替） | J91: 37000300 | K91: 000 | L91: 001 | M91: 1 | N91: 0885060600 | O91: 下水道事業費用 | P91: 特別損失 | Q91: 過年度損益修正損 | R91: 過年度損益修正損 | T91: 921481 | U91: 下水道使用料賦課徴収 | V91: 0 | W91: 0 | X91: 0 | Y91: 3822 | Z91: 088506001006000000 | AA91: 過年度損益修正損 | AB91: 3822 | AC91: 021402001002013000 | AD91: 未収下水道使用料３ | AE91: 3822 | AF91: 18 | AG91: 10 | AH91: 347 | AI91: 3475 | AL91: 37000300-000-001-1-0885060600-921481-18 | AM91: 1 | AN91: 0 | AO91: 0 | AP91: 0 | AS91: 18 | AT91: 10 | AV91: 0 | AW91: 0 | AX91: 0 | AY91: 0 | AZ91: 0 | BA91: 3822 | BB91: 3822 | BC91: 3822 | BD91: 0 | BF91: 0 | BG91: 0 | BH91: 0 | BI91: 0 | BJ91: 0 | BK91: 3475 | BL91: 3475 | BM91: 3475
A92: 1 | D92: 1502110500 | E92: 管理課 | F92: R05/09/01 | G92: R05/09/01 | H92: 令和３年度下水道使用料減額調定 ２件 | I92: 振替伝票（予算振替） | J92: 37000180 | K92: 000 | L92: 001 | M92: 1 | N92: 0885060600 | O92: 下水道事業費用 | P92: 特別損失 | Q92: 過年度損益修正損 | R92: 過年度損益修正損 | T92: 921481 | U92: 下水道使用料賦課徴収 | V92: 0 | W92: 0 | X92: 0 | Y92: 3058 | Z92: 088506001006000000 | AA92: 過年度損益修正損 | AB92: 3058 | AC92: 021402001002012000 | AD92: 未収下水道使用料２ | AE92: 3058 | AF92: 18 | AG92: 10 | AH92: 278 | AI92: 2780 | AL92: 37000180-000-001-1-0885060600-921481-18 | AM92: 1 | AN92: 0 | AO92: 0 | AP92: 0 | AS92: 18 | AT92: 10 | AV92: 0 | AW92: 0 | AX92: 0 | AY92: 0 | AZ92: 0 | BA92: 3058 | BB92: 3058 | BC92: 3058 | BD92: 0 | BF92: 0 | BG92: 0 | BH92: 0 | BI92: 0 | BJ92: 0 | BK92: 2780 | BL92: 2780 | BM92: 2780
A93: 1 | D93: 1502110500 | E93: 管理課 | F93: R05/04/20 | G93: R05/04/20 | H93: 令和４年度下水道使用料減額調定 １０件 | I93: 振替伝票（予算振替） | J93: 37000060 | K93: 000 | L93: 001 | M93: 1 | N93: 0885060600 | O93: 下水道事業費用 | P93: 特別損失 | Q93: 過年度損益修正損 | R93: 過年度損益修正損 | T93: 921481 | U93: 下水道使用料賦課徴収 | V93: 0 | W93: 0 | X93: 0 | Y93: 377391 | Z93: 088506001006000000 | AA93: 過年度損益修正損 | AB93: 377391 | AC93: 021402001002011000 | AD93: 未収下水道使用料１ | AE93: 377391 | AF93: 18 | AG93: 10 | AH93: 34302 | AI93: 343089 | AL93: 37000060-000-001-1-0885060600-921481-18 | AM93: 1 | AN93: 0 | AO93: 0 | AP93: 0 | AS93: 18 | AT93: 10 | AV93: 0 | AW93: 0 | AX93: 0 | AY93: 0 | AZ93: 0 | BA93: 377391 | BB93: 377391 | BC93: 377391 | BD93: 0 | BF93: 0 | BG93: 0 | BH93: 0 | BI93: 0 | BJ93: 0 | BK93: 343083 | BL93: 343083 | BM93: 343083
A94: 1 | D94: 1502110500 | E94: 管理課 | F94: R05/04/10 | G94: R05/04/10 | H94: 令和４年度下水道使用料減額調定 １３件 | I94: 振替伝票（予算振替） | J94: 37000059 | K94: 000 | L94: 001 | M94: 1 | N94: 0885060600 | O94: 下水道事業費用 | P94: 特別損失 | Q94: 過年度損益修正損 | R94: 過年度損益修正損 | T94: 921481 | U94: 下水道使用料賦課徴収 | V94: 0 | W94: 0 | X94: 0 | Y94: 660527 | Z94: 088506001006000000 | AA94: 過年度損益修正損 | AB94: 660527 | AC94: 021402001002011000 | AD94: 未収下水道使用料１ | AE94: 660527 | AF94: 18 | AG94: 10 | AH94: 60038 | AI94: 600489 | AL94: 37000059-000-001-1-0885060600-921481-18 | AM94: 1 | AN94: 0 | AO94: 0 | AP94: 0 | AS94: 18 | AT94: 10 | AV94: 0 | AW94: 0 | AX94: 0 | AY94: 0 | AZ94: 0 | BA94: 660527 | BB94: 660527 | BC94: 660527 | BD94: 0 | BF94: 0 | BG94: 0 | BH94: 0 | BI94: 0 | BJ94: 0 | BK94: 600479 | BL94: 600479 | BM94: 600479
A95: 1 | D95: 1502110500 | E95: 管理課 | F95: R06/01/01 | G95: R06/01/01 | H95: 令和４年度下水道使用料減額調定 １件 | I95: 振替伝票（予算振替） | J95: 37000301 | K95: 000 | L95: 001 | M95: 1 | N95: 0885060600 | O95: 下水道事業費用 | P95: 特別損失 | Q95: 過年度損益修正損 | R95: 過年度損益修正損 | T95: 921481 | U95: 下水道使用料賦課徴収 | V95: 0 | W95: 0 | X95: 0 | Y95: 1529 | Z95: 088506001006000000 | AA95: 過年度損益修正損 | AB95: 1529 | AC95: 021402001002011000 | AD95: 未収下水道使用料１ | AE95: 1529 | AF95: 18 | AG95: 10 | AH95: 139 | AI95: 1390 | AL95: 37000301-000-001-1-0885060600-921481-18 | AM95: 1 | AN95: 0 | AO95: 0 | AP95: 0 | AS95: 18 | AT95: 10 | AV95: 0 | AW95: 0 | AX95: 0 | AY95: 0 | AZ95: 0 | BA95: 1529 | BB95: 1529 | BC95: 1529 | BD95: 0 | BF95: 0 | BG95: 0 | BH95: 0 | BI95: 0 | BJ95: 0 | BK95: 1390 | BL95: 1390 | BM95: 1390
A96: 1 | D96: 1502110500 | E96: 管理課 | F96: R06/01/01 | G96: R06/01/01 | H96: 令和４年度下水道使用料減額調定 １件 | I96: 振替伝票（予算振替） | J96: 37000279 | K96: 000 | L96: 001 | M96: 1 | N96: 0885060600 | O96: 下水道事業費用 | P96: 特別損失 | Q96: 過年度損益修正損 | R96: 過年度損益修正損 | T96: 921481 | U96: 下水道使用料賦課徴収 | V96: 0 | W96: 0 | X96: 0 | Y96: 1519 | Z96: 088506001006000000 | AA96: 過年度損益修正損 | AB96: 1519 | AC96: 021402001002011000 | AD96: 未収下水道使用料１ | AE96: 1519 | AF96: 18 | AG96: 10 | AH96: 149 | AI96: 1370 | AL96: 37000279-000-001-1-0885060600-921481-18 | AM96: 1 | AN96: 0 | AO96: 0 | AP96: 0 | AS96: 18 | AT96: 10 | AV96: 0 | AW96: 0 | AX96: 0 | AY96: 0 | AZ96: 0 | BA96: 1519 | BB96: 1519 | BC96: 1519 | BD96: 0 | BF96: 0 | BG96: 0 | BH96: 0 | BI96: 0 | BJ96: 0 | BK96: 1381 | BL96: 1381 | BM96: 1381
A97: 1 | D97: 1502110500 | E97: 管理課 | F97: R05/08/01 | G97: R05/08/01 | H97: 令和４年度下水道使用料減額調定 １件 | I97: 振替伝票（予算振替） | J97: 37000151 | K97: 000 | L97: 001 | M97: 1 | N97: 0885060600 | O97: 下水道事業費用 | P97: 特別損失 | Q97: 過年度損益修正損 | R97: 過年度損益修正損 | T97: 921481 | U97: 下水道使用料賦課徴収 | V97: 0 | W97: 0 | X97: 0 | Y97: 1540 | Z97: 088506001006000000 | AA97: 過年度損益修正損 | AB97: 1540 | AC97: 021402001002011000 | AD97: 未収下水道使用料１ | AE97: 1540 | AF97: 18 | AG97: 10 | AH97: 140 | AI97: 1400 | AL97: 37000151-000-001-1-0885060600-921481-18 | AM97: 1 | AN97: 0 | AO97: 0 | AP97: 0 | AS97: 18 | AT97: 10 | AV97: 0 | AW97: 0 | AX97: 0 | AY97: 0 | AZ97: 0 | BA97: 1540 | BB97: 1540 | BC97: 1540 | BD97: 0 | BF97: 0 | BG97: 0 | BH97: 0 | BI97: 0 | BJ97: 0 | BK97: 1400 | BL97: 1400 | BM97: 1400
A98: 1 | D98: 1502110500 | E98: 管理課 | F98: R05/08/01 | G98: R05/08/01 | H98: 令和４年度下水道使用料減額調定 １件 | I98: 振替伝票（予算振替） | J98: 37000147 | K98: 000 | L98: 001 | M98: 1 | N98: 0885060600 | O98: 下水道事業費用 | P98: 特別損失 | Q98: 過年度損益修正損 | R98: 過年度損益修正損 | T98: 921481 | U98: 下水道使用料賦課徴収 | V98: 0 | W98: 0 | X98: 0 | Y98: 10403 | Z98: 088506001006000000 | AA98: 過年度損益修正損 | AB98: 10403 | AC98: 021402001002011000 | AD98: 未収下水道使用料１ | AE98: 10403 | AF98: 18 | AG98: 10 | AH98: 944 | AI98: 9459 | AL98: 37000147-000-001-1-0885060600-921481-18 | AM98: 1 | AN98: 0 | AO98: 0 | AP98: 0 | AS98: 18 | AT98: 10 | AV98: 0 | AW98: 0 | AX98: 0 | AY98: 0 | AZ98: 0 | BA98: 10403 | BB98: 10403 | BC98: 10403 | BD98: 0 | BF98: 0 | BG98: 0 | BH98: 0 | BI98: 0 | BJ98: 0 | BK98: 9457 | BL98: 9457 | BM98: 9457
A99: 1 | D99: 1502110500 | E99: 管理課 | F99: R05/09/01 | G99: R05/09/01 | H99: 令和４年度下水道使用料減額調定 １件 | I99: 振替伝票（予算振替） | J99: 37000178 | K99: 000 | L99: 001 | M99: 1 | N99: 0885060600 | O99: 下水道事業費用 | P99: 特別損失 | Q99: 過年度損益修正損 | R99: 過年度損益修正損 | T99: 921481 | U99: 下水道使用料賦課徴収 | V99: 0 | W99: 0 | X99: 0 | Y99: 18931 | Z99: 088506001006000000 | AA99: 過年度損益修正損 | AB99: 18931 | AC99: 021402001002011000 | AD99: 未収下水道使用料１ | AE99: 18931 | AF99: 18 | AG99: 10 | AH99: 1720 | AI99: 17211 | AL99: 37000178-000-001-1-0885060600-921481-18 | AM99: 1 | AN99: 0 | AO99: 0 | AP99: 0 | AS99: 18 | AT99: 10 | AV99: 0 | AW99: 0 | AX99: 0 | AY99: 0 | AZ99: 0 | BA99: 18931 | BB99: 18931 | BC99: 18931 | BD99: 0 | BF99: 0 | BG99: 0 | BH99: 0 | BI99: 0 | BJ99: 0 | BK99: 17210 | BL99: 17210 | BM99: 17210
A100: 1 | D100: 1502110500 | E100: 管理課 | F100: R05/08/01 | G100: R05/08/01 | H100: 令和４年度下水道使用料減額調定 ２件 | I100: 振替伝票（予算振替） | J100: 37000153 | K100: 000 | L100: 001 | M100: 1 | N100: 0885060600 | O100: 下水道事業費用 | P100: 特別損失 | Q100: 過年度損益修正損 | R100: 過年度損益修正損 | T100: 921481 | U100: 下水道使用料賦課徴収 | V100: 0 | W100: 0 | X100: 0 | Y100: 23778 | Z100: 088506001006000000 | AA100: 過年度損益修正損 | AB100: 23778 | AC100: 021402001002011000 | AD100: 未収下水道使用料１ | AE100: 23778 | AF100: 18 | AG100: 10 | AH100: 2162 | AI100: 21616 | AL100: 37000153-000-001-1-0885060600-921481-18 | AM100: 1 | AN100: 0 | AO100: 0 | AP100: 0 | AS100: 18 | AT100: 10 | AV100: 0 | AW100: 0 | AX100: 0 | AY100: 0 | AZ100: 0 | BA100: 23778 | BB100: 23778 | BC100: 23778 | BD100: 0 | BF100: 0 | BG100: 0 | BH100: 0 | BI100: 0 | BJ100: 0 | BK100: 21616 | BL100: 21616 | BM100: 21616
... A110: 3 | D110: 1502110500 | E110: 管理課 | F110: R05/04/20 | G110: R05/04/20 | H110: 令和４年度下水道使用料減額調定（農集） ０件 | I110: 振替伝票（予算振替） | J110: 37000069 | K110: 000 | L110: 001 | M110: 1 | N110: 0885060600 | O110: 下水道事業費用 | P110: 特別損失 | Q110: 過年度損益修正損 | R110: 過年度損益修正損 | T110: 921614 | U110: 下水道使用料賦課修正損（農集） | V110: 0 | W110: 0 | X110: 0 | Y110: 35499 | Z110: 088506001006000000 | AA110: 過年度損益修正損 | AB110: 35499 | AC110: 021402001002011000 | AD110: 未収下水道使用料１ | AE110: 35499 | AF110: 18 | AG110: 10 | AH110: 3227 | AI110: 32272 | AL110: 37000069-000-001-1-0885060600-921614-18 | AM110: 1 | AN110: 0 | AO110: 0 | AP110: 0 | AS110: 18 | AT110: 10 | AV110: 0 | AW110: 0 | AX110: 0 | AY110: 0 | AZ110: 0 | BA110: 35499 | BB110: 35499 | BC110: 35499 | BD110: 0 | BF110: 0 | BG110: 0 | BH110: 0 | BI110: 0 | BJ110: 0 | BK110: 32272 | BL110: 32272 | BM110: 32272

Sheet 基礎数値
B1: =+CONCATENATE(LEFT('[3]3条支出'!$D$1,8)," 消費税計算に係る基礎数値") -> 令和５年度決算 消費税計算に係る基礎数値
D2: 3%適用部分 | E2: 5%適用部分 | F2: 8%適用部分 | G2: 8%（軽）適用部分 | H2: 10%適用部分 | I2: 計 | J2: 備考
B3: 収益的収入のうち課税売上（税込） | D3: =+'[2]3条収入'!F69 -> 0 | E3: =+'[2]3条収入'!G69 -> 0 | F3: =+'[2]3条収入'!H69 -> 47053 | G3: =+'[2]3条収入'!I69 -> 0 | H3: =+'[2]3条収入'!J69 -> 20730008529 | I3: =SUM(D3:H3) -> 20730055582 | J3: 「決算総括表」より
B4: 資本的収入のうち課税売上（税込） | D4: =+'[4]4条収入'!F91 -> 0 | E4: =+'[4]4条収入'!G91 -> 0 | F4: =+'[4]4条収入'!H91 -> 0 | G4: =+'[4]4条収入'!I91 -> 0 | H4: =+'[4]4条収入'!J91 -> 39691410 | I4: =SUM(D4:H4) -> 39691410 | J4: 「決算総括表」より
B5: 課税売上から控除するもの
C6: 仕入対価の返還等の額（税込） | D6: =+対価返還!BC3 -> 0 | E6: =+対価返還!BC4 -> 0 | F6: =+対価返還!BC5 -> 0 | G6: =+対価返還!BC6 -> 0 | H6: =+対価返還!BC7 -> 0 | I6: =SUM(D6:H6) -> 0 | J6: 「過年度損益修正益」「その他特別利益」のうち、課税支出が返還されたもの（過去に支払った通勤手当の還付、建設負担金の精算に伴う還付など）
C7: 売上対価の返還等の額（税込） | D7: =+対価返還!BC9 -> 0 | E7: =+対価返還!BC10 -> 0 | F7: =+対価返還!BC11 -> 39339 | G7: =+対価返還!BC12 -> 0 | H7: =+対価返還!BC13 -> 10639743 | I7: =SUM(D7:H7) -> 10679082 | J7: 「雑支出」「過年度損益修正損」「その他特別損失」のうち、課税収入を返還したもの（下水道使用料の調定減額、過誤納還付金など）
B8: 免税売上額 | I8: =+'[2]3条収入'!M69 -> 86860 | J8: 管理課資料、「決算総括表」より
B9: 収益的収入のうち非課税売上（税込） | I9: =+'[2]3条収入'!L69 -> 22644840 | J9: 「決算総括表」より
B10: 資本的収入のうち非課税売上（税込） | I10: =+'[4]4条収入'!L91 -> 45948113 | J10: 「決算総括表」より
B11: 収益的支出のうち課税支出（税込） | D11: =+'[3]3条支出'!F41+D17 -> 0 | E11: =+'[3]3条支出'!G41+E17 -> 1120996 | F11: =+'[3]3条支出'!H41+F17 -> 25903142 | G11: =+'[3]3条支出'!I41+G17 -> 500878 | H11: =+'[3]3条支出'!J41+H17 -> 9106828850 | I11: =SUM(D11:H11) -> 9134353866 | J11: 「決算総括表」より （H27決算から貸倒引当金の取り崩し分を計上）
B12: 資本的支出のうち課税支出（税込） | D12: =+'[5]4条支出'!F41 -> 0 | E12: =+'[5]4条支出'!G41 -> 0 | F12: =+'[5]4条支出'!H41 -> 125712 | G12: =+'[5]4条支出'!I41 -> 36840 | H12: =+'[5]4条支出'!J41 -> 16278736624 | I12: =SUM(D12:H12) -> 16278899176 | J12: 「決算総括表」より
B13: 課税仕入れから控除するもの
C14: 返還等対価・貸倒れの額（税込） | D14: =+D7+D17 -> 0 | E14: =+E7+E17 -> 1120996 | F14: =+F7+F17 -> 24706340 | G14: =+G7+G17 -> 0 | H14: =+H7+H17 -> 10639743 | I14: =SUM(D14:H14) -> 36467079 | J14: 「雑支出」「過年度損益修正損」「その他特別損失」の課税支出うち、該当分（下水道使用料の減額調定・過誤納還付金・時効欠損*、排水設備取付管設置工事受託金の還付など）
C15: 仕入対価の返還等の額（税込） | D15: =+D6 -> 0 | E15: =+E6 -> 0 | F15: =+F6 -> 0 | G15: =+G6 -> 0 | H15: =+H6 -> 0 | I15: =SUM(D15:H15) -> 0
B16: 免税業者との取引額（税込） | D16: 0 | G16: 0 | H16: 34600 | I16: =SUM(D16:H16) -> 34600 | J16: 免税業者との取引額を税込額で入力
B17: 貸倒れに係る金額（税込） | D17: 0 | E17: 1120996 | F17: 24667001 | G17: 0 | H17: 0 | I17: =SUM(D17:H17) -> 25787997 | J17: 特別損失の課税支出のうち、時効欠損分*
B18: 収益的支出のうち特定収入 | D18: =+[7]総括表!K62 -> 0 | E18: =+[7]総括表!L62 -> 0 | F18: =+[7]総括表!M62 -> 455392 | G18: =+[7]総括表!N62 -> 130568 | H18: =+[7]総括表!O62 -> 2312306920 | I18: =SUM(D18:H18) -> 2312892880 | J18: 「決算総括表」の「不課税収入」のうち「課税仕入に特定」
B19: 資本的支出のうち特定収入 | D19: =+[7]総括表!K172 -> 0 | E19: =+[7]総括表!L172 -> 131982078 | F19: =+[7]総括表!M172 -> 1246904 | G19: =+[7]総括表!N172 -> 99 | H19: =+[7]総括表!O172 -> 5972404802 | I19: =SUM(D19:H19) -> 6105633883
B20: 使途不特定の特定収入 | I20: 0
B21: 中間納付税額
C22: 消費税 | I22: 365767600
C23: 地方消費税 | I23: 103164600
C24: 計 | I24: =SUM(I22:I23) -> 468932200
J25: ＊時効欠損は、平成26年度の会計制度の見直しに伴い、貸倒引当金を繰り入れたことから、平成27年度申告からは取崩し分を計上する

Sheet 消費税
F1: 消費税率 | G1: 0.03 | H1: 0.04 | I1: 0.063 | J1: 0.0624 | K1: 0.078 | N1: 消費税率 | O1: =+G1 -> 0.03 | P1: =+H1 -> 0.04 | Q1: =+I1 -> 0.063 | R1: =+J1 -> 0.0624 | S1: =+K1 -> 0.078 | U1: =+G1 -> 0.03 | V1: =+H1 -> 0.04 | W1: =+I1 -> 0.063 | X1: =+R1 -> 0.0624 | Y1: =+K1 -> 0.078 | AA1: =+G1 -> 0.03 | AB1: =+H1 -> 0.04 | AC1: =+I1 -> 0.063 | AD1: =+X1 -> 0.0624 | AE1: =+K1 -> 0.078
F2: 地方消費税率 | G2: =+G7-G1 -> 0 | H2: =+H7-H1 -> 0.01 | I2: =+I7-I1 -> 0.017 | J2: =+J7-J1 -> 0.0176 | K2: =+K7-K1 -> 0.022 | N2: 地方消費税率 | O2: =+O7-O1 -> 0 | P2: =+P7-P1 -> 0.01 | Q2: =+Q7-Q1 -> 0.017 | R2: =+R7-R1 -> 0.0176 | S2: =+S7-S1 -> 0.022 | U2: =+U7-U1 -> 0 | V2: =+V7-V1 -> 0.01 | W2: =+W7-W1 -> 0.017 | X2: =+X7-X1 -> 0.0176 | Y2: =+Y7-Y1 -> 0.022 | AA2: =+AA7-AA1 -> 0 | AB2: =+AB7-AB1 -> 0.01 | AC2: =+AC7-AC1 -> 0.017 | AD2: =+AD7-AD1 -> 0.0176 | AE2: =+AE7-AE1 -> 0.022
B3: =+CONCATENATE(LEFT('[3]3条支出'!$D$1,8)," 消費税等計算チェックシート") -> 令和５年度決算 消費税等計算チェックシート | L3: 単位：円 | AF3: 単位：円
B4: チェック項目 | F4: 収益的収支・資本的収支の別 | G4: 申告ベース（収益的収支と資本的収支の合計額） | N4: 収益的収支・資本的収支の別 | O4: 収益的収支のみ+資本的収支のみの単純計 | U4: 収益的収支のみ | AA4: 資本的収支のみ
E5: 区 分 | F5: 消費税及び地方消費税の計算 | G5: 申告ベース（消費税を計算後、地方消費税を計算） | N5: 消費税及び地方消費税の計算 | O5: 「消費税」を「消費税及び地方消費税」に読み替えて計算 | U5: 「消費税」を「消費税及び地方消費税」に読み替えて計算 | AA5: 「消費税」を「消費税及び地方消費税」に読み替えて計算
F6: 金額単位端数処理の取扱い | G6: 申告ベース（課税標準額千円単位、納税額百円単位） | N6: 金額単位端数処理の取扱い | O6: 1円単位での端数処理 | U6: 1円単位での端数処理 | AA6: 1円単位での端数処理
E7: 検証 | F7: 計算 | G7: 0.03 | H7: 0.05 | I7: 0.08 | J7: 0.08 | K7: 0.1 | L7: 合計 | M7: 申告書等 | N7: 計算 | O7: 0.03 | P7: 0.05 | Q7: 0.08 | R7: 0.08 | S7: 0.1 | T7: 合計 | U7: 0.03 | V7: 0.05 | W7: 0.08 | X7: 0.08 | Y7: 0.1 | Z7: 合計 | AA7: 0.03 | AB7: 0.05 | AC7: 0.08 | AD7: 0.08 | AE7: 0.1 | AF7: 合計
B8: 課税標準等 | C8: 1 | D8: 行政手数料収入を課税売上にしていないか（一部のものを除き、非課税となる） | E8: 「その他営業収益」の「手数料」をチェック
C10: 2 | D10: 土地の貸付（原則非課税）のうち、契約期間が1か月未満の場合や、駐車場その他の施設の利用に伴って土地が使用される場合は課税としているか | E10: 「雑収益」の「その他雑収益」をチェック
C13: 3 | D13: 課税の対象となる対価補償金以外の補償金を課税売上にしていないか（水道管移設保証金、ガス管移設保証金等は不課税）
C16: 4 | D16: 損害賠償金を課税売上にしていないか（一般的には不課税）
C18: 5 | D18: 建物等固定資産（土地を除く）の売却について、差益部分のみを課税売上にしていないか | E18: 「固定資産売却益」及び「土地売却代金」をチェック
C20: 6 | D20: 車両等を購入した場合、下取り価額を課税売上にしていないか
C22: 7 | D22: 土地建物一括譲渡の場合、対価の額の区分は正しいか
C24: 8 | D24: 課税売上額の計算 | E24: 収益的収入のうち課税売上（税込） | G24: =+基礎数値!$D3 -> 0 | H24: =+基礎数値!$E3 -> 0 | I24: =+基礎数値!$F3 -> 47053 | J24: =+基礎数値!$G3 -> 0 | K24: =+基礎数値!$H3 -> 20730008529 | L24: =+SUM(G24:K24) -> 20730055582 | O24: =+U24+AA24 -> 0 | P24: =+V24+AB24 -> 0 | Q24: =+W24+AC24 -> 47053 | R24: =+X24+AD24 -> 0 | S24: =+Y24+AE24 -> 20730008529 | T24: =+Z24+AF24 -> 20730055582 | U24: =+基礎数値!$D3 -> 0 | V24: =+基礎数値!$E3 -> 0 | W24: =+基礎数値!$F3 -> 47053 | X24: =+基礎数値!$G3 -> 0 | Y24: =+基礎数値!$H3 -> 20730008529 | Z24: =+SUM(U24:Y24) -> 20730055582 | AF24: =+SUM(AA24:AE24) -> 0
E25: 資本的収入のうち課税売上（税込） | G25: =+基礎数値!$D4 -> 0 | H25: =+基礎数値!$E4 -> 0 | I25: =+基礎数値!$F4 -> 0 | J25: =+基礎数値!$G4 -> 0 | K25: =+基礎数値!$H4 -> 39691410 | L25: =+SUM(G25:K25) -> 39691410 | O25: =+U25+AA25 -> 0 | P25: =+V25+AB25 -> 0 | Q25: =+W25+AC25 -> 0 | R25: =+X25+AD25 -> 0 | S25: =+Y25+AE25 -> 39691410 | T25: =+Z25+AF25 -> 39691410 | Z25: =+SUM(U25:Y25) -> 0 | AA25: =+基礎数値!$D4 -> 0 | AB25: =+基礎数値!$E4 -> 0 | AC25: =+基礎数値!$F4 -> 0 | AD25: =+基礎数値!$G4 -> 0 | AE25: =+基礎数値!$H4 -> 39691410 | AF25: =+SUM(AA25:AE25) -> 39691410
E26: 課税売上（税込） 計 | F26: A | G26: =+SUM(G24:G25) -> 0 | H26: =+SUM(H24:H25) -> 0 | I26: =+SUM(I24:I25) -> 47053 | J26: =+SUM(J24:J25) -> 0 | K26: =+SUM(K24:K25) -> 20769699939 | L26: =+SUM(G26:K26) -> 20769746992 | N26: A | O26: =+U26+AA26 -> 0 | P26: =+V26+AB26 -> 0 | Q26: =+W26+AC26 -> 47053 | R26: =+X26+AD26 -> 0 | S26: =+Y26+AE26 -> 20769699939 | T26: =+Z26+AF26 -> 20769746992 | U26: =+SUM(U24:U25) -> 0 | V26: =+SUM(V24:V25) -> 0 | W26: =+SUM(W24:W25) -> 47053 | X26: =+SUM(X24:X25) -> 0 | Y26: =+SUM(Y24:Y25) -> 20730008529 | Z26: =+SUM(U26:Y26) -> 20730055582 | AA26: =+SUM(AA24:AA25) -> 0 | AB26: =+SUM(AB24:AB25) -> 0 | AC26: =+SUM(AC24:AC25) -> 0 | AD26: =+SUM(AD24:AD25) -> 0 | AE26: =+SUM(AE24:AE25) -> 39691410 | AF26: =+SUM(AA26:AE26) -> 39691410
E27: 課税売上から控除するもの
E28: 仕入対価の返還等の額 | F28: B | G28: =+基礎数値!$D6 -> 0 | H28: =+基礎数値!$E6 -> 0 | I28: =+基礎数値!$F6 -> 0 | J28: =+基礎数値!$G6 -> 0 | K28: =+基礎数値!$H6 -> 0 | L28: =+SUM(G28:K28) -> 0 | N28: B | O28: =+U28+AA28 -> 0 | P28: =+V28+AB28 -> 0 | Q28: =+W28+AC28 -> 0 | R28: =+X28+AD28 -> 0 | S28: =+Y28+AE28 -> 0 | T28: =+Z28+AF28 -> 0 | U28: =+基礎数値!$D6 -> 0 | V28: =+基礎数値!$E6 -> 0 | W28: =+基礎数値!$F6 -> 0 | X28: =+基礎数値!$G6 -> 0 | Y28: =+基礎数値!$H6 -> 0 | Z28: =+SUM(U28:Y28) -> 0 | AF28: =+SUM(AA28:AE28) -> 0
E29: 売上対価の返還等の額 | F29: C | G29: =+基礎数値!$D7 -> 0 | H29: =+基礎数値!$E7 -> 0 | I29: =+基礎数値!$F7 -> 39339 | J29: =+基礎数値!$G7 -> 0 | K29: =+基礎数値!$H7 -> 10639743 | L29: =+SUM(G29:K29) -> 10679082 | N29: C | O29: =+U29+AA29 -> 0 | P29: =+V29+AB29 -> 0 | Q29: =+W29+AC29 -> 39339 | R29: =+X29+AD29 -> 0 | S29: =+Y29+AE29 -> 10639743 | T29: =+Z29+AF29 -> 10679082 | U29: =+基礎数値!$D7 -> 0 | V29: =+基礎数値!$E7 -> 0 | W29: =+基礎数値!$F7 -> 39339 | X29: =+基礎数値!$G7 -> 0 | Y29: =+基礎数値!$H7 -> 10639743 | Z29: =+SUM(U29:Y29) -> 10679082 | AF29: =+SUM(AA29:AE29) -> 0
E30: 課税売上額（税抜） | F30: D=（A-B-C)×（消費税及び地方消費税率） /（1+消費税及び地方消費税率） | G30: =+ROUNDDOWN((G26-G28-G29)*1/(1+G$7),0) -> 0 | H30: =+ROUNDDOWN((H26-H28-H29)*1/(1+H$7),0) -> 0 | I30: =+ROUNDDOWN((I26-I28-I29)*1/(1+I$7),0) -> 7142 | J30: =+ROUNDDOWN((J26-J28-J29)*1/(1+J$7),0) -> 0 | K30: =+ROUNDDOWN((K26-K28-K29)*1/(1+K$7),0) -> 18871872905 | L30: =+SUM(G30:K30) -> 18871880047 | M30: 付表２① | N30: D=（A-B-C)×（消費税及び地方消費税率） /（1+消費税及び地方消費税率） | O30: =+U30+AA30 -> 0 | P30: =+V30+AB30 -> 0 | Q30: =+W30+AC30 -> 7142 | R30: =+X30+AD30 -> 0 | S30: =+Y30+AE30 -> 18871872905 | T30: =+Z30+AF30 -> 18871880047 | U30: =+ROUNDDOWN((U26-U28-U29)*1/(1+U$7),0) -> 0 | V30: =+ROUNDDOWN((V26-V28-V29)*1/(1+V$7),0) -> 0 | W30: =+ROUNDDOWN((W26-W28-W29)*1/(1+W$7),0) -> 7142 | X30: =+ROUNDDOWN((X26-X28-X29)*1/(1+X$7),0) -> 0 | Y30: =+ROUNDDOWN((Y26-Y28-Y29)*1/(1+Y$7),0) -> 18835789805 | Z30: =+SUM(U30:Y30) -> 18835796947 | AA30: =+ROUNDDOWN((AA26-AA28-AA29)*1/(1+AA$7),0) -> 0 | AB30: =+ROUNDDOWN((AB26-AB28-AB29)*1/(1+AB$7),0) -> 0 | AC30: =+ROUNDDOWN((AC26-AC28-AC29)*1/(1+AC$7),0) -> 0 | AD30: =+ROUNDDOWN((AD26-AD28-AD29)*1/(1+AD$7),0) -> 0 | AE30: =+ROUNDDOWN((AE26-AE28-AE29)*1/(1+AE$7),0) -> 36083100 | AF30: =+SUM(AA30:AE30) -> 36083100
E31: 課税標準額（税抜） | F31: E=（A-B)×1/（1+消費税及び地方消費税率） | G31: =+ROUNDDOWN((G26-G28)*1/(1+G$7),-3) -> 0 | H31: =+ROUNDDOWN((H26-H28)*1/(1+H$7),-3) -> 0 | I31: =+ROUNDDOWN((I26-I28)*1/(1+I$7),-3) -> 43000 | J31: =+ROUNDDOWN((J26-J28)*1/(1+J$7),-3) -> 0 | K31: =+ROUNDDOWN((K26-K28)*1/(1+K$7),-3) -> 18881545000 | L31: =+SUM(G31:K31) -> 18881588000 | M31: 申告書① | N31: E=（A-B)×1/（1+消費税及び地方消費税率） | O31: =+U31+AA31 -> 0 | P31: =+V31+AB31 -> 0 | Q31: =+W31+AC31 -> 43567 | R31: =+X31+AD31 -> 0 | S31: =+Y31+AE31 -> 18881545399 | T31: =+Z31+AF31 -> 18881588966 | U31: =+ROUNDDOWN((U26-U28)*1/(1+U$7),0) -> 0 | V31: =+ROUNDDOWN((V26-V28)*1/(1+V$7),0) -> 0 | W31: =+ROUNDDOWN((W26-W28)*1/(1+W$7),0) -> 43567 | X31: =+ROUNDDOWN((X26-X28)*1/(1+X$7),0) -> 0 | Y31: =+ROUNDDOWN((Y26-Y28)*1/(1+Y$7),0) -> 18845462299 | Z31: =+SUM(U31:Y31) -> 18845505866 | AA31: =+ROUNDDOWN((AA26-AA28)*1/(1+AA$7),0) -> 0 | AB31: =+ROUNDDOWN((AB26-AB28)*1/(1+AB$7),0) -> 0 | AC31: =+ROUNDDOWN((AC26-AC28)*1/(1+AC$7),0) -> 0 | AD31: =+ROUNDDOWN((AD26-AD28)*1/(1+AD$7),0) -> 0 | AE31: =+ROUNDDOWN((AE26-AE28)*1/(1+AE$7),0) -> 36083100 | AF31: =+SUM(AA31:AE31) -> 36083100
E32: 課税標準額に対する消費税額 | F32: F=E×(消費税率） | G32: =+ROUNDDOWN(G31*G$1,0) -> 0 | H32: =+ROUNDDOWN(H31*H$1,0) -> 0 | I32: =+ROUNDDOWN(I31*I$1,0) -> 2709 | J32: =+ROUNDDOWN(J31*J$1,0) -> 0 | K32: =+ROUNDDOWN(K31*K$1,0) -> 1472760510 | L32: =+SUM(G32:K32) -> 1472763219 | M32: 申告書② | N32: F=E×（消費税及び地方消費税率） | O32: =+U32+AA32 -> 0 | P32: =+V32+AB32 -> 0 | Q32: =+W32+AC32 -> 3485 | R32: =+X32+AD32 -> 0 | S32: =+Y32+AE32 -> 1888154539 | T32: =+Z32+AF32 -> 1888158024 | U32: =+ROUNDDOWN(U31*U$7,0)+U135 -> 0 | V32: =+ROUNDDOWN(V31*V$7,0)+V135 -> 0 | W32: =+ROUNDDOWN(W31*W$7,0)+W135 -> 3485 | X32: =+ROUNDDOWN(X31*X$7,0)+X135 -> 0 | Y32: =+ROUNDDOWN(Y31*Y$7,0)+Y135 -> 1884546229 | Z32: =+SUM(U32:Y32) -> 1884549714 | AA32: =+ROUNDDOWN(AA31*AA$7,0)+AA135 -> 0 | AB32: =+ROUNDDOWN(AB31*AB$7,0)+AB135 -> 0 | AC32: =+ROUNDDOWN(AC31*AC$7,0)+AC135 -> 0 | AD32: =+ROUNDDOWN(AD31*AD$7,0)+AD135 -> 0 | AE32: =+ROUNDDOWN(AE31*AE$7,0)+AE135 -> 3608310 | AF32: =+SUM(AA32:AE32) -> 3608310
B33: 課税売上割合 | C33: 1 | D33: 課税売上割合の計算 | E33: 課税売上額 | F33: Dの合計（各税率の合計） | L33: =+L30 -> 18871880047 | N33: Dの合計（各税率の合計） | T33: =+L33 -> 18871880047
E34: 免税売上額 | F34: G | L34: =+基礎数値!$I8 -> 86860 | M34: 付表２② | N34: G | T34: =+基礎数値!$I8 -> 86860 | AG34: 管理課資料、「決算総括表」より
E35: 課税資産の譲渡等の対価の額 | F35: H=Dの合計+G | L35: =SUM(L33:L34) -> 18871966907 | M35: 申告書⑮ 付表２④⑤ | N35: H=Dの合計+G | T35: =+L35 -> 18871966907 | AG35: 課税売上割合の分子
E36: 収益的収入のうち非課税売上（税込） | L36: =+基礎数値!$I9 -> 22644840 | T36: =+基礎数値!$I9 -> 22644840 | AG36: 「決算総括表」より
E37: 資本的収入のうち非課税売上（税込） | L37: =+基礎数値!$I10 -> 45948113 | M37: 付表２⑥ | T37: =+基礎数値!$I10 -> 45948113 | AG37: 「決算総括表」より
E38: 非課税売上（税込） 計 | F38: Ｉ=3条非課税+4条非課税 | L38: =+SUM(L36:L37) -> 68592953 | N38: Ｉ=3条非課税+4条非課税 | T38: =+L38 -> 68592953
E39: 資産の譲渡等の対価の額 | F39: J=H＋I | L39: =+SUM(L35,L38) -> 18940559860 | M39: 申告書⑯、付表２⑦ | N39: J=H＋I | T39: =+L39 -> 18940559860 | AG39: 課税売上割合の分母
E40: 課税売上割合（端数切捨） | F40: =H/J（=下記Q） | L40: =+ROUND(L35/L39,4) -> 0.9964 | M40: 付表２④/⑦ | N40: =H/J（=下記Q） | T40: =+L40 -> 0.9964 | AG40: 端数切捨て
B41: 課税仕入れ | C41: 1 | D41: 土地の借受（原則非課税）のうち、契約期間が1か月未満の場合や、駐車場その他の施設の利用に伴って土地を使用する場合は課税としているか | E41: 賃借料をチェック | O41: =+U41+AA41 -> 0 | P41: =+V41+AB41 -> 0 | Q41: =+W41+AC41 -> 0 | R41: =+X41+AD41 -> 0 | S41: =+Y41+AE41 -> 0 | T41: =+Z41+AF41 -> 0
O42: =+U42+AA42 -> 0 | P42: =+V42+AB42 -> 0 | Q42: =+W42+AC42 -> 0 | R42: =+X42+AD42 -> 0 | S42: =+Y42+AE42 -> 0 | T42: =+Z42+AF42 -> 0
O43: =+U43+AA43 -> 0 | P43: =+V43+AB43 -> 0 | Q43: =+W43+AC43 -> 0 | R43: =+X43+AD43 -> 0 | S43: =+Y43+AE43 -> 0 | T43: =+Z43+AF43 -> 0
C44: 2 | D44: 課税の対象となる対価補償金以外の補償金を課税仕入れにしていないか（水道管移設保証金、ガス管移設保証金等は不課税） | E44: 保証金をチェック | O44: =+U44+AA44 -> 0 | P44: =+V44+AB44 -> 0 | Q44: =+W44+AC44 -> 0 | R44: =+X44+AD44 -> 0 | S44: =+Y44+AE44 -> 0 | T44: =+Z44+AF44 -> 0
O45: =+U45+AA45 -> 0 | P45: =+V45+AB45 -> 0 | Q45: =+W45+AC45 -> 0 | R45: =+X45+AD45 -> 0 | S45: =+Y45+AE45 -> 0 | T45: =+Z45+AF45 -> 0
O46: =+U46+AA46 -> 0 | P46: =+V46+AB46 -> 0 | Q46: =+W46+AC46 -> 0 | R46: =+X46+AD46 -> 0 | S46: =+Y46+AE46 -> 0 | T46: =+Z46+AF46 -> 0
C47: 3 | D47: 損害賠償金を課税仕入れにしていないか（一般的には不課税） | O47: =+U47+AA47 -> 0 | P47: =+V47+AB47 -> 0 | Q47: =+W47+AC47 -> 0 | R47: =+X47+AD47 -> 0 | S47: =+Y47+AE47 -> 0 | T47: =+Z47+AF47 -> 0
O48: =+U48+AA48 -> 0 | P48: =+V48+AB48 -> 0 | Q48: =+W48+AC48 -> 0 | R48: =+X48+AD48 -> 0 | S48: =+Y48+AE48 -> 0 | T48: =+Z48+AF48 -> 0
C49: 4 | D49: 免税・非課税・不課税仕入れを課税仕入れにしていないか | E49: 各費目をチェック | O49: =+U49+AA49 -> 0 | P49: =+V49+AB49 -> 0 | Q49: =+W49+AC49 -> 0 | R49: =+X49+AD49 -> 0 | S49: =+Y49+AE49 -> 0 | T49: =+Z49+AF49 -> 0
O50: =+U50+AA50 -> 0 | P50: =+V50+AB50 -> 0 | Q50: =+W50+AC50 -> 0 | R50: =+X50+AD50 -> 0 | S50: =+Y50+AE50 -> 0 | T50: =+Z50+AF50 -> 0
C51: 5 | D51: 資産の譲渡損を課税仕入れにしていないか | E51: 固定資産売却損をチェック | O51: =+U51+AA51 -> 0 | P51: =+V51+AB51 -> 0 | Q51: =+W51+AC51 -> 0 | R51: =+X51+AD51 -> 0 | S51: =+Y51+AE51 -> 0 | T51: =+Z51+AF51 -> 0
O52: =+U52+AA52 -> 0 | P52: =+V52+AB52 -> 0 | Q52: =+W52+AC52 -> 0 | R52: =+X52+AD52 -> 0 | S52: =+Y52+AE52 -> 0 | T52: =+Z52+AF52 -> 0
C53: 6 | D53: 経過措置対象取引（3%取引）がある場合、課税仕入れを3%取引と4%取引に区分して計算しているか | E53: 該当なし | O53: =+U53+AA53 -> 0 | P53: =+V53+AB53 -> 0 | Q53: =+W53+AC53 -> 0 | R53: =+X53+AD53 -> 0 | S53: =+Y53+AE53 -> 0 | T53: =+Z53+AF53 -> 0
O54: =+U54+AA54 -> 0 | P54: =+V54+AB54 -> 0 | Q54: =+W54+AC54 -> 0 | R54: =+X54+AD54 -> 0 | S54: =+Y54+AE54 -> 0 | T54: =+Z54+AF54 -> 0
C55: 7 | D55: 課税仕入れ等の税額の計算 | E55: 収益的支出のうち課税支出（税込） | G55: =+基礎数値!$D11 -> 0 | H55: =+基礎数値!$E11 -> 1120996 | I55: =+基礎数値!$F11 -> 25903142 | J55: =+基礎数値!$G11 -> 500878 | K55: =+基礎数値!$H11 -> 9106828850 | L55: =+SUM(G55:K55) -> 9134353866 | O55: =+U55+AA55 -> 0 | P55: =+V55+AB55 -> 1120996 | Q55: =+W55+AC55 -> 25903142 | R55: =+X55+AD55 -> 500878 | S55: =+Y55+AE55 -> 9106828850 | T55: =+Z55+AF55 -> 9134353866 | U55: =+基礎数値!$D11 -> 0 | V55: =+基礎数値!$E11 -> 1120996 | W55: =+基礎数値!$F11 -> 25903142 | X55: =+基礎数値!$G11 -> 500878 | Y55: =+基礎数値!$H11 -> 9106828850 | Z55: =+SUM(U55:Y55) -> 9134353866 | AF55: =+SUM(AA55:AE55) -> 0
E56: 資本的支出のうち課税支出（税込） | G56: =+基礎数値!$D12 -> 0 | H56: =+基礎数値!$E12 -> 0 | I56: =+基礎数値!$F12 -> 125712 | J56: =+基礎数値!$G12 -> 36840 | K56: =+基礎数値!$H12 -> 16278736624 | L56: =+SUM(G56:K56) -> 16278899176 | O56: =+U56+AA56 -> 0 | P56: =+V56+AB56 -> 0 | Q56: =+W56+AC56 -> 125712 | R56: =+X56+AD56 -> 36840 | S56: =+Y56+AE56 -> 16278736624 | T56: =+Z56+AF56 -> 16278899176 | Z56: =+SUM(U56:Y56) -> 0 | AA56: =+基礎数値!$D12 -> 0 | AB56: =+基礎数値!$E12 -> 0 | AC56: =+基礎数値!$F12 -> 125712 | AD56: =+基礎数値!$G12 -> 36840 | AE56: =+基礎数値!$H12 -> 16278736624 | AF56: =+SUM(AA56:AE56) -> 16278899176
E57: 課税支出（税込） 計 | F57: K=3条課税+4条課税 | G57: =SUM(G55:G56) -> 0 | H57: =SUM(H55:H56) -> 1120996 | I57: =SUM(I55:I56) -> 26028854 | J57: =SUM(J55:J56) -> 537718 | K57: =SUM(K55:K56) -> 25385565474 | L57: =+SUM(G57:K57) -> 25413253042 | N57: K=3条課税+4条課税 | O57: =+U57+AA57 -> 0 | P57: =+V57+AB57 -> 1120996 | Q57: =+W57+AC57 -> 26028854 | R57: =+X57+AD57 -> 537718 | S57: =+Y57+AE57 -> 25385565474 | T57: =+Z57+AF57 -> 25413253042 | U57: =SUM(U55:U56) -> 0 | V57: =SUM(V55:V56) -> 1120996 | W57: =SUM(W55:W56) -> 25903142 | X57: =SUM(X55:X56) -> 500878 | Y57: =SUM(Y55:Y56) -> 9106828850 | Z57: =+SUM(U57:Y57) -> 9134353866 | AA57: =SUM(AA55:AA56) -> 0 | AB57: =SUM(AB55:AB56) -> 0 | AC57: =SUM(AC55:AC56) -> 125712 | AD57: =SUM(AD55:AD56) -> 36840 | AE57: =SUM(AE55:AE56) -> 16278736624 | AF57: =+SUM(AA57:AE57) -> 16278899176
E58: 課税仕入れから控除するもの
E59: 免税業者との取引額 | K59: =基礎数値!H16 -> 34600 | L59: =+SUM(G59:K59) -> 34600 | S59: =+Y59+AE59 -> 34600 | T59: =+Z59+AF59 -> 34600 | Y59: =基礎数値!H16 -> 34600 | Z59: =+SUM(U59:Y59) -> 34600 | AF59: =+SUM(AA59:AE59) -> 0
E60: 免税業者との取引額のうち控除できない税額 | K60: =ROUNDDOWN(K59*0.2*K$1/(1+K$7),0) -> 490 | L60: =+SUM(G60:K60) -> 490 | S60: =+Y60+AE60 -> 629 | T60: =+Z60+AF60 -> 629 | Y60: =ROUNDDOWN(Y59*0.2*Y$7/(1+Y$7),0) -> 629 | Z60: =+SUM(U60:Y60) -> 629 | AF60: =+SUM(AA60:AE60) -> 0
E61: 免税業者との取引額のうち控除できる税額 | K61: =ROUNDDOWN(K59*K$1/(1+K$7),0)-K60 -> 1963 | L61: =+SUM(G61:K61) -> 1963 | S61: =+Y61+AE61 -> 2516 | T61: =+Z61+AF61 -> 2516 | Y61: =ROUNDDOWN(Y59*Y$7/(1+Y$7),0)-Y60 -> 2516 | Z61: =+SUM(U61:Y61) -> 2516 | AF61: =+SUM(AA61:AE61) -> 0
E62: 免税業者以外との取引額 | K62: =K66-K59 -> 25374891131 | L62: =+SUM(G62:K62) -> 25374891131 | S62: =+Y62+AE62 -> 25374891131 | T62: =+Z62+AF62 -> 25374891131 | Y62: =Y66-Y59 -> 9096154507 | Z62: =+SUM(U62:Y62) -> 9096154507 | AE62: =AE66-AE59 -> 16278736624 | AF62: =+SUM(AA62:AE62) -> 16278736624
E63: 免税業者以外との取引額の税額 | K63: =K67-K61 -> 1799310462 | L63: =+SUM(G63:K63) -> 1799310462 | S63: =+Y63+AE63 -> 2306808284 | T63: =+Z63+AF63 -> 2306808284 | Y63: =Y67-Y61 -> 826923137 | Z63: =+SUM(U63:Y63) -> 826923137 | AE63: =AE67-AE61 -> 1479885147 | AF63: =+SUM(AA63:AE63) -> 1479885147
E64: 売上対価の返還等の額 | F64: L | G64: =+基礎数値!$D14 -> 0 | H64: =+基礎数値!$E14 -> 1120996 | I64: =+基礎数値!$F14 -> 24706340 | J64: =+基礎数値!$G14 -> 0 | K64: =+基礎数値!$H14 -> 10639743 | L64: =+SUM(G64:K64) -> 36467079 | N64: L | O64: =+U64+AA64 -> 0 | P64: =+V64+AB64 -> 1120996 | Q64: =+W64+AC64 -> 24706340 | R64: =+X64+AD64 -> 0 | S64: =+Y64+AE64 -> 10639743 | T64: =+Z64+AF64 -> 36467079 | U64: =+基礎数値!$D14 -> 0 | V64: =+基礎数値!$E14 -> 1120996 | W64: =+基礎数値!$F14 -> 24706340 | X64: =+基礎数値!$G14 -> 0 | Y64: =+基礎数値!$H14 -> 10639743 | Z64: =+SUM(U64:Y64) -> 36467079 | AF64: =+SUM(AA64:AE64) -> 0
E65: 仕入対価の返還等の額 | F65: Bの再掲 | G65: =+基礎数値!$D15 -> 0 | H65: =+基礎数値!$E15 -> 0 | I65: =+基礎数値!$F15 -> 0 | J65: =+基礎数値!$G15 -> 0 | K65: =+基礎数値!$H15 -> 0 | L65: =+SUM(G65:K65) -> 0 | N65: Bの再掲 | O65: =+U65+AA65 -> 0 | P65: =+V65+AB65 -> 0 | Q65: =+W65+AC65 -> 0 | R65: =+X65+AD65 -> 0 | S65: =+Y65+AE65 -> 0 | T65: =+Z65+AF65 -> 0 | U65: =+基礎数値!$D15 -> 0 | V65: =+基礎数値!$E15 -> 0 | W65: =+基礎数値!$F15 -> 0 | X65: =+基礎数値!$G15 -> 0 | Y65: =+基礎数値!$H15 -> 0 | Z65: =+SUM(U65:Y65) -> 0 | AF65: =+SUM(AA65:AE65) -> 0
E66: 課税仕入れに係る支払対価の額（税込） | F66: =K-L-B | G66: =+G57-G64-G65 -> 0 | H66: =+H57-H64-H65 -> 0 | I66: =+I57-I64-I65 -> 1322514 | J66: =+J57-J64-J65 -> 537718 | K66: =+K57-K64-K65 -> 25374925731 | L66: =+SUM(G66:K66) -> 25376785963 | M66: 付表２⑧ | N66: =K-L-B | O66: =+U66+AA66 -> 0 | P66: =+V66+AB66 -> 0 | Q66: =+W66+AC66 -> 1322514 | R66: =+X66+AD66 -> 537718 | S66: =+Y66+AE66 -> 25374925731 | T66: =+Z66+AF66 -> 25376785963 | U66: =+U57-U64-U65 -> 0 | V66: =+V57-V64-V65 -> 0 | W66: =+W57-W64-W65 -> 1196802 | X66: =+X57-X64-X65 -> 500878 | Y66: =+Y57-Y64-Y65 -> 9096189107 | Z66: =+SUM(U66:Y66) -> 9097886787 | AA66: =+AA57-AA64-AA65 -> 0 | AB66: =+AB57-AB64-AB65 -> 0 | AC66: =+AC57-AC64-AC65 -> 125712 | AD66: =+AD57-AD64-AD65 -> 36840 | AE66: =+AE57-AE64-AE65 -> 16278736624 | AF66: =+SUM(AA66:AE66) -> 16278899176
E67: 課税仕入れに係る消費税額 | F67: M=（K-L-B)×(消費税率） /（1+消費税及び地方消費税率） | G67: =ROUNDDOWN((G57-G64)*G$1/(1+G$7),0)-ROUNDDOWN(G65*G$1/(1+G$7),0) -> 0 | H67: =ROUNDDOWN((H57-H64)*H$1/(1+H$7),0)-ROUNDDOWN(H65*H$1/(1+H$7),0) -> 0 | I67: =ROUNDDOWN((I57-I64)*I$1/(1+I$7),0)-ROUNDDOWN(I65*I$1/(1+I$7),0) -> 77146 | J67: =ROUNDDOWN((J57-J64)*J$1/(1+J$7),0)-ROUNDDOWN(J65*J$1/(1+J$7),0) -> 31068 | K67: =ROUNDDOWN((K57-K64)*K$1/(1+K$7),0)-ROUNDDOWN(K65*K$1/(1+K$7),0)-K60 -> 1799312425 | L67: =+SUM(G67:K67) -> 1799420639 | M67: 付表２⑨⑭ | N67: M=（K-L-B)×（消費税及び地方消費税率） /（1+消費税及び地方消費税率） | O67: =+U67+AA67 -> 0 | P67: =+V67+AB67 -> 0 | Q67: =+W67+AC67 -> 97964 | R67: =+X67+AD67 -> 39830 | S67: =+Y67+AE67 -> 2306810800 | T67: =+Z67+AF67 -> 2306948594 | U67: =ROUNDDOWN((U57-U64)*U$7/(1+U$7),0)-ROUNDDOWN(U65*U$7/(1+U$7),0)+U130 -> 0 | V67: =ROUNDDOWN((V57-V64)*V$7/(1+V$7),0)-ROUNDDOWN(V65*V$7/(1+V$7),0)+V130 -> 0 | W67: =ROUNDDOWN((W57-W64)*W$7/(1+W$7),0)-ROUNDDOWN(W65*W$7/(1+W$7),0)+W130 -> 88652 | X67: =ROUNDDOWN((X57-X64)*X$7/(1+X$7),0)-ROUNDDOWN(X65*X$7/(1+X$7),0)+X130 -> 37102 | Y67: =ROUNDDOWN((Y57-Y64)*Y$7/(1+Y$7),0)-ROUNDDOWN(Y65*Y$7/(1+Y$7),0)+Y130-Y60 -> 826925653 | Z67: =+SUM(U67:Y67) -> 827051407 | AA67: =ROUNDDOWN((AA57-AA64)*AA$7/(1+AA$7),0)-ROUNDDOWN(AA65*AA$7/(1+AA$7),0)+AA130 -> 0 | AB67: =ROUNDDOWN((AB57-AB64)*AB$7/(1+AB$7),0)-ROUNDDOWN(AB65*AB$7/(1+AB$7),0)+AB130 -> 0 | AC67: =ROUNDDOWN((AC57-AC64)*AC$7/(1+AC$7),0)-ROUNDDOWN(AC65*AC$7/(1+AC$7),0)+AC130 -> 9312 | AD67: =ROUNDDOWN((AD57-AD64)*AD$7/(1+AD$7),0)-ROUNDDOWN(AD65*AD$7/(1+AD$7),0)+AD130 -> 2728 | AE67: =ROUNDDOWN((AE57-AE64)*AE$7/(1+AE$7),0)-ROUNDDOWN(AE65*AE$7/(1+AE$7),0)+AE130 -> 1479885147 | AF67: =+SUM(AA67:AE67) -> 1479897187
B68: 特定収入の判定 | C68: 1 | D68: 通常の借入金（地方債の起債収入等）を特定収入にしていないか | E68: 「企業債」をチェック | O68: =+U68+AA68 -> 0 | P68: =+V68+AB68 -> 0 | Q68: =+W68+AC68 -> 0 | R68: =+X68+AD68 -> 0 | S68: =+Y68+AE68 -> 0 | T68: =+Z68+AF68 -> 0
O69: =+U69+AA69 -> 0 | P69: =+V69+AB69 -> 0 | Q69: =+W69+AC69 -> 0 | R69: =+X69+AD69 -> 0 | S69: =+Y69+AE69 -> 0 | T69: =+Z69+AF69 -> 0
C70: 2 | D70: 一般会計繰入金であっても、地方公営企業法適用企業が受け入れる出資金は特定収入から除かれる。出資金を特定収入にしていないか | E70: 「一般会計出資金」をチェック | O70: =+U70+AA70 -> 0 | P70: =+V70+AB70 -> 0 | Q70: =+W70+AC70 -> 0 | R70: =+X70+AD70 -> 0 | S70: =+Y70+AE70 -> 0 | T70: =+Z70+AF70 -> 0
O71: =+U71+AA71 -> 0 | P71: =+V71+AB71 -> 0 | Q71: =+W71+AC71 -> 0 | R71: =+X71+AD71 -> 0 | S71: =+Y71+AE71 -> 0 | T71: =+Z71+AF71 -> 0
O72: =+U72+AA72 -> 0 | P72: =+V72+AB72 -> 0 | Q72: =+W72+AC72 -> 0 | R72: =+X72+AD72 -> 0 | S72: =+Y72+AE72 -> 0 | T72: =+Z72+AF72 -> 0
C73: 3 | D73: 通常の借入金の元金返済のために一般会計から繰入金等があった場合、特定収入の判定（借入金で賄った事業のために使用されたとして使途を特定）をしているか | E73: 該当なし | O73: =+U73+AA73 -> 0 | P73: =+V73+AB73 -> 0 | Q73: =+W73+AC73 -> 0 | R73: =+X73+AD73 -> 0 | S73: =+Y73+AE73 -> 0 | T73: =+Z73+AF73 -> 0
O74: =+U74+AA74 -> 0 | P74: =+V74+AB74 -> 0 | Q74: =+W74+AC74 -> 0 | R74: =+X74+AD74 -> 0 | S74: =+Y74+AE74 -> 0 | T74: =+Z74+AF74 -> 0
O75: =+U75+AA75 -> 0 | P75: =+V75+AB75 -> 0 | Q75: =+W75+AC75 -> 0 | R75: =+X75+AD75 -> 0 | S75: =+Y75+AE75 -> 0 | T75: =+Z75+AF75 -> 0
O76: =+U76+AA76 -> 0 | P76: =+V76+AB76 -> 0 | Q76: =+W76+AC76 -> 0 | R76: =+X76+AD76 -> 0 | S76: =+Y76+AE76 -> 0 | T76: =+Z76+AF76 -> 0
C77: 4 | D77: 補助金等の一部を翌期に繰り越した場合、収入のあった課税期間で特定収入の調整（支出金額の割合により按分）を行っているか | E77: 「国庫補助金」をチェック | O77: =+U77+AA77 -> 0 | P77: =+V77+AB77 -> 0 | Q77: =+W77+AC77 -> 0 | R77: =+X77+AD77 -> 0 | S77: =+Y77+AE77 -> 0 | T77: =+Z77+AF77 -> 0
O78: =+U78+AA78 -> 0 | P78: =+V78+AB78 -> 0 | Q78: =+W78+AC78 -> 0 | R78: =+X78+AD78 -> 0 | S78: =+Y78+AE78 -> 0 | T78: =+Z78+AF78 -> 0
O79: =+U79+AA79 -> 0 | P79: =+V79+AB79 -> 0 | Q79: =+W79+AC79 -> 0 | R79: =+X79+AD79 -> 0 | S79: =+Y79+AE79 -> 0 | T79: =+Z79+AF79 -> 0
C80: 5 | D80: 還付加算金について、特定収入の判定をしているか | O80: =+U80+AA80 -> 0 | P80: =+V80+AB80 -> 0 | Q80: =+W80+AC80 -> 0 | R80: =+X80+AD80 -> 0 | S80: =+Y80+AE80 -> 0 | T80: =+Z80+AF80 -> 0
B81: 仕入税額控除の調整 | C81: 1 | D81: 特定収入割合の計算 | E81: 収益的収入のうち特定収入 | G81: =+基礎数値!$D18 -> 0 | H81: =+基礎数値!$E18 -> 0 | I81: =+基礎数値!$F18 -> 455392 | J81: =+基礎数値!$G18 -> 130568 | K81: =+基礎数値!$H18 -> 2312306920 | L81: =+SUM(G81:K81) -> 2312892880 | O81: =+U81+AA81 -> 0 | P81: =+V81+AB81 -> 0 | Q81: =+W81+AC81 -> 455392 | R81: =+X81+AD81 -> 130568 | S81: =+Y81+AE81 -> 2312306920 | T81: =+SUM(O81:S81) -> 2312892880 | U81: =+基礎数値!$D18 -> 0 | V81: =+基礎数値!$E18 -> 0 | W81: =+基礎数値!$F18 -> 455392 | X81: =+基礎数値!$G18 -> 130568 | Y81: =+基礎数値!$H18 -> 2312306920 | Z81: =+SUM(U81:Y81) -> 2312892880 | AF81: =+SUM(AA81:AE81) -> 0 | AG81: 「不課税収入」のうち「課税仕入に特定」
E82: 資本的収入のうち特定収入 | G82: =+基礎数値!$D19 -> 0 | H82: =+基礎数値!$E19 -> 131982078 | I82: =+基礎数値!$F19 -> 1246904 | J82: =+基礎数値!$G19 -> 99 | K82: =+基礎数値!$H19 -> 5972404802 | L82: =+SUM(G82:K82) -> 6105633883 | O82: =+U82+AA82 -> 0 | P82: =+V82+AB82 -> 131982078 | Q82: =+W82+AC82 -> 1246904 | R82: =+X82+AD82 -> 99 | S82: =+Y82+AE82 -> 5972404802 | T82: =+SUM(O82:S82) -> 6105633883 | Z82: =+SUM(U82:Y82) -> 0 | AA82: =+基礎数値!$D19 -> 0 | AB82: =+基礎数値!$E19 -> 131982078 | AC82: =+基礎数値!$F19 -> 1246904 | AD82: =+基礎数値!$G19 -> 99 | AE82: =+基礎数値!$H19 -> 5972404802 | AF82: =+SUM(AA82:AE82) -> 6105633883 | AG82: 「不課税収入」のうち「課税仕入に特定」
E83: 特定収入 計 | F83: N=3条特収+4条特収 | G83: =SUM(G81:G82) -> 0 | H83: =SUM(H81:H82) -> 131982078 | I83: =SUM(I81:I82) -> 1702296 | J83: =SUM(J81:J82) -> 130667 | K83: =SUM(K81:K82) -> 8284711722 | L83: =SUM(L81:L82) -> 8418526763 | N83: N=3条特収+4条特収 | O83: =+U83+AA83 -> 0 | P83: =+V83+AB83 -> 131982078 | Q83: =+W83+AC83 -> 1702296 | R83: =+X83+AD83 -> 130667 | S83: =+Y83+AE83 -> 8284711722 | T83: =SUM(T81:T82) -> 8418526763 | U83: =SUM(U81:U82) -> 0 | V83: =SUM(V81:V82) -> 0 | W83: =SUM(W81:W82) -> 455392 | X83: =SUM(X81:X82) -> 130568 | Y83: =SUM(Y81:Y82) -> 2312306920 | Z83: =SUM(Z81:Z82) -> 2312892880 | AA83: =SUM(AA81:AA82) -> 0 | ... AF83: =SUM(AF81:AF82) -> 6105633883
E84: 課税売上額（税抜） | F84: =A×1/（1+消費税及び地方消費税率） | G84: =ROUNDDOWN(G26*1/(1+G$7),0) -> 0 | H84: =ROUNDDOWN(H26*1/(1+H$7),0) -> 0 | I84: =ROUNDDOWN(I26*1/(1+I$7),0) -> 43567 | J84: =ROUNDDOWN(J26*1/(1+J$7),0) -> 0 | K84: =ROUNDDOWN(K26*1/(1+K$7),0) -> 18881545399 | L84: =+SUM(G84:K84) -> 18881588966 | N84: =A×1/（1+消費税及び地方消費税率） | O84: =+U84+AA84 -> 0 | P84: =+V84+AB84 -> 0 | Q84: =+W84+AC84 -> 43567 | R84: =+X84+AD84 -> 0 | S84: =+Y84+AE84 -> 18881545399 | T84: =+SUM(O84:S84) -> 18881588966 | U84: =ROUNDDOWN(U26*1/(1+U$7),0) -> 0 | V84: =ROUNDDOWN(V26*1/(1+V$7),0) -> 0 | W84: =ROUNDDOWN(W26*1/(1+W$7),0) -> 43567 | X84: =ROUNDDOWN(X26*1/(1+X$7),0) -> 0 | Y84: =ROUNDDOWN(Y26*1/(1+Y$7),0) -> 18845462299 | Z84: =+SUM(U84:Y84) -> 18845505866 | AA84: =ROUNDDOWN(AA26*1/(1+AA$7),0) -> 0 | AB84: =ROUNDDOWN(AB26*1/(1+AB$7),0) -> 0 | AC84: =ROUNDDOWN(AC26*1/(1+AC$7),0) -> 0 | AD84: =ROUNDDOWN(AD26*1/(1+AD$7),0) -> 0 | AE84: =ROUNDDOWN(AE26*1/(1+AE$7),0) -> 36083100 | AF84: =+SUM(AA84:AE84) -> 36083100
E85: 免税売上額 | F85: Gの再掲 | L85: =+L34 -> 86860 | N85: Gの再掲 | T85: =+T34 -> 86860
E86: 非課税売上額 | F86: Ｉの再掲 | L86: =+L38 -> 68592953 | N86: Ｉの再掲 | T86: =+T38 -> 68592953
E87: 資産の譲渡等の対価の額（課税（税抜）+免税+非課税売上の計） | L87: =SUM(L84:L86) -> 18950268779 | T87: =SUM(T84:T86) -> 18950268779
E88: 特定収入割合 | F88: N/(N+資産の譲渡等の対価の額) | L88: =+ROUNDUP(L83/SUM(L83,L87),3) -> 0.308 | N88: N/(N+資産の譲渡等の対価の額) | T88: =+ROUNDUP(T83/SUM(T83,T87),3) -> 0.308
C89: 2 | D89: 仕入税額控除の計算 | E89: 一括比例配分方式により控除する課税仕入れ等の税額 | F89: O=M×H/J | G89: =ROUNDDOWN(G67*$L$35/$L$39,0) -> 0 | H89: =ROUNDDOWN(H67*$L$35/$L$39,0) -> 0 | I89: =ROUNDDOWN(I67*$L$35/$L$39,0) -> 76866 | J89: =ROUNDDOWN(J67*$L$35/$L$39,0) -> 30955 | K89: =ROUNDDOWN(K67*$L$35/$L$39,0) -> 1792796242 | L89: =+SUM(G89:K89) -> 1792904063 | N89: O=M×H/J | O89: =+U89+AA89 -> 0 | P89: =+V89+AB89 -> 0 | Q89: =+W89+AC89 -> 97608 | R89: =+X89+AD89 -> 39685 | S89: =+Y89+AE89 -> 2298456719 | T89: =+SUM(O89:S89) -> 2298594012 | U89: =ROUNDDOWN(U67*$L$35/$L$39,0)+U145 -> 0 | V89: =ROUNDDOWN(V67*$L$35/$L$39,0)+V145 -> 0 | W89: =ROUNDDOWN(W67*$L$35/$L$39,0)+W145 -> 88330 | X89: =ROUNDDOWN(X67*$L$35/$L$39,0)+X145 -> 36967 | Y89: =ROUNDDOWN(Y67*$L$35/$L$39,0)+Y145 -> 823930954 | Z89: =+SUM(U89:Y89) -> 824056251 | AA89: =ROUNDDOWN(AA67*$L$35/$L$39,0)+AA145 -> 0 | AB89: =ROUNDDOWN(AB67*$L$35/$L$39,0)+AB145 -> 0 | AC89: =ROUNDDOWN(AC67*$L$35/$L$39,0)+AC145 -> 9278 | AD89: =ROUNDDOWN(AD67*$L$35/$L$39,0)+AD145 -> 2718 | AE89: =ROUNDDOWN(AE67*$L$35/$L$39,0)+AE145 -> 1474525765 | AF89: =+SUM(AA89:AE89) -> 1474537761
E90: 課税仕入れ等に係る特定収入 | F90: Ｎの再掲 | G90: =+G83 -> 0 | H90: =+H83 -> 131982078 | I90: =+I83 -> 1702296 | J90: =+J83 -> 130667 | K90: =+K83 -> 8284711722 | L90: =+SUM(G90:K90) -> 8418526763 | N90: Ｎの再掲 | O90: =+U90+AA90 -> 0 | P90: =+V90+AB90 -> 131982078 | Q90: =+W90+AC90 -> 1702296 | R90: =+X90+AD90 -> 130667 | S90: =+Y90+AE90 -> 8284711722 | T90: =+SUM(O90:S90) -> 8418526763 | U90: =+U83 -> 0 | V90: =+V83 -> 0 | W90: =+W83 -> 455392 | X90: =+X83 -> 130568 | Y90: =+Y83 -> 2312306920 | Z90: =+SUM(U90:Y90) -> 2312892880 | AA90: =+AA83 -> 0 | AB90: =+AB83 -> 131982078 | AC90: =+AC83 -> 1246904 | AD90: =+AD83 -> 99 | AE90: =+AE83 -> 5972404802 | AF90: =+SUM(AA90:AE90) -> 6105633883
E91: 課税仕入れ等に係る特定収入に係る消費税相当額 | F91: Ｐ=N×(消費税率） /（1+消費税及び地方消費税率） | G91: =ROUNDDOWN(G90*G$1/(1+G$7),0) -> 0 | H91: =ROUNDDOWN(H90*H$1/(1+H$7),0) -> 5027888 | I91: =ROUNDDOWN(I90*I$1/(1+I$7),0) -> 99300 | J91: =ROUNDDOWN(J90*J$1/(1+J$7),0) -> 7549 | K91: =ROUNDDOWN(K90*K$1/(1+K$7),0) -> 587461376 | L91: =+SUM(G91:K91) -> 592596113 | N91: Ｐ=N×（消費税及び地方消費税率） /（1+消費税及び地方消費税率） | O91: =+U91+AA91 -> 0 | P91: =+V91+AB91 -> 6284860 | Q91: =+W91+AC91 -> 126095 | R91: =+X91+AD91 -> 9678 | S91: =+Y91+AE91 -> 753155611 | T91: =+SUM(O91:S91) -> 759576244 | U91: =ROUNDDOWN(U90*U$7/(1+U$7),0)+U140 -> 0 | V91: =ROUNDDOWN(V90*V$7/(1+V$7),0)+V140 -> 0 | W91: =ROUNDDOWN(W90*W$7/(1+W$7),0)+W140 -> 33732 | X91: =ROUNDDOWN(X90*X$7/(1+X$7),0)+X140 -> 9671 | Y91: =ROUNDDOWN(Y90*Y$7/(1+Y$7),0)+Y140 -> 210209720 | Z91: =+SUM(U91:Y91) -> 210253123 | AA91: =ROUNDDOWN(AA90*AA$7/(1+AA$7),0)+AA140 -> 0 | AB91: =ROUNDDOWN(AB90*AB$7/(1+AB$7),0)+AB140 -> 6284860 | AC91: =ROUNDDOWN(AC90*AC$7/(1+AC$7),0)+AC140 -> 92363 | AD91: =ROUNDDOWN(AD90*AD$7/(1+AD$7),0)+AD140 -> 7 | AE91: =ROUNDDOWN(AE90*AE$7/(1+AE$7),0)+AE140 -> 542945891 | AF91: =+SUM(AA91:AE91) -> 549323121
E92: 課税売上割合 | F92: Ｑ=H/J | L92: =+L35 -> 18871966907 | M92: 計算表５⑥ | N92: Ｑ=H/J | O92: =+U92+AA92 -> 0 | P92: =+V92+AB92 -> 0 | Q92: =+W92+AC92 -> 0 | R92: =+X92+AD92 -> 0 | S92: =+Y92+AE92 -> 0 | T92: =+T35 -> 18871966907 | Z92: =+Z35 -> 0 | AF92: =+AF35 -> 0
L93: =+L39 -> 18940559860 | O93: =+U93+AA93 -> 0 | P93: =+V93+AB93 -> 0 | Q93: =+W93+AC93 -> 0 | R93: =+X93+AD93 -> 0 | S93: =+Y93+AE93 -> 0 | T93: =+T39 -> 18940559860 | Z93: =+Z39 -> 0 | AF93: =+AF39 -> 0
E94: 特定収入に係る課税仕入れ等の税額 | F94: R=P×H/J | G94: =ROUNDDOWN(G91*$L$92/$L$93,0) -> 0 | H94: =ROUNDDOWN(H91*$L$92/$L$93,0) -> 5009679 | I94: =ROUNDDOWN(I91*$L$92/$L$93,0) -> 98940 | J94: =ROUNDDOWN(J91*$L$92/$L$93,0) -> 7521 | K94: =ROUNDDOWN(K91*$L$92/$L$93,0) -> 585333893 | L94: =+SUM(G94:K94) -> 590450033 | N94: R=P×H/J | O94: =+U94+AA94 -> 0 | P94: =+V94+AB94 -> 6262099 | Q94: =+W94+AC94 -> 125637 | R94: =+X94+AD94 -> 9641 | S94: =+Y94+AE94 -> 750428068 | T94: =+SUM(O94:S94) -> 756825445 | U94: =ROUNDDOWN(U91*$L$92/$L$93,0) -> 0 | V94: =ROUNDDOWN(V91*$L$92/$L$93,0) -> 0 | W94: =ROUNDDOWN(W91*$L$92/$L$93,0) -> 33609 | X94: =ROUNDDOWN(X91*$L$92/$L$93,0) -> 9635 | Y94: =ROUNDDOWN(Y91*$L$92/$L$93,0) -> 209448448 | Z94: =+SUM(U94:Y94) -> 209491692 | AA94: =ROUNDDOWN(AA91*$L$92/$L$93,0)+AA150 -> 0 | AB94: =ROUNDDOWN(AB91*$L$92/$L$93,0)+AB150 -> 6262099 | AC94: =ROUNDDOWN(AC91*$L$92/$L$93,0)+AC150 -> 92028 | AD94: =ROUNDDOWN(AD91*$L$92/$L$93,0)+AD150 -> 6 | AE94: =ROUNDDOWN(AE91*$L$92/$L$93,0)+AE150 -> 540979620 | AF94: =+SUM(AA94:AE94) -> 547333753
E95: 使途不特定の特定収入の計算 | O95: =+U95+AA95 -> 0 | P95: =+V95+AB95 -> 0 | Q95: =+W95+AC95 -> 0 | R95: =+X95+AD95 -> 0 | S95: =+Y95+AE95 -> 0
E96: 課税仕入れ等の税額－特定収入に係る課税仕入れ等の税額 | F96: S=O-R | G96: =G89-G94 -> 0 | H96: =H89-H94 -> -5009679 | I96: =I89-I94 -> -22074 | J96: =J89-J94 -> 23434 | K96: =K89-K94 -> 1207462349 | L96: =+SUM(G96:K96) -> 1202454030 | N96: S=O-R | O96: =+U96+AA96 -> 0 | P96: =+V96+AB96 -> -6262099 | Q96: =+W96+AC96 -> -28029 | R96: =+X96+AD96 -> 30044 | S96: =+Y96+AE96 -> 1548028651 | T96: =+SUM(O96:S96) -> 1541768567 | U96: =U89-U94 -> 0 | V96: =V89-V94 -> 0 | W96: =W89-W94 -> 54721 | X96: =X89-X94 -> 27332 | Y96: =Y89-Y94 -> 614482506 | Z96: =+SUM(U96:Y96) -> 614564559 | AA96: =AA89-AA94 -> 0 | AB96: =AB89-AB94 -> -6262099 | AC96: =AC89-AC94 -> -82750 | AD96: =AD89-AD94 -> 2712 | AE96: =AE89-AE94 -> 933546145 | AF96: =+SUM(AA96:AE96) -> 927204008
E97: 調整割合 (使途不特定の特定収入/ | F97: T | L97: =+基礎数値!$I20 -> 0 | M97: 計算表５⑨ | N97: T | T97: =+基礎数値!$I20 -> 0 | Z97: =+基礎数値!$I20 -> 0 | AF97: =+基礎数値!$I20 -> 0 | AG97: 使途不特定はないので、ゼロ
E98: 資産の譲渡等の対価の額） | L98: =+L87 -> 18950268779 | T98: =+T87 -> 18950268779 | Z98: =+T87 -> 18950268779 | AF98: =+T87 -> 18950268779 | AG98: 資産の譲渡等の対価の額
E99: 使途不特定の特定収入の税額 | F99: U=S×T | G99: =ROUNDDOWN(G96*$L$97/$L$98,0) -> 0 | H99: =ROUNDDOWN(H96*$L$97/$L$98,0) -> 0 | I99: =ROUNDDOWN(I96*$L$97/$L$98,0) -> 0 | J99: =ROUNDDOWN(J96*$L$97/$L$98,0) -> 0 | K99: =ROUNDDOWN(K96*$L$97/$L$98,0) -> 0 | L99: =+SUM(G99:K99) -> 0 | N99: U=S×T | O99: =+U99+AA99 -> 0 | P99: =+V99+AB99 -> 0 | Q99: =+W99+AC99 -> 0 | R99: =+X99+AD99 -> 0 | S99: =+Y99+AE99 -> 0 | T99: =+SUM(O99:S99) -> 0 | U99: =ROUNDDOWN(U96*$Z$97/$Z$98,0) -> 0 | V99: =ROUNDDOWN(V96*$Z$97/$Z$98,0) -> 0 | W99: =ROUNDDOWN(W96*$Z$97/$Z$98,0) -> 0 | X99: =ROUNDDOWN(X96*$Z$97/$Z$98,0) -> 0 | Y99: =ROUNDDOWN(Y96*$Z$97/$Z$98,0) -> 0 | Z99: =+SUM(U99:Y99) -> 0 | AA99: =ROUNDDOWN(AA96*$AF$97/$AF$98,0) -> 0 | AB99: =ROUNDDOWN(AB96*$AF$97/$AF$98,0) -> 0 | AC99: =ROUNDDOWN(AC96*$AF$97/$AF$98,0) -> 0 | AD99: =ROUNDDOWN(AD96*$AF$97/$AF$98,0) -> 0 | AE99: =ROUNDDOWN(AE96*$AF$97/$AF$98,0) -> 0 | AF99: =+SUM(AA99:AE99) -> 0
E100: 特定収入に係る課税仕入れ等の税額 | F100: V=R+U | G100: =G94+G99 -> 0 | H100: =H94+H99 -> 5009679 | I100: =I94+I99 -> 98940 | J100: =J94+J99 -> 7521 | K100: =K94+K99 -> 585333893 | L100: =+SUM(G100:K100) -> 590450033 | N100: V=R+U | O100: =+U100+AA100 -> 0 | P100: =+V100+AB100 -> 6262099 | Q100: =+W100+AC100 -> 125637 | R100: =+X100+AD100 -> 9641 | S100: =+Y100+AE100 -> 750428068 | T100: =+SUM(O100:S100) -> 756825445 | U100: =U94+U99 -> 0 | V100: =V94+V99 -> 0 | W100: =W94+W99 -> 33609 | X100: =X94+X99 -> 9635 | Y100: =Y94+Y99 -> 209448448 | Z100: =+SUM(U100:Y100) -> 209491692 | AA100: =AA94+AA99 -> 0 | AB100: =AB94+AB99 -> 6262099 | AC100: =AC94+AC99 -> 92028 | AD100: =AD94+AD99 -> 6 | AE100: =AE94+AE99 -> 540979620 | AF100: =+SUM(AA100:AE100) -> 547333753
E101: 控除対象仕入税額 | F101: W=O-V | G101: =G89-G100 -> 0 | H101: =H89-H100 -> -5009679 | I101: =I89-I100 -> -22074 | J101: =J89-J100 -> 23434 | K101: =K89-K100 -> 1207462349 | L101: =+SUM(G101:K101) -> 1202454030 | N101: W=O-V | O101: =+U101+AA101 -> 0 | P101: =+V101+AB101 -> -6262099 | Q101: =+W101+AC101 -> -28029 | R101: =+X101+AD101 -> 30044 | S101: =+Y101+AE101 -> 1548028651 | T101: =+SUM(O101:S101) -> 1541768567 | U101: =U89-U100 -> 0 | V101: =V89-V100 -> 0 | W101: =W89-W100 -> 54721 | X101: =X89-X100 -> 27332 | Y101: =Y89-Y100 -> 614482506 | Z101: =+SUM(U101:Y101) -> 614564559 | AA101: =AA89-AA100 -> 0 | AB101: =AB89-AB100 -> -6262099 | AC101: =AC89-AC100 -> -82750 | AD101: =AD89-AD100 -> 2712 | AE101: =AE89-AE100 -> 933546145 | AF101: =+SUM(AA101:AE101) -> 927204008
B102: 納税額等の計算 | C102: 1 | D102: 控除税額の計算 | E102: 控除税額
E103: 控除対象仕入税額 | F103: Wの再掲 | G103: =+G101 -> 0 | H103: =+H101 -> -5009679 | I103: =+I101 -> -22074 | J103: =+J101 -> 23434 | K103: =+K101 -> 1207462349 | L103: =+SUM(G103:K103) -> 1202454030 | N103: Wの再掲 | O103: =+U103+AA103 -> 0 | P103: =+V103+AB103 -> -6262099 | Q103: =+W103+AC103 -> -28029 | R103: =+X103+AD103 -> 30044 | S103: =+Y103+AE103 -> 1548028651 | T103: =+Z103+AF103 -> 1541768567 | U103: =+U101 -> 0 | V103: =+V101 -> 0 | W103: =+W101 -> 54721 | X103: =+X101 -> 27332 | Y103: =+Y101 -> 614482506 | Z103: =+SUM(U103:Y103) -> 614564559 | AA103: =+AA101 -> 0 | AB103: =+AB101 -> -6262099 | AC103: =+AC101 -> -82750 | AD103: =+AD101 -> 2712 | AE103: =+AE101 -> 933546145 | AF103: =+SUM(AA103:AE103) -> 927204008
E104: 売上対価の返還等に係る税額 | F104: X=C×(消費税率） /（1+消費税及び地方消費税率） | G104: =ROUNDDOWN(G29*G$1/(1+G$7),0) -> 0 | H104: =ROUNDDOWN(H29*H$1/(1+H$7),0) -> 0 | I104: =ROUNDDOWN(I29*I$1/(1+I$7),0) -> 2294 | J104: =ROUNDDOWN(J29*J$1/(1+J$7),0) -> 0 | K104: =ROUNDDOWN(K29*K$1/(1+K$7),0) -> 754454 | L104: =+SUM(G104:K104) -> 756748 | M104: 申告書⑤ | N104: X=C×（消費税及び地方消費税率） /（1+消費税及び地方消費税率） | O104: =+U104+AA104 -> 0 | P104: =+V104+AB104 -> 0 | Q104: =+W104+AC104 -> 2914 | R104: =+X104+AD104 -> 0 | S104: =+Y104+AE104 -> 967249 | T104: =+Z104+AF104 -> 970163 | U104: =ROUNDDOWN(U29*U$7/(1+U$7),0) -> 0 | V104: =ROUNDDOWN(V29*V$7/(1+V$7),0) -> 0 | W104: =ROUNDDOWN(W29*W$7/(1+W$7),0) -> 2914 | X104: =ROUNDDOWN(X29*X$7/(1+X$7),0) -> 0 | Y104: =ROUNDDOWN(Y29*Y$7/(1+Y$7),0) -> 967249 | Z104: =+SUM(U104:Y104) -> 970163 | AA104: =ROUNDDOWN(AA29*AA$7/(1+AA$7),0) -> 0 | AB104: =ROUNDDOWN(AB29*AB$7/(1+AB$7),0) -> 0 | AC104: =ROUNDDOWN(AC29*AC$7/(1+AC$7),0) -> 0 | AD104: =ROUNDDOWN(AD29*AD$7/(1+AD$7),0) -> 0 | AE104: =ROUNDDOWN(AE29*AE$7/(1+AE$7),0) -> 0 | AF104: =+SUM(AA104:AE104) -> 0
E105: 貸倒れに係る金額（税込） | F105: Y | G105: =+基礎数値!$D17 -> 0 | H105: =+基礎数値!$E17 -> 1120996 | I105: =+基礎数値!$F17 -> 24667001 | J105: =+基礎数値!$G17 -> 0 | K105: =+基礎数値!$H17 -> 0 | L105: =+SUM(G105:K105) -> 25787997 | N105: Y | O105: =+U105+AA105 -> 0 | P105: =+V105+AB105 -> 1120996 | Q105: =+W105+AC105 -> 24667001 | R105: =+X105+AD105 -> 0 | S105: =+Y105+AE105 -> 0 | T105: =+Z105+AF105 -> 25787997 | U105: =+基礎数値!$D17 -> 0 | V105: =+基礎数値!$E17 -> 1120996 | W105: =+基礎数値!$F17 -> 24667001 | X105: =+基礎数値!$G17 -> 0 | Y105: =+基礎数値!$H17 -> 0 | Z105: =+SUM(U105:Y105) -> 25787997 | AF105: =+SUM(AA105:AE105) -> 0
E106: 貸倒れ（引当金取崩分）に係る税額 | F106: Z=Y×(消費税率） /（1+消費税及び地方消費税率） | G106: =ROUNDDOWN(G105*G$1/(1+G$7),0) -> 0 | H106: =ROUNDDOWN(H105*H$1/(1+H$7),0) -> 42704 | I106: =ROUNDDOWN(I105*I$1/(1+I$7),0) -> 1438908 | J106: =ROUNDDOWN(J105*J$1/(1+J$7),0) -> 0 | K106: =ROUNDDOWN(K105*K$1/(1+K$7),0) -> 0 | L106: =+SUM(G106:K106) -> 1481612 | M106: 申告書⑥ | N106: Z=Y×（消費税及び地方消費税率） /（1+消費税及び地方消費税率） | O106: =+U106+AA106 -> 0 | P106: =+V106+AB106 -> 53380 | Q106: =+W106+AC106 -> 1827185 | R106: =+X106+AD106 -> 0 | S106: =+Y106+AE106 -> 0 | T106: =+Z106+AF106 -> 1880565 | U106: =ROUNDDOWN(U105*U$7/(1+U$7),0) -> 0 | V106: =ROUNDDOWN(V105*V$7/(1+V$7),0) -> 53380 | W106: =ROUNDDOWN(W105*W$7/(1+W$7),0) -> 1827185 | X106: =ROUNDDOWN(X105*X$7/(1+X$7),0) -> 0 | Y106: =ROUNDDOWN(Y105*Y$7/(1+Y$7),0) -> 0 | Z106: =+SUM(U106:Y106) -> 1880565 | AA106: =ROUNDDOWN(AA105*AA$7/(1+AA$7),0) -> 0 | AB106: =ROUNDDOWN(AB105*AB$7/(1+AB$7),0) -> 0 | AC106: =ROUNDDOWN(AC105*AC$7/(1+AC$7),0) -> 0 | AD106: =ROUNDDOWN(AD105*AD$7/(1+AD$7),0) -> 0 | AE106: =ROUNDDOWN(AE105*AE$7/(1+AE$7),0) -> 0 | AF106: =+SUM(AA106:AE106) -> 0
E107: 控除税額 計 | F107: AA=W+X+Z | G107: =G103+G104+G106 -> 0 | H107: =H103+H104+H106 -> -4966975 | I107: =I103+I104+I106 -> 1419128 | J107: =J103+J104+J106 -> 23434 | K107: =K103+K104+K106 -> 1208216803 | L107: =+SUM(G107:K107) -> 1204692390 | M107: 申告書⑦ | N107: AA=W+X+Z | O107: =+U107+AA107 -> 0 | P107: =+V107+AB107 -> -6208719 | Q107: =+W107+AC107 -> 1802070 | R107: =+X107+AD107 -> 30044 | S107: =+Y107+AE107 -> 1548995900 | T107: =+Z107+AF107 -> 1544619295 | U107: =U103+U104+U106 -> 0 | V107: =V103+V104+V106 -> 53380 | W107: =W103+W104+W106 -> 1884820 | X107: =X103+X104+X106 -> 27332 | Y107: =Y103+Y104+Y106 -> 615449755 | Z107: =+SUM(U107:Y107) -> 617415287 | AA107: =AA103+AA104+AA106 -> 0 | AB107: =AB103+AB104+AB106 -> -6262099 | AC107: =AC103+AC104+AC106 -> -82750 | AD107: =AD103+AD104+AD106 -> 2712 | AE107: =AE103+AE104+AE106 -> 933546145 | AF107: =+SUM(AA107:AE107) -> 927204008
C108: 2 | D108: 消費税の納付税額の計算 | E108: 消費税額 | F108: Fの再掲 | G108: =G32 -> 0 | H108: =H32 -> 0 | I108: =I32 -> 2709 | J108: =J32 -> 0 | K108: =K32 -> 1472760510 | L108: =+SUM(G108:K108) -> 1472763219 | N108: Fの再掲 | O108: =+U108+AA108 -> 0 | P108: =+V108+AB108 -> 0 | Q108: =+W108+AC108 -> 3485 | R108: =+X108+AD108 -> 0 | S108: =+Y108+AE108 -> 1888154539 | T108: =+Z108+AF108 -> 1888158024 | U108: =U32 -> 0 | V108: =V32 -> 0 | W108: =W32 -> 3485 | X108: =X32 -> 0 | Y108: =Y32 -> 1884546229 | Z108: =+SUM(U108:Y108) -> 1884549714 | AA108: =AA32 -> 0 | AB108: =AB32 -> 0 | AC108: =AC32 -> 0 | AD108: =AD32 -> 0 | AE108: =AE32 -> 3608310 | AF108: =+SUM(AA108:AE108) -> 3608310
E109: 控除税額 | F109: AAの再掲 | G109: =G107 -> 0 | H109: =H107 -> -4966975 | I109: =I107 -> 1419128 | J109: =J107 -> 23434 | K109: =K107 -> 1208216803 | L109: =+SUM(G109:K109) -> 1204692390 | N109: AAの再掲 | O109: =+U109+AA109 -> 0 | P109: =+V109+AB109 -> -6208719 | Q109: =+W109+AC109 -> 1802070 | R109: =+X109+AD109 -> 30044 | S109: =+Y109+AE109 -> 1548995900 | T109: =+Z109+AF109 -> 1544619295 | U109: =U107 -> 0 | V109: =V107 -> 53380 | W109: =W107 -> 1884820 | X109: =X107 -> 27332 | Y109: =Y107 -> 615449755 | Z109: =+SUM(U109:Y109) -> 617415287 | AA109: =AA107 -> 0 | AB109: =AB107 -> -6262099 | AC109: =AC107 -> -82750 | AD109: =AD107 -> 2712 | AE109: =AE107 -> 933546145 | AF109: =+SUM(AA109:AE109) -> 927204008
...

Sheet 4条圧縮
A1: =+CONCATENATE(LEFT('[3]3条支出'!$D$1,8)," 資本的収支に関する特定収入に係る仕入控除できない消費税額の事業・収入科目別按分表") -> 令和５年度決算 資本的収支に関する特定収入に係る仕入控除できない消費税額の事業・収入科目別按分表
B2: 仮払消費税 ① | C2: 課税仕入等 に係る税額 ②=①×課税売上割合 | D2: 課税仕入れ等に係る特定収入に係る消費税額 不可消費税 ③ | E2: 特定収入に係る課税仕入れ等の税額 ④=③×課税売上割合 | F2: 仕入控除税額 ⑤=②-④ | G2: 課税売上割合を乗じることにより控除できなくなった額 ⑥=（①-②）-（③-④） | H2: 圧縮記帳額 ⑦=③+⑥=①-⑤
A3: 公共 国庫補助金 | D3: =+'[4]4条収入'!$AH25+'[4]4条収入'!$AH27 -> 516208819 | E3: =+E6-E4-E5 -> 514339374 | G3: =+G6-G4-G5 -> 3018302 | H3: =+D3+G3 -> 519227121
A4: 公共 受益負担金 | D4: =+'[4]4条収入'!AH43 -> 775000 | E4: =+IFERROR(ROUND(D4/$D$24*$E$24,0),0) -> 772193 | G4: =+IFERROR(ROUND($G$6*D4/$D$6,0),0) -> 4531 | H4: =+D4+G4 -> 779531
A5: 公共 工事負担金 | D5: =+'[4]4条収入'!AH51 -> 26207717 | E5: =+IFERROR(ROUND(D5/$D$24*$E$24,0),0) -> 26112806 | G5: =+IFERROR(ROUND($G$6*D5/$D$6,0),0) -> 153238 | H5: =+D5+G5 -> 26360955
A6: 公共 計 | B6: =+'[5]4条支出'!S6+'[5]4条支出'!S7+'[5]4条支出'!S8+'[5]4条支出'!S10+[5]諸公!S41 -> 1420200328 | C6: =+C24-C10-C14-C18 -> 1415057094 | D6: =+SUM(D3:D5) -> 543191536 | E6: =+E24-E10-E14-E18 -> 541224373 | F6: =+C6-E6 -> 873832721 | G6: =+B6-C6-(D6-E6) -> 3176071 | H6: =+SUM(H3:H5) -> 546367607
A7: 特環 国庫補助金 | D7: =+'[4]4条収入'!AH32+'[4]4条収入'!AH28 -> 2772727 | E7: =+E10-E8-E9 -> 2762685 | G7: =+G10-G8-G9 -> 85655 | H7: =+D7+G7 -> 2858382
A8: 特環 受益分担金 | D8: =+'[4]4条収入'!AH47 -> 1431014 | E8: =+IFERROR(ROUND(D8/$D$24*$E$24,0),0) -> 1425832 | G8: =IFERROR(ROUND(G10*D8/D10,0),0) -> 44207 | H8: =+D8+G8 -> 1475221
A9: 特環 工事負担金 | D9: =+'[4]4条収入'!AH52 -> 0 | E9: =+IFERROR(ROUND(D9/$D$24*$E$24,0),0) -> 0 | G9: =+IFERROR(ROUND($G$10*D9/$D$10,0),0) -> 0 | H9: =+D9+G9 -> 0
A10: 特環 計 | B10: =+[5]諸特!S41+[5]特整!S41 -> 40062545 | C10: =+IFERROR(ROUND(B10/$B$24*$C$24,0),0) -> 39917459 | D10: =+SUM(D7:D9) -> 4203741 | E10: =+IFERROR(ROUND(D10/$D$24*$E$24,0),0) -> 4188517 | F10: =+C10-E10 -> 35728942 | G10: =+B10-C10-(D10-E10) -> 129862 | H10: =+SUM(H7:H9) -> 4333603
A11: 農集 国庫補助金 | D11: =+'[4]4条収入'!AH33+'[4]4条収入'!AH29 -> 0 | E11: =+E14-E12-E13 -> 0 | G11: =+G14-G12-G13 -> 0 | H11: =+D11+G11 -> 0
A12: 農集 受益分担金 | D12: =+'[4]4条収入'!AH48 -> 1253458 | E12: =+IFERROR(ROUND(D12/$D$24*$E$24,0),0) -> 1248919 | G12: =IFERROR(ROUND(G14*D12/D14,0),0) -> 40427 | H12: =+D12+G12 -> 1293885
A13: 農集 工事負担金 | D13: =+'[4]4条収入'!AH53 -> 0 | E13: =+IFERROR(ROUND(D13/$D$24*$E$24,0),0) -> 0 | G13: =+IFERROR(ROUND($G$14*D13/$D$14,0),0) -> 0 | H13: =+D13+G13 -> 0
A14: 農集 計 | B14: =+[5]諸農!S41+[5]農整!S41 -> 12416364 | C14: =+IFERROR(ROUND(B14/$B$24*$C$24,0),0) -> 12371398 | D14: =+SUM(D11:D13) -> 1253458 | E14: =+IFERROR(ROUND(D14/$D$24*$E$24,0),0) -> 1248919 | F14: =+C14-E14 -> 11122479 | G14: =+B14-C14-(D14-E14) -> 40427 | H14: =+SUM(H11:H13) -> 1293885
A15: 浄化槽 国庫補助金 | D15: =+'[4]4条収入'!AH34+'[4]4条収入'!AH30 -> 317091 | E15: =+E18-E16-E17 -> 315943 | G15: =+G18-G16-G17 -> 11143 | H15: =+D15+G15 -> 328234
A16: 浄化槽 受益分担金 | D16: =+'[4]4条収入'!AH49 -> 357295 | E16: =+IFERROR(ROUND(D16/$D$24*$E$24,0),0) -> 356001 | G16: =IFERROR(ROUND(G18*D16/D18,0),0) -> 12555 | H16: =+D16+G16 -> 369850
A17: 浄化槽 工事負担金 | D17: =+'[4]4条収入'!AH54 -> 0 | E17: =+IFERROR(ROUND(D17/$D$24*$E$24,0),0) -> 0 | G17: =+IFERROR(ROUND($G$18*D17/$D$18,0),0) -> 0 | H17: =+D17+G17 -> 0
A18: 浄化槽 計 | B18: =+[5]浄整!S41 -> 7217950 | C18: =+IFERROR(ROUND(B18/$B$24*$C$24,0),0) -> 7191810 | D18: =+SUM(D15:D17) -> 674386 | E18: =+IFERROR(ROUND(D18/$D$24*$E$24,0),0) -> 671944 | F18: =+C18-E18 -> 6519866 | G18: =+B18-C18-(D18-E18) -> 23698 | H18: =+SUM(H15:H17) -> 698084
A19: 全事業 国庫補助金 | B19: =+B3+B7+B11+B15 -> 0 | C19: =+C3+C7+C11+C15 -> 0 | D19: =+D3+D7+D11+D15 -> 519298637 | E19: =+E3+E7+E11+E15 -> 517418002 | F19: =+F3+F7+F11+F15 -> 0 | G19: =+G3+G7+G11+G15 -> 3115100 | H19: =+H3+H7+H11+H15 -> 522413737
A20: 全事業 受益負担金 | B20: =+B4 -> 0 | C20: =+C4 -> 0 | D20: =+D4 -> 775000 | E20: =+E4 -> 772193 | F20: =+F4 -> 0 | G20: =+G4 -> 4531 | H20: =+H4 -> 779531
A21: 全事業 受益分担金 | B21: =+B8+B12+B16 -> 0 | C21: =+C8+C12+C16 -> 0 | D21: =+D8+D12+D16 -> 3041767 | E21: =+E8+E12+E16 -> 3030752 | F21: =+F8+F12+F16 -> 0 | G21: =+G8+G12+G16 -> 97189 | H21: =+H8+H12+H16 -> 3138956
A22: 全事業 工事負担金 | B22: =+B5 -> 0 | C22: =+C5 -> 0 | D22: =+D5+D9+D13+D17 -> 26207717 | E22: =+E5+E9+E13+E17 -> 26112806 | F22: =+F5+F9+F13+F17 -> 0 | G22: =+G5+G9+G13+G17 -> 153238 | H22: =+H5+H9+H13+H17 -> 26360955
A23: 全事業 計 | B23: =+SUM(B6,B10,B14,B18) -> 1479897187 | C23: =+SUM(C6,C10,C14,C18) -> 1474537761 | D23: =+SUM(D6,D10,D14,D18) -> 549323121 | E23: =+SUM(E6,E10,E14,E18) -> 547333753 | F23: =+SUM(F6,F10,F14,F18) -> 927204008 | G23: =+SUM(G6,G10,G14,G18) -> 3370058 | H23: =+SUM(H6,H10,H14,H18) -> 552693179
A24: 消費税シートより | B24: =+消費税!AF67 -> 1479897187 | C24: =+消費税!AF89 -> 1474537761 | D24: =+消費税!AF91 -> 549323121 | E24: =+消費税!AF94 -> 547333753 | F24: =+消費税!AF101 -> 927204008 | G24: =+消費税!AF122 -> 3370058 | H24: =+消費税!AF124 -> 552693179
B25: =+B23-B24 -> 0 | C25: =+C23-C24 -> 0 | D25: =+D23-D24 -> 0 | E25: =+E23-E24 -> 0 | F25: =+F23-F24 -> 0 | G25: =+G23-G24 -> 0 | H25: =+H23-H24 -> 0

Sheet 仮受仮払
F1: (単位：円) | I1: （単位：千円）
A2: 区分 | D2: =+LEFT('[3]3条支出'!$D$1,6) -> 令和５年度決 | G2: 平成１３年度決算見込
D3: 税 込 （ａ） | E3: 税 抜 （ｂ） | F3: 消費税額（ａ－ｂ） | G3: 税 込 （ａ） | H3: 税 抜 （ｂ） | I3: 消費税額（ａ－ｂ）
A4: ３条仮受消費税 | D4: =D5+D10+D17 -> 0 | E4: =E5+E10+E17 -> 0 | F4: =F5+F10+F17 -> 1884549714 | G4: =G5+G10+G17 -> 0 | H4: =H5+H10+H17 -> 0 | I4: =I5+I10+I17 -> 0
B5: 営業収益 | D5: =SUM(D6:D9) -> 0 | E5: =SUM(E6:E9) -> 0 | F5: =SUM(F6:F9) -> 1879828324 | G5: =SUM(G6:G9) -> 0 | H5: =SUM(H6:H9) -> 0 | I5: =SUM(I6:I9) -> 0
C6: 下水道使用料 | F6: =+'[2]3条収入'!AB8 -> 1862625061 | I6: =G6-H6 -> 0
C7: 一般会計負担金 | F7: =+'[2]3条収入'!AB9 -> 0 | I7: =G7-H7 -> 0
C8: 受託工事収益 | F8: =+'[2]3条収入'!AB17 -> 0
C9: その他営業収益 | F9: =+'[2]3条収入'!AB19 -> 17203263 | I9: =G9-H9 -> 0
B10: 営業外収益 | D10: =SUM(D11:D16) -> 0 | E10: =SUM(E11:E16) -> 0 | F10: =SUM(F11:F16) -> 4575502 | G10: =SUM(G11:G16) -> 0 | H10: =SUM(H11:H16) -> 0 | I10: =SUM(I11:I16) -> 0
C11: 受取利息 | F11: =+'[2]3条収入'!AB28 -> 0 | I11: =G11-H11 -> 0
C12: 国庫補助金 | F12: =+'[2]3条収入'!AB32 -> 0 | I12: =G12-H12 -> 0
C13: 負担金 | F13: =+'[2]3条収入'!AB39 -> 3365145 | I13: =G13-H13 -> 0
C14: 一般会計補助金 | F14: =+'[2]3条収入'!AB42 -> 0 | I14: =G14-H14 -> 0
C15: 消費税還付金 | D15: 0 | E15: 0 | F15: =+'[2]3条収入'!AB49 -> 0 | I15: =G15-H15 -> 0
C16: 雑収益 | F16: =+'[2]3条収入'!AB51 -> 1210357 | I16: =G16-H16 -> 0
B17: 特別利益 | D17: =SUM(D18:D20) -> 0 | E17: =SUM(E18:E20) -> 0 | F17: =SUM(F18:F20) -> 145888 | G17: =SUM(G18:G20) -> 0 | H17: =SUM(H18:H20) -> 0 | I17: =SUM(I18:I20) -> 0
C18: 固定資産売却収益 | F18: =+'[2]3条収入'!AB58 -> 0 | I18: =G18-H18 -> 0
C19: 過年度損益修正益 | F19: =+'[2]3条収入'!AB60 -> 145888 | I19: =G19-H19 -> 0
C20: その他特別利益 | F20: =+'[2]3条収入'!AB62 -> 0 | I20: =G20-H20 -> 0
A21: ３条仮払消費税 | D21: =D22+D38+D43+D46 -> 0 | E21: =E22+E38+E43+E46 -> 0 | F21: =F22+F38+F43+F46 -> 828022199 | G21: =G22+G38+G43+G46 -> 0 | H21: =H22+H38+H43+H46 -> 0 | I21: =I22+I38+I43+I46 -> 0
B22: 営業費用 | D22: =SUM(D23:D37) -> 0 | E22: =SUM(E23:E37) -> 0 | F22: =SUM(F23:F37) -> 820944501 | G22: =SUM(G23:G37) -> 0 | H22: =SUM(H23:H37) -> 0 | I22: =SUM(I23:I37) -> 0
C23: 管きょ費 | F23: =+'[3]3条支出'!S6 -> 47155349 | I23: =G23-H23 -> 0
C24: 水質指導費 | F24: =+'[3]3条支出'!S7 -> 1130574 | I24: =G24-H24 -> 0
C25: ポンプ場費 | F25: =+'[3]3条支出'!S8 -> 104382258 | I25: =G25-H25 -> 0
C26: 処理場費 | F26: =+'[3]3条支出'!S9 -> 519893786 | I26: =G26-H26 -> 0
C27: 受託工事費 | F27: =+'[3]3条支出'!S10 -> 0 | I27: =G27-H27 -> 0
C28: 普及促進費 | F28: =+'[3]3条支出'!S11 -> 1715497
C29: 水洗化貸付事業費 | F29: =+'[3]3条支出'!S12 -> 87589 | I29: =G29-H29 -> 0
C30: 業務費 | F30: =+'[3]3条支出'!S13 -> 90253429 | I30: =G30-H30 -> 0
C31: 総係費 | F31: =+'[3]3条支出'!S14 -> 17678805 | I31: =G31-H31 -> 0
C32: 特環費 | F32: =+'[3]3条支出'!S15 -> 9713984
C33: 農集費 | F33: =+'[3]3条支出'!S16 -> 22486229
C34: 浄化槽費 | F34: =+'[3]3条支出'!S17 -> 6447001
C35: 災害復旧費 | F35: =+'[3]3条支出'!S18 -> 0
C36: 減価償却費 | F36: =+'[3]3条支出'!S19 -> 0 | I36: =G36-H36 -> 0
C37: 資産減耗費 | F37: =+'[3]3条支出'!S20 -> 0 | I37: =G37-H37 -> 0
B38: 営業外費用 | D38: =SUM(D39:D42) -> 0 | E38: =SUM(E39:E42) -> 0 | F38: =SUM(F39:F42) -> 6109254 | G38: =SUM(G39:G42) -> 0 | H38: =SUM(H39:H42) -> 0 | I38: =SUM(I39:I42) -> 0
C39: 支払利息及び諸費 | F39: =+'[3]3条支出'!S23 -> 5619432 | I39: =G39-H39 -> 0
C40: 繰延勘定償却 | I40: =G40-H40 -> 0
C41: 消費税 | F41: =+'[3]3条支出'!S25 -> 0 | I41: =G41-H41 -> 0
C42: 雑支出 | F42: =+'[3]3条支出'!S24 -> 489822 | I42: =G42-H42 -> 0
B43: 特別損失 | D43: =SUM(D44:D45) -> 0 | E43: =SUM(E44:E45) -> 0 | F43: =SUM(F44:F45) -> 968444 | G43: =SUM(G44:G45) -> 0 | H43: =SUM(H44:H45) -> 0 | I43: =SUM(I44:I45) -> 0
C44: 過年度損益修正損 | F44: =+'[3]3条支出'!S28 -> 968444 | I44: =G44-H44 -> 0
C45: その他特別損失 | F45: =+'[3]3条支出'!S29 -> 0 | I45: =G45-H45 -> 0
B46: 予備費 | I46: =G46-H46 -> 0
A47: ４条仮受消費税 | D47: =D48+D51+D52+D53+D54+D59+D63+D65 -> 0 | E47: =E48+E51+E52+E53+E54+E59+E63+E65 -> 0 | F47: =F48+F51+F52+F53+F54+F59+F63+F65 -> 3608310 | G47: =G48+G51+G52+G53+G54+G59+G63+G65 -> 0 | H47: =H48+H51+H52+H53+H54+H59+H63+H65 -> 0 | I47: =I48+I51+I52+I53+I54+I59+I63+I65 -> 0
B48: 企業債 | D48: =SUM(D49:D50) -> 0 | E48: =SUM(E49:E50) -> 0 | F48: =SUM(F49:F50) -> 0 | G48: =SUM(G49:G50) -> 0 | H48: =SUM(H49:H50) -> 0 | I48: =SUM(I49:I50) -> 0
C49: 建設企業債 | F49: =+'[4]4条収入'!AB8 -> 0 | I49: =G49-H49 -> 0
C50: 借換債 | F50: =+'[4]4条収入'!AB16 -> 0 | I50: =G50-H50 -> 0
B51: 一般会計出資金 | F51: =+'[4]4条収入'!AB22 -> 0 | I51: =G51-H51 -> 0
B52: 国庫補助金 | F52: =+'[4]4条収入'!AB23 -> 0 | I52: =G52-H52 -> 0
B53: 工事受託金 | F53: =+'[4]4条収入'!AB37 -> 2215735 | I53: =G53-H53 -> 0
B54: 負担金 | D54: =SUM(D55:D58) -> 0 | E54: =SUM(E55:E58) -> 0 | F54: =SUM(F55:F58) -> 1392575 | G54: =SUM(G55:G58) -> 0 | H54: =SUM(H55:H58) -> 0 | I54: =SUM(I55:I58) -> 0
C55: 受益者負担金 | F55: =+'[4]4条収入'!AB43 -> 0 | I55: =G55-H55 -> 0
C56: 受益者分担金 | F56: =+'[4]4条収入'!AB45 -> 0
C57: 工事負担金 | F57: =+'[4]4条収入'!AB50 -> 1392575 | I57: =G57-H57 -> 0
C58: 他会計負担金 | I58: =G58-H58 -> 0
B59: 水洗化貸付事業収入 | D59: =SUM(D60:D62) -> 0 | E59: =SUM(E60:E62) -> 0 | F59: =SUM(F60:F62) -> 0 | G59: =SUM(G60:G62) -> 0 | H59: =SUM(H60:H62) -> 0 | I59: =SUM(I60:I62) -> 0
C60: 貸付企業債 | F60: =+'[4]4条収入'!AB56 -> 0 | I60: =G60-H60 -> 0
C61: 一般会計借入金 | F61: =+'[4]4条収入'!AB58 -> 0 | I61: =G61-H61 -> 0
C62: 貸付金回収金 | F62: =+'[4]4条収入'!AB71 -> 0 | I62: =G62-H62 -> 0
B63: 固定資産売却代金 | D63: =D64 -> 0 | E63: =E64 -> 0 | F63: =F64 -> 0 | G63: =G64 -> 0 | H63: =H64 -> 0 | I63: =I64 -> 0
C64: 土地売却代金 | F64: =+'[4]4条収入'!AB87 -> 0 | G64: 0 | H64: 0 | I64: =G64-H64 -> 0
B65: その他資本的収入 | D65: =D66 -> 0 | E65: =E66 -> 0 | F65: =F66 -> 0 | G65: =G66 -> 0 | H65: =H66 -> 0 | I65: =I66 -> 0
C66: 債券償還収入 | F66: =+'[4]4条収入'!AB89 -> 0 | G66: 0 | H66: 0 | I66: =G66-H66 -> 0
A67: ４条仮払消費税 | D67: =D68+D77+D79+D82 -> 0 | E67: =E68+E77+E79+E82 -> 0 | F67: =F68+F77+F79+F82 -> 1479897187 | G67: =G68+G77+G79+G82 -> 0 | H67: =H68+H77+H79+H82 -> 0 | I67: =I68+I77+I79+I82 -> 0
B68: 建設改良費 | D68: =SUM(D69:D75) -> 0 | E68: =SUM(E69:E75) -> 0 | F68: =SUM(F69:F76) -> 1479897187 | G68: =SUM(G69:G75) -> 0 | H68: =SUM(H69:H75) -> 0 | I68: =SUM(I69:I75) -> 0
C69: 公共下水道整備費 | F69: =+'[5]4条支出'!S6 -> 1356109400 | I69: =G69-H69 -> 0
C70: 受益者負担金業務費 | F70: =+'[5]4条支出'!S7 -> 543071 | I70: =G70-H70 -> 0
C71: 排水設備整備費 | F71: =+'[5]4条支出'!S8 -> 47147259 | I71: =G71-H71 -> 0
C72: 都市下水路整備費 | F72: =+'[5]4条支出'!S9 -> 0 | I72: =G72-H72 -> 0
C73: 流域下水道整備費 | F73: =+'[5]4条支出'!S10 -> 11020779 | I73: =G73-H73 -> 0
C74: 諸設備新設改良費 | F74: =+'[5]4条支出'!S11 -> 5379819 | I74: =G74-H74 -> 0
C75: 建設利息 | F75: =+'[5]4条支出'!S15 -> 0 | I75: =G75-H75 -> 0
C76: 市街化区域外整備費 | F76: =+'[5]4条支出'!S16 -> 59696859
B77: 償還金 | D77: =D78 -> 0 | E77: =E78 -> 0 | F77: =F78 -> 0 | G77: =G78 -> 0 | H77: =H78 -> 0 | I77: =I78 -> 0
C78: 企業債償還金 | F78: 0 | I78: =G78-H78 -> 0
B79: 水洗化貸付事業費 | D79: =SUM(D80:D81) -> 0 | E79: =SUM(E80:E81) -> 0 | F79: =SUM(F80:F81) -> 0 | G79: =SUM(G80:G81) -> 0 | H79: =SUM(H80:H81) -> 0 | I79: =SUM(I80:I81) -> 0
C80: 貸付金 | F80: 0 | I80: =G80-H80 -> 0
C81: 貸付資金企業債償還金 | F81: 0 | I81: =G81-H81 -> 0
B82: 補助金・借入金返還金 | F82: 0 | I82: =G82-H82 -> 0
A83: 仮受消費税合計 | F83: =F4+F47 -> 1888158024 | I83: =I4+I47 -> 0
A84: 仮払消費税合計 | F84: =F21+F67 -> 2307919386 | I84: =I21+I67 -> 0
A85: 仕入控除できない消費税額 | F85: =F86+F92 -> 763300091 | I85: =I86+I92 -> 0 | J85: =F85-F86-F92 -> 0
B86: ３条分 | F86: =SUM(F87:F91) -> 210606912
C87: 特定収入に係る課税仕入れ分 | F87: =+消費税!Z119 -> 210253123
C88: 仮払消費税×（１－課税売上割合）分 | F88: =+消費税!Z122 -> 2233725
C89: 仕入・売上対価返還等に係る消費税額
C90: 免税事業者に係る控除不能額 | F90: =消費税!Z123 -> 629
C91: 返還等対価、貸倒れに係る消費税額 | F91: =-消費税!Z125 -> -1880565
B92: ４条分 | F92: =SUM(F93:F97) -> 552693179 | I92: =SUM(I93:I97) -> 0
C93: 国庫補助金 | F93: =+'4条圧縮'!H19 -> 522413737
C94: 県補助金 | F94: 0
C95: 受益者負担金 | F95: =+'4条圧縮'!H20 -> 779531
C96: 受益者分担金 | F96: =+'4条圧縮'!H21 -> 3138956
C97: 工事負担金 | F97: =+'4条圧縮'!H22 -> 26360955
A98: （注） 税込は、消費税還付金を除く。

Sheet 精算表
D1: (単位：円)
A2: 区 分 | C2: =(LEFT('[3]3条支出'!$D$1,7)) -> 令和５年度決算
C3: 借 方 | D3: 貸 方
A4: 仮受消費税 | C4: =仮受仮払!F83 -> 1888158024
A5: 仮払消費税 | D5: =仮受仮払!F84 -> 2307919386
A6: 雑収益 | D6: =+-仮受仮払!F91 -> 1880565
A7: 雑支出 | C7: =+SUM(仮受仮払!F87:F90) -> 212487477
A8: 資本剰余金 | C8: =SUM(C9:C13) -> 552693179 | D8: =SUM(D9:D13) -> 0 | E8: =C8-仮受仮払!F92 -> 0
B9: 国庫補助金 | C9: =仮受仮払!F93 -> 522413737
B10: 県補助金 | C10: =仮受仮払!F94 -> 0
B11: 受益者負担金 | C11: =仮受仮払!F95 -> 779531
B12: 受益者分担金 | C12: =仮受仮払!F96 -> 3138956
B13: 工事負担金 | C13: =仮受仮払!F97 -> 26360955
A14: 未払消費税納付金 | C14: =-(消費税!Z118+消費税!AF118) -> -343538729
A15: 計 | C15: =C4+C5+C6+C7+C8+C14 -> 2309799951 | D15: =D4+D5+D6+D7+D8+D14 -> 2309799951
C16: =D15-C15 -> 0

Sheet 振替表
A1: 区分 | E1: 借方 | H1: 貸方
E2: 残高 | F2: 金額 | G2: 科目 | H2: 科目 | I2: 金額 | J2: 残高
A3: 収益的収入仮受消費税の振替 | E3: =F3-I3 -> 0 | F3: =+I3 -> 1884549714 | G3: 下水道事業収益 | H3: 仮受消費税 | I3: =+仮受仮払!F4 -> 1884549714 | J3: =I3-F3 -> 0
A4: 資本的収入仮受消費税の振替 | E4: =F4-I4 -> 0 | F4: =+I4 -> 3608310 | G4: 資本的収入 | H4: 仮受消費税 | I4: =+仮受仮払!F47 -> 3608310 | J4: =I4-F4 -> 0
A5: 収益的支出仮払消費税の振替 | E5: =F5-I5 -> 0 | F5: =+I5 -> 47155349 | G5: 仮払消費税 | H5: 管きょ費 | I5: =+仮受仮払!F23 -> 47155349 | J5: =I5-F5 -> 0
E6: =F6-I6 -> 0 | F6: =+I6 -> 1130574 | G6: 仮払消費税 | H6: 水質指導費 | I6: =+仮受仮払!F24 -> 1130574 | J6: =I6-F6 -> 0
E7: =F7-I7 -> 0 | F7: =+I7 -> 104382258 | G7: 仮払消費税 | H7: ポンプ場費 | I7: =+仮受仮払!F25 -> 104382258 | J7: =I7-F7 -> 0
E8: =F8-I8 -> 0 | F8: =+I8 -> 519893786 | G8: 仮払消費税 | H8: 処理場費 | I8: =+仮受仮払!F26 -> 519893786 | J8: =I8-F8 -> 0
E9: =F9-I9 -> 0 | F9: =+I9 -> 0 | G9: 仮払消費税 | H9: 受託工事費 | I9: =+仮受仮払!F27 -> 0 | J9: =I9-F9 -> 0
E10: =F10-I10 -> 0 | F10: =+I10 -> 1715497 | G10: 仮払消費税 | H10: 普及促進費 | I10: =+仮受仮払!F28 -> 1715497 | J10: =I10-F10 -> 0
E11: =F11-I11 -> 0 | F11: =+I11 -> 87589 | G11: 仮払消費税 | H11: 水洗化貸付事業費 | I11: =+仮受仮払!F29 -> 87589 | J11: =I11-F11 -> 0
E12: =F12-I12 -> 0 | F12: =+I12 -> 90253429 | G12: 仮払消費税 | H12: 業務費 | I12: =+仮受仮払!F30 -> 90253429 | J12: =I12-F12 -> 0
E13: =F13-I13 -> 0 | F13: =+I13 -> 17678805 | G13: 仮払消費税 | H13: 総係費 | I13: =+仮受仮払!F31 -> 17678805 | J13: =I13-F13 -> 0
E14: =F14-I14 -> 0 | F14: =+I14 -> 9713984 | G14: 仮払消費税 | H14: 特環公共下水道費 | I14: =+仮受仮払!F32 -> 9713984 | J14: =I14-F14 -> 0
E15: =F15-I15 -> 0 | F15: =+I15 -> 22486229 | G15: 仮払消費税 | H15: 農業集落排水費 | I15: =+仮受仮払!F33 -> 22486229 | J15: =I15-F15 -> 0
E16: =F16-I16 -> 0 | F16: =+I16 -> 6447001 | G16: 仮払消費税 | H16: 浄化槽費 | I16: =+仮受仮払!F34 -> 6447001 | J16: =I16-F16 -> 0
E17: =F17-I17 -> 0 | F17: =+I17 -> 0 | G17: 仮払消費税 | H17: 災害復旧費 | I17: =+仮受仮払!F35 -> 0 | J17: =I17-F17 -> 0
E18: =F18-I18 -> 0 | F18: =+I18 -> 0 | G18: 仮払消費税 | H18: 固定資産撤去費 | I18: =+仮受仮払!F37 -> 0 | J18: =I18-F18 -> 0
E19: =F19-I19 -> 0 | F19: =+I19 -> 6109254 | G19: 仮払消費税 | H19: 企業債手数料及び取扱費 | I19: =+仮受仮払!F38 -> 6109254 | J19: =I19-F19 -> 0
E20: =F20-I20 -> 0 | F20: =+I20 -> 968444 | G20: 仮払消費税 | H20: 過年度損益修正損 | I20: =+仮受仮払!F44 -> 968444 | J20: =I20-F20 -> 0
E21: =F21-I21 -> 0 | F21: =+I21 -> 0 | G21: 仮払消費税 | H21: その他特別損失 | I21: =+仮受仮払!F45 -> 0 | J21: =I21-F21 -> 0
A22: 資本的支出仮払消費税の振替 | E22: =F22-I22 -> 0 | F22: =+I22 -> 1356109400 | G22: 仮払消費税 | H22: 公共下水道整備費 | I22: =+仮受仮払!F69 -> 1356109400 | J22: =I22-F22 -> 0
E23: =F23-I23 -> 0 | F23: =+I23 -> 543071 | G23: 仮払消費税 | H23: 受益者負担業務費 | I23: =+仮受仮払!F70 -> 543071 | J23: =I23-F23 -> 0
E24: =F24-I24 -> 0 | F24: =+I24 -> 47147259 | G24: 仮払消費税 | H24: 排水設備整備費 | I24: =+仮受仮払!F71 -> 47147259 | J24: =I24-F24 -> 0
E25: =F25-I25 -> 0 | F25: =+I25 -> 0 | G25: 仮払消費税 | H25: 都市下水路整備費 | I25: =+仮受仮払!F72 -> 0 | J25: =I25-F25 -> 0
E26: =F26-I26 -> 0 | F26: =+I26 -> 11020779 | G26: 仮払消費税 | H26: 流域下水道整備費 | I26: =+仮受仮払!F73 -> 11020779 | J26: =I26-F26 -> 0
E27: =F27-I27 -> 0 | F27: =+I27 -> 5379819 | G27: 仮払消費税 | H27: 諸設備新設改良費 | I27: =+仮受仮払!F74 -> 5379819 | J27: =I27-F27 -> 0
E28: =F28-I28 -> 0 | F28: =+I28 -> 59696859 | G28: 仮払消費税 | H28: 市街化区域外整備費 | I28: =+仮受仮払!F76 -> 59696859 | J28: =I28-F28 -> 0
A29: 仮払消費税の振替 | E29: =F29-I29 -> 0 | F29: =+I29 -> 1886277459 | G29: 仮受消費税 | H29: 仮払消費税 | I29: =F3+F4-F38 -> 1886277459 | J29: =I29-F29 -> 0
E30: =F30-I30 -> 0 | F30: =+I30 -> -343538729 | G30: 消費税還付金 | H30: 仮払消費税 | I30: =精算表!C14 -> -343538729 | J30: =I30-F30 -> 0
A31: 資本的支出に係る控除できない仕入税額の振替 | E31: =F31-I31 -> 0 | F31: =+I31 -> 552693179 | G31: 特定収入仮払消費税 | H31: 仮払消費税 | I31: =+仮受仮払!F92 -> 552693179 | J31: =I31-F31 -> 0
A32: 資本的支出に係る控除できない仕入税額の圧縮記帳 | E32: =F32-I32 -> 0 | F32: =+I32 -> 522413737 | G32: 国庫補助金 | H32: 特定収入仮払消費税 | I32: =+仮受仮払!F93 -> 522413737 | J32: =I32-F32 -> 0
E33: =F33-I33 -> 0 | F33: =+I33 -> 0 | G33: 県補助金 | H33: 特定収入仮払消費税 | I33: =+仮受仮払!F94 -> 0 | J33: =I33-F33 -> 0
E34: =F34-I34 -> 0 | F34: =+I34 -> 0 | G34: 特定資金公共事業債 | H34: 特定収入仮払消費税 | J34: =I34-F34 -> 0
E35: =F35-I35 -> 0 | F35: =+I35 -> 779531 | G35: 受益者負担金 | H35: 特定収入仮払消費税 | I35: =+仮受仮払!F95 -> 779531 | J35: =I35-F35 -> 0
E36: =F36-I36 -> 0 | F36: =+I36 -> 3138956 | G36: 受益者分担金 | H36: 特定収入仮払消費税 | I36: =+仮受仮払!F96 -> 3138956 | J36: =I36-F36 -> 0
E37: =F37-I37 -> 0 | F37: =+I37 -> 26360955 | G37: 工事負担金 | H37: 特定収入仮払消費税 | I37: =+仮受仮払!F97 -> 26360955 | J37: =I37-F37 -> 0
A38: 収益的支出に係る返還等対価、貸倒れに係る税額の振替 | E38: =F38-I38 -> 0 | F38: =+I38 -> 1880565 | G38: 仮受消費税 | H38: 雑収益 | I38: =+-仮受仮払!F91 -> 1880565 | J38: =I38-F38 -> 0
A39: 収益的支出に係る控除できない仕入税額の振替 | E39: =F39-I39 -> 0 | F39: =+I39 -> 212487477 | G39: 雑支出 | H39: 仮払消費税 | I39: =+SUM(仮受仮払!F87:F90) -> 212487477 | J39: =I39-F39 -> 0
E40: =F40-I40 -> 0 | F40: =SUM(F3:F39) -> 7058570540 | G40: 合計 | H40: 合計 | I40: =SUM(I3:I39) -> 7058570540 | J40: =I40-F40 -> 0
E41: =F41-I41 -> 1884549714 | F41: =SUMIF($G$3:$G$39,G41,$F$3:$F$39) -> 1884549714 | G41: 下水道事業収益 | H41: 下水道事業収益 | I41: =SUMIF($H$3:$H$39,H41,$I$3:$I$39) -> 0
E42: =F42-I42 -> 0 | F42: =SUMIF($G$3:$G$39,G42,$F$3:$F$39) -> 1888158024 | G42: 仮受消費税 | H42: 仮受消費税 | I42: =SUMIF($H$3:$H$39,H42,$I$3:$I$39) -> 1888158024 | J42: =I42-F42 -> 0
E43: =F43-I43 -> 3608310 | F43: =SUMIF($G$3:$G$39,G43,$F$3:$F$39) -> 3608310 | G43: 資本的収入 | H43: 資本的収入 | I43: =SUMIF($H$3:$H$39,H43,$I$3:$I$39) -> 0
F44: =SUMIF($G$3:$G$39,G44,$F$3:$F$39) -> 2307919386 | G44: 仮払消費税 | H44: 仮払消費税 | I44: =SUMIF($H$3:$H$39,H44,$I$3:$I$39) -> 2307919386 | J44: =I44-F44 -> 0
F45: =SUMIF($G$3:$G$39,G45,$F$3:$F$39) -> 0 | G45: 管きょ費 | H45: 管きょ費 | I45: =SUMIF($H$3:$H$39,H45,$I$3:$I$39) -> 47155349 | J45: =I45-F45 -> 47155349
F46: =SUMIF($G$3:$G$39,G46,$F$3:$F$39) -> 0 | G46: 水質指導費 | H46: 水質指導費 | I46: =SUMIF($H$3:$H$39,H46,$I$3:$I$39) -> 1130574 | J46: =I46-F46 -> 1130574
F47: =SUMIF($G$3:$G$39,G47,$F$3:$F$39) -> 0 | G47: ポンプ場費 | H47: ポンプ場費 | I47: =SUMIF($H$3:$H$39,H47,$I$3:$I$39) -> 104382258 | J47: =I47-F47 -> 104382258
F48: =SUMIF($G$3:$G$39,G48,$F$3:$F$39) -> 0 | G48: 処理場費 | H48: 処理場費 | I48: =SUMIF($H$3:$H$39,H48,$I$3:$I$39) -> 519893786 | J48: =I48-F48 -> 519893786
F49: =SUMIF($G$3:$G$39,G49,$F$3:$F$39) -> 0 | G49: 受託工事費 | H49: 受託工事費 | I49: =SUMIF($H$3:$H$39,H49,$I$3:$I$39) -> 0 | J49: =I49-F49 -> 0
F50: =SUMIF($G$3:$G$39,G50,$F$3:$F$39) -> 0 | G50: 普及促進費 | H50: 普及促進費 | I50: =SUMIF($H$3:$H$39,H50,$I$3:$I$39) -> 1715497 | J50: =I50-F50 -> 1715497
F51: =SUMIF($G$3:$G$39,G51,$F$3:$F$39) -> 0 | G51: 水洗化貸付事業費 | H51: 水洗化貸付事業費 | I51: =SUMIF($H$3:$H$39,H51,$I$3:$I$39) -> 87589 | J51: =I51-F51 -> 87589
F52: =SUMIF($G$3:$G$39,G52,$F$3:$F$39) -> 0 | G52: 業務費 | H52: 業務費 | I52: =SUMIF($H$3:$H$39,H52,$I$3:$I$39) -> 90253429 | J52: =I52-F52 -> 90253429
F53: =SUMIF($G$3:$G$39,G53,$F$3:$F$39) -> 0 | G53: 総係費 | H53: 総係費 | I53: =SUMIF($H$3:$H$39,H53,$I$3:$I$39) -> 17678805 | J53: =I53-F53 -> 17678805
F54: =SUMIF($G$3:$G$39,G54,$F$3:$F$39) -> 0 | G54: 特環公共下水道費 | H54: 特環公共下水道費 | I54: =SUMIF($H$3:$H$39,H54,$I$3:$I$39) -> 9713984 | J54: =I54-F54 -> 9713984
F55: =SUMIF($G$3:$G$39,G55,$F$3:$F$39) -> 0 | G55: 農業集落排水費 | H55: 農業集落排水費 | I55: =SUMIF($H$3:$H$39,H55,$I$3:$I$39) -> 22486229 | J55: =I55-F55 -> 22486229
... F68: =SUMIF($G$3:$G$39,G68,$F$3:$F$39) -> 0 | G68: 市街化区域外整備費 | H68: 市街化区域外整備費 | I68: =SUMIF($H$3:$H$39,H68,$I$3:$I$39) -> 59696859 | J68: =I68-F68 -> 59696859
E69: =F69-I69 -> -343538729 | F69: =SUMIF($G$3:$G$39,G69,$F$3:$F$39) -> -343538729 | G69: 消費税還付金 | H69: 消費税還付金 | I69: =SUMIF($H$3:$H$39,H69,$I$3:$I$39) -> 0
E70: =F70-I70 -> 0 | F70: =SUMIF($G$3:$G$39,G70,$F$3:$F$39) -> 552693179 | G70: 特定収入仮払消費税 | H70: 特定収入仮払消費税 | I70: =SUMIF($H$3:$H$39,H70,$I$3:$I$39) -> 552693179
E71: =F71-I71 -> 522413737 | F71: =SUMIF($G$3:$G$39,G71,$F$3:$F$39) -> 522413737 | G71: 国庫補助金 | H71: 国庫補助金 | I71: =SUMIF($H$3:$H$39,H71,$I$3:$I$39) -> 0
E72: =F72-I72 -> 0 | F72: =SUMIF($G$3:$G$39,G72,$F$3:$F$39) -> 0 | G72: 県補助金 | H72: 県補助金 | I72: =SUMIF($H$3:$H$39,H72,$I$3:$I$39) -> 0
E73: =F73-I73 -> 0 | F73: =SUMIF($G$3:$G$39,G73,$F$3:$F$39) -> 0 | G73: 特定資金公共事業債 | H73: 特定資金公共事業債 | I73: =SUMIF($H$3:$H$39,H73,$I$3:$I$39) -> 0
E74: =F74-I74 -> 779531 | F74: =SUMIF($G$3:$G$39,G74,$F$3:$F$39) -> 779531 | G74: 受益者負担金 | H74: 受益者負担金 | I74: =SUMIF($H$3:$H$39,H74,$I$3:$I$39) -> 0
E75: =F75-I75 -> 3138956 | F75: =SUMIF($G$3:$G$39,G75,$F$3:$F$39) -> 3138956 | G75: 受益者分担金 | H75: 受益者分担金 | I75: =SUMIF($H$3:$H$39,H75,$I$3:$I$39) -> 0
E76: =F76-I76 -> 26360955 | F76: =SUMIF($G$3:$G$39,G76,$F$3:$F$39) -> 26360955 | G76: 工事負担金 | H76: 工事負担金 | I76: =SUMIF($H$3:$H$39,H76,$I$3:$I$39) -> 0
F77: =SUMIF($G$3:$G$39,G77,$F$3:$F$39) -> 0 | G77: 雑収益 | H77: 雑収益 | I77: =SUMIF($H$3:$H$39,H77,$I$3:$I$39) -> 1880565 | J77: =I77-F77 -> 1880565
E78: =F78-I78 -> 212487477 | F78: =SUMIF($G$3:$G$39,G78,$F$3:$F$39) -> 212487477 | G78: 雑支出 | H78: 雑支出 | I78: =SUMIF($H$3:$H$39,H78,$I$3:$I$39) -> 0
E79: =SUM(E41:E78) -> 2309799951 | F79: =SUM(F41:F78) -> 7058570540 | G79: 合計 | H79: 合計 | I79: =SUM(I41:I78) -> 7058570540 | J79: =SUM(J41:J78) -> 2309799951
