Workbook

Sheet 最終チェック（資本的支出の財源内訳と照合）
C1: ピンクは手入力、黄色は自動計算 | E1: 令和４年度 | G1: 令和5年度 | H1: 備考（資本的支出の財源内訳との照合場所）
C2: ※ここでの計算はエラーチェックのために行うものであり、他のシートには一切反映されません
A3: 資本的支出総額（執行額） | D3: a | E3: 59709459299 | G3: ='(繰)4条支出 '!G5 -> 61875977537 | H3: 全５（決算）の決算額 E72と一致
G4: 2.6989462e+09 | H4: 全５（決算）の一般財源R72を入力
A5: 資本的収入 | D5: b=c-d | E5: 39670381852 | G5: =G4+'(繰)4条収入'!G35 -> 41438646781 | H5: 全５（決算）の企業債～固定資産売却代金+一般財源 F72～M72+R72と一致
B6: 執行額（一般会計出資金収入含む） | D6: c | E6: =E5+E7 -> 40554720469 | G6: =G5+G7 -> 42025205141
B7: うち翌年度に繰越す予算への財源充当額 | D7: d | E7: 884338617 | G7: ='(繰)4条支出 '!J5-'(繰)4条収入'!L5 -> 586558360 | H7: 全３（繰越）の出資金 R75と一致
A9: 資本的収支不足額 | D9: e=a-b | E9: =E3-E5 -> 20039077447 | G9: =G3-G5 -> 20437330756
A11: 補填財源 | D11: f=g+h+i+j | E11: =SUM(E12:E13,E16:E17) -> 20039077447 | G11: =SUM(G12:G13,G16:G17) -> 20437330756
B12: 消費税資本的収支調整額 | D12: g | E12: 769659721 | G12: ='(繰)案'!E33 -> 923595698 | H12: 黄色部分は全１（現年）の当年度消費税 O78と一致
B13: 繰越工事資金 | D13: h=i+j | E13: =SUM(E14:E15) -> 627253803 | G13: =SUM(G14:G15) -> 884338617
C14: 前年度からの自己財源 | D14: i | E14: 627111363 | G14: =E7 -> 884338617
C15: 前々年度からの自己財源（事故繰越分） | D15: j | E15: 142440 | H15: 事故繰越分の予算繰越計算書の自己財源
B16: 損益勘定留保資金 | D16: k | E16: 17443558426 | G16: ='(繰)案'!E22 -> 17579830234 | H16: 全１（現年）の減価償却費+資産減耗費+その他 O74+O75+O79と一致
B17: 減債積立金 | D17: l | E17: 1198605497 | G17: ='(繰)案'!E34 -> 1049566207 | H17: 全１（現年）の減債積立金 O77と一致
A19: 過不足額 | D19: m=e-f | E19: =E9-E11 -> 0 | G19: =G9-G11 -> 0 | H19: ←この数値が０になることを確認

Sheet (繰)案
A1: （案の１）
A2: 1 一般会計繰入金予算額 | E2: ='(繰)対前年'!G46 -> 17495336000 | F2: 円
A3: 2 一般会計繰入金受入済額 | D3: （Ａ） | E3: =+E2 -> 17495336000 | F3: 円
A4: 3 前受金（災害復旧等繰越財源分） | D4: （Ｂ） | E4: =+'(繰)対前年'!G36 -> 0 | F4: 円
A5: 3 一般会計繰入金精算額 ＝ 下水決算額 | D5: （B） | E5: =+'(繰)対前年'!H39 -> 17481810139 | F5: 円 | H5: ↓非表示行あり
A6: 5 前年度一般会計出資金未収額 | D6: （Ｄ） | E6: =+'(繰)対前年'!H38 -> 0 | F6: 円
A7: 4 差引精算戻入額 | D7: （Ａ－Ｂ） | E7: =E3+E4-E5-E6 -> 13525861 | F7: 円
A9: 【一般会計繰入金精算額＝下水決算額の説明】
B10: 1 収益的収支（３条分、税抜き） | H10: ↓3条収入・支出シート
C11: (1) 支出決算額 | D11: （ア） | E11: ='(繰)3条支出 '!I4 -> 42028134935 | F11: 円 | H11: =+'[1]3条支出'!T41 -> 42028134935
C12: (2) 収入決算額（繰入金除く。） | D12: （イ） | E12: ='(繰)3条収入'!H4-'(繰)3条収入'!H7-'(繰)3条収入'!H15 -> 28375736546 | F12: 円 | H12: =+'[2]3条収入'!AI69 -> 42572042134
C13: (3) 当年度純利益 | D13: （ウ） | E13: =+'(繰)3条収入'!H4-'(繰)3条支出 '!I4 -> 543907199 | F13: 円 | H13: =+'[2]3条収入'!AI74 -> 543907199
C14: (4) 繰入金額（一般会計負担金、一般会計補助金） | D14: （ア－イ＋ウ） | E14: =E11-E12+E13 -> 14196305588 | F14: 円 | G14: （C） | H14: =+'[2]3条収入'!AI9+'[2]3条収入'!AI42 -> 14196305588
B16: ２ 資本的収支（４条分、税込み、みなしベース）
C17: (1) 支出決算額 | D17: （エ） | E17: ='(繰)4条支出 '!K5 -> 61852897933 | F17: 円
C18: (2) 収入決算額（繰入金除く。） | D18: （オ） | E18: =SUM('(繰)4条収入'!M6,'(繰)4条収入'!M16,'(繰)4条収入'!M20,'(繰)4条収入'!M22,'(繰)4条収入'!M29,'(繰)4条収入'!M30) -> 38957586329 | F18: 円
C19: （前年度充当財源（企業債未発行分）を除く）
C20: (3) 補てん財源 | D20: （カ） | E20: =E22+E31+E34+E35 -> 19609807053 | F20: 円
C21: （補てん財源の内訳）
C22: ①当年度分損益勘定留保資金 | E22: =SUM(E23:E30) -> 17579830234 | F22: 円 | H22: ↓資金余剰調整額
C23: ＊減価償却費 | E23: ='(繰)3条支出 '!I18-H23 -> 26551442230 | F23: 円
C24: ＊固定資産除却費 | E24: =+[1]減耗!T5 -> 503761871 | F24: 円 | H24: ↓非表示行あり
C25: ＊固定資産売却損 | E25: ='(繰)3条支出 '!G25 -> 10315355 | F25: 円
C26: ＊減損損失 | E26: =+'(繰)3条支出 '!I28 -> 0 | F26: 円
C27: ＊長期前受金戻入（償却・除却見合分） | E27: =-'(繰)3条収入'!H18 -> -9485355002 | F27: 円
C28: ＊長期前受金戻入益（減損見合分） | E28: =-'(繰)3条収入'!H20 -> 0
C29: ＊過年度損益修正益 | E29: -334220 | F29: 円
C30: ＊企業債発行差金(見なし決算分） | E30: =+[1]営外!T12 -> 0 | F30: 円
C31: ②消費税及び地方消費税資本的収支調整額 | E31: =E32+E33 -> 923595698 | F31: 円
C32: ＊過年度分 | E32: 0 | F32: 円
C33: ＊現年度分 | E33: =-[3]消費税!AF118 -> 923595698 | F33: 円
C34: ③減債積立金 | E34: 1049566207 | F34: 円 | H34: ↓非表示行あり
C35: ④繰越工事資金当年度充当額 | E35: 56814914 | F35: 円
C37: (4) 繰入金額（一般会計出資金、一般会計借入金） | D37: （エ－オ－カ） | E37: =E17-E18-E20 -> 3285504551 | F37: 円 | G37: （D） | J37: 予算
D38: （Ｄ）のうち 一般会計借入金 | E38: ='(繰)4条収入'!I28 -> 0 | J38: 3640474000
D39: 一般会計出資金 | E39: =E37-E38 -> 3285504551 | J39: =E37-J38 -> -354969449
B41: ３ 繰入金総額（C+D）＝今回精算（確定）額＝下水決算額
E42: =E14+E37 -> 17481810139 | F42: 円 | G42: （Ｂ）

Sheet (繰)精算書
H1: （案の２） | J1: =+DATE(MID([4]雨汚水!D1,3,1)+2019,3,31) -> 45382
B2: 広 島 市 長 様 （財政局財政課）
J3: 広島市長 （下水道局経営企画課）
A5: =+CONCATENATE(LEFT('[1]3条支出'!$D$1,7),"下水道事業会計に対する一般会計繰入金の精算について") -> 令和５年度決算下水道事業会計に対する一般会計繰入金の精算について
B7: このことについて、下記のとおり精算します。ついては、5月31日を納期限とした納入通知書を作成してください。
A8: 記
J9: （単位：円）
A10: 科 目 | G10: 受入済額(a) | H10: 精算額(b) | I10: 精算戻入額(a-b) | J10: 備 考 | K10: AAA | L10: AAA | M10: AAA | N10: AAA
A11: 下水道事業収益 | G11: =G12+G22 -> 13854862000 | H11: =H12+H22 -> 14196305588 | I11: =G11-H11 -> -341443588 | N11: =OR(G11>0,H11>0,I11>0) -> TRUE
B12: 営業収益 | G12: =G13 -> 13854862000 | H12: =H13 -> 14187102335 | I12: =G12-H12 -> -332240335 | N12: =OR(G12>0,H12>0,I12>0) -> TRUE
C13: 一般会計負担金 | G13: =G14+G19+G20+G21+G18 -> 13854862000 | H13: =H14+H19+H20+H21 -> 14187102335 | I13: =G13-H13 -> -332240335 | N13: =OR(G13>0,H13>0,I13>0) -> TRUE
D14: 雨水処理負担金 | G14: =SUM(G15:G17) -> 13738282000 | H14: =SUM(H15:H18) -> 14079749832 | I14: =G14-H14 -> -341467832 | N14: =OR(G14>0,H14>0,I14>0) -> TRUE
E15: 維持管理費分 | G15: =+'(繰)対前年'!G9 -> 3686798000 | H15: ='(繰)対前年'!H9-H18 -> 3591522898 | I15: =G15-H15 -> 95275102 | J15: 補助費 | N15: =OR(G15>0,H15>0,I15>0) -> TRUE
E16: 減価償却費分 | G16: =+'(繰)対前年'!G10 -> 7912710000 | H16: ='(繰)対前年'!H10 -> 8476549651 | I16: =G16-H16 -> -563839651 | J16: 普建 | N16: =OR(G16>0,H16>0,I16>0) -> TRUE
E17: 支払利息分 | G17: =+'(繰)対前年'!G11 -> 2138774000 | H17: ='(繰)対前年'!H11 -> 2011677283 | I17: =G17-H17 -> 127096717 | J17: 普建 | N17: =OR(G17>0,H17>0,I17>0) -> TRUE
E18: 維持管理費分（災害復旧繰越分) | G18: =+'(繰)対前年'!G12 -> 0 | H18: ='(繰)繰入金'!H11 -> 0 | I18: =G18-H18 -> 0 | J18: 補助費 | N18: =OR(G18>0,H18>0,I18>0) -> FALSE
D19: 水質指導費負担金 | G19: =+'(繰)対前年'!G13 -> 61778000 | H19: ='(繰)対前年'!H13 -> 52443869 | I19: =G19-H19 -> 9334131 | J19: 補助費 | N19: =OR(G19>0,H19>0,I19>0) -> TRUE
D20: 普及促進費負担金 | G20: =+'(繰)対前年'!G14 -> 40039000 | H20: ='(繰)対前年'!H14 -> 44424775 | I20: =G20-H20 -> -4385775 | J20: 補助費 | N20: =OR(G20>0,H20>0,I20>0) -> TRUE
D21: 貸付事業費負担金 | G21: =+'(繰)対前年'!G15 -> 14763000 | H21: ='(繰)対前年'!H15 -> 10483859 | I21: =G21-H21 -> 4279141 | J21: 補助費 | K21: =+'(繰)繰入金'!H11 -> 0 | L21: ← | M21: 普建分 | N21: =OR(G21>0,H21>0,I21>0) -> TRUE
B22: 営業外収益 | G22: =G23 -> 0 | H22: =H23 -> 9203253 | I22: =G22-H22 -> -9203253 | N22: =OR(G22>0,H22>0,I22>0) -> TRUE
C23: 一般会計補助金 | G23: =G24+G31 -> 0 | H23: =H24+H31 -> 9203253 | I23: =G23-H23 -> -9203253 | N23: =OR(G23>0,H23>0,I23>0) -> TRUE
D24: 汚水処理補助金 | G24: =SUM(G25:G28) -> 0 | H24: =SUM(H25:H28) -> 4980 | I24: =G24-H24 -> -4980 | N24: =OR(G24>0,H24>0,I24>0) -> TRUE
E25: 維持管理費分 | G25: ='(繰)対前年'!G19 -> 0 | H25: 0 | I25: =G25-H25 -> 0 | N25: =OR(G25>0,H25>0,I25>0) -> FALSE
E26: 減価償却費分 | G26: ='(繰)対前年'!G20 -> 0 | H26: ='(繰)対前年'!H20 -> 0 | I26: =G26-H26 -> 0 | J26: 普建 | N26: =OR(G26>0,H26>0,I26>0) -> FALSE
E27: 支払利息分 | G27: ='(繰)対前年'!G21 -> 0 | H27: ='(繰)対前年'!H21 -> 0 | I27: =G27-H27 -> 0 | J27: 普建 | N27: =OR(G27>0,H27>0,I27>0) -> FALSE
E28: 下水道使用料減免分 | G28: =+'(繰)対前年'!G22 -> 0 | H28: ='(繰)対前年'!H22 -> 4980 | I28: =G28-H28 -> -4980 | J28: 普建 | N28: =OR(G28>0,H28>0,I28>0) -> TRUE
F29: 当年度分 | G29: =+'(繰)対前年'!G23 -> 0 | H29: ='(繰)対前年'!H23 -> 0 | I29: =G29-H29 -> 0 | N29: =OR(G29>0,H29>0,I29>0) -> FALSE
F30: 前年度未収分 | G30: =+'(繰)対前年'!G24 -> 0 | H30: ='(繰)対前年'!H24 -> 0 | I30: =G30-H30 -> 0 | N30: =OR(G30>0,H30>0,I30>0) -> FALSE
D31: その他補助金 | G31: =+'(繰)対前年'!G25 -> 0 | H31: ='(繰)対前年'!H25 -> 9198273 | I31: =G31-H31 -> -9198273 | J31: 補助費 | N31: =OR(G31>0,H31>0,I31>0) -> TRUE
A32: 資本的収入 | G32: =G33+G36 -> 3640474000 | H32: =H33+H36 -> 3285504551 | I32: =G32-H32 -> 354969449 | N32: =OR(G32>0,H32>0,I32>0) -> TRUE
B33: 一般会計出資金 | G33: =G34 -> 3640474000 | H33: =H34 -> 3285504551 | I33: =G33-H33 -> 354969449 | N33: =OR(G33>0,H33>0,I33>0) -> TRUE
C34: 下水道建設費出資金 | G34: =SUM(G35:G35) -> 3640474000 | H34: =SUM(H35:H35) -> 3285504551 | I34: =G34-H34 -> 354969449 | N34: =OR(G34>0,H34>0,I34>0) -> TRUE
D35: 下水道建設費出資金 | G35: =+'(繰)対前年'!G29 -> 3640474000 | H35: ='(繰)対前年'!H29 -> 3285504551 | I35: =G35-H35 -> 354969449 | J35: 普建 | N35: =OR(G35>0,H35>0,I35>0) -> TRUE
B36: 水洗化貸付事業収入 | G36: =G37 -> 0 | H36: =H37 -> 0 | I36: =G36-H36 -> 0 | N36: =OR(G36>0,H36>0,I36>0) -> FALSE
C37: 一般会計借入金 | G37: =SUM(G38:G40) -> 0 | H37: =SUM(H38:H40) -> 0 | I37: =G37-H37 -> 0 | J37: 貸付金 | N37: =OR(G37>0,H37>0,I37>0) -> FALSE
D38: 水洗便所改造資金貸付借入金 | G38: =+'(繰)対前年'!G32 -> 0 | H38: ='(繰)対前年'!H32 -> 0 | I38: =G38-H38 -> 0 | N38: =OR(G38>0,H38>0,I38>0) -> FALSE
D39: し尿浄化槽廃止資金貸付借入金 | G39: =+'(繰)対前年'!G33 -> 0 | H39: ='(繰)対前年'!H33 -> 0 | I39: =G39-H39 -> 0 | N39: =OR(G39>0,H39>0,I39>0) -> FALSE
D40: 排水設備改修資金貸付借入金 | G40: =+'(繰)対前年'!G34 -> 0 | H40: ='(繰)対前年'!H34 -> 0 | I40: =G40-H40 -> 0 | N40: =OR(G40>0,H40>0,I40>0) -> FALSE
A41: 計 （当年度決算分） | N41: =TRUE() -> TRUE
G42: =G11+G32 -> 17495336000 | H42: =H11+H32 -> 17481810139 | I42: =I11+I32 -> 13525861 | N42: =TRUE() -> TRUE
N43: =TRUE() -> TRUE
A44: 前受金（災害復旧等繰越財源分） | N44: =TRUE() -> TRUE
G45: =+'(繰)対前年'!G36 -> 0 | H45: 0 | I45: =G45-H45 -> 0 | N45: =TRUE() -> TRUE
N46: =TRUE() -> TRUE
A47: 計（下水道事業会計決算額） | N47: =TRUE() -> TRUE
G48: =G42+G45 -> 17495336000 | H48: =H42+H45 -> 17481810139 | I48: =I42+I45 -> 13525861 | N48: =TRUE() -> TRUE
G49: （前受金） | N49: =TRUE() -> TRUE
A50: 前年度下水道建設費出資金未収金 | G50: =+'(繰)対前年'!G38 -> 0 | H50: ='(繰)対前年'!H38 -> 0 | I50: =G50-H50 -> 0 | J50: 普建 | N50: =TRUE() -> TRUE
A51: 合 計 | G51: =G48+G50 -> 17495336000 | H51: =H48+H50 -> 17481810139 | I51: =I48+I50 -> 13525861 | N51: =TRUE() -> TRUE
N52: =TRUE() -> TRUE
A53: 区 分 | G53: 受入済額(a) | H53: 精算額(b) | I53: 精算戻入額(a-b) | J53: 備 考 | N53: =TRUE() -> TRUE
N54: =TRUE() -> TRUE
A55: 内 訳 | D55: 普 建 | G55: =+'(繰)対前年'!G43 -> 13691958000 | H55: ='(繰)繰入金'!H41 -> 13773736465 | I55: =G55-H55 -> -81778465 | N55: =TRUE() -> TRUE
D56: 補助費 | G56: =+'(繰)対前年'!G44 -> 3803378000 | H56: ='(繰)繰入金'!H42-G45 -> 3708073674 | I56: =G56-H56 -> 95304326 | N56: =TRUE() -> TRUE
D57: 貸付金 | G57: =+'(繰)対前年'!G45 -> 0 | H57: ='(繰)繰入金'!H43 -> 0 | I57: =G57-H57 -> 0 | N57: =TRUE() -> TRUE
A58: 計（一般会計決算額) | G58: =SUM(G55:G57) -> 17495336000 | H58: =SUM(H55:H57) -> 17481810139 | I58: =SUM(I55:I57) -> 13525861 | N58: =TRUE() -> TRUE
E59: 普建分チェック | G59: =G16+G17+G26+G27+G28+G35 -> 13691958000 | H59: =H16+H17+H26+H27+H28+H35+K21 -> 13773736465 | I59: 精算戻入額チェック | J59: =+I51-I58 -> 0 | N59: =TRUE() -> TRUE
E60: 一般会計の普建との差 | G60: =G55-G59 -> 0 | H60: =H55-H59 -> 0 | N60: =TRUE() -> TRUE
E61: 下水会計の補助費 | G61: =G15+G18+G19+G20+G21 -> 3803378000 | H61: =H15+H18+H19+H20+H21-K21+H31 -> 3708073674 | N61: =TRUE() -> TRUE
E62: 一般会計の補助費との差 | G62: =G56-G61 -> 0 | H62: =H56-H61 -> 0 | N62: =TRUE() -> TRUE

Sheet (繰)繰入金
A1: =+CONCATENATE(LEFT('[1]3条支出'!$D$1,5),"一般会計繰入金の性質別等の区分") -> 令和５年度一般会計繰入金の性質別等の区分
J2: （単位：円）
A3: 科 目 | G3: 議決予算額(a) | H3: 決算額(b) | I3: 差 引(a-b) | J3: 備 考 | K3: 抽出用
A4: 下水道事業収益 | G4: =G5+G15 -> 13854862000 | H4: =H5+H15 -> 14196305588 | I4: =G4-H4 -> -341443588 | K4: =OR(G4>0,H4>0,I4>0) -> TRUE
B5: 営業収益 | G5: =G6 -> 13854862000 | H5: =H6 -> 14187102335 | I5: =G5-H5 -> -332240335 | K5: =OR(G5>0,H5>0,I5>0) -> TRUE
C6: 一般会計負担金 | G6: =G7+G12+G13+G14+G11 -> 13854862000 | H6: =H7+H12+H13+H14 -> 14187102335 | I6: =G6-H6 -> -332240335 | K6: =OR(G6>0,H6>0,I6>0) -> TRUE
D7: 雨水処理負担金 | G7: =SUM(G8:G10) -> 13738282000 | H7: =SUM(H8:H11) -> 14079749832 | I7: =G7-H7 -> -341467832 | K7: =OR(G7>0,H7>0,I7>0) -> TRUE
E8: 維持管理費分 | G8: ='(繰)対前年'!G9 -> 3686798000 | H8: ='(繰)対前年'!H9-H11 -> 3591522898 | I8: =G8-H8 -> 95275102 | J8: 補助費 | K8: =OR(G8>0,H8>0,I8>0) -> TRUE
E9: 減価償却費分 | G9: ='(繰)対前年'!G10 -> 7912710000 | H9: ='(繰)対前年'!H10 -> 8476549651 | I9: =G9-H9 -> -563839651 | J9: 普建 | K9: =OR(G9>0,H9>0,I9>0) -> TRUE
E10: 支払利息分 | G10: ='(繰)対前年'!G11 -> 2138774000 | H10: ='(繰)対前年'!H11 -> 2011677283 | I10: =G10-H10 -> 127096717 | J10: 普建 | K10: =OR(G10>0,H10>0,I10>0) -> TRUE
E11: 維持管理費分（災害復旧繰越分) | G11: 0 | H11: 0 | I11: =G11-H11 -> 0 | J11: 補助費 | K11: =OR(G11>0,H11>0,I11>0) -> FALSE
D12: 水質指導費負担金 | G12: ='(繰)対前年'!G13 -> 61778000 | H12: ='(繰)対前年'!H13 -> 52443869 | I12: =G12-H12 -> 9334131 | J12: 補助費 | K12: =OR(G12>0,H12>0,I12>0) -> TRUE
D13: 普及促進費負担金 | G13: ='(繰)対前年'!G14 -> 40039000 | H13: ='(繰)対前年'!H14 -> 44424775 | I13: =G13-H13 -> -4385775 | J13: 補助費 | K13: =OR(G13>0,H13>0,I13>0) -> TRUE
D14: 貸付事業費負担金 | G14: ='(繰)対前年'!G15 -> 14763000 | H14: ='(繰)対前年'!H15 -> 10483859 | I14: =G14-H14 -> 4279141 | J14: 補助費 | K14: =OR(G14>0,H14>0,I14>0) -> TRUE
B15: 営業外収益 | G15: =G16 -> 0 | H15: =H16 -> 9203253 | I15: =G15-H15 -> -9203253 | K15: =OR(G15>0,H15>0,I15>0) -> TRUE
C16: 一般会計補助金 | G16: =G17+G24 -> 0 | H16: =H17+H24 -> 9203253 | I16: =G16-H16 -> -9203253 | K16: =OR(G16>0,H16>0,I16>0) -> TRUE
D17: 汚水処理補助金 | G17: =SUM(G18:G21) -> 0 | H17: =SUM(H18:H21) -> 4980 | I17: =G17-H17 -> -4980 | K17: =OR(G17>0,H17>0,I17>0) -> TRUE
E18: 維持管理費分 | G18: 0 | H18: 0 | I18: =G18-H18 -> 0 | K18: =OR(G18>0,H18>0,I18>0) -> FALSE
E19: 減価償却費分 | G19: ='(繰)対前年'!G20 -> 0 | H19: ='(繰)対前年'!H20 -> 0 | I19: =G19-H19 -> 0 | J19: 普建 | K19: =OR(G19>0,H19>0,I19>0) -> FALSE
E20: 支払利息分 | G20: ='(繰)対前年'!G21 -> 0 | H20: ='(繰)対前年'!H21 -> 0 | I20: =G20-H20 -> 0 | J20: 普建 | K20: =OR(G20>0,H20>0,I20>0) -> FALSE
E21: 下水道使用料減免分 | G21: ='(繰)対前年'!G22 -> 0 | H21: ='(繰)対前年'!H22 -> 4980 | I21: =G21-H21 -> -4980 | J21: 普建 | K21: =OR(G21>0,H21>0,I21>0) -> TRUE
F22: 当年度分 | G22: ='(繰)対前年'!G23 -> 0 | H22: ='(繰)対前年'!H23 -> 0 | I22: =G22-H22 -> 0 | K22: =OR(G22>0,H22>0,I22>0) -> FALSE
F23: 前年度未収分 | G23: ='(繰)対前年'!G24 -> 0 | H23: ='(繰)対前年'!H24 -> 0 | I23: =G23-H23 -> 0 | K23: =OR(G23>0,H23>0,I23>0) -> FALSE
D24: その他補助金 | G24: ='(繰)対前年'!G25 -> 0 | H24: ='(繰)対前年'!H25 -> 9198273 | I24: =G24-H24 -> -9198273 | J24: 補助費 | K24: =OR(G24>0,H24>0,I24>0) -> TRUE
A25: 資本的収入 | G25: =G26+G29 -> 3640474000 | H25: =H26+H29 -> 3285504551 | I25: =G25-H25 -> 354969449 | K25: =OR(G25>0,H25>0,I25>0) -> TRUE
B26: 一般会計出資金 | G26: =G27 -> 3640474000 | H26: =H27 -> 3285504551 | I26: =G26-H26 -> 354969449 | K26: =OR(G26>0,H26>0,I26>0) -> TRUE
C27: 下水道建設費出資金 | G27: =SUM(G28:G28) -> 3640474000 | H27: =SUM(H28:H28) -> 3285504551 | I27: =G27-H27 -> 354969449 | K27: =OR(G27>0,H27>0,I27>0) -> TRUE
D28: 下水道建設費出資金 | G28: ='(繰)対前年'!G29 -> 3640474000 | H28: ='(繰)対前年'!H29 -> 3285504551 | I28: =G28-H28 -> 354969449 | J28: 普建 | K28: =OR(G28>0,H28>0,I28>0) -> TRUE
B29: 水洗化貸付事業収入 | G29: =G30 -> 0 | H29: =H30 -> 0 | I29: =G29-H29 -> 0 | K29: =OR(G29>0,H29>0,I29>0) -> FALSE
C30: 一般会計借入金 | G30: =SUM(G31:G33) -> 0 | H30: =SUM(H31:H33) -> 0 | I30: =G30-H30 -> 0 | J30: 貸付金 | K30: =OR(G30>0,H30>0,I30>0) -> FALSE
D31: 水洗便所改造資金貸付借入金 | G31: ='(繰)対前年'!G32 -> 0 | H31: ='(繰)対前年'!H32 -> 0 | I31: =G31-H31 -> 0 | K31: =OR(G31>0,H31>0,I31>0) -> FALSE
D32: し尿浄化槽廃止資金貸付借入金 | G32: ='(繰)対前年'!G33 -> 0 | H32: ='(繰)対前年'!H33 -> 0 | I32: =G32-H32 -> 0 | K32: =OR(G32>0,H32>0,I32>0) -> FALSE
D33: 排水設備改修資金貸付借入金 | G33: ='(繰)対前年'!G34 -> 0 | H33: ='(繰)対前年'!H34 -> 0 | I33: =G33-H33 -> 0 | K33: =OR(G33>0,H33>0,I33>0) -> FALSE
A34: 計 （当年度決算分） | G34: =G4+G25 -> 17495336000 | H34: =H4+H25 -> 17481810139 | I34: =I4+I25 -> 13525861 | K34: =OR(G34>0,H34>0,I34>0) -> TRUE
B35: 前受金（災害復旧等繰越財源分） | G35: ='(繰)精算書'!G45 -> 0 | H35: ='(繰)精算書'!H45 -> 0 | I35: =G35-H35 -> 0 | J35: 補助費 | K35: =OR(G35>0,H35>0,I35>0) -> FALSE
A36: 合計 | G36: =G34+G35 -> 17495336000 | H36: =H34+H35 -> 17481810139 | I36: =G36-H36 -> 13525861 | K36: =OR(G36>0,H36>0,I36>0) -> TRUE
A37: 前年度下水道建設費出資金未収金 | G37: ='(繰)対前年'!G38 -> 0 | H37: ='(繰)対前年'!H38 -> 0 | I37: =G37-H37 -> 0 | J37: 普建 | K37: =OR(G37>0,H37>0,I37>0) -> FALSE
A38: 合 計 | G38: =SUM(G36:G37) -> 17495336000 | H38: =SUM(H36:H37) -> 17481810139 | I38: =SUM(I36:I37) -> 13525861 | K38: =OR(G38>0,H38>0,I38>0) -> TRUE
E40: 区 分 | G40: 議決予算額 | H40: 決算額(b) | I40: 差 引(a-b)
E41: 普建 | G41: =+'(繰)対前年'!G43 -> 13691958000 | H41: =SUMIF(J4:J33,E41,H4:H33)+H37 -> 13773736465 | I41: =G41-H41 -> -81778465
E42: 補助費 | G42: =+'(繰)対前年'!G44 -> 3803378000 | H42: =SUMIF(J4:J35,E42,H4:H35) -> 3708073674 | I42: =G42-H42 -> 95304326
E43: 貸付金 | G43: =+'(繰)対前年'!G45 -> 0 | H43: =SUMIF(J4:J33,E43,H4:H33) -> 0 | I43: =G43-H43 -> 0
E44: 計 | G44: =SUM(G41:G43) -> 17495336000 | H44: =SUM(H41:H43) -> 17481810139 | I44: =SUM(I41:I43) -> 13525861

Sheet (繰)対前年
A1: =+CONCATENATE(LEFT('[1]3条支出'!$D$1,5),"一般会計繰入金の前年度比較表") -> 令和５年度一般会計繰入金の前年度比較表
L2: （単位：円）
A3: 科 目 | G3: 議決予算額 | H3: 決算額 | I3: 予算との比較 | K3: 前年度決算額 | L3: 前年度決算額との比較 | N3: 財政収支計画額 | O3: 財政収支計画額との比較 | Q3: 備 考
G4: (a) | H4: (b) | I4: 差引(a-b) | J4: 対予算 比 | K4: (c) | L4: 差引(ｂ-ｃ) | M4: 対前年 度比 | N4: （Ｄ） | O4: 差引き(d-b) | P4: 対前年度比 | R4: 抽出用
A5: 下水道事業収益 | G5: =G6+G16 -> 13854862000 | H5: =H6+H16 -> 14196305588 | I5: =G5-H5 -> -341443588 | J5: =IF(AND(G5=0,H5>0),"皆増",IF(AND(G5>0,H5=0),"皆減",IF(AND(G5=0,H5=0),"-",H5/G5))) -> 1.0246443 | K5: =K6+K16 -> 13993380952 | L5: =L6+L16 -> 202924636 | M5: =IF(AND(K5=0,H5>0),"皆増",IF(AND(K5>0,H5=0),"皆減",IF(AND(K5=0,H5=0),"-",H5/K5))) -> 1.0145015 | N5: =N6+N16 -> 0 | O5: =N5-H5 -> -14196305588 | P5: =H5/N5 -> #DIV/0! | R5: =IF(OR(G5>0,H5>0,K5>0),"表示（自動）","非表示（自動）") -> 表示（自動）
B6: 営業収益 | G6: =G7 -> 13854862000 | H6: =H7 -> 14187102335 | I6: =G6-H6 -> -332240335 | J6: =IF(AND(G6=0,H6>0),"皆増",IF(AND(G6>0,H6=0),"皆減",IF(AND(G6=0,H6=0),"-",H6/G6))) -> 1.0239801 | K6: =K7 -> 13993349494 | L6: =SUM(L7) -> 193752841 | M6: =IF(AND(K6=0,H6>0),"皆増",IF(AND(K6>0,H6=0),"皆減",IF(AND(K6=0,H6=0),"-",H6/K6))) -> 1.0138461 | N6: =N7 -> 0 | O6: =N6-H6 -> -14187102335 | P6: =H6/N6 -> #DIV/0! | R6: =IF(OR(G6>0,H6>0,K6>0),"表示（自動）","非表示（自動）") -> 表示（自動）
C7: 一般会計負担金 | G7: =G8+G13+G14+G15+G12 -> 13854862000 | H7: =H8+H13+H14+H15+H12 -> 14187102335 | I7: =G7-H7 -> -332240335 | J7: =IF(AND(G7=0,H7>0),"皆増",IF(AND(G7>0,H7=0),"皆減",IF(AND(G7=0,H7=0),"-",H7/G7))) -> 1.0239801 | K7: =K8+K13+K14+K15+K12 -> 13993349494 | L7: =L8+L13+L14+L15+L12 -> 193752841 | M7: =IF(AND(K7=0,H7>0),"皆増",IF(AND(K7>0,H7=0),"皆減",IF(AND(K7=0,H7=0),"-",H7/K7))) -> 1.0138461 | N7: =N8+N13+N14+N15+N12 -> 0 | O7: =N7-H7 -> -14187102335 | P7: =H7/N7 -> #DIV/0! | R7: =IF(OR(G7>0,H7>0,K7>0),"表示（自動）","非表示（自動）") -> 表示（自動）
D8: 雨水処理負担金 | G8: =SUM(G9:G11) -> 13738282000 | H8: =SUM(H9:H11) -> 14079749832 | I8: =G8-H8 -> -341467832 | J8: =IF(AND(G8=0,H8>0),"皆増",IF(AND(G8>0,H8=0),"皆減",IF(AND(G8=0,H8=0),"-",H8/G8))) -> 1.0248552 | K8: =SUM(K9:K11) -> 13893559179 | L8: =SUM(L9:L11) -> 186190653 | M8: =IF(AND(K8=0,H8>0),"皆増",IF(AND(K8>0,H8=0),"皆減",IF(AND(K8=0,H8=0),"-",H8/K8))) -> 1.0134012 | N8: =SUM(N9:N11) -> 0 | O8: =N8-H8 -> -14079749832 | P8: =H8/N8 -> #DIV/0! | R8: =IF(OR(G8>0,H8>0,K8>0),"表示（自動）","非表示（自動）") -> 表示（自動）
E9: 維持管理費分 | G9: =3629553000+4934000+52311000 -> 3686798000 | H9: =+'[2]3条収入'!AI11 -> 3591522898 | I9: =G9-H9 -> 95275102 | J9: =IF(AND(G9=0,H9>0),"皆増",IF(AND(G9>0,H9=0),"皆減",IF(AND(G9=0,H9=0),"-",H9/G9))) -> 0.97415776 | K9: 3319461162 | L9: =H9-K9 -> 272061736 | M9: =IF(AND(K9=0,H9>0),"皆増",IF(AND(K9>0,H9=0),"皆減",IF(AND(K9=0,H9=0),"-",H9/K9))) -> 1.0819596 | O9: =N9-H9 -> -3591522898 | P9: =H9/N9 -> #DIV/0! | Q9: 補助費 | R9: =IF(OR(G9>0,H9>0,K9>0),"表示（自動）","非表示（自動）") -> 表示（自動）
E10: 減価償却費分 | G10: 7912710000 | H10: =+'[2]3条収入'!AI12 -> 8476549651 | I10: =G10-H10 -> -563839651 | J10: =IF(AND(G10=0,H10>0),"皆増",IF(AND(G10>0,H10=0),"皆減",IF(AND(G10=0,H10=0),"-",H10/G10))) -> 1.0712575 | K10: 8333522738 | L10: =H10-K10 -> 143026913 | M10: =IF(AND(K10=0,H10>0),"皆増",IF(AND(K10>0,H10=0),"皆減",IF(AND(K10=0,H10=0),"-",H10/K10))) -> 1.0171628 | O10: =N10-H10 -> -8476549651 | P10: =H10/N10 -> #DIV/0! | Q10: 普建 | R10: =IF(OR(G10>0,H10>0,K10>0),"表示（自動）","非表示（自動）") -> 表示（自動）
E11: 支払利息分 | G11: 2138774000 | H11: =+'[2]3条収入'!AI13 -> 2011677283 | I11: =G11-H11 -> 127096717 | J11: =IF(AND(G11=0,H11>0),"皆増",IF(AND(G11>0,H11=0),"皆減",IF(AND(G11=0,H11=0),"-",H11/G11))) -> 0.94057497 | K11: 2240575279 | L11: =H11-K11 -> -228897996 | M11: =IF(AND(K11=0,H11>0),"皆増",IF(AND(K11>0,H11=0),"皆減",IF(AND(K11=0,H11=0),"-",H11/K11))) -> 0.89783963 | O11: =N11-H11 -> -2011677283 | P11: =H11/N11 -> #DIV/0! | Q11: 普建 | R11: =IF(OR(G11>0,H11>0,K11>0),"表示（自動）","非表示（自動）") -> 表示（自動） | S11: ↓高資本費対策 R5決算から使うよ
D12: 高資本費対策費負担金 | G12: 0 | H12: 0 | I12: =G12-H12 -> 0 | J12: =IF(AND(G12=0,H12>0),"皆増",IF(AND(G12>0,H12=0),"皆減",IF(AND(G12=0,H12=0),"-",H12/G12))) -> - | K12: 0 | L12: =H12-K12 -> 0 | M12: =IF(AND(K12=0,H12>0),"皆増",IF(AND(K12>0,H12=0),"皆減",IF(AND(K12=0,H12=0),"-",H12/K12))) -> - | O12: =N12-H12 -> 0 | P12: =H12/N12 -> #DIV/0! | Q12: 普建 | R12: =IF(OR(G12>0,H12>0,K12>0),"表示（自動）","非表示（自動）") -> 非表示（自動） | S12: R5決算から使うよ
D13: 水質指導費負担金 | G13: 61778000 | H13: =+'[2]3条収入'!AI14 -> 52443869 | I13: =G13-H13 -> 9334131 | J13: =IF(AND(G13=0,H13>0),"皆増",IF(AND(G13>0,H13=0),"皆減",IF(AND(G13=0,H13=0),"-",H13/G13))) -> 0.84890849 | K13: 51549179 | L13: =H13-K13 -> 894690 | M13: =IF(AND(K13=0,H13>0),"皆増",IF(AND(K13>0,H13=0),"皆減",IF(AND(K13=0,H13=0),"-",H13/K13))) -> 1.017356 | O13: =N13-H13 -> -52443869 | P13: =H13/N13 -> #DIV/0! | Q13: 補助費 | R13: =IF(OR(G13>0,H13>0,K13>0),"表示（自動）","非表示（自動）") -> 表示（自動）
D14: 普及促進費負担金 | G14: 40039000 | H14: =+'[2]3条収入'!AI15 -> 44424775 | I14: =G14-H14 -> -4385775 | J14: =IF(AND(G14=0,H14>0),"皆増",IF(AND(G14>0,H14=0),"皆減",IF(AND(G14=0,H14=0),"-",H14/G14))) -> 1.1095376 | K14: 37494710 | L14: =H14-K14 -> 6930065 | M14: =IF(AND(K14=0,H14>0),"皆増",IF(AND(K14>0,H14=0),"皆減",IF(AND(K14=0,H14=0),"-",H14/K14))) -> 1.1848278 | O14: =N14-H14 -> -44424775 | P14: =H14/N14 -> #DIV/0! | Q14: 補助費 | R14: =IF(OR(G14>0,H14>0,K14>0),"表示（自動）","非表示（自動）") -> 表示（自動）
D15: 貸付事業費負担金 | G15: 14763000 | H15: =+'[2]3条収入'!AI16 -> 10483859 | I15: =G15-H15 -> 4279141 | J15: =IF(AND(G15=0,H15>0),"皆増",IF(AND(G15>0,H15=0),"皆減",IF(AND(G15=0,H15=0),"-",H15/G15))) -> 0.71014421 | K15: 10746426 | L15: =H15-K15 -> -262567 | M15: =IF(AND(K15=0,H15>0),"皆増",IF(AND(K15>0,H15=0),"皆減",IF(AND(K15=0,H15=0),"-",H15/K15))) -> 0.97556704 | O15: =N15-H15 -> -10483859 | P15: =H15/N15 -> #DIV/0! | Q15: 補助費 | R15: =IF(OR(G15>0,H15>0,K15>0),"表示（自動）","非表示（自動）") -> 表示（自動）
B16: 営業外収益 | G16: =G17 -> 0 | H16: =H17 -> 9203253 | I16: =G16-H16 -> -9203253 | J16: =IF(AND(G16=0,H16>0),"皆増",IF(AND(G16>0,H16=0),"皆減",IF(AND(G16=0,H16=0),"-",H16/G16))) -> 皆増 | K16: =K17 -> 31458 | L16: =SUM(L17) -> 9171795 | M16: =IF(AND(K16=0,H16>0),"皆増",IF(AND(K16>0,H16=0),"皆減",IF(AND(K16=0,H16=0),"-",H16/K16))) -> 292.55684 | N16: =N17 -> 0 | O16: =N16-H16 -> -9203253 | P16: =H16/N16 -> #DIV/0! | R16: =IF(OR(G16>0,H16>0,K16>0),"表示（自動）","非表示（自動）") -> 表示（自動）
C17: 一般会計補助金 | G17: =G18+G25 -> 0 | H17: =H18+H25 -> 9203253 | I17: =G17-H17 -> -9203253 | J17: =IF(AND(G17=0,H17>0),"皆増",IF(AND(G17>0,H17=0),"皆減",IF(AND(G17=0,H17=0),"-",H17/G17))) -> 皆増 | K17: =K18+K25 -> 31458 | L17: =SUM(L18,L25) -> 9171795 | M17: =IF(AND(K17=0,H17>0),"皆増",IF(AND(K17>0,H17=0),"皆減",IF(AND(K17=0,H17=0),"-",H17/K17))) -> 292.55684 | N17: =N18 -> 0 | O17: =N17-H17 -> -9203253 | P17: =H17/N17 -> #DIV/0! | R17: =IF(OR(G17>0,H17>0,K17>0),"表示（自動）","非表示（自動）") -> 表示（自動）
D18: 汚水処理補助金 | G18: =SUM(G19:G22) -> 0 | H18: =SUM(H19:H22) -> 4980 | I18: =G18-H18 -> -4980 | J18: =IF(AND(G18=0,H18>0),"皆増",IF(AND(G18>0,H18=0),"皆減",IF(AND(G18=0,H18=0),"-",H18/G18))) -> 皆増 | K18: =SUM(K19:K22) -> 31458 | L18: =SUM(L19:L22) -> -26478 | M18: =IF(AND(K18=0,H18>0),"皆増",IF(AND(K18>0,H18=0),"皆減",IF(AND(K18=0,H18=0),"-",H18/K18))) -> 0.15830631 | N18: =SUM(N19:N22) -> 0 | O18: =N18-H18 -> -4980 | P18: =H18/N18 -> #DIV/0! | R18: =IF(OR(G18>0,H18>0,K18>0),"表示（自動）","非表示（自動）") -> 表示（自動）
E19: 維持管理費分 | G19: 0 | H19: =+'[2]3条収入'!AI44 -> 0 | I19: =G19-H19 -> 0 | J19: =IF(AND(G19=0,H19>0),"皆増",IF(AND(G19>0,H19=0),"皆減",IF(AND(G19=0,H19=0),"-",H19/G19))) -> - | L19: 0 | M19: =IF(AND(K19=0,H19>0),"皆増",IF(AND(K19>0,H19=0),"皆減",IF(AND(K19=0,H19=0),"-",H19/K19))) -> - | N19: 0 | O19: 0 | P19: - | R19: =IF(OR(G19>0,H19>0,K19>0),"表示（自動）","非表示（自動）") -> 非表示（自動）
E20: 減価償却費分 | G20: 0 | H20: =+'[2]3条収入'!AI45 -> 0 | I20: =G20-H20 -> 0 | J20: =IF(AND(G20=0,H20>0),"皆増",IF(AND(G20>0,H20=0),"皆減",IF(AND(G20=0,H20=0),"-",H20/G20))) -> - | K20: 0 | L20: =H20-K20 -> 0 | M20: =IF(AND(K20=0,H20>0),"皆増",IF(AND(K20>0,H20=0),"皆減",IF(AND(K20=0,H20=0),"-",H20/K20))) -> - | O20: =N20-H20 -> 0 | P20: =H20/N20 -> #DIV/0! | Q20: 普建 | R20: =IF(OR(G20>0,H20>0,K20>0),"表示（自動）","非表示（自動）") -> 非表示（自動）
E21: 支払利息分 | G21: 0 | H21: =+'[2]3条収入'!AI46 -> 0 | I21: =G21-H21 -> 0 | J21: =IF(AND(G21=0,H21>0),"皆増",IF(AND(G21>0,H21=0),"皆減",IF(AND(G21=0,H21=0),"-",H21/G21))) -> - | K21: 0 | L21: =H21-K21 -> 0 | M21: =IF(AND(K21=0,H21>0),"皆増",IF(AND(K21>0,H21=0),"皆減",IF(AND(K21=0,H21=0),"-",H21/K21))) -> - | O21: =N21-H21 -> 0 | P21: =H21/N21 -> #DIV/0! | Q21: 普建 | R21: =IF(OR(G21>0,H21>0,K21>0),"表示（自動）","非表示（自動）") -> 非表示（自動）
E22: 下水道使用料減免分 | G22: 0 | H22: =+'[2]3条収入'!AI47 -> 4980 | I22: =G22-H22 -> -4980 | J22: =IF(AND(G22=0,H22>0),"皆増",IF(AND(G22>0,H22=0),"皆減",IF(AND(G22=0,H22=0),"-",H22/G22))) -> 皆増 | K22: 31458 | L22: =H22-K22 -> -26478 | M22: =IF(AND(K22=0,H22>0),"皆増",IF(AND(K22>0,H22=0),"皆減",IF(AND(K22=0,H22=0),"-",H22/K22))) -> 0.15830631 | O22: =N22-H22 -> -4980 | P22: =H22/N22 -> #DIV/0! | Q22: 普建 | R22: =IF(OR(G22>0,H22>0,K22>0),"表示（自動）","非表示（自動）") -> 表示（自動）
F23: 当年度分 | I23: =G23-H23 -> 0 | J23: =IF(AND(G23=0,H23>0),"皆増",IF(AND(G23>0,H23=0),"皆減",IF(AND(G23=0,H23=0),"-",H23/G23))) -> - | L23: =H23-K23 -> 0 | M23: =IF(AND(K23=0,H23>0),"皆増",IF(AND(K23>0,H23=0),"皆減",IF(AND(K23=0,H23=0),"-",H23/K23))) -> - | R23: =IF(OR(G23>0,H23>0,K23>0),"表示（自動）","非表示（自動）") -> 非表示（自動）
F24: 前年度未収分 | G24: 0 | I24: =G24-H24 -> 0 | J24: =IF(AND(G24=0,H24>0),"皆増",IF(AND(G24>0,H24=0),"皆減",IF(AND(G24=0,H24=0),"-",H24/G24))) -> - | K24: 0 | L24: =H24-K24 -> 0 | M24: =IF(AND(K24=0,H24>0),"皆増",IF(AND(K24>0,H24=0),"皆減",IF(AND(K24=0,H24=0),"-",H24/K24))) -> - | R24: =IF(OR(G24>0,H24>0,K24>0),"表示（自動）","非表示（自動）") -> 非表示（自動） | T24: =IF(ISERROR(H24/G24),IF(AND(G24=0,H24=0),"-",IF(G24=0,"皆増",H24/G24)),H24/G24) -> -
D25: その他補助金 | G25: 0 | H25: =+'[2]3条収入'!AI48 -> 9198273 | I25: =G25-H25 -> -9198273 | J25: =IF(AND(G25=0,H25>0),"皆増",IF(AND(G25>0,H25=0),"皆減",IF(AND(G25=0,H25=0),"-",H25/G25))) -> 皆増 | K25: 0 | L25: =H25-K25 -> 9198273 | M25: =IF(AND(K25=0,H25>0),"皆増",IF(AND(K25>0,H25=0),"皆減",IF(AND(K25=0,H25=0),"-",H25/K25))) -> 皆増 | Q25: 補助費 | R25: =IF(OR(G25>0,H25>0,K25>0),"表示（自動）","非表示（自動）") -> 表示（自動）
A26: 資本的収入 | G26: =G27+G30 -> 3640474000 | H26: =H27+H30 -> 3285504551 | I26: =G26-H26 -> 354969449 | J26: =IF(AND(G26=0,H26>0),"皆増",IF(AND(G26>0,H26=0),"皆減",IF(AND(G26=0,H26=0),"-",H26/G26))) -> 0.90249362 | K26: =K27+K30 -> 4465118734 | L26: =H26-K26 -> -1179614183 | M26: =IF(AND(K26=0,H26>0),"皆増",IF(AND(K26>0,H26=0),"皆減",IF(AND(K26=0,H26=0),"-",H26/K26))) -> 0.73581572 | N26: =N27+N30 -> 0 | O26: =N26-H26 -> -3285504551 | P26: =H26/N26 -> #DIV/0! | R26: =IF(OR(G26>0,H26>0,K26>0),"表示（自動）","非表示（自動）") -> 表示（自動）
B27: 一般会計出資金 | G27: =G28 -> 3640474000 | H27: =H28 -> 3285504551 | I27: =G27-H27 -> 354969449 | J27: =IF(AND(G27=0,H27>0),"皆増",IF(AND(G27>0,H27=0),"皆減",IF(AND(G27=0,H27=0),"-",H27/G27))) -> 0.90249362 | K27: =K28 -> 4465118734 | L27: =H27-K27 -> -1179614183 | M27: =IF(AND(K27=0,H27>0),"皆増",IF(AND(K27>0,H27=0),"皆減",IF(AND(K27=0,H27=0),"-",H27/K27))) -> 0.73581572 | N27: =N28 -> 0 | O27: =N27-H27 -> -3285504551 | P27: =H27/N27 -> #DIV/0! | R27: =IF(OR(G27>0,H27>0,K27>0),"表示（自動）","非表示（自動）") -> 表示（自動）
C28: 下水道建設費出資金 | G28: =SUM(G29:G29) -> 3640474000 | H28: =SUM(H29:H29) -> 3285504551 | I28: =SUM(I29:I29) -> 354969449 | J28: =IF(AND(G28=0,H28>0),"皆増",IF(AND(G28>0,H28=0),"皆減",IF(AND(G28=0,H28=0),"-",H28/G28))) -> 0.90249362 | K28: =SUM(K29:K29) -> 4465118734 | L28: =H28-K28 -> -1179614183 | M28: =IF(AND(K28=0,H28>0),"皆増",IF(AND(K28>0,H28=0),"皆減",IF(AND(K28=0,H28=0),"-",H28/K28))) -> 0.73581572 | N28: =N29 -> 0 | O28: =N28-H28 -> -3285504551 | P28: =H28/N28 -> #DIV/0! | R28: =IF(OR(G28>0,H28>0,K28>0),"表示（自動）","非表示（自動）") -> 表示（自動）
D29: 下水道建設費出資金 | G29: 3640474000 | H29: =+'[5]4条収入'!E22 -> 3285504551 | I29: =G29-H29 -> 354969449 | J29: =IF(AND(G29=0,H29>0),"皆増",IF(AND(G29>0,H29=0),"皆減",IF(AND(G29=0,H29=0),"-",H29/G29))) -> 0.90249362 | K29: 4465118734 | L29: =H29-K29 -> -1179614183 | M29: =IF(AND(K29=0,H29>0),"皆増",IF(AND(K29>0,H29=0),"皆減",IF(AND(K29=0,H29=0),"-",H29/K29))) -> 0.73581572 | O29: =N29-H29 -> -3285504551 | P29: =H29/N29 -> #DIV/0! | Q29: 普建 | R29: =IF(OR(G29>0,H29>0,K29>0),"表示（自動）","非表示（自動）") -> 表示（自動）
B30: 水洗化貸付事業収入 | G30: =G31 -> 0 | H30: =H31 -> 0 | I30: =G30-H30 -> 0 | J30: =IF(AND(G30=0,H30>0),"皆増",IF(AND(G30>0,H30=0),"皆減",IF(AND(G30=0,H30=0),"-",H30/G30))) -> - | K30: =K31 -> 0 | L30: =H30-K30 -> 0 | M30: =IF(AND(K30=0,H30>0),"皆増",IF(AND(K30>0,H30=0),"皆減",IF(AND(K30=0,H30=0),"-",H30/K30))) -> - | N30: =N31 -> 0 | O30: =N30-H30 -> 0 | P30: =H30/N30 -> #DIV/0! | R30: =IF(OR(G30>0,H30>0,K30>0),"表示（自動）","非表示（自動）") -> 非表示（自動）
C31: 一般会計借入金 | G31: =SUM(G32:G34) -> 0 | H31: =SUM(H32:H34) -> 0 | I31: =G31-H31 -> 0 | J31: =IF(AND(G31=0,H31>0),"皆増",IF(AND(G31>0,H31=0),"皆減",IF(AND(G31=0,H31=0),"-",H31/G31))) -> - | K31: =SUM(K32:K34) -> 0 | L31: =H31-K31 -> 0 | M31: =IF(AND(K31=0,H31>0),"皆増",IF(AND(K31>0,H31=0),"皆減",IF(AND(K31=0,H31=0),"-",H31/K31))) -> - | N31: =SUM(N32:N34) -> 0 | O31: =N31-H31 -> 0 | P31: =H31/N31 -> #DIV/0! | Q31: 貸付金 | R31: =IF(OR(G31>0,H31>0,K31>0),"表示（自動）","非表示（自動）") -> 非表示（自動）
D32: 水洗便所改造資金 貸付借入金 | G32: 0 | H32: =+'[5]4条収入'!E59 -> 0 | I32: =G32-H32 -> 0 | J32: =IF(AND(G32=0,H32>0),"皆増",IF(AND(G32>0,H32=0),"皆減",IF(AND(G32=0,H32=0),"-",H32/G32))) -> - | K32: 0 | L32: =H32-K32 -> 0 | M32: =IF(AND(K32=0,H32>0),"皆増",IF(AND(K32>0,H32=0),"皆減",IF(AND(K32=0,H32=0),"-",H32/K32))) -> - | O32: =N32-H32 -> 0 | P32: =H32/N32 -> #DIV/0! | R32: =IF(OR(G32>0,H32>0,K32>0),"表示（自動）","非表示（自動）") -> 非表示（自動）
D33: し尿浄化槽廃止資金 貸付借入金 | G33: 0 | H33: =+'[5]4条収入'!E63 -> 0 | I33: =G33-H33 -> 0 | J33: =IF(AND(G33=0,H33>0),"皆増",IF(AND(G33>0,H33=0),"皆減",IF(AND(G33=0,H33=0),"-",H33/G33))) -> - | K33: 0 | L33: =H33-K33 -> 0 | M33: =IF(AND(K33=0,H33>0),"皆増",IF(AND(K33>0,H33=0),"皆減",IF(AND(K33=0,H33=0),"-",H33/K33))) -> - | O33: =N33-H33 -> 0 | P33: =H33/N33 -> #DIV/0! | R33: =IF(OR(G33>0,H33>0,K33>0),"表示（自動）","非表示（自動）") -> 非表示（自動）
D34: 排水設備改修資金 貸付借入金 | G34: 0 | H34: =+'[5]4条収入'!E67 -> 0 | I34: =G34-H34 -> 0 | J34: =IF(AND(G34=0,H34>0),"皆増",IF(AND(G34>0,H34=0),"皆減",IF(AND(G34=0,H34=0),"-",H34/G34))) -> - | K34: 0 | L34: =H34-K34 -> 0 | M34: =IF(AND(K34=0,H34>0),"皆増",IF(AND(K34>0,H34=0),"皆減",IF(AND(K34=0,H34=0),"-",H34/K34))) -> - | O34: =N34-H34 -> 0 | P34: =H34/N34 -> #DIV/0! | R34: =IF(OR(G34>0,H34>0,K34>0),"表示（自動）","非表示（自動）") -> 非表示（自動）
A35: 計 （下水決算分） | G35: =G5+G26 -> 17495336000 | H35: =H5+H26 -> 17481810139 | I35: =G35-H35 -> 13525861 | J35: =IF(AND(G35=0,H35>0),"皆増",IF(AND(G35>0,H35=0),"皆減",IF(AND(G35=0,H35=0),"-",H35/G35))) -> 0.99922689 | K35: =K5+K26 -> 18458499686 | L35: =H35-K35 -> -976689547 | M35: =IF(AND(K35=0,H35>0),"皆増",IF(AND(K35>0,H35=0),"皆減",IF(AND(K35=0,H35=0),"-",H35/K35))) -> 0.94708727 | N35: =N5+N26 -> 0 | O35: =N35-H35 -> -17481810139 | P35: =H35/N35 -> #DIV/0! | R35: =IF(OR(G35>0,H35>0,K35>0),"表示（自動）","非表示（自動）") -> 表示（自動）
A36: 前受金 （災害復旧等繰越財源分） | G36: 0 | H36: ='(繰)繰入金'!H35 -> 0 | I36: =G36-H36 -> 0 | J36: - | K36: 0 | L36: =H36-K36 -> 0 | M36: =IF(AND(K36=0,H36>0),"皆増",IF(AND(K36>0,H36=0),"皆減",IF(AND(K36=0,H36=0),"-",H36/K36))) -> - | N36: =N8+N29 -> 0 | O36: =N36-H36 -> 0 | P36: =H36/N36 -> #DIV/0! | Q36: 補助費 | R36: =IF(OR(G36>0,H36>0,K36>0),"表示（自動）","非表示（自動）") -> 非表示（自動）
A37: 計 | G37: =G35+G36 -> 17495336000 | H37: =H35+H36 -> 17481810139 | I37: =G37-H37 -> 13525861 | J37: =IF(AND(G37=0,H37>0),"皆増",IF(AND(G37>0,H37=0),"皆減",IF(AND(G37=0,H37=0),"-",H37/G37))) -> 0.99922689 | K37: =K35+K36 -> 18458499686 | L37: =H37-K37 -> -976689547 | M37: =IF(AND(K37=0,H37>0),"皆増",IF(AND(K37>0,H37=0),"皆減",IF(AND(K37=0,H37=0),"-",H37/K37))) -> 0.94708727 | N37: =N11+N32 -> 0 | O37: =N37-H37 -> -17481810139 | P37: =H37/N37 -> #DIV/0! | R37: =IF(OR(G37>0,H37>0,K37>0),"表示（自動）","非表示（自動）") -> 表示（自動）
A38: 前年度下水道建設費出資金未収金 | G38: 0 | H38: 0 | I38: =G38-H38 -> 0 | J38: - | K38: 0 | L38: =H38-K38 -> 0 | M38: =IF(AND(K38=0,H38>0),"皆増",IF(AND(K38>0,H38=0),"皆減",IF(AND(K38=0,H38=0),"-",H38/K38))) -> - | R38: =IF(OR(G38>0,H38>0,K38>0),"表示（自動）","非表示（自動）") -> 非表示（自動）
A39: 合 計 | G39: =G37+G38 -> 17495336000 | H39: =H37+H38 -> 17481810139 | I39: =I37+I38 -> 13525861 | J39: =IF(AND(G39=0,H39>0),"皆増",IF(AND(G39>0,H39=0),"皆減",IF(AND(G39=0,H39=0),"-",H39/G39))) -> 0.99922689 | K39: =K37+K38 -> 18458499686 | L39: =H39-K39 -> -976689547 | M39: =IF(AND(K39=0,H39>0),"皆増",IF(AND(K39>0,H39=0),"皆減",IF(AND(K39=0,H39=0),"-",H39/K39))) -> 0.94708727 | R39: =IF(OR(G39>0,H39>0,K39>0),"表示（自動）","非表示（自動）") -> 表示（自動）
R40: 表示（強制）
E41: 区 分 | G41: 議決予算額 | H41: 決算額(b) | I41: 予算との比較 | K41: 前年度決算額 | L41: 前年度決算額との比較 | R41: 非表示（強制）
G42: 【下水会計分】 | I42: 差引き(a-b) | J42: 対予算 比 | K42: （Ｃ） | L42: 差引き(ｂ-ｃ) | M42: 対前年 度比 | R42: 非表示（強制）
E43: 普建 | G43: =SUMIF($Q$5:$Q$34,$E$43,G5:G34) -> 13691958000 | H43: =SUMIF($Q$5:$Q$34,$E$43,H5:H34) -> 13773736465 | I43: =G43-H43 -> -81778465 | J43: =IF(AND(G43=0,H43>0),"皆増",IF(AND(G43>0,H43=0),"皆減",IF(AND(G43=0,H43=0),"-",H43/G43))) -> 1.0059727 | K43: 15039248209 | L43: =H43-K43 -> -1265511744 | M43: =IF(AND(K43=0,H43>0),"皆増",IF(AND(K43>0,H43=0),"皆減",IF(AND(K43=0,H43=0),"-",H43/K43))) -> 0.91585273 | R43: 表示（強制）
E44: 補助費 | G44: =SUMIF($Q$5:$Q$31,$E$44,G5:G31) -> 3803378000 | H44: =SUMIF($Q$5:$Q$36,$E$44,H5:H36) -> 3708073674 | I44: =G44-H44 -> 95304326 | J44: =IF(AND(G44=0,H44>0),"皆増",IF(AND(G44>0,H44=0),"皆減",IF(AND(G44=0,H44=0),"-",H44/G44))) -> 0.97494219 | K44: 3419251477 | L44: =H44-K44 -> 288822197 | M44: =IF(AND(K44=0,H44>0),"皆増",IF(AND(K44>0,H44=0),"皆減",IF(AND(K44=0,H44=0),"-",H44/K44))) -> 1.0844694 | R44: 表示（強制）
E45: 貸付金 | G45: =G31 -> 0 | H45: =H31 -> 0 | I45: =G45-H45 -> 0 | J45: =IF(AND(G45=0,H45>0),"皆増",IF(AND(G45>0,H45=0),"皆減",IF(AND(G45=0,H45=0),"-",H45/G45))) -> - | K45: 0 | L45: =H45-K45 -> 0 | M45: =IF(AND(K45=0,H45>0),"皆増",IF(AND(K45>0,H45=0),"皆減",IF(AND(K45=0,H45=0),"-",H45/K45))) -> - | R45: 表示（強制）
E46: 計 | G46: =SUM(G43:G45) -> 17495336000 | H46: =SUM(H43:H45) -> 17481810139 | I46: =G46-H46 -> 13525861 | J46: =IF(AND(G46=0,H46>0),"皆増",IF(AND(G46>0,H46=0),"皆減",IF(AND(G46=0,H46=0),"-",H46/G46))) -> 0.99922689 | K46: =SUM(K43:K45) -> 18458499686 | L46: =H46-K46 -> -976689547 | M46: =IF(AND(K46=0,H46>0),"皆増",IF(AND(K46>0,H46=0),"皆減",IF(AND(K46=0,H46=0),"-",H46/K46))) -> 0.94708727 | R46: 表示（強制）
E47: チェック | G47: =G35-G46 -> 0 | H47: =H37-H46 -> 0 | K47: =K37-K46 -> 0

Sheet (繰)3条収入
C1: =+CONCATENATE(LEFT('[1]3条支出'!$D$1,5)," 収益的収入（決算）") -> 令和５年度 収益的収入（決算） | H1: （単位：円）
A2: 科 目 | D2: 予算額（繰越+現年） | E2: 流用・振替等 | F2: 現計予算額 | G2: 税込決算額 | H2: 税抜決算額
D3: （補正後） Ａ | E3: 増減額 Ｂ | F3: Ｃ（Ａ＋Ｂ） | G3: Ｄ | H3: （消費税雑収益加算後）
A4: 下水道事業収益 | D4: =D5+D10+D19 -> 44975817000 | E4: =E5+E10+E19 -> 0 | F4: =D4+E4 -> 44975817000 | G4: =G5+G10+G19 -> 44454711283 | H4: =H5+H10+H19 -> 42572042134
B5: 営業収益 | D5: =+SUM(D6:D9) -> 35444153000 | E5: =+SUM(E6:E9) -> 0 | F5: =+SUM(F6:F9) -> 35444153000 | G5: =+SUM(G6:G9) -> 34865911732 | H5: =+SUM(H6:H9) -> 32986083408
C6: 下水道使用料 | D6: 21384728000 | F6: =D6+E6 -> 21384728000 | G6: =+'[2]3条収入'!$E$8 -> 20488962528 | H6: =+'[2]3条収入'!$AI$8 -> 18626337467
C7: 一般会計負担金 | D7: 13854862000 | F7: =D7+E7 -> 13854862000 | G7: =+'[2]3条収入'!$E$9 -> 14187102335 | H7: =+'[2]3条収入'!$AI$9 -> 14187102335
C8: 受託工事収益 | F8: =D8+E8 -> 0 | G8: =+'[2]3条収入'!$E$18 -> 0 | H8: =+'[2]3条収入'!$AI$18 -> 0
C9: その他営業収益 | D9: 204563000 | F9: =D9+E9 -> 204563000 | G9: =+'[2]3条収入'!$E$19 -> 189846869 | H9: =+'[2]3条収入'!$AI$19 -> 172643606
B10: 営業外収益 | D10: =+SUM(D11:D18) -> 9528788000 | E10: =+SUM(E11:E18) -> 0 | F10: =+SUM(F11:F18) -> 9528788000 | G10: =+SUM(G11:G18) -> 9584600552 | H10: =+SUM(H11:H18) -> 9581905615
C11: 受取利息 | D11: 70000 | F11: =D11+E11 -> 70000 | G11: =+'[2]3条収入'!$E$28 -> 88770 | H11: =+'[2]3条収入'!$AI$28 -> 88770
C12: 国庫補助金 | F12: =D12+E12 -> 0 | G12: =+'[2]3条収入'!$E$32 -> 0 | H12: =+'[2]3条収入'!$AI$32 -> 0
C13: 県補助金 | F13: =D13+E13 -> 0
C14: 負担金 | D14: 49683000 | F14: =D14+E14 -> 49683000 | G14: =+'[2]3条収入'!$E$39 -> 53493193 | H14: =+'[2]3条収入'!$AI$39 -> 50128048
C15: 一般会計補助金 | F15: =D15+E15 -> 0 | G15: =+'[2]3条収入'!$E$42 -> 9203253 | H15: =+'[2]3条収入'!$AI$42 -> 9203253
C16: 消費税等還付金 | D16: 0 | E16: 0 | F16: =D16+E16 -> 0 | G16: =+'[2]3条収入'!$E$49 -> 0 | H16: =+'[2]3条収入'!$AI$49 -> 0
C17: 雑収益 | D17: 23945000 | F17: =D17+E17 -> 23945000 | G17: =+'[2]3条収入'!$E$51 -> 36460334 | H17: =+'[2]3条収入'!$AI$51 -> 37130542
C18: 長期前受金戻入（償却・除却） | D18: 9455090000 | F18: =D18+E18 -> 9455090000 | G18: =+'[2]3条収入'!$E$55 -> 9485355002 | H18: =+'[2]3条収入'!$AI$55 -> 9485355002
B19: 特別利益 | D19: =+SUM(D20:D23) -> 2876000 | E19: =+SUM(E20:E23) -> 0 | F19: =+SUM(F20:F23) -> 2876000 | G19: =+SUM(G20:G23) -> 4198999 | H19: =+SUM(H20:H23) -> 4053111
C20: 長期前受金戻入益（減損） | D20: 0 | F20: =D20+E20 -> 0 | G20: =+'[2]3条収入'!$E$66 -> 0 | H20: =+'[2]3条収入'!$AI$66 -> 0
C21: 固定資産売却益 | D21: 0 | F21: =D21+E21 -> 0 | G21: =+'[2]3条収入'!$E$58 -> 0 | H21: =+'[2]3条収入'!$AI$58 -> 0
C22: 過年度損益修正益 | D22: 2876000 | F22: =D22+E22 -> 2876000 | G22: =+'[2]3条収入'!$E$60 -> 2769570 | H22: =+'[2]3条収入'!$AI$60 -> 2623682
C23: その他特別利益 | D23: 0 | F23: =D23+E23 -> 0 | G23: =+'[2]3条収入'!$E$62 -> 1429429 | H23: =+'[2]3条収入'!$AI$62 -> 1429429
F26: 純利益 | G26: =+G4-'(繰)3条支出 '!G4+[3]消費税!AF113 -> 1811041626 | H26: =+H4-'(繰)3条支出 '!I4 -> 543907199
F27: 繰入金を除いた額→ | G27: =G4-G7-G15 -> 30258405695 | H27: =H4-H7-H15 -> 28375736546
H29: =+'[2]3条収入'!AI74 -> 543907199
H30: =+H26-H29 -> 0

Sheet (繰)3条支出 
C1: =+CONCATENATE(LEFT('[1]3条支出'!$D$1,5)," 収益的支出（決算）") -> 令和５年度 収益的支出（決算） | I1: （単位：円）
A2: 科 目 | D2: 予算額（繰越+現年） | E2: 流用・振替等 | F2: 現計予算額 | G2: 税込決算額 | H2: 税抜決算額 | I2: 税抜決算額
D3: （補正後） Ａ | E3: 増減額 Ｂ | F3: Ｃ（Ａ＋Ｂ） | G3: Ｄ | H3: 控除不可消費税加算前 | I3: 控除不可消費税加算後
A4: 下水道事業費用 | D4: =D5+D20+D24+D29 -> 43953299000 | E4: =E5+E20+E24+E29 -> 0 | F4: =F5+F20+F24+F29 -> 43953299000 | G4: =G5+G20+G24+G29 -> 42643669657 | H4: =H5+H20+H24+H29 -> 41815647458 | I4: =I5+I20+I24+I29 -> 42028134935
B5: 営業費用 | D5: =+SUM(D6:D19) -> 39325285000 | E5: =+SUM(E6:E19) -> 0 | F5: =+SUM(F6:F19) -> 39325285000 | G5: =+SUM(G6:G19) -> 38667489041 | H5: =+SUM(H6:H19) -> 37846544540 | I5: =+SUM(I6:I19) -> 37846544540
C6: 管きょ費 | D6: 649416000 | E6: 0 | F6: =D6+E6 -> 649416000 | G6: =+'[1]3条支出'!$E$6 -> 611819957 | H6: =+'[1]3条支出'!$T$6 -> 564664608 | I6: =+'[1]3条支出'!$T$6 -> 564664608
C7: 水質指導費 | D7: 61778000 | E7: 0 | F7: =D7+E7 -> 61778000 | G7: =+'[1]3条支出'!$E$7 -> 52443869 | H7: =+'[1]3条支出'!$T$7 -> 51313295 | I7: =+'[1]3条支出'!$T$7 -> 51313295
C8: ポンプ場費 | D8: 2446053000 | E8: -14060287 | F8: =D8+E8 -> 2431992713 | G8: =+'[1]3条支出'!$E$8 -> 2356040225 | H8: =+'[1]3条支出'!$T$8 -> 2251657967 | I8: =+'[1]3条支出'!$T$8 -> 2251657967
C9: 処理場費 | D9: 7107004000 | E9: 1992633 | F9: =D9+E9 -> 7108996633 | G9: =+'[1]3条支出'!$E$9 -> 6557703864 | H9: =+'[1]3条支出'!$T$9 -> 6037810078 | I9: =+'[1]3条支出'!$T$9 -> 6037810078
C10: 普及促進費 | D10: 80070000 | E10: 12067654 | F10: =D10+E10 -> 92137654 | G10: =+'[1]3条支出'!$E$11 -> 88849549 | H10: =+'[1]3条支出'!$T$11 -> 87134052 | I10: =+'[1]3条支出'!$T$11 -> 87134052
C11: 水洗化貸付事業費 | D11: 14763000 | E11: 0 | F11: =D11+E11 -> 14763000 | G11: =+'[1]3条支出'!$E$12 -> 10483859 | H11: =+'[1]3条支出'!$T$12 -> 10396270 | I11: =+'[1]3条支出'!$T$12 -> 10396270
C12: 業務費 | D12: 1032244000 | E12: 0 | F12: =D12+E12 -> 1032244000 | G12: =+'[1]3条支出'!$E$13 -> 1019945143 | H12: =+'[1]3条支出'!$T$13 -> 929691714 | I12: =+'[1]3条支出'!$T$13 -> 929691714
C13: 総係費 | D13: 552278000 | E13: 0 | F13: =D13+E13 -> 552278000 | G13: =+'[1]3条支出'!$E$14 -> 483965214 | H13: =+'[1]3条支出'!$T$14 -> 466286409 | I13: =+'[1]3条支出'!$T$14 -> 466286409
C14: 特環公共下水道費 | D14: =108656000+623000 -> 109279000 | E14: 1800000 | F14: =D14+E14 -> 111079000 | G14: =+'[1]3条支出'!$E$15 -> 106990906 | H14: =+'[1]3条支出'!$T$15 -> 97276922 | I14: =+'[1]3条支出'!$T$15 -> 97276922
C15: 農業集落排水費 | D15: =257093000+4311000 -> 261404000 | E15: -1800000 | F15: =D15+E15 -> 259604000 | G15: =+'[1]3条支出'!$E$16 -> 247654024 | H15: =+'[1]3条支出'!$T$16 -> 225167795 | I15: =+'[1]3条支出'!$T$16 -> 225167795
C16: 浄化槽費 | D16: 78829000 | E16: 0 | F16: =D16+E16 -> 78829000 | G16: =+'[1]3条支出'!$E$17 -> 76388330 | H16: =+'[1]3条支出'!$T$17 -> 69941329 | I16: =+'[1]3条支出'!$T$17 -> 69941329
C17: 災害復旧費 | D17: 0 | E17: 0 | F17: =D17+E17 -> 0 | G17: =+'[1]3条支出'!$E$18 -> 0 | H17: =+'[1]3条支出'!$T$18 -> 0 | I17: =+'[1]3条支出'!$T$18 -> 0
C18: 減価償却費 | D18: 26580629000 | E18: 0 | F18: =D18+E18 -> 26580629000 | G18: =+'[1]3条支出'!$E$19 -> 26551442230 | H18: =+'[1]3条支出'!$T$19 -> 26551442230 | I18: =+'[1]3条支出'!$T$19 -> 26551442230
C19: 資産減耗費 | D19: 351538000 | E19: 0 | F19: =D19+E19 -> 351538000 | G19: =+'[1]3条支出'!$E$20 -> 503761871 | H19: =+'[1]3条支出'!$T$20 -> 503761871 | I19: =+'[1]3条支出'!$T$20 -> 503761871
B20: 営業外費用 | D20: =+SUM(D21:D23) -> 4599725000 | E20: =+SUM(E21:E23) -> 9198273 | F20: =+SUM(F21:F23) -> 4608923273 | G20: =+SUM(G21:G23) -> 3955185318 | H20: =+SUM(H21:H23) -> 3949076064 | I20: =+SUM(I21:I23) -> 4161563541
C21: 支払利息及び 企業債取扱諸費 | D21: 4207550000 | E21: -25896 | F21: =D21+E21 -> 4207524104 | G21: =+'[1]3条支出'!$E$23 -> 3945961149 | H21: =+'[1]3条支出'!$T$23 -> 3940341717 | I21: =+'[1]3条支出'!$T$23 -> 3940341717
C22: 消費税 | D22: 392158000 | E22: 0 | F22: =D22+E22 -> 392158000 | G22: =+[3]消費税!Z113+[3]消費税!AF113 -> 0
C23: 雑支出 | D23: 17000 | E23: 9224169 | F23: =D23+E23 -> 9241169 | G23: =+'[1]3条支出'!$E$24 -> 9224169 | H23: =+'[1]3条支出'!$T$24 -> 8734347 | I23: =+'[1]3条支出'!$T$24++'[1]3条支出'!$T$25 -> 221221824
B24: 特別損失 | D24: =+SUM(D25:D28) -> 8289000 | E24: =+SUM(E25:E28) -> 0 | F24: =+SUM(F25:F28) -> 8289000 | G24: =+SUM(G25:G28) -> 20995298 | H24: =+SUM(H25:H28) -> 20026854 | I24: =+SUM(I25:I28) -> 20026854
C25: 固定資産売却損 | D25: 0 | E25: 0 | F25: =D25+E25 -> 0 | G25: =+'[1]3条支出'!$E$30 -> 10315355 | H25: =+'[1]3条支出'!$T$30 -> 10315355 | I25: =+'[1]3条支出'!$T$30 -> 10315355
C26: 過年度損益修正損 | D26: 8248000 | E26: 0 | F26: =D26+E26 -> 8248000 | G26: =+'[1]3条支出'!$E$28 -> 10679943 | H26: =+'[1]3条支出'!$T$28 -> 9711499 | I26: =+'[1]3条支出'!$T$28 -> 9711499
C27: その他特別損失 | D27: 41000 | E27: 0 | F27: =D27+E27 -> 41000 | G27: =+'[1]3条支出'!$E$29 -> 0 | H27: =+'[1]3条支出'!$T$29 -> 0 | I27: =+'[1]3条支出'!$T$29 -> 0
C28: 減損損失 | D28: 0 | E28: 0 | F28: =D28+E28 -> 0 | G28: =+'[1]3条支出'!$E$31 -> 0 | H28: =+'[1]3条支出'!$T$31 -> 0 | I28: =+'[1]3条支出'!$T$31 -> 0
B29: 予備費 | D29: =D30 -> 20000000 | E29: =E30 -> -9198273 | F29: =F30 -> 10801727 | G29: =G30 -> 0 | H29: =H30 -> 0 | I29: =I30 -> 0
C30: 予備費 | D30: 20000000 | E30: -9198273 | F30: =D30+E30 -> 10801727 | G30: 0 | H30: 0 | I30: 0
E50: 、

Sheet (繰)4条収入
C1: =+CONCATENATE(LEFT('[1]3条支出'!$D$1,5)," 資本的収入（決算）") -> 令和５年度 資本的収入（決算）
A2: =+CONCATENATE("（",MID([4]雨汚水!D1,3,1),"年度現年度分みなしベース）") -> （５年度現年度分みなしベース） | M2: （単位：円） | O2: （単位：円）
A3: 科 目 | D3: 議決予算額 （補正後） | E3: 流用・振替等 増減額 | F3: 現計予算額 | G3: 決算額（電算） | H3: 前年度充当額（未発行債） | I3: 当年度決算額 | J3: 前年度繰越 充当財源 | K3: 当年度決算 未充当額 | L3: 翌年度繰越 充当財源 | M3: みなし決算額 | N3: 翌年度繰越 充当額 | O3: 差 引
D4: Ａ | E4: Ｂ | F4: Ｃ（Ａ＋Ｂ） | G4: Ｄ | H4: E | I4: F(D-E) | J4: Ｇ | K4: Ｈ | L4: Ｉ | M4: Ｊ(F-G+H＋Ｉ) | N4: K | O4: J－Ｃ
A5: 資本的収入 | D5: =SUM(D6,D13,D16,D20,D22,D26,D30,D32) -> 42627050000 | E5: =SUM(E6,E13,E16,E20,E22,E26,E30,E32) -> 0 | F5: =SUM(F6,F13,F16,F20,F22,F26,F30,F32) -> 42627050000 | G5: =SUM(G6,G13,G16,G20,G22,G26,G30,G32) -> 42025205141 | H5: =SUM(H6,H13,H16,H20,H22,H26,H30,H32) -> 0 | I5: =SUM(I6,I13,I16,I20,I22,I26,I30,I32) -> 42025205141 | J5: =SUM(J6,J13,J16,J20,J22,J26,J30,J32) -> 8421400000 | K5: =SUM(K6,K13,K16,K20,K22,K26,K30,K32) -> 0 | ... O5: =SUM(O6,O13,O16,O20,O22,O26,O30,O32) -> -411506598
B6: 企業債 | D6: =SUM(D7:D12) -> 32505200000 | E6: =SUM(E7:E12) -> 0 | F6: =SUM(F7:F12) -> 32505200000 | G6: =SUM(G7:G12) -> 32373300000 | H6: =SUM(H7:H12) -> 0 | I6: =SUM(I7:I12) -> 32373300000 | J6: =SUM(J7:J12) -> 5247400000 | K6: =SUM(K7:K12) -> 0 | ... O6: =SUM(O7:O12) -> -152500000
C7: 公共下水道事業債 | D7: =8330600000+654200000 -> 8984800000 | E7: 0 | F7: =D7+E7 -> 8984800000 | G7: =+'[5]4条収入'!$E$9 -> 8822500000 | H7: 0 | I7: =G7-H7 -> 8822500000 | J7: 4973100000 | L7: 5135400000 | M7: =I7-J7+K7+L7 -> 8984800000 | N7: =L7 -> 5135400000 | O7: =M7-F7 -> 0
C8: 市街化区域外汚水処理施設事業債 | D8: 310500000 | E8: 0 | F8: =D8+E8 -> 310500000 | G8: =+'[5]4条収入'!$E$12 -> 493400000 | H8: 0 | I8: =G8-H8 -> 493400000 | J8: 274300000 | L8: 91400000 | M8: =I8-J8+K8+L8 -> 310500000 | N8: =L8 -> 91400000 | O8: =F8-M8 -> 0
C9: 流域下水道事業債 | D9: 160100000 | E9: 0 | F9: =D9+E9 -> 160100000 | G9: =+'[5]4条収入'!$E$13 -> 120200000 | H9: 0 | I9: =G9-H9 -> 120200000 | M9: =I9-J9+K9+L9 -> 120200000 | N9: =L9 -> 0 | O9: =M9-F9 -> -39900000
C10: 資本費平準化債 | D10: 6039000000 | E10: 0 | F10: =D10+E10 -> 6039000000 | G10: =+'[5]4条収入'!$E$14 -> 5929500000 | H10: 0 | I10: =G10-H10 -> 5929500000 | M10: =I10-J10+K10+L10 -> 5929500000 | N10: =L10 -> 0 | O10: =M10-F10 -> -109500000
C11: 災害復旧事業債 | D11: 0 | E11: 0 | F11: =D11+E11 -> 0 | G11: =+'[5]4条収入'!$E$15 -> 0 | H11: 0 | I11: =G11-H11 -> 0 | M11: =I11-J11+K11+L11 -> 0 | N11: =L11 -> 0 | O11: =M11-F11 -> 0
C12: その他事業債（借換債等） | D12: =17007700000+3100000 -> 17010800000 | E12: 0 | F12: =D12+E12 -> 17010800000 | G12: =+'[5]4条収入'!$E$16 -> 17007700000 | H12: 0 | I12: =G12-H12 -> 17007700000 | M12: =I12-J12+K12+L12 -> 17007700000 | N12: =L12 -> 0 | O12: =M12-F12 -> -3100000
B13: 一般会計出資金 | D13: =SUM(D14:D15) -> 3640474000 | E13: =SUM(E14:E15) -> 0 | F13: =SUM(F14:F15) -> 3640474000 | G13: =SUM(G14:G15) -> 3285504551 | H13: =SUM(H14:H15) -> 0 | I13: =SUM(I14:I15) -> 3285504551 | J13: =SUM(J14:J15) -> 0 | K13: =SUM(K14:K15) -> 0 | ... O13: =SUM(O14:O15) -> -354969449
C14: 下水道建設費出資金 | D14: 3640474000 | F14: =D14+E14 -> 3640474000 | G14: =+'[5]4条収入'!E22 -> 3285504551 | H14: 0 | I14: =G14-H14 -> 3285504551 | J14: 0 | M14: =I14-J14+K14+L14 -> 3285504551 | N14: =L14 -> 0 | O14: =M14-F14 -> -354969449
C15: その他出資金 | D15: 0 | E15: 0 | F15: =D15+E15 -> 0 | G15: 0 | H15: 0 | I15: =G15-H15 -> 0 | J15: 0 | M15: =I15-J15+K15+L15 -> 0 | N15: =L15 -> 0 | O15: =F15-M15 -> 0
B16: 国庫補助金 | D16: =SUM(D17:D19) -> 5769500000 | E16: =SUM(E17:E19) -> 0 | F16: =SUM(F17:F19) -> 5769500000 | G16: =SUM(G17:G19) -> 5717788000 | H16: =SUM(H17:H19) -> 0 | I16: =SUM(I17:I19) -> 5717788000 | J16: =SUM(J17:J19) -> 3174000000 | K16: =SUM(K17:K19) -> 0 | ... O16: =SUM(O17:O19) -> -30773739
C17: 公共下水道整備国庫補助金 | D17: =5097000000+665800000 -> 5762800000 | E17: 0 | F17: =D17+E17 -> 5762800000 | G17: =+'[5]4条収入'!$E$25 -> 5683800000 | H17: 0 | I17: =G17-H17 -> 5683800000 | J17: 3156100000 | L17: 3218100000 | M17: =I17-J17+K17+L17 -> 5745800000 | N17: =L17 -> 3218100000 | O17: =M17-F17 -> -17000000
C18: その他国庫補助金 | D18: 2000000 | E18: 0 | F18: =D18+E18 -> 2000000 | G18: =+'[5]4条収入'!$E$26 -> 0 | H18: 0 | I18: =G18-H18 -> 0 | M18: =I18-J18+K18+L18 -> 0 | N18: =L18 -> 0 | O18: =F18-M18 -> 2000000
C19: 汚水処理施設整備交付金 | D19: 4700000 | E19: 0 | F19: =D19+E19 -> 4700000 | G19: =+'[5]4条収入'!$E$31 -> 33988000 | H19: 0 | I19: =G19-H19 -> 33988000 | J19: 17900000 | L19: =2400000+1985739 -> 4385739 | M19: =I19-J19+K19+L19 -> 20473739 | N19: =L19 -> 4385739 | O19: =F19-M19 -> -15773739
B20: 工事受託金 | D20: =D21 -> 54236000 | E20: =E21 -> 0 | F20: =F21 -> 54236000 | G20: =G21 -> 24373083 | H20: =H21 -> 0 | I20: =I21 -> 24373083 | J20: =J21 -> 0 | K20: =K21 -> 0 | ... O20: =O21 -> -29862917
C21: 工事受託金 | D21: 54236000 | E21: 0 | F21: =D21+E21 -> 54236000 | G21: =+'[5]4条収入'!$E$37 -> 24373083 | H21: 0 | I21: =G21-H21 -> 24373083 | K21: 0 | L21: 0 | M21: =I21-J21+K21+L21 -> 24373083 | N21: =L21 -> 0 | O21: =M21-F21 -> -29862917
B22: 負担金 | D22: =SUM(D23:D25) -> 632996000 | E22: =SUM(E23:E25) -> 0 | F22: =SUM(F23:F25) -> 632996000 | G22: =SUM(G23:G25) -> 574304394 | H22: =SUM(H23:H25) -> 0 | I22: =SUM(I23:I25) -> 574304394 | J22: =SUM(J23:J25) -> 0 | K22: =SUM(K23:K25) -> 0 | ... O22: =SUM(O23:O25) -> 131308394
C23: 受益者負担金 | D23: 14208000 | E23: 0 | F23: =D23+E23 -> 14208000 | G23: =+'[5]4条収入'!$E$43 -> 8799605 | H23: 0 | I23: =G23-H23 -> 8799605 | K23: 0 | L23: 0 | M23: =I23-J23+K23+L23 -> 8799605 | N23: =L23 -> 0 | O23: =M23-F23 -> -5408395
C24: 受益者分担金 | D24: 40980000 | E24: 0 | F24: =D24+E24 -> 40980000 | G24: =+'[5]4条収入'!$E$45 -> 35218280 | H24: 0 | I24: =G24-H24 -> 35218280 | K24: 0 | M24: =I24-J24+K24+L24 -> 35218280 | N24: =L24 -> 0 | O24: =M24-F24 -> -5761720
C25: 工事負担金 | D25: 577808000 | E25: 0 | F25: =D25+E25 -> 577808000 | G25: =+'[5]4条収入'!$E$50 -> 530286509 | H25: 0 | I25: =G25-H25 -> 530286509 | L25: =60000000+130000000 -> 190000000 | M25: =I25-J25+K25+L25 -> 720286509 | N25: =L25 -> 190000000 | O25: =M25-F25 -> 142478509
B26: 水洗化貸付事業収入 | D26: =SUM(D27:D29) -> 9913000 | E26: =SUM(E27:E29) -> 0 | F26: =SUM(F27:F29) -> 9913000 | G26: =SUM(G27:G29) -> 3987000 | H26: =SUM(H27:H29) -> 0 | I26: =SUM(I27:I29) -> 3987000 | J26: =SUM(J27:J29) -> 0 | K26: =SUM(K27:K29) -> 0 | M26: =SUM(M27:M29) -> 3987000 | N26: =SUM(N27:N29) -> 0 | O26: =SUM(O27:O29) -> -5926000
C27: 貸付企業債 | D27: 0 | E27: 0 | F27: =D27+E27 -> 0 | G27: =+'[5]4条収入'!$E$56 -> 0 | H27: 0 | I27: =G27-H27 -> 0 | K27: 0 | L27: 0 | M27: =I27-J27+K27+L27 -> 0 | N27: =L27 -> 0 | O27: =M27-F27 -> 0
C28: 一般会計借入金 | D28: 0 | E28: 0 | F28: =D28+E28 -> 0 | G28: =+'[5]4条収入'!$E$58 -> 0 | H28: 0 | I28: =G28-H28 -> 0 | K28: 0 | L28: 0 | M28: =I28-J28-K28-L28 -> 0 | N28: =L28 -> 0 | O28: =F28-M28 -> 0
C29: 貸付金回収金 | D29: 9913000 | E29: 0 | F29: =D29+E29 -> 9913000 | G29: =+'[5]4条収入'!$E$71 -> 3987000 | H29: 0 | I29: =G29-H29 -> 3987000 | K29: 0 | L29: 0 | M29: =I29-J29+K29+L29 -> 3987000 | N29: =L29 -> 0 | O29: =M29-F29 -> -5926000
B30: 固定資産売却代金 | D30: =D31 -> 14731000 | E30: =E31 -> 0 | F30: =F31 -> 14731000 | G30: =G31 -> 45948113 | H30: =H31 -> 0 | I30: =I31 -> 45948113 | J30: =J31 -> 0 | K30: =K31 -> 0 | ... O30: =O31 -> 31217113
C31: 土地売却代金 | D31: 14731000 | E31: 0 | F31: =D31+E31 -> 14731000 | G31: =+'[5]4条収入'!$E$87 -> 45948113 | H31: 0 | I31: =G31-H31 -> 45948113 | J31: 0 | K31: 0 | L31: 0 | M31: =I31-J31+K31+L31 -> 45948113 | N31: =L31 -> 0 | O31: =M31-F31 -> 31217113
B32: その他資本的収入 | D32: =D33 -> 0 | E32: =E33 -> 0 | F32: =F33 -> 0 | G32: =G33 -> 0 | H32: =H33 -> 0 | I32: =I33 -> 0 | J32: =J33 -> 0 | K32: =K33 -> 0 | ... O32: =O33 -> 0
C33: その他資本的収入 | D33: 0 | E33: 0 | F33: =D33+E33 -> 0 | G33: =+'[5]4条収入'!$E$89 -> 0 | H33: 0 | I33: =G33-H33 -> 0 | J33: 0 | K33: 0 | L33: 0 | M33: =I33-J33+K33+L33 -> 0 | N33: =L33 -> 0 | O33: =M33-F33 -> 0
B35: ＊ | C35: 資本的収入合計 | F35: ＝ | G35: =G5-G13 -> 38739700590 | K35: （収入決算額）
M43: =M5-M13 -> 38957586329

Sheet (繰)4条支出 
C1: =+CONCATENATE(LEFT('[1]3条支出'!$D$1,5)," 資本的支出（決算）") -> 令和５年度 資本的支出（決算）
A2: =+CONCATENATE("（",MID([4]雨汚水!D1,3,1),"年度現年度分みなしベース）") -> （５年度現年度分みなしベース） | K2: （単位：円）
A3: 科 目 | D3: 議決予算額 （補正後） | E3: 流用・振替等 増減額 | F3: 現計予算額 | G3: 決算額（電算） | H3: 4-5繰越 決算額 | I3: 5現年度分 決算額 | J3: 翌年度繰越額 | K3: みなし決算額 | L3: 不用額
D4: Ａ | E4: Ｂ | F4: Ｃ（Ａ＋Ｂ） | G4: Ｄ | H4: Ｅ | I4: Ｆ（Ｄ-Ｅ） | J4: Ｇ | K4: Ｈ（F+G） | L4: Ｃ－Ｈ
A5: 資本的支出 | D5: =SUM(D6,D15,D17,D21) -> 62055911000 | E5: =SUM(E6,E15,E17,E21) -> 0 | F5: =SUM(F6,F15,F17,F21) -> 62055911000 | G5: =SUM(G6,G15,G17,G21) -> 61875977537 | H5: =SUM(H6,H15,H17,H21) -> 9248923703 | I5: =SUM(I6,I15,I17,I21) -> 52627053834 | J5: =SUM(J6,J15,J17,J21) -> 9225844099 | K5: =SUM(K6,K15,K17,K21) -> 61852897933 | L5: =SUM(L6,L15,L17,L21) -> 203013067
B6: 建設改良費 | D6: =SUM(D7:D14) -> 17424201000 | E6: =SUM(E7:E14) -> 0 | F6: =SUM(F7:F14) -> 17424201000 | G6: =SUM(G7:G14) -> 17250555070 | H6: =SUM(H7:H14) -> 9248923703 | I6: =SUM(I7:I14) -> 8001631367 | J6: =SUM(J7:J14) -> 9225844099 | K6: =SUM(K7:K14) -> 17227475466 | L6: =SUM(L7:L14) -> 196725534
C7: 公共下水道整備費 | D7: =14573171000+1320000000 -> 15893171000 | E7: 0 | F7: =D7+E7 -> 15893171000 | G7: =+'[6]4条支出'!E6 -> 15677649564 | H7: 8377952802 | I7: =G7-H7 -> 7299696762 | J7: 8532522419 | K7: =G7+J7-H7 -> 15832219181 | L7: =F7-K7 -> 60951819
C8: 受益者負担金業務費 | D8: 18558000 | E8: 0 | F8: =D8+E8 -> 18558000 | G8: =+'[6]4条支出'!E7 -> 15860357 | I8: =G8-H8 -> 15860357 | K8: =G8+J8-H8 -> 15860357 | L8: =F8-K8 -> 2697643
C9: 排水設備整備費 | D9: 779527000 | E9: 0 | F9: =D9+E9 -> 779527000 | G9: =+'[6]4条支出'!E8 -> 665100151 | H9: 454024301 | I9: =G9-H9 -> 211075850 | J9: 520900202 | K9: =G9+J9-H9 -> 731976052 | L9: =F9-K9 -> 47550948
C10: 都市下水路整備費 | D10: 0 | E10: 0 | F10: =D10+E10 -> 0 | G10: =+'[6]4条支出'!E9 -> 0 | I10: =G10-H10 -> 0 | K10: =G10+J10-H10 -> 0 | L10: =F10-K10 -> 0
C11: 流域下水道整備費 | D11: 172142000 | E11: 0 | F11: =D11+E11 -> 172142000 | G11: =+'[6]4条支出'!E10 -> 131921564 | I11: =G11-H11 -> 131921564 | K11: =G11+J11-H11 -> 131921564 | L11: =F11-K11 -> 40220436
C12: 諸設備新設改良費 | D12: 90944000 | F12: =D12+E12 -> 90944000 | G12: =+'[6]4条支出'!E11 -> 59178010 | H12: 21253100 | I12: =G12-H12 -> 37924910 | J12: 46750000 | K12: =G12+J12-H12 -> 84674910 | L12: =F12-K12 -> 6269090
C13: 建設利息 | D13: 12600000 | E13: 0 | F13: =D13+E13 -> 12600000 | G13: =+'[6]4条支出'!E15 -> 12600000 | I13: =G13-H13 -> 12600000 | K13: =G13+J13-H13 -> 12600000 | L13: =F13-K13 -> 0
C14: 市街化区域外整備費 | D14: 457259000 | F14: =D14+E14 -> 457259000 | G14: =+'[6]4条支出'!E16 -> 688245424 | H14: 395693500 | I14: =G14-H14 -> 292551924 | J14: 125671478 | K14: =G14+J14-H14 -> 418223402 | L14: =F14-K14 -> 39035598
B15: 償還金 | D15: =D16 -> 44621423000 | E15: =E16 -> 0 | F15: =F16 -> 44621423000 | G15: =G16 -> 44621240467 | H15: =H16 -> 0 | I15: =I16 -> 44621240467 | J15: =J16 -> 0 | K15: =K16 -> 44621240467 | L15: =F15-K15 -> 182533
C16: 企業債償還金 | D16: 44621423000 | E16: 0 | F16: =D16+E16 -> 44621423000 | G16: =+'[6]4条支出'!E21 -> 44621240467 | H16: 0 | I16: =G16-H16 -> 44621240467 | J16: 0 | K16: =G16+J16-H16 -> 44621240467 | L16: =F16-K16 -> 182533
B17: 水洗化貸付事業費 | D17: =SUM(D18:D20) -> 10287000 | E17: =SUM(E18:E20) -> 0 | F17: =SUM(F18:F20) -> 10287000 | G17: =SUM(G18:G20) -> 4182000 | H17: =SUM(H18:H20) -> 0 | I17: =SUM(I18:I20) -> 4182000 | J17: =SUM(J18:J20) -> 0 | K17: =SUM(K18:K20) -> 4182000 | L17: =SUM(L18:L20) -> 6105000
C18: 貸付金 | D18: 8096000 | E18: 0 | F18: =D18+E18 -> 8096000 | G18: =+'[6]4条支出'!E24 -> 3759000 | H18: 0 | I18: =G18-H18 -> 3759000 | J18: 0 | K18: =G18+J18-H18 -> 3759000 | L18: =F18-K18 -> 4337000
C19: 貸付資金企業債償還金 | D19: 0 | E19: 0 | F19: =D19+E19 -> 0 | G19: =+'[6]4条支出'!E25 -> 0 | I19: =G19-H19 -> 0 | K19: =G19+J19-H19 -> 0 | L19: =F19-K19 -> 0
C20: 一般会計借入金償還金 | D20: 2191000 | E20: 0 | F20: =D20+E20 -> 2191000 | G20: =+'[6]4条支出'!E26 -> 423000 | H20: 0 | I20: =G20-H20 -> 423000 | J20: 0 | K20: =G20+J20-H20 -> 423000 | L20: =F20-K20 -> 1768000
B21: 返還金 | D21: =D22 -> 0 | E21: =E22 -> 0 | F21: =F22 -> 0 | G21: =G22 -> 0 | H21: =H22 -> 0 | I21: =I22 -> 0 | J21: =J22 -> 0 | K21: =K22 -> 0 | L21: =F21-K21 -> 0
C22: 国庫補助金返還金 | D22: 0 | E22: 0 | F22: =D22+E22 -> 0 | G22: =+'[6]4条支出'!E28 -> 0 | H22: 0 | I22: =G22-H22 -> 0 | J22: 0 | K22: =G22+J22-H22 -> 0 | L22: =F22-K22 -> 0

Sheet 出資金しくみ
B1: =+CONCATENATE(LEFT('[1]3条支出'!$D$1,5),"決算における一般会計出資金のしくみ") -> 令和５年度決算における一般会計出資金のしくみ
Q2: (単位:円)
B3: 収益的収入及び支出(税抜き) | L3: 資本的収入及び支出(税込み)
B4: (収入) | F4: (支出) | L4: (収入) | P4: (支出)
L6: 企業債
F7: 維持管理費 | L7: =+'(繰)4条収入'!M6 -> 32352700000
F8: =+[4]雨汚水!AD47 -> 11030037961 | M8: (現年度分)
B9: 下水道使用料 | M9: =+L7-M11 -> 27125900000
B10: =+'[2]3条収入'!AI8 -> 18626337467 | M10: (翌年度繰越分)
M11: =+'(繰)4条収入'!L6 -> 5226800000
F13: 資本費 | L13: 国庫補助金 | P13: 建設改良費
F14: =+[4]雨汚水!AD48 -> 30998096974 | L14: =+'(繰)4条収入'!M16 -> 5766273739 | P14: =+'(繰)4条支出 '!K6 -> 17227475466
B15: 国庫補助金・県補助金 | M15: (現年度分) | Q15: (現年度分)
B16: =+'[2]3条収入'!AI32 -> 0 | M16: =+L14-M18 -> 2543788000 | Q16: =P14-Q18 -> 8001631367
M17: (翌年度繰越分) | Q17: (翌年度繰越分)
M18: =+'(繰)4条収入'!L16 -> 3222485739 | Q18: =+'(繰)4条支出 '!J6 -> 9225844099
B19: 負担金 | L19: その他収入
B20: =+'[2]3条収入'!AI39 -> 50128048 | L20: =M22+M24 -> 838612590
M21: (現年度分)
M22: =(+SUM('(繰)4条収入'!M20,'(繰)4条収入'!M22,'(繰)4条収入'!M29,'(繰)4条収入'!M30))-M24 -> 648612590
M23: (翌年度繰越分)
M24: =+SUM('(繰)4条収入'!L20,'(繰)4条収入'!L22,'(繰)4条収入'!L29,'(繰)4条収入'!L30) -> 190000000
F27: 補てん財源 | L27: 補てん財源
F28: (損益勘定留保資金) | L28: =M30+M32+M34+M36+M38+M40 -> 19609807053
F29: =G34+G36+G38+G40 -> 17579830234 | M29: (過年度損益勘定留保資金)
B30: 一般会計負担金 | F30: (うち前年度からの繰越分を除く) | M30: =+G42 -> 0
B31: =+'[2]3条収入'!AI9 -> 14187102335 | G31: =-F29-G42 -> -17579830234 | M31: (当年度損益勘定留保資金)
M32: =+-G31 -> 17579830234
G33: 減価償却費 | P33: 企業債償還金
G34: =+[4]雨汚水!E34 -> 26551442230 | P34: =+'(繰)4条支出 '!K15 -> 44621240467
G35: 固定資産除却費等 | M35: (当年度消費税等資本的収支調整額)
B36: 一般会計補助金 | G36: =+[4]雨汚水!E35+[4]雨汚水!E42+[4]雨汚水!E44+[4]雨汚水!$E$28 -> 514077226 | M36: =+-[3]消費税!AF118 -> 923595698
B37: =+'[2]3条収入'!AI42 -> 9203253 | G37: 長期前受金戻入等 | M37: (減債積立金)
G38: =-([4]雨汚水!E85+[4]雨汚水!E86+[4]雨汚水!E93+[4]雨汚水!E95) -> -9485689222 | M38: =+'(繰)案'!E34 -> 1049566207
G39: 企業債発行差金（実決算） | M39: (前年度繰越工事資金当年度充当額)
G40: 0 | M40: =+'(繰)案'!E35 -> 56814914
G41: (うち前年度からの繰越分) | P41: 水洗化貸付事業費
G42: 0 | L42: 一般会計出資金 | P42: =+'(繰)4条支出 '!K17 -> 4182000
L43: =+'(繰)4条収入'!M14 -> 3285504551
F44: 合計額
F45: =F8+F14 -> 42028134935 | L45: 一般会計借入金 | P45: 出資金
B46: その他収入 | M46: =+'(繰)4条収入'!M28 -> 0 | P46: =+'(繰)4条支出 '!K22 -> 0
B47: =+'[2]3条収入'!AI69-B10-B16-B20-B31-B37 -> 9699271031 | F47: 純利益
B48: 合計額 | G48: =B49-F45 -> 543907199 | L48: 合計額 | P48: 合計額
B49: =B10+B16+B20+B31+B37+B47 -> 42572042134 | L49: =L43+L28+L20+L14+L7+M46 -> 61852897933 | P49: =P14+P34+P42+P46 -> 61852897933
K50: 注：資本的収入及び支出は、みなし決算額である。
F51: 3条収入シート純利益額→ | G51: =+'[2]3条収入'!AI74 -> 543907199 | Q51: 差引チェック（「０」が正しい）→ | R51: =L49-P49 -> 0
G52: =+G48-G51 -> 0

Sheet 総括表 (メモなし)
K1: 令和6年5月22日
K2: 経営企画課
A3: =DBCS(TEXT(DATE($T$4,12,31),"[$-ja-JP]ggge年度下水道事業会計決算【速報】")) -> 令和５年度下水道事業会計決算【速報】
A4: １ 決算 | T4: 2023
A5: (1) 収益的収入及び支出(税込) | K5: （単位：千円）
A6: 区 分 | E6: =TEXT(DATE(T4,12,31),"[$-ja-JP]ggge年度") -> 令和5年度 | H6: 増 △ 減
E7: 議決予算 （a） | F7: 4月決見 （b） | G7: 決算 (c) | H7: 決算(c) -議決予算(a) | J7: 決算(c) -4月決見(b) | X7: G列 項目名リスト
I8: 率 | K8: 率 | P8: 決算円 | Q8: 端数調整 | R8: 千円 | S8: 注意
A9: 下水道事業収益 | E9: =E10+E12+E13 -> 44975817 | F9: =F10+F12+F13 -> 44165221 | G9: =G10+G12+G13 -> 44454711 | H9: =G9-E9 -> -521106 | I9: =IF(AND(E9=0,G9=0),"－ ",IF(E9=0,"皆増 ",IF(G9=0,"皆減 ",H9/E9))) -> -0.01158636 | J9: =G9-F9 -> 289490 | K9: =IF(AND(F9=0,G9=0),"－ ",IF(F9=0,"皆増 ",IF(G9=0,"皆減 ",J9/F9))) -> 0.0065547051 | P9: =P10+P12+P13 -> 44454711283 | Q9: =Q10+Q12+Q13 -> -1 | R9: =R10+R12+R13 -> 44454711 | X9: 要求額 （ｃ）
B10: 営業収益 | E10: 35444153 | F10: 34582538 | G10: =R10 -> 34865912 | H10: =G10-E10 -> -578241 | I10: =IF(AND(E10=0,G10=0),"－ ",IF(E10=0,"皆増 ",IF(G10=0,"皆減 ",H10/E10))) -> -0.016314144 | J10: =G10-F10 -> 283374 | K10: =IF(AND(F10=0,G10=0),"－ ",IF(F10=0,"皆増 ",IF(G10=0,"皆減 ",J10/F10))) -> 0.0081941354 | P10: ='[2]3条収入'!$E$27 -> 34865911732 | R10: =ROUND(P10/1000,0)+Q10 -> 34865912 | X10: 査定額 （ｃ）
C11: (下水道使用料) | E11: 21384728 | F11: 20441757 | G11: =R11 -> 20488963 | H11: =G11-E11 -> -895765 | I11: =IF(AND(E11=0,G11=0),"－ ",IF(E11=0,"皆増 ",IF(G11=0,"皆減 ",H11/E11))) -> -0.041888071 | J11: =G11-F11 -> 47206 | K11: =IF(AND(F11=0,G11=0),"－ ",IF(F11=0,"皆増 ",IF(G11=0,"皆減 ",J11/F11))) -> 0.0023092927 | P11: ='[2]3条収入'!$E$7 -> 20488962528 | R11: =ROUND(P11/1000,0)+Q11 -> 20488963 | X11: 決見額 （ｃ）
B12: 営業外収益 | E12: 9528788 | F12: 9579686 | G12: =R12 -> 9584600 | H12: =G12-E12 -> 55812 | I12: =IF(AND(E12=0,G12=0),"－ ",IF(E12=0,"皆増 ",IF(G12=0,"皆減 ",H12/E12))) -> 0.0058571982 | J12: =G12-F12 -> 4914 | K12: =IF(AND(F12=0,G12=0),"－ ",IF(F12=0,"皆増 ",IF(G12=0,"皆減 ",J12/F12))) -> 0.00051296045 | P12: ='[2]3条収入'!$E$57 -> 9584600552 | Q12: -1 | R12: =ROUND(P12/1000,0)+Q12 -> 9584600 | X12: 予算案 （ｃ）
B13: 特別利益 | E13: 2876 | F13: 2997 | G13: =R13 -> 4199 | H13: =G13-E13 -> 1323 | I13: =IF(AND(E13=0,G13=0),"－ ",IF(E13=0,"皆増 ",IF(G13=0,"皆減 ",H13/E13))) -> 0.46001391 | J13: =G13-F13 -> 1202 | K13: =IF(AND(F13=0,G13=0),"－ ",IF(F13=0,"皆増 ",IF(G13=0,"皆減 ",J13/F13))) -> 0.40106773 | P13: ='[2]3条収入'!$E$68 -> 4198999 | R13: =ROUND(P13/1000,0)+Q13 -> 4199
A14: 下 水 道 事 業 費 用 | E14: =SUM(E15,E16,E17,E18) -> 43953299 | F14: =SUM(F15,F16,F17,F18) -> 43109924 | G14: =SUM(G15,G16,G17,G18) -> 42987208 | H14: =G14-E14 -> -966091 | I14: =IF(AND(E14=0,G14=0),"－ ",IF(E14=0,"皆増 ",IF(G14=0,"皆減 ",H14/E14))) -> -0.021979943 | J14: =G14-F14 -> -122716 | K14: =IF(AND(F14=0,G14=0),"－ ",IF(F14=0,"皆増 ",IF(G14=0,"皆減 ",J14/F14))) -> -0.0028465835 | P14: =SUM(P15:P18) -> 42987208386 | Q14: =SUM(Q15:Q18) -> 0 | R14: =SUM(R15:R18) -> 42987208
B15: 営業費用 | E15: 39325285 | F15: 38869045 | G15: =R15 -> 38667489 | H15: =G15-E15 -> -657796 | I15: =IF(AND(E15=0,G15=0),"－ ",IF(E15=0,"皆増 ",IF(G15=0,"皆減 ",H15/E15))) -> -0.01672705 | J15: =G15-F15 -> -201556 | K15: =IF(AND(F15=0,G15=0),"－ ",IF(F15=0,"皆増 ",IF(G15=0,"皆減 ",J15/F15))) -> -0.0051855146 | P15: ='[1]3条支出'!$E$5 -> 38667489041 | R15: =ROUND(P15/1000,0)+Q15 -> 38667489
B16: 営業外費用 | E16: 4599725 | F16: =4210270+8000 -> 4218270 | G16: =R16 -> 4298724 | H16: =G16-E16 -> -301001 | I16: =IF(AND(E16=0,G16=0),"－ ",IF(E16=0,"皆増 ",IF(G16=0,"皆減 ",H16/E16))) -> -0.065438912 | J16: =G16-F16 -> 80454 | K16: =IF(AND(F16=0,G16=0),"－ ",IF(F16=0,"皆増 ",IF(G16=0,"皆減 ",J16/F16))) -> 0.019072748 | P16: ='[1]3条支出'!$E$22+[1]営外!$E$22 -> 4298724047 | R16: =ROUND(P16/1000,0)+Q16 -> 4298724 | S16: 3条支出（3条消費税・4条消費税含む） ＝営業外費用（消費税除く）＋消費税
B17: 特別損失 | E17: 8289 | F17: =22609 -> 22609 | G17: =R17 -> 20995 | H17: =G17-E17 -> 12706 | I17: =IF(AND(E17=0,G17=0),"－ ",IF(E17=0,"皆増 ",IF(G17=0,"皆減 ",H17/E17))) -> 1.5328749 | J17: =G17-F17 -> -1614 | K17: =IF(AND(F17=0,G17=0),"－ ",IF(F17=0,"皆増 ",IF(G17=0,"皆減 ",J17/F17))) -> -0.071387501 | P17: ='[1]3条支出'!$E$27 -> 20995298 | R17: =ROUND(P17/1000,0)+Q17 -> 20995
B18: 予備費 | E18: 20000 | F18: 0 | G18: =R18 -> 0 | H18: =G18-E18 -> -20000 | I18: =IF(AND(E18=0,G18=0),"－ ",IF(E18=0,"皆増 ",IF(G18=0,"皆減 ",H18/E18))) -> 皆減 | J18: =G18-F18 -> 0 | K18: =IF(AND(F18=0,G18=0),"－ ",IF(F18=0,"皆増 ",IF(G18=0,"皆減 ",J18/F18))) -> － | P18: 0 | R18: =ROUND(P18/1000,0)+Q18 -> 0
A20: 収支差引 | E20: =E9-E14 -> 1022518 | F20: =F9-F14 -> 1055297 | G20: =G9-G14 -> 1467503 | H20: =G20-E20 -> 444985 | I20: =IF(AND(E20=0,G20=0),"－ ",IF(E20=0,"皆増 ",IF(G20=0,"皆減 ",H20/E20))) -> 0.43518549 | J20: =G20-F20 -> 412206 | K20: =IF(AND(F20=0,G20=0),"－ ",IF(F20=0,"皆増 ",IF(G20=0,"皆減 ",J20/F20))) -> 0.39060663 | P20: =P9-P14 -> 1467502897 | Q20: =Q9-Q14 -> -1 | R20: =R9-R14 -> 1467503
P21: =[3]消費税!$AF$118 -> -923595698 | R21: =ROUND(P21/1000,0)+Q21 -> -923596 | S21: 消費税資本的収支調整を控除 | V21: チェック
A22: 税抜収支差引（純利益） | E22: 120300 | F22: 87814 | G22: =R22 -> 543907 | H22: =G22-E22 -> 423607 | I22: =IF(AND(E22=0,G22=0),"－ ",IF(E22=0,"皆増 ",IF(G22=0,"皆減 ",H22/E22))) -> 3.5212552 | J22: =G22-F22 -> 456093 | K22: =IF(AND(F22=0,G22=0),"－ ",IF(F22=0,"皆増 ",IF(G22=0,"皆減 ",J22/F22))) -> 5.1938529 | P22: =SUM(P20:P21) -> 543907199 | R22: =ROUND(P22/1000,0)+Q22 -> 543907 | T22: ='(繰)案'!E13 -> 543907199 | V22: =P22-T22 -> 0
A24: (2) 資本的収入及び支出（税込） | M24: （単位：千円）
A25: 区 分 | E25: =E6 -> 令和5年度 | I25: 増 △ 減
E26: 議決予算 （a） | F26: 4月決見 （b） | G26: =G$7 -> 決算 (c) | H26: 翌年度への 繰越 (d) | I26: 決算(c)+翌年度への繰越(d) | L26: 決算(c)+翌年度への繰越(d)
I27: -議決予算(a) | K27: 率 | L27: -4月決見(b) | M27: 率 | T27: 税込３条収入（一般会計負担金を除く） | U27: ① | W27: =IF(G9=ROUND((V27+V28)/1000,0),"OK","エラー") -> エラー
A28: 資本的収入 | E28: =SUM(E29:E31) -> 51048450 | F28: =SUM(F29:F31) -> 50593733 | G28: =SUM(G29:G31) -> 42025205 | H28: =SUM(H29:H31) -> 8639286 | J28: =G28+H28-E28 -> -383959 | K28: =IF(AND(E28=0,SUM(G28:H28)=0),"－ ",IF(E28=0,"皆増 ",IF(SUM(G28:H28)=0,"皆減 ",J28/E28))) -> -0.0075214625 | L28: =G28+H28-F28 -> 70758 | M28: =IF(AND(F28=0,SUM(G28:H28)=0),"－ ",IF(F28=0,"皆増 ",IF(SUM(G28:H28)=0,"皆減 ",L28/F28))) -> 0.0013985527 | P28: =P29+P30+P31 -> 42025205141 | Q28: =Q29+Q30+Q31 -> 0 | R28: =R29+R30+R31 -> 42025205 | T28: 一般会計負担金 | U28: ②
B29: 企業債 | E29: =32505200+5247400 -> 37752600 | F29: =32352700+5247400 -> 37600100 | G29: =R29 -> 32373300 | H29: 5226800 | J29: =G29+H29-E29 -> -152500 | K29: =IF(AND(E29=0,SUM(G29:H29)=0),"－ ",IF(E29=0,"皆増 ",IF(SUM(G29:H29)=0,"皆減 ",J29/E29))) -> -0.0040394569 | L29: =G29+H29-F29 -> 0 | M29: =IF(AND(F29=0,SUM(G29:H29)=0),"－ ",IF(F29=0,"皆増 ",IF(SUM(G29:H29)=0,"皆減 ",L29/F29))) -> 0 | P29: ='[5]4条収入'!$E$7 -> 32373300000 | R29: =ROUND(P29/1000,0)+Q29 -> 32373300 | T29: 税込３条支出 | U29: ③ | W29: =IF(G14=ROUND((V29+V30)/1000,0),"OK","エラー") -> エラー
B30: 国庫補助金 | E30: =5769500+3174000 -> 8943500 | F30: =5766211+3174000 -> 8940211 | G30: =R30 -> 5717788 | H30: 3222486 | J30: =G30+H30-E30 -> -3226 | K30: =IF(AND(E30=0,SUM(G30:H30)=0),"－ ",IF(E30=0,"皆増 ",IF(SUM(G30:H30)=0,"皆減 ",J30/E30))) -> -0.00036070889 | L30: =G30+H30-F30 -> 63 | M30: =IF(AND(F30=0,SUM(G30:H30)=0),"－ ",IF(F30=0,"皆増 ",IF(SUM(G30:H30)=0,"皆減 ",L30/F30))) -> 7.0468135e-06 | P30: ='[5]4条収入'!$E$23 -> 5717788000 | R30: =ROUND(P30/1000,0)+Q30 -> 5717788 | T30: 消費税納付額 | U30: ④
B31: その他資本的収入 | E31: 4352350 | F31: 4053422 | G31: =R31 -> 3934117 | H31: =130000+60000 -> 190000 | J31: =G31+H31-E31 -> -228233 | K31: =IF(AND(E31=0,SUM(G31:H31)=0),"－ ",IF(E31=0,"皆増 ",IF(SUM(G31:H31)=0,"皆減 ",J31/E31))) -> -0.052439027 | L31: =G31+H31-F31 -> 70695 | M31: =IF(AND(F31=0,SUM(G31:H31)=0),"－ ",IF(F31=0,"皆増 ",IF(SUM(G31:H31)=0,"皆減 ",L31/F31))) -> 0.017440819 | P31: ='[5]4条収入'!$E$91-SUM(P29:P30) -> 3934117141 | R31: =ROUND(P31/1000,0)+Q31 -> 3934117 | T31: 消費税４条調整額 | U31: ⑤
A32: 資 本 的 支 出 | E32: =E33+E34+E35 -> 71361650 | F32: =F33+F34+F35 -> 71076971 | G32: =G33+G34+G35 -> 61875977 | H32: =H33+H34+H35 -> 9225844 | J32: =G32+H32-E32 -> -259829 | K32: =IF(AND(E32=0,SUM(G32:H32)=0),"－ ",IF(E32=0,"皆増 ",IF(SUM(G32:H32)=0,"皆減 ",J32/E32))) -> -0.0036410173 | L32: =G32+H32-F32 -> 24850 | M32: =IF(AND(F32=0,SUM(G32:H32)=0),"－ ",IF(F32=0,"皆増 ",IF(SUM(G32:H32)=0,"皆減 ",L32/F32))) -> 0.00034962098 | P32: =P33+P34+P35 -> 61875977537 | Q32: =Q33+Q34+Q35 -> 0 | R32: =R33+R34+R35 -> 61875977 | T32: 差引（純利益） （①＋②－③－④－⑤） | U32: ⑥
B33: 建設改良費 | E33: =17424201+9305739 -> 26729940 | F33: =17145810+9305739 -> 26451549 | G33: =R33 -> 17250555 | H33: 9225844 | J33: =G33+H33-E33 -> -253541 | K33: =IF(AND(E33=0,SUM(G33:H33)=0),"－ ",IF(E33=0,"皆増 ",IF(SUM(G33:H33)=0,"皆減 ",J33/E33))) -> -0.0094852813 | L33: =G33+H33-F33 -> 24850 | M33: =IF(AND(F33=0,SUM(G33:H33)=0),"－ ",IF(F33=0,"皆増 ",IF(SUM(G33:H33)=0,"皆減 ",L33/F33))) -> 0.00093945349 | P33: ='[6]4条支出'!$E$5 -> 17250555070 | R33: =ROUND(P33/1000,0)+Q33 -> 17250555 | T33: 税抜３条収入（一般会計負担金を除く） | U33: ⑦
B34: 償還金 | E34: 44621423 | F34: 44621240 | G34: =R34 -> 44621240 | H34: 0 | J34: =G34+H34-E34 -> -183 | K34: =IF(AND(E34=0,SUM(G34:H34)=0),"－ ",IF(E34=0,"皆増 ",IF(SUM(G34:H34)=0,"皆減 ",J34/E34))) -> -4.1011691e-06 | L34: =G34+H34-F34 -> 0 | M34: =IF(AND(F34=0,SUM(G34:H34)=0),"－ ",IF(F34=0,"皆増 ",IF(SUM(G34:H34)=0,"皆減 ",L34/F34))) -> 0 | P34: ='[6]4条支出'!$E$21 -> 44621240467 | R34: =ROUND(P34/1000,0)+Q34 -> 44621240 | T34: 税抜３条支出 | U34: ⑧
B35: 水洗化貸付事業費 | E35: 10287 | F35: 4182 | G35: =R35 -> 4182 | H35: 0 | J35: =G35+H35-E35 -> -6105 | K35: =IF(AND(E35=0,SUM(G35:H35)=0),"－ ",IF(E35=0,"皆増 ",IF(SUM(G35:H35)=0,"皆減 ",J35/E35))) -> -0.59346748 | L35: =G35+H35-F35 -> 0 | M35: =IF(AND(F35=0,SUM(G35:H35)=0),"－ ",IF(F35=0,"皆増 ",IF(SUM(G35:H35)=0,"皆減 ",L35/F35))) -> 0 | P35: ='[6]4条支出'!$E$41-SUM(P33:P34) -> 4182000 | R35: =ROUND(P35/1000,0)+Q35 -> 4182 | T35: 消費税雑支出 | U35: ⑨
B36: ※上記金額には前年度からの繰り越し分を含む。 | T36: 差引（純利益） （⑦＋②－⑧－⑨）
A38: ２ 一般会計繰入金の状況 | K38: （単位：千円）
A39: 区 分 | E39: =E6 -> 令和5年度 | H39: 増 △ 減
E40: =E$7 -> 議決予算 （a） | F40: =F$7 -> 4月決見 （b） | G40: =G$7 -> 決算 (c) | H40: =H7 -> 決算(c) -議決予算(a) | J40: =J7 -> 決算(c) -4月決見(b)
I41: 率 | K41: 率
A42: 一般会計負担金 | E42: 13854862 | F42: 13951285 | G42: =R42 -> 14187102 | H42: =G42-E42 -> 332240 | I42: =IF(AND(E42=0,G42=0),"－ ",IF(E42=0,"皆増 ",IF(G42=0,"皆減 ",H42/E42))) -> 0.02398003 | J42: =G42-F42 -> 235817 | K42: =IF(AND(F42=0,G42=0),"－ ",IF(F42=0,"皆増 ",IF(G42=0,"皆減 ",J42/F42))) -> 0.016902887 | P42: ='[2]3条収入'!$E$9 -> 14187102335 | R42: =ROUND(P42/1000,0)+Q42 -> 14187102
A43: 一般会計補助金 | E43: 0 | F43: 8000 | G43: =R43 -> 9203 | H43: =G43-E43 -> 9203 | I43: =IF(AND(E43=0,G43=0),"－ ",IF(E43=0,"皆増 ",IF(G43=0,"皆減 ",H43/E43))) -> 皆増 | J43: =G43-F43 -> 1203 | K43: =IF(AND(F43=0,G43=0),"－ ",IF(F43=0,"皆増 ",IF(G43=0,"皆減 ",J43/F43))) -> 0.150375 | P43: ='[2]3条収入'!$E$42 -> 9203253 | R43: =ROUND(P43/1000,0)+Q43 -> 9203
A44: 一般会計出資金 | E44: 3640474 | F44: 3379653 | G44: =R44 -> 3285505 | H44: =G44-E44 -> -354969 | I44: =IF(AND(E44=0,G44=0),"－ ",IF(E44=0,"皆増 ",IF(G44=0,"皆減 ",H44/E44))) -> -0.097506259 | J44: =G44-F44 -> -94148 | K44: =IF(AND(F44=0,G44=0),"－ ",IF(F44=0,"皆増 ",IF(G44=0,"皆減 ",J44/F44))) -> -0.027857298 | P44: ='[5]4条収入'!$E$21 -> 3285504551 | R44: =ROUND(P44/1000,0)+Q44 -> 3285505
A45: 一般会計借入金 | E45: 0 | F45: 0 | G45: 0 | H45: =G45-E45 -> 0 | I45: =IF(AND(E45=0,G45=0),"－ ",IF(E45=0,"皆増 ",IF(G45=0,"皆減 ",H45/E45))) -> － | J45: =G45-F45 -> 0 | K45: =IF(AND(F45=0,G45=0),"－ ",IF(F45=0,"皆増 ",IF(G45=0,"皆減 ",J45/F45))) -> － | R45: =ROUND(P45/1000,0)+Q45 -> 0
A46: 繰入金 合計 | E46: =SUM(E42:E45) -> 17495336 | F46: =SUM(F42:F45) -> 17338938 | G46: =SUM(G42:G45) -> 17481810 | H46: =G46-E46 -> -13526 | I46: =IF(AND(E46=0,G46=0),"－ ",IF(E46=0,"皆増 ",IF(G46=0,"皆減 ",H46/E46))) -> -0.00077312033 | J46: =G46-F46 -> 142872 | K46: =IF(AND(F46=0,G46=0),"－ ",IF(F46=0,"皆増 ",IF(G46=0,"皆減 ",J46/F46))) -> 0.008239951
B48: ３ 今後の変動要素
B49: (1) 人件費の修正（⇒現在は給与改定後の数値を使用しているが、人員配置見直しについては未反映）
B50: (2) 情報システム関連経費のCIO審査結果による修正
B51: (3) 財政課の査定による修正ほか

Sheet 総括表
K1: 令和6年5月22日
K2: 経営企画課
A3: =DBCS(TEXT(DATE($T$4,12,31),"[$-ja-JP]ggge年度下水道事業会計決算【速報】")) -> 令和５年度下水道事業会計決算【速報】
A4: １ 決算 | T4: 2023
A5: (1) 収益的収入及び支出(税込) | K5: （単位：千円）
A6: 区 分 | E6: =TEXT(DATE(T4,12,31),"[$-ja-JP]ggge年度") -> 令和5年度 | H6: 増 △ 減
E7: 議決予算 （a） | F7: 4月決見 （b） | G7: 決算 (c) | H7: 決算(c) -議決予算(a) | J7: 決算(c) -4月決見(b) | X7: G列 項目名リスト
I8: 率 | K8: 率 | P8: 決算円 | Q8: 端数調整 | R8: 千円 | S8: 注意
A9: 下水道事業収益 | E9: =E10+E12+E13 -> 44975817 | F9: =F10+F12+F13 -> 44165221 | G9: =G10+G12+G13 -> 44454711 | H9: =G9-E9 -> -521106 | I9: =IF(AND(E9=0,G9=0),"－ ",IF(E9=0,"皆増 ",IF(G9=0,"皆減 ",H9/E9))) -> -0.01158636 | J9: =G9-F9 -> 289490 | K9: =IF(AND(F9=0,G9=0),"－ ",IF(F9=0,"皆増 ",IF(G9=0,"皆減 ",J9/F9))) -> 0.0065547051 | P9: =P10+P12+P13 -> 44454711283 | Q9: =Q10+Q12+Q13 -> -1 | R9: =R10+R12+R13 -> 44454711 | X9: 要求額 （ｃ）
B10: 営業収益 | E10: 35444153 | F10: 34582538 | G10: =R10 -> 34865912 | H10: =G10-E10 -> -578241 | I10: =IF(AND(E10=0,G10=0),"－ ",IF(E10=0,"皆増 ",IF(G10=0,"皆減 ",H10/E10))) -> -0.016314144 | J10: =G10-F10 -> 283374 | K10: =IF(AND(F10=0,G10=0),"－ ",IF(F10=0,"皆増 ",IF(G10=0,"皆減 ",J10/F10))) -> 0.0081941354 | P10: ='[2]3条収入'!$E$27 -> 34865911732 | R10: =ROUND(P10/1000,0)+Q10 -> 34865912 | X10: 査定額 （ｃ）
C11: (下水道使用料) | E11: 21384728 | F11: 20441757 | G11: =R11 -> 20488963 | H11: =G11-E11 -> -895765 | I11: =IF(AND(E11=0,G11=0),"－ ",IF(E11=0,"皆増 ",IF(G11=0,"皆減 ",H11/E11))) -> -0.041888071 | J11: =G11-F11 -> 47206 | K11: =IF(AND(F11=0,G11=0),"－ ",IF(F11=0,"皆増 ",IF(G11=0,"皆減 ",J11/F11))) -> 0.0023092927 | P11: ='[2]3条収入'!$E$7 -> 20488962528 | R11: =ROUND(P11/1000,0)+Q11 -> 20488963 | X11: 決見額 （ｃ）
B12: 営業外収益 | E12: 9528788 | F12: 9579686 | G12: =R12 -> 9584600 | H12: =G12-E12 -> 55812 | I12: =IF(AND(E12=0,G12=0),"－ ",IF(E12=0,"皆増 ",IF(G12=0,"皆減 ",H12/E12))) -> 0.0058571982 | J12: =G12-F12 -> 4914 | K12: =IF(AND(F12=0,G12=0),"－ ",IF(F12=0,"皆増 ",IF(G12=0,"皆減 ",J12/F12))) -> 0.00051296045 | P12: ='[2]3条収入'!$E$57 -> 9584600552 | Q12: -1 | R12: =ROUND(P12/1000,0)+Q12 -> 9584600 | X12: 予算案 （ｃ）
B13: 特別利益 | E13: 2876 | F13: 2997 | G13: =R13 -> 4199 | H13: =G13-E13 -> 1323 | I13: =IF(AND(E13=0,G13=0),"－ ",IF(E13=0,"皆増 ",IF(G13=0,"皆減 ",H13/E13))) -> 0.46001391 | J13: =G13-F13 -> 1202 | K13: =IF(AND(F13=0,G13=0),"－ ",IF(F13=0,"皆増 ",IF(G13=0,"皆減 ",J13/F13))) -> 0.40106773 | P13: ='[2]3条収入'!$E$68 -> 4198999 | R13: =ROUND(P13/1000,0)+Q13 -> 4199
A14: 下 水 道 事 業 費 用 | E14: =SUM(E15,E16,E17,E18) -> 43953299 | F14: =SUM(F15,F16,F17,F18) -> 43109924 | G14: =SUM(G15,G16,G17,G18) -> 42987208 | H14: =G14-E14 -> -966091 | I14: =IF(AND(E14=0,G14=0),"－ ",IF(E14=0,"皆増 ",IF(G14=0,"皆減 ",H14/E14))) -> -0.021979943 | J14: =G14-F14 -> -122716 | K14: =IF(AND(F14=0,G14=0),"－ ",IF(F14=0,"皆増 ",IF(G14=0,"皆減 ",J14/F14))) -> -0.0028465835 | P14: =SUM(P15:P18) -> 42987208386 | Q14: =SUM(Q15:Q18) -> 0 | R14: =SUM(R15:R18) -> 42987208
B15: 営業費用 | E15: 39325285 | F15: 38869045 | G15: =R15 -> 38667489 | H15: =G15-E15 -> -657796 | I15: =IF(AND(E15=0,G15=0),"－ ",IF(E15=0,"皆増 ",IF(G15=0,"皆減 ",H15/E15))) -> -0.01672705 | J15: =G15-F15 -> -201556 | K15: =IF(AND(F15=0,G15=0),"－ ",IF(F15=0,"皆増 ",IF(G15=0,"皆減 ",J15/F15))) -> -0.0051855146 | P15: ='[1]3条支出'!$E$5 -> 38667489041 | R15: =ROUND(P15/1000,0)+Q15 -> 38667489
B16: 営業外費用 | E16: 4599725 | F16: =4210270+8000 -> 4218270 | G16: =R16 -> 4298724 | H16: =G16-E16 -> -301001 | I16: =IF(AND(E16=0,G16=0),"－ ",IF(E16=0,"皆増 ",IF(G16=0,"皆減 ",H16/E16))) -> -0.065438912 | J16: =G16-F16 -> 80454 | K16: =IF(AND(F16=0,G16=0),"－ ",IF(F16=0,"皆増 ",IF(G16=0,"皆減 ",J16/F16))) -> 0.019072748 | P16: ='[1]3条支出'!$E$22+[1]営外!$E$22 -> 4298724047 | R16: =ROUND(P16/1000,0)+Q16 -> 4298724 | S16: 3条支出（3条消費税・4条消費税含む） ＝営業外費用（消費税除く）＋消費税
B17: 特別損失 | E17: 8289 | F17: =22609 -> 22609 | G17: =R17 -> 20995 | H17: =G17-E17 -> 12706 | I17: =IF(AND(E17=0,G17=0),"－ ",IF(E17=0,"皆増 ",IF(G17=0,"皆減 ",H17/E17))) -> 1.5328749 | J17: =G17-F17 -> -1614 | K17: =IF(AND(F17=0,G17=0),"－ ",IF(F17=0,"皆増 ",IF(G17=0,"皆減 ",J17/F17))) -> -0.071387501 | P17: ='[1]3条支出'!$E$27 -> 20995298 | R17: =ROUND(P17/1000,0)+Q17 -> 20995
B18: 予備費 | E18: 20000 | F18: 0 | G18: =R18 -> 0 | H18: =G18-E18 -> -20000 | I18: =IF(AND(E18=0,G18=0),"－ ",IF(E18=0,"皆増 ",IF(G18=0,"皆減 ",H18/E18))) -> 皆減 | J18: =G18-F18 -> 0 | K18: =IF(AND(F18=0,G18=0),"－ ",IF(F18=0,"皆増 ",IF(G18=0,"皆減 ",J18/F18))) -> － | P18: 0 | R18: =ROUND(P18/1000,0)+Q18 -> 0
A20: 収支差引 | E20: =E9-E14 -> 1022518 | F20: =F9-F14 -> 1055297 | G20: =G9-G14 -> 1467503 | H20: =G20-E20 -> 444985 | I20: =IF(AND(E20=0,G20=0),"－ ",IF(E20=0,"皆増 ",IF(G20=0,"皆減 ",H20/E20))) -> 0.43518549 | J20: =G20-F20 -> 412206 | K20: =IF(AND(F20=0,G20=0),"－ ",IF(F20=0,"皆増 ",IF(G20=0,"皆減 ",J20/F20))) -> 0.39060663 | P20: =P9-P14 -> 1467502897 | Q20: =Q9-Q14 -> -1 | R20: =R9-R14 -> 1467503
P21: =[3]消費税!$AF$118 -> -923595698 | R21: =ROUND(P21/1000,0)+Q21 -> -923596 | S21: 消費税資本的収支調整を控除 | V21: チェック
A22: 税抜収支差引（純利益） | E22: 120300 | F22: 87814 | G22: =R22 -> 543907 | H22: =G22-E22 -> 423607 | I22: =IF(AND(E22=0,G22=0),"－ ",IF(E22=0,"皆増 ",IF(G22=0,"皆減 ",H22/E22))) -> 3.5212552 | J22: =G22-F22 -> 456093 | K22: =IF(AND(F22=0,G22=0),"－ ",IF(F22=0,"皆増 ",IF(G22=0,"皆減 ",J22/F22))) -> 5.1938529 | P22: =SUM(P20:P21) -> 543907199 | R22: =ROUND(P22/1000,0)+Q22 -> 543907 | T22: ='(繰)案'!E13 -> 543907199 | V22: =P22-T22 -> 0
A24: (2) 資本的収入及び支出（税込） | M24: （単位：千円）
A25: 区 分 | E25: =E6 -> 令和5年度 | I25: 増 △ 減
E26: 議決予算 （a） | F26: 4月決見 （b） | G26: =G$7 -> 決算 (c) | H26: 翌年度への 繰越 (d) | I26: 決算(c)+翌年度への繰越(d) | L26: 決算(c)+翌年度への繰越(d)
I27: -議決予算(a) | K27: 率 | L27: -4月決見(b) | M27: 率 | T27: 税込３条収入（一般会計負担金を除く） | U27: ① | W27: =IF(G9=ROUND((V27+V28)/1000,0),"OK","エラー") -> エラー
A28: 資本的収入 | E28: =SUM(E29:E31) -> 51048450 | F28: =SUM(F29:F31) -> 50593733 | G28: =SUM(G29:G31) -> 42025205 | H28: =SUM(H29:H31) -> 8639286 | J28: =G28+H28-E28 -> -383959 | K28: =IF(AND(E28=0,SUM(G28:H28)=0),"－ ",IF(E28=0,"皆増 ",IF(SUM(G28:H28)=0,"皆減 ",J28/E28))) -> -0.0075214625 | L28: =G28+H28-F28 -> 70758 | M28: =IF(AND(F28=0,SUM(G28:H28)=0),"－ ",IF(F28=0,"皆増 ",IF(SUM(G28:H28)=0,"皆減 ",L28/F28))) -> 0.0013985527 | P28: =P29+P30+P31 -> 42025205141 | Q28: =Q29+Q30+Q31 -> 0 | R28: =R29+R30+R31 -> 42025205 | T28: 一般会計負担金 | U28: ②
B29: 企業債 | E29: =32505200+5247400 -> 37752600 | F29: =32352700+5247400 -> 37600100 | G29: =R29 -> 32373300 | H29: 5226800 | J29: =G29+H29-E29 -> -152500 | K29: =IF(AND(E29=0,SUM(G29:H29)=0),"－ ",IF(E29=0,"皆増 ",IF(SUM(G29:H29)=0,"皆減 ",J29/E29))) -> -0.0040394569 | L29: =G29+H29-F29 -> 0 | M29: =IF(AND(F29=0,SUM(G29:H29)=0),"－ ",IF(F29=0,"皆増 ",IF(SUM(G29:H29)=0,"皆減 ",L29/F29))) -> 0 | P29: ='[5]4条収入'!$E$7 -> 32373300000 | R29: =ROUND(P29/1000,0)+Q29 -> 32373300 | T29: 税込３条支出 | U29: ③ | W29: =IF(G14=ROUND((V29+V30)/1000,0),"OK","エラー") -> エラー
B30: 国庫補助金 | E30: =5769500+3174000 -> 8943500 | F30: =5766211+3174000 -> 8940211 | G30: =R30 -> 5717788 | H30: 3222486 | J30: =G30+H30-E30 -> -3226 | K30: =IF(AND(E30=0,SUM(G30:H30)=0),"－ ",IF(E30=0,"皆増 ",IF(SUM(G30:H30)=0,"皆減 ",J30/E30))) -> -0.00036070889 | L30: =G30+H30-F30 -> 63 | M30: =IF(AND(F30=0,SUM(G30:H30)=0),"－ ",IF(F30=0,"皆増 ",IF(SUM(G30:H30)=0,"皆減 ",L30/F30))) -> 7.0468135e-06 | P30: ='[5]4条収入'!$E$23 -> 5717788000 | R30: =ROUND(P30/1000,0)+Q30 -> 5717788 | T30: 消費税納付額 | U30: ④
B31: その他資本的収入 | E31: 4352350 | F31: 4053422 | G31: =R31 -> 3934117 | H31: =130000+60000 -> 190000 | J31: =G31+H31-E31 -> -228233 | K31: =IF(AND(E31=0,SUM(G31:H31)=0),"－ ",IF(E31=0,"皆増 ",IF(SUM(G31:H31)=0,"皆減 ",J31/E31))) -> -0.052439027 | L31: =G31+H31-F31 -> 70695 | M31: =IF(AND(F31=0,SUM(G31:H31)=0),"－ ",IF(F31=0,"皆増 ",IF(SUM(G31:H31)=0,"皆減 ",L31/F31))) -> 0.017440819 | P31: ='[5]4条収入'!$E$91-SUM(P29:P30) -> 3934117141 | R31: =ROUND(P31/1000,0)+Q31 -> 3934117 | T31: 消費税４条調整額 | U31: ⑤
A32: 資 本 的 支 出 | E32: =E33+E34+E35 -> 71361650 | F32: =F33+F34+F35 -> 71076971 | G32: =G33+G34+G35 -> 61875977 | H32: =H33+H34+H35 -> 9225844 | J32: =G32+H32-E32 -> -259829 | K32: =IF(AND(E32=0,SUM(G32:H32)=0),"－ ",IF(E32=0,"皆増 ",IF(SUM(G32:H32)=0,"皆減 ",J32/E32))) -> -0.0036410173 | L32: =G32+H32-F32 -> 24850 | M32: =IF(AND(F32=0,SUM(G32:H32)=0),"－ ",IF(F32=0,"皆増 ",IF(SUM(G32:H32)=0,"皆減 ",L32/F32))) -> 0.00034962098 | P32: =P33+P34+P35 -> 61875977537 | Q32: =Q33+Q34+Q35 -> 0 | R32: =R33+R34+R35 -> 61875977 | T32: 差引（純利益） （①＋②－③－④－⑤） | U32: ⑥
B33: 建設改良費 | E33: =17424201+9305739 -> 26729940 | F33: =17145810+9305739 -> 26451549 | G33: =R33 -> 17250555 | H33: 9225844 | J33: =G33+H33-E33 -> -253541 | K33: =IF(AND(E33=0,SUM(G33:H33)=0),"－ ",IF(E33=0,"皆増 ",IF(SUM(G33:H33)=0,"皆減 ",J33/E33))) -> -0.0094852813 | L33: =G33+H33-F33 -> 24850 | M33: =IF(AND(F33=0,SUM(G33:H33)=0),"－ ",IF(F33=0,"皆増 ",IF(SUM(G33:H33)=0,"皆減 ",L33/F33))) -> 0.00093945349 | P33: ='[6]4条支出'!$E$5 -> 17250555070 | R33: =ROUND(P33/1000,0)+Q33 -> 17250555 | T33: 税抜３条収入（一般会計負担金を除く） | U33: ⑦
B34: 償還金 | E34: 44621423 | F34: 44621240 | G34: =R34 -> 44621240 | H34: 0 | J34: =G34+H34-E34 -> -183 | K34: =IF(AND(E34=0,SUM(G34:H34)=0),"－ ",IF(E34=0,"皆増 ",IF(SUM(G34:H34)=0,"皆減 ",J34/E34))) -> -4.1011691e-06 | L34: =G34+H34-F34 -> 0 | M34: =IF(AND(F34=0,SUM(G34:H34)=0),"－ ",IF(F34=0,"皆増 ",IF(SUM(G34:H34)=0,"皆減 ",L34/F34))) -> 0 | P34: ='[6]4条支出'!$E$21 -> 44621240467 | R34: =ROUND(P34/1000,0)+Q34 -> 44621240 | T34: 税抜３条支出 | U34: ⑧
B35: 水洗化貸付事業費 | E35: 10287 | F35: 4182 | G35: =R35 -> 4182 | H35: 0 | J35: =G35+H35-E35 -> -6105 | K35: =IF(AND(E35=0,SUM(G35:H35)=0),"－ ",IF(E35=0,"皆増 ",IF(SUM(G35:H35)=0,"皆減 ",J35/E35))) -> -0.59346748 | L35: =G35+H35-F35 -> 0 | M35: =IF(AND(F35=0,SUM(G35:H35)=0),"－ ",IF(F35=0,"皆増 ",IF(SUM(G35:H35)=0,"皆減 ",L35/F35))) -> 0 | P35: ='[6]4条支出'!$E$41-SUM(P33:P34) -> 4182000 | R35: =ROUND(P35/1000,0)+Q35 -> 4182 | T35: 消費税雑支出 | U35: ⑨
B36: ※上記金額には前年度からの繰り越し分を含む。 | T36: 差引（純利益） （⑦＋②－⑧－⑨）
A38: ２ 一般会計繰入金の状況 | K38: （単位：千円）
A39: 区 分 | E39: =E6 -> 令和5年度 | H39: 増 △ 減
E40: =E$7 -> 議決予算 （a） | F40: =F$7 -> 4月決見 （b） | G40: =G$7 -> 決算 (c) | H40: =H7 -> 決算(c) -議決予算(a) | J40: =J7 -> 決算(c) -4月決見(b)
I41: 率 | K41: 率
A42: 一般会計負担金 | E42: 13854862 | F42: 13951285 | G42: =R42 -> 14187102 | H42: =G42-E42 -> 332240 | I42: =IF(AND(E42=0,G42=0),"－ ",IF(E42=0,"皆増 ",IF(G42=0,"皆減 ",H42/E42))) -> 0.02398003 | J42: =G42-F42 -> 235817 | K42: =IF(AND(F42=0,G42=0),"－ ",IF(F42=0,"皆増 ",IF(G42=0,"皆減 ",J42/F42))) -> 0.016902887 | P42: ='[2]3条収入'!$E$9 -> 14187102335 | R42: =ROUND(P42/1000,0)+Q42 -> 14187102
A43: 一般会計補助金 | E43: 0 | F43: 8000 | G43: =R43 -> 9203 | H43: =G43-E43 -> 9203 | I43: =IF(AND(E43=0,G43=0),"－ ",IF(E43=0,"皆増 ",IF(G43=0,"皆減 ",H43/E43))) -> 皆増 | J43: =G43-F43 -> 1203 | K43: =IF(AND(F43=0,G43=0),"－ ",IF(F43=0,"皆増 ",IF(G43=0,"皆減 ",J43/F43))) -> 0.150375 | P43: ='[2]3条収入'!$E$42 -> 9203253 | R43: =ROUND(P43/1000,0)+Q43 -> 9203
A44: 一般会計出資金 | E44: 3640474 | F44: 3379653 | G44: =R44 -> 3285505 | H44: =G44-E44 -> -354969 | I44: =IF(AND(E44=0,G44=0),"－ ",IF(E44=0,"皆増 ",IF(G44=0,"皆減 ",H44/E44))) -> -0.097506259 | J44: =G44-F44 -> -94148 | K44: =IF(AND(F44=0,G44=0),"－ ",IF(F44=0,"皆増 ",IF(G44=0,"皆減 ",J44/F44))) -> -0.027857298 | P44: ='[5]4条収入'!$E$21 -> 3285504551 | R44: =ROUND(P44/1000,0)+Q44 -> 3285505
A45: 一般会計借入金 | E45: 0 | F45: 0 | G45: 0 | H45: =G45-E45 -> 0 | I45: =IF(AND(E45=0,G45=0),"－ ",IF(E45=0,"皆増 ",IF(G45=0,"皆減 ",H45/E45))) -> － | J45: =G45-F45 -> 0 | K45: =IF(AND(F45=0,G45=0),"－ ",IF(F45=0,"皆増 ",IF(G45=0,"皆減 ",J45/F45))) -> － | R45: =ROUND(P45/1000,0)+Q45 -> 0
A46: 繰入金 合計 | E46: =SUM(E42:E45) -> 17495336 | F46: =SUM(F42:F45) -> 17338938 | G46: =SUM(G42:G45) -> 17481810 | H46: =G46-E46 -> -13526 | I46: =IF(AND(E46=0,G46=0),"－ ",IF(E46=0,"皆増 ",IF(G46=0,"皆減 ",H46/E46))) -> -0.00077312033 | J46: =G46-F46 -> 142872 | K46: =IF(AND(F46=0,G46=0),"－ ",IF(F46=0,"皆増 ",IF(G46=0,"皆減 ",J46/F46))) -> 0.008239951
B48: ３ 今後の変動要素
B49: (1) 人件費の修正（⇒現在は給与改定後の数値を使用しているが、人員配置見直しについては未反映）
B50: (2) 情報システム関連経費のCIO審査結果による修正
B51: (3) 財政課の査定による修正ほか

Sheet ３条 税抜
A3: =CONCATENATE("令和",+DBCS(MID(出資金しくみ!B1,3,1)),"年度決算 収益的収支（税抜き）") -> 令和５年度決算 収益的収支（税抜き） | O3: =総括表!$K$1 -> 令和6年5月22日
A5: 収 入 | O5: （単位：千円、％）
J6: 差引増減
A7: 区分 | E7: 財政収支計画 （参考） | F7: Ｒ５ 議決予算 | G7: Ｒ５ 決見（4月） | H7: Ｒ５ 決算 | I7: Ｒ４ 決算 | J7: 対Ｒ５議決予算 | L7: 対Ｒ５決見（4月） | N7: 対Ｒ４決算 | R7: R5決算 | U7: 令和5年度4月決見
F8: (a) | G8: (b) | H8: (c) | I8: (d) | J8: (c-a) | K8: 率 | L8: (c-b) | M8: 率 | N8: (c-d) | O8: 率 | P8: 表示判定 | Q8: AAA | R8: （参照数式） | S8: 千円返還＋端数調整 | T8: ↓端数調整 | U8: 決見額千円 | V8: 調整 | W8: 決見額千円
A9: 下水道事業収益 | E9: =SUM(E10,E19,E27) -> 41202558 | F9: =SUM(F10,F19,F27) -> 43009658 | G9: =SUM(G10,G19,G27) -> 42285947 | H9: =SUM(H10,H19,H27) -> 42572042 | I9: =SUM(I10,I19,I27) -> 42499689 | J9: =IF(AND(F9=0,$H9=0),"－ ",$H9-F9) -> -437616 | K9: =IF(AND(F9=0,$H9>0),"皆増 ",IF(AND(F9>0,$H9=0),"皆減 ",IF(AND(F9=0,$H9=0),"－ ",J9/F9))) -> -0.010174831 | L9: =IF(AND(G9=0,$H9=0),"－ ",$H9-G9) -> 286095 | M9: =IF(AND(G9=0,$H9>0),"皆増 ",IF(AND(G9>0,$H9=0),"皆減 ",IF(AND(G9=0,$H9=0),"－ ",L9/G9))) -> 0.0067657229 | N9: =IF(AND(I9=0,$H9=0),"－ ",$H9-I9) -> 72353 | O9: =IF(AND(I9=0,$H9>0),"皆増 ",IF(AND(I9>0,$H9=0),"皆減 ",IF(AND(I9=0,$H9=0),"－ ",N9/I9))) -> 0.001702436 | P9: =IF(OR(F9>0,G9>0,H9>0,I9>0),"表示（判定）","×表示しない") -> 表示（判定）
B10: 営業収益 | E10: =SUM(E11:E12,E18) -> 39159297 | F10: =SUM(F11:F12,F18) -> 33481570 | G10: =SUM(G11:G12,G18) -> 32707017 | H10: =SUM(H11:H12,H18) -> 32986084 | I10: =SUM(I11:I12,I18) -> 32791345 | J10: =IF(AND(F10=0,$H10=0),"－ ",$H10-F10) -> -495486 | K10: =IF(AND(F10=0,$H10>0),"皆増 ",IF(AND(F10>0,$H10=0),"皆減 ",IF(AND(F10=0,$H10=0),"－ ",J10/F10))) -> -0.014798768 | L10: =IF(AND(G10=0,$H10=0),"－ ",$H10-G10) -> 279067 | M10: =IF(AND(G10=0,$H10>0),"皆増 ",IF(AND(G10>0,$H10=0),"皆減 ",IF(AND(G10=0,$H10=0),"－ ",L10/G10))) -> 0.0085323281 | N10: =IF(AND(I10=0,$H10=0),"－ ",$H10-I10) -> 194739 | O10: =IF(AND(I10=0,$H10>0),"皆増 ",IF(AND(I10>0,$H10=0),"皆減 ",IF(AND(I10=0,$H10=0),"－ ",N10/I10))) -> 0.0059387317 | P10: =IF(OR(F10>0,G10>0,H10>0,I10>0),"表示（判定）","×表示しない") -> 表示（判定）
C11: 下水道使用料 | E11: 21145614 | F11: 19440663 | G11: =W11 -> 18583417 | H11: =S11 -> 18626337 | I11: 18620214 | J11: =IF(AND(F11=0,$H11=0),"－ ",$H11-F11) -> -814326 | K11: =IF(AND(F11=0,$H11>0),"皆増 ",IF(AND(F11>0,$H11=0),"皆減 ",IF(AND(F11=0,$H11=0),"－ ",J11/F11))) -> -0.041887769 | L11: =IF(AND(G11=0,$H11=0),"－ ",$H11-G11) -> 42920 | M11: =IF(AND(G11=0,$H11>0),"皆増 ",IF(AND(G11>0,$H11=0),"皆減 ",IF(AND(G11=0,$H11=0),"－ ",L11/G11))) -> 0.002309586 | N11: =IF(AND(I11=0,$H11=0),"－ ",$H11-I11) -> 6123 | O11: =IF(AND(I11=0,$H11>0),"皆増 ",IF(AND(I11>0,$H11=0),"皆減 ",IF(AND(I11=0,$H11=0),"－ ",N11/I11))) -> 0.00032883618 | P11: =IF(OR(F11>0,G11>0,H11>0,I11>0),"表示（判定）","×表示しない") -> 表示（判定） | R11: ='[2]3条収入'!$AI$8 -> 18626337467 | S11: =ROUND(R11/1000,0)+T11 -> 18626337 | U11: 18583417 | W11: =SUM(U11:V11) -> 18583417
C12: 一般会計負担金 | E12: 18011826 | F12: =SUM(F13:F17) -> 13854862 | G12: =SUM(G13:G17) -> 13951285 | H12: =SUM(H13:H17) -> 14187103 | I12: =SUM(I13:I17) -> 13993349 | J12: =IF(AND(F12=0,$H12=0),"－ ",$H12-F12) -> 332241 | K12: =IF(AND(F12=0,$H12>0),"皆増 ",IF(AND(F12>0,$H12=0),"皆減 ",IF(AND(F12=0,$H12=0),"－ ",J12/F12))) -> 0.023980102 | L12: =IF(AND(G12=0,$H12=0),"－ ",$H12-G12) -> 235818 | M12: =IF(AND(G12=0,$H12>0),"皆増 ",IF(AND(G12>0,$H12=0),"皆減 ",IF(AND(G12=0,$H12=0),"－ ",L12/G12))) -> 0.016902959 | N12: =IF(AND(I12=0,$H12=0),"－ ",$H12-I12) -> 193754 | O12: =IF(AND(I12=0,$H12>0),"皆増 ",IF(AND(I12>0,$H12=0),"皆減 ",IF(AND(I12=0,$H12=0),"－ ",N12/I12))) -> 0.013846149 | P12: =IF(OR(F12>0,G12>0,H12>0,I12>0),"表示（判定）","×表示しない") -> 表示（判定）
D13: 雨水処理負担金 | E13: =E12-E14-E15-E16 -> 17853307 | F13: 13738282 | G13: =13852072-8000 -> 13844072 | H13: =S13 -> 14079750 | I13: 13893559 | J13: =IF(AND(F13=0,$H13=0),"－ ",$H13-F13) -> 341468 | K13: =IF(AND(F13=0,$H13>0),"皆増 ",IF(AND(F13>0,$H13=0),"皆減 ",IF(AND(F13=0,$H13=0),"－ ",J13/F13))) -> 0.024855218 | L13: =IF(AND(G13=0,$H13=0),"－ ",$H13-G13) -> 235678 | M13: =IF(AND(G13=0,$H13>0),"皆増 ",IF(AND(G13>0,$H13=0),"皆減 ",IF(AND(G13=0,$H13=0),"－ ",L13/G13))) -> 0.017023749 | N13: =IF(AND(I13=0,$H13=0),"－ ",$H13-I13) -> 186191 | O13: =IF(AND(I13=0,$H13>0),"皆増 ",IF(AND(I13>0,$H13=0),"皆減 ",IF(AND(I13=0,$H13=0),"－ ",N13/I13))) -> 0.013401246 | P13: =IF(OR(F13>0,G13>0,H13>0,I13>0),"表示（判定）","×表示しない") -> 表示（判定） | R13: ='[2]3条収入'!$AI$10 -> 14079749832 | S13: =ROUND(R13/1000,0)+T13 -> 14079750 | U13: 13852072 | V13: 8000 | W13: =SUM(U13:V13) -> 13860072
D14: 水質指導費負担金 | E14: 72773 | F14: 61778 | G14: 52650 | H14: =S14 -> 52444 | I14: 51549 | J14: =IF(AND(F14=0,$H14=0),"－ ",$H14-F14) -> -9334 | K14: =IF(AND(F14=0,$H14>0),"皆増 ",IF(AND(F14>0,$H14=0),"皆減 ",IF(AND(F14=0,$H14=0),"－ ",J14/F14))) -> -0.15108938 | L14: =IF(AND(G14=0,$H14=0),"－ ",$H14-G14) -> -206 | M14: =IF(AND(G14=0,$H14>0),"皆増 ",IF(AND(G14>0,$H14=0),"皆減 ",IF(AND(G14=0,$H14=0),"－ ",L14/G14))) -> -0.0039126306 | N14: =IF(AND(I14=0,$H14=0),"－ ",$H14-I14) -> 895 | O14: =IF(AND(I14=0,$H14>0),"皆増 ",IF(AND(I14>0,$H14=0),"皆減 ",IF(AND(I14=0,$H14=0),"－ ",N14/I14))) -> 0.017362121 | P14: =IF(OR(F14>0,G14>0,H14>0,I14>0),"表示（判定）","×表示しない") -> 表示（判定） | R14: ='[2]3条収入'!$AI$14 -> 52443869 | S14: =ROUND(R14/1000,0)+T14 -> 52444 | U14: 52650 | W14: =SUM(U14:V14) -> 52650
D15: 普及促進費負担金 | E15: 67470 | F15: 40039 | G15: 43851 | H15: =S15 -> 44425 | I15: 37495 | J15: =IF(AND(F15=0,$H15=0),"－ ",$H15-F15) -> 4386 | K15: =IF(AND(F15=0,$H15>0),"皆増 ",IF(AND(F15>0,$H15=0),"皆減 ",IF(AND(F15=0,$H15=0),"－ ",J15/F15))) -> 0.1095432 | L15: =IF(AND(G15=0,$H15=0),"－ ",$H15-G15) -> 574 | M15: =IF(AND(G15=0,$H15>0),"皆増 ",IF(AND(G15>0,$H15=0),"皆減 ",IF(AND(G15=0,$H15=0),"－ ",L15/G15))) -> 0.013089781 | N15: =IF(AND(I15=0,$H15=0),"－ ",$H15-I15) -> 6930 | O15: =IF(AND(I15=0,$H15>0),"皆増 ",IF(AND(I15>0,$H15=0),"皆減 ",IF(AND(I15=0,$H15=0),"－ ",N15/I15))) -> 0.18482464 | P15: =IF(OR(F15>0,G15>0,H15>0,I15>0),"表示（判定）","×表示しない") -> 表示（判定） | R15: ='[2]3条収入'!$AI$15 -> 44424775 | S15: =ROUND(R15/1000,0)+T15 -> 44425 | U15: 43851 | W15: =SUM(U15:V15) -> 43851
D16: 貸付事業費負担金 | E16: 18276 | F16: 14763 | G16: 10712 | H16: =S16 -> 10484 | I16: 10746 | J16: =IF(AND(F16=0,$H16=0),"－ ",$H16-F16) -> -4279 | K16: =IF(AND(F16=0,$H16>0),"皆増 ",IF(AND(F16>0,$H16=0),"皆減 ",IF(AND(F16=0,$H16=0),"－ ",J16/F16))) -> -0.28984624 | L16: =IF(AND(G16=0,$H16=0),"－ ",$H16-G16) -> -228 | M16: =IF(AND(G16=0,$H16>0),"皆増 ",IF(AND(G16>0,$H16=0),"皆減 ",IF(AND(G16=0,$H16=0),"－ ",L16/G16))) -> -0.021284541 | N16: =IF(AND(I16=0,$H16=0),"－ ",$H16-I16) -> -262 | O16: =IF(AND(I16=0,$H16>0),"皆増 ",IF(AND(I16>0,$H16=0),"皆減 ",IF(AND(I16=0,$H16=0),"－ ",N16/I16))) -> -0.024381165 | P16: =IF(OR(F16>0,G16>0,H16>0,I16>0),"表示（判定）","×表示しない") -> 表示（判定） | R16: ='[2]3条収入'!$AI$16 -> 10483859 | S16: =ROUND(R16/1000,0)+T16 -> 10484 | U16: 10712 | W16: =SUM(U16:V16) -> 10712
D17: 高資本費対策費負担金 | E17: 0 | J17: =IF(AND(F17=0,$H17=0),"－ ",$H17-F17) -> － | K17: =IF(AND(F17=0,$H17>0),"皆増 ",IF(AND(F17>0,$H17=0),"皆減 ",IF(AND(F17=0,$H17=0),"－ ",J17/F17))) -> － | L17: =IF(AND(G17=0,$H17=0),"－ ",$H17-G17) -> － | M17: =IF(AND(G17=0,$H17>0),"皆増 ",IF(AND(G17>0,$H17=0),"皆減 ",IF(AND(G17=0,$H17=0),"－ ",L17/G17))) -> － | N17: =IF(AND(I17=0,$H17=0),"－ ",$H17-I17) -> － | O17: =IF(AND(I17=0,$H17>0),"皆増 ",IF(AND(I17>0,$H17=0),"皆減 ",IF(AND(I17=0,$H17=0),"－ ",N17/I17))) -> － | P17: =IF(OR(F17>0,G17>0,H17>0,I17>0),"表示（判定）","×表示しない") -> ×表示しない | U17: 172315 | W17: =SUM(U17:V17) -> 172315
C18: その他営業収益 | E18: 1857 | F18: 186045 | G18: =W18 -> 172315 | H18: =S18 -> 172644 | I18: 177782 | J18: =IF(AND(F18=0,$H18=0),"－ ",$H18-F18) -> -13401 | K18: =IF(AND(F18=0,$H18>0),"皆増 ",IF(AND(F18>0,$H18=0),"皆減 ",IF(AND(F18=0,$H18=0),"－ ",J18/F18))) -> -0.07203096 | L18: =IF(AND(G18=0,$H18=0),"－ ",$H18-G18) -> 329 | M18: =IF(AND(G18=0,$H18>0),"皆増 ",IF(AND(G18>0,$H18=0),"皆減 ",IF(AND(G18=0,$H18=0),"－ ",L18/G18))) -> 0.001909294 | N18: =IF(AND(I18=0,$H18=0),"－ ",$H18-I18) -> -5138 | O18: =IF(AND(I18=0,$H18>0),"皆増 ",IF(AND(I18>0,$H18=0),"皆減 ",IF(AND(I18=0,$H18=0),"－ ",N18/I18))) -> -0.028900564 | P18: =IF(OR(F18>0,G18>0,H18>0,I18>0),"表示（判定）","×表示しない") -> 表示（判定） | R18: ='[2]3条収入'!$AI$19 -> 172643606 | S18: =ROUND(R18/1000,0)+T18 -> 172644 | U18: 172315 | W18: =SUM(U18:V18) -> 172315
B19: 営業外収益 | E19: =SUM(E20:E26) -> 2040440 | F19: =SUM(F20:F26) -> 9525454 | G19: =SUM(G20:G26) -> 9576214 | H19: =SUM(H20:H26) -> 9581905 | I19: =SUM(I20:I26) -> 9701941 | J19: =IF(AND(F19=0,$H19=0),"－ ",$H19-F19) -> 56451 | K19: =IF(AND(F19=0,$H19>0),"皆増 ",IF(AND(F19>0,$H19=0),"皆減 ",IF(AND(F19=0,$H19=0),"－ ",J19/F19))) -> 0.0059263317 | L19: =IF(AND(G19=0,$H19=0),"－ ",$H19-G19) -> 5691 | M19: =IF(AND(G19=0,$H19>0),"皆増 ",IF(AND(G19>0,$H19=0),"皆減 ",IF(AND(G19=0,$H19=0),"－ ",L19/G19))) -> 0.00059428496 | N19: =IF(AND(I19=0,$H19=0),"－ ",$H19-I19) -> -120036 | O19: =IF(AND(I19=0,$H19>0),"皆増 ",IF(AND(I19>0,$H19=0),"皆減 ",IF(AND(I19=0,$H19=0),"－ ",N19/I19))) -> -0.01237237 | P19: =IF(OR(F19>0,G19>0,H19>0,I19>0),"表示（判定）","×表示しない") -> 表示（判定）
C20: 受取利息 | E20: 7130 | F20: 70 | G20: =W20 -> 87 | H20: =S20 -> 89 | I20: 63 | J20: =IF(AND(F20=0,$H20=0),"－ ",$H20-F20) -> 19 | K20: =IF(AND(F20=0,$H20>0),"皆増 ",IF(AND(F20>0,$H20=0),"皆減 ",IF(AND(F20=0,$H20=0),"－ ",J20/F20))) -> 0.27142857 | L20: =IF(AND(G20=0,$H20=0),"－ ",$H20-G20) -> 2 | M20: =IF(AND(G20=0,$H20>0),"皆増 ",IF(AND(G20>0,$H20=0),"皆減 ",IF(AND(G20=0,$H20=0),"－ ",L20/G20))) -> 0.022988506 | N20: =IF(AND(I20=0,$H20=0),"－ ",$H20-I20) -> 26 | O20: =IF(AND(I20=0,$H20>0),"皆増 ",IF(AND(I20>0,$H20=0),"皆減 ",IF(AND(I20=0,$H20=0),"－ ",N20/I20))) -> 0.41269841 | P20: =IF(OR(F20>0,G20>0,H20>0,I20>0),"表示（判定）","×表示しない") -> 表示（判定） | R20: ='[2]3条収入'!$AI$28 -> 88770 | S20: =ROUND(R20/1000,0)+T20 -> 89 | U20: 87 | W20: =SUM(U20:V20) -> 87
C21: 国庫補助金 | E21: 108 | F21: 0 | G21: =W21 -> 0 | H21: =S21 -> 0 | I21: 0 | J21: =IF(AND(F21=0,$H21=0),"－ ",$H21-F21) -> － | K21: =IF(AND(F21=0,$H21>0),"皆増 ",IF(AND(F21>0,$H21=0),"皆減 ",IF(AND(F21=0,$H21=0),"－ ",J21/F21))) -> － | L21: =IF(AND(G21=0,$H21=0),"－ ",$H21-G21) -> － | M21: =IF(AND(G21=0,$H21>0),"皆増 ",IF(AND(G21>0,$H21=0),"皆減 ",IF(AND(G21=0,$H21=0),"－ ",L21/G21))) -> － | N21: =IF(AND(I21=0,$H21=0),"－ ",$H21-I21) -> － | O21: =IF(AND(I21=0,$H21>0),"皆増 ",IF(AND(I21>0,$H21=0),"皆減 ",IF(AND(I21=0,$H21=0),"－ ",N21/I21))) -> － | P21: =IF(OR(F21>0,G21>0,H21>0,I21>0),"表示（判定）","×表示しない") -> ×表示しない | R21: ='[2]3条収入'!$AI$32 -> 0 | S21: =ROUND(R21/1000,0)+T21 -> 0
C22: 負担金 | E22: 305814 | F22: 46672 | G22: =W22 -> 46672 | H22: =S22 -> 50128 | I22: 60819 | J22: =IF(AND(F22=0,$H22=0),"－ ",$H22-F22) -> 3456 | K22: =IF(AND(F22=0,$H22>0),"皆増 ",IF(AND(F22>0,$H22=0),"皆減 ",IF(AND(F22=0,$H22=0),"－ ",J22/F22))) -> 0.07404868 | L22: =IF(AND(G22=0,$H22=0),"－ ",$H22-G22) -> 3456 | M22: =IF(AND(G22=0,$H22>0),"皆増 ",IF(AND(G22>0,$H22=0),"皆減 ",IF(AND(G22=0,$H22=0),"－ ",L22/G22))) -> 0.07404868 | N22: =IF(AND(I22=0,$H22=0),"－ ",$H22-I22) -> -10691 | O22: =IF(AND(I22=0,$H22>0),"皆増 ",IF(AND(I22>0,$H22=0),"皆減 ",IF(AND(I22=0,$H22=0),"－ ",N22/I22))) -> -0.17578388 | P22: =IF(OR(F22>0,G22>0,H22>0,I22>0),"表示（判定）","×表示しない") -> 表示（判定） | R22: ='[2]3条収入'!$AI$39 -> 50128048 | S22: =ROUND(R22/1000,0)+T22 -> 50128 | U22: 46672 | W22: =SUM(U22:V22) -> 46672
C23: 一般会計補助金 | E23: 1708190 | F23: 0 | G23: =W23 -> 8000 | H23: =S23 -> 9203 | I23: 31 | J23: =IF(AND(F23=0,$H23=0),"－ ",$H23-F23) -> 9203 | K23: =IF(AND(F23=0,$H23>0),"皆増 ",IF(AND(F23>0,$H23=0),"皆減 ",IF(AND(F23=0,$H23=0),"－ ",J23/F23))) -> 皆増 | L23: =IF(AND(G23=0,$H23=0),"－ ",$H23-G23) -> 1203 | M23: =IF(AND(G23=0,$H23>0),"皆増 ",IF(AND(G23>0,$H23=0),"皆減 ",IF(AND(G23=0,$H23=0),"－ ",L23/G23))) -> 0.150375 | N23: =IF(AND(I23=0,$H23=0),"－ ",$H23-I23) -> 9172 | O23: =IF(AND(I23=0,$H23>0),"皆増 ",IF(AND(I23>0,$H23=0),"皆減 ",IF(AND(I23=0,$H23=0),"－ ",N23/I23))) -> 295.87097 | P23: =IF(OR(F23>0,G23>0,H23>0,I23>0),"表示（判定）","×表示しない") -> 表示（判定） | R23: ='[2]3条収入'!$AI$42 -> 9203253 | S23: =ROUND(R23/1000,0)+T23 -> 9203 | V23: 8000 | W23: =SUM(U23:V23) -> 8000
C24: 消費税還付金 | E24: 0 | G24: =W24 -> 0 | H24: =S24 -> 0 | I24: 0 | J24: =IF(AND(F24=0,$H24=0),"－ ",$H24-F24) -> － | K24: =IF(AND(F24=0,$H24>0),"皆増 ",IF(AND(F24>0,$H24=0),"皆減 ",IF(AND(F24=0,$H24=0),"－ ",J24/F24))) -> － | L24: =IF(AND(G24=0,$H24=0),"－ ",$H24-G24) -> － | M24: =IF(AND(G24=0,$H24>0),"皆増 ",IF(AND(G24>0,$H24=0),"皆減 ",IF(AND(G24=0,$H24=0),"－ ",L24/G24))) -> － | N24: =IF(AND(I24=0,$H24=0),"－ ",$H24-I24) -> － | O24: =IF(AND(I24=0,$H24>0),"皆増 ",IF(AND(I24>0,$H24=0),"皆減 ",IF(AND(I24=0,$H24=0),"－ ",N24/I24))) -> － | P24: =IF(OR(F24>0,G24>0,H24>0,I24>0),"表示（判定）","×表示しない") -> ×表示しない | R24: ='[2]3条収入'!$AI$49 -> 0 | S24: =ROUND(R24/1000,0)+T24 -> 0
C25: 長期前受金戻入 | E25: 9623 | F25: 9455090 | G25: =W25 -> 9488526 | H25: =S25 -> 9485355 | I25: 37024 | J25: =IF(AND(F25=0,$H25=0),"－ ",$H25-F25) -> 30265 | K25: =IF(AND(F25=0,$H25>0),"皆増 ",IF(AND(F25>0,$H25=0),"皆減 ",IF(AND(F25=0,$H25=0),"－ ",J25/F25))) -> 0.0032009214 | L25: =IF(AND(G25=0,$H25=0),"－ ",$H25-G25) -> -3171 | M25: =IF(AND(G25=0,$H25>0),"皆増 ",IF(AND(G25>0,$H25=0),"皆減 ",IF(AND(G25=0,$H25=0),"－ ",L25/G25))) -> -0.00033419311 | N25: =IF(AND(I25=0,$H25=0),"－ ",$H25-I25) -> 9448331 | O25: =IF(AND(I25=0,$H25>0),"皆増 ",IF(AND(I25>0,$H25=0),"皆減 ",IF(AND(I25=0,$H25=0),"－ ",N25/I25))) -> 255.19477 | P25: =IF(OR(F25>0,G25>0,H25>0,I25>0),"表示（判定）","×表示しない") -> 表示（判定） | R25: ='[2]3条収入'!$AI$55 -> 9485355002 | S25: =ROUND(R25/1000,0)+T25 -> 9485355 | U25: 9488526 | W25: =SUM(U25:V25) -> 9488526
C26: 雑収益 | E26: 9575 | F26: 23622 | G26: =W26 -> 32929 | H26: =S26 -> 37130 | I26: 9604004 | J26: =IF(AND(F26=0,$H26=0),"－ ",$H26-F26) -> 13508 | K26: =IF(AND(F26=0,$H26>0),"皆増 ",IF(AND(F26>0,$H26=0),"皆減 ",IF(AND(F26=0,$H26=0),"－ ",J26/F26))) -> 0.57183981 | L26: =IF(AND(G26=0,$H26=0),"－ ",$H26-G26) -> 4201 | M26: =IF(AND(G26=0,$H26>0),"皆増 ",IF(AND(G26>0,$H26=0),"皆減 ",IF(AND(G26=0,$H26=0),"－ ",L26/G26))) -> 0.12757752 | N26: =IF(AND(I26=0,$H26=0),"－ ",$H26-I26) -> -9566874 | O26: =IF(AND(I26=0,$H26>0),"皆増 ",IF(AND(I26>0,$H26=0),"皆減 ",IF(AND(I26=0,$H26=0),"－ ",N26/I26))) -> -0.9961339 | P26: =IF(OR(F26>0,G26>0,H26>0,I26>0),"表示（判定）","×表示しない") -> 表示（判定） | R26: ='[2]3条収入'!$AI$51 -> 37130542 | S26: =ROUND(R26/1000,0)+T26 -> 37130 | T26: -1 | U26: 32929 | W26: =SUM(U26:V26) -> 32929
B27: 特別利益 | E27: =SUM(E28:E31) -> 2821 | F27: =SUM(F28:F31) -> 2634 | G27: =SUM(G28:G31) -> 2716 | H27: =SUM(H28:H31) -> 4053 | I27: =SUM(I28:I31) -> 6403 | J27: =IF(AND(F27=0,$H27=0),"－ ",$H27-F27) -> 1419 | K27: =IF(AND(F27=0,$H27>0),"皆増 ",IF(AND(F27>0,$H27=0),"皆減 ",IF(AND(F27=0,$H27=0),"－ ",J27/F27))) -> 0.53872437 | L27: =IF(AND(G27=0,$H27=0),"－ ",$H27-G27) -> 1337 | M27: =IF(AND(G27=0,$H27>0),"皆増 ",IF(AND(G27>0,$H27=0),"皆減 ",IF(AND(G27=0,$H27=0),"－ ",L27/G27))) -> 0.49226804 | N27: =IF(AND(I27=0,$H27=0),"－ ",$H27-I27) -> -2350 | O27: =IF(AND(I27=0,$H27>0),"皆増 ",IF(AND(I27>0,$H27=0),"皆減 ",IF(AND(I27=0,$H27=0),"－ ",N27/I27))) -> -0.36701546 | P27: =IF(OR(F27>0,G27>0,H27>0,I27>0),"表示（判定）","×表示しない") -> 表示（判定）
C28: 固定資産売却収益 | E28: 0 | F28: 0 | G28: =W28 -> 0 | H28: =S28 -> 0 | I28: 0 | J28: =IF(AND(F28=0,$H28=0),"－ ",$H28-F28) -> － | K28: =IF(AND(F28=0,$H28>0),"皆増 ",IF(AND(F28>0,$H28=0),"皆減 ",IF(AND(F28=0,$H28=0),"－ ",J28/F28))) -> － | L28: =IF(AND(G28=0,$H28=0),"－ ",$H28-G28) -> － | M28: =IF(AND(G28=0,$H28>0),"皆増 ",IF(AND(G28>0,$H28=0),"皆減 ",IF(AND(G28=0,$H28=0),"－ ",L28/G28))) -> － | N28: =IF(AND(I28=0,$H28=0),"－ ",$H28-I28) -> － | O28: =IF(AND(I28=0,$H28>0),"皆増 ",IF(AND(I28>0,$H28=0),"皆減 ",IF(AND(I28=0,$H28=0),"－ ",N28/I28))) -> － | P28: =IF(OR(F28>0,G28>0,H28>0,I28>0),"表示（判定）","×表示しない") -> ×表示しない | R28: ='[2]3条収入'!$AI$58 -> 0 | S28: =ROUND(R28/1000,0)+T28 -> 0
C29: 過年度損益修正益 | E29: 2821 | F29: 2634 | G29: =W29 -> 1851 | H29: =S29 -> 2624 | I29: 3896 | J29: =IF(AND(F29=0,$H29=0),"－ ",$H29-F29) -> -10 | K29: =IF(AND(F29=0,$H29>0),"皆増 ",IF(AND(F29>0,$H29=0),"皆減 ",IF(AND(F29=0,$H29=0),"－ ",J29/F29))) -> -0.0037965072 | L29: =IF(AND(G29=0,$H29=0),"－ ",$H29-G29) -> 773 | M29: =IF(AND(G29=0,$H29>0),"皆増 ",IF(AND(G29>0,$H29=0),"皆減 ",IF(AND(G29=0,$H29=0),"－ ",L29/G29))) -> 0.4176121 | N29: =IF(AND(I29=0,$H29=0),"－ ",$H29-I29) -> -1272 | O29: =IF(AND(I29=0,$H29>0),"皆増 ",IF(AND(I29>0,$H29=0),"皆減 ",IF(AND(I29=0,$H29=0),"－ ",N29/I29))) -> -0.32648871 | P29: =IF(OR(F29>0,G29>0,H29>0,I29>0),"表示（判定）","×表示しない") -> 表示（判定） | R29: ='[2]3条収入'!$AI$60 -> 2623682 | S29: =ROUND(R29/1000,0)+T29 -> 2624 | U29: 1851 | W29: =SUM(U29:V29) -> 1851
C30: 長期前受金戻入益 | F30: 0 | G30: =W30 -> 0 | H30: =S30 -> 0 | I30: 0 | J30: =IF(AND(F30=0,$H30=0),"－ ",$H30-F30) -> － | K30: =IF(AND(F30=0,$H30>0),"皆増 ",IF(AND(F30>0,$H30=0),"皆減 ",IF(AND(F30=0,$H30=0),"－ ",J30/F30))) -> － | L30: =IF(AND(G30=0,$H30=0),"－ ",$H30-G30) -> － | M30: =IF(AND(G30=0,$H30>0),"皆増 ",IF(AND(G30>0,$H30=0),"皆減 ",IF(AND(G30=0,$H30=0),"－ ",L30/G30))) -> － | N30: =IF(AND(I30=0,$H30=0),"－ ",$H30-I30) -> － | O30: =IF(AND(I30=0,$H30>0),"皆増 ",IF(AND(I30>0,$H30=0),"皆減 ",IF(AND(I30=0,$H30=0),"－ ",N30/I30))) -> － | P30: =IF(OR(F30>0,G30>0,H30>0,I30>0),"表示（判定）","×表示しない") -> ×表示しない | R30: ='[2]3条収入'!$AI$66 -> 0 | S30: =ROUND(R30/1000,0)+T30 -> 0 | U30: 0 | W30: =SUM(U30:V30) -> 0
C31: その他特別利益 | E31: 0 | F31: 0 | G31: =W31 -> 865 | H31: =S31 -> 1429 | I31: 2507 | J31: =IF(AND(F31=0,$H31=0),"－ ",$H31-F31) -> 1429 | K31: =IF(AND(F31=0,$H31>0),"皆増 ",IF(AND(F31>0,$H31=0),"皆減 ",IF(AND(F31=0,$H31=0),"－ ",J31/F31))) -> 皆増 | L31: =IF(AND(G31=0,$H31=0),"－ ",$H31-G31) -> 564 | M31: =IF(AND(G31=0,$H31>0),"皆増 ",IF(AND(G31>0,$H31=0),"皆減 ",IF(AND(G31=0,$H31=0),"－ ",L31/G31))) -> 0.65202312 | N31: =IF(AND(I31=0,$H31=0),"－ ",$H31-I31) -> -1078 | O31: =IF(AND(I31=0,$H31>0),"皆増 ",IF(AND(I31>0,$H31=0),"皆減 ",IF(AND(I31=0,$H31=0),"－ ",N31/I31))) -> -0.42999601 | P31: =IF(OR(F31>0,G31>0,H31>0,I31>0),"表示（判定）","×表示しない") -> 表示（判定） | R31: ='[2]3条収入'!$AI$62 -> 1429429 | S31: =ROUND(R31/1000,0)+T31 -> 1429 | U31: 865 | W31: =SUM(U31:V31) -> 865
L32: =IF(AND(G32=0,$H32=0),"－ ",$H32-G32) -> － | N32: =IF(AND(I32=0,$H32=0),"－ ",$H32-I32) -> － | P32: 表示
A33: 一般会計負担金・補助金合計 | E33: =SUM(E12,E23) -> 19720016 | F33: =SUM(F12,F23) -> 13854862 | G33: =SUM(G12,G23) -> 13959285 | H33: =SUM(H12,H23) -> 14196306 | I33: =SUM(I12,I23) -> 13993380 | J33: =IF(AND(F33=0,$H33=0),"－ ",$H33-F33) -> 341444 | K33: =IF(AND(F33=0,$H33>0),"皆増 ",IF(AND(F33>0,$H33=0),"皆減 ",IF(AND(F33=0,$H33=0),"－ ",J33/F33))) -> 0.024644345 | L33: =IF(AND(G33=0,$H33=0),"－ ",$H33-G33) -> 237021 | M33: =IF(AND(G33=0,$H33>0),"皆増 ",IF(AND(G33>0,$H33=0),"皆減 ",IF(AND(G33=0,$H33=0),"－ ",L33/G33))) -> 0.016979451 | N33: =IF(AND(I33=0,$H33=0),"－ ",$H33-I33) -> 202926 | O33: =IF(AND(I33=0,$H33>0),"皆増 ",IF(AND(I33>0,$H33=0),"皆減 ",IF(AND(I33=0,$H33=0),"－ ",N33/I33))) -> 0.014501571 | P33: 表示 | R33: 各項目 合計 → | S33: =SUM(S11:S31) -> 42572042
P34: 表示
A35: 支 出 | P35: 表示 | T35: ↓端数調整
A36: 下 水 道 事 業 費 用 | E36: =SUM(E37,E51,E55,E60) -> 41192935 | F36: =SUM(F37,F51,F55,F60) -> 42889358 | G36: =SUM(G37,G51,G55,G60) -> 42198133 | H36: =SUM(H37,H51,H55,H60) -> 42028135 | I36: =SUM(I37,I51,I55,I60) -> 42051708 | J36: =IF(AND(F36=0,$H36=0),"－ ",$H36-F36) -> -861223 | K36: =IF(AND(F36=0,$H36>0),"皆増 ",IF(AND(F36>0,$H36=0),"皆減 ",IF(AND(F36=0,$H36=0),"－ ",J36/F36))) -> -0.020080109 | L36: =IF(AND(G36=0,$H36=0),"－ ",$H36-G36) -> -169998 | M36: =IF(AND(G36=0,$H36>0),"皆増 ",IF(AND(G36>0,$H36=0),"皆減 ",IF(AND(G36=0,$H36=0),"－ ",L36/G36))) -> -0.0040285669 | N36: =IF(AND(I36=0,$H36=0),"－ ",$H36-I36) -> -23573 | O36: =IF(AND(I36=0,$H36>0),"皆増 ",IF(AND(I36>0,$H36=0),"皆減 ",IF(AND(I36=0,$H36=0),"－ ",N36/I36))) -> -0.00056057176 | P36: =IF(OR(F36>0,G36>0,H36>0,I36>0),"表示（判定）","×表示しない") -> 表示（判定） | R36: =IF('[1]3条支出'!$T$41=SUM(R38:R60),'[1]3条支出'!$T$41,"エラー") -> 42028134935 | S36: =ROUND(R36/1000,0)+T36 -> 42028135
B37: 営業費用 | E37: =SUM(E38:E50) -> 24965206 | F37: =SUM(F38:F50) -> 38446311 | G37: =SUM(G38:G50) -> 38032169 | H37: =SUM(H38:H50) -> 37846545 | I37: =SUM(I38:I50) -> 37457359 | J37: =IF(AND(F37=0,$H37=0),"－ ",$H37-F37) -> -599766 | K37: =IF(AND(F37=0,$H37>0),"皆増 ",IF(AND(F37>0,$H37=0),"皆減 ",IF(AND(F37=0,$H37=0),"－ ",J37/F37))) -> -0.015600092 | L37: =IF(AND(G37=0,$H37=0),"－ ",$H37-G37) -> -185624 | M37: =IF(AND(G37=0,$H37>0),"皆増 ",IF(AND(G37>0,$H37=0),"皆減 ",IF(AND(G37=0,$H37=0),"－ ",L37/G37))) -> -0.0048807103 | N37: =IF(AND(I37=0,$H37=0),"－ ",$H37-I37) -> 389186 | O37: =IF(AND(I37=0,$H37>0),"皆増 ",IF(AND(I37>0,$H37=0),"皆減 ",IF(AND(I37=0,$H37=0),"－ ",N37/I37))) -> 0.010390108 | P37: =IF(OR(F37>0,G37>0,H37>0,I37>0),"表示（判定）","×表示しない") -> 表示（判定）
C38: 管きょ費 | E38: 589007 | F38: 599899 | G38: =W38 -> 586230 | H38: =S38 -> 564665 | I38: 719507 | J38: =IF(AND(F38=0,$H38=0),"－ ",$H38-F38) -> -35234 | K38: =IF(AND(F38=0,$H38>0),"皆増 ",IF(AND(F38>0,$H38=0),"皆減 ",IF(AND(F38=0,$H38=0),"－ ",J38/F38))) -> -0.05873322 | L38: =IF(AND(G38=0,$H38=0),"－ ",$H38-G38) -> -21565 | M38: =IF(AND(G38=0,$H38>0),"皆増 ",IF(AND(G38>0,$H38=0),"皆減 ",IF(AND(G38=0,$H38=0),"－ ",L38/G38))) -> -0.036785903 | N38: =IF(AND(I38=0,$H38=0),"－ ",$H38-I38) -> -154842 | O38: =IF(AND(I38=0,$H38>0),"皆増 ",IF(AND(I38>0,$H38=0),"皆減 ",IF(AND(I38=0,$H38=0),"－ ",N38/I38))) -> -0.21520569 | P38: =IF(OR(F38>0,G38>0,H38>0,I38>0),"表示（判定）","×表示しない") -> 表示（判定） | R38: ='[1]3条支出'!T6 -> 564664608 | S38: =ROUND(R38/1000,0)+T38 -> 564665 | U38: 586230 | W38: =SUM(U38:V38) -> 586230
C39: 水質指導費 | E39: 71637 | F39: 60255 | G39: =W39 -> 51456 | H39: =S39 -> 51313 | I39: 50382 | J39: =IF(AND(F39=0,$H39=0),"－ ",$H39-F39) -> -8942 | K39: =IF(AND(F39=0,$H39>0),"皆増 ",IF(AND(F39>0,$H39=0),"皆減 ",IF(AND(F39=0,$H39=0),"－ ",J39/F39))) -> -0.14840262 | L39: =IF(AND(G39=0,$H39=0),"－ ",$H39-G39) -> -143 | M39: =IF(AND(G39=0,$H39>0),"皆増 ",IF(AND(G39>0,$H39=0),"皆減 ",IF(AND(G39=0,$H39=0),"－ ",L39/G39))) -> -0.0027790734 | N39: =IF(AND(I39=0,$H39=0),"－ ",$H39-I39) -> 931 | O39: =IF(AND(I39=0,$H39>0),"皆増 ",IF(AND(I39>0,$H39=0),"皆減 ",IF(AND(I39=0,$H39=0),"－ ",N39/I39))) -> 0.018478822 | P39: =IF(OR(F39>0,G39>0,H39>0,I39>0),"表示（判定）","×表示しない") -> 表示（判定） | R39: ='[1]3条支出'!T7 -> 51313295 | S39: =ROUND(R39/1000,0)+T39 -> 51313 | U39: 51456 | W39: =SUM(U39:V39) -> 51456
C40: ポンプ場費 | E40: 2362983 | F40: 2337248 | G40: =W40 -> 2257378 | H40: =S40 -> 2251658 | I40: 2188384 | J40: =IF(AND(F40=0,$H40=0),"－ ",$H40-F40) -> -85590 | K40: =IF(AND(F40=0,$H40>0),"皆増 ",IF(AND(F40>0,$H40=0),"皆減 ",IF(AND(F40=0,$H40=0),"－ ",J40/F40))) -> -0.036619991 | L40: =IF(AND(G40=0,$H40=0),"－ ",$H40-G40) -> -5720 | M40: =IF(AND(G40=0,$H40>0),"皆増 ",IF(AND(G40>0,$H40=0),"皆減 ",IF(AND(G40=0,$H40=0),"－ ",L40/G40))) -> -0.0025339132 | N40: =IF(AND(I40=0,$H40=0),"－ ",$H40-I40) -> 63274 | O40: =IF(AND(I40=0,$H40>0),"皆増 ",IF(AND(I40>0,$H40=0),"皆減 ",IF(AND(I40=0,$H40=0),"－ ",N40/I40))) -> 0.028913573 | P40: =IF(OR(F40>0,G40>0,H40>0,I40>0),"表示（判定）","×表示しない") -> 表示（判定） | R40: ='[1]3条支出'!T8 -> 2251657967 | S40: =ROUND(R40/1000,0)+T40 -> 2251658 | U40: 2257378 | W40: =SUM(U40:V40) -> 2257378
C41: 処理場費 | E41: 5009251 | F41: =6489024+52311 -> 6541335 | G41: =W41 -> 6145362 | H41: =S41 -> 6037810 | I41: 5500570 | J41: =IF(AND(F41=0,$H41=0),"－ ",$H41-F41) -> -503525 | K41: =IF(AND(F41=0,$H41>0),"皆増 ",IF(AND(F41>0,$H41=0),"皆減 ",IF(AND(F41=0,$H41=0),"－ ",J41/F41))) -> -0.076975877 | L41: =IF(AND(G41=0,$H41=0),"－ ",$H41-G41) -> -107552 | M41: =IF(AND(G41=0,$H41>0),"皆増 ",IF(AND(G41>0,$H41=0),"皆減 ",IF(AND(G41=0,$H41=0),"－ ",L41/G41))) -> -0.017501329 | N41: =IF(AND(I41=0,$H41=0),"－ ",$H41-I41) -> 537240 | O41: =IF(AND(I41=0,$H41>0),"皆増 ",IF(AND(I41>0,$H41=0),"皆減 ",IF(AND(I41=0,$H41=0),"－ ",N41/I41))) -> 0.097669878 | P41: =IF(OR(F41>0,G41>0,H41>0,I41>0),"表示（判定）","×表示しない") -> 表示（判定） | R41: ='[1]3条支出'!T9 -> 6037810078 | S41: =ROUND(R41/1000,0)+T41 -> 6037810 | U41: 6145362 | W41: =SUM(U41:V41) -> 6145362
C42: 普及促進費 | E42: 92445 | F42: 78046 | G42: =W42 -> 85747 | H42: =S42 -> 87134 | I42: 73348 | J42: =IF(AND(F42=0,$H42=0),"－ ",$H42-F42) -> 9088 | K42: =IF(AND(F42=0,$H42>0),"皆増 ",IF(AND(F42>0,$H42=0),"皆減 ",IF(AND(F42=0,$H42=0),"－ ",J42/F42))) -> 0.11644415 | L42: =IF(AND(G42=0,$H42=0),"－ ",$H42-G42) -> 1387 | M42: =IF(AND(G42=0,$H42>0),"皆増 ",IF(AND(G42>0,$H42=0),"皆減 ",IF(AND(G42=0,$H42=0),"－ ",L42/G42))) -> 0.016175493 | N42: =IF(AND(I42=0,$H42=0),"－ ",$H42-I42) -> 13786 | O42: =IF(AND(I42=0,$H42>0),"皆増 ",IF(AND(I42>0,$H42=0),"皆減 ",IF(AND(I42=0,$H42=0),"－ ",N42/I42))) -> 0.18795332 | P42: =IF(OR(F42>0,G42>0,H42>0,I42>0),"表示（判定）","×表示しない") -> 表示（判定） | R42: ='[1]3条支出'!T11 -> 87134052 | S42: =ROUND(R42/1000,0)+T42 -> 87134 | U42: 85747 | W42: =SUM(U42:V42) -> 85747
C43: 水洗化貸付事業費 | E43: 18143 | F43: 14660 | G43: =W43 -> 10611 | H43: =S43 -> 10396 | I43: 10663 | J43: =IF(AND(F43=0,$H43=0),"－ ",$H43-F43) -> -4264 | K43: =IF(AND(F43=0,$H43>0),"皆増 ",IF(AND(F43>0,$H43=0),"皆減 ",IF(AND(F43=0,$H43=0),"－ ",J43/F43))) -> -0.29085948 | L43: =IF(AND(G43=0,$H43=0),"－ ",$H43-G43) -> -215 | M43: =IF(AND(G43=0,$H43>0),"皆増 ",IF(AND(G43>0,$H43=0),"皆減 ",IF(AND(G43=0,$H43=0),"－ ",L43/G43))) -> -0.020261992 | N43: =IF(AND(I43=0,$H43=0),"－ ",$H43-I43) -> -267 | O43: =IF(AND(I43=0,$H43>0),"皆増 ",IF(AND(I43>0,$H43=0),"皆減 ",IF(AND(I43=0,$H43=0),"－ ",N43/I43))) -> -0.025039857 | P43: =IF(OR(F43>0,G43>0,H43>0,I43>0),"表示（判定）","×表示しない") -> 表示（判定） | R43: ='[1]3条支出'!T12 -> 10396270 | S43: =ROUND(R43/1000,0)+T43 -> 10396 | U43: 10611 | W43: =SUM(U43:V43) -> 10611
C44: 業務費 | E44: 989662 | F44: 941911 | G44: =W44 -> 930360 | H44: =S44 -> 929692 | I44: 958816 | J44: =IF(AND(F44=0,$H44=0),"－ ",$H44-F44) -> -12219 | K44: =IF(AND(F44=0,$H44>0),"皆増 ",IF(AND(F44>0,$H44=0),"皆減 ",IF(AND(F44=0,$H44=0),"－ ",J44/F44))) -> -0.012972563 | L44: =IF(AND(G44=0,$H44=0),"－ ",$H44-G44) -> -668 | M44: =IF(AND(G44=0,$H44>0),"皆増 ",IF(AND(G44>0,$H44=0),"皆減 ",IF(AND(G44=0,$H44=0),"－ ",L44/G44))) -> -0.00071800163 | N44: =IF(AND(I44=0,$H44=0),"－ ",$H44-I44) -> -29124 | O44: =IF(AND(I44=0,$H44>0),"皆増 ",IF(AND(I44>0,$H44=0),"皆減 ",IF(AND(I44=0,$H44=0),"－ ",N44/I44))) -> -0.030374962 | P44: =IF(OR(F44>0,G44>0,H44>0,I44>0),"表示（判定）","×表示しない") -> 表示（判定） | R44: ='[1]3条支出'!T13 -> 929691714 | S44: =ROUND(R44/1000,0)+T44 -> 929692 | U44: 930360 | W44: =SUM(U44:V44) -> 930360
C45: 総係費 | E45: 592338 | F45: 531318 | G45: =W45 -> 496650 | H45: =S45 -> 466287 | I45: 523364 | J45: =IF(AND(F45=0,$H45=0),"－ ",$H45-F45) -> -65031 | K45: =IF(AND(F45=0,$H45>0),"皆増 ",IF(AND(F45>0,$H45=0),"皆減 ",IF(AND(F45=0,$H45=0),"－ ",J45/F45))) -> -0.12239563 | L45: =IF(AND(G45=0,$H45=0),"－ ",$H45-G45) -> -30363 | M45: =IF(AND(G45=0,$H45>0),"皆増 ",IF(AND(G45>0,$H45=0),"皆減 ",IF(AND(G45=0,$H45=0),"－ ",L45/G45))) -> -0.061135609 | N45: =IF(AND(I45=0,$H45=0),"－ ",$H45-I45) -> -57077 | O45: =IF(AND(I45=0,$H45>0),"皆増 ",IF(AND(I45>0,$H45=0),"皆減 ",IF(AND(I45=0,$H45=0),"－ ",N45/I45))) -> -0.10905794 | P45: =IF(OR(F45>0,G45>0,H45>0,I45>0),"表示（判定）","×表示しない") -> 表示（判定） | R45: ='[1]3条支出'!T14 -> 466286409 | S45: =ROUND(R45/1000,0)+T45 -> 466287 | T45: 1 | U45: 496650 | W45: =SUM(U45:V45) -> 496650
C46: 特環公共下水道費 | E46: 34809 | F46: =98793+623 -> 99416 | G46: =W46 -> 99545 | H46: =S46 -> 97277 | I46: 98056 | J46: =IF(AND(F46=0,$H46=0),"－ ",$H46-F46) -> -2139 | K46: =IF(AND(F46=0,$H46>0),"皆増 ",IF(AND(F46>0,$H46=0),"皆減 ",IF(AND(F46=0,$H46=0),"－ ",J46/F46))) -> -0.021515651 | L46: =IF(AND(G46=0,$H46=0),"－ ",$H46-G46) -> -2268 | M46: =IF(AND(G46=0,$H46>0),"皆増 ",IF(AND(G46>0,$H46=0),"皆減 ",IF(AND(G46=0,$H46=0),"－ ",L46/G46))) -> -0.022783666 | N46: =IF(AND(I46=0,$H46=0),"－ ",$H46-I46) -> -779 | O46: =IF(AND(I46=0,$H46>0),"皆増 ",IF(AND(I46>0,$H46=0),"皆減 ",IF(AND(I46=0,$H46=0),"－ ",N46/I46))) -> -0.0079444399 | P46: =IF(OR(F46>0,G46>0,H46>0,I46>0),"表示（判定）","×表示しない") -> 表示（判定） | R46: ='[1]3条支出'!T15 -> 97276922 | S46: =ROUND(R46/1000,0)+T46 -> 97277 | U46: 99545 | W46: =SUM(U46:V46) -> 99545
C47: 農業集落排水費 | E47: 172556 | F47: =233770+4311 -> 238081 | G47: =W47 -> 227999 | H47: =S47 -> 225168 | I47: 220773 | J47: =IF(AND(F47=0,$H47=0),"－ ",$H47-F47) -> -12913 | K47: =IF(AND(F47=0,$H47>0),"皆増 ",IF(AND(F47>0,$H47=0),"皆減 ",IF(AND(F47=0,$H47=0),"－ ",J47/F47))) -> -0.054237843 | L47: =IF(AND(G47=0,$H47=0),"－ ",$H47-G47) -> -2831 | M47: =IF(AND(G47=0,$H47>0),"皆増 ",IF(AND(G47>0,$H47=0),"皆減 ",IF(AND(G47=0,$H47=0),"－ ",L47/G47))) -> -0.012416721 | N47: =IF(AND(I47=0,$H47=0),"－ ",$H47-I47) -> 4395 | O47: =IF(AND(I47=0,$H47>0),"皆増 ",IF(AND(I47>0,$H47=0),"皆減 ",IF(AND(I47=0,$H47=0),"－ ",N47/I47))) -> 0.019907326 | P47: =IF(OR(F47>0,G47>0,H47>0,I47>0),"表示（判定）","×表示しない") -> 表示（判定） | R47: ='[1]3条支出'!T16 -> 225167795 | S47: =ROUND(R47/1000,0)+T47 -> 225168 | U47: 227999 | W47: =SUM(U47:V47) -> 227999
C48: 浄化槽費 | E48: 5865 | F48: 71975 | G48: =W48 -> 70452 | H48: =S48 -> 69941 | I48: 65034 | J48: =IF(AND(F48=0,$H48=0),"－ ",$H48-F48) -> -2034 | K48: =IF(AND(F48=0,$H48>0),"皆増 ",IF(AND(F48>0,$H48=0),"皆減 ",IF(AND(F48=0,$H48=0),"－ ",J48/F48))) -> -0.028259812 | L48: =IF(AND(G48=0,$H48=0),"－ ",$H48-G48) -> -511 | M48: =IF(AND(G48=0,$H48>0),"皆増 ",IF(AND(G48>0,$H48=0),"皆減 ",IF(AND(G48=0,$H48=0),"－ ",L48/G48))) -> -0.0072531653 | N48: =IF(AND(I48=0,$H48=0),"－ ",$H48-I48) -> 4907 | O48: =IF(AND(I48=0,$H48>0),"皆増 ",IF(AND(I48>0,$H48=0),"皆減 ",IF(AND(I48=0,$H48=0),"－ ",N48/I48))) -> 0.07545284 | P48: =IF(OR(F48>0,G48>0,H48>0,I48>0),"表示（判定）","×表示しない") -> 表示（判定） | R48: ='[1]3条支出'!T17 -> 69941329 | S48: =ROUND(R48/1000,0)+T48 -> 69941 | U48: 70452 | W48: =SUM(U48:V48) -> 70452
C49: 減価償却費 | E49: 14647769 | F49: 26580629 | G49: =W49 -> 26549687 | H49: =S49 -> 26551442 | I49: 26646058 | J49: =IF(AND(F49=0,$H49=0),"－ ",$H49-F49) -> -29187 | K49: =IF(AND(F49=0,$H49>0),"皆増 ",IF(AND(F49>0,$H49=0),"皆減 ",IF(AND(F49=0,$H49=0),"－ ",J49/F49))) -> -0.0010980553 | L49: =IF(AND(G49=0,$H49=0),"－ ",$H49-G49) -> 1755 | M49: =IF(AND(G49=0,$H49>0),"皆増 ",IF(AND(G49>0,$H49=0),"皆減 ",IF(AND(G49=0,$H49=0),"－ ",L49/G49))) -> 6.6102474e-05 | N49: =IF(AND(I49=0,$H49=0),"－ ",$H49-I49) -> -94616 | O49: =IF(AND(I49=0,$H49>0),"皆増 ",IF(AND(I49>0,$H49=0),"皆減 ",IF(AND(I49=0,$H49=0),"－ ",N49/I49))) -> -0.0035508442 | P49: =IF(OR(F49>0,G49>0,H49>0,I49>0),"表示（判定）","×表示しない") -> 表示（判定） | R49: ='[1]3条支出'!T19 -> 26551442230 | S49: =ROUND(R49/1000,0)+T49 -> 26551442 | U49: 26549687 | W49: =SUM(U49:V49) -> 26549687
C50: 資産減耗費 | E50: 378741 | F50: 351538 | G50: =W50 -> 520692 | H50: =S50 -> 503762 | I50: 402404 | J50: =IF(AND(F50=0,$H50=0),"－ ",$H50-F50) -> 152224 | K50: =IF(AND(F50=0,$H50>0),"皆増 ",IF(AND(F50>0,$H50=0),"皆減 ",IF(AND(F50=0,$H50=0),"－ ",J50/F50))) -> 0.43302289 | L50: =IF(AND(G50=0,$H50=0),"－ ",$H50-G50) -> -16930 | M50: =IF(AND(G50=0,$H50>0),"皆増 ",IF(AND(G50>0,$H50=0),"皆減 ",IF(AND(G50=0,$H50=0),"－ ",L50/G50))) -> -0.032514423 | N50: =IF(AND(I50=0,$H50=0),"－ ",$H50-I50) -> 101358 | O50: =IF(AND(I50=0,$H50>0),"皆増 ",IF(AND(I50>0,$H50=0),"皆減 ",IF(AND(I50=0,$H50=0),"－ ",N50/I50))) -> 0.25188119 | P50: =IF(OR(F50>0,G50>0,H50>0,I50>0),"表示（判定）","×表示しない") -> 表示（判定） | R50: ='[1]3条支出'!T20 -> 503761871 | S50: =ROUND(R50/1000,0)+T50 -> 503762 | U50: 520692 | W50: =SUM(U50:V50) -> 520692
B51: 営業外費用 | E51: =SUM(E52:E54) -> 16171804 | F51: =SUM(F52:F54) -> 4417315 | G51: =SUM(G52:G54) -> 4144435 | H51: =SUM(H52:H54) -> 4161564 | I51: =SUM(I52:I54) -> 4589507 | J51: =IF(AND(F51=0,$H51=0),"－ ",$H51-F51) -> -255751 | K51: =IF(AND(F51=0,$H51>0),"皆増 ",IF(AND(F51>0,$H51=0),"皆減 ",IF(AND(F51=0,$H51=0),"－ ",J51/F51))) -> -0.057897388 | L51: =IF(AND(G51=0,$H51=0),"－ ",$H51-G51) -> 17129 | M51: =IF(AND(G51=0,$H51>0),"皆増 ",IF(AND(G51>0,$H51=0),"皆減 ",IF(AND(G51=0,$H51=0),"－ ",L51/G51))) -> 0.0041330121 | N51: =IF(AND(I51=0,$H51=0),"－ ",$H51-I51) -> -427943 | O51: =IF(AND(I51=0,$H51>0),"皆増 ",IF(AND(I51>0,$H51=0),"皆減 ",IF(AND(I51=0,$H51=0),"－ ",N51/I51))) -> -0.093243784 | P51: =IF(OR(F51>0,G51>0,H51>0,I51>0),"表示（判定）","×表示しない") -> 表示（判定）
C52: 支払利息及び企業債取扱諸費 | E52: 16052113 | F52: 4199707 | G52: =W52 -> 3940345 | H52: =S52 -> 3940342 | I52: 4396333 | J52: =IF(AND(F52=0,$H52=0),"－ ",$H52-F52) -> -259365 | K52: =IF(AND(F52=0,$H52>0),"皆増 ",IF(AND(F52>0,$H52=0),"皆減 ",IF(AND(F52=0,$H52=0),"－ ",J52/F52))) -> -0.06175788 | L52: =IF(AND(G52=0,$H52=0),"－ ",$H52-G52) -> -3 | M52: =IF(AND(G52=0,$H52>0),"皆増 ",IF(AND(G52>0,$H52=0),"皆減 ",IF(AND(G52=0,$H52=0),"－ ",L52/G52))) -> -7.6135465e-07 | N52: =IF(AND(I52=0,$H52=0),"－ ",$H52-I52) -> -455991 | O52: =IF(AND(I52=0,$H52>0),"皆増 ",IF(AND(I52>0,$H52=0),"皆減 ",IF(AND(I52=0,$H52=0),"－ ",N52/I52))) -> -0.10372076 | P52: =IF(OR(F52>0,G52>0,H52>0,I52>0),"表示（判定）","×表示しない") -> 表示（判定） | R52: ='[1]3条支出'!T23 -> 3940341717 | S52: =ROUND(R52/1000,0)+T52 -> 3940342 | U52: 3940345 | W52: =SUM(U52:V52) -> 3940345
C53: 消費税及び地方消費税 | E53: 0 | G53: 0 | H53: 0 | I53: 0 | J53: =IF(AND(F53=0,$H53=0),"－ ",$H53-F53) -> － | K53: =IF(AND(F53=0,$H53>0),"皆増 ",IF(AND(F53>0,$H53=0),"皆減 ",IF(AND(F53=0,$H53=0),"－ ",J53/F53))) -> － | L53: =IF(AND(G53=0,$H53=0),"－ ",$H53-G53) -> － | M53: =IF(AND(G53=0,$H53>0),"皆増 ",IF(AND(G53>0,$H53=0),"皆減 ",IF(AND(G53=0,$H53=0),"－ ",L53/G53))) -> － | N53: =IF(AND(I53=0,$H53=0),"－ ",$H53-I53) -> － | O53: =IF(AND(I53=0,$H53>0),"皆増 ",IF(AND(I53>0,$H53=0),"皆減 ",IF(AND(I53=0,$H53=0),"－ ",N53/I53))) -> － | P53: =IF(OR(F53>0,G53>0,H53>0,I53>0),"表示（判定）","×表示しない") -> ×表示しない
C54: 雑支出 | E54: 119691 | F54: 217608 | G54: =W54 -> 204090 | H54: =S54 -> 221222 | I54: 193174 | J54: =IF(AND(F54=0,$H54=0),"－ ",$H54-F54) -> 3614 | K54: =IF(AND(F54=0,$H54>0),"皆増 ",IF(AND(F54>0,$H54=0),"皆減 ",IF(AND(F54=0,$H54=0),"－ ",J54/F54))) -> 0.016607845 | L54: =IF(AND(G54=0,$H54=0),"－ ",$H54-G54) -> 17132 | M54: =IF(AND(G54=0,$H54>0),"皆増 ",IF(AND(G54>0,$H54=0),"皆減 ",IF(AND(G54=0,$H54=0),"－ ",L54/G54))) -> 0.083943358 | N54: =IF(AND(I54=0,$H54=0),"－ ",$H54-I54) -> 28048 | O54: =IF(AND(I54=0,$H54>0),"皆増 ",IF(AND(I54>0,$H54=0),"皆減 ",IF(AND(I54=0,$H54=0),"－ ",N54/I54))) -> 0.14519552 | P54: =IF(OR(F54>0,G54>0,H54>0,I54>0),"表示（判定）","×表示しない") -> 表示（判定） | R54: ='[1]3条支出'!T24+'[1]3条支出'!$T$25 -> 221221824 | S54: =ROUND(R54/1000,0)+T54 -> 221222 | U54: 196817 | V54: 7273 | W54: =SUM(U54:V54) -> 204090
B55: 特別損失 | E55: =SUM(E56:E59) -> 55925 | F55: =SUM(F56:F59) -> 7550 | G55: =SUM(G56:G59) -> 21529 | H55: =SUM(H56:H59) -> 20026 | I55: =SUM(I56:I59) -> 4842 | J55: =IF(AND(F55=0,$H55=0),"－ ",$H55-F55) -> 12476 | K55: =IF(AND(F55=0,$H55>0),"皆増 ",IF(AND(F55>0,$H55=0),"皆減 ",IF(AND(F55=0,$H55=0),"－ ",J55/F55))) -> 1.6524503 | L55: =IF(AND(G55=0,$H55=0),"－ ",$H55-G55) -> -1503 | M55: =IF(AND(G55=0,$H55>0),"皆増 ",IF(AND(G55>0,$H55=0),"皆減 ",IF(AND(G55=0,$H55=0),"－ ",L55/G55))) -> -0.069812811 | N55: =IF(AND(I55=0,$H55=0),"－ ",$H55-I55) -> 15184 | O55: =IF(AND(I55=0,$H55>0),"皆増 ",IF(AND(I55>0,$H55=0),"皆減 ",IF(AND(I55=0,$H55=0),"－ ",N55/I55))) -> 3.1358943 | P55: =IF(OR(F55>0,G55>0,H55>0,I55>0),"表示（判定）","×表示しない") -> 表示（判定）
C56: 固定資産売却損 | E56: 0 | F56: 0 | G56: =W56 -> 10315 | H56: =S56 -> 10315 | I56: 0 | J56: =IF(AND(F56=0,$H56=0),"－ ",$H56-F56) -> 10315 | K56: =IF(AND(F56=0,$H56>0),"皆増 ",IF(AND(F56>0,$H56=0),"皆減 ",IF(AND(F56=0,$H56=0),"－ ",J56/F56))) -> 皆増 | L56: =IF(AND(G56=0,$H56=0),"－ ",$H56-G56) -> 0 | M56: =IF(AND(G56=0,$H56>0),"皆増 ",IF(AND(G56>0,$H56=0),"皆減 ",IF(AND(G56=0,$H56=0),"－ ",L56/G56))) -> 0 | N56: =IF(AND(I56=0,$H56=0),"－ ",$H56-I56) -> 10315 | O56: =IF(AND(I56=0,$H56>0),"皆増 ",IF(AND(I56>0,$H56=0),"皆減 ",IF(AND(I56=0,$H56=0),"－ ",N56/I56))) -> 皆増 | P56: =IF(OR(F56>0,G56>0,H56>0,I56>0),"表示（判定）","×表示しない") -> 表示（判定） | R56: ='[1]3条支出'!$T$30 -> 10315355 | S56: =ROUND(R56/1000,0)+T56 -> 10315 | U56: 10315 | W56: =SUM(U56:V56) -> 10315
C57: 過年度損益修正損 | E57: 41531 | F57: 7512 | G57: =W57 -> 11176 | H57: =S57 -> 9711 | I57: 4840 | J57: =IF(AND(F57=0,$H57=0),"－ ",$H57-F57) -> 2199 | K57: =IF(AND(F57=0,$H57>0),"皆増 ",IF(AND(F57>0,$H57=0),"皆減 ",IF(AND(F57=0,$H57=0),"－ ",J57/F57))) -> 0.29273163 | L57: =IF(AND(G57=0,$H57=0),"－ ",$H57-G57) -> -1465 | M57: =IF(AND(G57=0,$H57>0),"皆増 ",IF(AND(G57>0,$H57=0),"皆減 ",IF(AND(G57=0,$H57=0),"－ ",L57/G57))) -> -0.13108447 | N57: =IF(AND(I57=0,$H57=0),"－ ",$H57-I57) -> 4871 | O57: =IF(AND(I57=0,$H57>0),"皆増 ",IF(AND(I57>0,$H57=0),"皆減 ",IF(AND(I57=0,$H57=0),"－ ",N57/I57))) -> 1.006405 | P57: =IF(OR(F57>0,G57>0,H57>0,I57>0),"表示（判定）","×表示しない") -> 表示（判定） | R57: ='[1]3条支出'!$T$28 -> 9711499 | S57: =ROUND(R57/1000,0)+T57 -> 9711 | U57: 11176 | W57: =SUM(U57:V57) -> 11176
C58: 減損損失 | F58: 0 | G58: =W58 -> 0 | H58: =S58 -> 0 | I58: 0 | J58: =IF(AND(F58=0,$H58=0),"－ ",$H58-F58) -> － | K58: =IF(AND(F58=0,$H58>0),"皆増 ",IF(AND(F58>0,$H58=0),"皆減 ",IF(AND(F58=0,$H58=0),"－ ",J58/F58))) -> － | L58: =IF(AND(G58=0,$H58=0),"－ ",$H58-G58) -> － | M58: =IF(AND(G58=0,$H58>0),"皆増 ",IF(AND(G58>0,$H58=0),"皆減 ",IF(AND(G58=0,$H58=0),"－ ",L58/G58))) -> － | N58: =IF(AND(I58=0,$H58=0),"－ ",$H58-I58) -> － | O58: =IF(AND(I58=0,$H58>0),"皆増 ",IF(AND(I58>0,$H58=0),"皆減 ",IF(AND(I58=0,$H58=0),"－ ",N58/I58))) -> － | P58: =IF(OR(F58>0,G58>0,H58>0,I58>0),"表示（判定）","×表示しない") -> ×表示しない | R58: ='[1]3条支出'!$T$31 -> 0 | S58: =ROUND(R58/1000,0)+T58 -> 0 | U58: 0 | W58: =SUM(U58:V58) -> 0
C59: その他特別損失 | E59: 14394 | F59: 38 | G59: =W59 -> 38 | H59: =S59 -> 0 | I59: 2 | J59: =IF(AND(F59=0,$H59=0),"－ ",$H59-F59) -> -38 | K59: =IF(AND(F59=0,$H59>0),"皆増 ",IF(AND(F59>0,$H59=0),"皆減 ",IF(AND(F59=0,$H59=0),"－ ",J59/F59))) -> 皆減 | L59: =IF(AND(G59=0,$H59=0),"－ ",$H59-G59) -> -38 | M59: =IF(AND(G59=0,$H59>0),"皆増 ",IF(AND(G59>0,$H59=0),"皆減 ",IF(AND(G59=0,$H59=0),"－ ",L59/G59))) -> 皆減 | N59: =IF(AND(I59=0,$H59=0),"－ ",$H59-I59) -> -2 | O59: =IF(AND(I59=0,$H59>0),"皆増 ",IF(AND(I59>0,$H59=0),"皆減 ",IF(AND(I59=0,$H59=0),"－ ",N59/I59))) -> 皆減 | P59: =IF(OR(F59>0,G59>0,H59>0,I59>0),"表示（判定）","×表示しない") -> 表示（判定） | R59: ='[1]3条支出'!$T$29 -> 0 | S59: =ROUND(R59/1000,0)+T59 -> 0 | U59: 38 | W59: =SUM(U59:V59) -> 38
B60: 予備費 | E60: 0 | F60: 18182 | G60: =W60 -> 0 | H60: 0 | I60: 0 | J60: =IF(AND(F60=0,$H60=0),"－ ",$H60-F60) -> -18182 | K60: =IF(AND(F60=0,$H60>0),"皆増 ",IF(AND(F60>0,$H60=0),"皆減 ",IF(AND(F60=0,$H60=0),"－ ",J60/F60))) -> 皆減 | L60: =IF(AND(G60=0,$H60=0),"－ ",$H60-G60) -> － | M60: =IF(AND(G60=0,$H60>0),"皆増 ",IF(AND(G60>0,$H60=0),"皆減 ",IF(AND(G60=0,$H60=0),"－ ",L60/G60))) -> － | N60: =IF(AND(I60=0,$H60=0),"－ ",$H60-I60) -> － | O60: =IF(AND(I60=0,$H60>0),"皆増 ",IF(AND(I60>0,$H60=0),"皆減 ",IF(AND(I60=0,$H60=0),"－ ",N60/I60))) -> － | P60: =IF(OR(F60>0,G60>0,H60>0,I60>0),"表示（判定）","×表示しない") -> 表示（判定） | U60: 7273 | V60: -7273 | W60: =SUM(U60:V60) -> 0
P61: 表示
A62: 収支差引（純利益） | E62: =E9-E36 -> 9623 | F62: =F9-F36 -> 120300 | G62: =G9-G36 -> 87814 | H62: =H9-H36 -> 543907 | I62: =I9-I36 -> 447981 | J62: =IF(AND(F62=0,$H62=0),"－ ",$H62-F62) -> 423607 | K62: =IF(AND(F62=0,$H62>0),"皆増 ",IF(AND(F62>0,$H62=0),"皆減 ",IF(AND(F62=0,$H62=0),"－ ",J62/F62))) -> 3.5212552 | L62: =IF(AND(G62=0,$H62=0),"－ ",$H62-G62) -> 456093 | M62: =IF(AND(G62=0,$H62>0),"皆増 ",IF(AND(G62>0,$H62=0),"皆減 ",IF(AND(G62=0,$H62=0),"－ ",L62/G62))) -> 5.1938529 | N62: =IF(AND(I62=0,$H62=0),"－ ",$H62-I62) -> 95926 | O62: =IF(AND(I62=0,$H62>0),"皆増 ",IF(AND(I62>0,$H62=0),"皆減 ",IF(AND(I62=0,$H62=0),"－ ",N62/I62))) -> 0.21412962 | P62: 表示 | R62: 各項目 合計 → | S62: =SUM(S38:S60) -> 42028135
B63: 当年度補てん財源分 | P63: ×表示しない
B64: 翌年度補てん財源分 | P64: ×表示しない
Q67: 収支差引 | R67: =R9-R36 -> -42028134935 | S67: =S33-S62 -> 543907

Sheet 3条税込
A3: =CONCATENATE("令和",+DBCS(MID(出資金しくみ!B1,3,1)),"年度決算 収益的収支（税込）") -> 令和５年度決算 収益的収支（税込） | O3: =総括表!$K$1 -> 令和6年5月22日
A5: 収 入 | O5: （単位：千円、％）
J6: 差引増減
A7: 区分 | E7: 財政収支計画 （参考） | F7: Ｒ５ 議決予算 | G7: Ｒ５ 決見（4月） | H7: Ｒ５ 決算 | I7: Ｒ４ 決算 | J7: 対Ｒ５議決予算 | L7: 対Ｒ５決見（4月） | N7: 対Ｒ４決算 | R7: R5決算 | U7: 令和5年度4月決見
F8: (a) | G8: (b) | H8: (c) | I8: (d) | J8: (c-a) | K8: 率 | L8: (c-b) | M8: 率 | N8: (c-d) | O8: 率 | P8: 表示判定 | Q8: AAA | R8: （参照数式） | S8: 千円返還＋端数調整 | T8: ↓端数調整 | U8: 決見額千円 | V8: 調整 | W8: 決見額千円
A9: 下水道事業収益 | E9: =SUM(E10,E19,E27) -> 41202558 | F9: =SUM(F10,F19,F27) -> 44975817 | G9: =SUM(G10,G19,G27) -> 44165221 | H9: =SUM(H10,H19,H27) -> 44454712 | I9: =SUM(I10,I19,I27) -> 44381298 | J9: =IF(AND(F9=0,$H9=0),"－ ",$H9-F9) -> -521105 | K9: =IF(AND(F9=0,$H9>0),"皆増 ",IF(AND(F9>0,$H9=0),"皆減 ",IF(AND(F9=0,$H9=0),"－ ",J9/F9))) -> -0.011586338 | L9: =IF(AND(G9=0,$H9=0),"－ ",$H9-G9) -> 289491 | M9: =IF(AND(G9=0,$H9>0),"皆増 ",IF(AND(G9>0,$H9=0),"皆減 ",IF(AND(G9=0,$H9=0),"－ ",L9/G9))) -> 0.0065547278 | N9: =IF(AND(I9=0,$H9=0),"－ ",$H9-I9) -> 73414 | O9: =IF(AND(I9=0,$H9>0),"皆増 ",IF(AND(I9>0,$H9=0),"皆減 ",IF(AND(I9=0,$H9=0),"－ ",N9/I9))) -> 0.0016541652 | P9: =IF(OR(F9>0,G9>0,H9>0,I9>0),"表示（判定）","×表示しない") -> 表示（判定） | R9: =SUM(R10,R19,R27) -> 44454711283
B10: 営業収益 | E10: =SUM(E11:E12,E18) -> 39159297 | F10: =SUM(F11:F12,F18) -> 35444153 | G10: =SUM(G11:G12,G18) -> 34582538 | H10: =SUM(H11:H12,H18) -> 34865913 | I10: =SUM(I11:I12,I18) -> 34671095 | J10: =IF(AND(F10=0,$H10=0),"－ ",$H10-F10) -> -578240 | K10: =IF(AND(F10=0,$H10>0),"皆増 ",IF(AND(F10>0,$H10=0),"皆減 ",IF(AND(F10=0,$H10=0),"－ ",J10/F10))) -> -0.016314115 | L10: =IF(AND(G10=0,$H10=0),"－ ",$H10-G10) -> 283375 | M10: =IF(AND(G10=0,$H10>0),"皆増 ",IF(AND(G10>0,$H10=0),"皆減 ",IF(AND(G10=0,$H10=0),"－ ",L10/G10))) -> 0.0081941643 | N10: =IF(AND(I10=0,$H10=0),"－ ",$H10-I10) -> 194818 | O10: =IF(AND(I10=0,$H10>0),"皆増 ",IF(AND(I10>0,$H10=0),"皆減 ",IF(AND(I10=0,$H10=0),"－ ",N10/I10))) -> 0.0056190322 | P10: =IF(OR(F10>0,G10>0,H10>0,I10>0),"表示（判定）","×表示しない") -> 表示（判定） | R10: =SUM(R11:R12,R18) -> 34865911732
C11: 下水道使用料 | E11: 21145614 | F11: 21384728 | G11: 20441757 | H11: =S11 -> 20488963 | I11: 20482227 | J11: =IF(AND(F11=0,$H11=0),"－ ",$H11-F11) -> -895765 | K11: =IF(AND(F11=0,$H11>0),"皆増 ",IF(AND(F11>0,$H11=0),"皆減 ",IF(AND(F11=0,$H11=0),"－ ",J11/F11))) -> -0.041888071 | L11: =IF(AND(G11=0,$H11=0),"－ ",$H11-G11) -> 47206 | M11: =IF(AND(G11=0,$H11>0),"皆増 ",IF(AND(G11>0,$H11=0),"皆減 ",IF(AND(G11=0,$H11=0),"－ ",L11/G11))) -> 0.0023092927 | N11: =IF(AND(I11=0,$H11=0),"－ ",$H11-I11) -> 6736 | O11: =IF(AND(I11=0,$H11>0),"皆増 ",IF(AND(I11>0,$H11=0),"皆減 ",IF(AND(I11=0,$H11=0),"－ ",N11/I11))) -> 0.00032887049 | P11: =IF(OR(F11>0,G11>0,H11>0,I11>0),"表示（判定）","×表示しない") -> 表示（判定） | R11: ='[2]3条収入'!$E$8 -> 20488962528 | S11: =ROUND(R11/1000,0)+T11 -> 20488963 | U11: 18583417 | W11: =SUM(U11:V11) -> 18583417
C12: 一般会計負担金 | E12: 18011826 | F12: =SUM(F13:F17) -> 13854862 | G12: =SUM(G13:G17) -> 13951285 | H12: =SUM(H13:H17) -> 14187103 | I12: =SUM(I13:I17) -> 13993349 | J12: =IF(AND(F12=0,$H12=0),"－ ",$H12-F12) -> 332241 | K12: =IF(AND(F12=0,$H12>0),"皆増 ",IF(AND(F12>0,$H12=0),"皆減 ",IF(AND(F12=0,$H12=0),"－ ",J12/F12))) -> 0.023980102 | L12: =IF(AND(G12=0,$H12=0),"－ ",$H12-G12) -> 235818 | M12: =IF(AND(G12=0,$H12>0),"皆増 ",IF(AND(G12>0,$H12=0),"皆減 ",IF(AND(G12=0,$H12=0),"－ ",L12/G12))) -> 0.016902959 | N12: =IF(AND(I12=0,$H12=0),"－ ",$H12-I12) -> 193754 | O12: =IF(AND(I12=0,$H12>0),"皆増 ",IF(AND(I12>0,$H12=0),"皆減 ",IF(AND(I12=0,$H12=0),"－ ",N12/I12))) -> 0.013846149 | P12: =IF(OR(F12>0,G12>0,H12>0,I12>0),"表示（判定）","×表示しない") -> 表示（判定） | R12: =SUM(R13:R17) -> 14187102335
D13: 雨水処理負担金 | E13: =E12-E14-E15-E16 -> 17853307 | F13: 13738282 | G13: =13852072-8000 -> 13844072 | H13: =S13 -> 14079750 | I13: 13893559 | J13: =IF(AND(F13=0,$H13=0),"－ ",$H13-F13) -> 341468 | K13: =IF(AND(F13=0,$H13>0),"皆増 ",IF(AND(F13>0,$H13=0),"皆減 ",IF(AND(F13=0,$H13=0),"－ ",J13/F13))) -> 0.024855218 | L13: =IF(AND(G13=0,$H13=0),"－ ",$H13-G13) -> 235678 | M13: =IF(AND(G13=0,$H13>0),"皆増 ",IF(AND(G13>0,$H13=0),"皆減 ",IF(AND(G13=0,$H13=0),"－ ",L13/G13))) -> 0.017023749 | N13: =IF(AND(I13=0,$H13=0),"－ ",$H13-I13) -> 186191 | O13: =IF(AND(I13=0,$H13>0),"皆増 ",IF(AND(I13>0,$H13=0),"皆減 ",IF(AND(I13=0,$H13=0),"－ ",N13/I13))) -> 0.013401246 | P13: =IF(OR(F13>0,G13>0,H13>0,I13>0),"表示（判定）","×表示しない") -> 表示（判定） | R13: ='[2]3条収入'!$E$10 -> 14079749832 | S13: =ROUND(R13/1000,0)+T13 -> 14079750 | U13: 13852072 | V13: 8000 | W13: =SUM(U13:V13) -> 13860072
D14: 水質指導費負担金 | E14: 72773 | F14: 61778 | G14: 52650 | H14: =S14 -> 52444 | I14: 51549 | J14: =IF(AND(F14=0,$H14=0),"－ ",$H14-F14) -> -9334 | K14: =IF(AND(F14=0,$H14>0),"皆増 ",IF(AND(F14>0,$H14=0),"皆減 ",IF(AND(F14=0,$H14=0),"－ ",J14/F14))) -> -0.15108938 | L14: =IF(AND(G14=0,$H14=0),"－ ",$H14-G14) -> -206 | M14: =IF(AND(G14=0,$H14>0),"皆増 ",IF(AND(G14>0,$H14=0),"皆減 ",IF(AND(G14=0,$H14=0),"－ ",L14/G14))) -> -0.0039126306 | N14: =IF(AND(I14=0,$H14=0),"－ ",$H14-I14) -> 895 | O14: =IF(AND(I14=0,$H14>0),"皆増 ",IF(AND(I14>0,$H14=0),"皆減 ",IF(AND(I14=0,$H14=0),"－ ",N14/I14))) -> 0.017362121 | P14: =IF(OR(F14>0,G14>0,H14>0,I14>0),"表示（判定）","×表示しない") -> 表示（判定） | R14: ='[2]3条収入'!$E$14 -> 52443869 | S14: =ROUND(R14/1000,0)+T14 -> 52444 | U14: 52650 | W14: =SUM(U14:V14) -> 52650
D15: 普及促進費負担金 | E15: 67470 | F15: 40039 | G15: 43851 | H15: =S15 -> 44425 | I15: 37495 | J15: =IF(AND(F15=0,$H15=0),"－ ",$H15-F15) -> 4386 | K15: =IF(AND(F15=0,$H15>0),"皆増 ",IF(AND(F15>0,$H15=0),"皆減 ",IF(AND(F15=0,$H15=0),"－ ",J15/F15))) -> 0.1095432 | L15: =IF(AND(G15=0,$H15=0),"－ ",$H15-G15) -> 574 | M15: =IF(AND(G15=0,$H15>0),"皆増 ",IF(AND(G15>0,$H15=0),"皆減 ",IF(AND(G15=0,$H15=0),"－ ",L15/G15))) -> 0.013089781 | N15: =IF(AND(I15=0,$H15=0),"－ ",$H15-I15) -> 6930 | O15: =IF(AND(I15=0,$H15>0),"皆増 ",IF(AND(I15>0,$H15=0),"皆減 ",IF(AND(I15=0,$H15=0),"－ ",N15/I15))) -> 0.18482464 | P15: =IF(OR(F15>0,G15>0,H15>0,I15>0),"表示（判定）","×表示しない") -> 表示（判定） | R15: ='[2]3条収入'!$E$15 -> 44424775 | S15: =ROUND(R15/1000,0)+T15 -> 44425 | U15: 43851 | W15: =SUM(U15:V15) -> 43851
D16: 貸付事業費負担金 | E16: 18276 | F16: 14763 | G16: 10712 | H16: =S16 -> 10484 | I16: 10746 | J16: =IF(AND(F16=0,$H16=0),"－ ",$H16-F16) -> -4279 | K16: =IF(AND(F16=0,$H16>0),"皆増 ",IF(AND(F16>0,$H16=0),"皆減 ",IF(AND(F16=0,$H16=0),"－ ",J16/F16))) -> -0.28984624 | L16: =IF(AND(G16=0,$H16=0),"－ ",$H16-G16) -> -228 | M16: =IF(AND(G16=0,$H16>0),"皆増 ",IF(AND(G16>0,$H16=0),"皆減 ",IF(AND(G16=0,$H16=0),"－ ",L16/G16))) -> -0.021284541 | N16: =IF(AND(I16=0,$H16=0),"－ ",$H16-I16) -> -262 | O16: =IF(AND(I16=0,$H16>0),"皆増 ",IF(AND(I16>0,$H16=0),"皆減 ",IF(AND(I16=0,$H16=0),"－ ",N16/I16))) -> -0.024381165 | P16: =IF(OR(F16>0,G16>0,H16>0,I16>0),"表示（判定）","×表示しない") -> 表示（判定） | R16: ='[2]3条収入'!$E$16 -> 10483859 | S16: =ROUND(R16/1000,0)+T16 -> 10484 | U16: 10712 | W16: =SUM(U16:V16) -> 10712
D17: 高資本費対策費負担金 | E17: 0 | J17: =IF(AND(F17=0,$H17=0),"－ ",$H17-F17) -> － | K17: =IF(AND(F17=0,$H17>0),"皆増 ",IF(AND(F17>0,$H17=0),"皆減 ",IF(AND(F17=0,$H17=0),"－ ",J17/F17))) -> － | L17: =IF(AND(G17=0,$H17=0),"－ ",$H17-G17) -> － | M17: =IF(AND(G17=0,$H17>0),"皆増 ",IF(AND(G17>0,$H17=0),"皆減 ",IF(AND(G17=0,$H17=0),"－ ",L17/G17))) -> － | N17: =IF(AND(I17=0,$H17=0),"－ ",$H17-I17) -> － | O17: =IF(AND(I17=0,$H17>0),"皆増 ",IF(AND(I17>0,$H17=0),"皆減 ",IF(AND(I17=0,$H17=0),"－ ",N17/I17))) -> － | P17: =IF(OR(F17>0,G17>0,H17>0,I17>0),"表示（判定）","×表示しない") -> ×表示しない | U17: 172315 | W17: =SUM(U17:V17) -> 172315
C18: その他営業収益 | E18: 1857 | F18: 204563 | G18: 189496 | H18: =S18 -> 189847 | I18: 195519 | J18: =IF(AND(F18=0,$H18=0),"－ ",$H18-F18) -> -14716 | K18: =IF(AND(F18=0,$H18>0),"皆増 ",IF(AND(F18>0,$H18=0),"皆減 ",IF(AND(F18=0,$H18=0),"－ ",J18/F18))) -> -0.071938718 | L18: =IF(AND(G18=0,$H18=0),"－ ",$H18-G18) -> 351 | M18: =IF(AND(G18=0,$H18>0),"皆増 ",IF(AND(G18>0,$H18=0),"皆減 ",IF(AND(G18=0,$H18=0),"－ ",L18/G18))) -> 0.0018522818 | N18: =IF(AND(I18=0,$H18=0),"－ ",$H18-I18) -> -5672 | O18: =IF(AND(I18=0,$H18>0),"皆増 ",IF(AND(I18>0,$H18=0),"皆減 ",IF(AND(I18=0,$H18=0),"－ ",N18/I18))) -> -0.029009968 | P18: =IF(OR(F18>0,G18>0,H18>0,I18>0),"表示（判定）","×表示しない") -> 表示（判定） | R18: ='[2]3条収入'!$E$19 -> 189846869 | S18: =ROUND(R18/1000,0)+T18 -> 189847 | U18: 172315 | W18: =SUM(U18:V18) -> 172315
B19: 営業外収益 | E19: =SUM(E20:E26) -> 2040440 | F19: =SUM(F20:F26) -> 9528788 | G19: =SUM(G20:G26) -> 9579686 | H19: =SUM(H20:H26) -> 9584600 | I19: =SUM(I20:I26) -> 9703635 | J19: =IF(AND(F19=0,$H19=0),"－ ",$H19-F19) -> 55812 | K19: =IF(AND(F19=0,$H19>0),"皆増 ",IF(AND(F19>0,$H19=0),"皆減 ",IF(AND(F19=0,$H19=0),"－ ",J19/F19))) -> 0.0058571982 | L19: =IF(AND(G19=0,$H19=0),"－ ",$H19-G19) -> 4914 | M19: =IF(AND(G19=0,$H19>0),"皆増 ",IF(AND(G19>0,$H19=0),"皆減 ",IF(AND(G19=0,$H19=0),"－ ",L19/G19))) -> 0.00051296045 | N19: =IF(AND(I19=0,$H19=0),"－ ",$H19-I19) -> -119035 | O19: =IF(AND(I19=0,$H19>0),"皆増 ",IF(AND(I19>0,$H19=0),"皆減 ",IF(AND(I19=0,$H19=0),"－ ",N19/I19))) -> -0.012267053 | P19: =IF(OR(F19>0,G19>0,H19>0,I19>0),"表示（判定）","×表示しない") -> 表示（判定） | R19: =SUM(R20:R26) -> 9584600552
C20: 受取利息 | E20: 7130 | F20: 70 | G20: =W20 -> 87 | H20: =S20 -> 89 | I20: 63 | J20: =IF(AND(F20=0,$H20=0),"－ ",$H20-F20) -> 19 | K20: =IF(AND(F20=0,$H20>0),"皆増 ",IF(AND(F20>0,$H20=0),"皆減 ",IF(AND(F20=0,$H20=0),"－ ",J20/F20))) -> 0.27142857 | L20: =IF(AND(G20=0,$H20=0),"－ ",$H20-G20) -> 2 | M20: =IF(AND(G20=0,$H20>0),"皆増 ",IF(AND(G20>0,$H20=0),"皆減 ",IF(AND(G20=0,$H20=0),"－ ",L20/G20))) -> 0.022988506 | N20: =IF(AND(I20=0,$H20=0),"－ ",$H20-I20) -> 26 | O20: =IF(AND(I20=0,$H20>0),"皆増 ",IF(AND(I20>0,$H20=0),"皆減 ",IF(AND(I20=0,$H20=0),"－ ",N20/I20))) -> 0.41269841 | P20: =IF(OR(F20>0,G20>0,H20>0,I20>0),"表示（判定）","×表示しない") -> 表示（判定） | R20: ='[2]3条収入'!$E$28 -> 88770 | S20: =ROUND(R20/1000,0)+T20 -> 89 | U20: 87 | W20: =SUM(U20:V20) -> 87
C21: 国庫補助金 | E21: 108 | G21: =W21 -> 0 | H21: =S21 -> 0 | I21: 0 | J21: =IF(AND(F21=0,$H21=0),"－ ",$H21-F21) -> － | K21: =IF(AND(F21=0,$H21>0),"皆増 ",IF(AND(F21>0,$H21=0),"皆減 ",IF(AND(F21=0,$H21=0),"－ ",J21/F21))) -> － | L21: =IF(AND(G21=0,$H21=0),"－ ",$H21-G21) -> － | M21: =IF(AND(G21=0,$H21>0),"皆増 ",IF(AND(G21>0,$H21=0),"皆減 ",IF(AND(G21=0,$H21=0),"－ ",L21/G21))) -> － | N21: =IF(AND(I21=0,$H21=0),"－ ",$H21-I21) -> － | O21: =IF(AND(I21=0,$H21>0),"皆増 ",IF(AND(I21>0,$H21=0),"皆減 ",IF(AND(I21=0,$H21=0),"－ ",N21/I21))) -> － | P21: =IF(OR(F21>0,G21>0,H21>0,I21>0),"表示（判定）","×表示しない") -> ×表示しない | R21: ='[2]3条収入'!$AI$32 -> 0 | S21: =ROUND(R21/1000,0)+T21 -> 0
C22: 負担金 | E22: 305814 | F22: 49683 | G22: 49683 | H22: =S22 -> 53493 | I22: =64215+1 -> 64216 | J22: =IF(AND(F22=0,$H22=0),"－ ",$H22-F22) -> 3810 | K22: =IF(AND(F22=0,$H22>0),"皆増 ",IF(AND(F22>0,$H22=0),"皆減 ",IF(AND(F22=0,$H22=0),"－ ",J22/F22))) -> 0.07668619 | L22: =IF(AND(G22=0,$H22=0),"－ ",$H22-G22) -> 3810 | M22: =IF(AND(G22=0,$H22>0),"皆増 ",IF(AND(G22>0,$H22=0),"皆減 ",IF(AND(G22=0,$H22=0),"－ ",L22/G22))) -> 0.07668619 | N22: =IF(AND(I22=0,$H22=0),"－ ",$H22-I22) -> -10723 | O22: =IF(AND(I22=0,$H22>0),"皆増 ",IF(AND(I22>0,$H22=0),"皆減 ",IF(AND(I22=0,$H22=0),"－ ",N22/I22))) -> -0.16698331 | P22: =IF(OR(F22>0,G22>0,H22>0,I22>0),"表示（判定）","×表示しない") -> 表示（判定） | R22: ='[2]3条収入'!$E$39 -> 53493193 | S22: =ROUND(R22/1000,0)+T22 -> 53493 | U22: 46672 | W22: =SUM(U22:V22) -> 46672
C23: 一般会計補助金 | E23: 1708190 | F23: 0 | G23: =W23 -> 8000 | H23: =S23 -> 9203 | I23: 31 | J23: =IF(AND(F23=0,$H23=0),"－ ",$H23-F23) -> 9203 | K23: =IF(AND(F23=0,$H23>0),"皆増 ",IF(AND(F23>0,$H23=0),"皆減 ",IF(AND(F23=0,$H23=0),"－ ",J23/F23))) -> 皆増 | L23: =IF(AND(G23=0,$H23=0),"－ ",$H23-G23) -> 1203 | M23: =IF(AND(G23=0,$H23>0),"皆増 ",IF(AND(G23>0,$H23=0),"皆減 ",IF(AND(G23=0,$H23=0),"－ ",L23/G23))) -> 0.150375 | N23: =IF(AND(I23=0,$H23=0),"－ ",$H23-I23) -> 9172 | O23: =IF(AND(I23=0,$H23>0),"皆増 ",IF(AND(I23>0,$H23=0),"皆減 ",IF(AND(I23=0,$H23=0),"－ ",N23/I23))) -> 295.87097 | P23: =IF(OR(F23>0,G23>0,H23>0,I23>0),"表示（判定）","×表示しない") -> 表示（判定） | R23: ='[2]3条収入'!$E$42 -> 9203253 | S23: =ROUND(R23/1000,0)+T23 -> 9203 | V23: 8000 | W23: =SUM(U23:V23) -> 8000
C24: 消費税還付金 | E24: 0 | G24: =W24 -> 0 | H24: =S24 -> 0 | I24: 0 | J24: =IF(AND(F24=0,$H24=0),"－ ",$H24-F24) -> － | K24: =IF(AND(F24=0,$H24>0),"皆増 ",IF(AND(F24>0,$H24=0),"皆減 ",IF(AND(F24=0,$H24=0),"－ ",J24/F24))) -> － | L24: =IF(AND(G24=0,$H24=0),"－ ",$H24-G24) -> － | M24: =IF(AND(G24=0,$H24>0),"皆増 ",IF(AND(G24>0,$H24=0),"皆減 ",IF(AND(G24=0,$H24=0),"－ ",L24/G24))) -> － | N24: =IF(AND(I24=0,$H24=0),"－ ",$H24-I24) -> － | O24: =IF(AND(I24=0,$H24>0),"皆増 ",IF(AND(I24>0,$H24=0),"皆減 ",IF(AND(I24=0,$H24=0),"－ ",N24/I24))) -> － | P24: =IF(OR(F24>0,G24>0,H24>0,I24>0),"表示（判定）","×表示しない") -> ×表示しない | R24: ='[2]3条収入'!$AI$49 -> 0 | S24: =ROUND(R24/1000,0)+T24 -> 0
C25: 長期前受金戻入 | E25: 9623 | F25: 9455090 | G25: 9488527 | H25: =S25 -> 9485355 | I25: 9604004 | J25: =IF(AND(F25=0,$H25=0),"－ ",$H25-F25) -> 30265 | K25: =IF(AND(F25=0,$H25>0),"皆増 ",IF(AND(F25>0,$H25=0),"皆減 ",IF(AND(F25=0,$H25=0),"－ ",J25/F25))) -> 0.0032009214 | L25: =IF(AND(G25=0,$H25=0),"－ ",$H25-G25) -> -3172 | M25: =IF(AND(G25=0,$H25>0),"皆増 ",IF(AND(G25>0,$H25=0),"皆減 ",IF(AND(G25=0,$H25=0),"－ ",L25/G25))) -> -0.00033429846 | N25: =IF(AND(I25=0,$H25=0),"－ ",$H25-I25) -> -118649 | O25: =IF(AND(I25=0,$H25>0),"皆増 ",IF(AND(I25>0,$H25=0),"皆減 ",IF(AND(I25=0,$H25=0),"－ ",N25/I25))) -> -0.012354118 | P25: =IF(OR(F25>0,G25>0,H25>0,I25>0),"表示（判定）","×表示しない") -> 表示（判定） | R25: ='[2]3条収入'!$E$55 -> 9485355002 | S25: =ROUND(R25/1000,0)+T25 -> 9485355 | U25: 9488526 | W25: =SUM(U25:V25) -> 9488526
C26: 雑収益 | E26: 9575 | F26: 23945 | G26: 33389 | H26: =S26 -> 36460 | I26: 35321 | J26: =IF(AND(F26=0,$H26=0),"－ ",$H26-F26) -> 12515 | K26: =IF(AND(F26=0,$H26>0),"皆増 ",IF(AND(F26>0,$H26=0),"皆減 ",IF(AND(F26=0,$H26=0),"－ ",J26/F26))) -> 0.52265609 | L26: =IF(AND(G26=0,$H26=0),"－ ",$H26-G26) -> 3071 | M26: =IF(AND(G26=0,$H26>0),"皆増 ",IF(AND(G26>0,$H26=0),"皆減 ",IF(AND(G26=0,$H26=0),"－ ",L26/G26))) -> 0.091976399 | N26: =IF(AND(I26=0,$H26=0),"－ ",$H26-I26) -> 1139 | O26: =IF(AND(I26=0,$H26>0),"皆増 ",IF(AND(I26>0,$H26=0),"皆減 ",IF(AND(I26=0,$H26=0),"－ ",N26/I26))) -> 0.032247105 | P26: =IF(OR(F26>0,G26>0,H26>0,I26>0),"表示（判定）","×表示しない") -> 表示（判定） | R26: ='[2]3条収入'!$E$51 -> 36460334 | S26: =ROUND(R26/1000,0)+T26 -> 36460 | U26: 32929 | W26: =SUM(U26:V26) -> 32929
B27: 特別利益 | E27: =SUM(E28:E31) -> 2821 | F27: =SUM(F28:F31) -> 2876 | G27: =SUM(G28:G31) -> 2997 | H27: =SUM(H28:H31) -> 4199 | I27: =SUM(I28:I31) -> 6568 | J27: =IF(AND(F27=0,$H27=0),"－ ",$H27-F27) -> 1323 | K27: =IF(AND(F27=0,$H27>0),"皆増 ",IF(AND(F27>0,$H27=0),"皆減 ",IF(AND(F27=0,$H27=0),"－ ",J27/F27))) -> 0.46001391 | L27: =IF(AND(G27=0,$H27=0),"－ ",$H27-G27) -> 1202 | M27: =IF(AND(G27=0,$H27>0),"皆増 ",IF(AND(G27>0,$H27=0),"皆減 ",IF(AND(G27=0,$H27=0),"－ ",L27/G27))) -> 0.40106773 | N27: =IF(AND(I27=0,$H27=0),"－ ",$H27-I27) -> -2369 | O27: =IF(AND(I27=0,$H27>0),"皆増 ",IF(AND(I27>0,$H27=0),"皆減 ",IF(AND(I27=0,$H27=0),"－ ",N27/I27))) -> -0.36068819 | P27: =IF(OR(F27>0,G27>0,H27>0,I27>0),"表示（判定）","×表示しない") -> 表示（判定） | R27: =SUM(R28:R31) -> 4198999
C28: 固定資産売却収益 | E28: 0 | F28: 0 | G28: =W28 -> 0 | H28: =S28 -> 0 | I28: 0 | J28: =IF(AND(F28=0,$H28=0),"－ ",$H28-F28) -> － | K28: =IF(AND(F28=0,$H28>0),"皆増 ",IF(AND(F28>0,$H28=0),"皆減 ",IF(AND(F28=0,$H28=0),"－ ",J28/F28))) -> － | L28: =IF(AND(G28=0,$H28=0),"－ ",$H28-G28) -> － | M28: =IF(AND(G28=0,$H28>0),"皆増 ",IF(AND(G28>0,$H28=0),"皆減 ",IF(AND(G28=0,$H28=0),"－ ",L28/G28))) -> － | N28: =IF(AND(I28=0,$H28=0),"－ ",$H28-I28) -> － | O28: =IF(AND(I28=0,$H28>0),"皆増 ",IF(AND(I28>0,$H28=0),"皆減 ",IF(AND(I28=0,$H28=0),"－ ",N28/I28))) -> － | P28: =IF(OR(F28>0,G28>0,H28>0,I28>0),"表示（判定）","×表示しない") -> ×表示しない | R28: ='[2]3条収入'!$AI$58 -> 0 | S28: =ROUND(R28/1000,0)+T28 -> 0
C29: 過年度損益修正益 | E29: 2821 | F29: 2876 | G29: 2023 | H29: =S29 -> 2770 | I29: 4061 | J29: =IF(AND(F29=0,$H29=0),"－ ",$H29-F29) -> -106 | K29: =IF(AND(F29=0,$H29>0),"皆増 ",IF(AND(F29>0,$H29=0),"皆減 ",IF(AND(F29=0,$H29=0),"－ ",J29/F29))) -> -0.036856745 | L29: =IF(AND(G29=0,$H29=0),"－ ",$H29-G29) -> 747 | M29: =IF(AND(G29=0,$H29>0),"皆増 ",IF(AND(G29>0,$H29=0),"皆減 ",IF(AND(G29=0,$H29=0),"－ ",L29/G29))) -> 0.36925358 | N29: =IF(AND(I29=0,$H29=0),"－ ",$H29-I29) -> -1291 | O29: =IF(AND(I29=0,$H29>0),"皆増 ",IF(AND(I29>0,$H29=0),"皆減 ",IF(AND(I29=0,$H29=0),"－ ",N29/I29))) -> -0.31790199 | P29: =IF(OR(F29>0,G29>0,H29>0,I29>0),"表示（判定）","×表示しない") -> 表示（判定） | R29: ='[2]3条収入'!$E$60 -> 2769570 | S29: =ROUND(R29/1000,0)+T29 -> 2770 | U29: 1851 | W29: =SUM(U29:V29) -> 1851
C30: 長期前受金戻入益 | F30: 0 | G30: =W30 -> 0 | H30: =S30 -> 0 | I30: 0 | J30: =IF(AND(F30=0,$H30=0),"－ ",$H30-F30) -> － | K30: =IF(AND(F30=0,$H30>0),"皆増 ",IF(AND(F30>0,$H30=0),"皆減 ",IF(AND(F30=0,$H30=0),"－ ",J30/F30))) -> － | L30: =IF(AND(G30=0,$H30=0),"－ ",$H30-G30) -> － | M30: =IF(AND(G30=0,$H30>0),"皆増 ",IF(AND(G30>0,$H30=0),"皆減 ",IF(AND(G30=0,$H30=0),"－ ",L30/G30))) -> － | N30: =IF(AND(I30=0,$H30=0),"－ ",$H30-I30) -> － | O30: =IF(AND(I30=0,$H30>0),"皆増 ",IF(AND(I30>0,$H30=0),"皆減 ",IF(AND(I30=0,$H30=0),"－ ",N30/I30))) -> － | P30: =IF(OR(F30>0,G30>0,H30>0,I30>0),"表示（判定）","×表示しない") -> ×表示しない | R30: ='[2]3条収入'!$AI$66 -> 0 | S30: =ROUND(R30/1000,0)+T30 -> 0 | U30: 0 | W30: =SUM(U30:V30) -> 0
C31: その他特別利益 | E31: 0 | F31: 0 | G31: 974 | H31: =S31 -> 1429 | I31: 2507 | J31: =IF(AND(F31=0,$H31=0),"－ ",$H31-F31) -> 1429 | K31: =IF(AND(F31=0,$H31>0),"皆増 ",IF(AND(F31>0,$H31=0),"皆減 ",IF(AND(F31=0,$H31=0),"－ ",J31/F31))) -> 皆増 | L31: =IF(AND(G31=0,$H31=0),"－ ",$H31-G31) -> 455 | M31: =IF(AND(G31=0,$H31>0),"皆増 ",IF(AND(G31>0,$H31=0),"皆減 ",IF(AND(G31=0,$H31=0),"－ ",L31/G31))) -> 0.46714579 | N31: =IF(AND(I31=0,$H31=0),"－ ",$H31-I31) -> -1078 | O31: =IF(AND(I31=0,$H31>0),"皆増 ",IF(AND(I31>0,$H31=0),"皆減 ",IF(AND(I31=0,$H31=0),"－ ",N31/I31))) -> -0.42999601 | P31: =IF(OR(F31>0,G31>0,H31>0,I31>0),"表示（判定）","×表示しない") -> 表示（判定） | R31: ='[2]3条収入'!$E$62 -> 1429429 | S31: =ROUND(R31/1000,0)+T31 -> 1429 | U31: 865 | W31: =SUM(U31:V31) -> 865
L32: =IF(AND(G32=0,$H32=0),"－ ",$H32-G32) -> － | N32: =IF(AND(I32=0,$H32=0),"－ ",$H32-I32) -> － | P32: 表示
A33: 一般会計負担金・補助金合計 | E33: =SUM(E12,E23) -> 19720016 | F33: =SUM(F12,F23) -> 13854862 | G33: =SUM(G12,G23) -> 13959285 | H33: =SUM(H12,H23) -> 14196306 | I33: =SUM(I12,I23) -> 13993380 | J33: =IF(AND(F33=0,$H33=0),"－ ",$H33-F33) -> 341444 | K33: =IF(AND(F33=0,$H33>0),"皆増 ",IF(AND(F33>0,$H33=0),"皆減 ",IF(AND(F33=0,$H33=0),"－ ",J33/F33))) -> 0.024644345 | L33: =IF(AND(G33=0,$H33=0),"－ ",$H33-G33) -> 237021 | M33: =IF(AND(G33=0,$H33>0),"皆増 ",IF(AND(G33>0,$H33=0),"皆減 ",IF(AND(G33=0,$H33=0),"－ ",L33/G33))) -> 0.016979451 | N33: =IF(AND(I33=0,$H33=0),"－ ",$H33-I33) -> 202926 | O33: =IF(AND(I33=0,$H33>0),"皆増 ",IF(AND(I33>0,$H33=0),"皆減 ",IF(AND(I33=0,$H33=0),"－ ",N33/I33))) -> 0.014501571 | P33: 表示 | R33: 各項目 合計 → | S33: =SUM(S11:S31) -> 44454712
P34: 表示
A35: 支 出 | P35: 表示 | T35: ↓端数調整
A36: 下 水 道 事 業 費 用 | E36: =SUM(E37,E51,E55,E60) -> 41192935 | F36: =SUM(F37,F51,F55,F60) -> 43953299 | G36: =SUM(G37,G51,G55,G60) -> 43109924 | H36: =SUM(H37,H51,H55,H60) -> 42987208 | I36: =SUM(I37,I51,I55,I60) -> 43163657 | J36: =IF(AND(F36=0,$H36=0),"－ ",$H36-F36) -> -966091 | K36: =IF(AND(F36=0,$H36>0),"皆増 ",IF(AND(F36>0,$H36=0),"皆減 ",IF(AND(F36=0,$H36=0),"－ ",J36/F36))) -> -0.021979943 | L36: =IF(AND(G36=0,$H36=0),"－ ",$H36-G36) -> -122716 | M36: =IF(AND(G36=0,$H36>0),"皆増 ",IF(AND(G36>0,$H36=0),"皆減 ",IF(AND(G36=0,$H36=0),"－ ",L36/G36))) -> -0.0028465835 | N36: =IF(AND(I36=0,$H36=0),"－ ",$H36-I36) -> -176449 | O36: =IF(AND(I36=0,$H36>0),"皆増 ",IF(AND(I36>0,$H36=0),"皆減 ",IF(AND(I36=0,$H36=0),"－ ",N36/I36))) -> -0.0040879066 | P36: =IF(OR(F36>0,G36>0,H36>0,I36>0),"表示（判定）","×表示しない") -> 表示（判定） | R36: =SUM(R37,R51,R55,R60) -> 42987208386
B37: 営業費用 | E37: =SUM(E38:E50) -> 24965206 | F37: =SUM(F38:F50) -> 39325285 | G37: =SUM(G38:G50) -> 38869045 | H37: =SUM(H38:H50) -> 38667489 | I37: =SUM(I38:I50) -> 38245361 | J37: =IF(AND(F37=0,$H37=0),"－ ",$H37-F37) -> -657796 | K37: =IF(AND(F37=0,$H37>0),"皆増 ",IF(AND(F37>0,$H37=0),"皆減 ",IF(AND(F37=0,$H37=0),"－ ",J37/F37))) -> -0.01672705 | L37: =IF(AND(G37=0,$H37=0),"－ ",$H37-G37) -> -201556 | M37: =IF(AND(G37=0,$H37>0),"皆増 ",IF(AND(G37>0,$H37=0),"皆減 ",IF(AND(G37=0,$H37=0),"－ ",L37/G37))) -> -0.0051855146 | N37: =IF(AND(I37=0,$H37=0),"－ ",$H37-I37) -> 422128 | O37: =IF(AND(I37=0,$H37>0),"皆増 ",IF(AND(I37>0,$H37=0),"皆減 ",IF(AND(I37=0,$H37=0),"－ ",N37/I37))) -> 0.011037365 | P37: =IF(OR(F37>0,G37>0,H37>0,I37>0),"表示（判定）","×表示しない") -> 表示（判定） | R37: =SUM(R38:R50) -> 38667489041
C38: 管きょ費 | E38: 589007 | F38: 649416 | G38: 635566 | H38: =S38 -> 611820 | I38: 783145 | J38: =IF(AND(F38=0,$H38=0),"－ ",$H38-F38) -> -37596 | K38: =IF(AND(F38=0,$H38>0),"皆増 ",IF(AND(F38>0,$H38=0),"皆減 ",IF(AND(F38=0,$H38=0),"－ ",J38/F38))) -> -0.057892014 | L38: =IF(AND(G38=0,$H38=0),"－ ",$H38-G38) -> -23746 | M38: =IF(AND(G38=0,$H38>0),"皆増 ",IF(AND(G38>0,$H38=0),"皆減 ",IF(AND(G38=0,$H38=0),"－ ",L38/G38))) -> -0.037361973 | N38: =IF(AND(I38=0,$H38=0),"－ ",$H38-I38) -> -171325 | O38: =IF(AND(I38=0,$H38>0),"皆増 ",IF(AND(I38>0,$H38=0),"皆減 ",IF(AND(I38=0,$H38=0),"－ ",N38/I38))) -> -0.21876536 | P38: =IF(OR(F38>0,G38>0,H38>0,I38>0),"表示（判定）","×表示しない") -> 表示（判定） | R38: ='[1]3条支出'!E6 -> 611819957 | S38: =ROUND(R38/1000,0)+T38 -> 611820 | U38: 586230 | W38: =SUM(U38:V38) -> 586230
C39: 水質指導費 | E39: 71637 | F39: 61778 | G39: 52649 | H39: =S39 -> 52444 | I39: 51549 | J39: =IF(AND(F39=0,$H39=0),"－ ",$H39-F39) -> -9334 | K39: =IF(AND(F39=0,$H39>0),"皆増 ",IF(AND(F39>0,$H39=0),"皆減 ",IF(AND(F39=0,$H39=0),"－ ",J39/F39))) -> -0.15108938 | L39: =IF(AND(G39=0,$H39=0),"－ ",$H39-G39) -> -205 | M39: =IF(AND(G39=0,$H39>0),"皆増 ",IF(AND(G39>0,$H39=0),"皆減 ",IF(AND(G39=0,$H39=0),"－ ",L39/G39))) -> -0.0038937112 | N39: =IF(AND(I39=0,$H39=0),"－ ",$H39-I39) -> 895 | O39: =IF(AND(I39=0,$H39>0),"皆増 ",IF(AND(I39>0,$H39=0),"皆減 ",IF(AND(I39=0,$H39=0),"－ ",N39/I39))) -> 0.017362121 | P39: =IF(OR(F39>0,G39>0,H39>0,I39>0),"表示（判定）","×表示しない") -> 表示（判定） | R39: ='[1]3条支出'!E7 -> 52443869 | S39: =ROUND(R39/1000,0)+T39 -> 52444 | U39: 51456 | W39: =SUM(U39:V39) -> 51456
C40: ポンプ場費 | E40: 2362983 | F40: 2446053 | G40: 2362251 | H40: =S40 -> 2356040 | I40: 2289383 | J40: =IF(AND(F40=0,$H40=0),"－ ",$H40-F40) -> -90013 | K40: =IF(AND(F40=0,$H40>0),"皆増 ",IF(AND(F40>0,$H40=0),"皆減 ",IF(AND(F40=0,$H40=0),"－ ",J40/F40))) -> -0.036799284 | L40: =IF(AND(G40=0,$H40=0),"－ ",$H40-G40) -> -6211 | M40: =IF(AND(G40=0,$H40>0),"皆増 ",IF(AND(G40>0,$H40=0),"皆減 ",IF(AND(G40=0,$H40=0),"－ ",L40/G40))) -> -0.0026292718 | N40: =IF(AND(I40=0,$H40=0),"－ ",$H40-I40) -> 66657 | O40: =IF(AND(I40=0,$H40>0),"皆増 ",IF(AND(I40>0,$H40=0),"皆減 ",IF(AND(I40=0,$H40=0),"－ ",N40/I40))) -> 0.029115705 | P40: =IF(OR(F40>0,G40>0,H40>0,I40>0),"表示（判定）","×表示しない") -> 表示（判定） | R40: ='[1]3条支出'!E8 -> 2356040225 | S40: =ROUND(R40/1000,0)+T40 -> 2356040 | U40: 2257378 | W40: =SUM(U40:V40) -> 2257378
C41: 処理場費 | E41: 5009251 | F41: 7107004 | G41: 6676202 | H41: =S41 -> 6557704 | I41: 5969023 | J41: =IF(AND(F41=0,$H41=0),"－ ",$H41-F41) -> -549300 | K41: =IF(AND(F41=0,$H41>0),"皆増 ",IF(AND(F41>0,$H41=0),"皆減 ",IF(AND(F41=0,$H41=0),"－ ",J41/F41))) -> -0.077289952 | L41: =IF(AND(G41=0,$H41=0),"－ ",$H41-G41) -> -118498 | M41: =IF(AND(G41=0,$H41>0),"皆増 ",IF(AND(G41>0,$H41=0),"皆減 ",IF(AND(G41=0,$H41=0),"－ ",L41/G41))) -> -0.017749313 | N41: =IF(AND(I41=0,$H41=0),"－ ",$H41-I41) -> 588681 | O41: =IF(AND(I41=0,$H41>0),"皆増 ",IF(AND(I41>0,$H41=0),"皆減 ",IF(AND(I41=0,$H41=0),"－ ",N41/I41))) -> 0.098622672 | P41: =IF(OR(F41>0,G41>0,H41>0,I41>0),"表示（判定）","×表示しない") -> 表示（判定） | R41: ='[1]3条支出'!E9 -> 6557703864 | S41: =ROUND(R41/1000,0)+T41 -> 6557704 | U41: 6145362 | W41: =SUM(U41:V41) -> 6145362
C42: 普及促進費 | E42: 92445 | F42: 80070 | G42: 87703 | H42: =S42 -> 88850 | I42: 74989 | J42: =IF(AND(F42=0,$H42=0),"－ ",$H42-F42) -> 8780 | K42: =IF(AND(F42=0,$H42>0),"皆増 ",IF(AND(F42>0,$H42=0),"皆減 ",IF(AND(F42=0,$H42=0),"－ ",J42/F42))) -> 0.10965405 | L42: =IF(AND(G42=0,$H42=0),"－ ",$H42-G42) -> 1147 | M42: =IF(AND(G42=0,$H42>0),"皆増 ",IF(AND(G42>0,$H42=0),"皆減 ",IF(AND(G42=0,$H42=0),"－ ",L42/G42))) -> 0.01307823 | N42: =IF(AND(I42=0,$H42=0),"－ ",$H42-I42) -> 13861 | O42: =IF(AND(I42=0,$H42>0),"皆増 ",IF(AND(I42>0,$H42=0),"皆減 ",IF(AND(I42=0,$H42=0),"－ ",N42/I42))) -> 0.18484044 | P42: =IF(OR(F42>0,G42>0,H42>0,I42>0),"表示（判定）","×表示しない") -> 表示（判定） | R42: ='[1]3条支出'!E11 -> 88849549 | S42: =ROUND(R42/1000,0)+T42 -> 88850 | U42: 85747 | W42: =SUM(U42:V42) -> 85747
C43: 水洗化貸付事業費 | E43: 18143 | F43: 14763 | G43: 10712 | H43: =S43 -> 10484 | I43: 10746 | J43: =IF(AND(F43=0,$H43=0),"－ ",$H43-F43) -> -4279 | K43: =IF(AND(F43=0,$H43>0),"皆増 ",IF(AND(F43>0,$H43=0),"皆減 ",IF(AND(F43=0,$H43=0),"－ ",J43/F43))) -> -0.28984624 | L43: =IF(AND(G43=0,$H43=0),"－ ",$H43-G43) -> -228 | M43: =IF(AND(G43=0,$H43>0),"皆増 ",IF(AND(G43>0,$H43=0),"皆減 ",IF(AND(G43=0,$H43=0),"－ ",L43/G43))) -> -0.021284541 | N43: =IF(AND(I43=0,$H43=0),"－ ",$H43-I43) -> -262 | O43: =IF(AND(I43=0,$H43>0),"皆増 ",IF(AND(I43>0,$H43=0),"皆減 ",IF(AND(I43=0,$H43=0),"－ ",N43/I43))) -> -0.024381165 | P43: =IF(OR(F43>0,G43>0,H43>0,I43>0),"表示（判定）","×表示しない") -> 表示（判定） | R43: ='[1]3条支出'!E12 -> 10483859 | S43: =ROUND(R43/1000,0)+T43 -> 10484 | U43: 10611 | W43: =SUM(U43:V43) -> 10611
C44: 業務費 | E44: 989662 | F44: 1032244 | G44: 1020628 | H44: =S44 -> 1019945 | I44: 1051841 | J44: =IF(AND(F44=0,$H44=0),"－ ",$H44-F44) -> -12299 | K44: =IF(AND(F44=0,$H44>0),"皆増 ",IF(AND(F44>0,$H44=0),"皆減 ",IF(AND(F44=0,$H44=0),"－ ",J44/F44))) -> -0.011914819 | L44: =IF(AND(G44=0,$H44=0),"－ ",$H44-G44) -> -683 | M44: =IF(AND(G44=0,$H44>0),"皆増 ",IF(AND(G44>0,$H44=0),"皆減 ",IF(AND(G44=0,$H44=0),"－ ",L44/G44))) -> -0.00066919583 | N44: =IF(AND(I44=0,$H44=0),"－ ",$H44-I44) -> -31896 | O44: =IF(AND(I44=0,$H44>0),"皆増 ",IF(AND(I44>0,$H44=0),"皆減 ",IF(AND(I44=0,$H44=0),"－ ",N44/I44))) -> -0.030323975 | P44: =IF(OR(F44>0,G44>0,H44>0,I44>0),"表示（判定）","×表示しない") -> 表示（判定） | R44: ='[1]3条支出'!E13 -> 1019945143 | S44: =ROUND(R44/1000,0)+T44 -> 1019945 | U44: 930360 | W44: =SUM(U44:V44) -> 930360
C45: 総係費 | E45: 592338 | F45: 552278 | G45: 515763 | H45: =S45 -> 483965 | I45: 544322 | J45: =IF(AND(F45=0,$H45=0),"－ ",$H45-F45) -> -68313 | K45: =IF(AND(F45=0,$H45>0),"皆増 ",IF(AND(F45>0,$H45=0),"皆減 ",IF(AND(F45=0,$H45=0),"－ ",J45/F45))) -> -0.12369314 | L45: =IF(AND(G45=0,$H45=0),"－ ",$H45-G45) -> -31798 | M45: =IF(AND(G45=0,$H45>0),"皆増 ",IF(AND(G45>0,$H45=0),"皆減 ",IF(AND(G45=0,$H45=0),"－ ",L45/G45))) -> -0.061652348 | N45: =IF(AND(I45=0,$H45=0),"－ ",$H45-I45) -> -60357 | O45: =IF(AND(I45=0,$H45>0),"皆増 ",IF(AND(I45>0,$H45=0),"皆減 ",IF(AND(I45=0,$H45=0),"－ ",N45/I45))) -> -0.11088473 | P45: =IF(OR(F45>0,G45>0,H45>0,I45>0),"表示（判定）","×表示しない") -> 表示（判定） | R45: ='[1]3条支出'!E14 -> 483965214 | S45: =ROUND(R45/1000,0)+T45 -> 483965 | U45: 496650 | W45: =SUM(U45:V45) -> 496650
C46: 特環公共下水道費 | E46: 34809 | F46: 109279 | G46: 109485 | H46: =S46 -> 106991 | I46: 107848 | J46: =IF(AND(F46=0,$H46=0),"－ ",$H46-F46) -> -2288 | K46: =IF(AND(F46=0,$H46>0),"皆増 ",IF(AND(F46>0,$H46=0),"皆減 ",IF(AND(F46=0,$H46=0),"－ ",J46/F46))) -> -0.020937234 | L46: =IF(AND(G46=0,$H46=0),"－ ",$H46-G46) -> -2494 | M46: =IF(AND(G46=0,$H46>0),"皆増 ",IF(AND(G46>0,$H46=0),"皆減 ",IF(AND(G46=0,$H46=0),"－ ",L46/G46))) -> -0.022779376 | N46: =IF(AND(I46=0,$H46=0),"－ ",$H46-I46) -> -857 | O46: =IF(AND(I46=0,$H46>0),"皆増 ",IF(AND(I46>0,$H46=0),"皆減 ",IF(AND(I46=0,$H46=0),"－ ",N46/I46))) -> -0.007946369 | P46: =IF(OR(F46>0,G46>0,H46>0,I46>0),"表示（判定）","×表示しない") -> 表示（判定） | R46: ='[1]3条支出'!E15 -> 106990906 | S46: =ROUND(R46/1000,0)+T46 -> 106991 | U46: 99545 | W46: =SUM(U46:V46) -> 99545
C47: 農業集落排水費 | E47: 172556 | F47: 261404 | G47: 250756 | H47: =S47 -> 247654 | I47: 242798 | J47: =IF(AND(F47=0,$H47=0),"－ ",$H47-F47) -> -13750 | K47: =IF(AND(F47=0,$H47>0),"皆増 ",IF(AND(F47>0,$H47=0),"皆減 ",IF(AND(F47=0,$H47=0),"－ ",J47/F47))) -> -0.052600572 | L47: =IF(AND(G47=0,$H47=0),"－ ",$H47-G47) -> -3102 | M47: =IF(AND(G47=0,$H47>0),"皆増 ",IF(AND(G47>0,$H47=0),"皆減 ",IF(AND(G47=0,$H47=0),"－ ",L47/G47))) -> -0.012370591 | N47: =IF(AND(I47=0,$H47=0),"－ ",$H47-I47) -> 4856 | O47: =IF(AND(I47=0,$H47>0),"皆増 ",IF(AND(I47>0,$H47=0),"皆減 ",IF(AND(I47=0,$H47=0),"－ ",N47/I47))) -> 0.020000165 | P47: =IF(OR(F47>0,G47>0,H47>0,I47>0),"表示（判定）","×表示しない") -> 表示（判定） | R47: ='[1]3条支出'!E16 -> 247654024 | S47: =ROUND(R47/1000,0)+T47 -> 247654 | U47: 227999 | W47: =SUM(U47:V47) -> 227999
C48: 浄化槽費 | E48: 5865 | F48: 78829 | G48: 76951 | H48: =S48 -> 76388 | I48: 71165 | J48: =IF(AND(F48=0,$H48=0),"－ ",$H48-F48) -> -2441 | K48: =IF(AND(F48=0,$H48>0),"皆増 ",IF(AND(F48>0,$H48=0),"皆減 ",IF(AND(F48=0,$H48=0),"－ ",J48/F48))) -> -0.030965761 | L48: =IF(AND(G48=0,$H48=0),"－ ",$H48-G48) -> -563 | M48: =IF(AND(G48=0,$H48>0),"皆増 ",IF(AND(G48>0,$H48=0),"皆減 ",IF(AND(G48=0,$H48=0),"－ ",L48/G48))) -> -0.0073163442 | N48: =IF(AND(I48=0,$H48=0),"－ ",$H48-I48) -> 5223 | O48: =IF(AND(I48=0,$H48>0),"皆増 ",IF(AND(I48>0,$H48=0),"皆減 ",IF(AND(I48=0,$H48=0),"－ ",N48/I48))) -> 0.07339282 | P48: =IF(OR(F48>0,G48>0,H48>0,I48>0),"表示（判定）","×表示しない") -> 表示（判定） | R48: ='[1]3条支出'!E17 -> 76388330 | S48: =ROUND(R48/1000,0)+T48 -> 76388 | U48: 70452 | W48: =SUM(U48:V48) -> 70452
C49: 減価償却費 | E49: 14647769 | F49: 26580629 | G49: 26549687 | H49: =S49 -> 26551442 | I49: 26646058 | J49: =IF(AND(F49=0,$H49=0),"－ ",$H49-F49) -> -29187 | K49: =IF(AND(F49=0,$H49>0),"皆増 ",IF(AND(F49>0,$H49=0),"皆減 ",IF(AND(F49=0,$H49=0),"－ ",J49/F49))) -> -0.0010980553 | L49: =IF(AND(G49=0,$H49=0),"－ ",$H49-G49) -> 1755 | M49: =IF(AND(G49=0,$H49>0),"皆増 ",IF(AND(G49>0,$H49=0),"皆減 ",IF(AND(G49=0,$H49=0),"－ ",L49/G49))) -> 6.6102474e-05 | N49: =IF(AND(I49=0,$H49=0),"－ ",$H49-I49) -> -94616 | O49: =IF(AND(I49=0,$H49>0),"皆増 ",IF(AND(I49>0,$H49=0),"皆減 ",IF(AND(I49=0,$H49=0),"－ ",N49/I49))) -> -0.0035508442 | P49: =IF(OR(F49>0,G49>0,H49>0,I49>0),"表示（判定）","×表示しない") -> 表示（判定） | R49: ='[1]3条支出'!E19 -> 26551442230 | S49: =ROUND(R49/1000,0)+T49 -> 26551442 | U49: 26549687 | W49: =SUM(U49:V49) -> 26549687
C50: 資産減耗費 | E50: 378741 | F50: 351538 | G50: 520692 | H50: =S50 -> 503762 | I50: 402494 | J50: =IF(AND(F50=0,$H50=0),"－ ",$H50-F50) -> 152224 | K50: =IF(AND(F50=0,$H50>0),"皆増 ",IF(AND(F50>0,$H50=0),"皆減 ",IF(AND(F50=0,$H50=0),"－ ",J50/F50))) -> 0.43302289 | L50: =IF(AND(G50=0,$H50=0),"－ ",$H50-G50) -> -16930 | M50: =IF(AND(G50=0,$H50>0),"皆増 ",IF(AND(G50>0,$H50=0),"皆減 ",IF(AND(G50=0,$H50=0),"－ ",L50/G50))) -> -0.032514423 | N50: =IF(AND(I50=0,$H50=0),"－ ",$H50-I50) -> 101268 | O50: =IF(AND(I50=0,$H50>0),"皆増 ",IF(AND(I50>0,$H50=0),"皆減 ",IF(AND(I50=0,$H50=0),"－ ",N50/I50))) -> 0.25160127 | P50: =IF(OR(F50>0,G50>0,H50>0,I50>0),"表示（判定）","×表示しない") -> 表示（判定） | R50: ='[1]3条支出'!E20 -> 503761871 | S50: =ROUND(R50/1000,0)+T50 -> 503762 | U50: 520692 | W50: =SUM(U50:V50) -> 520692
B51: 営業外費用 | E51: =SUM(E52:E54) -> 16171804 | F51: =SUM(F52:F54) -> 4599725 | G51: =SUM(G52:G54) -> 4218270 | H51: =SUM(H52:H54) -> 4298724 | I51: =SUM(I52:I54) -> 4912974 | J51: =IF(AND(F51=0,$H51=0),"－ ",$H51-F51) -> -301001 | K51: =IF(AND(F51=0,$H51>0),"皆増 ",IF(AND(F51>0,$H51=0),"皆減 ",IF(AND(F51=0,$H51=0),"－ ",J51/F51))) -> -0.065438912 | L51: =IF(AND(G51=0,$H51=0),"－ ",$H51-G51) -> 80454 | M51: =IF(AND(G51=0,$H51>0),"皆増 ",IF(AND(G51>0,$H51=0),"皆減 ",IF(AND(G51=0,$H51=0),"－ ",L51/G51))) -> 0.019072748 | N51: =IF(AND(I51=0,$H51=0),"－ ",$H51-I51) -> -614250 | O51: =IF(AND(I51=0,$H51>0),"皆増 ",IF(AND(I51>0,$H51=0),"皆減 ",IF(AND(I51=0,$H51=0),"－ ",N51/I51))) -> -0.1250261 | P51: =IF(OR(F51>0,G51>0,H51>0,I51>0),"表示（判定）","×表示しない") -> 表示（判定） | R51: =SUM(R52:R54) -> 4298724047
C52: 支払利息及び企業債取扱諸費 | E52: 16052113 | F52: 4207550 | G52: 3945966 | H52: =S52 -> 3945961 | I52: 4401591 | J52: =IF(AND(F52=0,$H52=0),"－ ",$H52-F52) -> -261589 | K52: =IF(AND(F52=0,$H52>0),"皆増 ",IF(AND(F52>0,$H52=0),"皆減 ",IF(AND(F52=0,$H52=0),"－ ",J52/F52))) -> -0.062171335 | L52: =IF(AND(G52=0,$H52=0),"－ ",$H52-G52) -> -5 | M52: =IF(AND(G52=0,$H52>0),"皆増 ",IF(AND(G52>0,$H52=0),"皆減 ",IF(AND(G52=0,$H52=0),"－ ",L52/G52))) -> -1.2671168e-06 | N52: =IF(AND(I52=0,$H52=0),"－ ",$H52-I52) -> -455630 | O52: =IF(AND(I52=0,$H52>0),"皆増 ",IF(AND(I52>0,$H52=0),"皆減 ",IF(AND(I52=0,$H52=0),"－ ",N52/I52))) -> -0.10351484 | P52: =IF(OR(F52>0,G52>0,H52>0,I52>0),"表示（判定）","×表示しない") -> 表示（判定） | R52: ='[1]3条支出'!E23 -> 3945961149 | S52: =ROUND(R52/1000,0)+T52 -> 3945961 | U52: 3940345 | W52: =SUM(U52:V52) -> 3940345
C53: 消費税及び地方消費税 | E53: 0 | F53: 392158 | G53: 264261 | H53: =S53 -> 343539 | I53: 511383 | J53: =IF(AND(F53=0,$H53=0),"－ ",$H53-F53) -> -48619 | K53: =IF(AND(F53=0,$H53>0),"皆増 ",IF(AND(F53>0,$H53=0),"皆減 ",IF(AND(F53=0,$H53=0),"－ ",J53/F53))) -> -0.12397809 | L53: =IF(AND(G53=0,$H53=0),"－ ",$H53-G53) -> 79278 | M53: =IF(AND(G53=0,$H53>0),"皆増 ",IF(AND(G53>0,$H53=0),"皆減 ",IF(AND(G53=0,$H53=0),"－ ",L53/G53))) -> 0.29999886 | N53: =IF(AND(I53=0,$H53=0),"－ ",$H53-I53) -> -167844 | O53: =IF(AND(I53=0,$H53>0),"皆増 ",IF(AND(I53>0,$H53=0),"皆減 ",IF(AND(I53=0,$H53=0),"－ ",N53/I53))) -> -0.32821584 | P53: =IF(OR(F53>0,G53>0,H53>0,I53>0),"表示（判定）","×表示しない") -> 表示（判定） | R53: =[1]営外!$E$22 -> 343538729 | S53: =ROUND(R53/1000,0)+T53 -> 343539
C54: 雑支出 | E54: 119691 | F54: 17 | G54: =43+8000 -> 8043 | H54: =S54 -> 9224 | I54: 0 | J54: =IF(AND(F54=0,$H54=0),"－ ",$H54-F54) -> 9207 | K54: =IF(AND(F54=0,$H54>0),"皆増 ",IF(AND(F54>0,$H54=0),"皆減 ",IF(AND(F54=0,$H54=0),"－ ",J54/F54))) -> 541.58824 | L54: =IF(AND(G54=0,$H54=0),"－ ",$H54-G54) -> 1181 | M54: =IF(AND(G54=0,$H54>0),"皆増 ",IF(AND(G54>0,$H54=0),"皆減 ",IF(AND(G54=0,$H54=0),"－ ",L54/G54))) -> 0.14683576 | N54: =IF(AND(I54=0,$H54=0),"－ ",$H54-I54) -> 9224 | O54: =IF(AND(I54=0,$H54>0),"皆増 ",IF(AND(I54>0,$H54=0),"皆減 ",IF(AND(I54=0,$H54=0),"－ ",N54/I54))) -> 皆増 | P54: =IF(OR(F54>0,G54>0,H54>0,I54>0),"表示（判定）","×表示しない") -> 表示（判定） | R54: ='[1]3条支出'!E24+'[1]3条支出'!$E$25 -> 9224169 | S54: =ROUND(R54/1000,0)+T54 -> 9224 | U54: 196817 | V54: 7273 | W54: =SUM(U54:V54) -> 204090
B55: 特別損失 | E55: =SUM(E56:E59) -> 55925 | F55: =SUM(F56:F59) -> 8289 | G55: =SUM(G56:G59) -> 22609 | H55: =SUM(H56:H59) -> 20995 | I55: =SUM(I56:I59) -> 5322 | J55: =IF(AND(F55=0,$H55=0),"－ ",$H55-F55) -> 12706 | K55: =IF(AND(F55=0,$H55>0),"皆増 ",IF(AND(F55>0,$H55=0),"皆減 ",IF(AND(F55=0,$H55=0),"－ ",J55/F55))) -> 1.5328749 | L55: =IF(AND(G55=0,$H55=0),"－ ",$H55-G55) -> -1614 | M55: =IF(AND(G55=0,$H55>0),"皆増 ",IF(AND(G55>0,$H55=0),"皆減 ",IF(AND(G55=0,$H55=0),"－ ",L55/G55))) -> -0.071387501 | N55: =IF(AND(I55=0,$H55=0),"－ ",$H55-I55) -> 15673 | O55: =IF(AND(I55=0,$H55>0),"皆増 ",IF(AND(I55>0,$H55=0),"皆減 ",IF(AND(I55=0,$H55=0),"－ ",N55/I55))) -> 2.9449455 | P55: =IF(OR(F55>0,G55>0,H55>0,I55>0),"表示（判定）","×表示しない") -> 表示（判定） | R55: =SUM(R56:R59) -> 20995298
C56: 固定資産売却損 | E56: 0 | F56: 0 | G56: 10315 | H56: =S56 -> 10315 | I56: 0 | J56: =IF(AND(F56=0,$H56=0),"－ ",$H56-F56) -> 10315 | K56: =IF(AND(F56=0,$H56>0),"皆増 ",IF(AND(F56>0,$H56=0),"皆減 ",IF(AND(F56=0,$H56=0),"－ ",J56/F56))) -> 皆増 | L56: =IF(AND(G56=0,$H56=0),"－ ",$H56-G56) -> 0 | M56: =IF(AND(G56=0,$H56>0),"皆増 ",IF(AND(G56>0,$H56=0),"皆減 ",IF(AND(G56=0,$H56=0),"－ ",L56/G56))) -> 0 | N56: =IF(AND(I56=0,$H56=0),"－ ",$H56-I56) -> 10315 | O56: =IF(AND(I56=0,$H56>0),"皆増 ",IF(AND(I56>0,$H56=0),"皆減 ",IF(AND(I56=0,$H56=0),"－ ",N56/I56))) -> 皆増 | P56: =IF(OR(F56>0,G56>0,H56>0,I56>0),"表示（判定）","×表示しない") -> 表示（判定） | R56: ='[1]3条支出'!$E$30 -> 10315355 | S56: =ROUND(R56/1000,0)+T56 -> 10315 | U56: 10315 | W56: =SUM(U56:V56) -> 10315
C57: 過年度損益修正損 | E57: 41531 | F57: 8248 | G57: 12253 | H57: =S57 -> 10680 | I57: 5320 | J57: =IF(AND(F57=0,$H57=0),"－ ",$H57-F57) -> 2432 | K57: =IF(AND(F57=0,$H57>0),"皆増 ",IF(AND(F57>0,$H57=0),"皆減 ",IF(AND(F57=0,$H57=0),"－ ",J57/F57))) -> 0.29485936 | L57: =IF(AND(G57=0,$H57=0),"－ ",$H57-G57) -> -1573 | M57: =IF(AND(G57=0,$H57>0),"皆増 ",IF(AND(G57>0,$H57=0),"皆減 ",IF(AND(G57=0,$H57=0),"－ ",L57/G57))) -> -0.12837672 | N57: =IF(AND(I57=0,$H57=0),"－ ",$H57-I57) -> 5360 | O57: =IF(AND(I57=0,$H57>0),"皆増 ",IF(AND(I57>0,$H57=0),"皆減 ",IF(AND(I57=0,$H57=0),"－ ",N57/I57))) -> 1.0075188 | P57: =IF(OR(F57>0,G57>0,H57>0,I57>0),"表示（判定）","×表示しない") -> 表示（判定） | R57: ='[1]3条支出'!$E$28 -> 10679943 | S57: =ROUND(R57/1000,0)+T57 -> 10680 | U57: 11176 | W57: =SUM(U57:V57) -> 11176
C58: 減損損失 | F58: 0 | G58: =W58 -> 0 | H58: =S58 -> 0 | I58: 0 | J58: =IF(AND(F58=0,$H58=0),"－ ",$H58-F58) -> － | K58: =IF(AND(F58=0,$H58>0),"皆増 ",IF(AND(F58>0,$H58=0),"皆減 ",IF(AND(F58=0,$H58=0),"－ ",J58/F58))) -> － | L58: =IF(AND(G58=0,$H58=0),"－ ",$H58-G58) -> － | M58: =IF(AND(G58=0,$H58>0),"皆増 ",IF(AND(G58>0,$H58=0),"皆減 ",IF(AND(G58=0,$H58=0),"－ ",L58/G58))) -> － | N58: =IF(AND(I58=0,$H58=0),"－ ",$H58-I58) -> － | O58: =IF(AND(I58=0,$H58>0),"皆増 ",IF(AND(I58>0,$H58=0),"皆減 ",IF(AND(I58=0,$H58=0),"－ ",N58/I58))) -> － | P58: =IF(OR(F58>0,G58>0,H58>0,I58>0),"表示（判定）","×表示しない") -> ×表示しない | R58: ='[1]3条支出'!$T$31 -> 0 | S58: =ROUND(R58/1000,0)+T58 -> 0 | U58: 0 | W58: =SUM(U58:V58) -> 0
C59: その他特別損失 | E59: 14394 | F59: 41 | G59: 41 | H59: =S59 -> 0 | I59: 2 | J59: =IF(AND(F59=0,$H59=0),"－ ",$H59-F59) -> -41 | K59: =IF(AND(F59=0,$H59>0),"皆増 ",IF(AND(F59>0,$H59=0),"皆減 ",IF(AND(F59=0,$H59=0),"－ ",J59/F59))) -> 皆減 | L59: =IF(AND(G59=0,$H59=0),"－ ",$H59-G59) -> -41 | M59: =IF(AND(G59=0,$H59>0),"皆増 ",IF(AND(G59>0,$H59=0),"皆減 ",IF(AND(G59=0,$H59=0),"－ ",L59/G59))) -> 皆減 | N59: =IF(AND(I59=0,$H59=0),"－ ",$H59-I59) -> -2 | O59: =IF(AND(I59=0,$H59>0),"皆増 ",IF(AND(I59>0,$H59=0),"皆減 ",IF(AND(I59=0,$H59=0),"－ ",N59/I59))) -> 皆減 | P59: =IF(OR(F59>0,G59>0,H59>0,I59>0),"表示（判定）","×表示しない") -> 表示（判定） | R59: ='[1]3条支出'!$E$29 -> 0 | S59: =ROUND(R59/1000,0)+T59 -> 0 | U59: 38 | W59: =SUM(U59:V59) -> 38
B60: 予備費 | E60: 0 | F60: 20000 | G60: =W60 -> 0 | H60: 0 | I60: 0 | J60: =IF(AND(F60=0,$H60=0),"－ ",$H60-F60) -> -20000 | K60: =IF(AND(F60=0,$H60>0),"皆増 ",IF(AND(F60>0,$H60=0),"皆減 ",IF(AND(F60=0,$H60=0),"－ ",J60/F60))) -> 皆減 | L60: =IF(AND(G60=0,$H60=0),"－ ",$H60-G60) -> － | M60: =IF(AND(G60=0,$H60>0),"皆増 ",IF(AND(G60>0,$H60=0),"皆減 ",IF(AND(G60=0,$H60=0),"－ ",L60/G60))) -> － | N60: =IF(AND(I60=0,$H60=0),"－ ",$H60-I60) -> － | O60: =IF(AND(I60=0,$H60>0),"皆増 ",IF(AND(I60>0,$H60=0),"皆減 ",IF(AND(I60=0,$H60=0),"－ ",N60/I60))) -> － | P60: =IF(OR(F60>0,G60>0,H60>0,I60>0),"表示（判定）","×表示しない") -> 表示（判定） | U60: 7273 | V60: -7273 | W60: =SUM(U60:V60) -> 0
P61: 表示
A62: 収支差引 | E62: =E9-E36 -> 9623 | F62: =F9-F36 -> 1022518 | G62: =G9-G36 -> 1055297 | H62: =H9-H36 -> 1467504 | I62: =I9-I36 -> 1217641 | J62: =IF(AND(F62=0,$H62=0),"－ ",$H62-F62) -> 444986 | K62: =IF(AND(F62=0,$H62>0),"皆増 ",IF(AND(F62>0,$H62=0),"皆減 ",IF(AND(F62=0,$H62=0),"－ ",J62/F62))) -> 0.43518647 | L62: =IF(AND(G62=0,$H62=0),"－ ",$H62-G62) -> 412207 | M62: =IF(AND(G62=0,$H62>0),"皆増 ",IF(AND(G62>0,$H62=0),"皆減 ",IF(AND(G62=0,$H62=0),"－ ",L62/G62))) -> 0.39060757 | N62: =IF(AND(I62=0,$H62=0),"－ ",$H62-I62) -> 249863 | O62: =IF(AND(I62=0,$H62>0),"皆増 ",IF(AND(I62>0,$H62=0),"皆減 ",IF(AND(I62=0,$H62=0),"－ ",N62/I62))) -> 0.20520252 | P62: 表示 | R62: =R9-R36 -> 1467502897
P63: 表示 | Q63: 消費税資本的収支調整を控除 | R63: =[3]消費税!$AF$118 -> -923595698 | T63: =ROUND(R63/1000,0)+S63 -> -923596
A64: 税抜収支差引（純利益） | E64: =E11-E38 -> 20556607 | F64: 120300 | G64: 87714 | H64: =S64 -> 543907 | I64: 447981 | J64: =IF(AND(F64=0,$H64=0),"－ ",$H64-F64) -> 423607 | K64: =IF(AND(F64=0,$H64>0),"皆増 ",IF(AND(F64>0,$H64=0),"皆減 ",IF(AND(F64=0,$H64=0),"－ ",J64/F64))) -> 3.5212552 | L64: =IF(AND(G64=0,$H64=0),"－ ",$H64-G64) -> 456193 | M64: =IF(AND(G64=0,$H64>0),"皆増 ",IF(AND(G64>0,$H64=0),"皆減 ",IF(AND(G64=0,$H64=0),"－ ",L64/G64))) -> 5.2009143 | N64: =IF(AND(I64=0,$H64=0),"－ ",$H64-I64) -> 95926 | O64: =IF(AND(I64=0,$H64>0),"皆増 ",IF(AND(I64>0,$H64=0),"皆減 ",IF(AND(I64=0,$H64=0),"－ ",N64/I64))) -> 0.21412962 | P64: 表示 | R64: =SUM(R62:R63) -> 543907199 | S64: =ROUND(R64/1000,0)+T64 -> 543907
B65: 当年度補てん財源分 | P65: ×表示しない
B66: 翌年度補てん財源分 | P66: ×表示しない
Q69: 収支差引 | R69: =R9-R36 -> 1467502897 | S69: =S33-S62 -> 44454712

Sheet ４条（みなし）
A1: =+CONCATENATE("令和",+DBCS(MID(F5,2,1)),"年度決算 資本的収支（税込）みなし") -> 令和５年度決算 資本的収支（税込）みなし | P1: =総括表!$K$1 -> 令和6年5月22日
A3: 収 入 | O3: （単位：千円、％）
K4: 差引増減
A5: 区分 | E5: 財政収支計画 （参考） | F5: Ｒ５ 議決予算 | G5: Ｒ５ 決見（4月） | H5: Ｒ５ 決算 | J5: Ｒ４ 決算 | K5: 対Ｒ５議決予算 | M5: 対Ｒ５決見（4月） | O5: 対Ｒ４決算 | S5: R5決算 | V5: 令和5年度4月決見 | X5: 令和5年度4月決見 | Z5: 令和5年度4月決見
F6: (a) | G6: (b) | H6: (c) | I6: AAA | J6: (d) | K6: (c-a) | L6: 率 | M6: (c-b) | N6: 率 | O6: (c-d) | P6: 率 | Q6: 表示判定 | R6: AAA | S6: （参照数式） | T6: 千円返還＋端数調整 | U6: ↓端数調整 | V6: 決見額千円 | W6: 調整 | X6: 決見額千円 | Z6: 決見額千円
A7: 資本的収入 | E7: =SUM(E8,E19:E23,E28,E35,E36) -> 0 | F7: =SUM(F8,F19:F23,F28,F35,F36) -> 42627050 | G7: =SUM(G8,G19:G23,G28,G35,G36) -> 42172333 | H7: =SUM(H8,H19:H23,H28,H35,H36) -> 42243091 | J7: =SUM(J8,J19:J23,J28,J35,J36) -> 41780528 | K7: =IF(AND(F7=0,$H7=0),"－ ",$H7-F7) -> -383959 | L7: =IF(AND(F7=0,$H7>0),"皆増 ",IF(AND(F7>0,$H7=0),"皆減 ",IF(AND(F7=0,$H7=0),"－ ",K7/F7))) -> -0.0090074026 | M7: =IF(AND(G7=0,$H7=0),"－ ",$H7-G7) -> 70758 | N7: =IF(AND(G7=0,$H7>0),"皆増 ",IF(AND(G7>0,$H7=0),"皆減 ",IF(AND(G7=0,$H7=0),"－ ",M7/G7))) -> 0.0016778299 | O7: =IF(AND(J7=0,$H7=0),"－ ",$H7-J7) -> 462563 | P7: =IF(AND(J7=0,$H7>0),"皆増 ",IF(AND(J7>0,$H7=0),"皆減 ",IF(AND(J7=0,$H7=0),"－ ",O7/J7))) -> 0.011071258 | Q7: =IF(OR(F7>0,G7>0,H7>0,J7>0),"表示（判定）","×表示しない") -> 表示（判定） | S7: =IF('(繰)4条収入'!M5=SUM(S10:S36),'(繰)4条収入'!M5,"エラー") -> 42243090880 | T7: =ROUND(S7/1000,0)+U7 -> 42243091
B8: 企業債 | E8: =SUM(E9,E18) -> 0 | F8: =SUM(F9,F17,F18) -> 32505200 | G8: =SUM(G9,G17,G18) -> 32352700 | H8: =SUM(H9,H17,H18) -> 32352700 | J8: =SUM(J9,J17,J18) -> 31138800 | K8: =IF(AND(F8=0,$H8=0),"－ ",$H8-F8) -> -152500 | L8: =IF(AND(F8=0,$H8>0),"皆増 ",IF(AND(F8>0,$H8=0),"皆減 ",IF(AND(F8=0,$H8=0),"－ ",K8/F8))) -> -0.004691557 | M8: =IF(AND(G8=0,$H8=0),"－ ",$H8-G8) -> 0 | N8: =IF(AND(G8=0,$H8>0),"皆増 ",IF(AND(G8>0,$H8=0),"皆減 ",IF(AND(G8=0,$H8=0),"－ ",M8/G8))) -> 0 | O8: =IF(AND(J8=0,$H8=0),"－ ",$H8-J8) -> 1213900 | P8: =IF(AND(J8=0,$H8>0),"皆増 ",IF(AND(J8>0,$H8=0),"皆減 ",IF(AND(J8=0,$H8=0),"－ ",O8/J8))) -> 0.038983519 | Q8: =IF(OR(F8>0,G8>0,H8>0,J8>0),"表示（判定）","×表示しない") -> 表示（判定）
C9: 建設企業債 | E9: =SUM(E10:E16) -> 0 | F9: =SUM(F10:F16) -> 15494400 | G9: =SUM(G10:G16) -> 15345000 | H9: =SUM(H10:H16) -> 15345000 | J9: =SUM(J10:J16) -> 14805300 | K9: =IF(AND(F9=0,$H9=0),"－ ",$H9-F9) -> -149400 | L9: =IF(AND(F9=0,$H9>0),"皆増 ",IF(AND(F9>0,$H9=0),"皆減 ",IF(AND(F9=0,$H9=0),"－ ",K9/F9))) -> -0.0096421933 | M9: =IF(AND(G9=0,$H9=0),"－ ",$H9-G9) -> 0 | N9: =IF(AND(G9=0,$H9>0),"皆増 ",IF(AND(G9>0,$H9=0),"皆減 ",IF(AND(G9=0,$H9=0),"－ ",M9/G9))) -> 0 | O9: =IF(AND(J9=0,$H9=0),"－ ",$H9-J9) -> 539700 | P9: =IF(AND(J9=0,$H9>0),"皆増 ",IF(AND(J9>0,$H9=0),"皆減 ",IF(AND(J9=0,$H9=0),"－ ",O9/J9))) -> 0.036453162 | Q9: =IF(OR(F9>0,G9>0,H9>0,J9>0),"表示（判定）","×表示しない") -> 表示（判定）
D10: 公共下水道事業債 | F10: =ROUND('(繰)4条収入'!D7/1000,0) -> 8984800 | G10: =V10 -> 8984800 | H10: =T10 -> 8984800 | J10: 8443100 | K10: =IF(AND(F10=0,$H10=0),"－ ",$H10-F10) -> 0 | L10: =IF(AND(F10=0,$H10>0),"皆増 ",IF(AND(F10>0,$H10=0),"皆減 ",IF(AND(F10=0,$H10=0),"－ ",K10/F10))) -> 0 | M10: =IF(AND(G10=0,$H10=0),"－ ",$H10-G10) -> 0 | N10: =IF(AND(G10=0,$H10>0),"皆増 ",IF(AND(G10>0,$H10=0),"皆減 ",IF(AND(G10=0,$H10=0),"－ ",M10/G10))) -> 0 | O10: =IF(AND(J10=0,$H10=0),"－ ",$H10-J10) -> 541700 | P10: =IF(AND(J10=0,$H10>0),"皆増 ",IF(AND(J10>0,$H10=0),"皆減 ",IF(AND(J10=0,$H10=0),"－ ",O10/J10))) -> 0.064158899 | Q10: =IF(OR(F10>0,G10>0,H10>0,J10>0),"表示（判定）","×表示しない") -> 表示（判定） | S10: ='(繰)4条収入'!M7 -> 8984800000 | T10: =ROUND(S10/1000,0)+U10 -> 8984800 | V10: =SUM(W10:X10) -> 8984800 | X10: 8984800 | Z10: #='[4-04 集計表.xlsx]4条収支'!$G10
D11: 流域下水道事業債 | F11: =ROUND('(繰)4条収入'!D9/1000,0) -> 160100 | G11: =V11 -> 120200 | H11: =T11 -> 120200 | J11: 83200 | K11: =IF(AND(F11=0,$H11=0),"－ ",$H11-F11) -> -39900 | L11: =IF(AND(F11=0,$H11>0),"皆増 ",IF(AND(F11>0,$H11=0),"皆減 ",IF(AND(F11=0,$H11=0),"－ ",K11/F11))) -> -0.24921924 | M11: =IF(AND(G11=0,$H11=0),"－ ",$H11-G11) -> 0 | N11: =IF(AND(G11=0,$H11>0),"皆増 ",IF(AND(G11>0,$H11=0),"皆減 ",IF(AND(G11=0,$H11=0),"－ ",M11/G11))) -> 0 | O11: =IF(AND(J11=0,$H11=0),"－ ",$H11-J11) -> 37000 | P11: =IF(AND(J11=0,$H11>0),"皆増 ",IF(AND(J11>0,$H11=0),"皆減 ",IF(AND(J11=0,$H11=0),"－ ",O11/J11))) -> 0.44471154 | Q11: =IF(OR(F11>0,G11>0,H11>0,J11>0),"表示（判定）","×表示しない") -> 表示（判定） | S11: ='(繰)4条収入'!M9 -> 120200000 | T11: =ROUND(S11/1000,0)+U11 -> 120200 | V11: =SUM(W11:X11) -> 120200 | X11: 120200 | Z11: #='[4-04 集計表.xlsx]4条収支'!$G11
D12: 資本費平準化債（通常分） | F12: =F60 -> 12600 | G12: =V12 -> 12600 | H12: =T12 -> 12600 | J12: 3500 | K12: =IF(AND(F12=0,$H12=0),"－ ",$H12-F12) -> 0 | L12: =IF(AND(F12=0,$H12>0),"皆増 ",IF(AND(F12>0,$H12=0),"皆減 ",IF(AND(F12=0,$H12=0),"－ ",K12/F12))) -> 0 | M12: =IF(AND(G12=0,$H12=0),"－ ",$H12-G12) -> 0 | N12: =IF(AND(G12=0,$H12>0),"皆増 ",IF(AND(G12>0,$H12=0),"皆減 ",IF(AND(G12=0,$H12=0),"－ ",M12/G12))) -> 0 | O12: =IF(AND(J12=0,$H12=0),"－ ",$H12-J12) -> 9100 | P12: =IF(AND(J12=0,$H12>0),"皆増 ",IF(AND(J12>0,$H12=0),"皆減 ",IF(AND(J12=0,$H12=0),"－ ",O12/J12))) -> 2.6 | Q12: =IF(OR(F12>0,G12>0,H12>0,J12>0),"表示（判定）","×表示しない") -> 表示（判定） | S12: ='(繰)4条支出 '!K13 -> 12600000 | T12: =ROUND(S12/1000,0)+U12 -> 12600 | V12: =SUM(W12:X12) -> 12600 | X12: 12600 | Z12: #='[4-04 集計表.xlsx]4条収支'!$G12
D13: 資本費平準化債（拡大分） | F13: =ROUND('(繰)4条収入'!D10/1000,0)-F12 -> 6026400 | G13: =V13 -> 5916900 | H13: =T13 -> 5916900 | J13: 5840800 | K13: =IF(AND(F13=0,$H13=0),"－ ",$H13-F13) -> -109500 | L13: =IF(AND(F13=0,$H13>0),"皆増 ",IF(AND(F13>0,$H13=0),"皆減 ",IF(AND(F13=0,$H13=0),"－ ",K13/F13))) -> -0.018170052 | M13: =IF(AND(G13=0,$H13=0),"－ ",$H13-G13) -> 0 | N13: =IF(AND(G13=0,$H13>0),"皆増 ",IF(AND(G13>0,$H13=0),"皆減 ",IF(AND(G13=0,$H13=0),"－ ",M13/G13))) -> 0 | O13: =IF(AND(J13=0,$H13=0),"－ ",$H13-J13) -> 76100 | P13: =IF(AND(J13=0,$H13>0),"皆増 ",IF(AND(J13>0,$H13=0),"皆減 ",IF(AND(J13=0,$H13=0),"－ ",O13/J13))) -> 0.013029037 | Q13: =IF(OR(F13>0,G13>0,H13>0,J13>0),"表示（判定）","×表示しない") -> 表示（判定） | S13: ='(繰)4条収入'!M10-S12 -> 5916900000 | T13: =ROUND(S13/1000,0)+U13 -> 5916900 | V13: =SUM(W13:X13) -> 5916900 | X13: 5916900 | Z13: #='[4-04 集計表.xlsx]4条収支'!$G13
D14: 市街化区域外汚水処理施設事業債 | F14: =ROUND('(繰)4条収入'!D8/1000,0) -> 310500 | G14: =V14 -> 310500 | H14: =T14 -> 310500 | J14: 434700 | K14: =IF(AND(F14=0,$H14=0),"－ ",$H14-F14) -> 0 | L14: =IF(AND(F14=0,$H14>0),"皆増 ",IF(AND(F14>0,$H14=0),"皆減 ",IF(AND(F14=0,$H14=0),"－ ",K14/F14))) -> 0 | M14: =IF(AND(G14=0,$H14=0),"－ ",$H14-G14) -> 0 | N14: =IF(AND(G14=0,$H14>0),"皆増 ",IF(AND(G14>0,$H14=0),"皆減 ",IF(AND(G14=0,$H14=0),"－ ",M14/G14))) -> 0 | O14: =IF(AND(J14=0,$H14=0),"－ ",$H14-J14) -> -124200 | P14: =IF(AND(J14=0,$H14>0),"皆増 ",IF(AND(J14>0,$H14=0),"皆減 ",IF(AND(J14=0,$H14=0),"－ ",O14/J14))) -> -0.28571429 | Q14: =IF(OR(F14>0,G14>0,H14>0,J14>0),"表示（判定）","×表示しない") -> 表示（判定） | S14: ='(繰)4条収入'!M8 -> 310500000 | T14: =ROUND(S14/1000,0)+U14 -> 310500 | V14: =SUM(W14:X14) -> 310500 | X14: 310500 | Z14: #='[4-04 集計表.xlsx]4条収支'!$G14
D15: 災害復旧事業債 | F15: =ROUND('(繰)4条収入'!D11/1000,0) -> 0 | G15: =V15 -> 0 | H15: =T15 -> 0 | J15: 0 | K15: =IF(AND(F15=0,$H15=0),"－ ",$H15-F15) -> － | L15: =IF(AND(F15=0,$H15>0),"皆増 ",IF(AND(F15>0,$H15=0),"皆減 ",IF(AND(F15=0,$H15=0),"－ ",K15/F15))) -> － | M15: =IF(AND(G15=0,$H15=0),"－ ",$H15-G15) -> － | N15: =IF(AND(G15=0,$H15>0),"皆増 ",IF(AND(G15>0,$H15=0),"皆減 ",IF(AND(G15=0,$H15=0),"－ ",M15/G15))) -> － | O15: =IF(AND(J15=0,$H15=0),"－ ",$H15-J15) -> － | P15: =IF(AND(J15=0,$H15>0),"皆増 ",IF(AND(J15>0,$H15=0),"皆減 ",IF(AND(J15=0,$H15=0),"－ ",O15/J15))) -> － | Q15: =IF(OR(F15>0,G15>0,H15>0,J15>0),"表示（判定）","×表示しない") -> ×表示しない | S15: ='(繰)4条収入'!M11 -> 0 | T15: =ROUND(S15/1000,0)+U15 -> 0
J16: 0 | K16: =IF(AND(F16=0,$H16=0),"－ ",$H16-F16) -> － | L16: =IF(AND(F16=0,$H16>0),"皆増 ",IF(AND(F16>0,$H16=0),"皆減 ",IF(AND(F16=0,$H16=0),"－ ",K16/F16))) -> － | M16: =IF(AND(G16=0,$H16=0),"－ ",$H16-G16) -> － | N16: =IF(AND(G16=0,$H16>0),"皆増 ",IF(AND(G16>0,$H16=0),"皆減 ",IF(AND(G16=0,$H16=0),"－ ",M16/G16))) -> － | O16: =IF(AND(J16=0,$H16=0),"－ ",$H16-J16) -> － | P16: =IF(AND(J16=0,$H16>0),"皆増 ",IF(AND(J16>0,$H16=0),"皆減 ",IF(AND(J16=0,$H16=0),"－ ",O16/J16))) -> － | Q16: =IF(OR(F16>0,G16>0,H16>0,J16>0),"表示（判定）","×表示しない") -> ×表示しない
C17: 借換債 | F17: =ROUND('(繰)4条収入'!D12/1000,0) -> 17010800 | G17: =V17 -> 17007700 | H17: =T17 -> 17007700 | J17: 16333500 | K17: =IF(AND(F17=0,$H17=0),"－ ",$H17-F17) -> -3100 | L17: =IF(AND(F17=0,$H17>0),"皆増 ",IF(AND(F17>0,$H17=0),"皆減 ",IF(AND(F17=0,$H17=0),"－ ",K17/F17))) -> -0.00018223717 | M17: =IF(AND(G17=0,$H17=0),"－ ",$H17-G17) -> 0 | N17: =IF(AND(G17=0,$H17>0),"皆増 ",IF(AND(G17>0,$H17=0),"皆減 ",IF(AND(G17=0,$H17=0),"－ ",M17/G17))) -> 0 | O17: =IF(AND(J17=0,$H17=0),"－ ",$H17-J17) -> 674200 | P17: =IF(AND(J17=0,$H17>0),"皆増 ",IF(AND(J17>0,$H17=0),"皆減 ",IF(AND(J17=0,$H17=0),"－ ",O17/J17))) -> 0.04127713 | Q17: =IF(OR(F17>0,G17>0,H17>0,J17>0),"表示（判定）","×表示しない") -> 表示（判定） | S17: ='(繰)4条収入'!M12 -> 17007700000 | T17: =ROUND(S17/1000,0)+U17 -> 17007700 | V17: =SUM(W17:X17) -> 17007700 | X17: 17007700 | Z17: #='[4-04 集計表.xlsx]4条収支'!$G16
C18: 出資債 | K18: =IF(AND(F18=0,$H18=0),"－ ",$H18-F18) -> － | L18: =IF(AND(F18=0,$H18>0),"皆増 ",IF(AND(F18>0,$H18=0),"皆減 ",IF(AND(F18=0,$H18=0),"－ ",K18/F18))) -> － | M18: =IF(AND(G18=0,$H18=0),"－ ",$H18-G18) -> － | N18: =IF(AND(G18=0,$H18>0),"皆増 ",IF(AND(G18>0,$H18=0),"皆減 ",IF(AND(G18=0,$H18=0),"－ ",M18/G18))) -> － | O18: =IF(AND(J18=0,$H18=0),"－ ",$H18-J18) -> － | P18: =IF(AND(J18=0,$H18>0),"皆増 ",IF(AND(J18>0,$H18=0),"皆減 ",IF(AND(J18=0,$H18=0),"－ ",O18/J18))) -> － | Q18: =IF(OR(F18>0,G18>0,H18>0,J18>0),"表示（判定）","×表示しない") -> ×表示しない
B19: 一般会計出資金 | F19: =ROUND('(繰)4条収入'!D14/1000,0) -> 3640474 | G19: =V19 -> 3379653 | H19: =T19 -> 3285505 | J19: 4465119 | K19: =IF(AND(F19=0,$H19=0),"－ ",$H19-F19) -> -354969 | L19: =IF(AND(F19=0,$H19>0),"皆増 ",IF(AND(F19>0,$H19=0),"皆減 ",IF(AND(F19=0,$H19=0),"－ ",K19/F19))) -> -0.097506259 | M19: =IF(AND(G19=0,$H19=0),"－ ",$H19-G19) -> -94148 | N19: =IF(AND(G19=0,$H19>0),"皆増 ",IF(AND(G19>0,$H19=0),"皆減 ",IF(AND(G19=0,$H19=0),"－ ",M19/G19))) -> -0.027857298 | O19: =IF(AND(J19=0,$H19=0),"－ ",$H19-J19) -> -1179614 | P19: =IF(AND(J19=0,$H19>0),"皆増 ",IF(AND(J19>0,$H19=0),"皆減 ",IF(AND(J19=0,$H19=0),"－ ",O19/J19))) -> -0.26418422 | Q19: =IF(OR(F19>0,G19>0,H19>0,J19>0),"表示（判定）","×表示しない") -> 表示（判定） | S19: ='(繰)4条収入'!M13 -> 3285504551 | T19: =ROUND(S19/1000,0)+U19 -> 3285505 | V19: =SUM(W19:X19) -> 3379653 | W19: =60000+9916 -> 69916 | X19: 3309737 | Z19: 3309653
B20: 国庫補助金 | F20: =ROUND('(繰)4条収入'!D16/1000,0) -> 5769500 | G20: =V20 -> 5766211 | H20: =T20 -> 5766274 | J20: 5632700 | K20: =IF(AND(F20=0,$H20=0),"－ ",$H20-F20) -> -3226 | L20: =IF(AND(F20=0,$H20>0),"皆増 ",IF(AND(F20>0,$H20=0),"皆減 ",IF(AND(F20=0,$H20=0),"－ ",K20/F20))) -> -0.00055914724 | M20: =IF(AND(G20=0,$H20=0),"－ ",$H20-G20) -> 63 | N20: =IF(AND(G20=0,$H20>0),"皆増 ",IF(AND(G20>0,$H20=0),"皆減 ",IF(AND(G20=0,$H20=0),"－ ",M20/G20))) -> 1.0925719e-05 | O20: =IF(AND(J20=0,$H20=0),"－ ",$H20-J20) -> 133574 | P20: =IF(AND(J20=0,$H20>0),"皆増 ",IF(AND(J20>0,$H20=0),"皆減 ",IF(AND(J20=0,$H20=0),"－ ",O20/J20))) -> 0.023714027 | Q20: =IF(OR(F20>0,G20>0,H20>0,J20>0),"表示（判定）","×表示しない") -> 表示（判定） | S20: ='(繰)4条収入'!M16 -> 5766273739 | T20: =ROUND(S20/1000,0)+U20 -> 5766274 | V20: =SUM(W20:X20) -> 5766211 | X20: 5766211 | Z20: #='[4-04 集計表.xlsx]4条収支'!$G18
B21: 県補助金 | K21: =IF(AND(F21=0,$H21=0),"－ ",$H21-F21) -> － | L21: =IF(AND(F21=0,$H21>0),"皆増 ",IF(AND(F21>0,$H21=0),"皆減 ",IF(AND(F21=0,$H21=0),"－ ",K21/F21))) -> － | M21: =IF(AND(G21=0,$H21=0),"－ ",$H21-G21) -> － | N21: =IF(AND(G21=0,$H21>0),"皆増 ",IF(AND(G21>0,$H21=0),"皆減 ",IF(AND(G21=0,$H21=0),"－ ",M21/G21))) -> － | O21: =IF(AND(J21=0,$H21=0),"－ ",$H21-J21) -> － | P21: =IF(AND(J21=0,$H21>0),"皆増 ",IF(AND(J21>0,$H21=0),"皆減 ",IF(AND(J21=0,$H21=0),"－ ",O21/J21))) -> － | Q21: =IF(OR(F21>0,G21>0,H21>0,J21>0),"表示（判定）","×表示しない") -> ×表示しない
B22: 工事受託金 | F22: =ROUND('(繰)4条収入'!D20/1000,0) -> 54236 | G22: =V22 -> 54236 | H22: =T22 -> 24373 | J22: 31095 | K22: =IF(AND(F22=0,$H22=0),"－ ",$H22-F22) -> -29863 | L22: =IF(AND(F22=0,$H22>0),"皆増 ",IF(AND(F22>0,$H22=0),"皆減 ",IF(AND(F22=0,$H22=0),"－ ",K22/F22))) -> -0.55061214 | M22: =IF(AND(G22=0,$H22=0),"－ ",$H22-G22) -> -29863 | N22: =IF(AND(G22=0,$H22>0),"皆増 ",IF(AND(G22>0,$H22=0),"皆減 ",IF(AND(G22=0,$H22=0),"－ ",M22/G22))) -> -0.55061214 | O22: =IF(AND(J22=0,$H22=0),"－ ",$H22-J22) -> -6722 | P22: =IF(AND(J22=0,$H22>0),"皆増 ",IF(AND(J22>0,$H22=0),"皆減 ",IF(AND(J22=0,$H22=0),"－ ",O22/J22))) -> -0.21617623 | Q22: =IF(OR(F22>0,G22>0,H22>0,J22>0),"表示（判定）","×表示しない") -> 表示（判定） | S22: ='(繰)4条収入'!M20 -> 24373083 | T22: =ROUND(S22/1000,0)+U22 -> 24373 | V22: =SUM(W22:X22) -> 54236 | X22: 54236 | Z22: #='[4-04 集計表.xlsx]4条収支'!$G19
B23: 負担金 | E23: =SUM(E24:E27) -> 0 | F23: =SUM(F24:F27) -> 632996 | G23: =SUM(G24:G27) -> 571080 | H23: =SUM(H24:H27) -> 764304 | J23: =SUM(J24:J27) -> 505843 | K23: =IF(AND(F23=0,$H23=0),"－ ",$H23-F23) -> 131308 | L23: =IF(AND(F23=0,$H23>0),"皆増 ",IF(AND(F23>0,$H23=0),"皆減 ",IF(AND(F23=0,$H23=0),"－ ",K23/F23))) -> 0.20743891 | M23: =IF(AND(G23=0,$H23=0),"－ ",$H23-G23) -> 193224 | N23: =IF(AND(G23=0,$H23>0),"皆増 ",IF(AND(G23>0,$H23=0),"皆減 ",IF(AND(G23=0,$H23=0),"－ ",M23/G23))) -> 0.33834839 | O23: =IF(AND(J23=0,$H23=0),"－ ",$H23-J23) -> 258461 | P23: =IF(AND(J23=0,$H23>0),"皆増 ",IF(AND(J23>0,$H23=0),"皆減 ",IF(AND(J23=0,$H23=0),"－ ",O23/J23))) -> 0.51095103 | Q23: =IF(OR(F23>0,G23>0,H23>0,J23>0),"表示（判定）","×表示しない") -> 表示（判定） | T23: =ROUND(S23/1000,0)+U23 -> 0
C24: 受益者負担金 | F24: =ROUND('(繰)4条収入'!D23/1000,0) -> 14208 | G24: =V24 -> 14208 | H24: =T24 -> 8800 | J24: 23930 | K24: =IF(AND(F24=0,$H24=0),"－ ",$H24-F24) -> -5408 | L24: =IF(AND(F24=0,$H24>0),"皆増 ",IF(AND(F24>0,$H24=0),"皆減 ",IF(AND(F24=0,$H24=0),"－ ",K24/F24))) -> -0.38063063 | M24: =IF(AND(G24=0,$H24=0),"－ ",$H24-G24) -> -5408 | N24: =IF(AND(G24=0,$H24>0),"皆増 ",IF(AND(G24>0,$H24=0),"皆減 ",IF(AND(G24=0,$H24=0),"－ ",M24/G24))) -> -0.38063063 | O24: =IF(AND(J24=0,$H24=0),"－ ",$H24-J24) -> -15130 | P24: =IF(AND(J24=0,$H24>0),"皆増 ",IF(AND(J24>0,$H24=0),"皆減 ",IF(AND(J24=0,$H24=0),"－ ",O24/J24))) -> -0.63226076 | Q24: =IF(OR(F24>0,G24>0,H24>0,J24>0),"表示（判定）","×表示しない") -> 表示（判定） | S24: ='(繰)4条収入'!M23 -> 8799605 | T24: =ROUND(S24/1000,0)+U24 -> 8800 | V24: =SUM(W24:X24) -> 14208 | X24: 14208 | Z24: #='[4-04 集計表.xlsx]4条収支'!$G21
C25: 受益者分担金 | F25: =ROUND('(繰)4条収入'!D24/1000,0) -> 40980 | G25: =V25 -> 42420 | H25: =T25 -> 35218 | J25: 38497 | K25: =IF(AND(F25=0,$H25=0),"－ ",$H25-F25) -> -5762 | L25: =IF(AND(F25=0,$H25>0),"皆増 ",IF(AND(F25>0,$H25=0),"皆減 ",IF(AND(F25=0,$H25=0),"－ ",K25/F25))) -> -0.14060517 | M25: =IF(AND(G25=0,$H25=0),"－ ",$H25-G25) -> -7202 | N25: =IF(AND(G25=0,$H25>0),"皆増 ",IF(AND(G25>0,$H25=0),"皆減 ",IF(AND(G25=0,$H25=0),"－ ",M25/G25))) -> -0.16977841 | O25: =IF(AND(J25=0,$H25=0),"－ ",$H25-J25) -> -3279 | P25: =IF(AND(J25=0,$H25>0),"皆増 ",IF(AND(J25>0,$H25=0),"皆減 ",IF(AND(J25=0,$H25=0),"－ ",O25/J25))) -> -0.085175468 | Q25: =IF(OR(F25>0,G25>0,H25>0,J25>0),"表示（判定）","×表示しない") -> 表示（判定） | S25: ='(繰)4条収入'!M24 -> 35218280 | T25: =ROUND(S25/1000,0)+U25 -> 35218 | V25: =SUM(W25:X25) -> 42420 | X25: 42420 | Z25: #='[4-04 集計表.xlsx]4条収支'!$G22
C26: 工事負担金 | F26: =ROUND('(繰)4条収入'!D25/1000,0) -> 577808 | G26: =V26 -> 514452 | H26: =T26 -> 720286 | J26: 443416 | K26: =IF(AND(F26=0,$H26=0),"－ ",$H26-F26) -> 142478 | L26: =IF(AND(F26=0,$H26>0),"皆増 ",IF(AND(F26>0,$H26=0),"皆減 ",IF(AND(F26=0,$H26=0),"－ ",K26/F26))) -> 0.24658364 | M26: =IF(AND(G26=0,$H26=0),"－ ",$H26-G26) -> 205834 | N26: =IF(AND(G26=0,$H26>0),"皆増 ",IF(AND(G26>0,$H26=0),"皆減 ",IF(AND(G26=0,$H26=0),"－ ",M26/G26))) -> 0.40010341 | O26: =IF(AND(J26=0,$H26=0),"－ ",$H26-J26) -> 276870 | P26: =IF(AND(J26=0,$H26>0),"皆増 ",IF(AND(J26>0,$H26=0),"皆減 ",IF(AND(J26=0,$H26=0),"－ ",O26/J26))) -> 0.62440237 | Q26: =IF(OR(F26>0,G26>0,H26>0,J26>0),"表示（判定）","×表示しない") -> 表示（判定） | S26: ='(繰)4条収入'!M25 -> 720286509 | T26: =ROUND(S26/1000,0)+U26 -> 720286 | U26: -1 | V26: =SUM(W26:X26) -> 514452 | W26: -60000 | X26: 574452 | Z26: #='[4-04 集計表.xlsx]4条収支'!$G23
C27: 他会計負担金 | K27: =IF(AND(F27=0,$H27=0),"－ ",$H27-F27) -> － | L27: =IF(AND(F27=0,$H27>0),"皆増 ",IF(AND(F27>0,$H27=0),"皆減 ",IF(AND(F27=0,$H27=0),"－ ",K27/F27))) -> － | M27: =IF(AND(G27=0,$H27=0),"－ ",$H27-G27) -> － | N27: =IF(AND(G27=0,$H27>0),"皆増 ",IF(AND(G27>0,$H27=0),"皆減 ",IF(AND(G27=0,$H27=0),"－ ",M27/G27))) -> － | O27: =IF(AND(J27=0,$H27=0),"－ ",$H27-J27) -> － | P27: =IF(AND(J27=0,$H27>0),"皆増 ",IF(AND(J27>0,$H27=0),"皆減 ",IF(AND(J27=0,$H27=0),"－ ",O27/J27))) -> － | Q27: =IF(OR(F27>0,G27>0,H27>0,J27>0),"表示（判定）","×表示しない") -> ×表示しない
B28: 水洗化貸付事業収入 | E28: =SUM(E29:E31) -> 0 | F28: =SUM(F29:F31) -> 9913 | G28: =SUM(G29:G31) -> 3987 | H28: =SUM(H29:H31) -> 3987 | J28: =SUM(J29:J31) -> 5324 | K28: =IF(AND(F28=0,$H28=0),"－ ",$H28-F28) -> -5926 | L28: =IF(AND(F28=0,$H28>0),"皆増 ",IF(AND(F28>0,$H28=0),"皆減 ",IF(AND(F28=0,$H28=0),"－ ",K28/F28))) -> -0.59780087 | M28: =IF(AND(G28=0,$H28=0),"－ ",$H28-G28) -> 0 | N28: =IF(AND(G28=0,$H28>0),"皆増 ",IF(AND(G28>0,$H28=0),"皆減 ",IF(AND(G28=0,$H28=0),"－ ",M28/G28))) -> 0 | O28: =IF(AND(J28=0,$H28=0),"－ ",$H28-J28) -> -1337 | P28: =IF(AND(J28=0,$H28>0),"皆増 ",IF(AND(J28>0,$H28=0),"皆減 ",IF(AND(J28=0,$H28=0),"－ ",O28/J28))) -> -0.25112697 | Q28: =IF(OR(F28>0,G28>0,H28>0,J28>0),"表示（判定）","×表示しない") -> 表示（判定）
C29: 貸付企業債 | K29: =IF(AND(F29=0,$H29=0),"－ ",$H29-F29) -> － | L29: =IF(AND(F29=0,$H29>0),"皆増 ",IF(AND(F29>0,$H29=0),"皆減 ",IF(AND(F29=0,$H29=0),"－ ",K29/F29))) -> － | M29: =IF(AND(G29=0,$H29=0),"－ ",$H29-G29) -> － | N29: =IF(AND(G29=0,$H29>0),"皆増 ",IF(AND(G29>0,$H29=0),"皆減 ",IF(AND(G29=0,$H29=0),"－ ",M29/G29))) -> － | O29: =IF(AND(J29=0,$H29=0),"－ ",$H29-J29) -> － | P29: =IF(AND(J29=0,$H29>0),"皆増 ",IF(AND(J29>0,$H29=0),"皆減 ",IF(AND(J29=0,$H29=0),"－ ",O29/J29))) -> － | Q29: =IF(OR(F29>0,G29>0,H29>0,J29>0),"表示（判定）","×表示しない") -> ×表示しない
C30: 一般会計借入金 | F30: =ROUND('(繰)4条収入'!D28/1000,0) -> 0 | G30: =V30 -> 0 | H30: =T30 -> 0 | J30: 0 | K30: =IF(AND(F30=0,$H30=0),"－ ",$H30-F30) -> － | L30: =IF(AND(F30=0,$H30>0),"皆増 ",IF(AND(F30>0,$H30=0),"皆減 ",IF(AND(F30=0,$H30=0),"－ ",K30/F30))) -> － | M30: =IF(AND(G30=0,$H30=0),"－ ",$H30-G30) -> － | N30: =IF(AND(G30=0,$H30>0),"皆増 ",IF(AND(G30>0,$H30=0),"皆減 ",IF(AND(G30=0,$H30=0),"－ ",M30/G30))) -> － | O30: =IF(AND(J30=0,$H30=0),"－ ",$H30-J30) -> － | P30: =IF(AND(J30=0,$H30>0),"皆増 ",IF(AND(J30>0,$H30=0),"皆減 ",IF(AND(J30=0,$H30=0),"－ ",O30/J30))) -> － | Q30: =IF(OR(F30>0,G30>0,H30>0,J30>0),"表示（判定）","×表示しない") -> ×表示しない | S30: ='(繰)4条収入'!M28 -> 0 | T30: =ROUND(S30/1000,0)+U30 -> 0
C31: 貸付金回収金 | E31: =SUM(E32:E34) -> 0 | F31: =SUM(F32:F34) -> 9913 | G31: =SUM(G32:G34) -> 3987 | H31: =SUM(H32:H34) -> 3987 | J31: =SUM(J32:J34) -> 5324 | K31: =IF(AND(F31=0,$H31=0),"－ ",$H31-F31) -> -5926 | L31: =IF(AND(F31=0,$H31>0),"皆増 ",IF(AND(F31>0,$H31=0),"皆減 ",IF(AND(F31=0,$H31=0),"－ ",K31/F31))) -> -0.59780087 | M31: =IF(AND(G31=0,$H31=0),"－ ",$H31-G31) -> 0 | N31: =IF(AND(G31=0,$H31>0),"皆増 ",IF(AND(G31>0,$H31=0),"皆減 ",IF(AND(G31=0,$H31=0),"－ ",M31/G31))) -> 0 | O31: =IF(AND(J31=0,$H31=0),"－ ",$H31-J31) -> -1337 | P31: =IF(AND(J31=0,$H31>0),"皆増 ",IF(AND(J31>0,$H31=0),"皆減 ",IF(AND(J31=0,$H31=0),"－ ",O31/J31))) -> -0.25112697 | Q31: =IF(OR(F31>0,G31>0,H31>0,J31>0),"表示（判定）","×表示しない") -> 表示（判定）
D32: 水洗便所改造資金貸付金回収金 | F32: =1310+2440+1457+540 -> 5747 | G32: =V32 -> 2118 | H32: =T32 -> 2118 | J32: 3107 | K32: =IF(AND(F32=0,$H32=0),"－ ",$H32-F32) -> -3629 | L32: =IF(AND(F32=0,$H32>0),"皆増 ",IF(AND(F32>0,$H32=0),"皆減 ",IF(AND(F32=0,$H32=0),"－ ",K32/F32))) -> -0.63145989 | M32: =IF(AND(G32=0,$H32=0),"－ ",$H32-G32) -> 0 | N32: =IF(AND(G32=0,$H32>0),"皆増 ",IF(AND(G32>0,$H32=0),"皆減 ",IF(AND(G32=0,$H32=0),"－ ",M32/G32))) -> 0 | O32: =IF(AND(J32=0,$H32=0),"－ ",$H32-J32) -> -989 | P32: =IF(AND(J32=0,$H32>0),"皆増 ",IF(AND(J32>0,$H32=0),"皆減 ",IF(AND(J32=0,$H32=0),"－ ",O32/J32))) -> -0.31831349 | Q32: =IF(OR(F32>0,G32>0,H32>0,J32>0),"表示（判定）","×表示しない") -> 表示（判定） | S32: ='[5]4条収入'!E72 -> 2118000 | T32: =ROUND(S32/1000,0)+U32 -> 2118 | V32: =SUM(W32:X32) -> 2118 | X32: 2118 | Z32: #='[4-04 集計表.xlsx]4条収支'!$G29
D33: し尿浄化槽廃止資金貸付金回収金 | F33: =2508+1278+270+110 -> 4166 | G33: =V33 -> 1869 | H33: =T33 -> 1869 | J33: 2217 | K33: =IF(AND(F33=0,$H33=0),"－ ",$H33-F33) -> -2297 | L33: =IF(AND(F33=0,$H33>0),"皆増 ",IF(AND(F33>0,$H33=0),"皆減 ",IF(AND(F33=0,$H33=0),"－ ",K33/F33))) -> -0.55136822 | M33: =IF(AND(G33=0,$H33=0),"－ ",$H33-G33) -> 0 | N33: =IF(AND(G33=0,$H33>0),"皆増 ",IF(AND(G33>0,$H33=0),"皆減 ",IF(AND(G33=0,$H33=0),"－ ",M33/G33))) -> 0 | O33: =IF(AND(J33=0,$H33=0),"－ ",$H33-J33) -> -348 | P33: =IF(AND(J33=0,$H33>0),"皆増 ",IF(AND(J33>0,$H33=0),"皆減 ",IF(AND(J33=0,$H33=0),"－ ",O33/J33))) -> -0.15696888 | Q33: =IF(OR(F33>0,G33>0,H33>0,J33>0),"表示（判定）","×表示しない") -> 表示（判定） | S33: ='[5]4条収入'!E77 -> 1869000 | T33: =ROUND(S33/1000,0)+U33 -> 1869 | V33: =SUM(W33:X33) -> 1869 | X33: 1869 | Z33: #='[4-04 集計表.xlsx]4条収支'!$G30
D34: 排水設備改修資金貸付金回収金 | F34: 0 | G34: =V34 -> 0 | H34: =T34 -> 0 | J34: 0 | K34: =IF(AND(F34=0,$H34=0),"－ ",$H34-F34) -> － | L34: =IF(AND(F34=0,$H34>0),"皆増 ",IF(AND(F34>0,$H34=0),"皆減 ",IF(AND(F34=0,$H34=0),"－ ",K34/F34))) -> － | M34: =IF(AND(G34=0,$H34=0),"－ ",$H34-G34) -> － | N34: =IF(AND(G34=0,$H34>0),"皆増 ",IF(AND(G34>0,$H34=0),"皆減 ",IF(AND(G34=0,$H34=0),"－ ",M34/G34))) -> － | O34: =IF(AND(J34=0,$H34=0),"－ ",$H34-J34) -> － | P34: =IF(AND(J34=0,$H34>0),"皆増 ",IF(AND(J34>0,$H34=0),"皆減 ",IF(AND(J34=0,$H34=0),"－ ",O34/J34))) -> － | Q34: =IF(OR(F34>0,G34>0,H34>0,J34>0),"表示（判定）","×表示しない") -> ×表示しない | S34: ='[5]4条収入'!E82 -> 0 | T34: =ROUND(S34/1000,0)+U34 -> 0
B35: 固定資産売却代金 | F35: =ROUND('(繰)4条収入'!D31/1000,0) -> 14731 | G35: =V35 -> 44466 | H35: =T35 -> 45948 | J35: 1647 | K35: =IF(AND(F35=0,$H35=0),"－ ",$H35-F35) -> 31217 | L35: =IF(AND(F35=0,$H35>0),"皆増 ",IF(AND(F35>0,$H35=0),"皆減 ",IF(AND(F35=0,$H35=0),"－ ",K35/F35))) -> 2.1191365 | M35: =IF(AND(G35=0,$H35=0),"－ ",$H35-G35) -> 1482 | N35: =IF(AND(G35=0,$H35>0),"皆増 ",IF(AND(G35>0,$H35=0),"皆減 ",IF(AND(G35=0,$H35=0),"－ ",M35/G35))) -> 0.033328836 | O35: =IF(AND(J35=0,$H35=0),"－ ",$H35-J35) -> 44301 | P35: =IF(AND(J35=0,$H35>0),"皆増 ",IF(AND(J35>0,$H35=0),"皆減 ",IF(AND(J35=0,$H35=0),"－ ",O35/J35))) -> 26.897996 | Q35: =IF(OR(F35>0,G35>0,H35>0,J35>0),"表示（判定）","×表示しない") -> 表示（判定） | S35: ='(繰)4条収入'!M30 -> 45948113 | T35: =ROUND(S35/1000,0)+U35 -> 45948 | V35: =SUM(W35:X35) -> 44466 | X35: 44466 | Z35: #='[4-04 集計表.xlsx]4条収支'!$G32
B36: その他資本的収入 | E36: 0 | F36: 0 | G36: 0 | H36: 0 | J36: 0 | K36: =IF(AND(F36=0,$H36=0),"－ ",$H36-F36) -> － | L36: =IF(AND(F36=0,$H36>0),"皆増 ",IF(AND(F36>0,$H36=0),"皆減 ",IF(AND(F36=0,$H36=0),"－ ",K36/F36))) -> － | M36: =IF(AND(G36=0,$H36=0),"－ ",$H36-G36) -> － | N36: =IF(AND(G36=0,$H36>0),"皆増 ",IF(AND(G36>0,$H36=0),"皆減 ",IF(AND(G36=0,$H36=0),"－ ",M36/G36))) -> － | O36: =IF(AND(J36=0,$H36=0),"－ ",$H36-J36) -> － | P36: =IF(AND(J36=0,$H36>0),"皆増 ",IF(AND(J36>0,$H36=0),"皆減 ",IF(AND(J36=0,$H36=0),"－ ",O36/J36))) -> － | Q36: =IF(OR(F36>0,G36>0,H36>0,J36>0),"表示（判定）","×表示しない") -> ×表示しない
Q37: 表示
A38: 一般会計出資金・借入金合計 | E38: =SUM(E19,E30) -> 0 | F38: =SUM(F19,F30) -> 3640474 | G38: =SUM(G19,G30) -> 3379653 | H38: =SUM(H19,H30) -> 3285505 | J38: =SUM(J19,J30) -> 4465119 | K38: =IF(AND(F38=0,$H38=0),"－ ",$H38-F38) -> -354969 | L38: =IF(AND(F38=0,$H38>0),"皆増 ",IF(AND(F38>0,$H38=0),"皆減 ",IF(AND(F38=0,$H38=0),"－ ",K38/F38))) -> -0.097506259 | M38: =IF(AND(G38=0,$H38=0),"－ ",$H38-G38) -> -94148 | N38: =IF(AND(G38=0,$H38>0),"皆増 ",IF(AND(G38>0,$H38=0),"皆減 ",IF(AND(G38=0,$H38=0),"－ ",M38/G38))) -> -0.027857298 | O38: =IF(AND(J38=0,$H38=0),"－ ",$H38-J38) -> -1179614 | P38: =IF(AND(J38=0,$H38>0),"皆増 ",IF(AND(J38>0,$H38=0),"皆減 ",IF(AND(J38=0,$H38=0),"－ ",O38/J38))) -> -0.26418422 | Q38: =IF(OR(F38>0,G38>0,H38>0,J38>0),"表示（判定）","×表示しない") -> 表示（判定） | S38: 各項目 合計 → | T38: =SUM(T10:T36) -> 42243091
A39: 上記を除いた資本的収入 | F39: =F7-F38 -> 38986576 | G39: =G7-G38 -> 38792680 | H39: =H7-H38 -> 38957586 | J39: =J7-J38 -> 37315409 | K39: =IF(AND(F39=0,$H39=0),"－ ",$H39-F39) -> -28990 | L39: =IF(AND(F39=0,$H39>0),"皆増 ",IF(AND(F39>0,$H39=0),"皆減 ",IF(AND(F39=0,$H39=0),"－ ",K39/F39))) -> -0.00074358928 | M39: =IF(AND(G39=0,$H39=0),"－ ",$H39-G39) -> 164906 | N39: =IF(AND(G39=0,$H39>0),"皆増 ",IF(AND(G39>0,$H39=0),"皆減 ",IF(AND(G39=0,$H39=0),"－ ",M39/G39))) -> 0.0042509566 | O39: =IF(AND(J39=0,$H39=0),"－ ",$H39-J39) -> 1642177 | P39: =IF(AND(J39=0,$H39>0),"皆増 ",IF(AND(J39>0,$H39=0),"皆減 ",IF(AND(J39=0,$H39=0),"－ ",O39/J39))) -> 0.044008013 | Q39: 表示
A40: 支 出 | Q40: 表示
A41: 区 分 | E41: 平成２１年度 | F41: =+F4 -> 0 | J41: =+J4 -> 0 | K41: 増 減 | M41: 増 減 | O41: 増 減 | Q41: ×表示しない
E42: 財政収支計画 （参考） | F42: 議決予算額 （補正後） （a） | H42: 決算額 （b） | J42: 決算 （c） | K42: =+K5 -> 対Ｒ５議決予算 | M42: =+M5 -> 対Ｒ５決見（4月） | O42: =+O5 -> 対Ｒ４決算 | Q42: ×表示しない
L43: 率 | N43: 率 | P43: 率 | Q43: ×表示しない
A44: 資 本 的 支 出 | E44: =SUM(E45,E62:E63,E70) -> 0 | F44: =SUM(F45,F62:F63,F69,F70) -> 62055911 | G44: =SUM(G45,G62:G63,G70) -> 61771232 | H44: =SUM(H45,H62:H63,H70) -> 61852898 | J44: =SUM(J45,J62:J63,J69,J70) -> 61194703 | K44: =IF(AND(F44=0,$H44=0),"－ ",$H44-F44) -> -203013 | L44: =IF(AND(F44=0,$H44>0),"皆増 ",IF(AND(F44>0,$H44=0),"皆減 ",IF(AND(F44=0,$H44=0),"－ ",K44/F44))) -> -0.0032714531 | M44: =IF(AND(G44=0,$H44=0),"－ ",$H44-G44) -> 81666 | N44: =IF(AND(G44=0,$H44>0),"皆増 ",IF(AND(G44>0,$H44=0),"皆減 ",IF(AND(G44=0,$H44=0),"－ ",M44/G44))) -> 0.0013220717 | O44: =IF(AND(J44=0,$H44=0),"－ ",$H44-J44) -> 658195 | P44: =IF(AND(J44=0,$H44>0),"皆増 ",IF(AND(J44>0,$H44=0),"皆減 ",IF(AND(J44=0,$H44=0),"－ ",O44/J44))) -> 0.010755751 | Q44: =IF(OR(F44>0,G44>0,H44>0,J44>0),"表示（判定）","×表示しない") -> 表示（判定） | S44: =IF('(繰)4条支出 '!K5=SUM(S46:S68),'(繰)4条支出 '!K5,"エラー") -> 61852897933 | T44: =ROUND(S44/1000,0)+U44 -> 61852898
B45: 建設改良費 | E45: =SUM(E46,E55:E61) -> 0 | F45: =SUM(F46,F55:F61) -> 17424201 | G45: =SUM(G46,G55:G61) -> 17145810 | H45: =SUM(H46,H55:H61) -> 17227476 | J45: =SUM(J46,J55:J61) -> 16645934 | K45: =IF(AND(F45=0,$H45=0),"－ ",$H45-F45) -> -196725 | L45: =IF(AND(F45=0,$H45>0),"皆増 ",IF(AND(F45>0,$H45=0),"皆減 ",IF(AND(F45=0,$H45=0),"－ ",K45/F45))) -> -0.011290331 | M45: =IF(AND(G45=0,$H45=0),"－ ",$H45-G45) -> 81666 | N45: =IF(AND(G45=0,$H45>0),"皆増 ",IF(AND(G45>0,$H45=0),"皆減 ",IF(AND(G45=0,$H45=0),"－ ",M45/G45))) -> 0.0047630296 | O45: =IF(AND(J45=0,$H45=0),"－ ",$H45-J45) -> 581542 | P45: =IF(AND(J45=0,$H45>0),"皆増 ",IF(AND(J45>0,$H45=0),"皆減 ",IF(AND(J45=0,$H45=0),"－ ",O45/J45))) -> 0.034935979 | Q45: =IF(OR(F45>0,G45>0,H45>0,J45>0),"表示（判定）","×表示しない") -> 表示（判定）
C46: 公共下水道整備費 | F46: =ROUND('(繰)4条支出 '!D7/1000,0) -> 15893171 | G46: =V46 -> 15704609 | H46: =T46 -> 15832219 | J46: 15125501 | K46: =IF(AND(F46=0,$H46=0),"－ ",$H46-F46) -> -60952 | L46: =IF(AND(F46=0,$H46>0),"皆増 ",IF(AND(F46>0,$H46=0),"皆減 ",IF(AND(F46=0,$H46=0),"－ ",K46/F46))) -> -0.0038351063 | M46: =IF(AND(G46=0,$H46=0),"－ ",$H46-G46) -> 127610 | N46: =IF(AND(G46=0,$H46>0),"皆増 ",IF(AND(G46>0,$H46=0),"皆減 ",IF(AND(G46=0,$H46=0),"－ ",M46/G46))) -> 0.0081256401 | O46: =IF(AND(J46=0,$H46=0),"－ ",$H46-J46) -> 706718 | P46: =IF(AND(J46=0,$H46>0),"皆増 ",IF(AND(J46>0,$H46=0),"皆減 ",IF(AND(J46=0,$H46=0),"－ ",O46/J46))) -> 0.046723609 | Q46: =IF(OR(F46>0,G46>0,H46>0,J46>0),"表示（判定）","×表示しない") -> 表示（判定） | S46: ='(繰)4条支出 '!K7 -> 15832219181 | T46: =ROUND(S46/1000,0)+U46 -> 15832219 | V46: =SUM(W46:X46) -> 15704609 | X46: 15704609 | Z46: #='[4-04 集計表.xlsx]4条収支'!$G40
D47: （認 証 分） | K47: =IF(AND(F47=0,$H47=0),"－ ",$H47-F47) -> － | L47: =IF(AND(F47=0,$H47>0),"皆増 ",IF(AND(F47>0,$H47=0),"皆減 ",IF(AND(F47=0,$H47=0),"－ ",K47/F47))) -> － | M47: =IF(AND(G47=0,$H47=0),"－ ",$H47-G47) -> － | N47: =IF(AND(G47=0,$H47>0),"皆増 ",IF(AND(G47>0,$H47=0),"皆減 ",IF(AND(G47=0,$H47=0),"－ ",M47/G47))) -> － | O47: =IF(AND(J47=0,$H47=0),"－ ",$H47-J47) -> － | P47: =IF(AND(J47=0,$H47>0),"皆増 ",IF(AND(J47>0,$H47=0),"皆減 ",IF(AND(J47=0,$H47=0),"－ ",O47/J47))) -> － | Q47: =IF(OR(F47>0,G47>0,H47>0,J47>0),"表示（判定）","×表示しない") -> ×表示しない
D48: （単 独 分） | K48: =IF(AND(F48=0,$H48=0),"－ ",$H48-F48) -> － | L48: =IF(AND(F48=0,$H48>0),"皆増 ",IF(AND(F48>0,$H48=0),"皆減 ",IF(AND(F48=0,$H48=0),"－ ",K48/F48))) -> － | M48: =IF(AND(G48=0,$H48=0),"－ ",$H48-G48) -> － | N48: =IF(AND(G48=0,$H48>0),"皆増 ",IF(AND(G48>0,$H48=0),"皆減 ",IF(AND(G48=0,$H48=0),"－ ",M48/G48))) -> － | O48: =IF(AND(J48=0,$H48=0),"－ ",$H48-J48) -> － | P48: =IF(AND(J48=0,$H48>0),"皆増 ",IF(AND(J48>0,$H48=0),"皆減 ",IF(AND(J48=0,$H48=0),"－ ",O48/J48))) -> － | Q48: =IF(OR(F48>0,G48>0,H48>0,J48>0),"表示（判定）","×表示しない") -> ×表示しない
D49: （継足人件費） | K49: =IF(AND(F49=0,$H49=0),"－ ",$H49-F49) -> － | L49: =IF(AND(F49=0,$H49>0),"皆増 ",IF(AND(F49>0,$H49=0),"皆減 ",IF(AND(F49=0,$H49=0),"－ ",K49/F49))) -> － | M49: =IF(AND(G49=0,$H49=0),"－ ",$H49-G49) -> － | N49: =IF(AND(G49=0,$H49>0),"皆増 ",IF(AND(G49>0,$H49=0),"皆減 ",IF(AND(G49=0,$H49=0),"－ ",M49/G49))) -> － | O49: =IF(AND(J49=0,$H49=0),"－ ",$H49-J49) -> － | P49: =IF(AND(J49=0,$H49>0),"皆増 ",IF(AND(J49>0,$H49=0),"皆減 ",IF(AND(J49=0,$H49=0),"－ ",O49/J49))) -> － | Q49: =IF(OR(F49>0,G49>0,H49>0,J49>0),"表示（判定）","×表示しない") -> ×表示しない
D50: 管きょ整備 | K50: =IF(AND(F50=0,$H50=0),"－ ",$H50-F50) -> － | L50: =IF(AND(F50=0,$H50>0),"皆増 ",IF(AND(F50>0,$H50=0),"皆減 ",IF(AND(F50=0,$H50=0),"－ ",K50/F50))) -> － | M50: =IF(AND(G50=0,$H50=0),"－ ",$H50-G50) -> － | N50: =IF(AND(G50=0,$H50>0),"皆増 ",IF(AND(G50>0,$H50=0),"皆減 ",IF(AND(G50=0,$H50=0),"－ ",M50/G50))) -> － | O50: =IF(AND(J50=0,$H50=0),"－ ",$H50-J50) -> － | P50: =IF(AND(J50=0,$H50>0),"皆増 ",IF(AND(J50>0,$H50=0),"皆減 ",IF(AND(J50=0,$H50=0),"－ ",O50/J50))) -> － | Q50: =IF(OR(F50>0,G50>0,H50>0,J50>0),"表示（判定）","×表示しない") -> ×表示しない
D51: ポンプ場整備 | K51: =IF(AND(F51=0,$H51=0),"－ ",$H51-F51) -> － | L51: =IF(AND(F51=0,$H51>0),"皆増 ",IF(AND(F51>0,$H51=0),"皆減 ",IF(AND(F51=0,$H51=0),"－ ",K51/F51))) -> － | M51: =IF(AND(G51=0,$H51=0),"－ ",$H51-G51) -> － | N51: =IF(AND(G51=0,$H51>0),"皆増 ",IF(AND(G51>0,$H51=0),"皆減 ",IF(AND(G51=0,$H51=0),"－ ",M51/G51))) -> － | O51: =IF(AND(J51=0,$H51=0),"－ ",$H51-J51) -> － | P51: =IF(AND(J51=0,$H51>0),"皆増 ",IF(AND(J51>0,$H51=0),"皆減 ",IF(AND(J51=0,$H51=0),"－ ",O51/J51))) -> － | Q51: =IF(OR(F51>0,G51>0,H51>0,J51>0),"表示（判定）","×表示しない") -> ×表示しない
D52: 処理場整備 | K52: =IF(AND(F52=0,$H52=0),"－ ",$H52-F52) -> － | L52: =IF(AND(F52=0,$H52>0),"皆増 ",IF(AND(F52>0,$H52=0),"皆減 ",IF(AND(F52=0,$H52=0),"－ ",K52/F52))) -> － | M52: =IF(AND(G52=0,$H52=0),"－ ",$H52-G52) -> － | N52: =IF(AND(G52=0,$H52>0),"皆増 ",IF(AND(G52>0,$H52=0),"皆減 ",IF(AND(G52=0,$H52=0),"－ ",M52/G52))) -> － | O52: =IF(AND(J52=0,$H52=0),"－ ",$H52-J52) -> － | P52: =IF(AND(J52=0,$H52>0),"皆増 ",IF(AND(J52>0,$H52=0),"皆減 ",IF(AND(J52=0,$H52=0),"－ ",O52/J52))) -> － | Q52: =IF(OR(F52>0,G52>0,H52>0,J52>0),"表示（判定）","×表示しない") -> ×表示しない
D53: 浸水対策 | K53: =IF(AND(F53=0,$H53=0),"－ ",$H53-F53) -> － | L53: =IF(AND(F53=0,$H53>0),"皆増 ",IF(AND(F53>0,$H53=0),"皆減 ",IF(AND(F53=0,$H53=0),"－ ",K53/F53))) -> － | M53: =IF(AND(G53=0,$H53=0),"－ ",$H53-G53) -> － | N53: =IF(AND(G53=0,$H53>0),"皆増 ",IF(AND(G53>0,$H53=0),"皆減 ",IF(AND(G53=0,$H53=0),"－ ",M53/G53))) -> － | O53: =IF(AND(J53=0,$H53=0),"－ ",$H53-J53) -> － | P53: =IF(AND(J53=0,$H53>0),"皆増 ",IF(AND(J53>0,$H53=0),"皆減 ",IF(AND(J53=0,$H53=0),"－ ",O53/J53))) -> － | Q53: =IF(OR(F53>0,G53>0,H53>0,J53>0),"表示（判定）","×表示しない") -> ×表示しない
D54: その他 | K54: =IF(AND(F54=0,$H54=0),"－ ",$H54-F54) -> － | L54: =IF(AND(F54=0,$H54>0),"皆増 ",IF(AND(F54>0,$H54=0),"皆減 ",IF(AND(F54=0,$H54=0),"－ ",K54/F54))) -> － | M54: =IF(AND(G54=0,$H54=0),"－ ",$H54-G54) -> － | N54: =IF(AND(G54=0,$H54>0),"皆増 ",IF(AND(G54>0,$H54=0),"皆減 ",IF(AND(G54=0,$H54=0),"－ ",M54/G54))) -> － | O54: =IF(AND(J54=0,$H54=0),"－ ",$H54-J54) -> － | P54: =IF(AND(J54=0,$H54>0),"皆増 ",IF(AND(J54>0,$H54=0),"皆減 ",IF(AND(J54=0,$H54=0),"－ ",O54/J54))) -> － | Q54: =IF(OR(F54>0,G54>0,H54>0,J54>0),"表示（判定）","×表示しない") -> ×表示しない
C55: 受益者負担金業務費 | F55: =ROUND('(繰)4条支出 '!D8/1000,0) -> 18558 | G55: =V55 -> 17032 | H55: =T55 -> 15860 | J55: 12170 | K55: =IF(AND(F55=0,$H55=0),"－ ",$H55-F55) -> -2698 | L55: =IF(AND(F55=0,$H55>0),"皆増 ",IF(AND(F55>0,$H55=0),"皆減 ",IF(AND(F55=0,$H55=0),"－ ",K55/F55))) -> -0.14538205 | M55: =IF(AND(G55=0,$H55=0),"－ ",$H55-G55) -> -1172 | N55: =IF(AND(G55=0,$H55>0),"皆増 ",IF(AND(G55>0,$H55=0),"皆減 ",IF(AND(G55=0,$H55=0),"－ ",M55/G55))) -> -0.068811649 | O55: =IF(AND(J55=0,$H55=0),"－ ",$H55-J55) -> 3690 | P55: =IF(AND(J55=0,$H55>0),"皆増 ",IF(AND(J55>0,$H55=0),"皆減 ",IF(AND(J55=0,$H55=0),"－ ",O55/J55))) -> 0.3032046 | Q55: =IF(OR(F55>0,G55>0,H55>0,J55>0),"表示（判定）","×表示しない") -> 表示（判定） | S55: ='(繰)4条支出 '!K8 -> 15860357 | T55: =ROUND(S55/1000,0)+U55 -> 15860 | V55: =SUM(W55:X55) -> 17032 | X55: 17032 | Z55: #='[4-04 集計表.xlsx]4条収支'!$G49
C56: 排水設備整備費 | F56: =ROUND('(繰)4条支出 '!D9/1000,0) -> 779527 | G56: =V56 -> 730380 | H56: =T56 -> 731976 | J56: 720031 | K56: =IF(AND(F56=0,$H56=0),"－ ",$H56-F56) -> -47551 | L56: =IF(AND(F56=0,$H56>0),"皆増 ",IF(AND(F56>0,$H56=0),"皆減 ",IF(AND(F56=0,$H56=0),"－ ",K56/F56))) -> -0.060999811 | M56: =IF(AND(G56=0,$H56=0),"－ ",$H56-G56) -> 1596 | N56: =IF(AND(G56=0,$H56>0),"皆増 ",IF(AND(G56>0,$H56=0),"皆減 ",IF(AND(G56=0,$H56=0),"－ ",M56/G56))) -> 0.0021851639 | O56: =IF(AND(J56=0,$H56=0),"－ ",$H56-J56) -> 11945 | P56: =IF(AND(J56=0,$H56>0),"皆増 ",IF(AND(J56>0,$H56=0),"皆減 ",IF(AND(J56=0,$H56=0),"－ ",O56/J56))) -> 0.016589564 | Q56: =IF(OR(F56>0,G56>0,H56>0,J56>0),"表示（判定）","×表示しない") -> 表示（判定） | S56: ='(繰)4条支出 '!K9 -> 731976052 | T56: =ROUND(S56/1000,0)+U56 -> 731976 | V56: =SUM(W56:X56) -> 730380 | X56: 730380 | Z56: #='[4-04 集計表.xlsx]4条収支'!$G50
C57: 都市下水路整備費 | F57: =ROUND('(繰)4条支出 '!D10/1000,0) -> 0 | G57: =V57 -> 0 | H57: =T57 -> 0 | J57: 0 | K57: =IF(AND(F57=0,$H57=0),"－ ",$H57-F57) -> － | L57: =IF(AND(F57=0,$H57>0),"皆増 ",IF(AND(F57>0,$H57=0),"皆減 ",IF(AND(F57=0,$H57=0),"－ ",K57/F57))) -> － | M57: =IF(AND(G57=0,$H57=0),"－ ",$H57-G57) -> － | N57: =IF(AND(G57=0,$H57>0),"皆増 ",IF(AND(G57>0,$H57=0),"皆減 ",IF(AND(G57=0,$H57=0),"－ ",M57/G57))) -> － | O57: =IF(AND(J57=0,$H57=0),"－ ",$H57-J57) -> － | P57: =IF(AND(J57=0,$H57>0),"皆増 ",IF(AND(J57>0,$H57=0),"皆減 ",IF(AND(J57=0,$H57=0),"－ ",O57/J57))) -> － | Q57: =IF(OR(F57>0,G57>0,H57>0,J57>0),"表示（判定）","×表示しない") -> ×表示しない | S57: ='(繰)4条支出 '!K10 -> 0 | T57: =ROUND(S57/1000,0)+U57 -> 0 | V57: =SUM(W57:X57) -> 0 | X57: 0 | Z57: #='[4-04 集計表.xlsx]4条収支'!$G51
C58: 流域下水道整備費 | F58: =ROUND('(繰)4条支出 '!D11/1000,0) -> 172142 | G58: =V58 -> 172142 | H58: =T58 -> 131922 | J58: 93130 | K58: =IF(AND(F58=0,$H58=0),"－ ",$H58-F58) -> -40220 | L58: =IF(AND(F58=0,$H58>0),"皆増 ",IF(AND(F58>0,$H58=0),"皆減 ",IF(AND(F58=0,$H58=0),"－ ",K58/F58))) -> -0.23364432 | M58: =IF(AND(G58=0,$H58=0),"－ ",$H58-G58) -> -40220 | N58: =IF(AND(G58=0,$H58>0),"皆増 ",IF(AND(G58>0,$H58=0),"皆減 ",IF(AND(G58=0,$H58=0),"－ ",M58/G58))) -> -0.23364432 | O58: =IF(AND(J58=0,$H58=0),"－ ",$H58-J58) -> 38792 | P58: =IF(AND(J58=0,$H58>0),"皆増 ",IF(AND(J58>0,$H58=0),"皆減 ",IF(AND(J58=0,$H58=0),"－ ",O58/J58))) -> 0.41653602 | Q58: =IF(OR(F58>0,G58>0,H58>0,J58>0),"表示（判定）","×表示しない") -> 表示（判定） | S58: ='(繰)4条支出 '!K11 -> 131921564 | T58: =ROUND(S58/1000,0)+U58 -> 131922 | V58: =SUM(W58:X58) -> 172142 | X58: 172142 | Z58: #='[4-04 集計表.xlsx]4条収支'!$G52
C59: 諸設備新設改良費 | F59: =ROUND('(繰)4条支出 '!D12/1000,0) -> 90944 | G59: =V59 -> 85449 | H59: =T59 -> 84675 | J59: 51815 | K59: =IF(AND(F59=0,$H59=0),"－ ",$H59-F59) -> -6269 | L59: =IF(AND(F59=0,$H59>0),"皆増 ",IF(AND(F59>0,$H59=0),"皆減 ",IF(AND(F59=0,$H59=0),"－ ",K59/F59))) -> -0.06893253 | M59: =IF(AND(G59=0,$H59=0),"－ ",$H59-G59) -> -774 | N59: =IF(AND(G59=0,$H59>0),"皆増 ",IF(AND(G59>0,$H59=0),"皆減 ",IF(AND(G59=0,$H59=0),"－ ",M59/G59))) -> -0.0090580346 | O59: =IF(AND(J59=0,$H59=0),"－ ",$H59-J59) -> 32860 | P59: =IF(AND(J59=0,$H59>0),"皆増 ",IF(AND(J59>0,$H59=0),"皆減 ",IF(AND(J59=0,$H59=0),"－ ",O59/J59))) -> 0.63417929 | Q59: =IF(OR(F59>0,G59>0,H59>0,J59>0),"表示（判定）","×表示しない") -> 表示（判定） | S59: ='(繰)4条支出 '!K12 -> 84674910 | T59: =ROUND(S59/1000,0)+U59 -> 84675 | V59: =SUM(W59:X59) -> 85449 | X59: 85449 | Z59: #='[4-04 集計表.xlsx]4条収支'!$G53
C60: 建設利息 | F60: =ROUND('(繰)4条支出 '!D13/1000,0) -> 12600 | G60: =V60 -> 12600 | H60: =T60 -> 12600 | J60: 3500 | K60: =IF(AND(F60=0,$H60=0),"－ ",$H60-F60) -> 0 | L60: =IF(AND(F60=0,$H60>0),"皆増 ",IF(AND(F60>0,$H60=0),"皆減 ",IF(AND(F60=0,$H60=0),"－ ",K60/F60))) -> 0 | M60: =IF(AND(G60=0,$H60=0),"－ ",$H60-G60) -> 0 | N60: =IF(AND(G60=0,$H60>0),"皆増 ",IF(AND(G60>0,$H60=0),"皆減 ",IF(AND(G60=0,$H60=0),"－ ",M60/G60))) -> 0 | O60: =IF(AND(J60=0,$H60=0),"－ ",$H60-J60) -> 9100 | P60: =IF(AND(J60=0,$H60>0),"皆増 ",IF(AND(J60>0,$H60=0),"皆減 ",IF(AND(J60=0,$H60=0),"－ ",O60/J60))) -> 2.6 | Q60: =IF(OR(F60>0,G60>0,H60>0,J60>0),"表示（判定）","×表示しない") -> 表示（判定） | S60: ='(繰)4条支出 '!K13 -> 12600000 | T60: =ROUND(S60/1000,0)+U60 -> 12600 | V60: =SUM(W60:X60) -> 12600 | X60: 12600 | Z60: #='[4-04 集計表.xlsx]4条収支'!$G54
C61: 市街化区域外汚水処理施設整備費 | F61: =ROUND('(繰)4条支出 '!D14/1000,0) -> 457259 | G61: =V61 -> 423598 | H61: =T61 -> 418224 | J61: 639787 | K61: =IF(AND(F61=0,$H61=0),"－ ",$H61-F61) -> -39035 | L61: =IF(AND(F61=0,$H61>0),"皆増 ",IF(AND(F61>0,$H61=0),"皆減 ",IF(AND(F61=0,$H61=0),"－ ",K61/F61))) -> -0.085367374 | M61: =IF(AND(G61=0,$H61=0),"－ ",$H61-G61) -> -5374 | N61: =IF(AND(G61=0,$H61>0),"皆増 ",IF(AND(G61>0,$H61=0),"皆減 ",IF(AND(G61=0,$H61=0),"－ ",M61/G61))) -> -0.012686557 | O61: =IF(AND(J61=0,$H61=0),"－ ",$H61-J61) -> -221563 | P61: =IF(AND(J61=0,$H61>0),"皆増 ",IF(AND(J61>0,$H61=0),"皆減 ",IF(AND(J61=0,$H61=0),"－ ",O61/J61))) -> -0.34630744 | Q61: =IF(OR(F61>0,G61>0,H61>0,J61>0),"表示（判定）","×表示しない") -> 表示（判定） | S61: ='(繰)4条支出 '!K14 -> 418223402 | T61: =ROUND(S61/1000,0)+U61 -> 418224 | U61: 1 | V61: =SUM(W61:X61) -> 423598 | X61: 423598 | Z61: #='[4-04 集計表.xlsx]4条収支'!$G55
B62: 償還金 | F62: =ROUND('(繰)4条支出 '!D16/1000,0) -> 44621423 | G62: =V62 -> 44621240 | H62: =T62 -> 44621240 | J62: 44544306 | K62: =IF(AND(F62=0,$H62=0),"－ ",$H62-F62) -> -183 | L62: =IF(AND(F62=0,$H62>0),"皆増 ",IF(AND(F62>0,$H62=0),"皆減 ",IF(AND(F62=0,$H62=0),"－ ",K62/F62))) -> -4.1011691e-06 | M62: =IF(AND(G62=0,$H62=0),"－ ",$H62-G62) -> 0 | N62: =IF(AND(G62=0,$H62>0),"皆増 ",IF(AND(G62>0,$H62=0),"皆減 ",IF(AND(G62=0,$H62=0),"－ ",M62/G62))) -> 0 | O62: =IF(AND(J62=0,$H62=0),"－ ",$H62-J62) -> 76934 | P62: =IF(AND(J62=0,$H62>0),"皆増 ",IF(AND(J62>0,$H62=0),"皆減 ",IF(AND(J62=0,$H62=0),"－ ",O62/J62))) -> 0.0017271343 | Q62: =IF(OR(F62>0,G62>0,H62>0,J62>0),"表示（判定）","×表示しない") -> 表示（判定） | S62: ='(繰)4条支出 '!K15 -> 44621240467 | T62: =ROUND(S62/1000,0)+U62 -> 44621240 | V62: =SUM(W62:X62) -> 44621240 | X62: 44621240 | Z62: #='[4-04 集計表.xlsx]4条収支'!$G56
B63: 水洗化貸付事業費 | E63: =SUM(E64,E68) -> 0 | F63: =SUM(F64,F68) -> 10287 | G63: =SUM(G64,G68) -> 4182 | H63: =SUM(H64,H68) -> 4182 | J63: =SUM(J64,J68) -> 4463 | K63: =IF(AND(F63=0,$H63=0),"－ ",$H63-F63) -> -6105 | L63: =IF(AND(F63=0,$H63>0),"皆増 ",IF(AND(F63>0,$H63=0),"皆減 ",IF(AND(F63=0,$H63=0),"－ ",K63/F63))) -> -0.59346748 | M63: =IF(AND(G63=0,$H63=0),"－ ",$H63-G63) -> 0 | N63: =IF(AND(G63=0,$H63>0),"皆増 ",IF(AND(G63>0,$H63=0),"皆減 ",IF(AND(G63=0,$H63=0),"－ ",M63/G63))) -> 0 | O63: =IF(AND(J63=0,$H63=0),"－ ",$H63-J63) -> -281 | P63: =IF(AND(J63=0,$H63>0),"皆増 ",IF(AND(J63>0,$H63=0),"皆減 ",IF(AND(J63=0,$H63=0),"－ ",O63/J63))) -> -0.062962133 | Q63: =IF(OR(F63>0,G63>0,H63>0,J63>0),"表示（判定）","×表示しない") -> 表示（判定）
C64: 貸付金 | E64: =SUM(E65:E67) -> 0 | F64: =SUM(F65:F67) -> 8096 | G64: =SUM(G65:G67) -> 3759 | H64: =SUM(H65:H67) -> 3759 | J64: =SUM(J65:J67) -> 3215 | K64: =IF(AND(F64=0,$H64=0),"－ ",$H64-F64) -> -4337 | L64: =IF(AND(F64=0,$H64>0),"皆増 ",IF(AND(F64>0,$H64=0),"皆減 ",IF(AND(F64=0,$H64=0),"－ ",K64/F64))) -> -0.53569664 | M64: =IF(AND(G64=0,$H64=0),"－ ",$H64-G64) -> 0 | N64: =IF(AND(G64=0,$H64>0),"皆増 ",IF(AND(G64>0,$H64=0),"皆減 ",IF(AND(G64=0,$H64=0),"－ ",M64/G64))) -> 0 | O64: =IF(AND(J64=0,$H64=0),"－ ",$H64-J64) -> 544 | P64: =IF(AND(J64=0,$H64>0),"皆増 ",IF(AND(J64>0,$H64=0),"皆減 ",IF(AND(J64=0,$H64=0),"－ ",O64/J64))) -> 0.16920684 | Q64: =IF(OR(F64>0,G64>0,H64>0,J64>0),"表示（判定）","×表示しない") -> 表示（判定）
D65: 水洗便所改造資金貸付金 | F65: 2976 | G65: =V65 -> 2600 | H65: =T65 -> 2600 | J65: 1040 | K65: =IF(AND(F65=0,$H65=0),"－ ",$H65-F65) -> -376 | L65: =IF(AND(F65=0,$H65>0),"皆増 ",IF(AND(F65>0,$H65=0),"皆減 ",IF(AND(F65=0,$H65=0),"－ ",K65/F65))) -> -0.12634409 | M65: =IF(AND(G65=0,$H65=0),"－ ",$H65-G65) -> 0 | N65: =IF(AND(G65=0,$H65>0),"皆増 ",IF(AND(G65>0,$H65=0),"皆減 ",IF(AND(G65=0,$H65=0),"－ ",M65/G65))) -> 0 | O65: =IF(AND(J65=0,$H65=0),"－ ",$H65-J65) -> 1560 | P65: =IF(AND(J65=0,$H65>0),"皆増 ",IF(AND(J65>0,$H65=0),"皆減 ",IF(AND(J65=0,$H65=0),"－ ",O65/J65))) -> 1.5 | Q65: =IF(OR(F65>0,G65>0,H65>0,J65>0),"表示（判定）","×表示しない") -> 表示（判定） | S65: =[6]水洗!$E$6 -> 2600000 | T65: =ROUND(S65/1000,0)+U65 -> 2600 | V65: =SUM(W65:X65) -> 2600 | X65: 2600 | Z65: #='[4-04 集計表.xlsx]4条収支'!$G61
D66: し尿浄化槽廃止資金貸付金 | F66: 5120 | G66: =V66 -> 1159 | H66: =T66 -> 1159 | J66: 2175 | K66: =IF(AND(F66=0,$H66=0),"－ ",$H66-F66) -> -3961 | L66: =IF(AND(F66=0,$H66>0),"皆増 ",IF(AND(F66>0,$H66=0),"皆減 ",IF(AND(F66=0,$H66=0),"－ ",K66/F66))) -> -0.77363281 | M66: =IF(AND(G66=0,$H66=0),"－ ",$H66-G66) -> 0 | N66: =IF(AND(G66=0,$H66>0),"皆増 ",IF(AND(G66>0,$H66=0),"皆減 ",IF(AND(G66=0,$H66=0),"－ ",M66/G66))) -> 0 | O66: =IF(AND(J66=0,$H66=0),"－ ",$H66-J66) -> -1016 | P66: =IF(AND(J66=0,$H66>0),"皆増 ",IF(AND(J66>0,$H66=0),"皆減 ",IF(AND(J66=0,$H66=0),"－ ",O66/J66))) -> -0.46712644 | Q66: =IF(OR(F66>0,G66>0,H66>0,J66>0),"表示（判定）","×表示しない") -> 表示（判定） | S66: =[6]水洗!$E$12 -> 1159000 | T66: =ROUND(S66/1000,0)+U66 -> 1159 | V66: =SUM(W66:X66) -> 1159 | X66: 1159 | Z66: #='[4-04 集計表.xlsx]4条収支'!$G62
D67: 排水設備改修資金貸付金 | F67: 0 | G67: =V67 -> 0 | H67: =T67 -> 0 | J67: 0 | K67: =IF(AND(F67=0,$H67=0),"－ ",$H67-F67) -> － | L67: =IF(AND(F67=0,$H67>0),"皆増 ",IF(AND(F67>0,$H67=0),"皆減 ",IF(AND(F67=0,$H67=0),"－ ",K67/F67))) -> － | M67: =IF(AND(G67=0,$H67=0),"－ ",$H67-G67) -> － | N67: =IF(AND(G67=0,$H67>0),"皆増 ",IF(AND(G67>0,$H67=0),"皆減 ",IF(AND(G67=0,$H67=0),"－ ",M67/G67))) -> － | O67: =IF(AND(J67=0,$H67=0),"－ ",$H67-J67) -> － | P67: =IF(AND(J67=0,$H67>0),"皆増 ",IF(AND(J67>0,$H67=0),"皆減 ",IF(AND(J67=0,$H67=0),"－ ",O67/J67))) -> － | Q67: =IF(OR(F67>0,G67>0,H67>0,J67>0),"表示（判定）","×表示しない") -> ×表示しない | S67: =[6]水洗!$E$18 -> 0 | T67: =ROUND(S67/1000,0)+U67 -> 0
