Workbook
Name 委託費: リスト!$G$4:$G$16
Name 減価償却費: リスト!$U$4
Name 交際費: リスト!$Q$4
Name 光熱水料: リスト!$H$4
Name 厚生費: リスト!$C$4
Name 構成組合交付金: リスト!$S$4
Name 雑費: リスト!$T$4
Name 支払利息: リスト!$W$4
Name 事務費: リスト!$E$4:$E$11
Name 修繕費: リスト!$I$4
Name 諸謝金: リスト!$M$4:$M$8
Name 消費税: リスト!$P$4
Name 職員給与: リスト!$B$4:$B$8
Name 食糧費: リスト!$N$4
Name 選挙費: リスト!$R$4
Name 中項目: リスト!$A$3:$Y$3
Name 調査研究費: リスト!$K$4:$K$13
Name 賃金: リスト!$F$4
Name 賃借料: リスト!$J$4:$J$10
Name 特別修繕引当金繰入: リスト!$V$4
Name 普及費: リスト!$L$4:$L$8
Name 負担金: リスト!$O$4:$O$12
Name 旅費: リスト!$D$4:$D$6
Name 年度: '月次締め'!$C$4
Name 締月: '月次締め'!$C$6
Name 月初: '月次締め'!$C$7
Name 翌月初: '月次締め'!$D$7
Name 中項目・小項目: リスト!$A$3:$W$3
Name 役員報酬: リスト!$A$4:$A$6
Name 中項目・小項目: リスト!$A$3:$W$3
Name 役員報酬: リスト!$A$4:$A$6

Sheet 使い方
A1: 令和8年度 業務経理区分別執行管理簿（統合版） 使い方
A2: 元の「業務経理区分別執行管理簿」「貸付予算差引簿」「費用収益表」を1つにまとめました。シートの様式は元のままで、転記を自動にしています。
B4: 転記の流れ（すべて自動）
B5: ① 入力 | C5: 業務：「月例」に支払を入力（決算整理＝未払金は「決算整理」シート）。貸付：「貸付予算差引簿」の各費目に入力。 | D5: 入力するのは黄色のセルだけ
B6: ② 差引簿へ | C6: 「予算差引簿（短）」「予算差引簿（長）」へ、費目ごとに日付・摘要・金額が自動で転記されます。決算整理の分は「…未払」シートへ。 | D6: 人件費（非常勤職員手当・賃金）など全ての費目
B7: ③ 月別合計 | C7: 「差引簿集計（短）（長）」「貸付差引簿集計」で、費目ごとの月別合計が自動で出ます。 | D7: 確認済の分だけを集計
B8: ④ 費用収益表へ | C8: 費用収益表の各費目・各月へ自動で入ります。「月次締め」の「今回締める月」までが確定表示、それ以降は前年実績・見込（緑字）。 | D8: 手で転記する必要はありません
B10: 毎月の作業
B11: 支払担当者 | C11: 昨年実績の行を今年の支払に直し（日付・摘要・金額）、状態を「昨年実績」→「未確認」へ。 | D11: 旧：赤字を黒字にして金額を修正
B12: 経理担当者 | C12: 支払伝票が回ってきたら状態を「未確認」→「確認済」へ（プルダウン）。 | D12: 旧：金額を青く塗りつぶし
B13: 経理〆 | C13: 「月次締め」で今回締める月を選び、仮締め出納計算表の月合計を黄色セルに入力。差額0で OK。「検算」シートが全部 OK ならこのブックの数字は一致しています。
B15: 色のルール
B16: 黄色のセル | C16: 手入力するセル。それ以外は数式なので触りません。マクロ版（.xlsm）ではEnterで次の黄色セルへ移動します。
B17: 赤字 | C17: 状態＝昨年実績（今年の支払が確定するまで残す行）。
B18: 青字（月例）／水色の背景（差引簿の支出） | C18: 状態＝確認済。
B19: オレンジの背景（差引簿の支出） | C19: 状態＝未確認。
B20: 取り消し線（月例） | C20: 状態＝支払なし（今年度は支払がない行。差引簿・集計から除外）。
B22: 追加した列・シート（元の様式への追加）
B23: 月例・決算整理 P〜U列 | C23: P＝状態（入力）。Q〜U＝自動計算の作業列（費目・長期額・差引簿への通番・計上列）。消さないでください。
B24: 予算差引簿の「状態」列 | C24: 各ブロックの右端。月例の状態が自動で表示されます。
B25: 貸付予算差引簿の「状態」列 | C25: 各ブロックの右端（入力）。
B26: 差引簿のブロックの大きさ | C26: 行数は余裕を持たせてあります。足りなくなると見出しの右に赤字で「行不足」と出ます。

Sheet 月次締め
A1: 月次締め 操作盤と出納計算表との照合
A2: 月次〆のときは「今回締める月」を選ぶだけです。費用収益表がその月まで自動で確定表示になります（転記は不要）。黄色のセルに仮締めした出納計算表の月合計を入力し、差額が 0 になればOKです。
B4: 年度（令和） | C4: ='R7業務（長+短）'!E1 -> 8 | D4: ← 費用収益表（長+短）の年度から | F4: 自動検算 | G4: =IF(検算!$F$3=0,"すべてOK","NG "&検算!$F$3&"件（検算シート参照）") -> すべてOK
B5: 今回締める月 | C5: 9月 | D5: ← ここを変えると、その月まで費用収益表に確定計上されます（9月締め済みなら「9月」）
B6: 月番号（自動） | C6: =MATCH($C$5,科目表!$N$5:$N$18,0)-1 -> 6
B7: 対象月の開始日／翌月初（自動） | C7: =IF(締月=0,0,IF(締月=13,DATE(年度+2019,4,1),DATE(年度+2018+IF(締月>9,1,0),MOD(締月+2,12)+1,1))) -> 46266 | D7: =EDATE(C7,1) -> 46296
B9: ① 締める前のチェック（今回締める月の分）
B10: 項目 | C10: 業務 | D10: 貸付 | E10: 対応
B11: 確認済の件数 | C11: =IF(締月=0,0,COUNTIFS(月例!$U$5:$U$788,締月,月例!$P$5:$P$788,"確認済")+COUNTIFS(決算整理!$U$5:$U$1835,締月,決算整理!$P$5:$P$1835,"確認済")) -> 35 | D11: =IF(締月=0,0,COUNTIFS('旅費・事務費（消耗品・図書・通信・会議・雑費）R８'!$E$6:$E$25,"確認済",'旅費・事務費（消耗品・図書・通信・会議・雑費）R８'!$A$6:$A$25,">="&月初,'旅費・事務費（消耗品・図書・通信・会議・雑費）R８'!$A$6:$A$25,"<"&翌月初)+COUNTIFS('旅費・事務費（消耗品・図書・通信・会議・雑費）R８'!$E$29:$E$31,"確認済",'旅費・事務費（消耗品・図書・通信・会議・雑費）R８'!$A$29:$A$31,">="&月初,'旅費・事務費（消耗品・図書・通信・会議・雑費）R８'!$A$29:$A$31,"<"&翌月初)+COUNTIFS('旅費・事務費（消耗品・図書・通信・会議・雑費）R８'!$E$35:$E$67,"確認済",'旅費・事務費（消耗品・図書・通信・会議・雑費）R８'!$A$35:$A$67,">="&月初,'旅費・事務費（消耗品・図書・通信・会議・雑費）R８'!$A$35:$A$67,"<"&翌月初)+COUNTIFS('旅費・事務費（消耗品・図書・通信・会議・雑費）R８'!$J$6:$J$23,"確認済",'旅費・事務費（消耗品・図書・通信・会議・雑費）R８'!$F$6:$F$23,">="&月初,'旅費・事務費（消耗品・図書・通信・会議・雑費）R８'!$F$6:$F$23,"<"&翌月初)+COUNTIFS('旅費・事務費（消耗品・図書・通信・会議・雑費）R８'!$J$46:$J$67,"確認済",'旅費・事務費（消耗品・図書・通信・会議・雑費）R８'!$F$46:$F$67,">="&月初,'旅費・事務費（消耗品・図書・通信・会議・雑費）R８'!$F$46:$F$67,"<"&翌月初)+COUNTIFS('旅費・事務費（消耗品・図書・通信・会議・雑費）R８'!$J$27:$J$42,"確認済",'旅費・事務費（消耗品・図書・通信・会議・雑費）R８'!$F$27:$F$42,">="&月初,'旅費・事務費（消耗品・図書・通信・会議・雑費）R８'!$F$27:$F$42,"<"&翌月初)+COUNTIFS('旅費・事務費以外R８'!$E$29:$E$33,"確認済",'旅費・事務費以外R８'!$A$29:$A$33,">="&月初,'旅費・事務費以外R８'!$A$29:$A$33,"<"&翌月初)+COUNTIFS('旅費・事務費以外R８'!$E$6:$E$14,"確認済",'旅費・事務費以外R８'!$A$6:$A$14,">="&月初,'旅費・事務費以外R８'!$A$6:$A$14,"<"&翌月初)+COUNTIFS('旅費・事務費以外R８'!$E$18:$E$25,"確認済",'旅費・事務費以外R８'!$A$18:$A$25,">="&月初,'旅費・事務費以外R８'!$A$18:$A$25,"<"&翌月初)+COUNTIFS('旅費・事務費以外R８'!$E$37:$E$86,"確認済",'旅費・事務費以外R８'!$A$37:$A$86,">="&月初,'旅費・事務費以外R８'!$A$37:$A$86,"<"&翌月初)+COUNTIFS('旅費・事務費以外R８'!$J$6:$J$13,"確認済",'旅費・事務費以外R８'!$F$6:$F$13,">="&月初,'旅費・事務費以外R８'!$F$6:$F$13,"<"&翌月初)+COUNTIFS('旅費・事務費以外R８'!$J$26:$J$31,"確認済",'旅費・事務費以外R８'!$F$26:$F$31,">="&月初,'旅費・事務費以外R８'!$F$26:$F$31,"<"&翌月初)+COUNTIFS('旅費・事務費以外R８'!$J$45:$J$86,"確認済",'旅費・事務費以外R８'!$F$45:$F$86,">="&月初,'旅費・事務費以外R８'!$F$45:$F$86,"<"&翌月初)+COUNTIFS('旅費・事務費以外R８'!$J$35:$J$41,"確認済",'旅費・事務費以外R８'!$F$35:$F$41,">="&月初,'旅費・事務費以外R８'!$F$35:$F$41,"<"&翌月初)) -> 5 | E11: 差引簿・費用収益表に計上される行数
B12: 未確認（伝票待ち）の件数 | C12: =IF(締月=0,0,COUNTIFS(月例!$U$5:$U$788,締月,月例!$P$5:$P$788,"未確認")+COUNTIFS(決算整理!$U$5:$U$1835,締月,決算整理!$P$5:$P$1835,"未確認")) -> 0 | D12: =IF(締月=0,0,COUNTIFS('旅費・事務費（消耗品・図書・通信・会議・雑費）R８'!$E$6:$E$25,"未確認",'旅費・事務費（消耗品・図書・通信・会議・雑費）R８'!$A$6:$A$25,">="&月初,'旅費・事務費（消耗品・図書・通信・会議・雑費）R８'!$A$6:$A$25,"<"&翌月初)+COUNTIFS('旅費・事務費（消耗品・図書・通信・会議・雑費）R８'!$E$29:$E$31,"未確認",'旅費・事務費（消耗品・図書・通信・会議・雑費）R８'!$A$29:$A$31,">="&月初,'旅費・事務費（消耗品・図書・通信・会議・雑費）R８'!$A$29:$A$31,"<"&翌月初)+COUNTIFS('旅費・事務費（消耗品・図書・通信・会議・雑費）R８'!$E$35:$E$67,"未確認",'旅費・事務費（消耗品・図書・通信・会議・雑費）R８'!$A$35:$A$67,">="&月初,'旅費・事務費（消耗品・図書・通信・会議・雑費）R８'!$A$35:$A$67,"<"&翌月初)+COUNTIFS('旅費・事務費（消耗品・図書・通信・会議・雑費）R８'!$J$6:$J$23,"未確認",'旅費・事務費（消耗品・図書・通信・会議・雑費）R８'!$F$6:$F$23,">="&月初,'旅費・事務費（消耗品・図書・通信・会議・雑費）R８'!$F$6:$F$23,"<"&翌月初)+COUNTIFS('旅費・事務費（消耗品・図書・通信・会議・雑費）R８'!$J$46:$J$67,"未確認",'旅費・事務費（消耗品・図書・通信・会議・雑費）R８'!$F$46:$F$67,">="&月初,'旅費・事務費（消耗品・図書・通信・会議・雑費）R８'!$F$46:$F$67,"<"&翌月初)+COUNTIFS('旅費・事務費（消耗品・図書・通信・会議・雑費）R８'!$J$27:$J$42,"未確認",'旅費・事務費（消耗品・図書・通信・会議・雑費）R８'!$F$27:$F$42,">="&月初,'旅費・事務費（消耗品・図書・通信・会議・雑費）R８'!$F$27:$F$42,"<"&翌月初)+COUNTIFS('旅費・事務費以外R８'!$E$29:$E$33,"未確認",'旅費・事務費以外R８'!$A$29:$A$33,">="&月初,'旅費・事務費以外R８'!$A$29:$A$33,"<"&翌月初)+COUNTIFS('旅費・事務費以外R８'!$E$6:$E$14,"未確認",'旅費・事務費以外R８'!$A$6:$A$14,">="&月初,'旅費・事務費以外R８'!$A$6:$A$14,"<"&翌月初)+COUNTIFS('旅費・事務費以外R８'!$E$18:$E$25,"未確認",'旅費・事務費以外R８'!$A$18:$A$25,">="&月初,'旅費・事務費以外R８'!$A$18:$A$25,"<"&翌月初)+COUNTIFS('旅費・事務費以外R８'!$E$37:$E$86,"未確認",'旅費・事務費以外R８'!$A$37:$A$86,">="&月初,'旅費・事務費以外R８'!$A$37:$A$86,"<"&翌月初)+COUNTIFS('旅費・事務費以外R８'!$J$6:$J$13,"未確認",'旅費・事務費以外R８'!$F$6:$F$13,">="&月初,'旅費・事務費以外R８'!$F$6:$F$13,"<"&翌月初)+COUNTIFS('旅費・事務費以外R８'!$J$26:$J$31,"未確認",'旅費・事務費以外R８'!$F$26:$F$31,">="&月初,'旅費・事務費以外R８'!$F$26:$F$31,"<"&翌月初)+COUNTIFS('旅費・事務費以外R８'!$J$45:$J$86,"未確認",'旅費・事務費以外R８'!$F$45:$F$86,">="&月初,'旅費・事務費以外R８'!$F$45:$F$86,"<"&翌月初)+COUNTIFS('旅費・事務費以外R８'!$J$35:$J$41,"未確認",'旅費・事務費以外R８'!$F$35:$F$41,">="&月初,'旅費・事務費以外R８'!$F$35:$F$41,"<"&翌月初)) -> 0 | E12: 0 にしてから締めます（伝票を確認して「確認済」へ）
B13: 昨年実績のまま残っている件数（参考） | C13: =IF(締月=0,0,COUNTIFS(月例!$U$5:$U$788,締月,月例!$P$5:$P$788,"昨年実績")+COUNTIFS(決算整理!$U$5:$U$1835,締月,決算整理!$P$5:$P$1835,"昨年実績")) -> 22 | D13: =IF(締月=0,0,COUNTIFS('旅費・事務費（消耗品・図書・通信・会議・雑費）R８'!$E$6:$E$25,"昨年実績",'旅費・事務費（消耗品・図書・通信・会議・雑費）R８'!$A$6:$A$25,">="&月初,'旅費・事務費（消耗品・図書・通信・会議・雑費）R８'!$A$6:$A$25,"<"&翌月初)+COUNTIFS('旅費・事務費（消耗品・図書・通信・会議・雑費）R８'!$E$29:$E$31,"昨年実績",'旅費・事務費（消耗品・図書・通信・会議・雑費）R８'!$A$29:$A$31,">="&月初,'旅費・事務費（消耗品・図書・通信・会議・雑費）R８'!$A$29:$A$31,"<"&翌月初)+COUNTIFS('旅費・事務費（消耗品・図書・通信・会議・雑費）R８'!$E$35:$E$67,"昨年実績",'旅費・事務費（消耗品・図書・通信・会議・雑費）R８'!$A$35:$A$67,">="&月初,'旅費・事務費（消耗品・図書・通信・会議・雑費）R８'!$A$35:$A$67,"<"&翌月初)+COUNTIFS('旅費・事務費（消耗品・図書・通信・会議・雑費）R８'!$J$6:$J$23,"昨年実績",'旅費・事務費（消耗品・図書・通信・会議・雑費）R８'!$F$6:$F$23,">="&月初,'旅費・事務費（消耗品・図書・通信・会議・雑費）R８'!$F$6:$F$23,"<"&翌月初)+COUNTIFS('旅費・事務費（消耗品・図書・通信・会議・雑費）R８'!$J$46:$J$67,"昨年実績",'旅費・事務費（消耗品・図書・通信・会議・雑費）R８'!$F$46:$F$67,">="&月初,'旅費・事務費（消耗品・図書・通信・会議・雑費）R８'!$F$46:$F$67,"<"&翌月初)+COUNTIFS('旅費・事務費（消耗品・図書・通信・会議・雑費）R８'!$J$27:$J$42,"昨年実績",'旅費・事務費（消耗品・図書・通信・会議・雑費）R８'!$F$27:$F$42,">="&月初,'旅費・事務費（消耗品・図書・通信・会議・雑費）R８'!$F$27:$F$42,"<"&翌月初)+COUNTIFS('旅費・事務費以外R８'!$E$29:$E$33,"昨年実績",'旅費・事務費以外R８'!$A$29:$A$33,">="&月初,'旅費・事務費以外R８'!$A$29:$A$33,"<"&翌月初)+COUNTIFS('旅費・事務費以外R８'!$E$6:$E$14,"昨年実績",'旅費・事務費以外R８'!$A$6:$A$14,">="&月初,'旅費・事務費以外R８'!$A$6:$A$14,"<"&翌月初)+COUNTIFS('旅費・事務費以外R８'!$E$18:$E$25,"昨年実績",'旅費・事務費以外R８'!$A$18:$A$25,">="&月初,'旅費・事務費以外R８'!$A$18:$A$25,"<"&翌月初)+COUNTIFS('旅費・事務費以外R８'!$E$37:$E$86,"昨年実績",'旅費・事務費以外R８'!$A$37:$A$86,">="&月初,'旅費・事務費以外R８'!$A$37:$A$86,"<"&翌月初)+COUNTIFS('旅費・事務費以外R８'!$J$6:$J$13,"昨年実績",'旅費・事務費以外R８'!$F$6:$F$13,">="&月初,'旅費・事務費以外R８'!$F$6:$F$13,"<"&翌月初)+COUNTIFS('旅費・事務費以外R８'!$J$26:$J$31,"昨年実績",'旅費・事務費以外R８'!$F$26:$F$31,">="&月初,'旅費・事務費以外R８'!$F$26:$F$31,"<"&翌月初)+COUNTIFS('旅費・事務費以外R８'!$J$45:$J$86,"昨年実績",'旅費・事務費以外R８'!$F$45:$F$86,">="&月初,'旅費・事務費以外R８'!$F$45:$F$86,"<"&翌月初)+COUNTIFS('旅費・事務費以外R８'!$J$35:$J$41,"昨年実績",'旅費・事務費以外R８'!$F$35:$F$41,">="&月初,'旅費・事務費以外R８'!$F$35:$F$41,"<"&翌月初)) -> 0 | E13: 今年は支払がない行は「支払なし」にすると見やすくなります
B14: 点検NGの件数 | C14: =COUNTIF(月例!$Q$5:$Q$788,"※未登録")+COUNTIF(決算整理!$Q$5:$Q$1835,"※未登録")+COUNTIF('差引簿集計（短）'!$T$4:$T$80,"行不足")+COUNTIF('差引簿集計（長）'!$T$4:$T$80,"行不足") -> 0 | D14: =COUNTIFS('旅費・事務費（消耗品・図書・通信・会議・雑費）R８'!$A$6:$A$25,">0",'旅費・事務費（消耗品・図書・通信・会議・雑費）R８'!$E$6:$E$25,"")+COUNTIFS('旅費・事務費（消耗品・図書・通信・会議・雑費）R８'!$A$29:$A$31,">0",'旅費・事務費（消耗品・図書・通信・会議・雑費）R８'!$E$29:$E$31,"")+COUNTIFS('旅費・事務費（消耗品・図書・通信・会議・雑費）R８'!$A$35:$A$67,">0",'旅費・事務費（消耗品・図書・通信・会議・雑費）R８'!$E$35:$E$67,"")+COUNTIFS('旅費・事務費（消耗品・図書・通信・会議・雑費）R８'!$F$6:$F$23,">0",'旅費・事務費（消耗品・図書・通信・会議・雑費）R８'!$J$6:$J$23,"")+COUNTIFS('旅費・事務費（消耗品・図書・通信・会議・雑費）R８'!$F$46:$F$67,">0",'旅費・事務費（消耗品・図書・通信・会議・雑費）R８'!$J$46:$J$67,"")+COUNTIFS('旅費・事務費（消耗品・図書・通信・会議・雑費）R８'!$F$27:$F$42,">0",'旅費・事務費（消耗品・図書・通信・会議・雑費）R８'!$J$27:$J$42,"")+COUNTIFS('旅費・事務費以外R８'!$A$29:$A$33,">0",'旅費・事務費以外R８'!$E$29:$E$33,"")+COUNTIFS('旅費・事務費以外R８'!$A$6:$A$14,">0",'旅費・事務費以外R８'!$E$6:$E$14,"")+COUNTIFS('旅費・事務費以外R８'!$A$18:$A$25,">0",'旅費・事務費以外R８'!$E$18:$E$25,"")+COUNTIFS('旅費・事務費以外R８'!$A$37:$A$86,">0",'旅費・事務費以外R８'!$E$37:$E$86,"")+COUNTIFS('旅費・事務費以外R８'!$F$6:$F$13,">0",'旅費・事務費以外R８'!$J$6:$J$13,"")+COUNTIFS('旅費・事務費以外R８'!$F$26:$F$31,">0",'旅費・事務費以外R８'!$J$26:$J$31,"")+COUNTIFS('旅費・事務費以外R８'!$F$45:$F$86,">0",'旅費・事務費以外R８'!$J$45:$J$86,"")+COUNTIFS('旅費・事務費以外R８'!$F$35:$F$41,">0",'旅費・事務費以外R８'!$J$35:$J$41,"") -> 0 | E14: 費目未登録・差引簿の行不足・状態未設定
B15: 確認済 金額合計 | C15: =IF(締月=0,0,SUMIFS(月例!$F$5:$F$788,月例!$U$5:$U$788,締月,月例!$P$5:$P$788,"確認済")+SUMIFS(決算整理!$F$5:$F$1835,決算整理!$U$5:$U$1835,締月,決算整理!$P$5:$P$1835,"確認済")) -> 30634243 | D15: =IF(締月=0,0,SUMIFS('旅費・事務費（消耗品・図書・通信・会議・雑費）R８'!$C$6:$C$25,'旅費・事務費（消耗品・図書・通信・会議・雑費）R８'!$E$6:$E$25,"確認済",'旅費・事務費（消耗品・図書・通信・会議・雑費）R８'!$A$6:$A$25,">="&月初,'旅費・事務費（消耗品・図書・通信・会議・雑費）R８'!$A$6:$A$25,"<"&翌月初)+SUMIFS('旅費・事務費（消耗品・図書・通信・会議・雑費）R８'!$C$29:$C$31,'旅費・事務費（消耗品・図書・通信・会議・雑費）R８'!$E$29:$E$31,"確認済",'旅費・事務費（消耗品・図書・通信・会議・雑費）R８'!$A$29:$A$31,">="&月初,'旅費・事務費（消耗品・図書・通信・会議・雑費）R８'!$A$29:$A$31,"<"&翌月初)+SUMIFS('旅費・事務費（消耗品・図書・通信・会議・雑費）R８'!$C$35:$C$67,'旅費・事務費（消耗品・図書・通信・会議・雑費）R８'!$E$35:$E$67,"確認済",'旅費・事務費（消耗品・図書・通信・会議・雑費）R８'!$A$35:$A$67,">="&月初,'旅費・事務費（消耗品・図書・通信・会議・雑費）R８'!$A$35:$A$67,"<"&翌月初)+SUMIFS('旅費・事務費（消耗品・図書・通信・会議・雑費）R８'!$H$6:$H$23,'旅費・事務費（消耗品・図書・通信・会議・雑費）R８'!$J$6:$J$23,"確認済",'旅費・事務費（消耗品・図書・通信・会議・雑費）R８'!$F$6:$F$23,">="&月初,'旅費・事務費（消耗品・図書・通信・会議・雑費）R８'!$F$6:$F$23,"<"&翌月初)+SUMIFS('旅費・事務費（消耗品・図書・通信・会議・雑費）R８'!$H$46:$H$67,'旅費・事務費（消耗品・図書・通信・会議・雑費）R８'!$J$46:$J$67,"確認済",'旅費・事務費（消耗品・図書・通信・会議・雑費）R８'!$F$46:$F$67,">="&月初,'旅費・事務費（消耗品・図書・通信・会議・雑費）R８'!$F$46:$F$67,"<"&翌月初)+SUMIFS('旅費・事務費（消耗品・図書・通信・会議・雑費）R８'!$H$27:$H$42,'旅費・事務費（消耗品・図書・通信・会議・雑費）R８'!$J$27:$J$42,"確認済",'旅費・事務費（消耗品・図書・通信・会議・雑費）R８'!$F$27:$F$42,">="&月初,'旅費・事務費（消耗品・図書・通信・会議・雑費）R８'!$F$27:$F$42,"<"&翌月初)+SUMIFS('旅費・事務費以外R８'!$C$29:$C$33,'旅費・事務費以外R８'!$E$29:$E$33,"確認済",'旅費・事務費以外R８'!$A$29:$A$33,">="&月初,'旅費・事務費以外R８'!$A$29:$A$33,"<"&翌月初)+SUMIFS('旅費・事務費以外R８'!$C$6:$C$14,'旅費・事務費以外R８'!$E$6:$E$14,"確認済",'旅費・事務費以外R８'!$A$6:$A$14,">="&月初,'旅費・事務費以外R８'!$A$6:$A$14,"<"&翌月初)+SUMIFS('旅費・事務費以外R８'!$C$18:$C$25,'旅費・事務費以外R８'!$E$18:$E$25,"確認済",'旅費・事務費以外R８'!$A$18:$A$25,">="&月初,'旅費・事務費以外R８'!$A$18:$A$25,"<"&翌月初)+SUMIFS('旅費・事務費以外R８'!$C$37:$C$86,'旅費・事務費以外R８'!$E$37:$E$86,"確認済",'旅費・事務費以外R８'!$A$37:$A$86,">="&月初,'旅費・事務費以外R８'!$A$37:$A$86,"<"&翌月初)+SUMIFS('旅費・事務費以外R８'!$H$6:$H$13,'旅費・事務費以外R８'!$J$6:$J$13,"確認済",'旅費・事務費以外R８'!$F$6:$F$13,">="&月初,'旅費・事務費以外R８'!$F$6:$F$13,"<"&翌月初)+SUMIFS('旅費・事務費以外R８'!$H$26:$H$31,'旅費・事務費以外R８'!$J$26:$J$31,"確認済",'旅費・事務費以外R８'!$F$26:$F$31,">="&月初,'旅費・事務費以外R８'!$F$26:$F$31,"<"&翌月初)+SUMIFS('旅費・事務費以外R８'!$H$45:$H$86,'旅費・事務費以外R８'!$J$45:$J$86,"確認済",'旅費・事務費以外R８'!$F$45:$F$86,">="&月初,'旅費・事務費以外R８'!$F$45:$F$86,"<"&翌月初)+SUMIFS('旅費・事務費以外R８'!$H$35:$H$41,'旅費・事務費以外R８'!$J$35:$J$41,"確認済",'旅費・事務費以外R８'!$F$35:$F$41,">="&月初,'旅費・事務費以外R８'!$F$35:$F$41,"<"&翌月初)) -> 254511 | E15: 業務は短期＋長期の合計（月例＋決算整理）
B16: 締め可否 | C16: =IF(締月=0,"-",IF(AND(C12=0,C14=0),"OK","要対応")) -> OK | D16: =IF(締月=0,"-",IF(AND(D12=0,D14=0),"OK","要対応")) -> OK
B19: ② 出納計算表との照合（黄色のセルに仮締めした出納計算表の月合計を入力）
B21: 業務経理（短期）
B22: 月 | C22: 費用 | F22: 収益 | I22: 判定
C23: 費用収益表 | D23: 出納計算表 | E23: 差額 | F23: 費用収益表 | G23: 出納計算表 | H23: 差額
B24: 4月 | C24: ='R7業務 (短)'!C38 -> 534591 | E24: =IF(D24="","",C24-D24) | F24: ='R7業務 (短)'!C46 -> 2268000 | H24: =IF(G24="","",F24-G24) | I24: =IF(1>締月,"",IF(OR(D24="",G24=""),"出納計算表 未入力",IF(AND(E24=0,H24=0),"OK","NG 差額あり"))) -> 出納計算表 未入力
B25: 5月 | C25: ='R7業務 (短)'!D38 -> 4087081 | E25: =IF(D25="","",C25-D25) | F25: ='R7業務 (短)'!D46 -> 2150000 | H25: =IF(G25="","",F25-G25) | I25: =IF(2>締月,"",IF(OR(D25="",G25=""),"出納計算表 未入力",IF(AND(E25=0,H25=0),"OK","NG 差額あり"))) -> 出納計算表 未入力
B26: 6月 | C26: ='R7業務 (短)'!E38 -> 2455166 | E26: =IF(D26="","",C26-D26) | F26: ='R7業務 (短)'!E46 -> 2609000 | H26: =IF(G26="","",F26-G26) | I26: =IF(3>締月,"",IF(OR(D26="",G26=""),"出納計算表 未入力",IF(AND(E26=0,H26=0),"OK","NG 差額あり"))) -> 出納計算表 未入力
B27: 7月 | C27: ='R7業務 (短)'!F38 -> 1972276 | E27: =IF(D27="","",C27-D27) | F27: ='R7業務 (短)'!F46 -> 2725000 | H27: =IF(G27="","",F27-G27) | I27: =IF(4>締月,"",IF(OR(D27="",G27=""),"出納計算表 未入力",IF(AND(E27=0,H27=0),"OK","NG 差額あり"))) -> 出納計算表 未入力
B28: 8月 | C28: ='R7業務 (短)'!G38 -> 2709341 | E28: =IF(D28="","",C28-D28) | F28: ='R7業務 (短)'!G46 -> 2151000 | H28: =IF(G28="","",F28-G28) | I28: =IF(5>締月,"",IF(OR(D28="",G28=""),"出納計算表 未入力",IF(AND(E28=0,H28=0),"OK","NG 差額あり"))) -> 出納計算表 未入力
B29: 9月 | C29: ='R7業務 (短)'!H38 -> 24070375 | E29: =IF(D29="","",C29-D29) | F29: ='R7業務 (短)'!H46 -> 12794000 | H29: =IF(G29="","",F29-G29) | I29: =IF(6>締月,"",IF(OR(D29="",G29=""),"出納計算表 未入力",IF(AND(E29=0,H29=0),"OK","NG 差額あり"))) -> 出納計算表 未入力
B30: 10月 | C30: ='R7業務 (短)'!I38 -> 2454418 | E30: =IF(D30="","",C30-D30) | F30: ='R7業務 (短)'!I46 -> 2477000 | H30: =IF(G30="","",F30-G30) | I30: =IF(7>締月,"",IF(OR(D30="",G30=""),"出納計算表 未入力",IF(AND(E30=0,H30=0),"OK","NG 差額あり")))
B31: 11月 | C31: ='R7業務 (短)'!J38 -> 2501632 | E31: =IF(D31="","",C31-D31) | F31: ='R7業務 (短)'!J46 -> 2228000 | H31: =IF(G31="","",F31-G31) | I31: =IF(8>締月,"",IF(OR(D31="",G31=""),"出納計算表 未入力",IF(AND(E31=0,H31=0),"OK","NG 差額あり")))
B32: 12月 | C32: ='R7業務 (短)'!K38 -> 5009376 | E32: =IF(D32="","",C32-D32) | F32: ='R7業務 (短)'!K46 -> 2894000 | H32: =IF(G32="","",F32-G32) | I32: =IF(9>締月,"",IF(OR(D32="",G32=""),"出納計算表 未入力",IF(AND(E32=0,H32=0),"OK","NG 差額あり")))
B33: 1月 | C33: ='R7業務 (短)'!L38 -> 2079276 | E33: =IF(D33="","",C33-D33) | F33: ='R7業務 (短)'!L46 -> 2560000 | H33: =IF(G33="","",F33-G33) | I33: =IF(10>締月,"",IF(OR(D33="",G33=""),"出納計算表 未入力",IF(AND(E33=0,H33=0),"OK","NG 差額あり")))
B34: 2月 | C34: ='R7業務 (短)'!M38 -> 2212970 | E34: =IF(D34="","",C34-D34) | F34: ='R7業務 (短)'!M46 -> 2209000 | H34: =IF(G34="","",F34-G34) | I34: =IF(11>締月,"",IF(OR(D34="",G34=""),"出納計算表 未入力",IF(AND(E34=0,H34=0),"OK","NG 差額あり")))
B35: 3月 | C35: ='R7業務 (短)'!N38 -> 2135536 | E35: =IF(D35="","",C35-D35) | F35: ='R7業務 (短)'!N46 -> 3606000 | H35: =IF(G35="","",F35-G35) | I35: =IF(12>締月,"",IF(OR(D35="",G35=""),"出納計算表 未入力",IF(AND(E35=0,H35=0),"OK","NG 差額あり")))
B36: 4月(未払) | C36: ='R7業務 (短)'!O38 -> 3204092 | E36: =IF(D36="","",C36-D36) | F36: ='R7業務 (短)'!O46 -> 9655506 | H36: =IF(G36="","",F36-G36) | I36: =IF(13>締月,"",IF(OR(D36="",G36=""),"出納計算表 未入力",IF(AND(E36=0,H36=0),"OK","NG 差額あり")))
B37: 締め月までの合計 | C37: =SUMPRODUCT((ROW(C24:C36)-24+1<=締月)*C24:C36) -> 35828830 | D37: =SUMPRODUCT((ROW(D24:D36)-24+1<=締月)*D24:D36) -> 0 | E37: =C37-D37 -> 35828830 | F37: =SUMPRODUCT((ROW(F24:F36)-24+1<=締月)*F24:F36) -> 24697000 | G37: =SUMPRODUCT((ROW(G24:G36)-24+1<=締月)*G24:G36) -> 0 | H37: =F37-G37 -> 24697000
B39: 業務経理（長期）
B40: 月 | C40: 費用 | F40: 収益 | I40: 判定
C41: 費用収益表 | D41: 出納計算表 | E41: 差額 | F41: 費用収益表 | G41: 出納計算表 | H41: 差額
B42: 4月 | C42: ='R7業務（長）'!C38 -> 412079 | E42: =IF(D42="","",C42-D42) | F42: ='R7業務（長）'!C46 -> 4513000 | H42: =IF(G42="","",F42-G42) | I42: =IF(1>締月,"",IF(OR(D42="",G42=""),"出納計算表 未入力",IF(AND(E42=0,H42=0),"OK","NG 差額あり"))) -> 出納計算表 未入力
B43: 5月 | C43: ='R7業務（長）'!D38 -> 6019213 | E43: =IF(D43="","",C43-D43) | F43: ='R7業務（長）'!D46 -> 9026000 | H43: =IF(G43="","",F43-G43) | I43: =IF(2>締月,"",IF(OR(D43="",G43=""),"出納計算表 未入力",IF(AND(E43=0,H43=0),"OK","NG 差額あり"))) -> 出納計算表 未入力
B44: 6月 | C44: ='R7業務（長）'!E38 -> 6989919 | E44: =IF(D44="","",C44-D44) | F44: ='R7業務（長）'!E46 -> 10732000 | H44: =IF(G44="","",F44-G44) | I44: =IF(3>締月,"",IF(OR(D44="",G44=""),"出納計算表 未入力",IF(AND(E44=0,H44=0),"OK","NG 差額あり"))) -> 出納計算表 未入力
B45: 7月 | C45: ='R7業務（長）'!F38 -> 7671974 | E45: =IF(D45="","",C45-D45) | F45: ='R7業務（長）'!F46 -> 13189000 | H45: =IF(G45="","",F45-G45) | I45: =IF(4>締月,"",IF(OR(D45="",G45=""),"出納計算表 未入力",IF(AND(E45=0,H45=0),"OK","NG 差額あり"))) -> 出納計算表 未入力
B46: 8月 | C46: ='R7業務（長）'!G38 -> 7267746 | E46: =IF(D46="","",C46-D46) | F46: ='R7業務（長）'!G46 -> 9879000 | H46: =IF(G46="","",F46-G46) | I46: =IF(5>締月,"",IF(OR(D46="",G46=""),"出納計算表 未入力",IF(AND(E46=0,H46=0),"OK","NG 差額あり"))) -> 出納計算表 未入力
B47: 9月 | C47: ='R7業務（長）'!H38 -> 6563868 | E47: =IF(D47="","",C47-D47) | F47: ='R7業務（長）'!H46 -> 9882148 | H47: =IF(G47="","",F47-G47) | I47: =IF(6>締月,"",IF(OR(D47="",G47=""),"出納計算表 未入力",IF(AND(E47=0,H47=0),"OK","NG 差額あり"))) -> 出納計算表 未入力
B48: 10月 | C48: ='R7業務（長）'!I38 -> 5598151 | E48: =IF(D48="","",C48-D48) | F48: ='R7業務（長）'!I46 -> 4513000 | H48: =IF(G48="","",F48-G48) | I48: =IF(7>締月,"",IF(OR(D48="",G48=""),"出納計算表 未入力",IF(AND(E48=0,H48=0),"OK","NG 差額あり")))
B49: 11月 | C49: ='R7業務（長）'!J38 -> 6657637 | E49: =IF(D49="","",C49-D49) | F49: ='R7業務（長）'!J46 -> 4251590 | H49: =IF(G49="","",F49-G49) | I49: =IF(8>締月,"",IF(OR(D49="",G49=""),"出納計算表 未入力",IF(AND(E49=0,H49=0),"OK","NG 差額あり")))
B50: 12月 | C50: ='R7業務（長）'!K38 -> 6162473 | E50: =IF(D50="","",C50-D50) | F50: ='R7業務（長）'!K46 -> 4513000 | H50: =IF(G50="","",F50-G50) | I50: =IF(9>締月,"",IF(OR(D50="",G50=""),"出納計算表 未入力",IF(AND(E50=0,H50=0),"OK","NG 差額あり")))
B51: 1月 | C51: ='R7業務（長）'!L38 -> 6712949 | E51: =IF(D51="","",C51-D51) | F51: ='R7業務（長）'!L46 -> 4513000 | H51: =IF(G51="","",F51-G51) | I51: =IF(10>締月,"",IF(OR(D51="",G51=""),"出納計算表 未入力",IF(AND(E51=0,H51=0),"OK","NG 差額あり")))
B52: 2月 | C52: ='R7業務（長）'!M38 -> 6080259 | E52: =IF(D52="","",C52-D52) | F52: ='R7業務（長）'!M46 -> 4513000 | H52: =IF(G52="","",F52-G52) | I52: =IF(11>締月,"",IF(OR(D52="",G52=""),"出納計算表 未入力",IF(AND(E52=0,H52=0),"OK","NG 差額あり")))
B53: 3月 | C53: ='R7業務（長）'!N38 -> 10698750 | E53: =IF(D53="","",C53-D53) | F53: ='R7業務（長）'!N46 -> 4585258 | H53: =IF(G53="","",F53-G53) | I53: =IF(12>締月,"",IF(OR(D53="",G53=""),"出納計算表 未入力",IF(AND(E53=0,H53=0),"OK","NG 差額あり")))
B54: 4月(未払) | C54: ='R7業務（長）'!O38 -> 784007 | E54: =IF(D54="","",C54-D54) | F54: ='R7業務（長）'!O46 -> 0 | H54: =IF(G54="","",F54-G54) | I54: =IF(13>締月,"",IF(OR(D54="",G54=""),"出納計算表 未入力",IF(AND(E54=0,H54=0),"OK","NG 差額あり")))
B55: 締め月までの合計 | C55: =SUMPRODUCT((ROW(C42:C54)-42+1<=締月)*C42:C54) -> 34924799 | D55: =SUMPRODUCT((ROW(D42:D54)-42+1<=締月)*D42:D54) -> 0 | E55: =C55-D55 -> 34924799 | F55: =SUMPRODUCT((ROW(F42:F54)-42+1<=締月)*F42:F54) -> 57221148 | G55: =SUMPRODUCT((ROW(G42:G54)-42+1<=締月)*G42:G54) -> 0 | H55: =F55-G55 -> 57221148
B57: 貸付経理
B58: 月 | C58: 費用 | F58: 収益 | I58: 判定
C59: 費用収益表 | D59: 出納計算表 | E59: 差額 | F59: 費用収益表 | G59: 出納計算表 | H59: 差額
B60: 4月 | C60: ='R8貸付'!C31 -> 542066 | E60: =IF(D60="","",C60-D60) | F60: ='R8貸付'!C36 -> 809638 | H60: =IF(G60="","",F60-G60) | I60: =IF(1>締月,"",IF(OR(D60="",G60=""),"出納計算表 未入力",IF(AND(E60=0,H60=0),"OK","NG 差額あり"))) -> 出納計算表 未入力
B61: 5月 | C61: ='R8貸付'!D31 -> 962591 | E61: =IF(D61="","",C61-D61) | F61: ='R8貸付'!D36 -> 894954 | H61: =IF(G61="","",F61-G61) | I61: =IF(2>締月,"",IF(OR(D61="",G61=""),"出納計算表 未入力",IF(AND(E61=0,H61=0),"OK","NG 差額あり"))) -> 出納計算表 未入力
B62: 6月 | C62: ='R8貸付'!E31 -> 1900656 | E62: =IF(D62="","",C62-D62) | F62: ='R8貸付'!E36 -> 974223 | H62: =IF(G62="","",F62-G62) | I62: =IF(3>締月,"",IF(OR(D62="",G62=""),"出納計算表 未入力",IF(AND(E62=0,H62=0),"OK","NG 差額あり"))) -> 出納計算表 未入力
B63: 7月 | C63: ='R8貸付'!F31 -> 1106995 | E63: =IF(D63="","",C63-D63) | F63: ='R8貸付'!F36 -> 632156 | H63: =IF(G63="","",F63-G63) | I63: =IF(4>締月,"",IF(OR(D63="",G63=""),"出納計算表 未入力",IF(AND(E63=0,H63=0),"OK","NG 差額あり"))) -> 出納計算表 未入力
B64: 8月 | C64: ='R8貸付'!G31 -> 1423062 | E64: =IF(D64="","",C64-D64) | F64: ='R8貸付'!G36 -> 829696 | H64: =IF(G64="","",F64-G64) | I64: =IF(5>締月,"",IF(OR(D64="",G64=""),"出納計算表 未入力",IF(AND(E64=0,H64=0),"OK","NG 差額あり"))) -> 出納計算表 未入力
B65: 9月 | C65: ='R8貸付'!H31 -> 1089403 | E65: =IF(D65="","",C65-D65) | F65: ='R8貸付'!H36 -> 802084 | H65: =IF(G65="","",F65-G65) | I65: =IF(6>締月,"",IF(OR(D65="",G65=""),"出納計算表 未入力",IF(AND(E65=0,H65=0),"OK","NG 差額あり"))) -> 出納計算表 未入力
B66: 10月 | C66: ='R8貸付'!I31 -> 1080718 | E66: =IF(D66="","",C66-D66) | F66: ='R8貸付'!I36 -> 838256 | H66: =IF(G66="","",F66-G66) | I66: =IF(7>締月,"",IF(OR(D66="",G66=""),"出納計算表 未入力",IF(AND(E66=0,H66=0),"OK","NG 差額あり")))
B67: 11月 | C67: ='R8貸付'!J31 -> 913437 | E67: =IF(D67="","",C67-D67) | F67: ='R8貸付'!J36 -> 820237 | H67: =IF(G67="","",F67-G67) | I67: =IF(8>締月,"",IF(OR(D67="",G67=""),"出納計算表 未入力",IF(AND(E67=0,H67=0),"OK","NG 差額あり")))
B68: 12月 | C68: ='R8貸付'!K31 -> 1921335 | E68: =IF(D68="","",C68-D68) | F68: ='R8貸付'!K36 -> 1204671 | H68: =IF(G68="","",F68-G68) | I68: =IF(9>締月,"",IF(OR(D68="",G68=""),"出納計算表 未入力",IF(AND(E68=0,H68=0),"OK","NG 差額あり")))
B69: 1月 | C69: ='R8貸付'!L31 -> 1092749 | E69: =IF(D69="","",C69-D69) | F69: ='R8貸付'!L36 -> 814454 | H69: =IF(G69="","",F69-G69) | I69: =IF(10>締月,"",IF(OR(D69="",G69=""),"出納計算表 未入力",IF(AND(E69=0,H69=0),"OK","NG 差額あり")))
B70: 2月 | C70: ='R8貸付'!M31 -> 1053997 | E70: =IF(D70="","",C70-D70) | F70: ='R8貸付'!M36 -> 834390 | H70: =IF(G70="","",F70-G70) | I70: =IF(11>締月,"",IF(OR(D70="",G70=""),"出納計算表 未入力",IF(AND(E70=0,H70=0),"OK","NG 差額あり")))
B71: 3月 | C71: ='R8貸付'!N31 -> 1006894 | E71: =IF(D71="","",C71-D71) | F71: ='R8貸付'!N36 -> 801567 | H71: =IF(G71="","",F71-G71) | I71: =IF(12>締月,"",IF(OR(D71="",G71=""),"出納計算表 未入力",IF(AND(E71=0,H71=0),"OK","NG 差額あり")))
B72: 4月(未払) | C72: ='R8貸付'!O31 -> 595170 | E72: =IF(D72="","",C72-D72) | F72: ='R8貸付'!O36 -> 247126 | H72: =IF(G72="","",F72-G72) | I72: =IF(13>締月,"",IF(OR(D72="",G72=""),"出納計算表 未入力",IF(AND(E72=0,H72=0),"OK","NG 差額あり")))
B73: 締め月までの合計 | C73: =SUMPRODUCT((ROW(C60:C72)-60+1<=締月)*C60:C72) -> 7024773 | D73: =SUMPRODUCT((ROW(D60:D72)-60+1<=締月)*D60:D72) -> 0 | E73: =C73-D73 -> 7024773 | F73: =SUMPRODUCT((ROW(F60:F72)-60+1<=締月)*F60:F72) -> 4942751 | G73: =SUMPRODUCT((ROW(G60:G72)-60+1<=締月)*G60:G72) -> 0 | H73: =F73-G73 -> 4942751

Sheet 月例
A1: 令和 ８ 年 度 業 務 経 理 経 費 給 付 区 分 別 執 行 額 一 覧 表
K2: （単位:円）
P3: ←支払担当者が「未確認」、経理担当者が伝票確認後に「確認済」
A4: 支出日 | C4: 中項目 | D4: 小項目 | E4: 摘要 | F4: 執行額 | G4: 経費区分 | H4: 短期 | I4: 厚年 | J4: 経過的 | K4: 退職等 | L4: （再掲） 退職等単独 | M4: 作業列 （支給月） | P4: 状態 | Q4: 費目 (自動) | R4: 長期額 (自動) | S4: 短期 通番キー | T4: 長期 通番キー | U4: 計上列 (自動)
A5: 45756 | C5: 事務費 | D5: 通信運搬費 | E5: 切手 | F5: 178000 | G5: 2 | H5: =IF(G5=1,F5-I5-J5-K5,IF(G5=2,F5,0)) -> 178000 | I5: =ROUND(IF(G5=1,F5*10/23,IF(G5=3,F5-J5-K5,IF(G5=4,F5,IF(G5=5,F5*10/11,IF(G5=7,F5*10/11,0))))),0) -> 0 | J5: =ROUND(IF(G5=1,F5/23,IF(G5=3,F5/12,IF(G5=5,F5-I5,IF(G5=8,F5,0)))),0) -> 0 | K5: =ROUND(IF(G5=1,F5/23,IF(G5=3,F5/12,IF(G5=6,F5,IF(G5=7,F5-I5,0)))),0) -> 0 | L5: =IF(G5=6,F5,0) -> 0 | M5: =IF(F5="",0,MONTH(A5)) -> 4 | P5: 昨年実績 | Q5: =IF($F5="","",IFERROR(VLOOKUP($C5&"|"&$D5,科目表!$A$5:$B$200,2,FALSE),"※未登録")) -> 通信運搬費 | R5: =IF($F5="","",$I5+$J5+$K5) -> 0 | S5: =IF(OR($F5="",$P5="支払なし",$H5=0,$Q5=""),"",$Q5&"|S|"&(COUNTIF(S$4:S4,$Q5&"|S|*")+1)) -> 通信運搬費|S|1 | T5: =IF(OR($F5="",$P5="支払なし",$R5=0,$Q5=""),"",$Q5&"|L|"&(COUNTIF(T$4:T4,$Q5&"|L|*")+1)) | U5: =IF(OR($F5="",$A5=""),"",MOD(MONTH($A5)-4,12)+1) -> 1
A6: 46140 | C6: 事務費 | D6: 事務用消耗品費 | E6: 令和８年度基幹ウイルス対策ソフト（ミツイワ株式会社）短期 | F6: 20482 | G6: 2 | H6: =IF(G6=1,F6-I6-J6-K6,IF(G6=2,F6,0)) -> 20482 | I6: =ROUND(IF(G6=1,F6*10/23,IF(G6=3,F6-J6-K6,IF(G6=4,F6,IF(G6=5,F6*10/11,IF(G6=7,F6*10/11,0))))),0) -> 0 | J6: =ROUND(IF(G6=1,F6/23,IF(G6=3,F6/12,IF(G6=5,F6-I6,IF(G6=8,F6,0)))),0) -> 0 | K6: =ROUND(IF(G6=1,F6/23,IF(G6=3,F6/12,IF(G6=6,F6,IF(G6=7,F6-I6,0)))),0) -> 0 | L6: =IF(G6=6,F6,0) -> 0 | M6: =IF(F6="",0,MONTH(A6)) -> 4 | P6: 確認済 | Q6: =IF($F6="","",IFERROR(VLOOKUP($C6&"|"&$D6,科目表!$A$5:$B$200,2,FALSE),"※未登録")) -> 事務用消耗品費 | R6: =IF($F6="","",$I6+$J6+$K6) -> 0 | S6: =IF(OR($F6="",$P6="支払なし",$H6=0,$Q6=""),"",$Q6&"|S|"&(COUNTIF(S$4:S5,$Q6&"|S|*")+1)) -> 事務用消耗品費|S|1 | T6: =IF(OR($F6="",$P6="支払なし",$R6=0,$Q6=""),"",$Q6&"|L|"&(COUNTIF(T$4:T5,$Q6&"|L|*")+1)) | U6: =IF(OR($F6="",$A6=""),"",MOD(MONTH($A6)-4,12)+1) -> 1
A7: 46140 | C7: 事務費 | D7: 事務用消耗品費 | E7: 令和８年度基幹ウイルス対策ソフト（ミツイワ株式会社）長期 | F7: 8778 | G7: 3 | H7: =IF(G7=1,F7-I7-J7-K7,IF(G7=2,F7,0)) -> 0 | I7: =ROUND(IF(G7=1,F7*10/23,IF(G7=3,F7-J7-K7,IF(G7=4,F7,IF(G7=5,F7*10/11,IF(G7=7,F7*10/11,0))))),0) -> 7314 | J7: =ROUND(IF(G7=1,F7/23,IF(G7=3,F7/12,IF(G7=5,F7-I7,IF(G7=8,F7,0)))),0) -> 732 | K7: =ROUND(IF(G7=1,F7/23,IF(G7=3,F7/12,IF(G7=6,F7,IF(G7=7,F7-I7,0)))),0) -> 732 | L7: =IF(G7=6,F7,0) -> 0 | M7: =IF(F7="",0,MONTH(A7)) -> 4 | P7: 確認済 | Q7: =IF($F7="","",IFERROR(VLOOKUP($C7&"|"&$D7,科目表!$A$5:$B$200,2,FALSE),"※未登録")) -> 事務用消耗品費 | R7: =IF($F7="","",$I7+$J7+$K7) -> 8778 | S7: =IF(OR($F7="",$P7="支払なし",$H7=0,$Q7=""),"",$Q7&"|S|"&(COUNTIF(S$4:S6,$Q7&"|S|*")+1)) | T7: =IF(OR($F7="",$P7="支払なし",$R7=0,$Q7=""),"",$Q7&"|L|"&(COUNTIF(T$4:T6,$Q7&"|L|*")+1)) -> 事務用消耗品費|L|1 | U7: =IF(OR($F7="",$A7=""),"",MOD(MONTH($A7)-4,12)+1) -> 1
A8: 44316 | C8: 事務費 | D8: 事務用消耗品費 | E8: CD／DVDファイルＡ４１２ＪーＣ 他 | F8: 24407 | G8: 2 | H8: =IF(G8=1,F8-I8-J8-K8,IF(G8=2,F8,0)) -> 24407 | I8: =ROUND(IF(G8=1,F8*10/23,IF(G8=3,F8-J8-K8,IF(G8=4,F8,IF(G8=5,F8*10/11,IF(G8=7,F8*10/11,0))))),0) -> 0 | J8: =ROUND(IF(G8=1,F8/23,IF(G8=3,F8/12,IF(G8=5,F8-I8,IF(G8=8,F8,0)))),0) -> 0 | K8: =ROUND(IF(G8=1,F8/23,IF(G8=3,F8/12,IF(G8=6,F8,IF(G8=7,F8-I8,0)))),0) -> 0 | L8: =IF(G8=6,F8,0) -> 0 | M8: =IF(F8="",0,MONTH(A8)) -> 4 | P8: 昨年実績 | Q8: =IF($F8="","",IFERROR(VLOOKUP($C8&"|"&$D8,科目表!$A$5:$B$200,2,FALSE),"※未登録")) -> 事務用消耗品費 | R8: =IF($F8="","",$I8+$J8+$K8) -> 0 | S8: =IF(OR($F8="",$P8="支払なし",$H8=0,$Q8=""),"",$Q8&"|S|"&(COUNTIF(S$4:S7,$Q8&"|S|*")+1)) -> 事務用消耗品費|S|2 | T8: =IF(OR($F8="",$P8="支払なし",$R8=0,$Q8=""),"",$Q8&"|L|"&(COUNTIF(T$4:T7,$Q8&"|L|*")+1)) | U8: =IF(OR($F8="",$A8=""),"",MOD(MONTH($A8)-4,12)+1) -> 1
A9: 45764 | C9: 事務費 | D9: 通信運搬費 | E9: 切手 | F9: 173700 | G9: 3 | H9: =IF(G9=1,F9-I9-J9-K9,IF(G9=2,F9,0)) -> 0 | I9: =ROUND(IF(G9=1,F9*10/23,IF(G9=3,F9-J9-K9,IF(G9=4,F9,IF(G9=5,F9*10/11,IF(G9=7,F9*10/11,0))))),0) -> 144750 | J9: =ROUND(IF(G9=1,F9/23,IF(G9=3,F9/12,IF(G9=5,F9-I9,IF(G9=8,F9,0)))),0) -> 14475 | K9: =ROUND(IF(G9=1,F9/23,IF(G9=3,F9/12,IF(G9=6,F9,IF(G9=7,F9-I9,0)))),0) -> 14475 | L9: =IF(G9=6,F9,0) -> 0 | M9: =IF(F9="",0,MONTH(A9)) -> 4 | P9: 昨年実績 | Q9: =IF($F9="","",IFERROR(VLOOKUP($C9&"|"&$D9,科目表!$A$5:$B$200,2,FALSE),"※未登録")) -> 通信運搬費 | R9: =IF($F9="","",$I9+$J9+$K9) -> 173700 | S9: =IF(OR($F9="",$P9="支払なし",$H9=0,$Q9=""),"",$Q9&"|S|"&(COUNTIF(S$4:S8,$Q9&"|S|*")+1)) | T9: =IF(OR($F9="",$P9="支払なし",$R9=0,$Q9=""),"",$Q9&"|L|"&(COUNTIF(T$4:T8,$Q9&"|L|*")+1)) -> 通信運搬費|L|1 | U9: =IF(OR($F9="",$A9=""),"",MOD(MONTH($A9)-4,12)+1) -> 1
A10: 46132 | C10: 委託費 | E10: レセプト電子データ提供料（1月診療分） | F10: 60235 | G10: 2 | H10: =IF(G10=1,F10-I10-J10-K10,IF(G10=2,F10,0)) -> 60235 | I10: =ROUND(IF(G10=1,F10*10/23,IF(G10=3,F10-J10-K10,IF(G10=4,F10,IF(G10=5,F10*10/11,IF(G10=7,F10*10/11,0))))),0) -> 0 | J10: =ROUND(IF(G10=1,F10/23,IF(G10=3,F10/12,IF(G10=5,F10-I10,IF(G10=8,F10,0)))),0) -> 0 | K10: =ROUND(IF(G10=1,F10/23,IF(G10=3,F10/12,IF(G10=6,F10,IF(G10=7,F10-I10,0)))),0) -> 0 | L10: =IF(G10=6,F10,0) -> 0 | M10: =IF(F10="",0,MONTH(A10)) -> 4 | P10: 確認済 | Q10: =IF($F10="","",IFERROR(VLOOKUP($C10&"|"&$D10,科目表!$A$5:$B$200,2,FALSE),"※未登録")) -> 委託費 | R10: =IF($F10="","",$I10+$J10+$K10) -> 0 | S10: =IF(OR($F10="",$P10="支払なし",$H10=0,$Q10=""),"",$Q10&"|S|"&(COUNTIF(S$4:S9,$Q10&"|S|*")+1)) -> 委託費|S|1 | T10: =IF(OR($F10="",$P10="支払なし",$R10=0,$Q10=""),"",$Q10&"|L|"&(COUNTIF(T$4:T9,$Q10&"|L|*")+1)) | U10: =IF(OR($F10="",$A10=""),"",MOD(MONTH($A10)-4,12)+1) -> 1
A11: 43941 | C11: 事務費 | D11: 雑費 | E11: 電子証明書発行・更新料（令和2年4月請求） | F11: 4000 | G11: 2 | H11: =IF(G11=1,F11-I11-J11-K11,IF(G11=2,F11,0)) -> 4000 | I11: =ROUND(IF(G11=1,F11*10/23,IF(G11=3,F11-J11-K11,IF(G11=4,F11,IF(G11=5,F11*10/11,IF(G11=7,F11*10/11,0))))),0) -> 0 | J11: =ROUND(IF(G11=1,F11/23,IF(G11=3,F11/12,IF(G11=5,F11-I11,IF(G11=8,F11,0)))),0) -> 0 | K11: =ROUND(IF(G11=1,F11/23,IF(G11=3,F11/12,IF(G11=6,F11,IF(G11=7,F11-I11,0)))),0) -> 0 | L11: =IF(G11=6,F11,0) -> 0 | M11: =IF(F11="",0,MONTH(A11)) -> 4 | P11: 昨年実績 | Q11: =IF($F11="","",IFERROR(VLOOKUP($C11&"|"&$D11,科目表!$A$5:$B$200,2,FALSE),"※未登録")) -> 事務費・雑費 | R11: =IF($F11="","",$I11+$J11+$K11) -> 0 | S11: =IF(OR($F11="",$P11="支払なし",$H11=0,$Q11=""),"",$Q11&"|S|"&(COUNTIF(S$4:S10,$Q11&"|S|*")+1)) -> 事務費・雑費|S|1 | T11: =IF(OR($F11="",$P11="支払なし",$R11=0,$Q11=""),"",$Q11&"|L|"&(COUNTIF(T$4:T10,$Q11&"|L|*")+1)) | U11: =IF(OR($F11="",$A11=""),"",MOD(MONTH($A11)-4,12)+1) -> 1
A12: 46150 | C12: 負担金 | E12: 広島県社会保険協会年会費(短期) | F12: 780 | G12: 2 | H12: =IF(G12=1,F12-I12-J12-K12,IF(G12=2,F12,0)) -> 780 | I12: =ROUND(IF(G12=1,F12*10/23,IF(G12=3,F12-J12-K12,IF(G12=4,F12,IF(G12=5,F12*10/11,IF(G12=7,F12*10/11,0))))),0) -> 0 | J12: =ROUND(IF(G12=1,F12/23,IF(G12=3,F12/12,IF(G12=5,F12-I12,IF(G12=8,F12,0)))),0) -> 0 | K12: =ROUND(IF(G12=1,F12/23,IF(G12=3,F12/12,IF(G12=6,F12,IF(G12=7,F12-I12,0)))),0) -> 0 | L12: =IF(G12=6,F12,0) -> 0 | M12: =IF(F12="",0,MONTH(A12)) -> 5 | P12: 確認済 | Q12: =IF($F12="","",IFERROR(VLOOKUP($C12&"|"&$D12,科目表!$A$5:$B$200,2,FALSE),"※未登録")) -> 県社保協会費 | R12: =IF($F12="","",$I12+$J12+$K12) -> 0 | S12: =IF(OR($F12="",$P12="支払なし",$H12=0,$Q12=""),"",$Q12&"|S|"&(COUNTIF(S$4:S11,$Q12&"|S|*")+1)) -> 県社保協会費|S|1 | T12: =IF(OR($F12="",$P12="支払なし",$R12=0,$Q12=""),"",$Q12&"|L|"&(COUNTIF(T$4:T11,$Q12&"|L|*")+1)) | U12: =IF(OR($F12="",$A12=""),"",MOD(MONTH($A12)-4,12)+1) -> 2
A13: 46150 | C13: 負担金 | E13: 広島県社会保険協会年会費(長期) | F13: 520 | G13: 3 | H13: =IF(G13=1,F13-I13-J13-K13,IF(G13=2,F13,0)) -> 0 | I13: =ROUND(IF(G13=1,F13*10/23,IF(G13=3,F13-J13-K13,IF(G13=4,F13,IF(G13=5,F13*10/11,IF(G13=7,F13*10/11,0))))),0) -> 434 | J13: =ROUND(IF(G13=1,F13/23,IF(G13=3,F13/12,IF(G13=5,F13-I13,IF(G13=8,F13,0)))),0) -> 43 | K13: =ROUND(IF(G13=1,F13/23,IF(G13=3,F13/12,IF(G13=6,F13,IF(G13=7,F13-I13,0)))),0) -> 43 | L13: =IF(G13=6,F13,0) -> 0 | M13: =IF(F13="",0,MONTH(A13)) -> 5 | P13: 確認済 | Q13: =IF($F13="","",IFERROR(VLOOKUP($C13&"|"&$D13,科目表!$A$5:$B$200,2,FALSE),"※未登録")) -> 県社保協会費 | R13: =IF($F13="","",$I13+$J13+$K13) -> 520 | S13: =IF(OR($F13="",$P13="支払なし",$H13=0,$Q13=""),"",$Q13&"|S|"&(COUNTIF(S$4:S12,$Q13&"|S|*")+1)) | T13: =IF(OR($F13="",$P13="支払なし",$R13=0,$Q13=""),"",$Q13&"|L|"&(COUNTIF(T$4:T12,$Q13&"|L|*")+1)) -> 県社保協会費|L|1 | U13: =IF(OR($F13="",$A13=""),"",MOD(MONTH($A13)-4,12)+1) -> 2
A14: 46133 | C14: 職員給与 | D14: 非常勤職員手当 | E14: ４月分給与（長期分） | F14: 380800 | G14: 3 | H14: =IF(G14=1,F14-I14-J14-K14,IF(G14=2,F14,0)) -> 0 | I14: =ROUND(IF(G14=1,F14*10/23,IF(G14=3,F14-J14-K14,IF(G14=4,F14,IF(G14=5,F14*10/11,IF(G14=7,F14*10/11,0))))),0) -> 317334 | J14: =ROUND(IF(G14=1,F14/23,IF(G14=3,F14/12,IF(G14=5,F14-I14,IF(G14=8,F14,0)))),0) -> 31733 | K14: =ROUND(IF(G14=1,F14/23,IF(G14=3,F14/12,IF(G14=6,F14,IF(G14=7,F14-I14,0)))),0) -> 31733 | L14: =IF(G14=6,F14,0) -> 0 | M14: =IF(F14="",0,MONTH(A14)) -> 4 | P14: 確認済 | Q14: =IF($F14="","",IFERROR(VLOOKUP($C14&"|"&$D14,科目表!$A$5:$B$200,2,FALSE),"※未登録")) -> 非常勤職員手当 | R14: =IF($F14="","",$I14+$J14+$K14) -> 380800 | S14: =IF(OR($F14="",$P14="支払なし",$H14=0,$Q14=""),"",$Q14&"|S|"&(COUNTIF(S$4:S13,$Q14&"|S|*")+1)) | T14: =IF(OR($F14="",$P14="支払なし",$R14=0,$Q14=""),"",$Q14&"|L|"&(COUNTIF(T$4:T13,$Q14&"|L|*")+1)) -> 非常勤職員手当|L|1 | U14: =IF(OR($F14="",$A14=""),"",MOD(MONTH($A14)-4,12)+1) -> 1
A15: 46133 | C15: 職員給与 | D15: 非常勤職員手当 | E15: ４月分給与（短期分）3月時間外除く | F15: 317340 | G15: 2 | H15: =IF(G15=1,F15-I15-J15-K15,IF(G15=2,F15,0)) -> 317340 | I15: =ROUND(IF(G15=1,F15*10/23,IF(G15=3,F15-J15-K15,IF(G15=4,F15,IF(G15=5,F15*10/11,IF(G15=7,F15*10/11,0))))),0) -> 0 | J15: =ROUND(IF(G15=1,F15/23,IF(G15=3,F15/12,IF(G15=5,F15-I15,IF(G15=8,F15,0)))),0) -> 0 | K15: =ROUND(IF(G15=1,F15/23,IF(G15=3,F15/12,IF(G15=6,F15,IF(G15=7,F15-I15,0)))),0) -> 0 | L15: 0 | M15: =IF(F15="",0,MONTH(A15)) -> 4 | P15: 確認済 | Q15: =IF($F15="","",IFERROR(VLOOKUP($C15&"|"&$D15,科目表!$A$5:$B$200,2,FALSE),"※未登録")) -> 非常勤職員手当 | R15: =IF($F15="","",$I15+$J15+$K15) -> 0 | S15: =IF(OR($F15="",$P15="支払なし",$H15=0,$Q15=""),"",$Q15&"|S|"&(COUNTIF(S$4:S14,$Q15&"|S|*")+1)) -> 非常勤職員手当|S|1 | T15: =IF(OR($F15="",$P15="支払なし",$R15=0,$Q15=""),"",$Q15&"|L|"&(COUNTIF(T$4:T14,$Q15&"|L|*")+1)) | U15: =IF(OR($F15="",$A15=""),"",MOD(MONTH($A15)-4,12)+1) -> 1
A16: 46133 | C16: 負担金 | D16: 互助会費 | E16: 助成金（４月長期分） | F16: 466 | G16: 3 | H16: =IF(G16=1,F16-I16-J16-K16,IF(G16=2,F16,0)) -> 0 | I16: =ROUND(IF(G16=1,F16*10/23,IF(G16=3,F16-J16-K16,IF(G16=4,F16,IF(G16=5,F16*10/11,IF(G16=7,F16*10/11,0))))),0) -> 388 | J16: =ROUND(IF(G16=1,F16/23,IF(G16=3,F16/12,IF(G16=5,F16-I16,IF(G16=8,F16,0)))),0) -> 39 | K16: =ROUND(IF(G16=1,F16/23,IF(G16=3,F16/12,IF(G16=6,F16,IF(G16=7,F16-I16,0)))),0) -> 39 | L16: =IF(G16=6,F16,0) -> 0 | M16: =IF(F16="",0,MONTH(A16)) -> 4 | P16: 確認済 | Q16: =IF($F16="","",IFERROR(VLOOKUP($C16&"|"&$D16,科目表!$A$5:$B$200,2,FALSE),"※未登録")) -> 互助会費 | R16: =IF($F16="","",$I16+$J16+$K16) -> 466 | S16: =IF(OR($F16="",$P16="支払なし",$H16=0,$Q16=""),"",$Q16&"|S|"&(COUNTIF(S$4:S15,$Q16&"|S|*")+1)) | T16: =IF(OR($F16="",$P16="支払なし",$R16=0,$Q16=""),"",$Q16&"|L|"&(COUNTIF(T$4:T15,$Q16&"|L|*")+1)) -> 互助会費|L|1 | U16: =IF(OR($F16="",$A16=""),"",MOD(MONTH($A16)-4,12)+1) -> 1
A17: 46133 | C17: 負担金 | D17: 互助会費 | E17: 助成金（４月短期分） | F17: 240 | G17: 2 | H17: =IF(G17=1,F17-I17-J17-K17,IF(G17=2,F17,0)) -> 240 | I17: =ROUND(IF(G17=1,F17*10/23,IF(G17=3,F17-J17-K17,IF(G17=4,F17,IF(G17=5,F17*10/11,IF(G17=7,F17*10/11,0))))),0) -> 0 | J17: =ROUND(IF(G17=1,F17/23,IF(G17=3,F17/12,IF(G17=5,F17-I17,IF(G17=8,F17,0)))),0) -> 0 | K17: =ROUND(IF(G17=1,F17/23,IF(G17=3,F17/12,IF(G17=6,F17,IF(G17=7,F17-I17,0)))),0) -> 0 | L17: =IF(G17=6,F17,0) -> 0 | M17: =IF(F17="",0,MONTH(A17)) -> 4 | P17: 確認済 | Q17: =IF($F17="","",IFERROR(VLOOKUP($C17&"|"&$D17,科目表!$A$5:$B$200,2,FALSE),"※未登録")) -> 互助会費 | R17: =IF($F17="","",$I17+$J17+$K17) -> 0 | S17: =IF(OR($F17="",$P17="支払なし",$H17=0,$Q17=""),"",$Q17&"|S|"&(COUNTIF(S$4:S16,$Q17&"|S|*")+1)) -> 互助会費|S|1 | T17: =IF(OR($F17="",$P17="支払なし",$R17=0,$Q17=""),"",$Q17&"|L|"&(COUNTIF(T$4:T16,$Q17&"|L|*")+1)) | U17: =IF(OR($F17="",$A17=""),"",MOD(MONTH($A17)-4,12)+1) -> 1
A18: 45044 | C18: 委託費 | E18: 個人番号管理システムシンクライアント（４～１０月） | F18: 24486 | G18: 2 | H18: =IF(G18=1,F18-I18-J18-K18,IF(G18=2,F18,0)) -> 24486 | I18: =ROUND(IF(G18=1,F18*10/23,IF(G18=3,F18-J18-K18,IF(G18=4,F18,IF(G18=5,F18*10/11,IF(G18=7,F18*10/11,0))))),0) -> 0 | J18: =ROUND(IF(G18=1,F18/23,IF(G18=3,F18/12,IF(G18=5,F18-I18,IF(G18=8,F18,0)))),0) -> 0 | K18: =ROUND(IF(G18=1,F18/23,IF(G18=3,F18/12,IF(G18=6,F18,IF(G18=7,F18-I18,0)))),0) -> 0 | L18: =IF(G18=6,F18,0) -> 0 | M18: =IF(F18="",0,MONTH(A18)) -> 4 | P18: 昨年実績 | Q18: =IF($F18="","",IFERROR(VLOOKUP($C18&"|"&$D18,科目表!$A$5:$B$200,2,FALSE),"※未登録")) -> 委託費 | R18: =IF($F18="","",$I18+$J18+$K18) -> 0 | S18: =IF(OR($F18="",$P18="支払なし",$H18=0,$Q18=""),"",$Q18&"|S|"&(COUNTIF(S$4:S17,$Q18&"|S|*")+1)) -> 委託費|S|2 | T18: =IF(OR($F18="",$P18="支払なし",$R18=0,$Q18=""),"",$Q18&"|L|"&(COUNTIF(T$4:T17,$Q18&"|L|*")+1)) | U18: =IF(OR($F18="",$A18=""),"",MOD(MONTH($A18)-4,12)+1) -> 1
A19: 45807 | C19: 事務費 | D19: 図書印刷費 | E19: 窓付封筒 １，０００枚 | F19: 49500 | G19: 2 | H19: =IF(G19=1,F19-I19-J19-K19,IF(G19=2,F19,0)) -> 49500 | I19: =ROUND(IF(G19=1,F19*10/23,IF(G19=3,F19-J19-K19,IF(G19=4,F19,IF(G19=5,F19*10/11,IF(G19=7,F19*10/11,0))))),0) -> 0 | J19: =ROUND(IF(G19=1,F19/23,IF(G19=3,F19/12,IF(G19=5,F19-I19,IF(G19=8,F19,0)))),0) -> 0 | K19: =ROUND(IF(G19=1,F19/23,IF(G19=3,F19/12,IF(G19=6,F19,IF(G19=7,F19-I19,0)))),0) -> 0 | L19: =IF(G19=6,F19,0) -> 0 | M19: =IF(F19="",0,MONTH(A19)) -> 5 | P19: 昨年実績 | Q19: =IF($F19="","",IFERROR(VLOOKUP($C19&"|"&$D19,科目表!$A$5:$B$200,2,FALSE),"※未登録")) -> 図書印刷費 | R19: =IF($F19="","",$I19+$J19+$K19) -> 0 | S19: =IF(OR($F19="",$P19="支払なし",$H19=0,$Q19=""),"",$Q19&"|S|"&(COUNTIF(S$4:S18,$Q19&"|S|*")+1)) -> 図書印刷費|S|1 | T19: =IF(OR($F19="",$P19="支払なし",$R19=0,$Q19=""),"",$Q19&"|L|"&(COUNTIF(T$4:T18,$Q19&"|L|*")+1)) | U19: =IF(OR($F19="",$A19=""),"",MOD(MONTH($A19)-4,12)+1) -> 2
A20: 45061 | C20: 事務費 | D20: 図書印刷費 | E20: 定年延長と共済組合制度 ３０部 | F20: 2970 | G20: 3 | H20: =IF(G20=1,F20-I20-J20-K20,IF(G20=2,F20,0)) -> 0 | I20: =ROUND(IF(G20=1,F20*10/23,IF(G20=3,F20-J20-K20,IF(G20=4,F20,IF(G20=5,F20*10/11,IF(G20=7,F20*10/11,0))))),0) -> 2474 | J20: =ROUND(IF(G20=1,F20/23,IF(G20=3,F20/12,IF(G20=5,F20-I20,IF(G20=8,F20,0)))),0) -> 248 | K20: =ROUND(IF(G20=1,F20/23,IF(G20=3,F20/12,IF(G20=6,F20,IF(G20=7,F20-I20,0)))),0) -> 248 | L20: =IF(G20=6,F20,0) -> 0 | M20: =IF(F20="",0,MONTH(A20)) -> 5 | P20: 昨年実績 | Q20: =IF($F20="","",IFERROR(VLOOKUP($C20&"|"&$D20,科目表!$A$5:$B$200,2,FALSE),"※未登録")) -> 図書印刷費 | R20: =IF($F20="","",$I20+$J20+$K20) -> 2970 | S20: =IF(OR($F20="",$P20="支払なし",$H20=0,$Q20=""),"",$Q20&"|S|"&(COUNTIF(S$4:S19,$Q20&"|S|*")+1)) | T20: =IF(OR($F20="",$P20="支払なし",$R20=0,$Q20=""),"",$Q20&"|L|"&(COUNTIF(T$4:T19,$Q20&"|L|*")+1)) -> 図書印刷費|L|1 | U20: =IF(OR($F20="",$A20=""),"",MOD(MONTH($A20)-4,12)+1) -> 2
A21: 45477 | C21: 事務費 | D21: 図書印刷費 | E21: 組合員原票（Ａ４）８００部 ほか | F21: 133650 | G21: 3 | H21: =IF(G21=1,F21-I21-J21-K21,IF(G21=2,F21,0)) -> 0 | I21: =ROUND(IF(G21=1,F21*10/23,IF(G21=3,F21-J21-K21,IF(G21=4,F21,IF(G21=5,F21*10/11,IF(G21=7,F21*10/11,0))))),0) -> 111374 | J21: =ROUND(IF(G21=1,F21/23,IF(G21=3,F21/12,IF(G21=5,F21-I21,IF(G21=8,F21,0)))),0) -> 11138 | K21: =ROUND(IF(G21=1,F21/23,IF(G21=3,F21/12,IF(G21=6,F21,IF(G21=7,F21-I21,0)))),0) -> 11138 | L21: =IF(G21=6,F21,0) -> 0 | M21: =IF(F21="",0,MONTH(A21)) -> 7 | P21: 昨年実績 | Q21: =IF($F21="","",IFERROR(VLOOKUP($C21&"|"&$D21,科目表!$A$5:$B$200,2,FALSE),"※未登録")) -> 図書印刷費 | R21: =IF($F21="","",$I21+$J21+$K21) -> 133650 | S21: =IF(OR($F21="",$P21="支払なし",$H21=0,$Q21=""),"",$Q21&"|S|"&(COUNTIF(S$4:S20,$Q21&"|S|*")+1)) | T21: =IF(OR($F21="",$P21="支払なし",$R21=0,$Q21=""),"",$Q21&"|L|"&(COUNTIF(T$4:T20,$Q21&"|L|*")+1)) -> 図書印刷費|L|2 | U21: =IF(OR($F21="",$A21=""),"",MOD(MONTH($A21)-4,12)+1) -> 4
A22: 44377 | C22: 事務費 | D22: 事務用消耗品費 | E22: 鋳造ゴム印 ３号以下214字 他 | F22: 9733 | G22: 3 | H22: =IF(G22=1,F22-I22-J22-K22,IF(G22=2,F22,0)) -> 0 | I22: =ROUND(IF(G22=1,F22*10/23,IF(G22=3,F22-J22-K22,IF(G22=4,F22,IF(G22=5,F22*10/11,IF(G22=7,F22*10/11,0))))),0) -> 8111 | J22: =ROUND(IF(G22=1,F22/23,IF(G22=3,F22/12,IF(G22=5,F22-I22,IF(G22=8,F22,0)))),0) -> 811 | K22: =ROUND(IF(G22=1,F22/23,IF(G22=3,F22/12,IF(G22=6,F22,IF(G22=7,F22-I22,0)))),0) -> 811 | L22: =IF(G22=6,F22,0) -> 0 | M22: =IF(F22="",0,MONTH(A22)) -> 6 | P22: 昨年実績 | Q22: =IF($F22="","",IFERROR(VLOOKUP($C22&"|"&$D22,科目表!$A$5:$B$200,2,FALSE),"※未登録")) -> 事務用消耗品費 | R22: =IF($F22="","",$I22+$J22+$K22) -> 9733 | S22: =IF(OR($F22="",$P22="支払なし",$H22=0,$Q22=""),"",$Q22&"|S|"&(COUNTIF(S$4:S21,$Q22&"|S|*")+1)) | T22: =IF(OR($F22="",$P22="支払なし",$R22=0,$Q22=""),"",$Q22&"|L|"&(COUNTIF(T$4:T21,$Q22&"|L|*")+1)) -> 事務用消耗品費|L|2 | U22: =IF(OR($F22="",$A22=""),"",MOD(MONTH($A22)-4,12)+1) -> 3
A23: 46171 | C23: 事務費 | D23: 事務用消耗品費 | E23: ラベル用紙 LBP-F7656-100N ２冊 他 | F23: 43890 | G23: 2 | H23: =IF(G23=1,F23-I23-J23-K23,IF(G23=2,F23,0)) -> 43890 | I23: =ROUND(IF(G23=1,F23*10/23,IF(G23=3,F23-J23-K23,IF(G23=4,F23,IF(G23=5,F23*10/11,IF(G23=7,F23*10/11,0))))),0) -> 0 | J23: =ROUND(IF(G23=1,F23/23,IF(G23=3,F23/12,IF(G23=5,F23-I23,IF(G23=8,F23,0)))),0) -> 0 | K23: =ROUND(IF(G23=1,F23/23,IF(G23=3,F23/12,IF(G23=6,F23,IF(G23=7,F23-I23,0)))),0) -> 0 | L23: =IF(G23=6,F23,0) -> 0 | M23: =IF(F23="",0,MONTH(A23)) -> 5 | P23: 確認済 | Q23: =IF($F23="","",IFERROR(VLOOKUP($C23&"|"&$D23,科目表!$A$5:$B$200,2,FALSE),"※未登録")) -> 事務用消耗品費 | R23: =IF($F23="","",$I23+$J23+$K23) -> 0 | S23: =IF(OR($F23="",$P23="支払なし",$H23=0,$Q23=""),"",$Q23&"|S|"&(COUNTIF(S$4:S22,$Q23&"|S|*")+1)) -> 事務用消耗品費|S|3 | T23: =IF(OR($F23="",$P23="支払なし",$R23=0,$Q23=""),"",$Q23&"|L|"&(COUNTIF(T$4:T22,$Q23&"|L|*")+1)) | U23: =IF(OR($F23="",$A23=""),"",MOD(MONTH($A23)-4,12)+1) -> 2
A24: 46154 | C24: 事務費負担金払込金 | E24: ４月分事務費負担金払込金と連合会交付金との相殺 | F24: 5366000 | G24: 5 | H24: =IF(G24=1,F24-I24-J24-K24,IF(G24=2,F24,0)) -> 0 | I24: =ROUND(IF(G24=1,F24*10/23,IF(G24=3,F24-J24-K24,IF(G24=4,F24,IF(G24=5,F24*10/11,IF(G24=7,F24*10/11,0))))),0) -> 4878182 | J24: =ROUND(IF(G24=1,F24/23,IF(G24=3,F24/12,IF(G24=5,F24-I24,IF(G24=8,F24,0)))),0) -> 487818 | K24: =ROUND(IF(G24=1,F24/23,IF(G24=3,F24/12,IF(G24=6,F24,IF(G24=7,F24-I24,0)))),0) -> 0 | L24: =IF(G24=6,F24,0) -> 0 | M24: =IF(F24="",0,MONTH(A24)) -> 5 | P24: 確認済 | Q24: =IF($F24="","",IFERROR(VLOOKUP($C24&"|"&$D24,科目表!$A$5:$B$200,2,FALSE),"※未登録")) -> 事務費負担金払込金 | R24: =IF($F24="","",$I24+$J24+$K24) -> 5366000 | S24: =IF(OR($F24="",$P24="支払なし",$H24=0,$Q24=""),"",$Q24&"|S|"&(COUNTIF(S$4:S23,$Q24&"|S|*")+1)) | T24: =IF(OR($F24="",$P24="支払なし",$R24=0,$Q24=""),"",$Q24&"|L|"&(COUNTIF(T$4:T23,$Q24&"|L|*")+1)) -> 事務費負担金払込金|L|1 | U24: =IF(OR($F24="",$A24=""),"",MOD(MONTH($A24)-4,12)+1) -> 2
A25: 46139 | C25: 負担金 | D25: 負担金 | E25: 共済短期・介護・子ども子育て負担金（4月月例分）長期 | F25: 22035 | G25: 3 | H25: =IF(G25=1,F25-I25-J25-K25,IF(G25=2,F25,0)) -> 0 | I25: =ROUND(IF(G25=1,F25*10/23,IF(G25=3,F25-J25-K25,IF(G25=4,F25,IF(G25=5,F25*10/11,IF(G25=7,F25*10/11,0))))),0) -> 18363 | J25: =ROUND(IF(G25=1,F25/23,IF(G25=3,F25/12,IF(G25=5,F25-I25,IF(G25=8,F25,0)))),0) -> 1836 | K25: =ROUND(IF(G25=1,F25/23,IF(G25=3,F25/12,IF(G25=6,F25,IF(G25=7,F25-I25,0)))),0) -> 1836 | L25: =IF(G25=6,F25,0) -> 0 | M25: =IF(F25="",0,MONTH(A25)) -> 4 | P25: 確認済 | Q25: =IF($F25="","",IFERROR(VLOOKUP($C25&"|"&$D25,科目表!$A$5:$B$200,2,FALSE),"※未登録")) -> 共済負担金等 | R25: =IF($F25="","",$I25+$J25+$K25) -> 22035 | S25: =IF(OR($F25="",$P25="支払なし",$H25=0,$Q25=""),"",$Q25&"|S|"&(COUNTIF(S$4:S24,$Q25&"|S|*")+1)) | T25: =IF(OR($F25="",$P25="支払なし",$R25=0,$Q25=""),"",$Q25&"|L|"&(COUNTIF(T$4:T24,$Q25&"|L|*")+1)) -> 共済負担金等|L|1 | U25: =IF(OR($F25="",$A25=""),"",MOD(MONTH($A25)-4,12)+1) -> 1
A26: 46139 | C26: 負担金 | D26: 負担金 | E26: 共済短期・介護・子ども子育て負担金（4月月例分）短期 | F26: 37074 | G26: 2 | H26: =IF(G26=1,F26-I26-J26-K26,IF(G26=2,F26,0)) -> 37074 | I26: =ROUND(IF(G26=1,F26*10/23,IF(G26=3,F26-J26-K26,IF(G26=4,F26,IF(G26=5,F26*10/11,IF(G26=7,F26*10/11,0))))),0) -> 0 | J26: =ROUND(IF(G26=1,F26/23,IF(G26=3,F26/12,IF(G26=5,F26-I26,IF(G26=8,F26,0)))),0) -> 0 | K26: =ROUND(IF(G26=1,F26/23,IF(G26=3,F26/12,IF(G26=6,F26,IF(G26=7,F26-I26,0)))),0) -> 0 | L26: =IF(G26=6,F26,0) -> 0 | M26: =IF(F26="",0,MONTH(A26)) -> 4 | P26: 確認済 | Q26: =IF($F26="","",IFERROR(VLOOKUP($C26&"|"&$D26,科目表!$A$5:$B$200,2,FALSE),"※未登録")) -> 共済負担金等 | R26: =IF($F26="","",$I26+$J26+$K26) -> 0 | S26: =IF(OR($F26="",$P26="支払なし",$H26=0,$Q26=""),"",$Q26&"|S|"&(COUNTIF(S$4:S25,$Q26&"|S|*")+1)) -> 共済負担金等|S|1 | T26: =IF(OR($F26="",$P26="支払なし",$R26=0,$Q26=""),"",$Q26&"|L|"&(COUNTIF(T$4:T25,$Q26&"|L|*")+1)) | U26: =IF(OR($F26="",$A26=""),"",MOD(MONTH($A26)-4,12)+1) -> 1
A27: 46153 | C27: 事務費 | D27: 送金料 | E27: 振込手数料（広銀）４月分 長期分 | F27: 18493 | G27: 3 | H27: =IF(G27=1,F27-I27-J27-K27,IF(G27=2,F27,0)) -> 0 | I27: =ROUND(IF(G27=1,F27*10/23,IF(G27=3,F27-J27-K27,IF(G27=4,F27,IF(G27=5,F27*10/11,IF(G27=7,F27*10/11,0))))),0) -> 15411 | J27: =ROUND(IF(G27=1,F27/23,IF(G27=3,F27/12,IF(G27=5,F27-I27,IF(G27=8,F27,0)))),0) -> 1541 | K27: =ROUND(IF(G27=1,F27/23,IF(G27=3,F27/12,IF(G27=6,F27,IF(G27=7,F27-I27,0)))),0) -> 1541 | L27: =IF(G27=6,F27,0) -> 0 | M27: =IF(F27="",0,MONTH(A27)) -> 5 | P27: 確認済 | Q27: =IF($F27="","",IFERROR(VLOOKUP($C27&"|"&$D27,科目表!$A$5:$B$200,2,FALSE),"※未登録")) -> 送金料 | R27: =IF($F27="","",$I27+$J27+$K27) -> 18493 | S27: =IF(OR($F27="",$P27="支払なし",$H27=0,$Q27=""),"",$Q27&"|S|"&(COUNTIF(S$4:S26,$Q27&"|S|*")+1)) | T27: =IF(OR($F27="",$P27="支払なし",$R27=0,$Q27=""),"",$Q27&"|L|"&(COUNTIF(T$4:T26,$Q27&"|L|*")+1)) -> 送金料|L|1 | U27: =IF(OR($F27="",$A27=""),"",MOD(MONTH($A27)-4,12)+1) -> 2
A28: 46153 | C28: 事務費 | D28: 送金料 | E28: 振込手数料（広銀）４月分 短期分 | F28: 139883 | G28: 2 | H28: =IF(G28=1,F28-I28-J28-K28,IF(G28=2,F28,0)) -> 139883 | I28: =ROUND(IF(G28=1,F28*10/23,IF(G28=3,F28-J28-K28,IF(G28=4,F28,IF(G28=5,F28*10/11,IF(G28=7,F28*10/11,0))))),0) -> 0 | J28: =ROUND(IF(G28=1,F28/23,IF(G28=3,F28/12,IF(G28=5,F28-I28,IF(G28=8,F28,0)))),0) -> 0 | K28: =ROUND(IF(G28=1,F28/23,IF(G28=3,F28/12,IF(G28=6,F28,IF(G28=7,F28-I28,0)))),0) -> 0 | L28: =IF(G28=6,F28,0) -> 0 | M28: =IF(F28="",0,MONTH(A28)) -> 5 | P28: 確認済 | Q28: =IF($F28="","",IFERROR(VLOOKUP($C28&"|"&$D28,科目表!$A$5:$B$200,2,FALSE),"※未登録")) -> 送金料 | R28: =IF($F28="","",$I28+$J28+$K28) -> 0 | S28: =IF(OR($F28="",$P28="支払なし",$H28=0,$Q28=""),"",$Q28&"|S|"&(COUNTIF(S$4:S27,$Q28&"|S|*")+1)) -> 送金料|S|1 | T28: =IF(OR($F28="",$P28="支払なし",$R28=0,$Q28=""),"",$Q28&"|L|"&(COUNTIF(T$4:T27,$Q28&"|L|*")+1)) | U28: =IF(OR($F28="",$A28=""),"",MOD(MONTH($A28)-4,12)+1) -> 2
A29: 46171 | C29: 事務費 | D29: 事務用消耗品費 | E29: ダイヤルロック UNK-02 7個 他 | F29: 14518 | G29: 2 | H29: =IF(G29=1,F29-I29-J29-K29,IF(G29=2,F29,0)) -> 14518 | I29: =ROUND(IF(G29=1,F29*10/23,IF(G29=3,F29-J29-K29,IF(G29=4,F29,IF(G29=5,F29*10/11,IF(G29=7,F29*10/11,0))))),0) -> 0 | J29: =ROUND(IF(G29=1,F29/23,IF(G29=3,F29/12,IF(G29=5,F29-I29,IF(G29=8,F29,0)))),0) -> 0 | K29: =ROUND(IF(G29=1,F29/23,IF(G29=3,F29/12,IF(G29=6,F29,IF(G29=7,F29-I29,0)))),0) -> 0 | L29: =IF(G29=6,F29,0) -> 0 | M29: =IF(F29="",0,MONTH(A29)) -> 5 | P29: 確認済 | Q29: =IF($F29="","",IFERROR(VLOOKUP($C29&"|"&$D29,科目表!$A$5:$B$200,2,FALSE),"※未登録")) -> 事務用消耗品費 | R29: =IF($F29="","",$I29+$J29+$K29) -> 0 | S29: =IF(OR($F29="",$P29="支払なし",$H29=0,$Q29=""),"",$Q29&"|S|"&(COUNTIF(S$4:S28,$Q29&"|S|*")+1)) -> 事務用消耗品費|S|4 | T29: =IF(OR($F29="",$P29="支払なし",$R29=0,$Q29=""),"",$Q29&"|L|"&(COUNTIF(T$4:T28,$Q29&"|L|*")+1)) | U29: =IF(OR($F29="",$A29=""),"",MOD(MONTH($A29)-4,12)+1) -> 2
A30: 46171 | C30: 賃借料 | E30: パソコン（業務経理用）４月分 | F30: 5060 | G30: 2 | H30: =IF(G30=1,F30-I30-J30-K30,IF(G30=2,F30,0)) -> 5060 | I30: =ROUND(IF(G30=1,F30*10/23,IF(G30=3,F30-J30-K30,IF(G30=4,F30,IF(G30=5,F30*10/11,IF(G30=7,F30*10/11,0))))),0) -> 0 | J30: =ROUND(IF(G30=1,F30/23,IF(G30=3,F30/12,IF(G30=5,F30-I30,IF(G30=8,F30,0)))),0) -> 0 | K30: =ROUND(IF(G30=1,F30/23,IF(G30=3,F30/12,IF(G30=6,F30,IF(G30=7,F30-I30,0)))),0) -> 0 | L30: =IF(G30=6,F30,0) -> 0 | M30: =IF(F30="",0,MONTH(A30)) -> 5 | P30: 確認済 | Q30: =IF($F30="","",IFERROR(VLOOKUP($C30&"|"&$D30,科目表!$A$5:$B$200,2,FALSE),"※未登録")) -> 賃借料 | R30: =IF($F30="","",$I30+$J30+$K30) -> 0 | S30: =IF(OR($F30="",$P30="支払なし",$H30=0,$Q30=""),"",$Q30&"|S|"&(COUNTIF(S$4:S29,$Q30&"|S|*")+1)) -> 賃借料|S|1 | T30: =IF(OR($F30="",$P30="支払なし",$R30=0,$Q30=""),"",$Q30&"|L|"&(COUNTIF(T$4:T29,$Q30&"|L|*")+1)) | U30: =IF(OR($F30="",$A30=""),"",MOD(MONTH($A30)-4,12)+1) -> 2
A31: 46157 | C31: 賃金 | E31: 臨時職員賃金４月分 天畠吏梨外1名分（短期１００％） | F31: 425880 | G31: 2 | H31: =IF(G31=1,F31-I31-J31-K31,IF(G31=2,F31,0)) -> 425880 | I31: =ROUND(IF(G31=1,F31*10/23,IF(G31=3,F31-J31-K31,IF(G31=4,F31,IF(G31=5,F31*10/11,IF(G31=7,F31*10/11,0))))),0) -> 0 | J31: =ROUND(IF(G31=1,F31/23,IF(G31=3,F31/12,IF(G31=5,F31-I31,IF(G31=8,F31,0)))),0) -> 0 | K31: =ROUND(IF(G31=1,F31/23,IF(G31=3,F31/12,IF(G31=6,F31,IF(G31=7,F31-I31,0)))),0) -> 0 | L31: =IF(G31=6,F31,0) -> 0 | M31: =IF(F31="",0,MONTH(A31)) -> 5 | P31: 確認済 | Q31: =IF($F31="","",IFERROR(VLOOKUP($C31&"|"&$D31,科目表!$A$5:$B$200,2,FALSE),"※未登録")) -> 賃金 | R31: =IF($F31="","",$I31+$J31+$K31) -> 0 | S31: =IF(OR($F31="",$P31="支払なし",$H31=0,$Q31=""),"",$Q31&"|S|"&(COUNTIF(S$4:S30,$Q31&"|S|*")+1)) -> 賃金|S|1 | T31: =IF(OR($F31="",$P31="支払なし",$R31=0,$Q31=""),"",$Q31&"|L|"&(COUNTIF(T$4:T30,$Q31&"|L|*")+1)) | U31: =IF(OR($F31="",$A31=""),"",MOD(MONTH($A31)-4,12)+1) -> 2
A32: 46162 | C32: 委託費 | E32: 社会保障等制度 中間サーバー等運営負担金 | F32: 1798068 | G32: 2 | H32: =IF(G32=1,F32-I32-J32-K32,IF(G32=2,F32,0)) -> 1798068 | I32: =ROUND(IF(G32=1,F32*10/23,IF(G32=3,F32-J32-K32,IF(G32=4,F32,IF(G32=5,F32*10/11,IF(G32=7,F32*10/11,0))))),0) -> 0 | J32: =ROUND(IF(G32=1,F32/23,IF(G32=3,F32/12,IF(G32=5,F32-I32,IF(G32=8,F32,0)))),0) -> 0 | K32: =ROUND(IF(G32=1,F32/23,IF(G32=3,F32/12,IF(G32=6,F32,IF(G32=7,F32-I32,0)))),0) -> 0 | L32: =IF(G32=6,F32,0) -> 0 | M32: =IF(F32="",0,MONTH(A32)) -> 5 | P32: 確認済 | Q32: =IF($F32="","",IFERROR(VLOOKUP($C32&"|"&$D32,科目表!$A$5:$B$200,2,FALSE),"※未登録")) -> 委託費 | R32: =IF($F32="","",$I32+$J32+$K32) -> 0 | S32: =IF(OR($F32="",$P32="支払なし",$H32=0,$Q32=""),"",$Q32&"|S|"&(COUNTIF(S$4:S31,$Q32&"|S|*")+1)) -> 委託費|S|3 | T32: =IF(OR($F32="",$P32="支払なし",$R32=0,$Q32=""),"",$Q32&"|L|"&(COUNTIF(T$4:T31,$Q32&"|L|*")+1)) | U32: =IF(OR($F32="",$A32=""),"",MOD(MONTH($A32)-4,12)+1) -> 2
A33: 46171 | C33: 事務費 | D33: 送金料 | E33: ゆうちょ銀行手数料（４月分）短期 | F33: 109019 | G33: 2 | H33: =IF(G33=1,F33-I33-J33-K33,IF(G33=2,F33,0)) -> 109019 | I33: =ROUND(IF(G33=1,F33*10/23,IF(G33=3,F33-J33-K33,IF(G33=4,F33,IF(G33=5,F33*10/11,IF(G33=7,F33*10/11,0))))),0) -> 0 | J33: =ROUND(IF(G33=1,F33/23,IF(G33=3,F33/12,IF(G33=5,F33-I33,IF(G33=8,F33,0)))),0) -> 0 | K33: =ROUND(IF(G33=1,F33/23,IF(G33=3,F33/12,IF(G33=6,F33,IF(G33=7,F33-I33,0)))),0) -> 0 | L33: =IF(G33=6,F33,0) -> 0 | M33: =IF(F33="",0,MONTH(A33)) -> 5 | P33: 確認済 | Q33: =IF($F33="","",IFERROR(VLOOKUP($C33&"|"&$D33,科目表!$A$5:$B$200,2,FALSE),"※未登録")) -> 送金料 | R33: =IF($F33="","",$I33+$J33+$K33) -> 0 | S33: =IF(OR($F33="",$P33="支払なし",$H33=0,$Q33=""),"",$Q33&"|S|"&(COUNTIF(S$4:S32,$Q33&"|S|*")+1)) -> 送金料|S|2 | T33: =IF(OR($F33="",$P33="支払なし",$R33=0,$Q33=""),"",$Q33&"|L|"&(COUNTIF(T$4:T32,$Q33&"|L|*")+1)) | U33: =IF(OR($F33="",$A33=""),"",MOD(MONTH($A33)-4,12)+1) -> 2
A34: 46171 | C34: 事務費 | D34: 雑費 | E34: ゆうちょ銀行振替口座残高証明（４月分）短期 | F34: 550 | G34: 2 | H34: =IF(G34=1,F34-I34-J34-K34,IF(G34=2,F34,0)) -> 550 | I34: =ROUND(IF(G34=1,F34*10/23,IF(G34=3,F34-J34-K34,IF(G34=4,F34,IF(G34=5,F34*10/11,IF(G34=7,F34*10/11,0))))),0) -> 0 | J34: =ROUND(IF(G34=1,F34/23,IF(G34=3,F34/12,IF(G34=5,F34-I34,IF(G34=8,F34,0)))),0) -> 0 | K34: =ROUND(IF(G34=1,F34/23,IF(G34=3,F34/12,IF(G34=6,F34,IF(G34=7,F34-I34,0)))),0) -> 0 | L34: =IF(G34=6,F34,0) -> 0 | M34: =IF(F34="",0,MONTH(A34)) -> 5 | P34: 確認済 | Q34: =IF($F34="","",IFERROR(VLOOKUP($C34&"|"&$D34,科目表!$A$5:$B$200,2,FALSE),"※未登録")) -> 事務費・雑費 | R34: =IF($F34="","",$I34+$J34+$K34) -> 0 | S34: =IF(OR($F34="",$P34="支払なし",$H34=0,$Q34=""),"",$Q34&"|S|"&(COUNTIF(S$4:S33,$Q34&"|S|*")+1)) -> 事務費・雑費|S|2 | T34: =IF(OR($F34="",$P34="支払なし",$R34=0,$Q34=""),"",$Q34&"|L|"&(COUNTIF(T$4:T33,$Q34&"|L|*")+1)) | U34: =IF(OR($F34="",$A34=""),"",MOD(MONTH($A34)-4,12)+1) -> 2
A35: 46163 | C35: 職員給与 | D35: 非常勤職員手当 | E35: ５月分給与（長期分） | F35: 380800 | G35: 3 | H35: =IF(G35=1,F35-I35-J35-K35,IF(G35=2,F35,0)) -> 0 | I35: =ROUND(IF(G35=1,F35*10/23,IF(G35=3,F35-J35-K35,IF(G35=4,F35,IF(G35=5,F35*10/11,IF(G35=7,F35*10/11,0))))),0) -> 317334 | J35: =ROUND(IF(G35=1,F35/23,IF(G35=3,F35/12,IF(G35=5,F35-I35,IF(G35=8,F35,0)))),0) -> 31733 | K35: =ROUND(IF(G35=1,F35/23,IF(G35=3,F35/12,IF(G35=6,F35,IF(G35=7,F35-I35,0)))),0) -> 31733 | L35: =IF(G35=6,F35,0) -> 0 | M35: =IF(F35="",0,MONTH(A35)) -> 5 | P35: 確認済 | Q35: =IF($F35="","",IFERROR(VLOOKUP($C35&"|"&$D35,科目表!$A$5:$B$200,2,FALSE),"※未登録")) -> 非常勤職員手当 | R35: =IF($F35="","",$I35+$J35+$K35) -> 380800 | S35: =IF(OR($F35="",$P35="支払なし",$H35=0,$Q35=""),"",$Q35&"|S|"&(COUNTIF(S$4:S34,$Q35&"|S|*")+1)) | T35: =IF(OR($F35="",$P35="支払なし",$R35=0,$Q35=""),"",$Q35&"|L|"&(COUNTIF(T$4:T34,$Q35&"|L|*")+1)) -> 非常勤職員手当|L|2 | U35: =IF(OR($F35="",$A35=""),"",MOD(MONTH($A35)-4,12)+1) -> 2
A36: 46163 | C36: 職員給与 | D36: 非常勤職員手当 | E36: ５月分給与（短期分） | F36: 248436 | G36: 2 | H36: =IF(G36=1,F36-I36-J36-K36,IF(G36=2,F36,0)) -> 248436 | I36: =ROUND(IF(G36=1,F36*10/23,IF(G36=3,F36-J36-K36,IF(G36=4,F36,IF(G36=5,F36*10/11,IF(G36=7,F36*10/11,0))))),0) -> 0 | J36: =ROUND(IF(G36=1,F36/23,IF(G36=3,F36/12,IF(G36=5,F36-I36,IF(G36=8,F36,0)))),0) -> 0 | K36: =ROUND(IF(G36=1,F36/23,IF(G36=3,F36/12,IF(G36=6,F36,IF(G36=7,F36-I36,0)))),0) -> 0 | L36: 0 | M36: =IF(F36="",0,MONTH(A36)) -> 5 | P36: 確認済 | Q36: =IF($F36="","",IFERROR(VLOOKUP($C36&"|"&$D36,科目表!$A$5:$B$200,2,FALSE),"※未登録")) -> 非常勤職員手当 | R36: =IF($F36="","",$I36+$J36+$K36) -> 0 | S36: =IF(OR($F36="",$P36="支払なし",$H36=0,$Q36=""),"",$Q36&"|S|"&(COUNTIF(S$4:S35,$Q36&"|S|*")+1)) -> 非常勤職員手当|S|2 | T36: =IF(OR($F36="",$P36="支払なし",$R36=0,$Q36=""),"",$Q36&"|L|"&(COUNTIF(T$4:T35,$Q36&"|L|*")+1)) | U36: =IF(OR($F36="",$A36=""),"",MOD(MONTH($A36)-4,12)+1) -> 2
A37: 46163 | C37: 負担金 | D37: 互助会費 | E37: 助成金（５月長期分） | F37: 466 | G37: 3 | H37: =IF(G37=1,F37-I37-J37-K37,IF(G37=2,F37,0)) -> 0 | I37: =ROUND(IF(G37=1,F37*10/23,IF(G37=3,F37-J37-K37,IF(G37=4,F37,IF(G37=5,F37*10/11,IF(G37=7,F37*10/11,0))))),0) -> 388 | J37: =ROUND(IF(G37=1,F37/23,IF(G37=3,F37/12,IF(G37=5,F37-I37,IF(G37=8,F37,0)))),0) -> 39 | K37: =ROUND(IF(G37=1,F37/23,IF(G37=3,F37/12,IF(G37=6,F37,IF(G37=7,F37-I37,0)))),0) -> 39 | L37: =IF(G37=6,F37,0) -> 0 | M37: =IF(F37="",0,MONTH(A37)) -> 5 | P37: 確認済 | Q37: =IF($F37="","",IFERROR(VLOOKUP($C37&"|"&$D37,科目表!$A$5:$B$200,2,FALSE),"※未登録")) -> 互助会費 | R37: =IF($F37="","",$I37+$J37+$K37) -> 466 | S37: =IF(OR($F37="",$P37="支払なし",$H37=0,$Q37=""),"",$Q37&"|S|"&(COUNTIF(S$4:S36,$Q37&"|S|*")+1)) | T37: =IF(OR($F37="",$P37="支払なし",$R37=0,$Q37=""),"",$Q37&"|L|"&(COUNTIF(T$4:T36,$Q37&"|L|*")+1)) -> 互助会費|L|2 | U37: =IF(OR($F37="",$A37=""),"",MOD(MONTH($A37)-4,12)+1) -> 2
A38: 46163 | C38: 負担金 | D38: 互助会費 | E38: 助成金（５月短期分） | F38: 240 | G38: 2 | H38: =IF(G38=1,F38-I38-J38-K38,IF(G38=2,F38,0)) -> 240 | I38: =ROUND(IF(G38=1,F38*10/23,IF(G38=3,F38-J38-K38,IF(G38=4,F38,IF(G38=5,F38*10/11,IF(G38=7,F38*10/11,0))))),0) -> 0 | J38: =ROUND(IF(G38=1,F38/23,IF(G38=3,F38/12,IF(G38=5,F38-I38,IF(G38=8,F38,0)))),0) -> 0 | K38: =ROUND(IF(G38=1,F38/23,IF(G38=3,F38/12,IF(G38=6,F38,IF(G38=7,F38-I38,0)))),0) -> 0 | L38: =IF(G38=6,F38,0) -> 0 | M38: =IF(F38="",0,MONTH(A38)) -> 5 | P38: 確認済 | Q38: =IF($F38="","",IFERROR(VLOOKUP($C38&"|"&$D38,科目表!$A$5:$B$200,2,FALSE),"※未登録")) -> 互助会費 | R38: =IF($F38="","",$I38+$J38+$K38) -> 0 | S38: =IF(OR($F38="",$P38="支払なし",$H38=0,$Q38=""),"",$Q38&"|S|"&(COUNTIF(S$4:S37,$Q38&"|S|*")+1)) -> 互助会費|S|2 | T38: =IF(OR($F38="",$P38="支払なし",$R38=0,$Q38=""),"",$Q38&"|L|"&(COUNTIF(T$4:T37,$Q38&"|L|*")+1)) | U38: =IF(OR($F38="",$A38=""),"",MOD(MONTH($A38)-4,12)+1) -> 2
A39: 46162 | C39: 委託費 | E39: レセプト電子データ提供料（２月診療分） | F39: 61859 | G39: 2 | H39: =IF(G39=1,F39-I39-J39-K39,IF(G39=2,F39,0)) -> 61859 | I39: =ROUND(IF(G39=1,F39*10/23,IF(G39=3,F39-J39-K39,IF(G39=4,F39,IF(G39=5,F39*10/11,IF(G39=7,F39*10/11,0))))),0) -> 0 | J39: =ROUND(IF(G39=1,F39/23,IF(G39=3,F39/12,IF(G39=5,F39-I39,IF(G39=8,F39,0)))),0) -> 0 | K39: =ROUND(IF(G39=1,F39/23,IF(G39=3,F39/12,IF(G39=6,F39,IF(G39=7,F39-I39,0)))),0) -> 0 | L39: =IF(G39=6,F39,0) -> 0 | M39: =IF(F39="",0,MONTH(A39)) -> 5 | P39: 確認済 | Q39: =IF($F39="","",IFERROR(VLOOKUP($C39&"|"&$D39,科目表!$A$5:$B$200,2,FALSE),"※未登録")) -> 委託費 | R39: =IF($F39="","",$I39+$J39+$K39) -> 0 | S39: =IF(OR($F39="",$P39="支払なし",$H39=0,$Q39=""),"",$Q39&"|S|"&(COUNTIF(S$4:S38,$Q39&"|S|*")+1)) -> 委託費|S|4 | T39: =IF(OR($F39="",$P39="支払なし",$R39=0,$Q39=""),"",$Q39&"|L|"&(COUNTIF(T$4:T38,$Q39&"|L|*")+1)) | U39: =IF(OR($F39="",$A39=""),"",MOD(MONTH($A39)-4,12)+1) -> 2
A40: 45065 | C40: 委託費 | E40: 社会保障等制度 中間サーバー等運営負担金 | F40: 661740 | G40: 2 | H40: =IF(G40=1,F40-I40-J40-K40,IF(G40=2,F40,0)) -> 661740 | I40: =ROUND(IF(G40=1,F40*10/23,IF(G40=3,F40-J40-K40,IF(G40=4,F40,IF(G40=5,F40*10/11,IF(G40=7,F40*10/11,0))))),0) -> 0 | J40: =ROUND(IF(G40=1,F40/23,IF(G40=3,F40/12,IF(G40=5,F40-I40,IF(G40=8,F40,0)))),0) -> 0 | K40: =ROUND(IF(G40=1,F40/23,IF(G40=3,F40/12,IF(G40=6,F40,IF(G40=7,F40-I40,0)))),0) -> 0 | L40: =IF(G40=6,F40,0) -> 0 | M40: =IF(F40="",0,MONTH(A40)) -> 5 | P40: 昨年実績 | Q40: =IF($F40="","",IFERROR(VLOOKUP($C40&"|"&$D40,科目表!$A$5:$B$200,2,FALSE),"※未登録")) -> 委託費 | R40: =IF($F40="","",$I40+$J40+$K40) -> 0 | S40: =IF(OR($F40="",$P40="支払なし",$H40=0,$Q40=""),"",$Q40&"|S|"&(COUNTIF(S$4:S39,$Q40&"|S|*")+1)) -> 委託費|S|5 | T40: =IF(OR($F40="",$P40="支払なし",$R40=0,$Q40=""),"",$Q40&"|L|"&(COUNTIF(T$4:T39,$Q40&"|L|*")+1)) | U40: =IF(OR($F40="",$A40=""),"",MOD(MONTH($A40)-4,12)+1) -> 2
A41: 44336 | C41: 事務費 | D41: 通信運搬費 | E41: 電話料金（４月使用・５月請求分） | F41: 5407 | G41: 2 | H41: =IF(G41=1,F41-I41-J41-K41,IF(G41=2,F41,0)) -> 5407 | I41: =ROUND(IF(G41=1,F41*10/23,IF(G41=3,F41-J41-K41,IF(G41=4,F41,IF(G41=5,F41*10/11,IF(G41=7,F41*10/11,0))))),0) -> 0 | J41: =ROUND(IF(G41=1,F41/23,IF(G41=3,F41/12,IF(G41=5,F41-I41,IF(G41=8,F41,0)))),0) -> 0 | K41: =ROUND(IF(G41=1,F41/23,IF(G41=3,F41/12,IF(G41=6,F41,IF(G41=7,F41-I41,0)))),0) -> 0 | L41: =IF(G41=6,F41,0) -> 0 | M41: =IF(F41="",0,MONTH(A41)) -> 5 | P41: 昨年実績 | Q41: =IF($F41="","",IFERROR(VLOOKUP($C41&"|"&$D41,科目表!$A$5:$B$200,2,FALSE),"※未登録")) -> 通信運搬費 | R41: =IF($F41="","",$I41+$J41+$K41) -> 0 | S41: =IF(OR($F41="",$P41="支払なし",$H41=0,$Q41=""),"",$Q41&"|S|"&(COUNTIF(S$4:S40,$Q41&"|S|*")+1)) -> 通信運搬費|S|2 | T41: =IF(OR($F41="",$P41="支払なし",$R41=0,$Q41=""),"",$Q41&"|L|"&(COUNTIF(T$4:T40,$Q41&"|L|*")+1)) | U41: =IF(OR($F41="",$A41=""),"",MOD(MONTH($A41)-4,12)+1) -> 2
A42: 45807 | C42: 事務費 | D42: 事務用消耗品費 | E42: ポストイット ５００１SS-K 2個 他 | F42: 19730 | G42: 2 | H42: =IF(G42=1,F42-I42-J42-K42,IF(G42=2,F42,0)) -> 19730 | I42: =ROUND(IF(G42=1,F42*10/23,IF(G42=3,F42-J42-K42,IF(G42=4,F42,IF(G42=5,F42*10/11,IF(G42=7,F42*10/11,0))))),0) -> 0 | J42: =ROUND(IF(G42=1,F42/23,IF(G42=3,F42/12,IF(G42=5,F42-I42,IF(G42=8,F42,0)))),0) -> 0 | K42: =ROUND(IF(G42=1,F42/23,IF(G42=3,F42/12,IF(G42=6,F42,IF(G42=7,F42-I42,0)))),0) -> 0 | L42: =IF(G42=6,F42,0) -> 0 | M42: =IF(F42="",0,MONTH(A42)) -> 5 | P42: 昨年実績 | Q42: =IF($F42="","",IFERROR(VLOOKUP($C42&"|"&$D42,科目表!$A$5:$B$200,2,FALSE),"※未登録")) -> 事務用消耗品費 | R42: =IF($F42="","",$I42+$J42+$K42) -> 0 | S42: =IF(OR($F42="",$P42="支払なし",$H42=0,$Q42=""),"",$Q42&"|S|"&(COUNTIF(S$4:S41,$Q42&"|S|*")+1)) -> 事務用消耗品費|S|5 | T42: =IF(OR($F42="",$P42="支払なし",$R42=0,$Q42=""),"",$Q42&"|L|"&(COUNTIF(T$4:T41,$Q42&"|L|*")+1)) | U42: =IF(OR($F42="",$A42=""),"",MOD(MONTH($A42)-4,12)+1) -> 2
A43: 45793 | C43: 事務費 | D43: 図書印刷費 | E43: 短期給付決定通知書 ３，０００枚 | F43: 128700 | G43: 2 | H43: =IF(G43=1,F43-I43-J43-K43,IF(G43=2,F43,0)) -> 128700 | I43: =ROUND(IF(G43=1,F43*10/23,IF(G43=3,F43-J43-K43,IF(G43=4,F43,IF(G43=5,F43*10/11,IF(G43=7,F43*10/11,0))))),0) -> 0 | J43: =ROUND(IF(G43=1,F43/23,IF(G43=3,F43/12,IF(G43=5,F43-I43,IF(G43=8,F43,0)))),0) -> 0 | K43: =ROUND(IF(G43=1,F43/23,IF(G43=3,F43/12,IF(G43=6,F43,IF(G43=7,F43-I43,0)))),0) -> 0 | L43: =IF(G43=6,F43,0) -> 0 | M43: =IF(F43="",0,MONTH(A43)) -> 5 | P43: 昨年実績 | Q43: =IF($F43="","",IFERROR(VLOOKUP($C43&"|"&$D43,科目表!$A$5:$B$200,2,FALSE),"※未登録")) -> 図書印刷費 | R43: =IF($F43="","",$I43+$J43+$K43) -> 0 | S43: =IF(OR($F43="",$P43="支払なし",$H43=0,$Q43=""),"",$Q43&"|S|"&(COUNTIF(S$4:S42,$Q43&"|S|*")+1)) -> 図書印刷費|S|2 | T43: =IF(OR($F43="",$P43="支払なし",$R43=0,$Q43=""),"",$Q43&"|L|"&(COUNTIF(T$4:T42,$Q43&"|L|*")+1)) | U43: =IF(OR($F43="",$A43=""),"",MOD(MONTH($A43)-4,12)+1) -> 2
A44: 45786 | C44: 事務費 | D44: 事務用消耗品費 | E44: トナーカートリッジＬＰＢ３Ｔ２７ 2個 | F44: 10560 | G44: 3 | H44: =IF(G44=1,F44-I44-J44-K44,IF(G44=2,F44,0)) -> 0 | I44: =ROUND(IF(G44=1,F44*10/23,IF(G44=3,F44-J44-K44,IF(G44=4,F44,IF(G44=5,F44*10/11,IF(G44=7,F44*10/11,0))))),0) -> 8800 | J44: =ROUND(IF(G44=1,F44/23,IF(G44=3,F44/12,IF(G44=5,F44-I44,IF(G44=8,F44,0)))),0) -> 880 | K44: =ROUND(IF(G44=1,F44/23,IF(G44=3,F44/12,IF(G44=6,F44,IF(G44=7,F44-I44,0)))),0) -> 880 | L44: =IF(G44=6,F44,0) -> 0 | M44: =IF(F44="",0,MONTH(A44)) -> 5 | P44: 昨年実績 | Q44: =IF($F44="","",IFERROR(VLOOKUP($C44&"|"&$D44,科目表!$A$5:$B$200,2,FALSE),"※未登録")) -> 事務用消耗品費 | R44: =IF($F44="","",$I44+$J44+$K44) -> 10560 | S44: =IF(OR($F44="",$P44="支払なし",$H44=0,$Q44=""),"",$Q44&"|S|"&(COUNTIF(S$4:S43,$Q44&"|S|*")+1)) | T44: =IF(OR($F44="",$P44="支払なし",$R44=0,$Q44=""),"",$Q44&"|L|"&(COUNTIF(T$4:T43,$Q44&"|L|*")+1)) -> 事務用消耗品費|L|3 | U44: =IF(OR($F44="",$A44=""),"",MOD(MONTH($A44)-4,12)+1) -> 2
A45: 46162 | C45: 賃借料 | E45: 統合管理端末リース料（４月分） | F45: 12738 | G45: 2 | H45: =IF(G45=1,F45-I45-J45-K45,IF(G45=2,F45,0)) -> 12738 | I45: =ROUND(IF(G45=1,F45*10/23,IF(G45=3,F45-J45-K45,IF(G45=4,F45,IF(G45=5,F45*10/11,IF(G45=7,F45*10/11,0))))),0) -> 0 | J45: =ROUND(IF(G45=1,F45/23,IF(G45=3,F45/12,IF(G45=5,F45-I45,IF(G45=8,F45,0)))),0) -> 0 | K45: =ROUND(IF(G45=1,F45/23,IF(G45=3,F45/12,IF(G45=6,F45,IF(G45=7,F45-I45,0)))),0) -> 0 | L45: =IF(G45=6,F45,0) -> 0 | M45: =IF(F45="",0,MONTH(A45)) -> 5 | P45: 確認済 | Q45: =IF($F45="","",IFERROR(VLOOKUP($C45&"|"&$D45,科目表!$A$5:$B$200,2,FALSE),"※未登録")) -> 賃借料 | R45: =IF($F45="","",$I45+$J45+$K45) -> 0 | S45: =IF(OR($F45="",$P45="支払なし",$H45=0,$Q45=""),"",$Q45&"|S|"&(COUNTIF(S$4:S44,$Q45&"|S|*")+1)) -> 賃借料|S|2 | T45: =IF(OR($F45="",$P45="支払なし",$R45=0,$Q45=""),"",$Q45&"|L|"&(COUNTIF(T$4:T44,$Q45&"|L|*")+1)) | U45: =IF(OR($F45="",$A45=""),"",MOD(MONTH($A45)-4,12)+1) -> 2
A46: 44347 | C46: 委託費 | E46: 短期給付個人番号管理システム端末保守サービス（４月分） | F46: 385 | G46: 2 | H46: =IF(G46=1,F46-I46-J46-K46,IF(G46=2,F46,0)) -> 385 | I46: =ROUND(IF(G46=1,F46*10/23,IF(G46=3,F46-J46-K46,IF(G46=4,F46,IF(G46=5,F46*10/11,IF(G46=7,F46*10/11,0))))),0) -> 0 | J46: =ROUND(IF(G46=1,F46/23,IF(G46=3,F46/12,IF(G46=5,F46-I46,IF(G46=8,F46,0)))),0) -> 0 | K46: =ROUND(IF(G46=1,F46/23,IF(G46=3,F46/12,IF(G46=6,F46,IF(G46=7,F46-I46,0)))),0) -> 0 | L46: =IF(G46=6,F46,0) -> 0 | M46: =IF(F46="",0,MONTH(A46)) -> 5 | P46: 昨年実績 | Q46: =IF($F46="","",IFERROR(VLOOKUP($C46&"|"&$D46,科目表!$A$5:$B$200,2,FALSE),"※未登録")) -> 委託費 | R46: =IF($F46="","",$I46+$J46+$K46) -> 0 | S46: =IF(OR($F46="",$P46="支払なし",$H46=0,$Q46=""),"",$Q46&"|S|"&(COUNTIF(S$4:S45,$Q46&"|S|*")+1)) -> 委託費|S|6 | T46: =IF(OR($F46="",$P46="支払なし",$R46=0,$Q46=""),"",$Q46&"|L|"&(COUNTIF(T$4:T45,$Q46&"|L|*")+1)) | U46: =IF(OR($F46="",$A46=""),"",MOD(MONTH($A46)-4,12)+1) -> 2
A47: 46162 | C47: 委託費 | E47: 統合管理端末保守料（４月～３月分） | F47: 149050 | G47: 2 | H47: =IF(G47=1,F47-I47-J47-K47,IF(G47=2,F47,0)) -> 149050 | I47: =ROUND(IF(G47=1,F47*10/23,IF(G47=3,F47-J47-K47,IF(G47=4,F47,IF(G47=5,F47*10/11,IF(G47=7,F47*10/11,0))))),0) -> 0 | J47: =ROUND(IF(G47=1,F47/23,IF(G47=3,F47/12,IF(G47=5,F47-I47,IF(G47=8,F47,0)))),0) -> 0 | K47: =ROUND(IF(G47=1,F47/23,IF(G47=3,F47/12,IF(G47=6,F47,IF(G47=7,F47-I47,0)))),0) -> 0 | L47: =IF(G47=6,F47,0) -> 0 | M47: =IF(F47="",0,MONTH(A47)) -> 5 | P47: 確認済 | Q47: =IF($F47="","",IFERROR(VLOOKUP($C47&"|"&$D47,科目表!$A$5:$B$200,2,FALSE),"※未登録")) -> 委託費 | R47: =IF($F47="","",$I47+$J47+$K47) -> 0 | S47: =IF(OR($F47="",$P47="支払なし",$H47=0,$Q47=""),"",$Q47&"|S|"&(COUNTIF(S$4:S46,$Q47&"|S|*")+1)) -> 委託費|S|7 | T47: =IF(OR($F47="",$P47="支払なし",$R47=0,$Q47=""),"",$Q47&"|L|"&(COUNTIF(T$4:T46,$Q47&"|L|*")+1)) | U47: =IF(OR($F47="",$A47=""),"",MOD(MONTH($A47)-4,12)+1) -> 2
A48: 46142 | C48: 事務費 | D48: 図書印刷費 | E48: 角２封筒エルコン付き クラフト８５ｇ枠付 ５，５００枚 | F48: 99220 | G48: 2 | H48: =IF(G48=1,F48-I48-J48-K48,IF(G48=2,F48,0)) -> 99220 | I48: =ROUND(IF(G48=1,F48*10/23,IF(G48=3,F48-J48-K48,IF(G48=4,F48,IF(G48=5,F48*10/11,IF(G48=7,F48*10/11,0))))),0) -> 0 | J48: =ROUND(IF(G48=1,F48/23,IF(G48=3,F48/12,IF(G48=5,F48-I48,IF(G48=8,F48,0)))),0) -> 0 | K48: =ROUND(IF(G48=1,F48/23,IF(G48=3,F48/12,IF(G48=6,F48,IF(G48=7,F48-I48,0)))),0) -> 0 | L48: =IF(G48=6,F48,0) -> 0 | M48: =IF(F48="",0,MONTH(A48)) -> 4 | P48: 確認済 | Q48: =IF($F48="","",IFERROR(VLOOKUP($C48&"|"&$D48,科目表!$A$5:$B$200,2,FALSE),"※未登録")) -> 図書印刷費 | R48: =IF($F48="","",$I48+$J48+$K48) -> 0 | S48: =IF(OR($F48="",$P48="支払なし",$H48=0,$Q48=""),"",$Q48&"|S|"&(COUNTIF(S$4:S47,$Q48&"|S|*")+1)) -> 図書印刷費|S|3 | T48: =IF(OR($F48="",$P48="支払なし",$R48=0,$Q48=""),"",$Q48&"|L|"&(COUNTIF(T$4:T47,$Q48&"|L|*")+1)) | U48: =IF(OR($F48="",$A48=""),"",MOD(MONTH($A48)-4,12)+1) -> 1
H49: =IF(G49=1,F49-I49-J49-K49,IF(G49=2,F49,0)) -> 0 | I49: =ROUND(IF(G49=1,F49*10/23,IF(G49=3,F49-J49-K49,IF(G49=4,F49,IF(G49=5,F49*10/11,IF(G49=7,F49*10/11,0))))),0) -> 0 | J49: =ROUND(IF(G49=1,F49/23,IF(G49=3,F49/12,IF(G49=5,F49-I49,IF(G49=8,F49,0)))),0) -> 0 | K49: =ROUND(IF(G49=1,F49/23,IF(G49=3,F49/12,IF(G49=6,F49,IF(G49=7,F49-I49,0)))),0) -> 0 | L49: =IF(G49=6,F49,0) -> 0 | M49: =IF(F49="",0,MONTH(A49)) -> 0 | Q49: =IF($F49="","",IFERROR(VLOOKUP($C49&"|"&$D49,科目表!$A$5:$B$200,2,FALSE),"※未登録")) | R49: =IF($F49="","",$I49+$J49+$K49) | S49: =IF(OR($F49="",$P49="支払なし",$H49=0,$Q49=""),"",$Q49&"|S|"&(COUNTIF(S$4:S48,$Q49&"|S|*")+1)) | T49: =IF(OR($F49="",$P49="支払なし",$R49=0,$Q49=""),"",$Q49&"|L|"&(COUNTIF(T$4:T48,$Q49&"|L|*")+1)) | U49: =IF(OR($F49="",$A49=""),"",MOD(MONTH($A49)-4,12)+1)
A50: 46174 | C50: 負担金 | D50: 厚年負担金等 | E50: ４月月例分（短期分）子ども子育て拠出金を含む | F50: 62766 | G50: 2 | H50: =IF(G50=1,F50-I50-J50-K50,IF(G50=2,F50,0)) -> 62766 | I50: =ROUND(IF(G50=1,F50*10/23,IF(G50=3,F50-J50-K50,IF(G50=4,F50,IF(G50=5,F50*10/11,IF(G50=7,F50*10/11,0))))),0) -> 0 | J50: =ROUND(IF(G50=1,F50/23,IF(G50=3,F50/12,IF(G50=5,F50-I50,IF(G50=8,F50,0)))),0) -> 0 | K50: =ROUND(IF(G50=1,F50/23,IF(G50=3,F50/12,IF(G50=6,F50,IF(G50=7,F50-I50,0)))),0) -> 0 | L50: =IF(G50=6,F50,0) -> 0 | M50: =IF(F50="",0,MONTH(A50)) -> 6 | P50: 確認済 | Q50: =IF($F50="","",IFERROR(VLOOKUP($C50&"|"&$D50,科目表!$A$5:$B$200,2,FALSE),"※未登録")) -> 厚年負担金等 | R50: =IF($F50="","",$I50+$J50+$K50) -> 0 | S50: =IF(OR($F50="",$P50="支払なし",$H50=0,$Q50=""),"",$Q50&"|S|"&(COUNTIF(S$4:S49,$Q50&"|S|*")+1)) -> 厚年負担金等|S|1 | T50: =IF(OR($F50="",$P50="支払なし",$R50=0,$Q50=""),"",$Q50&"|L|"&(COUNTIF(T$4:T49,$Q50&"|L|*")+1)) | U50: =IF(OR($F50="",$A50=""),"",MOD(MONTH($A50)-4,12)+1) -> 3
H51: =IF(G51=1,F51-I51-J51-K51,IF(G51=2,F51,0)) -> 0 | I51: =ROUND(IF(G51=1,F51*10/23,IF(G51=3,F51-J51-K51,IF(G51=4,F51,IF(G51=5,F51*10/11,IF(G51=7,F51*10/11,0))))),0) -> 0 | J51: =ROUND(IF(G51=1,F51/23,IF(G51=3,F51/12,IF(G51=5,F51-I51,IF(G51=8,F51,0)))),0) -> 0 | K51: =ROUND(IF(G51=1,F51/23,IF(G51=3,F51/12,IF(G51=6,F51,IF(G51=7,F51-I51,0)))),0) -> 0 | L51: =IF(G51=6,F51,0) -> 0 | M51: =IF(F51="",0,MONTH(A51)) -> 0 | Q51: =IF($F51="","",IFERROR(VLOOKUP($C51&"|"&$D51,科目表!$A$5:$B$200,2,FALSE),"※未登録")) | R51: =IF($F51="","",$I51+$J51+$K51) | S51: =IF(OR($F51="",$P51="支払なし",$H51=0,$Q51=""),"",$Q51&"|S|"&(COUNTIF(S$4:S50,$Q51&"|S|*")+1)) | T51: =IF(OR($F51="",$P51="支払なし",$R51=0,$Q51=""),"",$Q51&"|L|"&(COUNTIF(T$4:T50,$Q51&"|L|*")+1)) | U51: =IF(OR($F51="",$A51=""),"",MOD(MONTH($A51)-4,12)+1)
A52: 46174 | C52: 負担金 | D52: 厚年負担金等 | E52: ４月月例分（長期分）子ども子育て拠出金を含む | F52: 37089 | G52: 3 | H52: =IF(G52=1,F52-I52-J52-K52,IF(G52=2,F52,0)) -> 0 | I52: =ROUND(IF(G52=1,F52*10/23,IF(G52=3,F52-J52-K52,IF(G52=4,F52,IF(G52=5,F52*10/11,IF(G52=7,F52*10/11,0))))),0) -> 30907 | J52: =ROUND(IF(G52=1,F52/23,IF(G52=3,F52/12,IF(G52=5,F52-I52,IF(G52=8,F52,0)))),0) -> 3091 | K52: =ROUND(IF(G52=1,F52/23,IF(G52=3,F52/12,IF(G52=6,F52,IF(G52=7,F52-I52,0)))),0) -> 3091 | L52: =IF(G52=6,F52,0) -> 0 | M52: =IF(F52="",0,MONTH(A52)) -> 6 | P52: 確認済 | Q52: =IF($F52="","",IFERROR(VLOOKUP($C52&"|"&$D52,科目表!$A$5:$B$200,2,FALSE),"※未登録")) -> 厚年負担金等 | R52: =IF($F52="","",$I52+$J52+$K52) -> 37089 | S52: =IF(OR($F52="",$P52="支払なし",$H52=0,$Q52=""),"",$Q52&"|S|"&(COUNTIF(S$4:S51,$Q52&"|S|*")+1)) | T52: =IF(OR($F52="",$P52="支払なし",$R52=0,$Q52=""),"",$Q52&"|L|"&(COUNTIF(T$4:T51,$Q52&"|L|*")+1)) -> 厚年負担金等|L|1 | U52: =IF(OR($F52="",$A52=""),"",MOD(MONTH($A52)-4,12)+1) -> 3
A53: 46171 | C53: 事務費 | D53: 図書印刷費 | E53: 厚生法規総覧追録６０９６－６１０５号 | F53: 33154 | G53: 2 | H53: =IF(G53=1,F53-I53-J53-K53,IF(G53=2,F53,0)) -> 33154 | I53: =ROUND(IF(G53=1,F53*10/23,IF(G53=3,F53-J53-K53,IF(G53=4,F53,IF(G53=5,F53*10/11,IF(G53=7,F53*10/11,0))))),0) -> 0 | J53: =ROUND(IF(G53=1,F53/23,IF(G53=3,F53/12,IF(G53=5,F53-I53,IF(G53=8,F53,0)))),0) -> 0 | K53: =ROUND(IF(G53=1,F53/23,IF(G53=3,F53/12,IF(G53=6,F53,IF(G53=7,F53-I53,0)))),0) -> 0 | L53: =IF(G53=6,F53,0) -> 0 | M53: =IF(F53="",0,MONTH(A53)) -> 5 | P53: 確認済 | Q53: =IF($F53="","",IFERROR(VLOOKUP($C53&"|"&$D53,科目表!$A$5:$B$200,2,FALSE),"※未登録")) -> 図書印刷費 | R53: =IF($F53="","",$I53+$J53+$K53) -> 0 | S53: =IF(OR($F53="",$P53="支払なし",$H53=0,$Q53=""),"",$Q53&"|S|"&(COUNTIF(S$4:S52,$Q53&"|S|*")+1)) -> 図書印刷費|S|4 | T53: =IF(OR($F53="",$P53="支払なし",$R53=0,$Q53=""),"",$Q53&"|L|"&(COUNTIF(T$4:T52,$Q53&"|L|*")+1)) | U53: =IF(OR($F53="",$A53=""),"",MOD(MONTH($A53)-4,12)+1) -> 2
A54: 45077 | C54: 事務費 | D54: 通信運搬費 | E54: 柔整申請書送付（４月分） | F54: 1489 | G54: 2 | H54: =IF(G54=1,F54-I54-J54-K54,IF(G54=2,F54,0)) -> 1489 | I54: =ROUND(IF(G54=1,F54*10/23,IF(G54=3,F54-J54-K54,IF(G54=4,F54,IF(G54=5,F54*10/11,IF(G54=7,F54*10/11,0))))),0) -> 0 | J54: =ROUND(IF(G54=1,F54/23,IF(G54=3,F54/12,IF(G54=5,F54-I54,IF(G54=8,F54,0)))),0) -> 0 | K54: =ROUND(IF(G54=1,F54/23,IF(G54=3,F54/12,IF(G54=6,F54,IF(G54=7,F54-I54,0)))),0) -> 0 | L54: =IF(G54=6,F54,0) -> 0 | M54: =IF(F54="",0,MONTH(A54)) -> 5 | P54: 昨年実績 | Q54: =IF($F54="","",IFERROR(VLOOKUP($C54&"|"&$D54,科目表!$A$5:$B$200,2,FALSE),"※未登録")) -> 通信運搬費 | R54: =IF($F54="","",$I54+$J54+$K54) -> 0 | S54: =IF(OR($F54="",$P54="支払なし",$H54=0,$Q54=""),"",$Q54&"|S|"&(COUNTIF(S$4:S53,$Q54&"|S|*")+1)) -> 通信運搬費|S|3 | T54: =IF(OR($F54="",$P54="支払なし",$R54=0,$Q54=""),"",$Q54&"|L|"&(COUNTIF(T$4:T53,$Q54&"|L|*")+1)) | U54: =IF(OR($F54="",$A54=""),"",MOD(MONTH($A54)-4,12)+1) -> 2
A55: 43980 | C55: 事務費 | D55: 通信運搬費 | E55: メール便（４月分） | F55: 6636 | G55: 2 | H55: =IF(G55=1,F55-I55-J55-K55,IF(G55=2,F55,0)) -> 6636 | I55: =ROUND(IF(G55=1,F55*10/23,IF(G55=3,F55-J55-K55,IF(G55=4,F55,IF(G55=5,F55*10/11,IF(G55=7,F55*10/11,0))))),0) -> 0 | J55: =ROUND(IF(G55=1,F55/23,IF(G55=3,F55/12,IF(G55=5,F55-I55,IF(G55=8,F55,0)))),0) -> 0 | K55: =ROUND(IF(G55=1,F55/23,IF(G55=3,F55/12,IF(G55=6,F55,IF(G55=7,F55-I55,0)))),0) -> 0 | L55: =IF(G55=6,F55,0) -> 0 | M55: =IF(F55="",0,MONTH(A55)) -> 5 | P55: 昨年実績 | Q55: =IF($F55="","",IFERROR(VLOOKUP($C55&"|"&$D55,科目表!$A$5:$B$200,2,FALSE),"※未登録")) -> 通信運搬費 | R55: =IF($F55="","",$I55+$J55+$K55) -> 0 | S55: =IF(OR($F55="",$P55="支払なし",$H55=0,$Q55=""),"",$Q55&"|S|"&(COUNTIF(S$4:S54,$Q55&"|S|*")+1)) -> 通信運搬費|S|4 | T55: =IF(OR($F55="",$P55="支払なし",$R55=0,$Q55=""),"",$Q55&"|L|"&(COUNTIF(T$4:T54,$Q55&"|L|*")+1)) | U55: =IF(OR($F55="",$A55=""),"",MOD(MONTH($A55)-4,12)+1) -> 2
A56: 45077 | C56: 事務費 | D56: 通信運搬費 | E56: メール便（任継者宛厚生だより４月分） | F56: 17220 | G56: 2 | H56: =IF(G56=1,F56-I56-J56-K56,IF(G56=2,F56,0)) -> 17220 | I56: =ROUND(IF(G56=1,F56*10/23,IF(G56=3,F56-J56-K56,IF(G56=4,F56,IF(G56=5,F56*10/11,IF(G56=7,F56*10/11,0))))),0) -> 0 | J56: =ROUND(IF(G56=1,F56/23,IF(G56=3,F56/12,IF(G56=5,F56-I56,IF(G56=8,F56,0)))),0) -> 0 | K56: =ROUND(IF(G56=1,F56/23,IF(G56=3,F56/12,IF(G56=6,F56,IF(G56=7,F56-I56,0)))),0) -> 0 | L56: =IF(G56=6,F56,0) -> 0 | M56: =IF(F56="",0,MONTH(A56)) -> 5 | P56: 昨年実績 | Q56: =IF($F56="","",IFERROR(VLOOKUP($C56&"|"&$D56,科目表!$A$5:$B$200,2,FALSE),"※未登録")) -> 通信運搬費 | R56: =IF($F56="","",$I56+$J56+$K56) -> 0 | S56: =IF(OR($F56="",$P56="支払なし",$H56=0,$Q56=""),"",$Q56&"|S|"&(COUNTIF(S$4:S55,$Q56&"|S|*")+1)) -> 通信運搬費|S|5 | T56: =IF(OR($F56="",$P56="支払なし",$R56=0,$Q56=""),"",$Q56&"|L|"&(COUNTIF(T$4:T55,$Q56&"|L|*")+1)) | U56: =IF(OR($F56="",$A56=""),"",MOD(MONTH($A56)-4,12)+1) -> 2
A57: 46171 | C57: 賃借料 | E57: 基幹システム用機器賃借料 4月分（短期） | F57: 672934 | G57: 2 | H57: =IF(G57=1,F57-I57-J57-K57,IF(G57=2,F57,0)) -> 672934 | I57: =ROUND(IF(G57=1,F57*10/23,IF(G57=3,F57-J57-K57,IF(G57=4,F57,IF(G57=5,F57*10/11,IF(G57=7,F57*10/11,0))))),0) -> 0 | J57: =ROUND(IF(G57=1,F57/23,IF(G57=3,F57/12,IF(G57=5,F57-I57,IF(G57=8,F57,0)))),0) -> 0 | K57: =ROUND(IF(G57=1,F57/23,IF(G57=3,F57/12,IF(G57=6,F57,IF(G57=7,F57-I57,0)))),0) -> 0 | L57: =IF(G57=6,F57,0) -> 0 | M57: =IF(F57="",0,MONTH(A57)) -> 5 | P57: 確認済 | Q57: =IF($F57="","",IFERROR(VLOOKUP($C57&"|"&$D57,科目表!$A$5:$B$200,2,FALSE),"※未登録")) -> 賃借料 | R57: =IF($F57="","",$I57+$J57+$K57) -> 0 | S57: =IF(OR($F57="",$P57="支払なし",$H57=0,$Q57=""),"",$Q57&"|S|"&(COUNTIF(S$4:S56,$Q57&"|S|*")+1)) -> 賃借料|S|3 | T57: =IF(OR($F57="",$P57="支払なし",$R57=0,$Q57=""),"",$Q57&"|L|"&(COUNTIF(T$4:T56,$Q57&"|L|*")+1)) | U57: =IF(OR($F57="",$A57=""),"",MOD(MONTH($A57)-4,12)+1) -> 2
A58: 46171 | C58: 賃借料 | E58: 基幹システム用機器賃借料 4月分（長期） | F58: 69613 | G58: 3 | H58: =IF(G58=1,F58-I58-J58-K58,IF(G58=2,F58,0)) -> 0 | I58: =ROUND(IF(G58=1,F58*10/23,IF(G58=3,F58-J58-K58,IF(G58=4,F58,IF(G58=5,F58*10/11,IF(G58=7,F58*10/11,0))))),0) -> 58011 | J58: =ROUND(IF(G58=1,F58/23,IF(G58=3,F58/12,IF(G58=5,F58-I58,IF(G58=8,F58,0)))),0) -> 5801 | K58: =ROUND(IF(G58=1,F58/23,IF(G58=3,F58/12,IF(G58=6,F58,IF(G58=7,F58-I58,0)))),0) -> 5801 | L58: =IF(G58=6,F58,0) -> 0 | M58: =IF(F58="",0,MONTH(A58)) -> 5 | P58: 確認済 | Q58: =IF($F58="","",IFERROR(VLOOKUP($C58&"|"&$D58,科目表!$A$5:$B$200,2,FALSE),"※未登録")) -> 賃借料 | R58: =IF($F58="","",$I58+$J58+$K58) -> 69613 | S58: =IF(OR($F58="",$P58="支払なし",$H58=0,$Q58=""),"",$Q58&"|S|"&(COUNTIF(S$4:S57,$Q58&"|S|*")+1)) | T58: =IF(OR($F58="",$P58="支払なし",$R58=0,$Q58=""),"",$Q58&"|L|"&(COUNTIF(T$4:T57,$Q58&"|L|*")+1)) -> 賃借料|L|1 | U58: =IF(OR($F58="",$A58=""),"",MOD(MONTH($A58)-4,12)+1) -> 2
A59: 46171 | C59: 委託費 | E59: 柔整等療養費支給申請書の入力（４月分） | F59: 137918 | G59: 2 | H59: =IF(G59=1,F59-I59-J59-K59,IF(G59=2,F59,0)) -> 137918 | I59: =ROUND(IF(G59=1,F59*10/23,IF(G59=3,F59-J59-K59,IF(G59=4,F59,IF(G59=5,F59*10/11,IF(G59=7,F59*10/11,0))))),0) -> 0 | J59: =ROUND(IF(G59=1,F59/23,IF(G59=3,F59/12,IF(G59=5,F59-I59,IF(G59=8,F59,0)))),0) -> 0 | K59: =ROUND(IF(G59=1,F59/23,IF(G59=3,F59/12,IF(G59=6,F59,IF(G59=7,F59-I59,0)))),0) -> 0 | L59: =IF(G59=6,F59,0) -> 0 | M59: =IF(F59="",0,MONTH(A59)) -> 5 | P59: 確認済 | Q59: =IF($F59="","",IFERROR(VLOOKUP($C59&"|"&$D59,科目表!$A$5:$B$200,2,FALSE),"※未登録")) -> 委託費 | R59: =IF($F59="","",$I59+$J59+$K59) -> 0 | S59: =IF(OR($F59="",$P59="支払なし",$H59=0,$Q59=""),"",$Q59&"|S|"&(COUNTIF(S$4:S58,$Q59&"|S|*")+1)) -> 委託費|S|8 | T59: =IF(OR($F59="",$P59="支払なし",$R59=0,$Q59=""),"",$Q59&"|L|"&(COUNTIF(T$4:T58,$Q59&"|L|*")+1)) | U59: =IF(OR($F59="",$A59=""),"",MOD(MONTH($A59)-4,12)+1) -> 2
A60: 45443 | C60: 委託費 | E60: 柔整等療養費支給申請書の入力（４月分） | F60: 70730 | G60: 2 | H60: =IF(G60=1,F60-I60-J60-K60,IF(G60=2,F60,0)) -> 70730 | I60: =ROUND(IF(G60=1,F60*10/23,IF(G60=3,F60-J60-K60,IF(G60=4,F60,IF(G60=5,F60*10/11,IF(G60=7,F60*10/11,0))))),0) -> 0 | J60: =ROUND(IF(G60=1,F60/23,IF(G60=3,F60/12,IF(G60=5,F60-I60,IF(G60=8,F60,0)))),0) -> 0 | K60: =ROUND(IF(G60=1,F60/23,IF(G60=3,F60/12,IF(G60=6,F60,IF(G60=7,F60-I60,0)))),0) -> 0 | L60: =IF(G60=6,F60,0) -> 0 | M60: =IF(F60="",0,MONTH(A60)) -> 5 | P60: 昨年実績 | Q60: =IF($F60="","",IFERROR(VLOOKUP($C60&"|"&$D60,科目表!$A$5:$B$200,2,FALSE),"※未登録")) -> 委託費 | R60: =IF($F60="","",$I60+$J60+$K60) -> 0 | S60: =IF(OR($F60="",$P60="支払なし",$H60=0,$Q60=""),"",$Q60&"|S|"&(COUNTIF(S$4:S59,$Q60&"|S|*")+1)) -> 委託費|S|9 | T60: =IF(OR($F60="",$P60="支払なし",$R60=0,$Q60=""),"",$Q60&"|L|"&(COUNTIF(T$4:T59,$Q60&"|L|*")+1)) | U60: =IF(OR($F60="",$A60=""),"",MOD(MONTH($A60)-4,12)+1) -> 2
A61: 45810 | C61: 事務費 | D61: 通信運搬費 | E61: フレッツ光ネクスト利用料等（４月利用・５月請求分） | F61: 5126 | G61: 2 | H61: =IF(G61=1,F61-I61-J61-K61,IF(G61=2,F61,0)) -> 5126 | I61: =ROUND(IF(G61=1,F61*10/23,IF(G61=3,F61-J61-K61,IF(G61=4,F61,IF(G61=5,F61*10/11,IF(G61=7,F61*10/11,0))))),0) -> 0 | J61: =ROUND(IF(G61=1,F61/23,IF(G61=3,F61/12,IF(G61=5,F61-I61,IF(G61=8,F61,0)))),0) -> 0 | K61: =ROUND(IF(G61=1,F61/23,IF(G61=3,F61/12,IF(G61=6,F61,IF(G61=7,F61-I61,0)))),0) -> 0 | L61: =IF(G61=6,F61,0) -> 0 | M61: =IF(F61="",0,MONTH(A61)) -> 6 | P61: 昨年実績 | Q61: =IF($F61="","",IFERROR(VLOOKUP($C61&"|"&$D61,科目表!$A$5:$B$200,2,FALSE),"※未登録")) -> 通信運搬費 | R61: =IF($F61="","",$I61+$J61+$K61) -> 0 | S61: =IF(OR($F61="",$P61="支払なし",$H61=0,$Q61=""),"",$Q61&"|S|"&(COUNTIF(S$4:S60,$Q61&"|S|*")+1)) -> 通信運搬費|S|6 | T61: =IF(OR($F61="",$P61="支払なし",$R61=0,$Q61=""),"",$Q61&"|L|"&(COUNTIF(T$4:T60,$Q61&"|L|*")+1)) | U61: =IF(OR($F61="",$A61=""),"",MOD(MONTH($A61)-4,12)+1) -> 3
A62: 46174 | C62: 事務費 | D62: 通信運搬費 | E62: インターネット通信料金（３月、４月使用・５月請求分） | F62: 3663 | G62: 2 | H62: =IF(G62=1,F62-I62-J62-K62,IF(G62=2,F62,0)) -> 3663 | I62: =ROUND(IF(G62=1,F62*10/23,IF(G62=3,F62-J62-K62,IF(G62=4,F62,IF(G62=5,F62*10/11,IF(G62=7,F62*10/11,0))))),0) -> 0 | J62: =ROUND(IF(G62=1,F62/23,IF(G62=3,F62/12,IF(G62=5,F62-I62,IF(G62=8,F62,0)))),0) -> 0 | K62: =ROUND(IF(G62=1,F62/23,IF(G62=3,F62/12,IF(G62=6,F62,IF(G62=7,F62-I62,0)))),0) -> 0 | L62: =IF(G62=6,F62,0) -> 0 | M62: =IF(F62="",0,MONTH(A62)) -> 6 | P62: 確認済 | Q62: =IF($F62="","",IFERROR(VLOOKUP($C62&"|"&$D62,科目表!$A$5:$B$200,2,FALSE),"※未登録")) -> 通信運搬費 | R62: =IF($F62="","",$I62+$J62+$K62) -> 0 | S62: =IF(OR($F62="",$P62="支払なし",$H62=0,$Q62=""),"",$Q62&"|S|"&(COUNTIF(S$4:S61,$Q62&"|S|*")+1)) -> 通信運搬費|S|7 | T62: =IF(OR($F62="",$P62="支払なし",$R62=0,$Q62=""),"",$Q62&"|L|"&(COUNTIF(T$4:T61,$Q62&"|L|*")+1)) | U62: =IF(OR($F62="",$A62=""),"",MOD(MONTH($A62)-4,12)+1) -> 3
A63: 46171 | C63: 事務費 | D63: 事務用消耗品費 | E63: 鋳造ゴム印 3号以下 147字 他 | F63: 14040 | G63: 3 | H63: =IF(G63=1,F63-I63-J63-K63,IF(G63=2,F63,0)) -> 0 | I63: =ROUND(IF(G63=1,F63*10/23,IF(G63=3,F63-J63-K63,IF(G63=4,F63,IF(G63=5,F63*10/11,IF(G63=7,F63*10/11,0))))),0) -> 11700 | J63: =ROUND(IF(G63=1,F63/23,IF(G63=3,F63/12,IF(G63=5,F63-I63,IF(G63=8,F63,0)))),0) -> 1170 | K63: =ROUND(IF(G63=1,F63/23,IF(G63=3,F63/12,IF(G63=6,F63,IF(G63=7,F63-I63,0)))),0) -> 1170 | L63: =IF(G63=6,F63,0) -> 0 | M63: =IF(F63="",0,MONTH(A63)) -> 5 | P63: 確認済 | Q63: =IF($F63="","",IFERROR(VLOOKUP($C63&"|"&$D63,科目表!$A$5:$B$200,2,FALSE),"※未登録")) -> 事務用消耗品費 | R63: =IF($F63="","",$I63+$J63+$K63) -> 14040 | S63: =IF(OR($F63="",$P63="支払なし",$H63=0,$Q63=""),"",$Q63&"|S|"&(COUNTIF(S$4:S62,$Q63&"|S|*")+1)) | T63: =IF(OR($F63="",$P63="支払なし",$R63=0,$Q63=""),"",$Q63&"|L|"&(COUNTIF(T$4:T62,$Q63&"|L|*")+1)) -> 事務用消耗品費|L|4 | U63: =IF(OR($F63="",$A63=""),"",MOD(MONTH($A63)-4,12)+1) -> 2
A64: 45412 | C64: 事務費 | D64: 事務用消耗品費 | E64: 令和６年度基幹ウイルス対策ソフト（ミツイワ株式会社） | F64: 21450 | G64: 2 | H64: =IF(G64=1,F64-I64-J64-K64,IF(G64=2,F64,0)) -> 21450 | I64: =ROUND(IF(G64=1,F64*10/23,IF(G64=3,F64-J64-K64,IF(G64=4,F64,IF(G64=5,F64*10/11,IF(G64=7,F64*10/11,0))))),0) -> 0 | J64: =ROUND(IF(G64=1,F64/23,IF(G64=3,F64/12,IF(G64=5,F64-I64,IF(G64=8,F64,0)))),0) -> 0 | K64: =ROUND(IF(G64=1,F64/23,IF(G64=3,F64/12,IF(G64=6,F64,IF(G64=7,F64-I64,0)))),0) -> 0 | L64: =IF(G64=6,F64,0) -> 0 | M64: =IF(F64="",0,MONTH(A64)) -> 4 | P64: 昨年実績 | Q64: =IF($F64="","",IFERROR(VLOOKUP($C64&"|"&$D64,科目表!$A$5:$B$200,2,FALSE),"※未登録")) -> 事務用消耗品費 | R64: =IF($F64="","",$I64+$J64+$K64) -> 0 | S64: =IF(OR($F64="",$P64="支払なし",$H64=0,$Q64=""),"",$Q64&"|S|"&(COUNTIF(S$4:S63,$Q64&"|S|*")+1)) -> 事務用消耗品費|S|6 | T64: =IF(OR($F64="",$P64="支払なし",$R64=0,$Q64=""),"",$Q64&"|L|"&(COUNTIF(T$4:T63,$Q64&"|L|*")+1)) | U64: =IF(OR($F64="",$A64=""),"",MOD(MONTH($A64)-4,12)+1) -> 1
A65: 45443 | C65: 事務費 | D65: 事務用消耗品費 | E65: 保存ボックス 4370 50個 | F65: 29650 | G65: 2 | H65: =IF(G65=1,F65-I65-J65-K65,IF(G65=2,F65,0)) -> 29650 | I65: =ROUND(IF(G65=1,F65*10/23,IF(G65=3,F65-J65-K65,IF(G65=4,F65,IF(G65=5,F65*10/11,IF(G65=7,F65*10/11,0))))),0) -> 0 | J65: =ROUND(IF(G65=1,F65/23,IF(G65=3,F65/12,IF(G65=5,F65-I65,IF(G65=8,F65,0)))),0) -> 0 | K65: =ROUND(IF(G65=1,F65/23,IF(G65=3,F65/12,IF(G65=6,F65,IF(G65=7,F65-I65,0)))),0) -> 0 | L65: =IF(G65=6,F65,0) -> 0 | M65: =IF(F65="",0,MONTH(A65)) -> 5 | P65: 昨年実績 | Q65: =IF($F65="","",IFERROR(VLOOKUP($C65&"|"&$D65,科目表!$A$5:$B$200,2,FALSE),"※未登録")) -> 事務用消耗品費 | R65: =IF($F65="","",$I65+$J65+$K65) -> 0 | S65: =IF(OR($F65="",$P65="支払なし",$H65=0,$Q65=""),"",$Q65&"|S|"&(COUNTIF(S$4:S64,$Q65&"|S|*")+1)) -> 事務用消耗品費|S|7 | T65: =IF(OR($F65="",$P65="支払なし",$R65=0,$Q65=""),"",$Q65&"|L|"&(COUNTIF(T$4:T64,$Q65&"|L|*")+1)) | U65: =IF(OR($F65="",$A65=""),"",MOD(MONTH($A65)-4,12)+1) -> 2
A66: 46176 | C66: 事務費 | D66: 図書印刷費 | E66: 国家公務員等共済組合関係法令要覧追録５３５－５３８号 | F66: 17600 | G66: 3 | H66: =IF(G66=1,F66-I66-J66-K66,IF(G66=2,F66,0)) -> 0 | I66: =ROUND(IF(G66=1,F66*10/23,IF(G66=3,F66-J66-K66,IF(G66=4,F66,IF(G66=5,F66*10/11,IF(G66=7,F66*10/11,0))))),0) -> 14666 | J66: =ROUND(IF(G66=1,F66/23,IF(G66=3,F66/12,IF(G66=5,F66-I66,IF(G66=8,F66,0)))),0) -> 1467 | K66: =ROUND(IF(G66=1,F66/23,IF(G66=3,F66/12,IF(G66=6,F66,IF(G66=7,F66-I66,0)))),0) -> 1467 | L66: =IF(G66=6,F66,0) -> 0 | M66: =IF(F66="",0,MONTH(A66)) -> 6 | P66: 確認済 | Q66: =IF($F66="","",IFERROR(VLOOKUP($C66&"|"&$D66,科目表!$A$5:$B$200,2,FALSE),"※未登録")) -> 図書印刷費 | R66: =IF($F66="","",$I66+$J66+$K66) -> 17600 | S66: =IF(OR($F66="",$P66="支払なし",$H66=0,$Q66=""),"",$Q66&"|S|"&(COUNTIF(S$4:S65,$Q66&"|S|*")+1)) | T66: =IF(OR($F66="",$P66="支払なし",$R66=0,$Q66=""),"",$Q66&"|L|"&(COUNTIF(T$4:T65,$Q66&"|L|*")+1)) -> 図書印刷費|L|3 | U66: =IF(OR($F66="",$A66=""),"",MOD(MONTH($A66)-4,12)+1) -> 3
A67: 46181 | C67: 役員報酬 | E67: 業務監査６／８ 学識経験監事 栗栖 一雄 | F67: 11000 | G67: 1 | H67: =IF(G67=1,F67-I67-J67-K67,IF(G67=2,F67,0)) -> 5261 | I67: =ROUND(IF(G67=1,F67*10/23,IF(G67=3,F67-J67-K67,IF(G67=4,F67,IF(G67=5,F67*10/11,IF(G67=7,F67*10/11,0))))),0) -> 4783 | J67: =ROUND(IF(G67=1,F67/23,IF(G67=3,F67/12,IF(G67=5,F67-I67,IF(G67=8,F67,0)))),0) -> 478 | K67: =ROUND(IF(G67=1,F67/23,IF(G67=3,F67/12,IF(G67=6,F67,IF(G67=7,F67-I67,0)))),0) -> 478 | L67: =IF(G67=6,F67,0) -> 0 | M67: =IF(F67="",0,MONTH(A67)) -> 6 | P67: 確認済 | Q67: =IF($F67="","",IFERROR(VLOOKUP($C67&"|"&$D67,科目表!$A$5:$B$200,2,FALSE),"※未登録")) -> 役員報酬 | R67: =IF($F67="","",$I67+$J67+$K67) -> 5739 | S67: =IF(OR($F67="",$P67="支払なし",$H67=0,$Q67=""),"",$Q67&"|S|"&(COUNTIF(S$4:S66,$Q67&"|S|*")+1)) -> 役員報酬|S|1 | T67: =IF(OR($F67="",$P67="支払なし",$R67=0,$Q67=""),"",$Q67&"|L|"&(COUNTIF(T$4:T66,$Q67&"|L|*")+1)) -> 役員報酬|L|1 | U67: =IF(OR($F67="",$A67=""),"",MOD(MONTH($A67)-4,12)+1) -> 3
A68: 46169 | C68: 負担金 | D68: 負担金 | E68: 共済短期・介護負担金（5月月例分）長期 | F68: 22035 | G68: 3 | H68: =IF(G68=1,F68-I68-J68-K68,IF(G68=2,F68,0)) -> 0 | I68: =ROUND(IF(G68=1,F68*10/23,IF(G68=3,F68-J68-K68,IF(G68=4,F68,IF(G68=5,F68*10/11,IF(G68=7,F68*10/11,0))))),0) -> 18363 | J68: =ROUND(IF(G68=1,F68/23,IF(G68=3,F68/12,IF(G68=5,F68-I68,IF(G68=8,F68,0)))),0) -> 1836 | K68: =ROUND(IF(G68=1,F68/23,IF(G68=3,F68/12,IF(G68=6,F68,IF(G68=7,F68-I68,0)))),0) -> 1836 | L68: =IF(G68=6,F68,0) -> 0 | M68: =IF(F68="",0,MONTH(A68)) -> 5 | P68: 確認済 | Q68: =IF($F68="","",IFERROR(VLOOKUP($C68&"|"&$D68,科目表!$A$5:$B$200,2,FALSE),"※未登録")) -> 共済負担金等 | R68: =IF($F68="","",$I68+$J68+$K68) -> 22035 | S68: =IF(OR($F68="",$P68="支払なし",$H68=0,$Q68=""),"",$Q68&"|S|"&(COUNTIF(S$4:S67,$Q68&"|S|*")+1)) | T68: =IF(OR($F68="",$P68="支払なし",$R68=0,$Q68=""),"",$Q68&"|L|"&(COUNTIF(T$4:T67,$Q68&"|L|*")+1)) -> 共済負担金等|L|2 | U68: =IF(OR($F68="",$A68=""),"",MOD(MONTH($A68)-4,12)+1) -> 2
A69: 46169 | C69: 負担金 | D69: 負担金 | E69: 共済短期・介護負担金（5月月例分）短期 | F69: 37074 | G69: 2 | H69: =IF(G69=1,F69-I69-J69-K69,IF(G69=2,F69,0)) -> 37074 | I69: =ROUND(IF(G69=1,F69*10/23,IF(G69=3,F69-J69-K69,IF(G69=4,F69,IF(G69=5,F69*10/11,IF(G69=7,F69*10/11,0))))),0) -> 0 | J69: =ROUND(IF(G69=1,F69/23,IF(G69=3,F69/12,IF(G69=5,F69-I69,IF(G69=8,F69,0)))),0) -> 0 | K69: =ROUND(IF(G69=1,F69/23,IF(G69=3,F69/12,IF(G69=6,F69,IF(G69=7,F69-I69,0)))),0) -> 0 | L69: =IF(G69=6,F69,0) -> 0 | M69: =IF(F69="",0,MONTH(A69)) -> 5 | P69: 確認済 | Q69: =IF($F69="","",IFERROR(VLOOKUP($C69&"|"&$D69,科目表!$A$5:$B$200,2,FALSE),"※未登録")) -> 共済負担金等 | R69: =IF($F69="","",$I69+$J69+$K69) -> 0 | S69: =IF(OR($F69="",$P69="支払なし",$H69=0,$Q69=""),"",$Q69&"|S|"&(COUNTIF(S$4:S68,$Q69&"|S|*")+1)) -> 共済負担金等|S|2 | T69: =IF(OR($F69="",$P69="支払なし",$R69=0,$Q69=""),"",$Q69&"|L|"&(COUNTIF(T$4:T68,$Q69&"|L|*")+1)) | U69: =IF(OR($F69="",$A69=""),"",MOD(MONTH($A69)-4,12)+1) -> 2
A70: 43622 | C70: 旅費 | E70: 6/10事務局長会議 特別区 胡子事務局長 | F70: 38020 | G70: 1 | H70: =IF(G70=1,F70-I70-J70-K70,IF(G70=2,F70,0)) -> 18184 | I70: =ROUND(IF(G70=1,F70*10/23,IF(G70=3,F70-J70-K70,IF(G70=4,F70,IF(G70=5,F70*10/11,IF(G70=7,F70*10/11,0))))),0) -> 16530 | J70: =ROUND(IF(G70=1,F70/23,IF(G70=3,F70/12,IF(G70=5,F70-I70,IF(G70=8,F70,0)))),0) -> 1653 | K70: =ROUND(IF(G70=1,F70/23,IF(G70=3,F70/12,IF(G70=6,F70,IF(G70=7,F70-I70,0)))),0) -> 1653 | L70: =IF(G70=6,F70,0) -> 0 | M70: =IF(F70="",0,MONTH(A70)) -> 6 | P70: 昨年実績 | Q70: =IF($F70="","",IFERROR(VLOOKUP($C70&"|"&$D70,科目表!$A$5:$B$200,2,FALSE),"※未登録")) -> 旅費 | R70: =IF($F70="","",$I70+$J70+$K70) -> 19836 | S70: =IF(OR($F70="",$P70="支払なし",$H70=0,$Q70=""),"",$Q70&"|S|"&(COUNTIF(S$4:S69,$Q70&"|S|*")+1)) -> 旅費|S|1 | T70: =IF(OR($F70="",$P70="支払なし",$R70=0,$Q70=""),"",$Q70&"|L|"&(COUNTIF(T$4:T69,$Q70&"|L|*")+1)) -> 旅費|L|1 | U70: =IF(OR($F70="",$A70=""),"",MOD(MONTH($A70)-4,12)+1) -> 3
A71: 43635 | C71: 旅費 | E71: 6/21サーバー等説明会 福岡市 永山主事 | F71: 19040 | G71: 2 | H71: =IF(G71=1,F71-I71-J71-K71,IF(G71=2,F71,0)) -> 19040 | I71: =ROUND(IF(G71=1,F71*10/23,IF(G71=3,F71-J71-K71,IF(G71=4,F71,IF(G71=5,F71*10/11,IF(G71=7,F71*10/11,0))))),0) -> 0 | J71: =ROUND(IF(G71=1,F71/23,IF(G71=3,F71/12,IF(G71=5,F71-I71,IF(G71=8,F71,0)))),0) -> 0 | K71: =ROUND(IF(G71=1,F71/23,IF(G71=3,F71/12,IF(G71=6,F71,IF(G71=7,F71-I71,0)))),0) -> 0 | L71: =IF(G71=6,F71,0) -> 0 | M71: =IF(F71="",0,MONTH(A71)) -> 6 | P71: 昨年実績 | Q71: =IF($F71="","",IFERROR(VLOOKUP($C71&"|"&$D71,科目表!$A$5:$B$200,2,FALSE),"※未登録")) -> 旅費 | R71: =IF($F71="","",$I71+$J71+$K71) -> 0 | S71: =IF(OR($F71="",$P71="支払なし",$H71=0,$Q71=""),"",$Q71&"|S|"&(COUNTIF(S$4:S70,$Q71&"|S|*")+1)) -> 旅費|S|2 | T71: =IF(OR($F71="",$P71="支払なし",$R71=0,$Q71=""),"",$Q71&"|L|"&(COUNTIF(T$4:T70,$Q71&"|L|*")+1)) | U71: =IF(OR($F71="",$A71=""),"",MOD(MONTH($A71)-4,12)+1) -> 3
A72: 45805 | C72: 旅費 | E72: 6/2保健事業事務研修会 特別区 清水課長補佐 | F72: 37160 | G72: 2 | H72: =IF(G72=1,F72-I72-J72-K72,IF(G72=2,F72,0)) -> 37160 | I72: =ROUND(IF(G72=1,F72*10/23,IF(G72=3,F72-J72-K72,IF(G72=4,F72,IF(G72=5,F72*10/11,IF(G72=7,F72*10/11,0))))),0) -> 0 | J72: =ROUND(IF(G72=1,F72/23,IF(G72=3,F72/12,IF(G72=5,F72-I72,IF(G72=8,F72,0)))),0) -> 0 | K72: =ROUND(IF(G72=1,F72/23,IF(G72=3,F72/12,IF(G72=6,F72,IF(G72=7,F72-I72,0)))),0) -> 0 | L72: =IF(G72=6,F72,0) -> 0 | M72: =IF(F72="",0,MONTH(A72)) -> 5 | P72: 昨年実績 | Q72: =IF($F72="","",IFERROR(VLOOKUP($C72&"|"&$D72,科目表!$A$5:$B$200,2,FALSE),"※未登録")) -> 旅費 | R72: =IF($F72="","",$I72+$J72+$K72) -> 0 | S72: =IF(OR($F72="",$P72="支払なし",$H72=0,$Q72=""),"",$Q72&"|S|"&(COUNTIF(S$4:S71,$Q72&"|S|*")+1)) -> 旅費|S|3 | T72: =IF(OR($F72="",$P72="支払なし",$R72=0,$Q72=""),"",$Q72&"|L|"&(COUNTIF(T$4:T71,$Q72&"|L|*")+1)) | U72: =IF(OR($F72="",$A72=""),"",MOD(MONTH($A72)-4,12)+1) -> 2
A73: 45805 | C73: 旅費 | E73: 6/2保健事業事務研修会 特別区 上野主事 | F73: 37390 | G73: 2 | H73: =IF(G73=1,F73-I73-J73-K73,IF(G73=2,F73,0)) -> 37390 | I73: =ROUND(IF(G73=1,F73*10/23,IF(G73=3,F73-J73-K73,IF(G73=4,F73,IF(G73=5,F73*10/11,IF(G73=7,F73*10/11,0))))),0) -> 0 | J73: =ROUND(IF(G73=1,F73/23,IF(G73=3,F73/12,IF(G73=5,F73-I73,IF(G73=8,F73,0)))),0) -> 0 | K73: =ROUND(IF(G73=1,F73/23,IF(G73=3,F73/12,IF(G73=6,F73,IF(G73=7,F73-I73,0)))),0) -> 0 | L73: =IF(G73=6,F73,0) -> 0 | M73: =IF(F73="",0,MONTH(A73)) -> 5 | P73: 昨年実績 | Q73: =IF($F73="","",IFERROR(VLOOKUP($C73&"|"&$D73,科目表!$A$5:$B$200,2,FALSE),"※未登録")) -> 旅費 | R73: =IF($F73="","",$I73+$J73+$K73) -> 0 | S73: =IF(OR($F73="",$P73="支払なし",$H73=0,$Q73=""),"",$Q73&"|S|"&(COUNTIF(S$4:S72,$Q73&"|S|*")+1)) -> 旅費|S|4 | T73: =IF(OR($F73="",$P73="支払なし",$R73=0,$Q73=""),"",$Q73&"|L|"&(COUNTIF(T$4:T72,$Q73&"|L|*")+1)) | U73: =IF(OR($F73="",$A73=""),"",MOD(MONTH($A73)-4,12)+1) -> 2
A74: 43636 | C74: 旅費 | E74: 6/24～26 年金事務初任者研修会 特別区 梅谷主事 | F74: 63820 | G74: 3 | H74: =IF(G74=1,F74-I74-J74-K74,IF(G74=2,F74,0)) -> 0 | I74: =ROUND(IF(G74=1,F74*10/23,IF(G74=3,F74-J74-K74,IF(G74=4,F74,IF(G74=5,F74*10/11,IF(G74=7,F74*10/11,0))))),0) -> 53184 | J74: =ROUND(IF(G74=1,F74/23,IF(G74=3,F74/12,IF(G74=5,F74-I74,IF(G74=8,F74,0)))),0) -> 5318 | K74: =ROUND(IF(G74=1,F74/23,IF(G74=3,F74/12,IF(G74=6,F74,IF(G74=7,F74-I74,0)))),0) -> 5318 | L74: =IF(G74=6,F74,0) -> 0 | M74: =IF(F74="",0,MONTH(A74)) -> 6 | P74: 昨年実績 | Q74: =IF($F74="","",IFERROR(VLOOKUP($C74&"|"&$D74,科目表!$A$5:$B$200,2,FALSE),"※未登録")) -> 旅費 | R74: =IF($F74="","",$I74+$J74+$K74) -> 63820 | S74: =IF(OR($F74="",$P74="支払なし",$H74=0,$Q74=""),"",$Q74&"|S|"&(COUNTIF(S$4:S73,$Q74&"|S|*")+1)) | T74: =IF(OR($F74="",$P74="支払なし",$R74=0,$Q74=""),"",$Q74&"|L|"&(COUNTIF(T$4:T73,$Q74&"|L|*")+1)) -> 旅費|L|2 | U74: =IF(OR($F74="",$A74=""),"",MOD(MONTH($A74)-4,12)+1) -> 3
A75: 46178 | C75: 事務費負担金払込金 | E75: ５月分事務費負担金払込金と連合会交付金との相殺 | F75: 5366000 | G75: 5 | H75: =IF(G75=1,F75-I75-J75-K75,IF(G75=2,F75,0)) -> 0 | I75: =ROUND(IF(G75=1,F75*10/23,IF(G75=3,F75-J75-K75,IF(G75=4,F75,IF(G75=5,F75*10/11,IF(G75=7,F75*10/11,0))))),0) -> 4878182 | J75: =ROUND(IF(G75=1,F75/23,IF(G75=3,F75/12,IF(G75=5,F75-I75,IF(G75=8,F75,0)))),0) -> 487818 | K75: =ROUND(IF(G75=1,F75/23,IF(G75=3,F75/12,IF(G75=6,F75,IF(G75=7,F75-I75,0)))),0) -> 0 | L75: =IF(G75=6,F75,0) -> 0 | M75: =IF(F75="",0,MONTH(A75)) -> 6 | P75: 確認済 | Q75: =IF($F75="","",IFERROR(VLOOKUP($C75&"|"&$D75,科目表!$A$5:$B$200,2,FALSE),"※未登録")) -> 事務費負担金払込金 | R75: =IF($F75="","",$I75+$J75+$K75) -> 5366000 | S75: =IF(OR($F75="",$P75="支払なし",$H75=0,$Q75=""),"",$Q75&"|S|"&(COUNTIF(S$4:S74,$Q75&"|S|*")+1)) | T75: =IF(OR($F75="",$P75="支払なし",$R75=0,$Q75=""),"",$Q75&"|L|"&(COUNTIF(T$4:T74,$Q75&"|L|*")+1)) -> 事務費負担金払込金|L|2 | U75: =IF(OR($F75="",$A75=""),"",MOD(MONTH($A75)-4,12)+1) -> 3
A76: 45084 | C76: 事務費負担金払込金 | E76: ５月分事務費負担金払込金と連合会交付金との相殺 | F76: 3553000 | G76: 5 | H76: =IF(G76=1,F76-I76-J76-K76,IF(G76=2,F76,0)) -> 0 | I76: =ROUND(IF(G76=1,F76*10/23,IF(G76=3,F76-J76-K76,IF(G76=4,F76,IF(G76=5,F76*10/11,IF(G76=7,F76*10/11,0))))),0) -> 3230000 | J76: =ROUND(IF(G76=1,F76/23,IF(G76=3,F76/12,IF(G76=5,F76-I76,IF(G76=8,F76,0)))),0) -> 323000 | K76: =ROUND(IF(G76=1,F76/23,IF(G76=3,F76/12,IF(G76=6,F76,IF(G76=7,F76-I76,0)))),0) -> 0 | L76: =IF(G76=6,F76,0) -> 0 | M76: =IF(F76="",0,MONTH(A76)) -> 6 | P76: 昨年実績 | Q76: =IF($F76="","",IFERROR(VLOOKUP($C76&"|"&$D76,科目表!$A$5:$B$200,2,FALSE),"※未登録")) -> 事務費負担金払込金 | R76: =IF($F76="","",$I76+$J76+$K76) -> 3553000 | S76: =IF(OR($F76="",$P76="支払なし",$H76=0,$Q76=""),"",$Q76&"|S|"&(COUNTIF(S$4:S75,$Q76&"|S|*")+1)) | T76: =IF(OR($F76="",$P76="支払なし",$R76=0,$Q76=""),"",$Q76&"|L|"&(COUNTIF(T$4:T75,$Q76&"|L|*")+1)) -> 事務費負担金払込金|L|3 | U76: =IF(OR($F76="",$A76=""),"",MOD(MONTH($A76)-4,12)+1) -> 3
A77: 44718 | C77: 厚生費 | D77: 健康診断費 | E77: 健康診断費自己負担超分（一山） | F77: 1569 | G77: 2 | H77: =IF(G77=1,F77-I77-J77-K77,IF(G77=2,F77,0)) -> 1569 | I77: =ROUND(IF(G77=1,F77*10/23,IF(G77=3,F77-J77-K77,IF(G77=4,F77,IF(G77=5,F77*10/11,IF(G77=7,F77*10/11,0))))),0) -> 0 | J77: =ROUND(IF(G77=1,F77/23,IF(G77=3,F77/12,IF(G77=5,F77-I77,IF(G77=8,F77,0)))),0) -> 0 | K77: =ROUND(IF(G77=1,F77/23,IF(G77=3,F77/12,IF(G77=6,F77,IF(G77=7,F77-I77,0)))),0) -> 0 | L77: =IF(G77=6,F77,0) -> 0 | M77: =IF(F77="",0,MONTH(A77)) -> 6 | P77: 昨年実績 | Q77: =IF($F77="","",IFERROR(VLOOKUP($C77&"|"&$D77,科目表!$A$5:$B$200,2,FALSE),"※未登録")) -> 厚生費 | R77: =IF($F77="","",$I77+$J77+$K77) -> 0 | S77: =IF(OR($F77="",$P77="支払なし",$H77=0,$Q77=""),"",$Q77&"|S|"&(COUNTIF(S$4:S76,$Q77&"|S|*")+1)) -> 厚生費|S|1 | T77: =IF(OR($F77="",$P77="支払なし",$R77=0,$Q77=""),"",$Q77&"|L|"&(COUNTIF(T$4:T76,$Q77&"|L|*")+1)) | U77: =IF(OR($F77="",$A77=""),"",MOD(MONTH($A77)-4,12)+1) -> 3
A78: 44708 | C78: 事務費 | D78: 雑費 | E78: ＪＡ残高証明書（手数料）R4.3.31時点 | F78: 220 | G78: 2 | H78: =IF(G78=1,F78-I78-J78-K78,IF(G78=2,F78,0)) -> 220 | I78: =ROUND(IF(G78=1,F78*10/23,IF(G78=3,F78-J78-K78,IF(G78=4,F78,IF(G78=5,F78*10/11,IF(G78=7,F78*10/11,0))))),0) -> 0 | J78: =ROUND(IF(G78=1,F78/23,IF(G78=3,F78/12,IF(G78=5,F78-I78,IF(G78=8,F78,0)))),0) -> 0 | K78: =ROUND(IF(G78=1,F78/23,IF(G78=3,F78/12,IF(G78=6,F78,IF(G78=7,F78-I78,0)))),0) -> 0 | L78: =IF(G78=6,F78,0) -> 0 | M78: =IF(F78="",0,MONTH(A78)) -> 5 | P78: 昨年実績 | Q78: =IF($F78="","",IFERROR(VLOOKUP($C78&"|"&$D78,科目表!$A$5:$B$200,2,FALSE),"※未登録")) -> 事務費・雑費 | R78: =IF($F78="","",$I78+$J78+$K78) -> 0 | S78: =IF(OR($F78="",$P78="支払なし",$H78=0,$Q78=""),"",$Q78&"|S|"&(COUNTIF(S$4:S77,$Q78&"|S|*")+1)) -> 事務費・雑費|S|3 | T78: =IF(OR($F78="",$P78="支払なし",$R78=0,$Q78=""),"",$Q78&"|L|"&(COUNTIF(T$4:T77,$Q78&"|L|*")+1)) | U78: =IF(OR($F78="",$A78=""),"",MOD(MONTH($A78)-4,12)+1) -> 2
A79: 44711 | C79: 負担金 | D79: 負担金 | E79: 収入印紙 | F79: 5000 | G79: 3 | H79: =IF(G79=1,F79-I79-J79-K79,IF(G79=2,F79,0)) -> 0 | I79: =ROUND(IF(G79=1,F79*10/23,IF(G79=3,F79-J79-K79,IF(G79=4,F79,IF(G79=5,F79*10/11,IF(G79=7,F79*10/11,0))))),0) -> 4166 | J79: =ROUND(IF(G79=1,F79/23,IF(G79=3,F79/12,IF(G79=5,F79-I79,IF(G79=8,F79,0)))),0) -> 417 | K79: =ROUND(IF(G79=1,F79/23,IF(G79=3,F79/12,IF(G79=6,F79,IF(G79=7,F79-I79,0)))),0) -> 417 | L79: =IF(G79=6,F79,0) -> 0 | M79: =IF(F79="",0,MONTH(A79)) -> 5 | P79: 昨年実績 | Q79: =IF($F79="","",IFERROR(VLOOKUP($C79&"|"&$D79,科目表!$A$5:$B$200,2,FALSE),"※未登録")) -> 共済負担金等 | R79: =IF($F79="","",$I79+$J79+$K79) -> 5000 | S79: =IF(OR($F79="",$P79="支払なし",$H79=0,$Q79=""),"",$Q79&"|S|"&(COUNTIF(S$4:S78,$Q79&"|S|*")+1)) | T79: =IF(OR($F79="",$P79="支払なし",$R79=0,$Q79=""),"",$Q79&"|L|"&(COUNTIF(T$4:T78,$Q79&"|L|*")+1)) -> 共済負担金等|L|3 | U79: =IF(OR($F79="",$A79=""),"",MOD(MONTH($A79)-4,12)+1) -> 2
A80: 46183 | C80: 事務費 | D80: 送金料 | E80: 振込手数料（広銀）５月分 長期分 | F80: 12725 | G80: 3 | H80: =IF(G80=1,F80-I80-J80-K80,IF(G80=2,F80,0)) -> 0 | I80: =ROUND(IF(G80=1,F80*10/23,IF(G80=3,F80-J80-K80,IF(G80=4,F80,IF(G80=5,F80*10/11,IF(G80=7,F80*10/11,0))))),0) -> 10605 | J80: =ROUND(IF(G80=1,F80/23,IF(G80=3,F80/12,IF(G80=5,F80-I80,IF(G80=8,F80,0)))),0) -> 1060 | K80: =ROUND(IF(G80=1,F80/23,IF(G80=3,F80/12,IF(G80=6,F80,IF(G80=7,F80-I80,0)))),0) -> 1060 | L80: =IF(G80=6,F80,0) -> 0 | M80: =IF(F80="",0,MONTH(A80)) -> 6 | P80: 確認済 | Q80: =IF($F80="","",IFERROR(VLOOKUP($C80&"|"&$D80,科目表!$A$5:$B$200,2,FALSE),"※未登録")) -> 送金料 | R80: =IF($F80="","",$I80+$J80+$K80) -> 12725 | S80: =IF(OR($F80="",$P80="支払なし",$H80=0,$Q80=""),"",$Q80&"|S|"&(COUNTIF(S$4:S79,$Q80&"|S|*")+1)) | T80: =IF(OR($F80="",$P80="支払なし",$R80=0,$Q80=""),"",$Q80&"|L|"&(COUNTIF(T$4:T79,$Q80&"|L|*")+1)) -> 送金料|L|2 | U80: =IF(OR($F80="",$A80=""),"",MOD(MONTH($A80)-4,12)+1) -> 3
A81: 46183 | C81: 事務費 | D81: 送金料 | E81: 振込手数料（広銀）５月分 短期分 | F81: 135833 | G81: 2 | H81: =IF(G81=1,F81-I81-J81-K81,IF(G81=2,F81,0)) -> 135833 | I81: =ROUND(IF(G81=1,F81*10/23,IF(G81=3,F81-J81-K81,IF(G81=4,F81,IF(G81=5,F81*10/11,IF(G81=7,F81*10/11,0))))),0) -> 0 | J81: =ROUND(IF(G81=1,F81/23,IF(G81=3,F81/12,IF(G81=5,F81-I81,IF(G81=8,F81,0)))),0) -> 0 | K81: =ROUND(IF(G81=1,F81/23,IF(G81=3,F81/12,IF(G81=6,F81,IF(G81=7,F81-I81,0)))),0) -> 0 | L81: =IF(G81=6,F81,0) -> 0 | M81: =IF(F81="",0,MONTH(A81)) -> 6 | P81: 確認済 | Q81: =IF($F81="","",IFERROR(VLOOKUP($C81&"|"&$D81,科目表!$A$5:$B$200,2,FALSE),"※未登録")) -> 送金料 | R81: =IF($F81="","",$I81+$J81+$K81) -> 0 | S81: =IF(OR($F81="",$P81="支払なし",$H81=0,$Q81=""),"",$Q81&"|S|"&(COUNTIF(S$4:S80,$Q81&"|S|*")+1)) -> 送金料|S|3 | T81: =IF(OR($F81="",$P81="支払なし",$R81=0,$Q81=""),"",$Q81&"|L|"&(COUNTIF(T$4:T80,$Q81&"|L|*")+1)) | U81: =IF(OR($F81="",$A81=""),"",MOD(MONTH($A81)-4,12)+1) -> 3
A82: 46202 | C82: 役員報酬 | E82: 組合会６／２９ 学識経験監事 栗栖 一雄 | F82: 11000 | G82: 1 | H82: =IF(G82=1,F82-I82-J82-K82,IF(G82=2,F82,0)) -> 5261 | I82: =ROUND(IF(G82=1,F82*10/23,IF(G82=3,F82-J82-K82,IF(G82=4,F82,IF(G82=5,F82*10/11,IF(G82=7,F82*10/11,0))))),0) -> 4783 | J82: =ROUND(IF(G82=1,F82/23,IF(G82=3,F82/12,IF(G82=5,F82-I82,IF(G82=8,F82,0)))),0) -> 478 | K82: =ROUND(IF(G82=1,F82/23,IF(G82=3,F82/12,IF(G82=6,F82,IF(G82=7,F82-I82,0)))),0) -> 478 | L82: =IF(G82=6,F82,0) -> 0 | M82: =IF(F82="",0,MONTH(A82)) -> 6 | P82: 確認済 | Q82: =IF($F82="","",IFERROR(VLOOKUP($C82&"|"&$D82,科目表!$A$5:$B$200,2,FALSE),"※未登録")) -> 役員報酬 | R82: =IF($F82="","",$I82+$J82+$K82) -> 5739 | S82: =IF(OR($F82="",$P82="支払なし",$H82=0,$Q82=""),"",$Q82&"|S|"&(COUNTIF(S$4:S81,$Q82&"|S|*")+1)) -> 役員報酬|S|2 | T82: =IF(OR($F82="",$P82="支払なし",$R82=0,$Q82=""),"",$Q82&"|L|"&(COUNTIF(T$4:T81,$Q82&"|L|*")+1)) -> 役員報酬|L|2 | U82: =IF(OR($F82="",$A82=""),"",MOD(MONTH($A82)-4,12)+1) -> 3
A83: 46202 | C83: 旅費 | E83: 7/9全国理事研修会 香川県 山田理事 | F83: 14320 | G83: 1 | H83: =IF(G83=1,F83-I83-J83-K83,IF(G83=2,F83,0)) -> 6848 | I83: =ROUND(IF(G83=1,F83*10/23,IF(G83=3,F83-J83-K83,IF(G83=4,F83,IF(G83=5,F83*10/11,IF(G83=7,F83*10/11,0))))),0) -> 6226 | J83: =ROUND(IF(G83=1,F83/23,IF(G83=3,F83/12,IF(G83=5,F83-I83,IF(G83=8,F83,0)))),0) -> 623 | K83: =ROUND(IF(G83=1,F83/23,IF(G83=3,F83/12,IF(G83=6,F83,IF(G83=7,F83-I83,0)))),0) -> 623 | L83: =IF(G83=6,F83,0) -> 0 | M83: =IF(F83="",0,MONTH(A83)) -> 6 | P83: 確認済 | Q83: =IF($F83="","",IFERROR(VLOOKUP($C83&"|"&$D83,科目表!$A$5:$B$200,2,FALSE),"※未登録")) -> 旅費 | R83: =IF($F83="","",$I83+$J83+$K83) -> 7472 | S83: =IF(OR($F83="",$P83="支払なし",$H83=0,$Q83=""),"",$Q83&"|S|"&(COUNTIF(S$4:S82,$Q83&"|S|*")+1)) -> 旅費|S|5 | T83: =IF(OR($F83="",$P83="支払なし",$R83=0,$Q83=""),"",$Q83&"|L|"&(COUNTIF(T$4:T82,$Q83&"|L|*")+1)) -> 旅費|L|3 | U83: =IF(OR($F83="",$A83=""),"",MOD(MONTH($A83)-4,12)+1) -> 3
A84: 46202 | C84: 旅費 | E84: 7/9全国理事研修会 香川県 柴野理事 | F84: 14320 | G84: 1 | H84: =IF(G84=1,F84-I84-J84-K84,IF(G84=2,F84,0)) -> 6848 | I84: =ROUND(IF(G84=1,F84*10/23,IF(G84=3,F84-J84-K84,IF(G84=4,F84,IF(G84=5,F84*10/11,IF(G84=7,F84*10/11,0))))),0) -> 6226 | J84: =ROUND(IF(G84=1,F84/23,IF(G84=3,F84/12,IF(G84=5,F84-I84,IF(G84=8,F84,0)))),0) -> 623 | K84: =ROUND(IF(G84=1,F84/23,IF(G84=3,F84/12,IF(G84=6,F84,IF(G84=7,F84-I84,0)))),0) -> 623 | L84: =IF(G84=6,F84,0) -> 0 | M84: =IF(F84="",0,MONTH(A84)) -> 6 | P84: 確認済 | Q84: =IF($F84="","",IFERROR(VLOOKUP($C84&"|"&$D84,科目表!$A$5:$B$200,2,FALSE),"※未登録")) -> 旅費 | R84: =IF($F84="","",$I84+$J84+$K84) -> 7472 | S84: =IF(OR($F84="",$P84="支払なし",$H84=0,$Q84=""),"",$Q84&"|S|"&(COUNTIF(S$4:S83,$Q84&"|S|*")+1)) -> 旅費|S|6 | T84: =IF(OR($F84="",$P84="支払なし",$R84=0,$Q84=""),"",$Q84&"|L|"&(COUNTIF(T$4:T83,$Q84&"|L|*")+1)) -> 旅費|L|4 | U84: =IF(OR($F84="",$A84=""),"",MOD(MONTH($A84)-4,12)+1) -> 3
A85: 46202 | C85: 旅費 | E85: 7/9全国理事研修会 香川県 濵理事 | F85: 14320 | G85: 1 | H85: =IF(G85=1,F85-I85-J85-K85,IF(G85=2,F85,0)) -> 6848 | I85: =ROUND(IF(G85=1,F85*10/23,IF(G85=3,F85-J85-K85,IF(G85=4,F85,IF(G85=5,F85*10/11,IF(G85=7,F85*10/11,0))))),0) -> 6226 | J85: =ROUND(IF(G85=1,F85/23,IF(G85=3,F85/12,IF(G85=5,F85-I85,IF(G85=8,F85,0)))),0) -> 623 | K85: =ROUND(IF(G85=1,F85/23,IF(G85=3,F85/12,IF(G85=6,F85,IF(G85=7,F85-I85,0)))),0) -> 623 | L85: =IF(G85=6,F85,0) -> 0 | M85: =IF(F85="",0,MONTH(A85)) -> 6 | P85: 確認済 | Q85: =IF($F85="","",IFERROR(VLOOKUP($C85&"|"&$D85,科目表!$A$5:$B$200,2,FALSE),"※未登録")) -> 旅費 | R85: =IF($F85="","",$I85+$J85+$K85) -> 7472 | S85: =IF(OR($F85="",$P85="支払なし",$H85=0,$Q85=""),"",$Q85&"|S|"&(COUNTIF(S$4:S84,$Q85&"|S|*")+1)) -> 旅費|S|7 | T85: =IF(OR($F85="",$P85="支払なし",$R85=0,$Q85=""),"",$Q85&"|L|"&(COUNTIF(T$4:T84,$Q85&"|L|*")+1)) -> 旅費|L|5 | U85: =IF(OR($F85="",$A85=""),"",MOD(MONTH($A85)-4,12)+1) -> 3
A86: 46220 | C86: 委託費 | E86: ねんきん定期便（４月分）送付業務 | F86: 84057 | G86: 5 | H86: =IF(G86=1,F86-I86-J86-K86,IF(G86=2,F86,0)) -> 0 | I86: =ROUND(IF(G86=1,F86*10/23,IF(G86=3,F86-J86-K86,IF(G86=4,F86,IF(G86=5,F86*10/11,IF(G86=7,F86*10/11,0))))),0) -> 76415 | J86: =ROUND(IF(G86=1,F86/23,IF(G86=3,F86/12,IF(G86=5,F86-I86,IF(G86=8,F86,0)))),0) -> 7642 | K86: =ROUND(IF(G86=1,F86/23,IF(G86=3,F86/12,IF(G86=6,F86,IF(G86=7,F86-I86,0)))),0) -> 0 | L86: =IF(G86=6,F86,0) -> 0 | M86: =IF(F86="",0,MONTH(A86)) -> 7 | P86: 確認済 | Q86: =IF($F86="","",IFERROR(VLOOKUP($C86&"|"&$D86,科目表!$A$5:$B$200,2,FALSE),"※未登録")) -> 委託費 | R86: =IF($F86="","",$I86+$J86+$K86) -> 84057 | S86: =IF(OR($F86="",$P86="支払なし",$H86=0,$Q86=""),"",$Q86&"|S|"&(COUNTIF(S$4:S85,$Q86&"|S|*")+1)) | T86: =IF(OR($F86="",$P86="支払なし",$R86=0,$Q86=""),"",$Q86&"|L|"&(COUNTIF(T$4:T85,$Q86&"|L|*")+1)) -> 委託費|L|1 | U86: =IF(OR($F86="",$A86=""),"",MOD(MONTH($A86)-4,12)+1) -> 4
A87: 45831 | C87: 事務費 | D87: 通信運搬費 | E87: 切手等 | F87: 172500 | G87: 3 | H87: =IF(G87=1,F87-I87-J87-K87,IF(G87=2,F87,0)) -> 0 | I87: =ROUND(IF(G87=1,F87*10/23,IF(G87=3,F87-J87-K87,IF(G87=4,F87,IF(G87=5,F87*10/11,IF(G87=7,F87*10/11,0))))),0) -> 143750 | J87: =ROUND(IF(G87=1,F87/23,IF(G87=3,F87/12,IF(G87=5,F87-I87,IF(G87=8,F87,0)))),0) -> 14375 | K87: =ROUND(IF(G87=1,F87/23,IF(G87=3,F87/12,IF(G87=6,F87,IF(G87=7,F87-I87,0)))),0) -> 14375 | L87: =IF(G87=6,F87,0) -> 0 | M87: =IF(F87="",0,MONTH(A87)) -> 6 | P87: 昨年実績 | Q87: =IF($F87="","",IFERROR(VLOOKUP($C87&"|"&$D87,科目表!$A$5:$B$200,2,FALSE),"※未登録")) -> 通信運搬費 | R87: =IF($F87="","",$I87+$J87+$K87) -> 172500 | S87: =IF(OR($F87="",$P87="支払なし",$H87=0,$Q87=""),"",$Q87&"|S|"&(COUNTIF(S$4:S86,$Q87&"|S|*")+1)) | T87: =IF(OR($F87="",$P87="支払なし",$R87=0,$Q87=""),"",$Q87&"|L|"&(COUNTIF(T$4:T86,$Q87&"|L|*")+1)) -> 通信運搬費|L|2 | U87: =IF(OR($F87="",$A87=""),"",MOD(MONTH($A87)-4,12)+1) -> 3
A88: 43984 | C88: 負担金 | D88: 負担金 | E88: 収入印紙 | F88: 2000 | G88: 2 | H88: =IF(G88=1,F88-I88-J88-K88,IF(G88=2,F88,0)) -> 2000 | I88: =ROUND(IF(G88=1,F88*10/23,IF(G88=3,F88-J88-K88,IF(G88=4,F88,IF(G88=5,F88*10/11,IF(G88=7,F88*10/11,0))))),0) -> 0 | J88: =ROUND(IF(G88=1,F88/23,IF(G88=3,F88/12,IF(G88=5,F88-I88,IF(G88=8,F88,0)))),0) -> 0 | K88: =ROUND(IF(G88=1,F88/23,IF(G88=3,F88/12,IF(G88=6,F88,IF(G88=7,F88-I88,0)))),0) -> 0 | L88: =IF(G88=6,F88,0) -> 0 | M88: =IF(F88="",0,MONTH(A88)) -> 6 | P88: 昨年実績 | Q88: =IF($F88="","",IFERROR(VLOOKUP($C88&"|"&$D88,科目表!$A$5:$B$200,2,FALSE),"※未登録")) -> 共済負担金等 | R88: =IF($F88="","",$I88+$J88+$K88) -> 0 | S88: =IF(OR($F88="",$P88="支払なし",$H88=0,$Q88=""),"",$Q88&"|S|"&(COUNTIF(S$4:S87,$Q88&"|S|*")+1)) -> 共済負担金等|S|3 | T88: =IF(OR($F88="",$P88="支払なし",$R88=0,$Q88=""),"",$Q88&"|L|"&(COUNTIF(T$4:T87,$Q88&"|L|*")+1)) | U88: =IF(OR($F88="",$A88=""),"",MOD(MONTH($A88)-4,12)+1) -> 3
A89: 46202 | C89: 賃借料 | E89: パソコン（業務経理用）５月分 | F89: 5060 | G89: 2 | H89: =IF(G89=1,F89-I89-J89-K89,IF(G89=2,F89,0)) -> 5060 | I89: =ROUND(IF(G89=1,F89*10/23,IF(G89=3,F89-J89-K89,IF(G89=4,F89,IF(G89=5,F89*10/11,IF(G89=7,F89*10/11,0))))),0) -> 0 | J89: =ROUND(IF(G89=1,F89/23,IF(G89=3,F89/12,IF(G89=5,F89-I89,IF(G89=8,F89,0)))),0) -> 0 | K89: =ROUND(IF(G89=1,F89/23,IF(G89=3,F89/12,IF(G89=6,F89,IF(G89=7,F89-I89,0)))),0) -> 0 | L89: =IF(G89=6,F89,0) -> 0 | M89: =IF(F89="",0,MONTH(A89)) -> 6 | P89: 確認済 | Q89: =IF($F89="","",IFERROR(VLOOKUP($C89&"|"&$D89,科目表!$A$5:$B$200,2,FALSE),"※未登録")) -> 賃借料 | R89: =IF($F89="","",$I89+$J89+$K89) -> 0 | S89: =IF(OR($F89="",$P89="支払なし",$H89=0,$Q89=""),"",$Q89&"|S|"&(COUNTIF(S$4:S88,$Q89&"|S|*")+1)) -> 賃借料|S|4 | T89: =IF(OR($F89="",$P89="支払なし",$R89=0,$Q89=""),"",$Q89&"|L|"&(COUNTIF(T$4:T88,$Q89&"|L|*")+1)) | U89: =IF(OR($F89="",$A89=""),"",MOD(MONTH($A89)-4,12)+1) -> 3
A90: 44392 | C90: 賃借料 | E90: ﾊﾟｿｺﾝｳｨﾙｽ対策ｿﾌﾄ(業務用)ｻﾝﾈｯﾄ（5月分） | F90: 2090 | G90: 2 | H90: =IF(G90=1,F90-I90-J90-K90,IF(G90=2,F90,0)) -> 2090 | I90: =ROUND(IF(G90=1,F90*10/23,IF(G90=3,F90-J90-K90,IF(G90=4,F90,IF(G90=5,F90*10/11,IF(G90=7,F90*10/11,0))))),0) -> 0 | J90: =ROUND(IF(G90=1,F90/23,IF(G90=3,F90/12,IF(G90=5,F90-I90,IF(G90=8,F90,0)))),0) -> 0 | K90: =ROUND(IF(G90=1,F90/23,IF(G90=3,F90/12,IF(G90=6,F90,IF(G90=7,F90-I90,0)))),0) -> 0 | L90: =IF(G90=6,F90,0) -> 0 | M90: =IF(F90="",0,MONTH(A90)) -> 7 | P90: 昨年実績 | Q90: =IF($F90="","",IFERROR(VLOOKUP($C90&"|"&$D90,科目表!$A$5:$B$200,2,FALSE),"※未登録")) -> 賃借料 | R90: =IF($F90="","",$I90+$J90+$K90) -> 0 | S90: =IF(OR($F90="",$P90="支払なし",$H90=0,$Q90=""),"",$Q90&"|S|"&(COUNTIF(S$4:S89,$Q90&"|S|*")+1)) -> 賃借料|S|5 | T90: =IF(OR($F90="",$P90="支払なし",$R90=0,$Q90=""),"",$Q90&"|L|"&(COUNTIF(T$4:T89,$Q90&"|L|*")+1)) | U90: =IF(OR($F90="",$A90=""),"",MOD(MONTH($A90)-4,12)+1) -> 4
A91: 46188 | C91: 賃金 | E91: 臨時職員賃金５月分 天畠吏梨外１名分（短期１００％） | F91: 365040 | G91: 2 | H91: =IF(G91=1,F91-I91-J91-K91,IF(G91=2,F91,0)) -> 365040 | I91: =ROUND(IF(G91=1,F91*10/23,IF(G91=3,F91-J91-K91,IF(G91=4,F91,IF(G91=5,F91*10/11,IF(G91=7,F91*10/11,0))))),0) -> 0 | J91: =ROUND(IF(G91=1,F91/23,IF(G91=3,F91/12,IF(G91=5,F91-I91,IF(G91=8,F91,0)))),0) -> 0 | K91: =ROUND(IF(G91=1,F91/23,IF(G91=3,F91/12,IF(G91=6,F91,IF(G91=7,F91-I91,0)))),0) -> 0 | L91: =IF(G91=6,F91,0) -> 0 | M91: =IF(F91="",0,MONTH(A91)) -> 6 | P91: 確認済 | Q91: =IF($F91="","",IFERROR(VLOOKUP($C91&"|"&$D91,科目表!$A$5:$B$200,2,FALSE),"※未登録")) -> 賃金 | R91: =IF($F91="","",$I91+$J91+$K91) -> 0 | S91: =IF(OR($F91="",$P91="支払なし",$H91=0,$Q91=""),"",$Q91&"|S|"&(COUNTIF(S$4:S90,$Q91&"|S|*")+1)) -> 賃金|S|2 | T91: =IF(OR($F91="",$P91="支払なし",$R91=0,$Q91=""),"",$Q91&"|L|"&(COUNTIF(T$4:T90,$Q91&"|L|*")+1)) | U91: =IF(OR($F91="",$A91=""),"",MOD(MONTH($A91)-4,12)+1) -> 3
A92: 46210 | C92: 負担金 | D92: 労災・雇用保険料 | E92: 労災保険料 雇用保険料 一般拠出金（長期分） | F92: 71152 | G92: 3 | H92: =IF(G92=1,F92-I92-J92-K92,IF(G92=2,F92,0)) -> 0 | I92: =ROUND(IF(G92=1,F92*10/23,IF(G92=3,F92-J92-K92,IF(G92=4,F92,IF(G92=5,F92*10/11,IF(G92=7,F92*10/11,0))))),0) -> 59294 | J92: =ROUND(IF(G92=1,F92/23,IF(G92=3,F92/12,IF(G92=5,F92-I92,IF(G92=8,F92,0)))),0) -> 5929 | K92: =ROUND(IF(G92=1,F92/23,IF(G92=3,F92/12,IF(G92=6,F92,IF(G92=7,F92-I92,0)))),0) -> 5929 | L92: =IF(G92=6,F92,0) -> 0 | M92: =IF(F92="",0,MONTH(A92)) -> 7 | P92: 確認済 | Q92: =IF($F92="","",IFERROR(VLOOKUP($C92&"|"&$D92,科目表!$A$5:$B$200,2,FALSE),"※未登録")) -> 労災・雇用保険料 | R92: =IF($F92="","",$I92+$J92+$K92) -> 71152 | S92: =IF(OR($F92="",$P92="支払なし",$H92=0,$Q92=""),"",$Q92&"|S|"&(COUNTIF(S$4:S91,$Q92&"|S|*")+1)) | T92: =IF(OR($F92="",$P92="支払なし",$R92=0,$Q92=""),"",$Q92&"|L|"&(COUNTIF(T$4:T91,$Q92&"|L|*")+1)) -> 労災・雇用保険料|L|1 | U92: =IF(OR($F92="",$A92=""),"",MOD(MONTH($A92)-4,12)+1) -> 4
A93: 46210 | C93: 負担金 | D93: 労災・雇用保険料 | E93: 労災保険料 雇用保険料 一般拠出金（短期分） | F93: 108215 | G93: 2 | H93: =IF(G93=1,F93-I93-J93-K93,IF(G93=2,F93,0)) -> 108215 | I93: =ROUND(IF(G93=1,F93*10/23,IF(G93=3,F93-J93-K93,IF(G93=4,F93,IF(G93=5,F93*10/11,IF(G93=7,F93*10/11,0))))),0) -> 0 | J93: =ROUND(IF(G93=1,F93/23,IF(G93=3,F93/12,IF(G93=5,F93-I93,IF(G93=8,F93,0)))),0) -> 0 | K93: =ROUND(IF(G93=1,F93/23,IF(G93=3,F93/12,IF(G93=6,F93,IF(G93=7,F93-I93,0)))),0) -> 0 | L93: =IF(G93=6,F93,0) -> 0 | M93: =IF(F93="",0,MONTH(A93)) -> 7 | P93: 確認済 | Q93: =IF($F93="","",IFERROR(VLOOKUP($C93&"|"&$D93,科目表!$A$5:$B$200,2,FALSE),"※未登録")) -> 労災・雇用保険料 | R93: =IF($F93="","",$I93+$J93+$K93) -> 0 | S93: =IF(OR($F93="",$P93="支払なし",$H93=0,$Q93=""),"",$Q93&"|S|"&(COUNTIF(S$4:S92,$Q93&"|S|*")+1)) -> 労災・雇用保険料|S|1 | T93: =IF(OR($F93="",$P93="支払なし",$R93=0,$Q93=""),"",$Q93&"|L|"&(COUNTIF(T$4:T92,$Q93&"|L|*")+1)) | U93: =IF(OR($F93="",$A93=""),"",MOD(MONTH($A93)-4,12)+1) -> 4
A94: 46203 | C94: 事務費 | D94: 事務用消耗品費 | E94: 鋳造ゴム印 3号以下 51字 他5点 | F94: 24508 | G94: 2 | H94: =IF(G94=1,F94-I94-J94-K94,IF(G94=2,F94,0)) -> 24508 | I94: =ROUND(IF(G94=1,F94*10/23,IF(G94=3,F94-J94-K94,IF(G94=4,F94,IF(G94=5,F94*10/11,IF(G94=7,F94*10/11,0))))),0) -> 0 | J94: =ROUND(IF(G94=1,F94/23,IF(G94=3,F94/12,IF(G94=5,F94-I94,IF(G94=8,F94,0)))),0) -> 0 | K94: =ROUND(IF(G94=1,F94/23,IF(G94=3,F94/12,IF(G94=6,F94,IF(G94=7,F94-I94,0)))),0) -> 0 | L94: =IF(G94=6,F94,0) -> 0 | M94: =IF(F94="",0,MONTH(A94)) -> 6 | P94: 確認済 | Q94: =IF($F94="","",IFERROR(VLOOKUP($C94&"|"&$D94,科目表!$A$5:$B$200,2,FALSE),"※未登録")) -> 事務用消耗品費 | R94: =IF($F94="","",$I94+$J94+$K94) -> 0 | S94: =IF(OR($F94="",$P94="支払なし",$H94=0,$Q94=""),"",$Q94&"|S|"&(COUNTIF(S$4:S93,$Q94&"|S|*")+1)) -> 事務用消耗品費|S|8 | T94: =IF(OR($F94="",$P94="支払なし",$R94=0,$Q94=""),"",$Q94&"|L|"&(COUNTIF(T$4:T93,$Q94&"|L|*")+1)) | U94: =IF(OR($F94="",$A94=""),"",MOD(MONTH($A94)-4,12)+1) -> 3
A95: 45835 | C95: 事務費 | D95: 事務用消耗品費 | E95: 色上質紙 厚口／５００枚／Ａ４／浅黄 １包 外９点 | F95: 16374 | G95: 3 | H95: =IF(G95=1,F95-I95-J95-K95,IF(G95=2,F95,0)) -> 0 | I95: =ROUND(IF(G95=1,F95*10/23,IF(G95=3,F95-J95-K95,IF(G95=4,F95,IF(G95=5,F95*10/11,IF(G95=7,F95*10/11,0))))),0) -> 13644 | J95: =ROUND(IF(G95=1,F95/23,IF(G95=3,F95/12,IF(G95=5,F95-I95,IF(G95=8,F95,0)))),0) -> 1365 | K95: =ROUND(IF(G95=1,F95/23,IF(G95=3,F95/12,IF(G95=6,F95,IF(G95=7,F95-I95,0)))),0) -> 1365 | L95: =IF(G95=6,F95,0) -> 0 | M95: =IF(F95="",0,MONTH(A95)) -> 6 | P95: 昨年実績 | Q95: =IF($F95="","",IFERROR(VLOOKUP($C95&"|"&$D95,科目表!$A$5:$B$200,2,FALSE),"※未登録")) -> 事務用消耗品費 | R95: =IF($F95="","",$I95+$J95+$K95) -> 16374 | S95: =IF(OR($F95="",$P95="支払なし",$H95=0,$Q95=""),"",$Q95&"|S|"&(COUNTIF(S$4:S94,$Q95&"|S|*")+1)) | T95: =IF(OR($F95="",$P95="支払なし",$R95=0,$Q95=""),"",$Q95&"|L|"&(COUNTIF(T$4:T94,$Q95&"|L|*")+1)) -> 事務用消耗品費|L|5 | U95: =IF(OR($F95="",$A95=""),"",MOD(MONTH($A95)-4,12)+1) -> 3
A96: 46171 | C96: 事務費 | D96: 通信運搬費 | E96: 料金後納利用料（4月分） | F96: 147246 | G96: 3 | H96: =IF(G96=1,F96-I96-J96-K96,IF(G96=2,F96,0)) -> 0 | I96: =ROUND(IF(G96=1,F96*10/23,IF(G96=3,F96-J96-K96,IF(G96=4,F96,IF(G96=5,F96*10/11,IF(G96=7,F96*10/11,0))))),0) -> 122704 | J96: =ROUND(IF(G96=1,F96/23,IF(G96=3,F96/12,IF(G96=5,F96-I96,IF(G96=8,F96,0)))),0) -> 12271 | K96: =ROUND(IF(G96=1,F96/23,IF(G96=3,F96/12,IF(G96=6,F96,IF(G96=7,F96-I96,0)))),0) -> 12271 | L96: =IF(G96=6,F96,0) -> 0 | M96: =IF(F96="",0,MONTH(A96)) -> 5 | P96: 確認済 | Q96: =IF($F96="","",IFERROR(VLOOKUP($C96&"|"&$D96,科目表!$A$5:$B$200,2,FALSE),"※未登録")) -> 通信運搬費 | R96: =IF($F96="","",$I96+$J96+$K96) -> 147246 | S96: =IF(OR($F96="",$P96="支払なし",$H96=0,$Q96=""),"",$Q96&"|S|"&(COUNTIF(S$4:S95,$Q96&"|S|*")+1)) | T96: =IF(OR($F96="",$P96="支払なし",$R96=0,$Q96=""),"",$Q96&"|L|"&(COUNTIF(T$4:T95,$Q96&"|L|*")+1)) -> 通信運搬費|L|3 | U96: =IF(OR($F96="",$A96=""),"",MOD(MONTH($A96)-4,12)+1) -> 2
A97: 46171 | C97: 事務費 | D97: 通信運搬費 | E97: 料金後納利用料（4月分） | F97: 196030 | G97: 2 | H97: =IF(G97=1,F97-I97-J97-K97,IF(G97=2,F97,0)) -> 196030 | I97: =ROUND(IF(G97=1,F97*10/23,IF(G97=3,F97-J97-K97,IF(G97=4,F97,IF(G97=5,F97*10/11,IF(G97=7,F97*10/11,0))))),0) -> 0 | J97: =ROUND(IF(G97=1,F97/23,IF(G97=3,F97/12,IF(G97=5,F97-I97,IF(G97=8,F97,0)))),0) -> 0 | K97: =ROUND(IF(G97=1,F97/23,IF(G97=3,F97/12,IF(G97=6,F97,IF(G97=7,F97-I97,0)))),0) -> 0 | L97: =IF(G97=6,F97,0) -> 0 | M97: =IF(F97="",0,MONTH(A97)) -> 5 | P97: 確認済 | Q97: =IF($F97="","",IFERROR(VLOOKUP($C97&"|"&$D97,科目表!$A$5:$B$200,2,FALSE),"※未登録")) -> 通信運搬費 | R97: =IF($F97="","",$I97+$J97+$K97) -> 0 | S97: =IF(OR($F97="",$P97="支払なし",$H97=0,$Q97=""),"",$Q97&"|S|"&(COUNTIF(S$4:S96,$Q97&"|S|*")+1)) -> 通信運搬費|S|8 | T97: =IF(OR($F97="",$P97="支払なし",$R97=0,$Q97=""),"",$Q97&"|L|"&(COUNTIF(T$4:T96,$Q97&"|L|*")+1)) | U97: =IF(OR($F97="",$A97=""),"",MOD(MONTH($A97)-4,12)+1) -> 2
A98: 44368 | C98: 事務費 | D98: 通信運搬費 | E98: 電話料金（５月使用・６月請求分） | F98: 5407 | G98: 2 | H98: =IF(G98=1,F98-I98-J98-K98,IF(G98=2,F98,0)) -> 5407 | I98: =ROUND(IF(G98=1,F98*10/23,IF(G98=3,F98-J98-K98,IF(G98=4,F98,IF(G98=5,F98*10/11,IF(G98=7,F98*10/11,0))))),0) -> 0 | J98: =ROUND(IF(G98=1,F98/23,IF(G98=3,F98/12,IF(G98=5,F98-I98,IF(G98=8,F98,0)))),0) -> 0 | K98: =ROUND(IF(G98=1,F98/23,IF(G98=3,F98/12,IF(G98=6,F98,IF(G98=7,F98-I98,0)))),0) -> 0 | L98: =IF(G98=6,F98,0) -> 0 | M98: =IF(F98="",0,MONTH(A98)) -> 6 | P98: 昨年実績 | Q98: =IF($F98="","",IFERROR(VLOOKUP($C98&"|"&$D98,科目表!$A$5:$B$200,2,FALSE),"※未登録")) -> 通信運搬費 | R98: =IF($F98="","",$I98+$J98+$K98) -> 0 | S98: =IF(OR($F98="",$P98="支払なし",$H98=0,$Q98=""),"",$Q98&"|S|"&(COUNTIF(S$4:S97,$Q98&"|S|*")+1)) -> 通信運搬費|S|9 | T98: =IF(OR($F98="",$P98="支払なし",$R98=0,$Q98=""),"",$Q98&"|L|"&(COUNTIF(T$4:T97,$Q98&"|L|*")+1)) | U98: =IF(OR($F98="",$A98=""),"",MOD(MONTH($A98)-4,12)+1) -> 3
A99: 46192 | C99: 委託費 | E99: レセプト電子データ提供料（３月診療分） | F99: 66423 | G99: 2 | H99: =IF(G99=1,F99-I99-J99-K99,IF(G99=2,F99,0)) -> 66423 | I99: =ROUND(IF(G99=1,F99*10/23,IF(G99=3,F99-J99-K99,IF(G99=4,F99,IF(G99=5,F99*10/11,IF(G99=7,F99*10/11,0))))),0) -> 0 | J99: =ROUND(IF(G99=1,F99/23,IF(G99=3,F99/12,IF(G99=5,F99-I99,IF(G99=8,F99,0)))),0) -> 0 | K99: =ROUND(IF(G99=1,F99/23,IF(G99=3,F99/12,IF(G99=6,F99,IF(G99=7,F99-I99,0)))),0) -> 0 | L99: =IF(G99=6,F99,0) -> 0 | M99: =IF(F99="",0,MONTH(A99)) -> 6 | P99: 確認済 | Q99: =IF($F99="","",IFERROR(VLOOKUP($C99&"|"&$D99,科目表!$A$5:$B$200,2,FALSE),"※未登録")) -> 委託費 | R99: =IF($F99="","",$I99+$J99+$K99) -> 0 | S99: =IF(OR($F99="",$P99="支払なし",$H99=0,$Q99=""),"",$Q99&"|S|"&(COUNTIF(S$4:S98,$Q99&"|S|*")+1)) -> 委託費|S|10 | T99: =IF(OR($F99="",$P99="支払なし",$R99=0,$Q99=""),"",$Q99&"|L|"&(COUNTIF(T$4:T98,$Q99&"|L|*")+1)) | U99: =IF(OR($F99="",$A99=""),"",MOD(MONTH($A99)-4,12)+1) -> 3
A100: 46192 | C100: 職員給与 | D100: 非常勤職員手当 | E100: ６月分給与（長期分） | F100: 380800 | G100: 3 | H100: =IF(G100=1,F100-I100-J100-K100,IF(G100=2,F100,0)) -> 0 | I100: =ROUND(IF(G100=1,F100*10/23,IF(G100=3,F100-J100-K100,IF(G100=4,F100,IF(G100=5,F100*10/11,IF(G100=7,F100*10/11,0))))),0) -> 317334 | J100: =ROUND(IF(G100=1,F100/23,IF(G100=3,F100/12,IF(G100=5,F100-I100,IF(G100=8,F100,0)))),0) -> 31733 | K100: =ROUND(IF(G100=1,F100/23,IF(G100=3,F100/12,IF(G100=6,F100,IF(G100=7,F100-I100,0)))),0) -> 31733 | L100: =IF(G100=6,F100,0) -> 0 | M100: =IF(F100="",0,MONTH(A100)) -> 6 | P100: 確認済 | Q100: =IF($F100="","",IFERROR(VLOOKUP($C100&"|"&$D100,科目表!$A$5:$B$200,2,FALSE),"※未登録")) -> 非常勤職員手当 | R100: =IF($F100="","",$I100+$J100+$K100) -> 380800 | S100: =IF(OR($F100="",$P100="支払なし",$H100=0,$Q100=""),"",$Q100&"|S|"&(COUNTIF(S$4:S99,$Q100&"|S|*")+1)) | T100: =IF(OR($F100="",$P100="支払なし",$R100=0,$Q100=""),"",$Q100&"|L|"&(COUNTIF(T$4:T99,$Q100&"|L|*")+1)) -> 非常勤職員手当|L|3 | U100: =IF(OR($F100="",$A100=""),"",MOD(MONTH($A100)-4,12)+1) -> 3
...

Sheet 決算整理
A1: 【 決 算 整 理 】 令 和 ８ 年 度 業 務 経 理 経 費 給 付 区 分 別 執 行 額 一 覧 表
K2: （単位:円）
P3: ←支払担当者が「未確認」、経理担当者が伝票確認後に「確認済」
A4: 支出日 | B4: 決算整理 区分 | C4: 中項目 | D4: 小項目 | E4: 摘要 | F4: 執行額 | G4: 経費区分 | H4: 短期 | I4: 厚年 | J4: 経過的 | K4: 退職等 | L4: （再掲） 退職等単独 | P4: 状態 | Q4: 費目 (自動) | R4: 長期額 (自動) | S4: 短期 通番キー | T4: 長期 通番キー | U4: 計上列 (自動)
A5: 43951 | B5: 未払金 | C5: 委託費 | E5: 人・給システム、庶務事務システム及び端末の使用料（短期分） | F5: 17630 | G5: 2 | H5: =IF(G5=1,F5-I5-J5-K5,IF(G5=2,F5,0)) -> 17630 | I5: =ROUND(IF(G5=1,F5*10/23,IF(G5=3,F5-J5-K5,IF(G5=4,F5,IF(G5=5,F5*10/11,IF(G5=7,F5*10/11,0))))),0) -> 0 | J5: =ROUND(IF(G5=1,F5/23,IF(G5=3,F5/12,IF(G5=5,F5-I5,IF(G5=8,F5,0)))),0) -> 0 | K5: =ROUND(IF(G5=1,F5/23,IF(G5=3,F5/12,IF(G5=6,F5,IF(G5=7,F5-I5,0)))),0) -> 0 | L5: =IF(G5=6,F5,0) -> 0 | N5: 非常勤職員手当 | P5: 昨年実績 | Q5: =IF($F5="","",IFERROR(VLOOKUP($C5&"|"&$D5,科目表!$A$5:$B$200,2,FALSE),"※未登録")) -> 委託費 | R5: =IF($F5="","",$I5+$J5+$K5) -> 0 | S5: =IF(OR($F5="",$P5="支払なし",$H5=0,$Q5=""),"",$Q5&"|S|"&(COUNTIF(S$4:S4,$Q5&"|S|*")+1)) -> 委託費|S|1 | T5: =IF(OR($F5="",$P5="支払なし",$R5=0,$Q5=""),"",$Q5&"|L|"&(COUNTIF(T$4:T4,$Q5&"|L|*")+1)) | U5: =IF($F5="","",13) -> 13
A6: 44666 | B6: 未払金 | C6: 事務費 | D6: 図書印刷費 | E6: 窓付角形封筒（のり付）１，０００枚ほか | F6: 149600 | G6: 3 | H6: =IF(G6=1,F6-I6-J6-K6,IF(G6=2,F6,0)) -> 0 | I6: =ROUND(IF(G6=1,F6*10/23,IF(G6=3,F6-J6-K6,IF(G6=4,F6,IF(G6=5,F6*10/11,IF(G6=7,F6*10/11,0))))),0) -> 124666 | J6: =ROUND(IF(G6=1,F6/23,IF(G6=3,F6/12,IF(G6=5,F6-I6,IF(G6=8,F6,0)))),0) -> 12467 | K6: =ROUND(IF(G6=1,F6/23,IF(G6=3,F6/12,IF(G6=6,F6,IF(G6=7,F6-I6,0)))),0) -> 12467 | L6: =IF(G6=6,F6,0) -> 0 | P6: 昨年実績 | Q6: =IF($F6="","",IFERROR(VLOOKUP($C6&"|"&$D6,科目表!$A$5:$B$200,2,FALSE),"※未登録")) -> 図書印刷費 | R6: =IF($F6="","",$I6+$J6+$K6) -> 149600 | S6: =IF(OR($F6="",$P6="支払なし",$H6=0,$Q6=""),"",$Q6&"|S|"&(COUNTIF(S$4:S5,$Q6&"|S|*")+1)) | T6: =IF(OR($F6="",$P6="支払なし",$R6=0,$Q6=""),"",$Q6&"|L|"&(COUNTIF(T$4:T5,$Q6&"|L|*")+1)) -> 図書印刷費|L|1 | U6: =IF($F6="","",13) -> 13
A7: 45777 | B7: 未払金 | C7: 事務費 | D7: 図書印刷費 | E7: 厚生法規総覧追録 ５９６６－５９７５号 | F7: 33154 | G7: 2 | H7: =IF(G7=1,F7-I7-J7-K7,IF(G7=2,F7,0)) -> 33154 | I7: =ROUND(IF(G7=1,F7*10/23,IF(G7=3,F7-J7-K7,IF(G7=4,F7,IF(G7=5,F7*10/11,IF(G7=7,F7*10/11,0))))),0) -> 0 | J7: =ROUND(IF(G7=1,F7/23,IF(G7=3,F7/12,IF(G7=5,F7-I7,IF(G7=8,F7,0)))),0) -> 0 | K7: =ROUND(IF(G7=1,F7/23,IF(G7=3,F7/12,IF(G7=6,F7,IF(G7=7,F7-I7,0)))),0) -> 0 | L7: =IF(G7=6,F7,0) -> 0 | P7: 昨年実績 | Q7: =IF($F7="","",IFERROR(VLOOKUP($C7&"|"&$D7,科目表!$A$5:$B$200,2,FALSE),"※未登録")) -> 図書印刷費 | R7: =IF($F7="","",$I7+$J7+$K7) -> 0 | S7: =IF(OR($F7="",$P7="支払なし",$H7=0,$Q7=""),"",$Q7&"|S|"&(COUNTIF(S$4:S6,$Q7&"|S|*")+1)) -> 図書印刷費|S|1 | T7: =IF(OR($F7="",$P7="支払なし",$R7=0,$Q7=""),"",$Q7&"|L|"&(COUNTIF(T$4:T6,$Q7&"|L|*")+1)) | U7: =IF($F7="","",13) -> 13
A8: 45777 | B8: 未払金 | C8: 事務費 | D8: 図書印刷費 | E8: 長３封筒 ４，０００枚 | F8: 48400 | G8: 2 | H8: =IF(G8=1,F8-I8-J8-K8,IF(G8=2,F8,0)) -> 48400 | I8: =ROUND(IF(G8=1,F8*10/23,IF(G8=3,F8-J8-K8,IF(G8=4,F8,IF(G8=5,F8*10/11,IF(G8=7,F8*10/11,0))))),0) -> 0 | J8: =ROUND(IF(G8=1,F8/23,IF(G8=3,F8/12,IF(G8=5,F8-I8,IF(G8=8,F8,0)))),0) -> 0 | K8: =ROUND(IF(G8=1,F8/23,IF(G8=3,F8/12,IF(G8=6,F8,IF(G8=7,F8-I8,0)))),0) -> 0 | L8: =IF(G8=6,F8,0) -> 0 | P8: 昨年実績 | Q8: =IF($F8="","",IFERROR(VLOOKUP($C8&"|"&$D8,科目表!$A$5:$B$200,2,FALSE),"※未登録")) -> 図書印刷費 | R8: =IF($F8="","",$I8+$J8+$K8) -> 0 | S8: =IF(OR($F8="",$P8="支払なし",$H8=0,$Q8=""),"",$Q8&"|S|"&(COUNTIF(S$4:S7,$Q8&"|S|*")+1)) -> 図書印刷費|S|2 | T8: =IF(OR($F8="",$P8="支払なし",$R8=0,$Q8=""),"",$Q8&"|L|"&(COUNTIF(T$4:T7,$Q8&"|L|*")+1)) | U8: =IF($F8="","",13) -> 13
A9: 46127 | B9: 未払金 | C9: 委託費 | E9: 個別システム保守料（令７年度）短期分 | F9: 360360 | G9: 2 | H9: =IF(G9=1,F9-I9-J9-K9,IF(G9=2,F9,0)) -> 360360 | I9: =ROUND(IF(G9=1,F9*10/23,IF(G9=3,F9-J9-K9,IF(G9=4,F9,IF(G9=5,F9*10/11,IF(G9=7,F9*10/11,0))))),0) -> 0 | J9: =ROUND(IF(G9=1,F9/23,IF(G9=3,F9/12,IF(G9=5,F9-I9,IF(G9=8,F9,0)))),0) -> 0 | K9: =ROUND(IF(G9=1,F9/23,IF(G9=3,F9/12,IF(G9=6,F9,IF(G9=7,F9-I9,0)))),0) -> 0 | L9: =IF(G9=6,F9,0) -> 0 | N9: 退職給与金 | P9: 昨年実績 | Q9: =IF($F9="","",IFERROR(VLOOKUP($C9&"|"&$D9,科目表!$A$5:$B$200,2,FALSE),"※未登録")) -> 委託費 | R9: =IF($F9="","",$I9+$J9+$K9) -> 0 | S9: =IF(OR($F9="",$P9="支払なし",$H9=0,$Q9=""),"",$Q9&"|S|"&(COUNTIF(S$4:S8,$Q9&"|S|*")+1)) -> 委託費|S|2 | T9: =IF(OR($F9="",$P9="支払なし",$R9=0,$Q9=""),"",$Q9&"|L|"&(COUNTIF(T$4:T8,$Q9&"|L|*")+1)) | U9: =IF($F9="","",13) -> 13
A10: 43951 | B10: 未払金 | C10: 委託費 | E10: 短期給付等に係る個人番号管理システム端末保守サービス（３月分） | F10: 385 | G10: 2 | H10: =IF(G10=1,F10-I10-J10-K10,IF(G10=2,F10,0)) -> 385 | I10: =ROUND(IF(G10=1,F10*10/23,IF(G10=3,F10-J10-K10,IF(G10=4,F10,IF(G10=5,F10*10/11,IF(G10=7,F10*10/11,0))))),0) -> 0 | J10: =ROUND(IF(G10=1,F10/23,IF(G10=3,F10/12,IF(G10=5,F10-I10,IF(G10=8,F10,0)))),0) -> 0 | K10: =ROUND(IF(G10=1,F10/23,IF(G10=3,F10/12,IF(G10=6,F10,IF(G10=7,F10-I10,0)))),0) -> 0 | L10: =IF(G10=6,F10,0) -> 0 | N10: 健康診断費 | P10: 昨年実績 | Q10: =IF($F10="","",IFERROR(VLOOKUP($C10&"|"&$D10,科目表!$A$5:$B$200,2,FALSE),"※未登録")) -> 委託費 | R10: =IF($F10="","",$I10+$J10+$K10) -> 0 | S10: =IF(OR($F10="",$P10="支払なし",$H10=0,$Q10=""),"",$Q10&"|S|"&(COUNTIF(S$4:S9,$Q10&"|S|*")+1)) -> 委託費|S|3 | T10: =IF(OR($F10="",$P10="支払なし",$R10=0,$Q10=""),"",$Q10&"|L|"&(COUNTIF(T$4:T9,$Q10&"|L|*")+1)) | U10: =IF($F10="","",13) -> 13
A11: 44679 | B11: 未払金 | C11: 委託費 | E11: 病院機構人給システム（ネットワーク等経費）短期 | F11: 43626 | G11: 2 | H11: =IF(G11=1,F11-I11-J11-K11,IF(G11=2,F11,0)) -> 43626 | I11: =ROUND(IF(G11=1,F11*10/23,IF(G11=3,F11-J11-K11,IF(G11=4,F11,IF(G11=5,F11*10/11,IF(G11=7,F11*10/11,0))))),0) -> 0 | J11: =ROUND(IF(G11=1,F11/23,IF(G11=3,F11/12,IF(G11=5,F11-I11,IF(G11=8,F11,0)))),0) -> 0 | K11: =ROUND(IF(G11=1,F11/23,IF(G11=3,F11/12,IF(G11=6,F11,IF(G11=7,F11-I11,0)))),0) -> 0 | L11: =IF(G11=6,F11,0) -> 0 | N11: 事務用消耗品費 | P11: 昨年実績 | Q11: =IF($F11="","",IFERROR(VLOOKUP($C11&"|"&$D11,科目表!$A$5:$B$200,2,FALSE),"※未登録")) -> 委託費 | R11: =IF($F11="","",$I11+$J11+$K11) -> 0 | S11: =IF(OR($F11="",$P11="支払なし",$H11=0,$Q11=""),"",$Q11&"|S|"&(COUNTIF(S$4:S10,$Q11&"|S|*")+1)) -> 委託費|S|4 | T11: =IF(OR($F11="",$P11="支払なし",$R11=0,$Q11=""),"",$Q11&"|L|"&(COUNTIF(T$4:T10,$Q11&"|L|*")+1)) | U11: =IF($F11="","",13) -> 13
A12: 43951 | B12: 未払金 | C12: 委託費 | E12: 清掃・警備・ごみ処理（１０～３月分） | F12: 4154 | G12: 2 | H12: =IF(G12=1,F12-I12-J12-K12,IF(G12=2,F12,0)) -> 4154 | I12: =ROUND(IF(G12=1,F12*10/23,IF(G12=3,F12-J12-K12,IF(G12=4,F12,IF(G12=5,F12*10/11,IF(G12=7,F12*10/11,0))))),0) -> 0 | J12: =ROUND(IF(G12=1,F12/23,IF(G12=3,F12/12,IF(G12=5,F12-I12,IF(G12=8,F12,0)))),0) -> 0 | K12: =ROUND(IF(G12=1,F12/23,IF(G12=3,F12/12,IF(G12=6,F12,IF(G12=7,F12-I12,0)))),0) -> 0 | L12: =IF(G12=6,F12,0) -> 0 | N12: 図書印刷費 | P12: 昨年実績 | Q12: =IF($F12="","",IFERROR(VLOOKUP($C12&"|"&$D12,科目表!$A$5:$B$200,2,FALSE),"※未登録")) -> 委託費 | R12: =IF($F12="","",$I12+$J12+$K12) -> 0 | S12: =IF(OR($F12="",$P12="支払なし",$H12=0,$Q12=""),"",$Q12&"|S|"&(COUNTIF(S$4:S11,$Q12&"|S|*")+1)) -> 委託費|S|5 | T12: =IF(OR($F12="",$P12="支払なし",$R12=0,$Q12=""),"",$Q12&"|L|"&(COUNTIF(T$4:T11,$Q12&"|L|*")+1)) | U12: =IF($F12="","",13) -> 13
A13: 43951 | B13: 未払金 | C13: 委託費 | E13: 柔整等療養費支給申請書の入力（３月分） | F13: 61281 | G13: 2 | H13: =IF(G13=1,F13-I13-J13-K13,IF(G13=2,F13,0)) -> 61281 | I13: =ROUND(IF(G13=1,F13*10/23,IF(G13=3,F13-J13-K13,IF(G13=4,F13,IF(G13=5,F13*10/11,IF(G13=7,F13*10/11,0))))),0) -> 0 | J13: =ROUND(IF(G13=1,F13/23,IF(G13=3,F13/12,IF(G13=5,F13-I13,IF(G13=8,F13,0)))),0) -> 0 | K13: =ROUND(IF(G13=1,F13/23,IF(G13=3,F13/12,IF(G13=6,F13,IF(G13=7,F13-I13,0)))),0) -> 0 | L13: =IF(G13=6,F13,0) -> 0 | N13: 送金料 | P13: 昨年実績 | Q13: =IF($F13="","",IFERROR(VLOOKUP($C13&"|"&$D13,科目表!$A$5:$B$200,2,FALSE),"※未登録")) -> 委託費 | R13: =IF($F13="","",$I13+$J13+$K13) -> 0 | S13: =IF(OR($F13="",$P13="支払なし",$H13=0,$Q13=""),"",$Q13&"|S|"&(COUNTIF(S$4:S12,$Q13&"|S|*")+1)) -> 委託費|S|6 | T13: =IF(OR($F13="",$P13="支払なし",$R13=0,$Q13=""),"",$Q13&"|L|"&(COUNTIF(T$4:T12,$Q13&"|L|*")+1)) | U13: =IF($F13="","",13) -> 13
A14: 44679 | B14: 未払金 | C14: 委託費 | E14: 統合管理端末保守料（３月分） | F14: 770 | G14: 2 | H14: =IF(G14=1,F14-I14-J14-K14,IF(G14=2,F14,0)) -> 770 | I14: =ROUND(IF(G14=1,F14*10/23,IF(G14=3,F14-J14-K14,IF(G14=4,F14,IF(G14=5,F14*10/11,IF(G14=7,F14*10/11,0))))),0) -> 0 | J14: =ROUND(IF(G14=1,F14/23,IF(G14=3,F14/12,IF(G14=5,F14-I14,IF(G14=8,F14,0)))),0) -> 0 | K14: =ROUND(IF(G14=1,F14/23,IF(G14=3,F14/12,IF(G14=6,F14,IF(G14=7,F14-I14,0)))),0) -> 0 | L14: =IF(G14=6,F14,0) -> 0 | N14: 通信運搬費 | P14: 昨年実績 | Q14: =IF($F14="","",IFERROR(VLOOKUP($C14&"|"&$D14,科目表!$A$5:$B$200,2,FALSE),"※未登録")) -> 委託費 | R14: =IF($F14="","",$I14+$J14+$K14) -> 0 | S14: =IF(OR($F14="",$P14="支払なし",$H14=0,$Q14=""),"",$Q14&"|S|"&(COUNTIF(S$4:S13,$Q14&"|S|*")+1)) -> 委託費|S|7 | T14: =IF(OR($F14="",$P14="支払なし",$R14=0,$Q14=""),"",$Q14&"|L|"&(COUNTIF(T$4:T13,$Q14&"|L|*")+1)) | U14: =IF($F14="","",13) -> 13
A15: 43980 | B15: 未払金 | C15: 委託費 | E15: 個人番号管理システム（短期等）平成３１年度分 | F15: 686447 | G15: 2 | H15: =IF(G15=1,F15-I15-J15-K15,IF(G15=2,F15,0)) -> 686447 | I15: =ROUND(IF(G15=1,F15*10/23,IF(G15=3,F15-J15-K15,IF(G15=4,F15,IF(G15=5,F15*10/11,IF(G15=7,F15*10/11,0))))),0) -> 0 | J15: =ROUND(IF(G15=1,F15/23,IF(G15=3,F15/12,IF(G15=5,F15-I15,IF(G15=8,F15,0)))),0) -> 0 | K15: =ROUND(IF(G15=1,F15/23,IF(G15=3,F15/12,IF(G15=6,F15,IF(G15=7,F15-I15,0)))),0) -> 0 | L15: =IF(G15=6,F15,0) -> 0 | N15: 会議費 | P15: 昨年実績 | Q15: =IF($F15="","",IFERROR(VLOOKUP($C15&"|"&$D15,科目表!$A$5:$B$200,2,FALSE),"※未登録")) -> 委託費 | R15: =IF($F15="","",$I15+$J15+$K15) -> 0 | S15: =IF(OR($F15="",$P15="支払なし",$H15=0,$Q15=""),"",$Q15&"|S|"&(COUNTIF(S$4:S14,$Q15&"|S|*")+1)) -> 委託費|S|8 | T15: =IF(OR($F15="",$P15="支払なし",$R15=0,$Q15=""),"",$Q15&"|L|"&(COUNTIF(T$4:T14,$Q15&"|L|*")+1)) | U15: =IF($F15="","",13) -> 13
A16: 43951 | B16: 未払金 | C16: 光熱水料 | D16: ガス料 | E16: 行政財産使用ガス料（１０～３月分） | F16: 1255 | G16: 2 | H16: =IF(G16=1,F16-I16-J16-K16,IF(G16=2,F16,0)) -> 1255 | I16: =ROUND(IF(G16=1,F16*10/23,IF(G16=3,F16-J16-K16,IF(G16=4,F16,IF(G16=5,F16*10/11,IF(G16=7,F16*10/11,0))))),0) -> 0 | J16: =ROUND(IF(G16=1,F16/23,IF(G16=3,F16/12,IF(G16=5,F16-I16,IF(G16=8,F16,0)))),0) -> 0 | K16: =ROUND(IF(G16=1,F16/23,IF(G16=3,F16/12,IF(G16=6,F16,IF(G16=7,F16-I16,0)))),0) -> 0 | L16: =IF(G16=6,F16,0) -> 0 | N16: 雑費 | P16: 昨年実績 | Q16: =IF($F16="","",IFERROR(VLOOKUP($C16&"|"&$D16,科目表!$A$5:$B$200,2,FALSE),"※未登録")) -> 光熱水料 | R16: =IF($F16="","",$I16+$J16+$K16) -> 0 | S16: =IF(OR($F16="",$P16="支払なし",$H16=0,$Q16=""),"",$Q16&"|S|"&(COUNTIF(S$4:S15,$Q16&"|S|*")+1)) -> 光熱水料|S|1 | T16: =IF(OR($F16="",$P16="支払なし",$R16=0,$Q16=""),"",$Q16&"|L|"&(COUNTIF(T$4:T15,$Q16&"|L|*")+1)) | U16: =IF($F16="","",13) -> 13
A17: 43951 | B17: 未払金 | C17: 光熱水料 | D17: 水道料 | E17: 行政財産使用水道料（１０～３月分） | F17: 2324 | G17: 2 | H17: =IF(G17=1,F17-I17-J17-K17,IF(G17=2,F17,0)) -> 2324 | I17: =ROUND(IF(G17=1,F17*10/23,IF(G17=3,F17-J17-K17,IF(G17=4,F17,IF(G17=5,F17*10/11,IF(G17=7,F17*10/11,0))))),0) -> 0 | J17: =ROUND(IF(G17=1,F17/23,IF(G17=3,F17/12,IF(G17=5,F17-I17,IF(G17=8,F17,0)))),0) -> 0 | K17: =ROUND(IF(G17=1,F17/23,IF(G17=3,F17/12,IF(G17=6,F17,IF(G17=7,F17-I17,0)))),0) -> 0 | L17: =IF(G17=6,F17,0) -> 0 | N17: 電気料 | P17: 昨年実績 | Q17: =IF($F17="","",IFERROR(VLOOKUP($C17&"|"&$D17,科目表!$A$5:$B$200,2,FALSE),"※未登録")) -> 光熱水料 | R17: =IF($F17="","",$I17+$J17+$K17) -> 0 | S17: =IF(OR($F17="",$P17="支払なし",$H17=0,$Q17=""),"",$Q17&"|S|"&(COUNTIF(S$4:S16,$Q17&"|S|*")+1)) -> 光熱水料|S|2 | T17: =IF(OR($F17="",$P17="支払なし",$R17=0,$Q17=""),"",$Q17&"|L|"&(COUNTIF(T$4:T16,$Q17&"|L|*")+1)) | U17: =IF($F17="","",13) -> 13
A18: 43951 | B18: 未払金 | C18: 光熱水料 | D18: 電気料 | E18: 行政財産使用電気料（１０～３月分） | F18: 3770 | G18: 2 | H18: =IF(G18=1,F18-I18-J18-K18,IF(G18=2,F18,0)) -> 3770 | I18: =ROUND(IF(G18=1,F18*10/23,IF(G18=3,F18-J18-K18,IF(G18=4,F18,IF(G18=5,F18*10/11,IF(G18=7,F18*10/11,0))))),0) -> 0 | J18: =ROUND(IF(G18=1,F18/23,IF(G18=3,F18/12,IF(G18=5,F18-I18,IF(G18=8,F18,0)))),0) -> 0 | K18: =ROUND(IF(G18=1,F18/23,IF(G18=3,F18/12,IF(G18=6,F18,IF(G18=7,F18-I18,0)))),0) -> 0 | L18: =IF(G18=6,F18,0) -> 0 | N18: ガス料 | P18: 昨年実績 | Q18: =IF($F18="","",IFERROR(VLOOKUP($C18&"|"&$D18,科目表!$A$5:$B$200,2,FALSE),"※未登録")) -> 光熱水料 | R18: =IF($F18="","",$I18+$J18+$K18) -> 0 | S18: =IF(OR($F18="",$P18="支払なし",$H18=0,$Q18=""),"",$Q18&"|S|"&(COUNTIF(S$4:S17,$Q18&"|S|*")+1)) -> 光熱水料|S|3 | T18: =IF(OR($F18="",$P18="支払なし",$R18=0,$Q18=""),"",$Q18&"|L|"&(COUNTIF(T$4:T17,$Q18&"|L|*")+1)) | U18: =IF($F18="","",13) -> 13
A19: 43951 | B19: 未払金 | C19: 事務費 | D19: 事務用消耗品費 | E19: 複写機用紙等購入代分担金（第4四半期）短期 | F19: 92843 | G19: 2 | H19: =IF(G19=1,F19-I19-J19-K19,IF(G19=2,F19,0)) -> 92843 | I19: =ROUND(IF(G19=1,F19*10/23,IF(G19=3,F19-J19-K19,IF(G19=4,F19,IF(G19=5,F19*10/11,IF(G19=7,F19*10/11,0))))),0) -> 0 | J19: =ROUND(IF(G19=1,F19/23,IF(G19=3,F19/12,IF(G19=5,F19-I19,IF(G19=8,F19,0)))),0) -> 0 | K19: =ROUND(IF(G19=1,F19/23,IF(G19=3,F19/12,IF(G19=6,F19,IF(G19=7,F19-I19,0)))),0) -> 0 | L19: =IF(G19=6,F19,0) -> 0 | N19: 水道料 | P19: 昨年実績 | Q19: =IF($F19="","",IFERROR(VLOOKUP($C19&"|"&$D19,科目表!$A$5:$B$200,2,FALSE),"※未登録")) -> 事務用消耗品費 | R19: =IF($F19="","",$I19+$J19+$K19) -> 0 | S19: =IF(OR($F19="",$P19="支払なし",$H19=0,$Q19=""),"",$Q19&"|S|"&(COUNTIF(S$4:S18,$Q19&"|S|*")+1)) -> 事務用消耗品費|S|1 | T19: =IF(OR($F19="",$P19="支払なし",$R19=0,$Q19=""),"",$Q19&"|L|"&(COUNTIF(T$4:T18,$Q19&"|L|*")+1)) | U19: =IF($F19="","",13) -> 13
A20: 43931 | B20: 未払金 | C20: 事務費 | D20: 送金料 | E20: 広銀手数料（３月分）短期 | F20: 100870 | G20: 2 | H20: =IF(G20=1,F20-I20-J20-K20,IF(G20=2,F20,0)) -> 100870 | I20: =ROUND(IF(G20=1,F20*10/23,IF(G20=3,F20-J20-K20,IF(G20=4,F20,IF(G20=5,F20*10/11,IF(G20=7,F20*10/11,0))))),0) -> 0 | J20: =ROUND(IF(G20=1,F20/23,IF(G20=3,F20/12,IF(G20=5,F20-I20,IF(G20=8,F20,0)))),0) -> 0 | K20: =ROUND(IF(G20=1,F20/23,IF(G20=3,F20/12,IF(G20=6,F20,IF(G20=7,F20-I20,0)))),0) -> 0 | L20: =IF(G20=6,F20,0) -> 0 | N20: 協会けんぽ保険料等 | P20: 昨年実績 | Q20: =IF($F20="","",IFERROR(VLOOKUP($C20&"|"&$D20,科目表!$A$5:$B$200,2,FALSE),"※未登録")) -> 送金料 | R20: =IF($F20="","",$I20+$J20+$K20) -> 0 | S20: =IF(OR($F20="",$P20="支払なし",$H20=0,$Q20=""),"",$Q20&"|S|"&(COUNTIF(S$4:S19,$Q20&"|S|*")+1)) -> 送金料|S|1 | T20: =IF(OR($F20="",$P20="支払なし",$R20=0,$Q20=""),"",$Q20&"|L|"&(COUNTIF(T$4:T19,$Q20&"|L|*")+1)) | U20: =IF($F20="","",13) -> 13
A21: 44679 | B21: 未払金 | C21: 事務費 | D21: 通信運搬費 | E21: 柔整申請書送付（3月分） | F21: 1386 | G21: 2 | H21: =IF(G21=1,F21-I21-J21-K21,IF(G21=2,F21,0)) -> 1386 | I21: =ROUND(IF(G21=1,F21*10/23,IF(G21=3,F21-J21-K21,IF(G21=4,F21,IF(G21=5,F21*10/11,IF(G21=7,F21*10/11,0))))),0) -> 0 | J21: =ROUND(IF(G21=1,F21/23,IF(G21=3,F21/12,IF(G21=5,F21-I21,IF(G21=8,F21,0)))),0) -> 0 | K21: =ROUND(IF(G21=1,F21/23,IF(G21=3,F21/12,IF(G21=6,F21,IF(G21=7,F21-I21,0)))),0) -> 0 | L21: =IF(G21=6,F21,0) -> 0 | N21: 厚年負担金等 | P21: 昨年実績 | Q21: =IF($F21="","",IFERROR(VLOOKUP($C21&"|"&$D21,科目表!$A$5:$B$200,2,FALSE),"※未登録")) -> 通信運搬費 | R21: =IF($F21="","",$I21+$J21+$K21) -> 0 | S21: =IF(OR($F21="",$P21="支払なし",$H21=0,$Q21=""),"",$Q21&"|S|"&(COUNTIF(S$4:S20,$Q21&"|S|*")+1)) -> 通信運搬費|S|1 | T21: =IF(OR($F21="",$P21="支払なし",$R21=0,$Q21=""),"",$Q21&"|L|"&(COUNTIF(T$4:T20,$Q21&"|L|*")+1)) | U21: =IF($F21="","",13) -> 13
A22: 45383 | B22: 未払金 | C22: 事務費 | D22: 通信運搬費 | E22: フレッツ光ネクスト利用料等（2月利用・3月請求分） | F22: 4906 | G22: 2 | H22: =IF(G22=1,F22-I22-J22-K22,IF(G22=2,F22,0)) -> 4906 | I22: =ROUND(IF(G22=1,F22*10/23,IF(G22=3,F22-J22-K22,IF(G22=4,F22,IF(G22=5,F22*10/11,IF(G22=7,F22*10/11,0))))),0) -> 0 | J22: =ROUND(IF(G22=1,F22/23,IF(G22=3,F22/12,IF(G22=5,F22-I22,IF(G22=8,F22,0)))),0) -> 0 | K22: =ROUND(IF(G22=1,F22/23,IF(G22=3,F22/12,IF(G22=6,F22,IF(G22=7,F22-I22,0)))),0) -> 0 | L22: =IF(G22=6,F22,0) -> 0 | P22: 昨年実績 | Q22: =IF($F22="","",IFERROR(VLOOKUP($C22&"|"&$D22,科目表!$A$5:$B$200,2,FALSE),"※未登録")) -> 通信運搬費 | R22: =IF($F22="","",$I22+$J22+$K22) -> 0 | S22: =IF(OR($F22="",$P22="支払なし",$H22=0,$Q22=""),"",$Q22&"|S|"&(COUNTIF(S$4:S21,$Q22&"|S|*")+1)) -> 通信運搬費|S|2 | T22: =IF(OR($F22="",$P22="支払なし",$R22=0,$Q22=""),"",$Q22&"|L|"&(COUNTIF(T$4:T21,$Q22&"|L|*")+1)) | U22: =IF($F22="","",13) -> 13
A23: 43951 | B23: 未払金 | C23: 事務費 | D23: 通信運搬費 | E23: 事務局電話代 3月使用4月請求分 | F23: 5406 | G23: 2 | H23: =IF(G23=1,F23-I23-J23-K23,IF(G23=2,F23,0)) -> 5406 | I23: =ROUND(IF(G23=1,F23*10/23,IF(G23=3,F23-J23-K23,IF(G23=4,F23,IF(G23=5,F23*10/11,IF(G23=7,F23*10/11,0))))),0) -> 0 | J23: =ROUND(IF(G23=1,F23/23,IF(G23=3,F23/12,IF(G23=5,F23-I23,IF(G23=8,F23,0)))),0) -> 0 | K23: =ROUND(IF(G23=1,F23/23,IF(G23=3,F23/12,IF(G23=6,F23,IF(G23=7,F23-I23,0)))),0) -> 0 | L23: =IF(G23=6,F23,0) -> 0 | N23: 労災・雇用保険料 | P23: 昨年実績 | Q23: =IF($F23="","",IFERROR(VLOOKUP($C23&"|"&$D23,科目表!$A$5:$B$200,2,FALSE),"※未登録")) -> 通信運搬費 | R23: =IF($F23="","",$I23+$J23+$K23) -> 0 | S23: =IF(OR($F23="",$P23="支払なし",$H23=0,$Q23=""),"",$Q23&"|S|"&(COUNTIF(S$4:S22,$Q23&"|S|*")+1)) -> 通信運搬費|S|3 | T23: =IF(OR($F23="",$P23="支払なし",$R23=0,$Q23=""),"",$Q23&"|L|"&(COUNTIF(T$4:T22,$Q23&"|L|*")+1)) | U23: =IF($F23="","",13) -> 13
A24: 43951 | B24: 未払金 | C24: 事務費 | D24: 通信運搬費 | E24: ファクシミリ電話代等分担金（第4四半期）短期 | F24: 5952 | G24: 2 | H24: =IF(G24=1,F24-I24-J24-K24,IF(G24=2,F24,0)) -> 5952 | I24: =ROUND(IF(G24=1,F24*10/23,IF(G24=3,F24-J24-K24,IF(G24=4,F24,IF(G24=5,F24*10/11,IF(G24=7,F24*10/11,0))))),0) -> 0 | J24: =ROUND(IF(G24=1,F24/23,IF(G24=3,F24/12,IF(G24=5,F24-I24,IF(G24=8,F24,0)))),0) -> 0 | K24: =ROUND(IF(G24=1,F24/23,IF(G24=3,F24/12,IF(G24=6,F24,IF(G24=7,F24-I24,0)))),0) -> 0 | L24: =IF(G24=6,F24,0) -> 0 | N24: 互助会費 | P24: 昨年実績 | Q24: =IF($F24="","",IFERROR(VLOOKUP($C24&"|"&$D24,科目表!$A$5:$B$200,2,FALSE),"※未登録")) -> 通信運搬費 | R24: =IF($F24="","",$I24+$J24+$K24) -> 0 | S24: =IF(OR($F24="",$P24="支払なし",$H24=0,$Q24=""),"",$Q24&"|S|"&(COUNTIF(S$4:S23,$Q24&"|S|*")+1)) -> 通信運搬費|S|4 | T24: =IF(OR($F24="",$P24="支払なし",$R24=0,$Q24=""),"",$Q24&"|L|"&(COUNTIF(T$4:T23,$Q24&"|L|*")+1)) | U24: =IF($F24="","",13) -> 13
A25: 43951 | B25: 未払金 | C25: 事務費 | D25: 通信運搬費 | E25: 行政財産使用電話料（１０～３月分） | F25: 54000 | G25: 2 | H25: =IF(G25=1,F25-I25-J25-K25,IF(G25=2,F25,0)) -> 54000 | I25: =ROUND(IF(G25=1,F25*10/23,IF(G25=3,F25-J25-K25,IF(G25=4,F25,IF(G25=5,F25*10/11,IF(G25=7,F25*10/11,0))))),0) -> 0 | J25: =ROUND(IF(G25=1,F25/23,IF(G25=3,F25/12,IF(G25=5,F25-I25,IF(G25=8,F25,0)))),0) -> 0 | K25: =ROUND(IF(G25=1,F25/23,IF(G25=3,F25/12,IF(G25=6,F25,IF(G25=7,F25-I25,0)))),0) -> 0 | L25: =IF(G25=6,F25,0) -> 0 | N25: 会議出席負担金等 | P25: 昨年実績 | Q25: =IF($F25="","",IFERROR(VLOOKUP($C25&"|"&$D25,科目表!$A$5:$B$200,2,FALSE),"※未登録")) -> 通信運搬費 | R25: =IF($F25="","",$I25+$J25+$K25) -> 0 | S25: =IF(OR($F25="",$P25="支払なし",$H25=0,$Q25=""),"",$Q25&"|S|"&(COUNTIF(S$4:S24,$Q25&"|S|*")+1)) -> 通信運搬費|S|5 | T25: =IF(OR($F25="",$P25="支払なし",$R25=0,$Q25=""),"",$Q25&"|L|"&(COUNTIF(T$4:T24,$Q25&"|L|*")+1)) | U25: =IF($F25="","",13) -> 13
A26: 45383 | B26: 未払金 | C26: 事務費 | D26: 通信運搬費 | E26: インターネット通信料金（１月・２月使用・３月請求分） | F26: 3415 | G26: 2 | H26: =IF(G26=1,F26-I26-J26-K26,IF(G26=2,F26,0)) -> 3415 | I26: =ROUND(IF(G26=1,F26*10/23,IF(G26=3,F26-J26-K26,IF(G26=4,F26,IF(G26=5,F26*10/11,IF(G26=7,F26*10/11,0))))),0) -> 0 | J26: =ROUND(IF(G26=1,F26/23,IF(G26=3,F26/12,IF(G26=5,F26-I26,IF(G26=8,F26,0)))),0) -> 0 | K26: =ROUND(IF(G26=1,F26/23,IF(G26=3,F26/12,IF(G26=6,F26,IF(G26=7,F26-I26,0)))),0) -> 0 | L26: =IF(G26=6,F26,0) -> 0 | N26: 市町村連合会分担金 | P26: 昨年実績 | Q26: =IF($F26="","",IFERROR(VLOOKUP($C26&"|"&$D26,科目表!$A$5:$B$200,2,FALSE),"※未登録")) -> 通信運搬費 | R26: =IF($F26="","",$I26+$J26+$K26) -> 0 | S26: =IF(OR($F26="",$P26="支払なし",$H26=0,$Q26=""),"",$Q26&"|S|"&(COUNTIF(S$4:S25,$Q26&"|S|*")+1)) -> 通信運搬費|S|6 | T26: =IF(OR($F26="",$P26="支払なし",$R26=0,$Q26=""),"",$Q26&"|L|"&(COUNTIF(T$4:T25,$Q26&"|L|*")+1)) | U26: =IF($F26="","",13) -> 13
A27: 46127 | B27: 未払費用 | C27: 賃金 | E27: 臨時職員賃金３月分 佐藤幸恵他１名分（短期１００％） | F27: 376346 | G27: 2 | H27: =IF(G27=1,F27-I27-J27-K27,IF(G27=2,F27,0)) -> 376346 | I27: =ROUND(IF(G27=1,F27*10/23,IF(G27=3,F27-J27-K27,IF(G27=4,F27,IF(G27=5,F27*10/11,IF(G27=7,F27*10/11,0))))),0) -> 0 | J27: =ROUND(IF(G27=1,F27/23,IF(G27=3,F27/12,IF(G27=5,F27-I27,IF(G27=8,F27,0)))),0) -> 0 | K27: =ROUND(IF(G27=1,F27/23,IF(G27=3,F27/12,IF(G27=6,F27,IF(G27=7,F27-I27,0)))),0) -> 0 | L27: =IF(G27=6,F27,0) -> 0 | N27: 器具及び備品 | P27: 昨年実績 | Q27: =IF($F27="","",IFERROR(VLOOKUP($C27&"|"&$D27,科目表!$A$5:$B$200,2,FALSE),"※未登録")) -> 賃金 | R27: =IF($F27="","",$I27+$J27+$K27) -> 0 | S27: =IF(OR($F27="",$P27="支払なし",$H27=0,$Q27=""),"",$Q27&"|S|"&(COUNTIF(S$4:S26,$Q27&"|S|*")+1)) -> 賃金|S|1 | T27: =IF(OR($F27="",$P27="支払なし",$R27=0,$Q27=""),"",$Q27&"|L|"&(COUNTIF(T$4:T26,$Q27&"|L|*")+1)) | U27: =IF($F27="","",13) -> 13
A28: 46127 | B28: 未払金 | C28: 賃借料 | E28: パソコン（業務経理用）3月分 | F28: 5060 | G28: 2 | H28: =IF(G28=1,F28-I28-J28-K28,IF(G28=2,F28,0)) -> 5060 | I28: =ROUND(IF(G28=1,F28*10/23,IF(G28=3,F28-J28-K28,IF(G28=4,F28,IF(G28=5,F28*10/11,IF(G28=7,F28*10/11,0))))),0) -> 0 | J28: =ROUND(IF(G28=1,F28/23,IF(G28=3,F28/12,IF(G28=5,F28-I28,IF(G28=8,F28,0)))),0) -> 0 | K28: =ROUND(IF(G28=1,F28/23,IF(G28=3,F28/12,IF(G28=6,F28,IF(G28=7,F28-I28,0)))),0) -> 0 | L28: =IF(G28=6,F28,0) -> 0 | P28: 昨年実績 | Q28: =IF($F28="","",IFERROR(VLOOKUP($C28&"|"&$D28,科目表!$A$5:$B$200,2,FALSE),"※未登録")) -> 賃借料 | R28: =IF($F28="","",$I28+$J28+$K28) -> 0 | S28: =IF(OR($F28="",$P28="支払なし",$H28=0,$Q28=""),"",$Q28&"|S|"&(COUNTIF(S$4:S27,$Q28&"|S|*")+1)) -> 賃借料|S|1 | T28: =IF(OR($F28="",$P28="支払なし",$R28=0,$Q28=""),"",$Q28&"|L|"&(COUNTIF(T$4:T27,$Q28&"|L|*")+1)) | U28: =IF($F28="","",13) -> 13
A29: 44316 | B29: 未払金 | C29: 事務費 | D29: 事務用消耗品費 | E29: リサイクルトナー ＬＰＢ３Ｔ２７ | F29: 49500 | G29: 2 | H29: =IF(G29=1,F29-I29-J29-K29,IF(G29=2,F29,0)) -> 49500 | I29: =ROUND(IF(G29=1,F29*10/23,IF(G29=3,F29-J29-K29,IF(G29=4,F29,IF(G29=5,F29*10/11,IF(G29=7,F29*10/11,0))))),0) -> 0 | J29: =ROUND(IF(G29=1,F29/23,IF(G29=3,F29/12,IF(G29=5,F29-I29,IF(G29=8,F29,0)))),0) -> 0 | K29: =ROUND(IF(G29=1,F29/23,IF(G29=3,F29/12,IF(G29=6,F29,IF(G29=7,F29-I29,0)))),0) -> 0 | L29: =IF(G29=6,F29,0) -> 0 | P29: 昨年実績 | Q29: =IF($F29="","",IFERROR(VLOOKUP($C29&"|"&$D29,科目表!$A$5:$B$200,2,FALSE),"※未登録")) -> 事務用消耗品費 | R29: =IF($F29="","",$I29+$J29+$K29) -> 0 | S29: =IF(OR($F29="",$P29="支払なし",$H29=0,$Q29=""),"",$Q29&"|S|"&(COUNTIF(S$4:S28,$Q29&"|S|*")+1)) -> 事務用消耗品費|S|2 | T29: =IF(OR($F29="",$P29="支払なし",$R29=0,$Q29=""),"",$Q29&"|L|"&(COUNTIF(T$4:T28,$Q29&"|L|*")+1)) | U29: =IF($F29="","",13) -> 13
A30: 46140 | B30: 未払金 | C30: 賃借料 | E30: サーバーラック賃借料 （短期） | F30: 156144 | G30: 2 | H30: =IF(G30=1,F30-I30-J30-K30,IF(G30=2,F30,0)) -> 156144 | I30: =ROUND(IF(G30=1,F30*10/23,IF(G30=3,F30-J30-K30,IF(G30=4,F30,IF(G30=5,F30*10/11,IF(G30=7,F30*10/11,0))))),0) -> 0 | J30: =ROUND(IF(G30=1,F30/23,IF(G30=3,F30/12,IF(G30=5,F30-I30,IF(G30=8,F30,0)))),0) -> 0 | K30: =ROUND(IF(G30=1,F30/23,IF(G30=3,F30/12,IF(G30=6,F30,IF(G30=7,F30-I30,0)))),0) -> 0 | L30: =IF(G30=6,F30,0) -> 0 | P30: 昨年実績 | Q30: =IF($F30="","",IFERROR(VLOOKUP($C30&"|"&$D30,科目表!$A$5:$B$200,2,FALSE),"※未登録")) -> 賃借料 | R30: =IF($F30="","",$I30+$J30+$K30) -> 0 | S30: =IF(OR($F30="",$P30="支払なし",$H30=0,$Q30=""),"",$Q30&"|S|"&(COUNTIF(S$4:S29,$Q30&"|S|*")+1)) -> 賃借料|S|2 | T30: =IF(OR($F30="",$P30="支払なし",$R30=0,$Q30=""),"",$Q30&"|L|"&(COUNTIF(T$4:T29,$Q30&"|L|*")+1)) | U30: =IF($F30="","",13) -> 13
A31: 45397 | B31: 未払金 | C31: 賃借料 | E31: サーバーラック賃借料 （長期） | F31: 372 | G31: 3 | H31: =IF(G31=1,F31-I31-J31-K31,IF(G31=2,F31,0)) -> 0 | I31: =ROUND(IF(G31=1,F31*10/23,IF(G31=3,F31-J31-K31,IF(G31=4,F31,IF(G31=5,F31*10/11,IF(G31=7,F31*10/11,0))))),0) -> 310 | J31: =ROUND(IF(G31=1,F31/23,IF(G31=3,F31/12,IF(G31=5,F31-I31,IF(G31=8,F31,0)))),0) -> 31 | K31: =ROUND(IF(G31=1,F31/23,IF(G31=3,F31/12,IF(G31=6,F31,IF(G31=7,F31-I31,0)))),0) -> 31 | L31: =IF(G31=6,F31,0) -> 0 | P31: 昨年実績 | Q31: =IF($F31="","",IFERROR(VLOOKUP($C31&"|"&$D31,科目表!$A$5:$B$200,2,FALSE),"※未登録")) -> 賃借料 | R31: =IF($F31="","",$I31+$J31+$K31) -> 372 | S31: =IF(OR($F31="",$P31="支払なし",$H31=0,$Q31=""),"",$Q31&"|S|"&(COUNTIF(S$4:S30,$Q31&"|S|*")+1)) | T31: =IF(OR($F31="",$P31="支払なし",$R31=0,$Q31=""),"",$Q31&"|L|"&(COUNTIF(T$4:T30,$Q31&"|L|*")+1)) -> 賃借料|L|1 | U31: =IF($F31="","",13) -> 13
A32: 44679 | B32: 未払金 | C32: 賃借料 | E32: 病院機構人給システム（パソコン・プリンタ使用料）短期 | F32: 25902 | G32: 2 | H32: =IF(G32=1,F32-I32-J32-K32,IF(G32=2,F32,0)) -> 25902 | I32: =ROUND(IF(G32=1,F32*10/23,IF(G32=3,F32-J32-K32,IF(G32=4,F32,IF(G32=5,F32*10/11,IF(G32=7,F32*10/11,0))))),0) -> 0 | J32: =ROUND(IF(G32=1,F32/23,IF(G32=3,F32/12,IF(G32=5,F32-I32,IF(G32=8,F32,0)))),0) -> 0 | K32: =ROUND(IF(G32=1,F32/23,IF(G32=3,F32/12,IF(G32=6,F32,IF(G32=7,F32-I32,0)))),0) -> 0 | L32: =IF(G32=6,F32,0) -> 0 | P32: 昨年実績 | Q32: =IF($F32="","",IFERROR(VLOOKUP($C32&"|"&$D32,科目表!$A$5:$B$200,2,FALSE),"※未登録")) -> 賃借料 | R32: =IF($F32="","",$I32+$J32+$K32) -> 0 | S32: =IF(OR($F32="",$P32="支払なし",$H32=0,$Q32=""),"",$Q32&"|S|"&(COUNTIF(S$4:S31,$Q32&"|S|*")+1)) -> 賃借料|S|3 | T32: =IF(OR($F32="",$P32="支払なし",$R32=0,$Q32=""),"",$Q32&"|L|"&(COUNTIF(T$4:T31,$Q32&"|L|*")+1)) | U32: =IF($F32="","",13) -> 13
A33: 46128 | B33: 未払金 | C33: 賃借料 | E33: 統合管理端末リース料（３月分） | F33: 12738 | G33: 2 | H33: =IF(G33=1,F33-I33-J33-K33,IF(G33=2,F33,0)) -> 12738 | I33: =ROUND(IF(G33=1,F33*10/23,IF(G33=3,F33-J33-K33,IF(G33=4,F33,IF(G33=5,F33*10/11,IF(G33=7,F33*10/11,0))))),0) -> 0 | J33: =ROUND(IF(G33=1,F33/23,IF(G33=3,F33/12,IF(G33=5,F33-I33,IF(G33=8,F33,0)))),0) -> 0 | K33: =ROUND(IF(G33=1,F33/23,IF(G33=3,F33/12,IF(G33=6,F33,IF(G33=7,F33-I33,0)))),0) -> 0 | L33: =IF(G33=6,F33,0) -> 0 | P33: 昨年実績 | Q33: =IF($F33="","",IFERROR(VLOOKUP($C33&"|"&$D33,科目表!$A$5:$B$200,2,FALSE),"※未登録")) -> 賃借料 | R33: =IF($F33="","",$I33+$J33+$K33) -> 0 | S33: =IF(OR($F33="",$P33="支払なし",$H33=0,$Q33=""),"",$Q33&"|S|"&(COUNTIF(S$4:S32,$Q33&"|S|*")+1)) -> 賃借料|S|4 | T33: =IF(OR($F33="",$P33="支払なし",$R33=0,$Q33=""),"",$Q33&"|L|"&(COUNTIF(T$4:T32,$Q33&"|L|*")+1)) | U33: =IF($F33="","",13) -> 13
A34: 43951 | B34: 未払金 | C34: 普及費 | E34: 厚生だより等印刷代分担金（第4四半期）短期 | F34: 532196 | G34: 2 | H34: =IF(G34=1,F34-I34-J34-K34,IF(G34=2,F34,0)) -> 532196 | I34: =ROUND(IF(G34=1,F34*10/23,IF(G34=3,F34-J34-K34,IF(G34=4,F34,IF(G34=5,F34*10/11,IF(G34=7,F34*10/11,0))))),0) -> 0 | J34: =ROUND(IF(G34=1,F34/23,IF(G34=3,F34/12,IF(G34=5,F34-I34,IF(G34=8,F34,0)))),0) -> 0 | K34: =ROUND(IF(G34=1,F34/23,IF(G34=3,F34/12,IF(G34=6,F34,IF(G34=7,F34-I34,0)))),0) -> 0 | L34: =IF(G34=6,F34,0) -> 0 | P34: 昨年実績 | Q34: =IF($F34="","",IFERROR(VLOOKUP($C34&"|"&$D34,科目表!$A$5:$B$200,2,FALSE),"※未登録")) -> 普及費 | R34: =IF($F34="","",$I34+$J34+$K34) -> 0 | S34: =IF(OR($F34="",$P34="支払なし",$H34=0,$Q34=""),"",$Q34&"|S|"&(COUNTIF(S$4:S33,$Q34&"|S|*")+1)) -> 普及費|S|1 | T34: =IF(OR($F34="",$P34="支払なし",$R34=0,$Q34=""),"",$Q34&"|L|"&(COUNTIF(T$4:T33,$Q34&"|L|*")+1)) | U34: =IF($F34="","",13) -> 13
A35: 43951 | B35: 未払金 | C35: 負担金 | D35: 厚年負担金等 | E35: ３月月例+３月賞与分（短期分）子ども子育て拠出金を含む | F35: 49538 | G35: 2 | H35: =IF(G35=1,F35-I35-J35-K35,IF(G35=2,F35,0)) -> 49538 | I35: =ROUND(IF(G35=1,F35*10/23,IF(G35=3,F35-J35-K35,IF(G35=4,F35,IF(G35=5,F35*10/11,IF(G35=7,F35*10/11,0))))),0) -> 0 | J35: =ROUND(IF(G35=1,F35/23,IF(G35=3,F35/12,IF(G35=5,F35-I35,IF(G35=8,F35,0)))),0) -> 0 | K35: =ROUND(IF(G35=1,F35/23,IF(G35=3,F35/12,IF(G35=6,F35,IF(G35=7,F35-I35,0)))),0) -> 0 | L35: =IF(G35=6,F35,0) -> 0 | P35: 昨年実績 | Q35: =IF($F35="","",IFERROR(VLOOKUP($C35&"|"&$D35,科目表!$A$5:$B$200,2,FALSE),"※未登録")) -> 厚年負担金等 | R35: =IF($F35="","",$I35+$J35+$K35) -> 0 | S35: =IF(OR($F35="",$P35="支払なし",$H35=0,$Q35=""),"",$Q35&"|S|"&(COUNTIF(S$4:S34,$Q35&"|S|*")+1)) -> 厚年負担金等|S|1 | T35: =IF(OR($F35="",$P35="支払なし",$R35=0,$Q35=""),"",$Q35&"|L|"&(COUNTIF(T$4:T34,$Q35&"|L|*")+1)) | U35: =IF($F35="","",13) -> 13
A36: 43951 | B36: 未払金 | C36: 負担金 | D36: 協会けんぽ保険料等 | E36: ３月月例+３月賞与分（短期分） | F36: 28829 | G36: 2 | H36: =IF(G36=1,F36-I36-J36-K36,IF(G36=2,F36,0)) -> 28829 | I36: =ROUND(IF(G36=1,F36*10/23,IF(G36=3,F36-J36-K36,IF(G36=4,F36,IF(G36=5,F36*10/11,IF(G36=7,F36*10/11,0))))),0) -> 0 | J36: =ROUND(IF(G36=1,F36/23,IF(G36=3,F36/12,IF(G36=5,F36-I36,IF(G36=8,F36,0)))),0) -> 0 | K36: =ROUND(IF(G36=1,F36/23,IF(G36=3,F36/12,IF(G36=6,F36,IF(G36=7,F36-I36,0)))),0) -> 0 | L36: =IF(G36=6,F36,0) -> 0 | P36: 昨年実績 | Q36: =IF($F36="","",IFERROR(VLOOKUP($C36&"|"&$D36,科目表!$A$5:$B$200,2,FALSE),"※未登録")) -> 協会けんぽ保険料等 | R36: =IF($F36="","",$I36+$J36+$K36) -> 0 | S36: =IF(OR($F36="",$P36="支払なし",$H36=0,$Q36=""),"",$Q36&"|S|"&(COUNTIF(S$4:S35,$Q36&"|S|*")+1)) -> 協会けんぽ保険料等|S|1 | T36: =IF(OR($F36="",$P36="支払なし",$R36=0,$Q36=""),"",$Q36&"|L|"&(COUNTIF(T$4:T35,$Q36&"|L|*")+1)) | U36: =IF($F36="","",13) -> 13
A37: 43942 | B37: 未払金 | C37: 立替金 | E37: ゆうちょ銀行払込料金 | F37: 6400 | G37: 3 | H37: =IF(G37=1,F37-I37-J37-K37,IF(G37=2,F37,0)) -> 0 | I37: =ROUND(IF(G37=1,F37*10/23,IF(G37=3,F37-J37-K37,IF(G37=4,F37,IF(G37=5,F37*10/11,IF(G37=7,F37*10/11,0))))),0) -> 5334 | J37: =ROUND(IF(G37=1,F37/23,IF(G37=3,F37/12,IF(G37=5,F37-I37,IF(G37=8,F37,0)))),0) -> 533 | K37: =ROUND(IF(G37=1,F37/23,IF(G37=3,F37/12,IF(G37=6,F37,IF(G37=7,F37-I37,0)))),0) -> 533 | L37: =IF(G37=6,F37,0) -> 0 | P37: 昨年実績 | Q37: =IF($F37="","",IFERROR(VLOOKUP($C37&"|"&$D37,科目表!$A$5:$B$200,2,FALSE),"※未登録")) -> 立替金 | R37: =IF($F37="","",$I37+$J37+$K37) -> 6400 | S37: =IF(OR($F37="",$P37="支払なし",$H37=0,$Q37=""),"",$Q37&"|S|"&(COUNTIF(S$4:S36,$Q37&"|S|*")+1)) | T37: =IF(OR($F37="",$P37="支払なし",$R37=0,$Q37=""),"",$Q37&"|L|"&(COUNTIF(T$4:T36,$Q37&"|L|*")+1)) -> 立替金|L|1 | U37: =IF($F37="","",13) -> 13
A38: 45768 | B38: 未払金 | C38: 事務費 | D38: 雑費 | E38: ゆうちょ銀行一般振替口座 残高証明書発行手数料 | F38: 3300 | G38: 3 | H38: =IF(G38=1,F38-I38-J38-K38,IF(G38=2,F38,0)) -> 0 | I38: =ROUND(IF(G38=1,F38*10/23,IF(G38=3,F38-J38-K38,IF(G38=4,F38,IF(G38=5,F38*10/11,IF(G38=7,F38*10/11,0))))),0) -> 2750 | J38: =ROUND(IF(G38=1,F38/23,IF(G38=3,F38/12,IF(G38=5,F38-I38,IF(G38=8,F38,0)))),0) -> 275 | K38: =ROUND(IF(G38=1,F38/23,IF(G38=3,F38/12,IF(G38=6,F38,IF(G38=7,F38-I38,0)))),0) -> 275 | L38: =IF(G38=6,F38,0) -> 0 | P38: 昨年実績 | Q38: =IF($F38="","",IFERROR(VLOOKUP($C38&"|"&$D38,科目表!$A$5:$B$200,2,FALSE),"※未登録")) -> 事務費・雑費 | R38: =IF($F38="","",$I38+$J38+$K38) -> 3300 | S38: =IF(OR($F38="",$P38="支払なし",$H38=0,$Q38=""),"",$Q38&"|S|"&(COUNTIF(S$4:S37,$Q38&"|S|*")+1)) | T38: =IF(OR($F38="",$P38="支払なし",$R38=0,$Q38=""),"",$Q38&"|L|"&(COUNTIF(T$4:T37,$Q38&"|L|*")+1)) -> 事務費・雑費|L|1 | U38: =IF($F38="","",13) -> 13
A39: 43936 | B39: 未払金 | C39: 委託費 | E39: 個別システム保守料（平成３１年度）長期分 | F39: 198020 | G39: 3 | H39: =IF(G39=1,F39-I39-J39-K39,IF(G39=2,F39,0)) -> 0 | I39: =ROUND(IF(G39=1,F39*10/23,IF(G39=3,F39-J39-K39,IF(G39=4,F39,IF(G39=5,F39*10/11,IF(G39=7,F39*10/11,0))))),0) -> 165016 | J39: =ROUND(IF(G39=1,F39/23,IF(G39=3,F39/12,IF(G39=5,F39-I39,IF(G39=8,F39,0)))),0) -> 16502 | K39: =ROUND(IF(G39=1,F39/23,IF(G39=3,F39/12,IF(G39=6,F39,IF(G39=7,F39-I39,0)))),0) -> 16502 | L39: =IF(G39=6,F39,0) -> 0 | P39: 昨年実績 | Q39: =IF($F39="","",IFERROR(VLOOKUP($C39&"|"&$D39,科目表!$A$5:$B$200,2,FALSE),"※未登録")) -> 委託費 | R39: =IF($F39="","",$I39+$J39+$K39) -> 198020 | S39: =IF(OR($F39="",$P39="支払なし",$H39=0,$Q39=""),"",$Q39&"|S|"&(COUNTIF(S$4:S38,$Q39&"|S|*")+1)) | T39: =IF(OR($F39="",$P39="支払なし",$R39=0,$Q39=""),"",$Q39&"|L|"&(COUNTIF(T$4:T38,$Q39&"|L|*")+1)) -> 委託費|L|1 | U39: =IF($F39="","",13) -> 13
A40: 44679 | B40: 未払金 | C40: 委託費 | E40: 病院機構人給システム（ネットワーク等経費）長期 | F40: 43626 | G40: 3 | H40: =IF(G40=1,F40-I40-J40-K40,IF(G40=2,F40,0)) -> 0 | I40: =ROUND(IF(G40=1,F40*10/23,IF(G40=3,F40-J40-K40,IF(G40=4,F40,IF(G40=5,F40*10/11,IF(G40=7,F40*10/11,0))))),0) -> 36354 | J40: =ROUND(IF(G40=1,F40/23,IF(G40=3,F40/12,IF(G40=5,F40-I40,IF(G40=8,F40,0)))),0) -> 3636 | K40: =ROUND(IF(G40=1,F40/23,IF(G40=3,F40/12,IF(G40=6,F40,IF(G40=7,F40-I40,0)))),0) -> 3636 | L40: =IF(G40=6,F40,0) -> 0 | P40: 昨年実績 | Q40: =IF($F40="","",IFERROR(VLOOKUP($C40&"|"&$D40,科目表!$A$5:$B$200,2,FALSE),"※未登録")) -> 委託費 | R40: =IF($F40="","",$I40+$J40+$K40) -> 43626 | S40: =IF(OR($F40="",$P40="支払なし",$H40=0,$Q40=""),"",$Q40&"|S|"&(COUNTIF(S$4:S39,$Q40&"|S|*")+1)) | T40: =IF(OR($F40="",$P40="支払なし",$R40=0,$Q40=""),"",$Q40&"|L|"&(COUNTIF(T$4:T39,$Q40&"|L|*")+1)) -> 委託費|L|2 | U40: =IF($F40="","",13) -> 13
A41: 45044 | B41: 未払金 | C41: 事務費 | D41: 事務用消耗品費 | E41: マグネットポケット マクー５００NB 1個 | F41: 1579 | G41: 2 | H41: =IF(G41=1,F41-I41-J41-K41,IF(G41=2,F41,0)) -> 1579 | I41: =ROUND(IF(G41=1,F41*10/23,IF(G41=3,F41-J41-K41,IF(G41=4,F41,IF(G41=5,F41*10/11,IF(G41=7,F41*10/11,0))))),0) -> 0 | J41: =ROUND(IF(G41=1,F41/23,IF(G41=3,F41/12,IF(G41=5,F41-I41,IF(G41=8,F41,0)))),0) -> 0 | K41: =ROUND(IF(G41=1,F41/23,IF(G41=3,F41/12,IF(G41=6,F41,IF(G41=7,F41-I41,0)))),0) -> 0 | L41: =IF(G41=6,F41,0) -> 0 | P41: 昨年実績 | Q41: =IF($F41="","",IFERROR(VLOOKUP($C41&"|"&$D41,科目表!$A$5:$B$200,2,FALSE),"※未登録")) -> 事務用消耗品費 | R41: =IF($F41="","",$I41+$J41+$K41) -> 0 | S41: =IF(OR($F41="",$P41="支払なし",$H41=0,$Q41=""),"",$Q41&"|S|"&(COUNTIF(S$4:S40,$Q41&"|S|*")+1)) -> 事務用消耗品費|S|3 | T41: =IF(OR($F41="",$P41="支払なし",$R41=0,$Q41=""),"",$Q41&"|L|"&(COUNTIF(T$4:T40,$Q41&"|L|*")+1)) | U41: =IF($F41="","",13) -> 13
A42: 43951 | B42: 未払金 | C42: 委託費 | E42: 清掃・警備・ごみ処理（１０～３月分） | F42: 23404 | G42: 3 | H42: =IF(G42=1,F42-I42-J42-K42,IF(G42=2,F42,0)) -> 0 | I42: =ROUND(IF(G42=1,F42*10/23,IF(G42=3,F42-J42-K42,IF(G42=4,F42,IF(G42=5,F42*10/11,IF(G42=7,F42*10/11,0))))),0) -> 19504 | J42: =ROUND(IF(G42=1,F42/23,IF(G42=3,F42/12,IF(G42=5,F42-I42,IF(G42=8,F42,0)))),0) -> 1950 | K42: =ROUND(IF(G42=1,F42/23,IF(G42=3,F42/12,IF(G42=6,F42,IF(G42=7,F42-I42,0)))),0) -> 1950 | L42: =IF(G42=6,F42,0) -> 0 | P42: 昨年実績 | Q42: =IF($F42="","",IFERROR(VLOOKUP($C42&"|"&$D42,科目表!$A$5:$B$200,2,FALSE),"※未登録")) -> 委託費 | R42: =IF($F42="","",$I42+$J42+$K42) -> 23404 | S42: =IF(OR($F42="",$P42="支払なし",$H42=0,$Q42=""),"",$Q42&"|S|"&(COUNTIF(S$4:S41,$Q42&"|S|*")+1)) | T42: =IF(OR($F42="",$P42="支払なし",$R42=0,$Q42=""),"",$Q42&"|L|"&(COUNTIF(T$4:T41,$Q42&"|L|*")+1)) -> 委託費|L|3 | U42: =IF($F42="","",13) -> 13
A43: 43951 | B43: 未払金 | C43: 光熱水料 | D43: ガス料 | E43: 行政財産使用ガス料（１０～３月分） | F43: 7073 | G43: 3 | H43: =IF(G43=1,F43-I43-J43-K43,IF(G43=2,F43,0)) -> 0 | I43: =ROUND(IF(G43=1,F43*10/23,IF(G43=3,F43-J43-K43,IF(G43=4,F43,IF(G43=5,F43*10/11,IF(G43=7,F43*10/11,0))))),0) -> 5895 | J43: =ROUND(IF(G43=1,F43/23,IF(G43=3,F43/12,IF(G43=5,F43-I43,IF(G43=8,F43,0)))),0) -> 589 | K43: =ROUND(IF(G43=1,F43/23,IF(G43=3,F43/12,IF(G43=6,F43,IF(G43=7,F43-I43,0)))),0) -> 589 | L43: =IF(G43=6,F43,0) -> 0 | P43: 昨年実績 | Q43: =IF($F43="","",IFERROR(VLOOKUP($C43&"|"&$D43,科目表!$A$5:$B$200,2,FALSE),"※未登録")) -> 光熱水料 | R43: =IF($F43="","",$I43+$J43+$K43) -> 7073 | S43: =IF(OR($F43="",$P43="支払なし",$H43=0,$Q43=""),"",$Q43&"|S|"&(COUNTIF(S$4:S42,$Q43&"|S|*")+1)) | T43: =IF(OR($F43="",$P43="支払なし",$R43=0,$Q43=""),"",$Q43&"|L|"&(COUNTIF(T$4:T42,$Q43&"|L|*")+1)) -> 光熱水料|L|1 | U43: =IF($F43="","",13) -> 13
A44: 43951 | B44: 未払金 | C44: 光熱水料 | D44: 水道料 | E44: 行政財産使用水道料（１０～３月分） | F44: 13093 | G44: 3 | H44: =IF(G44=1,F44-I44-J44-K44,IF(G44=2,F44,0)) -> 0 | I44: =ROUND(IF(G44=1,F44*10/23,IF(G44=3,F44-J44-K44,IF(G44=4,F44,IF(G44=5,F44*10/11,IF(G44=7,F44*10/11,0))))),0) -> 10911 | J44: =ROUND(IF(G44=1,F44/23,IF(G44=3,F44/12,IF(G44=5,F44-I44,IF(G44=8,F44,0)))),0) -> 1091 | K44: =ROUND(IF(G44=1,F44/23,IF(G44=3,F44/12,IF(G44=6,F44,IF(G44=7,F44-I44,0)))),0) -> 1091 | L44: =IF(G44=6,F44,0) -> 0 | P44: 昨年実績 | Q44: =IF($F44="","",IFERROR(VLOOKUP($C44&"|"&$D44,科目表!$A$5:$B$200,2,FALSE),"※未登録")) -> 光熱水料 | R44: =IF($F44="","",$I44+$J44+$K44) -> 13093 | S44: =IF(OR($F44="",$P44="支払なし",$H44=0,$Q44=""),"",$Q44&"|S|"&(COUNTIF(S$4:S43,$Q44&"|S|*")+1)) | T44: =IF(OR($F44="",$P44="支払なし",$R44=0,$Q44=""),"",$Q44&"|L|"&(COUNTIF(T$4:T43,$Q44&"|L|*")+1)) -> 光熱水料|L|2 | U44: =IF($F44="","",13) -> 13
A45: 43951 | B45: 未払金 | C45: 光熱水料 | D45: 電気料 | E45: 行政財産使用電気料（１０～３月分） | F45: 21240 | G45: 3 | H45: =IF(G45=1,F45-I45-J45-K45,IF(G45=2,F45,0)) -> 0 | I45: =ROUND(IF(G45=1,F45*10/23,IF(G45=3,F45-J45-K45,IF(G45=4,F45,IF(G45=5,F45*10/11,IF(G45=7,F45*10/11,0))))),0) -> 17700 | J45: =ROUND(IF(G45=1,F45/23,IF(G45=3,F45/12,IF(G45=5,F45-I45,IF(G45=8,F45,0)))),0) -> 1770 | K45: =ROUND(IF(G45=1,F45/23,IF(G45=3,F45/12,IF(G45=6,F45,IF(G45=7,F45-I45,0)))),0) -> 1770 | L45: =IF(G45=6,F45,0) -> 0 | P45: 昨年実績 | Q45: =IF($F45="","",IFERROR(VLOOKUP($C45&"|"&$D45,科目表!$A$5:$B$200,2,FALSE),"※未登録")) -> 光熱水料 | R45: =IF($F45="","",$I45+$J45+$K45) -> 21240 | S45: =IF(OR($F45="",$P45="支払なし",$H45=0,$Q45=""),"",$Q45&"|S|"&(COUNTIF(S$4:S44,$Q45&"|S|*")+1)) | T45: =IF(OR($F45="",$P45="支払なし",$R45=0,$Q45=""),"",$Q45&"|L|"&(COUNTIF(T$4:T44,$Q45&"|L|*")+1)) -> 光熱水料|L|3 | U45: =IF($F45="","",13) -> 13
A46: 45775 | B46: 未払金 | C46: 事務費 | D46: 事務用消耗品費 | E46: ゴム印 １式 | F46: 16035 | G46: 3 | H46: =IF(G46=1,F46-I46-J46-K46,IF(G46=2,F46,0)) -> 0 | I46: =ROUND(IF(G46=1,F46*10/23,IF(G46=3,F46-J46-K46,IF(G46=4,F46,IF(G46=5,F46*10/11,IF(G46=7,F46*10/11,0))))),0) -> 13363 | J46: =ROUND(IF(G46=1,F46/23,IF(G46=3,F46/12,IF(G46=5,F46-I46,IF(G46=8,F46,0)))),0) -> 1336 | K46: =ROUND(IF(G46=1,F46/23,IF(G46=3,F46/12,IF(G46=6,F46,IF(G46=7,F46-I46,0)))),0) -> 1336 | L46: =IF(G46=6,F46,0) -> 0 | P46: 昨年実績 | Q46: =IF($F46="","",IFERROR(VLOOKUP($C46&"|"&$D46,科目表!$A$5:$B$200,2,FALSE),"※未登録")) -> 事務用消耗品費 | R46: =IF($F46="","",$I46+$J46+$K46) -> 16035 | S46: =IF(OR($F46="",$P46="支払なし",$H46=0,$Q46=""),"",$Q46&"|S|"&(COUNTIF(S$4:S45,$Q46&"|S|*")+1)) | T46: =IF(OR($F46="",$P46="支払なし",$R46=0,$Q46=""),"",$Q46&"|L|"&(COUNTIF(T$4:T45,$Q46&"|L|*")+1)) -> 事務用消耗品費|L|1 | U46: =IF($F46="","",13) -> 13
A47: 43951 | B47: 未払金 | C47: 事務費 | D47: 事務用消耗品費 | E47: 複写機用紙等購入代分担金（第4四半期）長期 | F47: 92843 | G47: 3 | H47: =IF(G47=1,F47-I47-J47-K47,IF(G47=2,F47,0)) -> 0 | I47: =ROUND(IF(G47=1,F47*10/23,IF(G47=3,F47-J47-K47,IF(G47=4,F47,IF(G47=5,F47*10/11,IF(G47=7,F47*10/11,0))))),0) -> 77369 | J47: =ROUND(IF(G47=1,F47/23,IF(G47=3,F47/12,IF(G47=5,F47-I47,IF(G47=8,F47,0)))),0) -> 7737 | K47: =ROUND(IF(G47=1,F47/23,IF(G47=3,F47/12,IF(G47=6,F47,IF(G47=7,F47-I47,0)))),0) -> 7737 | L47: =IF(G47=6,F47,0) -> 0 | P47: 昨年実績 | Q47: =IF($F47="","",IFERROR(VLOOKUP($C47&"|"&$D47,科目表!$A$5:$B$200,2,FALSE),"※未登録")) -> 事務用消耗品費 | R47: =IF($F47="","",$I47+$J47+$K47) -> 92843 | S47: =IF(OR($F47="",$P47="支払なし",$H47=0,$Q47=""),"",$Q47&"|S|"&(COUNTIF(S$4:S46,$Q47&"|S|*")+1)) | T47: =IF(OR($F47="",$P47="支払なし",$R47=0,$Q47=""),"",$Q47&"|L|"&(COUNTIF(T$4:T46,$Q47&"|L|*")+1)) -> 事務用消耗品費|L|2 | U47: =IF($F47="","",13) -> 13
A48: 43942 | B48: 未払金 | C48: 事務費 | D48: 送金料 | E48: 年金過払金等返還金振替料金（ゆうちょ銀行） | F48: 1022 | G48: 3 | H48: =IF(G48=1,F48-I48-J48-K48,IF(G48=2,F48,0)) -> 0 | I48: =ROUND(IF(G48=1,F48*10/23,IF(G48=3,F48-J48-K48,IF(G48=4,F48,IF(G48=5,F48*10/11,IF(G48=7,F48*10/11,0))))),0) -> 852 | J48: =ROUND(IF(G48=1,F48/23,IF(G48=3,F48/12,IF(G48=5,F48-I48,IF(G48=8,F48,0)))),0) -> 85 | K48: =ROUND(IF(G48=1,F48/23,IF(G48=3,F48/12,IF(G48=6,F48,IF(G48=7,F48-I48,0)))),0) -> 85 | L48: =IF(G48=6,F48,0) -> 0 | P48: 昨年実績 | Q48: =IF($F48="","",IFERROR(VLOOKUP($C48&"|"&$D48,科目表!$A$5:$B$200,2,FALSE),"※未登録")) -> 送金料 | R48: =IF($F48="","",$I48+$J48+$K48) -> 1022 | S48: =IF(OR($F48="",$P48="支払なし",$H48=0,$Q48=""),"",$Q48&"|S|"&(COUNTIF(S$4:S47,$Q48&"|S|*")+1)) | T48: =IF(OR($F48="",$P48="支払なし",$R48=0,$Q48=""),"",$Q48&"|L|"&(COUNTIF(T$4:T47,$Q48&"|L|*")+1)) -> 送金料|L|1 | U48: =IF($F48="","",13) -> 13
A49: 43931 | B49: 未払金 | C49: 事務費 | D49: 送金料 | E49: 広銀手数料（３月分）長期 | F49: 19580 | G49: 3 | H49: =IF(G49=1,F49-I49-J49-K49,IF(G49=2,F49,0)) -> 0 | I49: =ROUND(IF(G49=1,F49*10/23,IF(G49=3,F49-J49-K49,IF(G49=4,F49,IF(G49=5,F49*10/11,IF(G49=7,F49*10/11,0))))),0) -> 16316 | J49: =ROUND(IF(G49=1,F49/23,IF(G49=3,F49/12,IF(G49=5,F49-I49,IF(G49=8,F49,0)))),0) -> 1632 | K49: =ROUND(IF(G49=1,F49/23,IF(G49=3,F49/12,IF(G49=6,F49,IF(G49=7,F49-I49,0)))),0) -> 1632 | L49: =IF(G49=6,F49,0) -> 0 | P49: 昨年実績 | Q49: =IF($F49="","",IFERROR(VLOOKUP($C49&"|"&$D49,科目表!$A$5:$B$200,2,FALSE),"※未登録")) -> 送金料 | R49: =IF($F49="","",$I49+$J49+$K49) -> 19580 | S49: =IF(OR($F49="",$P49="支払なし",$H49=0,$Q49=""),"",$Q49&"|S|"&(COUNTIF(S$4:S48,$Q49&"|S|*")+1)) | T49: =IF(OR($F49="",$P49="支払なし",$R49=0,$Q49=""),"",$Q49&"|L|"&(COUNTIF(T$4:T48,$Q49&"|L|*")+1)) -> 送金料|L|2 | U49: =IF($F49="","",13) -> 13
A50: 43951 | B50: 未払金 | C50: 事務費 | D50: 通信運搬費 | E50: 後納料金利用料 3月分 | F50: 80599 | G50: 3 | H50: =IF(G50=1,F50-I50-J50-K50,IF(G50=2,F50,0)) -> 0 | I50: =ROUND(IF(G50=1,F50*10/23,IF(G50=3,F50-J50-K50,IF(G50=4,F50,IF(G50=5,F50*10/11,IF(G50=7,F50*10/11,0))))),0) -> 67165 | J50: =ROUND(IF(G50=1,F50/23,IF(G50=3,F50/12,IF(G50=5,F50-I50,IF(G50=8,F50,0)))),0) -> 6717 | K50: =ROUND(IF(G50=1,F50/23,IF(G50=3,F50/12,IF(G50=6,F50,IF(G50=7,F50-I50,0)))),0) -> 6717 | L50: =IF(G50=6,F50,0) -> 0 | P50: 昨年実績 | Q50: =IF($F50="","",IFERROR(VLOOKUP($C50&"|"&$D50,科目表!$A$5:$B$200,2,FALSE),"※未登録")) -> 通信運搬費 | R50: =IF($F50="","",$I50+$J50+$K50) -> 80599 | S50: =IF(OR($F50="",$P50="支払なし",$H50=0,$Q50=""),"",$Q50&"|S|"&(COUNTIF(S$4:S49,$Q50&"|S|*")+1)) | T50: =IF(OR($F50="",$P50="支払なし",$R50=0,$Q50=""),"",$Q50&"|L|"&(COUNTIF(T$4:T49,$Q50&"|L|*")+1)) -> 通信運搬費|L|1 | U50: =IF($F50="","",13) -> 13
A51: 43951 | B51: 未払金 | C51: 事務費 | D51: 通信運搬費 | E51: ファクシミリ電話代等分担金（第4四半期）長期 | F51: 5952 | G51: 3 | H51: =IF(G51=1,F51-I51-J51-K51,IF(G51=2,F51,0)) -> 0 | I51: =ROUND(IF(G51=1,F51*10/23,IF(G51=3,F51-J51-K51,IF(G51=4,F51,IF(G51=5,F51*10/11,IF(G51=7,F51*10/11,0))))),0) -> 4960 | J51: =ROUND(IF(G51=1,F51/23,IF(G51=3,F51/12,IF(G51=5,F51-I51,IF(G51=8,F51,0)))),0) -> 496 | K51: =ROUND(IF(G51=1,F51/23,IF(G51=3,F51/12,IF(G51=6,F51,IF(G51=7,F51-I51,0)))),0) -> 496 | L51: =IF(G51=6,F51,0) -> 0 | P51: 昨年実績 | Q51: =IF($F51="","",IFERROR(VLOOKUP($C51&"|"&$D51,科目表!$A$5:$B$200,2,FALSE),"※未登録")) -> 通信運搬費 | R51: =IF($F51="","",$I51+$J51+$K51) -> 5952 | S51: =IF(OR($F51="",$P51="支払なし",$H51=0,$Q51=""),"",$Q51&"|S|"&(COUNTIF(S$4:S50,$Q51&"|S|*")+1)) | T51: =IF(OR($F51="",$P51="支払なし",$R51=0,$Q51=""),"",$Q51&"|L|"&(COUNTIF(T$4:T50,$Q51&"|L|*")+1)) -> 通信運搬費|L|2 | U51: =IF($F51="","",13) -> 13
A52: 43951 | B52: 未払金 | C52: 事務費 | D52: 通信運搬費 | E52: 行政財産使用電話料（１０～３月分） | F52: 18000 | G52: 3 | H52: =IF(G52=1,F52-I52-J52-K52,IF(G52=2,F52,0)) -> 0 | I52: =ROUND(IF(G52=1,F52*10/23,IF(G52=3,F52-J52-K52,IF(G52=4,F52,IF(G52=5,F52*10/11,IF(G52=7,F52*10/11,0))))),0) -> 15000 | J52: =ROUND(IF(G52=1,F52/23,IF(G52=3,F52/12,IF(G52=5,F52-I52,IF(G52=8,F52,0)))),0) -> 1500 | K52: =ROUND(IF(G52=1,F52/23,IF(G52=3,F52/12,IF(G52=6,F52,IF(G52=7,F52-I52,0)))),0) -> 1500 | L52: =IF(G52=6,F52,0) -> 0 | P52: 昨年実績 | Q52: =IF($F52="","",IFERROR(VLOOKUP($C52&"|"&$D52,科目表!$A$5:$B$200,2,FALSE),"※未登録")) -> 通信運搬費 | R52: =IF($F52="","",$I52+$J52+$K52) -> 18000 | S52: =IF(OR($F52="",$P52="支払なし",$H52=0,$Q52=""),"",$Q52&"|S|"&(COUNTIF(S$4:S51,$Q52&"|S|*")+1)) | T52: =IF(OR($F52="",$P52="支払なし",$R52=0,$Q52=""),"",$Q52&"|L|"&(COUNTIF(T$4:T51,$Q52&"|L|*")+1)) -> 通信運搬費|L|3 | U52: =IF($F52="","",13) -> 13
A53: 43942 | B53: 未払金 | C53: 事務費 | E53: ゆうちょ銀行一般振替口座 残高証明書発行手数料 | F53: 617 | G53: 3 | H53: =IF(G53=1,F53-I53-J53-K53,IF(G53=2,F53,0)) -> 0 | I53: =ROUND(IF(G53=1,F53*10/23,IF(G53=3,F53-J53-K53,IF(G53=4,F53,IF(G53=5,F53*10/11,IF(G53=7,F53*10/11,0))))),0) -> 515 | J53: =ROUND(IF(G53=1,F53/23,IF(G53=3,F53/12,IF(G53=5,F53-I53,IF(G53=8,F53,0)))),0) -> 51 | K53: =ROUND(IF(G53=1,F53/23,IF(G53=3,F53/12,IF(G53=6,F53,IF(G53=7,F53-I53,0)))),0) -> 51 | L53: =IF(G53=6,F53,0) -> 0 | P53: 昨年実績 | Q53: =IF($F53="","",IFERROR(VLOOKUP($C53&"|"&$D53,科目表!$A$5:$B$200,2,FALSE),"※未登録")) -> 事務費・雑費 | R53: =IF($F53="","",$I53+$J53+$K53) -> 617 | S53: =IF(OR($F53="",$P53="支払なし",$H53=0,$Q53=""),"",$Q53&"|S|"&(COUNTIF(S$4:S52,$Q53&"|S|*")+1)) | T53: =IF(OR($F53="",$P53="支払なし",$R53=0,$Q53=""),"",$Q53&"|L|"&(COUNTIF(T$4:T52,$Q53&"|L|*")+1)) -> 事務費・雑費|L|2 | U53: =IF($F53="","",13) -> 13
A54: 46140 | B54: 未払金 | C54: 賃借料 | E54: サーバラック（長期） | F54: 16152 | G54: 3 | H54: =IF(G54=1,F54-I54-J54-K54,IF(G54=2,F54,0)) -> 0 | I54: =ROUND(IF(G54=1,F54*10/23,IF(G54=3,F54-J54-K54,IF(G54=4,F54,IF(G54=5,F54*10/11,IF(G54=7,F54*10/11,0))))),0) -> 13460 | J54: =ROUND(IF(G54=1,F54/23,IF(G54=3,F54/12,IF(G54=5,F54-I54,IF(G54=8,F54,0)))),0) -> 1346 | K54: =ROUND(IF(G54=1,F54/23,IF(G54=3,F54/12,IF(G54=6,F54,IF(G54=7,F54-I54,0)))),0) -> 1346 | L54: =IF(G54=6,F54,0) -> 0 | P54: 昨年実績 | Q54: =IF($F54="","",IFERROR(VLOOKUP($C54&"|"&$D54,科目表!$A$5:$B$200,2,FALSE),"※未登録")) -> 賃借料 | R54: =IF($F54="","",$I54+$J54+$K54) -> 16152 | S54: =IF(OR($F54="",$P54="支払なし",$H54=0,$Q54=""),"",$Q54&"|S|"&(COUNTIF(S$4:S53,$Q54&"|S|*")+1)) | T54: =IF(OR($F54="",$P54="支払なし",$R54=0,$Q54=""),"",$Q54&"|L|"&(COUNTIF(T$4:T53,$Q54&"|L|*")+1)) -> 賃借料|L|2 | U54: =IF($F54="","",13) -> 13
A55: 44679 | B55: 未払金 | C55: 賃借料 | E55: 病院機構人給システム（パソコン・プリンタ使用料）長期 | F55: 25902 | G55: 3 | H55: =IF(G55=1,F55-I55-J55-K55,IF(G55=2,F55,0)) -> 0 | I55: =ROUND(IF(G55=1,F55*10/23,IF(G55=3,F55-J55-K55,IF(G55=4,F55,IF(G55=5,F55*10/11,IF(G55=7,F55*10/11,0))))),0) -> 21584 | J55: =ROUND(IF(G55=1,F55/23,IF(G55=3,F55/12,IF(G55=5,F55-I55,IF(G55=8,F55,0)))),0) -> 2159 | K55: =ROUND(IF(G55=1,F55/23,IF(G55=3,F55/12,IF(G55=6,F55,IF(G55=7,F55-I55,0)))),0) -> 2159 | L55: =IF(G55=6,F55,0) -> 0 | P55: 昨年実績 | Q55: =IF($F55="","",IFERROR(VLOOKUP($C55&"|"&$D55,科目表!$A$5:$B$200,2,FALSE),"※未登録")) -> 賃借料 | R55: =IF($F55="","",$I55+$J55+$K55) -> 25902 | S55: =IF(OR($F55="",$P55="支払なし",$H55=0,$Q55=""),"",$Q55&"|S|"&(COUNTIF(S$4:S54,$Q55&"|S|*")+1)) | T55: =IF(OR($F55="",$P55="支払なし",$R55=0,$Q55=""),"",$Q55&"|L|"&(COUNTIF(T$4:T54,$Q55&"|L|*")+1)) -> 賃借料|L|3 | U55: =IF($F55="","",13) -> 13
A56: 43951 | B56: 未払金 | C56: 普及費 | E56: 厚生だより等印刷代分担金（第4四半期）長期 | F56: 522996 | G56: 3 | H56: =IF(G56=1,F56-I56-J56-K56,IF(G56=2,F56,0)) -> 0 | I56: =ROUND(IF(G56=1,F56*10/23,IF(G56=3,F56-J56-K56,IF(G56=4,F56,IF(G56=5,F56*10/11,IF(G56=7,F56*10/11,0))))),0) -> 435830 | J56: =ROUND(IF(G56=1,F56/23,IF(G56=3,F56/12,IF(G56=5,F56-I56,IF(G56=8,F56,0)))),0) -> 43583 | K56: =ROUND(IF(G56=1,F56/23,IF(G56=3,F56/12,IF(G56=6,F56,IF(G56=7,F56-I56,0)))),0) -> 43583 | L56: =IF(G56=6,F56,0) -> 0 | P56: 昨年実績 | Q56: =IF($F56="","",IFERROR(VLOOKUP($C56&"|"&$D56,科目表!$A$5:$B$200,2,FALSE),"※未登録")) -> 普及費 | R56: =IF($F56="","",$I56+$J56+$K56) -> 522996 | S56: =IF(OR($F56="",$P56="支払なし",$H56=0,$Q56=""),"",$Q56&"|S|"&(COUNTIF(S$4:S55,$Q56&"|S|*")+1)) | T56: =IF(OR($F56="",$P56="支払なし",$R56=0,$Q56=""),"",$Q56&"|L|"&(COUNTIF(T$4:T55,$Q56&"|L|*")+1)) -> 普及費|L|1 | U56: =IF($F56="","",13) -> 13
A57: 43951 | B57: 未払金 | C57: 負担金 | D57: 厚年負担金等 | E57: ３月月例+３月賞与分（長期分）子ども子育て拠出金を含む | F57: 39858 | G57: 3 | H57: =IF(G57=1,F57-I57-J57-K57,IF(G57=2,F57,0)) -> 0 | I57: =ROUND(IF(G57=1,F57*10/23,IF(G57=3,F57-J57-K57,IF(G57=4,F57,IF(G57=5,F57*10/11,IF(G57=7,F57*10/11,0))))),0) -> 33214 | J57: =ROUND(IF(G57=1,F57/23,IF(G57=3,F57/12,IF(G57=5,F57-I57,IF(G57=8,F57,0)))),0) -> 3322 | K57: =ROUND(IF(G57=1,F57/23,IF(G57=3,F57/12,IF(G57=6,F57,IF(G57=7,F57-I57,0)))),0) -> 3322 | L57: =IF(G57=6,F57,0) -> 0 | P57: 昨年実績 | Q57: =IF($F57="","",IFERROR(VLOOKUP($C57&"|"&$D57,科目表!$A$5:$B$200,2,FALSE),"※未登録")) -> 厚年負担金等 | R57: =IF($F57="","",$I57+$J57+$K57) -> 39858 | S57: =IF(OR($F57="",$P57="支払なし",$H57=0,$Q57=""),"",$Q57&"|S|"&(COUNTIF(S$4:S56,$Q57&"|S|*")+1)) | T57: =IF(OR($F57="",$P57="支払なし",$R57=0,$Q57=""),"",$Q57&"|L|"&(COUNTIF(T$4:T56,$Q57&"|L|*")+1)) -> 厚年負担金等|L|1 | U57: =IF($F57="","",13) -> 13
A58: 43951 | B58: 未払金 | C58: 負担金 | D58: 協会けんぽ保険料等 | E58: ３月月例+３月賞与分（長期分） | F58: 22364 | G58: 3 | H58: =IF(G58=1,F58-I58-J58-K58,IF(G58=2,F58,0)) -> 0 | I58: =ROUND(IF(G58=1,F58*10/23,IF(G58=3,F58-J58-K58,IF(G58=4,F58,IF(G58=5,F58*10/11,IF(G58=7,F58*10/11,0))))),0) -> 18636 | J58: =ROUND(IF(G58=1,F58/23,IF(G58=3,F58/12,IF(G58=5,F58-I58,IF(G58=8,F58,0)))),0) -> 1864 | K58: =ROUND(IF(G58=1,F58/23,IF(G58=3,F58/12,IF(G58=6,F58,IF(G58=7,F58-I58,0)))),0) -> 1864 | L58: =IF(G58=6,F58,0) -> 0 | P58: 昨年実績 | Q58: =IF($F58="","",IFERROR(VLOOKUP($C58&"|"&$D58,科目表!$A$5:$B$200,2,FALSE),"※未登録")) -> 協会けんぽ保険料等 | R58: =IF($F58="","",$I58+$J58+$K58) -> 22364 | S58: =IF(OR($F58="",$P58="支払なし",$H58=0,$Q58=""),"",$Q58&"|S|"&(COUNTIF(S$4:S57,$Q58&"|S|*")+1)) | T58: =IF(OR($F58="",$P58="支払なし",$R58=0,$Q58=""),"",$Q58&"|L|"&(COUNTIF(T$4:T57,$Q58&"|L|*")+1)) -> 協会けんぽ保険料等|L|1 | U58: =IF($F58="","",13) -> 13
A59: 46127 | B59: 未払金 | C59: 委託費 | E59: ねんきん定期便（３月分）送付業務 | F59: 80964 | G59: 5 | H59: =IF(G59=1,F59-I59-J59-K59,IF(G59=2,F59,0)) -> 0 | I59: =ROUND(IF(G59=1,F59*10/23,IF(G59=3,F59-J59-K59,IF(G59=4,F59,IF(G59=5,F59*10/11,IF(G59=7,F59*10/11,0))))),0) -> 73604 | J59: =ROUND(IF(G59=1,F59/23,IF(G59=3,F59/12,IF(G59=5,F59-I59,IF(G59=8,F59,0)))),0) -> 7360 | K59: =ROUND(IF(G59=1,F59/23,IF(G59=3,F59/12,IF(G59=6,F59,IF(G59=7,F59-I59,0)))),0) -> 0 | L59: =IF(G59=6,F59,0) -> 0 | P59: 昨年実績 | Q59: =IF($F59="","",IFERROR(VLOOKUP($C59&"|"&$D59,科目表!$A$5:$B$200,2,FALSE),"※未登録")) -> 委託費 | R59: =IF($F59="","",$I59+$J59+$K59) -> 80964 | S59: =IF(OR($F59="",$P59="支払なし",$H59=0,$Q59=""),"",$Q59&"|S|"&(COUNTIF(S$4:S58,$Q59&"|S|*")+1)) | T59: =IF(OR($F59="",$P59="支払なし",$R59=0,$Q59=""),"",$Q59&"|L|"&(COUNTIF(T$4:T58,$Q59&"|L|*")+1)) -> 委託費|L|4 | U59: =IF($F59="","",13) -> 13
A60: 46127 | B60: 未払金 | C60: 賃借料 | E60: サーバ版標準システム構成機器（10～3月分) | F60: 87450 | G60: 3 | H60: =IF(G60=1,F60-I60-J60-K60,IF(G60=2,F60,0)) -> 0 | I60: =ROUND(IF(G60=1,F60*10/23,IF(G60=3,F60-J60-K60,IF(G60=4,F60,IF(G60=5,F60*10/11,IF(G60=7,F60*10/11,0))))),0) -> 72874 | J60: =ROUND(IF(G60=1,F60/23,IF(G60=3,F60/12,IF(G60=5,F60-I60,IF(G60=8,F60,0)))),0) -> 7288 | K60: =ROUND(IF(G60=1,F60/23,IF(G60=3,F60/12,IF(G60=6,F60,IF(G60=7,F60-I60,0)))),0) -> 7288 | L60: =IF(G60=6,F60,0) -> 0 | P60: 昨年実績 | Q60: =IF($F60="","",IFERROR(VLOOKUP($C60&"|"&$D60,科目表!$A$5:$B$200,2,FALSE),"※未登録")) -> 賃借料 | R60: =IF($F60="","",$I60+$J60+$K60) -> 87450 | S60: =IF(OR($F60="",$P60="支払なし",$H60=0,$Q60=""),"",$Q60&"|S|"&(COUNTIF(S$4:S59,$Q60&"|S|*")+1)) | T60: =IF(OR($F60="",$P60="支払なし",$R60=0,$Q60=""),"",$Q60&"|L|"&(COUNTIF(T$4:T59,$Q60&"|L|*")+1)) -> 賃借料|L|4 | U60: =IF($F60="","",13) -> 13
A61: 46140 | B61: 未払金 | C61: 賃借料 | E61: 基幹システム用機器賃借料 ３月分（長期） | F61: 69613 | G61: 3 | H61: =IF(G61=1,F61-I61-J61-K61,IF(G61=2,F61,0)) -> 0 | I61: =ROUND(IF(G61=1,F61*10/23,IF(G61=3,F61-J61-K61,IF(G61=4,F61,IF(G61=5,F61*10/11,IF(G61=7,F61*10/11,0))))),0) -> 58011 | J61: =ROUND(IF(G61=1,F61/23,IF(G61=3,F61/12,IF(G61=5,F61-I61,IF(G61=8,F61,0)))),0) -> 5801 | K61: =ROUND(IF(G61=1,F61/23,IF(G61=3,F61/12,IF(G61=6,F61,IF(G61=7,F61-I61,0)))),0) -> 5801 | L61: =IF(G61=6,F61,0) -> 0 | P61: 昨年実績 | Q61: =IF($F61="","",IFERROR(VLOOKUP($C61&"|"&$D61,科目表!$A$5:$B$200,2,FALSE),"※未登録")) -> 賃借料 | R61: =IF($F61="","",$I61+$J61+$K61) -> 69613 | S61: =IF(OR($F61="",$P61="支払なし",$H61=0,$Q61=""),"",$Q61&"|S|"&(COUNTIF(S$4:S60,$Q61&"|S|*")+1)) | T61: =IF(OR($F61="",$P61="支払なし",$R61=0,$Q61=""),"",$Q61&"|L|"&(COUNTIF(T$4:T60,$Q61&"|L|*")+1)) -> 賃借料|L|5 | U61: =IF($F61="","",13) -> 13
A62: 46140 | B62: 未払金 | C62: 賃借料 | E62: 基幹システム用機器賃借料 ３月分（短期） | F62: 672934 | G62: 2 | H62: =IF(G62=1,F62-I62-J62-K62,IF(G62=2,F62,0)) -> 672934 | I62: =ROUND(IF(G62=1,F62*10/23,IF(G62=3,F62-J62-K62,IF(G62=4,F62,IF(G62=5,F62*10/11,IF(G62=7,F62*10/11,0))))),0) -> 0 | J62: =ROUND(IF(G62=1,F62/23,IF(G62=3,F62/12,IF(G62=5,F62-I62,IF(G62=8,F62,0)))),0) -> 0 | K62: =ROUND(IF(G62=1,F62/23,IF(G62=3,F62/12,IF(G62=6,F62,IF(G62=7,F62-I62,0)))),0) -> 0 | L62: =IF(G62=6,F62,0) -> 0 | P62: 昨年実績 | Q62: =IF($F62="","",IFERROR(VLOOKUP($C62&"|"&$D62,科目表!$A$5:$B$200,2,FALSE),"※未登録")) -> 賃借料 | R62: =IF($F62="","",$I62+$J62+$K62) -> 0 | S62: =IF(OR($F62="",$P62="支払なし",$H62=0,$Q62=""),"",$Q62&"|S|"&(COUNTIF(S$4:S61,$Q62&"|S|*")+1)) -> 賃借料|S|5 | T62: =IF(OR($F62="",$P62="支払なし",$R62=0,$Q62=""),"",$Q62&"|L|"&(COUNTIF(T$4:T61,$Q62&"|L|*")+1)) | U62: =IF($F62="","",13) -> 13
A63: 44679 | B63: 未払金 | C63: 事務費 | D63: 通信運搬費 | E63: メール便（任継者宛厚生だより３月分） | F63: 3024 | G63: 2 | H63: =IF(G63=1,F63-I63-J63-K63,IF(G63=2,F63,0)) -> 3024 | I63: =ROUND(IF(G63=1,F63*10/23,IF(G63=3,F63-J63-K63,IF(G63=4,F63,IF(G63=5,F63*10/11,IF(G63=7,F63*10/11,0))))),0) -> 0 | J63: =ROUND(IF(G63=1,F63/23,IF(G63=3,F63/12,IF(G63=5,F63-I63,IF(G63=8,F63,0)))),0) -> 0 | K63: =ROUND(IF(G63=1,F63/23,IF(G63=3,F63/12,IF(G63=6,F63,IF(G63=7,F63-I63,0)))),0) -> 0 | L63: =IF(G63=6,F63,0) -> 0 | P63: 昨年実績 | Q63: =IF($F63="","",IFERROR(VLOOKUP($C63&"|"&$D63,科目表!$A$5:$B$200,2,FALSE),"※未登録")) -> 通信運搬費 | R63: =IF($F63="","",$I63+$J63+$K63) -> 0 | S63: =IF(OR($F63="",$P63="支払なし",$H63=0,$Q63=""),"",$Q63&"|S|"&(COUNTIF(S$4:S62,$Q63&"|S|*")+1)) -> 通信運搬費|S|7 | T63: =IF(OR($F63="",$P63="支払なし",$R63=0,$Q63=""),"",$Q63&"|L|"&(COUNTIF(T$4:T62,$Q63&"|L|*")+1)) | U63: =IF($F63="","",13) -> 13
H64: =IF(G64=1,F64-I64-J64-K64,IF(G64=2,F64,0)) -> 0 | I64: =ROUND(IF(G64=1,F64*10/23,IF(G64=3,F64-J64-K64,IF(G64=4,F64,IF(G64=5,F64*10/11,IF(G64=7,F64*10/11,0))))),0) -> 0 | J64: =ROUND(IF(G64=1,F64/23,IF(G64=3,F64/12,IF(G64=5,F64-I64,IF(G64=8,F64,0)))),0) -> 0 | K64: =ROUND(IF(G64=1,F64/23,IF(G64=3,F64/12,IF(G64=6,F64,IF(G64=7,F64-I64,0)))),0) -> 0 | L64: =IF(G64=6,F64,0) -> 0 | Q64: =IF($F64="","",IFERROR(VLOOKUP($C64&"|"&$D64,科目表!$A$5:$B$200,2,FALSE),"※未登録")) | R64: =IF($F64="","",$I64+$J64+$K64) | S64: =IF(OR($F64="",$P64="支払なし",$H64=0,$Q64=""),"",$Q64&"|S|"&(COUNTIF(S$4:S63,$Q64&"|S|*")+1)) | T64: =IF(OR($F64="",$P64="支払なし",$R64=0,$Q64=""),"",$Q64&"|L|"&(COUNTIF(T$4:T63,$Q64&"|L|*")+1)) | U64: =IF($F64="","",13)
H65: =IF(G65=1,F65-I65-J65-K65,IF(G65=2,F65,0)) -> 0 | I65: =ROUND(IF(G65=1,F65*10/23,IF(G65=3,F65-J65-K65,IF(G65=4,F65,IF(G65=5,F65*10/11,IF(G65=7,F65*10/11,0))))),0) -> 0 | J65: =ROUND(IF(G65=1,F65/23,IF(G65=3,F65/12,IF(G65=5,F65-I65,IF(G65=8,F65,0)))),0) -> 0 | K65: =ROUND(IF(G65=1,F65/23,IF(G65=3,F65/12,IF(G65=6,F65,IF(G65=7,F65-I65,0)))),0) -> 0 | L65: =IF(G65=6,F65,0) -> 0 | Q65: =IF($F65="","",IFERROR(VLOOKUP($C65&"|"&$D65,科目表!$A$5:$B$200,2,FALSE),"※未登録")) | R65: =IF($F65="","",$I65+$J65+$K65) | S65: =IF(OR($F65="",$P65="支払なし",$H65=0,$Q65=""),"",$Q65&"|S|"&(COUNTIF(S$4:S64,$Q65&"|S|*")+1)) | T65: =IF(OR($F65="",$P65="支払なし",$R65=0,$Q65=""),"",$Q65&"|L|"&(COUNTIF(T$4:T64,$Q65&"|L|*")+1)) | U65: =IF($F65="","",13)
H66: =IF(G66=1,F66-I66-J66-K66,IF(G66=2,F66,0)) -> 0 | I66: =ROUND(IF(G66=1,F66*10/23,IF(G66=3,F66-J66-K66,IF(G66=4,F66,IF(G66=5,F66*10/11,IF(G66=7,F66*10/11,0))))),0) -> 0 | J66: =ROUND(IF(G66=1,F66/23,IF(G66=3,F66/12,IF(G66=5,F66-I66,IF(G66=8,F66,0)))),0) -> 0 | K66: =ROUND(IF(G66=1,F66/23,IF(G66=3,F66/12,IF(G66=6,F66,IF(G66=7,F66-I66,0)))),0) -> 0 | L66: =IF(G66=6,F66,0) -> 0 | Q66: =IF($F66="","",IFERROR(VLOOKUP($C66&"|"&$D66,科目表!$A$5:$B$200,2,FALSE),"※未登録")) | R66: =IF($F66="","",$I66+$J66+$K66) | S66: =IF(OR($F66="",$P66="支払なし",$H66=0,$Q66=""),"",$Q66&"|S|"&(COUNTIF(S$4:S65,$Q66&"|S|*")+1)) | T66: =IF(OR($F66="",$P66="支払なし",$R66=0,$Q66=""),"",$Q66&"|L|"&(COUNTIF(T$4:T65,$Q66&"|L|*")+1)) | U66: =IF($F66="","",13)
H67: =IF(G67=1,F67-I67-J67-K67,IF(G67=2,F67,0)) -> 0 | I67: =ROUND(IF(G67=1,F67*10/23,IF(G67=3,F67-J67-K67,IF(G67=4,F67,IF(G67=5,F67*10/11,IF(G67=7,F67*10/11,0))))),0) -> 0 | J67: =ROUND(IF(G67=1,F67/23,IF(G67=3,F67/12,IF(G67=5,F67-I67,IF(G67=8,F67,0)))),0) -> 0 | K67: =ROUND(IF(G67=1,F67/23,IF(G67=3,F67/12,IF(G67=6,F67,IF(G67=7,F67-I67,0)))),0) -> 0 | L67: =IF(G67=6,F67,0) -> 0 | Q67: =IF($F67="","",IFERROR(VLOOKUP($C67&"|"&$D67,科目表!$A$5:$B$200,2,FALSE),"※未登録")) | R67: =IF($F67="","",$I67+$J67+$K67) | S67: =IF(OR($F67="",$P67="支払なし",$H67=0,$Q67=""),"",$Q67&"|S|"&(COUNTIF(S$4:S66,$Q67&"|S|*")+1)) | T67: =IF(OR($F67="",$P67="支払なし",$R67=0,$Q67=""),"",$Q67&"|L|"&(COUNTIF(T$4:T66,$Q67&"|L|*")+1)) | U67: =IF($F67="","",13)
H68: =IF(G68=1,F68-I68-J68-K68,IF(G68=2,F68,0)) -> 0 | I68: =ROUND(IF(G68=1,F68*10/23,IF(G68=3,F68-J68-K68,IF(G68=4,F68,IF(G68=5,F68*10/11,IF(G68=7,F68*10/11,0))))),0) -> 0 | J68: =ROUND(IF(G68=1,F68/23,IF(G68=3,F68/12,IF(G68=5,F68-I68,IF(G68=8,F68,0)))),0) -> 0 | K68: =ROUND(IF(G68=1,F68/23,IF(G68=3,F68/12,IF(G68=6,F68,IF(G68=7,F68-I68,0)))),0) -> 0 | L68: =IF(G68=6,F68,0) -> 0 | Q68: =IF($F68="","",IFERROR(VLOOKUP($C68&"|"&$D68,科目表!$A$5:$B$200,2,FALSE),"※未登録")) | R68: =IF($F68="","",$I68+$J68+$K68) | S68: =IF(OR($F68="",$P68="支払なし",$H68=0,$Q68=""),"",$Q68&"|S|"&(COUNTIF(S$4:S67,$Q68&"|S|*")+1)) | T68: =IF(OR($F68="",$P68="支払なし",$R68=0,$Q68=""),"",$Q68&"|L|"&(COUNTIF(T$4:T67,$Q68&"|L|*")+1)) | U68: =IF($F68="","",13)
H69: =IF(G69=1,F69-I69-J69-K69,IF(G69=2,F69,0)) -> 0 | I69: =ROUND(IF(G69=1,F69*10/23,IF(G69=3,F69-J69-K69,IF(G69=4,F69,IF(G69=5,F69*10/11,IF(G69=7,F69*10/11,0))))),0) -> 0 | J69: =ROUND(IF(G69=1,F69/23,IF(G69=3,F69/12,IF(G69=5,F69-I69,IF(G69=8,F69,0)))),0) -> 0 | K69: =ROUND(IF(G69=1,F69/23,IF(G69=3,F69/12,IF(G69=6,F69,IF(G69=7,F69-I69,0)))),0) -> 0 | L69: =IF(G69=6,F69,0) -> 0 | Q69: =IF($F69="","",IFERROR(VLOOKUP($C69&"|"&$D69,科目表!$A$5:$B$200,2,FALSE),"※未登録")) | R69: =IF($F69="","",$I69+$J69+$K69) | S69: =IF(OR($F69="",$P69="支払なし",$H69=0,$Q69=""),"",$Q69&"|S|"&(COUNTIF(S$4:S68,$Q69&"|S|*")+1)) | T69: =IF(OR($F69="",$P69="支払なし",$R69=0,$Q69=""),"",$Q69&"|L|"&(COUNTIF(T$4:T68,$Q69&"|L|*")+1)) | U69: =IF($F69="","",13)
H70: =IF(G70=1,F70-I70-J70-K70,IF(G70=2,F70,0)) -> 0 | I70: =ROUND(IF(G70=1,F70*10/23,IF(G70=3,F70-J70-K70,IF(G70=4,F70,IF(G70=5,F70*10/11,IF(G70=7,F70*10/11,0))))),0) -> 0 | J70: =ROUND(IF(G70=1,F70/23,IF(G70=3,F70/12,IF(G70=5,F70-I70,IF(G70=8,F70,0)))),0) -> 0 | K70: =ROUND(IF(G70=1,F70/23,IF(G70=3,F70/12,IF(G70=6,F70,IF(G70=7,F70-I70,0)))),0) -> 0 | L70: =IF(G70=6,F70,0) -> 0 | Q70: =IF($F70="","",IFERROR(VLOOKUP($C70&"|"&$D70,科目表!$A$5:$B$200,2,FALSE),"※未登録")) | R70: =IF($F70="","",$I70+$J70+$K70) | S70: =IF(OR($F70="",$P70="支払なし",$H70=0,$Q70=""),"",$Q70&"|S|"&(COUNTIF(S$4:S69,$Q70&"|S|*")+1)) | T70: =IF(OR($F70="",$P70="支払なし",$R70=0,$Q70=""),"",$Q70&"|L|"&(COUNTIF(T$4:T69,$Q70&"|L|*")+1)) | U70: =IF($F70="","",13)
H71: =IF(G71=1,F71-I71-J71-K71,IF(G71=2,F71,0)) -> 0 | I71: =ROUND(IF(G71=1,F71*10/23,IF(G71=3,F71-J71-K71,IF(G71=4,F71,IF(G71=5,F71*10/11,IF(G71=7,F71*10/11,0))))),0) -> 0 | J71: =ROUND(IF(G71=1,F71/23,IF(G71=3,F71/12,IF(G71=5,F71-I71,IF(G71=8,F71,0)))),0) -> 0 | K71: =ROUND(IF(G71=1,F71/23,IF(G71=3,F71/12,IF(G71=6,F71,IF(G71=7,F71-I71,0)))),0) -> 0 | L71: =IF(G71=6,F71,0) -> 0 | Q71: =IF($F71="","",IFERROR(VLOOKUP($C71&"|"&$D71,科目表!$A$5:$B$200,2,FALSE),"※未登録")) | R71: =IF($F71="","",$I71+$J71+$K71) | S71: =IF(OR($F71="",$P71="支払なし",$H71=0,$Q71=""),"",$Q71&"|S|"&(COUNTIF(S$4:S70,$Q71&"|S|*")+1)) | T71: =IF(OR($F71="",$P71="支払なし",$R71=0,$Q71=""),"",$Q71&"|L|"&(COUNTIF(T$4:T70,$Q71&"|L|*")+1)) | U71: =IF($F71="","",13)
H72: =IF(G72=1,F72-I72-J72-K72,IF(G72=2,F72,0)) -> 0 | I72: =ROUND(IF(G72=1,F72*10/23,IF(G72=3,F72-J72-K72,IF(G72=4,F72,IF(G72=5,F72*10/11,IF(G72=7,F72*10/11,0))))),0) -> 0 | J72: =ROUND(IF(G72=1,F72/23,IF(G72=3,F72/12,IF(G72=5,F72-I72,IF(G72=8,F72,0)))),0) -> 0 | K72: =ROUND(IF(G72=1,F72/23,IF(G72=3,F72/12,IF(G72=6,F72,IF(G72=7,F72-I72,0)))),0) -> 0 | L72: =IF(G72=6,F72,0) -> 0 | Q72: =IF($F72="","",IFERROR(VLOOKUP($C72&"|"&$D72,科目表!$A$5:$B$200,2,FALSE),"※未登録")) | R72: =IF($F72="","",$I72+$J72+$K72) | S72: =IF(OR($F72="",$P72="支払なし",$H72=0,$Q72=""),"",$Q72&"|S|"&(COUNTIF(S$4:S71,$Q72&"|S|*")+1)) | T72: =IF(OR($F72="",$P72="支払なし",$R72=0,$Q72=""),"",$Q72&"|L|"&(COUNTIF(T$4:T71,$Q72&"|L|*")+1)) | U72: =IF($F72="","",13)
H73: =IF(G73=1,F73-I73-J73-K73,IF(G73=2,F73,0)) -> 0 | I73: =ROUND(IF(G73=1,F73*10/23,IF(G73=3,F73-J73-K73,IF(G73=4,F73,IF(G73=5,F73*10/11,IF(G73=7,F73*10/11,0))))),0) -> 0 | J73: =ROUND(IF(G73=1,F73/23,IF(G73=3,F73/12,IF(G73=5,F73-I73,IF(G73=8,F73,0)))),0) -> 0 | K73: =ROUND(IF(G73=1,F73/23,IF(G73=3,F73/12,IF(G73=6,F73,IF(G73=7,F73-I73,0)))),0) -> 0 | L73: =IF(G73=6,F73,0) -> 0 | Q73: =IF($F73="","",IFERROR(VLOOKUP($C73&"|"&$D73,科目表!$A$5:$B$200,2,FALSE),"※未登録")) | R73: =IF($F73="","",$I73+$J73+$K73) | S73: =IF(OR($F73="",$P73="支払なし",$H73=0,$Q73=""),"",$Q73&"|S|"&(COUNTIF(S$4:S72,$Q73&"|S|*")+1)) | T73: =IF(OR($F73="",$P73="支払なし",$R73=0,$Q73=""),"",$Q73&"|L|"&(COUNTIF(T$4:T72,$Q73&"|L|*")+1)) | U73: =IF($F73="","",13)
H74: =IF(G74=1,F74-I74-J74-K74,IF(G74=2,F74,0)) -> 0 | I74: =ROUND(IF(G74=1,F74*10/23,IF(G74=3,F74-J74-K74,IF(G74=4,F74,IF(G74=5,F74*10/11,IF(G74=7,F74*10/11,0))))),0) -> 0 | J74: =ROUND(IF(G74=1,F74/23,IF(G74=3,F74/12,IF(G74=5,F74-I74,IF(G74=8,F74,0)))),0) -> 0 | K74: =ROUND(IF(G74=1,F74/23,IF(G74=3,F74/12,IF(G74=6,F74,IF(G74=7,F74-I74,0)))),0) -> 0 | L74: =IF(G74=6,F74,0) -> 0 | Q74: =IF($F74="","",IFERROR(VLOOKUP($C74&"|"&$D74,科目表!$A$5:$B$200,2,FALSE),"※未登録")) | R74: =IF($F74="","",$I74+$J74+$K74) | S74: =IF(OR($F74="",$P74="支払なし",$H74=0,$Q74=""),"",$Q74&"|S|"&(COUNTIF(S$4:S73,$Q74&"|S|*")+1)) | T74: =IF(OR($F74="",$P74="支払なし",$R74=0,$Q74=""),"",$Q74&"|L|"&(COUNTIF(T$4:T73,$Q74&"|L|*")+1)) | U74: =IF($F74="","",13)
H75: =IF(G75=1,F75-I75-J75-K75,IF(G75=2,F75,0)) -> 0 | I75: =ROUND(IF(G75=1,F75*10/23,IF(G75=3,F75-J75-K75,IF(G75=4,F75,IF(G75=5,F75*10/11,IF(G75=7,F75*10/11,0))))),0) -> 0 | J75: =ROUND(IF(G75=1,F75/23,IF(G75=3,F75/12,IF(G75=5,F75-I75,IF(G75=8,F75,0)))),0) -> 0 | K75: =ROUND(IF(G75=1,F75/23,IF(G75=3,F75/12,IF(G75=6,F75,IF(G75=7,F75-I75,0)))),0) -> 0 | L75: =IF(G75=6,F75,0) -> 0 | Q75: =IF($F75="","",IFERROR(VLOOKUP($C75&"|"&$D75,科目表!$A$5:$B$200,2,FALSE),"※未登録")) | R75: =IF($F75="","",$I75+$J75+$K75) | S75: =IF(OR($F75="",$P75="支払なし",$H75=0,$Q75=""),"",$Q75&"|S|"&(COUNTIF(S$4:S74,$Q75&"|S|*")+1)) | T75: =IF(OR($F75="",$P75="支払なし",$R75=0,$Q75=""),"",$Q75&"|L|"&(COUNTIF(T$4:T74,$Q75&"|L|*")+1)) | U75: =IF($F75="","",13)
... H1835: =IF(G1835=1,F1835-I1835-J1835-K1835,IF(G1835=2,F1835,0)) -> 0 | I1835: =ROUND(IF(G1835=1,F1835*10/23,IF(G1835=3,F1835-J1835-K1835,IF(G1835=4,F1835,IF(G1835=5,F1835*10/11,IF(G1835=7,F1835*10/11,0))))),0) -> 0 | J1835: =ROUND(IF(G1835=1,F1835/23,IF(G1835=3,F1835/12,IF(G1835=5,F1835-I1835,IF(G1835=8,F1835,0)))),0) -> 0 | K1835: =ROUND(IF(G1835=1,F1835/23,IF(G1835=3,F1835/12,IF(G1835=6,F1835,IF(G1835=7,F1835-I1835,0)))),0) -> 0 | L1835: =IF(G1835=6,F1835,0) -> 0 | Q1835: =IF($F1835="","",IFERROR(VLOOKUP($C1835&"|"&$D1835,科目表!$A$5:$B$200,2,FALSE),"※未登録")) | R1835: =IF($F1835="","",$I1835+$J1835+$K1835) | S1835: =IF(OR($F1835="",$P1835="支払なし",$H1835=0,$Q1835=""),"",$Q1835&"|S|"&(COUNTIF(S$4:S1834,$Q1835&"|S|*")+1)) | T1835: =IF(OR($F1835="",$P1835="支払なし",$R1835=0,$Q1835=""),"",$Q1835&"|L|"&(COUNTIF(T$4:T1834,$Q1835&"|L|*")+1)) | U1835: =IF($F1835="","",13)
A1837: 4月分計 | C1837: 費用 | F1837: =SUMPRODUCT((MONTH($A$5:$A$1835)=4)*($F$5:$F$1835))-F1838 -> 4325752 | H1837: =SUMPRODUCT((MONTH($A$5:$A$1835)=4)*($H$5:$H$1835))-H1838 -> 2759677 | I1837: =SUMPRODUCT((MONTH($A$5:$A$1835)=4)*($I$5:$I$1835))-I1838 -> 1311193 | J1837: =SUMPRODUCT((MONTH($A$5:$A$1835)=4)*($J$5:$J$1835))-J1838 -> 131121 | K1837: =SUMPRODUCT((MONTH($A$5:$A$1835)=4)*($K$5:$K$1835))-K1838 -> 123761 | L1837: =SUMPRODUCT((MONTH($A$5:$A$1835)=4)*($L$5:$L$1835))-L1838 -> 0
A1838: 4月分計 | C1838: 仮払消費税 | F1838: =SUMPRODUCT((MONTH($A$5:$A$1835)=4)*(($C$5:$C$1835)=$C$1838)*($F$5:$F$1835)) -> 0 | H1838: =SUMPRODUCT((MONTH($A$5:$A$1835)=4)*(($C$5:$C$1835)=$C$1838)*($H$5:$H$1835)) -> 0 | I1838: =SUMPRODUCT((MONTH($A$5:$A$1835)=4)*(($C$5:$C$1835)=$C$1838)*($I$5:$I$1835)) -> 0 | J1838: =SUMPRODUCT((MONTH($A$5:$A$1835)=4)*(($C$5:$C$1835)=$C$1838)*($J$5:$J$1835)) -> 0 | K1838: =SUMPRODUCT((MONTH($A$5:$A$1835)=4)*(($C$5:$C$1835)=$C$1838)*($K$5:$K$1835)) -> 0 | L1838: =SUMPRODUCT((MONTH($A$5:$A$1835)=4)*(($C$5:$C$1835)=$C$1838)*($L$5:$L$1835)) -> 0
A1839: 4月分計 | C1839: 合計 | F1839: =SUM(F1837:F1838) -> 4325752 | H1839: =SUM(H1837:H1838) -> 2759677 | I1839: =SUM(I1837:I1838) -> 1311193 | J1839: =SUM(J1837:J1838) -> 131121 | K1839: =SUM(K1837:K1838) -> 123761 | L1839: =SUM(L1837:L1838) -> 0
A1841: 5月分計 | C1841: 費用 | F1841: =SUMPRODUCT((MONTH($A$5:$A$1835)=5)*($F$5:$F$1835))-F1842 -> 686447 | H1841: =SUMPRODUCT((MONTH($A$5:$A$1835)=5)*($H$5:$H$1835))-H1842 -> 686447 | I1841: =SUMPRODUCT((MONTH($A$5:$A$1835)=5)*($I$5:$I$1835))-I1842 -> 0 | J1841: =SUMPRODUCT((MONTH($A$5:$A$1835)=5)*($J$5:$J$1835))-J1842 -> 0 | K1841: =SUMPRODUCT((MONTH($A$5:$A$1835)=5)*($K$5:$K$1835))-K1842 -> 0 | L1841: =SUMPRODUCT((MONTH($A$5:$A$1835)=5)*($L$5:$L$1835))-L1842 -> 0
A1842: 5月分計 | C1842: 仮払消費税 | F1842: =SUMPRODUCT((MONTH($A$5:$A$1835)=5)*(($C$5:$C$1835)=$C$1842)*($F$5:$F$1835)) -> 0 | H1842: =SUMPRODUCT((MONTH($A$5:$A$1835)=5)*(($C$5:$C$1835)=$C$1842)*($H$5:$H$1835)) -> 0 | I1842: =SUMPRODUCT((MONTH($A$5:$A$1835)=5)*(($C$5:$C$1835)=$C$1842)*($I$5:$I$1835)) -> 0 | J1842: =SUMPRODUCT((MONTH($A$5:$A$1835)=5)*(($C$5:$C$1835)=$C$1842)*($J$5:$J$1835)) -> 0 | K1842: =SUMPRODUCT((MONTH($A$5:$A$1835)=5)*(($C$5:$C$1835)=$C$1842)*($K$5:$K$1835)) -> 0 | L1842: =SUMPRODUCT((MONTH($A$5:$A$1835)=5)*(($C$5:$C$1835)=$C$1842)*($L$5:$L$1835)) -> 0
A1843: 5月分計 | C1843: 合計 | F1843: =SUM(F1841:F1842) -> 686447 | H1843: =SUM(H1841:H1842) -> 686447 | I1843: =SUM(I1841:I1842) -> 0 | J1843: =SUM(J1841:J1842) -> 0 | K1843: =SUM(K1841:K1842) -> 0 | L1843: =SUM(L1841:L1842) -> 0
A1845: 6月分計 | C1845: 費用 | F1845: =SUMPRODUCT((MONTH($A$5:$A$1835)=6)*($F$5:$F$1835))-F1846 -> 0 | H1845: =SUMPRODUCT((MONTH($A$5:$A$1835)=6)*($H$5:$H$1835))-H1846 -> 0 | I1845: =SUMPRODUCT((MONTH($A$5:$A$1835)=6)*($I$5:$I$1835))-I1846 -> 0 | J1845: =SUMPRODUCT((MONTH($A$5:$A$1835)=6)*($J$5:$J$1835))-J1846 -> 0 | K1845: =SUMPRODUCT((MONTH($A$5:$A$1835)=6)*($K$5:$K$1835))-K1846 -> 0 | L1845: =SUMPRODUCT((MONTH($A$5:$A$1835)=6)*($L$5:$L$1835))-L1846 -> 0
A1846: 6月分計 | C1846: 仮払消費税 | F1846: =SUMPRODUCT((MONTH($A$5:$A$1835)=6)*(($C$5:$C$1835)=$C$1846)*($F$5:$F$1835)) -> 0 | H1846: =SUMPRODUCT((MONTH($A$5:$A$1835)=6)*(($C$5:$C$1835)=$C$1846)*($H$5:$H$1835)) -> 0 | I1846: =SUMPRODUCT((MONTH($A$5:$A$1835)=6)*(($C$5:$C$1835)=$C$1846)*($I$5:$I$1835)) -> 0 | J1846: =SUMPRODUCT((MONTH($A$5:$A$1835)=6)*(($C$5:$C$1835)=$C$1846)*($J$5:$J$1835)) -> 0 | K1846: =SUMPRODUCT((MONTH($A$5:$A$1835)=6)*(($C$5:$C$1835)=$C$1846)*($K$5:$K$1835)) -> 0 | L1846: =SUMPRODUCT((MONTH($A$5:$A$1835)=6)*(($C$5:$C$1835)=$C$1846)*($L$5:$L$1835)) -> 0
A1847: 6月分計 | C1847: 合計 | F1847: =SUM(F1845:F1846) -> 0 | H1847: =SUM(H1845:H1846) -> 0 | I1847: =SUM(I1845:I1846) -> 0 | J1847: =SUM(J1845:J1846) -> 0 | K1847: =SUM(K1845:K1846) -> 0 | L1847: =SUM(L1845:L1846) -> 0
A1849: 7月分計 | C1849: 費用 | F1849: =SUMPRODUCT((MONTH($A$5:$A$1835)=7)*($F$5:$F$1835))-F1850 -> 0 | H1849: =SUMPRODUCT((MONTH($A$5:$A$1835)=7)*($H$5:$H$1835))-H1850 -> 0 | I1849: =SUMPRODUCT((MONTH($A$5:$A$1835)=7)*($I$5:$I$1835))-I1850 -> 0 | J1849: =SUMPRODUCT((MONTH($A$5:$A$1835)=7)*($J$5:$J$1835))-J1850 -> 0 | K1849: =SUMPRODUCT((MONTH($A$5:$A$1835)=7)*($K$5:$K$1835))-K1850 -> 0 | L1849: =SUMPRODUCT((MONTH($A$5:$A$1835)=7)*($L$5:$L$1835))-L1850 -> 0
A1850: 7月分計 | C1850: 仮払消費税 | F1850: =SUMPRODUCT((MONTH($A$5:$A$1835)=7)*(($C$5:$C$1835)=$C$1850)*($F$5:$F$1835)) -> 0 | H1850: =SUMPRODUCT((MONTH($A$5:$A$1835)=7)*(($C$5:$C$1835)=$C$1850)*($H$5:$H$1835)) -> 0 | I1850: =SUMPRODUCT((MONTH($A$5:$A$1835)=7)*(($C$5:$C$1835)=$C$1850)*($I$5:$I$1835)) -> 0 | J1850: =SUMPRODUCT((MONTH($A$5:$A$1835)=7)*(($C$5:$C$1835)=$C$1850)*($J$5:$J$1835)) -> 0 | K1850: =SUMPRODUCT((MONTH($A$5:$A$1835)=7)*(($C$5:$C$1835)=$C$1850)*($K$5:$K$1835)) -> 0 | L1850: =SUMPRODUCT((MONTH($A$5:$A$1835)=7)*(($C$5:$C$1835)=$C$1850)*($L$5:$L$1835)) -> 0
A1851: 7月分計 | C1851: 合計 | F1851: =SUM(F1849:F1850) -> 0 | H1851: =SUM(H1849:H1850) -> 0 | I1851: =SUM(I1849:I1850) -> 0 | J1851: =SUM(J1849:J1850) -> 0 | K1851: =SUM(K1849:K1850) -> 0 | L1851: =SUM(L1849:L1850) -> 0
A1853: 8月分計 | C1853: 費用 | F1853: =SUMPRODUCT((MONTH($A$5:$A$1835)=8)*($F$5:$F$1835))-F1854 -> 0 | H1853: =SUMPRODUCT((MONTH($A$5:$A$1835)=8)*($H$5:$H$1835))-H1854 -> 0 | I1853: =SUMPRODUCT((MONTH($A$5:$A$1835)=8)*($I$5:$I$1835))-I1854 -> 0 | J1853: =SUMPRODUCT((MONTH($A$5:$A$1835)=8)*($J$5:$J$1835))-J1854 -> 0 | K1853: =SUMPRODUCT((MONTH($A$5:$A$1835)=8)*($K$5:$K$1835))-K1854 -> 0 | L1853: =SUMPRODUCT((MONTH($A$5:$A$1835)=8)*($L$5:$L$1835))-L1854 -> 0
A1854: 8月分計 | C1854: 仮払消費税 | F1854: =SUMPRODUCT((MONTH($A$5:$A$1835)=8)*(($C$5:$C$1835)=$C$1854)*($F$5:$F$1835)) -> 0 | H1854: =SUMPRODUCT((MONTH($A$5:$A$1835)=8)*(($C$5:$C$1835)=$C$1854)*($H$5:$H$1835)) -> 0 | I1854: =SUMPRODUCT((MONTH($A$5:$A$1835)=8)*(($C$5:$C$1835)=$C$1854)*($I$5:$I$1835)) -> 0 | J1854: =SUMPRODUCT((MONTH($A$5:$A$1835)=8)*(($C$5:$C$1835)=$C$1854)*($J$5:$J$1835)) -> 0 | K1854: =SUMPRODUCT((MONTH($A$5:$A$1835)=8)*(($C$5:$C$1835)=$C$1854)*($K$5:$K$1835)) -> 0 | L1854: =SUMPRODUCT((MONTH($A$5:$A$1835)=8)*(($C$5:$C$1835)=$C$1854)*($L$5:$L$1835)) -> 0
A1855: 8月分計 | C1855: 合計 | F1855: =SUM(F1853:F1854) -> 0 | H1855: =SUM(H1853:H1854) -> 0 | I1855: =SUM(I1853:I1854) -> 0 | J1855: =SUM(J1853:J1854) -> 0 | K1855: =SUM(K1853:K1854) -> 0 | L1855: =SUM(L1853:L1854) -> 0
A1857: 9月分計 | C1857: 費用 | F1857: =SUMPRODUCT((MONTH($A$5:$A$1835)=9)*($F$5:$F$1835))-F1858 -> 0 | H1857: =SUMPRODUCT((MONTH($A$5:$A$1835)=9)*($H$5:$H$1835))-H1858 -> 0 | I1857: =SUMPRODUCT((MONTH($A$5:$A$1835)=9)*($I$5:$I$1835))-I1858 -> 0 | J1857: =SUMPRODUCT((MONTH($A$5:$A$1835)=9)*($J$5:$J$1835))-J1858 -> 0 | K1857: =SUMPRODUCT((MONTH($A$5:$A$1835)=9)*($K$5:$K$1835))-K1858 -> 0 | L1857: =SUMPRODUCT((MONTH($A$5:$A$1835)=9)*($L$5:$L$1835))-L1858 -> 0
A1858: 9月分計 | C1858: 仮払消費税 | F1858: =SUMPRODUCT((MONTH($A$5:$A$1835)=9)*(($C$5:$C$1835)=$C$1858)*($F$5:$F$1835)) -> 0 | H1858: =SUMPRODUCT((MONTH($A$5:$A$1835)=8)*(($C$5:$C$1835)=$C$1858)*($H$5:$H$1835)) -> 0 | I1858: =SUMPRODUCT((MONTH($A$5:$A$1835)=9)*(($C$5:$C$1835)=$C$1858)*($I$5:$I$1835)) -> 0 | J1858: =SUMPRODUCT((MONTH($A$5:$A$1835)=9)*(($C$5:$C$1835)=$C$1858)*($J$5:$J$1835)) -> 0 | K1858: =SUMPRODUCT((MONTH($A$5:$A$1835)=9)*(($C$5:$C$1835)=$C$1858)*($K$5:$K$1835)) -> 0 | L1858: =SUMPRODUCT((MONTH($A$5:$A$1835)=9)*(($C$5:$C$1835)=$C$1858)*($L$5:$L$1835)) -> 0
A1859: 9月分計 | C1859: 合計 | F1859: =SUM(F1857:F1858) -> 0 | H1859: =SUM(H1857:H1858) -> 0 | I1859: =SUM(I1857:I1858) -> 0 | J1859: =SUM(J1857:J1858) -> 0 | K1859: =SUM(K1857:K1858) -> 0 | L1859: =SUM(L1857:L1858) -> 0
A1861: 10月分計 | C1861: 費用 | F1861: =SUMPRODUCT((MONTH($A$5:$A$1835)=10)*($F$5:$F$1835))-F1862 -> 0 | H1861: =SUMPRODUCT((MONTH($A$5:$A$1835)=10)*($H$5:$H$1835))-H1862 -> 0 | I1861: =SUMPRODUCT((MONTH($A$5:$A$1835)=10)*($I$5:$I$1835))-I1862 -> 0 | J1861: =SUMPRODUCT((MONTH($A$5:$A$1835)=10)*($J$5:$J$1835))-J1862 -> 0 | K1861: =SUMPRODUCT((MONTH($A$5:$A$1835)=10)*($K$5:$K$1835))-K1862 -> 0 | L1861: =SUMPRODUCT((MONTH($A$5:$A$1835)=10)*($L$5:$L$1835))-L1862 -> 0
A1862: 10月分計 | C1862: 仮払消費税 | F1862: =SUMPRODUCT((MONTH($A$5:$A$1835)=10)*(($C$5:$C$1835)=$C$1862)*($F$5:$F$1835)) -> 0 | H1862: =SUMPRODUCT((MONTH($A$5:$A$1835)=10)*(($C$5:$C$1835)=$C$1862)*($H$5:$H$1835)) -> 0 | I1862: =SUMPRODUCT((MONTH($A$5:$A$1835)=10)*(($C$5:$C$1835)=$C$1862)*($I$5:$I$1835)) -> 0 | J1862: =SUMPRODUCT((MONTH($A$5:$A$1835)=10)*(($C$5:$C$1835)=$C$1862)*($J$5:$J$1835)) -> 0 | K1862: =SUMPRODUCT((MONTH($A$5:$A$1835)=10)*(($C$5:$C$1835)=$C$1862)*($K$5:$K$1835)) -> 0 | L1862: =SUMPRODUCT((MONTH($A$5:$A$1835)=10)*(($C$5:$C$1835)=$C$1862)*($L$5:$L$1835)) -> 0
A1863: 10月分計 | C1863: 合計 | F1863: =SUM(F1861:F1862) -> 0 | H1863: =SUM(H1861:H1862) -> 0 | I1863: =SUM(I1861:I1862) -> 0 | J1863: =SUM(J1861:J1862) -> 0 | K1863: =SUM(K1861:K1862) -> 0 | L1863: =SUM(L1861:L1862) -> 0
A1865: 11月分計 | C1865: 費用 | F1865: =SUMPRODUCT((MONTH($A$5:$A$1835)=11)*($F$5:$F$1835))-F1866 -> 0 | H1865: =SUMPRODUCT((MONTH($A$5:$A$1835)=11)*($H$5:$H$1835))-H1866 -> 0 | I1865: =SUMPRODUCT((MONTH($A$5:$A$1835)=11)*($I$5:$I$1835))-I1866 -> 0 | J1865: =SUMPRODUCT((MONTH($A$5:$A$1835)=11)*($J$5:$J$1835))-J1866 -> 0 | K1865: =SUMPRODUCT((MONTH($A$5:$A$1835)=11)*($K$5:$K$1835))-K1866 -> 0 | L1865: =SUMPRODUCT((MONTH($A$5:$A$1835)=11)*($L$5:$L$1835))-L1866 -> 0
A1866: 11月分計 | C1866: 仮払消費税 | F1866: =SUMPRODUCT((MONTH($A$5:$A$1835)=11)*(($C$5:$C$1835)=$C$1866)*($F$5:$F$1835)) -> 0 | H1866: =SUMPRODUCT((MONTH($A$5:$A$1835)=11)*(($C$5:$C$1835)=$C$1866)*($H$5:$H$1835)) -> 0 | I1866: =SUMPRODUCT((MONTH($A$5:$A$1835)=11)*(($C$5:$C$1835)=$C$1866)*($I$5:$I$1835)) -> 0 | J1866: =SUMPRODUCT((MONTH($A$5:$A$1835)=11)*(($C$5:$C$1835)=$C$1866)*($J$5:$J$1835)) -> 0 | K1866: =SUMPRODUCT((MONTH($A$5:$A$1835)=11)*(($C$5:$C$1835)=$C$1866)*($K$5:$K$1835)) -> 0 | L1866: =SUMPRODUCT((MONTH($A$5:$A$1835)=11)*(($C$5:$C$1835)=$C$1866)*($L$5:$L$1835)) -> 0
A1867: 11月分計 | C1867: 合計 | F1867: =SUM(F1865:F1866) -> 0 | H1867: =SUM(H1865:H1866) -> 0 | I1867: =SUM(I1865:I1866) -> 0 | J1867: =SUM(J1865:J1866) -> 0 | K1867: =SUM(K1865:K1866) -> 0 | L1867: =SUM(L1865:L1866) -> 0
...

Sheet 予算差引簿（短）
B3: ○事務費 通信運搬費 | D3: 業務（短） | E3: =IF(COUNTIF(月例!$S$5:$S$788,"通信運搬費|S|*")>106,"行不足","") | G3: ○委託費 | I3: 業務（短） | J3: =IF(COUNTIF(月例!$S$5:$S$788,"委託費|S|*")>103,"行不足","") | L3: ○賃借料 | N3: 業務（短） | O3: =IF(COUNTIF(月例!$S$5:$S$788,"賃借料|S|*")>84,"行不足","") | Q3: ○事務費 事務用消耗品費 | S3: 業務（短） | T3: =IF(COUNTIF(月例!$S$5:$S$788,"事務用消耗品費|S|*")>73,"行不足","")
A4: 支出日 | B4: 摘要 | C4: 支出 | D4: 残額 | E4: 状態 | F4: 支出日 | G4: 摘要 | H4: 支出 | I4: 残額 | J4: 状態 | K4: 支出日 | L4: 摘要 | M4: 支出 | N4: 残額 | O4: 状態 | P4: 支出日 | Q4: 摘要 | R4: 支出 | S4: 残額 | T4: 状態
B5: 予算現額 | D5: ='R7業務 (短)'!$S$15 -> 983000 | G5: 予算現額 | I5: ='R7業務 (短)'!$S$20 -> 10478000 | L5: 予算現額 | N5: ='R7業務 (短)'!$S$23 -> 8441000 | Q5: 予算現額 | S5: ='R7業務 (短)'!$S$12 -> 1537000
A6: =IFERROR(INDEX(月例!$A$5:$A$788,MATCH("通信運搬費|S|1",月例!$S$5:$S$788,0)),"") -> 45756 | B6: =IFERROR(INDEX(月例!$E$5:$E$788,MATCH("通信運搬費|S|1",月例!$S$5:$S$788,0)),"") -> 切手 | C6: =IFERROR(INDEX(月例!$H$5:$H$788,MATCH("通信運搬費|S|1",月例!$S$5:$S$788,0)),"") -> 178000 | D6: =IF(C6="","",D5-C6) -> 805000 | E6: =IFERROR(INDEX(月例!$P$5:$P$788,MATCH("通信運搬費|S|1",月例!$S$5:$S$788,0)),"") -> 昨年実績 | F6: =IFERROR(INDEX(月例!$A$5:$A$788,MATCH("委託費|S|1",月例!$S$5:$S$788,0)),"") -> 46132 | G6: =IFERROR(INDEX(月例!$E$5:$E$788,MATCH("委託費|S|1",月例!$S$5:$S$788,0)),"") -> レセプト電子データ提供料（1月診療分） | H6: =IFERROR(INDEX(月例!$H$5:$H$788,MATCH("委託費|S|1",月例!$S$5:$S$788,0)),"") -> 60235 | I6: =IF(H6="","",I5-H6) -> 10417765 | J6: =IFERROR(INDEX(月例!$P$5:$P$788,MATCH("委託費|S|1",月例!$S$5:$S$788,0)),"") -> 確認済 | K6: =IFERROR(INDEX(月例!$A$5:$A$788,MATCH("賃借料|S|1",月例!$S$5:$S$788,0)),"") -> 46171 | L6: =IFERROR(INDEX(月例!$E$5:$E$788,MATCH("賃借料|S|1",月例!$S$5:$S$788,0)),"") -> パソコン（業務経理用）４月分 | M6: =IFERROR(INDEX(月例!$H$5:$H$788,MATCH("賃借料|S|1",月例!$S$5:$S$788,0)),"") -> 5060 | N6: =IF(M6="","",N5-M6) -> 8435940 | O6: =IFERROR(INDEX(月例!$P$5:$P$788,MATCH("賃借料|S|1",月例!$S$5:$S$788,0)),"") -> 確認済 | P6: =IFERROR(INDEX(月例!$A$5:$A$788,MATCH("事務用消耗品費|S|1",月例!$S$5:$S$788,0)),"") -> 46140 | Q6: =IFERROR(INDEX(月例!$E$5:$E$788,MATCH("事務用消耗品費|S|1",月例!$S$5:$S$788,0)),"") -> 令和８年度基幹ウイルス対策ソフト（ミツイワ株式会社）短期 | R6: =IFERROR(INDEX(月例!$H$5:$H$788,MATCH("事務用消耗品費|S|1",月例!$S$5:$S$788,0)),"") -> 20482 | S6: =IF(R6="","",S5-R6) -> 1516518 | T6: =IFERROR(INDEX(月例!$P$5:$P$788,MATCH("事務用消耗品費|S|1",月例!$S$5:$S$788,0)),"") -> 確認済
A7: =IFERROR(INDEX(月例!$A$5:$A$788,MATCH("通信運搬費|S|2",月例!$S$5:$S$788,0)),"") -> 44336 | B7: =IFERROR(INDEX(月例!$E$5:$E$788,MATCH("通信運搬費|S|2",月例!$S$5:$S$788,0)),"") -> 電話料金（４月使用・５月請求分） | C7: =IFERROR(INDEX(月例!$H$5:$H$788,MATCH("通信運搬費|S|2",月例!$S$5:$S$788,0)),"") -> 5407 | D7: =IF(C7="","",D6-C7) -> 799593 | E7: =IFERROR(INDEX(月例!$P$5:$P$788,MATCH("通信運搬費|S|2",月例!$S$5:$S$788,0)),"") -> 昨年実績 | F7: =IFERROR(INDEX(月例!$A$5:$A$788,MATCH("委託費|S|2",月例!$S$5:$S$788,0)),"") -> 45044 | G7: =IFERROR(INDEX(月例!$E$5:$E$788,MATCH("委託費|S|2",月例!$S$5:$S$788,0)),"") -> 個人番号管理システムシンクライアント（４～１０月） | H7: =IFERROR(INDEX(月例!$H$5:$H$788,MATCH("委託費|S|2",月例!$S$5:$S$788,0)),"") -> 24486 | I7: =IF(H7="","",I6-H7) -> 10393279 | J7: =IFERROR(INDEX(月例!$P$5:$P$788,MATCH("委託費|S|2",月例!$S$5:$S$788,0)),"") -> 昨年実績 | K7: =IFERROR(INDEX(月例!$A$5:$A$788,MATCH("賃借料|S|2",月例!$S$5:$S$788,0)),"") -> 46162 | L7: =IFERROR(INDEX(月例!$E$5:$E$788,MATCH("賃借料|S|2",月例!$S$5:$S$788,0)),"") -> 統合管理端末リース料（４月分） | M7: =IFERROR(INDEX(月例!$H$5:$H$788,MATCH("賃借料|S|2",月例!$S$5:$S$788,0)),"") -> 12738 | N7: =IF(M7="","",N6-M7) -> 8423202 | O7: =IFERROR(INDEX(月例!$P$5:$P$788,MATCH("賃借料|S|2",月例!$S$5:$S$788,0)),"") -> 確認済 | P7: =IFERROR(INDEX(月例!$A$5:$A$788,MATCH("事務用消耗品費|S|2",月例!$S$5:$S$788,0)),"") -> 44316 | Q7: =IFERROR(INDEX(月例!$E$5:$E$788,MATCH("事務用消耗品費|S|2",月例!$S$5:$S$788,0)),"") -> CD／DVDファイルＡ４１２ＪーＣ 他 | R7: =IFERROR(INDEX(月例!$H$5:$H$788,MATCH("事務用消耗品費|S|2",月例!$S$5:$S$788,0)),"") -> 24407 | S7: =IF(R7="","",S6-R7) -> 1492111 | T7: =IFERROR(INDEX(月例!$P$5:$P$788,MATCH("事務用消耗品費|S|2",月例!$S$5:$S$788,0)),"") -> 昨年実績
A8: =IFERROR(INDEX(月例!$A$5:$A$788,MATCH("通信運搬費|S|3",月例!$S$5:$S$788,0)),"") -> 45077 | B8: =IFERROR(INDEX(月例!$E$5:$E$788,MATCH("通信運搬費|S|3",月例!$S$5:$S$788,0)),"") -> 柔整申請書送付（４月分） | C8: =IFERROR(INDEX(月例!$H$5:$H$788,MATCH("通信運搬費|S|3",月例!$S$5:$S$788,0)),"") -> 1489 | D8: =IF(C8="","",D7-C8) -> 798104 | E8: =IFERROR(INDEX(月例!$P$5:$P$788,MATCH("通信運搬費|S|3",月例!$S$5:$S$788,0)),"") -> 昨年実績 | F8: =IFERROR(INDEX(月例!$A$5:$A$788,MATCH("委託費|S|3",月例!$S$5:$S$788,0)),"") -> 46162 | G8: =IFERROR(INDEX(月例!$E$5:$E$788,MATCH("委託費|S|3",月例!$S$5:$S$788,0)),"") -> 社会保障等制度 中間サーバー等運営負担金 | H8: =IFERROR(INDEX(月例!$H$5:$H$788,MATCH("委託費|S|3",月例!$S$5:$S$788,0)),"") -> 1798068 | I8: =IF(H8="","",I7-H8) -> 8595211 | J8: =IFERROR(INDEX(月例!$P$5:$P$788,MATCH("委託費|S|3",月例!$S$5:$S$788,0)),"") -> 確認済 | K8: =IFERROR(INDEX(月例!$A$5:$A$788,MATCH("賃借料|S|3",月例!$S$5:$S$788,0)),"") -> 46171 | L8: =IFERROR(INDEX(月例!$E$5:$E$788,MATCH("賃借料|S|3",月例!$S$5:$S$788,0)),"") -> 基幹システム用機器賃借料 4月分（短期） | M8: =IFERROR(INDEX(月例!$H$5:$H$788,MATCH("賃借料|S|3",月例!$S$5:$S$788,0)),"") -> 672934 | N8: =IF(M8="","",N7-M8) -> 7750268 | O8: =IFERROR(INDEX(月例!$P$5:$P$788,MATCH("賃借料|S|3",月例!$S$5:$S$788,0)),"") -> 確認済 | P8: =IFERROR(INDEX(月例!$A$5:$A$788,MATCH("事務用消耗品費|S|3",月例!$S$5:$S$788,0)),"") -> 46171 | Q8: =IFERROR(INDEX(月例!$E$5:$E$788,MATCH("事務用消耗品費|S|3",月例!$S$5:$S$788,0)),"") -> ラベル用紙 LBP-F7656-100N ２冊 他 | R8: =IFERROR(INDEX(月例!$H$5:$H$788,MATCH("事務用消耗品費|S|3",月例!$S$5:$S$788,0)),"") -> 43890 | S8: =IF(R8="","",S7-R8) -> 1448221 | T8: =IFERROR(INDEX(月例!$P$5:$P$788,MATCH("事務用消耗品費|S|3",月例!$S$5:$S$788,0)),"") -> 確認済
A9: =IFERROR(INDEX(月例!$A$5:$A$788,MATCH("通信運搬費|S|4",月例!$S$5:$S$788,0)),"") -> 43980 | B9: =IFERROR(INDEX(月例!$E$5:$E$788,MATCH("通信運搬費|S|4",月例!$S$5:$S$788,0)),"") -> メール便（４月分） | C9: =IFERROR(INDEX(月例!$H$5:$H$788,MATCH("通信運搬費|S|4",月例!$S$5:$S$788,0)),"") -> 6636 | D9: =IF(C9="","",D8-C9) -> 791468 | E9: =IFERROR(INDEX(月例!$P$5:$P$788,MATCH("通信運搬費|S|4",月例!$S$5:$S$788,0)),"") -> 昨年実績 | F9: =IFERROR(INDEX(月例!$A$5:$A$788,MATCH("委託費|S|4",月例!$S$5:$S$788,0)),"") -> 46162 | G9: =IFERROR(INDEX(月例!$E$5:$E$788,MATCH("委託費|S|4",月例!$S$5:$S$788,0)),"") -> レセプト電子データ提供料（２月診療分） | H9: =IFERROR(INDEX(月例!$H$5:$H$788,MATCH("委託費|S|4",月例!$S$5:$S$788,0)),"") -> 61859 | I9: =IF(H9="","",I8-H9) -> 8533352 | J9: =IFERROR(INDEX(月例!$P$5:$P$788,MATCH("委託費|S|4",月例!$S$5:$S$788,0)),"") -> 確認済 | K9: =IFERROR(INDEX(月例!$A$5:$A$788,MATCH("賃借料|S|4",月例!$S$5:$S$788,0)),"") -> 46202 | L9: =IFERROR(INDEX(月例!$E$5:$E$788,MATCH("賃借料|S|4",月例!$S$5:$S$788,0)),"") -> パソコン（業務経理用）５月分 | M9: =IFERROR(INDEX(月例!$H$5:$H$788,MATCH("賃借料|S|4",月例!$S$5:$S$788,0)),"") -> 5060 | N9: =IF(M9="","",N8-M9) -> 7745208 | O9: =IFERROR(INDEX(月例!$P$5:$P$788,MATCH("賃借料|S|4",月例!$S$5:$S$788,0)),"") -> 確認済 | P9: =IFERROR(INDEX(月例!$A$5:$A$788,MATCH("事務用消耗品費|S|4",月例!$S$5:$S$788,0)),"") -> 46171 | Q9: =IFERROR(INDEX(月例!$E$5:$E$788,MATCH("事務用消耗品費|S|4",月例!$S$5:$S$788,0)),"") -> ダイヤルロック UNK-02 7個 他 | R9: =IFERROR(INDEX(月例!$H$5:$H$788,MATCH("事務用消耗品費|S|4",月例!$S$5:$S$788,0)),"") -> 14518 | S9: =IF(R9="","",S8-R9) -> 1433703 | T9: =IFERROR(INDEX(月例!$P$5:$P$788,MATCH("事務用消耗品費|S|4",月例!$S$5:$S$788,0)),"") -> 確認済
A10: =IFERROR(INDEX(月例!$A$5:$A$788,MATCH("通信運搬費|S|5",月例!$S$5:$S$788,0)),"") -> 45077 | B10: =IFERROR(INDEX(月例!$E$5:$E$788,MATCH("通信運搬費|S|5",月例!$S$5:$S$788,0)),"") -> メール便（任継者宛厚生だより４月分） | C10: =IFERROR(INDEX(月例!$H$5:$H$788,MATCH("通信運搬費|S|5",月例!$S$5:$S$788,0)),"") -> 17220 | D10: =IF(C10="","",D9-C10) -> 774248 | E10: =IFERROR(INDEX(月例!$P$5:$P$788,MATCH("通信運搬費|S|5",月例!$S$5:$S$788,0)),"") -> 昨年実績 | F10: =IFERROR(INDEX(月例!$A$5:$A$788,MATCH("委託費|S|5",月例!$S$5:$S$788,0)),"") -> 45065 | G10: =IFERROR(INDEX(月例!$E$5:$E$788,MATCH("委託費|S|5",月例!$S$5:$S$788,0)),"") -> 社会保障等制度 中間サーバー等運営負担金 | H10: =IFERROR(INDEX(月例!$H$5:$H$788,MATCH("委託費|S|5",月例!$S$5:$S$788,0)),"") -> 661740 | I10: =IF(H10="","",I9-H10) -> 7871612 | J10: =IFERROR(INDEX(月例!$P$5:$P$788,MATCH("委託費|S|5",月例!$S$5:$S$788,0)),"") -> 昨年実績 | K10: =IFERROR(INDEX(月例!$A$5:$A$788,MATCH("賃借料|S|5",月例!$S$5:$S$788,0)),"") -> 44392 | L10: =IFERROR(INDEX(月例!$E$5:$E$788,MATCH("賃借料|S|5",月例!$S$5:$S$788,0)),"") -> ﾊﾟｿｺﾝｳｨﾙｽ対策ｿﾌﾄ(業務用)ｻﾝﾈｯﾄ（5月分） | M10: =IFERROR(INDEX(月例!$H$5:$H$788,MATCH("賃借料|S|5",月例!$S$5:$S$788,0)),"") -> 2090 | N10: =IF(M10="","",N9-M10) -> 7743118 | O10: =IFERROR(INDEX(月例!$P$5:$P$788,MATCH("賃借料|S|5",月例!$S$5:$S$788,0)),"") -> 昨年実績 | P10: =IFERROR(INDEX(月例!$A$5:$A$788,MATCH("事務用消耗品費|S|5",月例!$S$5:$S$788,0)),"") -> 45807 | Q10: =IFERROR(INDEX(月例!$E$5:$E$788,MATCH("事務用消耗品費|S|5",月例!$S$5:$S$788,0)),"") -> ポストイット ５００１SS-K 2個 他 | R10: =IFERROR(INDEX(月例!$H$5:$H$788,MATCH("事務用消耗品費|S|5",月例!$S$5:$S$788,0)),"") -> 19730 | S10: =IF(R10="","",S9-R10) -> 1413973 | T10: =IFERROR(INDEX(月例!$P$5:$P$788,MATCH("事務用消耗品費|S|5",月例!$S$5:$S$788,0)),"") -> 昨年実績
A11: =IFERROR(INDEX(月例!$A$5:$A$788,MATCH("通信運搬費|S|6",月例!$S$5:$S$788,0)),"") -> 45810 | B11: =IFERROR(INDEX(月例!$E$5:$E$788,MATCH("通信運搬費|S|6",月例!$S$5:$S$788,0)),"") -> フレッツ光ネクスト利用料等（４月利用・５月請求分） | C11: =IFERROR(INDEX(月例!$H$5:$H$788,MATCH("通信運搬費|S|6",月例!$S$5:$S$788,0)),"") -> 5126 | D11: =IF(C11="","",D10-C11) -> 769122 | E11: =IFERROR(INDEX(月例!$P$5:$P$788,MATCH("通信運搬費|S|6",月例!$S$5:$S$788,0)),"") -> 昨年実績 | F11: =IFERROR(INDEX(月例!$A$5:$A$788,MATCH("委託費|S|6",月例!$S$5:$S$788,0)),"") -> 44347 | G11: =IFERROR(INDEX(月例!$E$5:$E$788,MATCH("委託費|S|6",月例!$S$5:$S$788,0)),"") -> 短期給付個人番号管理システム端末保守サービス（４月分） | H11: =IFERROR(INDEX(月例!$H$5:$H$788,MATCH("委託費|S|6",月例!$S$5:$S$788,0)),"") -> 385 | I11: =IF(H11="","",I10-H11) -> 7871227 | J11: =IFERROR(INDEX(月例!$P$5:$P$788,MATCH("委託費|S|6",月例!$S$5:$S$788,0)),"") -> 昨年実績 | K11: =IFERROR(INDEX(月例!$A$5:$A$788,MATCH("賃借料|S|6",月例!$S$5:$S$788,0)),"") -> 46202 | L11: =IFERROR(INDEX(月例!$E$5:$E$788,MATCH("賃借料|S|6",月例!$S$5:$S$788,0)),"") -> 基幹システム用機器賃借料 5月分（短期） | M11: =IFERROR(INDEX(月例!$H$5:$H$788,MATCH("賃借料|S|6",月例!$S$5:$S$788,0)),"") -> 672934 | N11: =IF(M11="","",N10-M11) -> 7070184 | O11: =IFERROR(INDEX(月例!$P$5:$P$788,MATCH("賃借料|S|6",月例!$S$5:$S$788,0)),"") -> 確認済 | P11: =IFERROR(INDEX(月例!$A$5:$A$788,MATCH("事務用消耗品費|S|6",月例!$S$5:$S$788,0)),"") -> 45412 | Q11: =IFERROR(INDEX(月例!$E$5:$E$788,MATCH("事務用消耗品費|S|6",月例!$S$5:$S$788,0)),"") -> 令和６年度基幹ウイルス対策ソフト（ミツイワ株式会社） | R11: =IFERROR(INDEX(月例!$H$5:$H$788,MATCH("事務用消耗品費|S|6",月例!$S$5:$S$788,0)),"") -> 21450 | S11: =IF(R11="","",S10-R11) -> 1392523 | T11: =IFERROR(INDEX(月例!$P$5:$P$788,MATCH("事務用消耗品費|S|6",月例!$S$5:$S$788,0)),"") -> 昨年実績
A12: =IFERROR(INDEX(月例!$A$5:$A$788,MATCH("通信運搬費|S|7",月例!$S$5:$S$788,0)),"") -> 46174 | B12: =IFERROR(INDEX(月例!$E$5:$E$788,MATCH("通信運搬費|S|7",月例!$S$5:$S$788,0)),"") -> インターネット通信料金（３月、４月使用・５月請求分） | C12: =IFERROR(INDEX(月例!$H$5:$H$788,MATCH("通信運搬費|S|7",月例!$S$5:$S$788,0)),"") -> 3663 | D12: =IF(C12="","",D11-C12) -> 765459 | E12: =IFERROR(INDEX(月例!$P$5:$P$788,MATCH("通信運搬費|S|7",月例!$S$5:$S$788,0)),"") -> 確認済 | F12: =IFERROR(INDEX(月例!$A$5:$A$788,MATCH("委託費|S|7",月例!$S$5:$S$788,0)),"") -> 46162 | G12: =IFERROR(INDEX(月例!$E$5:$E$788,MATCH("委託費|S|7",月例!$S$5:$S$788,0)),"") -> 統合管理端末保守料（４月～３月分） | H12: =IFERROR(INDEX(月例!$H$5:$H$788,MATCH("委託費|S|7",月例!$S$5:$S$788,0)),"") -> 149050 | I12: =IF(H12="","",I11-H12) -> 7722177 | J12: =IFERROR(INDEX(月例!$P$5:$P$788,MATCH("委託費|S|7",月例!$S$5:$S$788,0)),"") -> 確認済 | K12: =IFERROR(INDEX(月例!$A$5:$A$788,MATCH("賃借料|S|7",月例!$S$5:$S$788,0)),"") -> 46203 | L12: =IFERROR(INDEX(月例!$E$5:$E$788,MATCH("賃借料|S|7",月例!$S$5:$S$788,0)),"") -> 統合管理端末リース料（５月分） | M12: =IFERROR(INDEX(月例!$H$5:$H$788,MATCH("賃借料|S|7",月例!$S$5:$S$788,0)),"") -> 12738 | N12: =IF(M12="","",N11-M12) -> 7057446 | O12: =IFERROR(INDEX(月例!$P$5:$P$788,MATCH("賃借料|S|7",月例!$S$5:$S$788,0)),"") -> 確認済 | P12: =IFERROR(INDEX(月例!$A$5:$A$788,MATCH("事務用消耗品費|S|7",月例!$S$5:$S$788,0)),"") -> 45443 | Q12: =IFERROR(INDEX(月例!$E$5:$E$788,MATCH("事務用消耗品費|S|7",月例!$S$5:$S$788,0)),"") -> 保存ボックス 4370 50個 | R12: =IFERROR(INDEX(月例!$H$5:$H$788,MATCH("事務用消耗品費|S|7",月例!$S$5:$S$788,0)),"") -> 29650 | S12: =IF(R12="","",S11-R12) -> 1362873 | T12: =IFERROR(INDEX(月例!$P$5:$P$788,MATCH("事務用消耗品費|S|7",月例!$S$5:$S$788,0)),"") -> 昨年実績
A13: =IFERROR(INDEX(月例!$A$5:$A$788,MATCH("通信運搬費|S|8",月例!$S$5:$S$788,0)),"") -> 46171 | B13: =IFERROR(INDEX(月例!$E$5:$E$788,MATCH("通信運搬費|S|8",月例!$S$5:$S$788,0)),"") -> 料金後納利用料（4月分） | C13: =IFERROR(INDEX(月例!$H$5:$H$788,MATCH("通信運搬費|S|8",月例!$S$5:$S$788,0)),"") -> 196030 | D13: =IF(C13="","",D12-C13) -> 569429 | E13: =IFERROR(INDEX(月例!$P$5:$P$788,MATCH("通信運搬費|S|8",月例!$S$5:$S$788,0)),"") -> 確認済 | F13: =IFERROR(INDEX(月例!$A$5:$A$788,MATCH("委託費|S|8",月例!$S$5:$S$788,0)),"") -> 46171 | G13: =IFERROR(INDEX(月例!$E$5:$E$788,MATCH("委託費|S|8",月例!$S$5:$S$788,0)),"") -> 柔整等療養費支給申請書の入力（４月分） | H13: =IFERROR(INDEX(月例!$H$5:$H$788,MATCH("委託費|S|8",月例!$S$5:$S$788,0)),"") -> 137918 | I13: =IF(H13="","",I12-H13) -> 7584259 | J13: =IFERROR(INDEX(月例!$P$5:$P$788,MATCH("委託費|S|8",月例!$S$5:$S$788,0)),"") -> 確認済 | K13: =IFERROR(INDEX(月例!$A$5:$A$788,MATCH("賃借料|S|8",月例!$S$5:$S$788,0)),"") -> 43644 | L13: =IFERROR(INDEX(月例!$E$5:$E$788,MATCH("賃借料|S|8",月例!$S$5:$S$788,0)),"") -> 基幹システム（短期）用機器リース料５月分 | M13: =IFERROR(INDEX(月例!$H$5:$H$788,MATCH("賃借料|S|8",月例!$S$5:$S$788,0)),"") -> 193676 | N13: =IF(M13="","",N12-M13) -> 6863770 | O13: =IFERROR(INDEX(月例!$P$5:$P$788,MATCH("賃借料|S|8",月例!$S$5:$S$788,0)),"") -> 昨年実績 | P13: =IFERROR(INDEX(月例!$A$5:$A$788,MATCH("事務用消耗品費|S|8",月例!$S$5:$S$788,0)),"") -> 46203 | Q13: =IFERROR(INDEX(月例!$E$5:$E$788,MATCH("事務用消耗品費|S|8",月例!$S$5:$S$788,0)),"") -> 鋳造ゴム印 3号以下 51字 他5点 | R13: =IFERROR(INDEX(月例!$H$5:$H$788,MATCH("事務用消耗品費|S|8",月例!$S$5:$S$788,0)),"") -> 24508 | S13: =IF(R13="","",S12-R13) -> 1338365 | T13: =IFERROR(INDEX(月例!$P$5:$P$788,MATCH("事務用消耗品費|S|8",月例!$S$5:$S$788,0)),"") -> 確認済
A14: =IFERROR(INDEX(月例!$A$5:$A$788,MATCH("通信運搬費|S|9",月例!$S$5:$S$788,0)),"") -> 44368 | B14: =IFERROR(INDEX(月例!$E$5:$E$788,MATCH("通信運搬費|S|9",月例!$S$5:$S$788,0)),"") -> 電話料金（５月使用・６月請求分） | C14: =IFERROR(INDEX(月例!$H$5:$H$788,MATCH("通信運搬費|S|9",月例!$S$5:$S$788,0)),"") -> 5407 | D14: =IF(C14="","",D13-C14) -> 564022 | E14: =IFERROR(INDEX(月例!$P$5:$P$788,MATCH("通信運搬費|S|9",月例!$S$5:$S$788,0)),"") -> 昨年実績 | F14: =IFERROR(INDEX(月例!$A$5:$A$788,MATCH("委託費|S|9",月例!$S$5:$S$788,0)),"") -> 45443 | G14: =IFERROR(INDEX(月例!$E$5:$E$788,MATCH("委託費|S|9",月例!$S$5:$S$788,0)),"") -> 柔整等療養費支給申請書の入力（４月分） | H14: =IFERROR(INDEX(月例!$H$5:$H$788,MATCH("委託費|S|9",月例!$S$5:$S$788,0)),"") -> 70730 | I14: =IF(H14="","",I13-H14) -> 7513529 | J14: =IFERROR(INDEX(月例!$P$5:$P$788,MATCH("委託費|S|9",月例!$S$5:$S$788,0)),"") -> 昨年実績 | K14: =IFERROR(INDEX(月例!$A$5:$A$788,MATCH("賃借料|S|9",月例!$S$5:$S$788,0)),"") -> 46232 | L14: =IFERROR(INDEX(月例!$E$5:$E$788,MATCH("賃借料|S|9",月例!$S$5:$S$788,0)),"") -> 基幹システム用機器賃借料 6月分（短期） | M14: =IFERROR(INDEX(月例!$H$5:$H$788,MATCH("賃借料|S|9",月例!$S$5:$S$788,0)),"") -> 672934 | N14: =IF(M14="","",N13-M14) -> 6190836 | O14: =IFERROR(INDEX(月例!$P$5:$P$788,MATCH("賃借料|S|9",月例!$S$5:$S$788,0)),"") -> 確認済 | P14: =IFERROR(INDEX(月例!$A$5:$A$788,MATCH("事務用消耗品費|S|9",月例!$S$5:$S$788,0)),"") -> 46203 | Q14: =IFERROR(INDEX(月例!$E$5:$E$788,MATCH("事務用消耗品費|S|9",月例!$S$5:$S$788,0)),"") -> アラビック補充用 ＥＮＡ－９６０／３本入 ５箱 | R14: =IFERROR(INDEX(月例!$H$5:$H$788,MATCH("事務用消耗品費|S|9",月例!$S$5:$S$788,0)),"") -> 13860 | S14: =IF(R14="","",S13-R14) -> 1324505 | T14: =IFERROR(INDEX(月例!$P$5:$P$788,MATCH("事務用消耗品費|S|9",月例!$S$5:$S$788,0)),"") -> 確認済
A15: =IFERROR(INDEX(月例!$A$5:$A$788,MATCH("通信運搬費|S|10",月例!$S$5:$S$788,0)),"") -> 45138 | B15: =IFERROR(INDEX(月例!$E$5:$E$788,MATCH("通信運搬費|S|10",月例!$S$5:$S$788,0)),"") -> メール便（任継者宛厚生だより５月分） | C15: =IFERROR(INDEX(月例!$H$5:$H$788,MATCH("通信運搬費|S|10",月例!$S$5:$S$788,0)),"") -> 19320 | D15: =IF(C15="","",D14-C15) -> 544702 | E15: =IFERROR(INDEX(月例!$P$5:$P$788,MATCH("通信運搬費|S|10",月例!$S$5:$S$788,0)),"") -> 昨年実績 | F15: =IFERROR(INDEX(月例!$A$5:$A$788,MATCH("委託費|S|10",月例!$S$5:$S$788,0)),"") -> 46192 | G15: =IFERROR(INDEX(月例!$E$5:$E$788,MATCH("委託費|S|10",月例!$S$5:$S$788,0)),"") -> レセプト電子データ提供料（３月診療分） | H15: =IFERROR(INDEX(月例!$H$5:$H$788,MATCH("委託費|S|10",月例!$S$5:$S$788,0)),"") -> 66423 | I15: =IF(H15="","",I14-H15) -> 7447106 | J15: =IFERROR(INDEX(月例!$P$5:$P$788,MATCH("委託費|S|10",月例!$S$5:$S$788,0)),"") -> 確認済 | K15: =IFERROR(INDEX(月例!$A$5:$A$788,MATCH("賃借料|S|10",月例!$S$5:$S$788,0)),"") -> 46232 | L15: =IFERROR(INDEX(月例!$E$5:$E$788,MATCH("賃借料|S|10",月例!$S$5:$S$788,0)),"") -> パソコン（業務経理用）６月分 | M15: =IFERROR(INDEX(月例!$H$5:$H$788,MATCH("賃借料|S|10",月例!$S$5:$S$788,0)),"") -> 5060 | N15: =IF(M15="","",N14-M15) -> 6185776 | O15: =IFERROR(INDEX(月例!$P$5:$P$788,MATCH("賃借料|S|10",月例!$S$5:$S$788,0)),"") -> 確認済 | P15: =IFERROR(INDEX(月例!$A$5:$A$788,MATCH("事務用消耗品費|S|10",月例!$S$5:$S$788,0)),"") -> 45838 | Q15: =IFERROR(INDEX(月例!$E$5:$E$788,MATCH("事務用消耗品費|S|10",月例!$S$5:$S$788,0)),"") -> のり B765J-10/10本入 1箱 ほか | R15: =IFERROR(INDEX(月例!$H$5:$H$788,MATCH("事務用消耗品費|S|10",月例!$S$5:$S$788,0)),"") -> 2906 | S15: =IF(R15="","",S14-R15) -> 1321599 | T15: =IFERROR(INDEX(月例!$P$5:$P$788,MATCH("事務用消耗品費|S|10",月例!$S$5:$S$788,0)),"") -> 昨年実績
