Workbook
Name 年度: '月次締め'!$C$4
Name 締月: '月次締め'!$C$6

Sheet 使い方
A1: 令和8年度 費用収益表 統合ブック 使い方
A2: 旧：管理簿・予算差引簿・費用収益表の3ファイルを、「入力は台帳1か所だけ」「費用収益表は自動計上」「照合も自動」に作り替えたブックです。
B4: 毎月の流れ（旧→新）
B5: 担当 | C5: 新しいやり方 | D5: 旧
B6: ① 支払担当者 | C6: 入力シートで、昨年実績の行を今年の支払に直します（日付・金額）。状態を「昨年実績」→「未確認」へ。 | D6: 赤字を黒字にして金額を修正
B7: ② 経理担当者 | C7: 支払伝票が回ってきたら、その行の状態を「未確認」→「確認済」へ（プルダウン）。 | D7: 金額を青で塗りつぶして確認
B8: ③ 経理〆 | C8: 「月次締め」シートで「今回締める月」を選ぶ。費用収益表はその月まで自動で確定計上されます。 | D8: 黒字＋色塗りを費用収益表へ手で転記
B9: ④ 照合 | C9: 「月次締め」の黄色いセルに仮締め出納計算表の月合計を入力。差額が 0 で「OK」になればOK。 | D9: 費用収益表と出納計算表を目で照合
B10: ⑤ 月次更新 | C10: OK を確認して基幹システムで月次更新処理。「検算」シートが全部 OK ならこのブックの数字は一致しています。 | D10: 同じ
B12: 色のルール（状態から自動で付きます）
B13: 赤字 | C13: 状態＝昨年実績。今年の支払が確定するまで残しておく行（集計には入りません）。
B14: 黄色の背景 | C14: 状態＝未確認。今年の支払として入力済みだが、伝票確認前。
B15: 青い背景 | C15: 状態＝確認済。締め月までの分が費用収益表に計上されます。
B16: 取り消し線（灰色） | C16: 状態＝支払なし。今年度は支払がない行（集計から除外。行は残せます）。
B17: 費用収益表の緑字 | C17: 締め月より後の月＝前年実績・見込（旧表の値）。締め月までは黒字の確定値になります。
B18: 青字のセル | C18: 手入力するセル（金額・予算・収益など）。黒字は数式なので触りません。
B20: シート一覧
B21: 月次締め | C21: 操作盤。今回締める月の選択／締める前のチェック／出納計算表との照合。
B22: 入力_業務 / 入力_貸付 | C22: 台帳（旧：管理簿・予算差引簿）。支払はここだけに入力。行を足すときは最終行の下へ（業務1,600行・貸付400行まで）。
B23: 費用収益表（4枚） | C23: 業務合計・短期・長期・貸付。旧表と同じ配置。台帳連動の行は自動計算、収益・給与・予算などは手入力。
B24: 給付区分別 | C24: 旧：給付区分別執行額（月別／年度分）。確認済のみ集計。
B25: 科目表 | C25: プルダウンの元と、台帳の科目を費用収益表のどの行に入れるかのルール。
B26: 検算 / 旧表照合 | C26: 自動検算。旧表照合は、旧・費用収益表（9月締め時点）と1セルずつ突き合わせた結果。
B28: 注意
B29: 数式の列は消さない | C29: 灰色の列（短期・厚年…・費用収益表の行・計上列・点検など）は数式です。台帳に行を足すときは最終行の下の空き行に入力するだけでOK（数式は1,600行／400行分あらかじめ入っています）。
B30: 経費区分 | C30: 1〜8の按分ルールは旧「端数処理」と同じです（科目表の右側に一覧）。
B31: 来年度の更新 | C31: ①ブックを複製 ②月次締めの年度を変更 ③台帳の状態をすべて「昨年実績」に（フィルタ→コピー貼り付け）④費用収益表の予算・参考値を更新。

Sheet 月次締め
A1: 月次締め 操作盤と出納計算表との照合
A2: 月次〆のときは「今回締める月」を選ぶだけです。費用収益表がその月まで自動で確定表示になります（転記は不要）。黄色のセルに仮締めした出納計算表の月合計を入力し、差額が 0 になればOKです。
B4: 年度（令和） | C4: 8 | F4: 自動検算 | G4: =IF(検算!$F$3=0,"すべてOK","NG "&検算!$F$3&"件（検算シート参照）") -> すべてOK
B5: 今回締める月 | C5: 9月 | D5: ← ここを変えると、その月まで費用収益表に確定計上されます（9月締め済みなら「9月」）
B6: 月番号（自動） | C6: =MATCH($C$5,科目表!$N$5:$N$18,0)-1 -> 6
B8: ① 締める前のチェック（今回締める月の分）
B9: 項目 | C9: 業務 | D9: 貸付 | E9: 対応
B10: 確認済（青塗り相当）の件数 | C10: =IF(締月=0,0,COUNTIFS(入力_業務!$P$5:$P$1604,締月,入力_業務!$I$5:$I$1604,"確認済")) -> 35 | D10: =IF(締月=0,0,COUNTIFS(入力_貸付!$H$5:$H$404,締月,入力_貸付!$G$5:$G$404,"確認済")) -> 6 | E10: 費用収益表に計上される行数です
B11: 未確認（伝票待ち）の件数 | C11: =IF(締月=0,0,COUNTIFS(入力_業務!$P$5:$P$1604,締月,入力_業務!$I$5:$I$1604,"未確認")) -> 0 | D11: =IF(締月=0,0,COUNTIFS(入力_貸付!$H$5:$H$404,締月,入力_貸付!$G$5:$G$404,"未確認")) -> 0 | E11: 0 にしてから締めます（伝票を確認して「確認済」へ）
B12: 昨年実績のまま残っている件数（参考） | C12: =IF(締月=0,0,COUNTIFS(入力_業務!$P$5:$P$1604,締月,入力_業務!$I$5:$I$1604,"昨年実績")) -> 22 | D12: =IF(締月=0,0,COUNTIFS(入力_貸付!$H$5:$H$404,締月,入力_貸付!$G$5:$G$404,"昨年実績")) -> 2 | E12: 今年は支払がない行は「支払なし」にすると見やすくなります
B13: 点検NGの件数（台帳全体） | C13: =COUNTIF(入力_業務!$Q$5:$Q$1604,"?*") -> 0 | D13: =COUNTIF(入力_貸付!$J$5:$J$404,"?*") -> 0 | E13: 入力シートの「点検」列に内容が出ます
B14: 確認済 金額合計 | C14: =IF(締月=0,0,SUMIFS(入力_業務!$G$5:$G$1604,入力_業務!$P$5:$P$1604,締月,入力_業務!$I$5:$I$1604,"確認済")) -> 30634243 | D14: =IF(締月=0,0,SUMIFS(入力_貸付!$F$5:$F$404,入力_貸付!$H$5:$H$404,締月,入力_貸付!$G$5:$G$404,"確認済")) -> 325836 | E14: 旧：転記する金額の合計。業務は短期＋長期の合計
B15: 締め可否 | C15: =IF(締月=0,"-",IF(AND(C11=0,C13=0),"OK","要対応")) -> OK | D15: =IF(締月=0,"-",IF(AND(D11=0,D13=0),"OK","要対応")) -> OK
B18: ② 出納計算表との照合（黄色のセルに仮締めした出納計算表の月合計を入力）
B20: 業務経理（短期）
B21: 月 | C21: 費用 | F21: 収益 | I21: 判定
C22: 費用収益表 | D22: 出納計算表 | E22: 差額 | F22: 費用収益表 | G22: 出納計算表 | H22: 差額
B23: 4月 | C23: ='費用収益表_業務短期'!C38 -> 534591 | E23: =IF(D23="","",C23-D23) | F23: ='費用収益表_業務短期'!C46 -> 2268000 | H23: =IF(G23="","",F23-G23) | I23: =IF(1>締月,"",IF(OR(D23="",G23=""),"出納計算表 未入力",IF(AND(E23=0,H23=0),"OK","NG 差額あり"))) -> 出納計算表 未入力
B24: 5月 | C24: ='費用収益表_業務短期'!D38 -> 4087081 | E24: =IF(D24="","",C24-D24) | F24: ='費用収益表_業務短期'!D46 -> 2150000 | H24: =IF(G24="","",F24-G24) | I24: =IF(2>締月,"",IF(OR(D24="",G24=""),"出納計算表 未入力",IF(AND(E24=0,H24=0),"OK","NG 差額あり"))) -> 出納計算表 未入力
B25: 6月 | C25: ='費用収益表_業務短期'!E38 -> 2455166 | E25: =IF(D25="","",C25-D25) | F25: ='費用収益表_業務短期'!E46 -> 2609000 | H25: =IF(G25="","",F25-G25) | I25: =IF(3>締月,"",IF(OR(D25="",G25=""),"出納計算表 未入力",IF(AND(E25=0,H25=0),"OK","NG 差額あり"))) -> 出納計算表 未入力
B26: 7月 | C26: ='費用収益表_業務短期'!F38 -> 1972276 | E26: =IF(D26="","",C26-D26) | F26: ='費用収益表_業務短期'!F46 -> 2725000 | H26: =IF(G26="","",F26-G26) | I26: =IF(4>締月,"",IF(OR(D26="",G26=""),"出納計算表 未入力",IF(AND(E26=0,H26=0),"OK","NG 差額あり"))) -> 出納計算表 未入力
B27: 8月 | C27: ='費用収益表_業務短期'!G38 -> 2709341 | E27: =IF(D27="","",C27-D27) | F27: ='費用収益表_業務短期'!G46 -> 2151000 | H27: =IF(G27="","",F27-G27) | I27: =IF(5>締月,"",IF(OR(D27="",G27=""),"出納計算表 未入力",IF(AND(E27=0,H27=0),"OK","NG 差額あり"))) -> 出納計算表 未入力
B28: 9月 | C28: ='費用収益表_業務短期'!H38 -> 24070375 | E28: =IF(D28="","",C28-D28) | F28: ='費用収益表_業務短期'!H46 -> 12794000 | H28: =IF(G28="","",F28-G28) | I28: =IF(6>締月,"",IF(OR(D28="",G28=""),"出納計算表 未入力",IF(AND(E28=0,H28=0),"OK","NG 差額あり"))) -> 出納計算表 未入力
B29: 10月 | C29: ='費用収益表_業務短期'!I38 -> 2454418 | E29: =IF(D29="","",C29-D29) | F29: ='費用収益表_業務短期'!I46 -> 2477000 | H29: =IF(G29="","",F29-G29) | I29: =IF(7>締月,"",IF(OR(D29="",G29=""),"出納計算表 未入力",IF(AND(E29=0,H29=0),"OK","NG 差額あり")))
B30: 11月 | C30: ='費用収益表_業務短期'!J38 -> 2501632 | E30: =IF(D30="","",C30-D30) | F30: ='費用収益表_業務短期'!J46 -> 2228000 | H30: =IF(G30="","",F30-G30) | I30: =IF(8>締月,"",IF(OR(D30="",G30=""),"出納計算表 未入力",IF(AND(E30=0,H30=0),"OK","NG 差額あり")))
B31: 12月 | C31: ='費用収益表_業務短期'!K38 -> 5009376 | E31: =IF(D31="","",C31-D31) | F31: ='費用収益表_業務短期'!K46 -> 2894000 | H31: =IF(G31="","",F31-G31) | I31: =IF(9>締月,"",IF(OR(D31="",G31=""),"出納計算表 未入力",IF(AND(E31=0,H31=0),"OK","NG 差額あり")))
B32: 1月 | C32: ='費用収益表_業務短期'!L38 -> 2079276 | E32: =IF(D32="","",C32-D32) | F32: ='費用収益表_業務短期'!L46 -> 2560000 | H32: =IF(G32="","",F32-G32) | I32: =IF(10>締月,"",IF(OR(D32="",G32=""),"出納計算表 未入力",IF(AND(E32=0,H32=0),"OK","NG 差額あり")))
B33: 2月 | C33: ='費用収益表_業務短期'!M38 -> 2212970 | E33: =IF(D33="","",C33-D33) | F33: ='費用収益表_業務短期'!M46 -> 2209000 | H33: =IF(G33="","",F33-G33) | I33: =IF(11>締月,"",IF(OR(D33="",G33=""),"出納計算表 未入力",IF(AND(E33=0,H33=0),"OK","NG 差額あり")))
B34: 3月 | C34: ='費用収益表_業務短期'!N38 -> 2135536 | E34: =IF(D34="","",C34-D34) | F34: ='費用収益表_業務短期'!N46 -> 3606000 | H34: =IF(G34="","",F34-G34) | I34: =IF(12>締月,"",IF(OR(D34="",G34=""),"出納計算表 未入力",IF(AND(E34=0,H34=0),"OK","NG 差額あり")))
B35: 4月(未払) | C35: ='費用収益表_業務短期'!O38 -> 3204092 | E35: =IF(D35="","",C35-D35) | F35: ='費用収益表_業務短期'!O46 -> 9655506 | H35: =IF(G35="","",F35-G35) | I35: =IF(13>締月,"",IF(OR(D35="",G35=""),"出納計算表 未入力",IF(AND(E35=0,H35=0),"OK","NG 差額あり")))
B36: 締め月までの合計 | C36: =SUMPRODUCT((ROW(C23:C35)-23+1<=締月)*C23:C35) -> 35828830 | D36: =SUMPRODUCT((ROW(D23:D35)-23+1<=締月)*D23:D35) -> 0 | E36: =C36-D36 -> 35828830 | F36: =SUMPRODUCT((ROW(F23:F35)-23+1<=締月)*F23:F35) -> 24697000 | G36: =SUMPRODUCT((ROW(G23:G35)-23+1<=締月)*G23:G35) -> 0 | H36: =F36-G36 -> 24697000
B38: 業務経理（長期）
B39: 月 | C39: 費用 | F39: 収益 | I39: 判定
C40: 費用収益表 | D40: 出納計算表 | E40: 差額 | F40: 費用収益表 | G40: 出納計算表 | H40: 差額
B41: 4月 | C41: ='費用収益表_業務長期'!C38 -> 412079 | E41: =IF(D41="","",C41-D41) | F41: ='費用収益表_業務長期'!C46 -> 4513000 | H41: =IF(G41="","",F41-G41) | I41: =IF(1>締月,"",IF(OR(D41="",G41=""),"出納計算表 未入力",IF(AND(E41=0,H41=0),"OK","NG 差額あり"))) -> 出納計算表 未入力
B42: 5月 | C42: ='費用収益表_業務長期'!D38 -> 6019213 | E42: =IF(D42="","",C42-D42) | F42: ='費用収益表_業務長期'!D46 -> 9026000 | H42: =IF(G42="","",F42-G42) | I42: =IF(2>締月,"",IF(OR(D42="",G42=""),"出納計算表 未入力",IF(AND(E42=0,H42=0),"OK","NG 差額あり"))) -> 出納計算表 未入力
B43: 6月 | C43: ='費用収益表_業務長期'!E38 -> 6989919 | E43: =IF(D43="","",C43-D43) | F43: ='費用収益表_業務長期'!E46 -> 10732000 | H43: =IF(G43="","",F43-G43) | I43: =IF(3>締月,"",IF(OR(D43="",G43=""),"出納計算表 未入力",IF(AND(E43=0,H43=0),"OK","NG 差額あり"))) -> 出納計算表 未入力
B44: 7月 | C44: ='費用収益表_業務長期'!F38 -> 7671974 | E44: =IF(D44="","",C44-D44) | F44: ='費用収益表_業務長期'!F46 -> 13189000 | H44: =IF(G44="","",F44-G44) | I44: =IF(4>締月,"",IF(OR(D44="",G44=""),"出納計算表 未入力",IF(AND(E44=0,H44=0),"OK","NG 差額あり"))) -> 出納計算表 未入力
B45: 8月 | C45: ='費用収益表_業務長期'!G38 -> 7267746 | E45: =IF(D45="","",C45-D45) | F45: ='費用収益表_業務長期'!G46 -> 9879000 | H45: =IF(G45="","",F45-G45) | I45: =IF(5>締月,"",IF(OR(D45="",G45=""),"出納計算表 未入力",IF(AND(E45=0,H45=0),"OK","NG 差額あり"))) -> 出納計算表 未入力
B46: 9月 | C46: ='費用収益表_業務長期'!H38 -> 6563868 | E46: =IF(D46="","",C46-D46) | F46: ='費用収益表_業務長期'!H46 -> 9882148 | H46: =IF(G46="","",F46-G46) | I46: =IF(6>締月,"",IF(OR(D46="",G46=""),"出納計算表 未入力",IF(AND(E46=0,H46=0),"OK","NG 差額あり"))) -> 出納計算表 未入力
B47: 10月 | C47: ='費用収益表_業務長期'!I38 -> 5598151 | E47: =IF(D47="","",C47-D47) | F47: ='費用収益表_業務長期'!I46 -> 4513000 | H47: =IF(G47="","",F47-G47) | I47: =IF(7>締月,"",IF(OR(D47="",G47=""),"出納計算表 未入力",IF(AND(E47=0,H47=0),"OK","NG 差額あり")))
B48: 11月 | C48: ='費用収益表_業務長期'!J38 -> 6657637 | E48: =IF(D48="","",C48-D48) | F48: ='費用収益表_業務長期'!J46 -> 4251590 | H48: =IF(G48="","",F48-G48) | I48: =IF(8>締月,"",IF(OR(D48="",G48=""),"出納計算表 未入力",IF(AND(E48=0,H48=0),"OK","NG 差額あり")))
B49: 12月 | C49: ='費用収益表_業務長期'!K38 -> 6162473 | E49: =IF(D49="","",C49-D49) | F49: ='費用収益表_業務長期'!K46 -> 4513000 | H49: =IF(G49="","",F49-G49) | I49: =IF(9>締月,"",IF(OR(D49="",G49=""),"出納計算表 未入力",IF(AND(E49=0,H49=0),"OK","NG 差額あり")))
B50: 1月 | C50: ='費用収益表_業務長期'!L38 -> 6712949 | E50: =IF(D50="","",C50-D50) | F50: ='費用収益表_業務長期'!L46 -> 4513000 | H50: =IF(G50="","",F50-G50) | I50: =IF(10>締月,"",IF(OR(D50="",G50=""),"出納計算表 未入力",IF(AND(E50=0,H50=0),"OK","NG 差額あり")))
B51: 2月 | C51: ='費用収益表_業務長期'!M38 -> 6080259 | E51: =IF(D51="","",C51-D51) | F51: ='費用収益表_業務長期'!M46 -> 4513000 | H51: =IF(G51="","",F51-G51) | I51: =IF(11>締月,"",IF(OR(D51="",G51=""),"出納計算表 未入力",IF(AND(E51=0,H51=0),"OK","NG 差額あり")))
B52: 3月 | C52: ='費用収益表_業務長期'!N38 -> 10698750 | E52: =IF(D52="","",C52-D52) | F52: ='費用収益表_業務長期'!N46 -> 4585258 | H52: =IF(G52="","",F52-G52) | I52: =IF(12>締月,"",IF(OR(D52="",G52=""),"出納計算表 未入力",IF(AND(E52=0,H52=0),"OK","NG 差額あり")))
B53: 4月(未払) | C53: ='費用収益表_業務長期'!O38 -> 784007 | E53: =IF(D53="","",C53-D53) | F53: ='費用収益表_業務長期'!O46 -> 0 | H53: =IF(G53="","",F53-G53) | I53: =IF(13>締月,"",IF(OR(D53="",G53=""),"出納計算表 未入力",IF(AND(E53=0,H53=0),"OK","NG 差額あり")))
B54: 締め月までの合計 | C54: =SUMPRODUCT((ROW(C41:C53)-41+1<=締月)*C41:C53) -> 34924799 | D54: =SUMPRODUCT((ROW(D41:D53)-41+1<=締月)*D41:D53) -> 0 | E54: =C54-D54 -> 34924799 | F54: =SUMPRODUCT((ROW(F41:F53)-41+1<=締月)*F41:F53) -> 57221148 | G54: =SUMPRODUCT((ROW(G41:G53)-41+1<=締月)*G41:G53) -> 0 | H54: =F54-G54 -> 57221148
B56: 貸付経理
B57: 月 | C57: 費用 | F57: 収益 | I57: 判定
C58: 費用収益表 | D58: 出納計算表 | E58: 差額 | F58: 費用収益表 | G58: 出納計算表 | H58: 差額
B59: 4月 | C59: ='費用収益表_貸付'!C31 -> 542066 | E59: =IF(D59="","",C59-D59) | F59: ='費用収益表_貸付'!C36 -> 809638 | H59: =IF(G59="","",F59-G59) | I59: =IF(1>締月,"",IF(OR(D59="",G59=""),"出納計算表 未入力",IF(AND(E59=0,H59=0),"OK","NG 差額あり"))) -> 出納計算表 未入力
B60: 5月 | C60: ='費用収益表_貸付'!D31 -> 962591 | E60: =IF(D60="","",C60-D60) | F60: ='費用収益表_貸付'!D36 -> 894954 | H60: =IF(G60="","",F60-G60) | I60: =IF(2>締月,"",IF(OR(D60="",G60=""),"出納計算表 未入力",IF(AND(E60=0,H60=0),"OK","NG 差額あり"))) -> 出納計算表 未入力
B61: 6月 | C61: ='費用収益表_貸付'!E31 -> 1900656 | E61: =IF(D61="","",C61-D61) | F61: ='費用収益表_貸付'!E36 -> 974223 | H61: =IF(G61="","",F61-G61) | I61: =IF(3>締月,"",IF(OR(D61="",G61=""),"出納計算表 未入力",IF(AND(E61=0,H61=0),"OK","NG 差額あり"))) -> 出納計算表 未入力
B62: 7月 | C62: ='費用収益表_貸付'!F31 -> 1106995 | E62: =IF(D62="","",C62-D62) | F62: ='費用収益表_貸付'!F36 -> 632156 | H62: =IF(G62="","",F62-G62) | I62: =IF(4>締月,"",IF(OR(D62="",G62=""),"出納計算表 未入力",IF(AND(E62=0,H62=0),"OK","NG 差額あり"))) -> 出納計算表 未入力
B63: 8月 | C63: ='費用収益表_貸付'!G31 -> 1423062 | E63: =IF(D63="","",C63-D63) | F63: ='費用収益表_貸付'!G36 -> 829696 | H63: =IF(G63="","",F63-G63) | I63: =IF(5>締月,"",IF(OR(D63="",G63=""),"出納計算表 未入力",IF(AND(E63=0,H63=0),"OK","NG 差額あり"))) -> 出納計算表 未入力
B64: 9月 | C64: ='費用収益表_貸付'!H31 -> 1089403 | E64: =IF(D64="","",C64-D64) | F64: ='費用収益表_貸付'!H36 -> 802084 | H64: =IF(G64="","",F64-G64) | I64: =IF(6>締月,"",IF(OR(D64="",G64=""),"出納計算表 未入力",IF(AND(E64=0,H64=0),"OK","NG 差額あり"))) -> 出納計算表 未入力
B65: 10月 | C65: ='費用収益表_貸付'!I31 -> 1080718 | E65: =IF(D65="","",C65-D65) | F65: ='費用収益表_貸付'!I36 -> 838256 | H65: =IF(G65="","",F65-G65) | I65: =IF(7>締月,"",IF(OR(D65="",G65=""),"出納計算表 未入力",IF(AND(E65=0,H65=0),"OK","NG 差額あり")))
B66: 11月 | C66: ='費用収益表_貸付'!J31 -> 913437 | E66: =IF(D66="","",C66-D66) | F66: ='費用収益表_貸付'!J36 -> 820237 | H66: =IF(G66="","",F66-G66) | I66: =IF(8>締月,"",IF(OR(D66="",G66=""),"出納計算表 未入力",IF(AND(E66=0,H66=0),"OK","NG 差額あり")))
B67: 12月 | C67: ='費用収益表_貸付'!K31 -> 1921335 | E67: =IF(D67="","",C67-D67) | F67: ='費用収益表_貸付'!K36 -> 1204671 | H67: =IF(G67="","",F67-G67) | I67: =IF(9>締月,"",IF(OR(D67="",G67=""),"出納計算表 未入力",IF(AND(E67=0,H67=0),"OK","NG 差額あり")))
B68: 1月 | C68: ='費用収益表_貸付'!L31 -> 1092749 | E68: =IF(D68="","",C68-D68) | F68: ='費用収益表_貸付'!L36 -> 814454 | H68: =IF(G68="","",F68-G68) | I68: =IF(10>締月,"",IF(OR(D68="",G68=""),"出納計算表 未入力",IF(AND(E68=0,H68=0),"OK","NG 差額あり")))
B69: 2月 | C69: ='費用収益表_貸付'!M31 -> 1053997 | E69: =IF(D69="","",C69-D69) | F69: ='費用収益表_貸付'!M36 -> 834390 | H69: =IF(G69="","",F69-G69) | I69: =IF(11>締月,"",IF(OR(D69="",G69=""),"出納計算表 未入力",IF(AND(E69=0,H69=0),"OK","NG 差額あり")))
B70: 3月 | C70: ='費用収益表_貸付'!N31 -> 1006894 | E70: =IF(D70="","",C70-D70) | F70: ='費用収益表_貸付'!N36 -> 801567 | H70: =IF(G70="","",F70-G70) | I70: =IF(12>締月,"",IF(OR(D70="",G70=""),"出納計算表 未入力",IF(AND(E70=0,H70=0),"OK","NG 差額あり")))
B71: 4月(未払) | C71: ='費用収益表_貸付'!O31 -> 595170 | E71: =IF(D71="","",C71-D71) | F71: ='費用収益表_貸付'!O36 -> 247126 | H71: =IF(G71="","",F71-G71) | I71: =IF(13>締月,"",IF(OR(D71="",G71=""),"出納計算表 未入力",IF(AND(E71=0,H71=0),"OK","NG 差額あり")))
B72: 締め月までの合計 | C72: =SUMPRODUCT((ROW(C59:C71)-59+1<=締月)*C59:C71) -> 7024773 | D72: =SUMPRODUCT((ROW(D59:D71)-59+1<=締月)*D59:D71) -> 0 | E72: =C72-D72 -> 7024773 | F72: =SUMPRODUCT((ROW(F59:F71)-59+1<=締月)*F59:F71) -> 4942751 | G72: =SUMPRODUCT((ROW(G59:G71)-59+1<=締月)*G59:G71) -> 0 | H72: =F72-G72 -> 4942751

Sheet 入力_業務
A1: 入力_業務 業務経理 台帳（旧：管理簿「月例」「決算整理」を一本化）
A2: 支払担当者：昨年実績の行を今年の支払に直し、状態を「未確認」へ。 経理担当者：支払伝票を確認したら状態を「確認済」へ（旧：金額を青塗り）。 色は状態から自動で付きます（赤字＝昨年実績／黄＝未確認／青＝確認済）。 灰色の列は数式なので消さないでください。
A4: No | B4: 種別 | C4: 支払日 | D4: 中項目 | E4: 小項目 | F4: 摘要 | G4: 金額 | H4: 経費区分 | I4: 状態 | J4: 短期 | K4: 厚年 | L4: 経過的 | M4: 退職等 | N4: 長期計 | O4: 費用収益表の行 | P4: 計上列 | Q4: 点検 | R4: 元データ
A5: 1 | B5: 月例 | C5: 45756 | D5: 事務費 | E5: 通信運搬費 | F5: 切手 | G5: 178000 | H5: 2 | I5: 昨年実績 | J5: =IF($G5="","",IF($H5=1,$G5-ROUND($G5*10/23,0)-2*ROUND($G5/23,0),IF($H5=2,$G5,0))) -> 178000 | K5: =IF($G5="","",IF($H5=1,ROUND($G5*10/23,0),IF($H5=3,$G5-2*ROUND($G5/12,0),IF($H5=4,$G5,IF(OR($H5=5,$H5=7),ROUND($G5*10/11,0),0))))) -> 0 | L5: =IF($G5="","",IF($H5=1,ROUND($G5/23,0),IF($H5=3,ROUND($G5/12,0),IF($H5=5,$G5-ROUND($G5*10/11,0),IF($H5=8,$G5,0))))) -> 0 | M5: =IF($G5="","",IF($H5=1,ROUND($G5/23,0),IF($H5=3,ROUND($G5/12,0),IF($H5=6,$G5,IF($H5=7,$G5-ROUND($G5*10/11,0),0))))) -> 0 | N5: =IF($G5="","",K5+L5+M5) -> 0 | O5: =IF($G5="","",IFERROR(VLOOKUP($D5&"|"&$E5,科目表!$A$5:$B$200,2,FALSE),"※未登録")) -> 通信運搬費 | P5: =IF(OR($G5="",$C5=""),"",IF($B5="決算整理",13,MOD(MONTH($C5)-4,12)+1)) -> 1 | Q5: =IF($G5="","",TRIM(IF(J5+K5+L5+M5<>$G5,"按分不一致 ","")&IF(O5="※未登録","科目未登録 ","")&IF(OR($H5="",ISERROR(MATCH($H5,{1,2,3,4,5,6,7,8},0))),"経費区分? ","")&IF($I5="","状態未設定 ","")&IF(AND(OR($I5="確認済",$I5="未確認"),$B5="月例",OR($C5="",$C5<DATE(年度+2018,4,1),$C5>DATE(年度+2019,3,31))),"年度外の日付 ","")&IF(AND(OR($I5="確認済",$I5="未確認"),O5="対象外"),"対象外の科目 ",""))) | R5: 月例!5
A6: 2 | B6: 月例 | C6: 46140 | D6: 事務費 | E6: 事務用消耗品費 | F6: 令和８年度基幹ウイルス対策ソフト（ミツイワ株式会社）短期 | G6: 20482 | H6: 2 | I6: 確認済 | J6: =IF($G6="","",IF($H6=1,$G6-ROUND($G6*10/23,0)-2*ROUND($G6/23,0),IF($H6=2,$G6,0))) -> 20482 | K6: =IF($G6="","",IF($H6=1,ROUND($G6*10/23,0),IF($H6=3,$G6-2*ROUND($G6/12,0),IF($H6=4,$G6,IF(OR($H6=5,$H6=7),ROUND($G6*10/11,0),0))))) -> 0 | L6: =IF($G6="","",IF($H6=1,ROUND($G6/23,0),IF($H6=3,ROUND($G6/12,0),IF($H6=5,$G6-ROUND($G6*10/11,0),IF($H6=8,$G6,0))))) -> 0 | M6: =IF($G6="","",IF($H6=1,ROUND($G6/23,0),IF($H6=3,ROUND($G6/12,0),IF($H6=6,$G6,IF($H6=7,$G6-ROUND($G6*10/11,0),0))))) -> 0 | N6: =IF($G6="","",K6+L6+M6) -> 0 | O6: =IF($G6="","",IFERROR(VLOOKUP($D6&"|"&$E6,科目表!$A$5:$B$200,2,FALSE),"※未登録")) -> 事務用消耗品費 | P6: =IF(OR($G6="",$C6=""),"",IF($B6="決算整理",13,MOD(MONTH($C6)-4,12)+1)) -> 1 | Q6: =IF($G6="","",TRIM(IF(J6+K6+L6+M6<>$G6,"按分不一致 ","")&IF(O6="※未登録","科目未登録 ","")&IF(OR($H6="",ISERROR(MATCH($H6,{1,2,3,4,5,6,7,8},0))),"経費区分? ","")&IF($I6="","状態未設定 ","")&IF(AND(OR($I6="確認済",$I6="未確認"),$B6="月例",OR($C6="",$C6<DATE(年度+2018,4,1),$C6>DATE(年度+2019,3,31))),"年度外の日付 ","")&IF(AND(OR($I6="確認済",$I6="未確認"),O6="対象外"),"対象外の科目 ",""))) | R6: 月例!6
A7: 3 | B7: 月例 | C7: 46140 | D7: 事務費 | E7: 事務用消耗品費 | F7: 令和８年度基幹ウイルス対策ソフト（ミツイワ株式会社）長期 | G7: 8778 | H7: 3 | I7: 確認済 | J7: =IF($G7="","",IF($H7=1,$G7-ROUND($G7*10/23,0)-2*ROUND($G7/23,0),IF($H7=2,$G7,0))) -> 0 | K7: =IF($G7="","",IF($H7=1,ROUND($G7*10/23,0),IF($H7=3,$G7-2*ROUND($G7/12,0),IF($H7=4,$G7,IF(OR($H7=5,$H7=7),ROUND($G7*10/11,0),0))))) -> 7314 | L7: =IF($G7="","",IF($H7=1,ROUND($G7/23,0),IF($H7=3,ROUND($G7/12,0),IF($H7=5,$G7-ROUND($G7*10/11,0),IF($H7=8,$G7,0))))) -> 732 | M7: =IF($G7="","",IF($H7=1,ROUND($G7/23,0),IF($H7=3,ROUND($G7/12,0),IF($H7=6,$G7,IF($H7=7,$G7-ROUND($G7*10/11,0),0))))) -> 732 | N7: =IF($G7="","",K7+L7+M7) -> 8778 | O7: =IF($G7="","",IFERROR(VLOOKUP($D7&"|"&$E7,科目表!$A$5:$B$200,2,FALSE),"※未登録")) -> 事務用消耗品費 | P7: =IF(OR($G7="",$C7=""),"",IF($B7="決算整理",13,MOD(MONTH($C7)-4,12)+1)) -> 1 | Q7: =IF($G7="","",TRIM(IF(J7+K7+L7+M7<>$G7,"按分不一致 ","")&IF(O7="※未登録","科目未登録 ","")&IF(OR($H7="",ISERROR(MATCH($H7,{1,2,3,4,5,6,7,8},0))),"経費区分? ","")&IF($I7="","状態未設定 ","")&IF(AND(OR($I7="確認済",$I7="未確認"),$B7="月例",OR($C7="",$C7<DATE(年度+2018,4,1),$C7>DATE(年度+2019,3,31))),"年度外の日付 ","")&IF(AND(OR($I7="確認済",$I7="未確認"),O7="対象外"),"対象外の科目 ",""))) | R7: 月例!7
A8: 4 | B8: 月例 | C8: 44316 | D8: 事務費 | E8: 事務用消耗品費 | F8: CD／DVDファイルＡ４１２ＪーＣ 他 | G8: 24407 | H8: 2 | I8: 昨年実績 | J8: =IF($G8="","",IF($H8=1,$G8-ROUND($G8*10/23,0)-2*ROUND($G8/23,0),IF($H8=2,$G8,0))) -> 24407 | K8: =IF($G8="","",IF($H8=1,ROUND($G8*10/23,0),IF($H8=3,$G8-2*ROUND($G8/12,0),IF($H8=4,$G8,IF(OR($H8=5,$H8=7),ROUND($G8*10/11,0),0))))) -> 0 | L8: =IF($G8="","",IF($H8=1,ROUND($G8/23,0),IF($H8=3,ROUND($G8/12,0),IF($H8=5,$G8-ROUND($G8*10/11,0),IF($H8=8,$G8,0))))) -> 0 | M8: =IF($G8="","",IF($H8=1,ROUND($G8/23,0),IF($H8=3,ROUND($G8/12,0),IF($H8=6,$G8,IF($H8=7,$G8-ROUND($G8*10/11,0),0))))) -> 0 | N8: =IF($G8="","",K8+L8+M8) -> 0 | O8: =IF($G8="","",IFERROR(VLOOKUP($D8&"|"&$E8,科目表!$A$5:$B$200,2,FALSE),"※未登録")) -> 事務用消耗品費 | P8: =IF(OR($G8="",$C8=""),"",IF($B8="決算整理",13,MOD(MONTH($C8)-4,12)+1)) -> 1 | Q8: =IF($G8="","",TRIM(IF(J8+K8+L8+M8<>$G8,"按分不一致 ","")&IF(O8="※未登録","科目未登録 ","")&IF(OR($H8="",ISERROR(MATCH($H8,{1,2,3,4,5,6,7,8},0))),"経費区分? ","")&IF($I8="","状態未設定 ","")&IF(AND(OR($I8="確認済",$I8="未確認"),$B8="月例",OR($C8="",$C8<DATE(年度+2018,4,1),$C8>DATE(年度+2019,3,31))),"年度外の日付 ","")&IF(AND(OR($I8="確認済",$I8="未確認"),O8="対象外"),"対象外の科目 ",""))) | R8: 月例!8
A9: 5 | B9: 月例 | C9: 45764 | D9: 事務費 | E9: 通信運搬費 | F9: 切手 | G9: 173700 | H9: 3 | I9: 昨年実績 | J9: =IF($G9="","",IF($H9=1,$G9-ROUND($G9*10/23,0)-2*ROUND($G9/23,0),IF($H9=2,$G9,0))) -> 0 | K9: =IF($G9="","",IF($H9=1,ROUND($G9*10/23,0),IF($H9=3,$G9-2*ROUND($G9/12,0),IF($H9=4,$G9,IF(OR($H9=5,$H9=7),ROUND($G9*10/11,0),0))))) -> 144750 | L9: =IF($G9="","",IF($H9=1,ROUND($G9/23,0),IF($H9=3,ROUND($G9/12,0),IF($H9=5,$G9-ROUND($G9*10/11,0),IF($H9=8,$G9,0))))) -> 14475 | M9: =IF($G9="","",IF($H9=1,ROUND($G9/23,0),IF($H9=3,ROUND($G9/12,0),IF($H9=6,$G9,IF($H9=7,$G9-ROUND($G9*10/11,0),0))))) -> 14475 | N9: =IF($G9="","",K9+L9+M9) -> 173700 | O9: =IF($G9="","",IFERROR(VLOOKUP($D9&"|"&$E9,科目表!$A$5:$B$200,2,FALSE),"※未登録")) -> 通信運搬費 | P9: =IF(OR($G9="",$C9=""),"",IF($B9="決算整理",13,MOD(MONTH($C9)-4,12)+1)) -> 1 | Q9: =IF($G9="","",TRIM(IF(J9+K9+L9+M9<>$G9,"按分不一致 ","")&IF(O9="※未登録","科目未登録 ","")&IF(OR($H9="",ISERROR(MATCH($H9,{1,2,3,4,5,6,7,8},0))),"経費区分? ","")&IF($I9="","状態未設定 ","")&IF(AND(OR($I9="確認済",$I9="未確認"),$B9="月例",OR($C9="",$C9<DATE(年度+2018,4,1),$C9>DATE(年度+2019,3,31))),"年度外の日付 ","")&IF(AND(OR($I9="確認済",$I9="未確認"),O9="対象外"),"対象外の科目 ",""))) | R9: 月例!9
A10: 6 | B10: 月例 | C10: 46132 | D10: 委託費 | F10: レセプト電子データ提供料（1月診療分） | G10: 60235 | H10: 2 | I10: 確認済 | J10: =IF($G10="","",IF($H10=1,$G10-ROUND($G10*10/23,0)-2*ROUND($G10/23,0),IF($H10=2,$G10,0))) -> 60235 | K10: =IF($G10="","",IF($H10=1,ROUND($G10*10/23,0),IF($H10=3,$G10-2*ROUND($G10/12,0),IF($H10=4,$G10,IF(OR($H10=5,$H10=7),ROUND($G10*10/11,0),0))))) -> 0 | L10: =IF($G10="","",IF($H10=1,ROUND($G10/23,0),IF($H10=3,ROUND($G10/12,0),IF($H10=5,$G10-ROUND($G10*10/11,0),IF($H10=8,$G10,0))))) -> 0 | M10: =IF($G10="","",IF($H10=1,ROUND($G10/23,0),IF($H10=3,ROUND($G10/12,0),IF($H10=6,$G10,IF($H10=7,$G10-ROUND($G10*10/11,0),0))))) -> 0 | N10: =IF($G10="","",K10+L10+M10) -> 0 | O10: =IF($G10="","",IFERROR(VLOOKUP($D10&"|"&$E10,科目表!$A$5:$B$200,2,FALSE),"※未登録")) -> 委託費 | P10: =IF(OR($G10="",$C10=""),"",IF($B10="決算整理",13,MOD(MONTH($C10)-4,12)+1)) -> 1 | Q10: =IF($G10="","",TRIM(IF(J10+K10+L10+M10<>$G10,"按分不一致 ","")&IF(O10="※未登録","科目未登録 ","")&IF(OR($H10="",ISERROR(MATCH($H10,{1,2,3,4,5,6,7,8},0))),"経費区分? ","")&IF($I10="","状態未設定 ","")&IF(AND(OR($I10="確認済",$I10="未確認"),$B10="月例",OR($C10="",$C10<DATE(年度+2018,4,1),$C10>DATE(年度+2019,3,31))),"年度外の日付 ","")&IF(AND(OR($I10="確認済",$I10="未確認"),O10="対象外"),"対象外の科目 ",""))) | R10: 月例!10
A11: 7 | B11: 月例 | C11: 43941 | D11: 事務費 | E11: 雑費 | F11: 電子証明書発行・更新料（令和2年4月請求） | G11: 4000 | H11: 2 | I11: 昨年実績 | J11: =IF($G11="","",IF($H11=1,$G11-ROUND($G11*10/23,0)-2*ROUND($G11/23,0),IF($H11=2,$G11,0))) -> 4000 | K11: =IF($G11="","",IF($H11=1,ROUND($G11*10/23,0),IF($H11=3,$G11-2*ROUND($G11/12,0),IF($H11=4,$G11,IF(OR($H11=5,$H11=7),ROUND($G11*10/11,0),0))))) -> 0 | L11: =IF($G11="","",IF($H11=1,ROUND($G11/23,0),IF($H11=3,ROUND($G11/12,0),IF($H11=5,$G11-ROUND($G11*10/11,0),IF($H11=8,$G11,0))))) -> 0 | M11: =IF($G11="","",IF($H11=1,ROUND($G11/23,0),IF($H11=3,ROUND($G11/12,0),IF($H11=6,$G11,IF($H11=7,$G11-ROUND($G11*10/11,0),0))))) -> 0 | N11: =IF($G11="","",K11+L11+M11) -> 0 | O11: =IF($G11="","",IFERROR(VLOOKUP($D11&"|"&$E11,科目表!$A$5:$B$200,2,FALSE),"※未登録")) -> 事務費・雑費 | P11: =IF(OR($G11="",$C11=""),"",IF($B11="決算整理",13,MOD(MONTH($C11)-4,12)+1)) -> 1 | Q11: =IF($G11="","",TRIM(IF(J11+K11+L11+M11<>$G11,"按分不一致 ","")&IF(O11="※未登録","科目未登録 ","")&IF(OR($H11="",ISERROR(MATCH($H11,{1,2,3,4,5,6,7,8},0))),"経費区分? ","")&IF($I11="","状態未設定 ","")&IF(AND(OR($I11="確認済",$I11="未確認"),$B11="月例",OR($C11="",$C11<DATE(年度+2018,4,1),$C11>DATE(年度+2019,3,31))),"年度外の日付 ","")&IF(AND(OR($I11="確認済",$I11="未確認"),O11="対象外"),"対象外の科目 ",""))) | R11: 月例!11
A12: 8 | B12: 月例 | C12: 46150 | D12: 負担金 | F12: 広島県社会保険協会年会費(短期) | G12: 780 | H12: 2 | I12: 確認済 | J12: =IF($G12="","",IF($H12=1,$G12-ROUND($G12*10/23,0)-2*ROUND($G12/23,0),IF($H12=2,$G12,0))) -> 780 | K12: =IF($G12="","",IF($H12=1,ROUND($G12*10/23,0),IF($H12=3,$G12-2*ROUND($G12/12,0),IF($H12=4,$G12,IF(OR($H12=5,$H12=7),ROUND($G12*10/11,0),0))))) -> 0 | L12: =IF($G12="","",IF($H12=1,ROUND($G12/23,0),IF($H12=3,ROUND($G12/12,0),IF($H12=5,$G12-ROUND($G12*10/11,0),IF($H12=8,$G12,0))))) -> 0 | M12: =IF($G12="","",IF($H12=1,ROUND($G12/23,0),IF($H12=3,ROUND($G12/12,0),IF($H12=6,$G12,IF($H12=7,$G12-ROUND($G12*10/11,0),0))))) -> 0 | N12: =IF($G12="","",K12+L12+M12) -> 0 | O12: =IF($G12="","",IFERROR(VLOOKUP($D12&"|"&$E12,科目表!$A$5:$B$200,2,FALSE),"※未登録")) -> 県社保協会費 | P12: =IF(OR($G12="",$C12=""),"",IF($B12="決算整理",13,MOD(MONTH($C12)-4,12)+1)) -> 2 | Q12: =IF($G12="","",TRIM(IF(J12+K12+L12+M12<>$G12,"按分不一致 ","")&IF(O12="※未登録","科目未登録 ","")&IF(OR($H12="",ISERROR(MATCH($H12,{1,2,3,4,5,6,7,8},0))),"経費区分? ","")&IF($I12="","状態未設定 ","")&IF(AND(OR($I12="確認済",$I12="未確認"),$B12="月例",OR($C12="",$C12<DATE(年度+2018,4,1),$C12>DATE(年度+2019,3,31))),"年度外の日付 ","")&IF(AND(OR($I12="確認済",$I12="未確認"),O12="対象外"),"対象外の科目 ",""))) | R12: 月例!12
A13: 9 | B13: 月例 | C13: 46150 | D13: 負担金 | F13: 広島県社会保険協会年会費(長期) | G13: 520 | H13: 3 | I13: 確認済 | J13: =IF($G13="","",IF($H13=1,$G13-ROUND($G13*10/23,0)-2*ROUND($G13/23,0),IF($H13=2,$G13,0))) -> 0 | K13: =IF($G13="","",IF($H13=1,ROUND($G13*10/23,0),IF($H13=3,$G13-2*ROUND($G13/12,0),IF($H13=4,$G13,IF(OR($H13=5,$H13=7),ROUND($G13*10/11,0),0))))) -> 434 | L13: =IF($G13="","",IF($H13=1,ROUND($G13/23,0),IF($H13=3,ROUND($G13/12,0),IF($H13=5,$G13-ROUND($G13*10/11,0),IF($H13=8,$G13,0))))) -> 43 | M13: =IF($G13="","",IF($H13=1,ROUND($G13/23,0),IF($H13=3,ROUND($G13/12,0),IF($H13=6,$G13,IF($H13=7,$G13-ROUND($G13*10/11,0),0))))) -> 43 | N13: =IF($G13="","",K13+L13+M13) -> 520 | O13: =IF($G13="","",IFERROR(VLOOKUP($D13&"|"&$E13,科目表!$A$5:$B$200,2,FALSE),"※未登録")) -> 県社保協会費 | P13: =IF(OR($G13="",$C13=""),"",IF($B13="決算整理",13,MOD(MONTH($C13)-4,12)+1)) -> 2 | Q13: =IF($G13="","",TRIM(IF(J13+K13+L13+M13<>$G13,"按分不一致 ","")&IF(O13="※未登録","科目未登録 ","")&IF(OR($H13="",ISERROR(MATCH($H13,{1,2,3,4,5,6,7,8},0))),"経費区分? ","")&IF($I13="","状態未設定 ","")&IF(AND(OR($I13="確認済",$I13="未確認"),$B13="月例",OR($C13="",$C13<DATE(年度+2018,4,1),$C13>DATE(年度+2019,3,31))),"年度外の日付 ","")&IF(AND(OR($I13="確認済",$I13="未確認"),O13="対象外"),"対象外の科目 ",""))) | R13: 月例!13
A14: 10 | B14: 月例 | C14: 46133 | D14: 職員給与 | E14: 非常勤職員手当 | F14: ４月分給与（長期分） | G14: 380800 | H14: 3 | I14: 確認済 | J14: =IF($G14="","",IF($H14=1,$G14-ROUND($G14*10/23,0)-2*ROUND($G14/23,0),IF($H14=2,$G14,0))) -> 0 | K14: =IF($G14="","",IF($H14=1,ROUND($G14*10/23,0),IF($H14=3,$G14-2*ROUND($G14/12,0),IF($H14=4,$G14,IF(OR($H14=5,$H14=7),ROUND($G14*10/11,0),0))))) -> 317334 | L14: =IF($G14="","",IF($H14=1,ROUND($G14/23,0),IF($H14=3,ROUND($G14/12,0),IF($H14=5,$G14-ROUND($G14*10/11,0),IF($H14=8,$G14,0))))) -> 31733 | M14: =IF($G14="","",IF($H14=1,ROUND($G14/23,0),IF($H14=3,ROUND($G14/12,0),IF($H14=6,$G14,IF($H14=7,$G14-ROUND($G14*10/11,0),0))))) -> 31733 | N14: =IF($G14="","",K14+L14+M14) -> 380800 | O14: =IF($G14="","",IFERROR(VLOOKUP($D14&"|"&$E14,科目表!$A$5:$B$200,2,FALSE),"※未登録")) -> 非常勤職員手当 | P14: =IF(OR($G14="",$C14=""),"",IF($B14="決算整理",13,MOD(MONTH($C14)-4,12)+1)) -> 1 | Q14: =IF($G14="","",TRIM(IF(J14+K14+L14+M14<>$G14,"按分不一致 ","")&IF(O14="※未登録","科目未登録 ","")&IF(OR($H14="",ISERROR(MATCH($H14,{1,2,3,4,5,6,7,8},0))),"経費区分? ","")&IF($I14="","状態未設定 ","")&IF(AND(OR($I14="確認済",$I14="未確認"),$B14="月例",OR($C14="",$C14<DATE(年度+2018,4,1),$C14>DATE(年度+2019,3,31))),"年度外の日付 ","")&IF(AND(OR($I14="確認済",$I14="未確認"),O14="対象外"),"対象外の科目 ",""))) | R14: 月例!14
A15: 11 | B15: 月例 | C15: 46133 | D15: 職員給与 | E15: 非常勤職員手当 | F15: ４月分給与（短期分）3月時間外除く | G15: 317340 | H15: 2 | I15: 確認済 | J15: =IF($G15="","",IF($H15=1,$G15-ROUND($G15*10/23,0)-2*ROUND($G15/23,0),IF($H15=2,$G15,0))) -> 317340 | K15: =IF($G15="","",IF($H15=1,ROUND($G15*10/23,0),IF($H15=3,$G15-2*ROUND($G15/12,0),IF($H15=4,$G15,IF(OR($H15=5,$H15=7),ROUND($G15*10/11,0),0))))) -> 0 | L15: =IF($G15="","",IF($H15=1,ROUND($G15/23,0),IF($H15=3,ROUND($G15/12,0),IF($H15=5,$G15-ROUND($G15*10/11,0),IF($H15=8,$G15,0))))) -> 0 | M15: =IF($G15="","",IF($H15=1,ROUND($G15/23,0),IF($H15=3,ROUND($G15/12,0),IF($H15=6,$G15,IF($H15=7,$G15-ROUND($G15*10/11,0),0))))) -> 0 | N15: =IF($G15="","",K15+L15+M15) -> 0 | O15: =IF($G15="","",IFERROR(VLOOKUP($D15&"|"&$E15,科目表!$A$5:$B$200,2,FALSE),"※未登録")) -> 非常勤職員手当 | P15: =IF(OR($G15="",$C15=""),"",IF($B15="決算整理",13,MOD(MONTH($C15)-4,12)+1)) -> 1 | Q15: =IF($G15="","",TRIM(IF(J15+K15+L15+M15<>$G15,"按分不一致 ","")&IF(O15="※未登録","科目未登録 ","")&IF(OR($H15="",ISERROR(MATCH($H15,{1,2,3,4,5,6,7,8},0))),"経費区分? ","")&IF($I15="","状態未設定 ","")&IF(AND(OR($I15="確認済",$I15="未確認"),$B15="月例",OR($C15="",$C15<DATE(年度+2018,4,1),$C15>DATE(年度+2019,3,31))),"年度外の日付 ","")&IF(AND(OR($I15="確認済",$I15="未確認"),O15="対象外"),"対象外の科目 ",""))) | R15: 月例!15
A16: 12 | B16: 月例 | C16: 46133 | D16: 負担金 | E16: 互助会費 | F16: 助成金（４月長期分） | G16: 466 | H16: 3 | I16: 確認済 | J16: =IF($G16="","",IF($H16=1,$G16-ROUND($G16*10/23,0)-2*ROUND($G16/23,0),IF($H16=2,$G16,0))) -> 0 | K16: =IF($G16="","",IF($H16=1,ROUND($G16*10/23,0),IF($H16=3,$G16-2*ROUND($G16/12,0),IF($H16=4,$G16,IF(OR($H16=5,$H16=7),ROUND($G16*10/11,0),0))))) -> 388 | L16: =IF($G16="","",IF($H16=1,ROUND($G16/23,0),IF($H16=3,ROUND($G16/12,0),IF($H16=5,$G16-ROUND($G16*10/11,0),IF($H16=8,$G16,0))))) -> 39 | M16: =IF($G16="","",IF($H16=1,ROUND($G16/23,0),IF($H16=3,ROUND($G16/12,0),IF($H16=6,$G16,IF($H16=7,$G16-ROUND($G16*10/11,0),0))))) -> 39 | N16: =IF($G16="","",K16+L16+M16) -> 466 | O16: =IF($G16="","",IFERROR(VLOOKUP($D16&"|"&$E16,科目表!$A$5:$B$200,2,FALSE),"※未登録")) -> 互助会費 | P16: =IF(OR($G16="",$C16=""),"",IF($B16="決算整理",13,MOD(MONTH($C16)-4,12)+1)) -> 1 | Q16: =IF($G16="","",TRIM(IF(J16+K16+L16+M16<>$G16,"按分不一致 ","")&IF(O16="※未登録","科目未登録 ","")&IF(OR($H16="",ISERROR(MATCH($H16,{1,2,3,4,5,6,7,8},0))),"経費区分? ","")&IF($I16="","状態未設定 ","")&IF(AND(OR($I16="確認済",$I16="未確認"),$B16="月例",OR($C16="",$C16<DATE(年度+2018,4,1),$C16>DATE(年度+2019,3,31))),"年度外の日付 ","")&IF(AND(OR($I16="確認済",$I16="未確認"),O16="対象外"),"対象外の科目 ",""))) | R16: 月例!16
A17: 13 | B17: 月例 | C17: 46133 | D17: 負担金 | E17: 互助会費 | F17: 助成金（４月短期分） | G17: 240 | H17: 2 | I17: 確認済 | J17: =IF($G17="","",IF($H17=1,$G17-ROUND($G17*10/23,0)-2*ROUND($G17/23,0),IF($H17=2,$G17,0))) -> 240 | K17: =IF($G17="","",IF($H17=1,ROUND($G17*10/23,0),IF($H17=3,$G17-2*ROUND($G17/12,0),IF($H17=4,$G17,IF(OR($H17=5,$H17=7),ROUND($G17*10/11,0),0))))) -> 0 | L17: =IF($G17="","",IF($H17=1,ROUND($G17/23,0),IF($H17=3,ROUND($G17/12,0),IF($H17=5,$G17-ROUND($G17*10/11,0),IF($H17=8,$G17,0))))) -> 0 | M17: =IF($G17="","",IF($H17=1,ROUND($G17/23,0),IF($H17=3,ROUND($G17/12,0),IF($H17=6,$G17,IF($H17=7,$G17-ROUND($G17*10/11,0),0))))) -> 0 | N17: =IF($G17="","",K17+L17+M17) -> 0 | O17: =IF($G17="","",IFERROR(VLOOKUP($D17&"|"&$E17,科目表!$A$5:$B$200,2,FALSE),"※未登録")) -> 互助会費 | P17: =IF(OR($G17="",$C17=""),"",IF($B17="決算整理",13,MOD(MONTH($C17)-4,12)+1)) -> 1 | Q17: =IF($G17="","",TRIM(IF(J17+K17+L17+M17<>$G17,"按分不一致 ","")&IF(O17="※未登録","科目未登録 ","")&IF(OR($H17="",ISERROR(MATCH($H17,{1,2,3,4,5,6,7,8},0))),"経費区分? ","")&IF($I17="","状態未設定 ","")&IF(AND(OR($I17="確認済",$I17="未確認"),$B17="月例",OR($C17="",$C17<DATE(年度+2018,4,1),$C17>DATE(年度+2019,3,31))),"年度外の日付 ","")&IF(AND(OR($I17="確認済",$I17="未確認"),O17="対象外"),"対象外の科目 ",""))) | R17: 月例!17
A18: 14 | B18: 月例 | C18: 45044 | D18: 委託費 | F18: 個人番号管理システムシンクライアント（４～１０月） | G18: 24486 | H18: 2 | I18: 昨年実績 | J18: =IF($G18="","",IF($H18=1,$G18-ROUND($G18*10/23,0)-2*ROUND($G18/23,0),IF($H18=2,$G18,0))) -> 24486 | K18: =IF($G18="","",IF($H18=1,ROUND($G18*10/23,0),IF($H18=3,$G18-2*ROUND($G18/12,0),IF($H18=4,$G18,IF(OR($H18=5,$H18=7),ROUND($G18*10/11,0),0))))) -> 0 | L18: =IF($G18="","",IF($H18=1,ROUND($G18/23,0),IF($H18=3,ROUND($G18/12,0),IF($H18=5,$G18-ROUND($G18*10/11,0),IF($H18=8,$G18,0))))) -> 0 | M18: =IF($G18="","",IF($H18=1,ROUND($G18/23,0),IF($H18=3,ROUND($G18/12,0),IF($H18=6,$G18,IF($H18=7,$G18-ROUND($G18*10/11,0),0))))) -> 0 | N18: =IF($G18="","",K18+L18+M18) -> 0 | O18: =IF($G18="","",IFERROR(VLOOKUP($D18&"|"&$E18,科目表!$A$5:$B$200,2,FALSE),"※未登録")) -> 委託費 | P18: =IF(OR($G18="",$C18=""),"",IF($B18="決算整理",13,MOD(MONTH($C18)-4,12)+1)) -> 1 | Q18: =IF($G18="","",TRIM(IF(J18+K18+L18+M18<>$G18,"按分不一致 ","")&IF(O18="※未登録","科目未登録 ","")&IF(OR($H18="",ISERROR(MATCH($H18,{1,2,3,4,5,6,7,8},0))),"経費区分? ","")&IF($I18="","状態未設定 ","")&IF(AND(OR($I18="確認済",$I18="未確認"),$B18="月例",OR($C18="",$C18<DATE(年度+2018,4,1),$C18>DATE(年度+2019,3,31))),"年度外の日付 ","")&IF(AND(OR($I18="確認済",$I18="未確認"),O18="対象外"),"対象外の科目 ",""))) | R18: 月例!18
A19: 15 | B19: 月例 | C19: 45807 | D19: 事務費 | E19: 図書印刷費 | F19: 窓付封筒 １，０００枚 | G19: 49500 | H19: 2 | I19: 昨年実績 | J19: =IF($G19="","",IF($H19=1,$G19-ROUND($G19*10/23,0)-2*ROUND($G19/23,0),IF($H19=2,$G19,0))) -> 49500 | K19: =IF($G19="","",IF($H19=1,ROUND($G19*10/23,0),IF($H19=3,$G19-2*ROUND($G19/12,0),IF($H19=4,$G19,IF(OR($H19=5,$H19=7),ROUND($G19*10/11,0),0))))) -> 0 | L19: =IF($G19="","",IF($H19=1,ROUND($G19/23,0),IF($H19=3,ROUND($G19/12,0),IF($H19=5,$G19-ROUND($G19*10/11,0),IF($H19=8,$G19,0))))) -> 0 | M19: =IF($G19="","",IF($H19=1,ROUND($G19/23,0),IF($H19=3,ROUND($G19/12,0),IF($H19=6,$G19,IF($H19=7,$G19-ROUND($G19*10/11,0),0))))) -> 0 | N19: =IF($G19="","",K19+L19+M19) -> 0 | O19: =IF($G19="","",IFERROR(VLOOKUP($D19&"|"&$E19,科目表!$A$5:$B$200,2,FALSE),"※未登録")) -> 図書印刷費 | P19: =IF(OR($G19="",$C19=""),"",IF($B19="決算整理",13,MOD(MONTH($C19)-4,12)+1)) -> 2 | Q19: =IF($G19="","",TRIM(IF(J19+K19+L19+M19<>$G19,"按分不一致 ","")&IF(O19="※未登録","科目未登録 ","")&IF(OR($H19="",ISERROR(MATCH($H19,{1,2,3,4,5,6,7,8},0))),"経費区分? ","")&IF($I19="","状態未設定 ","")&IF(AND(OR($I19="確認済",$I19="未確認"),$B19="月例",OR($C19="",$C19<DATE(年度+2018,4,1),$C19>DATE(年度+2019,3,31))),"年度外の日付 ","")&IF(AND(OR($I19="確認済",$I19="未確認"),O19="対象外"),"対象外の科目 ",""))) | R19: 月例!19
A20: 16 | B20: 月例 | C20: 45061 | D20: 事務費 | E20: 図書印刷費 | F20: 定年延長と共済組合制度 ３０部 | G20: 2970 | H20: 3 | I20: 昨年実績 | J20: =IF($G20="","",IF($H20=1,$G20-ROUND($G20*10/23,0)-2*ROUND($G20/23,0),IF($H20=2,$G20,0))) -> 0 | K20: =IF($G20="","",IF($H20=1,ROUND($G20*10/23,0),IF($H20=3,$G20-2*ROUND($G20/12,0),IF($H20=4,$G20,IF(OR($H20=5,$H20=7),ROUND($G20*10/11,0),0))))) -> 2474 | L20: =IF($G20="","",IF($H20=1,ROUND($G20/23,0),IF($H20=3,ROUND($G20/12,0),IF($H20=5,$G20-ROUND($G20*10/11,0),IF($H20=8,$G20,0))))) -> 248 | M20: =IF($G20="","",IF($H20=1,ROUND($G20/23,0),IF($H20=3,ROUND($G20/12,0),IF($H20=6,$G20,IF($H20=7,$G20-ROUND($G20*10/11,0),0))))) -> 248 | N20: =IF($G20="","",K20+L20+M20) -> 2970 | O20: =IF($G20="","",IFERROR(VLOOKUP($D20&"|"&$E20,科目表!$A$5:$B$200,2,FALSE),"※未登録")) -> 図書印刷費 | P20: =IF(OR($G20="",$C20=""),"",IF($B20="決算整理",13,MOD(MONTH($C20)-4,12)+1)) -> 2 | Q20: =IF($G20="","",TRIM(IF(J20+K20+L20+M20<>$G20,"按分不一致 ","")&IF(O20="※未登録","科目未登録 ","")&IF(OR($H20="",ISERROR(MATCH($H20,{1,2,3,4,5,6,7,8},0))),"経費区分? ","")&IF($I20="","状態未設定 ","")&IF(AND(OR($I20="確認済",$I20="未確認"),$B20="月例",OR($C20="",$C20<DATE(年度+2018,4,1),$C20>DATE(年度+2019,3,31))),"年度外の日付 ","")&IF(AND(OR($I20="確認済",$I20="未確認"),O20="対象外"),"対象外の科目 ",""))) | R20: 月例!20
A21: 17 | B21: 月例 | C21: 45477 | D21: 事務費 | E21: 図書印刷費 | F21: 組合員原票（Ａ４）８００部 ほか | G21: 133650 | H21: 3 | I21: 昨年実績 | J21: =IF($G21="","",IF($H21=1,$G21-ROUND($G21*10/23,0)-2*ROUND($G21/23,0),IF($H21=2,$G21,0))) -> 0 | K21: =IF($G21="","",IF($H21=1,ROUND($G21*10/23,0),IF($H21=3,$G21-2*ROUND($G21/12,0),IF($H21=4,$G21,IF(OR($H21=5,$H21=7),ROUND($G21*10/11,0),0))))) -> 111374 | L21: =IF($G21="","",IF($H21=1,ROUND($G21/23,0),IF($H21=3,ROUND($G21/12,0),IF($H21=5,$G21-ROUND($G21*10/11,0),IF($H21=8,$G21,0))))) -> 11138 | M21: =IF($G21="","",IF($H21=1,ROUND($G21/23,0),IF($H21=3,ROUND($G21/12,0),IF($H21=6,$G21,IF($H21=7,$G21-ROUND($G21*10/11,0),0))))) -> 11138 | N21: =IF($G21="","",K21+L21+M21) -> 133650 | O21: =IF($G21="","",IFERROR(VLOOKUP($D21&"|"&$E21,科目表!$A$5:$B$200,2,FALSE),"※未登録")) -> 図書印刷費 | P21: =IF(OR($G21="",$C21=""),"",IF($B21="決算整理",13,MOD(MONTH($C21)-4,12)+1)) -> 4 | Q21: =IF($G21="","",TRIM(IF(J21+K21+L21+M21<>$G21,"按分不一致 ","")&IF(O21="※未登録","科目未登録 ","")&IF(OR($H21="",ISERROR(MATCH($H21,{1,2,3,4,5,6,7,8},0))),"経費区分? ","")&IF($I21="","状態未設定 ","")&IF(AND(OR($I21="確認済",$I21="未確認"),$B21="月例",OR($C21="",$C21<DATE(年度+2018,4,1),$C21>DATE(年度+2019,3,31))),"年度外の日付 ","")&IF(AND(OR($I21="確認済",$I21="未確認"),O21="対象外"),"対象外の科目 ",""))) | R21: 月例!21
A22: 18 | B22: 月例 | C22: 44377 | D22: 事務費 | E22: 事務用消耗品費 | F22: 鋳造ゴム印 ３号以下214字 他 | G22: 9733 | H22: 3 | I22: 昨年実績 | J22: =IF($G22="","",IF($H22=1,$G22-ROUND($G22*10/23,0)-2*ROUND($G22/23,0),IF($H22=2,$G22,0))) -> 0 | K22: =IF($G22="","",IF($H22=1,ROUND($G22*10/23,0),IF($H22=3,$G22-2*ROUND($G22/12,0),IF($H22=4,$G22,IF(OR($H22=5,$H22=7),ROUND($G22*10/11,0),0))))) -> 8111 | L22: =IF($G22="","",IF($H22=1,ROUND($G22/23,0),IF($H22=3,ROUND($G22/12,0),IF($H22=5,$G22-ROUND($G22*10/11,0),IF($H22=8,$G22,0))))) -> 811 | M22: =IF($G22="","",IF($H22=1,ROUND($G22/23,0),IF($H22=3,ROUND($G22/12,0),IF($H22=6,$G22,IF($H22=7,$G22-ROUND($G22*10/11,0),0))))) -> 811 | N22: =IF($G22="","",K22+L22+M22) -> 9733 | O22: =IF($G22="","",IFERROR(VLOOKUP($D22&"|"&$E22,科目表!$A$5:$B$200,2,FALSE),"※未登録")) -> 事務用消耗品費 | P22: =IF(OR($G22="",$C22=""),"",IF($B22="決算整理",13,MOD(MONTH($C22)-4,12)+1)) -> 3 | Q22: =IF($G22="","",TRIM(IF(J22+K22+L22+M22<>$G22,"按分不一致 ","")&IF(O22="※未登録","科目未登録 ","")&IF(OR($H22="",ISERROR(MATCH($H22,{1,2,3,4,5,6,7,8},0))),"経費区分? ","")&IF($I22="","状態未設定 ","")&IF(AND(OR($I22="確認済",$I22="未確認"),$B22="月例",OR($C22="",$C22<DATE(年度+2018,4,1),$C22>DATE(年度+2019,3,31))),"年度外の日付 ","")&IF(AND(OR($I22="確認済",$I22="未確認"),O22="対象外"),"対象外の科目 ",""))) | R22: 月例!22
A23: 19 | B23: 月例 | C23: 46171 | D23: 事務費 | E23: 事務用消耗品費 | F23: ラベル用紙 LBP-F7656-100N ２冊 他 | G23: 43890 | H23: 2 | I23: 確認済 | J23: =IF($G23="","",IF($H23=1,$G23-ROUND($G23*10/23,0)-2*ROUND($G23/23,0),IF($H23=2,$G23,0))) -> 43890 | K23: =IF($G23="","",IF($H23=1,ROUND($G23*10/23,0),IF($H23=3,$G23-2*ROUND($G23/12,0),IF($H23=4,$G23,IF(OR($H23=5,$H23=7),ROUND($G23*10/11,0),0))))) -> 0 | L23: =IF($G23="","",IF($H23=1,ROUND($G23/23,0),IF($H23=3,ROUND($G23/12,0),IF($H23=5,$G23-ROUND($G23*10/11,0),IF($H23=8,$G23,0))))) -> 0 | M23: =IF($G23="","",IF($H23=1,ROUND($G23/23,0),IF($H23=3,ROUND($G23/12,0),IF($H23=6,$G23,IF($H23=7,$G23-ROUND($G23*10/11,0),0))))) -> 0 | N23: =IF($G23="","",K23+L23+M23) -> 0 | O23: =IF($G23="","",IFERROR(VLOOKUP($D23&"|"&$E23,科目表!$A$5:$B$200,2,FALSE),"※未登録")) -> 事務用消耗品費 | P23: =IF(OR($G23="",$C23=""),"",IF($B23="決算整理",13,MOD(MONTH($C23)-4,12)+1)) -> 2 | Q23: =IF($G23="","",TRIM(IF(J23+K23+L23+M23<>$G23,"按分不一致 ","")&IF(O23="※未登録","科目未登録 ","")&IF(OR($H23="",ISERROR(MATCH($H23,{1,2,3,4,5,6,7,8},0))),"経費区分? ","")&IF($I23="","状態未設定 ","")&IF(AND(OR($I23="確認済",$I23="未確認"),$B23="月例",OR($C23="",$C23<DATE(年度+2018,4,1),$C23>DATE(年度+2019,3,31))),"年度外の日付 ","")&IF(AND(OR($I23="確認済",$I23="未確認"),O23="対象外"),"対象外の科目 ",""))) | R23: 月例!23
A24: 20 | B24: 月例 | C24: 46154 | D24: 事務費負担金払込金 | F24: ４月分事務費負担金払込金と連合会交付金との相殺 | G24: 5366000 | H24: 5 | I24: 確認済 | J24: =IF($G24="","",IF($H24=1,$G24-ROUND($G24*10/23,0)-2*ROUND($G24/23,0),IF($H24=2,$G24,0))) -> 0 | K24: =IF($G24="","",IF($H24=1,ROUND($G24*10/23,0),IF($H24=3,$G24-2*ROUND($G24/12,0),IF($H24=4,$G24,IF(OR($H24=5,$H24=7),ROUND($G24*10/11,0),0))))) -> 4878182 | L24: =IF($G24="","",IF($H24=1,ROUND($G24/23,0),IF($H24=3,ROUND($G24/12,0),IF($H24=5,$G24-ROUND($G24*10/11,0),IF($H24=8,$G24,0))))) -> 487818 | M24: =IF($G24="","",IF($H24=1,ROUND($G24/23,0),IF($H24=3,ROUND($G24/12,0),IF($H24=6,$G24,IF($H24=7,$G24-ROUND($G24*10/11,0),0))))) -> 0 | N24: =IF($G24="","",K24+L24+M24) -> 5366000 | O24: =IF($G24="","",IFERROR(VLOOKUP($D24&"|"&$E24,科目表!$A$5:$B$200,2,FALSE),"※未登録")) -> 事務費負担金払込金 | P24: =IF(OR($G24="",$C24=""),"",IF($B24="決算整理",13,MOD(MONTH($C24)-4,12)+1)) -> 2 | Q24: =IF($G24="","",TRIM(IF(J24+K24+L24+M24<>$G24,"按分不一致 ","")&IF(O24="※未登録","科目未登録 ","")&IF(OR($H24="",ISERROR(MATCH($H24,{1,2,3,4,5,6,7,8},0))),"経費区分? ","")&IF($I24="","状態未設定 ","")&IF(AND(OR($I24="確認済",$I24="未確認"),$B24="月例",OR($C24="",$C24<DATE(年度+2018,4,1),$C24>DATE(年度+2019,3,31))),"年度外の日付 ","")&IF(AND(OR($I24="確認済",$I24="未確認"),O24="対象外"),"対象外の科目 ",""))) | R24: 月例!24
A25: 21 | B25: 月例 | C25: 46139 | D25: 負担金 | E25: 負担金 | F25: 共済短期・介護・子ども子育て負担金（4月月例分）長期 | G25: 22035 | H25: 3 | I25: 確認済 | J25: =IF($G25="","",IF($H25=1,$G25-ROUND($G25*10/23,0)-2*ROUND($G25/23,0),IF($H25=2,$G25,0))) -> 0 | K25: =IF($G25="","",IF($H25=1,ROUND($G25*10/23,0),IF($H25=3,$G25-2*ROUND($G25/12,0),IF($H25=4,$G25,IF(OR($H25=5,$H25=7),ROUND($G25*10/11,0),0))))) -> 18363 | L25: =IF($G25="","",IF($H25=1,ROUND($G25/23,0),IF($H25=3,ROUND($G25/12,0),IF($H25=5,$G25-ROUND($G25*10/11,0),IF($H25=8,$G25,0))))) -> 1836 | M25: =IF($G25="","",IF($H25=1,ROUND($G25/23,0),IF($H25=3,ROUND($G25/12,0),IF($H25=6,$G25,IF($H25=7,$G25-ROUND($G25*10/11,0),0))))) -> 1836 | N25: =IF($G25="","",K25+L25+M25) -> 22035 | O25: =IF($G25="","",IFERROR(VLOOKUP($D25&"|"&$E25,科目表!$A$5:$B$200,2,FALSE),"※未登録")) -> 共済負担金等 | P25: =IF(OR($G25="",$C25=""),"",IF($B25="決算整理",13,MOD(MONTH($C25)-4,12)+1)) -> 1 | Q25: =IF($G25="","",TRIM(IF(J25+K25+L25+M25<>$G25,"按分不一致 ","")&IF(O25="※未登録","科目未登録 ","")&IF(OR($H25="",ISERROR(MATCH($H25,{1,2,3,4,5,6,7,8},0))),"経費区分? ","")&IF($I25="","状態未設定 ","")&IF(AND(OR($I25="確認済",$I25="未確認"),$B25="月例",OR($C25="",$C25<DATE(年度+2018,4,1),$C25>DATE(年度+2019,3,31))),"年度外の日付 ","")&IF(AND(OR($I25="確認済",$I25="未確認"),O25="対象外"),"対象外の科目 ",""))) | R25: 月例!25
A26: 22 | B26: 月例 | C26: 46139 | D26: 負担金 | E26: 負担金 | F26: 共済短期・介護・子ども子育て負担金（4月月例分）短期 | G26: 37074 | H26: 2 | I26: 確認済 | J26: =IF($G26="","",IF($H26=1,$G26-ROUND($G26*10/23,0)-2*ROUND($G26/23,0),IF($H26=2,$G26,0))) -> 37074 | K26: =IF($G26="","",IF($H26=1,ROUND($G26*10/23,0),IF($H26=3,$G26-2*ROUND($G26/12,0),IF($H26=4,$G26,IF(OR($H26=5,$H26=7),ROUND($G26*10/11,0),0))))) -> 0 | L26: =IF($G26="","",IF($H26=1,ROUND($G26/23,0),IF($H26=3,ROUND($G26/12,0),IF($H26=5,$G26-ROUND($G26*10/11,0),IF($H26=8,$G26,0))))) -> 0 | M26: =IF($G26="","",IF($H26=1,ROUND($G26/23,0),IF($H26=3,ROUND($G26/12,0),IF($H26=6,$G26,IF($H26=7,$G26-ROUND($G26*10/11,0),0))))) -> 0 | N26: =IF($G26="","",K26+L26+M26) -> 0 | O26: =IF($G26="","",IFERROR(VLOOKUP($D26&"|"&$E26,科目表!$A$5:$B$200,2,FALSE),"※未登録")) -> 共済負担金等 | P26: =IF(OR($G26="",$C26=""),"",IF($B26="決算整理",13,MOD(MONTH($C26)-4,12)+1)) -> 1 | Q26: =IF($G26="","",TRIM(IF(J26+K26+L26+M26<>$G26,"按分不一致 ","")&IF(O26="※未登録","科目未登録 ","")&IF(OR($H26="",ISERROR(MATCH($H26,{1,2,3,4,5,6,7,8},0))),"経費区分? ","")&IF($I26="","状態未設定 ","")&IF(AND(OR($I26="確認済",$I26="未確認"),$B26="月例",OR($C26="",$C26<DATE(年度+2018,4,1),$C26>DATE(年度+2019,3,31))),"年度外の日付 ","")&IF(AND(OR($I26="確認済",$I26="未確認"),O26="対象外"),"対象外の科目 ",""))) | R26: 月例!26
A27: 23 | B27: 月例 | C27: 46153 | D27: 事務費 | E27: 送金料 | F27: 振込手数料（広銀）４月分 長期分 | G27: 18493 | H27: 3 | I27: 確認済 | J27: =IF($G27="","",IF($H27=1,$G27-ROUND($G27*10/23,0)-2*ROUND($G27/23,0),IF($H27=2,$G27,0))) -> 0 | K27: =IF($G27="","",IF($H27=1,ROUND($G27*10/23,0),IF($H27=3,$G27-2*ROUND($G27/12,0),IF($H27=4,$G27,IF(OR($H27=5,$H27=7),ROUND($G27*10/11,0),0))))) -> 15411 | L27: =IF($G27="","",IF($H27=1,ROUND($G27/23,0),IF($H27=3,ROUND($G27/12,0),IF($H27=5,$G27-ROUND($G27*10/11,0),IF($H27=8,$G27,0))))) -> 1541 | M27: =IF($G27="","",IF($H27=1,ROUND($G27/23,0),IF($H27=3,ROUND($G27/12,0),IF($H27=6,$G27,IF($H27=7,$G27-ROUND($G27*10/11,0),0))))) -> 1541 | N27: =IF($G27="","",K27+L27+M27) -> 18493 | O27: =IF($G27="","",IFERROR(VLOOKUP($D27&"|"&$E27,科目表!$A$5:$B$200,2,FALSE),"※未登録")) -> 送金料 | P27: =IF(OR($G27="",$C27=""),"",IF($B27="決算整理",13,MOD(MONTH($C27)-4,12)+1)) -> 2 | Q27: =IF($G27="","",TRIM(IF(J27+K27+L27+M27<>$G27,"按分不一致 ","")&IF(O27="※未登録","科目未登録 ","")&IF(OR($H27="",ISERROR(MATCH($H27,{1,2,3,4,5,6,7,8},0))),"経費区分? ","")&IF($I27="","状態未設定 ","")&IF(AND(OR($I27="確認済",$I27="未確認"),$B27="月例",OR($C27="",$C27<DATE(年度+2018,4,1),$C27>DATE(年度+2019,3,31))),"年度外の日付 ","")&IF(AND(OR($I27="確認済",$I27="未確認"),O27="対象外"),"対象外の科目 ",""))) | R27: 月例!27
A28: 24 | B28: 月例 | C28: 46153 | D28: 事務費 | E28: 送金料 | F28: 振込手数料（広銀）４月分 短期分 | G28: 139883 | H28: 2 | I28: 確認済 | J28: =IF($G28="","",IF($H28=1,$G28-ROUND($G28*10/23,0)-2*ROUND($G28/23,0),IF($H28=2,$G28,0))) -> 139883 | K28: =IF($G28="","",IF($H28=1,ROUND($G28*10/23,0),IF($H28=3,$G28-2*ROUND($G28/12,0),IF($H28=4,$G28,IF(OR($H28=5,$H28=7),ROUND($G28*10/11,0),0))))) -> 0 | L28: =IF($G28="","",IF($H28=1,ROUND($G28/23,0),IF($H28=3,ROUND($G28/12,0),IF($H28=5,$G28-ROUND($G28*10/11,0),IF($H28=8,$G28,0))))) -> 0 | M28: =IF($G28="","",IF($H28=1,ROUND($G28/23,0),IF($H28=3,ROUND($G28/12,0),IF($H28=6,$G28,IF($H28=7,$G28-ROUND($G28*10/11,0),0))))) -> 0 | N28: =IF($G28="","",K28+L28+M28) -> 0 | O28: =IF($G28="","",IFERROR(VLOOKUP($D28&"|"&$E28,科目表!$A$5:$B$200,2,FALSE),"※未登録")) -> 送金料 | P28: =IF(OR($G28="",$C28=""),"",IF($B28="決算整理",13,MOD(MONTH($C28)-4,12)+1)) -> 2 | Q28: =IF($G28="","",TRIM(IF(J28+K28+L28+M28<>$G28,"按分不一致 ","")&IF(O28="※未登録","科目未登録 ","")&IF(OR($H28="",ISERROR(MATCH($H28,{1,2,3,4,5,6,7,8},0))),"経費区分? ","")&IF($I28="","状態未設定 ","")&IF(AND(OR($I28="確認済",$I28="未確認"),$B28="月例",OR($C28="",$C28<DATE(年度+2018,4,1),$C28>DATE(年度+2019,3,31))),"年度外の日付 ","")&IF(AND(OR($I28="確認済",$I28="未確認"),O28="対象外"),"対象外の科目 ",""))) | R28: 月例!28
A29: 25 | B29: 月例 | C29: 46171 | D29: 事務費 | E29: 事務用消耗品費 | F29: ダイヤルロック UNK-02 7個 他 | G29: 14518 | H29: 2 | I29: 確認済 | J29: =IF($G29="","",IF($H29=1,$G29-ROUND($G29*10/23,0)-2*ROUND($G29/23,0),IF($H29=2,$G29,0))) -> 14518 | K29: =IF($G29="","",IF($H29=1,ROUND($G29*10/23,0),IF($H29=3,$G29-2*ROUND($G29/12,0),IF($H29=4,$G29,IF(OR($H29=5,$H29=7),ROUND($G29*10/11,0),0))))) -> 0 | L29: =IF($G29="","",IF($H29=1,ROUND($G29/23,0),IF($H29=3,ROUND($G29/12,0),IF($H29=5,$G29-ROUND($G29*10/11,0),IF($H29=8,$G29,0))))) -> 0 | M29: =IF($G29="","",IF($H29=1,ROUND($G29/23,0),IF($H29=3,ROUND($G29/12,0),IF($H29=6,$G29,IF($H29=7,$G29-ROUND($G29*10/11,0),0))))) -> 0 | N29: =IF($G29="","",K29+L29+M29) -> 0 | O29: =IF($G29="","",IFERROR(VLOOKUP($D29&"|"&$E29,科目表!$A$5:$B$200,2,FALSE),"※未登録")) -> 事務用消耗品費 | P29: =IF(OR($G29="",$C29=""),"",IF($B29="決算整理",13,MOD(MONTH($C29)-4,12)+1)) -> 2 | Q29: =IF($G29="","",TRIM(IF(J29+K29+L29+M29<>$G29,"按分不一致 ","")&IF(O29="※未登録","科目未登録 ","")&IF(OR($H29="",ISERROR(MATCH($H29,{1,2,3,4,5,6,7,8},0))),"経費区分? ","")&IF($I29="","状態未設定 ","")&IF(AND(OR($I29="確認済",$I29="未確認"),$B29="月例",OR($C29="",$C29<DATE(年度+2018,4,1),$C29>DATE(年度+2019,3,31))),"年度外の日付 ","")&IF(AND(OR($I29="確認済",$I29="未確認"),O29="対象外"),"対象外の科目 ",""))) | R29: 月例!29
A30: 26 | B30: 月例 | C30: 46171 | D30: 賃借料 | F30: パソコン（業務経理用）４月分 | G30: 5060 | H30: 2 | I30: 確認済 | J30: =IF($G30="","",IF($H30=1,$G30-ROUND($G30*10/23,0)-2*ROUND($G30/23,0),IF($H30=2,$G30,0))) -> 5060 | K30: =IF($G30="","",IF($H30=1,ROUND($G30*10/23,0),IF($H30=3,$G30-2*ROUND($G30/12,0),IF($H30=4,$G30,IF(OR($H30=5,$H30=7),ROUND($G30*10/11,0),0))))) -> 0 | L30: =IF($G30="","",IF($H30=1,ROUND($G30/23,0),IF($H30=3,ROUND($G30/12,0),IF($H30=5,$G30-ROUND($G30*10/11,0),IF($H30=8,$G30,0))))) -> 0 | M30: =IF($G30="","",IF($H30=1,ROUND($G30/23,0),IF($H30=3,ROUND($G30/12,0),IF($H30=6,$G30,IF($H30=7,$G30-ROUND($G30*10/11,0),0))))) -> 0 | N30: =IF($G30="","",K30+L30+M30) -> 0 | O30: =IF($G30="","",IFERROR(VLOOKUP($D30&"|"&$E30,科目表!$A$5:$B$200,2,FALSE),"※未登録")) -> 賃借料 | P30: =IF(OR($G30="",$C30=""),"",IF($B30="決算整理",13,MOD(MONTH($C30)-4,12)+1)) -> 2 | Q30: =IF($G30="","",TRIM(IF(J30+K30+L30+M30<>$G30,"按分不一致 ","")&IF(O30="※未登録","科目未登録 ","")&IF(OR($H30="",ISERROR(MATCH($H30,{1,2,3,4,5,6,7,8},0))),"経費区分? ","")&IF($I30="","状態未設定 ","")&IF(AND(OR($I30="確認済",$I30="未確認"),$B30="月例",OR($C30="",$C30<DATE(年度+2018,4,1),$C30>DATE(年度+2019,3,31))),"年度外の日付 ","")&IF(AND(OR($I30="確認済",$I30="未確認"),O30="対象外"),"対象外の科目 ",""))) | R30: 月例!30
A31: 27 | B31: 月例 | C31: 46157 | D31: 賃金 | F31: 臨時職員賃金４月分 天畠吏梨外1名分（短期１００％） | G31: 425880 | H31: 2 | I31: 確認済 | J31: =IF($G31="","",IF($H31=1,$G31-ROUND($G31*10/23,0)-2*ROUND($G31/23,0),IF($H31=2,$G31,0))) -> 425880 | K31: =IF($G31="","",IF($H31=1,ROUND($G31*10/23,0),IF($H31=3,$G31-2*ROUND($G31/12,0),IF($H31=4,$G31,IF(OR($H31=5,$H31=7),ROUND($G31*10/11,0),0))))) -> 0 | L31: =IF($G31="","",IF($H31=1,ROUND($G31/23,0),IF($H31=3,ROUND($G31/12,0),IF($H31=5,$G31-ROUND($G31*10/11,0),IF($H31=8,$G31,0))))) -> 0 | M31: =IF($G31="","",IF($H31=1,ROUND($G31/23,0),IF($H31=3,ROUND($G31/12,0),IF($H31=6,$G31,IF($H31=7,$G31-ROUND($G31*10/11,0),0))))) -> 0 | N31: =IF($G31="","",K31+L31+M31) -> 0 | O31: =IF($G31="","",IFERROR(VLOOKUP($D31&"|"&$E31,科目表!$A$5:$B$200,2,FALSE),"※未登録")) -> 賃金 | P31: =IF(OR($G31="",$C31=""),"",IF($B31="決算整理",13,MOD(MONTH($C31)-4,12)+1)) -> 2 | Q31: =IF($G31="","",TRIM(IF(J31+K31+L31+M31<>$G31,"按分不一致 ","")&IF(O31="※未登録","科目未登録 ","")&IF(OR($H31="",ISERROR(MATCH($H31,{1,2,3,4,5,6,7,8},0))),"経費区分? ","")&IF($I31="","状態未設定 ","")&IF(AND(OR($I31="確認済",$I31="未確認"),$B31="月例",OR($C31="",$C31<DATE(年度+2018,4,1),$C31>DATE(年度+2019,3,31))),"年度外の日付 ","")&IF(AND(OR($I31="確認済",$I31="未確認"),O31="対象外"),"対象外の科目 ",""))) | R31: 月例!31
A32: 28 | B32: 月例 | C32: 46162 | D32: 委託費 | F32: 社会保障等制度 中間サーバー等運営負担金 | G32: 1798068 | H32: 2 | I32: 確認済 | J32: =IF($G32="","",IF($H32=1,$G32-ROUND($G32*10/23,0)-2*ROUND($G32/23,0),IF($H32=2,$G32,0))) -> 1798068 | K32: =IF($G32="","",IF($H32=1,ROUND($G32*10/23,0),IF($H32=3,$G32-2*ROUND($G32/12,0),IF($H32=4,$G32,IF(OR($H32=5,$H32=7),ROUND($G32*10/11,0),0))))) -> 0 | L32: =IF($G32="","",IF($H32=1,ROUND($G32/23,0),IF($H32=3,ROUND($G32/12,0),IF($H32=5,$G32-ROUND($G32*10/11,0),IF($H32=8,$G32,0))))) -> 0 | M32: =IF($G32="","",IF($H32=1,ROUND($G32/23,0),IF($H32=3,ROUND($G32/12,0),IF($H32=6,$G32,IF($H32=7,$G32-ROUND($G32*10/11,0),0))))) -> 0 | N32: =IF($G32="","",K32+L32+M32) -> 0 | O32: =IF($G32="","",IFERROR(VLOOKUP($D32&"|"&$E32,科目表!$A$5:$B$200,2,FALSE),"※未登録")) -> 委託費 | P32: =IF(OR($G32="",$C32=""),"",IF($B32="決算整理",13,MOD(MONTH($C32)-4,12)+1)) -> 2 | Q32: =IF($G32="","",TRIM(IF(J32+K32+L32+M32<>$G32,"按分不一致 ","")&IF(O32="※未登録","科目未登録 ","")&IF(OR($H32="",ISERROR(MATCH($H32,{1,2,3,4,5,6,7,8},0))),"経費区分? ","")&IF($I32="","状態未設定 ","")&IF(AND(OR($I32="確認済",$I32="未確認"),$B32="月例",OR($C32="",$C32<DATE(年度+2018,4,1),$C32>DATE(年度+2019,3,31))),"年度外の日付 ","")&IF(AND(OR($I32="確認済",$I32="未確認"),O32="対象外"),"対象外の科目 ",""))) | R32: 月例!32
A33: 29 | B33: 月例 | C33: 46171 | D33: 事務費 | E33: 送金料 | F33: ゆうちょ銀行手数料（４月分）短期 | G33: 109019 | H33: 2 | I33: 確認済 | J33: =IF($G33="","",IF($H33=1,$G33-ROUND($G33*10/23,0)-2*ROUND($G33/23,0),IF($H33=2,$G33,0))) -> 109019 | K33: =IF($G33="","",IF($H33=1,ROUND($G33*10/23,0),IF($H33=3,$G33-2*ROUND($G33/12,0),IF($H33=4,$G33,IF(OR($H33=5,$H33=7),ROUND($G33*10/11,0),0))))) -> 0 | L33: =IF($G33="","",IF($H33=1,ROUND($G33/23,0),IF($H33=3,ROUND($G33/12,0),IF($H33=5,$G33-ROUND($G33*10/11,0),IF($H33=8,$G33,0))))) -> 0 | M33: =IF($G33="","",IF($H33=1,ROUND($G33/23,0),IF($H33=3,ROUND($G33/12,0),IF($H33=6,$G33,IF($H33=7,$G33-ROUND($G33*10/11,0),0))))) -> 0 | N33: =IF($G33="","",K33+L33+M33) -> 0 | O33: =IF($G33="","",IFERROR(VLOOKUP($D33&"|"&$E33,科目表!$A$5:$B$200,2,FALSE),"※未登録")) -> 送金料 | P33: =IF(OR($G33="",$C33=""),"",IF($B33="決算整理",13,MOD(MONTH($C33)-4,12)+1)) -> 2 | Q33: =IF($G33="","",TRIM(IF(J33+K33+L33+M33<>$G33,"按分不一致 ","")&IF(O33="※未登録","科目未登録 ","")&IF(OR($H33="",ISERROR(MATCH($H33,{1,2,3,4,5,6,7,8},0))),"経費区分? ","")&IF($I33="","状態未設定 ","")&IF(AND(OR($I33="確認済",$I33="未確認"),$B33="月例",OR($C33="",$C33<DATE(年度+2018,4,1),$C33>DATE(年度+2019,3,31))),"年度外の日付 ","")&IF(AND(OR($I33="確認済",$I33="未確認"),O33="対象外"),"対象外の科目 ",""))) | R33: 月例!33
A34: 30 | B34: 月例 | C34: 46171 | D34: 事務費 | E34: 雑費 | F34: ゆうちょ銀行振替口座残高証明（４月分）短期 | G34: 550 | H34: 2 | I34: 確認済 | J34: =IF($G34="","",IF($H34=1,$G34-ROUND($G34*10/23,0)-2*ROUND($G34/23,0),IF($H34=2,$G34,0))) -> 550 | K34: =IF($G34="","",IF($H34=1,ROUND($G34*10/23,0),IF($H34=3,$G34-2*ROUND($G34/12,0),IF($H34=4,$G34,IF(OR($H34=5,$H34=7),ROUND($G34*10/11,0),0))))) -> 0 | L34: =IF($G34="","",IF($H34=1,ROUND($G34/23,0),IF($H34=3,ROUND($G34/12,0),IF($H34=5,$G34-ROUND($G34*10/11,0),IF($H34=8,$G34,0))))) -> 0 | M34: =IF($G34="","",IF($H34=1,ROUND($G34/23,0),IF($H34=3,ROUND($G34/12,0),IF($H34=6,$G34,IF($H34=7,$G34-ROUND($G34*10/11,0),0))))) -> 0 | N34: =IF($G34="","",K34+L34+M34) -> 0 | O34: =IF($G34="","",IFERROR(VLOOKUP($D34&"|"&$E34,科目表!$A$5:$B$200,2,FALSE),"※未登録")) -> 事務費・雑費 | P34: =IF(OR($G34="",$C34=""),"",IF($B34="決算整理",13,MOD(MONTH($C34)-4,12)+1)) -> 2 | Q34: =IF($G34="","",TRIM(IF(J34+K34+L34+M34<>$G34,"按分不一致 ","")&IF(O34="※未登録","科目未登録 ","")&IF(OR($H34="",ISERROR(MATCH($H34,{1,2,3,4,5,6,7,8},0))),"経費区分? ","")&IF($I34="","状態未設定 ","")&IF(AND(OR($I34="確認済",$I34="未確認"),$B34="月例",OR($C34="",$C34<DATE(年度+2018,4,1),$C34>DATE(年度+2019,3,31))),"年度外の日付 ","")&IF(AND(OR($I34="確認済",$I34="未確認"),O34="対象外"),"対象外の科目 ",""))) | R34: 月例!34
A35: 31 | B35: 月例 | C35: 46163 | D35: 職員給与 | E35: 非常勤職員手当 | F35: ５月分給与（長期分） | G35: 380800 | H35: 3 | I35: 確認済 | J35: =IF($G35="","",IF($H35=1,$G35-ROUND($G35*10/23,0)-2*ROUND($G35/23,0),IF($H35=2,$G35,0))) -> 0 | K35: =IF($G35="","",IF($H35=1,ROUND($G35*10/23,0),IF($H35=3,$G35-2*ROUND($G35/12,0),IF($H35=4,$G35,IF(OR($H35=5,$H35=7),ROUND($G35*10/11,0),0))))) -> 317334 | L35: =IF($G35="","",IF($H35=1,ROUND($G35/23,0),IF($H35=3,ROUND($G35/12,0),IF($H35=5,$G35-ROUND($G35*10/11,0),IF($H35=8,$G35,0))))) -> 31733 | M35: =IF($G35="","",IF($H35=1,ROUND($G35/23,0),IF($H35=3,ROUND($G35/12,0),IF($H35=6,$G35,IF($H35=7,$G35-ROUND($G35*10/11,0),0))))) -> 31733 | N35: =IF($G35="","",K35+L35+M35) -> 380800 | O35: =IF($G35="","",IFERROR(VLOOKUP($D35&"|"&$E35,科目表!$A$5:$B$200,2,FALSE),"※未登録")) -> 非常勤職員手当 | P35: =IF(OR($G35="",$C35=""),"",IF($B35="決算整理",13,MOD(MONTH($C35)-4,12)+1)) -> 2 | Q35: =IF($G35="","",TRIM(IF(J35+K35+L35+M35<>$G35,"按分不一致 ","")&IF(O35="※未登録","科目未登録 ","")&IF(OR($H35="",ISERROR(MATCH($H35,{1,2,3,4,5,6,7,8},0))),"経費区分? ","")&IF($I35="","状態未設定 ","")&IF(AND(OR($I35="確認済",$I35="未確認"),$B35="月例",OR($C35="",$C35<DATE(年度+2018,4,1),$C35>DATE(年度+2019,3,31))),"年度外の日付 ","")&IF(AND(OR($I35="確認済",$I35="未確認"),O35="対象外"),"対象外の科目 ",""))) | R35: 月例!35
A36: 32 | B36: 月例 | C36: 46163 | D36: 職員給与 | E36: 非常勤職員手当 | F36: ５月分給与（短期分） | G36: 248436 | H36: 2 | I36: 確認済 | J36: =IF($G36="","",IF($H36=1,$G36-ROUND($G36*10/23,0)-2*ROUND($G36/23,0),IF($H36=2,$G36,0))) -> 248436 | K36: =IF($G36="","",IF($H36=1,ROUND($G36*10/23,0),IF($H36=3,$G36-2*ROUND($G36/12,0),IF($H36=4,$G36,IF(OR($H36=5,$H36=7),ROUND($G36*10/11,0),0))))) -> 0 | L36: =IF($G36="","",IF($H36=1,ROUND($G36/23,0),IF($H36=3,ROUND($G36/12,0),IF($H36=5,$G36-ROUND($G36*10/11,0),IF($H36=8,$G36,0))))) -> 0 | M36: =IF($G36="","",IF($H36=1,ROUND($G36/23,0),IF($H36=3,ROUND($G36/12,0),IF($H36=6,$G36,IF($H36=7,$G36-ROUND($G36*10/11,0),0))))) -> 0 | N36: =IF($G36="","",K36+L36+M36) -> 0 | O36: =IF($G36="","",IFERROR(VLOOKUP($D36&"|"&$E36,科目表!$A$5:$B$200,2,FALSE),"※未登録")) -> 非常勤職員手当 | P36: =IF(OR($G36="",$C36=""),"",IF($B36="決算整理",13,MOD(MONTH($C36)-4,12)+1)) -> 2 | Q36: =IF($G36="","",TRIM(IF(J36+K36+L36+M36<>$G36,"按分不一致 ","")&IF(O36="※未登録","科目未登録 ","")&IF(OR($H36="",ISERROR(MATCH($H36,{1,2,3,4,5,6,7,8},0))),"経費区分? ","")&IF($I36="","状態未設定 ","")&IF(AND(OR($I36="確認済",$I36="未確認"),$B36="月例",OR($C36="",$C36<DATE(年度+2018,4,1),$C36>DATE(年度+2019,3,31))),"年度外の日付 ","")&IF(AND(OR($I36="確認済",$I36="未確認"),O36="対象外"),"対象外の科目 ",""))) | R36: 月例!36
A37: 33 | B37: 月例 | C37: 46163 | D37: 負担金 | E37: 互助会費 | F37: 助成金（５月長期分） | G37: 466 | H37: 3 | I37: 確認済 | J37: =IF($G37="","",IF($H37=1,$G37-ROUND($G37*10/23,0)-2*ROUND($G37/23,0),IF($H37=2,$G37,0))) -> 0 | K37: =IF($G37="","",IF($H37=1,ROUND($G37*10/23,0),IF($H37=3,$G37-2*ROUND($G37/12,0),IF($H37=4,$G37,IF(OR($H37=5,$H37=7),ROUND($G37*10/11,0),0))))) -> 388 | L37: =IF($G37="","",IF($H37=1,ROUND($G37/23,0),IF($H37=3,ROUND($G37/12,0),IF($H37=5,$G37-ROUND($G37*10/11,0),IF($H37=8,$G37,0))))) -> 39 | M37: =IF($G37="","",IF($H37=1,ROUND($G37/23,0),IF($H37=3,ROUND($G37/12,0),IF($H37=6,$G37,IF($H37=7,$G37-ROUND($G37*10/11,0),0))))) -> 39 | N37: =IF($G37="","",K37+L37+M37) -> 466 | O37: =IF($G37="","",IFERROR(VLOOKUP($D37&"|"&$E37,科目表!$A$5:$B$200,2,FALSE),"※未登録")) -> 互助会費 | P37: =IF(OR($G37="",$C37=""),"",IF($B37="決算整理",13,MOD(MONTH($C37)-4,12)+1)) -> 2 | Q37: =IF($G37="","",TRIM(IF(J37+K37+L37+M37<>$G37,"按分不一致 ","")&IF(O37="※未登録","科目未登録 ","")&IF(OR($H37="",ISERROR(MATCH($H37,{1,2,3,4,5,6,7,8},0))),"経費区分? ","")&IF($I37="","状態未設定 ","")&IF(AND(OR($I37="確認済",$I37="未確認"),$B37="月例",OR($C37="",$C37<DATE(年度+2018,4,1),$C37>DATE(年度+2019,3,31))),"年度外の日付 ","")&IF(AND(OR($I37="確認済",$I37="未確認"),O37="対象外"),"対象外の科目 ",""))) | R37: 月例!37
A38: 34 | B38: 月例 | C38: 46163 | D38: 負担金 | E38: 互助会費 | F38: 助成金（５月短期分） | G38: 240 | H38: 2 | I38: 確認済 | J38: =IF($G38="","",IF($H38=1,$G38-ROUND($G38*10/23,0)-2*ROUND($G38/23,0),IF($H38=2,$G38,0))) -> 240 | K38: =IF($G38="","",IF($H38=1,ROUND($G38*10/23,0),IF($H38=3,$G38-2*ROUND($G38/12,0),IF($H38=4,$G38,IF(OR($H38=5,$H38=7),ROUND($G38*10/11,0),0))))) -> 0 | L38: =IF($G38="","",IF($H38=1,ROUND($G38/23,0),IF($H38=3,ROUND($G38/12,0),IF($H38=5,$G38-ROUND($G38*10/11,0),IF($H38=8,$G38,0))))) -> 0 | M38: =IF($G38="","",IF($H38=1,ROUND($G38/23,0),IF($H38=3,ROUND($G38/12,0),IF($H38=6,$G38,IF($H38=7,$G38-ROUND($G38*10/11,0),0))))) -> 0 | N38: =IF($G38="","",K38+L38+M38) -> 0 | O38: =IF($G38="","",IFERROR(VLOOKUP($D38&"|"&$E38,科目表!$A$5:$B$200,2,FALSE),"※未登録")) -> 互助会費 | P38: =IF(OR($G38="",$C38=""),"",IF($B38="決算整理",13,MOD(MONTH($C38)-4,12)+1)) -> 2 | Q38: =IF($G38="","",TRIM(IF(J38+K38+L38+M38<>$G38,"按分不一致 ","")&IF(O38="※未登録","科目未登録 ","")&IF(OR($H38="",ISERROR(MATCH($H38,{1,2,3,4,5,6,7,8},0))),"経費区分? ","")&IF($I38="","状態未設定 ","")&IF(AND(OR($I38="確認済",$I38="未確認"),$B38="月例",OR($C38="",$C38<DATE(年度+2018,4,1),$C38>DATE(年度+2019,3,31))),"年度外の日付 ","")&IF(AND(OR($I38="確認済",$I38="未確認"),O38="対象外"),"対象外の科目 ",""))) | R38: 月例!38
A39: 35 | B39: 月例 | C39: 46162 | D39: 委託費 | F39: レセプト電子データ提供料（２月診療分） | G39: 61859 | H39: 2 | I39: 確認済 | J39: =IF($G39="","",IF($H39=1,$G39-ROUND($G39*10/23,0)-2*ROUND($G39/23,0),IF($H39=2,$G39,0))) -> 61859 | K39: =IF($G39="","",IF($H39=1,ROUND($G39*10/23,0),IF($H39=3,$G39-2*ROUND($G39/12,0),IF($H39=4,$G39,IF(OR($H39=5,$H39=7),ROUND($G39*10/11,0),0))))) -> 0 | L39: =IF($G39="","",IF($H39=1,ROUND($G39/23,0),IF($H39=3,ROUND($G39/12,0),IF($H39=5,$G39-ROUND($G39*10/11,0),IF($H39=8,$G39,0))))) -> 0 | M39: =IF($G39="","",IF($H39=1,ROUND($G39/23,0),IF($H39=3,ROUND($G39/12,0),IF($H39=6,$G39,IF($H39=7,$G39-ROUND($G39*10/11,0),0))))) -> 0 | N39: =IF($G39="","",K39+L39+M39) -> 0 | O39: =IF($G39="","",IFERROR(VLOOKUP($D39&"|"&$E39,科目表!$A$5:$B$200,2,FALSE),"※未登録")) -> 委託費 | P39: =IF(OR($G39="",$C39=""),"",IF($B39="決算整理",13,MOD(MONTH($C39)-4,12)+1)) -> 2 | Q39: =IF($G39="","",TRIM(IF(J39+K39+L39+M39<>$G39,"按分不一致 ","")&IF(O39="※未登録","科目未登録 ","")&IF(OR($H39="",ISERROR(MATCH($H39,{1,2,3,4,5,6,7,8},0))),"経費区分? ","")&IF($I39="","状態未設定 ","")&IF(AND(OR($I39="確認済",$I39="未確認"),$B39="月例",OR($C39="",$C39<DATE(年度+2018,4,1),$C39>DATE(年度+2019,3,31))),"年度外の日付 ","")&IF(AND(OR($I39="確認済",$I39="未確認"),O39="対象外"),"対象外の科目 ",""))) | R39: 月例!39
A40: 36 | B40: 月例 | C40: 45065 | D40: 委託費 | F40: 社会保障等制度 中間サーバー等運営負担金 | G40: 661740 | H40: 2 | I40: 昨年実績 | J40: =IF($G40="","",IF($H40=1,$G40-ROUND($G40*10/23,0)-2*ROUND($G40/23,0),IF($H40=2,$G40,0))) -> 661740 | K40: =IF($G40="","",IF($H40=1,ROUND($G40*10/23,0),IF($H40=3,$G40-2*ROUND($G40/12,0),IF($H40=4,$G40,IF(OR($H40=5,$H40=7),ROUND($G40*10/11,0),0))))) -> 0 | L40: =IF($G40="","",IF($H40=1,ROUND($G40/23,0),IF($H40=3,ROUND($G40/12,0),IF($H40=5,$G40-ROUND($G40*10/11,0),IF($H40=8,$G40,0))))) -> 0 | M40: =IF($G40="","",IF($H40=1,ROUND($G40/23,0),IF($H40=3,ROUND($G40/12,0),IF($H40=6,$G40,IF($H40=7,$G40-ROUND($G40*10/11,0),0))))) -> 0 | N40: =IF($G40="","",K40+L40+M40) -> 0 | O40: =IF($G40="","",IFERROR(VLOOKUP($D40&"|"&$E40,科目表!$A$5:$B$200,2,FALSE),"※未登録")) -> 委託費 | P40: =IF(OR($G40="",$C40=""),"",IF($B40="決算整理",13,MOD(MONTH($C40)-4,12)+1)) -> 2 | Q40: =IF($G40="","",TRIM(IF(J40+K40+L40+M40<>$G40,"按分不一致 ","")&IF(O40="※未登録","科目未登録 ","")&IF(OR($H40="",ISERROR(MATCH($H40,{1,2,3,4,5,6,7,8},0))),"経費区分? ","")&IF($I40="","状態未設定 ","")&IF(AND(OR($I40="確認済",$I40="未確認"),$B40="月例",OR($C40="",$C40<DATE(年度+2018,4,1),$C40>DATE(年度+2019,3,31))),"年度外の日付 ","")&IF(AND(OR($I40="確認済",$I40="未確認"),O40="対象外"),"対象外の科目 ",""))) | R40: 月例!40
A41: 37 | B41: 月例 | C41: 44336 | D41: 事務費 | E41: 通信運搬費 | F41: 電話料金（４月使用・５月請求分） | G41: 5407 | H41: 2 | I41: 昨年実績 | J41: =IF($G41="","",IF($H41=1,$G41-ROUND($G41*10/23,0)-2*ROUND($G41/23,0),IF($H41=2,$G41,0))) -> 5407 | K41: =IF($G41="","",IF($H41=1,ROUND($G41*10/23,0),IF($H41=3,$G41-2*ROUND($G41/12,0),IF($H41=4,$G41,IF(OR($H41=5,$H41=7),ROUND($G41*10/11,0),0))))) -> 0 | L41: =IF($G41="","",IF($H41=1,ROUND($G41/23,0),IF($H41=3,ROUND($G41/12,0),IF($H41=5,$G41-ROUND($G41*10/11,0),IF($H41=8,$G41,0))))) -> 0 | M41: =IF($G41="","",IF($H41=1,ROUND($G41/23,0),IF($H41=3,ROUND($G41/12,0),IF($H41=6,$G41,IF($H41=7,$G41-ROUND($G41*10/11,0),0))))) -> 0 | N41: =IF($G41="","",K41+L41+M41) -> 0 | O41: =IF($G41="","",IFERROR(VLOOKUP($D41&"|"&$E41,科目表!$A$5:$B$200,2,FALSE),"※未登録")) -> 通信運搬費 | P41: =IF(OR($G41="",$C41=""),"",IF($B41="決算整理",13,MOD(MONTH($C41)-4,12)+1)) -> 2 | Q41: =IF($G41="","",TRIM(IF(J41+K41+L41+M41<>$G41,"按分不一致 ","")&IF(O41="※未登録","科目未登録 ","")&IF(OR($H41="",ISERROR(MATCH($H41,{1,2,3,4,5,6,7,8},0))),"経費区分? ","")&IF($I41="","状態未設定 ","")&IF(AND(OR($I41="確認済",$I41="未確認"),$B41="月例",OR($C41="",$C41<DATE(年度+2018,4,1),$C41>DATE(年度+2019,3,31))),"年度外の日付 ","")&IF(AND(OR($I41="確認済",$I41="未確認"),O41="対象外"),"対象外の科目 ",""))) | R41: 月例!41
A42: 38 | B42: 月例 | C42: 45807 | D42: 事務費 | E42: 事務用消耗品費 | F42: ポストイット ５００１SS-K 2個 他 | G42: 19730 | H42: 2 | I42: 昨年実績 | J42: =IF($G42="","",IF($H42=1,$G42-ROUND($G42*10/23,0)-2*ROUND($G42/23,0),IF($H42=2,$G42,0))) -> 19730 | K42: =IF($G42="","",IF($H42=1,ROUND($G42*10/23,0),IF($H42=3,$G42-2*ROUND($G42/12,0),IF($H42=4,$G42,IF(OR($H42=5,$H42=7),ROUND($G42*10/11,0),0))))) -> 0 | L42: =IF($G42="","",IF($H42=1,ROUND($G42/23,0),IF($H42=3,ROUND($G42/12,0),IF($H42=5,$G42-ROUND($G42*10/11,0),IF($H42=8,$G42,0))))) -> 0 | M42: =IF($G42="","",IF($H42=1,ROUND($G42/23,0),IF($H42=3,ROUND($G42/12,0),IF($H42=6,$G42,IF($H42=7,$G42-ROUND($G42*10/11,0),0))))) -> 0 | N42: =IF($G42="","",K42+L42+M42) -> 0 | O42: =IF($G42="","",IFERROR(VLOOKUP($D42&"|"&$E42,科目表!$A$5:$B$200,2,FALSE),"※未登録")) -> 事務用消耗品費 | P42: =IF(OR($G42="",$C42=""),"",IF($B42="決算整理",13,MOD(MONTH($C42)-4,12)+1)) -> 2 | Q42: =IF($G42="","",TRIM(IF(J42+K42+L42+M42<>$G42,"按分不一致 ","")&IF(O42="※未登録","科目未登録 ","")&IF(OR($H42="",ISERROR(MATCH($H42,{1,2,3,4,5,6,7,8},0))),"経費区分? ","")&IF($I42="","状態未設定 ","")&IF(AND(OR($I42="確認済",$I42="未確認"),$B42="月例",OR($C42="",$C42<DATE(年度+2018,4,1),$C42>DATE(年度+2019,3,31))),"年度外の日付 ","")&IF(AND(OR($I42="確認済",$I42="未確認"),O42="対象外"),"対象外の科目 ",""))) | R42: 月例!42
A43: 39 | B43: 月例 | C43: 45793 | D43: 事務費 | E43: 図書印刷費 | F43: 短期給付決定通知書 ３，０００枚 | G43: 128700 | H43: 2 | I43: 昨年実績 | J43: =IF($G43="","",IF($H43=1,$G43-ROUND($G43*10/23,0)-2*ROUND($G43/23,0),IF($H43=2,$G43,0))) -> 128700 | K43: =IF($G43="","",IF($H43=1,ROUND($G43*10/23,0),IF($H43=3,$G43-2*ROUND($G43/12,0),IF($H43=4,$G43,IF(OR($H43=5,$H43=7),ROUND($G43*10/11,0),0))))) -> 0 | L43: =IF($G43="","",IF($H43=1,ROUND($G43/23,0),IF($H43=3,ROUND($G43/12,0),IF($H43=5,$G43-ROUND($G43*10/11,0),IF($H43=8,$G43,0))))) -> 0 | M43: =IF($G43="","",IF($H43=1,ROUND($G43/23,0),IF($H43=3,ROUND($G43/12,0),IF($H43=6,$G43,IF($H43=7,$G43-ROUND($G43*10/11,0),0))))) -> 0 | N43: =IF($G43="","",K43+L43+M43) -> 0 | O43: =IF($G43="","",IFERROR(VLOOKUP($D43&"|"&$E43,科目表!$A$5:$B$200,2,FALSE),"※未登録")) -> 図書印刷費 | P43: =IF(OR($G43="",$C43=""),"",IF($B43="決算整理",13,MOD(MONTH($C43)-4,12)+1)) -> 2 | Q43: =IF($G43="","",TRIM(IF(J43+K43+L43+M43<>$G43,"按分不一致 ","")&IF(O43="※未登録","科目未登録 ","")&IF(OR($H43="",ISERROR(MATCH($H43,{1,2,3,4,5,6,7,8},0))),"経費区分? ","")&IF($I43="","状態未設定 ","")&IF(AND(OR($I43="確認済",$I43="未確認"),$B43="月例",OR($C43="",$C43<DATE(年度+2018,4,1),$C43>DATE(年度+2019,3,31))),"年度外の日付 ","")&IF(AND(OR($I43="確認済",$I43="未確認"),O43="対象外"),"対象外の科目 ",""))) | R43: 月例!43
A44: 40 | B44: 月例 | C44: 45786 | D44: 事務費 | E44: 事務用消耗品費 | F44: トナーカートリッジＬＰＢ３Ｔ２７ 2個 | G44: 10560 | H44: 3 | I44: 昨年実績 | J44: =IF($G44="","",IF($H44=1,$G44-ROUND($G44*10/23,0)-2*ROUND($G44/23,0),IF($H44=2,$G44,0))) -> 0 | K44: =IF($G44="","",IF($H44=1,ROUND($G44*10/23,0),IF($H44=3,$G44-2*ROUND($G44/12,0),IF($H44=4,$G44,IF(OR($H44=5,$H44=7),ROUND($G44*10/11,0),0))))) -> 8800 | L44: =IF($G44="","",IF($H44=1,ROUND($G44/23,0),IF($H44=3,ROUND($G44/12,0),IF($H44=5,$G44-ROUND($G44*10/11,0),IF($H44=8,$G44,0))))) -> 880 | M44: =IF($G44="","",IF($H44=1,ROUND($G44/23,0),IF($H44=3,ROUND($G44/12,0),IF($H44=6,$G44,IF($H44=7,$G44-ROUND($G44*10/11,0),0))))) -> 880 | N44: =IF($G44="","",K44+L44+M44) -> 10560 | O44: =IF($G44="","",IFERROR(VLOOKUP($D44&"|"&$E44,科目表!$A$5:$B$200,2,FALSE),"※未登録")) -> 事務用消耗品費 | P44: =IF(OR($G44="",$C44=""),"",IF($B44="決算整理",13,MOD(MONTH($C44)-4,12)+1)) -> 2 | Q44: =IF($G44="","",TRIM(IF(J44+K44+L44+M44<>$G44,"按分不一致 ","")&IF(O44="※未登録","科目未登録 ","")&IF(OR($H44="",ISERROR(MATCH($H44,{1,2,3,4,5,6,7,8},0))),"経費区分? ","")&IF($I44="","状態未設定 ","")&IF(AND(OR($I44="確認済",$I44="未確認"),$B44="月例",OR($C44="",$C44<DATE(年度+2018,4,1),$C44>DATE(年度+2019,3,31))),"年度外の日付 ","")&IF(AND(OR($I44="確認済",$I44="未確認"),O44="対象外"),"対象外の科目 ",""))) | R44: 月例!44
A45: 41 | B45: 月例 | C45: 46162 | D45: 賃借料 | F45: 統合管理端末リース料（４月分） | G45: 12738 | H45: 2 | I45: 確認済 | J45: =IF($G45="","",IF($H45=1,$G45-ROUND($G45*10/23,0)-2*ROUND($G45/23,0),IF($H45=2,$G45,0))) -> 12738 | K45: =IF($G45="","",IF($H45=1,ROUND($G45*10/23,0),IF($H45=3,$G45-2*ROUND($G45/12,0),IF($H45=4,$G45,IF(OR($H45=5,$H45=7),ROUND($G45*10/11,0),0))))) -> 0 | L45: =IF($G45="","",IF($H45=1,ROUND($G45/23,0),IF($H45=3,ROUND($G45/12,0),IF($H45=5,$G45-ROUND($G45*10/11,0),IF($H45=8,$G45,0))))) -> 0 | M45: =IF($G45="","",IF($H45=1,ROUND($G45/23,0),IF($H45=3,ROUND($G45/12,0),IF($H45=6,$G45,IF($H45=7,$G45-ROUND($G45*10/11,0),0))))) -> 0 | N45: =IF($G45="","",K45+L45+M45) -> 0 | O45: =IF($G45="","",IFERROR(VLOOKUP($D45&"|"&$E45,科目表!$A$5:$B$200,2,FALSE),"※未登録")) -> 賃借料 | P45: =IF(OR($G45="",$C45=""),"",IF($B45="決算整理",13,MOD(MONTH($C45)-4,12)+1)) -> 2 | Q45: =IF($G45="","",TRIM(IF(J45+K45+L45+M45<>$G45,"按分不一致 ","")&IF(O45="※未登録","科目未登録 ","")&IF(OR($H45="",ISERROR(MATCH($H45,{1,2,3,4,5,6,7,8},0))),"経費区分? ","")&IF($I45="","状態未設定 ","")&IF(AND(OR($I45="確認済",$I45="未確認"),$B45="月例",OR($C45="",$C45<DATE(年度+2018,4,1),$C45>DATE(年度+2019,3,31))),"年度外の日付 ","")&IF(AND(OR($I45="確認済",$I45="未確認"),O45="対象外"),"対象外の科目 ",""))) | R45: 月例!45
A46: 42 | B46: 月例 | C46: 44347 | D46: 委託費 | F46: 短期給付個人番号管理システム端末保守サービス（４月分） | G46: 385 | H46: 2 | I46: 昨年実績 | J46: =IF($G46="","",IF($H46=1,$G46-ROUND($G46*10/23,0)-2*ROUND($G46/23,0),IF($H46=2,$G46,0))) -> 385 | K46: =IF($G46="","",IF($H46=1,ROUND($G46*10/23,0),IF($H46=3,$G46-2*ROUND($G46/12,0),IF($H46=4,$G46,IF(OR($H46=5,$H46=7),ROUND($G46*10/11,0),0))))) -> 0 | L46: =IF($G46="","",IF($H46=1,ROUND($G46/23,0),IF($H46=3,ROUND($G46/12,0),IF($H46=5,$G46-ROUND($G46*10/11,0),IF($H46=8,$G46,0))))) -> 0 | M46: =IF($G46="","",IF($H46=1,ROUND($G46/23,0),IF($H46=3,ROUND($G46/12,0),IF($H46=6,$G46,IF($H46=7,$G46-ROUND($G46*10/11,0),0))))) -> 0 | N46: =IF($G46="","",K46+L46+M46) -> 0 | O46: =IF($G46="","",IFERROR(VLOOKUP($D46&"|"&$E46,科目表!$A$5:$B$200,2,FALSE),"※未登録")) -> 委託費 | P46: =IF(OR($G46="",$C46=""),"",IF($B46="決算整理",13,MOD(MONTH($C46)-4,12)+1)) -> 2 | Q46: =IF($G46="","",TRIM(IF(J46+K46+L46+M46<>$G46,"按分不一致 ","")&IF(O46="※未登録","科目未登録 ","")&IF(OR($H46="",ISERROR(MATCH($H46,{1,2,3,4,5,6,7,8},0))),"経費区分? ","")&IF($I46="","状態未設定 ","")&IF(AND(OR($I46="確認済",$I46="未確認"),$B46="月例",OR($C46="",$C46<DATE(年度+2018,4,1),$C46>DATE(年度+2019,3,31))),"年度外の日付 ","")&IF(AND(OR($I46="確認済",$I46="未確認"),O46="対象外"),"対象外の科目 ",""))) | R46: 月例!46
A47: 43 | B47: 月例 | C47: 46162 | D47: 委託費 | F47: 統合管理端末保守料（４月～３月分） | G47: 149050 | H47: 2 | I47: 確認済 | J47: =IF($G47="","",IF($H47=1,$G47-ROUND($G47*10/23,0)-2*ROUND($G47/23,0),IF($H47=2,$G47,0))) -> 149050 | K47: =IF($G47="","",IF($H47=1,ROUND($G47*10/23,0),IF($H47=3,$G47-2*ROUND($G47/12,0),IF($H47=4,$G47,IF(OR($H47=5,$H47=7),ROUND($G47*10/11,0),0))))) -> 0 | L47: =IF($G47="","",IF($H47=1,ROUND($G47/23,0),IF($H47=3,ROUND($G47/12,0),IF($H47=5,$G47-ROUND($G47*10/11,0),IF($H47=8,$G47,0))))) -> 0 | M47: =IF($G47="","",IF($H47=1,ROUND($G47/23,0),IF($H47=3,ROUND($G47/12,0),IF($H47=6,$G47,IF($H47=7,$G47-ROUND($G47*10/11,0),0))))) -> 0 | N47: =IF($G47="","",K47+L47+M47) -> 0 | O47: =IF($G47="","",IFERROR(VLOOKUP($D47&"|"&$E47,科目表!$A$5:$B$200,2,FALSE),"※未登録")) -> 委託費 | P47: =IF(OR($G47="",$C47=""),"",IF($B47="決算整理",13,MOD(MONTH($C47)-4,12)+1)) -> 2 | Q47: =IF($G47="","",TRIM(IF(J47+K47+L47+M47<>$G47,"按分不一致 ","")&IF(O47="※未登録","科目未登録 ","")&IF(OR($H47="",ISERROR(MATCH($H47,{1,2,3,4,5,6,7,8},0))),"経費区分? ","")&IF($I47="","状態未設定 ","")&IF(AND(OR($I47="確認済",$I47="未確認"),$B47="月例",OR($C47="",$C47<DATE(年度+2018,4,1),$C47>DATE(年度+2019,3,31))),"年度外の日付 ","")&IF(AND(OR($I47="確認済",$I47="未確認"),O47="対象外"),"対象外の科目 ",""))) | R47: 月例!47
A48: 44 | B48: 月例 | C48: 46142 | D48: 事務費 | E48: 図書印刷費 | F48: 角２封筒エルコン付き クラフト８５ｇ枠付 ５，５００枚 | G48: 99220 | H48: 2 | I48: 確認済 | J48: =IF($G48="","",IF($H48=1,$G48-ROUND($G48*10/23,0)-2*ROUND($G48/23,0),IF($H48=2,$G48,0))) -> 99220 | K48: =IF($G48="","",IF($H48=1,ROUND($G48*10/23,0),IF($H48=3,$G48-2*ROUND($G48/12,0),IF($H48=4,$G48,IF(OR($H48=5,$H48=7),ROUND($G48*10/11,0),0))))) -> 0 | L48: =IF($G48="","",IF($H48=1,ROUND($G48/23,0),IF($H48=3,ROUND($G48/12,0),IF($H48=5,$G48-ROUND($G48*10/11,0),IF($H48=8,$G48,0))))) -> 0 | M48: =IF($G48="","",IF($H48=1,ROUND($G48/23,0),IF($H48=3,ROUND($G48/12,0),IF($H48=6,$G48,IF($H48=7,$G48-ROUND($G48*10/11,0),0))))) -> 0 | N48: =IF($G48="","",K48+L48+M48) -> 0 | O48: =IF($G48="","",IFERROR(VLOOKUP($D48&"|"&$E48,科目表!$A$5:$B$200,2,FALSE),"※未登録")) -> 図書印刷費 | P48: =IF(OR($G48="",$C48=""),"",IF($B48="決算整理",13,MOD(MONTH($C48)-4,12)+1)) -> 1 | Q48: =IF($G48="","",TRIM(IF(J48+K48+L48+M48<>$G48,"按分不一致 ","")&IF(O48="※未登録","科目未登録 ","")&IF(OR($H48="",ISERROR(MATCH($H48,{1,2,3,4,5,6,7,8},0))),"経費区分? ","")&IF($I48="","状態未設定 ","")&IF(AND(OR($I48="確認済",$I48="未確認"),$B48="月例",OR($C48="",$C48<DATE(年度+2018,4,1),$C48>DATE(年度+2019,3,31))),"年度外の日付 ","")&IF(AND(OR($I48="確認済",$I48="未確認"),O48="対象外"),"対象外の科目 ",""))) | R48: 月例!48
A49: 45 | B49: 月例 | C49: 46174 | D49: 負担金 | E49: 厚年負担金等 | F49: ４月月例分（短期分）子ども子育て拠出金を含む | G49: 62766 | H49: 2 | I49: 確認済 | J49: =IF($G49="","",IF($H49=1,$G49-ROUND($G49*10/23,0)-2*ROUND($G49/23,0),IF($H49=2,$G49,0))) -> 62766 | K49: =IF($G49="","",IF($H49=1,ROUND($G49*10/23,0),IF($H49=3,$G49-2*ROUND($G49/12,0),IF($H49=4,$G49,IF(OR($H49=5,$H49=7),ROUND($G49*10/11,0),0))))) -> 0 | L49: =IF($G49="","",IF($H49=1,ROUND($G49/23,0),IF($H49=3,ROUND($G49/12,0),IF($H49=5,$G49-ROUND($G49*10/11,0),IF($H49=8,$G49,0))))) -> 0 | M49: =IF($G49="","",IF($H49=1,ROUND($G49/23,0),IF($H49=3,ROUND($G49/12,0),IF($H49=6,$G49,IF($H49=7,$G49-ROUND($G49*10/11,0),0))))) -> 0 | N49: =IF($G49="","",K49+L49+M49) -> 0 | O49: =IF($G49="","",IFERROR(VLOOKUP($D49&"|"&$E49,科目表!$A$5:$B$200,2,FALSE),"※未登録")) -> 厚年負担金等 | P49: =IF(OR($G49="",$C49=""),"",IF($B49="決算整理",13,MOD(MONTH($C49)-4,12)+1)) -> 3 | Q49: =IF($G49="","",TRIM(IF(J49+K49+L49+M49<>$G49,"按分不一致 ","")&IF(O49="※未登録","科目未登録 ","")&IF(OR($H49="",ISERROR(MATCH($H49,{1,2,3,4,5,6,7,8},0))),"経費区分? ","")&IF($I49="","状態未設定 ","")&IF(AND(OR($I49="確認済",$I49="未確認"),$B49="月例",OR($C49="",$C49<DATE(年度+2018,4,1),$C49>DATE(年度+2019,3,31))),"年度外の日付 ","")&IF(AND(OR($I49="確認済",$I49="未確認"),O49="対象外"),"対象外の科目 ",""))) | R49: 月例!50
A50: 46 | B50: 月例 | C50: 46174 | D50: 負担金 | E50: 厚年負担金等 | F50: ４月月例分（長期分）子ども子育て拠出金を含む | G50: 37089 | H50: 3 | I50: 確認済 | J50: =IF($G50="","",IF($H50=1,$G50-ROUND($G50*10/23,0)-2*ROUND($G50/23,0),IF($H50=2,$G50,0))) -> 0 | K50: =IF($G50="","",IF($H50=1,ROUND($G50*10/23,0),IF($H50=3,$G50-2*ROUND($G50/12,0),IF($H50=4,$G50,IF(OR($H50=5,$H50=7),ROUND($G50*10/11,0),0))))) -> 30907 | L50: =IF($G50="","",IF($H50=1,ROUND($G50/23,0),IF($H50=3,ROUND($G50/12,0),IF($H50=5,$G50-ROUND($G50*10/11,0),IF($H50=8,$G50,0))))) -> 3091 | M50: =IF($G50="","",IF($H50=1,ROUND($G50/23,0),IF($H50=3,ROUND($G50/12,0),IF($H50=6,$G50,IF($H50=7,$G50-ROUND($G50*10/11,0),0))))) -> 3091 | N50: =IF($G50="","",K50+L50+M50) -> 37089 | O50: =IF($G50="","",IFERROR(VLOOKUP($D50&"|"&$E50,科目表!$A$5:$B$200,2,FALSE),"※未登録")) -> 厚年負担金等 | P50: =IF(OR($G50="",$C50=""),"",IF($B50="決算整理",13,MOD(MONTH($C50)-4,12)+1)) -> 3 | Q50: =IF($G50="","",TRIM(IF(J50+K50+L50+M50<>$G50,"按分不一致 ","")&IF(O50="※未登録","科目未登録 ","")&IF(OR($H50="",ISERROR(MATCH($H50,{1,2,3,4,5,6,7,8},0))),"経費区分? ","")&IF($I50="","状態未設定 ","")&IF(AND(OR($I50="確認済",$I50="未確認"),$B50="月例",OR($C50="",$C50<DATE(年度+2018,4,1),$C50>DATE(年度+2019,3,31))),"年度外の日付 ","")&IF(AND(OR($I50="確認済",$I50="未確認"),O50="対象外"),"対象外の科目 ",""))) | R50: 月例!52
A51: 47 | B51: 月例 | C51: 46171 | D51: 事務費 | E51: 図書印刷費 | F51: 厚生法規総覧追録６０９６－６１０５号 | G51: 33154 | H51: 2 | I51: 確認済 | J51: =IF($G51="","",IF($H51=1,$G51-ROUND($G51*10/23,0)-2*ROUND($G51/23,0),IF($H51=2,$G51,0))) -> 33154 | K51: =IF($G51="","",IF($H51=1,ROUND($G51*10/23,0),IF($H51=3,$G51-2*ROUND($G51/12,0),IF($H51=4,$G51,IF(OR($H51=5,$H51=7),ROUND($G51*10/11,0),0))))) -> 0 | L51: =IF($G51="","",IF($H51=1,ROUND($G51/23,0),IF($H51=3,ROUND($G51/12,0),IF($H51=5,$G51-ROUND($G51*10/11,0),IF($H51=8,$G51,0))))) -> 0 | M51: =IF($G51="","",IF($H51=1,ROUND($G51/23,0),IF($H51=3,ROUND($G51/12,0),IF($H51=6,$G51,IF($H51=7,$G51-ROUND($G51*10/11,0),0))))) -> 0 | N51: =IF($G51="","",K51+L51+M51) -> 0 | O51: =IF($G51="","",IFERROR(VLOOKUP($D51&"|"&$E51,科目表!$A$5:$B$200,2,FALSE),"※未登録")) -> 図書印刷費 | P51: =IF(OR($G51="",$C51=""),"",IF($B51="決算整理",13,MOD(MONTH($C51)-4,12)+1)) -> 2 | Q51: =IF($G51="","",TRIM(IF(J51+K51+L51+M51<>$G51,"按分不一致 ","")&IF(O51="※未登録","科目未登録 ","")&IF(OR($H51="",ISERROR(MATCH($H51,{1,2,3,4,5,6,7,8},0))),"経費区分? ","")&IF($I51="","状態未設定 ","")&IF(AND(OR($I51="確認済",$I51="未確認"),$B51="月例",OR($C51="",$C51<DATE(年度+2018,4,1),$C51>DATE(年度+2019,3,31))),"年度外の日付 ","")&IF(AND(OR($I51="確認済",$I51="未確認"),O51="対象外"),"対象外の科目 ",""))) | R51: 月例!53
A52: 48 | B52: 月例 | C52: 45077 | D52: 事務費 | E52: 通信運搬費 | F52: 柔整申請書送付（４月分） | G52: 1489 | H52: 2 | I52: 昨年実績 | J52: =IF($G52="","",IF($H52=1,$G52-ROUND($G52*10/23,0)-2*ROUND($G52/23,0),IF($H52=2,$G52,0))) -> 1489 | K52: =IF($G52="","",IF($H52=1,ROUND($G52*10/23,0),IF($H52=3,$G52-2*ROUND($G52/12,0),IF($H52=4,$G52,IF(OR($H52=5,$H52=7),ROUND($G52*10/11,0),0))))) -> 0 | L52: =IF($G52="","",IF($H52=1,ROUND($G52/23,0),IF($H52=3,ROUND($G52/12,0),IF($H52=5,$G52-ROUND($G52*10/11,0),IF($H52=8,$G52,0))))) -> 0 | M52: =IF($G52="","",IF($H52=1,ROUND($G52/23,0),IF($H52=3,ROUND($G52/12,0),IF($H52=6,$G52,IF($H52=7,$G52-ROUND($G52*10/11,0),0))))) -> 0 | N52: =IF($G52="","",K52+L52+M52) -> 0 | O52: =IF($G52="","",IFERROR(VLOOKUP($D52&"|"&$E52,科目表!$A$5:$B$200,2,FALSE),"※未登録")) -> 通信運搬費 | P52: =IF(OR($G52="",$C52=""),"",IF($B52="決算整理",13,MOD(MONTH($C52)-4,12)+1)) -> 2 | Q52: =IF($G52="","",TRIM(IF(J52+K52+L52+M52<>$G52,"按分不一致 ","")&IF(O52="※未登録","科目未登録 ","")&IF(OR($H52="",ISERROR(MATCH($H52,{1,2,3,4,5,6,7,8},0))),"経費区分? ","")&IF($I52="","状態未設定 ","")&IF(AND(OR($I52="確認済",$I52="未確認"),$B52="月例",OR($C52="",$C52<DATE(年度+2018,4,1),$C52>DATE(年度+2019,3,31))),"年度外の日付 ","")&IF(AND(OR($I52="確認済",$I52="未確認"),O52="対象外"),"対象外の科目 ",""))) | R52: 月例!54
A53: 49 | B53: 月例 | C53: 43980 | D53: 事務費 | E53: 通信運搬費 | F53: メール便（４月分） | G53: 6636 | H53: 2 | I53: 昨年実績 | J53: =IF($G53="","",IF($H53=1,$G53-ROUND($G53*10/23,0)-2*ROUND($G53/23,0),IF($H53=2,$G53,0))) -> 6636 | K53: =IF($G53="","",IF($H53=1,ROUND($G53*10/23,0),IF($H53=3,$G53-2*ROUND($G53/12,0),IF($H53=4,$G53,IF(OR($H53=5,$H53=7),ROUND($G53*10/11,0),0))))) -> 0 | L53: =IF($G53="","",IF($H53=1,ROUND($G53/23,0),IF($H53=3,ROUND($G53/12,0),IF($H53=5,$G53-ROUND($G53*10/11,0),IF($H53=8,$G53,0))))) -> 0 | M53: =IF($G53="","",IF($H53=1,ROUND($G53/23,0),IF($H53=3,ROUND($G53/12,0),IF($H53=6,$G53,IF($H53=7,$G53-ROUND($G53*10/11,0),0))))) -> 0 | N53: =IF($G53="","",K53+L53+M53) -> 0 | O53: =IF($G53="","",IFERROR(VLOOKUP($D53&"|"&$E53,科目表!$A$5:$B$200,2,FALSE),"※未登録")) -> 通信運搬費 | P53: =IF(OR($G53="",$C53=""),"",IF($B53="決算整理",13,MOD(MONTH($C53)-4,12)+1)) -> 2 | Q53: =IF($G53="","",TRIM(IF(J53+K53+L53+M53<>$G53,"按分不一致 ","")&IF(O53="※未登録","科目未登録 ","")&IF(OR($H53="",ISERROR(MATCH($H53,{1,2,3,4,5,6,7,8},0))),"経費区分? ","")&IF($I53="","状態未設定 ","")&IF(AND(OR($I53="確認済",$I53="未確認"),$B53="月例",OR($C53="",$C53<DATE(年度+2018,4,1),$C53>DATE(年度+2019,3,31))),"年度外の日付 ","")&IF(AND(OR($I53="確認済",$I53="未確認"),O53="対象外"),"対象外の科目 ",""))) | R53: 月例!55
A54: 50 | B54: 月例 | C54: 45077 | D54: 事務費 | E54: 通信運搬費 | F54: メール便（任継者宛厚生だより４月分） | G54: 17220 | H54: 2 | I54: 昨年実績 | J54: =IF($G54="","",IF($H54=1,$G54-ROUND($G54*10/23,0)-2*ROUND($G54/23,0),IF($H54=2,$G54,0))) -> 17220 | K54: =IF($G54="","",IF($H54=1,ROUND($G54*10/23,0),IF($H54=3,$G54-2*ROUND($G54/12,0),IF($H54=4,$G54,IF(OR($H54=5,$H54=7),ROUND($G54*10/11,0),0))))) -> 0 | L54: =IF($G54="","",IF($H54=1,ROUND($G54/23,0),IF($H54=3,ROUND($G54/12,0),IF($H54=5,$G54-ROUND($G54*10/11,0),IF($H54=8,$G54,0))))) -> 0 | M54: =IF($G54="","",IF($H54=1,ROUND($G54/23,0),IF($H54=3,ROUND($G54/12,0),IF($H54=6,$G54,IF($H54=7,$G54-ROUND($G54*10/11,0),0))))) -> 0 | N54: =IF($G54="","",K54+L54+M54) -> 0 | O54: =IF($G54="","",IFERROR(VLOOKUP($D54&"|"&$E54,科目表!$A$5:$B$200,2,FALSE),"※未登録")) -> 通信運搬費 | P54: =IF(OR($G54="",$C54=""),"",IF($B54="決算整理",13,MOD(MONTH($C54)-4,12)+1)) -> 2 | Q54: =IF($G54="","",TRIM(IF(J54+K54+L54+M54<>$G54,"按分不一致 ","")&IF(O54="※未登録","科目未登録 ","")&IF(OR($H54="",ISERROR(MATCH($H54,{1,2,3,4,5,6,7,8},0))),"経費区分? ","")&IF($I54="","状態未設定 ","")&IF(AND(OR($I54="確認済",$I54="未確認"),$B54="月例",OR($C54="",$C54<DATE(年度+2018,4,1),$C54>DATE(年度+2019,3,31))),"年度外の日付 ","")&IF(AND(OR($I54="確認済",$I54="未確認"),O54="対象外"),"対象外の科目 ",""))) | R54: 月例!56
A55: 51 | B55: 月例 | C55: 46171 | D55: 賃借料 | F55: 基幹システム用機器賃借料 4月分（短期） | G55: 672934 | H55: 2 | I55: 確認済 | J55: =IF($G55="","",IF($H55=1,$G55-ROUND($G55*10/23,0)-2*ROUND($G55/23,0),IF($H55=2,$G55,0))) -> 672934 | K55: =IF($G55="","",IF($H55=1,ROUND($G55*10/23,0),IF($H55=3,$G55-2*ROUND($G55/12,0),IF($H55=4,$G55,IF(OR($H55=5,$H55=7),ROUND($G55*10/11,0),0))))) -> 0 | L55: =IF($G55="","",IF($H55=1,ROUND($G55/23,0),IF($H55=3,ROUND($G55/12,0),IF($H55=5,$G55-ROUND($G55*10/11,0),IF($H55=8,$G55,0))))) -> 0 | M55: =IF($G55="","",IF($H55=1,ROUND($G55/23,0),IF($H55=3,ROUND($G55/12,0),IF($H55=6,$G55,IF($H55=7,$G55-ROUND($G55*10/11,0),0))))) -> 0 | N55: =IF($G55="","",K55+L55+M55) -> 0 | O55: =IF($G55="","",IFERROR(VLOOKUP($D55&"|"&$E55,科目表!$A$5:$B$200,2,FALSE),"※未登録")) -> 賃借料 | P55: =IF(OR($G55="",$C55=""),"",IF($B55="決算整理",13,MOD(MONTH($C55)-4,12)+1)) -> 2 | Q55: =IF($G55="","",TRIM(IF(J55+K55+L55+M55<>$G55,"按分不一致 ","")&IF(O55="※未登録","科目未登録 ","")&IF(OR($H55="",ISERROR(MATCH($H55,{1,2,3,4,5,6,7,8},0))),"経費区分? ","")&IF($I55="","状態未設定 ","")&IF(AND(OR($I55="確認済",$I55="未確認"),$B55="月例",OR($C55="",$C55<DATE(年度+2018,4,1),$C55>DATE(年度+2019,3,31))),"年度外の日付 ","")&IF(AND(OR($I55="確認済",$I55="未確認"),O55="対象外"),"対象外の科目 ",""))) | R55: 月例!57
A56: 52 | B56: 月例 | C56: 46171 | D56: 賃借料 | F56: 基幹システム用機器賃借料 4月分（長期） | G56: 69613 | H56: 3 | I56: 確認済 | J56: =IF($G56="","",IF($H56=1,$G56-ROUND($G56*10/23,0)-2*ROUND($G56/23,0),IF($H56=2,$G56,0))) -> 0 | K56: =IF($G56="","",IF($H56=1,ROUND($G56*10/23,0),IF($H56=3,$G56-2*ROUND($G56/12,0),IF($H56=4,$G56,IF(OR($H56=5,$H56=7),ROUND($G56*10/11,0),0))))) -> 58011 | L56: =IF($G56="","",IF($H56=1,ROUND($G56/23,0),IF($H56=3,ROUND($G56/12,0),IF($H56=5,$G56-ROUND($G56*10/11,0),IF($H56=8,$G56,0))))) -> 5801 | M56: =IF($G56="","",IF($H56=1,ROUND($G56/23,0),IF($H56=3,ROUND($G56/12,0),IF($H56=6,$G56,IF($H56=7,$G56-ROUND($G56*10/11,0),0))))) -> 5801 | N56: =IF($G56="","",K56+L56+M56) -> 69613 | O56: =IF($G56="","",IFERROR(VLOOKUP($D56&"|"&$E56,科目表!$A$5:$B$200,2,FALSE),"※未登録")) -> 賃借料 | P56: =IF(OR($G56="",$C56=""),"",IF($B56="決算整理",13,MOD(MONTH($C56)-4,12)+1)) -> 2 | Q56: =IF($G56="","",TRIM(IF(J56+K56+L56+M56<>$G56,"按分不一致 ","")&IF(O56="※未登録","科目未登録 ","")&IF(OR($H56="",ISERROR(MATCH($H56,{1,2,3,4,5,6,7,8},0))),"経費区分? ","")&IF($I56="","状態未設定 ","")&IF(AND(OR($I56="確認済",$I56="未確認"),$B56="月例",OR($C56="",$C56<DATE(年度+2018,4,1),$C56>DATE(年度+2019,3,31))),"年度外の日付 ","")&IF(AND(OR($I56="確認済",$I56="未確認"),O56="対象外"),"対象外の科目 ",""))) | R56: 月例!58
A57: 53 | B57: 月例 | C57: 46171 | D57: 委託費 | F57: 柔整等療養費支給申請書の入力（４月分） | G57: 137918 | H57: 2 | I57: 確認済 | J57: =IF($G57="","",IF($H57=1,$G57-ROUND($G57*10/23,0)-2*ROUND($G57/23,0),IF($H57=2,$G57,0))) -> 137918 | K57: =IF($G57="","",IF($H57=1,ROUND($G57*10/23,0),IF($H57=3,$G57-2*ROUND($G57/12,0),IF($H57=4,$G57,IF(OR($H57=5,$H57=7),ROUND($G57*10/11,0),0))))) -> 0 | L57: =IF($G57="","",IF($H57=1,ROUND($G57/23,0),IF($H57=3,ROUND($G57/12,0),IF($H57=5,$G57-ROUND($G57*10/11,0),IF($H57=8,$G57,0))))) -> 0 | M57: =IF($G57="","",IF($H57=1,ROUND($G57/23,0),IF($H57=3,ROUND($G57/12,0),IF($H57=6,$G57,IF($H57=7,$G57-ROUND($G57*10/11,0),0))))) -> 0 | N57: =IF($G57="","",K57+L57+M57) -> 0 | O57: =IF($G57="","",IFERROR(VLOOKUP($D57&"|"&$E57,科目表!$A$5:$B$200,2,FALSE),"※未登録")) -> 委託費 | P57: =IF(OR($G57="",$C57=""),"",IF($B57="決算整理",13,MOD(MONTH($C57)-4,12)+1)) -> 2 | Q57: =IF($G57="","",TRIM(IF(J57+K57+L57+M57<>$G57,"按分不一致 ","")&IF(O57="※未登録","科目未登録 ","")&IF(OR($H57="",ISERROR(MATCH($H57,{1,2,3,4,5,6,7,8},0))),"経費区分? ","")&IF($I57="","状態未設定 ","")&IF(AND(OR($I57="確認済",$I57="未確認"),$B57="月例",OR($C57="",$C57<DATE(年度+2018,4,1),$C57>DATE(年度+2019,3,31))),"年度外の日付 ","")&IF(AND(OR($I57="確認済",$I57="未確認"),O57="対象外"),"対象外の科目 ",""))) | R57: 月例!59
A58: 54 | B58: 月例 | C58: 45443 | D58: 委託費 | F58: 柔整等療養費支給申請書の入力（４月分） | G58: 70730 | H58: 2 | I58: 昨年実績 | J58: =IF($G58="","",IF($H58=1,$G58-ROUND($G58*10/23,0)-2*ROUND($G58/23,0),IF($H58=2,$G58,0))) -> 70730 | K58: =IF($G58="","",IF($H58=1,ROUND($G58*10/23,0),IF($H58=3,$G58-2*ROUND($G58/12,0),IF($H58=4,$G58,IF(OR($H58=5,$H58=7),ROUND($G58*10/11,0),0))))) -> 0 | L58: =IF($G58="","",IF($H58=1,ROUND($G58/23,0),IF($H58=3,ROUND($G58/12,0),IF($H58=5,$G58-ROUND($G58*10/11,0),IF($H58=8,$G58,0))))) -> 0 | M58: =IF($G58="","",IF($H58=1,ROUND($G58/23,0),IF($H58=3,ROUND($G58/12,0),IF($H58=6,$G58,IF($H58=7,$G58-ROUND($G58*10/11,0),0))))) -> 0 | N58: =IF($G58="","",K58+L58+M58) -> 0 | O58: =IF($G58="","",IFERROR(VLOOKUP($D58&"|"&$E58,科目表!$A$5:$B$200,2,FALSE),"※未登録")) -> 委託費 | P58: =IF(OR($G58="",$C58=""),"",IF($B58="決算整理",13,MOD(MONTH($C58)-4,12)+1)) -> 2 | Q58: =IF($G58="","",TRIM(IF(J58+K58+L58+M58<>$G58,"按分不一致 ","")&IF(O58="※未登録","科目未登録 ","")&IF(OR($H58="",ISERROR(MATCH($H58,{1,2,3,4,5,6,7,8},0))),"経費区分? ","")&IF($I58="","状態未設定 ","")&IF(AND(OR($I58="確認済",$I58="未確認"),$B58="月例",OR($C58="",$C58<DATE(年度+2018,4,1),$C58>DATE(年度+2019,3,31))),"年度外の日付 ","")&IF(AND(OR($I58="確認済",$I58="未確認"),O58="対象外"),"対象外の科目 ",""))) | R58: 月例!60
A59: 55 | B59: 月例 | C59: 45810 | D59: 事務費 | E59: 通信運搬費 | F59: フレッツ光ネクスト利用料等（４月利用・５月請求分） | G59: 5126 | H59: 2 | I59: 昨年実績 | J59: =IF($G59="","",IF($H59=1,$G59-ROUND($G59*10/23,0)-2*ROUND($G59/23,0),IF($H59=2,$G59,0))) -> 5126 | K59: =IF($G59="","",IF($H59=1,ROUND($G59*10/23,0),IF($H59=3,$G59-2*ROUND($G59/12,0),IF($H59=4,$G59,IF(OR($H59=5,$H59=7),ROUND($G59*10/11,0),0))))) -> 0 | L59: =IF($G59="","",IF($H59=1,ROUND($G59/23,0),IF($H59=3,ROUND($G59/12,0),IF($H59=5,$G59-ROUND($G59*10/11,0),IF($H59=8,$G59,0))))) -> 0 | M59: =IF($G59="","",IF($H59=1,ROUND($G59/23,0),IF($H59=3,ROUND($G59/12,0),IF($H59=6,$G59,IF($H59=7,$G59-ROUND($G59*10/11,0),0))))) -> 0 | N59: =IF($G59="","",K59+L59+M59) -> 0 | O59: =IF($G59="","",IFERROR(VLOOKUP($D59&"|"&$E59,科目表!$A$5:$B$200,2,FALSE),"※未登録")) -> 通信運搬費 | P59: =IF(OR($G59="",$C59=""),"",IF($B59="決算整理",13,MOD(MONTH($C59)-4,12)+1)) -> 3 | Q59: =IF($G59="","",TRIM(IF(J59+K59+L59+M59<>$G59,"按分不一致 ","")&IF(O59="※未登録","科目未登録 ","")&IF(OR($H59="",ISERROR(MATCH($H59,{1,2,3,4,5,6,7,8},0))),"経費区分? ","")&IF($I59="","状態未設定 ","")&IF(AND(OR($I59="確認済",$I59="未確認"),$B59="月例",OR($C59="",$C59<DATE(年度+2018,4,1),$C59>DATE(年度+2019,3,31))),"年度外の日付 ","")&IF(AND(OR($I59="確認済",$I59="未確認"),O59="対象外"),"対象外の科目 ",""))) | R59: 月例!61
A60: 56 | B60: 月例 | C60: 46174 | D60: 事務費 | E60: 通信運搬費 | F60: インターネット通信料金（３月、４月使用・５月請求分） | G60: 3663 | H60: 2 | I60: 確認済 | J60: =IF($G60="","",IF($H60=1,$G60-ROUND($G60*10/23,0)-2*ROUND($G60/23,0),IF($H60=2,$G60,0))) -> 3663 | K60: =IF($G60="","",IF($H60=1,ROUND($G60*10/23,0),IF($H60=3,$G60-2*ROUND($G60/12,0),IF($H60=4,$G60,IF(OR($H60=5,$H60=7),ROUND($G60*10/11,0),0))))) -> 0 | L60: =IF($G60="","",IF($H60=1,ROUND($G60/23,0),IF($H60=3,ROUND($G60/12,0),IF($H60=5,$G60-ROUND($G60*10/11,0),IF($H60=8,$G60,0))))) -> 0 | M60: =IF($G60="","",IF($H60=1,ROUND($G60/23,0),IF($H60=3,ROUND($G60/12,0),IF($H60=6,$G60,IF($H60=7,$G60-ROUND($G60*10/11,0),0))))) -> 0 | N60: =IF($G60="","",K60+L60+M60) -> 0 | O60: =IF($G60="","",IFERROR(VLOOKUP($D60&"|"&$E60,科目表!$A$5:$B$200,2,FALSE),"※未登録")) -> 通信運搬費 | P60: =IF(OR($G60="",$C60=""),"",IF($B60="決算整理",13,MOD(MONTH($C60)-4,12)+1)) -> 3 | Q60: =IF($G60="","",TRIM(IF(J60+K60+L60+M60<>$G60,"按分不一致 ","")&IF(O60="※未登録","科目未登録 ","")&IF(OR($H60="",ISERROR(MATCH($H60,{1,2,3,4,5,6,7,8},0))),"経費区分? ","")&IF($I60="","状態未設定 ","")&IF(AND(OR($I60="確認済",$I60="未確認"),$B60="月例",OR($C60="",$C60<DATE(年度+2018,4,1),$C60>DATE(年度+2019,3,31))),"年度外の日付 ","")&IF(AND(OR($I60="確認済",$I60="未確認"),O60="対象外"),"対象外の科目 ",""))) | R60: 月例!62
A61: 57 | B61: 月例 | C61: 46171 | D61: 事務費 | E61: 事務用消耗品費 | F61: 鋳造ゴム印 3号以下 147字 他 | G61: 14040 | H61: 3 | I61: 確認済 | J61: =IF($G61="","",IF($H61=1,$G61-ROUND($G61*10/23,0)-2*ROUND($G61/23,0),IF($H61=2,$G61,0))) -> 0 | K61: =IF($G61="","",IF($H61=1,ROUND($G61*10/23,0),IF($H61=3,$G61-2*ROUND($G61/12,0),IF($H61=4,$G61,IF(OR($H61=5,$H61=7),ROUND($G61*10/11,0),0))))) -> 11700 | L61: =IF($G61="","",IF($H61=1,ROUND($G61/23,0),IF($H61=3,ROUND($G61/12,0),IF($H61=5,$G61-ROUND($G61*10/11,0),IF($H61=8,$G61,0))))) -> 1170 | M61: =IF($G61="","",IF($H61=1,ROUND($G61/23,0),IF($H61=3,ROUND($G61/12,0),IF($H61=6,$G61,IF($H61=7,$G61-ROUND($G61*10/11,0),0))))) -> 1170 | N61: =IF($G61="","",K61+L61+M61) -> 14040 | O61: =IF($G61="","",IFERROR(VLOOKUP($D61&"|"&$E61,科目表!$A$5:$B$200,2,FALSE),"※未登録")) -> 事務用消耗品費 | P61: =IF(OR($G61="",$C61=""),"",IF($B61="決算整理",13,MOD(MONTH($C61)-4,12)+1)) -> 2 | Q61: =IF($G61="","",TRIM(IF(J61+K61+L61+M61<>$G61,"按分不一致 ","")&IF(O61="※未登録","科目未登録 ","")&IF(OR($H61="",ISERROR(MATCH($H61,{1,2,3,4,5,6,7,8},0))),"経費区分? ","")&IF($I61="","状態未設定 ","")&IF(AND(OR($I61="確認済",$I61="未確認"),$B61="月例",OR($C61="",$C61<DATE(年度+2018,4,1),$C61>DATE(年度+2019,3,31))),"年度外の日付 ","")&IF(AND(OR($I61="確認済",$I61="未確認"),O61="対象外"),"対象外の科目 ",""))) | R61: 月例!63
A62: 58 | B62: 月例 | C62: 45412 | D62: 事務費 | E62: 事務用消耗品費 | F62: 令和６年度基幹ウイルス対策ソフト（ミツイワ株式会社） | G62: 21450 | H62: 2 | I62: 昨年実績 | J62: =IF($G62="","",IF($H62=1,$G62-ROUND($G62*10/23,0)-2*ROUND($G62/23,0),IF($H62=2,$G62,0))) -> 21450 | K62: =IF($G62="","",IF($H62=1,ROUND($G62*10/23,0),IF($H62=3,$G62-2*ROUND($G62/12,0),IF($H62=4,$G62,IF(OR($H62=5,$H62=7),ROUND($G62*10/11,0),0))))) -> 0 | L62: =IF($G62="","",IF($H62=1,ROUND($G62/23,0),IF($H62=3,ROUND($G62/12,0),IF($H62=5,$G62-ROUND($G62*10/11,0),IF($H62=8,$G62,0))))) -> 0 | M62: =IF($G62="","",IF($H62=1,ROUND($G62/23,0),IF($H62=3,ROUND($G62/12,0),IF($H62=6,$G62,IF($H62=7,$G62-ROUND($G62*10/11,0),0))))) -> 0 | N62: =IF($G62="","",K62+L62+M62) -> 0 | O62: =IF($G62="","",IFERROR(VLOOKUP($D62&"|"&$E62,科目表!$A$5:$B$200,2,FALSE),"※未登録")) -> 事務用消耗品費 | P62: =IF(OR($G62="",$C62=""),"",IF($B62="決算整理",13,MOD(MONTH($C62)-4,12)+1)) -> 1 | Q62: =IF($G62="","",TRIM(IF(J62+K62+L62+M62<>$G62,"按分不一致 ","")&IF(O62="※未登録","科目未登録 ","")&IF(OR($H62="",ISERROR(MATCH($H62,{1,2,3,4,5,6,7,8},0))),"経費区分? ","")&IF($I62="","状態未設定 ","")&IF(AND(OR($I62="確認済",$I62="未確認"),$B62="月例",OR($C62="",$C62<DATE(年度+2018,4,1),$C62>DATE(年度+2019,3,31))),"年度外の日付 ","")&IF(AND(OR($I62="確認済",$I62="未確認"),O62="対象外"),"対象外の科目 ",""))) | R62: 月例!64
A63: 59 | B63: 月例 | C63: 45443 | D63: 事務費 | E63: 事務用消耗品費 | F63: 保存ボックス 4370 50個 | G63: 29650 | H63: 2 | I63: 昨年実績 | J63: =IF($G63="","",IF($H63=1,$G63-ROUND($G63*10/23,0)-2*ROUND($G63/23,0),IF($H63=2,$G63,0))) -> 29650 | K63: =IF($G63="","",IF($H63=1,ROUND($G63*10/23,0),IF($H63=3,$G63-2*ROUND($G63/12,0),IF($H63=4,$G63,IF(OR($H63=5,$H63=7),ROUND($G63*10/11,0),0))))) -> 0 | L63: =IF($G63="","",IF($H63=1,ROUND($G63/23,0),IF($H63=3,ROUND($G63/12,0),IF($H63=5,$G63-ROUND($G63*10/11,0),IF($H63=8,$G63,0))))) -> 0 | M63: =IF($G63="","",IF($H63=1,ROUND($G63/23,0),IF($H63=3,ROUND($G63/12,0),IF($H63=6,$G63,IF($H63=7,$G63-ROUND($G63*10/11,0),0))))) -> 0 | N63: =IF($G63="","",K63+L63+M63) -> 0 | O63: =IF($G63="","",IFERROR(VLOOKUP($D63&"|"&$E63,科目表!$A$5:$B$200,2,FALSE),"※未登録")) -> 事務用消耗品費 | P63: =IF(OR($G63="",$C63=""),"",IF($B63="決算整理",13,MOD(MONTH($C63)-4,12)+1)) -> 2 | Q63: =IF($G63="","",TRIM(IF(J63+K63+L63+M63<>$G63,"按分不一致 ","")&IF(O63="※未登録","科目未登録 ","")&IF(OR($H63="",ISERROR(MATCH($H63,{1,2,3,4,5,6,7,8},0))),"経費区分? ","")&IF($I63="","状態未設定 ","")&IF(AND(OR($I63="確認済",$I63="未確認"),$B63="月例",OR($C63="",$C63<DATE(年度+2018,4,1),$C63>DATE(年度+2019,3,31))),"年度外の日付 ","")&IF(AND(OR($I63="確認済",$I63="未確認"),O63="対象外"),"対象外の科目 ",""))) | R63: 月例!65
A64: 60 | B64: 月例 | C64: 46176 | D64: 事務費 | E64: 図書印刷費 | F64: 国家公務員等共済組合関係法令要覧追録５３５－５３８号 | G64: 17600 | H64: 3 | I64: 確認済 | J64: =IF($G64="","",IF($H64=1,$G64-ROUND($G64*10/23,0)-2*ROUND($G64/23,0),IF($H64=2,$G64,0))) -> 0 | K64: =IF($G64="","",IF($H64=1,ROUND($G64*10/23,0),IF($H64=3,$G64-2*ROUND($G64/12,0),IF($H64=4,$G64,IF(OR($H64=5,$H64=7),ROUND($G64*10/11,0),0))))) -> 14666 | L64: =IF($G64="","",IF($H64=1,ROUND($G64/23,0),IF($H64=3,ROUND($G64/12,0),IF($H64=5,$G64-ROUND($G64*10/11,0),IF($H64=8,$G64,0))))) -> 1467 | M64: =IF($G64="","",IF($H64=1,ROUND($G64/23,0),IF($H64=3,ROUND($G64/12,0),IF($H64=6,$G64,IF($H64=7,$G64-ROUND($G64*10/11,0),0))))) -> 1467 | N64: =IF($G64="","",K64+L64+M64) -> 17600 | O64: =IF($G64="","",IFERROR(VLOOKUP($D64&"|"&$E64,科目表!$A$5:$B$200,2,FALSE),"※未登録")) -> 図書印刷費 | P64: =IF(OR($G64="",$C64=""),"",IF($B64="決算整理",13,MOD(MONTH($C64)-4,12)+1)) -> 3 | Q64: =IF($G64="","",TRIM(IF(J64+K64+L64+M64<>$G64,"按分不一致 ","")&IF(O64="※未登録","科目未登録 ","")&IF(OR($H64="",ISERROR(MATCH($H64,{1,2,3,4,5,6,7,8},0))),"経費区分? ","")&IF($I64="","状態未設定 ","")&IF(AND(OR($I64="確認済",$I64="未確認"),$B64="月例",OR($C64="",$C64<DATE(年度+2018,4,1),$C64>DATE(年度+2019,3,31))),"年度外の日付 ","")&IF(AND(OR($I64="確認済",$I64="未確認"),O64="対象外"),"対象外の科目 ",""))) | R64: 月例!66
A65: 61 | B65: 月例 | C65: 46181 | D65: 役員報酬 | F65: 業務監査６／８ 学識経験監事 栗栖 一雄 | G65: 11000 | H65: 1 | I65: 確認済 | J65: =IF($G65="","",IF($H65=1,$G65-ROUND($G65*10/23,0)-2*ROUND($G65/23,0),IF($H65=2,$G65,0))) -> 5261 | K65: =IF($G65="","",IF($H65=1,ROUND($G65*10/23,0),IF($H65=3,$G65-2*ROUND($G65/12,0),IF($H65=4,$G65,IF(OR($H65=5,$H65=7),ROUND($G65*10/11,0),0))))) -> 4783 | L65: =IF($G65="","",IF($H65=1,ROUND($G65/23,0),IF($H65=3,ROUND($G65/12,0),IF($H65=5,$G65-ROUND($G65*10/11,0),IF($H65=8,$G65,0))))) -> 478 | M65: =IF($G65="","",IF($H65=1,ROUND($G65/23,0),IF($H65=3,ROUND($G65/12,0),IF($H65=6,$G65,IF($H65=7,$G65-ROUND($G65*10/11,0),0))))) -> 478 | N65: =IF($G65="","",K65+L65+M65) -> 5739 | O65: =IF($G65="","",IFERROR(VLOOKUP($D65&"|"&$E65,科目表!$A$5:$B$200,2,FALSE),"※未登録")) -> 役員報酬 | P65: =IF(OR($G65="",$C65=""),"",IF($B65="決算整理",13,MOD(MONTH($C65)-4,12)+1)) -> 3 | Q65: =IF($G65="","",TRIM(IF(J65+K65+L65+M65<>$G65,"按分不一致 ","")&IF(O65="※未登録","科目未登録 ","")&IF(OR($H65="",ISERROR(MATCH($H65,{1,2,3,4,5,6,7,8},0))),"経費区分? ","")&IF($I65="","状態未設定 ","")&IF(AND(OR($I65="確認済",$I65="未確認"),$B65="月例",OR($C65="",$C65<DATE(年度+2018,4,1),$C65>DATE(年度+2019,3,31))),"年度外の日付 ","")&IF(AND(OR($I65="確認済",$I65="未確認"),O65="対象外"),"対象外の科目 ",""))) | R65: 月例!67
A66: 62 | B66: 月例 | C66: 46169 | D66: 負担金 | E66: 負担金 | F66: 共済短期・介護負担金（5月月例分）長期 | G66: 22035 | H66: 3 | I66: 確認済 | J66: =IF($G66="","",IF($H66=1,$G66-ROUND($G66*10/23,0)-2*ROUND($G66/23,0),IF($H66=2,$G66,0))) -> 0 | K66: =IF($G66="","",IF($H66=1,ROUND($G66*10/23,0),IF($H66=3,$G66-2*ROUND($G66/12,0),IF($H66=4,$G66,IF(OR($H66=5,$H66=7),ROUND($G66*10/11,0),0))))) -> 18363 | L66: =IF($G66="","",IF($H66=1,ROUND($G66/23,0),IF($H66=3,ROUND($G66/12,0),IF($H66=5,$G66-ROUND($G66*10/11,0),IF($H66=8,$G66,0))))) -> 1836 | M66: =IF($G66="","",IF($H66=1,ROUND($G66/23,0),IF($H66=3,ROUND($G66/12,0),IF($H66=6,$G66,IF($H66=7,$G66-ROUND($G66*10/11,0),0))))) -> 1836 | N66: =IF($G66="","",K66+L66+M66) -> 22035 | O66: =IF($G66="","",IFERROR(VLOOKUP($D66&"|"&$E66,科目表!$A$5:$B$200,2,FALSE),"※未登録")) -> 共済負担金等 | P66: =IF(OR($G66="",$C66=""),"",IF($B66="決算整理",13,MOD(MONTH($C66)-4,12)+1)) -> 2 | Q66: =IF($G66="","",TRIM(IF(J66+K66+L66+M66<>$G66,"按分不一致 ","")&IF(O66="※未登録","科目未登録 ","")&IF(OR($H66="",ISERROR(MATCH($H66,{1,2,3,4,5,6,7,8},0))),"経費区分? ","")&IF($I66="","状態未設定 ","")&IF(AND(OR($I66="確認済",$I66="未確認"),$B66="月例",OR($C66="",$C66<DATE(年度+2018,4,1),$C66>DATE(年度+2019,3,31))),"年度外の日付 ","")&IF(AND(OR($I66="確認済",$I66="未確認"),O66="対象外"),"対象外の科目 ",""))) | R66: 月例!68
A67: 63 | B67: 月例 | C67: 46169 | D67: 負担金 | E67: 負担金 | F67: 共済短期・介護負担金（5月月例分）短期 | G67: 37074 | H67: 2 | I67: 確認済 | J67: =IF($G67="","",IF($H67=1,$G67-ROUND($G67*10/23,0)-2*ROUND($G67/23,0),IF($H67=2,$G67,0))) -> 37074 | K67: =IF($G67="","",IF($H67=1,ROUND($G67*10/23,0),IF($H67=3,$G67-2*ROUND($G67/12,0),IF($H67=4,$G67,IF(OR($H67=5,$H67=7),ROUND($G67*10/11,0),0))))) -> 0 | L67: =IF($G67="","",IF($H67=1,ROUND($G67/23,0),IF($H67=3,ROUND($G67/12,0),IF($H67=5,$G67-ROUND($G67*10/11,0),IF($H67=8,$G67,0))))) -> 0 | M67: =IF($G67="","",IF($H67=1,ROUND($G67/23,0),IF($H67=3,ROUND($G67/12,0),IF($H67=6,$G67,IF($H67=7,$G67-ROUND($G67*10/11,0),0))))) -> 0 | N67: =IF($G67="","",K67+L67+M67) -> 0 | O67: =IF($G67="","",IFERROR(VLOOKUP($D67&"|"&$E67,科目表!$A$5:$B$200,2,FALSE),"※未登録")) -> 共済負担金等 | P67: =IF(OR($G67="",$C67=""),"",IF($B67="決算整理",13,MOD(MONTH($C67)-4,12)+1)) -> 2 | Q67: =IF($G67="","",TRIM(IF(J67+K67+L67+M67<>$G67,"按分不一致 ","")&IF(O67="※未登録","科目未登録 ","")&IF(OR($H67="",ISERROR(MATCH($H67,{1,2,3,4,5,6,7,8},0))),"経費区分? ","")&IF($I67="","状態未設定 ","")&IF(AND(OR($I67="確認済",$I67="未確認"),$B67="月例",OR($C67="",$C67<DATE(年度+2018,4,1),$C67>DATE(年度+2019,3,31))),"年度外の日付 ","")&IF(AND(OR($I67="確認済",$I67="未確認"),O67="対象外"),"対象外の科目 ",""))) | R67: 月例!69
A68: 64 | B68: 月例 | C68: 43622 | D68: 旅費 | F68: 6/10事務局長会議 特別区 胡子事務局長 | G68: 38020 | H68: 1 | I68: 昨年実績 | J68: =IF($G68="","",IF($H68=1,$G68-ROUND($G68*10/23,0)-2*ROUND($G68/23,0),IF($H68=2,$G68,0))) -> 18184 | K68: =IF($G68="","",IF($H68=1,ROUND($G68*10/23,0),IF($H68=3,$G68-2*ROUND($G68/12,0),IF($H68=4,$G68,IF(OR($H68=5,$H68=7),ROUND($G68*10/11,0),0))))) -> 16530 | L68: =IF($G68="","",IF($H68=1,ROUND($G68/23,0),IF($H68=3,ROUND($G68/12,0),IF($H68=5,$G68-ROUND($G68*10/11,0),IF($H68=8,$G68,0))))) -> 1653 | M68: =IF($G68="","",IF($H68=1,ROUND($G68/23,0),IF($H68=3,ROUND($G68/12,0),IF($H68=6,$G68,IF($H68=7,$G68-ROUND($G68*10/11,0),0))))) -> 1653 | N68: =IF($G68="","",K68+L68+M68) -> 19836 | O68: =IF($G68="","",IFERROR(VLOOKUP($D68&"|"&$E68,科目表!$A$5:$B$200,2,FALSE),"※未登録")) -> 旅費 | P68: =IF(OR($G68="",$C68=""),"",IF($B68="決算整理",13,MOD(MONTH($C68)-4,12)+1)) -> 3 | Q68: =IF($G68="","",TRIM(IF(J68+K68+L68+M68<>$G68,"按分不一致 ","")&IF(O68="※未登録","科目未登録 ","")&IF(OR($H68="",ISERROR(MATCH($H68,{1,2,3,4,5,6,7,8},0))),"経費区分? ","")&IF($I68="","状態未設定 ","")&IF(AND(OR($I68="確認済",$I68="未確認"),$B68="月例",OR($C68="",$C68<DATE(年度+2018,4,1),$C68>DATE(年度+2019,3,31))),"年度外の日付 ","")&IF(AND(OR($I68="確認済",$I68="未確認"),O68="対象外"),"対象外の科目 ",""))) | R68: 月例!70
A69: 65 | B69: 月例 | C69: 43635 | D69: 旅費 | F69: 6/21サーバー等説明会 福岡市 永山主事 | G69: 19040 | H69: 2 | I69: 昨年実績 | J69: =IF($G69="","",IF($H69=1,$G69-ROUND($G69*10/23,0)-2*ROUND($G69/23,0),IF($H69=2,$G69,0))) -> 19040 | K69: =IF($G69="","",IF($H69=1,ROUND($G69*10/23,0),IF($H69=3,$G69-2*ROUND($G69/12,0),IF($H69=4,$G69,IF(OR($H69=5,$H69=7),ROUND($G69*10/11,0),0))))) -> 0 | L69: =IF($G69="","",IF($H69=1,ROUND($G69/23,0),IF($H69=3,ROUND($G69/12,0),IF($H69=5,$G69-ROUND($G69*10/11,0),IF($H69=8,$G69,0))))) -> 0 | M69: =IF($G69="","",IF($H69=1,ROUND($G69/23,0),IF($H69=3,ROUND($G69/12,0),IF($H69=6,$G69,IF($H69=7,$G69-ROUND($G69*10/11,0),0))))) -> 0 | N69: =IF($G69="","",K69+L69+M69) -> 0 | O69: =IF($G69="","",IFERROR(VLOOKUP($D69&"|"&$E69,科目表!$A$5:$B$200,2,FALSE),"※未登録")) -> 旅費 | P69: =IF(OR($G69="",$C69=""),"",IF($B69="決算整理",13,MOD(MONTH($C69)-4,12)+1)) -> 3 | Q69: =IF($G69="","",TRIM(IF(J69+K69+L69+M69<>$G69,"按分不一致 ","")&IF(O69="※未登録","科目未登録 ","")&IF(OR($H69="",ISERROR(MATCH($H69,{1,2,3,4,5,6,7,8},0))),"経費区分? ","")&IF($I69="","状態未設定 ","")&IF(AND(OR($I69="確認済",$I69="未確認"),$B69="月例",OR($C69="",$C69<DATE(年度+2018,4,1),$C69>DATE(年度+2019,3,31))),"年度外の日付 ","")&IF(AND(OR($I69="確認済",$I69="未確認"),O69="対象外"),"対象外の科目 ",""))) | R69: 月例!71
A70: 66 | B70: 月例 | C70: 45805 | D70: 旅費 | F70: 6/2保健事業事務研修会 特別区 清水課長補佐 | G70: 37160 | H70: 2 | I70: 昨年実績 | J70: =IF($G70="","",IF($H70=1,$G70-ROUND($G70*10/23,0)-2*ROUND($G70/23,0),IF($H70=2,$G70,0))) -> 37160 | K70: =IF($G70="","",IF($H70=1,ROUND($G70*10/23,0),IF($H70=3,$G70-2*ROUND($G70/12,0),IF($H70=4,$G70,IF(OR($H70=5,$H70=7),ROUND($G70*10/11,0),0))))) -> 0 | L70: =IF($G70="","",IF($H70=1,ROUND($G70/23,0),IF($H70=3,ROUND($G70/12,0),IF($H70=5,$G70-ROUND($G70*10/11,0),IF($H70=8,$G70,0))))) -> 0 | M70: =IF($G70="","",IF($H70=1,ROUND($G70/23,0),IF($H70=3,ROUND($G70/12,0),IF($H70=6,$G70,IF($H70=7,$G70-ROUND($G70*10/11,0),0))))) -> 0 | N70: =IF($G70="","",K70+L70+M70) -> 0 | O70: =IF($G70="","",IFERROR(VLOOKUP($D70&"|"&$E70,科目表!$A$5:$B$200,2,FALSE),"※未登録")) -> 旅費 | P70: =IF(OR($G70="",$C70=""),"",IF($B70="決算整理",13,MOD(MONTH($C70)-4,12)+1)) -> 2 | Q70: =IF($G70="","",TRIM(IF(J70+K70+L70+M70<>$G70,"按分不一致 ","")&IF(O70="※未登録","科目未登録 ","")&IF(OR($H70="",ISERROR(MATCH($H70,{1,2,3,4,5,6,7,8},0))),"経費区分? ","")&IF($I70="","状態未設定 ","")&IF(AND(OR($I70="確認済",$I70="未確認"),$B70="月例",OR($C70="",$C70<DATE(年度+2018,4,1),$C70>DATE(年度+2019,3,31))),"年度外の日付 ","")&IF(AND(OR($I70="確認済",$I70="未確認"),O70="対象外"),"対象外の科目 ",""))) | R70: 月例!72
A71: 67 | B71: 月例 | C71: 45805 | D71: 旅費 | F71: 6/2保健事業事務研修会 特別区 上野主事 | G71: 37390 | H71: 2 | I71: 昨年実績 | J71: =IF($G71="","",IF($H71=1,$G71-ROUND($G71*10/23,0)-2*ROUND($G71/23,0),IF($H71=2,$G71,0))) -> 37390 | K71: =IF($G71="","",IF($H71=1,ROUND($G71*10/23,0),IF($H71=3,$G71-2*ROUND($G71/12,0),IF($H71=4,$G71,IF(OR($H71=5,$H71=7),ROUND($G71*10/11,0),0))))) -> 0 | L71: =IF($G71="","",IF($H71=1,ROUND($G71/23,0),IF($H71=3,ROUND($G71/12,0),IF($H71=5,$G71-ROUND($G71*10/11,0),IF($H71=8,$G71,0))))) -> 0 | M71: =IF($G71="","",IF($H71=1,ROUND($G71/23,0),IF($H71=3,ROUND($G71/12,0),IF($H71=6,$G71,IF($H71=7,$G71-ROUND($G71*10/11,0),0))))) -> 0 | N71: =IF($G71="","",K71+L71+M71) -> 0 | O71: =IF($G71="","",IFERROR(VLOOKUP($D71&"|"&$E71,科目表!$A$5:$B$200,2,FALSE),"※未登録")) -> 旅費 | P71: =IF(OR($G71="",$C71=""),"",IF($B71="決算整理",13,MOD(MONTH($C71)-4,12)+1)) -> 2 | Q71: =IF($G71="","",TRIM(IF(J71+K71+L71+M71<>$G71,"按分不一致 ","")&IF(O71="※未登録","科目未登録 ","")&IF(OR($H71="",ISERROR(MATCH($H71,{1,2,3,4,5,6,7,8},0))),"経費区分? ","")&IF($I71="","状態未設定 ","")&IF(AND(OR($I71="確認済",$I71="未確認"),$B71="月例",OR($C71="",$C71<DATE(年度+2018,4,1),$C71>DATE(年度+2019,3,31))),"年度外の日付 ","")&IF(AND(OR($I71="確認済",$I71="未確認"),O71="対象外"),"対象外の科目 ",""))) | R71: 月例!73
A72: 68 | B72: 月例 | C72: 43636 | D72: 旅費 | F72: 6/24～26 年金事務初任者研修会 特別区 梅谷主事 | G72: 63820 | H72: 3 | I72: 昨年実績 | J72: =IF($G72="","",IF($H72=1,$G72-ROUND($G72*10/23,0)-2*ROUND($G72/23,0),IF($H72=2,$G72,0))) -> 0 | K72: =IF($G72="","",IF($H72=1,ROUND($G72*10/23,0),IF($H72=3,$G72-2*ROUND($G72/12,0),IF($H72=4,$G72,IF(OR($H72=5,$H72=7),ROUND($G72*10/11,0),0))))) -> 53184 | L72: =IF($G72="","",IF($H72=1,ROUND($G72/23,0),IF($H72=3,ROUND($G72/12,0),IF($H72=5,$G72-ROUND($G72*10/11,0),IF($H72=8,$G72,0))))) -> 5318 | M72: =IF($G72="","",IF($H72=1,ROUND($G72/23,0),IF($H72=3,ROUND($G72/12,0),IF($H72=6,$G72,IF($H72=7,$G72-ROUND($G72*10/11,0),0))))) -> 5318 | N72: =IF($G72="","",K72+L72+M72) -> 63820 | O72: =IF($G72="","",IFERROR(VLOOKUP($D72&"|"&$E72,科目表!$A$5:$B$200,2,FALSE),"※未登録")) -> 旅費 | P72: =IF(OR($G72="",$C72=""),"",IF($B72="決算整理",13,MOD(MONTH($C72)-4,12)+1)) -> 3 | Q72: =IF($G72="","",TRIM(IF(J72+K72+L72+M72<>$G72,"按分不一致 ","")&IF(O72="※未登録","科目未登録 ","")&IF(OR($H72="",ISERROR(MATCH($H72,{1,2,3,4,5,6,7,8},0))),"経費区分? ","")&IF($I72="","状態未設定 ","")&IF(AND(OR($I72="確認済",$I72="未確認"),$B72="月例",OR($C72="",$C72<DATE(年度+2018,4,1),$C72>DATE(年度+2019,3,31))),"年度外の日付 ","")&IF(AND(OR($I72="確認済",$I72="未確認"),O72="対象外"),"対象外の科目 ",""))) | R72: 月例!74
A73: 69 | B73: 月例 | C73: 46178 | D73: 事務費負担金払込金 | F73: ５月分事務費負担金払込金と連合会交付金との相殺 | G73: 5366000 | H73: 5 | I73: 確認済 | J73: =IF($G73="","",IF($H73=1,$G73-ROUND($G73*10/23,0)-2*ROUND($G73/23,0),IF($H73=2,$G73,0))) -> 0 | K73: =IF($G73="","",IF($H73=1,ROUND($G73*10/23,0),IF($H73=3,$G73-2*ROUND($G73/12,0),IF($H73=4,$G73,IF(OR($H73=5,$H73=7),ROUND($G73*10/11,0),0))))) -> 4878182 | L73: =IF($G73="","",IF($H73=1,ROUND($G73/23,0),IF($H73=3,ROUND($G73/12,0),IF($H73=5,$G73-ROUND($G73*10/11,0),IF($H73=8,$G73,0))))) -> 487818 | M73: =IF($G73="","",IF($H73=1,ROUND($G73/23,0),IF($H73=3,ROUND($G73/12,0),IF($H73=6,$G73,IF($H73=7,$G73-ROUND($G73*10/11,0),0))))) -> 0 | N73: =IF($G73="","",K73+L73+M73) -> 5366000 | O73: =IF($G73="","",IFERROR(VLOOKUP($D73&"|"&$E73,科目表!$A$5:$B$200,2,FALSE),"※未登録")) -> 事務費負担金払込金 | P73: =IF(OR($G73="",$C73=""),"",IF($B73="決算整理",13,MOD(MONTH($C73)-4,12)+1)) -> 3 | Q73: =IF($G73="","",TRIM(IF(J73+K73+L73+M73<>$G73,"按分不一致 ","")&IF(O73="※未登録","科目未登録 ","")&IF(OR($H73="",ISERROR(MATCH($H73,{1,2,3,4,5,6,7,8},0))),"経費区分? ","")&IF($I73="","状態未設定 ","")&IF(AND(OR($I73="確認済",$I73="未確認"),$B73="月例",OR($C73="",$C73<DATE(年度+2018,4,1),$C73>DATE(年度+2019,3,31))),"年度外の日付 ","")&IF(AND(OR($I73="確認済",$I73="未確認"),O73="対象外"),"対象外の科目 ",""))) | R73: 月例!75
A74: 70 | B74: 月例 | C74: 45084 | D74: 事務費負担金払込金 | F74: ５月分事務費負担金払込金と連合会交付金との相殺 | G74: 3553000 | H74: 5 | I74: 昨年実績 | J74: =IF($G74="","",IF($H74=1,$G74-ROUND($G74*10/23,0)-2*ROUND($G74/23,0),IF($H74=2,$G74,0))) -> 0 | K74: =IF($G74="","",IF($H74=1,ROUND($G74*10/23,0),IF($H74=3,$G74-2*ROUND($G74/12,0),IF($H74=4,$G74,IF(OR($H74=5,$H74=7),ROUND($G74*10/11,0),0))))) -> 3230000 | L74: =IF($G74="","",IF($H74=1,ROUND($G74/23,0),IF($H74=3,ROUND($G74/12,0),IF($H74=5,$G74-ROUND($G74*10/11,0),IF($H74=8,$G74,0))))) -> 323000 | M74: =IF($G74="","",IF($H74=1,ROUND($G74/23,0),IF($H74=3,ROUND($G74/12,0),IF($H74=6,$G74,IF($H74=7,$G74-ROUND($G74*10/11,0),0))))) -> 0 | N74: =IF($G74="","",K74+L74+M74) -> 3553000 | O74: =IF($G74="","",IFERROR(VLOOKUP($D74&"|"&$E74,科目表!$A$5:$B$200,2,FALSE),"※未登録")) -> 事務費負担金払込金 | P74: =IF(OR($G74="",$C74=""),"",IF($B74="決算整理",13,MOD(MONTH($C74)-4,12)+1)) -> 3 | Q74: =IF($G74="","",TRIM(IF(J74+K74+L74+M74<>$G74,"按分不一致 ","")&IF(O74="※未登録","科目未登録 ","")&IF(OR($H74="",ISERROR(MATCH($H74,{1,2,3,4,5,6,7,8},0))),"経費区分? ","")&IF($I74="","状態未設定 ","")&IF(AND(OR($I74="確認済",$I74="未確認"),$B74="月例",OR($C74="",$C74<DATE(年度+2018,4,1),$C74>DATE(年度+2019,3,31))),"年度外の日付 ","")&IF(AND(OR($I74="確認済",$I74="未確認"),O74="対象外"),"対象外の科目 ",""))) | R74: 月例!76
A75: 71 | B75: 月例 | C75: 44718 | D75: 厚生費 | E75: 健康診断費 | F75: 健康診断費自己負担超分（一山） | G75: 1569 | H75: 2 | I75: 昨年実績 | J75: =IF($G75="","",IF($H75=1,$G75-ROUND($G75*10/23,0)-2*ROUND($G75/23,0),IF($H75=2,$G75,0))) -> 1569 | K75: =IF($G75="","",IF($H75=1,ROUND($G75*10/23,0),IF($H75=3,$G75-2*ROUND($G75/12,0),IF($H75=4,$G75,IF(OR($H75=5,$H75=7),ROUND($G75*10/11,0),0))))) -> 0 | L75: =IF($G75="","",IF($H75=1,ROUND($G75/23,0),IF($H75=3,ROUND($G75/12,0),IF($H75=5,$G75-ROUND($G75*10/11,0),IF($H75=8,$G75,0))))) -> 0 | M75: =IF($G75="","",IF($H75=1,ROUND($G75/23,0),IF($H75=3,ROUND($G75/12,0),IF($H75=6,$G75,IF($H75=7,$G75-ROUND($G75*10/11,0),0))))) -> 0 | N75: =IF($G75="","",K75+L75+M75) -> 0 | O75: =IF($G75="","",IFERROR(VLOOKUP($D75&"|"&$E75,科目表!$A$5:$B$200,2,FALSE),"※未登録")) -> 厚生費 | P75: =IF(OR($G75="",$C75=""),"",IF($B75="決算整理",13,MOD(MONTH($C75)-4,12)+1)) -> 3 | Q75: =IF($G75="","",TRIM(IF(J75+K75+L75+M75<>$G75,"按分不一致 ","")&IF(O75="※未登録","科目未登録 ","")&IF(OR($H75="",ISERROR(MATCH($H75,{1,2,3,4,5,6,7,8},0))),"経費区分? ","")&IF($I75="","状態未設定 ","")&IF(AND(OR($I75="確認済",$I75="未確認"),$B75="月例",OR($C75="",$C75<DATE(年度+2018,4,1),$C75>DATE(年度+2019,3,31))),"年度外の日付 ","")&IF(AND(OR($I75="確認済",$I75="未確認"),O75="対象外"),"対象外の科目 ",""))) | R75: 月例!77
A76: 72 | B76: 月例 | C76: 44708 | D76: 事務費 | E76: 雑費 | F76: ＪＡ残高証明書（手数料）R4.3.31時点 | G76: 220 | H76: 2 | I76: 昨年実績 | J76: =IF($G76="","",IF($H76=1,$G76-ROUND($G76*10/23,0)-2*ROUND($G76/23,0),IF($H76=2,$G76,0))) -> 220 | K76: =IF($G76="","",IF($H76=1,ROUND($G76*10/23,0),IF($H76=3,$G76-2*ROUND($G76/12,0),IF($H76=4,$G76,IF(OR($H76=5,$H76=7),ROUND($G76*10/11,0),0))))) -> 0 | L76: =IF($G76="","",IF($H76=1,ROUND($G76/23,0),IF($H76=3,ROUND($G76/12,0),IF($H76=5,$G76-ROUND($G76*10/11,0),IF($H76=8,$G76,0))))) -> 0 | M76: =IF($G76="","",IF($H76=1,ROUND($G76/23,0),IF($H76=3,ROUND($G76/12,0),IF($H76=6,$G76,IF($H76=7,$G76-ROUND($G76*10/11,0),0))))) -> 0 | N76: =IF($G76="","",K76+L76+M76) -> 0 | O76: =IF($G76="","",IFERROR(VLOOKUP($D76&"|"&$E76,科目表!$A$5:$B$200,2,FALSE),"※未登録")) -> 事務費・雑費 | P76: =IF(OR($G76="",$C76=""),"",IF($B76="決算整理",13,MOD(MONTH($C76)-4,12)+1)) -> 2 | Q76: =IF($G76="","",TRIM(IF(J76+K76+L76+M76<>$G76,"按分不一致 ","")&IF(O76="※未登録","科目未登録 ","")&IF(OR($H76="",ISERROR(MATCH($H76,{1,2,3,4,5,6,7,8},0))),"経費区分? ","")&IF($I76="","状態未設定 ","")&IF(AND(OR($I76="確認済",$I76="未確認"),$B76="月例",OR($C76="",$C76<DATE(年度+2018,4,1),$C76>DATE(年度+2019,3,31))),"年度外の日付 ","")&IF(AND(OR($I76="確認済",$I76="未確認"),O76="対象外"),"対象外の科目 ",""))) | R76: 月例!78
A77: 73 | B77: 月例 | C77: 44711 | D77: 負担金 | E77: 負担金 | F77: 収入印紙 | G77: 5000 | H77: 3 | I77: 昨年実績 | J77: =IF($G77="","",IF($H77=1,$G77-ROUND($G77*10/23,0)-2*ROUND($G77/23,0),IF($H77=2,$G77,0))) -> 0 | K77: =IF($G77="","",IF($H77=1,ROUND($G77*10/23,0),IF($H77=3,$G77-2*ROUND($G77/12,0),IF($H77=4,$G77,IF(OR($H77=5,$H77=7),ROUND($G77*10/11,0),0))))) -> 4166 | L77: =IF($G77="","",IF($H77=1,ROUND($G77/23,0),IF($H77=3,ROUND($G77/12,0),IF($H77=5,$G77-ROUND($G77*10/11,0),IF($H77=8,$G77,0))))) -> 417 | M77: =IF($G77="","",IF($H77=1,ROUND($G77/23,0),IF($H77=3,ROUND($G77/12,0),IF($H77=6,$G77,IF($H77=7,$G77-ROUND($G77*10/11,0),0))))) -> 417 | N77: =IF($G77="","",K77+L77+M77) -> 5000 | O77: =IF($G77="","",IFERROR(VLOOKUP($D77&"|"&$E77,科目表!$A$5:$B$200,2,FALSE),"※未登録")) -> 共済負担金等 | P77: =IF(OR($G77="",$C77=""),"",IF($B77="決算整理",13,MOD(MONTH($C77)-4,12)+1)) -> 2 | Q77: =IF($G77="","",TRIM(IF(J77+K77+L77+M77<>$G77,"按分不一致 ","")&IF(O77="※未登録","科目未登録 ","")&IF(OR($H77="",ISERROR(MATCH($H77,{1,2,3,4,5,6,7,8},0))),"経費区分? ","")&IF($I77="","状態未設定 ","")&IF(AND(OR($I77="確認済",$I77="未確認"),$B77="月例",OR($C77="",$C77<DATE(年度+2018,4,1),$C77>DATE(年度+2019,3,31))),"年度外の日付 ","")&IF(AND(OR($I77="確認済",$I77="未確認"),O77="対象外"),"対象外の科目 ",""))) | R77: 月例!79
A78: 74 | B78: 月例 | C78: 46183 | D78: 事務費 | E78: 送金料 | F78: 振込手数料（広銀）５月分 長期分 | G78: 12725 | H78: 3 | I78: 確認済 | J78: =IF($G78="","",IF($H78=1,$G78-ROUND($G78*10/23,0)-2*ROUND($G78/23,0),IF($H78=2,$G78,0))) -> 0 | K78: =IF($G78="","",IF($H78=1,ROUND($G78*10/23,0),IF($H78=3,$G78-2*ROUND($G78/12,0),IF($H78=4,$G78,IF(OR($H78=5,$H78=7),ROUND($G78*10/11,0),0))))) -> 10605 | L78: =IF($G78="","",IF($H78=1,ROUND($G78/23,0),IF($H78=3,ROUND($G78/12,0),IF($H78=5,$G78-ROUND($G78*10/11,0),IF($H78=8,$G78,0))))) -> 1060 | M78: =IF($G78="","",IF($H78=1,ROUND($G78/23,0),IF($H78=3,ROUND($G78/12,0),IF($H78=6,$G78,IF($H78=7,$G78-ROUND($G78*10/11,0),0))))) -> 1060 | N78: =IF($G78="","",K78+L78+M78) -> 12725 | O78: =IF($G78="","",IFERROR(VLOOKUP($D78&"|"&$E78,科目表!$A$5:$B$200,2,FALSE),"※未登録")) -> 送金料 | P78: =IF(OR($G78="",$C78=""),"",IF($B78="決算整理",13,MOD(MONTH($C78)-4,12)+1)) -> 3 | Q78: =IF($G78="","",TRIM(IF(J78+K78+L78+M78<>$G78,"按分不一致 ","")&IF(O78="※未登録","科目未登録 ","")&IF(OR($H78="",ISERROR(MATCH($H78,{1,2,3,4,5,6,7,8},0))),"経費区分? ","")&IF($I78="","状態未設定 ","")&IF(AND(OR($I78="確認済",$I78="未確認"),$B78="月例",OR($C78="",$C78<DATE(年度+2018,4,1),$C78>DATE(年度+2019,3,31))),"年度外の日付 ","")&IF(AND(OR($I78="確認済",$I78="未確認"),O78="対象外"),"対象外の科目 ",""))) | R78: 月例!80
A79: 75 | B79: 月例 | C79: 46183 | D79: 事務費 | E79: 送金料 | F79: 振込手数料（広銀）５月分 短期分 | G79: 135833 | H79: 2 | I79: 確認済 | J79: =IF($G79="","",IF($H79=1,$G79-ROUND($G79*10/23,0)-2*ROUND($G79/23,0),IF($H79=2,$G79,0))) -> 135833 | K79: =IF($G79="","",IF($H79=1,ROUND($G79*10/23,0),IF($H79=3,$G79-2*ROUND($G79/12,0),IF($H79=4,$G79,IF(OR($H79=5,$H79=7),ROUND($G79*10/11,0),0))))) -> 0 | L79: =IF($G79="","",IF($H79=1,ROUND($G79/23,0),IF($H79=3,ROUND($G79/12,0),IF($H79=5,$G79-ROUND($G79*10/11,0),IF($H79=8,$G79,0))))) -> 0 | M79: =IF($G79="","",IF($H79=1,ROUND($G79/23,0),IF($H79=3,ROUND($G79/12,0),IF($H79=6,$G79,IF($H79=7,$G79-ROUND($G79*10/11,0),0))))) -> 0 | N79: =IF($G79="","",K79+L79+M79) -> 0 | O79: =IF($G79="","",IFERROR(VLOOKUP($D79&"|"&$E79,科目表!$A$5:$B$200,2,FALSE),"※未登録")) -> 送金料 | P79: =IF(OR($G79="",$C79=""),"",IF($B79="決算整理",13,MOD(MONTH($C79)-4,12)+1)) -> 3 | Q79: =IF($G79="","",TRIM(IF(J79+K79+L79+M79<>$G79,"按分不一致 ","")&IF(O79="※未登録","科目未登録 ","")&IF(OR($H79="",ISERROR(MATCH($H79,{1,2,3,4,5,6,7,8},0))),"経費区分? ","")&IF($I79="","状態未設定 ","")&IF(AND(OR($I79="確認済",$I79="未確認"),$B79="月例",OR($C79="",$C79<DATE(年度+2018,4,1),$C79>DATE(年度+2019,3,31))),"年度外の日付 ","")&IF(AND(OR($I79="確認済",$I79="未確認"),O79="対象外"),"対象外の科目 ",""))) | R79: 月例!81
A80: 76 | B80: 月例 | C80: 46202 | D80: 役員報酬 | F80: 組合会６／２９ 学識経験監事 栗栖 一雄 | G80: 11000 | H80: 1 | I80: 確認済 | J80: =IF($G80="","",IF($H80=1,$G80-ROUND($G80*10/23,0)-2*ROUND($G80/23,0),IF($H80=2,$G80,0))) -> 5261 | K80: =IF($G80="","",IF($H80=1,ROUND($G80*10/23,0),IF($H80=3,$G80-2*ROUND($G80/12,0),IF($H80=4,$G80,IF(OR($H80=5,$H80=7),ROUND($G80*10/11,0),0))))) -> 4783 | L80: =IF($G80="","",IF($H80=1,ROUND($G80/23,0),IF($H80=3,ROUND($G80/12,0),IF($H80=5,$G80-ROUND($G80*10/11,0),IF($H80=8,$G80,0))))) -> 478 | M80: =IF($G80="","",IF($H80=1,ROUND($G80/23,0),IF($H80=3,ROUND($G80/12,0),IF($H80=6,$G80,IF($H80=7,$G80-ROUND($G80*10/11,0),0))))) -> 478 | N80: =IF($G80="","",K80+L80+M80) -> 5739 | O80: =IF($G80="","",IFERROR(VLOOKUP($D80&"|"&$E80,科目表!$A$5:$B$200,2,FALSE),"※未登録")) -> 役員報酬 | P80: =IF(OR($G80="",$C80=""),"",IF($B80="決算整理",13,MOD(MONTH($C80)-4,12)+1)) -> 3 | Q80: =IF($G80="","",TRIM(IF(J80+K80+L80+M80<>$G80,"按分不一致 ","")&IF(O80="※未登録","科目未登録 ","")&IF(OR($H80="",ISERROR(MATCH($H80,{1,2,3,4,5,6,7,8},0))),"経費区分? ","")&IF($I80="","状態未設定 ","")&IF(AND(OR($I80="確認済",$I80="未確認"),$B80="月例",OR($C80="",$C80<DATE(年度+2018,4,1),$C80>DATE(年度+2019,3,31))),"年度外の日付 ","")&IF(AND(OR($I80="確認済",$I80="未確認"),O80="対象外"),"対象外の科目 ",""))) | R80: 月例!82
A81: 77 | B81: 月例 | C81: 46202 | D81: 旅費 | F81: 7/9全国理事研修会 香川県 山田理事 | G81: 14320 | H81: 1 | I81: 確認済 | J81: =IF($G81="","",IF($H81=1,$G81-ROUND($G81*10/23,0)-2*ROUND($G81/23,0),IF($H81=2,$G81,0))) -> 6848 | K81: =IF($G81="","",IF($H81=1,ROUND($G81*10/23,0),IF($H81=3,$G81-2*ROUND($G81/12,0),IF($H81=4,$G81,IF(OR($H81=5,$H81=7),ROUND($G81*10/11,0),0))))) -> 6226 | L81: =IF($G81="","",IF($H81=1,ROUND($G81/23,0),IF($H81=3,ROUND($G81/12,0),IF($H81=5,$G81-ROUND($G81*10/11,0),IF($H81=8,$G81,0))))) -> 623 | M81: =IF($G81="","",IF($H81=1,ROUND($G81/23,0),IF($H81=3,ROUND($G81/12,0),IF($H81=6,$G81,IF($H81=7,$G81-ROUND($G81*10/11,0),0))))) -> 623 | N81: =IF($G81="","",K81+L81+M81) -> 7472 | O81: =IF($G81="","",IFERROR(VLOOKUP($D81&"|"&$E81,科目表!$A$5:$B$200,2,FALSE),"※未登録")) -> 旅費 | P81: =IF(OR($G81="",$C81=""),"",IF($B81="決算整理",13,MOD(MONTH($C81)-4,12)+1)) -> 3 | Q81: =IF($G81="","",TRIM(IF(J81+K81+L81+M81<>$G81,"按分不一致 ","")&IF(O81="※未登録","科目未登録 ","")&IF(OR($H81="",ISERROR(MATCH($H81,{1,2,3,4,5,6,7,8},0))),"経費区分? ","")&IF($I81="","状態未設定 ","")&IF(AND(OR($I81="確認済",$I81="未確認"),$B81="月例",OR($C81="",$C81<DATE(年度+2018,4,1),$C81>DATE(年度+2019,3,31))),"年度外の日付 ","")&IF(AND(OR($I81="確認済",$I81="未確認"),O81="対象外"),"対象外の科目 ",""))) | R81: 月例!83
A82: 78 | B82: 月例 | C82: 46202 | D82: 旅費 | F82: 7/9全国理事研修会 香川県 柴野理事 | G82: 14320 | H82: 1 | I82: 確認済 | J82: =IF($G82="","",IF($H82=1,$G82-ROUND($G82*10/23,0)-2*ROUND($G82/23,0),IF($H82=2,$G82,0))) -> 6848 | K82: =IF($G82="","",IF($H82=1,ROUND($G82*10/23,0),IF($H82=3,$G82-2*ROUND($G82/12,0),IF($H82=4,$G82,IF(OR($H82=5,$H82=7),ROUND($G82*10/11,0),0))))) -> 6226 | L82: =IF($G82="","",IF($H82=1,ROUND($G82/23,0),IF($H82=3,ROUND($G82/12,0),IF($H82=5,$G82-ROUND($G82*10/11,0),IF($H82=8,$G82,0))))) -> 623 | M82: =IF($G82="","",IF($H82=1,ROUND($G82/23,0),IF($H82=3,ROUND($G82/12,0),IF($H82=6,$G82,IF($H82=7,$G82-ROUND($G82*10/11,0),0))))) -> 623 | N82: =IF($G82="","",K82+L82+M82) -> 7472 | O82: =IF($G82="","",IFERROR(VLOOKUP($D82&"|"&$E82,科目表!$A$5:$B$200,2,FALSE),"※未登録")) -> 旅費 | P82: =IF(OR($G82="",$C82=""),"",IF($B82="決算整理",13,MOD(MONTH($C82)-4,12)+1)) -> 3 | Q82: =IF($G82="","",TRIM(IF(J82+K82+L82+M82<>$G82,"按分不一致 ","")&IF(O82="※未登録","科目未登録 ","")&IF(OR($H82="",ISERROR(MATCH($H82,{1,2,3,4,5,6,7,8},0))),"経費区分? ","")&IF($I82="","状態未設定 ","")&IF(AND(OR($I82="確認済",$I82="未確認"),$B82="月例",OR($C82="",$C82<DATE(年度+2018,4,1),$C82>DATE(年度+2019,3,31))),"年度外の日付 ","")&IF(AND(OR($I82="確認済",$I82="未確認"),O82="対象外"),"対象外の科目 ",""))) | R82: 月例!84
A83: 79 | B83: 月例 | C83: 46202 | D83: 旅費 | F83: 7/9全国理事研修会 香川県 濵理事 | G83: 14320 | H83: 1 | I83: 確認済 | J83: =IF($G83="","",IF($H83=1,$G83-ROUND($G83*10/23,0)-2*ROUND($G83/23,0),IF($H83=2,$G83,0))) -> 6848 | K83: =IF($G83="","",IF($H83=1,ROUND($G83*10/23,0),IF($H83=3,$G83-2*ROUND($G83/12,0),IF($H83=4,$G83,IF(OR($H83=5,$H83=7),ROUND($G83*10/11,0),0))))) -> 6226 | L83: =IF($G83="","",IF($H83=1,ROUND($G83/23,0),IF($H83=3,ROUND($G83/12,0),IF($H83=5,$G83-ROUND($G83*10/11,0),IF($H83=8,$G83,0))))) -> 623 | M83: =IF($G83="","",IF($H83=1,ROUND($G83/23,0),IF($H83=3,ROUND($G83/12,0),IF($H83=6,$G83,IF($H83=7,$G83-ROUND($G83*10/11,0),0))))) -> 623 | N83: =IF($G83="","",K83+L83+M83) -> 7472 | O83: =IF($G83="","",IFERROR(VLOOKUP($D83&"|"&$E83,科目表!$A$5:$B$200,2,FALSE),"※未登録")) -> 旅費 | P83: =IF(OR($G83="",$C83=""),"",IF($B83="決算整理",13,MOD(MONTH($C83)-4,12)+1)) -> 3 | Q83: =IF($G83="","",TRIM(IF(J83+K83+L83+M83<>$G83,"按分不一致 ","")&IF(O83="※未登録","科目未登録 ","")&IF(OR($H83="",ISERROR(MATCH($H83,{1,2,3,4,5,6,7,8},0))),"経費区分? ","")&IF($I83="","状態未設定 ","")&IF(AND(OR($I83="確認済",$I83="未確認"),$B83="月例",OR($C83="",$C83<DATE(年度+2018,4,1),$C83>DATE(年度+2019,3,31))),"年度外の日付 ","")&IF(AND(OR($I83="確認済",$I83="未確認"),O83="対象外"),"対象外の科目 ",""))) | R83: 月例!85
A84: 80 | B84: 月例 | C84: 46220 | D84: 委託費 | F84: ねんきん定期便（４月分）送付業務 | G84: 84057 | H84: 5 | I84: 確認済 | J84: =IF($G84="","",IF($H84=1,$G84-ROUND($G84*10/23,0)-2*ROUND($G84/23,0),IF($H84=2,$G84,0))) -> 0 | K84: =IF($G84="","",IF($H84=1,ROUND($G84*10/23,0),IF($H84=3,$G84-2*ROUND($G84/12,0),IF($H84=4,$G84,IF(OR($H84=5,$H84=7),ROUND($G84*10/11,0),0))))) -> 76415 | L84: =IF($G84="","",IF($H84=1,ROUND($G84/23,0),IF($H84=3,ROUND($G84/12,0),IF($H84=5,$G84-ROUND($G84*10/11,0),IF($H84=8,$G84,0))))) -> 7642 | M84: =IF($G84="","",IF($H84=1,ROUND($G84/23,0),IF($H84=3,ROUND($G84/12,0),IF($H84=6,$G84,IF($H84=7,$G84-ROUND($G84*10/11,0),0))))) -> 0 | N84: =IF($G84="","",K84+L84+M84) -> 84057 | O84: =IF($G84="","",IFERROR(VLOOKUP($D84&"|"&$E84,科目表!$A$5:$B$200,2,FALSE),"※未登録")) -> 委託費 | P84: =IF(OR($G84="",$C84=""),"",IF($B84="決算整理",13,MOD(MONTH($C84)-4,12)+1)) -> 4 | Q84: =IF($G84="","",TRIM(IF(J84+K84+L84+M84<>$G84,"按分不一致 ","")&IF(O84="※未登録","科目未登録 ","")&IF(OR($H84="",ISERROR(MATCH($H84,{1,2,3,4,5,6,7,8},0))),"経費区分? ","")&IF($I84="","状態未設定 ","")&IF(AND(OR($I84="確認済",$I84="未確認"),$B84="月例",OR($C84="",$C84<DATE(年度+2018,4,1),$C84>DATE(年度+2019,3,31))),"年度外の日付 ","")&IF(AND(OR($I84="確認済",$I84="未確認"),O84="対象外"),"対象外の科目 ",""))) | R84: 月例!86
A85: 81 | B85: 月例 | C85: 45831 | D85: 事務費 | E85: 通信運搬費 | F85: 切手等 | G85: 172500 | H85: 3 | I85: 昨年実績 | J85: =IF($G85="","",IF($H85=1,$G85-ROUND($G85*10/23,0)-2*ROUND($G85/23,0),IF($H85=2,$G85,0))) -> 0 | K85: =IF($G85="","",IF($H85=1,ROUND($G85*10/23,0),IF($H85=3,$G85-2*ROUND($G85/12,0),IF($H85=4,$G85,IF(OR($H85=5,$H85=7),ROUND($G85*10/11,0),0))))) -> 143750 | L85: =IF($G85="","",IF($H85=1,ROUND($G85/23,0),IF($H85=3,ROUND($G85/12,0),IF($H85=5,$G85-ROUND($G85*10/11,0),IF($H85=8,$G85,0))))) -> 14375 | M85: =IF($G85="","",IF($H85=1,ROUND($G85/23,0),IF($H85=3,ROUND($G85/12,0),IF($H85=6,$G85,IF($H85=7,$G85-ROUND($G85*10/11,0),0))))) -> 14375 | N85: =IF($G85="","",K85+L85+M85) -> 172500 | O85: =IF($G85="","",IFERROR(VLOOKUP($D85&"|"&$E85,科目表!$A$5:$B$200,2,FALSE),"※未登録")) -> 通信運搬費 | P85: =IF(OR($G85="",$C85=""),"",IF($B85="決算整理",13,MOD(MONTH($C85)-4,12)+1)) -> 3 | Q85: =IF($G85="","",TRIM(IF(J85+K85+L85+M85<>$G85,"按分不一致 ","")&IF(O85="※未登録","科目未登録 ","")&IF(OR($H85="",ISERROR(MATCH($H85,{1,2,3,4,5,6,7,8},0))),"経費区分? ","")&IF($I85="","状態未設定 ","")&IF(AND(OR($I85="確認済",$I85="未確認"),$B85="月例",OR($C85="",$C85<DATE(年度+2018,4,1),$C85>DATE(年度+2019,3,31))),"年度外の日付 ","")&IF(AND(OR($I85="確認済",$I85="未確認"),O85="対象外"),"対象外の科目 ",""))) | R85: 月例!87
A86: 82 | B86: 月例 | C86: 43984 | D86: 負担金 | E86: 負担金 | F86: 収入印紙 | G86: 2000 | H86: 2 | I86: 昨年実績 | J86: =IF($G86="","",IF($H86=1,$G86-ROUND($G86*10/23,0)-2*ROUND($G86/23,0),IF($H86=2,$G86,0))) -> 2000 | K86: =IF($G86="","",IF($H86=1,ROUND($G86*10/23,0),IF($H86=3,$G86-2*ROUND($G86/12,0),IF($H86=4,$G86,IF(OR($H86=5,$H86=7),ROUND($G86*10/11,0),0))))) -> 0 | L86: =IF($G86="","",IF($H86=1,ROUND($G86/23,0),IF($H86=3,ROUND($G86/12,0),IF($H86=5,$G86-ROUND($G86*10/11,0),IF($H86=8,$G86,0))))) -> 0 | M86: =IF($G86="","",IF($H86=1,ROUND($G86/23,0),IF($H86=3,ROUND($G86/12,0),IF($H86=6,$G86,IF($H86=7,$G86-ROUND($G86*10/11,0),0))))) -> 0 | N86: =IF($G86="","",K86+L86+M86) -> 0 | O86: =IF($G86="","",IFERROR(VLOOKUP($D86&"|"&$E86,科目表!$A$5:$B$200,2,FALSE),"※未登録")) -> 共済負担金等 | P86: =IF(OR($G86="",$C86=""),"",IF($B86="決算整理",13,MOD(MONTH($C86)-4,12)+1)) -> 3 | Q86: =IF($G86="","",TRIM(IF(J86+K86+L86+M86<>$G86,"按分不一致 ","")&IF(O86="※未登録","科目未登録 ","")&IF(OR($H86="",ISERROR(MATCH($H86,{1,2,3,4,5,6,7,8},0))),"経費区分? ","")&IF($I86="","状態未設定 ","")&IF(AND(OR($I86="確認済",$I86="未確認"),$B86="月例",OR($C86="",$C86<DATE(年度+2018,4,1),$C86>DATE(年度+2019,3,31))),"年度外の日付 ","")&IF(AND(OR($I86="確認済",$I86="未確認"),O86="対象外"),"対象外の科目 ",""))) | R86: 月例!88
A87: 83 | B87: 月例 | C87: 46202 | D87: 賃借料 | F87: パソコン（業務経理用）５月分 | G87: 5060 | H87: 2 | I87: 確認済 | J87: =IF($G87="","",IF($H87=1,$G87-ROUND($G87*10/23,0)-2*ROUND($G87/23,0),IF($H87=2,$G87,0))) -> 5060 | K87: =IF($G87="","",IF($H87=1,ROUND($G87*10/23,0),IF($H87=3,$G87-2*ROUND($G87/12,0),IF($H87=4,$G87,IF(OR($H87=5,$H87=7),ROUND($G87*10/11,0),0))))) -> 0 | L87: =IF($G87="","",IF($H87=1,ROUND($G87/23,0),IF($H87=3,ROUND($G87/12,0),IF($H87=5,$G87-ROUND($G87*10/11,0),IF($H87=8,$G87,0))))) -> 0 | M87: =IF($G87="","",IF($H87=1,ROUND($G87/23,0),IF($H87=3,ROUND($G87/12,0),IF($H87=6,$G87,IF($H87=7,$G87-ROUND($G87*10/11,0),0))))) -> 0 | N87: =IF($G87="","",K87+L87+M87) -> 0 | O87: =IF($G87="","",IFERROR(VLOOKUP($D87&"|"&$E87,科目表!$A$5:$B$200,2,FALSE),"※未登録")) -> 賃借料 | P87: =IF(OR($G87="",$C87=""),"",IF($B87="決算整理",13,MOD(MONTH($C87)-4,12)+1)) -> 3 | Q87: =IF($G87="","",TRIM(IF(J87+K87+L87+M87<>$G87,"按分不一致 ","")&IF(O87="※未登録","科目未登録 ","")&IF(OR($H87="",ISERROR(MATCH($H87,{1,2,3,4,5,6,7,8},0))),"経費区分? ","")&IF($I87="","状態未設定 ","")&IF(AND(OR($I87="確認済",$I87="未確認"),$B87="月例",OR($C87="",$C87<DATE(年度+2018,4,1),$C87>DATE(年度+2019,3,31))),"年度外の日付 ","")&IF(AND(OR($I87="確認済",$I87="未確認"),O87="対象外"),"対象外の科目 ",""))) | R87: 月例!89
A88: 84 | B88: 月例 | C88: 44392 | D88: 賃借料 | F88: ﾊﾟｿｺﾝｳｨﾙｽ対策ｿﾌﾄ(業務用)ｻﾝﾈｯﾄ（5月分） | G88: 2090 | H88: 2 | I88: 昨年実績 | J88: =IF($G88="","",IF($H88=1,$G88-ROUND($G88*10/23,0)-2*ROUND($G88/23,0),IF($H88=2,$G88,0))) -> 2090 | K88: =IF($G88="","",IF($H88=1,ROUND($G88*10/23,0),IF($H88=3,$G88-2*ROUND($G88/12,0),IF($H88=4,$G88,IF(OR($H88=5,$H88=7),ROUND($G88*10/11,0),0))))) -> 0 | L88: =IF($G88="","",IF($H88=1,ROUND($G88/23,0),IF($H88=3,ROUND($G88/12,0),IF($H88=5,$G88-ROUND($G88*10/11,0),IF($H88=8,$G88,0))))) -> 0 | M88: =IF($G88="","",IF($H88=1,ROUND($G88/23,0),IF($H88=3,ROUND($G88/12,0),IF($H88=6,$G88,IF($H88=7,$G88-ROUND($G88*10/11,0),0))))) -> 0 | N88: =IF($G88="","",K88+L88+M88) -> 0 | O88: =IF($G88="","",IFERROR(VLOOKUP($D88&"|"&$E88,科目表!$A$5:$B$200,2,FALSE),"※未登録")) -> 賃借料 | P88: =IF(OR($G88="",$C88=""),"",IF($B88="決算整理",13,MOD(MONTH($C88)-4,12)+1)) -> 4 | Q88: =IF($G88="","",TRIM(IF(J88+K88+L88+M88<>$G88,"按分不一致 ","")&IF(O88="※未登録","科目未登録 ","")&IF(OR($H88="",ISERROR(MATCH($H88,{1,2,3,4,5,6,7,8},0))),"経費区分? ","")&IF($I88="","状態未設定 ","")&IF(AND(OR($I88="確認済",$I88="未確認"),$B88="月例",OR($C88="",$C88<DATE(年度+2018,4,1),$C88>DATE(年度+2019,3,31))),"年度外の日付 ","")&IF(AND(OR($I88="確認済",$I88="未確認"),O88="対象外"),"対象外の科目 ",""))) | R88: 月例!90
A89: 85 | B89: 月例 | C89: 46188 | D89: 賃金 | F89: 臨時職員賃金５月分 天畠吏梨外１名分（短期１００％） | G89: 365040 | H89: 2 | I89: 確認済 | J89: =IF($G89="","",IF($H89=1,$G89-ROUND($G89*10/23,0)-2*ROUND($G89/23,0),IF($H89=2,$G89,0))) -> 365040 | K89: =IF($G89="","",IF($H89=1,ROUND($G89*10/23,0),IF($H89=3,$G89-2*ROUND($G89/12,0),IF($H89=4,$G89,IF(OR($H89=5,$H89=7),ROUND($G89*10/11,0),0))))) -> 0 | L89: =IF($G89="","",IF($H89=1,ROUND($G89/23,0),IF($H89=3,ROUND($G89/12,0),IF($H89=5,$G89-ROUND($G89*10/11,0),IF($H89=8,$G89,0))))) -> 0 | M89: =IF($G89="","",IF($H89=1,ROUND($G89/23,0),IF($H89=3,ROUND($G89/12,0),IF($H89=6,$G89,IF($H89=7,$G89-ROUND($G89*10/11,0),0))))) -> 0 | N89: =IF($G89="","",K89+L89+M89) -> 0 | O89: =IF($G89="","",IFERROR(VLOOKUP($D89&"|"&$E89,科目表!$A$5:$B$200,2,FALSE),"※未登録")) -> 賃金 | P89: =IF(OR($G89="",$C89=""),"",IF($B89="決算整理",13,MOD(MONTH($C89)-4,12)+1)) -> 3 | Q89: =IF($G89="","",TRIM(IF(J89+K89+L89+M89<>$G89,"按分不一致 ","")&IF(O89="※未登録","科目未登録 ","")&IF(OR($H89="",ISERROR(MATCH($H89,{1,2,3,4,5,6,7,8},0))),"経費区分? ","")&IF($I89="","状態未設定 ","")&IF(AND(OR($I89="確認済",$I89="未確認"),$B89="月例",OR($C89="",$C89<DATE(年度+2018,4,1),$C89>DATE(年度+2019,3,31))),"年度外の日付 ","")&IF(AND(OR($I89="確認済",$I89="未確認"),O89="対象外"),"対象外の科目 ",""))) | R89: 月例!91
A90: 86 | B90: 月例 | C90: 46210 | D90: 負担金 | E90: 労災・雇用保険料 | F90: 労災保険料 雇用保険料 一般拠出金（長期分） | G90: 71152 | H90: 3 | I90: 確認済 | J90: =IF($G90="","",IF($H90=1,$G90-ROUND($G90*10/23,0)-2*ROUND($G90/23,0),IF($H90=2,$G90,0))) -> 0 | K90: =IF($G90="","",IF($H90=1,ROUND($G90*10/23,0),IF($H90=3,$G90-2*ROUND($G90/12,0),IF($H90=4,$G90,IF(OR($H90=5,$H90=7),ROUND($G90*10/11,0),0))))) -> 59294 | L90: =IF($G90="","",IF($H90=1,ROUND($G90/23,0),IF($H90=3,ROUND($G90/12,0),IF($H90=5,$G90-ROUND($G90*10/11,0),IF($H90=8,$G90,0))))) -> 5929 | M90: =IF($G90="","",IF($H90=1,ROUND($G90/23,0),IF($H90=3,ROUND($G90/12,0),IF($H90=6,$G90,IF($H90=7,$G90-ROUND($G90*10/11,0),0))))) -> 5929 | N90: =IF($G90="","",K90+L90+M90) -> 71152 | O90: =IF($G90="","",IFERROR(VLOOKUP($D90&"|"&$E90,科目表!$A$5:$B$200,2,FALSE),"※未登録")) -> 労災・雇用保険料 | P90: =IF(OR($G90="",$C90=""),"",IF($B90="決算整理",13,MOD(MONTH($C90)-4,12)+1)) -> 4 | Q90: =IF($G90="","",TRIM(IF(J90+K90+L90+M90<>$G90,"按分不一致 ","")&IF(O90="※未登録","科目未登録 ","")&IF(OR($H90="",ISERROR(MATCH($H90,{1,2,3,4,5,6,7,8},0))),"経費区分? ","")&IF($I90="","状態未設定 ","")&IF(AND(OR($I90="確認済",$I90="未確認"),$B90="月例",OR($C90="",$C90<DATE(年度+2018,4,1),$C90>DATE(年度+2019,3,31))),"年度外の日付 ","")&IF(AND(OR($I90="確認済",$I90="未確認"),O90="対象外"),"対象外の科目 ",""))) | R90: 月例!92
A91: 87 | B91: 月例 | C91: 46210 | D91: 負担金 | E91: 労災・雇用保険料 | F91: 労災保険料 雇用保険料 一般拠出金（短期分） | G91: 108215 | H91: 2 | I91: 確認済 | J91: =IF($G91="","",IF($H91=1,$G91-ROUND($G91*10/23,0)-2*ROUND($G91/23,0),IF($H91=2,$G91,0))) -> 108215 | K91: =IF($G91="","",IF($H91=1,ROUND($G91*10/23,0),IF($H91=3,$G91-2*ROUND($G91/12,0),IF($H91=4,$G91,IF(OR($H91=5,$H91=7),ROUND($G91*10/11,0),0))))) -> 0 | L91: =IF($G91="","",IF($H91=1,ROUND($G91/23,0),IF($H91=3,ROUND($G91/12,0),IF($H91=5,$G91-ROUND($G91*10/11,0),IF($H91=8,$G91,0))))) -> 0 | M91: =IF($G91="","",IF($H91=1,ROUND($G91/23,0),IF($H91=3,ROUND($G91/12,0),IF($H91=6,$G91,IF($H91=7,$G91-ROUND($G91*10/11,0),0))))) -> 0 | N91: =IF($G91="","",K91+L91+M91) -> 0 | O91: =IF($G91="","",IFERROR(VLOOKUP($D91&"|"&$E91,科目表!$A$5:$B$200,2,FALSE),"※未登録")) -> 労災・雇用保険料 | P91: =IF(OR($G91="",$C91=""),"",IF($B91="決算整理",13,MOD(MONTH($C91)-4,12)+1)) -> 4 | Q91: =IF($G91="","",TRIM(IF(J91+K91+L91+M91<>$G91,"按分不一致 ","")&IF(O91="※未登録","科目未登録 ","")&IF(OR($H91="",ISERROR(MATCH($H91,{1,2,3,4,5,6,7,8},0))),"経費区分? ","")&IF($I91="","状態未設定 ","")&IF(AND(OR($I91="確認済",$I91="未確認"),$B91="月例",OR($C91="",$C91<DATE(年度+2018,4,1),$C91>DATE(年度+2019,3,31))),"年度外の日付 ","")&IF(AND(OR($I91="確認済",$I91="未確認"),O91="対象外"),"対象外の科目 ",""))) | R91: 月例!93
A92: 88 | B92: 月例 | C92: 46203 | D92: 事務費 | E92: 事務用消耗品費 | F92: 鋳造ゴム印 3号以下 51字 他5点 | G92: 24508 | H92: 2 | I92: 確認済 | J92: =IF($G92="","",IF($H92=1,$G92-ROUND($G92*10/23,0)-2*ROUND($G92/23,0),IF($H92=2,$G92,0))) -> 24508 | K92: =IF($G92="","",IF($H92=1,ROUND($G92*10/23,0),IF($H92=3,$G92-2*ROUND($G92/12,0),IF($H92=4,$G92,IF(OR($H92=5,$H92=7),ROUND($G92*10/11,0),0))))) -> 0 | L92: =IF($G92="","",IF($H92=1,ROUND($G92/23,0),IF($H92=3,ROUND($G92/12,0),IF($H92=5,$G92-ROUND($G92*10/11,0),IF($H92=8,$G92,0))))) -> 0 | M92: =IF($G92="","",IF($H92=1,ROUND($G92/23,0),IF($H92=3,ROUND($G92/12,0),IF($H92=6,$G92,IF($H92=7,$G92-ROUND($G92*10/11,0),0))))) -> 0 | N92: =IF($G92="","",K92+L92+M92) -> 0 | O92: =IF($G92="","",IFERROR(VLOOKUP($D92&"|"&$E92,科目表!$A$5:$B$200,2,FALSE),"※未登録")) -> 事務用消耗品費 | P92: =IF(OR($G92="",$C92=""),"",IF($B92="決算整理",13,MOD(MONTH($C92)-4,12)+1)) -> 3 | Q92: =IF($G92="","",TRIM(IF(J92+K92+L92+M92<>$G92,"按分不一致 ","")&IF(O92="※未登録","科目未登録 ","")&IF(OR($H92="",ISERROR(MATCH($H92,{1,2,3,4,5,6,7,8},0))),"経費区分? ","")&IF($I92="","状態未設定 ","")&IF(AND(OR($I92="確認済",$I92="未確認"),$B92="月例",OR($C92="",$C92<DATE(年度+2018,4,1),$C92>DATE(年度+2019,3,31))),"年度外の日付 ","")&IF(AND(OR($I92="確認済",$I92="未確認"),O92="対象外"),"対象外の科目 ",""))) | R92: 月例!94
A93: 89 | B93: 月例 | C93: 45835 | D93: 事務費 | E93: 事務用消耗品費 | F93: 色上質紙 厚口／５００枚／Ａ４／浅黄 １包 外９点 | G93: 16374 | H93: 3 | I93: 昨年実績 | J93: =IF($G93="","",IF($H93=1,$G93-ROUND($G93*10/23,0)-2*ROUND($G93/23,0),IF($H93=2,$G93,0))) -> 0 | K93: =IF($G93="","",IF($H93=1,ROUND($G93*10/23,0),IF($H93=3,$G93-2*ROUND($G93/12,0),IF($H93=4,$G93,IF(OR($H93=5,$H93=7),ROUND($G93*10/11,0),0))))) -> 13644 | L93: =IF($G93="","",IF($H93=1,ROUND($G93/23,0),IF($H93=3,ROUND($G93/12,0),IF($H93=5,$G93-ROUND($G93*10/11,0),IF($H93=8,$G93,0))))) -> 1365 | M93: =IF($G93="","",IF($H93=1,ROUND($G93/23,0),IF($H93=3,ROUND($G93/12,0),IF($H93=6,$G93,IF($H93=7,$G93-ROUND($G93*10/11,0),0))))) -> 1365 | N93: =IF($G93="","",K93+L93+M93) -> 16374 | O93: =IF($G93="","",IFERROR(VLOOKUP($D93&"|"&$E93,科目表!$A$5:$B$200,2,FALSE),"※未登録")) -> 事務用消耗品費 | P93: =IF(OR($G93="",$C93=""),"",IF($B93="決算整理",13,MOD(MONTH($C93)-4,12)+1)) -> 3 | Q93: =IF($G93="","",TRIM(IF(J93+K93+L93+M93<>$G93,"按分不一致 ","")&IF(O93="※未登録","科目未登録 ","")&IF(OR($H93="",ISERROR(MATCH($H93,{1,2,3,4,5,6,7,8},0))),"経費区分? ","")&IF($I93="","状態未設定 ","")&IF(AND(OR($I93="確認済",$I93="未確認"),$B93="月例",OR($C93="",$C93<DATE(年度+2018,4,1),$C93>DATE(年度+2019,3,31))),"年度外の日付 ","")&IF(AND(OR($I93="確認済",$I93="未確認"),O93="対象外"),"対象外の科目 ",""))) | R93: 月例!95
A94: 90 | B94: 月例 | C94: 46171 | D94: 事務費 | E94: 通信運搬費 | F94: 料金後納利用料（4月分） | G94: 147246 | H94: 3 | I94: 確認済 | J94: =IF($G94="","",IF($H94=1,$G94-ROUND($G94*10/23,0)-2*ROUND($G94/23,0),IF($H94=2,$G94,0))) -> 0 | K94: =IF($G94="","",IF($H94=1,ROUND($G94*10/23,0),IF($H94=3,$G94-2*ROUND($G94/12,0),IF($H94=4,$G94,IF(OR($H94=5,$H94=7),ROUND($G94*10/11,0),0))))) -> 122704 | L94: =IF($G94="","",IF($H94=1,ROUND($G94/23,0),IF($H94=3,ROUND($G94/12,0),IF($H94=5,$G94-ROUND($G94*10/11,0),IF($H94=8,$G94,0))))) -> 12271 | M94: =IF($G94="","",IF($H94=1,ROUND($G94/23,0),IF($H94=3,ROUND($G94/12,0),IF($H94=6,$G94,IF($H94=7,$G94-ROUND($G94*10/11,0),0))))) -> 12271 | N94: =IF($G94="","",K94+L94+M94) -> 147246 | O94: =IF($G94="","",IFERROR(VLOOKUP($D94&"|"&$E94,科目表!$A$5:$B$200,2,FALSE),"※未登録")) -> 通信運搬費 | P94: =IF(OR($G94="",$C94=""),"",IF($B94="決算整理",13,MOD(MONTH($C94)-4,12)+1)) -> 2 | Q94: =IF($G94="","",TRIM(IF(J94+K94+L94+M94<>$G94,"按分不一致 ","")&IF(O94="※未登録","科目未登録 ","")&IF(OR($H94="",ISERROR(MATCH($H94,{1,2,3,4,5,6,7,8},0))),"経費区分? ","")&IF($I94="","状態未設定 ","")&IF(AND(OR($I94="確認済",$I94="未確認"),$B94="月例",OR($C94="",$C94<DATE(年度+2018,4,1),$C94>DATE(年度+2019,3,31))),"年度外の日付 ","")&IF(AND(OR($I94="確認済",$I94="未確認"),O94="対象外"),"対象外の科目 ",""))) | R94: 月例!96
A95: 91 | B95: 月例 | C95: 46171 | D95: 事務費 | E95: 通信運搬費 | F95: 料金後納利用料（4月分） | G95: 196030 | H95: 2 | I95: 確認済 | J95: =IF($G95="","",IF($H95=1,$G95-ROUND($G95*10/23,0)-2*ROUND($G95/23,0),IF($H95=2,$G95,0))) -> 196030 | K95: =IF($G95="","",IF($H95=1,ROUND($G95*10/23,0),IF($H95=3,$G95-2*ROUND($G95/12,0),IF($H95=4,$G95,IF(OR($H95=5,$H95=7),ROUND($G95*10/11,0),0))))) -> 0 | L95: =IF($G95="","",IF($H95=1,ROUND($G95/23,0),IF($H95=3,ROUND($G95/12,0),IF($H95=5,$G95-ROUND($G95*10/11,0),IF($H95=8,$G95,0))))) -> 0 | M95: =IF($G95="","",IF($H95=1,ROUND($G95/23,0),IF($H95=3,ROUND($G95/12,0),IF($H95=6,$G95,IF($H95=7,$G95-ROUND($G95*10/11,0),0))))) -> 0 | N95: =IF($G95="","",K95+L95+M95) -> 0 | O95: =IF($G95="","",IFERROR(VLOOKUP($D95&"|"&$E95,科目表!$A$5:$B$200,2,FALSE),"※未登録")) -> 通信運搬費 | P95: =IF(OR($G95="",$C95=""),"",IF($B95="決算整理",13,MOD(MONTH($C95)-4,12)+1)) -> 2 | Q95: =IF($G95="","",TRIM(IF(J95+K95+L95+M95<>$G95,"按分不一致 ","")&IF(O95="※未登録","科目未登録 ","")&IF(OR($H95="",ISERROR(MATCH($H95,{1,2,3,4,5,6,7,8},0))),"経費区分? ","")&IF($I95="","状態未設定 ","")&IF(AND(OR($I95="確認済",$I95="未確認"),$B95="月例",OR($C95="",$C95<DATE(年度+2018,4,1),$C95>DATE(年度+2019,3,31))),"年度外の日付 ","")&IF(AND(OR($I95="確認済",$I95="未確認"),O95="対象外"),"対象外の科目 ",""))) | R95: 月例!97
A96: 92 | B96: 月例 | C96: 44368 | D96: 事務費 | E96: 通信運搬費 | F96: 電話料金（５月使用・６月請求分） | G96: 5407 | H96: 2 | I96: 昨年実績 | J96: =IF($G96="","",IF($H96=1,$G96-ROUND($G96*10/23,0)-2*ROUND($G96/23,0),IF($H96=2,$G96,0))) -> 5407 | K96: =IF($G96="","",IF($H96=1,ROUND($G96*10/23,0),IF($H96=3,$G96-2*ROUND($G96/12,0),IF($H96=4,$G96,IF(OR($H96=5,$H96=7),ROUND($G96*10/11,0),0))))) -> 0 | L96: =IF($G96="","",IF($H96=1,ROUND($G96/23,0),IF($H96=3,ROUND($G96/12,0),IF($H96=5,$G96-ROUND($G96*10/11,0),IF($H96=8,$G96,0))))) -> 0 | M96: =IF($G96="","",IF($H96=1,ROUND($G96/23,0),IF($H96=3,ROUND($G96/12,0),IF($H96=6,$G96,IF($H96=7,$G96-ROUND($G96*10/11,0),0))))) -> 0 | N96: =IF($G96="","",K96+L96+M96) -> 0 | O96: =IF($G96="","",IFERROR(VLOOKUP($D96&"|"&$E96,科目表!$A$5:$B$200,2,FALSE),"※未登録")) -> 通信運搬費 | P96: =IF(OR($G96="",$C96=""),"",IF($B96="決算整理",13,MOD(MONTH($C96)-4,12)+1)) -> 3 | Q96: =IF($G96="","",TRIM(IF(J96+K96+L96+M96<>$G96,"按分不一致 ","")&IF(O96="※未登録","科目未登録 ","")&IF(OR($H96="",ISERROR(MATCH($H96,{1,2,3,4,5,6,7,8},0))),"経費区分? ","")&IF($I96="","状態未設定 ","")&IF(AND(OR($I96="確認済",$I96="未確認"),$B96="月例",OR($C96="",$C96<DATE(年度+2018,4,1),$C96>DATE(年度+2019,3,31))),"年度外の日付 ","")&IF(AND(OR($I96="確認済",$I96="未確認"),O96="対象外"),"対象外の科目 ",""))) | R96: 月例!98
A97: 93 | B97: 月例 | C97: 46192 | D97: 委託費 | F97: レセプト電子データ提供料（３月診療分） | G97: 66423 | H97: 2 | I97: 確認済 | J97: =IF($G97="","",IF($H97=1,$G97-ROUND($G97*10/23,0)-2*ROUND($G97/23,0),IF($H97=2,$G97,0))) -> 66423 | K97: =IF($G97="","",IF($H97=1,ROUND($G97*10/23,0),IF($H97=3,$G97-2*ROUND($G97/12,0),IF($H97=4,$G97,IF(OR($H97=5,$H97=7),ROUND($G97*10/11,0),0))))) -> 0 | L97: =IF($G97="","",IF($H97=1,ROUND($G97/23,0),IF($H97=3,ROUND($G97/12,0),IF($H97=5,$G97-ROUND($G97*10/11,0),IF($H97=8,$G97,0))))) -> 0 | M97: =IF($G97="","",IF($H97=1,ROUND($G97/23,0),IF($H97=3,ROUND($G97/12,0),IF($H97=6,$G97,IF($H97=7,$G97-ROUND($G97*10/11,0),0))))) -> 0 | N97: =IF($G97="","",K97+L97+M97) -> 0 | O97: =IF($G97="","",IFERROR(VLOOKUP($D97&"|"&$E97,科目表!$A$5:$B$200,2,FALSE),"※未登録")) -> 委託費 | P97: =IF(OR($G97="",$C97=""),"",IF($B97="決算整理",13,MOD(MONTH($C97)-4,12)+1)) -> 3 | Q97: =IF($G97="","",TRIM(IF(J97+K97+L97+M97<>$G97,"按分不一致 ","")&IF(O97="※未登録","科目未登録 ","")&IF(OR($H97="",ISERROR(MATCH($H97,{1,2,3,4,5,6,7,8},0))),"経費区分? ","")&IF($I97="","状態未設定 ","")&IF(AND(OR($I97="確認済",$I97="未確認"),$B97="月例",OR($C97="",$C97<DATE(年度+2018,4,1),$C97>DATE(年度+2019,3,31))),"年度外の日付 ","")&IF(AND(OR($I97="確認済",$I97="未確認"),O97="対象外"),"対象外の科目 ",""))) | R97: 月例!99
A98: 94 | B98: 月例 | C98: 46192 | D98: 職員給与 | E98: 非常勤職員手当 | F98: ６月分給与（長期分） | G98: 380800 | H98: 3 | I98: 確認済 | J98: =IF($G98="","",IF($H98=1,$G98-ROUND($G98*10/23,0)-2*ROUND($G98/23,0),IF($H98=2,$G98,0))) -> 0 | K98: =IF($G98="","",IF($H98=1,ROUND($G98*10/23,0),IF($H98=3,$G98-2*ROUND($G98/12,0),IF($H98=4,$G98,IF(OR($H98=5,$H98=7),ROUND($G98*10/11,0),0))))) -> 317334 | L98: =IF($G98="","",IF($H98=1,ROUND($G98/23,0),IF($H98=3,ROUND($G98/12,0),IF($H98=5,$G98-ROUND($G98*10/11,0),IF($H98=8,$G98,0))))) -> 31733 | M98: =IF($G98="","",IF($H98=1,ROUND($G98/23,0),IF($H98=3,ROUND($G98/12,0),IF($H98=6,$G98,IF($H98=7,$G98-ROUND($G98*10/11,0),0))))) -> 31733 | N98: =IF($G98="","",K98+L98+M98) -> 380800 | O98: =IF($G98="","",IFERROR(VLOOKUP($D98&"|"&$E98,科目表!$A$5:$B$200,2,FALSE),"※未登録")) -> 非常勤職員手当 | P98: =IF(OR($G98="",$C98=""),"",IF($B98="決算整理",13,MOD(MONTH($C98)-4,12)+1)) -> 3 | Q98: =IF($G98="","",TRIM(IF(J98+K98+L98+M98<>$G98,"按分不一致 ","")&IF(O98="※未登録","科目未登録 ","")&IF(OR($H98="",ISERROR(MATCH($H98,{1,2,3,4,5,6,7,8},0))),"経費区分? ","")&IF($I98="","状態未設定 ","")&IF(AND(OR($I98="確認済",$I98="未確認"),$B98="月例",OR($C98="",$C98<DATE(年度+2018,4,1),$C98>DATE(年度+2019,3,31))),"年度外の日付 ","")&IF(AND(OR($I98="確認済",$I98="未確認"),O98="対象外"),"対象外の科目 ",""))) | R98: 月例!100
A99: 95 | B99: 月例 | C99: 46192 | D99: 職員給与 | E99: 非常勤職員手当 | F99: ６月分給与（短期分） | G99: 250504 | H99: 2 | I99: 確認済 | J99: =IF($G99="","",IF($H99=1,$G99-ROUND($G99*10/23,0)-2*ROUND($G99/23,0),IF($H99=2,$G99,0))) -> 250504 | K99: =IF($G99="","",IF($H99=1,ROUND($G99*10/23,0),IF($H99=3,$G99-2*ROUND($G99/12,0),IF($H99=4,$G99,IF(OR($H99=5,$H99=7),ROUND($G99*10/11,0),0))))) -> 0 | L99: =IF($G99="","",IF($H99=1,ROUND($G99/23,0),IF($H99=3,ROUND($G99/12,0),IF($H99=5,$G99-ROUND($G99*10/11,0),IF($H99=8,$G99,0))))) -> 0 | M99: =IF($G99="","",IF($H99=1,ROUND($G99/23,0),IF($H99=3,ROUND($G99/12,0),IF($H99=6,$G99,IF($H99=7,$G99-ROUND($G99*10/11,0),0))))) -> 0 | N99: =IF($G99="","",K99+L99+M99) -> 0 | O99: =IF($G99="","",IFERROR(VLOOKUP($D99&"|"&$E99,科目表!$A$5:$B$200,2,FALSE),"※未登録")) -> 非常勤職員手当 | P99: =IF(OR($G99="",$C99=""),"",IF($B99="決算整理",13,MOD(MONTH($C99)-4,12)+1)) -> 3 | Q99: =IF($G99="","",TRIM(IF(J99+K99+L99+M99<>$G99,"按分不一致 ","")&IF(O99="※未登録","科目未登録 ","")&IF(OR($H99="",ISERROR(MATCH($H99,{1,2,3,4,5,6,7,8},0))),"経費区分? ","")&IF($I99="","状態未設定 ","")&IF(AND(OR($I99="確認済",$I99="未確認"),$B99="月例",OR($C99="",$C99<DATE(年度+2018,4,1),$C99>DATE(年度+2019,3,31))),"年度外の日付 ","")&IF(AND(OR($I99="確認済",$I99="未確認"),O99="対象外"),"対象外の科目 ",""))) | R99: 月例!101
A100: 96 | B100: 月例 | C100: 46192 | D100: 負担金 | E100: 互助会費 | F100: 助成金（６月長期分） | G100: 466 | H100: 3 | I100: 確認済 | J100: =IF($G100="","",IF($H100=1,$G100-ROUND($G100*10/23,0)-2*ROUND($G100/23,0),IF($H100=2,$G100,0))) -> 0 | K100: =IF($G100="","",IF($H100=1,ROUND($G100*10/23,0),IF($H100=3,$G100-2*ROUND($G100/12,0),IF($H100=4,$G100,IF(OR($H100=5,$H100=7),ROUND($G100*10/11,0),0))))) -> 388 | L100: =IF($G100="","",IF($H100=1,ROUND($G100/23,0),IF($H100=3,ROUND($G100/12,0),IF($H100=5,$G100-ROUND($G100*10/11,0),IF($H100=8,$G100,0))))) -> 39 | M100: =IF($G100="","",IF($H100=1,ROUND($G100/23,0),IF($H100=3,ROUND($G100/12,0),IF($H100=6,$G100,IF($H100=7,$G100-ROUND($G100*10/11,0),0))))) -> 39 | N100: =IF($G100="","",K100+L100+M100) -> 466 | O100: =IF($G100="","",IFERROR(VLOOKUP($D100&"|"&$E100,科目表!$A$5:$B$200,2,FALSE),"※未登録")) -> 互助会費 | P100: =IF(OR($G100="",$C100=""),"",IF($B100="決算整理",13,MOD(MONTH($C100)-4,12)+1)) -> 3 | Q100: =IF($G100="","",TRIM(IF(J100+K100+L100+M100<>$G100,"按分不一致 ","")&IF(O100="※未登録","科目未登録 ","")&IF(OR($H100="",ISERROR(MATCH($H100,{1,2,3,4,5,6,7,8},0))),"経費区分? ","")&IF($I100="","状態未設定 ","")&IF(AND(OR($I100="確認済",$I100="未確認"),$B100="月例",OR($C100="",$C100<DATE(年度+2018,4,1),$C100>DATE(年度+2019,3,31))),"年度外の日付 ","")&IF(AND(OR($I100="確認済",$I100="未確認"),O100="対象外"),"対象外の科目 ",""))) | R100: 月例!102
A101: 97 | B101: 月例 | C101: 46192 | D101: 負担金 | E101: 互助会費 | F101: 助成金（６月短期分） | G101: 240 | H101: 2 | I101: 確認済 | J101: =IF($G101="","",IF($H101=1,$G101-ROUND($G101*10/23,0)-2*ROUND($G101/23,0),IF($H101=2,$G101,0))) -> 240 | K101: =IF($G101="","",IF($H101=1,ROUND($G101*10/23,0),IF($H101=3,$G101-2*ROUND($G101/12,0),IF($H101=4,$G101,IF(OR($H101=5,$H101=7),ROUND($G101*10/11,0),0))))) -> 0 | L101: =IF($G101="","",IF($H101=1,ROUND($G101/23,0),IF($H101=3,ROUND($G101/12,0),IF($H101=5,$G101-ROUND($G101*10/11,0),IF($H101=8,$G101,0))))) -> 0 | M101: =IF($G101="","",IF($H101=1,ROUND($G101/23,0),IF($H101=3,ROUND($G101/12,0),IF($H101=6,$G101,IF($H101=7,$G101-ROUND($G101*10/11,0),0))))) -> 0 | N101: =IF($G101="","",K101+L101+M101) -> 0 | O101: =IF($G101="","",IFERROR(VLOOKUP($D101&"|"&$E101,科目表!$A$5:$B$200,2,FALSE),"※未登録")) -> 互助会費 | P101: =IF(OR($G101="",$C101=""),"",IF($B101="決算整理",13,MOD(MONTH($C101)-4,12)+1)) -> 3 | Q101: =IF($G101="","",TRIM(IF(J101+K101+L101+M101<>$G101,"按分不一致 ","")&IF(O101="※未登録","科目未登録 ","")&IF(OR($H101="",ISERROR(MATCH($H101,{1,2,3,4,5,6,7,8},0))),"経費区分? ","")&IF($I101="","状態未設定 ","")&IF(AND(OR($I101="確認済",$I101="未確認"),$B101="月例",OR($C101="",$C101<DATE(年度+2018,4,1),$C101>DATE(年度+2019,3,31))),"年度外の日付 ","")&IF(AND(OR($I101="確認済",$I101="未確認"),O101="対象外"),"対象外の科目 ",""))) | R101: 月例!103
...

Sheet 入力_貸付
A1: 入力_貸付 貸付経理 台帳（旧：貸付予算差引簿を一本化）
A2: 科目ごとに並べてあります（予算差引簿と同じ見方で「見込残額」が見られます）。新しい支払は最終行の下に追記してください。 状態の使い方は「入力_業務」と同じです。 種別「決算整理」＝3月分を4月に支払うもの（旧：黄色）。
A4: No | B4: 種別 | C4: 支払日 | D4: 科目 | E4: 摘要 | F4: 金額 | G4: 状態 | H4: 計上列 | I4: 見込残額 | J4: 点検 | K4: 元データ
A5: 1 | B5: 通常 | C5: 45559 | D5: 厚生費 | E5: 定期健康診断等（神岡、中村、作本） | F5: 10890 | G5: 昨年実績 | H5: =IF(OR($F5="",$C5=""),"",IF($B5="決算整理",13,MOD(MONTH($C5)-4,12)+1)) -> 6 | I5: =IF(OR($F5="",$D5=""),"",IFERROR(INDEX(費用収益表_貸付!$S$1:$S$60,VLOOKUP($D5,科目表!$K$5:$L$40,2,FALSE))-SUMIFS($F$5:$F5,$D$5:$D5,$D5),"?")) -> 13110 | J5: =IF($F5="","",TRIM(IF(ISERROR(MATCH($D5,科目表!$K$5:$K$40,0)),"科目未登録 ","")&IF($G5="","状態未設定 ","")&IF(AND(OR($G5="確認済",$G5="未確認"),$B5="通常",OR($C5="",$C5<DATE(年度+2018,4,1),$C5>DATE(年度+2019,3,31))),"年度外の日付 ",""))) | K5: 管理簿②!6
A6: 2 | B6: 通常 | C6: 44592 | D6: 厚生費 | E6: 人間ドック 神岡 | F6: 13940 | G6: 昨年実績 | H6: =IF(OR($F6="",$C6=""),"",IF($B6="決算整理",13,MOD(MONTH($C6)-4,12)+1)) -> 10 | I6: =IF(OR($F6="",$D6=""),"",IFERROR(INDEX(費用収益表_貸付!$S$1:$S$60,VLOOKUP($D6,科目表!$K$5:$L$40,2,FALSE))-SUMIFS($F$5:$F6,$D$5:$D6,$D6),"?")) -> -830 | J6: =IF($F6="","",TRIM(IF(ISERROR(MATCH($D6,科目表!$K$5:$K$40,0)),"科目未登録 ","")&IF($G6="","状態未設定 ","")&IF(AND(OR($G6="確認済",$G6="未確認"),$B6="通常",OR($C6="",$C6<DATE(年度+2018,4,1),$C6>DATE(年度+2019,3,31))),"年度外の日付 ",""))) | K6: 管理簿②!7
A7: 3 | B7: 通常 | C7: 44592 | D7: 厚生費 | E7: 定期健康診断（勝部、作本） | F7: 13860 | G7: 昨年実績 | H7: =IF(OR($F7="",$C7=""),"",IF($B7="決算整理",13,MOD(MONTH($C7)-4,12)+1)) -> 10 | I7: =IF(OR($F7="",$D7=""),"",IFERROR(INDEX(費用収益表_貸付!$S$1:$S$60,VLOOKUP($D7,科目表!$K$5:$L$40,2,FALSE))-SUMIFS($F$5:$F7,$D$5:$D7,$D7),"?")) -> -14690 | J7: =IF($F7="","",TRIM(IF(ISERROR(MATCH($D7,科目表!$K$5:$K$40,0)),"科目未登録 ","")&IF($G7="","状態未設定 ","")&IF(AND(OR($G7="確認済",$G7="未確認"),$B7="通常",OR($C7="",$C7<DATE(年度+2018,4,1),$C7>DATE(年度+2019,3,31))),"年度外の日付 ",""))) | K7: 管理簿②!8
A8: 4 | B8: 通常 | C8: 46262 | D8: 厚生費 | E8: 定期健康診断等 貸付経理分（神岡） | F8: 1980 | G8: 確認済 | H8: =IF(OR($F8="",$C8=""),"",IF($B8="決算整理",13,MOD(MONTH($C8)-4,12)+1)) -> 5 | I8: =IF(OR($F8="",$D8=""),"",IFERROR(INDEX(費用収益表_貸付!$S$1:$S$60,VLOOKUP($D8,科目表!$K$5:$L$40,2,FALSE))-SUMIFS($F$5:$F8,$D$5:$D8,$D8),"?")) -> -16670 | J8: =IF($F8="","",TRIM(IF(ISERROR(MATCH($D8,科目表!$K$5:$K$40,0)),"科目未登録 ","")&IF($G8="","状態未設定 ","")&IF(AND(OR($G8="確認済",$G8="未確認"),$B8="通常",OR($C8="",$C8<DATE(年度+2018,4,1),$C8>DATE(年度+2019,3,31))),"年度外の日付 ",""))) | K8: 管理簿②!9
A9: 5 | B9: 通常 | C9: 46280 | D9: 厚生費 | E9: 定期健康診断（中村、作本、福場） | F9: 21527 | G9: 確認済 | H9: =IF(OR($F9="",$C9=""),"",IF($B9="決算整理",13,MOD(MONTH($C9)-4,12)+1)) -> 6 | I9: =IF(OR($F9="",$D9=""),"",IFERROR(INDEX(費用収益表_貸付!$S$1:$S$60,VLOOKUP($D9,科目表!$K$5:$L$40,2,FALSE))-SUMIFS($F$5:$F9,$D$5:$D9,$D9),"?")) -> -38197 | J9: =IF($F9="","",TRIM(IF(ISERROR(MATCH($D9,科目表!$K$5:$K$40,0)),"科目未登録 ","")&IF($G9="","状態未設定 ","")&IF(AND(OR($G9="確認済",$G9="未確認"),$B9="通常",OR($C9="",$C9<DATE(年度+2018,4,1),$C9>DATE(年度+2019,3,31))),"年度外の日付 ",""))) | K9: 管理簿②!11
A10: 6 | B10: 通常 | C10: 46140 | D10: 事務用消耗品費 | E10: 令和８年度基幹ウイルス対策ソフト（ミツイワ株式会社） | F10: 4389 | G10: 確認済 | H10: =IF(OR($F10="",$C10=""),"",IF($B10="決算整理",13,MOD(MONTH($C10)-4,12)+1)) -> 1 | I10: =IF(OR($F10="",$D10=""),"",IFERROR(INDEX(費用収益表_貸付!$S$1:$S$60,VLOOKUP($D10,科目表!$K$5:$L$40,2,FALSE))-SUMIFS($F$5:$F10,$D$5:$D10,$D10),"?")) -> 437611 | J10: =IF($F10="","",TRIM(IF(ISERROR(MATCH($D10,科目表!$K$5:$K$40,0)),"科目未登録 ","")&IF($G10="","状態未設定 ","")&IF(AND(OR($G10="確認済",$G10="未確認"),$B10="通常",OR($C10="",$C10<DATE(年度+2018,4,1),$C10>DATE(年度+2019,3,31))),"年度外の日付 ",""))) | K10: 管理簿①!6
A11: 7 | B11: 通常 | C11: 46188 | D11: 事務用消耗品費 | E11: フラッグインデックス ６８２－１－ＲＥ ２個 ほか８点 | F11: 11491 | G11: 確認済 | H11: =IF(OR($F11="",$C11=""),"",IF($B11="決算整理",13,MOD(MONTH($C11)-4,12)+1)) -> 3 | I11: =IF(OR($F11="",$D11=""),"",IFERROR(INDEX(費用収益表_貸付!$S$1:$S$60,VLOOKUP($D11,科目表!$K$5:$L$40,2,FALSE))-SUMIFS($F$5:$F11,$D$5:$D11,$D11),"?")) -> 426120 | J11: =IF($F11="","",TRIM(IF(ISERROR(MATCH($D11,科目表!$K$5:$K$40,0)),"科目未登録 ","")&IF($G11="","状態未設定 ","")&IF(AND(OR($G11="確認済",$G11="未確認"),$B11="通常",OR($C11="",$C11<DATE(年度+2018,4,1),$C11>DATE(年度+2019,3,31))),"年度外の日付 ",""))) | K11: 管理簿①!7
A12: 8 | B12: 通常 | C12: 45884 | D12: 事務用消耗品費 | E12: ドラムカートリッジ純正品（LB322） １個 | F12: 45265 | G12: 昨年実績 | H12: =IF(OR($F12="",$C12=""),"",IF($B12="決算整理",13,MOD(MONTH($C12)-4,12)+1)) -> 5 | I12: =IF(OR($F12="",$D12=""),"",IFERROR(INDEX(費用収益表_貸付!$S$1:$S$60,VLOOKUP($D12,科目表!$K$5:$L$40,2,FALSE))-SUMIFS($F$5:$F12,$D$5:$D12,$D12),"?")) -> 380855 | J12: =IF($F12="","",TRIM(IF(ISERROR(MATCH($D12,科目表!$K$5:$K$40,0)),"科目未登録 ","")&IF($G12="","状態未設定 ","")&IF(AND(OR($G12="確認済",$G12="未確認"),$B12="通常",OR($C12="",$C12<DATE(年度+2018,4,1),$C12>DATE(年度+2019,3,31))),"年度外の日付 ",""))) | K12: 管理簿①!8
A13: 9 | B13: 通常 | C13: 44515 | D13: 事務用消耗品費 | E13: ニイタカケミガード４㎏ | F13: 2700 | G13: 昨年実績 | H13: =IF(OR($F13="",$C13=""),"",IF($B13="決算整理",13,MOD(MONTH($C13)-4,12)+1)) -> 8 | I13: =IF(OR($F13="",$D13=""),"",IFERROR(INDEX(費用収益表_貸付!$S$1:$S$60,VLOOKUP($D13,科目表!$K$5:$L$40,2,FALSE))-SUMIFS($F$5:$F13,$D$5:$D13,$D13),"?")) -> 378155 | J13: =IF($F13="","",TRIM(IF(ISERROR(MATCH($D13,科目表!$K$5:$K$40,0)),"科目未登録 ","")&IF($G13="","状態未設定 ","")&IF(AND(OR($G13="確認済",$G13="未確認"),$B13="通常",OR($C13="",$C13<DATE(年度+2018,4,1),$C13>DATE(年度+2019,3,31))),"年度外の日付 ",""))) | K13: 管理簿①!9
A14: 10 | B14: 通常 | C14: 45562 | D14: 事務用消耗品費 | E14: トナーカートリッジ再生品（ＬＰＢ３Ｔ３４） 3個 | F14: 22770 | G14: 昨年実績 | H14: =IF(OR($F14="",$C14=""),"",IF($B14="決算整理",13,MOD(MONTH($C14)-4,12)+1)) -> 6 | I14: =IF(OR($F14="",$D14=""),"",IFERROR(INDEX(費用収益表_貸付!$S$1:$S$60,VLOOKUP($D14,科目表!$K$5:$L$40,2,FALSE))-SUMIFS($F$5:$F14,$D$5:$D14,$D14),"?")) -> 355385 | J14: =IF($F14="","",TRIM(IF(ISERROR(MATCH($D14,科目表!$K$5:$K$40,0)),"科目未登録 ","")&IF($G14="","状態未設定 ","")&IF(AND(OR($G14="確認済",$G14="未確認"),$B14="通常",OR($C14="",$C14<DATE(年度+2018,4,1),$C14>DATE(年度+2019,3,31))),"年度外の日付 ",""))) | K14: 管理簿①!10
A15: 11 | B15: 通常 | C15: 45588 | D15: 事務用消耗品費 | E15: ＤＶＤドライブ ＬＤＲ－ＰＭＪ８Ｕ２ＬＢＫ １台 | F15: 5162 | G15: 昨年実績 | H15: =IF(OR($F15="",$C15=""),"",IF($B15="決算整理",13,MOD(MONTH($C15)-4,12)+1)) -> 7 | I15: =IF(OR($F15="",$D15=""),"",IFERROR(INDEX(費用収益表_貸付!$S$1:$S$60,VLOOKUP($D15,科目表!$K$5:$L$40,2,FALSE))-SUMIFS($F$5:$F15,$D$5:$D15,$D15),"?")) -> 350223 | J15: =IF($F15="","",TRIM(IF(ISERROR(MATCH($D15,科目表!$K$5:$K$40,0)),"科目未登録 ","")&IF($G15="","状態未設定 ","")&IF(AND(OR($G15="確認済",$G15="未確認"),$B15="通常",OR($C15="",$C15<DATE(年度+2018,4,1),$C15>DATE(年度+2019,3,31))),"年度外の日付 ",""))) | K15: 管理簿①!11
A16: 12 | B16: 通常 | C16: 44620 | D16: 事務用消耗品費 | E16: トナーカートリッジ（ＰＲ－Ｌ８３００－１２） 5個 | F16: 49500 | G16: 昨年実績 | H16: =IF(OR($F16="",$C16=""),"",IF($B16="決算整理",13,MOD(MONTH($C16)-4,12)+1)) -> 11 | I16: =IF(OR($F16="",$D16=""),"",IFERROR(INDEX(費用収益表_貸付!$S$1:$S$60,VLOOKUP($D16,科目表!$K$5:$L$40,2,FALSE))-SUMIFS($F$5:$F16,$D$5:$D16,$D16),"?")) -> 300723 | J16: =IF($F16="","",TRIM(IF(ISERROR(MATCH($D16,科目表!$K$5:$K$40,0)),"科目未登録 ","")&IF($G16="","状態未設定 ","")&IF(AND(OR($G16="確認済",$G16="未確認"),$B16="通常",OR($C16="",$C16<DATE(年度+2018,4,1),$C16>DATE(年度+2019,3,31))),"年度外の日付 ",""))) | K16: 管理簿①!12
... A35: 31 | B35: 通常 | C35: 43899 | D35: 通信運搬費 | E35: パスピーチャージ | F35: 30000 | G35: 昨年実績 | H35: =IF(OR($F35="",$C35=""),"",IF($B35="決算整理",13,MOD(MONTH($C35)-4,12)+1)) -> 12 | I35: =IF(OR($F35="",$D35=""),"",IFERROR(INDEX(費用収益表_貸付!$S$1:$S$60,VLOOKUP($D35,科目表!$K$5:$L$40,2,FALSE))-SUMIFS($F$5:$F35,$D$5:$D35,$D35),"?")) -> 15771 | J35: =IF($F35="","",TRIM(IF(ISERROR(MATCH($D35,科目表!$K$5:$K$40,0)),"科目未登録 ","")&IF($G35="","状態未設定 ","")&IF(AND(OR($G35="確認済",$G35="未確認"),$B35="通常",OR($C35="",$C35<DATE(年度+2018,4,1),$C35>DATE(年度+2019,3,31))),"年度外の日付 ",""))) | K35: 管理簿①!30
A36: 32 | B36: 通常 | D36: 通信運搬費 | E36: 分担金ファックス代 | F36: 6340 | G36: 昨年実績 | H36: =IF(OR($F36="",$C36=""),"",IF($B36="決算整理",13,MOD(MONTH($C36)-4,12)+1)) | I36: =IF(OR($F36="",$D36=""),"",IFERROR(INDEX(費用収益表_貸付!$S$1:$S$60,VLOOKUP($D36,科目表!$K$5:$L$40,2,FALSE))-SUMIFS($F$5:$F36,$D$5:$D36,$D36),"?")) -> 9431 | J36: =IF($F36="","",TRIM(IF(ISERROR(MATCH($D36,科目表!$K$5:$K$40,0)),"科目未登録 ","")&IF($G36="","状態未設定 ","")&IF(AND(OR($G36="確認済",$G36="未確認"),$B36="通常",OR($C36="",$C36<DATE(年度+2018,4,1),$C36>DATE(年度+2019,3,31))),"年度外の日付 ",""))) | K36: 管理簿①!40
A37: 33 | B37: 通常 | C37: 46171 | D37: 事務費・雑費 | E37: 広銀手数料（４月分） | F37: 16190 | G37: 確認済 | H37: =IF(OR($F37="",$C37=""),"",IF($B37="決算整理",13,MOD(MONTH($C37)-4,12)+1)) -> 2 | I37: =IF(OR($F37="",$D37=""),"",IFERROR(INDEX(費用収益表_貸付!$S$1:$S$60,VLOOKUP($D37,科目表!$K$5:$L$40,2,FALSE))-SUMIFS($F$5:$F37,$D$5:$D37,$D37),"?")) -> 173810 | J37: =IF($F37="","",TRIM(IF(ISERROR(MATCH($D37,科目表!$K$5:$K$40,0)),"科目未登録 ","")&IF($G37="","状態未設定 ","")&IF(AND(OR($G37="確認済",$G37="未確認"),$B37="通常",OR($C37="",$C37<DATE(年度+2018,4,1),$C37>DATE(年度+2019,3,31))),"年度外の日付 ",""))) | K37: 管理簿①!35
A38: 34 | B38: 通常 | C38: 46203 | D38: 事務費・雑費 | E38: 広銀手数料（５月分） | F38: 5750 | G38: 確認済 | H38: =IF(OR($F38="",$C38=""),"",IF($B38="決算整理",13,MOD(MONTH($C38)-4,12)+1)) -> 3 | I38: =IF(OR($F38="",$D38=""),"",IFERROR(INDEX(費用収益表_貸付!$S$1:$S$60,VLOOKUP($D38,科目表!$K$5:$L$40,2,FALSE))-SUMIFS($F$5:$F38,$D$5:$D38,$D38),"?")) -> 168060 | J38: =IF($F38="","",TRIM(IF(ISERROR(MATCH($D38,科目表!$K$5:$K$40,0)),"科目未登録 ","")&IF($G38="","状態未設定 ","")&IF(AND(OR($G38="確認済",$G38="未確認"),$B38="通常",OR($C38="",$C38<DATE(年度+2018,4,1),$C38>DATE(年度+2019,3,31))),"年度外の日付 ",""))) | K38: 管理簿①!36
A39: 35 | B39: 通常 | C39: 46234 | D39: 事務費・雑費 | E39: 広銀手数料（６月分） | F39: 6090 | G39: 確認済 | H39: =IF(OR($F39="",$C39=""),"",IF($B39="決算整理",13,MOD(MONTH($C39)-4,12)+1)) -> 4 | I39: =IF(OR($F39="",$D39=""),"",IFERROR(INDEX(費用収益表_貸付!$S$1:$S$60,VLOOKUP($D39,科目表!$K$5:$L$40,2,FALSE))-SUMIFS($F$5:$F39,$D$5:$D39,$D39),"?")) -> 161970 | J39: =IF($F39="","",TRIM(IF(ISERROR(MATCH($D39,科目表!$K$5:$K$40,0)),"科目未登録 ","")&IF($G39="","状態未設定 ","")&IF(AND(OR($G39="確認済",$G39="未確認"),$B39="通常",OR($C39="",$C39<DATE(年度+2018,4,1),$C39>DATE(年度+2019,3,31))),"年度外の日付 ",""))) | K39: 管理簿①!37
A40: 36 | B40: 通常 | C40: 46265 | D40: 事務費・雑費 | E40: 広銀手数料（７月分） | F40: 5530 | G40: 確認済 | H40: =IF(OR($F40="",$C40=""),"",IF($B40="決算整理",13,MOD(MONTH($C40)-4,12)+1)) -> 5 | I40: =IF(OR($F40="",$D40=""),"",IFERROR(INDEX(費用収益表_貸付!$S$1:$S$60,VLOOKUP($D40,科目表!$K$5:$L$40,2,FALSE))-SUMIFS($F$5:$F40,$D$5:$D40,$D40),"?")) -> 156440 | J40: =IF($F40="","",TRIM(IF(ISERROR(MATCH($D40,科目表!$K$5:$K$40,0)),"科目未登録 ","")&IF($G40="","状態未設定 ","")&IF(AND(OR($G40="確認済",$G40="未確認"),$B40="通常",OR($C40="",$C40<DATE(年度+2018,4,1),$C40>DATE(年度+2019,3,31))),"年度外の日付 ",""))) | K40: 管理簿①!38
A41: 37 | B41: 通常 | C41: 46295 | D41: 事務費・雑費 | E41: 広銀手数料（８月分） | F41: 5190 | G41: 確認済 | H41: =IF(OR($F41="",$C41=""),"",IF($B41="決算整理",13,MOD(MONTH($C41)-4,12)+1)) -> 6 | I41: =IF(OR($F41="",$D41=""),"",IFERROR(INDEX(費用収益表_貸付!$S$1:$S$60,VLOOKUP($D41,科目表!$K$5:$L$40,2,FALSE))-SUMIFS($F$5:$F41,$D$5:$D41,$D41),"?")) -> 151250 | J41: =IF($F41="","",TRIM(IF(ISERROR(MATCH($D41,科目表!$K$5:$K$40,0)),"科目未登録 ","")&IF($G41="","状態未設定 ","")&IF(AND(OR($G41="確認済",$G41="未確認"),$B41="通常",OR($C41="",$C41<DATE(年度+2018,4,1),$C41>DATE(年度+2019,3,31))),"年度外の日付 ",""))) | K41: 管理簿①!39
A42: 38 | B42: 通常 | C42: 46325 | D42: 事務費・雑費 | E42: 広銀手数料（９月分） | F42: 5200 | G42: 確認済 | H42: =IF(OR($F42="",$C42=""),"",IF($B42="決算整理",13,MOD(MONTH($C42)-4,12)+1)) -> 7 | I42: =IF(OR($F42="",$D42=""),"",IFERROR(INDEX(費用収益表_貸付!$S$1:$S$60,VLOOKUP($D42,科目表!$K$5:$L$40,2,FALSE))-SUMIFS($F$5:$F42,$D$5:$D42,$D42),"?")) -> 146050 | J42: =IF($F42="","",TRIM(IF(ISERROR(MATCH($D42,科目表!$K$5:$K$40,0)),"科目未登録 ","")&IF($G42="","状態未設定 ","")&IF(AND(OR($G42="確認済",$G42="未確認"),$B42="通常",OR($C42="",$C42<DATE(年度+2018,4,1),$C42>DATE(年度+2019,3,31))),"年度外の日付 ",""))) | K42: 管理簿①!40
A43: 39 | B43: 通常 | C43: 45981 | D43: 事務費・雑費 | E43: 広銀手数料（１０月分） | F43: 5750 | G43: 昨年実績 | H43: =IF(OR($F43="",$C43=""),"",IF($B43="決算整理",13,MOD(MONTH($C43)-4,12)+1)) -> 8 | I43: =IF(OR($F43="",$D43=""),"",IFERROR(INDEX(費用収益表_貸付!$S$1:$S$60,VLOOKUP($D43,科目表!$K$5:$L$40,2,FALSE))-SUMIFS($F$5:$F43,$D$5:$D43,$D43),"?")) -> 140300 | J43: =IF($F43="","",TRIM(IF(ISERROR(MATCH($D43,科目表!$K$5:$K$40,0)),"科目未登録 ","")&IF($G43="","状態未設定 ","")&IF(AND(OR($G43="確認済",$G43="未確認"),$B43="通常",OR($C43="",$C43<DATE(年度+2018,4,1),$C43>DATE(年度+2019,3,31))),"年度外の日付 ",""))) | K43: 管理簿①!41
A44: 40 | B44: 通常 | C44: 46010 | D44: 事務費・雑費 | E44: 広銀手数料（１１月分） | F44: 9239 | G44: 昨年実績 | H44: =IF(OR($F44="",$C44=""),"",IF($B44="決算整理",13,MOD(MONTH($C44)-4,12)+1)) -> 9 | I44: =IF(OR($F44="",$D44=""),"",IFERROR(INDEX(費用収益表_貸付!$S$1:$S$60,VLOOKUP($D44,科目表!$K$5:$L$40,2,FALSE))-SUMIFS($F$5:$F44,$D$5:$D44,$D44),"?")) -> 131061 | J44: =IF($F44="","",TRIM(IF(ISERROR(MATCH($D44,科目表!$K$5:$K$40,0)),"科目未登録 ","")&IF($G44="","状態未設定 ","")&IF(AND(OR($G44="確認済",$G44="未確認"),$B44="通常",OR($C44="",$C44<DATE(年度+2018,4,1),$C44>DATE(年度+2019,3,31))),"年度外の日付 ",""))) | K44: 管理簿①!42
A45: 41 | B45: 通常 | C45: 46035 | D45: 事務費・雑費 | E45: HITLINE基本料 | F45: 2200 | G45: 昨年実績 | H45: =IF(OR($F45="",$C45=""),"",IF($B45="決算整理",13,MOD(MONTH($C45)-4,12)+1)) -> 10 | I45: =IF(OR($F45="",$D45=""),"",IFERROR(INDEX(費用収益表_貸付!$S$1:$S$60,VLOOKUP($D45,科目表!$K$5:$L$40,2,FALSE))-SUMIFS($F$5:$F45,$D$5:$D45,$D45),"?")) -> 128861 | J45: =IF($F45="","",TRIM(IF(ISERROR(MATCH($D45,科目表!$K$5:$K$40,0)),"科目未登録 ","")&IF($G45="","状態未設定 ","")&IF(AND(OR($G45="確認済",$G45="未確認"),$B45="通常",OR($C45="",$C45<DATE(年度+2018,4,1),$C45>DATE(年度+2019,3,31))),"年度外の日付 ",""))) | K45: 管理簿①!43
A46: 42 | B46: 通常 | C46: 46035 | D46: 事務費・雑費 | E46: HITLINE手数料 | F46: 11220 | G46: 昨年実績 | H46: =IF(OR($F46="",$C46=""),"",IF($B46="決算整理",13,MOD(MONTH($C46)-4,12)+1)) -> 10 | I46: =IF(OR($F46="",$D46=""),"",IFERROR(INDEX(費用収益表_貸付!$S$1:$S$60,VLOOKUP($D46,科目表!$K$5:$L$40,2,FALSE))-SUMIFS($F$5:$F46,$D$5:$D46,$D46),"?")) -> 117641 | J46: =IF($F46="","",TRIM(IF(ISERROR(MATCH($D46,科目表!$K$5:$K$40,0)),"科目未登録 ","")&IF($G46="","状態未設定 ","")&IF(AND(OR($G46="確認済",$G46="未確認"),$B46="通常",OR($C46="",$C46<DATE(年度+2018,4,1),$C46>DATE(年度+2019,3,31))),"年度外の日付 ",""))) | K46: 管理簿①!44
A47: 43 | B47: 通常 | C47: 46051 | D47: 事務費・雑費 | E47: 広銀手数料（１２月分） | F47: 6210 | G47: 昨年実績 | H47: =IF(OR($F47="",$C47=""),"",IF($B47="決算整理",13,MOD(MONTH($C47)-4,12)+1)) -> 10 | I47: =IF(OR($F47="",$D47=""),"",IFERROR(INDEX(費用収益表_貸付!$S$1:$S$60,VLOOKUP($D47,科目表!$K$5:$L$40,2,FALSE))-SUMIFS($F$5:$F47,$D$5:$D47,$D47),"?")) -> 111431 | J47: =IF($F47="","",TRIM(IF(ISERROR(MATCH($D47,科目表!$K$5:$K$40,0)),"科目未登録 ","")&IF($G47="","状態未設定 ","")&IF(AND(OR($G47="確認済",$G47="未確認"),$B47="通常",OR($C47="",$C47<DATE(年度+2018,4,1),$C47>DATE(年度+2019,3,31))),"年度外の日付 ",""))) | K47: 管理簿①!45
A48: 44 | B48: 通常 | C48: 46078 | D48: 事務費・雑費 | E48: 広銀手数料（１月分） | F48: 7190 | G48: 昨年実績 | H48: =IF(OR($F48="",$C48=""),"",IF($B48="決算整理",13,MOD(MONTH($C48)-4,12)+1)) -> 11 | I48: =IF(OR($F48="",$D48=""),"",IFERROR(INDEX(費用収益表_貸付!$S$1:$S$60,VLOOKUP($D48,科目表!$K$5:$L$40,2,FALSE))-SUMIFS($F$5:$F48,$D$5:$D48,$D48),"?")) -> 104241 | J48: =IF($F48="","",TRIM(IF(ISERROR(MATCH($D48,科目表!$K$5:$K$40,0)),"科目未登録 ","")&IF($G48="","状態未設定 ","")&IF(AND(OR($G48="確認済",$G48="未確認"),$B48="通常",OR($C48="",$C48<DATE(年度+2018,4,1),$C48>DATE(年度+2019,3,31))),"年度外の日付 ",""))) | K48: 管理簿①!46
... A87: 83 | B87: 通常 | C87: 46210 | D87: 労災・雇用等保険料 | E87: 労働保険料・一般拠出金 事業主負担分 | F87: 129149 | G87: 確認済 | H87: =IF(OR($F87="",$C87=""),"",IF($B87="決算整理",13,MOD(MONTH($C87)-4,12)+1)) -> 4 | I87: =IF(OR($F87="",$D87=""),"",IFERROR(INDEX(費用収益表_貸付!$S$1:$S$60,VLOOKUP($D87,科目表!$K$5:$L$40,2,FALSE))-SUMIFS($F$5:$F87,$D$5:$D87,$D87),"?")) -> -129149 | J87: =IF($F87="","",TRIM(IF(ISERROR(MATCH($D87,科目表!$K$5:$K$40,0)),"科目未登録 ","")&IF($G87="","状態未設定 ","")&IF(AND(OR($G87="確認済",$G87="未確認"),$B87="通常",OR($C87="",$C87<DATE(年度+2018,4,1),$C87>DATE(年度+2019,3,31))),"年度外の日付 ",""))) | K87: 管理簿②!28
H88: =IF(OR($F88="",$C88=""),"",IF($B88="決算整理",13,MOD(MONTH($C88)-4,12)+1)) | I88: =IF(OR($F88="",$D88=""),"",IFERROR(INDEX(費用収益表_貸付!$S$1:$S$60,VLOOKUP($D88,科目表!$K$5:$L$40,2,FALSE))-SUMIFS($F$5:$F88,$D$5:$D88,$D88),"?")) | J88: =IF($F88="","",TRIM(IF(ISERROR(MATCH($D88,科目表!$K$5:$K$40,0)),"科目未登録 ","")&IF($G88="","状態未設定 ","")&IF(AND(OR($G88="確認済",$G88="未確認"),$B88="通常",OR($C88="",$C88<DATE(年度+2018,4,1),$C88>DATE(年度+2019,3,31))),"年度外の日付 ","")))
H89: =IF(OR($F89="",$C89=""),"",IF($B89="決算整理",13,MOD(MONTH($C89)-4,12)+1)) | I89: =IF(OR($F89="",$D89=""),"",IFERROR(INDEX(費用収益表_貸付!$S$1:$S$60,VLOOKUP($D89,科目表!$K$5:$L$40,2,FALSE))-SUMIFS($F$5:$F89,$D$5:$D89,$D89),"?")) | J89: =IF($F89="","",TRIM(IF(ISERROR(MATCH($D89,科目表!$K$5:$K$40,0)),"科目未登録 ","")&IF($G89="","状態未設定 ","")&IF(AND(OR($G89="確認済",$G89="未確認"),$B89="通常",OR($C89="",$C89<DATE(年度+2018,4,1),$C89>DATE(年度+2019,3,31))),"年度外の日付 ","")))
H90: =IF(OR($F90="",$C90=""),"",IF($B90="決算整理",13,MOD(MONTH($C90)-4,12)+1)) | I90: =IF(OR($F90="",$D90=""),"",IFERROR(INDEX(費用収益表_貸付!$S$1:$S$60,VLOOKUP($D90,科目表!$K$5:$L$40,2,FALSE))-SUMIFS($F$5:$F90,$D$5:$D90,$D90),"?")) | J90: =IF($F90="","",TRIM(IF(ISERROR(MATCH($D90,科目表!$K$5:$K$40,0)),"科目未登録 ","")&IF($G90="","状態未設定 ","")&IF(AND(OR($G90="確認済",$G90="未確認"),$B90="通常",OR($C90="",$C90<DATE(年度+2018,4,1),$C90>DATE(年度+2019,3,31))),"年度外の日付 ","")))
H91: =IF(OR($F91="",$C91=""),"",IF($B91="決算整理",13,MOD(MONTH($C91)-4,12)+1)) | I91: =IF(OR($F91="",$D91=""),"",IFERROR(INDEX(費用収益表_貸付!$S$1:$S$60,VLOOKUP($D91,科目表!$K$5:$L$40,2,FALSE))-SUMIFS($F$5:$F91,$D$5:$D91,$D91),"?")) | J91: =IF($F91="","",TRIM(IF(ISERROR(MATCH($D91,科目表!$K$5:$K$40,0)),"科目未登録 ","")&IF($G91="","状態未設定 ","")&IF(AND(OR($G91="確認済",$G91="未確認"),$B91="通常",OR($C91="",$C91<DATE(年度+2018,4,1),$C91>DATE(年度+2019,3,31))),"年度外の日付 ","")))
H92: =IF(OR($F92="",$C92=""),"",IF($B92="決算整理",13,MOD(MONTH($C92)-4,12)+1)) | I92: =IF(OR($F92="",$D92=""),"",IFERROR(INDEX(費用収益表_貸付!$S$1:$S$60,VLOOKUP($D92,科目表!$K$5:$L$40,2,FALSE))-SUMIFS($F$5:$F92,$D$5:$D92,$D92),"?")) | J92: =IF($F92="","",TRIM(IF(ISERROR(MATCH($D92,科目表!$K$5:$K$40,0)),"科目未登録 ","")&IF($G92="","状態未設定 ","")&IF(AND(OR($G92="確認済",$G92="未確認"),$B92="通常",OR($C92="",$C92<DATE(年度+2018,4,1),$C92>DATE(年度+2019,3,31))),"年度外の日付 ","")))
H93: =IF(OR($F93="",$C93=""),"",IF($B93="決算整理",13,MOD(MONTH($C93)-4,12)+1)) | I93: =IF(OR($F93="",$D93=""),"",IFERROR(INDEX(費用収益表_貸付!$S$1:$S$60,VLOOKUP($D93,科目表!$K$5:$L$40,2,FALSE))-SUMIFS($F$5:$F93,$D$5:$D93,$D93),"?")) | J93: =IF($F93="","",TRIM(IF(ISERROR(MATCH($D93,科目表!$K$5:$K$40,0)),"科目未登録 ","")&IF($G93="","状態未設定 ","")&IF(AND(OR($G93="確認済",$G93="未確認"),$B93="通常",OR($C93="",$C93<DATE(年度+2018,4,1),$C93>DATE(年度+2019,3,31))),"年度外の日付 ","")))
H94: =IF(OR($F94="",$C94=""),"",IF($B94="決算整理",13,MOD(MONTH($C94)-4,12)+1)) | I94: =IF(OR($F94="",$D94=""),"",IFERROR(INDEX(費用収益表_貸付!$S$1:$S$60,VLOOKUP($D94,科目表!$K$5:$L$40,2,FALSE))-SUMIFS($F$5:$F94,$D$5:$D94,$D94),"?")) | J94: =IF($F94="","",TRIM(IF(ISERROR(MATCH($D94,科目表!$K$5:$K$40,0)),"科目未登録 ","")&IF($G94="","状態未設定 ","")&IF(AND(OR($G94="確認済",$G94="未確認"),$B94="通常",OR($C94="",$C94<DATE(年度+2018,4,1),$C94>DATE(年度+2019,3,31))),"年度外の日付 ","")))
H95: =IF(OR($F95="",$C95=""),"",IF($B95="決算整理",13,MOD(MONTH($C95)-4,12)+1)) | I95: =IF(OR($F95="",$D95=""),"",IFERROR(INDEX(費用収益表_貸付!$S$1:$S$60,VLOOKUP($D95,科目表!$K$5:$L$40,2,FALSE))-SUMIFS($F$5:$F95,$D$5:$D95,$D95),"?")) | J95: =IF($F95="","",TRIM(IF(ISERROR(MATCH($D95,科目表!$K$5:$K$40,0)),"科目未登録 ","")&IF($G95="","状態未設定 ","")&IF(AND(OR($G95="確認済",$G95="未確認"),$B95="通常",OR($C95="",$C95<DATE(年度+2018,4,1),$C95>DATE(年度+2019,3,31))),"年度外の日付 ","")))
H96: =IF(OR($F96="",$C96=""),"",IF($B96="決算整理",13,MOD(MONTH($C96)-4,12)+1)) | I96: =IF(OR($F96="",$D96=""),"",IFERROR(INDEX(費用収益表_貸付!$S$1:$S$60,VLOOKUP($D96,科目表!$K$5:$L$40,2,FALSE))-SUMIFS($F$5:$F96,$D$5:$D96,$D96),"?")) | J96: =IF($F96="","",TRIM(IF(ISERROR(MATCH($D96,科目表!$K$5:$K$40,0)),"科目未登録 ","")&IF($G96="","状態未設定 ","")&IF(AND(OR($G96="確認済",$G96="未確認"),$B96="通常",OR($C96="",$C96<DATE(年度+2018,4,1),$C96>DATE(年度+2019,3,31))),"年度外の日付 ","")))
H97: =IF(OR($F97="",$C97=""),"",IF($B97="決算整理",13,MOD(MONTH($C97)-4,12)+1)) | I97: =IF(OR($F97="",$D97=""),"",IFERROR(INDEX(費用収益表_貸付!$S$1:$S$60,VLOOKUP($D97,科目表!$K$5:$L$40,2,FALSE))-SUMIFS($F$5:$F97,$D$5:$D97,$D97),"?")) | J97: =IF($F97="","",TRIM(IF(ISERROR(MATCH($D97,科目表!$K$5:$K$40,0)),"科目未登録 ","")&IF($G97="","状態未設定 ","")&IF(AND(OR($G97="確認済",$G97="未確認"),$B97="通常",OR($C97="",$C97<DATE(年度+2018,4,1),$C97>DATE(年度+2019,3,31))),"年度外の日付 ","")))
H98: =IF(OR($F98="",$C98=""),"",IF($B98="決算整理",13,MOD(MONTH($C98)-4,12)+1)) | I98: =IF(OR($F98="",$D98=""),"",IFERROR(INDEX(費用収益表_貸付!$S$1:$S$60,VLOOKUP($D98,科目表!$K$5:$L$40,2,FALSE))-SUMIFS($F$5:$F98,$D$5:$D98,$D98),"?")) | J98: =IF($F98="","",TRIM(IF(ISERROR(MATCH($D98,科目表!$K$5:$K$40,0)),"科目未登録 ","")&IF($G98="","状態未設定 ","")&IF(AND(OR($G98="確認済",$G98="未確認"),$B98="通常",OR($C98="",$C98<DATE(年度+2018,4,1),$C98>DATE(年度+2019,3,31))),"年度外の日付 ","")))
H99: =IF(OR($F99="",$C99=""),"",IF($B99="決算整理",13,MOD(MONTH($C99)-4,12)+1)) | I99: =IF(OR($F99="",$D99=""),"",IFERROR(INDEX(費用収益表_貸付!$S$1:$S$60,VLOOKUP($D99,科目表!$K$5:$L$40,2,FALSE))-SUMIFS($F$5:$F99,$D$5:$D99,$D99),"?")) | J99: =IF($F99="","",TRIM(IF(ISERROR(MATCH($D99,科目表!$K$5:$K$40,0)),"科目未登録 ","")&IF($G99="","状態未設定 ","")&IF(AND(OR($G99="確認済",$G99="未確認"),$B99="通常",OR($C99="",$C99<DATE(年度+2018,4,1),$C99>DATE(年度+2019,3,31))),"年度外の日付 ","")))
... H404: =IF(OR($F404="",$C404=""),"",IF($B404="決算整理",13,MOD(MONTH($C404)-4,12)+1)) | I404: =IF(OR($F404="",$D404=""),"",IFERROR(INDEX(費用収益表_貸付!$S$1:$S$60,VLOOKUP($D404,科目表!$K$5:$L$40,2,FALSE))-SUMIFS($F$5:$F404,$D$5:$D404,$D404),"?")) | J404: =IF($F404="","",TRIM(IF(ISERROR(MATCH($D404,科目表!$K$5:$K$40,0)),"科目未登録 ","")&IF($G404="","状態未設定 ","")&IF(AND(OR($G404="確認済",$G404="未確認"),$B404="通常",OR($C404="",$C404<DATE(年度+2018,4,1),$C404>DATE(年度+2019,3,31))),"年度外の日付 ","")))

Sheet 費用収益表_業務合計
A1: ="令和"&年度&"年度 業務経理（長期・短期給付事務合計分） 費用収益表" -> 令和8年度 業務経理（長期・短期給付事務合計分） 費用収益表 | P1: 緑字＝未締め月（前年実績・見込）／黒字＝締め済み／青字＝手入力セル
A2: 費用 | C2: 1 | D2: 2 | E2: 3 | F2: 4 | G2: 5 | H2: 6 | I2: 7 | J2: 8 | K2: 9 | L2: 10 | M2: 11 | N2: 12 | O2: 13 | AA2: ▼ 参考値（旧表の値：未締め月に表示される前年実績・見込）
A3: 支払月 | C3: ４月支払 | D3: ５月 | E3: ６月 | F3: ７月 | G3: ８月 | H3: ９月 | I3: １０月 | J3: １１月 | K3: １２月 | L3: １月 | M3: ２月 | N3: ３月 | O3: ４月(未払） | P3: 決算額 | Q3: 予算額 | R3: 流用振替額 | S3: 予算現額 | T3: 不用額 | V3: 締め月まで 累計 | W3: 予算残額 （現在） | X3: 台帳連動 | AA3: 4月 | AB3: 5月 | AC3: 6月 | AD3: 7月 | AE3: 8月 | AF3: 9月 | AG3: 10月 | AH3: 11月 | AI3: 12月 | AJ3: 1月 | AK3: 2月 | AL3: 3月 | AM3: 4月(未払)
A4: 役員報酬 | C4: =SUM('費用収益表_業務長期'!C4,'費用収益表_業務短期'!C4) -> 0 | D4: =SUM('費用収益表_業務長期'!D4,'費用収益表_業務短期'!D4) -> 0 | E4: =SUM('費用収益表_業務長期'!E4,'費用収益表_業務短期'!E4) -> 22000 | F4: =SUM('費用収益表_業務長期'!F4,'費用収益表_業務短期'!F4) -> 0 | G4: =SUM('費用収益表_業務長期'!G4,'費用収益表_業務短期'!G4) -> 0 | H4: =SUM('費用収益表_業務長期'!H4,'費用収益表_業務短期'!H4) -> 0 | I4: =SUM('費用収益表_業務長期'!I4,'費用収益表_業務短期'!I4) -> 0 | J4: =SUM('費用収益表_業務長期'!J4,'費用収益表_業務短期'!J4) -> 0 | ... O4: =SUM('費用収益表_業務長期'!O4,'費用収益表_業務短期'!O4) -> 0 | P4: =SUM(C4:O4) -> 33000 | Q4: =SUM('費用収益表_業務長期'!Q4,'費用収益表_業務短期'!Q4) -> 33000 | R4: =SUM('費用収益表_業務長期'!R4,'費用収益表_業務短期'!R4) -> 0 | S4: =SUM('費用収益表_業務長期'!S4,'費用収益表_業務短期'!S4) -> 33000 | T4: =S4-P4 -> 0 | V4: =SUMIF($C$2:$N$2,"<="&締月,C4:N4) -> 22000 | W4: =S4-V4 -> 11000
A5: 職員給与 | B5: 基本給 | C5: =SUM('費用収益表_業務長期'!C5,'費用収益表_業務短期'!C5) -> 0 | D5: =SUM('費用収益表_業務長期'!D5,'費用収益表_業務短期'!D5) -> 0 | E5: =SUM('費用収益表_業務長期'!E5,'費用収益表_業務短期'!E5) -> 0 | F5: =SUM('費用収益表_業務長期'!F5,'費用収益表_業務短期'!F5) -> 0 | G5: =SUM('費用収益表_業務長期'!G5,'費用収益表_業務短期'!G5) -> 0 | H5: =SUM('費用収益表_業務長期'!H5,'費用収益表_業務短期'!H5) -> 0 | I5: =SUM('費用収益表_業務長期'!I5,'費用収益表_業務短期'!I5) -> 0 | J5: =SUM('費用収益表_業務長期'!J5,'費用収益表_業務短期'!J5) -> 0 | ... O5: =SUM('費用収益表_業務長期'!O5,'費用収益表_業務短期'!O5) -> 0 | P5: =SUM(C5:O5) -> 0 | Q5: =SUM('費用収益表_業務長期'!Q5,'費用収益表_業務短期'!Q5) -> 0 | R5: =SUM('費用収益表_業務長期'!R5,'費用収益表_業務短期'!R5) -> 0 | S5: =SUM('費用収益表_業務長期'!S5,'費用収益表_業務短期'!S5) -> 0 | T5: =S5-P5 -> 0 | V5: =SUMIF($C$2:$N$2,"<="&締月,C5:N5) -> 0 | W5: =S5-V5 -> 0
B6: 諸手当 | C6: =SUM('費用収益表_業務長期'!C6,'費用収益表_業務短期'!C6) -> 0 | D6: =SUM('費用収益表_業務長期'!D6,'費用収益表_業務短期'!D6) -> 0 | E6: =SUM('費用収益表_業務長期'!E6,'費用収益表_業務短期'!E6) -> 0 | F6: =SUM('費用収益表_業務長期'!F6,'費用収益表_業務短期'!F6) -> 0 | G6: =SUM('費用収益表_業務長期'!G6,'費用収益表_業務短期'!G6) -> 0 | H6: =SUM('費用収益表_業務長期'!H6,'費用収益表_業務短期'!H6) -> 0 | I6: =SUM('費用収益表_業務長期'!I6,'費用収益表_業務短期'!I6) -> 0 | J6: =SUM('費用収益表_業務長期'!J6,'費用収益表_業務短期'!J6) -> 0 | ... O6: =SUM('費用収益表_業務長期'!O6,'費用収益表_業務短期'!O6) -> 0 | P6: =SUM(C6:O6) -> 0 | Q6: =SUM('費用収益表_業務長期'!Q6,'費用収益表_業務短期'!Q6) -> 0 | R6: =SUM('費用収益表_業務長期'!R6,'費用収益表_業務短期'!R6) -> 0 | S6: =SUM('費用収益表_業務長期'!S6,'費用収益表_業務短期'!S6) -> 0 | T6: =S6-P6 -> 0 | V6: =SUMIF($C$2:$N$2,"<="&締月,C6:N6) -> 0 | W6: =S6-V6 -> 0
B7: 非常勤職員手当 | C7: =SUM('費用収益表_業務長期'!C7,'費用収益表_業務短期'!C7) -> 698140 | D7: =SUM('費用収益表_業務長期'!D7,'費用収益表_業務短期'!D7) -> 629236 | E7: =SUM('費用収益表_業務長期'!E7,'費用収益表_業務短期'!E7) -> 1946789 | F7: =SUM('費用収益表_業務長期'!F7,'費用収益表_業務短期'!F7) -> 637508 | G7: =SUM('費用収益表_業務長期'!G7,'費用収益表_業務短期'!G7) -> 625100 | H7: =SUM('費用収益表_業務長期'!H7,'費用収益表_業務短期'!H7) -> 639576 | I7: =SUM('費用収益表_業務長期'!I7,'費用収益表_業務短期'!I7) -> 764882 | J7: =SUM('費用収益表_業務長期'!J7,'費用収益表_業務短期'!J7) -> 609611 | ... O7: =SUM('費用収益表_業務長期'!O7,'費用収益表_業務短期'!O7) -> 42640 | P7: =SUM(C7:O7) -> 10457044 | Q7: =SUM('費用収益表_業務長期'!Q7,'費用収益表_業務短期'!Q7) -> 11834000 | R7: =SUM('費用収益表_業務長期'!R7,'費用収益表_業務短期'!R7) -> 0 | S7: =SUM('費用収益表_業務長期'!S7,'費用収益表_業務短期'!S7) -> 11834000 | T7: =S7-P7 -> 1376956 | V7: =SUMIF($C$2:$N$2,"<="&締月,C7:N7) -> 5176349 | W7: =S7-V7 -> 6657651
B8: 退職給与金 | C8: =SUM('費用収益表_業務長期'!C8,'費用収益表_業務短期'!C8) -> 0 | D8: =SUM('費用収益表_業務長期'!D8,'費用収益表_業務短期'!D8) -> 0 | E8: =SUM('費用収益表_業務長期'!E8,'費用収益表_業務短期'!E8) -> 0 | F8: =SUM('費用収益表_業務長期'!F8,'費用収益表_業務短期'!F8) -> 0 | G8: =SUM('費用収益表_業務長期'!G8,'費用収益表_業務短期'!G8) -> 0 | H8: =SUM('費用収益表_業務長期'!H8,'費用収益表_業務短期'!H8) -> 0 | I8: =SUM('費用収益表_業務長期'!I8,'費用収益表_業務短期'!I8) -> 0 | J8: =SUM('費用収益表_業務長期'!J8,'費用収益表_業務短期'!J8) -> 0 | ... O8: =SUM('費用収益表_業務長期'!O8,'費用収益表_業務短期'!O8) -> 0 | P8: =SUM(C8:O8) -> 0 | Q8: =SUM('費用収益表_業務長期'!Q8,'費用収益表_業務短期'!Q8) -> 0 | R8: =SUM('費用収益表_業務長期'!R8,'費用収益表_業務短期'!R8) -> 0 | S8: =SUM('費用収益表_業務長期'!S8,'費用収益表_業務短期'!S8) -> 0 | T8: =S8-P8 -> 0 | V8: =SUMIF($C$2:$N$2,"<="&締月,C8:N8) -> 0 | W8: =S8-V8 -> 0
B9: 計 | C9: =SUM(C5:C8) -> 698140 | D9: =SUM(D5:D8) -> 629236 | E9: =SUM(E5:E8) -> 1946789 | F9: =SUM(F5:F8) -> 637508 | G9: =SUM(G5:G8) -> 625100 | H9: =SUM(H5:H8) -> 639576 | I9: =SUM(I5:I8) -> 764882 | J9: =SUM(J5:J8) -> 609611 | ... S9: =SUM(S5:S8) -> 11834000 | T9: =S9-P9 -> 1376956 | V9: =SUMIF($C$2:$N$2,"<="&締月,C9:N9) -> 5176349 | W9: =S9-V9 -> 6657651
A10: 厚生費 | C10: =SUM('費用収益表_業務長期'!C10,'費用収益表_業務短期'!C10) -> 0 | D10: =SUM('費用収益表_業務長期'!D10,'費用収益表_業務短期'!D10) -> 0 | E10: =SUM('費用収益表_業務長期'!E10,'費用収益表_業務短期'!E10) -> 0 | F10: =SUM('費用収益表_業務長期'!F10,'費用収益表_業務短期'!F10) -> 0 | G10: =SUM('費用収益表_業務長期'!G10,'費用収益表_業務短期'!G10) -> 1980 | H10: =SUM('費用収益表_業務長期'!H10,'費用収益表_業務短期'!H10) -> 16874 | I10: =SUM('費用収益表_業務長期'!I10,'費用収益表_業務短期'!I10) -> 0 | J10: =SUM('費用収益表_業務長期'!J10,'費用収益表_業務短期'!J10) -> 0 | ... O10: =SUM('費用収益表_業務長期'!O10,'費用収益表_業務短期'!O10) -> 0 | P10: =SUM(C10:O10) -> 18854 | Q10: =SUM('費用収益表_業務長期'!Q10,'費用収益表_業務短期'!Q10) -> 87000 | R10: =SUM('費用収益表_業務長期'!R10,'費用収益表_業務短期'!R10) -> 0 | S10: =SUM('費用収益表_業務長期'!S10,'費用収益表_業務短期'!S10) -> 87000 | T10: =S10-P10 -> 68146 | V10: =SUMIF($C$2:$N$2,"<="&締月,C10:N10) -> 18854 | W10: =S10-V10 -> 68146
A11: 旅費 | C11: =SUM('費用収益表_業務長期'!C11,'費用収益表_業務短期'!C11) -> 0 | D11: =SUM('費用収益表_業務長期'!D11,'費用収益表_業務短期'!D11) -> 0 | E11: =SUM('費用収益表_業務長期'!E11,'費用収益表_業務短期'!E11) -> 82920 | F11: =SUM('費用収益表_業務長期'!F11,'費用収益表_業務短期'!F11) -> 0 | G11: =SUM('費用収益表_業務長期'!G11,'費用収益表_業務短期'!G11) -> 60780 | H11: =SUM('費用収益表_業務長期'!H11,'費用収益表_業務短期'!H11) -> 0 | I11: =SUM('費用収益表_業務長期'!I11,'費用収益表_業務短期'!I11) -> 0 | J11: =SUM('費用収益表_業務長期'!J11,'費用収益表_業務短期'!J11) -> 38940 | ... O11: =SUM('費用収益表_業務長期'!O11,'費用収益表_業務短期'!O11) -> 0 | P11: =SUM(C11:O11) -> 302882 | Q11: =SUM('費用収益表_業務長期'!Q11,'費用収益表_業務短期'!Q11) -> 697000 | R11: =SUM('費用収益表_業務長期'!R11,'費用収益表_業務短期'!R11) -> 0 | S11: =SUM('費用収益表_業務長期'!S11,'費用収益表_業務短期'!S11) -> 697000 | T11: =S11-P11 -> 394118 | V11: =SUMIF($C$2:$N$2,"<="&締月,C11:N11) -> 143700 | W11: =S11-V11 -> 553300
A12: 事務費 | B12: 事務用消耗品費 | C12: =SUM('費用収益表_業務長期'!C12,'費用収益表_業務短期'!C12) -> 29260 | D12: =SUM('費用収益表_業務長期'!D12,'費用収益表_業務短期'!D12) -> 72448 | E12: =SUM('費用収益表_業務長期'!E12,'費用収益表_業務短期'!E12) -> 91498 | F12: =SUM('費用収益表_業務長期'!F12,'費用収益表_業務短期'!F12) -> 0 | G12: =SUM('費用収益表_業務長期'!G12,'費用収益表_業務短期'!G12) -> 131903 | H12: =SUM('費用収益表_業務長期'!H12,'費用収益表_業務短期'!H12) -> 45203 | I12: =SUM('費用収益表_業務長期'!I12,'費用収益表_業務短期'!I12) -> 147320 | J12: =SUM('費用収益表_業務長期'!J12,'費用収益表_業務短期'!J12) -> 417870 | ... O12: =SUM('費用収益表_業務長期'!O12,'費用収益表_業務短期'!O12) -> 199581 | P12: =SUM(C12:O12) -> 1571168 | Q12: =SUM('費用収益表_業務長期'!Q12,'費用収益表_業務短期'!Q12) -> 2117000 | R12: =SUM('費用収益表_業務長期'!R12,'費用収益表_業務短期'!R12) -> 0 | S12: =SUM('費用収益表_業務長期'!S12,'費用収益表_業務短期'!S12) -> 2117000 | T12: =S12-P12 -> 545832 | V12: =SUMIF($C$2:$N$2,"<="&締月,C12:N12) -> 370312 | W12: =S12-V12 -> 1746688
B13: 図書印刷費 | C13: =SUM('費用収益表_業務長期'!C13,'費用収益表_業務短期'!C13) -> 99220 | D13: =SUM('費用収益表_業務長期'!D13,'費用収益表_業務短期'!D13) -> 33154 | E13: =SUM('費用収益表_業務長期'!E13,'費用収益表_業務短期'!E13) -> 50754 | F13: =SUM('費用収益表_業務長期'!F13,'費用収益表_業務短期'!F13) -> 33154 | G13: =SUM('費用収益表_業務長期'!G13,'費用収益表_業務短期'!G13) -> 271964 | H13: =SUM('費用収益表_業務長期'!H13,'費用収益表_業務短期'!H13) -> 434830 | I13: =SUM('費用収益表_業務長期'!I13,'費用収益表_業務短期'!I13) -> 48619 | J13: =SUM('費用収益表_業務長期'!J13,'費用収益表_業務短期'!J13) -> 260854 | ... O13: =SUM('費用収益表_業務長期'!O13,'費用収益表_業務短期'!O13) -> 116600 | P13: =SUM(C13:O13) -> 1992365 | Q13: =SUM('費用収益表_業務長期'!Q13,'費用収益表_業務短期'!Q13) -> 1934000 | R13: =SUM('費用収益表_業務長期'!R13,'費用収益表_業務短期'!R13) -> 0 | S13: =SUM('費用収益表_業務長期'!S13,'費用収益表_業務短期'!S13) -> 1934000 | T13: =S13-P13 -> -58365 | V13: =SUMIF($C$2:$N$2,"<="&締月,C13:N13) -> 923076 | W13: =S13-V13 -> 1010924
B14: 送金料 | C14: =SUM('費用収益表_業務長期'!C14,'費用収益表_業務短期'!C14) -> 0 | D14: =SUM('費用収益表_業務長期'!D14,'費用収益表_業務短期'!D14) -> 267395 | E14: =SUM('費用収益表_業務長期'!E14,'費用収益表_業務短期'!E14) -> 164037 | F14: =SUM('費用収益表_業務長期'!F14,'費用収益表_業務短期'!F14) -> 157952 | G14: =SUM('費用収益表_業務長期'!G14,'費用収益表_業務短期'!G14) -> 171747 | H14: =SUM('費用収益表_業務長期'!H14,'費用収益表_業務短期'!H14) -> 177532 | I14: =SUM('費用収益表_業務長期'!I14,'費用収益表_業務短期'!I14) -> 186538 | J14: =SUM('費用収益表_業務長期'!J14,'費用収益表_業務短期'!J14) -> 174104 | ... O14: =SUM('費用収益表_業務長期'!O14,'費用収益表_業務短期'!O14) -> 165455 | P14: =SUM(C14:O14) -> 2135096 | Q14: =SUM('費用収益表_業務長期'!Q14,'費用収益表_業務短期'!Q14) -> 2101000 | R14: =SUM('費用収益表_業務長期'!R14,'費用収益表_業務短期'!R14) -> 0 | S14: =SUM('費用収益表_業務長期'!S14,'費用収益表_業務短期'!S14) -> 2101000 | T14: =S14-P14 -> -34096 | V14: =SUMIF($C$2:$N$2,"<="&締月,C14:N14) -> 938663 | W14: =S14-V14 -> 1162337
B15: 通信運搬費 | C15: =SUM('費用収益表_業務長期'!C15,'費用収益表_業務短期'!C15) -> 0 | D15: =SUM('費用収益表_業務長期'!D15,'費用収益表_業務短期'!D15) -> 343276 | E15: =SUM('費用収益表_業務長期'!E15,'費用収益表_業務短期'!E15) -> 70603 | F15: =SUM('費用収益表_業務長期'!F15,'費用収益表_業務短期'!F15) -> 1560523 | G15: =SUM('費用収益表_業務長期'!G15,'費用収益表_業務短期'!G15) -> 102819 | H15: =SUM('費用収益表_業務長期'!H15,'費用収益表_業務短期'!H15) -> 109815 | I15: =SUM('費用収益表_業務長期'!I15,'費用収益表_業務短期'!I15) -> 393650 | J15: =SUM('費用収益表_業務長期'!J15,'費用収益表_業務短期'!J15) -> 1143632 | ... O15: =SUM('費用収益表_業務長期'!O15,'費用収益表_業務短期'!O15) -> 132832 | P15: =SUM(C15:O15) -> 7276759 | Q15: =SUM('費用収益表_業務長期'!Q15,'費用収益表_業務短期'!Q15) -> 8501000 | R15: =SUM('費用収益表_業務長期'!R15,'費用収益表_業務短期'!R15) -> 0 | S15: =SUM('費用収益表_業務長期'!S15,'費用収益表_業務短期'!S15) -> 8501000 | T15: =S15-P15 -> 1224241 | V15: =SUMIF($C$2:$N$2,"<="&締月,C15:N15) -> 2187036 | W15: =S15-V15 -> 6313964
B16: 会議費 | C16: =SUM('費用収益表_業務長期'!C16,'費用収益表_業務短期'!C16) -> 0 | D16: =SUM('費用収益表_業務長期'!D16,'費用収益表_業務短期'!D16) -> 0 | E16: =SUM('費用収益表_業務長期'!E16,'費用収益表_業務短期'!E16) -> 0 | F16: =SUM('費用収益表_業務長期'!F16,'費用収益表_業務短期'!F16) -> 0 | G16: =SUM('費用収益表_業務長期'!G16,'費用収益表_業務短期'!G16) -> 0 | H16: =SUM('費用収益表_業務長期'!H16,'費用収益表_業務短期'!H16) -> 0 | I16: =SUM('費用収益表_業務長期'!I16,'費用収益表_業務短期'!I16) -> 0 | J16: =SUM('費用収益表_業務長期'!J16,'費用収益表_業務短期'!J16) -> 0 | ... O16: =SUM('費用収益表_業務長期'!O16,'費用収益表_業務短期'!O16) -> 0 | P16: =SUM(C16:O16) -> 0 | Q16: =SUM('費用収益表_業務長期'!Q16,'費用収益表_業務短期'!Q16) -> 0 | R16: =SUM('費用収益表_業務長期'!R16,'費用収益表_業務短期'!R16) -> 0 | S16: =SUM('費用収益表_業務長期'!S16,'費用収益表_業務短期'!S16) -> 0 | T16: =S16-P16 -> 0 | V16: =SUMIF($C$2:$N$2,"<="&締月,C16:N16) -> 0 | W16: =S16-V16 -> 0
B17: 雑費 | C17: =SUM('費用収益表_業務長期'!C17,'費用収益表_業務短期'!C17) -> 0 | D17: =SUM('費用収益表_業務長期'!D17,'費用収益表_業務短期'!D17) -> 550 | E17: =SUM('費用収益表_業務長期'!E17,'費用収益表_業務短期'!E17) -> 550 | F17: =SUM('費用収益表_業務長期'!F17,'費用収益表_業務短期'!F17) -> 550 | G17: =SUM('費用収益表_業務長期'!G17,'費用収益表_業務短期'!G17) -> 550 | H17: =SUM('費用収益表_業務長期'!H17,'費用収益表_業務短期'!H17) -> 550 | I17: =SUM('費用収益表_業務長期'!I17,'費用収益表_業務短期'!I17) -> 3850 | J17: =SUM('費用収益表_業務長期'!J17,'費用収益表_業務短期'!J17) -> 550 | ... O17: =SUM('費用収益表_業務長期'!O17,'費用収益表_業務短期'!O17) -> 3850 | P17: =SUM(C17:O17) -> 13200 | Q17: =SUM('費用収益表_業務長期'!Q17,'費用収益表_業務短期'!Q17) -> 7000 | R17: =SUM('費用収益表_業務長期'!R17,'費用収益表_業務短期'!R17) -> 0 | S17: =SUM('費用収益表_業務長期'!S17,'費用収益表_業務短期'!S17) -> 7000 | T17: =S17-P17 -> -6200 | V17: =SUMIF($C$2:$N$2,"<="&締月,C17:N17) -> 2750 | W17: =S17-V17 -> 4250
B18: 計 | C18: =SUM(C12:C17) -> 128480 | D18: =SUM(D12:D17) -> 716823 | E18: =SUM(E12:E17) -> 377442 | F18: =SUM(F12:F17) -> 1752179 | G18: =SUM(G12:G17) -> 678983 | H18: =SUM(H12:H17) -> 767930 | I18: =SUM(I12:I17) -> 779977 | J18: =SUM(J12:J17) -> 1997010 | ... S18: =SUM(S12:S17) -> 14660000 | T18: =S18-P18 -> 1671412 | V18: =SUMIF($C$2:$N$2,"<="&締月,C18:N18) -> 4421837 | W18: =S18-V18 -> 10238163
A19: 賃金 | C19: =SUM('費用収益表_業務長期'!C19,'費用収益表_業務短期'!C19) -> 0 | D19: =SUM('費用収益表_業務長期'!D19,'費用収益表_業務短期'!D19) -> 425880 | E19: =SUM('費用収益表_業務長期'!E19,'費用収益表_業務短期'!E19) -> 365040 | F19: =SUM('費用収益表_業務長期'!F19,'費用収益表_業務短期'!F19) -> 446160 | G19: =SUM('費用収益表_業務長期'!G19,'費用収益表_業務短期'!G19) -> 445720 | H19: =SUM('費用収益表_業務長期'!H19,'費用収益表_業務短期'!H19) -> 384480 | I19: =SUM('費用収益表_業務長期'!I19,'費用収益表_業務短期'!I19) -> 389160 | J19: =SUM('費用収益表_業務長期'!J19,'費用収益表_業務短期'!J19) -> 416580 | ... O19: =SUM('費用収益表_業務長期'!O19,'費用収益表_業務短期'!O19) -> 339568 | P19: =SUM(C19:O19) -> 4629488 | Q19: =SUM('費用収益表_業務長期'!Q19,'費用収益表_業務短期'!Q19) -> 5520000 | R19: =SUM('費用収益表_業務長期'!R19,'費用収益表_業務短期'!R19) -> 0 | S19: =SUM('費用収益表_業務長期'!S19,'費用収益表_業務短期'!S19) -> 5520000 | T19: =S19-P19 -> 890512 | V19: =SUMIF($C$2:$N$2,"<="&締月,C19:N19) -> 2067280 | W19: =S19-V19 -> 3452720
A20: 委託費 | C20: =SUM('費用収益表_業務長期'!C20,'費用収益表_業務短期'!C20) -> 60235 | D20: =SUM('費用収益表_業務長期'!D20,'費用収益表_業務短期'!D20) -> 2146895 | E20: =SUM('費用収益表_業務長期'!E20,'費用収益表_業務短期'!E20) -> 188645 | F20: =SUM('費用収益表_業務長期'!F20,'費用収益表_業務短期'!F20) -> 343021 | G20: =SUM('費用収益表_業務長期'!G20,'費用収益表_業務短期'!G20) -> 1382282 | H20: =SUM('費用収益表_業務長期'!H20,'費用収益表_業務短期'!H20) -> 2099782 | I20: =SUM('費用収益表_業務長期'!I20,'費用収益表_業務短期'!I20) -> 682958 | J20: =SUM('費用収益表_業務長期'!J20,'費用収益表_業務短期'!J20) -> 283902 | ... O20: =SUM('費用収益表_業務長期'!O20,'費用収益表_業務短期'!O20) -> 1396243 | P20: =SUM(C20:O20) -> 12087397 | Q20: =SUM('費用収益表_業務長期'!Q20,'費用収益表_業務短期'!Q20) -> 13053000 | R20: =SUM('費用収益表_業務長期'!R20,'費用収益表_業務短期'!R20) -> 0 | S20: =SUM('費用収益表_業務長期'!S20,'費用収益表_業務短期'!S20) -> 13053000 | T20: =S20-P20 -> 965603 | V20: =SUMIF($C$2:$N$2,"<="&締月,C20:N20) -> 6220860 | W20: =S20-V20 -> 6832140
A21: 光熱水料 | C21: ='費用収益表_業務長期'!C21+'費用収益表_業務短期'!C21 -> 0 | D21: ='費用収益表_業務長期'!D21+'費用収益表_業務短期'!D21 -> 0 | E21: ='費用収益表_業務長期'!E21+'費用収益表_業務短期'!E21 -> 0 | F21: ='費用収益表_業務長期'!F21+'費用収益表_業務短期'!F21 -> 0 | G21: ='費用収益表_業務長期'!G21+'費用収益表_業務短期'!G21 -> 0 | H21: ='費用収益表_業務長期'!H21+'費用収益表_業務短期'!H21 -> 0 | I21: ='費用収益表_業務長期'!I21+'費用収益表_業務短期'!I21 -> 0 | J21: ='費用収益表_業務長期'!J21+'費用収益表_業務短期'!J21 -> 0 | ... O21: ='費用収益表_業務長期'!O21+'費用収益表_業務短期'!O21 -> 70268 | P21: =SUM(C21:O21) -> 127652 | Q21: =SUM('費用収益表_業務長期'!Q21,'費用収益表_業務短期'!Q21) -> 118000 | R21: =SUM('費用収益表_業務長期'!R21,'費用収益表_業務短期'!R21) -> 0 | S21: =SUM('費用収益表_業務長期'!S21,'費用収益表_業務短期'!S21) -> 118000 | T21: =S21-P21 -> -9652 | V21: =SUMIF($C$2:$N$2,"<="&締月,C21:N21) -> 0 | W21: =S21-V21 -> 118000
A22: 修繕費 | C22: ='費用収益表_業務長期'!C22+'費用収益表_業務短期'!C22 -> 0 | D22: ='費用収益表_業務長期'!D22+'費用収益表_業務短期'!D22 -> 0 | E22: ='費用収益表_業務長期'!E22+'費用収益表_業務短期'!E22 -> 0 | F22: ='費用収益表_業務長期'!F22+'費用収益表_業務短期'!F22 -> 0 | G22: ='費用収益表_業務長期'!G22+'費用収益表_業務短期'!G22 -> 0 | H22: ='費用収益表_業務長期'!H22+'費用収益表_業務短期'!H22 -> 0 | I22: ='費用収益表_業務長期'!I22+'費用収益表_業務短期'!I22 -> 0 | J22: ='費用収益表_業務長期'!J22+'費用収益表_業務短期'!J22 -> 0 | ... O22: ='費用収益表_業務長期'!O22+'費用収益表_業務短期'!O22 -> 0 | P22: =SUM(C22:O22) -> 0 | Q22: =SUM('費用収益表_業務長期'!Q22,'費用収益表_業務短期'!Q22) -> 0 | R22: =SUM('費用収益表_業務長期'!R22,'費用収益表_業務短期'!R22) -> 0 | S22: =SUM('費用収益表_業務長期'!S22,'費用収益表_業務短期'!S22) -> 0 | T22: =S22-P22 -> 0 | V22: =SUMIF($C$2:$N$2,"<="&締月,C22:N22) -> 0 | W22: =S22-V22 -> 0
A23: 賃借料 | C23: =SUM('費用収益表_業務長期'!C23,'費用収益表_業務短期'!C23) -> 0 | D23: =SUM('費用収益表_業務長期'!D23,'費用収益表_業務短期'!D23) -> 760345 | E23: =SUM('費用収益表_業務長期'!E23,'費用収益表_業務短期'!E23) -> 760345 | F23: =SUM('費用収益表_業務長期'!F23,'費用収益表_業務短期'!F23) -> 760345 | G23: =SUM('費用収益表_業務長期'!G23,'費用収益表_業務短期'!G23) -> 760345 | H23: =SUM('費用収益表_業務長期'!H23,'費用収益表_業務短期'!H23) -> 760345 | I23: =SUM('費用収益表_業務長期'!I23,'費用収益表_業務短期'!I23) -> 760345 | J23: =SUM('費用収益表_業務長期'!J23,'費用収益表_業務短期'!J23) -> 807227 | ... O23: =SUM('費用収益表_業務長期'!O23,'費用収益表_業務短期'!O23) -> 564503 | P23: =SUM(C23:O23) -> 8975180 | Q23: =SUM('費用収益表_業務長期'!Q23,'費用収益表_業務短期'!Q23) -> 9468000 | R23: =SUM('費用収益表_業務長期'!R23,'費用収益表_業務短期'!R23) -> 0 | S23: =SUM('費用収益表_業務長期'!S23,'費用収益表_業務短期'!S23) -> 9468000 | T23: =S23-P23 -> 492820 | V23: =SUMIF($C$2:$N$2,"<="&締月,C23:N23) -> 3801725 | W23: =S23-V23 -> 5666275
A24: 普及費 | C24: =SUM('費用収益表_業務長期'!C24,'費用収益表_業務短期'!C24) -> 0 | D24: =SUM('費用収益表_業務長期'!D24,'費用収益表_業務短期'!D24) -> 0 | E24: =SUM('費用収益表_業務長期'!E24,'費用収益表_業務短期'!E24) -> 0 | F24: =SUM('費用収益表_業務長期'!F24,'費用収益表_業務短期'!F24) -> 0 | G24: =SUM('費用収益表_業務長期'!G24,'費用収益表_業務短期'!G24) -> 371265 | H24: =SUM('費用収益表_業務長期'!H24,'費用収益表_業務短期'!H24) -> 0 | I24: =SUM('費用収益表_業務長期'!I24,'費用収益表_業務短期'!I24) -> 0 | J24: =SUM('費用収益表_業務長期'!J24,'費用収益表_業務短期'!J24) -> 429656 | ... O24: =SUM('費用収益表_業務長期'!O24,'費用収益表_業務短期'!O24) -> 692131 | P24: =SUM(C24:O24) -> 1919663 | Q24: =SUM('費用収益表_業務長期'!Q24,'費用収益表_業務短期'!Q24) -> 2525000 | R24: =SUM('費用収益表_業務長期'!R24,'費用収益表_業務短期'!R24) -> 0 | S24: =SUM('費用収益表_業務長期'!S24,'費用収益表_業務短期'!S24) -> 2525000 | T24: =S24-P24 -> 605337 | V24: =SUMIF($C$2:$N$2,"<="&締月,C24:N24) -> 371265 | W24: =S24-V24 -> 2153735
A25: 諸謝金 | C25: =SUM('費用収益表_業務長期'!C25,'費用収益表_業務短期'!C25) -> 0 | D25: =SUM('費用収益表_業務長期'!D25,'費用収益表_業務短期'!D25) -> 0 | E25: =SUM('費用収益表_業務長期'!E25,'費用収益表_業務短期'!E25) -> 0 | F25: =SUM('費用収益表_業務長期'!F25,'費用収益表_業務短期'!F25) -> 0 | G25: =SUM('費用収益表_業務長期'!G25,'費用収益表_業務短期'!G25) -> 0 | H25: =SUM('費用収益表_業務長期'!H25,'費用収益表_業務短期'!H25) -> 0 | I25: =SUM('費用収益表_業務長期'!I25,'費用収益表_業務短期'!I25) -> 0 | J25: =SUM('費用収益表_業務長期'!J25,'費用収益表_業務短期'!J25) -> 0 | ... O25: =SUM('費用収益表_業務長期'!O25,'費用収益表_業務短期'!O25) -> 0 | P25: =SUM(C25:O25) -> 0 | Q25: =SUM('費用収益表_業務長期'!Q25,'費用収益表_業務短期'!Q25) -> 0 | R25: =SUM('費用収益表_業務長期'!R25,'費用収益表_業務短期'!R25) -> 0 | S25: =SUM('費用収益表_業務長期'!S25,'費用収益表_業務短期'!S25) -> 0 | T25: =S25-P25 -> 0 | V25: =SUMIF($C$2:$N$2,"<="&締月,C25:N25) -> 0 | W25: =S25-V25 -> 0
A26: 負担金 | B26: 会議出席負担金等 | C26: =SUM('費用収益表_業務長期'!C26,'費用収益表_業務短期'!C26) -> 0 | D26: =SUM('費用収益表_業務長期'!D26,'費用収益表_業務短期'!D26) -> 0 | E26: =SUM('費用収益表_業務長期'!E26,'費用収益表_業務短期'!E26) -> 0 | F26: =SUM('費用収益表_業務長期'!F26,'費用収益表_業務短期'!F26) -> 0 | G26: =SUM('費用収益表_業務長期'!G26,'費用収益表_業務短期'!G26) -> 0 | H26: =SUM('費用収益表_業務長期'!H26,'費用収益表_業務短期'!H26) -> 0 | I26: =SUM('費用収益表_業務長期'!I26,'費用収益表_業務短期'!I26) -> 0 | J26: =SUM('費用収益表_業務長期'!J26,'費用収益表_業務短期'!J26) -> 0 | ... O26: =SUM('費用収益表_業務長期'!O26,'費用収益表_業務短期'!O26) -> 0 | P26: =SUM(C26:O26) -> 0 | Q26: =SUM('費用収益表_業務長期'!Q26,'費用収益表_業務短期'!Q26) -> 0 | R26: =SUM('費用収益表_業務長期'!R26,'費用収益表_業務短期'!R26) -> 0 | S26: =SUM('費用収益表_業務長期'!S26,'費用収益表_業務短期'!S26) -> 0 | T26: =S26-P26 -> 0 | V26: =SUMIF($C$2:$N$2,"<="&締月,C26:N26) -> 0 | W26: =S26-V26 -> 0
B27: 互助会費 | C27: =SUM('費用収益表_業務長期'!C27,'費用収益表_業務短期'!C27) -> 706 | D27: =SUM('費用収益表_業務長期'!D27,'費用収益表_業務短期'!D27) -> 706 | E27: =SUM('費用収益表_業務長期'!E27,'費用収益表_業務短期'!E27) -> 706 | F27: =SUM('費用収益表_業務長期'!F27,'費用収益表_業務短期'!F27) -> 706 | G27: =SUM('費用収益表_業務長期'!G27,'費用収益表_業務短期'!G27) -> 706 | H27: =SUM('費用収益表_業務長期'!H27,'費用収益表_業務短期'!H27) -> 706 | I27: =SUM('費用収益表_業務長期'!I27,'費用収益表_業務短期'!I27) -> 811 | J27: =SUM('費用収益表_業務長期'!J27,'費用収益表_業務短期'!J27) -> 811 | ... O27: =SUM('費用収益表_業務長期'!O27,'費用収益表_業務短期'!O27) -> 0 | P27: =SUM(C27:O27) -> 9426 | Q27: =SUM('費用収益表_業務長期'!Q27:Q31,'費用収益表_業務短期'!Q27:Q31) -> 2820000 | R27: =SUM('費用収益表_業務長期'!R27:R31,'費用収益表_業務短期'!R27:R31) -> 0 | S27: =SUM('費用収益表_業務長期'!S27:S31,'費用収益表_業務短期'!S27:S31) -> 2820000 | T27: =S27-SUM(P27:P31) -> 350407 | V27: =SUMIF($C$2:$N$2,"<="&締月,C27:N27) -> 4236
B28: 協会けんぽ保険料等 | C28: =SUM('費用収益表_業務長期'!C28,'費用収益表_業務短期'!C28) -> 0 | D28: =SUM('費用収益表_業務長期'!D28,'費用収益表_業務短期'!D28) -> 0 | E28: =SUM('費用収益表_業務長期'!E28,'費用収益表_業務短期'!E28) -> 0 | F28: =SUM('費用収益表_業務長期'!F28,'費用収益表_業務短期'!F28) -> 0 | G28: =SUM('費用収益表_業務長期'!G28,'費用収益表_業務短期'!G28) -> 0 | H28: =SUM('費用収益表_業務長期'!H28,'費用収益表_業務短期'!H28) -> 0 | I28: =SUM('費用収益表_業務長期'!I28,'費用収益表_業務短期'!I28) -> 0 | J28: =SUM('費用収益表_業務長期'!J28,'費用収益表_業務短期'!J28) -> 0 | ... O28: =SUM('費用収益表_業務長期'!O28,'費用収益表_業務短期'!O28) -> 0 | P28: =SUM(C28:O28) -> 0 | V28: =SUMIF($C$2:$N$2,"<="&締月,C28:N28) -> 0
B29: 共済負担金等 | C29: =SUM('費用収益表_業務長期'!C29,'費用収益表_業務短期'!C29) -> 59109 | D29: =SUM('費用収益表_業務長期'!D29,'費用収益表_業務短期'!D29) -> 59109 | E29: =SUM('費用収益表_業務長期'!E29,'費用収益表_業務短期'!E29) -> 135488 | F29: =SUM('費用収益表_業務長期'!F29,'費用収益表_業務短期'!F29) -> 59109 | G29: =SUM('費用収益表_業務長期'!G29,'費用収益表_業務短期'!G29) -> 59109 | H29: =SUM('費用収益表_業務長期'!H29,'費用収益表_業務短期'!H29) -> 58737 | I29: =SUM('費用収益表_業務長期'!I29,'費用収益表_業務短期'!I29) -> 62532 | J29: =SUM('費用収益表_業務長期'!J29,'費用収益表_業務短期'!J29) -> 62532 | ... O29: =SUM('費用収益表_業務長期'!O29,'費用収益表_業務短期'!O29) -> 0 | P29: =SUM(C29:O29) -> 878265 | V29: =SUMIF($C$2:$N$2,"<="&締月,C29:N29) -> 430661
B30: 厚年負担金等 | C30: =SUM('費用収益表_業務長期'!C30,'費用収益表_業務短期'!C30) -> 0 | D30: =SUM('費用収益表_業務長期'!D30,'費用収益表_業務短期'!D30) -> 0 | E30: =SUM('費用収益表_業務長期'!E30,'費用収益表_業務短期'!E30) -> 199710 | F30: =SUM('費用収益表_業務長期'!F30,'費用収益表_業務短期'!F30) -> 99855 | G30: =SUM('費用収益表_業務長期'!G30,'費用収益表_業務短期'!G30) -> 224817 | H30: =SUM('費用収益表_業務長期'!H30,'費用収益表_業務短期'!H30) -> 99855 | I30: =SUM('費用収益表_業務長期'!I30,'費用収益表_業務短期'!I30) -> 98904 | J30: =SUM('費用収益表_業務長期'!J30,'費用収益表_業務短期'!J30) -> 0 | ... O30: =SUM('費用収益表_業務長期'!O30,'費用収益表_業務短期'!O30) -> 87872 | P30: =SUM(C30:O30) -> 1402535 | V30: =SUMIF($C$2:$N$2,"<="&締月,C30:N30) -> 624237
B31: 労災保険料 | C31: =SUM('費用収益表_業務長期'!C31,'費用収益表_業務短期'!C31) -> 0 | D31: =SUM('費用収益表_業務長期'!D31,'費用収益表_業務短期'!D31) -> 0 | E31: =SUM('費用収益表_業務長期'!E31,'費用収益表_業務短期'!E31) -> 0 | F31: =SUM('費用収益表_業務長期'!F31,'費用収益表_業務短期'!F31) -> 179367 | G31: =SUM('費用収益表_業務長期'!G31,'費用収益表_業務短期'!G31) -> 0 | H31: =SUM('費用収益表_業務長期'!H31,'費用収益表_業務短期'!H31) -> 0 | I31: =SUM('費用収益表_業務長期'!I31,'費用収益表_業務短期'!I31) -> 0 | J31: =SUM('費用収益表_業務長期'!J31,'費用収益表_業務短期'!J31) -> 0 | ... O31: =SUM('費用収益表_業務長期'!O31,'費用収益表_業務短期'!O31) -> 0 | P31: =SUM(C31:O31) -> 179367 | V31: =SUMIF($C$2:$N$2,"<="&締月,C31:N31) -> 179367
B32: 協議会会費 | C32: =SUM('費用収益表_業務長期'!C32,'費用収益表_業務短期'!C32) -> 0 | D32: =SUM('費用収益表_業務長期'!D32,'費用収益表_業務短期'!D32) -> 1300 | E32: =SUM('費用収益表_業務長期'!E32,'費用収益表_業務短期'!E32) -> 0 | F32: =SUM('費用収益表_業務長期'!F32,'費用収益表_業務短期'!F32) -> 0 | G32: =SUM('費用収益表_業務長期'!G32,'費用収益表_業務短期'!G32) -> 0 | H32: =SUM('費用収益表_業務長期'!H32,'費用収益表_業務短期'!H32) -> 0 | I32: =SUM('費用収益表_業務長期'!I32,'費用収益表_業務短期'!I32) -> 0 | J32: =SUM('費用収益表_業務長期'!J32,'費用収益表_業務短期'!J32) -> 0 | ... O32: =SUM('費用収益表_業務長期'!O32,'費用収益表_業務短期'!O32) -> 0 | P32: =SUM(C32:O32) -> 1300 | Q32: =SUM('費用収益表_業務長期'!Q32,'費用収益表_業務短期'!Q32) -> 2000 | R32: =SUM('費用収益表_業務長期'!R32,'費用収益表_業務短期'!R32) -> 0 | S32: =SUM('費用収益表_業務長期'!S32,'費用収益表_業務短期'!S32) -> 2000 | T32: =S32-P32 -> 700 | V32: =SUMIF($C$2:$N$2,"<="&締月,C32:N32) -> 1300 | W32: =S32-V32 -> 700
B33: 計 | C33: =SUM(C26:C32) -> 59815 | D33: =SUM(D26:D32) -> 61115 | E33: =SUM(E26:E32) -> 335904 | F33: =SUM(F26:F32) -> 339037 | G33: =SUM(G26:G32) -> 284632 | H33: =SUM(H26:H32) -> 159298 | I33: =SUM(I26:I32) -> 162247 | J33: =SUM(J26:J32) -> 63343 | ... S33: =SUM(S26:S32) -> 2822000 | T33: =S33-P33 -> 351107 | V33: =SUMIF($C$2:$N$2,"<="&締月,C33:N33) -> 1239801 | W33: =S33-V33 -> 1582199
A34: 連合会分担金 | C34: =SUM('費用収益表_業務長期'!C34,'費用収益表_業務短期'!C34) -> 0 | D34: =SUM('費用収益表_業務長期'!D34,'費用収益表_業務短期'!D34) -> 0 | E34: =SUM('費用収益表_業務長期'!E34,'費用収益表_業務短期'!E34) -> 0 | F34: =SUM('費用収益表_業務長期'!F34,'費用収益表_業務短期'!F34) -> 0 | G34: =SUM('費用収益表_業務長期'!G34,'費用収益表_業務短期'!G34) -> 0 | H34: =SUM('費用収益表_業務長期'!H34,'費用収益表_業務短期'!H34) -> 20439958 | I34: =SUM('費用収益表_業務長期'!I34,'費用収益表_業務短期'!I34) -> 0 | J34: =SUM('費用収益表_業務長期'!J34,'費用収益表_業務短期'!J34) -> 0 | ... O34: =SUM('費用収益表_業務長期'!O34,'費用収益表_業務短期'!O34) -> 0 | P34: =SUM(C34:O34) -> 20439958 | Q34: =SUM('費用収益表_業務長期'!Q34,'費用収益表_業務短期'!Q34) -> 20921000 | R34: =SUM('費用収益表_業務長期'!R34,'費用収益表_業務短期'!R34) -> 0 | S34: =SUM('費用収益表_業務長期'!S34,'費用収益表_業務短期'!S34) -> 20921000 | T34: =S34-P34 -> 481042 | V34: =SUMIF($C$2:$N$2,"<="&締月,C34:N34) -> 20439958 | W34: =S34-V34 -> 481042
A35: 事務費負担金払込金 | C35: =SUM('費用収益表_業務長期'!C35,'費用収益表_業務短期'!C35) -> 0 | D35: =SUM('費用収益表_業務長期'!D35,'費用収益表_業務短期'!D35) -> 5366000 | E35: =SUM('費用収益表_業務長期'!E35,'費用収益表_業務短期'!E35) -> 5366000 | F35: =SUM('費用収益表_業務長期'!F35,'費用収益表_業務短期'!F35) -> 5366000 | G35: =SUM('費用収益表_業務長期'!G35,'費用収益表_業務短期'!G35) -> 5366000 | H35: =SUM('費用収益表_業務長期'!H35,'費用収益表_業務短期'!H35) -> 5366000 | I35: =SUM('費用収益表_業務長期'!I35,'費用収益表_業務短期'!I35) -> 4513000 | J35: =SUM('費用収益表_業務長期'!J35,'費用収益表_業務短期'!J35) -> 4513000 | ... O35: =SUM('費用収益表_業務長期'!O35,'費用収益表_業務短期'!O35) -> 0 | P35: =SUM(C35:O35) -> 58418000 | Q35: =SUM('費用収益表_業務長期'!Q35,'費用収益表_業務短期'!Q35) -> 64386000 | R35: =SUM('費用収益表_業務長期'!R35,'費用収益表_業務短期'!R35) -> 0 | S35: =SUM('費用収益表_業務長期'!S35,'費用収益表_業務短期'!S35) -> 64386000 | T35: =S35-P35 -> 5968000 | V35: =SUMIF($C$2:$N$2,"<="&締月,C35:N35) -> 26830000 | W35: =S35-V35 -> 37556000
A36: 雑費 | C36: =SUM('費用収益表_業務長期'!C36,'費用収益表_業務短期'!C36) -> 0 | D36: =SUM('費用収益表_業務長期'!D36,'費用収益表_業務短期'!D36) -> 0 | E36: =SUM('費用収益表_業務長期'!E36,'費用収益表_業務短期'!E36) -> 0 | F36: =SUM('費用収益表_業務長期'!F36,'費用収益表_業務短期'!F36) -> 0 | G36: =SUM('費用収益表_業務長期'!G36,'費用収益表_業務短期'!G36) -> 0 | H36: =SUM('費用収益表_業務長期'!H36,'費用収益表_業務短期'!H36) -> 0 | I36: =SUM('費用収益表_業務長期'!I36,'費用収益表_業務短期'!I36) -> 0 | J36: =SUM('費用収益表_業務長期'!J36,'費用収益表_業務短期'!J36) -> 0 | ... O36: =SUM('費用収益表_業務長期'!O36,'費用収益表_業務短期'!O36) -> 0 | P36: =SUM(C36:O36) -> 0 | Q36: =SUM('費用収益表_業務長期'!Q36,'費用収益表_業務短期'!Q36) -> 0 | R36: =SUM('費用収益表_業務長期'!R36,'費用収益表_業務短期'!R36) -> 0 | S36: =SUM('費用収益表_業務長期'!S36,'費用収益表_業務短期'!S36) -> 0 | T36: =S36-P36 -> 0 | V36: =SUMIF($C$2:$N$2,"<="&締月,C36:N36) -> 0 | W36: =S36-V36 -> 0
A37: 減価償却費 | C37: =SUM('費用収益表_業務長期'!C37,'費用収益表_業務短期'!C37) -> 0 | D37: =SUM('費用収益表_業務長期'!D37,'費用収益表_業務短期'!D37) -> 0 | E37: =SUM('費用収益表_業務長期'!E37,'費用収益表_業務短期'!E37) -> 0 | F37: =SUM('費用収益表_業務長期'!F37,'費用収益表_業務短期'!F37) -> 0 | G37: =SUM('費用収益表_業務長期'!G37,'費用収益表_業務短期'!G37) -> 0 | H37: =SUM('費用収益表_業務長期'!H37,'費用収益表_業務短期'!H37) -> 0 | I37: =SUM('費用収益表_業務長期'!I37,'費用収益表_業務短期'!I37) -> 0 | J37: =SUM('費用収益表_業務長期'!J37,'費用収益表_業務短期'!J37) -> 0 | ... O37: =SUM('費用収益表_業務長期'!O37,'費用収益表_業務短期'!O37) -> 176556 | P37: =SUM(C37:O37) -> 176556 | Q37: =SUM('費用収益表_業務長期'!Q37,'費用収益表_業務短期'!Q37) -> 172000 | R37: =SUM('費用収益表_業務長期'!R37,'費用収益表_業務短期'!R37) -> 0 | S37: =SUM('費用収益表_業務長期'!S37,'費用収益表_業務短期'!S37) -> 172000 | T37: =S37-P37 -> -4556 | U37: 検算 | V37: =SUMIF($C$2:$N$2,"<="&締月,C37:N37) -> 0 | W37: =S37-V37 -> 172000
A38: 合 計 | C38: =SUM(C9+C18+C19+C20+C21+C22+C23+C24+C25+C26+C33+C34+C35+C36+C37) -> 946670 | D38: =SUM(D4+D9+D10+D11+D18+D19+D20+D21+D22+D23+D24+D25+D33+D34+D35+D36+D37) -> 10106294 | E38: =SUM(E4+E9+E10+E11+E18+E19+E20+E21+E22+E23+E24+E25+E33+E34+E35+E36+E37) -> 9445085 | F38: =SUM(F4+F9+F10+F11+F18+F19+F20+F21+F22+F23+F24+F25+F33+F34+F35+F36+F37) -> 9644250 | G38: =SUM(G4+G9+G10+G11+G18+G19+G20+G21+G22+G23+G24+G25+G33+G34+G35+G36+G37) -> 9977087 | H38: =SUM(H4+H9+H10+H11+H18+H19+H20+H21+H22+H23+H24+H25+H33+H34+H35+H36+H37) -> 30634243 | I38: =SUM(I4+I9+I10+I11+I18+I19+I20+I21+I22+I23+I24+I25+I33+I34+I35+I36+I37) -> 8052569 | J38: =SUM(J4+J9+J10+J11+J18+J19+J20+J21+J22+J23+J24+J25+J33+J34+J35+J36+J37) -> 9159269 | K38: =SUM(K4+K9+K10+K11+K18+K19+K20+K21+K22+K23+K24+K25+K33+K34+K35+K36+K37) -> 11171849 | ... S38: =SUM(S4+S9+S10+S11+S18+S19+S20+S21+S22+S23+S24+S25+S33+S34+S35+S36+S37) -> 146296000 | T38: =Q38-P38 -> 13250845 | U38: =T4+T9+T10+T11+T18+T19+T20+T21+T22+T23+T24+T25+T33+T34+T36+T37 -> 7282845 | V38: =SUMIF($C$2:$N$2,"<="&締月,C38:N38) -> 70753629 | W38: =S38-V38 -> 75542371
A39: 収益
A40: 区 分 | C40: ４月 | D40: ５月 | E40: ６月 | F40: ７月 | G40: ８月 | H40: ９月 | I40: １０月 | J40: １１月 | K40: １２月 | L40: １月 | M40: ２月 | N40: ３月 | O40: ４月（未収） | P40: 収入済計 | Q40: 予算額 | R40: 流用振替額 | S40: 予算現額
A41: 地方公共団体負担金 | C41: =SUM('費用収益表_業務長期'!C41,'費用収益表_業務短期'!C41) -> 6781000 | D41: =SUM('費用収益表_業務長期'!D41,'費用収益表_業務短期'!D41) -> 6663000 | E41: =SUM('費用収益表_業務長期'!E41,'費用収益表_業務短期'!E41) -> 7975000 | F41: =SUM('費用収益表_業務長期'!F41,'費用収益表_業務短期'!F41) -> 10548000 | G41: =SUM('費用収益表_業務長期'!G41,'費用収益表_業務短期'!G41) -> 6664000 | H41: =SUM('費用収益表_業務長期'!H41,'費用収益表_業務短期'!H41) -> 17307000 | I41: =SUM('費用収益表_業務長期'!I41,'費用収益表_業務短期'!I41) -> 6990000 | J41: =SUM('費用収益表_業務長期'!J41,'費用収益表_業務短期'!J41) -> 6741000 | ... O41: =SUM('費用収益表_業務長期'!O41,'費用収益表_業務短期'!O41) -> 2075480 | P41: =SUM(C41:O41) -> 101062480 | Q41: =SUM('費用収益表_業務長期'!S41,'費用収益表_業務短期'!S41) -> 94968000 | R41: =SUM('費用収益表_業務長期'!R41,'費用収益表_業務短期'!R41) -> -11744404 | S41: =SUM('費用収益表_業務長期'!T41,'費用収益表_業務短期'!T41) -> 31002076 | V41: =SUMIF($C$2:$N$2,"<="&締月,C41:N41) -> 55938000
A42: 雑収入 | C42: =SUM('費用収益表_業務長期'!C42,'費用収益表_業務短期'!C42) -> 0 | D42: =SUM('費用収益表_業務長期'!D42,'費用収益表_業務短期'!D42) -> 0 | E42: =SUM('費用収益表_業務長期'!E42,'費用収益表_業務短期'!E42) -> 0 | F42: =SUM('費用収益表_業務長期'!F42,'費用収益表_業務短期'!F42) -> 0 | G42: =SUM('費用収益表_業務長期'!G42,'費用収益表_業務短期'!G42) -> 0 | H42: =SUM('費用収益表_業務長期'!H42,'費用収益表_業務短期'!H42) -> 0 | I42: =SUM('費用収益表_業務長期'!I42,'費用収益表_業務短期'!I42) -> 0 | J42: =SUM('費用収益表_業務長期'!J42,'費用収益表_業務短期'!J42) -> 0 | ... O42: =SUM('費用収益表_業務長期'!O42,'費用収益表_業務短期'!O42) -> 0 | P42: =SUM(C42:O42) -> 75258 | Q42: =SUM('費用収益表_業務長期'!S42,'費用収益表_業務短期'!Q42) -> 0 | R42: =SUM('費用収益表_業務長期'!R42,'費用収益表_業務短期'!R42) -> 0 | S42: =SUM('費用収益表_業務長期'!T42,'費用収益表_業務短期'!T42) -> 0 | V42: =SUMIF($C$2:$N$2,"<="&締月,C42:N42) -> 0
A43: 連合会交付金 | C43: =SUM('費用収益表_業務長期'!C43,'費用収益表_業務短期'!C43) -> 0 | D43: =SUM('費用収益表_業務長期'!D43,'費用収益表_業務短期'!D43) -> 4513000 | E43: =SUM('費用収益表_業務長期'!E43,'費用収益表_業務短期'!E43) -> 5366000 | F43: =SUM('費用収益表_業務長期'!F43,'費用収益表_業務短期'!F43) -> 5366000 | G43: =SUM('費用収益表_業務長期'!G43,'費用収益表_業務短期'!G43) -> 5366000 | H43: =SUM('費用収益表_業務長期'!H43,'費用収益表_業務短期'!H43) -> 5369148 | I43: =SUM('費用収益表_業務長期'!I43,'費用収益表_業務短期'!I43) -> 0 | J43: =SUM('費用収益表_業務長期'!J43,'費用収益表_業務短期'!J43) -> -261410 | ... O43: =SUM('費用収益表_業務長期'!O43,'費用収益表_業務短期'!O43) -> 0 | P43: =SUM(C43:O43) -> 25718738 | Q43: =SUM('費用収益表_業務長期'!S43,'費用収益表_業務短期'!Q43) -> 23147000 | R43: =SUM('費用収益表_業務長期'!R43,'費用収益表_業務短期'!R43) -> 0 | S43: =SUM('費用収益表_業務長期'!T43,'費用収益表_業務短期'!T43) -> 0 | V43: =SUMIF($C$2:$N$2,"<="&締月,C43:N43) -> 25980148
A44: 長期経理より繰入 | C44: =SUM('費用収益表_業務長期'!C44) -> 0 | D44: =SUM('費用収益表_業務長期'!D44) -> 0 | E44: =SUM('費用収益表_業務長期'!E44) -> 0 | F44: =SUM('費用収益表_業務長期'!F44) -> 0 | G44: =SUM('費用収益表_業務長期'!G44) -> 0 | H44: =SUM('費用収益表_業務長期'!H44) -> 0 | I44: =SUM('費用収益表_業務長期'!I44) -> 0 | J44: =SUM('費用収益表_業務長期'!J44) -> 0 | ... O44: =SUM('費用収益表_業務長期'!O44) -> 0 | P44: =SUM(C44:O44) -> 0 | Q44: =SUM('費用収益表_業務長期'!S44) -> 0 | R44: =SUM('費用収益表_業務長期'!R44) -> 0 | S44: =SUM('費用収益表_業務長期'!T44) -> 0 | V44: =SUMIF($C$2:$N$2,"<="&締月,C44:N44) -> 0
A45: 短期経理より繰入 | C45: =SUM('費用収益表_業務短期'!C44) -> 0 | D45: =SUM('費用収益表_業務短期'!D44) -> 0 | E45: =SUM('費用収益表_業務短期'!E44) -> 0 | F45: =SUM('費用収益表_業務短期'!F44) -> 0 | G45: =SUM('費用収益表_業務短期'!G44) -> 0 | H45: =SUM('費用収益表_業務短期'!H44) -> 0 | I45: =SUM('費用収益表_業務短期'!I44) -> 0 | J45: =SUM('費用収益表_業務短期'!J44) -> 0 | ... O45: =SUM('費用収益表_業務短期'!O44) -> 7580026 | P45: =SUM(C45:O45) -> 7580026 | Q45: =SUM('費用収益表_業務短期'!S44) -> 13605000 | R45: =SUM('費用収益表_業務短期'!R44) -> 0 | S45: =SUM('費用収益表_業務短期'!T44) -> 0 | V45: =SUMIF($C$2:$N$2,"<="&締月,C45:N45) -> 0
A46: 当期損失金 | C46: =SUM('費用収益表_業務長期'!C45,'費用収益表_業務短期'!C45) -> 0 | D46: =SUM('費用収益表_業務長期'!D45,'費用収益表_業務短期'!D45) -> 0 | E46: =SUM('費用収益表_業務長期'!E45,'費用収益表_業務短期'!E45) -> 0 | F46: =SUM('費用収益表_業務長期'!F45,'費用収益表_業務短期'!F45) -> 0 | G46: =SUM('費用収益表_業務長期'!G45,'費用収益表_業務短期'!G45) -> 0 | H46: =SUM('費用収益表_業務長期'!H45,'費用収益表_業務短期'!H45) -> 0 | I46: =SUM('費用収益表_業務長期'!I45,'費用収益表_業務短期'!I45) -> 0 | J46: =SUM('費用収益表_業務長期'!J45,'費用収益表_業務短期'!J45) -> 0 | ... O46: =SUM('費用収益表_業務長期'!O45,'費用収益表_業務短期'!O45) -> 0 | P46: =SUM(C46:O46) -> 0 | Q46: =SUM('費用収益表_業務長期'!S45,'費用収益表_業務短期'!S45) -> 0 | R46: =SUM('費用収益表_業務長期'!R45,'費用収益表_業務短期'!R45) -> 0 | S46: =SUM('費用収益表_業務長期'!T45,'費用収益表_業務短期'!T45) -> 0 | V46: =SUMIF($C$2:$N$2,"<="&締月,C46:N46) -> 0
A47: 合 計 | C47: =SUM(C41:C45) -> 6781000 | D47: =SUM(D41:D45) -> 11176000 | E47: =SUM(E41:E45) -> 13341000 | F47: =SUM(F41:F45) -> 15914000 | G47: =SUM(G41:G45) -> 12030000 | H47: =SUM(H41:H45) -> 22676148 | I47: =SUM(I41:I45) -> 6990000 | J47: =SUM(J41:J45) -> 6479590 | ... P47: =SUM(P41:P45) -> 134436502 | Q47: =Q41+Q42+Q43+Q44+Q45+Q46 -> 131720000 | R47: =R41+R42+R43+R44+R45+R46 -> -11744404 | S47: =S41+S42+S43+S44+S45+S46 -> 31002076 | V47: =SUMIF($C$2:$N$2,"<="&締月,C47:N47) -> 81918148
J48: 通帳残高見込 | L48: =SUM(L49) -> -1719225 | M48: =SUM(L49:M49) -> -3290454 | N48: =SUM(L49:N49) -> -7933482 | O48: =SUM(L49:O49) -> -2266075
A49: 収益－費用 | C49: =C47-C38 -> 5834330 | D49: =D47-D38 -> 1069706 | E49: =E47-E38 -> 3895915 | F49: =F47-F38 -> 6269750 | G49: =G47-G38 -> 2052913 | H49: =H47-H38 -> -7958095 | I49: =I47-I38 -> -1062569 | J49: =J47-J38 -> -2679679 | ... S49: =S47-S38 -> -115293924 | V49: =SUMIF($C$2:$N$2,"<="&締月,C49:N49) -> 11164519
B51: 参考（職員給与） | C51: ４月支払 | D51: ５月支払 | E51: ６月支払 | F51: ７月支払 | G51: ８月支払 | H51: ９月支払 | I51: １０月支払 | J51: １１月支払 | K51: １２月支払 | L51: １月支払 | M51: ２月支払 | N51: ３月支払 | O51: 未払 | Q51: 合計
B52: 臨時賃金 | C52: =SUM('費用収益表_業務長期'!C59,'費用収益表_業務短期'!C59) -> 0 | D52: =SUM('費用収益表_業務長期'!D59,'費用収益表_業務短期'!D59) -> 425880 | E52: =SUM('費用収益表_業務長期'!E59,'費用収益表_業務短期'!E59) -> 365040 | F52: =SUM('費用収益表_業務長期'!F59,'費用収益表_業務短期'!F59) -> 446160 | G52: =SUM('費用収益表_業務長期'!G59,'費用収益表_業務短期'!G59) -> 445720 | H52: =SUM('費用収益表_業務長期'!H59,'費用収益表_業務短期'!H59) -> 384480 | I52: =SUM('費用収益表_業務長期'!I59,'費用収益表_業務短期'!I59) -> 389160 | J52: =SUM('費用収益表_業務長期'!J59,'費用収益表_業務短期'!J59) -> 416580 | ... O52: =SUM('費用収益表_業務長期'!O59,'費用収益表_業務短期'!O59) -> 339568 | Q52: =SUM(C52:O52) -> 4629488 | V52: =SUMIF($C$2:$N$2,"<="&締月,C52:N52) -> 2067280
B53: 職員基本給 | C53: =SUM('費用収益表_業務長期'!C51,'費用収益表_業務短期'!C51) -> 0 | D53: =SUM('費用収益表_業務長期'!D51,'費用収益表_業務短期'!D51) -> 0 | E53: =SUM('費用収益表_業務長期'!E51,'費用収益表_業務短期'!E51) -> 0 | F53: =SUM('費用収益表_業務長期'!F51,'費用収益表_業務短期'!F51) -> 0 | G53: =SUM('費用収益表_業務長期'!G51,'費用収益表_業務短期'!G51) -> 0 | H53: =SUM('費用収益表_業務長期'!H51,'費用収益表_業務短期'!H51) -> 0 | I53: =SUM('費用収益表_業務長期'!I51,'費用収益表_業務短期'!I51) -> 0 | J53: =SUM('費用収益表_業務長期'!J51,'費用収益表_業務短期'!J51) -> 0 | ... O53: =SUM('費用収益表_業務長期'!O51,'費用収益表_業務短期'!O51) -> 0 | Q53: =SUM(C53:O53) -> 0 | V53: =SUMIF($C$2:$N$2,"<="&締月,C53:N53) -> 0
B54: 基本給計 | C54: =SUM(C52:C53) -> 0 | D54: =SUM(D52:D53) -> 425880 | E54: =SUM(E52:E53) -> 365040 | F54: =SUM(F52:F53) -> 446160 | G54: =SUM(G52:G53) -> 445720 | H54: =SUM(H52:H53) -> 384480 | I54: =SUM(I52:I53) -> 389160 | J54: =SUM(J52:J53) -> 416580 | ... O54: =SUM(O52:O53) -> 339568 | Q54: =SUM(C54:O54) -> 4629488 | V54: =SUMIF($C$2:$N$2,"<="&締月,C54:N54) -> 2067280
B55: 手当（賞与以外） | C55: =SUM('費用収益表_業務長期'!C53,'費用収益表_業務短期'!C53) -> 0 | D55: =SUM('費用収益表_業務長期'!D53,'費用収益表_業務短期'!D53) -> 0 | E55: =SUM('費用収益表_業務長期'!E53,'費用収益表_業務短期'!E53) -> 0 | F55: =SUM('費用収益表_業務長期'!F53,'費用収益表_業務短期'!F53) -> 0 | G55: =SUM('費用収益表_業務長期'!G53,'費用収益表_業務短期'!G53) -> 0 | H55: =SUM('費用収益表_業務長期'!H53,'費用収益表_業務短期'!H53) -> 0 | I55: =SUM('費用収益表_業務長期'!I53,'費用収益表_業務短期'!I53) -> 0 | J55: =SUM('費用収益表_業務長期'!J53,'費用収益表_業務短期'!J53) -> 0 | ... O55: =SUM('費用収益表_業務長期'!O53,'費用収益表_業務短期'!O53) -> 0 | Q55: =SUM(C55:O55) -> 0 | V55: =SUMIF($C$2:$N$2,"<="&締月,C55:N55) -> 0
B56: 賞与 | C56: =SUM('費用収益表_業務長期'!C54,'費用収益表_業務短期'!C54) -> 0 | D56: =SUM('費用収益表_業務長期'!D54,'費用収益表_業務短期'!D54) -> 0 | E56: =SUM('費用収益表_業務長期'!E54,'費用収益表_業務短期'!E54) -> 0 | F56: =SUM('費用収益表_業務長期'!F54,'費用収益表_業務短期'!F54) -> 0 | G56: =SUM('費用収益表_業務長期'!G54,'費用収益表_業務短期'!G54) -> 0 | H56: =SUM('費用収益表_業務長期'!H54,'費用収益表_業務短期'!H54) -> 0 | I56: =SUM('費用収益表_業務長期'!I54,'費用収益表_業務短期'!I54) -> 0 | J56: =SUM('費用収益表_業務長期'!J54,'費用収益表_業務短期'!J54) -> 0 | ... O56: =SUM('費用収益表_業務長期'!O54,'費用収益表_業務短期'!O54) -> 0 | Q56: =SUM(C56:O56) -> 0 | V56: =SUMIF($C$2:$N$2,"<="&締月,C56:N56) -> 0
B57: 手当計 | C57: =SUM(C55:C56) -> 0 | D57: =SUM(D55:D56) -> 0 | E57: =SUM(E55:E56) -> 0 | F57: =SUM(F55:F56) -> 0 | G57: =SUM(G55:G56) -> 0 | H57: =SUM(H55:H56) -> 0 | I57: =SUM(I55:I56) -> 0 | J57: =SUM(J55:J56) -> 0 | ... O57: =SUM(O55:O56) -> 0 | Q57: =SUM(C57:O57) -> 0 | V57: =SUMIF($C$2:$N$2,"<="&締月,C57:N57) -> 0
B58: 嘱託報酬 | C58: =SUM('費用収益表_業務長期'!C56,'費用収益表_業務短期'!C56) -> 698140 | D58: =SUM('費用収益表_業務長期'!D56,'費用収益表_業務短期'!D56) -> 629236 | E58: =SUM('費用収益表_業務長期'!E56,'費用収益表_業務短期'!E56) -> 631304 | F58: =SUM('費用収益表_業務長期'!F56,'費用収益表_業務短期'!F56) -> 637508 | G58: =SUM('費用収益表_業務長期'!G56,'費用収益表_業務短期'!G56) -> 625100 | H58: =SUM('費用収益表_業務長期'!H56,'費用収益表_業務短期'!H56) -> 639576 | I58: =SUM('費用収益表_業務長期'!I56,'費用収益表_業務短期'!I56) -> 764882 | J58: =SUM('費用収益表_業務長期'!J56,'費用収益表_業務短期'!J56) -> 609611 | ... O58: =SUM('費用収益表_業務長期'!O56,'費用収益表_業務短期'!O56) -> 42640 | Q58: =SUM(C58:O58) -> 8086922 | V58: =SUMIF($C$2:$N$2,"<="&締月,C58:N58) -> 3860864
B59: 増額報酬 | C59: =SUM('費用収益表_業務長期'!C57,'費用収益表_業務短期'!C57) -> 0 | D59: =SUM('費用収益表_業務長期'!D57,'費用収益表_業務短期'!D57) -> 0 | E59: =SUM('費用収益表_業務長期'!E57,'費用収益表_業務短期'!E57) -> 1315485 | F59: =SUM('費用収益表_業務長期'!F57,'費用収益表_業務短期'!F57) -> 0 | G59: =SUM('費用収益表_業務長期'!G57,'費用収益表_業務短期'!G57) -> 0 | H59: =SUM('費用収益表_業務長期'!H57,'費用収益表_業務短期'!H57) -> 0 | I59: =SUM('費用収益表_業務長期'!I57,'費用収益表_業務短期'!I57) -> 0 | J59: =SUM('費用収益表_業務長期'!J57,'費用収益表_業務短期'!J57) -> 0 | ... O59: =SUM('費用収益表_業務長期'!O57,'費用収益表_業務短期'!O57) -> 0 | Q59: =SUM(C59:O59) -> 2370122 | V59: =SUMIF($C$2:$N$2,"<="&締月,C59:N59) -> 1315485
B60: 非常勤手当計 | C60: =SUM(C58:C59) -> 698140 | D60: =SUM(D58:D59) -> 629236 | E60: =SUM(E58:E59) -> 1946789 | F60: =SUM(F58:F59) -> 637508 | G60: =SUM(G58:G59) -> 625100 | H60: =SUM(H58:H59) -> 639576 | I60: =SUM(I58:I59) -> 764882 | J60: =SUM(J58:J59) -> 609611 | ... O60: =SUM(O58:O59) -> 42640 | Q60: =SUM(C60:O60) -> 10457044 | V60: =SUMIF($C$2:$N$2,"<="&締月,C60:N60) -> 5176349
B62: 合計 | C62: =C54+C57+C60 -> 698140 | D62: =D54+D57+D60 -> 1055116 | E62: =E54+E57+E60 -> 2311829 | F62: =F54+F57+F60 -> 1083668 | G62: =G54+G57+G60 -> 1070820 | H62: =H54+H57+H60 -> 1024056 | I62: =I54+I57+I60 -> 1154042 | J62: =J54+J57+J60 -> 1026191 | ... O62: =O54+O57+O60 -> 382208 | Q62: =SUM(C62:O62) -> 15086532 | V62: =SUMIF($C$2:$N$2,"<="&締月,C62:N62) -> 7243629

Sheet 費用収益表_業務短期
A1: ="令和"&年度&"年度 業務経理（短期給付事務分） 費用収益表" -> 令和8年度 業務経理（短期給付事務分） 費用収益表 | P1: 緑字＝未締め月（前年実績・見込）／黒字＝締め済み／青字＝手入力セル
A2: 費用 | C2: 1 | D2: 2 | E2: 3 | F2: 4 | G2: 5 | H2: 6 | I2: 7 | J2: 8 | K2: 9 | L2: 10 | M2: 11 | N2: 12 | O2: 13 | AA2: ▼ 参考値（旧表の値：未締め月に表示される前年実績・見込）
A3: 支払月 | C3: ４月支払 | D3: ５月 | E3: ６月 | F3: ７月 | G3: ８月 | H3: ９月 | I3: １０月 | J3: １１月 | K3: １２月 | L3: １月 | M3: ２月 | N3: ３月 | O3: ４月(未払） | P3: 決算額 | Q3: 予算額 | R3: 流用振替額 | S3: 予算現額 | T3: 不用額 | V3: 締め月まで 累計 | W3: 予算残額 （現在） | X3: 台帳連動 | AA3: 4月 | AB3: 5月 | AC3: 6月 | AD3: 7月 | AE3: 8月 | AF3: 9月 | AG3: 10月 | AH3: 11月 | AI3: 12月 | AJ3: 1月 | AK3: 2月 | AL3: 3月 | AM3: 4月(未払)
A4: 役員報酬 | C4: =IF(C$2<=締月,SUMIFS(入力_業務!$J$5:$J$1604,入力_業務!$O$5:$O$1604,"役員報酬",入力_業務!$P$5:$P$1604,C$2,入力_業務!$I$5:$I$1604,"確認済"),AA4) -> 0 | D4: =IF(D$2<=締月,SUMIFS(入力_業務!$J$5:$J$1604,入力_業務!$O$5:$O$1604,"役員報酬",入力_業務!$P$5:$P$1604,D$2,入力_業務!$I$5:$I$1604,"確認済"),AB4) -> 0 | E4: =IF(E$2<=締月,SUMIFS(入力_業務!$J$5:$J$1604,入力_業務!$O$5:$O$1604,"役員報酬",入力_業務!$P$5:$P$1604,E$2,入力_業務!$I$5:$I$1604,"確認済"),AC4) -> 10522 | F4: =IF(F$2<=締月,SUMIFS(入力_業務!$J$5:$J$1604,入力_業務!$O$5:$O$1604,"役員報酬",入力_業務!$P$5:$P$1604,F$2,入力_業務!$I$5:$I$1604,"確認済"),AD4) -> 0 | G4: =IF(G$2<=締月,SUMIFS(入力_業務!$J$5:$J$1604,入力_業務!$O$5:$O$1604,"役員報酬",入力_業務!$P$5:$P$1604,G$2,入力_業務!$I$5:$I$1604,"確認済"),AE4) -> 0 | H4: =IF(H$2<=締月,SUMIFS(入力_業務!$J$5:$J$1604,入力_業務!$O$5:$O$1604,"役員報酬",入力_業務!$P$5:$P$1604,H$2,入力_業務!$I$5:$I$1604,"確認済"),AF4) -> 0 | I4: =IF(I$2<=締月,SUMIFS(入力_業務!$J$5:$J$1604,入力_業務!$O$5:$O$1604,"役員報酬",入力_業務!$P$5:$P$1604,I$2,入力_業務!$I$5:$I$1604,"確認済"),AG4) -> 0 | J4: =IF(J$2<=締月,SUMIFS(入力_業務!$J$5:$J$1604,入力_業務!$O$5:$O$1604,"役員報酬",入力_業務!$P$5:$P$1604,J$2,入力_業務!$I$5:$I$1604,"確認済"),AH4) -> 0 | ... O4: =IF(O$2<=締月,SUMIFS(入力_業務!$J$5:$J$1604,入力_業務!$O$5:$O$1604,"役員報酬",入力_業務!$P$5:$P$1604,O$2,入力_業務!$I$5:$I$1604,"確認済"),AM4) -> 0 | P4: =SUM(C4:O4) -> 15783 | Q4: 16000 | S4: =SUM(Q4:R4) -> 16000 | T4: =S4-P4 -> 217 | V4: =SUMIF($C$2:$N$2,"<="&締月,C4:N4) -> 10522 | W4: =S4-V4 -> 5478 | X4: 1 | AA4: 0 | AB4: 0 | AC4: 10522 | AD4: 0 | AE4: 0 | AF4: 0 | AG4: 0 | AH4: 0 | AI4: 0 | AJ4: 0 | AK4: 0 | AL4: 5261 | AM4: 0
A5: 職員給与 | B5: 基本給 | C5: =C52 -> 0 | D5: =D52 -> 0 | E5: =E52 -> 0 | F5: =F52 -> 0 | G5: =G52 -> 0 | H5: =H52 -> 0 | I5: =I52 -> 0 | J5: =J52 -> 0 | ... O5: =O52 -> 0 | P5: =SUM(C5:O5) -> 0 | Q5: 0 | S5: =SUM(Q5:R5) -> 0 | T5: =S5-P5 -> 0 | V5: =SUMIF($C$2:$N$2,"<="&締月,C5:N5) -> 0 | W5: =S5-V5 -> 0
B6: 諸手当 | C6: =C55 -> 0 | D6: =D55 -> 0 | E6: =E55 -> 0 | F6: =F55 -> 0 | G6: =G55 -> 0 | H6: =H55 -> 0 | I6: =I55 -> 0 | J6: =J55 -> 0 | ... O6: =O55 -> 0 | P6: =SUM(C6:O6) -> 0 | Q6: 0 | S6: =SUM(Q6:R6) -> 0 | T6: =S6-P6 -> 0 | V6: =SUMIF($C$2:$N$2,"<="&締月,C6:N6) -> 0 | W6: =S6-V6 -> 0
B7: 非常勤職員手当 | C7: =C58 -> 317340 | D7: =D58 -> 248436 | E7: =E58 -> 698299 | F7: =F58 -> 256708 | G7: =G58 -> 244300 | H7: =H58 -> 258776 | I7: =I58 -> 383109 | J7: =J58 -> 227838 | ... O7: =O58 -> 42640 | P7: =SUM(C7:O7) -> 4114477 | Q7: 4381000 | S7: =SUM(Q7:R7) -> 4381000 | T7: =S7-P7 -> 266523 | V7: =SUMIF($C$2:$N$2,"<="&締月,C7:N7) -> 2023859 | W7: =S7-V7 -> 2357141
B8: 退職給与金 | P8: =SUM(C8:O8) -> 0 | Q8: 0 | S8: =SUM(Q8:R8) -> 0 | T8: =S8-P8 -> 0 | V8: =SUMIF($C$2:$N$2,"<="&締月,C8:N8) -> 0 | W8: =S8-V8 -> 0
B9: 計 | C9: =SUM(C5:C8) -> 317340 | D9: =SUM(D5:D8) -> 248436 | E9: =SUM(E5:E8) -> 698299 | F9: =SUM(F5:F8) -> 256708 | G9: =SUM(G5:G8) -> 244300 | H9: =SUM(H5:H8) -> 258776 | I9: =SUM(I5:I8) -> 383109 | J9: =SUM(J5:J8) -> 227838 | ... Q9: =SUM(Q5:Q8) -> 4381000 | S9: =SUM(Q9:R9) -> 4381000 | T9: =S9-P9 -> 266523 | V9: =SUMIF($C$2:$N$2,"<="&締月,C9:N9) -> 2023859 | W9: =S9-V9 -> 2357141
A10: 厚生費 | C10: =IF(C$2<=締月,SUMIFS(入力_業務!$J$5:$J$1604,入力_業務!$O$5:$O$1604,"厚生費",入力_業務!$P$5:$P$1604,C$2,入力_業務!$I$5:$I$1604,"確認済"),AA10) -> 0 | D10: =IF(D$2<=締月,SUMIFS(入力_業務!$J$5:$J$1604,入力_業務!$O$5:$O$1604,"厚生費",入力_業務!$P$5:$P$1604,D$2,入力_業務!$I$5:$I$1604,"確認済"),AB10) -> 0 | E10: =IF(E$2<=締月,SUMIFS(入力_業務!$J$5:$J$1604,入力_業務!$O$5:$O$1604,"厚生費",入力_業務!$P$5:$P$1604,E$2,入力_業務!$I$5:$I$1604,"確認済"),AC10) -> 0 | F10: =IF(F$2<=締月,SUMIFS(入力_業務!$J$5:$J$1604,入力_業務!$O$5:$O$1604,"厚生費",入力_業務!$P$5:$P$1604,F$2,入力_業務!$I$5:$I$1604,"確認済"),AD10) -> 0 | G10: =IF(G$2<=締月,SUMIFS(入力_業務!$J$5:$J$1604,入力_業務!$O$5:$O$1604,"厚生費",入力_業務!$P$5:$P$1604,G$2,入力_業務!$I$5:$I$1604,"確認済"),AE10) -> 0 | H10: =IF(H$2<=締月,SUMIFS(入力_業務!$J$5:$J$1604,入力_業務!$O$5:$O$1604,"厚生費",入力_業務!$P$5:$P$1604,H$2,入力_業務!$I$5:$I$1604,"確認済"),AF10) -> 14894 | I10: =IF(I$2<=締月,SUMIFS(入力_業務!$J$5:$J$1604,入力_業務!$O$5:$O$1604,"厚生費",入力_業務!$P$5:$P$1604,I$2,入力_業務!$I$5:$I$1604,"確認済"),AG10) -> 0 | J10: =IF(J$2<=締月,SUMIFS(入力_業務!$J$5:$J$1604,入力_業務!$O$5:$O$1604,"厚生費",入力_業務!$P$5:$P$1604,J$2,入力_業務!$I$5:$I$1604,"確認済"),AH10) -> 0 | ... O10: =IF(O$2<=締月,SUMIFS(入力_業務!$J$5:$J$1604,入力_業務!$O$5:$O$1604,"厚生費",入力_業務!$P$5:$P$1604,O$2,入力_業務!$I$5:$I$1604,"確認済"),AM10) -> 0 | P10: =SUM(C10:O10) -> 14894 | Q10: 62000 | S10: =SUM(Q10:R10) -> 62000 | T10: =S10-P10 -> 47106 | V10: =SUMIF($C$2:$N$2,"<="&締月,C10:N10) -> 14894 | W10: =S10-V10 -> 47106 | X10: 1 | AA10: 0 | AB10: 0 | AC10: 0 | AD10: 0 | AE10: 0 | AF10: 14894 | AG10: 0 | AH10: 0 | AI10: 0 | AJ10: 0 | AK10: 0 | AL10: 0 | AM10: 0
A11: 旅費 | C11: =IF(C$2<=締月,SUMIFS(入力_業務!$J$5:$J$1604,入力_業務!$O$5:$O$1604,"旅費",入力_業務!$P$5:$P$1604,C$2,入力_業務!$I$5:$I$1604,"確認済"),AA11) -> 0 | D11: =IF(D$2<=締月,SUMIFS(入力_業務!$J$5:$J$1604,入力_業務!$O$5:$O$1604,"旅費",入力_業務!$P$5:$P$1604,D$2,入力_業務!$I$5:$I$1604,"確認済"),AB11) -> 0 | E11: =IF(E$2<=締月,SUMIFS(入力_業務!$J$5:$J$1604,入力_業務!$O$5:$O$1604,"旅費",入力_業務!$P$5:$P$1604,E$2,入力_業務!$I$5:$I$1604,"確認済"),AC11) -> 39656 | F11: =IF(F$2<=締月,SUMIFS(入力_業務!$J$5:$J$1604,入力_業務!$O$5:$O$1604,"旅費",入力_業務!$P$5:$P$1604,F$2,入力_業務!$I$5:$I$1604,"確認済"),AD11) -> 0 | G11: =IF(G$2<=締月,SUMIFS(入力_業務!$J$5:$J$1604,入力_業務!$O$5:$O$1604,"旅費",入力_業務!$P$5:$P$1604,G$2,入力_業務!$I$5:$I$1604,"確認済"),AE11) -> 29068 | H11: =IF(H$2<=締月,SUMIFS(入力_業務!$J$5:$J$1604,入力_業務!$O$5:$O$1604,"旅費",入力_業務!$P$5:$P$1604,H$2,入力_業務!$I$5:$I$1604,"確認済"),AF11) -> 0 | I11: =IF(I$2<=締月,SUMIFS(入力_業務!$J$5:$J$1604,入力_業務!$O$5:$O$1604,"旅費",入力_業務!$P$5:$P$1604,I$2,入力_業務!$I$5:$I$1604,"確認済"),AG11) -> 0 | J11: =IF(J$2<=締月,SUMIFS(入力_業務!$J$5:$J$1604,入力_業務!$O$5:$O$1604,"旅費",入力_業務!$P$5:$P$1604,J$2,入力_業務!$I$5:$I$1604,"確認済"),AH11) -> 18624 | ... O11: =IF(O$2<=締月,SUMIFS(入力_業務!$J$5:$J$1604,入力_業務!$O$5:$O$1604,"旅費",入力_業務!$P$5:$P$1604,O$2,入力_業務!$I$5:$I$1604,"確認済"),AM11) -> 0 | P11: =SUM(C11:O11) -> 187066 | Q11: 98000 | S11: =SUM(Q11:R11) -> 98000 | T11: =S11-P11 -> -89066 | V11: =SUMIF($C$2:$N$2,"<="&締月,C11:N11) -> 68724 | W11: =S11-V11 -> 29276 | X11: 1 | AA11: 0 | AB11: 0 | AC11: 39656 | AD11: 0 | AE11: 29068 | AF11: 0 | AG11: 0 | AH11: 18624 | AI11: 80902 | AJ11: 0 | AK11: 18816 | AL11: 0 | AM11: 0
